Workbook
Name 财务费用: Word附注!$B$2010
Name 持有待售资产和负债: Word附注!$B$540
Name 持有至到期投资: Word附注!$B$687
Name 存货: Word附注!$B$434
Name 递延收益: Word附注!$B$1889
Name 递延所得税资产与递延所得税负债: Word附注!$B$1257
Name 短期借款: Word附注!$B$1307
Name 非经常性损益: Word附注!$B$2239
Name 工程物资: Word附注!$B$1018
Name 公允价值变动收益: Word附注!$B$2065
Name 固定资产: Word附注!$B$871
Name 固定资产明细: Word附注!$B$877
Name 固定资产清理: Word附注!$B$957
Name 管理费用: Word附注!$B$1979
Name 合同负债: Word附注!$B$1415
Name 合同资产: Word附注!$B$511
Name 货币资金: Word附注!$B$2
Name 交易性金融负债: Word附注!$B$1329
Name 交易性金融资产: Word附注!$B$23
Name 净敞口套期收益: Word附注!$B$2051
Name 开发支出: Word附注!$B$1200
Name 可供出售金融资产: Word附注!$B$629
Name 其他非流动负债: Word附注!$B$1904
Name 其他非流动金融资产: Word附注!$B$790
Name 其他非流动资产: Word附注!$B$1296
Name 其他流动负债: Word附注!$B$1609
Name 其他流动资产: Word附注!$B$597
Name 其他权益工具投资: Word附注!$B$780
Name 其他收益: Word附注!$B$2025
Name 其他应付款: Word附注!$B$1497
Name 其他应付款明细: Word附注!$B$1545
Name 其他应收款: Word附注!$B$252
Name 其他应收款_以下不适用的_请删除: Word附注!$B$298
Name 其他债权投资: Word附注!$B$675
Name 商誉: Word附注!$B$1221
Name 设定受益计划净资产: Word附注!$B$756
Name 生产性生物资产: Word附注!$B$1028
Name 使用权资产: Word附注!$B$1112
Name 税金及附加: Word附注!$B$1955
Name 所得税费用: Word附注!$B$2146
Name 所有权或使用权受到限制的资产: Word附注!$B$2280
Name 投资收益: Word附注!$B$2037
Name 投资性房地产: Word附注!$B$802
Name 无形资产: Word附注!$B$1139
Name 现金流量表项目注释: Word附注!$B$2170
Name 销售费用: Word附注!$B$1967
Name 信用减值损失: Word附注!$B$2076
Name 研发费用: Word附注!$B$1994
Name 衍生金融负债: Word附注!$B$1356
Name 衍生金融资产: Word附注!$B$50
Name 一年内到期的非流动负债: Word附注!$B$1561
Name 一年内到期的非流动资产: Word附注!$B$588
Name 以公允价值计量且其变动计入当期损益的金融负债: Word附注!$B$1341
Name 以公允价值计量且其变动计入当期损益的金融资产: Word附注!$B$34
Name 应付股利: Word附注!$B$1526
Name 应付利息: Word附注!$B$1505
Name 应付票据: Word附注!$B$1367
Name 应付债券: Word附注!$B$1667
Name 应付账款: Word附注!$B$1375
Name 应付职工薪酬: Word附注!$B$1432

Sheet 目录
A1: 序号 | B1: 资产 | C1: 序号 | D1: 负债 | E1: 序号 | F1: 损益 | G1: 序号 | H1: 其他 | I1: 序号 | J1: 期后事项
A2: 1 | B2: 货币资金 | C2: =A42+1 -> 35 | D2: 短期借款 | E2: =C29+1 -> 58 | F2: 营业收入 | G2: =E19+1 -> 76 | H2: 现金流量表附表 | I2: =G6+1 -> 81 | J2: 资产负债表日后事项
A3: =A2+1 -> 2 | B3: 交易性金融资产 | C3: =C2+1 -> 36 | D3: 交易性金融负债 | E3: =E2+1 -> 59 | F3: 营业成本 | G3: =G2+1 -> 77 | H3: 非经常性损益
A4: =A3+1 -> 3 | B4: 以公允价值计量且其变动计入当期损益的金融资产 | C4: =C3+1 -> 37 | D4: 以公允价值计量且其变动计入当期损益的金融负债 | E4: =E3+1 -> 60 | F4: 税金及附加 | G4: =G3+1 -> 78 | H4: 所有权受限资产
A5: =A4+1 -> 4 | B5: 衍生金融资产 | C5: =C4+1 -> 38 | D5: 衍生金融负债 | E5: =E4+1 -> 61 | F5: 销售费用 | G5: =G4+1 -> 79 | H5: 终止经营
A6: =A5+1 -> 5 | B6: 应收票据 | C6: =C5+1 -> 39 | D6: 应付票据 | E6: =E5+1 -> 62 | F6: 管理费用 | G6: =G5+1 -> 80 | H6: 政府补助
A7: =A6+1 -> 6 | B7: 应收账款 | C7: =C6+1 -> 40 | D7: 应付账款 | E7: =E6+1 -> 63 | F7: 研发费用
A8: =A7+1 -> 7 | B8: 预付款项 | C8: =C7+1 -> 41 | D8: 预收款项 | E8: =E7+1 -> 64 | F8: 财务费用
A9: =A8+1 -> 8 | B9: 其他应收款 | C9: =C8+1 -> 42 | D9: 合同负债 | E9: =E8+1 -> 65 | F9: 其他收益
A10: =A9+0.1 -> 8.1 | B10: 其中：应收利息 | C10: =C9+1 -> 43 | D10: 应付职工薪酬 | E10: =E9+1 -> 66 | F10: 投资收益
A11: =A10+0.1 -> 8.2 | B11: 应收股利 | C11: =C10+1 -> 44 | D11: 应交税费 | E11: =E10+1 -> 67 | F11: 净敞口套期收益
A12: =A11+0.1 -> 8.3 | B12: 其他应收款 | C12: =C11+1 -> 45 | D12: 其他应付款 | E12: =E11+1 -> 68 | F12: 公允价值变动收益
A13: =A9+1 -> 9 | B13: 存货 | C13: =C12+0.1 -> 45.1 | D13: 其中：应付利息 | E13: =E12+1 -> 69 | F13: 信用减值损失
A14: =A13+1 -> 10 | B14: 合同资产 | C14: =C13+0.1 -> 45.2 | D14: 应付股利 | E14: =E13+1 -> 70 | F14: 资产减值损失
A15: =A14+1 -> 11 | B15: 持有待售资产 | C15: =C14+0.1 -> 45.3 | D15: 其他应付款 | E15: =E14+1 -> 71 | F15: 资产减值准备
A16: =A15+1 -> 12 | B16: 一年内到期的非流动资产 | C16: =C12+1 -> 46 | D16: 持有待售负债 | E16: =E15+1 -> 72 | F16: 资产处置收益
A17: =A16+1 -> 13 | B17: 其他流动资产 | C17: =C16+1 -> 47 | D17: 一年内到期的非流动负债 | E17: =E16+1 -> 73 | F17: 营业外收入
A18: =A17+1 -> 14 | B18: 债权投资 | C18: =C17+1 -> 48 | D18: 其他流动负债 | E18: =E17+1 -> 74 | F18: 营业外支出
A19: =A18+1 -> 15 | B19: 可供出售金融资产 | C19: =C18+1 -> 49 | D19: 长期借款 | E19: =E18+1 -> 75 | F19: 所得税费用
A20: =A19+1 -> 16 | B20: 其他债权投资 | C20: =C19+1 -> 50 | D20: 应付债券
A21: =A20+1 -> 17 | B21: 持有至到期投资 | C21: =C20+1 -> 51 | D21: 租赁负债
A22: =A21+1 -> 18 | B22: 长期应收款 | C22: =C21+1 -> 52 | D22: 长期应付款
A23: =A22+1 -> 19 | B23: 设定受益计划净资产 | C23: =C22+0.1 -> 52.1 | D23: 其中：长期应付款
A24: =A23+1 -> 20 | B24: 长期股权投资 | C24: =C23+0.1 -> 52.2 | D24: 专项应付款
A25: =A24+1 -> 21 | B25: 其他权益工具投资 | C25: =C22+1 -> 53 | D25: 长期应付职工薪酬
A26: =A25+1 -> 22 | B26: 其他非流动金融资产 | C26: =C25+1 -> 54 | D26: 预计负债
A27: =A26+1 -> 23 | B27: 投资性房地产 | C27: =C26+1 -> 55 | D27: 递延收益
A28: =A27+1 -> 24 | B28: 固定资产 | C28: =C27+1 -> 56 | D28: 递延所得税负债
A29: =A28+0.1 -> 24.1 | B29: 其中：固定资产 | C29: =C28+1 -> 57 | D29: 其他非流动负债
A30: =A29+0.1 -> 24.2 | B30: 固定资产清理
A31: =A28+1 -> 25 | B31: 在建工程
A32: =A31+0.1 -> 25.1 | B32: 其中：在建工程
A33: =A32+0.1 -> 25.2 | B33: 工程物资
A34: =A31+1 -> 26 | B34: 生产性生物资产
A35: =A34+1 -> 27 | B35: 油气资产
A36: =A35+1 -> 28 | B36: 使用权资产
A37: =A36+1 -> 29 | B37: 无形资产
A38: =A37+1 -> 30 | B38: 开发支出
A39: =A38+1 -> 31 | B39: 商誉
A40: =A39+1 -> 32 | B40: 长期待摊费用
A41: =A40+1 -> 33 | B41: 递延所得税资产
A42: =A41+1 -> 34 | B42: 其他非流动资产

Sheet Word附注
A1: 序号 | B1: 科目名称
A2: 1 | B2: 货币资金 | E2: 汇总明细
C3: 项 目 | D3: 期末数 | G3: 期初数
D4: 外币金额 | E4: 折算率 | F4: 人民币金额 | G4: 外币金额 | H4: 折算率 | I4: 人民币金额
C5: 库存现金： | F5: =货币资金!B3 -> 0 | I5: =G5*H5 -> 0
C6: 人民币 | F6: =货币资金!B4 -> 0 | I6: =G6*H6 -> 0
C7: 美元 | F7: =货币资金!B5 -> 0 | I7: =G7*H7 -> 0
C8: 银行存款： | F8: =货币资金!B6 -> 0 | I8: =G8*H8 -> 0
C9: 人民币 | F9: =货币资金!B7 -> 0 | I9: =G9*H9 -> 0
C10: 美元 | F10: =货币资金!B8 -> 0 | I10: =G10*H10 -> 0
C11: 银行存款中：财务公司存款 | F11: =货币资金!B35 -> 0 | I11: =G11*H11 -> 0
C12: 其中：人民币 | F12: =货币资金!B33 -> 0 | I12: =G12*H12 -> 0
C13: 美元 | F13: =货币资金!B34 -> 0 | I13: =G13*H13 -> 0
C14: 其他货币资金： | F14: =货币资金!B9 -> 0 | I14: =G14*H14 -> 0
C15: 人民币 | F15: =货币资金!B10 -> 0 | I15: =G15*H15 -> 0
C16: 美元 | F16: =货币资金!B11 -> 0 | I16: =G16*H16 -> 0
C17: 合 计 | F17: =F5+F8+F14 -> 0 | I17: =I5+I8+I14 -> 0
C18: 其中：存放在境外的款项总额 | F18: =货币资金!B29 -> 0
C19: （如无外币，直接用库存现金、银行存款、其他货币资金三行）
C20: 期末，本集团不存在抵押、质押或冻结、或存放在境外且资金汇回受到限制的款项。
C21: （披露因抵押、质押或冻结等对使用有限制的款项，以及存放在境外的款项总额。公司应单独披露存放在境外且资金汇回受到限制的款项。）
A23: 2 | B23: 交易性金融资产 | E23: 汇总明细
C24: 项 目 | D24: 期末
C25: 债务工具投资 | D25: =交易性金融资产!D4 -> 0
C26: 权益工具投资 | D26: =交易性金融资产!D5 -> 0
C27: 衍生金融资产 | D27: =交易性金融资产!D6 -> 0
C28: 其他 | D28: =交易性金融资产!D7 -> 0
C29: 合 计 | D29: =SUM(D25:D28) -> 0
C30: （说明：
C31: （1）管理层认为交易性金融资产投资变现[不存在重大限制]。/〔存在下列限制：具体限制及原因〕）
C32: （2）请说明交易性金融资产期末公允价值的确认方法及对当期损益的影响，如采用估值技术确定公允价值时，应详细披露估值模型、重要参数的选取依据和估值过程，以及必要的敏感性分析。）
A34: 3 | B34: 以公允价值计量且其变动计入当期损益的金融资产 | E34: 汇总明细
G35: 证券公司格式 | H35: 项 目 | I35: 期末数 | K35: 期初数 | M35: 本期
C36: 项 目 | D36: 期末公允价值 | E36: 期初公允价值 | I36: 成本 | J36: 公允价值 | K36: 成本 | L36: 公允价值 | M36: 变动
C37: 交易性金融资产 | D37: =SUM(D38:D41) -> 0 | E37: =SUM(E38:E41) -> 0 | H37: 交易性金融资产 | I37: =SUM(I38:I41) -> 0 | J37: =SUM(J38:J41) -> 0 | K37: =SUM(K38:K41) -> 0 | L37: =SUM(L38:L41) -> 0 | M37: =J37-L37 -> 0
C38: 其中：债务工具投资 | D38: =以公允价值计量且其变动计入当期损益的金融资产!B4 -> 0 | H38: 其中：债务工具投资 | I38: =以公允价值计量且其变动计入当期损益的金融资产!B21 -> 0 | J38: =以公允价值计量且其变动计入当期损益的金融资产!B4 -> 0 | M38: =J38-L38 -> 0
C39: 权益工具投资 | D39: =以公允价值计量且其变动计入当期损益的金融资产!B5 -> 0 | H39: 权益工具投资 | I39: =以公允价值计量且其变动计入当期损益的金融资产!B22 -> 0 | J39: =以公允价值计量且其变动计入当期损益的金融资产!B5 -> 0 | M39: =J39-L39 -> 0
C40: 衍生金融资产 | D40: =以公允价值计量且其变动计入当期损益的金融资产!B6 -> 0 | H40: 衍生金融资产 | I40: =以公允价值计量且其变动计入当期损益的金融资产!B23 -> 0 | J40: =以公允价值计量且其变动计入当期损益的金融资产!B6 -> 0 | M40: =J40-L40 -> 0
C41: 其他 | D41: =以公允价值计量且其变动计入当期损益的金融资产!B7 -> 0 | H41: 其他 | I41: =以公允价值计量且其变动计入当期损益的金融资产!B24 -> 0 | J41: =以公允价值计量且其变动计入当期损益的金融资产!B7 -> 0 | M41: =J41-L41 -> 0
C42: 指定为以公允价值计量且其变动计入当期损益的金融资产 | D42: =SUM(D43:D46) -> 0 | E42: =SUM(E43:E46) -> 0 | H42: 指定为以公允价值计量且其变动计入当期损益的金融资产 | I42: =SUM(I43:I46) -> 0 | J42: =SUM(J43:J46) -> 0 | K42: =SUM(K43:K46) -> 0 | L42: =SUM(L43:L46) -> 0 | M42: =J42-L42 -> 0
C43: 其中：债务工具投资 | D43: =以公允价值计量且其变动计入当期损益的金融资产!B9 -> 0 | H43: 其中：债务工具投资 | I43: =以公允价值计量且其变动计入当期损益的金融资产!B26 -> 0 | J43: =以公允价值计量且其变动计入当期损益的金融资产!B9 -> 0 | M43: =J43-L43 -> 0
C44: 权益工具投资 | D44: =以公允价值计量且其变动计入当期损益的金融资产!B10 -> 0 | H44: 权益工具投资 | I44: =以公允价值计量且其变动计入当期损益的金融资产!B27 -> 0 | J44: =以公允价值计量且其变动计入当期损益的金融资产!B10 -> 0 | M44: =J44-L44 -> 0
C45: 衍生金融资产 | D45: =以公允价值计量且其变动计入当期损益的金融资产!B11 -> 0 | H45: 衍生金融资产 | I45: =以公允价值计量且其变动计入当期损益的金融资产!B28 -> 0 | J45: =以公允价值计量且其变动计入当期损益的金融资产!B11 -> 0 | M45: =J45-L45 -> 0
C46: 其他 | D46: =以公允价值计量且其变动计入当期损益的金融资产!B12 -> 0 | H46: 其他 | I46: =以公允价值计量且其变动计入当期损益的金融资产!B29 -> 0 | J46: =以公允价值计量且其变动计入当期损益的金融资产!B12 -> 0 | M46: =J46-L46 -> 0
C47: 合 计 | D47: =D37+D42 -> 0 | E47: =E37+E42 -> 0 | H47: 合 计 | I47: =I37+I42 -> 0 | J47: =J37+J42 -> 0 | K47: =K37+K42 -> 0 | L47: =L37+L42 -> 0 | M47: =M37+M42 -> 0
C48: 说明：
A50: 4 | B50: 衍生金融资产 | E50: 汇总明细
C51: （提示：企业衍生金融工具业务具有重要性的，单独披露衍生金融资产。）
C52: （15号文第十九条（三），分类列示衍生金融资产期初余额、期末余额，披露其产生的原因以及相关会计处理。）
C53: 项 目 | D53: 期末公允价值 | E53: 期初公允价值
C54: =衍生金融资产!A3 -> 0 | D54: =衍生金融资产!B3 -> 0
C55: =衍生金融资产!A4 -> 0 | D55: =衍生金融资产!B4 -> 0
C56: =衍生金融资产!A5 -> 0 | D56: =衍生金融资产!B6 -> 0
C57: =衍生金融资产!A6 -> 0 | D57: =衍生金融资产!B7 -> 0
C58: =衍生金融资产!A7 -> 0 | D58: =衍生金融资产!B8 -> 0
C59: =衍生金融资产!A8 -> 0 | D59: =衍生金融资产!B9 -> 0
C60: 合 计 | D60: =SUM(D54:D59) -> 0 | E60: =SUM(E54:E59) -> 0
C61: 说明：（衍生金融资产产生的原因以及相关会计处理。）
A64: 5 | B64: 应收票据 | E64: 汇总明细
C66: 种 类 | D66: 期末数 | E66: 期初数
C67: 银行承兑汇票 | D67: =应收票据!B3 -> 0
C68: 商业承兑汇票 | D68: =应收票据!B4 -> 0
C69: 合 计 | D69: =SUM(D67:D68) -> 0 | E69: =SUM(E67:E68) -> 0
C71: （1）期末本集团已质押的应收票据
C73: 种 类 | D73: 期末已质押金额
C74: 银行承兑票据 | D74: =应收票据!B11 -> 0
C75: 商业承兑票据 | D75: =应收票据!B12 -> 0
C76: 可无限量添加行
C77: 合 计 | D77: =SUM(D74:D76) -> 0
C79: （2）期末本集团已背书或贴现但尚未到期的应收票据
C80: 种 类 | D80: 期末终止确认金额 | E80: 期末未终止确认金额
C81: 银行承兑票据 | D81: =应收票据!B18+应收票据!B23 -> 0
C82: 商业承兑票据 | D82: =应收票据!B19+应收票据!B24 -> 0
C83: 可无限量添加行
C84: 合 计 | D84: =SUM(D81:D83) -> 0 | E84: =SUM(E81:E83) -> 0
C85: （如根据《企业会计准则第23号——金融资产转移》终止确认的应收票据，列示其终止确认的金额，及与终止确认相关的利得和损失）
C87: （3）期末本集团因出票人未履约而其转应收账款的票据
C88: 种 类 | D88: 期末转应收账款金额
C89: 商业承兑票据 | D89: =应收票据!B30 -> 0
C92: 合 计 | D92: =SUM(D89:D91) -> 0
A94: 6 | B94: 应收账款 | E94: 汇总明细
C95: （1）应收账款按种类披露
C96: 种 类 | D96: 期末数
D97: 金 额 | E97: 比例% | F97: 坏账准备 | G97: 计提比例% | H97: 净额
C98: 单项金额重大并单项计提坏账准备的应收账款 | D98: =应收账款!B4 -> 0 | E98: =D98/$D$105*100 -> #DIV/0! | F98: =应收账款!B13 -> 0 | G98: =F98/D98*100 -> #DIV/0! | H98: =D98-F98 -> 0
C99: 按组合计提坏账准备的应收账款 | D99: =应收账款!B5 -> 0 | E99: =D99/$D$105*100 -> #DIV/0! | F99: =应收账款!B14 -> 0 | G99: =F99/D99*100 -> #DIV/0! | H99: =D99-F99 -> 0
C100: 其中：账龄组合 | D100: =应收账款!B6 -> 0 | E100: =D100/$D$105*100 -> #DIV/0! | F100: =应收账款!B15 -> 0 | G100: =F100/D100*100 -> #DIV/0! | H100: =D100-F100 -> 0
C101: 资产状态组合 | D101: =应收账款!B7 -> 0 | E101: =D101/$D$105*100 -> #DIV/0! | F101: =应收账款!B16 -> 0 | G101: =F101/D101*100 -> #DIV/0! | H101: =D101-F101 -> 0
C102: …… | D102: =应收账款!B8 -> 0 | E102: =D102/$D$105*100 -> #DIV/0! | F102: =应收账款!B17 -> 0 | G102: =F102/D102*100 -> #DIV/0! | H102: =D102-F102 -> 0
C103: 组合小计 | D103: =SUM(D100:D102) -> 0 | E103: =D103/$D$105*100 -> #DIV/0! | F103: =SUM(F100:F102) -> 0 | G103: =F103/D103*100 -> #DIV/0! | H103: =D103-F103 -> 0
C104: 单项金额虽不重大但单项计提坏账准备的应收账款 | D104: =应收账款!B10 -> 0 | E104: =D104/$D$105*100 -> #DIV/0! | F104: =应收账款!B19 -> 0 | G104: =F104/D104*100 -> #DIV/0! | H104: =D104-F104 -> 0
C105: 合 计 | D105: =D98+D103+D104 -> 0 | E105: =D105/$D$105*100 -> #DIV/0! | F105: =F98+F103+F104 -> 0 | G105: =F105/D105*100 -> #DIV/0! | H105: =H98+H103+H104 -> 0
C107: 应收账款按种类披露（续）
C109: 种 类 | D109: 期初数
D110: 金 额 | E110: 比例% | F110: 坏账准备 | G110: 计提比例% | H110: 净额
C111: 单项金额重大并单项计提坏账准备的应收账款 | E111: =D111/$D$118*100 -> #DIV/0! | G111: =F111/D111*100 -> #DIV/0! | H111: =D111-F111 -> 0
C112: 按组合计提坏账准备的应收账款 | E112: =D112/$D$118*100 -> #DIV/0! | G112: =F112/D112*100 -> #DIV/0! | H112: =D112-F112 -> 0
C113: 其中：账龄组合 | E113: =D113/$D$118*100 -> #DIV/0! | G113: =F113/D113*100 -> #DIV/0! | H113: =D113-F113 -> 0
C114: 资产状态组合 | E114: =D114/$D$118*100 -> #DIV/0! | G114: =F114/D114*100 -> #DIV/0! | H114: =D114-F114 -> 0
C115: …… | E115: =D115/$D$118*100 -> #DIV/0! | G115: =F115/D115*100 -> #DIV/0! | H115: =D115-F115 -> 0
...

Sheet 现金流量表主表
A1: 致同会计师事务所
A2: 现金流量表-主表核查记录
A3: 客户名称： | C3: 编制人： | E3: 日期： | F3: 索引： | G3: A5-1-2
A4: 会计期间： | C4: 复核人： | E4: 日期: | F4: 页次：
A5: 项目 | B5: 行次 | C5: 差异(按报表账户) | D5: 原报数 | E5: 测算数 | F5: 有关测算依据
C6: 1=3-2 | D6: 2 | E6: 3 | F6: 4
A7: 一、经营活动产生的现金流量：
A8: 销售商品、提供劳务收到的现金 | B8: 1 | C8: =E8-D8 -> 0 | E8: =G18 -> 0 | F8: = 营业收入 | G8: =营业收入!B12+营业收入!B54 -> 0
F9: ＋应收账款期初余额-应收账款期末余额 | G9: =现金流量表附表!I54 -> 0
F10: ＋应收票据期初余额-应收票据期末余额 | G10: =现金流量表附表!I53 -> 0
F11: ＋预收账款期末余额-预收账款期初余额 | G11: =现金流量表附表!I65 -> 0
F12: ＋当期收回前期核销的坏账
F13: —以非现金资产抵偿债务而减少的应收账款和应收票据
F14: —当期核销的坏账 | G14: =应收账款!B103+其他应收款!B91 -> 0
F15: —票据贴现的利息 | G15: =财务费用!B6 -> 0
F16: ＋当期收到的销项税
F17: ＋其他
F18: 小计 | G18: =G8+G9+G10+G11+G12-G13-G14-G15+G16+G17 -> 0
A20: 收到的税费返还 | B20: 2 | C20: =E20-D20 -> 0 | E20: =G28 -> 0 | F20: = 增值税退税： | G20: =G21+G22 -> 0
F21: 实际收到的出口退税(不包括用于抵减内销产品应纳税额的部分)=根据应收补贴款账户以及应交增值税(出口退税)专栏分析确定
F22: 先征后返增值税=补贴收入(返还增值税)账户发生额
F23: ＋所得税退税 | G23: =G24 -> 0
F24: 所得税账户当期退税数
F25: ＋先征后返的消费税、营业税 | G25: =G26 -> 0
F26: 根据营业税金及附加、其他业务支出等账户发生额分析确定
F27: ＋其他
F28: 小计 | G28: =G20+G23+G25+G27 -> 0
A30: 收到的其他与经营活动有关的现金 | B30: 3 | C30: =E30-D30 -> 0 | E30: =G35 -> 0 | F30: = 补贴收入
F31: + 财务费用-利息收入 | G31: =财务费用!B5 -> 0
F32: + 营业外收入（扣除处置长期资产利得、债务重组等）
F33: ＋(其他应收款期初余额-其他应收款期末余额) | G33: =现金流量表附表!I55 -> 0
F34: ＋其他
F35: 小计 | G35: =G30+G31+G32+G33+G34 -> 0
A37: 经营活动现金流入小计 | B37: 4 | C37: =C8+C20+C30 -> 0 | D37: =D8+D20+D30 -> 0 | E37: =E8+E20+E30 -> 0
A38: 购买商品、接受劳务支付的现金 | B38: 5 | C38: =E38-D38 -> 0 | E38: =G53 -> 0 | F38: = 营业成本 | G38: =营业成本!B12+营业成本!B54 -> 0
F39: - 存货期初余额-存货期末余额 | G39: =现金流量表附表!I50 -> 0
F40: + 应付账款期初余额-应付账款期末余额 | G40: =-现金流量表附表!I63 -> 0
F41: + 预付账款期初余额-预付账款期末余额 | G41: =现金流量表附表!I56 -> 0
F42: + 应付票据期初余额-应付票据期末余额 | G42: =-现金流量表附表!I64 -> 0
F43: - 当期以非现金资产清偿债务减少的应付账款和应付票据
F44: + 进项税
F45: - 进行税额转出
F46: - 计入生产成本、制造费用的折旧费
F47: - 计入生产成本、制造费用的工资
F48: - 计入生产成本、制造费用的福利费
F49: ＋当期支付的在管理费用中列支的购买商品和接受劳务费用
F50: ＋当期支付的在营业费用中列支的购买商品和接受劳务费用
F51: + 其他
F52: 小计 | G52: =G38-G39+G40+G41+G42-G43+G44-G45-G46-G47-G48+G49+G50+G51 -> 0
A54: 支付给职工以及为职工支付的现金 | B54: 6 | C54: =E54-D54 -> 0 | E54: =G57 -> 0 | F54: = 应付工资借方发生额 | G54: =应付职工薪酬!B27 -> 0
F55: - 支付的在建工程人员的工资等，在“购建固定资产、无形资产和其他长期资产所支付的现金”项目反映。
F56: ＋ 其他
F57: 小计 | G57: =G54+G56-G55 -> 0
A59: 支付的各项税费 | B59: 7 | C59: =E59-D59 -> 0 | E59: =G62 -> 0 | F59: = 应交税费借方发生额 | G59: =应交税费!B36 -> 0
F60: - 其中个人所得税本期支付金额
F61: ＋当期支付的直接列入管理费用的印花税等税费
F62: 小计 | G62: =G59-G60+G61 -> 0
A64: 支付的其他与经营活动有关的现金 | B64: 8 | C64: =E64-D64 -> 0 | E64: =G75 -> 0 | F64: = 管理费用 | G64: =管理费用!B14 -> 0
F65: - 管理费用中的固定资产折旧、无形资产摊销、低值易耗品摊销
F66: - 管理费用中的职工薪酬等
F67: - 管理费用中的税费等 | G67: =G61 -> 0
F68: + 销售费用 | G68: =销售费用!B14 -> 0
F69: - 销售费用中的固定资产折旧、无形资产摊销、低值易耗品摊销
F70: - 销售费用中的职工薪酬等
F71: - 销售费用中的税费等
F72: + 营业外支出(捐赠支出、罚款支出等)
F73: + 其他应付款期初余额-其他应付款期末余额 | G73: =-现金流量表附表!I68 -> 0
F74: ＋ 其他
F75: 小计 | G75: =G64-G65-G66-G67+G68-G69-G70-G71+G72+G73+G74 -> 0
A77: 经营活动现金流出小计 | B77: 9 | C77: =E77-D77 -> 0 | E77: =SUM(E38:E64) -> 0
A78: 经营活动产生的现金流量净额 | B78: 10 | C78: =E78-D78 -> 0 | E78: =SUM(-E77,E37) -> 0
A79: 二、投资活动产生的现金流量： | B79: 11 | C79: =E79-D79 -> 0
A80: 收回投资所收到的现金 | B80: 12 | C80: =E80-D80 -> 0 | E80: =G85 -> 0 | F80: = 短期投资(贷方发生额)
F81: ＋ 长期股权投资(股票投资贷方发生额)
F82: ＋ 长期股权投资(其他股权投资贷方发生额-收回固定资产或 其他非现金资产的入账净值)
F83: ＋ 长期债权投资(债券投资面值贷方发生额)
F84: ＋ 长期债权投资(其他债权投资本金贷方发生额)
F85: 小计 | G85: =SUM(G80:G84) -> 0
A87: 取得投资收益所收到的现金 | B87: 13 | C87: =E87-D87 -> 0 | E87: =G91 -> 0 | F87: = 投资收益(股利或利润)
F88: ＋ [应收股利(短期投资)期初余额-应收股利(短期投资)期末余 额]+[应收股利(长期股权投资，成本法)期初余额-应收股利 (长期股权投资，成本法)期末余额]
F89: + [长期股权投资(按权益法分享的利润；如亏损，用负数表示) 期初余额-长期股权投资(按权益法分享的利润；如亏损，用 负数表示)期末余额]
F90: ＋ 投资收益(债券利息收入)
F91: 小计 | G91: =SUM(G86:G90) -> 0
A93: 处置固定资产、无形资产和其他长期资产所收回的现金净额 | B93: 14 | C93: =E93-D93 -> 0
A94: 处置子公司及其他营业单位收到的现金净额 | B94: 15 | C94: =E94-D94 -> 0
A95: 收到的其他与投资活动有关的现金 | B95: 16 | C95: =E95-D95 -> 0 | E95: =G97 -> 0 | F95: = 接受现金捐赠
F96: +其他
F97: 小计 | G97: =SUM(G95:G96) -> 0
A99: 投资活动现金流入小计 | B99: 17 | C99: =E99-D99 -> 0 | E99: =SUM(E80:E95) -> 0
A100: 购建固定资产、无形资产和其他资产所支付的现金 | B100: 18 | C100: =E100-D100 -> 0 | E100: =G112 -> 0 | F100: + 投资性房地产原值本期购置增加 | G100: ='投资性房地产（成本模式）'!B16 -> 0
F101: + 无形资产原值本期购置增加 | G101: =无形资产!B19 -> 0
F102: + 固定资产原值本期购置增加 | G102: =固定资产!B18 -> 0
F103: + 固定资产采购进项税额
F104: + 在建工程原值本期购置增加
F105: + 工程物资原值本期增加
F106: + 开发支出原值本期增加
F107: + 本期长期待摊费用及其他长期资产的增加
F108: + 预付账款的增加（设备及工程）
F109: + 应付账款的减少（设备及工程）
F110: + 其他应付款的减少（长期资产款项）
...

Sheet 现金流量表附表
A1: 致同会计师事务所
A2: 现金流量表-补充资料的核查记录
A3: 客户名称： | C3: 编制人： | G3: 日期： | J3: 返回Excel目录 | M3: 索引： | N3: A5-1-3
A4: 会计期间： | C4: 复核人: | G4: 日期: | M4: 页次：
A5: （一）现金流量表补充资料
A6: 补充资料 | B6: 行次 | C6: 差异(按报表账户) | D6: 原报数 | E6: 测算数 | F6: 有关测算依据
C7: 1=3-2 | D7: 2 | E7: 3 | F7: 4
A8: 1、将净利润调节为经营活动现金流量：
A9: 净利润 | B9: 40 | C9: =E9-D9 -> 0
A10: 加：少数股东收益
A11: 加：计提的资产减值准备 | B11: 41 | C11: =E11-D11 -> 0 | E11: =G26 -> 0 | F11: = 本期计提应收帐款坏账准备
F12: + 本期计提其他应收款坏账准备
F13: + 本期计提存货跌价准备 | G13: =资产减值损失!B4 -> 0
F14: + 本期计提可供出售金融资产减值准备 | G14: =资产减值损失!B5 -> 0
F15: + 本期计提持有至到期投资减值准备 | G15: =资产减值损失!B6 -> 0
F16: + 本期计提长期投资减值准备 | G16: =资产减值损失!B7 -> 0
F17: + 本期计提投资性房地产减值准备 | G17: =资产减值损失!B8 -> 0
F18: + 本期计提固定资产减值准备 | G18: =资产减值损失!B9 -> 0
F19: + 本期计提工程物资减值准备 | G19: =资产减值损失!B10 -> 0
F20: + 本期计提在建工程减值准备 | G20: =资产减值损失!B11 -> 0
F21: + 本期计提生产性生物资产减值准备 | G21: =资产减值损失!B12 -> 0
F22: + 本期计提油气资产减值准备 | G22: =资产减值损失!B13 -> 0
F23: + 本期计提无形资产减值准备 | G23: =资产减值损失!B14 -> 0
F24: + 本期计提商誉减值准备 | G24: =资产减值损失!B15 -> 0
F25: + 本期计提其他减值准备 | G25: =资产减值损失!B16 -> 0
F26: 小计 | G26: =SUM(G11:G25) -> 0
A28: 固定资产折旧、油气资产折耗、生产性生物资产折旧 | B28: 43 | C28: =E28-D28 -> 0 | E28: =G30 -> 0 | F28: = 固定资产本期计提折旧额 | G28: =固定资产!B82 -> 0
F29: + 油气资产本期计提折耗额
F30: + 生产性生物资产本期计提折旧额 | G30: ='生产性生物资产（成本计量）'!B84 -> 0
F31: 小计 | G31: =SUM(G28:G30) -> 0
A33: 无形资产摊销 | B33: 44 | C33: =E33-D33 -> 0 | E33: =G33 -> 0 | F33: = 无形资产本期计提摊销额 | G33: =无形资产!B92 -> 0
A34: 长期待摊费用摊销 | B34: 45 | C34: =E34-D34 -> 0 | E34: =G34 -> 0 | F34: = 长期待摊费用本期摊销数 | G34: =长期待摊费用!B27 -> 0
A35: 处置固定资产、无形资产和其他长期资产的损失（收益以"-"填列） | B35: 46 | C35: =E35-D35 -> 0 | E35: =L40 -> 0 | G35: 原值 | H35: 累计折旧 | I35: 减值准备 | J35: 净值 | K35: 收现/付现 | L35: 净损失
F36: = 固定资产 | J36: =G36-H36-I36 -> 0 | L36: =J36-K36 -> 0
F37: = 无形资产 | J37: =G37-H37-I37 -> 0 | L37: =J37-K37 -> 0
F38: = 其他长期资产 | J38: =G38-H38-I38 -> 0 | L38: =J38-K38 -> 0
F39: = 其他 | J39: =G39-H39-I39 -> 0 | L39: =J39-K39 -> 0
F40: 小计 | G40: =SUM(G36:G39) -> 0 | H40: =SUM(H36:H39) -> 0 | I40: =SUM(I36:I39) -> 0 | J40: =SUM(J36:J39) -> 0 | K40: =SUM(K36:K39) -> 0 | L40: =SUM(L36:L39) -> 0
A41: 固定资产报废损失（收益以"-"填列） | B41: 47 | C41: =E41-D41 -> 0 | E41: =固定资产!B45-固定资产!B100-固定资产!B155-E35 -> 0
A42: 公允价值变动损失（收益以“－”号填列） | B42: 48 | C42: =E42-D42 -> 0 | E42: =G42 -> 0 | F42: = 公允价值变动损益本期发生额 | G42: =-公允价值变动收益!B9 -> 0
A43: 财务费用（收益以"-"填列） | B43: 49 | C43: =E43-D43 -> 0 | E43: =G43 -> 0 | F43: 筹资财务费用借方数(扣除贴现利息支出后)-经营性项目汇兑损失-筹资、投资性项目汇兑收益+货币资金项目汇兑损失（减：收益）
A44: 投资损失（收益以"-"填列） | B44: 50 | C44: =E44-D44 -> 0 | F44: = 投资收益本期发生额 | G44: =-投资收益!B13 -> 0
A45: 递延所得税资产减少（增加以“－”号填列） | B45: 51 | C45: =E45-D45 -> 0 | E45: =I46 -> 0 | F45: = 递延所得税资产期初余额-递延所得税资产期末余额 | G45: 期初余额 | H45: 期末余额 | I45: 期初-期末
H46: =递延所得税资产!B11 -> 0 | I46: =G46-H46 -> 0
A47: 递延所得税负债增加（减少以“－”号填列） | B47: 52 | C47: =E47-D47 -> 0 | E47: =I48 -> 0 | F47: = 递延所得税负债期末余额-递延所得税资产期初余额 | G47: 期初余额 | H47: 期末余额 | I47: 期末-期初
H48: =递延所得税负债!B11 -> 0 | I48: =H48-G48 -> 0
B49: 53 | C49: =E49-D49 -> 0 | E49: =K50 -> 0 | F49: = 存货期初余额-存货期末余额 | G49: 期初余额 | H49: 期末余额 | I49: 期初-期末 | J49: 非经营性减少 | K49: 存货实际减少
G50: =存货!B11 -> 0 | H50: =存货!B41 -> 0 | I50: =G50-H50 -> 0 | K50: =I50-J50 -> 0
A52: 经营性应收项目的减少（增加以“－”号填列） | B52: 54 | C52: =E52-D52 -> 0 | E52: =K60 -> 0 | G52: 期初余额 | H52: 期末余额 | I52: 期初-期末 | J52: 非经营性减少 | K52: 实际减少
F53: 应收票据的减少 | H53: =应收票据!B5 -> 0 | I53: =G53-H53 -> 0 | K53: =I53-J53 -> 0
F54: 应收账款的减少 | H54: =应收账款!B9 -> 0 | I54: =G54-H54 -> 0 | K54: =I54-J54 -> 0
F55: 其他应收款的减少 | H55: =其他应收款!B9 -> 0 | I55: =G55-H55 -> 0 | K55: =I55-J55 -> 0
F56: 预付账款的减少 | H56: =预付款项!B7 -> 0 | I56: =G56-H56 -> 0 | K56: =I56-J56 -> 0
F57: 一年内到期的非流动资产减少 | H57: =一年内到期的非流动资产!B7 -> 0 | I57: =G57-H57 -> 0 | K57: =I57-J57 -> 0
F58: 其他流动资产的减少 | H58: =其他流动资产!B9 -> 0 | I58: =G58-H58 -> 0 | K58: =I58-J58 -> 0
F59: 长期应收款的减少 | H59: =长期应收款!B14 -> 0 | I59: =G59-H59 -> 0 | K59: =I59-J59 -> 0
F60: 小计 | G60: =SUM(G53:G59) -> 0 | H60: =SUM(H53:H59) -> 0 | I60: =SUM(I53:I59) -> 0 | J60: =SUM(J53:J59) -> 0 | K60: =SUM(K53:K59) -> 0
A62: 经营性应付项目的增加（减少以“－”号填列） | B62: 55 | C62: =E62-D62 -> 0 | E62: =K75 -> 0 | F62: 负债方经营性项目增加 | G62: 期初余额 | H62: 期末余额 | I62: 期末-期初 | J62: 非经营性减少 | K62: 实际增加
F63: 应付帐款的增加 | H63: =应付账款!B10 -> 0 | I63: =H63-G63 -> 0 | K63: =I63-J63 -> 0
F64: 应付票据的增加 | H64: =应付票据!B5 -> 0 | I64: =H64-G64 -> 0 | K64: =I64-J64 -> 0
F65: 预收帐款的增加 | H65: 0 | I65: =H65-G65 -> 0 | K65: =I65-J65 -> 0
F66: 应付职工薪酬的增加 | G66: =应付职工薪酬!B9 -> 0 | H66: =应付职工薪酬!B36 -> 0 | I66: =H66-G66 -> 0 | K66: =I66-J66 -> 0
F67: 应交税费的增加 | G67: =应交税费!B12 -> 0 | H67: =应交税费!B48 -> 0 | I67: =H67-G67 -> 0 | K67: =I67-J67 -> 0
F68: 其他应付款的增加 | H68: =其他应付款!B8 -> 0 | I68: =H68-G68 -> 0 | K68: =I68-J68 -> 0
F69: 一年内到期的非流动负债增加 | H69: =一年内到期的非流动负债!B10 -> 0 | I69: =H69-G69 -> 0 | K69: =I69-J69 -> 0
F70: 其他流动负债增加 | H70: =其他流动负债!B7 -> 0 | I70: =H70-G70 -> 0 | K70: =I70-J70 -> 0
F71: 长期应付款增加 | H71: =长期应付款!B9 -> 0 | I71: =H71-G71 -> 0 | K71: =I71-J71 -> 0
F72: 专项应付款增加 | G72: =专项应付款!B9 -> 0 | H72: =专项应付款!B36 -> 0 | I72: =H72-G72 -> 0 | K72: =I72-J72 -> 0
F73: 预计负债增加 | H73: =预计负债!B10 -> 0 | I73: =H73-G73 -> 0 | K73: =I73-J73 -> 0
F74: 其他非流动负债增加 | H74: =其他非流动负债!B7 -> 0 | I74: =H74-G74 -> 0 | K74: =I74-J74 -> 0
F75: 小计 | G75: =SUM(G63:G74) -> 0 | H75: =SUM(H63:H74) -> 0 | I75: =SUM(I63:I74) -> 0 | J75: =SUM(J63:J74) -> 0 | K75: =SUM(K63:K74) -> 0
A76: 其他 | B76: 56 | C76: =E76-D76 -> 0
A77: 经营活动产生的现金流量净额 | B77: 57 | C77: =E77-D77 -> 0 | E77: =SUM(E9:E76) -> 0
A78: 2、不涉及现金收支的投资和筹资活动 | B78: 58 | C78: =E78-D78 -> 0
A79: 债务转为资本 | B79: 59 | C79: =E79-D79 -> 0
A80: 一年内到期的可转换公司债券 | B80: 60 | C80: =E80-D80 -> 0
A81: 融资租入固定资产 | B81: 61 | C81: =E81-D81 -> 0
A82: 3、现金及现金等价物净增加情况： | B82: 62 | C82: =E82-D82 -> 0
A83: 现金期末余额 | B83: 63 | C83: =E83-D83 -> 0
A84: 减：现金的期初余额 | B84: 64 | C84: =E84-D84 -> 0
A85: 加：现金等价物的期末余额 | B85: 65 | C85: =E85-D85 -> 0
A86: 减：现金等价物的期初余额 | B86: 66 | C86: =E86-D86 -> 0
A87: 现金及现金等价物净增加额 | B87: 67 | C87: =E87-D87 -> 0 | E87: =E83-E84 -> 0
A90: 编制说明：
A91: 1、所谓间接法，是指以净利润为起算点，调整不涉及现金的收入、费用、营业外收支等有关项目，剔除投资活动、筹资活动对现金流量的影响，据此计算出经营活动产生的现金流量。
A92: 2、由于净利润是按照权责发生制原则确定的，且包括了与投资活动和筹资活动相关的收益和费用，将净利润调节为经营活动现金流量，实际上就是将按权责发生制原则确定的净利润
A93: 调整为现金净流入，并剔除投资活动和筹资活动对现金流量的影响。
A95: 3、财务费用：企业发生的财务费用中不属于经营活动的部分，应加回。
A96: 4、存货的减少(减：增加)：如果存货的增减变化过程属于投资活动，如在建工程领用存货，应当将这一因素剔除。

Sheet 货币资金
A1: 货币资金附注汇总 | D1: 返回Excel目录 | E1: 返回word附注
A2: 项目 | B2: 审定数 | C2: 抵消数 | D2: 汇总 | E2: 母公司审定 | F2: 子公司1 | G2: 子公司2 | H2: 子公司3 | I2: 子公司4 | J2: 子公司5 | K2: 子公司6 | L2: 子公司7 | M2: 子公司8 | N2: 子公司9 | O2: 子公司10 | P2: 子公司11 | Q2: 子公司12
A3: 现金 | B3: =SUM(B4:B5) -> 0 | C3: =SUM(C4:C5) -> 0 | D3: =SUM(E3:Q3) -> 0 | E3: =SUM(E4:E5) -> 0 | F3: =SUM(F4:F5) -> 0 | G3: =SUM(G4:G5) -> 0 | H3: =SUM(H4:H5) -> 0 | I3: =SUM(I4:I5) -> 0 | J3: =SUM(J4:J5) -> 0 | K3: =SUM(K4:K5) -> 0 | L3: =SUM(L4:L5) -> 0 | ... Q3: =SUM(Q4:Q5) -> 0
A4: 其中：人民币 | B4: =D4-C4 -> 0 | D4: =SUM(E4:Q4) -> 0 | E4: 0
A5: 美元 | B5: =D5-C5 -> 0 | D5: =SUM(E5:Q5) -> 0 | E5: 0
A6: 银行存款 | B6: =SUM(B7:B8) -> 0 | C6: =SUM(C7:C8) -> 0 | D6: =SUM(E6:Q6) -> 0 | E6: =SUM(E7:E8) -> 0 | F6: =SUM(F7:F8) -> 0 | G6: =SUM(G7:G8) -> 0 | H6: =SUM(H7:H8) -> 0 | I6: =SUM(I7:I8) -> 0 | J6: =SUM(J7:J8) -> 0 | K6: =SUM(K7:K8) -> 0 | L6: =SUM(L7:L8) -> 0 | ... Q6: =SUM(Q7:Q8) -> 0
A7: 其中：人民币 | B7: =D7-C7 -> 0 | D7: =SUM(E7:Q7) -> 0 | E7: 0
A8: 美元 | B8: =D8-C8 -> 0 | D8: =SUM(E8:Q8) -> 0 | E8: 0
A9: 其他货币资金 | B9: =SUM(B10:B11) -> 0 | C9: =SUM(C10:C11) -> 0 | D9: =SUM(E9:Q9) -> 0 | E9: =SUM(E10:E11) -> 0 | F9: =SUM(F10:F11) -> 0 | G9: =SUM(G10:G11) -> 0 | H9: =SUM(H10:H11) -> 0 | I9: =SUM(I10:I11) -> 0 | J9: =SUM(J10:J11) -> 0 | K9: =SUM(K10:K11) -> 0 | L9: =SUM(L10:L11) -> 0 | ... Q9: =SUM(Q10:Q11) -> 0
A10: 其中：人民币 | B10: =D10-C10 -> 0 | D10: =SUM(E10:Q10) -> 0 | E10: 0
A11: 美元 | B11: =D11-C11 -> 0 | D11: =SUM(E11:Q11) -> 0 | E11: 0
A12: 合计 | B12: =B3+B6+B9 -> 0 | C12: =C3+C6+C9 -> 0 | D12: =D3+D6+D9 -> 0 | E12: =E3+E6+E9 -> 0 | F12: =F3+F6+F9 -> 0 | G12: =G3+G6+G9 -> 0 | H12: =H3+H6+H9 -> 0 | I12: =I3+I6+I9 -> 0 | ... Q12: =Q3+Q6+Q9 -> 0
A13: 试算表链接： | B13: 0 | D13: =SUM(E13:Q13) -> 0 | E13: 0
A14: 差异 | B14: =B12-B13 -> 0 | D14: =D12-D13 -> 0 | E14: =E12-E13 -> 0 | F14: =F12-F13 -> 0 | G14: =G12-G13 -> 0 | H14: =H12-H13 -> 0 | I14: =I12-I13 -> 0 | J14: =J12-J13 -> 0 | K14: =K12-K13 -> 0 | ... Q14: =Q12-Q13 -> 0
A16: 说明存在抵押、冻结等对变现有限制或存放在境外、或有潜在回收风险的资金
A17: 其他货币资金明细
A18: 项目 | B18: 审定数 | C18: 抵消数 | D18: 汇总 | E18: 母公司 | F18: 子公司1 | G18: 子公司2 | H18: 子公司3 | I18: 子公司4 | J18: 子公司5 | K18: 子公司6 | L18: 子公司7 | M18: 子公司8 | N18: 子公司9 | O18: 子公司10 | P18: 子公司11 | Q18: 子公司12
A19: 票据保证金 | B19: =D19-C19 -> 0 | D19: =SUM(E19:Q19) -> 0 | E19: 0
A20: 信用证保证金 | B20: =D20-C20 -> 0 | D20: =SUM(E20:Q20) -> 0 | E20: 0
A21: 存出投资款 | B21: =D21-C21 -> 0 | D21: =SUM(E21:Q21) -> 0 | E21: 0
A22: … | B22: =D22-C22 -> 0 | D22: =SUM(E22:Q22) -> 0 | E22: 0
A23: 合计 | B23: =SUM(B19:B22) -> 0 | C23: =SUM(C19:C22) -> 0 | D23: =SUM(D19:D22) -> 0 | E23: =SUM(E19:E22) -> 0 | F23: =SUM(F19:F22) -> 0 | J23: =SUM(J19:J22) -> 0 | K23: =SUM(K19:K22) -> 0 | P23: =SUM(P19:P22) -> 0 | Q23: =SUM(Q19:Q22) -> 0
A24: 差异 | B24: =B9-B23 -> 0 | C24: =C9-C23 -> 0 | D24: =D9-D23 -> 0 | E24: =E9-E23 -> 0 | F24: =F9-F23 -> 0 | J24: =J9-J23 -> 0 | K24: =K9-K23 -> 0 | P24: =P9-P23 -> 0 | Q24: =Q9-Q23 -> 0
A26: 存放境外的款项
A27: 项目 | B27: 审定数 | C27: 抵消数 | D27: 汇总 | E27: 母公司 | F27: 子公司1 | G27: 子公司2 | H27: 子公司3 | I27: 子公司4 | J27: 子公司5 | K27: 子公司6 | L27: 子公司7 | M27: 子公司8 | N27: 子公司9 | O27: 子公司10 | P27: 子公司11 | Q27: 子公司12
B28: =D28-C28 -> 0 | D28: =SUM(E28:Q28) -> 0 | E28: 0
A29: 合计 | B29: =B28 -> 0 | C29: =C28 -> 0 | D29: =D28 -> 0 | E29: =E28 -> 0 | F29: =F28 -> 0 | J29: =J28 -> 0 | K29: =K28 -> 0 | P29: =P28 -> 0 | Q29: =Q28 -> 0
A31: 银行存款中：财务公司存款
A32: 项目 | B32: 审定数 | C32: 抵消数 | D32: 汇总 | E32: 母公司 | F32: 子公司1 | G32: 子公司2 | H32: 子公司3 | I32: 子公司4 | J32: 子公司5 | K32: 子公司6 | L32: 子公司7 | M32: 子公司8 | N32: 子公司9 | O32: 子公司10 | P32: 子公司11 | Q32: 子公司12
A33: 其中：人民币 | B33: =D33-C33 -> 0 | D33: =SUM(E33:Q33) -> 0 | E33: 0
A34: 美元 | B34: =D34-C34 -> 0 | D34: =SUM(E34:Q34) -> 0 | E34: 0
A35: 合计 | B35: =SUM(B33:B34) -> 0 | C35: =SUM(C33:C34) -> 0 | D35: =SUM(D33:D34) -> 0 | E35: =SUM(E33:E34) -> 0 | F35: =SUM(F33:F34) -> 0 | G35: =SUM(G33:G34) -> 0 | H35: =SUM(H33:H34) -> 0 | I35: =SUM(I33:I34) -> 0 | ... Q35: =SUM(Q33:Q34) -> 0

Sheet 交易性金融资产
A1: 交易性金融资产附注汇总 | D1: 返回Excel目录 | E1: 返回word附注
A3: 项目 | B3: 审定数 | C3: 抵消数 | D3: 汇总 | E3: 母公司审定 | F3: 子公司1 | G3: 子公司2 | H3: 子公司3 | I3: 子公司4 | J3: 子公司5 | K3: 子公司6 | L3: 子公司7 | M3: 子公司8 | N3: 子公司9 | O3: 子公司10 | P3: 子公司11 | Q3: 子公司12
A4: 债务工具投资 | B4: =D4-C4 -> 0 | D4: =SUM(E4:Q4) -> 0 | E4: 0
A5: 权益工具投资 | B5: =D5-C5 -> 0 | D5: =SUM(E5:Q5) -> 0 | E5: 0
A6: 衍生金融资产 | B6: =D6-C6 -> 0 | D6: =SUM(E6:Q6) -> 0 | E6: 0
A7: 其他 | B7: =D7-C7 -> 0 | D7: =SUM(E7:Q7) -> 0 | E7: 0
A8: 合计 | B8: =SUM(B4:B7) -> 0 | C8: =SUM(C4:C7) -> 0 | D8: =SUM(D4:D7) -> 0 | E8: =SUM(E4:E7) -> 0 | F8: =SUM(F4:F7) -> 0 | G8: =SUM(G4:G7) -> 0 | H8: =SUM(H4:H7) -> 0 | I8: =SUM(I4:I7) -> 0 | ... Q8: =SUM(Q4:Q7) -> 0
A9: 试算表链接：
A10: 差异 | B10: =B8-B9 -> 0
A11: 说明：
A12: （1）管理层认为交易性金融资产投资变现[不存在重大限制]。/〔存在下列限制：具体限制及原因〕）
A13: （2）请说明交易性金融资产期末公允价值的确认方法及对当期损益的影响，如采用估值技术确定公允价值时，应详细披露估值模型、重要参数的选取依据和估值过程，以及必要的敏感性分析。

Sheet 以公允价值计量且其变动计入当期损益的金融资产
A1: 以公允价值计量且其变动计入当期损益的金融资产 | E1: 返回Excel目录 | F1: 返回word附注
A2: 项目 | B2: 审定数 | C2: 抵消数 | D2: 汇总 | E2: 母公司审定 | F2: 子公司1 | G2: 子公司2 | H2: 子公司3 | I2: 子公司4 | J2: 子公司5 | K2: 子公司6 | L2: 子公司7 | M2: 子公司8 | N2: 子公司9 | O2: 子公司10 | P2: 子公司11 | Q2: 子公司12
A3: 交易性金融资产 | B3: =SUM(B4:B7) -> 0 | C3: =SUM(C4:C7) -> 0 | D3: =SUM(E3:Q3) -> 0 | E3: =SUM(E4:E7) -> 0 | F3: =SUM(F4:F7) -> 0 | G3: =SUM(G4:G7) -> 0 | H3: =SUM(H4:H7) -> 0 | I3: =SUM(I4:I7) -> 0 | J3: =SUM(J4:J7) -> 0 | K3: =SUM(K4:K7) -> 0 | L3: =SUM(L4:L7) -> 0 | ... Q3: =SUM(Q4:Q7) -> 0
A4: 其中：债务工具投资 | B4: =D4-C4 -> 0 | D4: =SUM(E4:Q4) -> 0 | E4: 0
A5: 权益工具投资 | B5: =D5-C5 -> 0 | D5: =SUM(E5:Q5) -> 0 | E5: 0
A6: 衍生金融资产 | B6: =D6-C6 -> 0 | D6: =SUM(E6:Q6) -> 0 | E6: 0
A7: 其他 | B7: =D7-C7 -> 0 | D7: =SUM(E7:Q7) -> 0 | E7: 0
A8: 指定为以公允价值计量且其变动计入当期损益的金融资产 | B8: =SUM(B9:B12) -> 0 | C8: =SUM(C9:C12) -> 0 | D8: =SUM(E8:Q8) -> 0 | E8: =SUM(E9:E12) -> 0 | F8: =SUM(F9:F12) -> 0 | G8: =SUM(G9:G12) -> 0 | H8: =SUM(H9:H12) -> 0 | I8: =SUM(I9:I12) -> 0 | J8: =SUM(J9:J12) -> 0 | K8: =SUM(K9:K12) -> 0 | L8: =SUM(L9:L12) -> 0 | ... Q8: =SUM(Q9:Q12) -> 0
A9: 其中：债务工具投资 | B9: =D9-C9 -> 0 | D9: =SUM(E9:Q9) -> 0 | E9: 0
A10: 权益工具投资 | B10: =D10-C10 -> 0 | D10: =SUM(E10:Q10) -> 0 | E10: 0
A11: 衍生金融资产 | B11: =D11-C11 -> 0 | D11: =SUM(E11:Q11) -> 0 | E11: 0
A12: 其他 | B12: =D12-C12 -> 0 | D12: =SUM(E12:Q12) -> 0 | E12: 0
A13: 合 计 | B13: =B3+B8 -> 0 | C13: =C3+C8 -> 0 | D13: =SUM(E13:Q13) -> 0 | E13: =E3+E8 -> 0 | F13: =F3+F8 -> 0 | G13: =G3+G8 -> 0 | H13: =H3+H8 -> 0 | I13: =I3+I8 -> 0 | J13: =J3+J8 -> 0 | K13: =K3+K8 -> 0 | L13: =L3+L8 -> 0 | ... Q13: =Q3+Q8 -> 0
A14: 试算表链接： | B14: 0 | D14: =SUM(E14:Q14) -> 0 | E14: 0
A15: 差异 | B15: =B13-B14 -> 0 | D15: =D13-D14 -> 0 | E15: =E13-E14 -> 0 | F15: =F13-F14 -> 0 | G15: =G13-G14 -> 0 | H15: =H13-H14 -> 0 | I15: =I13-I14 -> 0 | J15: =J13-J14 -> 0 | K15: =K13-K14 -> 0 | ... Q15: =Q13-Q14 -> 0
A16: 说明：
A18: 适用：证券公司披露成本金额
A19: 项目 | B19: 审定数 | C19: 抵消数 | D19: 汇总 | E19: 母公司审定 | F19: 子公司1 | G19: 子公司2 | H19: 子公司3 | I19: 子公司4 | J19: 子公司5 | K19: 子公司6 | L19: 子公司7 | M19: 子公司8 | N19: 子公司9 | O19: 子公司10 | P19: 子公司11 | Q19: 子公司12
A20: 交易性金融资产 | B20: =SUM(B21:B24) -> 0 | C20: =SUM(C21:C24) -> 0 | D20: =SUM(E20:Q20) -> 0 | E20: =SUM(E21:E24) -> 0 | F20: =SUM(F21:F24) -> 0 | G20: =SUM(G21:G24) -> 0 | H20: =SUM(H21:H24) -> 0 | I20: =SUM(I21:I24) -> 0 | J20: =SUM(J21:J24) -> 0 | K20: =SUM(K21:K24) -> 0 | L20: =SUM(L21:L24) -> 0 | ... Q20: =SUM(Q21:Q24) -> 0
A21: 其中：债务工具投资 | B21: =D21-C21 -> 0 | D21: =SUM(E21:Q21) -> 0 | E21: 0
A22: 权益工具投资 | B22: =D22-C22 -> 0 | D22: =SUM(E22:Q22) -> 0 | E22: 0
A23: 衍生金融资产 | B23: =D23-C23 -> 0 | D23: =SUM(E23:Q23) -> 0 | E23: 0
A24: 其他 | B24: =D24-C24 -> 0 | D24: =SUM(E24:Q24) -> 0 | E24: 0
A25: 指定为以公允价值计量且其变动计入当期损益的金融资产 | B25: =SUM(B26:B29) -> 0 | C25: =SUM(C26:C29) -> 0 | D25: =SUM(E25:Q25) -> 0 | E25: 0 | F25: =SUM(F26:F29) -> 0 | G25: =SUM(G26:G29) -> 0 | H25: =SUM(H26:H29) -> 0 | I25: =SUM(I26:I29) -> 0 | J25: =SUM(J26:J29) -> 0 | K25: =SUM(K26:K29) -> 0 | L25: =SUM(L26:L29) -> 0 | M25: =SUM(M26:M29) -> 0 | ... Q25: =SUM(Q26:Q29) -> 0
A26: 其中：债务工具投资 | B26: =D26-C26 -> 0 | D26: =SUM(E26:Q26) -> 0 | E26: 0
A27: 权益工具投资 | B27: =D27-C27 -> 0 | D27: =SUM(E27:Q27) -> 0 | E27: 0
A28: 衍生金融资产 | B28: =D28-C28 -> 0 | D28: =SUM(E28:Q28) -> 0 | E28: 0
A29: 其他 | B29: =D29-C29 -> 0 | D29: =SUM(E29:Q29) -> 0 | E29: 0
A30: 合 计 | B30: =B20+B25 -> 0 | C30: =C20+C25 -> 0 | D30: =SUM(E30:Q30) -> 0 | E30: =E20+E25 -> 0 | F30: =F20+F25 -> 0 | G30: =G20+G25 -> 0 | H30: =H20+H25 -> 0 | I30: =I20+I25 -> 0 | J30: =J20+J25 -> 0 | K30: =K20+K25 -> 0 | L30: =L20+L25 -> 0 | ... Q30: =Q20+Q25 -> 0

Sheet 衍生金融资产
A1: 衍生金融资产附注 | D1: 返回Excel目录 | E1: 返回word附注
A2: 项目 | B2: 审定数 | C2: 抵消数 | D2: 汇总 | E2: 母公司审定 | F2: 子公司1 | G2: 子公司2 | H2: 子公司3 | I2: 子公司4 | J2: 子公司5 | K2: 子公司6 | L2: 子公司7 | M2: 子公司8 | N2: 子公司9 | O2: 子公司10 | P2: 子公司11 | Q2: 子公司12
B3: =D3-C3 -> 0 | D3: =SUM(E3:Q3) -> 0 | E3: 0
B4: =D4-C4 -> 0 | D4: =SUM(E4:Q4) -> 0 | E4: 0
B5: =D5-C5 -> 0 | D5: =SUM(E5:Q5) -> 0 | E5: 0
B6: =D6-C6 -> 0 | D6: =SUM(E6:Q6) -> 0 | E6: 0
B7: =D7-C7 -> 0 | D7: =SUM(E7:Q7) -> 0 | E7: 0
B8: =D8-C8 -> 0 | D8: =SUM(E8:Q8) -> 0 | E8: 0
A9: 合计 | B9: =SUM(B3:B8) -> 0 | C9: =SUM(C3:C8) -> 0 | D9: =SUM(D3:D8) -> 0 | E9: =SUM(E3:E8) -> 0 | F9: =SUM(F3:F8) -> 0 | G9: =SUM(G3:G8) -> 0 | H9: =SUM(H3:H8) -> 0 | I9: =SUM(I3:I8) -> 0 | ... Q9: =SUM(Q3:Q8) -> 0
A10: 试算表链接： | B10: 0 | D10: =SUM(E10:Q10) -> 0 | E10: 0
A11: 差异 | B11: =B9-B10 -> 0 | D11: =D9-D10 -> 0 | E11: =E9-E10 -> 0 | F11: =F9-F10 -> 0 | G11: =G9-G10 -> 0 | H11: =H9-H10 -> 0 | I11: =I9-I10 -> 0 | J11: =J9-J10 -> 0 | K11: =K9-K10 -> 0 | ... Q11: =Q9-Q10 -> 0
A12: 说明：（衍生金融资产产生的原因以及相关会计处理。）

Sheet 应收票据
A1: 应收票据附注汇总 | D1: 返回Excel目录 | E1: 返回word附注
A2: 项目 | B2: 审定数 | C2: 抵消数 | D2: 汇总 | E2: 母公司审定 | F2: 子公司1 | G2: 子公司2 | H2: 子公司3 | I2: 子公司4 | J2: 子公司5 | K2: 子公司6 | L2: 子公司7 | M2: 子公司8 | N2: 子公司9 | O2: 子公司10 | P2: 子公司11 | Q2: 子公司12
A3: 银行承兑汇票 | B3: =D3-C3 -> 0 | D3: =SUM(E3:Q3) -> 0 | E3: 0
A4: 商业承兑汇票 | B4: =D4-C4 -> 0 | D4: =SUM(E4:Q4) -> 0 | E4: 0
A5: 合计 | B5: =SUM(B3:B4) -> 0 | C5: =SUM(C3:C4) -> 0 | D5: =SUM(E5:Q5) -> 0 | E5: =SUM(E3:E4) -> 0 | F5: =SUM(F3:F4) -> 0 | G5: =SUM(G3:G4) -> 0 | H5: =SUM(H3:H4) -> 0 | I5: =SUM(I3:I4) -> 0 | J5: =SUM(J3:J4) -> 0 | K5: =SUM(K3:K4) -> 0 | L5: =SUM(L3:L4) -> 0 | ... Q5: =SUM(Q3:Q4) -> 0
A6: 试算表链接： | B6: 0 | D6: =SUM(E6:Q6) -> 0 | E6: 0
A7: 差异 | B7: =B5-B6 -> 0 | C7: =C5-C6 -> 0 | D7: =D5-D6 -> 0 | E7: =E5-E6 -> 0 | F7: =F5-F6 -> 0 | G7: =G5-G6 -> 0 | H7: =H5-H6 -> 0 | I7: =I5-I6 -> 0 | ... Q7: =Q5-Q6 -> 0
A9: （1）期末本集团已质押的应收票据
A10: 项目 | B10: 审定数 | C10: 抵消数 | D10: 汇总 | E10: 母公司审定 | F10: 子公司1 | G10: 子公司2 | H10: 子公司3 | I10: 子公司4 | J10: 子公司5 | K10: 子公司6 | L10: 子公司7 | M10: 子公司8 | N10: 子公司9 | O10: 子公司10 | P10: 子公司11 | Q10: 子公司12
A11: 银行承兑汇票 | B11: =D11-C11 -> 0 | D11: =SUM(E11:Q11) -> 0 | E11: 0
A12: 商业承兑汇票 | B12: =D12-C12 -> 0 | D12: =SUM(E12:Q12) -> 0 | E12: 0
A13: 合计 | B13: =SUM(B11:B12) -> 0 | C13: =SUM(C11:C12) -> 0 | D13: =SUM(E13:Q13) -> 0 | E13: =SUM(E11:E12) -> 0 | F13: =SUM(F11:F12) -> 0 | G13: =SUM(G11:G12) -> 0 | H13: =SUM(H11:H12) -> 0 | I13: =SUM(I11:I12) -> 0 | J13: =SUM(J11:J12) -> 0 | K13: =SUM(K11:K12) -> 0 | L13: =SUM(L11:L12) -> 0 | ... Q13: =SUM(Q11:Q12) -> 0
A15: （2）期末本集团已背书或贴现但尚未到期的应收票据
A16: A、背书尚未到期
A17: 项目 | B17: 审定数 | C17: 抵消数 | D17: 汇总 | E17: 母公司审定 | F17: 子公司1 | G17: 子公司2 | H17: 子公司3 | I17: 子公司4 | J17: 子公司5 | K17: 子公司6 | L17: 子公司7 | M17: 子公司8 | N17: 子公司9 | O17: 子公司10 | P17: 子公司11 | Q17: 子公司12
A18: 银行承兑汇票 | B18: =D18-C18 -> 0 | D18: =SUM(E18:Q18) -> 0 | E18: 0
A19: 商业承兑汇票 | B19: =D19-C19 -> 0 | D19: =SUM(E19:Q19) -> 0 | E19: 0
A20: 合计 | B20: =SUM(B18:B19) -> 0 | C20: =SUM(C18:C19) -> 0 | D20: =SUM(E20:Q20) -> 0 | E20: =SUM(E18:E19) -> 0 | F20: =SUM(F18:F19) -> 0 | G20: =SUM(G18:G19) -> 0 | H20: =SUM(H18:H19) -> 0 | I20: =SUM(I18:I19) -> 0 | J20: =SUM(J18:J19) -> 0 | K20: =SUM(K18:K19) -> 0 | L20: =SUM(L18:L19) -> 0 | ... Q20: =SUM(Q18:Q19) -> 0
A21: B、贴现金额
A22: 项目 | B22: 审定数 | C22: 抵消数 | D22: 汇总 | E22: 母公司审定 | F22: 子公司1 | G22: 子公司2 | H22: 子公司3 | I22: 子公司4 | J22: 子公司5 | K22: 子公司6 | L22: 子公司7 | M22: 子公司8 | N22: 子公司9 | O22: 子公司10 | P22: 子公司11 | Q22: 子公司12
A23: 银行承兑汇票 | B23: =D23-C23 -> 0 | D23: =SUM(E23:Q23) -> 0 | E23: 0
A24: 商业承兑汇票 | B24: =D24-C24 -> 0 | D24: =SUM(E24:Q24) -> 0 | E24: 0
A25: 合计 | B25: =SUM(B23:B24) -> 0 | C25: =SUM(C23:C24) -> 0 | D25: =SUM(E25:Q25) -> 0 | E25: =SUM(E23:E24) -> 0 | F25: =SUM(F23:F24) -> 0 | G25: =SUM(G23:G24) -> 0 | H25: =SUM(H23:H24) -> 0 | I25: =SUM(I23:I24) -> 0 | J25: =SUM(J23:J24) -> 0 | K25: =SUM(K23:K24) -> 0 | L25: =SUM(L23:L24) -> 0 | ... Q25: =SUM(Q23:Q24) -> 0
A26: （如根据《企业会计准则第23号——金融资产转移》终止确认的应收票据，列示其终止确认的金额，及与终止确认相关的利得和损失）
A28: （3）期末本集团因出票人未履约而其转应收账款的票据
A29: 项目 | B29: 审定数 | C29: 抵消数 | D29: 汇总 | E29: 母公司审定 | F29: 子公司1 | G29: 子公司2 | H29: 子公司3 | I29: 子公司4 | J29: 子公司5 | K29: 子公司6 | L29: 子公司7 | M29: 子公司8 | N29: 子公司9 | O29: 子公司10 | P29: 子公司11 | Q29: 子公司12
A30: 商业承兑汇票 | B30: =D30-C30 -> 0 | D30: =SUM(E30:Q30) -> 0 | E30: 0
B31: =D31-C31 -> 0 | D31: =SUM(E31:Q31) -> 0 | E31: 0
A32: 合计 | B32: =SUM(B30:B31) -> 0 | C32: =SUM(C30:C31) -> 0 | D32: =SUM(E32:Q32) -> 0 | E32: =SUM(E30:E31) -> 0 | F32: =SUM(F30:F31) -> 0 | G32: =SUM(G30:G31) -> 0 | H32: =SUM(H30:H31) -> 0 | I32: =SUM(I30:I31) -> 0 | J32: =SUM(J30:J31) -> 0 | K32: =SUM(K30:K31) -> 0 | L32: =SUM(L30:L31) -> 0 | ... Q32: =SUM(Q30:Q31) -> 0

Sheet 应收账款
A1: 应收账款附注 | E1: 返回Excel目录 | F1: 返回word附注
A2: 一、单项金额分类（原值）
A3: 项目 | B3: 审定数 | C3: 各项占比 | D3: 抵消数 | E3: 汇总 | F3: 母公司审定 | G3: 子公司1 | H3: 子公司2 | I3: 子公司3 | J3: 子公司4 | K3: 子公司5 | L3: 子公司6 | M3: 子公司7 | N3: 子公司8 | O3: 子公司9 | P3: 子公司10 | Q3: 子公司11 | R3: 子公司12
A4: 单项金额重大单项计提 | B4: =E4-D4 -> 0 | C4: =IF(ISERROR(B4/$B$9),"",B4/$B$9%) | E4: =SUM(F4:R4) -> 0 | F4: 0
A5: 按组合计提坏账 | B5: =E5-D5 -> 0 | C5: =IF(ISERROR(B5/$B$9),"",B5/$B$9%) | E5: =SUM(F5:R5) -> 0 | F5: 0
A6: 组合1 | B6: =E6-D6 -> 0 | C6: =IF(ISERROR(B6/$B$9),"",B6/$B$9%) | E6: =SUM(F6:R6) -> 0 | F6: 0
A7: 组合2 | B7: =E7-D7 -> 0 | C7: =IF(ISERROR(B7/$B$9),"",B7/$B$9%) | E7: =SUM(F7:R7) -> 0 | F7: 0
A8: 单项不重大单项计提坏账 | B8: =E8-D8 -> 0 | C8: =IF(ISERROR(B8/$B$9),"",B8/$B$9%) | E8: =SUM(F8:R8) -> 0 | F8: 0
A9: 合计 | B9: =SUM(B4:B8) -> 0 | C9: =SUM(C4:C8) -> 0 | D9: =SUM(D4:D8) -> 0 | E9: =SUM(F9:R9) -> 0 | F9: =SUM(F4:F8) -> 0 | G9: =SUM(G4:G8) -> 0 | H9: =SUM(H4:H8) -> 0 | I9: =SUM(I4:I8) -> 0 | J9: =SUM(J4:J8) -> 0 | K9: =SUM(K4:K8) -> 0 | L9: =SUM(L4:L8) -> 0 | M9: =SUM(M4:M8) -> 0 | ... R9: =SUM(R4:R8) -> 0
A11: 二、单项金额分类（坏账准备）
A12: 项目 | B12: 审定数 | C12: 计提比例 | D12: 抵消数 | E12: 汇总 | F12: 母公司审定 | G12: 子公司1 | H12: 子公司2 | I12: 子公司3 | J12: 子公司4 | K12: 子公司5 | L12: 子公司6 | M12: 子公司7 | N12: 子公司8 | O12: 子公司9 | P12: 子公司10 | Q12: 子公司11 | R12: 子公司12
A13: 单项金额重大单项计提 | B13: =E13-D13 -> 0 | C13: =IF(ISERROR(B13/B4),"",B13/B4) | E13: =SUM(F13:R13) -> 0 | F13: 0
A14: 按组合计提坏账 | B14: =E14-D14 -> 0 | C14: =IF(ISERROR(B14/B5),"",B14/B5) | E14: =SUM(F14:R14) -> 0 | F14: 0
A15: 组合1 | B15: =E15-D15 -> 0 | C15: =IF(ISERROR(B15/B6),"",B15/B6) | E15: =SUM(F15:R15) -> 0 | F15: 0
A16: 组合2 | B16: =E16-D16 -> 0 | C16: =IF(ISERROR(B16/B7),"",B16/B7) | E16: =SUM(F16:R16) -> 0 | F16: 0
A17: 单项不重大单项计提坏账 | B17: =E17-D17 -> 0 | C17: =IF(ISERROR(B17/B8),"",B17/B8) | E17: =SUM(F17:R17) -> 0 | F17: 0
A18: 合计 | B18: =SUM(B13:B17) -> 0 | C18: =IF(ISERROR(B18/B9),"",B18/B9) | D18: =SUM(D13:D17) -> 0 | E18: =SUM(F18:R18) -> 0 | F18: =SUM(F13:F17) -> 0 | G18: =SUM(G13:G17) -> 0 | H18: =SUM(H13:H17) -> 0 | I18: =SUM(I13:I17) -> 0 | J18: =SUM(J13:J17) -> 0 | K18: =SUM(K13:K17) -> 0 | L18: =SUM(L13:L17) -> 0 | M18: =SUM(M13:M17) -> 0 | ... R18: =SUM(R13:R17) -> 0
A19: 净值 | B19: =B9-B18 -> 0 | D19: =D9-D18 -> 0 | E19: =SUM(F19:R19) -> 0 | F19: =F9-F18 -> 0 | G19: =G9-G18 -> 0 | H19: =H9-H18 -> 0 | I19: =I9-I18 -> 0 | J19: =J9-J18 -> 0 | K19: =K9-K18 -> 0 | L19: =L9-L18 -> 0 | M19: =M9-M18 -> 0 | ... R19: =R9-R18 -> 0
A20: 试算表链接： | B20: 0 | E20: =SUM(F20:R20) -> 0 | F20: 0
A21: 差异 | B21: =B19-B20 -> 0 | E21: =E19-E20 -> 0 | F21: =F19-F20 -> 0 | G21: =G19-G20 -> 0 | H21: =H19-H20 -> 0 | I21: =I19-I20 -> 0 | J21: =J19-J20 -> 0 | K21: =K19-K20 -> 0 | L21: =L19-L20 -> 0 | ... R21: =R19-R20 -> 0
A22: 三、按账龄组合计提坏账（原值）
A23: 项目 | B23: 审定数 | C23: 各项占比 | D23: 抵消数 | E23: 汇总 | F23: 母公司审定 | G23: 子公司1 | H23: 子公司2 | I23: 子公司3 | J23: 子公司4 | K23: 子公司5 | L23: 子公司6 | M23: 子公司7 | N23: 子公司8 | O23: 子公司9 | P23: 子公司10 | Q23: 子公司11 | R23: 子公司12
A24: 1年以内 | B24: =E24-D24 -> 0 | C24: =IF(ISERROR(B24/$B$30),"",B24/$B$30) | E24: =SUM(F24:R24) -> 0 | F24: 0
A25: 1-2年 | B25: =E25-D25 -> 0 | C25: =IF(ISERROR(B25/$B$30),"",B25/$B$30) | E25: =SUM(F25:R25) -> 0 | F25: 0
A26: 2-3年 | B26: =E26-D26 -> 0 | C26: =IF(ISERROR(B26/$B$30),"",B26/$B$30) | E26: =SUM(F26:R26) -> 0 | F26: 0
A27: 3-4年 | B27: =E27-D27 -> 0 | C27: =IF(ISERROR(B27/$B$30),"",B27/$B$30) | E27: =SUM(F27:R27) -> 0 | F27: 0
A28: 4-5年 | B28: =E28-D28 -> 0 | C28: =IF(ISERROR(B28/$B$30),"",B28/$B$30) | E28: =SUM(F28:R28) -> 0 | F28: 0
A29: 5年以上 | B29: =E29-D29 -> 0 | C29: =IF(ISERROR(B29/$B$30),"",B29/$B$30) | E29: =SUM(F29:R29) -> 0 | F29: 0
A30: 合计 | B30: =SUM(B24:B29) -> 0 | C30: =SUM(C24:C29) -> 0 | D30: =SUM(D24:D29) -> 0 | E30: =SUM(F30:R30) -> 0 | F30: =SUM(F24:F29) -> 0 | G30: =SUM(G24:G29) -> 0 | H30: =SUM(H24:H29) -> 0 | I30: =SUM(I24:I29) -> 0 | J30: =SUM(J24:J29) -> 0 | K30: =SUM(K24:K29) -> 0 | L30: =SUM(L24:L29) -> 0 | M30: =SUM(M24:M29) -> 0 | ... R30: =SUM(R24:R29) -> 0
A31: 差异 | B31: =B5-B30 -> 0 | E31: =E5-E30 -> 0 | F31: =F5-F30 -> 0 | G31: =G5-G30 -> 0 | H31: =H5-H30 -> 0 | I31: =I5-I30 -> 0 | J31: =J5-J30 -> 0 | K31: =K5-K30 -> 0 | L31: =L5-L30 -> 0 | ... R31: =R5-R30 -> 0
A33: 四、按账龄组合计提坏账（坏账准备）
A34: 项目 | B34: 审定数 | C34: 计提比例 | D34: 抵消数 | E34: 汇总 | F34: 母公司审定 | G34: 子公司1 | H34: 子公司2 | I34: 子公司3 | J34: 子公司4 | K34: 子公司5 | L34: 子公司6 | M34: 子公司7 | N34: 子公司8 | O34: 子公司9 | P34: 子公司10 | Q34: 子公司11 | R34: 子公司12
A35: 1年以内 | B35: =E35-D35 -> 0 | C35: =IF(ISERROR(B35/B24),"",B35/B24%) | E35: =SUM(F35:R35) -> 0 | F35: 0
A36: 1-2年 | B36: =E36-D36 -> 0 | C36: =IF(ISERROR(B36/B25),"",B36/B25%) | E36: =SUM(F36:R36) -> 0 | F36: 0
A37: 2-3年 | B37: =E37-D37 -> 0 | C37: =IF(ISERROR(B37/B26),"",B37/B26%) | E37: =SUM(F37:R37) -> 0 | F37: 0
A38: 3-4年 | B38: =E38-D38 -> 0 | C38: =IF(ISERROR(B38/B27),"",B38/B27%) | E38: =SUM(F38:R38) -> 0 | F38: 0
A39: 4-5年 | B39: =E39-D39 -> 0 | C39: =IF(ISERROR(B39/B28),"",B39/B28%) | E39: =SUM(F39:R39) -> 0 | F39: 0
A40: 5年以上 | B40: =E40-D40 -> 0 | C40: =IF(ISERROR(B40/B29),"",B40/B29%) | E40: =SUM(F40:R40) -> 0 | F40: 0
A41: 合计 | B41: =SUM(B35:B40) -> 0 | C41: =IF(ISERROR(B41/B30),"",B41/B30%) | D41: =SUM(D35:D40) -> 0 | E41: =SUM(F41:R41) -> 0 | F41: =SUM(F35:F40) -> 0 | G41: =SUM(G35:G40) -> 0 | H41: =SUM(H35:H40) -> 0 | I41: =SUM(I35:I40) -> 0 | J41: =SUM(J35:J40) -> 0 | K41: =SUM(K35:K40) -> 0 | L41: =SUM(L35:L40) -> 0 | M41: =SUM(M35:M40) -> 0 | ... R41: =SUM(R35:R40) -> 0
A42: 差异 | B42: =B41-B14 -> 0 | E42: =E41-E14 -> 0 | F42: =F41-F14 -> 0 | G42: =G41-G14 -> 0 | H42: =H41-H14 -> 0 | I42: =I41-I14 -> 0 | J42: =J41-J14 -> 0 | K42: =K41-K14 -> 0 | L42: =L41-L14 -> 0 | ... R42: =R41-R14 -> 0
A44: 五、单项重大单项计提坏账准备披露
A45: 债权单位 | B45: 债务单位 | C45: 账面余额 | D45: 坏账准备 | E45: 计提比例% | F45: 计提理由
E46: =D46/C46 -> #DIV/0!
E47: =D47/C47 -> #DIV/0!
E48: =D48/C48 -> #DIV/0!
E49: =D49/C49 -> #DIV/0!
E50: =D50/C50 -> #DIV/0!
E51: =D51/C51 -> #DIV/0!
E52: =D52/C52 -> #DIV/0!
E53: =D53/C53 -> #DIV/0!
E54: =D54/C54 -> #DIV/0!
E55: =D55/C55 -> #DIV/0!
A56: 合 计 | C56: =SUM(C46:C55) -> 0 | D56: =SUM(D46:D55) -> 0 | E56: =D56/C56 -> #DIV/0!
A57: 差异 | C57: =C56-B4 -> 0 | D57: =D56-B13 -> 0
A59: 七、组合中，采用余额百分比法计提坏账准备的应收账款：（不适用的删除）
A60: 债权单位 | B60: 组合名称 | C60: 账面余额 | D60: 坏账准备 | E60: 计提比例%
B61: 组合1（注明具体组合名称） | E61: =D61/C61 -> #DIV/0!
B62: 组合2（注明具体组合名称） | E62: =D62/C62 -> #DIV/0!
B63: …… | E63: =D63/C63 -> #DIV/0!
E64: =D64/C64 -> #DIV/0!
E65: =D65/C65 -> #DIV/0!
E66: =D66/C66 -> #DIV/0!
A67: 合 计 | C67: =SUM(C61:C66) -> 0 | D67: =SUM(D61:D66) -> 0 | E67: =D67/C67 -> #DIV/0!
A69: 八、组合中，采用其他方法计提坏账准备的应收账款：（不适用的删除）
A70: 债权单位 | B70: 组合名称 | C70: 账面余额 | D70: 坏账准备 | E70: 计提比例%
B71: 组合1（注明具体组合名称） | E71: =D71/C71 -> #DIV/0!
B72: 组合2（注明具体组合名称） | E72: =D72/C72 -> #DIV/0!
B73: …… | E73: =D73/C73 -> #DIV/0!
E74: =D74/C74 -> #DIV/0!
E75: =D75/C75 -> #DIV/0!
E76: =D76/C76 -> #DIV/0!
A77: 合 计 | C77: =SUM(C71:C76) -> 0 | D77: =SUM(D71:D76) -> 0 | E77: =D77/C77 -> #DIV/0!
A79: 九、按欠款方归集的应收账款期末余额前五名单位情况
A80: 债权单位 | B80: 单位名称 | C80: 与本公司关系 | D80: 金额 | E80: 年限 | F80: 占应收账款总额比例
F81: =D81/$B$9% -> #DIV/0!
F82: =D82/$B$9% -> #DIV/0!
F83: =D83/$B$9% -> #DIV/0!
F84: =D84/$B$9% -> #DIV/0!
F85: =D85/$B$9% -> #DIV/0!
A86: 合 计 | C86: -- | D86: =SUM(D81:D85) -> 0 | E86: -- | F86: =SUM(F81:F85) -> #DIV/0!
A88: 十、本期计提、收回或转回的坏账准备情况
A89: 本期计提坏账准备金额XX元；本期收回或转回坏账准备金额XX元。
A90: 其中，本期坏账准备转回或收回金额重要的：
A91: 债权人单位 | B91: 单位名称 | C91: 转回原因 | D91: 收回方式 | E91: 原确定坏账准备的依据 | F91: 转回或收回金额
A98: 可无限量添加行
A99: 合 计 | F99: =SUM(F92:F98) -> 0
A100: 【15号文第十九条（五）2，本期坏账准备收回或转回金额重要的，应披露转回原因、收回方式、确定原坏账准备计提比例的依据及其合理性；】
A101: 十一、本期实际核销的应收账款情况
A102: 项目 | B102: 审定数 | C102: 抵消数 | D102: 汇总 | E102: 母公司审定 | F102: 子公司1 | G102: 子公司2 | H102: 子公司3 | I102: 子公司4 | J102: 子公司5 | K102: 子公司6 | L102: 子公司7 | M102: 子公司8 | N102: 子公司9 | O102: 子公司10 | P102: 子公司11 | Q102: 子公司12
A103: 实际核销的应收账款 | B103: =D103-C103 -> 0 | D103: =SUM(E103:Q103) -> 0 | E103: 0
A105: 其中，重要的应收账款核销情况（逐项披露）：
A106: 债权人单位 | B106: 单位名称 | C106: 应收账款性质 | D106: 核销金额 | E106: 核销原因 | F106: 履行的核销程序 | G106: 是否由关联交易产成
A110: 合 计 | D110: =SUM(D107:D109) -> 0
A111: 【15号文第十九条（五）3，对于其中重要的应收款项，应逐项披露款项性质、核销原因、履行的核销程序及核销金额。实际核销的款项由关联交易产生的，应单独披露；】
A113: 十二、因金融资产转移而终止确认的应收账款情况
A114: 【15号文第十九条（五）6，因金融资产转移而终止确认的应收款项，应列示金融资产转移的方式、终止确认的应收款项金额，及与终止确认相关的利得或损失；】
A115: 债权人单位 | B115: 单位名称 | C115: 转移方式 | D115: 终止确认金额 | E115: 与终止确认相关的利得或损失
A119: 合 计 | D119: =SUM(D116:D118) -> 0 | E119: --
A120: 说明：
A121: ①期末，本集团因办理了不附追索权的应收账款保理，保理金额为XXX元，同时终止确认应收账款账面价值为XXX元，账面余额为XXX元，账龄为一年以内，已计提坏账准备XXX元。
...

Sheet 预付款项
A1: 预付款项附注 | E1: 返回Excel目录 | F1: 返回word附注
A2: 项目 | B2: 审定数 | C2: 各项占比 | D2: 抵消数 | E2: 汇总 | F2: 母公司审定 | G2: 子公司1 | H2: 子公司2 | I2: 子公司3 | J2: 子公司4 | K2: 子公司5 | L2: 子公司6 | M2: 子公司7 | N2: 子公司8 | O2: 子公司9 | P2: 子公司10 | Q2: 子公司11 | R2: 子公司12
A3: 1年以内 | B3: =E3-D3 -> 0 | C3: =B3/$B$7 -> #DIV/0! | E3: =SUM(F3:R3) -> 0 | F3: 0
A4: 1-2年 | B4: =E4-D4 -> 0 | C4: =B4/$B$7 -> #DIV/0! | E4: =SUM(F4:R4) -> 0 | F4: 0
A5: 2-3年 | B5: =E5-D5 -> 0 | C5: =B5/$B$7 -> #DIV/0! | E5: =SUM(F5:R5) -> 0 | F5: 0
A6: 3年以上 | B6: =E6-D6 -> 0 | C6: =B6/$B$7 -> #DIV/0! | E6: =SUM(F6:R6) -> 0 | F6: 0
A7: 合计 | B7: =SUM(B3:B6) -> 0 | C7: =B7/$B$7 -> #DIV/0! | D7: =SUM(D3:D6) -> 0 | E7: =SUM(F7:R7) -> 0 | F7: =SUM(F3:F6) -> 0 | G7: =SUM(G3:G6) -> 0 | H7: =SUM(H3:H6) -> 0 | I7: =SUM(I3:I6) -> 0 | J7: =SUM(J3:J6) -> 0 | K7: =SUM(K3:K6) -> 0 | L7: =SUM(L3:L6) -> 0 | M7: =SUM(M3:M6) -> 0 | ... R7: =SUM(R3:R6) -> 0
A8: 试算表链接： | B8: 0 | E8: =SUM(F8:R8) -> 0 | F8: 0
A9: 差异 | B9: =B7-B8 -> 0 | E9: =E7-E8 -> 0 | F9: =F7-F8 -> 0 | G9: =G7-G8 -> 0 | H9: =H7-H8 -> 0 | I9: =I7-I8 -> 0 | J9: =J7-J8 -> 0 | K9: =K7-K8 -> 0 | L9: =L7-L8 -> 0 | ... R9: =R7-R8 -> 0
A11: 说明：（账龄超过1年的金额重要预付账款，应说明未及时结算的原因。）
A14: 2、预付款项金额前五名单位情况
A15: （按预付对象集中度，汇总或分别披露期末余额前五名的预付款项的期末余额及占预付款项期末余额合计数的比例。）
A16: 汇总披露格式：
A17: 本期按预付对象归集的期末余额前五名预付款项汇总金额XXXX元，占预付款项期末余额合计数的比例 %。
A18: 分别披露格式：
A20: 债权人名称 | B20: 单位名称 | C20: 预付款项期末余额 | D20: 占预付款项期末余额合计数的比例%
D21: =C21/$B$7% -> #DIV/0!
D22: =C22/$B$7% -> #DIV/0!
D23: =C23/$B$7% -> #DIV/0!
D24: =C24/$B$7% -> #DIV/0!
D25: =C25/$B$7% -> #DIV/0!
A26: 合 计 | C26: =SUM(C21:C25) -> 0 | D26: =SUM(D21:D25) -> #DIV/0!

Sheet 应收利息、应收股利、其他应收款
A1: 其他应收款汇总附注 | D1: 返回Excel目录 | E1: 返回word附注
A2: 项目 | B2: 审定数 | C2: 抵消数 | D2: 汇总 | E2: 母公司审定 | F2: 子公司1 | G2: 子公司2 | H2: 子公司3 | I2: 子公司4 | J2: 子公司5 | K2: 子公司6 | L2: 子公司7 | M2: 子公司8 | N2: 子公司9 | O2: 子公司10 | P2: 子公司11 | Q2: 子公司12
A3: 应收利息 | B3: =D3-C3 -> 0 | D3: =SUM(E3:Q3) -> 0 | E3: =应收利息!E7 -> 0 | F3: =应收利息!F7 -> 0 | G3: =应收利息!G7 -> 0 | H3: =应收利息!H7 -> 0 | I3: =应收利息!I7 -> 0 | J3: =应收利息!J7 -> 0 | K3: =应收利息!K7 -> 0 | L3: =应收利息!L7 -> 0 | ... Q3: =应收利息!Q7 -> 0
A4: 应收股利 | B4: =D4-C4 -> 0 | D4: =SUM(E4:Q4) -> 0 | E4: =应收股利!E10 -> 0 | F4: =应收股利!F10 -> 0 | G4: =应收股利!G10 -> 0 | H4: =应收股利!H10 -> 0 | I4: =应收股利!I10 -> 0 | J4: =应收股利!J10 -> 0 | K4: =应收股利!K10 -> 0 | L4: =应收股利!L10 -> 0 | ... Q4: =应收股利!Q10 -> 0
A5: 其他应收款 | B5: =D5-C5 -> 0 | D5: =SUM(E5:Q5) -> 0 | E5: =其他应收款!F19 -> 0 | F5: =其他应收款!G19 -> 0 | G5: =其他应收款!H19 -> 0 | H5: =其他应收款!I19 -> 0 | I5: =其他应收款!J19 -> 0 | J5: =其他应收款!K19 -> 0 | K5: =其他应收款!L19 -> 0 | L5: =其他应收款!M19 -> 0 | ... Q5: =其他应收款!R19 -> 0
A6: 合 计 | B6: =SUM(B3:B5) -> 0 | C6: =SUM(C3:C5) -> 0 | D6: =SUM(D3:D5) -> 0 | E6: =SUM(E3:E5) -> 0 | F6: =SUM(F3:F5) -> 0 | G6: =SUM(G3:G5) -> 0 | H6: =SUM(H3:H5) -> 0 | I6: =SUM(I3:I5) -> 0 | ... Q6: =SUM(Q3:Q5) -> 0

Sheet 应收利息
A1: 应收利息附注 | D1: 返回Excel目录 | E1: 返回word附注
A2: 项目 | B2: 审定数 | C2: 抵消数 | D2: 汇总 | E2: 母公司审定 | F2: 子公司1 | G2: 子公司2 | H2: 子公司3 | I2: 子公司4 | J2: 子公司5 | K2: 子公司6 | L2: 子公司7 | M2: 子公司8 | N2: 子公司9 | O2: 子公司10 | P2: 子公司11 | Q2: 子公司12
A3: 定期存款 | B3: =D3-C3 -> 0 | D3: =SUM(E3:Q3) -> 0 | E3: 0
A4: 委托贷款 | B4: =D4-C4 -> 0 | D4: =SUM(E4:Q4) -> 0 | E4: 0
A5: 债券投资 | B5: =D5-C5 -> 0 | D5: =SUM(E5:Q5) -> 0 | E5: 0
A6: 可无限量添加行 | B6: =D6-C6 -> 0 | D6: =SUM(E6:Q6) -> 0 | E6: 0
A7: 合 计 | B7: =SUM(B3:B6) -> 0 | C7: =SUM(C3:C6) -> 0 | D7: =SUM(E7:Q7) -> 0 | E7: =SUM(E3:E6) -> 0 | F7: =SUM(F3:F6) -> 0 | G7: =SUM(G3:G6) -> 0 | H7: =SUM(H3:H6) -> 0 | I7: =SUM(I3:I6) -> 0 | J7: =SUM(J3:J6) -> 0 | K7: =SUM(K3:K6) -> 0 | L7: =SUM(L3:L6) -> 0 | ... Q7: =SUM(Q3:Q6) -> 0
A8: 试算表链接： | B8: 0 | D8: =SUM(E8:Q8) -> 0 | E8: 0
A9: 差异 | B9: =B7-B8 -> 0 | D9: =D7-D8 -> 0 | E9: =E7-E8 -> 0 | F9: =F7-F8 -> 0 | G9: =G7-G8 -> 0 | H9: =H7-H8 -> 0 | I9: =I7-I8 -> 0 | J9: =J7-J8 -> 0 | K9: =K7-K8 -> 0 | ... Q9: =Q7-Q8 -> 0
A11: 其中，重要的逾期应收利息如下：
A12: 债权单位 | B12: 借款单位 | C12: 期末数 | D12: 逾期时间 | E12: 逾期原因 | F12: 是否发生减值及其原因
A21: 合 计 | C21: =SUM(C13:C20) -> 0
A22: （对于重要的逾期应收利息，应按借款单位披露应收利息的期末余额、逾期时间和逾期原因、是否发生减值的判断。）
A23: 其他说明：

Sheet 应收股利
A1: 应收股利附注 | D1: 返回Excel目录 | E1: 返回word附注
A2: 项目 | B2: 审定数 | C2: 抵消数 | D2: 汇总 | E2: 母公司审定 | F2: 子公司1 | G2: 子公司2 | H2: 子公司3 | I2: 子公司4 | J2: 子公司5 | K2: 子公司6 | L2: 子公司7 | M2: 子公司8 | N2: 子公司9 | O2: 子公司10 | P2: 子公司11 | Q2: 子公司12
B3: =D3-C3 -> 0 | D3: =SUM(E3:Q3) -> 0 | E3: 0
B4: =D4-C4 -> 0 | D4: =SUM(E4:Q4) -> 0 | E4: 0
B5: =D5-C5 -> 0 | D5: =SUM(E5:Q5) -> 0 | E5: 0
B6: =D6-C6 -> 0 | D6: =SUM(E6:Q6) -> 0 | E6: 0
B7: =D7-C7 -> 0 | D7: =SUM(E7:Q7) -> 0 | E7: 0
B8: =D8-C8 -> 0 | D8: =SUM(E8:Q8) -> 0 | E8: 0
B9: =D9-C9 -> 0 | D9: =SUM(E9:Q9) -> 0 | E9: 0
A10: 合 计 | B10: =SUM(B3:B9) -> 0 | C10: =SUM(C3:C9) -> 0 | D10: =SUM(D3:D9) -> 0 | E10: =SUM(E3:E9) -> 0 | F10: =SUM(F3:F9) -> 0 | G10: =SUM(G3:G9) -> 0 | H10: =SUM(H3:H9) -> 0 | I10: =SUM(I3:I9) -> 0 | ... Q10: =SUM(Q3:Q9) -> 0
A11: 试算表链接： | B11: 0 | D11: =SUM(E11:Q11) -> 0 | E11: 0
A12: 差异 | B12: =B10-B11 -> 0 | D12: =D10-D11 -> 0 | E12: =E10-E11 -> 0 | F12: =F10-F11 -> 0 | G12: =G10-G11 -> 0 | H12: =H10-H11 -> 0 | I12: =I10-I11 -> 0 | J12: =J10-J11 -> 0 | K12: =K10-K11 -> 0 | ... Q12: =Q10-Q11 -> 0
A13: 其中，重要的账龄超过1年的应收股利如下：
A14: 投资单位名称 | B14: 被投资单位 | C14: 期末数 | D14: 账龄 | E14: 未收回的原因 | F14: 是否发生减值及其判断依据
A24: 合 计 | C24: =SUM(C15:C23) -> 0
A25: （对于重要的账龄超过1 年的应收股利，应披露未收回的原因和对相关款项是否发生减值的判断。）
A26: 其他说明：

Sheet 其他应收款
A1: 其他应收款附注汇总 | D1: 返回Excel目录 | E1: 返回word附注
A2: 一、单项金额分类（原值）（按照股份公司标准，300万元）
A3: 项目 | B3: 审定数 | C3: 计提比例 | D3: 抵消数 | E3: 汇总 | F3: 母公司审定 | G3: 子公司1 | H3: 子公司2 | I3: 子公司3 | J3: 子公司4 | K3: 子公司5 | L3: 子公司6 | M3: 子公司7 | N3: 子公司8 | O3: 子公司9 | P3: 子公司10 | Q3: 子公司11 | R3: 子公司12
A4: 单项金额重大单项计提 | B4: =E4-D4 -> 0 | C4: =IF(ISERROR(B4/$B$9),"",B4/$B$9%) | E4: =SUM(F4:R4) -> 0 | F4: 0
A5: 按组合计提坏账 | B5: =E5-D5 -> 0 | C5: =IF(ISERROR(B5/$B$9),"",B5/$B$9%) | E5: =SUM(F5:R5) -> 0 | F5: 0
A6: 组合1 | B6: =E6-D6 -> 0 | C6: =IF(ISERROR(B6/$B$9),"",B6/$B$9%) | E6: =SUM(F6:R6) -> 0 | F6: 0
A7: 组合2 | B7: =E7-D7 -> 0 | C7: =IF(ISERROR(B7/$B$9),"",B7/$B$9%) | E7: =SUM(F7:R7) -> 0 | F7: 0
A8: 单项不重大单项计提坏账 | B8: =E8-D8 -> 0 | C8: =IF(ISERROR(B8/$B$9),"",B8/$B$9%) | E8: =SUM(F8:R8) -> 0 | F8: 0
A9: 合计 | B9: =SUM(B4:B8) -> 0 | C9: =SUM(C4:C8) -> 0 | D9: =SUM(D4:D8) -> 0 | E9: =SUM(F9:R9) -> 0 | F9: =SUM(F4:F8) -> 0 | G9: =SUM(G4:G8) -> 0 | H9: =SUM(H4:H8) -> 0 | I9: =SUM(I4:I8) -> 0 | J9: =SUM(J4:J8) -> 0 | K9: =SUM(K4:K8) -> 0 | L9: =SUM(L4:L8) -> 0 | M9: =SUM(M4:M8) -> 0 | ... R9: =SUM(R4:R8) -> 0
A11: 二、单项金额分类（坏账准备）
A12: 项目 | B12: 审定数 | C12: 计提比例 | D12: 抵消数 | E12: 汇总 | F12: 母公司审定 | G12: 子公司1 | H12: 子公司2 | I12: 子公司3 | J12: 子公司4 | K12: 子公司5 | L12: 子公司6 | M12: 子公司7 | N12: 子公司8 | O12: 子公司9 | P12: 子公司10 | Q12: 子公司11 | R12: 子公司12
A13: 单项金额重大单项计提 | B13: =E13-D13 -> 0 | C13: =IF(ISERROR(B13/$B$18),"",B13/$B$18%) | E13: =SUM(F13:R13) -> 0 | F13: 0
A14: 按组合计提坏账 | B14: =E14-D14 -> 0 | C14: =IF(ISERROR(B14/$B$18),"",B14/$B$18%) | E14: =SUM(F14:R14) -> 0 | F14: 0
A15: 组合1 | B15: =E15-D15 -> 0 | C15: =IF(ISERROR(B15/$B$18),"",B15/$B$18%) | E15: =SUM(F15:R15) -> 0 | F15: 0
A16: 组合2 | B16: =E16-D16 -> 0 | C16: =IF(ISERROR(B16/$B$18),"",B16/$B$18%) | E16: =SUM(F16:R16) -> 0 | F16: 0
A17: 单项不重大单项计提坏账 | B17: =E17-D17 -> 0 | C17: =IF(ISERROR(B17/$B$18),"",B17/$B$18%) | E17: =SUM(F17:R17) -> 0 | F17: 0
A18: 合计 | B18: =SUM(B13:B17) -> 0 | C18: =SUM(C13:C17) -> 0 | D18: =SUM(D13:D17) -> 0 | E18: =SUM(F18:R18) -> 0 | F18: =SUM(F13:F17) -> 0 | G18: =SUM(G13:G17) -> 0 | H18: =SUM(H13:H17) -> 0 | I18: =SUM(I13:I17) -> 0 | J18: =SUM(J13:J17) -> 0 | K18: =SUM(K13:K17) -> 0 | L18: =SUM(L13:L17) -> 0 | M18: =SUM(M13:M17) -> 0 | ... R18: =SUM(R13:R17) -> 0
A19: 净值 | B19: =B9-B18 -> 0 | D19: =D9-D18 -> 0 | E19: =E9-E18 -> 0 | F19: =F9-F18 -> 0 | G19: =G9-G18 -> 0 | H19: =H9-H18 -> 0 | I19: =I9-I18 -> 0 | J19: =J9-J18 -> 0 | K19: =K9-K18 -> 0 | ... R19: =R9-R18 -> 0
A20: 试算表链接： | B20: 0 | E20: =SUM(F20:R20) -> 0 | F20: 0
A21: 差异 | B21: =B19-B20 -> 0 | D21: =D19-D20 -> 0 | E21: =E19-E20 -> 0 | F21: =F19-F20 -> 0 | G21: =G19-G20 -> 0 | H21: =H19-H20 -> 0 | I21: =I19-I20 -> 0 | J21: =J19-J20 -> 0 | K21: =K19-K20 -> 0 | ... R21: =R19-R20 -> 0
A23: 三、按账龄组合分类
A24: 项目 | B24: 审定数 | C24: 各项占比 | D24: 抵消数 | E24: 汇总 | F24: 母公司审定 | G24: 子公司1 | H24: 子公司2 | I24: 子公司3 | J24: 子公司4 | K24: 子公司5 | L24: 子公司6 | M24: 子公司7 | N24: 子公司8 | O24: 子公司9 | P24: 子公司10 | Q24: 子公司11 | R24: 子公司12
A25: 1年以内 | B25: =E25-D25 -> 0 | C25: =IF(ISERROR(B25/$B$31),"",B25/$B$31%) | E25: =SUM(F25:R25) -> 0 | F25: 0
A26: 1-2年 | B26: =E26-D26 -> 0 | C26: =IF(ISERROR(B26/$B$31),"",B26/$B$31%) | E26: =SUM(F26:R26) -> 0 | F26: 0
A27: 2-3年 | B27: =E27-D27 -> 0 | C27: =IF(ISERROR(B27/$B$31),"",B27/$B$31%) | E27: =SUM(F27:R27) -> 0 | F27: 0
A28: 3-4年 | B28: =E28-D28 -> 0 | C28: =IF(ISERROR(B28/$B$31),"",B28/$B$31%) | E28: =SUM(F28:R28) -> 0 | F28: 0
A29: 4-5年 | B29: =E29-D29 -> 0 | C29: =IF(ISERROR(B29/$B$31),"",B29/$B$31%) | E29: =SUM(F29:R29) -> 0 | F29: 0
A30: 5年以上 | B30: =E30-D30 -> 0 | C30: =IF(ISERROR(B30/$B$31),"",B30/$B$31%) | E30: =SUM(F30:R30) -> 0 | F30: 0
A31: 合计 | B31: =SUM(B25:B30) -> 0 | C31: =SUM(C25:C30) -> 0 | D31: =SUM(D25:D30) -> 0 | E31: =SUM(F31:R31) -> 0 | F31: =SUM(F25:F30) -> 0 | G31: =SUM(G25:G30) -> 0 | H31: =SUM(H25:H30) -> 0 | I31: =SUM(I25:I30) -> 0 | J31: =SUM(J25:J30) -> 0 | K31: =SUM(K25:K30) -> 0 | L31: =SUM(L25:L30) -> 0 | M31: =SUM(M25:M30) -> 0 | ... R31: =SUM(R25:R30) -> 0
A32: 差异 | B32: =B5-B31 -> 0 | D32: =D5-D31 -> 0 | E32: =E5-E31 -> 0 | F32: =F5-F31 -> 0 | G32: =G5-G31 -> 0 | H32: =H5-H31 -> 0 | I32: =I5-I31 -> 0 | J32: =J5-J31 -> 0 | K32: =K5-K31 -> 0 | ... R32: =R5-R31 -> 0
A34: 四、按账龄组合分类（坏账准备）
A35: 项目 | B35: 审定数 | C35: 计提比例 | D35: 抵消数 | E35: 汇总 | F35: 母公司审定 | G35: 子公司1 | H35: 子公司2 | I35: 子公司3 | J35: 子公司4 | K35: 子公司5 | L35: 子公司6 | M35: 子公司7 | N35: 子公司8 | O35: 子公司9 | P35: 子公司10 | Q35: 子公司11 | R35: 子公司12
A36: 1年以内 | B36: =E36-D36 -> 0 | C36: =IF(ISERROR(B36/B25),"",B36/B25%) | E36: =SUM(F36:R36) -> 0 | F36: 0
A37: 1-2年 | B37: =E37-D37 -> 0 | C37: =IF(ISERROR(B37/B26),"",B37/B26%) | E37: =SUM(F37:R37) -> 0 | F37: 0
A38: 2-3年 | B38: =E38-D38 -> 0 | C38: =IF(ISERROR(B38/B27),"",B38/B27%) | E38: =SUM(F38:R38) -> 0 | F38: 0
A39: 3-4年 | B39: =E39-D39 -> 0 | C39: =IF(ISERROR(B39/B28),"",B39/B28%) | E39: =SUM(F39:R39) -> 0 | F39: 0
A40: 4-5年 | B40: =E40-D40 -> 0 | C40: =IF(ISERROR(B40/B29),"",B40/B29%) | E40: =SUM(F40:R40) -> 0 | F40: 0
A41: 5年以上 | B41: =E41-D41 -> 0 | C41: =IF(ISERROR(B41/B30),"",B41/B30%) | E41: =SUM(F41:R41) -> 0 | F41: 0
A42: 合计 | B42: =SUM(B36:B41) -> 0 | C42: =IF(ISERROR(B42/B31),"",B42/B31%) | D42: =SUM(D36:D41) -> 0 | E42: =SUM(F42:R42) -> 0 | F42: =SUM(F36:F41) -> 0 | G42: =SUM(G36:G41) -> 0 | H42: =SUM(H36:H41) -> 0 | I42: =SUM(I36:I41) -> 0 | J42: =SUM(J36:J41) -> 0 | K42: =SUM(K36:K41) -> 0 | L42: =SUM(L36:L41) -> 0 | M42: =SUM(M36:M41) -> 0 | ... R42: =SUM(R36:R41) -> 0
A43: 差异 | B43: =B42-B14 -> 0 | D43: =D42-D14 -> 0 | E43: =E42-E14 -> 0 | F43: =F42-F14 -> 0 | G43: =G42-G14 -> 0 | H43: =H42-H14 -> 0 | I43: =I42-I14 -> 0 | J43: =J42-J14 -> 0 | K43: =K42-K14 -> 0 | ... R43: =R42-R14 -> 0
A45: 五、期末单项金额重大并单项计提坏账准备的其他应收款
A46: 债权单位 | B46: 债务单位 | C46: 账面余额 | D46: 坏账准备 | E46: 计提比例% | F46: 计提理由
E47: =D47/C47 -> #DIV/0!
E48: =D48/C48 -> #DIV/0!
E49: =D49/C49 -> #DIV/0!
E50: =D50/C50 -> #DIV/0!
E51: =D51/C51 -> #DIV/0!
E52: =D52/C52 -> #DIV/0!
E53: =D53/C53 -> #DIV/0!
A54: 合 计 | C54: =SUM(C47:C53) -> 0 | D54: =SUM(D47:D53) -> 0 | E54: -- | F54: --
A55: 差异 | C55: =C54-B4 -> 0 | D55: =D54-B13 -> 0
A56: 六、组合中，采用余额百分比法计提坏账准备的应收账款：（不适用的删除）
A57: 债权单位 | B57: 组合名称 | C57: 账面余额 | D57: 坏账准备 | E57: 计提比例%
B58: 组合1（注明具体组合名称） | E58: =D58/C58 -> #DIV/0!
B59: 组合2（注明具体组合名称） | E59: =D59/C59 -> #DIV/0!
B60: …… | E60: =D60/C60 -> #DIV/0!
E61: =D61/C61 -> #DIV/0!
E62: =D62/C62 -> #DIV/0!
E63: =D63/C63 -> #DIV/0!
A64: 合 计 | C64: =SUM(C58:C63) -> 0 | D64: =SUM(D58:D63) -> 0 | E64: =D64/C64 -> #DIV/0!
A66: 七、组合中，采用其他方法计提坏账准备的应收账款：（不适用的删除）
A67: 债权单位 | B67: 组合名称 | C67: 账面余额 | D67: 坏账准备 | E67: 计提比例%
B68: 组合1（注明具体组合名称） | E68: =D68/C68 -> #DIV/0!
B69: 组合2（注明具体组合名称） | E69: =D69/C69 -> #DIV/0!
B70: …… | E70: =D70/C70 -> #DIV/0!
E71: =D71/C71 -> #DIV/0!
E72: =D72/C72 -> #DIV/0!
E73: =D73/C73 -> #DIV/0!
A74: 合 计 | C74: =SUM(C68:C73) -> 0 | D74: =SUM(D68:D73) -> 0 | E74: =D74/C74 -> #DIV/0!
A76: 八、本期计提、收回或转回的坏账准备情况
A77: 本期计提坏账准备金额XX元；本期收回或转回坏账准备金额XX元。
A78: 其中，本期坏账准备转回或收回金额重要的：
A79: 债权单位名称 | B79: 债务人名称 | C79: 转回原因 | D79: 收回方式 | E79: 原确定坏账准备的依据 | F79: 转回或收回金额
A86: 合 计 | F86: =SUM(F80:F85) -> 0
A87: 注：本期坏账准备收回或转回金额重要的，应披露转回原因、收回方式、确定原坏账准备计提比例的依据及其合理性；
A89: 九、本期实际核销的应收账款情况
A90: 项目 | B90: 审定数 | C90: 抵消数 | D90: 汇总 | E90: 母公司审定 | F90: 子公司1 | G90: 子公司2 | H90: 子公司3 | I90: 子公司4 | J90: 子公司5 | K90: 子公司6 | L90: 子公司7 | M90: 子公司8 | N90: 子公司9 | O90: 子公司10 | P90: 子公司11 | Q90: 子公司12
A91: 实际核销的应收账款 | B91: =D91-C91 -> 0 | D91: =SUM(E91:Q91) -> 0 | E91: 0
A93: 其中，重要的应收账款核销情况（逐项披露）：
A94: 债权人单位 | B94: 单位名称 | C94: 应收账款性质 | D94: 核销金额 | E94: 核销原因 | F94: 履行的核销程序 | G94: 是否由关联交易产成
A98: 合 计 | D98: =SUM(D95:D97) -> 0
A99: （对于其中重要的应收款项，应逐项披露款项性质、核销原因、履行的核销程序及核销金额。实际核销的款项由关联交易产生的，应单独披露；）
A100: 说明：
A101: 十、其他应收款按性质披露
A102: 项目 | B102: 审定数 | C102: 抵消数 | D102: 汇总 | E102: 母公司审定 | F102: 子公司1 | G102: 子公司2 | H102: 子公司3 | I102: 子公司4 | J102: 子公司5 | K102: 子公司6 | L102: 子公司7 | M102: 子公司8 | N102: 子公司9 | O102: 子公司10 | P102: 子公司11 | Q102: 子公司12
A103: 备用金 | D103: =SUM(E103:Q103) -> 0 | E103: 0
A104: 保证金 | D104: =SUM(E104:Q104) -> 0 | E104: 0
A105: 可无限量添加行 | D105: =SUM(E105:Q105) -> 0 | E105: 0
D106: =SUM(E106:Q106) -> 0 | E106: 0
D107: =SUM(E107:Q107) -> 0 | E107: 0
D108: =SUM(E108:Q108) -> 0 | E108: 0
A109: 合计 | B109: =SUM(B103:B108) -> 0 | C109: =SUM(C103:C108) -> 0 | D109: =SUM(E109:Q109) -> 0 | E109: =SUM(E103:E108) -> 0 | F109: =SUM(F103:F108) -> 0 | G109: =SUM(G103:G108) -> 0 | H109: =SUM(H103:H108) -> 0 | I109: =SUM(I103:I108) -> 0 | J109: =SUM(J103:J108) -> 0 | K109: =SUM(K103:K108) -> 0 | L109: =SUM(L103:L108) -> 0 | ... Q109: =SUM(Q103:Q108) -> 0
A110: 试算表链接： | B110: 0 | D110: 0 | E110: =SUM(F110:R110) -> 0
A111: 差异 | B111: =B109-B110 -> 0 | D111: =C109-D110 -> 0 | E111: =D109-E110 -> 0 | F111: =E109-F110 -> 0 | G111: =F109-G110 -> 0 | H111: =G109-H110 -> 0 | I111: =H109-I110 -> 0 | J111: =I109-J110 -> 0 | K111: =J109-K110 -> 0 | ... R111: =Q109-R110 -> 0
A113: 十一、按欠款方归集的其他应收款期末余额前五名单位情况
A114: 债权单位名称 | B114: 债务人名称 | C114: 款项性质 | D114: 其他应收款期末余额 | E114: 账龄 | F114: 占其他应收款期末余额合计数的比例(%) | G114: 坏账准备期末余额
F115: =D115/$B$9 -> #DIV/0!
F116: =D116/$B$9 -> #DIV/0!
F117: =D117/$B$9 -> #DIV/0!
F118: =D118/$B$9 -> #DIV/0!
...

Sheet 存货
A1: 存货附注汇总 | D1: 返回Excel目录 | E1: 返回word附注
A2: 存货账面原值
A3: 1、存货期初数
A4: 项目 | B4: 审定数 | C4: 抵消数 | D4: 汇总 | E4: 母公司审定 | F4: 子公司1 | G4: 子公司2 | H4: 子公司3 | I4: 子公司4 | J4: 子公司5 | K4: 子公司6 | L4: 子公司7 | M4: 子公司8 | N4: 子公司9 | O4: 子公司10 | P4: 子公司11 | Q4: 子公司12
A5: 原材料 | B5: =D5-C5 -> 0 | D5: =SUM(E5:Q5) -> 0 | E5: 0
A6: 自制半成品及在产品（在研品） | B6: =D6-C6 -> 0 | D6: =SUM(E6:Q6) -> 0 | E6: 0
A7: 库存商品（产成品） | B7: =D7-C7 -> 0 | D7: =SUM(E7:Q7) -> 0 | E7: 0
A8: 周转材料（包装物、低值易耗品等） | B8: =D8-C8 -> 0 | D8: =SUM(E8:Q8) -> 0 | E8: 0
A9: 工程施工（工程施工减工程结算） | B9: =D9-C9 -> 0 | D9: =SUM(E9:Q9) -> 0 | E9: 0
A10: 其他(发出商品） | B10: =D10-C10 -> 0 | D10: =SUM(E10:Q10) -> 0 | E10: 0
A11: 合计 | B11: =SUM(B5:B10) -> 0 | C11: =SUM(C5:C10) -> 0 | D11: =SUM(E11:Q11) -> 0 | E11: =SUM(E5:E10) -> 0 | F11: =SUM(F5:F10) -> 0 | G11: =SUM(G5:G10) -> 0 | H11: =SUM(H5:H10) -> 0 | I11: =SUM(I5:I10) -> 0 | J11: =SUM(J5:J10) -> 0 | K11: =SUM(K5:K10) -> 0 | L11: =SUM(L5:L10) -> 0 | ... Q11: =SUM(Q5:Q10) -> 0
A13: 2、本期增加
A14: 项目 | B14: 审定数 | C14: 抵消数 | D14: 汇总 | E14: 母公司审定 | F14: 子公司1 | G14: 子公司2 | H14: 子公司3 | I14: 子公司4 | J14: 子公司5 | K14: 子公司6 | L14: 子公司7 | M14: 子公司8 | N14: 子公司9 | O14: 子公司10 | P14: 子公司11 | Q14: 子公司12
A15: =A5 -> 原材料 | B15: =D15-C15 -> 0 | D15: =SUM(E15:Q15) -> 0 | E15: 0
A16: =A6 -> 自制半成品及在产品（在研品） | B16: =D16-C16 -> 0 | D16: =SUM(E16:Q16) -> 0 | E16: 0
A17: =A7 -> 库存商品（产成品） | B17: =D17-C17 -> 0 | D17: =SUM(E17:Q17) -> 0 | E17: 0
A18: =A8 -> 周转材料（包装物、低值易耗品等） | B18: =D18-C18 -> 0 | D18: =SUM(E18:Q18) -> 0 | E18: 0
A19: =A9 -> 工程施工（工程施工减工程结算） | B19: =D19-C19 -> 0 | D19: =SUM(E19:Q19) -> 0 | E19: 0
A20: =A10 -> 其他(发出商品） | B20: =D20-C20 -> 0 | D20: =SUM(E20:Q20) -> 0 | E20: 0
A21: 合计 | B21: =SUM(B15:B20) -> 0 | C21: =SUM(C15:C20) -> 0 | D21: =SUM(E21:Q21) -> 0 | E21: =SUM(E15:E20) -> 0 | F21: =SUM(F15:F20) -> 0 | G21: =SUM(G15:G20) -> 0 | H21: =SUM(H15:H20) -> 0 | I21: =SUM(I15:I20) -> 0 | J21: =SUM(J15:J20) -> 0 | K21: =SUM(K15:K20) -> 0 | L21: =SUM(L15:L20) -> 0 | ... Q21: =SUM(Q15:Q20) -> 0
A23: 3、本期减少
A24: 项目 | B24: 审定数 | C24: 抵消数 | D24: 汇总 | E24: 母公司审定 | F24: 子公司1 | G24: 子公司2 | H24: 子公司3 | I24: 子公司4 | J24: 子公司5 | K24: 子公司6 | L24: 子公司7 | M24: 子公司8 | N24: 子公司9 | O24: 子公司10 | P24: 子公司11 | Q24: 子公司12
A25: =A15 -> 原材料 | B25: =D25-C25 -> 0 | D25: =SUM(E25:Q25) -> 0 | E25: 0
A26: =A16 -> 自制半成品及在产品（在研品） | B26: =D26-C26 -> 0 | D26: =SUM(E26:Q26) -> 0 | E26: 0
A27: =A17 -> 库存商品（产成品） | B27: =D27-C27 -> 0 | D27: =SUM(E27:Q27) -> 0 | E27: 0
A28: =A18 -> 周转材料（包装物、低值易耗品等） | B28: =D28-C28 -> 0 | D28: =SUM(E28:Q28) -> 0 | E28: 0
A29: =A19 -> 工程施工（工程施工减工程结算） | B29: =D29-C29 -> 0 | D29: =SUM(E29:Q29) -> 0 | E29: 0
A30: =A20 -> 其他(发出商品） | B30: =D30-C30 -> 0 | D30: =SUM(E30:Q30) -> 0 | E30: 0
A31: 合计 | B31: =SUM(B25:B30) -> 0 | C31: =SUM(C25:C30) -> 0 | D31: =SUM(E31:Q31) -> 0 | E31: =SUM(E25:E30) -> 0 | F31: =SUM(F25:F30) -> 0 | G31: =SUM(G25:G30) -> 0 | H31: =SUM(H25:H30) -> 0 | I31: =SUM(I25:I30) -> 0 | J31: =SUM(J25:J30) -> 0 | K31: =SUM(K25:K30) -> 0 | L31: =SUM(L25:L30) -> 0 | ... Q31: =SUM(Q25:Q30) -> 0
A33: 4、存货期末数
A34: 项目 | B34: 审定数 | C34: 抵消数 | D34: 汇总 | E34: 母公司审定 | F34: 子公司1 | G34: 子公司2 | H34: 子公司3 | I34: 子公司4 | J34: 子公司5 | K34: 子公司6 | L34: 子公司7 | M34: 子公司8 | N34: 子公司9 | O34: 子公司10 | P34: 子公司11 | Q34: 子公司12
A35: =A25 -> 原材料 | B35: =D35-C35 -> 0 | C35: =C5+C15-C25 -> 0 | D35: =SUM(E35:Q35) -> 0 | E35: =E5+E15-E25 -> 0 | F35: =F5+F15-F25 -> 0 | G35: =G5+G15-G25 -> 0 | H35: =H5+H15-H25 -> 0 | I35: =I5+I15-I25 -> 0 | J35: =J5+J15-J25 -> 0 | K35: =K5+K15-K25 -> 0 | L35: =L5+L15-L25 -> 0 | ... Q35: =Q5+Q15-Q25 -> 0
A36: =A26 -> 自制半成品及在产品（在研品） | B36: =D36-C36 -> 0 | C36: =C6+C16-C26 -> 0 | D36: =SUM(E36:Q36) -> 0 | E36: =E6+E16-E26 -> 0 | F36: =F6+F16-F26 -> 0 | G36: =G6+G16-G26 -> 0 | H36: =H6+H16-H26 -> 0 | I36: =I6+I16-I26 -> 0 | J36: =J6+J16-J26 -> 0 | K36: =K6+K16-K26 -> 0 | L36: =L6+L16-L26 -> 0 | ... Q36: =Q6+Q16-Q26 -> 0
A37: =A27 -> 库存商品（产成品） | B37: =D37-C37 -> 0 | C37: =C7+C17-C27 -> 0 | D37: =SUM(E37:Q37) -> 0 | E37: =E7+E17-E27 -> 0 | F37: =F7+F17-F27 -> 0 | G37: =G7+G17-G27 -> 0 | H37: =H7+H17-H27 -> 0 | I37: =I7+I17-I27 -> 0 | J37: =J7+J17-J27 -> 0 | K37: =K7+K17-K27 -> 0 | L37: =L7+L17-L27 -> 0 | ... Q37: =Q7+Q17-Q27 -> 0
A38: =A28 -> 周转材料（包装物、低值易耗品等） | B38: =D38-C38 -> 0 | C38: =C8+C18-C28 -> 0 | D38: =SUM(E38:Q38) -> 0 | E38: =E8+E18-E28 -> 0 | F38: =F8+F18-F28 -> 0 | G38: =G8+G18-G28 -> 0 | H38: =H8+H18-H28 -> 0 | I38: =I8+I18-I28 -> 0 | J38: =J8+J18-J28 -> 0 | K38: =K8+K18-K28 -> 0 | L38: =L8+L18-L28 -> 0 | ... Q38: =Q8+Q18-Q28 -> 0
A39: =A29 -> 工程施工（工程施工减工程结算） | B39: =D39-C39 -> 0 | C39: =C9+C19-C29 -> 0 | D39: =SUM(E39:Q39) -> 0 | E39: =E9+E19-E29 -> 0 | F39: =F9+F19-F29 -> 0 | G39: =G9+G19-G29 -> 0 | H39: =H9+H19-H29 -> 0 | I39: =I9+I19-I29 -> 0 | J39: =J9+J19-J29 -> 0 | K39: =K9+K19-K29 -> 0 | L39: =L9+L19-L29 -> 0 | ... Q39: =Q9+Q19-Q29 -> 0
A40: =A30 -> 其他(发出商品） | B40: =D40-C40 -> 0 | C40: =C10+C20-C30 -> 0 | D40: =SUM(E40:Q40) -> 0 | E40: =E10+E20-E30 -> 0 | F40: =F10+F20-F30 -> 0 | G40: =G10+G20-G30 -> 0 | H40: =H10+H20-H30 -> 0 | I40: =I10+I20-I30 -> 0 | J40: =J10+J20-J30 -> 0 | K40: =K10+K20-K30 -> 0 | L40: =L10+L20-L30 -> 0 | ... Q40: =Q10+Q20-Q30 -> 0
A41: 合计 | B41: =SUM(B35:B40) -> 0 | C41: =SUM(C35:C40) -> 0 | D41: =SUM(E41:Q41) -> 0 | E41: =SUM(E35:E40) -> 0 | F41: =SUM(F35:F40) -> 0 | G41: =SUM(G35:G40) -> 0 | H41: =SUM(H35:H40) -> 0 | I41: =SUM(I35:I40) -> 0 | J41: =SUM(J35:J40) -> 0 | K41: =SUM(K35:K40) -> 0 | L41: =SUM(L35:L40) -> 0 | ... Q41: =SUM(Q35:Q40) -> 0
A43: 存货减值准备
A44: 1、存货跌价准备期初数
A45: 项目 | B45: 审定数 | C45: 抵消数 | D45: 汇总 | E45: 母公司审定 | F45: 子公司1 | G45: 子公司2 | H45: 子公司3 | I45: 子公司4 | J45: 子公司5 | K45: 子公司6 | L45: 子公司7 | M45: 子公司8 | N45: 子公司9 | O45: 子公司10 | P45: 子公司11 | Q45: 子公司12
A46: =A35 -> 原材料 | B46: =D46-C46 -> 0 | D46: =SUM(E46:Q46) -> 0 | E46: 0
A47: =A36 -> 自制半成品及在产品（在研品） | B47: =D47-C47 -> 0 | D47: =SUM(E47:Q47) -> 0 | E47: 0
A48: =A37 -> 库存商品（产成品） | B48: =D48-C48 -> 0 | D48: =SUM(E48:Q48) -> 0 | E48: 0
A49: =A38 -> 周转材料（包装物、低值易耗品等） | B49: =D49-C49 -> 0 | D49: =SUM(E49:Q49) -> 0 | E49: 0
A50: =A39 -> 工程施工（工程施工减工程结算） | B50: =D50-C50 -> 0 | D50: =SUM(E50:Q50) -> 0 | E50: 0
A51: =A40 -> 其他(发出商品） | B51: =D51-C51 -> 0 | D51: =SUM(E51:Q51) -> 0 | E51: 0
A52: 合计 | B52: =SUM(B46:B51) -> 0 | C52: =SUM(C46:C51) -> 0 | D52: =SUM(E52:Q52) -> 0 | E52: =SUM(E46:E51) -> 0 | F52: =SUM(F46:F51) -> 0 | G52: =SUM(G46:G51) -> 0 | H52: =SUM(H46:H51) -> 0 | I52: =SUM(I46:I51) -> 0 | J52: =SUM(J46:J51) -> 0 | K52: =SUM(K46:K51) -> 0 | L52: =SUM(L46:L51) -> 0 | ... Q52: =SUM(Q46:Q51) -> 0
A54: 2、本期增加（计提）
A55: 项目 | B55: 审定数 | C55: 抵消数 | D55: 汇总 | E55: 母公司审定 | F55: 子公司1 | G55: 子公司2 | H55: 子公司3 | I55: 子公司4 | J55: 子公司5 | K55: 子公司6 | L55: 子公司7 | M55: 子公司8 | N55: 子公司9 | O55: 子公司10 | P55: 子公司11 | Q55: 子公司12
A56: =A46 -> 原材料 | B56: =D56-C56 -> 0 | D56: =SUM(E56:Q56) -> 0 | E56: 0
A57: =A47 -> 自制半成品及在产品（在研品） | B57: =D57-C57 -> 0 | D57: =SUM(E57:Q57) -> 0 | E57: 0
A58: =A48 -> 库存商品（产成品） | B58: =D58-C58 -> 0 | D58: =SUM(E58:Q58) -> 0 | E58: 0
A59: =A49 -> 周转材料（包装物、低值易耗品等） | B59: =D59-C59 -> 0 | D59: =SUM(E59:Q59) -> 0 | E59: 0
A60: =A50 -> 工程施工（工程施工减工程结算） | B60: =D60-C60 -> 0 | D60: =SUM(E60:Q60) -> 0 | E60: 0
A61: =A51 -> 其他(发出商品） | B61: =D61-C61 -> 0 | D61: =SUM(E61:Q61) -> 0 | E61: 0
A62: 合计 | B62: =SUM(B56:B61) -> 0 | C62: =SUM(C56:C61) -> 0 | D62: =SUM(E62:Q62) -> 0 | E62: =SUM(E56:E61) -> 0 | F62: =SUM(F56:F61) -> 0 | G62: =SUM(G56:G61) -> 0 | H62: =SUM(H56:H61) -> 0 | I62: =SUM(I56:I61) -> 0 | J62: =SUM(J56:J61) -> 0 | K62: =SUM(K56:K61) -> 0 | L62: =SUM(L56:L61) -> 0 | ... Q62: =SUM(Q56:Q61) -> 0
A64: 3、本期增加（其他）
A65: 项目 | B65: 审定数 | C65: 抵消数 | D65: 汇总 | E65: 母公司审定 | F65: 子公司1 | G65: 子公司2 | H65: 子公司3 | I65: 子公司4 | J65: 子公司5 | K65: 子公司6 | L65: 子公司7 | M65: 子公司8 | N65: 子公司9 | O65: 子公司10 | P65: 子公司11 | Q65: 子公司12
A66: =A56 -> 原材料 | B66: =D66-C66 -> 0 | D66: =SUM(E66:Q66) -> 0 | E66: 0
A67: =A57 -> 自制半成品及在产品（在研品） | B67: =D67-C67 -> 0 | D67: =SUM(E67:Q67) -> 0 | E67: 0
A68: =A58 -> 库存商品（产成品） | B68: =D68-C68 -> 0 | D68: =SUM(E68:Q68) -> 0 | E68: 0
A69: =A59 -> 周转材料（包装物、低值易耗品等） | B69: =D69-C69 -> 0 | D69: =SUM(E69:Q69) -> 0 | E69: 0
A70: =A60 -> 工程施工（工程施工减工程结算） | B70: =D70-C70 -> 0 | D70: =SUM(E70:Q70) -> 0 | E70: 0
A71: =A61 -> 其他(发出商品） | B71: =D71-C71 -> 0 | D71: =SUM(E71:Q71) -> 0 | E71: 0
A72: 合计 | B72: =SUM(B66:B71) -> 0 | C72: =SUM(C66:C71) -> 0 | D72: =SUM(E72:Q72) -> 0 | E72: =SUM(E66:E71) -> 0 | F72: =SUM(F66:F71) -> 0 | G72: =SUM(G66:G71) -> 0 | H72: =SUM(H66:H71) -> 0 | I72: =SUM(I66:I71) -> 0 | J72: =SUM(J66:J71) -> 0 | K72: =SUM(K66:K71) -> 0 | L72: =SUM(L66:L71) -> 0 | ... Q72: =SUM(Q66:Q71) -> 0
A74: 4、本期减少（转回）
A75: 项目 | B75: 审定数 | C75: 抵消数 | D75: 汇总 | E75: 母公司审定 | F75: 子公司1 | G75: 子公司2 | H75: 子公司3 | I75: 子公司4 | J75: 子公司5 | K75: 子公司6 | L75: 子公司7 | M75: 子公司8 | N75: 子公司9 | O75: 子公司10 | P75: 子公司11 | Q75: 子公司12
A76: =A66 -> 原材料 | B76: =D76-C76 -> 0 | D76: =SUM(E76:Q76) -> 0 | E76: 0
A77: =A67 -> 自制半成品及在产品（在研品） | B77: =D77-C77 -> 0 | D77: =SUM(E77:Q77) -> 0 | E77: 0
A78: =A68 -> 库存商品（产成品） | B78: =D78-C78 -> 0 | D78: =SUM(E78:Q78) -> 0 | E78: 0
A79: =A69 -> 周转材料（包装物、低值易耗品等） | B79: =D79-C79 -> 0 | D79: =SUM(E79:Q79) -> 0 | E79: 0
A80: =A70 -> 工程施工（工程施工减工程结算） | B80: =D80-C80 -> 0 | D80: =SUM(E80:Q80) -> 0 | E80: 0
A81: =A71 -> 其他(发出商品） | B81: =D81-C81 -> 0 | D81: =SUM(E81:Q81) -> 0 | E81: 0
A82: 合计 | B82: =SUM(B76:B81) -> 0 | C82: =SUM(C76:C81) -> 0 | D82: =SUM(E82:Q82) -> 0 | E82: =SUM(E76:E81) -> 0 | F82: =SUM(F76:F81) -> 0 | G82: =SUM(G76:G81) -> 0 | H82: =SUM(H76:H81) -> 0 | I82: =SUM(I76:I81) -> 0 | J82: =SUM(J76:J81) -> 0 | K82: =SUM(K76:K81) -> 0 | L82: =SUM(L76:L81) -> 0 | ... Q82: =SUM(Q76:Q81) -> 0
A84: 5、本期减少（转销）
A85: 项目 | B85: 审定数 | C85: 抵消数 | D85: 汇总 | E85: 母公司审定 | F85: 子公司1 | G85: 子公司2 | H85: 子公司3 | I85: 子公司4 | J85: 子公司5 | K85: 子公司6 | L85: 子公司7 | M85: 子公司8 | N85: 子公司9 | O85: 子公司10 | P85: 子公司11 | Q85: 子公司12
A86: =A76 -> 原材料 | B86: =D86-C86 -> 0 | D86: =SUM(E86:Q86) -> 0 | E86: 0
A87: =A77 -> 自制半成品及在产品（在研品） | B87: =D87-C87 -> 0 | D87: =SUM(E87:Q87) -> 0 | E87: 0
A88: =A78 -> 库存商品（产成品） | B88: =D88-C88 -> 0 | D88: =SUM(E88:Q88) -> 0 | E88: 0
A89: =A79 -> 周转材料（包装物、低值易耗品等） | B89: =D89-C89 -> 0 | D89: =SUM(E89:Q89) -> 0 | E89: 0
A90: =A80 -> 工程施工（工程施工减工程结算） | B90: =D90-C90 -> 0 | D90: =SUM(E90:Q90) -> 0 | E90: 0
A91: =A81 -> 其他(发出商品） | B91: =D91-C91 -> 0 | D91: =SUM(E91:Q91) -> 0 | E91: 0
A92: 合计 | B92: =SUM(B86:B91) -> 0 | C92: =SUM(C86:C91) -> 0 | D92: =SUM(E92:Q92) -> 0 | E92: =SUM(E86:E91) -> 0 | F92: =SUM(F86:F91) -> 0 | G92: =SUM(G86:G91) -> 0 | H92: =SUM(H86:H91) -> 0 | I92: =SUM(I86:I91) -> 0 | J92: =SUM(J86:J91) -> 0 | K92: =SUM(K86:K91) -> 0 | L92: =SUM(L86:L91) -> 0 | ... Q92: =SUM(Q86:Q91) -> 0
A94: 6、本期减少（其他）
A95: 项目 | B95: 审定数 | C95: 抵消数 | D95: 汇总 | E95: 母公司审定 | F95: 子公司1 | G95: 子公司2 | H95: 子公司3 | I95: 子公司4 | J95: 子公司5 | K95: 子公司6 | L95: 子公司7 | M95: 子公司8 | N95: 子公司9 | O95: 子公司10 | P95: 子公司11 | Q95: 子公司12
A96: =A86 -> 原材料 | B96: =D96-C96 -> 0 | D96: =SUM(E96:Q96) -> 0 | E96: 0
A97: =A87 -> 自制半成品及在产品（在研品） | B97: =D97-C97 -> 0 | D97: =SUM(E97:Q97) -> 0 | E97: 0
A98: =A88 -> 库存商品（产成品） | B98: =D98-C98 -> 0 | D98: =SUM(E98:Q98) -> 0 | E98: 0
A99: =A89 -> 周转材料（包装物、低值易耗品等） | B99: =D99-C99 -> 0 | D99: =SUM(E99:Q99) -> 0 | E99: 0
A100: =A90 -> 工程施工（工程施工减工程结算） | B100: =D100-C100 -> 0 | D100: =SUM(E100:Q100) -> 0 | E100: 0
A101: =A91 -> 其他(发出商品） | B101: =D101-C101 -> 0 | D101: =SUM(E101:Q101) -> 0 | E101: 0
A102: 合计 | B102: =SUM(B96:B101) -> 0 | C102: =SUM(C96:C101) -> 0 | D102: =SUM(E102:Q102) -> 0 | E102: =SUM(E96:E101) -> 0 | F102: =SUM(F96:F101) -> 0 | G102: =SUM(G96:G101) -> 0 | H102: =SUM(H96:H101) -> 0 | I102: =SUM(I96:I101) -> 0 | J102: =SUM(J96:J101) -> 0 | K102: =SUM(K96:K101) -> 0 | L102: =SUM(L96:L101) -> 0 | ... Q102: =SUM(Q96:Q101) -> 0
A104: 7、存货跌价准备期末余额
A105: 项目 | B105: 审定数 | C105: 抵消数 | D105: 汇总 | E105: 母公司审定 | F105: 子公司1 | G105: 子公司2 | H105: 子公司3 | I105: 子公司4 | J105: 子公司5 | K105: 子公司6 | L105: 子公司7 | M105: 子公司8 | N105: 子公司9 | O105: 子公司10 | P105: 子公司11 | Q105: 子公司12
A106: =A96 -> 原材料 | B106: =D106-C106 -> 0 | C106: =C46+C56+C66-C76-C86-C96 -> 0 | D106: =SUM(E106:Q106) -> 0 | E106: =E46+E56+E66-E76-E86-E96 -> 0 | F106: =F46+F56+F66-F76-F86-F96 -> 0 | G106: =G46+G56+G66-G76-G86-G96 -> 0 | H106: =H46+H56+H66-H76-H86-H96 -> 0 | I106: =I46+I56+I66-I76-I86-I96 -> 0 | J106: =J46+J56+J66-J76-J86-J96 -> 0 | K106: =K46+K56+K66-K76-K86-K96 -> 0 | L106: =L46+L56+L66-L76-L86-L96 -> 0 | ... Q106: =Q46+Q56+Q66-Q76-Q86-Q96 -> 0
A107: =A97 -> 自制半成品及在产品（在研品） | B107: =D107-C107 -> 0 | C107: =C47+C57+C67-C77-C87-C97 -> 0 | D107: =SUM(E107:Q107) -> 0 | E107: =E47+E57+E67-E77-E87-E97 -> 0 | F107: =F47+F57+F67-F77-F87-F97 -> 0 | G107: =G47+G57+G67-G77-G87-G97 -> 0 | H107: =H47+H57+H67-H77-H87-H97 -> 0 | I107: =I47+I57+I67-I77-I87-I97 -> 0 | J107: =J47+J57+J67-J77-J87-J97 -> 0 | K107: =K47+K57+K67-K77-K87-K97 -> 0 | L107: =L47+L57+L67-L77-L87-L97 -> 0 | ... Q107: =Q47+Q57+Q67-Q77-Q87-Q97 -> 0
A108: =A98 -> 库存商品（产成品） | B108: =D108-C108 -> 0 | C108: =C48+C58+C68-C78-C88-C98 -> 0 | D108: =SUM(E108:Q108) -> 0 | E108: =E48+E58+E68-E78-E88-E98 -> 0 | F108: =F48+F58+F68-F78-F88-F98 -> 0 | G108: =G48+G58+G68-G78-G88-G98 -> 0 | H108: =H48+H58+H68-H78-H88-H98 -> 0 | I108: =I48+I58+I68-I78-I88-I98 -> 0 | J108: =J48+J58+J68-J78-J88-J98 -> 0 | K108: =K48+K58+K68-K78-K88-K98 -> 0 | L108: =L48+L58+L68-L78-L88-L98 -> 0 | ... Q108: =Q48+Q58+Q68-Q78-Q88-Q98 -> 0
A109: =A99 -> 周转材料（包装物、低值易耗品等） | B109: =D109-C109 -> 0 | C109: =C49+C59+C69-C79-C89-C99 -> 0 | D109: =SUM(E109:Q109) -> 0 | E109: =E49+E59+E69-E79-E89-E99 -> 0 | F109: =F49+F59+F69-F79-F89-F99 -> 0 | G109: =G49+G59+G69-G79-G89-G99 -> 0 | H109: =H49+H59+H69-H79-H89-H99 -> 0 | I109: =I49+I59+I69-I79-I89-I99 -> 0 | J109: =J49+J59+J69-J79-J89-J99 -> 0 | K109: =K49+K59+K69-K79-K89-K99 -> 0 | L109: =L49+L59+L69-L79-L89-L99 -> 0 | ... Q109: =Q49+Q59+Q69-Q79-Q89-Q99 -> 0
A110: =A100 -> 工程施工（工程施工减工程结算） | B110: =D110-C110 -> 0 | C110: =C50+C60+C70-C80-C90-C100 -> 0 | D110: =SUM(E110:Q110) -> 0 | E110: =E50+E60+E70-E80-E90-E100 -> 0 | F110: =F50+F60+F70-F80-F90-F100 -> 0 | G110: =G50+G60+G70-G80-G90-G100 -> 0 | H110: =H50+H60+H70-H80-H90-H100 -> 0 | I110: =I50+I60+I70-I80-I90-I100 -> 0 | J110: =J50+J60+J70-J80-J90-J100 -> 0 | K110: =K50+K60+K70-K80-K90-K100 -> 0 | L110: =L50+L60+L70-L80-L90-L100 -> 0 | ... Q110: =Q50+Q60+Q70-Q80-Q90-Q100 -> 0
...

Sheet 合同资产
A1: 合同资产附注汇总 | D1: 返回Excel目录 | E1: 返回word附注
A2: 合同资产
A3: 1、合同资产期初数
A4: 项目 | B4: 审定数 | C4: 抵消数 | D4: 汇总 | E4: 母公司审定 | F4: 子公司1 | G4: 子公司2 | H4: 子公司3 | I4: 子公司4 | J4: 子公司5 | K4: 子公司6 | L4: 子公司7 | M4: 子公司8 | N4: 子公司9 | O4: 子公司10 | P4: 子公司11 | Q4: 子公司12
A5: 一、合同资产原值
A6: 类别A | B6: =D6-C6 -> 0 | D6: =SUM(E6:Q6) -> 0 | E6: 0
A7: 类别B | B7: =D7-C7 -> 0 | D7: =SUM(E7:Q7) -> 0 | E7: 0
A8: 类别C | B8: =D8-C8 -> 0 | D8: =SUM(E8:Q8) -> 0 | E8: 0
A9: 小计 | B9: =SUM(B6:B8) -> 0 | C9: =SUM(C6:C8) -> 0 | D9: =SUM(D6:D8) -> 0 | E9: =SUM(E6:E8) -> 0 | F9: =SUM(F6:F8) -> 0 | G9: =SUM(G6:G8) -> 0 | H9: =SUM(H6:H8) -> 0 | I9: =SUM(I6:I8) -> 0 | ... Q9: =SUM(Q6:Q8) -> 0
A10: 二、合同资产坏账准备
A11: 类别A | B11: =D11-C11 -> 0 | C11: =C45 -> 0 | D11: =SUM(E11:Q11) -> 0 | E11: =E45 -> 0 | F11: =F45 -> 0 | G11: =G45 -> 0 | H11: =H45 -> 0 | I11: =I45 -> 0 | J11: =J45 -> 0 | K11: =K45 -> 0 | L11: =L45 -> 0 | ... Q11: =Q45 -> 0
A12: 类别B | B12: =D12-C12 -> 0 | C12: =C52 -> 0 | D12: =SUM(E12:Q12) -> 0 | E12: =E52 -> 0 | F12: =F52 -> 0 | G12: =G52 -> 0 | H12: =H52 -> 0 | I12: =I52 -> 0 | J12: =J52 -> 0 | K12: =K52 -> 0 | L12: =L52 -> 0 | ... Q12: =Q52 -> 0
A13: 类别C | B13: =D13-C13 -> 0 | C13: =C59 -> 0 | D13: =SUM(E13:Q13) -> 0 | E13: =E59 -> 0 | F13: =F59 -> 0 | G13: =G59 -> 0 | H13: =H59 -> 0 | I13: =I59 -> 0 | J13: =J59 -> 0 | K13: =K59 -> 0 | L13: =L59 -> 0 | ... Q13: =Q59 -> 0
A14: 小计 | B14: =SUM(B11:B13) -> 0 | C14: =SUM(C11:C13) -> 0 | D14: =SUM(D11:D13) -> 0 | E14: =SUM(E11:E13) -> 0 | F14: =SUM(F11:F13) -> 0 | G14: =SUM(G11:G13) -> 0 | H14: =SUM(H11:H13) -> 0 | I14: =SUM(I11:I13) -> 0 | ... Q14: =SUM(Q11:Q13) -> 0
A15: 三、合同资产净值
A16: 类别A | B16: =D16-C16 -> 0 | C16: =C6-C11 -> 0 | D16: =SUM(E16:Q16) -> 0 | E16: =E6-E11 -> 0 | F16: =F6-F11 -> 0 | G16: =G6-G11 -> 0 | H16: =H6-H11 -> 0 | I16: =I6-I11 -> 0 | J16: =J6-J11 -> 0 | K16: =K6-K11 -> 0 | L16: =L6-L11 -> 0 | ... Q16: =Q6-Q11 -> 0
A17: 类别B | B17: =D17-C17 -> 0 | C17: =C7-C12 -> 0 | D17: =SUM(E17:Q17) -> 0 | E17: =E7-E12 -> 0 | F17: =F7-F12 -> 0 | G17: =G7-G12 -> 0 | H17: =H7-H12 -> 0 | I17: =I7-I12 -> 0 | J17: =J7-J12 -> 0 | K17: =K7-K12 -> 0 | L17: =L7-L12 -> 0 | ... Q17: =Q7-Q12 -> 0
A18: 类别C | B18: =D18-C18 -> 0 | C18: =C8-C13 -> 0 | D18: =SUM(E18:Q18) -> 0 | E18: =E8-E13 -> 0 | F18: =F8-F13 -> 0 | G18: =G8-G13 -> 0 | H18: =H8-H13 -> 0 | I18: =I8-I13 -> 0 | J18: =J8-J13 -> 0 | K18: =K8-K13 -> 0 | L18: =L8-L13 -> 0 | ... Q18: =Q8-Q13 -> 0
A19: 合计 | B19: =SUM(B16:B18) -> 0 | C19: =SUM(C16:C18) -> 0 | D19: =SUM(D16:D18) -> 0 | E19: =SUM(E16:E18) -> 0 | F19: =SUM(F16:F18) -> 0 | G19: =SUM(G16:G18) -> 0 | H19: =SUM(H16:H18) -> 0 | I19: =SUM(I16:I18) -> 0 | ... Q19: =SUM(Q16:Q18) -> 0
A20: 2、合同资产期末数
A21: 项目 | B21: 审定数 | C21: 抵消数 | D21: 汇总 | E21: 母公司审定 | F21: 子公司1 | G21: 子公司2 | H21: 子公司3 | I21: 子公司4 | J21: 子公司5 | K21: 子公司6 | L21: 子公司7 | M21: 子公司8 | N21: 子公司9 | O21: 子公司10 | P21: 子公司11 | Q21: 子公司12
A22: 一、合同资产原值
A23: 类别A | B23: =D23-C23 -> 0 | D23: =SUM(E23:Q23) -> 0 | E23: 0
A24: 类别B | B24: =D24-C24 -> 0 | D24: =SUM(E24:Q24) -> 0 | E24: 0
A25: 类别C | B25: =D25-C25 -> 0 | D25: =SUM(E25:Q25) -> 0 | E25: 0
A26: 小计 | B26: =SUM(B23:B25) -> 0 | C26: =SUM(C23:C25) -> 0 | D26: =SUM(D23:D25) -> 0 | E26: =SUM(E23:E25) -> 0 | F26: =SUM(F23:F25) -> 0 | G26: =SUM(G23:G25) -> 0 | H26: =SUM(H23:H25) -> 0 | I26: =SUM(I23:I25) -> 0 | ... Q26: =SUM(Q23:Q25) -> 0
A27: 二、合同资产坏账准备
A28: 类别A | B28: =D28-C28 -> 0 | C28: =C160 -> 0 | D28: =SUM(E28:Q28) -> 0 | E28: =E160 -> 0 | F28: =F160 -> 0 | G28: =G160 -> 0 | H28: =H160 -> 0 | I28: =I160 -> 0 | J28: =J160 -> 0 | K28: =K160 -> 0 | L28: =L160 -> 0 | ... Q28: =Q160 -> 0
A29: 类别B | B29: =D29-C29 -> 0 | C29: =C167 -> 0 | D29: =SUM(E29:Q29) -> 0 | E29: =E167 -> 0 | F29: =F167 -> 0 | G29: =G167 -> 0 | H29: =H167 -> 0 | I29: =I167 -> 0 | J29: =J167 -> 0 | K29: =K167 -> 0 | L29: =L167 -> 0 | ... Q29: =Q167 -> 0
A30: 类别C | B30: =D30-C30 -> 0 | C30: =C174 -> 0 | D30: =SUM(E30:Q30) -> 0 | E30: =E174 -> 0 | F30: =F174 -> 0 | G30: =G174 -> 0 | H30: =H174 -> 0 | I30: =I174 -> 0 | J30: =J174 -> 0 | K30: =K174 -> 0 | L30: =L174 -> 0 | ... Q30: =Q174 -> 0
A31: 小计 | B31: =SUM(B28:B30) -> 0 | C31: =SUM(C28:C30) -> 0 | D31: =SUM(D28:D30) -> 0 | E31: =SUM(E28:E30) -> 0 | F31: =SUM(F28:F30) -> 0 | G31: =SUM(G28:G30) -> 0 | H31: =SUM(H28:H30) -> 0 | I31: =SUM(I28:I30) -> 0 | ... Q31: =SUM(Q28:Q30) -> 0
A32: 三、合同资产净值
A33: 类别A | B33: =D33-C33 -> 0 | C33: =C23-C28 -> 0 | D33: =SUM(E33:Q33) -> 0 | E33: =E23-E28 -> 0 | F33: =F23-F28 -> 0 | G33: =G23-G28 -> 0 | H33: =H23-H28 -> 0 | I33: =I23-I28 -> 0 | J33: =J23-J28 -> 0 | K33: =K23-K28 -> 0 | L33: =L23-L28 -> 0 | ... Q33: =Q23-Q28 -> 0
A34: 类别B | B34: =D34-C34 -> 0 | C34: =C24-C29 -> 0 | D34: =SUM(E34:Q34) -> 0 | E34: =E24-E29 -> 0 | F34: =F24-F29 -> 0 | G34: =G24-G29 -> 0 | H34: =H24-H29 -> 0 | I34: =I24-I29 -> 0 | J34: =J24-J29 -> 0 | K34: =K24-K29 -> 0 | L34: =L24-L29 -> 0 | ... Q34: =Q24-Q29 -> 0
A35: 类别C | B35: =D35-C35 -> 0 | C35: =C25-C30 -> 0 | D35: =SUM(E35:Q35) -> 0 | E35: =E25-E30 -> 0 | F35: =F25-F30 -> 0 | G35: =G25-G30 -> 0 | H35: =H25-H30 -> 0 | I35: =I25-I30 -> 0 | J35: =J25-J30 -> 0 | K35: =K25-K30 -> 0 | L35: =L25-L30 -> 0 | ... Q35: =Q25-Q30 -> 0
A36: 合计 | B36: =SUM(B33:B35) -> 0 | C36: =SUM(C33:C35) -> 0 | D36: =SUM(D33:D35) -> 0 | E36: =SUM(E33:E35) -> 0 | F36: =SUM(F33:F35) -> 0 | G36: =SUM(G33:G35) -> 0 | H36: =SUM(H33:H35) -> 0 | I36: =SUM(I33:I35) -> 0 | ... Q36: =SUM(Q33:Q35) -> 0
A37: 坏账准备情况
A38: 1、坏账准备期初数
A39: 一、类别A | B39: 审定数 | C39: 抵消数 | D39: 汇总 | E39: 母公司审定 | F39: 子公司1 | G39: 子公司2 | H39: 子公司3 | I39: 子公司4 | J39: 子公司5 | K39: 子公司6 | L39: 子公司7 | M39: 子公司8 | N39: 子公司9 | O39: 子公司10 | P39: 子公司11 | Q39: 子公司12
A40: 未逾期 | B40: =D40-C40 -> 0 | D40: =SUM(E40:Q40) -> 0 | E40: 0
A41: 逾期1至30日 | B41: =D41-C41 -> 0 | D41: =SUM(E41:Q41) -> 0 | E41: 0
A42: 逾期31至60日 | B42: =D42-C42 -> 0 | D42: =SUM(E42:Q42) -> 0 | E42: 0
A43: 逾期61至90日 | B43: =D43-C43 -> 0 | D43: =SUM(E43:Q43) -> 0 | E43: 0
A44: 逾期超过90日 | B44: =D44-C44 -> 0 | D44: =SUM(E44:Q44) -> 0 | E44: 0
A45: 小计 | B45: =SUM(B40:B44) -> 0 | C45: =SUM(C40:C44) -> 0 | D45: =SUM(D40:D44) -> 0 | E45: =SUM(E40:E44) -> 0 | F45: =SUM(F40:F44) -> 0 | G45: =SUM(G40:G44) -> 0 | H45: =SUM(H40:H44) -> 0 | I45: =SUM(I40:I44) -> 0 | ... Q45: =SUM(Q40:Q44) -> 0
A46: 二、类别B | B46: 审定数 | C46: 抵消数 | D46: 汇总 | E46: 母公司审定 | F46: 子公司1 | G46: 子公司2 | H46: 子公司3 | I46: 子公司4 | J46: 子公司5 | K46: 子公司6 | L46: 子公司7 | M46: 子公司8 | N46: 子公司9 | O46: 子公司10 | P46: 子公司11 | Q46: 子公司12
A47: 未逾期 | B47: =D47-C47 -> 0 | D47: =SUM(E47:Q47) -> 0 | E47: 0
A48: 逾期1至30日 | B48: =D48-C48 -> 0 | D48: =SUM(E48:Q48) -> 0 | E48: 0
A49: 逾期31至60日 | B49: =D49-C49 -> 0 | D49: =SUM(E49:Q49) -> 0 | E49: 0
A50: 逾期61至90日 | B50: =D50-C50 -> 0 | D50: =SUM(E50:Q50) -> 0 | E50: 0
A51: 逾期超过90日 | B51: =D51-C51 -> 0 | D51: =SUM(E51:Q51) -> 0 | E51: 0
A52: 小计 | B52: =SUM(B47:B51) -> 0 | C52: =SUM(C47:C51) -> 0 | D52: =SUM(D47:D51) -> 0 | E52: =SUM(E47:E51) -> 0 | F52: =SUM(F47:F51) -> 0 | G52: =SUM(G47:G51) -> 0 | H52: =SUM(H47:H51) -> 0 | I52: =SUM(I47:I51) -> 0 | ... Q52: =SUM(Q47:Q51) -> 0
A53: 三、类别C | B53: 审定数 | C53: 抵消数 | D53: 汇总 | E53: 母公司审定 | F53: 子公司1 | G53: 子公司2 | H53: 子公司3 | I53: 子公司4 | J53: 子公司5 | K53: 子公司6 | L53: 子公司7 | M53: 子公司8 | N53: 子公司9 | O53: 子公司10 | P53: 子公司11 | Q53: 子公司12
A54: 未逾期 | B54: =D54-C54 -> 0 | D54: =SUM(E54:Q54) -> 0 | E54: 0
A55: 逾期1至30日 | B55: =D55-C55 -> 0 | D55: =SUM(E55:Q55) -> 0 | E55: 0
A56: 逾期31至60日 | B56: =D56-C56 -> 0 | D56: =SUM(E56:Q56) -> 0 | E56: 0
A57: 逾期61至90日 | B57: =D57-C57 -> 0 | D57: =SUM(E57:Q57) -> 0 | E57: 0
A58: 逾期超过90日 | B58: =D58-C58 -> 0 | D58: =SUM(E58:Q58) -> 0 | E58: 0
A59: 小计 | B59: =SUM(B54:B58) -> 0 | C59: =SUM(C54:C58) -> 0 | D59: =SUM(D54:D58) -> 0 | E59: =SUM(E54:E58) -> 0 | F59: =SUM(F54:F58) -> 0 | G59: =SUM(G54:G58) -> 0 | H59: =SUM(H54:H58) -> 0 | I59: =SUM(I54:I58) -> 0 | ... Q59: =SUM(Q54:Q58) -> 0
A60: 合计 | B60: =B45+B52+B59 -> 0 | C60: =C45+C52+C59 -> 0 | D60: =D45+D52+D59 -> 0 | E60: =E45+E52+E59 -> 0 | F60: =F45+F52+F59 -> 0 | G60: =G45+G52+G59 -> 0 | H60: =H45+H52+H59 -> 0 | I60: =I45+I52+I59 -> 0 | ... Q60: =Q45+Q52+Q59 -> 0
A61: 2、坏账准备本期计提
A62: 一、类别A | B62: 审定数 | C62: 抵消数 | D62: 汇总 | E62: 母公司审定 | F62: 子公司1 | G62: 子公司2 | H62: 子公司3 | I62: 子公司4 | J62: 子公司5 | K62: 子公司6 | L62: 子公司7 | M62: 子公司8 | N62: 子公司9 | O62: 子公司10 | P62: 子公司11 | Q62: 子公司12
A63: 未逾期 | B63: =D63-C63 -> 0 | D63: =SUM(E63:Q63) -> 0 | E63: 0
A64: 逾期1至30日 | B64: =D64-C64 -> 0 | D64: =SUM(E64:Q64) -> 0 | E64: 0
A65: 逾期31至60日 | B65: =D65-C65 -> 0 | D65: =SUM(E65:Q65) -> 0 | E65: 0
A66: 逾期61至90日 | B66: =D66-C66 -> 0 | D66: =SUM(E66:Q66) -> 0 | E66: 0
A67: 逾期超过90日 | B67: =D67-C67 -> 0 | D67: =SUM(E67:Q67) -> 0 | E67: 0
A68: 小计 | B68: =SUM(B63:B67) -> 0 | C68: =SUM(C63:C67) -> 0 | D68: =SUM(D63:D67) -> 0 | E68: =SUM(E63:E67) -> 0 | F68: =SUM(F63:F67) -> 0 | G68: =SUM(G63:G67) -> 0 | H68: =SUM(H63:H67) -> 0 | I68: =SUM(I63:I67) -> 0 | ... Q68: =SUM(Q63:Q67) -> 0
A69: 二、类别B | B69: 审定数 | C69: 抵消数 | D69: 汇总 | E69: 母公司审定 | F69: 子公司1 | G69: 子公司2 | H69: 子公司3 | I69: 子公司4 | J69: 子公司5 | K69: 子公司6 | L69: 子公司7 | M69: 子公司8 | N69: 子公司9 | O69: 子公司10 | P69: 子公司11 | Q69: 子公司12
A70: 未逾期 | B70: =D70-C70 -> 0 | D70: =SUM(E70:Q70) -> 0 | E70: 0
A71: 逾期1至30日 | B71: =D71-C71 -> 0 | D71: =SUM(E71:Q71) -> 0 | E71: 0
A72: 逾期31至60日 | B72: =D72-C72 -> 0 | D72: =SUM(E72:Q72) -> 0 | E72: 0
A73: 逾期61至90日 | B73: =D73-C73 -> 0 | D73: =SUM(E73:Q73) -> 0 | E73: 0
A74: 逾期超过90日 | B74: =D74-C74 -> 0 | D74: =SUM(E74:Q74) -> 0 | E74: 0
A75: 小计 | B75: =SUM(B70:B74) -> 0 | C75: =SUM(C70:C74) -> 0 | D75: =SUM(D70:D74) -> 0 | E75: =SUM(E70:E74) -> 0 | F75: =SUM(F70:F74) -> 0 | G75: =SUM(G70:G74) -> 0 | H75: =SUM(H70:H74) -> 0 | I75: =SUM(I70:I74) -> 0 | ... Q75: =SUM(Q70:Q74) -> 0
A76: 三、类别C | B76: 审定数 | C76: 抵消数 | D76: 汇总 | E76: 母公司审定 | F76: 子公司1 | G76: 子公司2 | H76: 子公司3 | I76: 子公司4 | J76: 子公司5 | K76: 子公司6 | L76: 子公司7 | M76: 子公司8 | N76: 子公司9 | O76: 子公司10 | P76: 子公司11 | Q76: 子公司12
A77: 未逾期 | B77: =D77-C77 -> 0 | D77: =SUM(E77:Q77) -> 0 | E77: 0
A78: 逾期1至30日 | B78: =D78-C78 -> 0 | D78: =SUM(E78:Q78) -> 0 | E78: 0
A79: 逾期31至60日 | B79: =D79-C79 -> 0 | D79: =SUM(E79:Q79) -> 0 | E79: 0
A80: 逾期61至90日 | B80: =D80-C80 -> 0 | D80: =SUM(E80:Q80) -> 0 | E80: 0
A81: 逾期超过90日 | B81: =D81-C81 -> 0 | D81: =SUM(E81:Q81) -> 0 | E81: 0
A82: 小计 | B82: =SUM(B77:B81) -> 0 | C82: =SUM(C77:C81) -> 0 | D82: =SUM(D77:D81) -> 0 | E82: =SUM(E77:E81) -> 0 | F82: =SUM(F77:F81) -> 0 | G82: =SUM(G77:G81) -> 0 | H82: =SUM(H77:H81) -> 0 | I82: =SUM(I77:I81) -> 0 | ... Q82: =SUM(Q77:Q81) -> 0
A83: 合计 | B83: =B68+B75+B82 -> 0 | C83: =C68+C75+C82 -> 0 | D83: =D68+D75+D82 -> 0 | E83: =E68+E75+E82 -> 0 | F83: =F68+F75+F82 -> 0 | G83: =G68+G75+G82 -> 0 | H83: =H68+H75+H82 -> 0 | I83: =I68+I75+I82 -> 0 | ... Q83: =Q68+Q75+Q82 -> 0
A84: 3、坏账准备本期其他增加
A85: 一、类别A | B85: 审定数 | C85: 抵消数 | D85: 汇总 | E85: 母公司审定 | F85: 子公司1 | G85: 子公司2 | H85: 子公司3 | I85: 子公司4 | J85: 子公司5 | K85: 子公司6 | L85: 子公司7 | M85: 子公司8 | N85: 子公司9 | O85: 子公司10 | P85: 子公司11 | Q85: 子公司12
A86: 未逾期 | B86: =D86-C86 -> 0 | D86: =SUM(E86:Q86) -> 0 | E86: 0
A87: 逾期1至30日 | B87: =D87-C87 -> 0 | D87: =SUM(E87:Q87) -> 0 | E87: 0
A88: 逾期31至60日 | B88: =D88-C88 -> 0 | D88: =SUM(E88:Q88) -> 0 | E88: 0
A89: 逾期61至90日 | B89: =D89-C89 -> 0 | D89: =SUM(E89:Q89) -> 0 | E89: 0
A90: 逾期超过90日 | B90: =D90-C90 -> 0 | D90: =SUM(E90:Q90) -> 0 | E90: 0
A91: 小计 | B91: =SUM(B86:B90) -> 0 | C91: =SUM(C86:C90) -> 0 | D91: =SUM(D86:D90) -> 0 | E91: =SUM(E86:E90) -> 0 | F91: =SUM(F86:F90) -> 0 | G91: =SUM(G86:G90) -> 0 | H91: =SUM(H86:H90) -> 0 | I91: =SUM(I86:I90) -> 0 | ... Q91: =SUM(Q86:Q90) -> 0
A92: 二、类别B | B92: 审定数 | C92: 抵消数 | D92: 汇总 | E92: 母公司审定 | F92: 子公司1 | G92: 子公司2 | H92: 子公司3 | I92: 子公司4 | J92: 子公司5 | K92: 子公司6 | L92: 子公司7 | M92: 子公司8 | N92: 子公司9 | O92: 子公司10 | P92: 子公司11 | Q92: 子公司12
A93: 未逾期 | B93: =D93-C93 -> 0 | D93: =SUM(E93:Q93) -> 0 | E93: 0
A94: 逾期1至30日 | B94: =D94-C94 -> 0 | D94: =SUM(E94:Q94) -> 0 | E94: 0
A95: 逾期31至60日 | B95: =D95-C95 -> 0 | D95: =SUM(E95:Q95) -> 0 | E95: 0
A96: 逾期61至90日 | B96: =D96-C96 -> 0 | D96: =SUM(E96:Q96) -> 0 | E96: 0
A97: 逾期超过90日 | B97: =D97-C97 -> 0 | D97: =SUM(E97:Q97) -> 0 | E97: 0
A98: 小计 | B98: =SUM(B93:B97) -> 0 | C98: =SUM(C93:C97) -> 0 | D98: =SUM(D93:D97) -> 0 | E98: =SUM(E93:E97) -> 0 | F98: =SUM(F93:F97) -> 0 | G98: =SUM(G93:G97) -> 0 | H98: =SUM(H93:H97) -> 0 | I98: =SUM(I93:I97) -> 0 | ... Q98: =SUM(Q93:Q97) -> 0
A99: 三、类别C | B99: 审定数 | C99: 抵消数 | D99: 汇总 | E99: 母公司审定 | F99: 子公司1 | G99: 子公司2 | H99: 子公司3 | I99: 子公司4 | J99: 子公司5 | K99: 子公司6 | L99: 子公司7 | M99: 子公司8 | N99: 子公司9 | O99: 子公司10 | P99: 子公司11 | Q99: 子公司12
A100: 未逾期 | B100: =D100-C100 -> 0 | D100: =SUM(E100:Q100) -> 0 | E100: 0
...

Sheet 持有待售资产
A1: 持有待售资产附注汇总 | D1: 返回Excel目录 | E1: 返回word附注
A2: 项目 | B2: 审定数 | C2: 抵消数 | D2: 汇总 | E2: 母公司审定 | F2: 子公司1 | G2: 子公司2 | H2: 子公司3 | I2: 子公司4 | J2: 子公司5 | K2: 子公司6 | L2: 子公司7 | M2: 子公司8 | N2: 子公司9 | O2: 子公司10 | P2: 子公司11 | Q2: 子公司12
A3: 持有待售资产：
A4: 持有待售非流动资产 | B4: =D4-C4 -> 0 | D4: =SUM(E4:Q4) -> 0 | E4: 0
A5: 持有待售的处置组中的资产 | B5: =B6+B7 -> 0 | C5: =C6+C7 -> 0 | D5: =SUM(E5:Q5) -> 0 | E5: =E6+E7 -> 0 | F5: =F6+F7 -> 0 | G5: =G6+G7 -> 0 | H5: =H6+H7 -> 0 | I5: =I6+I7 -> 0 | J5: =J6+J7 -> 0 | K5: =K6+K7 -> 0 | L5: =L6+L7 -> 0 | ... Q5: =Q6+Q7 -> 0
A6: 其中：子公司A | B6: =D6-C6 -> 0 | D6: =SUM(E6:Q6) -> 0 | E6: 0
A7: 子公司B | B7: =D7-C7 -> 0 | D7: =SUM(E7:Q7) -> 0 | E7: 0
A8: 合 计 | B8: =B4+B5 -> 0 | C8: =C4+C5 -> 0 | D8: =D4+D5 -> 0 | E8: =E4+E5 -> 0 | F8: =F4+F5 -> 0 | G8: =G4+G5 -> 0 | H8: =H4+H5 -> 0 | I8: =I4+I5 -> 0 | ... Q8: =Q4+Q5 -> 0
A9: 试算表链接： | B9: 0 | D9: =SUM(E9:Q9) -> 0 | E9: 0
A10: 差异 | B10: =B8-B9 -> 0 | C10: =C8-C9 -> 0 | D10: =D8-D9 -> 0 | E10: =E8-E9 -> 0 | F10: =F8-F9 -> 0 | G10: =G8-G9 -> 0 | H10: =H8-H9 -> 0 | I10: =I8-I9 -> 0 | ... Q10: =Q8-Q9 -> 0
A12: 项目 | B12: 审定数 | C12: 抵消数 | D12: 汇总 | E12: 母公司审定 | F12: 子公司1 | G12: 子公司2 | H12: 子公司3 | I12: 子公司4 | J12: 子公司5 | K12: 子公司6 | L12: 子公司7 | M12: 子公司8 | N12: 子公司9 | O12: 子公司10 | P12: 子公司11 | Q12: 子公司12
A13: 持有待售负债：
A14: 持有待售的处置组中的负债 | B14: =B15+B16 -> 0 | C14: =C15+C16 -> 0 | D14: =SUM(E14:Q14) -> 0 | E14: =E15+E16 -> 0 | F14: =F15+F16 -> 0 | G14: =G15+G16 -> 0 | H14: =H15+H16 -> 0 | I14: =I15+I16 -> 0 | J14: =J15+J16 -> 0 | K14: =K15+K16 -> 0 | L14: =L15+L16 -> 0 | ... Q14: =Q15+Q16 -> 0
A15: 其中：子公司A | B15: =D15-C15 -> 0 | D15: =SUM(E15:Q15) -> 0 | E15: 0
A16: 子公司B | B16: =D16-C16 -> 0 | D16: =SUM(E16:Q16) -> 0 | E16: 0
A17: 合 计 | B17: =B14 -> 0 | C17: =C14 -> 0 | D17: =D14 -> 0 | E17: =E14 -> 0 | F17: =F14 -> 0 | G17: =G14 -> 0 | H17: =H14 -> 0 | I17: =I14 -> 0 | ... Q17: =Q14 -> 0
A18: 试算表链接： | B18: 0 | D18: =SUM(E18:Q18) -> 0 | E18: 0
A19: 差异 | B19: =B17-B18 -> 0 | C19: =C17-C18 -> 0 | D19: =D17-D18 -> 0 | E19: =E17-E18 -> 0 | F19: =F17-F18 -> 0 | G19: =G17-G18 -> 0 | H19: =H17-H18 -> 0 | I19: =I17-I18 -> 0 | ... Q19: =Q17-Q18 -> 0
A21: 说明：（应当说明持有待售的非流动资产及持有待售的处置组中的资产产生的原因、内容及性质）
A22: （1）持有待售的非流动资产
A23: 期末，持有待售的资产的情况：
A24: 项 目 | B24: 账面价值 | C24: 公允价值 | D24: 预计处置费用 | E24: 预计处置时间
A29: 合 计 | B29: =SUM(B25:B28) -> 0 | C29: =SUM(C25:C28) -> 0 | D29: =SUM(D25:D28) -> 0
A30: （2）持有待售的处置组
A31: ①子公司A
A32: 项 目 | B32: 账面价值 | C32: 公允价值 | D32: 预计处置费用 | E32: 预计处置时间
A33: 持有待售的处置组中的资产
A34: 货币资金
A36: 固定资产
A37: ……
A39: 持有待售的处置组中的负债
A40: 应付账款
A41: 长期应付款
A42: ……
A43: ②子公司B
A44: 项 目 | B44: 账面价值 | C44: 公允价值 | D44: 预计处置费用 | E44: 预计处置时间
A45: 持有待售的处置组中的资产
A46: 货币资金
A48: 固定资产
A49: ……
A51: 持有待售的处置组中的负债
A52: 应付账款
A53: 长期应付款
A54: ……

Sheet 一年内到期的非流动资产
A1: 一年内到期的非流动资产附注汇总 | D1: 返回Excel目录 | E1: 返回word附注
A2: 项目 | B2: 审定数 | C2: 抵消数 | D2: 汇总 | E2: 母公司审定 | F2: 子公司1 | G2: 子公司2 | H2: 子公司3 | I2: 子公司4 | J2: 子公司5 | K2: 子公司6 | L2: 子公司7 | M2: 子公司8 | N2: 子公司9 | O2: 子公司10 | P2: 子公司11 | Q2: 子公司12
A3: 1年内到期的长期应收款 | B3: =D3-C3 -> 0 | D3: =SUM(E3:Q3) -> 0 | E3: 0
A4: 1年内到期的持有至到期投资 | B4: =D4-C4 -> 0 | D4: =SUM(E4:Q4) -> 0 | E4: 0
A5: 1年内到期的长期待摊费用 | B5: =D5-C5 -> 0 | D5: =SUM(E5:Q5) -> 0 | E5: 0
A6: 其他 | B6: =D6-C6 -> 0 | D6: =SUM(E6:Q6) -> 0 | E6: 0
A7: 合 计 | B7: =SUM(B3:B6) -> 0 | C7: =SUM(C3:C6) -> 0 | D7: =SUM(D3:D6) -> 0 | E7: =SUM(E3:E6) -> 0 | F7: =SUM(F3:F6) -> 0 | G7: =SUM(G3:G6) -> 0 | H7: =SUM(H3:H6) -> 0 | I7: =SUM(I3:I6) -> 0 | ... Q7: =SUM(Q3:Q6) -> 0
A8: 试算表链接： | B8: 0 | D8: =SUM(E8:Q8) -> 0 | E8: 0
A9: 差异 | B9: =B7-B8 -> 0 | D9: =D7-D8 -> 0 | E9: =E7-E8 -> 0 | F9: =F7-F8 -> 0 | G9: =G7-G8 -> 0 | H9: =H7-H8 -> 0 | I9: =I7-I8 -> 0 | J9: =J7-J8 -> 0 | K9: =K7-K8 -> 0 | ... Q9: =Q7-Q8 -> 0
A11: 说明：（对于大额的一年内到期的非流动资产说明形成的原因、内容、性质。）

Sheet 其他流动资产
A1: 其他流动资产附注 | D1: 返回Excel目录 | E1: 返回word附注
A2: 项目 | B2: 审定数 | C2: 抵消数 | D2: 汇总 | E2: 母公司审定 | F2: 子公司1 | G2: 子公司2 | H2: 子公司3 | I2: 子公司4 | J2: 子公司5 | K2: 子公司6 | L2: 子公司7 | M2: 子公司8 | N2: 子公司9 | O2: 子公司10 | P2: 子公司11 | Q2: 子公司12
A3: 待抵扣进项税 | B3: =D3-C3 -> 0 | D3: =SUM(E3:Q3) -> 0 | E3: 0
A4: 预缴所得税 | B4: =D4-C4 -> 0 | D4: =SUM(E4:Q4) -> 0 | E4: 0
A5: 委托贷款 | B5: =D5-C5 -> 0 | D5: =SUM(E5:Q5) -> 0 | E5: 0
A6: 预缴其他税费 | B6: =D6-C6 -> 0 | D6: =SUM(E6:Q6) -> 0 | E6: 0
B7: =D7-C7 -> 0 | D7: =SUM(E7:Q7) -> 0 | E7: 0
B8: =D8-C8 -> 0 | D8: =SUM(E8:Q8) -> 0 | E8: 0
A9: 合计 | B9: =SUM(B3:B8) -> 0 | C9: =SUM(C3:C8) -> 0 | D9: =SUM(D3:D8) -> 0 | E9: =SUM(E3:E8) -> 0 | F9: =SUM(F3:F8) -> 0 | G9: =SUM(G3:G8) -> 0 | H9: =SUM(H3:H8) -> 0 | I9: =SUM(I3:I8) -> 0 | ... Q9: =SUM(Q3:Q8) -> 0
A10: 试算表链接： | B10: 0 | D10: =SUM(E10:Q10) -> 0 | E10: 0
A11: 差异 | B11: =B9-B10 -> 0 | D11: =D9-D10 -> 0 | E11: =E9-E10 -> 0 | F11: =F9-F10 -> 0 | G11: =G9-G10 -> 0 | H11: =H9-H10 -> 0 | I11: =I9-I10 -> 0 | J11: =J9-J10 -> 0 | K11: =K9-K10 -> 0 | ... Q11: =Q9-Q10 -> 0
A12: （金额较大的其他流动资产，应说明其内容、性质）

Sheet 债权投资
A1: 债权投资附注 | D1: 返回Excel目录 | E1: 返回word附注
A2: （1）债权投资情况
A3: 项目 | B3: 审定数 | C3: 抵消数 | D3: 汇总 | E3: 母公司审定 | F3: 子公司1 | G3: 子公司2 | H3: 子公司3 | I3: 子公司4 | J3: 子公司5 | K3: 子公司6 | L3: 子公司7 | M3: 子公司8 | N3: 子公司9 | O3: 子公司10 | P3: 子公司11 | Q3: 子公司12
A4: 项目A | B4: =D4-C4 -> 0 | D4: =SUM(E4:Q4) -> 0 | E4: 0
A5: 项目B | B5: =D5-C5 -> 0 | D5: =SUM(E5:Q5) -> 0 | E5: 0
A6: 项目C | B6: =D6-C6 -> 0 | D6: =SUM(E6:Q6) -> 0 | E6: 0
A7: …… | B7: =D7-C7 -> 0 | D7: =SUM(E7:Q7) -> 0 | E7: 0
A8: 合计 | B8: =SUM(B4:B7) -> 0 | C8: =SUM(C4:C7) -> 0 | D8: =SUM(D4:D7) -> 0 | E8: =SUM(E4:E7) -> 0 | F8: =SUM(F4:F7) -> 0 | G8: =SUM(G4:G7) -> 0 | H8: =SUM(H4:H7) -> 0 | I8: =SUM(I4:I7) -> 0 | ... Q8: =SUM(Q4:Q7) -> 0
A9: 减值准备
A10: 项目 | B10: 审定数 | C10: 抵消数 | D10: 汇总 | E10: 母公司审定 | F10: 子公司1 | G10: 子公司2 | H10: 子公司3 | I10: 子公司4 | J10: 子公司5 | K10: 子公司6 | L10: 子公司7 | M10: 子公司8 | N10: 子公司9 | O10: 子公司10 | P10: 子公司11 | Q10: 子公司12
A11: 项目A | B11: =D11-C11 -> 0 | D11: =SUM(E11:Q11) -> 0 | E11: 0
A12: 项目B | B12: =D12-C12 -> 0 | D12: =SUM(E12:Q12) -> 0 | E12: 0
A13: 项目C | B13: =D13-C13 -> 0 | D13: =SUM(E13:Q13) -> 0 | E13: 0
A14: …… | B14: =D14-C14 -> 0 | D14: =SUM(E14:Q14) -> 0 | E14: 0
A15: 合计 | B15: =SUM(B11:B14) -> 0 | C15: =SUM(C11:C14) -> 0 | D15: =SUM(D11:D14) -> 0 | E15: =SUM(E11:E14) -> 0 | F15: =SUM(F11:F14) -> 0 | G15: =SUM(G11:G14) -> 0 | H15: =SUM(H11:H14) -> 0 | I15: =SUM(I11:I14) -> 0 | ... Q15: =SUM(Q11:Q14) -> 0
A16: 账面价值
A17: 项目 | B17: 审定数 | C17: 抵消数 | D17: 汇总 | E17: 母公司审定 | F17: 子公司1 | G17: 子公司2 | H17: 子公司3 | I17: 子公司4 | J17: 子公司5 | K17: 子公司6 | L17: 子公司7 | M17: 子公司8 | N17: 子公司9 | O17: 子公司10 | P17: 子公司11 | Q17: 子公司12
A18: 项目A | B18: =D18-C18 -> 0 | C18: =C4-C11 -> 0 | D18: =SUM(E18:Q18) -> 0 | E18: =E4-E11 -> 0 | F18: =F4-F11 -> 0 | G18: =G4-G11 -> 0 | H18: =H4-H11 -> 0 | I18: =I4-I11 -> 0 | J18: =J4-J11 -> 0 | K18: =K4-K11 -> 0 | L18: =L4-L11 -> 0 | ... Q18: =Q4-Q11 -> 0
A19: 项目B | B19: =D19-C19 -> 0 | C19: =C5-C12 -> 0 | D19: =SUM(E19:Q19) -> 0 | E19: =E5-E12 -> 0 | F19: =F5-F12 -> 0 | G19: =G5-G12 -> 0 | H19: =H5-H12 -> 0 | I19: =I5-I12 -> 0 | J19: =J5-J12 -> 0 | K19: =K5-K12 -> 0 | L19: =L5-L12 -> 0 | ... Q19: =Q5-Q12 -> 0
A20: 项目C | B20: =D20-C20 -> 0 | C20: =C6-C13 -> 0 | D20: =SUM(E20:Q20) -> 0 | E20: =E6-E13 -> 0 | F20: =F6-F13 -> 0 | G20: =G6-G13 -> 0 | H20: =H6-H13 -> 0 | I20: =I6-I13 -> 0 | J20: =J6-J13 -> 0 | K20: =K6-K13 -> 0 | L20: =L6-L13 -> 0 | ... Q20: =Q6-Q13 -> 0
A21: …… | B21: =D21-C21 -> 0 | C21: =C7-C14 -> 0 | D21: =SUM(E21:Q21) -> 0 | E21: =E7-E14 -> 0 | F21: =F7-F14 -> 0 | G21: =G7-G14 -> 0 | H21: =H7-H14 -> 0 | I21: =I7-I14 -> 0 | J21: =J7-J14 -> 0 | K21: =K7-K14 -> 0 | L21: =L7-L14 -> 0 | ... Q21: =Q7-Q14 -> 0
A22: 合计 | B22: =SUM(B18:B21) -> 0 | C22: =SUM(C18:C21) -> 0 | D22: =SUM(D18:D21) -> 0 | E22: =SUM(E18:E21) -> 0 | F22: =SUM(F18:F21) -> 0 | G22: =SUM(G18:G21) -> 0 | H22: =SUM(H18:H21) -> 0 | I22: =SUM(I18:I21) -> 0 | ... Q22: =SUM(Q18:Q21) -> 0
A23: 1年内到期的债权投资原值
A24: 项目 | B24: 审定数 | C24: 抵消数 | D24: 汇总 | E24: 母公司审定 | F24: 子公司1 | G24: 子公司2 | H24: 子公司3 | I24: 子公司4 | J24: 子公司5 | K24: 子公司6 | L24: 子公司7 | M24: 子公司8 | N24: 子公司9 | O24: 子公司10 | P24: 子公司11 | Q24: 子公司12
A25: 项目A | B25: =D25-C25 -> 0 | D25: =SUM(E25:Q25) -> 0 | E25: 0
A26: 项目B | B26: =D26-C26 -> 0 | D26: =SUM(E26:Q26) -> 0 | E26: 0
A27: 项目C | B27: =D27-C27 -> 0 | D27: =SUM(E27:Q27) -> 0 | E27: 0
A28: …… | B28: =D28-C28 -> 0 | D28: =SUM(E28:Q28) -> 0 | E28: 0
A29: 合计 | B29: =SUM(B25:B28) -> 0 | C29: =SUM(C25:C28) -> 0 | D29: =SUM(D25:D28) -> 0 | E29: =SUM(E25:E28) -> 0 | F29: =SUM(F25:F28) -> 0 | G29: =SUM(G25:G28) -> 0 | H29: =SUM(H25:H28) -> 0 | I29: =SUM(I25:I28) -> 0 | ... Q29: =SUM(Q25:Q28) -> 0
A30: 1年内到期的债权投资减值准备
A31: 项目 | B31: 审定数 | C31: 抵消数 | D31: 汇总 | E31: 母公司审定 | F31: 子公司1 | G31: 子公司2 | H31: 子公司3 | I31: 子公司4 | J31: 子公司5 | K31: 子公司6 | L31: 子公司7 | M31: 子公司8 | N31: 子公司9 | O31: 子公司10 | P31: 子公司11 | Q31: 子公司12
A32: 项目A | B32: =D32-C32 -> 0 | D32: =SUM(E32:Q32) -> 0 | E32: 0
A33: 项目B | B33: =D33-C33 -> 0 | D33: =SUM(E33:Q33) -> 0 | E33: 0
A34: 项目C | B34: =D34-C34 -> 0 | D34: =SUM(E34:Q34) -> 0 | E34: 0
A35: …… | B35: =D35-C35 -> 0 | D35: =SUM(E35:Q35) -> 0 | E35: 0
A36: 合计 | B36: =SUM(B32:B35) -> 0 | C36: =SUM(C32:C35) -> 0 | D36: =SUM(D32:D35) -> 0 | E36: =SUM(E32:E35) -> 0 | F36: =SUM(F32:F35) -> 0 | G36: =SUM(G32:G35) -> 0 | H36: =SUM(H32:H35) -> 0 | I36: =SUM(I32:I35) -> 0 | ... Q36: =SUM(Q32:Q35) -> 0
A37: 1年内到期的债权投资账面价值
A38: 项目 | B38: 审定数 | C38: 抵消数 | D38: 汇总 | E38: 母公司审定 | F38: 子公司1 | G38: 子公司2 | H38: 子公司3 | I38: 子公司4 | J38: 子公司5 | K38: 子公司6 | L38: 子公司7 | M38: 子公司8 | N38: 子公司9 | O38: 子公司10 | P38: 子公司11 | Q38: 子公司12
A39: 项目A | B39: =D39-C39 -> 0 | C39: =C25-C32 -> 0 | D39: =SUM(E39:Q39) -> 0 | E39: =E25-E32 -> 0 | F39: =F25-F32 -> 0 | G39: =G25-G32 -> 0 | H39: =H25-H32 -> 0 | I39: =I25-I32 -> 0 | J39: =J25-J32 -> 0 | K39: =K25-K32 -> 0 | L39: =L25-L32 -> 0 | ... Q39: =Q25-Q32 -> 0
A40: 项目B | B40: =D40-C40 -> 0 | C40: =C26-C33 -> 0 | D40: =SUM(E40:Q40) -> 0 | E40: =E26-E33 -> 0 | F40: =F26-F33 -> 0 | G40: =G26-G33 -> 0 | H40: =H26-H33 -> 0 | I40: =I26-I33 -> 0 | J40: =J26-J33 -> 0 | K40: =K26-K33 -> 0 | L40: =L26-L33 -> 0 | ... Q40: =Q26-Q33 -> 0
A41: 项目C | B41: =D41-C41 -> 0 | C41: =C27-C34 -> 0 | D41: =SUM(E41:Q41) -> 0 | E41: =E27-E34 -> 0 | F41: =F27-F34 -> 0 | G41: =G27-G34 -> 0 | H41: =H27-H34 -> 0 | I41: =I27-I34 -> 0 | J41: =J27-J34 -> 0 | K41: =K27-K34 -> 0 | L41: =L27-L34 -> 0 | ... Q41: =Q27-Q34 -> 0
A42: …… | B42: =D42-C42 -> 0 | C42: =C28-C35 -> 0 | D42: =SUM(E42:Q42) -> 0 | E42: =E28-E35 -> 0 | F42: =F28-F35 -> 0 | G42: =G28-G35 -> 0 | H42: =H28-H35 -> 0 | I42: =I28-I35 -> 0 | J42: =J28-J35 -> 0 | K42: =K28-K35 -> 0 | L42: =L28-L35 -> 0 | ... Q42: =Q28-Q35 -> 0
A43: 合计 | B43: =SUM(B39:B42) -> 0 | C43: =SUM(C39:C42) -> 0 | D43: =SUM(D39:D42) -> 0 | E43: =SUM(E39:E42) -> 0 | F43: =SUM(F39:F42) -> 0 | G43: =SUM(G39:G42) -> 0 | H43: =SUM(H39:H42) -> 0 | I43: =SUM(I39:I42) -> 0 | ... Q43: =SUM(Q39:Q42) -> 0
A44: 扣除1年内到期的债权投资后的账面价值
A45: 项目 | B45: 审定数 | C45: 抵消数 | D45: 汇总 | E45: 母公司审定 | F45: 子公司1 | G45: 子公司2 | H45: 子公司3 | I45: 子公司4 | J45: 子公司5 | K45: 子公司6 | L45: 子公司7 | M45: 子公司8 | N45: 子公司9 | O45: 子公司10 | P45: 子公司11 | Q45: 子公司12
A46: 项目A | B46: =D46-C46 -> 0 | C46: =C18-C39 -> 0 | D46: =SUM(E46:Q46) -> 0 | E46: =E18-E39 -> 0 | F46: =F18-F39 -> 0 | G46: =G18-G39 -> 0 | H46: =H18-H39 -> 0 | I46: =I18-I39 -> 0 | J46: =J18-J39 -> 0 | K46: =K18-K39 -> 0 | L46: =L18-L39 -> 0 | ... Q46: =Q18-Q39 -> 0
A47: 项目B | B47: =D47-C47 -> 0 | C47: =C19-C40 -> 0 | D47: =SUM(E47:Q47) -> 0 | E47: =E19-E40 -> 0 | F47: =F19-F40 -> 0 | G47: =G19-G40 -> 0 | H47: =H19-H40 -> 0 | I47: =I19-I40 -> 0 | J47: =J19-J40 -> 0 | K47: =K19-K40 -> 0 | L47: =L19-L40 -> 0 | ... Q47: =Q19-Q40 -> 0
A48: 项目C | B48: =D48-C48 -> 0 | C48: =C20-C41 -> 0 | D48: =SUM(E48:Q48) -> 0 | E48: =E20-E41 -> 0 | F48: =F20-F41 -> 0 | G48: =G20-G41 -> 0 | H48: =H20-H41 -> 0 | I48: =I20-I41 -> 0 | J48: =J20-J41 -> 0 | K48: =K20-K41 -> 0 | L48: =L20-L41 -> 0 | ... Q48: =Q20-Q41 -> 0
A49: …… | B49: =D49-C49 -> 0 | C49: =C21-C42 -> 0 | D49: =SUM(E49:Q49) -> 0 | E49: =E21-E42 -> 0 | F49: =F21-F42 -> 0 | G49: =G21-G42 -> 0 | H49: =H21-H42 -> 0 | I49: =I21-I42 -> 0 | J49: =J21-J42 -> 0 | K49: =K21-K42 -> 0 | L49: =L21-L42 -> 0 | ... Q49: =Q21-Q42 -> 0
A50: 合计 | B50: =SUM(B46:B49) -> 0 | C50: =SUM(C46:C49) -> 0 | D50: =SUM(D46:D49) -> 0 | E50: =SUM(E46:E49) -> 0 | F50: =SUM(F46:F49) -> 0 | G50: =SUM(G46:G49) -> 0 | H50: =SUM(H46:H49) -> 0 | I50: =SUM(I46:I49) -> 0 | ... Q50: =SUM(Q46:Q49) -> 0
A52: （2）重要的债权投资
A53: 债权投资项目 | B53: 面值 | C53: 票面利率 | D53: 实际利率 | E53: 到期日 | F53: 来源公司
A54: 项目A
A55: 项目B
A56: 项目C
A57: ……
A58: 合计 | B58: =SUM(B54:B57) -> 0 | C58: —— | D58: —— | E58: —— | F58: ——

Sheet 可供出售金融资产
A1: 可供出售金融资产附注 | D1: 返回Excel目录 | E1: 返回word附注
A2: 一、账面余额
A3: 项目 | B3: 审定数 | C3: 抵消数 | D3: 汇总 | E3: 母公司审定 | F3: 子公司1 | G3: 子公司2 | H3: 子公司3 | I3: 子公司4 | J3: 子公司5 | K3: 子公司6 | L3: 子公司7 | M3: 子公司8 | N3: 子公司9 | O3: 子公司10 | P3: 子公司11 | Q3: 子公司12
A4: 可供出售债务工具 | B4: =D4-C4 -> 0 | D4: =SUM(E4:Q4) -> 0 | E4: 0
A5: 可供出售权益工具 | B5: =B6+B7 -> 0 | C5: =C6+C7 -> 0 | D5: =SUM(E5:Q5) -> 0 | E5: 0 | F5: =F6+F7 -> 0 | G5: =G6+G7 -> 0 | H5: =H6+H7 -> 0 | I5: =I6+I7 -> 0 | J5: =J6+J7 -> 0 | K5: =K6+K7 -> 0 | L5: =L6+L7 -> 0 | M5: =M6+M7 -> 0 | ... Q5: =Q6+Q7 -> 0
A6: 其中：按公允价值计量 | B6: =D6-C6 -> 0 | D6: =SUM(E6:Q6) -> 0 | E6: 0
A7: 按成本计量 | B7: =D7-C7 -> 0 | D7: =SUM(E7:Q7) -> 0 | E7: 0
A8: 其他 | B8: =D8-C8 -> 0 | D8: =SUM(E8:Q8) -> 0 | E8: 0
A9: 合 计 | B9: =B4+B5+B8 -> 0 | C9: =C4+C5+C8 -> 0 | D9: =D4+D5+D8 -> 0 | E9: =E4+E5+E8 -> 0 | F9: =F4+F5+F8 -> 0 | G9: =G4+G5+G8 -> 0 | H9: =H4+H5+H8 -> 0 | I9: =I4+I5+I8 -> 0 | ... Q9: =Q4+Q5+Q8 -> 0
A11: 二、减值准备
A12: 项目 | B12: 审定数 | C12: 抵消数 | D12: 汇总 | E12: 母公司审定 | F12: 子公司1 | G12: 子公司2 | H12: 子公司3 | I12: 子公司4 | J12: 子公司5 | K12: 子公司6 | L12: 子公司7 | M12: 子公司8 | N12: 子公司9 | O12: 子公司10 | P12: 子公司11 | Q12: 子公司12
A13: 可供出售债务工具 | B13: =D13-C13 -> 0 | D13: =SUM(E13:Q13) -> 0 | E13: 0
A14: 可供出售权益工具 | B14: =B15+B16 -> 0 | C14: =C15+C16 -> 0 | D14: =SUM(E14:Q14) -> 0 | E14: 0 | F14: =F15+F16 -> 0 | G14: =G15+G16 -> 0 | H14: =H15+H16 -> 0 | I14: =I15+I16 -> 0 | J14: =J15+J16 -> 0 | K14: =K15+K16 -> 0 | L14: =L15+L16 -> 0 | M14: =M15+M16 -> 0 | ... Q14: =Q15+Q16 -> 0
A15: 其中：按公允价值计量 | B15: =D15-C15 -> 0 | D15: =SUM(E15:Q15) -> 0 | E15: 0
A16: 按成本计量 | B16: =D16-C16 -> 0 | D16: =SUM(E16:Q16) -> 0 | E16: 0
A17: 其他 | B17: =D17-C17 -> 0 | D17: =SUM(E17:Q17) -> 0 | E17: 0
A18: 合 计 | B18: =B13+B14+B17 -> 0 | C18: =C13+C14+C17 -> 0 | D18: =D13+D14+D17 -> 0 | E18: =E13+E14+E17 -> 0 | F18: =F13+F14+F17 -> 0 | G18: =G13+G14+G17 -> 0 | H18: =H13+H14+H17 -> 0 | I18: =I13+I14+I17 -> 0 | ... Q18: =Q13+Q14+Q17 -> 0
A19: 净 值 | B19: =B9-B18 -> 0 | C19: =C9-C18 -> 0 | D19: =D9-D18 -> 0 | E19: =E9-E18 -> 0 | F19: =F9-F18 -> 0 | G19: =G9-G18 -> 0 | H19: =H9-H18 -> 0 | I19: =I9-I18 -> 0 | ... Q19: =Q9-Q18 -> 0
A20: 试算表链接： | B20: 0 | D20: =SUM(E20:Q20) -> 0 | E20: 0
A21: 差异 | B21: =B19-B20 -> 0 | D21: =D19-D20 -> 0 | E21: =E19-E20 -> 0 | F21: =F19-F20 -> 0 | G21: =G19-G20 -> 0 | H21: =H19-H20 -> 0 | I21: =I19-I20 -> 0 | J21: =J19-J20 -> 0 | K21: =K19-K20 -> 0 | ... Q21: =Q19-Q20 -> 0
A22: 三、按公允价值计量的可供出售金融资产-权益工具
A23: 项目 | B23: 审定数 | C23: 抵消数 | D23: 汇总 | E23: 母公司审定 | F23: 子公司1 | G23: 子公司2 | H23: 子公司3 | I23: 子公司4 | J23: 子公司5 | K23: 子公司6 | L23: 子公司7 | M23: 子公司8 | N23: 子公司9 | O23: 子公司10 | P23: 子公司11 | Q23: 子公司12
A24: 权益工具的成本A | B24: =D24-C24 -> 0 | D24: =SUM(E24:Q24) -> 0 | E24: 0
A25: 公允价值B | B25: =D25-C25 -> 0 | D25: =SUM(E25:Q25) -> 0 | E25: 0
A26: 累计计入其他综合收益的公允价值变动金额C | B26: =D26-C26 -> 0 | D26: =SUM(E26:Q26) -> 0 | E26: 0
A27: 已计提减值金额D | B27: =D27-C27 -> 0 | D27: =SUM(E27:Q27) -> 0 | E27: 0
A29: 四、按公允价值计量的可供出售金融资产-债务工具
A30: 项目 | B30: 审定数 | C30: 抵消数 | D30: 汇总 | E30: 母公司审定 | F30: 子公司1 | G30: 子公司2 | H30: 子公司3 | I30: 子公司4 | J30: 子公司5 | K30: 子公司6 | L30: 子公司7 | M30: 子公司8 | N30: 子公司9 | O30: 子公司10 | P30: 子公司11 | Q30: 子公司12
A31: 权益工具的成本A | B31: =D31-C31 -> 0 | D31: =SUM(E31:Q31) -> 0 | E31: 0
A32: 公允价值B | B32: =D32-C32 -> 0 | D32: =SUM(E32:Q32) -> 0 | E32: 0
A33: 累计计入其他综合收益的公允价值变动金额C | B33: =D33-C33 -> 0 | D33: =SUM(E33:Q33) -> 0 | E33: 0
A34: 已计提减值金额D | B34: =D34-C34 -> 0 | D34: =SUM(E34:Q34) -> 0 | E34: 0
A35: 【提示：C+D= B-A】
A37: 五、采用成本计量的可供出售权益工具
A38: 【15号文第十九条（十一），对划分为可供出售类别且采用成本计量的权益工具投资，应分项披露相关信息。】
A39: 【按照《CAS37-金融工具列报》第六十条 活跃市场中没有报价且其公允价值无法可靠计量的权益工具投资以及与该工具挂钩的衍生工具，企业应当披露下列信息：
A40: （一）对金融工具的描述及其账面价值，以及因公允价值无法可靠计量而未披露其公允价值的事实和说明。
A41: （二）金融工具的相关市场信息。
A42: （三）企业是否有意图及如何处置这些金融工具。
A43: （四）已终止确认金融工具的事实，以及终止确认时的账面价值和形成的利得或损失。】
A44: 投资单位名称 | B44: 被投资单位 | C44: 账面余额 | G44: 减值准备 | K44: 在被投资单位持股比例(%) | L44: 本期现金红利
C45: 期初 | D45: 本期增加 | E45: 本期减少 | F45: 期末 | G45: 期初 | H45: 本期增加 | I45: 本期减少 | J45: 期末
A46: 母公司审定 | B46: 公司1 | F46: =C46+D46-E46 -> 0 | J46: =G46+H46-I46 -> 0
A47: 子公司1 | B47: 公司2 | F47: =C47+D47-E47 -> 0 | J47: =G47+H47-I47 -> 0
A48: 子公司2 | F48: =C48+D48-E48 -> 0 | J48: =G48+H48-I48 -> 0
A49: … | F49: =C49+D49-E49 -> 0 | J49: =G49+H49-I49 -> 0
F50: =C50+D50-E50 -> 0 | J50: =G50+H50-I50 -> 0
B51: 可无限量添加行 | F51: =C51+D51-E51 -> 0 | J51: =G51+H51-I51 -> 0
A52: 合 计 | C52: =SUM(C46:C51) -> 0 | D52: =SUM(D46:D51) -> 0 | E52: =SUM(E46:E51) -> 0 | F52: =C52+D52-E52 -> 0 | G52: =SUM(G46:G51) -> 0 | H52: =SUM(H46:H51) -> 0 | I52: =SUM(I46:I51) -> 0 | J52: =G52+H52-I52 -> 0 | K52: -- | L52: =SUM(L46:L51) -> 0
A53: 说明：按被投资单位逐项描述，说明因公允价值无法可靠计量而未披露其公允价值的事实和说明；相关市场信息；企业是否有意图及如何处置这些金融工具；已终止确认的事实，以及终止确认时的账面价值和形成的利得或损失（如，当期处置对损益的影响）。
A56: 六、报告期内可供出售金融资产减值的变动情况-权益工具
A57: 项目 | B57: 审定数 | C57: 抵消数 | D57: 汇总 | E57: 母公司审定 | F57: 子公司1 | G57: 子公司2 | H57: 子公司3 | I57: 子公司4 | J57: 子公司5 | K57: 子公司6 | L57: 子公司7 | M57: 子公司8 | N57: 子公司9 | O57: 子公司10 | P57: 子公司11 | Q57: 子公司12
A58: 期初已计提减值金额 | B58: =D58-C58 -> 0 | D58: =SUM(E58:Q58) -> 0 | E58: 0
A59: 本年计提 | B59: =D59-C59 -> 0 | D59: =SUM(E59:Q59) -> 0 | E59: 0
A60: 其中：从其他综合收益转入 | B60: =D60-C60 -> 0 | D60: =SUM(E60:Q60) -> 0 | E60: 0
A61: 本年减少 | B61: =D61-C61 -> 0 | D61: =SUM(E61:Q61) -> 0 | E61: 0
A62: 其中：期后公允价值回升转回 | B62: —— | D62: —— | E62: —— | F62: —— | G62: —— | H62: —— | I62: —— | J62: —— | K62: —— | L62: —— | M62: —— | N62: —— | O62: —— | P62: —— | Q62: ——
A63: 期末已计提减值金额 | B63: =B58+B59-B61 -> 0 | C63: =C58+C59-C61 -> 0 | D63: =SUM(E63:Q63) -> 0 | E63: =E58+E59-E61 -> 0 | F63: =F58+F59-F61 -> 0 | G63: =G58+G59-G61 -> 0 | H63: =H58+H59-H61 -> 0 | I63: =I58+I59-I61 -> 0 | J63: =J58+J59-J61 -> 0 | K63: =K58+K59-K61 -> 0 | L63: =L58+L59-L61 -> 0 | ... Q63: =Q58+Q59-Q61 -> 0
A65: 七、报告期内可供出售金融资产减值的变动情况-债务工具
A66: 项目 | B66: 审定数 | C66: 抵消数 | D66: 汇总 | E66: 母公司审定 | F66: 子公司1 | G66: 子公司2 | H66: 子公司3 | I66: 子公司4 | J66: 子公司5 | K66: 子公司6 | L66: 子公司7 | M66: 子公司8 | N66: 子公司9 | O66: 子公司10 | P66: 子公司11 | Q66: 子公司12
A67: 期初已计提减值金额 | B67: =D67-C67 -> 0 | D67: =SUM(E67:Q67) -> 0 | E67: 0
A68: 本年计提 | B68: =D68-C68 -> 0 | D68: =SUM(E68:Q68) -> 0 | E68: 0
A69: 其中：从其他综合收益转入 | B69: =D69-C69 -> 0 | D69: =SUM(E69:Q69) -> 0 | E69: 0
A70: 本年减少 | B70: =D70-C70 -> 0 | D70: =SUM(E70:Q70) -> 0 | E70: 0
A71: 其中：期后公允价值回升转回 | B71: =D71-C71 -> 0 | D71: =SUM(E71:Q71) -> 0 | E71: 0
A72: 期末已计提减值金额 | B72: =B67+B68-B70 -> 0 | C72: =C67+C68-C70 -> 0 | D72: =SUM(E72:Q72) -> 0 | E72: =E67+E68-E70 -> 0 | F72: =F67+F68-F70 -> 0 | G72: =G67+G68-G70 -> 0 | H72: =H67+H68-H70 -> 0 | I72: =I67+I68-I70 -> 0 | J72: =J67+J68-J70 -> 0 | K72: =K67+K68-K70 -> 0 | L72: =L67+L68-L70 -> 0 | ... Q72: =Q67+Q68-Q70 -> 0
A75: 八、可供出售权益工具期末公允价值大幅下跌或持续下跌相关说明：
A76: 投资单位名称 | B76: 可供出售权益工具项目 | C76: 投资成本 | D76: 期末公允价值 | E76: 公允价值相对于成本的下跌幅度（%） | F76: 持续下跌时间（个月） | G76: 已计提减值金额 | H76: 未计提减值原因
A77: 母公司 | B77: 可无限量添加行
A78: 子公司1
A79: 子公司2
A80: …
A82: 合 计 | C82: =SUM(C77:C81) -> 0 | D82: =SUM(D77:D81) -> 0 | G82: =SUM(G77:G81) -> 0 | H82: --
A84: 说明：（对于期末公允价值相对于成本的下跌幅度已达到或超过50%，或者持续下跌时间已达到或超过12个月，尚未根据成本与期末公允价值差额计提减值的可供出售权益工具，公司应详细披露各项投资的成本和公允价值的金额、公允价值相对于成本的下跌幅度、持续下跌时间、已计提减值金额，以及未根据成本与期末公允价值的差额计提减值的理由。）

Sheet 其他债权投资
A1: 其他债权投资附注 | D1: 返回Excel目录 | E1: 返回word附注
A2: 一、期末账面价值
A3: 项目 | B3: 审定数 | C3: 抵消数 | D3: 汇总 | E3: 母公司审定 | F3: 子公司1 | G3: 子公司2 | H3: 子公司3 | I3: 子公司4 | J3: 子公司5 | K3: 子公司6 | L3: 子公司7 | M3: 子公司8 | N3: 子公司9 | O3: 子公司10 | P3: 子公司11 | Q3: 子公司12
A4: 项目A | B4: =D4-C4 -> 0 | D4: =SUM(E4:Q4) -> 0 | E4: 0
A5: 项目B | B5: =D5-C5 -> 0 | D5: =SUM(E5:Q5) -> 0 | E5: 0
A6: 项目C | B6: =D6-C6 -> 0 | D6: =SUM(E6:Q6) -> 0 | E6: 0
A7: …… | B7: =D7-C7 -> 0 | D7: =SUM(E7:Q7) -> 0 | E7: 0
A8: 合计 | B8: =SUM(B4:B7) -> 0 | C8: =SUM(C4:C7) -> 0 | D8: =SUM(D4:D7) -> 0 | E8: =SUM(E4:E7) -> 0 | F8: =SUM(F4:F7) -> 0 | G8: =SUM(G4:G7) -> 0 | H8: =SUM(H4:H7) -> 0 | I8: =SUM(I4:I7) -> 0 | ... Q8: =SUM(Q4:Q7) -> 0
A9: 减：1年内到期的债权投资
A10: 项目 | B10: 审定数 | C10: 抵消数 | D10: 汇总 | E10: 母公司审定 | F10: 子公司1 | G10: 子公司2 | H10: 子公司3 | I10: 子公司4 | J10: 子公司5 | K10: 子公司6 | L10: 子公司7 | M10: 子公司8 | N10: 子公司9 | O10: 子公司10 | P10: 子公司11 | Q10: 子公司12
A11: 项目A | B11: =D11-C11 -> 0 | D11: =SUM(E11:Q11) -> 0 | E11: 0
A12: 项目B | B12: =D12-C12 -> 0 | D12: =SUM(E12:Q12) -> 0 | E12: 0
A13: 项目C | B13: =D13-C13 -> 0 | D13: =SUM(E13:Q13) -> 0 | E13: 0
A14: …… | B14: =D14-C14 -> 0 | D14: =SUM(E14:Q14) -> 0 | E14: 0
A15: 合计 | B15: =SUM(B11:B14) -> 0 | C15: =SUM(C11:C14) -> 0 | D15: =SUM(D11:D14) -> 0 | E15: =SUM(E11:E14) -> 0 | F15: =SUM(F11:F14) -> 0 | G15: =SUM(G11:G14) -> 0 | H15: =SUM(H11:H14) -> 0 | I15: =SUM(I11:I14) -> 0 | ... Q15: =SUM(Q11:Q14) -> 0
A16: 合计
A17: 项目 | B17: 审定数 | C17: 抵消数 | D17: 汇总 | E17: 母公司审定 | F17: 子公司1 | G17: 子公司2 | H17: 子公司3 | I17: 子公司4 | J17: 子公司5 | K17: 子公司6 | L17: 子公司7 | M17: 子公司8 | N17: 子公司9 | O17: 子公司10 | P17: 子公司11 | Q17: 子公司12
A18: 项目A | B18: =D18-C18 -> 0 | C18: =C4-C11 -> 0 | D18: =SUM(E18:Q18) -> 0 | E18: =E4-E11 -> 0 | F18: =F4-F11 -> 0 | G18: =G4-G11 -> 0 | H18: =H4-H11 -> 0 | I18: =I4-I11 -> 0 | J18: =J4-J11 -> 0 | K18: =K4-K11 -> 0 | L18: =L4-L11 -> 0 | ... Q18: =Q4-Q11 -> 0
A19: 项目B | B19: =D19-C19 -> 0 | C19: =C5-C12 -> 0 | D19: =SUM(E19:Q19) -> 0 | E19: =E5-E12 -> 0 | F19: =F5-F12 -> 0 | G19: =G5-G12 -> 0 | H19: =H5-H12 -> 0 | I19: =I5-I12 -> 0 | J19: =J5-J12 -> 0 | K19: =K5-K12 -> 0 | L19: =L5-L12 -> 0 | ... Q19: =Q5-Q12 -> 0
A20: 项目C | B20: =D20-C20 -> 0 | C20: =C6-C13 -> 0 | D20: =SUM(E20:Q20) -> 0 | E20: =E6-E13 -> 0 | F20: =F6-F13 -> 0 | G20: =G6-G13 -> 0 | H20: =H6-H13 -> 0 | I20: =I6-I13 -> 0 | J20: =J6-J13 -> 0 | K20: =K6-K13 -> 0 | L20: =L6-L13 -> 0 | ... Q20: =Q6-Q13 -> 0
A21: …… | B21: =D21-C21 -> 0 | C21: =C7-C14 -> 0 | D21: =SUM(E21:Q21) -> 0 | E21: =E7-E14 -> 0 | F21: =F7-F14 -> 0 | G21: =G7-G14 -> 0 | H21: =H7-H14 -> 0 | I21: =I7-I14 -> 0 | J21: =J7-J14 -> 0 | K21: =K7-K14 -> 0 | L21: =L7-L14 -> 0 | ... Q21: =Q7-Q14 -> 0
A22: 合计 | B22: =SUM(B18:B21) -> 0 | C22: =SUM(C18:C21) -> 0 | D22: =SUM(D18:D21) -> 0 | E22: =SUM(E18:E21) -> 0 | F22: =SUM(F18:F21) -> 0 | G22: =SUM(G18:G21) -> 0 | H22: =SUM(H18:H21) -> 0 | I22: =SUM(I18:I21) -> 0 | ... Q22: =SUM(Q18:Q21) -> 0

Sheet 持有至到期投资
A1: 持有至到期投资附注 | D1: 返回Excel目录 | E1: 返回word附注
A2: 一、账面余额
A3: 项目 | B3: 审定数 | C3: 抵消数 | D3: 汇总 | E3: 母公司审定 | F3: 子公司1 | G3: 子公司2 | H3: 子公司3 | I3: 子公司4 | J3: 子公司5 | K3: 子公司6 | L3: 子公司7 | M3: 子公司8 | N3: 子公司9 | O3: 子公司10 | P3: 子公司11 | Q3: 子公司12
B4: =D4-C4 -> 0 | D4: =SUM(E4:Q4) -> 0 | E4: 0
B5: =D5-C5 -> 0 | D5: =SUM(E5:Q5) -> 0 | E5: 0
B6: =D6-C6 -> 0 | D6: =SUM(E6:Q6) -> 0 | E6: 0
B7: =D7-C7 -> 0 | D7: =SUM(E7:Q7) -> 0 | E7: 0
B8: =D8-C8 -> 0 | D8: =SUM(E8:Q8) -> 0 | E8: 0
B9: =D9-C9 -> 0 | D9: =SUM(E9:Q9) -> 0 | E9: 0
A10: 小 计 | B10: =SUM(B4:B9) -> 0 | C10: =SUM(C4:C9) -> 0 | D10: =SUM(D4:D9) -> 0 | E10: =SUM(E4:E9) -> 0 | F10: =SUM(F4:F9) -> 0 | G10: =SUM(G4:G9) -> 0 | H10: =SUM(H4:H9) -> 0 | I10: =SUM(I4:I9) -> 0 | ... Q10: =SUM(Q4:Q9) -> 0
A11: 减：1年内到期的持有至到期投资 | B11: =D11-C11 -> 0 | D11: =SUM(E11:Q11) -> 0
A12: 合 计 | B12: =B10-B11 -> 0 | C12: =C10-C11 -> 0 | D12: =D10-D11 -> 0 | E12: =E10-E11 -> 0 | F12: =F10-F11 -> 0 | G12: =G10-G11 -> 0 | H12: =H10-H11 -> 0 | I12: =I10-I11 -> 0 | ... Q12: =Q10-Q11 -> 0
A14: 二、减值准备
A15: 项目 | B15: 审定数 | C15: 抵消数 | D15: 汇总 | E15: 母公司审定 | F15: 子公司1 | G15: 子公司2 | H15: 子公司3 | I15: 子公司4 | J15: 子公司5 | K15: 子公司6 | L15: 子公司7 | M15: 子公司8 | N15: 子公司9 | O15: 子公司10 | P15: 子公司11 | Q15: 子公司12
A16: =A4 -> 0 | B16: =D16-C16 -> 0 | D16: =SUM(E16:Q16) -> 0 | E16: 0
A17: =A5 -> 0 | B17: =D17-C17 -> 0 | D17: =SUM(E17:Q17) -> 0 | E17: 0
A18: =A6 -> 0 | B18: =D18-C18 -> 0 | D18: =SUM(E18:Q18) -> 0 | E18: 0
A19: =A7 -> 0 | B19: =D19-C19 -> 0 | D19: =SUM(E19:Q19) -> 0 | E19: 0
A20: =A8 -> 0 | B20: =D20-C20 -> 0 | D20: =SUM(E20:Q20) -> 0 | E20: 0
A21: =A9 -> 0 | B21: =D21-C21 -> 0 | D21: =SUM(E21:Q21) -> 0 | E21: 0
A22: =A10 -> 小 计 | B22: =SUM(B16:B21) -> 0 | C22: =SUM(C16:C21) -> 0 | D22: =SUM(D16:D21) -> 0 | E22: =SUM(E16:E21) -> 0 | F22: =SUM(F16:F21) -> 0 | G22: =SUM(G16:G21) -> 0 | H22: =SUM(H16:H21) -> 0 | I22: =SUM(I16:I21) -> 0 | ... Q22: =SUM(Q16:Q21) -> 0
A23: =A11 -> 减：1年内到期的持有至到期投资 | B23: =D23-C23 -> 0 | D23: =SUM(E23:Q23) -> 0 | E23: 0
A24: 合 计 | B24: =B22-B23 -> 0 | C24: =C22-C23 -> 0 | D24: =D22-D23 -> 0 | E24: =E22-E23 -> 0 | F24: =F22-F23 -> 0 | G24: =G22-G23 -> 0 | H24: =H22-H23 -> 0 | I24: =I22-I23 -> 0 | ... Q24: =Q22-Q23 -> 0
A25: 净值 | B25: =B12-B24 -> 0 | C25: =C12-C24 -> 0 | D25: =D12-D24 -> 0 | E25: =E12-E24 -> 0 | F25: =F12-F24 -> 0 | G25: =G12-G24 -> 0 | H25: =H12-H24 -> 0 | I25: =I12-I24 -> 0 | ... Q25: =Q12-Q24 -> 0
A26: 试算表链接： | B26: 0 | D26: =SUM(E26:Q26) -> 0 | E26: 0
A27: 差异 | B27: =B25-B26 -> 0 | D27: =D25-D26 -> 0 | E27: =E25-E26 -> 0 | F27: =F25-F26 -> 0 | G27: =G25-G26 -> 0 | H27: =H25-H26 -> 0 | I27: =I25-I26 -> 0 | J27: =J25-J26 -> 0 | K27: =K25-K26 -> 0 | ... Q27: =Q25-Q26 -> 0
A29: 三、重要的持有至到期投资
A30: 投资单位名称 | B30: 债券项目 | C30: 面值 | D30: 票面利率 | E30: 实际利率 | F30: 到期日
A31: 母公司
A32: 子公司1
A33: 子公司2
A34: 子公司2
A35: 合 计 | C35: =SUM(C31:C34) -> 0 | D35: -- | E35: -- | F35: --
A37: （对于重要的持有至到期投资，应分别列示其面值、票面利率、实际利率、到期日。）
A39: 四、持有至到期投资重分类情况
A40: （本期存在重分类的，应披露重分类的原因和具体情况。）
A41: 由于XX原因，本期将持有至到期投资重分类为可供出售金融资产，重分类的金额XX元，该金额占重分类前持有至到期投资总额的比例XX%。

Sheet 长期应收款
A1: 长期应收款附注 | D1: 返回Excel目录 | E1: 返回word附注
A2: 一、账面余额
A3: 项目 | B3: 审定数 | C3: 抵消数 | D3: 汇总 | E3: 母公司审定 | F3: 子公司1 | G3: 子公司2 | H3: 子公司3 | I3: 子公司4 | J3: 子公司5 | K3: 子公司6 | L3: 子公司7 | M3: 子公司8 | N3: 子公司9 | O3: 子公司10 | P3: 子公司11 | Q3: 子公司12
A4: 融资租赁款 | B4: =D4-C4 -> 0 | D4: =SUM(E4:Q4) -> 0 | E4: 0
A5: 其中：未实现融资收益 | B5: =D5-C5 -> 0 | D5: =SUM(E5:Q5) -> 0 | E5: 0
A6: 分期收款销售商品 | B6: =D6-C6 -> 0 | D6: =SUM(E6:Q6) -> 0 | E6: 0
A7: 其中：未实现融资收益 | B7: =D7-C7 -> 0 | D7: =SUM(E7:Q7) -> 0 | E7: 0
A8: 分期收款提供劳务 | B8: =D8-C8 -> 0 | D8: =SUM(E8:Q8) -> 0 | E8: 0
A9: 其中：未实现融资收益 | B9: =D9-C9 -> 0 | D9: =SUM(E9:Q9) -> 0 | E9: 0
B10: =D10-C10 -> 0 | D10: =SUM(E10:Q10) -> 0 | E10: 0
A11: 可无限量添加行 | B11: =D11-C11 -> 0 | D11: =SUM(E11:Q11) -> 0 | E11: 0
A12: 小 计 | B12: =B4+B6+B8+B10 -> 0 | C12: =C4+C6+C8+C10 -> 0 | D12: =D4+D6+D8+D10 -> 0 | E12: =E4+E6+E8+E10 -> 0 | F12: =F4+F6+F8+F10 -> 0 | G12: =G4+G6+G8+G10 -> 0 | H12: =H4+H6+H8+H10 -> 0 | I12: =I4+I6+I8+I10 -> 0 | ... Q12: =Q4+Q6+Q8+Q10 -> 0
A13: 减：1年内到期的长期应收款 | B13: =D13-C13 -> 0 | D13: =SUM(E13:Q13) -> 0 | E13: 0
A14: 合 计 | B14: =B12-B13 -> 0 | C14: =C12-C13 -> 0 | D14: =D12-D13 -> 0 | E14: =E12-E13 -> 0 | F14: =F12-F13 -> 0 | G14: =G12-G13 -> 0 | H14: =H12-H13 -> 0 | I14: =I12-I13 -> 0 | ... Q14: =Q12-Q13 -> 0
A16: 二、坏账准备
A17: 项目 | B17: 审定数 | C17: 抵消数 | D17: 汇总 | E17: 母公司审定 | F17: 子公司1 | G17: 子公司2 | H17: 子公司3 | I17: 子公司4 | J17: 子公司5 | K17: 子公司6 | L17: 子公司7 | M17: 子公司8 | N17: 子公司9 | O17: 子公司10 | P17: 子公司11 | Q17: 子公司12
A18: =A4 -> 融资租赁款 | B18: =D18-C18 -> 0 | D18: =SUM(E18:Q18) -> 0 | E18: 0
A19: =A5 -> 其中：未实现融资收益 | B19: =D19-C19 -> 0 | D19: =SUM(E19:Q19) -> 0 | E19: 0
A20: =A6 -> 分期收款销售商品 | B20: =D20-C20 -> 0 | D20: =SUM(E20:Q20) -> 0 | E20: 0
A21: =A7 -> 其中：未实现融资收益 | B21: =D21-C21 -> 0 | D21: =SUM(E21:Q21) -> 0 | E21: 0
A22: =A8 -> 分期收款提供劳务 | B22: =D22-C22 -> 0 | D22: =SUM(E22:Q22) -> 0 | E22: 0
A23: =A9 -> 其中：未实现融资收益 | B23: =D23-C23 -> 0 | D23: =SUM(E23:Q23) -> 0 | E23: 0
A24: =A10 -> 0 | B24: =D24-C24 -> 0 | D24: =SUM(E24:Q24) -> 0 | E24: 0
A25: =A11 -> 可无限量添加行 | B25: =D25-C25 -> 0 | D25: =SUM(E25:Q25) -> 0 | E25: 0
A26: =A12 -> 小 计 | B26: =B18+B20+B22+B24 -> 0 | C26: =C18+C20+C22+C24 -> 0 | D26: =D18+D20+D22+D24 -> 0 | E26: =E18+E20+E22+E24 -> 0 | F26: =F18+F20+F22+F24 -> 0 | G26: =G18+G20+G22+G24 -> 0 | H26: =H18+H20+H22+H24 -> 0 | I26: =I18+I20+I22+I24 -> 0 | ... Q26: =Q18+Q20+Q22+Q24 -> 0
A27: =A13 -> 减：1年内到期的长期应收款 | B27: =D27-C27 -> 0 | D27: =SUM(E27:Q27) -> 0 | E27: 0
A28: 合 计 | B28: =B26-B27 -> 0 | C28: =C26-C27 -> 0 | D28: =D26-D27 -> 0 | E28: =E26-E27 -> 0 | F28: =F26-F27 -> 0 | G28: =G26-G27 -> 0 | H28: =H26-H27 -> 0 | I28: =I26-I27 -> 0 | ... Q28: =Q26-Q27 -> 0
A29: 净值 | B29: =B14-B28 -> 0 | C29: =C14-C28 -> 0 | D29: =D14-D28 -> 0 | E29: =E14-E28 -> 0 | F29: =F14-F28 -> 0 | G29: =G14-G28 -> 0 | H29: =H14-H28 -> 0 | I29: =I14-I28 -> 0 | ... Q29: =Q14-Q28 -> 0
A30: 试算表链接： | B30: 0 | D30: =SUM(E30:Q30) -> 0 | E30: 0
A31: 差异 | B31: =B29-B30 -> 0 | D31: =D29-D30 -> 0 | E31: =E29-E30 -> 0 | F31: =F29-F30 -> 0 | G31: =G29-G30 -> 0 | H31: =H29-H30 -> 0 | I31: =I29-I30 -> 0 | J31: =J29-J30 -> 0 | K31: =K29-K30 -> 0 | ... Q31: =Q29-Q30 -> 0
A32: 说明：
A33: 三、长期应收款逾期情况分析：
A34: 项目 | B34: 审定数 | C34: 抵消数 | D34: 汇总 | E34: 母公司审定 | F34: 子公司1 | G34: 子公司2 | H34: 子公司3 | I34: 子公司4 | J34: 子公司5 | K34: 子公司6 | L34: 子公司7 | M34: 子公司8 | N34: 子公司9 | O34: 子公司10 | P34: 子公司11 | Q34: 子公司12
A35: 1年以内 | B35: =D35-C35 -> 0 | D35: =SUM(E35:Q35) -> 0 | E35: 0
A36: 1至2年 | B36: =D36-C36 -> 0 | D36: =SUM(E36:Q36) -> 0 | E36: 0
A37: 2至3年 | B37: =D37-C37 -> 0 | D37: =SUM(E37:Q37) -> 0 | E37: 0
A38: 3年以上 | B38: =D38-C38 -> 0 | D38: =SUM(E38:Q38) -> 0 | E38: 0
A39: 合 计 | B39: =SUM(B35:B38) -> 0 | D39: =SUM(D35:D38) -> 0 | E39: =SUM(E35:E38) -> 0 | F39: =SUM(F35:F38) -> 0 | G39: =SUM(G35:G38) -> 0 | H39: =SUM(H35:H38) -> 0 | I39: =SUM(I35:I38) -> 0 | J39: =SUM(J35:J38) -> 0 | K39: =SUM(K35:K38) -> 0 | ... Q39: =SUM(Q35:Q38) -> 0
A40: 说明：（逾期客户的名称、逾期年限、逾期原因等）
A41: 四、终止确认的长期应收款情况
A42: （因资产转移而终止确认的长期应收款，列示资产转移的方式、终止确认的长期应收款金额，以及与终止确认相关的利得或损失。）
A43: 债权单位 | B43: 项 目 | C43: 转移方式 | D43: 终止确认金额 | E43: 与终止确认相关的利得或损失
A47: 合 计 | D47: =SUM(D44:D46) -> 0 | E47: --
A48: 说明：
A49: 五、转移长期应收款且继续涉入形成的资产、负债的金额
A50: （转移长期应收款且继续涉入的，应披露资产转移方式、分项列示继续涉入形成的资产、负债的金额。）
A51: 项目 | B51: 审定数 | C51: 抵消数 | D51: 汇总 | E51: 母公司审定 | F51: 子公司1 | G51: 子公司2 | H51: 子公司3 | I51: 子公司4 | J51: 子公司5 | K51: 子公司6 | L51: 子公司7 | M51: 子公司8 | N51: 子公司9 | O51: 子公司10 | P51: 子公司11 | Q51: 子公司12
A52: 资产：
B53: =D53-C53 -> 0 | D53: =SUM(E53:Q53) -> 0 | E53: 0
B54: =D54-C54 -> 0 | D54: =SUM(E54:Q54) -> 0 | E54: 0
A55: 资产小计 | B55: =SUM(B53:B54) -> 0 | C55: =SUM(C53:C54) -> 0 | D55: =SUM(E55:Q55) -> 0 | E55: =SUM(E53:E54) -> 0 | F55: =SUM(F53:F54) -> 0 | G55: =SUM(G53:G54) -> 0 | H55: =SUM(H53:H54) -> 0 | I55: =SUM(I53:I54) -> 0 | J55: =SUM(J53:J54) -> 0 | K55: =SUM(K53:K54) -> 0 | L55: =SUM(L53:L54) -> 0 | ... Q55: =SUM(Q53:Q54) -> 0
A56: 负债：
B57: =D57-C57 -> 0 | D57: =SUM(E57:Q57) -> 0 | E57: 0
B58: =D58-C58 -> 0 | D58: =SUM(E58:Q58) -> 0 | E58: 0
A59: 负债小计 | B59: =SUM(B57:B58) -> 0 | C59: =SUM(C57:C58) -> 0 | D59: =SUM(E59:Q59) -> 0 | E59: =SUM(E57:E58) -> 0 | F59: =SUM(F57:F58) -> 0 | G59: =SUM(G57:G58) -> 0 | H59: =SUM(H57:H58) -> 0 | I59: =SUM(I57:I58) -> 0 | J59: =SUM(J57:J58) -> 0 | K59: =SUM(K57:K58) -> 0 | L59: =SUM(L57:L58) -> 0 | ... Q59: =SUM(Q57:Q58) -> 0
A60: 说明：
A61: （资产转移方式；未全部终止确认的被转移金融资产与相关负债之间的关系，已终止确认的金融资产继续涉入的性质及相关风险的信息。）

Sheet 设定受益计划净资产
A1: 设定受益计划净资产附注 | D1: 返回Excel目录 | E1: 返回word附注
A3: 项目 | B3: 审定数 | C3: 抵消数 | D3: 汇总 | E3: 母公司审定 | F3: 子公司1 | G3: 子公司2 | H3: 子公司3 | I3: 子公司4 | J3: 子公司5 | K3: 子公司6 | L3: 子公司7 | M3: 子公司8 | N3: 子公司9 | O3: 子公司10 | P3: 子公司11 | Q3: 子公司12
A4: 设定受益计划净资产 | B4: =D4-C4 -> 0 | D4: =SUM(E4:Q4) -> 0 | E4: 0
B5: =D5-C5 -> 0 | D5: =SUM(E5:Q5) -> 0 | E5: 0
A6: 符合设定受益计划条件的其他长期职工福利的净资产（不适用删除） | B6: =D6-C6 -> 0 | D6: =SUM(E6:Q6) -> 0 | E6: 0
A7: …… | B7: =D7-C7 -> 0 | D7: =SUM(E7:Q7) -> 0 | E7: 0
A8: 合计 | B8: =SUM(B4:B7) -> 0 | C8: =SUM(C4:C7) -> 0 | D8: =SUM(D4:D7) -> 0 | E8: =SUM(E4:E7) -> 0 | F8: =SUM(F4:F7) -> 0 | G8: =SUM(G4:G7) -> 0 | H8: =SUM(H4:H7) -> 0 | I8: =SUM(I4:I7) -> 0 | ... Q8: =SUM(Q4:Q7) -> 0
A9: 试算表链接： | B9: 0
A10: 差异 | B10: =B8-B9 -> 0

Sheet 长期股权投资
A1: 长期股权投资附注汇总 | D1: 返回Excel目录 | E1: 返回word附注
A2: 项目 | B2: 审定数 | C2: 抵消数 | D2: 汇总 | E2: 母公司审定 | F2: 子公司1 | G2: 子公司2 | H2: 子公司3 | I2: 子公司4 | J2: 子公司5 | K2: 子公司6 | L2: 子公司7 | M2: 子公司8 | N2: 子公司9 | O2: 子公司10 | P2: 子公司11 | Q2: 子公司12
A3: 对联营企业投资 | B3: =D3-C3 -> 0 | D3: =SUM(E3:Q3) -> 0 | E3: 0
A4: 对合营企业投资 | B4: =D4-C4 -> 0 | D4: =SUM(E4:Q4) -> 0 | E4: 0
A5: 减去：长期股权投资减值准备 | E5: 0
A6: 合计 | B6: =SUM(B3:B4)-B5 -> 0 | C6: =SUM(C3:C4)-C5 -> 0 | D6: =SUM(D3:D4)-D5 -> 0 | E6: =SUM(E3:E4)-E5 -> 0 | F6: =SUM(F3:F4)-F5 -> 0 | G6: =SUM(G3:G4)-G5 -> 0 | H6: =SUM(H3:H4)-H5 -> 0 | I6: =SUM(I3:I4)-I5 -> 0 | ... Q6: =SUM(Q3:Q4)-Q5 -> 0
A7: 试算表链接： | B7: 0 | D7: =SUM(E7:Q7) -> 0 | E7: 0
A8: 差异 | B8: =B6-B7 -> 0 | D8: =D6-D7 -> 0 | E8: =E6-E7 -> 0 | F8: =F6-F7 -> 0 | G8: =G6-G7 -> 0 | H8: =H6-H7 -> 0 | I8: =I6-I7 -> 0 | J8: =J6-J7 -> 0 | K8: =K6-K7 -> 0 | ... Q8: =Q6-Q7 -> 0
A10: 被投资单位 | B10: 期初余额 | C10: 本期增减变动 | K10: 期末余额 | L10: 减值准备期末余额
C11: 追加投资 | D11: 减少投资 | E11: 权益法下确认的投资损益 | F11: 其他综合收益调整 | G11: 其他权益变动 | H11: 宣告发放现金股利或利润 | I11: 计提减值准备 | J11: 其他
A12: ①合营企业
A13: … | K13: =B13+C13-D13+E13+F13+G13-H13-I13+J13 -> 0
K14: =B14+C14-D14+E14+F14+G14-H14-I14+J14 -> 0
A15: 小计 | B15: =SUM(B12:B14) -> 0 | C15: =SUM(C12:C14) -> 0 | D15: =SUM(D12:D14) -> 0 | E15: =SUM(E12:E14) -> 0 | F15: =SUM(F12:F14) -> 0 | G15: =SUM(G12:G14) -> 0 | H15: =SUM(H12:H14) -> 0 | I15: =SUM(I12:I14) -> 0 | ... L15: =SUM(L12:L14) -> 0
A16: ②联营企业
A17: … | K17: =B17+C17-D17+E17+F17+G17-H17-I17+J17 -> 0
K18: =B18+C18-D18+E18+F18+G18-H18-I18+J18 -> 0
K19: =B19+C19-D19+E19+F19+G19-H19-I19+J19 -> 0
K20: =B20+C20-D20+E20+F20+G20-H20-I20+J20 -> 0
K21: =B21+C21-D21+E21+F21+G21-H21-I21+J21 -> 0
A22: 小计 | B22: =SUM(B16:B21) -> 0 | C22: =SUM(C16:C21) -> 0 | D22: =SUM(D16:D21) -> 0 | E22: =SUM(E16:E21) -> 0 | F22: =SUM(F16:F21) -> 0 | G22: =SUM(G16:G21) -> 0 | H22: =SUM(H16:H21) -> 0 | I22: =SUM(I16:I21) -> 0 | ... L22: =SUM(L16:L21) -> 0
A23: 合 计 | B23: =B15+B22 -> 0 | C23: =C15+C22 -> 0 | D23: =D15+D22 -> 0 | E23: =E15+E22 -> 0 | F23: =F15+F22 -> 0 | G23: =G15+G22 -> 0 | H23: =H15+H22 -> 0 | I23: =I15+I22 -> 0 | ... L23: =L15+L22 -> 0

Sheet 其他权益工具投资
A1: 其他权益工具投资附注 | D1: 返回Excel目录 | E1: 返回word附注
A3: 项目 | B3: 审定数 | C3: 抵消数 | D3: 汇总 | E3: 母公司审定 | F3: 子公司1 | G3: 子公司2 | H3: 子公司3 | I3: 子公司4 | J3: 子公司5 | K3: 子公司6 | L3: 子公司7 | M3: 子公司8 | N3: 子公司9 | O3: 子公司10 | P3: 子公司11 | Q3: 子公司12
A4: 项目A | B4: =D4-C4 -> 0 | D4: =SUM(E4:Q4) -> 0 | E4: 0
A5: 项目B | B5: =D5-C5 -> 0 | D5: =SUM(E5:Q5) -> 0 | E5: 0
A6: 项目C | B6: =D6-C6 -> 0 | D6: =SUM(E6:Q6) -> 0 | E6: 0
A7: …… | B7: =D7-C7 -> 0 | D7: =SUM(E7:Q7) -> 0 | E7: 0
A8: 合计 | B8: =SUM(B4:B7) -> 0 | C8: =SUM(C4:C7) -> 0 | D8: =SUM(D4:D7) -> 0 | E8: =SUM(E4:E7) -> 0 | F8: =SUM(F4:F7) -> 0 | G8: =SUM(G4:G7) -> 0 | H8: =SUM(H4:H7) -> 0 | I8: =SUM(I4:I7) -> 0 | ... Q8: =SUM(Q4:Q7) -> 0

Sheet 其他非流动金融资产
A1: 其他非流动金融资产附注 | D1: 返回Excel目录 | E1: 返回word附注
A3: 项目 | B3: 审定数 | C3: 抵消数 | D3: 汇总 | E3: 母公司审定 | F3: 子公司1 | G3: 子公司2 | H3: 子公司3 | I3: 子公司4 | J3: 子公司5 | K3: 子公司6 | L3: 子公司7 | M3: 子公司8 | N3: 子公司9 | O3: 子公司10 | P3: 子公司11 | Q3: 子公司12
A4: 项目A | B4: =D4-C4 -> 0 | D4: =SUM(E4:Q4) -> 0 | E4: 0
A5: 项目B | B5: =D5-C5 -> 0 | D5: =SUM(E5:Q5) -> 0 | E5: 0
A6: 项目C | B6: =D6-C6 -> 0 | D6: =SUM(E6:Q6) -> 0 | E6: 0
A7: …… | B7: =D7-C7 -> 0 | D7: =SUM(E7:Q7) -> 0 | E7: 0
A8: 合计 | B8: =SUM(B4:B7) -> 0 | C8: =SUM(C4:C7) -> 0 | D8: =SUM(D4:D7) -> 0 | E8: =SUM(E4:E7) -> 0 | F8: =SUM(F4:F7) -> 0 | G8: =SUM(G4:G7) -> 0 | H8: =SUM(H4:H7) -> 0 | I8: =SUM(I4:I7) -> 0 | ... Q8: =SUM(Q4:Q7) -> 0

Sheet 投资性房地产（成本模式）
A1: 投资性房地产附注汇总 | D1: 返回Excel目录 | E1: 返回word附注
A2: （1）按成本计量的投资性房地产
A3: 投资性房地产原值
A4: 1、投资性房地产原值期初数
A5: 项目 | B5: 审定数 | C5: 抵消数 | D5: 汇总 | E5: 母公司审定 | F5: 子公司1 | G5: 子公司2 | H5: 子公司3 | I5: 子公司4 | J5: 子公司5 | K5: 子公司6 | L5: 子公司7 | M5: 子公司8 | N5: 子公司9 | O5: 子公司10 | P5: 子公司11 | Q5: 子公司12
A6: 房屋、建筑物 | B6: =D6-C6 -> 0 | D6: =SUM(E6:Q6) -> 0 | E6: 0
A7: 土地使用权 | B7: =D7-C7 -> 0 | D7: =SUM(E7:Q7) -> 0 | E7: 0
A8: 在建工程 | B8: =D8-C8 -> 0 | D8: =SUM(E8:Q8) -> 0 | E8: 0
A9: 合计 | B9: =SUM(B6:B8) -> 0 | C9: =SUM(C6:C8) -> 0 | D9: =SUM(E9:Q9) -> 0 | E9: =SUM(E6:E8) -> 0 | F9: =SUM(F6:F8) -> 0 | G9: =SUM(G6:G8) -> 0 | H9: =SUM(H6:H8) -> 0 | I9: =SUM(I6:I8) -> 0 | J9: =SUM(J6:J8) -> 0 | K9: =SUM(K6:K8) -> 0 | L9: =SUM(L6:L8) -> 0 | ... Q9: =SUM(Q6:Q8) -> 0
A11: 2、投资性房地产本期增加（外购）
A12: 项目 | B12: 审定数 | C12: 抵消数 | D12: 汇总 | E12: 母公司审定 | F12: 子公司1 | G12: 子公司2 | H12: 子公司3 | I12: 子公司4 | J12: 子公司5 | K12: 子公司6 | L12: 子公司7 | M12: 子公司8 | N12: 子公司9 | O12: 子公司10 | P12: 子公司11 | Q12: 子公司12
A13: =A6 -> 房屋、建筑物 | B13: =D13-C13 -> 0 | D13: =SUM(E13:Q13) -> 0 | E13: 0
A14: =A7 -> 土地使用权 | B14: =D14-C14 -> 0 | D14: =SUM(E14:Q14) -> 0 | E14: 0
A15: =A8 -> 在建工程 | B15: =D15-C15 -> 0 | D15: =SUM(E15:Q15) -> 0 | E15: 0
A16: 合计 | B16: =SUM(B13:B15) -> 0 | C16: =SUM(C13:C15) -> 0 | D16: =SUM(E16:Q16) -> 0 | E16: =SUM(E13:E15) -> 0 | F16: =SUM(F13:F15) -> 0 | G16: =SUM(G13:G15) -> 0 | H16: =SUM(H13:H15) -> 0 | I16: =SUM(I13:I15) -> 0 | J16: =SUM(J13:J15) -> 0 | K16: =SUM(K13:K15) -> 0 | L16: =SUM(L13:L15) -> 0 | ... Q16: =SUM(Q13:Q15) -> 0
A18: 3、投资性房地产本期增加（存货、固定资产、在建工程转入）
A19: 项目 | B19: 审定数 | C19: 抵消数 | D19: 汇总 | E19: 母公司审定 | F19: 子公司1 | G19: 子公司2 | H19: 子公司3 | I19: 子公司4 | J19: 子公司5 | K19: 子公司6 | L19: 子公司7 | M19: 子公司8 | N19: 子公司9 | O19: 子公司10 | P19: 子公司11 | Q19: 子公司12
A20: =A13 -> 房屋、建筑物 | B20: =D20-C20 -> 0 | D20: =SUM(E20:Q20) -> 0 | E20: 0
A21: =A14 -> 土地使用权 | B21: =D21-C21 -> 0 | D21: =SUM(E21:Q21) -> 0 | E21: 0
A22: =A15 -> 在建工程 | B22: =D22-C22 -> 0 | D22: =SUM(E22:Q22) -> 0 | E22: 0
A23: 合计 | B23: =SUM(B20:B22) -> 0 | C23: =SUM(C20:C22) -> 0 | D23: =SUM(E23:Q23) -> 0 | E23: =SUM(E20:E22) -> 0 | F23: =SUM(F20:F22) -> 0 | G23: =SUM(G20:G22) -> 0 | H23: =SUM(H20:H22) -> 0 | I23: =SUM(I20:I22) -> 0 | J23: =SUM(J20:J22) -> 0 | K23: =SUM(K20:K22) -> 0 | L23: =SUM(L20:L22) -> 0 | ... Q23: =SUM(Q20:Q22) -> 0
A25: 4、投资性房地产本期增加（企业合并增加）
A26: 项目 | B26: 审定数 | C26: 抵消数 | D26: 汇总 | E26: 母公司审定 | F26: 子公司1 | G26: 子公司2 | H26: 子公司3 | I26: 子公司4 | J26: 子公司5 | K26: 子公司6 | L26: 子公司7 | M26: 子公司8 | N26: 子公司9 | O26: 子公司10 | P26: 子公司11 | Q26: 子公司12
A27: =A20 -> 房屋、建筑物 | B27: =D27-C27 -> 0 | D27: =SUM(E27:Q27) -> 0 | E27: 0
A28: =A21 -> 土地使用权 | B28: =D28-C28 -> 0 | D28: =SUM(E28:Q28) -> 0 | E28: 0
A29: =A22 -> 在建工程 | B29: =D29-C29 -> 0 | D29: =SUM(E29:Q29) -> 0 | E29: 0
A30: 合计 | B30: =SUM(B27:B29) -> 0 | C30: =SUM(C27:C29) -> 0 | D30: =SUM(E30:Q30) -> 0 | E30: =SUM(E27:E29) -> 0 | F30: =SUM(F27:F29) -> 0 | G30: =SUM(G27:G29) -> 0 | H30: =SUM(H27:H29) -> 0 | I30: =SUM(I27:I29) -> 0 | J30: =SUM(J27:J29) -> 0 | K30: =SUM(K27:K29) -> 0 | L30: =SUM(L27:L29) -> 0 | ... Q30: =SUM(Q27:Q29) -> 0
A32: 5、投资性房地产减少（处置或报废）
A33: 项目 | B33: 审定数 | C33: 抵消数 | D33: 汇总 | E33: 母公司审定 | F33: 子公司1 | G33: 子公司2 | H33: 子公司3 | I33: 子公司4 | J33: 子公司5 | K33: 子公司6 | L33: 子公司7 | M33: 子公司8 | N33: 子公司9 | O33: 子公司10 | P33: 子公司11 | Q33: 子公司12
A34: =A27 -> 房屋、建筑物 | B34: =D34-C34 -> 0 | D34: =SUM(E34:Q34) -> 0 | E34: 0
A35: =A28 -> 土地使用权 | B35: =D35-C35 -> 0 | D35: =SUM(E35:Q35) -> 0 | E35: 0
A36: =A29 -> 在建工程 | B36: =D36-C36 -> 0 | D36: =SUM(E36:Q36) -> 0 | E36: 0
A37: 合计 | B37: =SUM(B34:B36) -> 0 | C37: =SUM(C34:C36) -> 0 | D37: =SUM(E37:Q37) -> 0 | E37: =SUM(E34:E36) -> 0 | F37: =SUM(F34:F36) -> 0 | G37: =SUM(G34:G36) -> 0 | H37: =SUM(H34:H36) -> 0 | I37: =SUM(I34:I36) -> 0 | J37: =SUM(J34:J36) -> 0 | K37: =SUM(K34:K36) -> 0 | L37: =SUM(L34:L36) -> 0 | ... Q37: =SUM(Q34:Q36) -> 0
A39: 6、投资性房地产减少（其他转出）
A40: 项目 | B40: 审定数 | C40: 抵消数 | D40: 汇总 | E40: 母公司审定 | F40: 子公司1 | G40: 子公司2 | H40: 子公司3 | I40: 子公司4 | J40: 子公司5 | K40: 子公司6 | L40: 子公司7 | M40: 子公司8 | N40: 子公司9 | O40: 子公司10 | P40: 子公司11 | Q40: 子公司12
A41: =A34 -> 房屋、建筑物 | B41: =D41-C41 -> 0 | D41: =SUM(E41:Q41) -> 0 | E41: 0
A42: =A35 -> 土地使用权 | B42: =D42-C42 -> 0 | D42: =SUM(E42:Q42) -> 0 | E42: 0
A43: =A36 -> 在建工程 | B43: =D43-C43 -> 0 | D43: =SUM(E43:Q43) -> 0 | E43: 0
A44: 合计 | B44: =SUM(B41:B43) -> 0 | C44: =SUM(C41:C43) -> 0 | D44: =SUM(E44:Q44) -> 0 | E44: =SUM(E41:E43) -> 0 | F44: =SUM(F41:F43) -> 0 | G44: =SUM(G41:G43) -> 0 | H44: =SUM(H41:H43) -> 0 | I44: =SUM(I41:I43) -> 0 | J44: =SUM(J41:J43) -> 0 | K44: =SUM(K41:K43) -> 0 | L44: =SUM(L41:L43) -> 0 | ... Q44: =SUM(Q41:Q43) -> 0
A46: 7、投资性房地产原值期末数
A47: 项目 | B47: 审定数 | C47: 抵消数 | D47: 汇总 | E47: 母公司审定 | F47: 子公司1 | G47: 子公司2 | H47: 子公司3 | I47: 子公司4 | J47: 子公司5 | K47: 子公司6 | L47: 子公司7 | M47: 子公司8 | N47: 子公司9 | O47: 子公司10 | P47: 子公司11 | Q47: 子公司12
A48: =A41 -> 房屋、建筑物 | B48: =D48-C48 -> 0 | D48: =SUM(E48:Q48) -> 0 | E48: =E6+E13+E20+E27-E34-E41 -> 0 | F48: =F6+F13+F20+F27-F34-F41 -> 0 | G48: =G6+G13+G20+G27-G34-G41 -> 0 | H48: =H6+H13+H20+H27-H34-H41 -> 0 | I48: =I6+I13+I20+I27-I34-I41 -> 0 | J48: =J6+J13+J20+J27-J34-J41 -> 0 | K48: =K6+K13+K20+K27-K34-K41 -> 0 | L48: =L6+L13+L20+L27-L34-L41 -> 0 | ... Q48: =Q6+Q13+Q20+Q27-Q34-Q41 -> 0
A49: =A42 -> 土地使用权 | B49: =D49-C49 -> 0 | D49: =SUM(E49:Q49) -> 0 | E49: =E7+E14+E21+E28-E35-E42 -> 0 | F49: =F7+F14+F21+F28-F35-F42 -> 0 | G49: =G7+G14+G21+G28-G35-G42 -> 0 | H49: =H7+H14+H21+H28-H35-H42 -> 0 | I49: =I7+I14+I21+I28-I35-I42 -> 0 | J49: =J7+J14+J21+J28-J35-J42 -> 0 | K49: =K7+K14+K21+K28-K35-K42 -> 0 | L49: =L7+L14+L21+L28-L35-L42 -> 0 | ... Q49: =Q7+Q14+Q21+Q28-Q35-Q42 -> 0
A50: =A43 -> 在建工程 | B50: =D50-C50 -> 0 | D50: =SUM(E50:Q50) -> 0 | E50: =E8+E15+E22+E29-E36-E43 -> 0 | F50: =F8+F15+F22+F29-F36-F43 -> 0 | G50: =G8+G15+G22+G29-G36-G43 -> 0 | H50: =H8+H15+H22+H29-H36-H43 -> 0 | I50: =I8+I15+I22+I29-I36-I43 -> 0 | J50: =J8+J15+J22+J29-J36-J43 -> 0 | K50: =K8+K15+K22+K29-K36-K43 -> 0 | L50: =L8+L15+L22+L29-L36-L43 -> 0 | ... Q50: =Q8+Q15+Q22+Q29-Q36-Q43 -> 0
A51: 合计 | B51: =SUM(B48:B50) -> 0 | C51: =SUM(C48:C50) -> 0 | D51: =SUM(E51:Q51) -> 0 | E51: =SUM(E48:E50) -> 0 | F51: =SUM(F48:F50) -> 0 | G51: =SUM(G48:G50) -> 0 | H51: =SUM(H48:H50) -> 0 | I51: =SUM(I48:I50) -> 0 | J51: =SUM(J48:J50) -> 0 | K51: =SUM(K48:K50) -> 0 | L51: =SUM(L48:L50) -> 0 | ... Q51: =SUM(Q48:Q50) -> 0
A53: 投资性房地产累计折旧
A54: 1、累计折旧期初数
A55: 项目 | B55: 审定数 | C55: 抵消数 | D55: 汇总 | E55: 母公司审定 | F55: 子公司1 | G55: 子公司2 | H55: 子公司3 | I55: 子公司4 | J55: 子公司5 | K55: 子公司6 | L55: 子公司7 | M55: 子公司8 | N55: 子公司9 | O55: 子公司10 | P55: 子公司11 | Q55: 子公司12
A56: =A48 -> 房屋、建筑物 | B56: =D56-C56 -> 0 | D56: =SUM(E56:Q56) -> 0 | E56: 0
A57: =A49 -> 土地使用权 | B57: =D57-C57 -> 0 | D57: =SUM(E57:Q57) -> 0 | E57: 0
A58: =A50 -> 在建工程 | B58: =D58-C58 -> 0 | D58: =SUM(E58:Q58) -> 0 | E58: 0
A59: 合计 | B59: =SUM(B56:B58) -> 0 | C59: =SUM(C56:C58) -> 0 | D59: =SUM(E59:Q59) -> 0 | E59: =SUM(E56:E58) -> 0 | F59: =SUM(F56:F58) -> 0 | G59: =SUM(G56:G58) -> 0 | H59: =SUM(H56:H58) -> 0 | I59: =SUM(I56:I58) -> 0 | J59: =SUM(J56:J58) -> 0 | K59: =SUM(K56:K58) -> 0 | L59: =SUM(L56:L58) -> 0 | ... Q59: =SUM(Q56:Q58) -> 0
A61: 2、累计折旧本期增加（计提或摊销）
A62: 项目 | B62: 审定数 | C62: 抵消数 | D62: 汇总 | E62: 母公司审定 | F62: 子公司1 | G62: 子公司2 | H62: 子公司3 | I62: 子公司4 | J62: 子公司5 | K62: 子公司6 | L62: 子公司7 | M62: 子公司8 | N62: 子公司9 | O62: 子公司10 | P62: 子公司11 | Q62: 子公司12
A63: =A56 -> 房屋、建筑物 | B63: =D63-C63 -> 0 | D63: =SUM(E63:Q63) -> 0 | E63: 0
A64: =A57 -> 土地使用权 | B64: =D64-C64 -> 0 | D64: =SUM(E64:Q64) -> 0 | E64: 0
A65: =A58 -> 在建工程 | B65: =D65-C65 -> 0 | D65: =SUM(E65:Q65) -> 0 | E65: 0
A66: 合计 | B66: =SUM(B63:B65) -> 0 | C66: =SUM(C63:C65) -> 0 | D66: =SUM(E66:Q66) -> 0 | E66: =SUM(E63:E65) -> 0 | F66: =SUM(F63:F65) -> 0 | G66: =SUM(G63:G65) -> 0 | H66: =SUM(H63:H65) -> 0 | I66: =SUM(I63:I65) -> 0 | J66: =SUM(J63:J65) -> 0 | K66: =SUM(K63:K65) -> 0 | L66: =SUM(L63:L65) -> 0 | ... Q66: =SUM(Q63:Q65) -> 0
A68: 3、累计折旧本期增加（企业合并增加）
A69: 项目 | B69: 审定数 | C69: 抵消数 | D69: 汇总 | E69: 母公司审定 | F69: 子公司1 | G69: 子公司2 | H69: 子公司3 | I69: 子公司4 | J69: 子公司5 | K69: 子公司6 | L69: 子公司7 | M69: 子公司8 | N69: 子公司9 | O69: 子公司10 | P69: 子公司11 | Q69: 子公司12
A70: =A63 -> 房屋、建筑物 | B70: =D70-C70 -> 0 | D70: =SUM(E70:Q70) -> 0 | E70: 0
A71: =A64 -> 土地使用权 | B71: =D71-C71 -> 0 | D71: =SUM(E71:Q71) -> 0 | E71: 0
A72: =A65 -> 在建工程 | B72: =D72-C72 -> 0 | D72: =SUM(E72:Q72) -> 0 | E72: 0
A73: 合计 | B73: =SUM(B70:B72) -> 0 | C73: =SUM(C70:C72) -> 0 | D73: =SUM(E73:Q73) -> 0 | E73: =SUM(E70:E72) -> 0 | F73: =SUM(F70:F72) -> 0 | G73: =SUM(G70:G72) -> 0 | H73: =SUM(H70:H72) -> 0 | I73: =SUM(I70:I72) -> 0 | J73: =SUM(J70:J72) -> 0 | K73: =SUM(K70:K72) -> 0 | L73: =SUM(L70:L72) -> 0 | ... Q73: =SUM(Q70:Q72) -> 0
A75: 4、累计折旧本期增加（其他增加）
A76: 项目 | B76: 审定数 | C76: 抵消数 | D76: 汇总 | E76: 母公司审定 | F76: 子公司1 | G76: 子公司2 | H76: 子公司3 | I76: 子公司4 | J76: 子公司5 | K76: 子公司6 | L76: 子公司7 | M76: 子公司8 | N76: 子公司9 | O76: 子公司10 | P76: 子公司11 | Q76: 子公司12
A77: =A70 -> 房屋、建筑物 | B77: =D77-C77 -> 0 | D77: =SUM(E77:Q77) -> 0 | E77: 0
A78: =A71 -> 土地使用权 | B78: =D78-C78 -> 0 | D78: =SUM(E78:Q78) -> 0 | E78: 0
A79: =A72 -> 在建工程 | B79: =D79-C79 -> 0 | D79: =SUM(E79:Q79) -> 0 | E79: 0
A80: 合计 | B80: =SUM(B77:B79) -> 0 | C80: =SUM(C77:C79) -> 0 | D80: =SUM(E80:Q80) -> 0 | E80: =SUM(E77:E79) -> 0 | F80: =SUM(F77:F79) -> 0 | G80: =SUM(G77:G79) -> 0 | H80: =SUM(H77:H79) -> 0 | I80: =SUM(I77:I79) -> 0 | J80: =SUM(J77:J79) -> 0 | K80: =SUM(K77:K79) -> 0 | L80: =SUM(L77:L79) -> 0 | ... Q80: =SUM(Q77:Q79) -> 0
A82: 5、累计折旧本期减少（处置）
A83: 项目 | B83: 审定数 | C83: 抵消数 | D83: 汇总 | E83: 母公司审定 | F83: 子公司1 | G83: 子公司2 | H83: 子公司3 | I83: 子公司4 | J83: 子公司5 | K83: 子公司6 | L83: 子公司7 | M83: 子公司8 | N83: 子公司9 | O83: 子公司10 | P83: 子公司11 | Q83: 子公司12
A84: =A77 -> 房屋、建筑物 | B84: =D84-C84 -> 0 | D84: =SUM(E84:Q84) -> 0 | E84: 0
A85: =A78 -> 土地使用权 | B85: =D85-C85 -> 0 | D85: =SUM(E85:Q85) -> 0 | E85: 0
A86: =A79 -> 在建工程 | B86: =D86-C86 -> 0 | D86: =SUM(E86:Q86) -> 0 | E86: 0
A87: 合计 | B87: =SUM(B84:B86) -> 0 | C87: =SUM(C84:C86) -> 0 | D87: =SUM(E87:Q87) -> 0 | E87: =SUM(E84:E86) -> 0 | F87: =SUM(F84:F86) -> 0 | G87: =SUM(G84:G86) -> 0 | H87: =SUM(H84:H86) -> 0 | I87: =SUM(I84:I86) -> 0 | J87: =SUM(J84:J86) -> 0 | K87: =SUM(K84:K86) -> 0 | L87: =SUM(L84:L86) -> 0 | ... Q87: =SUM(Q84:Q86) -> 0
A89: 6、累计折旧本期减少（其他转出）
A90: 项目 | B90: 审定数 | C90: 抵消数 | D90: 汇总 | E90: 母公司审定 | F90: 子公司1 | G90: 子公司2 | H90: 子公司3 | I90: 子公司4 | J90: 子公司5 | K90: 子公司6 | L90: 子公司7 | M90: 子公司8 | N90: 子公司9 | O90: 子公司10 | P90: 子公司11 | Q90: 子公司12
A91: =A84 -> 房屋、建筑物 | B91: =D91-C91 -> 0 | D91: =SUM(E91:Q91) -> 0 | E91: 0
A92: =A85 -> 土地使用权 | B92: =D92-C92 -> 0 | D92: =SUM(E92:Q92) -> 0 | E92: 0
A93: =A86 -> 在建工程 | B93: =D93-C93 -> 0 | D93: =SUM(E93:Q93) -> 0 | E93: 0
A94: 合计 | B94: =SUM(B91:B93) -> 0 | C94: =SUM(C91:C93) -> 0 | D94: =SUM(E94:Q94) -> 0 | E94: =SUM(E91:E93) -> 0 | F94: =SUM(F91:F93) -> 0 | G94: =SUM(G91:G93) -> 0 | H94: =SUM(H91:H93) -> 0 | I94: =SUM(I91:I93) -> 0 | J94: =SUM(J91:J93) -> 0 | K94: =SUM(K91:K93) -> 0 | L94: =SUM(L91:L93) -> 0 | ... Q94: =SUM(Q91:Q93) -> 0
A96: 7、累计折旧期末余额
A97: 项目 | B97: 审定数 | C97: 抵消数 | D97: 汇总 | E97: 母公司审定 | F97: 子公司1 | G97: 子公司2 | H97: 子公司3 | I97: 子公司4 | J97: 子公司5 | K97: 子公司6 | L97: 子公司7 | M97: 子公司8 | N97: 子公司9 | O97: 子公司10 | P97: 子公司11 | Q97: 子公司12
A98: =A91 -> 房屋、建筑物 | B98: =D98-C98 -> 0 | D98: =SUM(E98:Q98) -> 0 | E98: =E56+E63+E70+E77-E84-E91 -> 0 | F98: =F56+F63+F70+F77-F84-F91 -> 0 | G98: =G56+G63+G70+G77-G84-G91 -> 0 | H98: =H56+H63+H70+H77-H84-H91 -> 0 | I98: =I56+I63+I70+I77-I84-I91 -> 0 | J98: =J56+J63+J70+J77-J84-J91 -> 0 | K98: =K56+K63+K70+K77-K84-K91 -> 0 | L98: =L56+L63+L70+L77-L84-L91 -> 0 | ... Q98: =Q56+Q63+Q70+Q77-Q84-Q91 -> 0
A99: =A92 -> 土地使用权 | B99: =D99-C99 -> 0 | D99: =SUM(E99:Q99) -> 0 | E99: =E57+E64+E71+E78-E85-E92 -> 0 | F99: =F57+F64+F71+F78-F85-F92 -> 0 | G99: =G57+G64+G71+G78-G85-G92 -> 0 | H99: =H57+H64+H71+H78-H85-H92 -> 0 | I99: =I57+I64+I71+I78-I85-I92 -> 0 | J99: =J57+J64+J71+J78-J85-J92 -> 0 | K99: =K57+K64+K71+K78-K85-K92 -> 0 | L99: =L57+L64+L71+L78-L85-L92 -> 0 | ... Q99: =Q57+Q64+Q71+Q78-Q85-Q92 -> 0
A100: =A93 -> 在建工程 | B100: =D100-C100 -> 0 | D100: =SUM(E100:Q100) -> 0 | E100: =E58+E65+E72+E79-E86-E93 -> 0 | F100: =F58+F65+F72+F79-F86-F93 -> 0 | G100: =G58+G65+G72+G79-G86-G93 -> 0 | H100: =H58+H65+H72+H79-H86-H93 -> 0 | I100: =I58+I65+I72+I79-I86-I93 -> 0 | J100: =J58+J65+J72+J79-J86-J93 -> 0 | K100: =K58+K65+K72+K79-K86-K93 -> 0 | L100: =L58+L65+L72+L79-L86-L93 -> 0 | ... Q100: =Q58+Q65+Q72+Q79-Q86-Q93 -> 0
A101: 合计 | B101: =SUM(B98:B100) -> 0 | C101: =SUM(C98:C100) -> 0 | D101: =SUM(E101:Q101) -> 0 | E101: =SUM(E98:E100) -> 0 | F101: =SUM(F98:F100) -> 0 | G101: =SUM(G98:G100) -> 0 | H101: =SUM(H98:H100) -> 0 | I101: =SUM(I98:I100) -> 0 | J101: =SUM(J98:J100) -> 0 | K101: =SUM(K98:K100) -> 0 | L101: =SUM(L98:L100) -> 0 | ... Q101: =SUM(Q98:Q100) -> 0
A103: 投资性房地产减值准备
A104: 1、投资性房地产减值准备期初数
A105: 项目 | B105: 审定数 | C105: 抵消数 | D105: 汇总 | E105: 母公司审定 | F105: 子公司1 | G105: 子公司2 | H105: 子公司3 | I105: 子公司4 | J105: 子公司5 | K105: 子公司6 | L105: 子公司7 | M105: 子公司8 | N105: 子公司9 | O105: 子公司10 | P105: 子公司11 | Q105: 子公司12
A106: =A98 -> 房屋、建筑物 | B106: =D106-C106 -> 0 | D106: =SUM(E106:Q106) -> 0 | E106: 0
A107: =A99 -> 土地使用权 | B107: =D107-C107 -> 0 | D107: =SUM(E107:Q107) -> 0 | E107: 0
A108: =A100 -> 在建工程 | B108: =D108-C108 -> 0 | D108: =SUM(E108:Q108) -> 0 | E108: 0
A109: 合计 | B109: =SUM(B106:B108) -> 0 | C109: =SUM(C106:C108) -> 0 | D109: =SUM(E109:Q109) -> 0 | E109: =SUM(E106:E108) -> 0 | F109: =SUM(F106:F108) -> 0 | G109: =SUM(G106:G108) -> 0 | H109: =SUM(H106:H108) -> 0 | I109: =SUM(I106:I108) -> 0 | J109: =SUM(J106:J108) -> 0 | K109: =SUM(K106:K108) -> 0 | L109: =SUM(L106:L108) -> 0 | ... Q109: =SUM(Q106:Q108) -> 0
A111: 2、投资性房地产减值准备本期增加（计提）
A112: 项目 | B112: 审定数 | C112: 抵消数 | D112: 汇总 | E112: 母公司审定 | F112: 子公司1 | G112: 子公司2 | H112: 子公司3 | I112: 子公司4 | J112: 子公司5 | K112: 子公司6 | L112: 子公司7 | M112: 子公司8 | N112: 子公司9 | O112: 子公司10 | P112: 子公司11 | Q112: 子公司12
A113: =A106 -> 房屋、建筑物 | B113: =D113-C113 -> 0 | D113: =SUM(E113:Q113) -> 0 | E113: 0
A114: =A107 -> 土地使用权 | B114: =D114-C114 -> 0 | D114: =SUM(E114:Q114) -> 0 | E114: 0
A115: =A108 -> 在建工程 | B115: =D115-C115 -> 0 | D115: =SUM(E115:Q115) -> 0 | E115: 0
...

Sheet 投资性房地产（公允价值模式）
A1: 投资性房地产附注汇总 | D1: 返回Excel目录 | E1: 返回word附注
A2: （1）按公允价值计量的投资性房地产
A3: 1、投资性房地产期初原值
A4: 项目 | B4: 审定数 | C4: 抵消数 | D4: 汇总 | E4: 母公司审定 | F4: 子公司1 | G4: 子公司2 | H4: 子公司3 | I4: 子公司4 | J4: 子公司5 | K4: 子公司6 | L4: 子公司7 | M4: 子公司8 | N4: 子公司9 | O4: 子公司10 | P4: 子公司11 | Q4: 子公司12
A5: 房屋、建筑物 | B5: =D5-C5 -> 0 | D5: =SUM(E5:Q5) -> 0 | E5: 0
A6: 土地使用权 | B6: =D6-C6 -> 0 | D6: =SUM(E6:Q6) -> 0 | E6: 0
A7: 在建工程 | B7: =D7-C7 -> 0 | D7: =SUM(E7:Q7) -> 0 | E7: 0
A8: 合计 | B8: =SUM(B5:B7) -> 0 | C8: =SUM(C5:C7) -> 0 | D8: =SUM(E8:Q8) -> 0 | E8: =SUM(E5:E7) -> 0 | F8: =SUM(F5:F7) -> 0 | G8: =SUM(G5:G7) -> 0 | H8: =SUM(H5:H7) -> 0 | I8: =SUM(I5:I7) -> 0 | J8: =SUM(J5:J7) -> 0 | K8: =SUM(K5:K7) -> 0 | L8: =SUM(L5:L7) -> 0 | ... Q8: =SUM(Q5:Q7) -> 0
A10: 2、投资性房地产期初公允价值变动
A11: 项目 | B11: 审定数 | C11: 抵消数 | D11: 汇总 | E11: 母公司审定 | F11: 子公司1 | G11: 子公司2 | H11: 子公司3 | I11: 子公司4 | J11: 子公司5 | K11: 子公司6 | L11: 子公司7 | M11: 子公司8 | N11: 子公司9 | O11: 子公司10 | P11: 子公司11 | Q11: 子公司12
A12: =A5 -> 房屋、建筑物 | B12: =D12-C12 -> 0 | D12: =SUM(E12:Q12) -> 0 | E12: 0
A13: =A6 -> 土地使用权 | B13: =D13-C13 -> 0 | D13: =SUM(E13:Q13) -> 0 | E13: 0
A14: =A7 -> 在建工程 | B14: =D14-C14 -> 0 | D14: =SUM(E14:Q14) -> 0 | E14: 0
A15: 合计 | B15: =SUM(B12:B14) -> 0 | C15: =SUM(C12:C14) -> 0 | D15: =SUM(E15:Q15) -> 0 | E15: =SUM(E12:E14) -> 0 | F15: =SUM(F12:F14) -> 0 | G15: =SUM(G12:G14) -> 0 | H15: =SUM(H12:H14) -> 0 | I15: =SUM(I12:I14) -> 0 | J15: =SUM(J12:J14) -> 0 | K15: =SUM(K12:K14) -> 0 | L15: =SUM(L12:L14) -> 0 | ... Q15: =SUM(Q12:Q14) -> 0
A17: 3、投资性房地产本期原值增加（外购）
A18: 项目 | B18: 审定数 | C18: 抵消数 | D18: 汇总 | E18: 母公司审定 | F18: 子公司1 | G18: 子公司2 | H18: 子公司3 | I18: 子公司4 | J18: 子公司5 | K18: 子公司6 | L18: 子公司7 | M18: 子公司8 | N18: 子公司9 | O18: 子公司10 | P18: 子公司11 | Q18: 子公司12
A19: =A12 -> 房屋、建筑物 | B19: =D19-C19 -> 0 | D19: =SUM(E19:Q19) -> 0 | E19: 0
A20: =A13 -> 土地使用权 | B20: =D20-C20 -> 0 | D20: =SUM(E20:Q20) -> 0 | E20: 0
A21: =A14 -> 在建工程 | B21: =D21-C21 -> 0 | D21: =SUM(E21:Q21) -> 0 | E21: 0
A22: 合计 | B22: =SUM(B19:B21) -> 0 | C22: =SUM(C19:C21) -> 0 | D22: =SUM(E22:Q22) -> 0 | E22: =SUM(E19:E21) -> 0 | F22: =SUM(F19:F21) -> 0 | G22: =SUM(G19:G21) -> 0 | H22: =SUM(H19:H21) -> 0 | I22: =SUM(I19:I21) -> 0 | J22: =SUM(J19:J21) -> 0 | K22: =SUM(K19:K21) -> 0 | L22: =SUM(L19:L21) -> 0 | ... Q22: =SUM(Q19:Q21) -> 0
A24: 4、投资性房地产本期原值增加（存货、固定资产、在建工程转入）
A25: 项目 | B25: 审定数 | C25: 抵消数 | D25: 汇总 | E25: 母公司审定 | F25: 子公司1 | G25: 子公司2 | H25: 子公司3 | I25: 子公司4 | J25: 子公司5 | K25: 子公司6 | L25: 子公司7 | M25: 子公司8 | N25: 子公司9 | O25: 子公司10 | P25: 子公司11 | Q25: 子公司12
A26: =A19 -> 房屋、建筑物 | B26: =D26-C26 -> 0 | D26: =SUM(E26:Q26) -> 0 | E26: 0
A27: =A20 -> 土地使用权 | B27: =D27-C27 -> 0 | D27: =SUM(E27:Q27) -> 0 | E27: 0
A28: =A21 -> 在建工程 | B28: =D28-C28 -> 0 | D28: =SUM(E28:Q28) -> 0 | E28: 0
A29: 合计 | B29: =SUM(B26:B28) -> 0 | C29: =SUM(C26:C28) -> 0 | D29: =SUM(E29:Q29) -> 0 | E29: =SUM(E26:E28) -> 0 | F29: =SUM(F26:F28) -> 0 | G29: =SUM(G26:G28) -> 0 | H29: =SUM(H26:H28) -> 0 | I29: =SUM(I26:I28) -> 0 | J29: =SUM(J26:J28) -> 0 | K29: =SUM(K26:K28) -> 0 | L29: =SUM(L26:L28) -> 0 | ... Q29: =SUM(Q26:Q28) -> 0
A31: 5、投资性房地产本期原值增加（企业合并增加）
A32: 项目 | B32: 审定数 | C32: 抵消数 | D32: 汇总 | E32: 母公司审定 | F32: 子公司1 | G32: 子公司2 | H32: 子公司3 | I32: 子公司4 | J32: 子公司5 | K32: 子公司6 | L32: 子公司7 | M32: 子公司8 | N32: 子公司9 | O32: 子公司10 | P32: 子公司11 | Q32: 子公司12
A33: =A26 -> 房屋、建筑物 | B33: =D33-C33 -> 0 | D33: =SUM(E33:Q33) -> 0 | E33: 0
A34: =A27 -> 土地使用权 | B34: =D34-C34 -> 0 | D34: =SUM(E34:Q34) -> 0 | E34: 0
A35: =A28 -> 在建工程 | B35: =D35-C35 -> 0 | D35: =SUM(E35:Q35) -> 0 | E35: 0
A36: 合计 | B36: =SUM(B33:B35) -> 0 | C36: =SUM(C33:C35) -> 0 | D36: =SUM(E36:Q36) -> 0 | E36: =SUM(E33:E35) -> 0 | F36: =SUM(F33:F35) -> 0 | G36: =SUM(G33:G35) -> 0 | H36: =SUM(H33:H35) -> 0 | I36: =SUM(I33:I35) -> 0 | J36: =SUM(J33:J35) -> 0 | K36: =SUM(K33:K35) -> 0 | L36: =SUM(L33:L35) -> 0 | ... Q36: =SUM(Q33:Q35) -> 0
A38: 6、投资性房地产本期原值减少（处置）
A39: 项目 | B39: 审定数 | C39: 抵消数 | D39: 汇总 | E39: 母公司审定 | F39: 子公司1 | G39: 子公司2 | H39: 子公司3 | I39: 子公司4 | J39: 子公司5 | K39: 子公司6 | L39: 子公司7 | M39: 子公司8 | N39: 子公司9 | O39: 子公司10 | P39: 子公司11 | Q39: 子公司12
A40: =A33 -> 房屋、建筑物 | B40: =D40-C40 -> 0 | D40: =SUM(E40:Q40) -> 0 | E40: 0
A41: =A34 -> 土地使用权 | B41: =D41-C41 -> 0 | D41: =SUM(E41:Q41) -> 0 | E41: 0
A42: =A35 -> 在建工程 | B42: =D42-C42 -> 0 | D42: =SUM(E42:Q42) -> 0 | E42: 0
A43: 合计 | B43: =SUM(B40:B42) -> 0 | C43: =SUM(C40:C42) -> 0 | D43: =SUM(E43:Q43) -> 0 | E43: =SUM(E40:E42) -> 0 | F43: =SUM(F40:F42) -> 0 | G43: =SUM(G40:G42) -> 0 | H43: =SUM(H40:H42) -> 0 | I43: =SUM(I40:I42) -> 0 | J43: =SUM(J40:J42) -> 0 | K43: =SUM(K40:K42) -> 0 | L43: =SUM(L40:L42) -> 0 | ... Q43: =SUM(Q40:Q42) -> 0
A45: 7、投资性房地产本期原值减少（其他转出）
A46: 项目 | B46: 审定数 | C46: 抵消数 | D46: 汇总 | E46: 母公司审定 | F46: 子公司1 | G46: 子公司2 | H46: 子公司3 | I46: 子公司4 | J46: 子公司5 | K46: 子公司6 | L46: 子公司7 | M46: 子公司8 | N46: 子公司9 | O46: 子公司10 | P46: 子公司11 | Q46: 子公司12
A47: =A40 -> 房屋、建筑物 | B47: =D47-C47 -> 0 | D47: =SUM(E47:Q47) -> 0 | E47: 0
A48: =A41 -> 土地使用权 | B48: =D48-C48 -> 0 | D48: =SUM(E48:Q48) -> 0 | E48: 0
A49: =A42 -> 在建工程 | B49: =D49-C49 -> 0 | D49: =SUM(E49:Q49) -> 0 | E49: 0
A50: 合计 | B50: =SUM(B47:B49) -> 0 | C50: =SUM(C47:C49) -> 0 | D50: =SUM(E50:Q50) -> 0 | E50: =SUM(E47:E49) -> 0 | F50: =SUM(F47:F49) -> 0 | G50: =SUM(G47:G49) -> 0 | H50: =SUM(H47:H49) -> 0 | I50: =SUM(I47:I49) -> 0 | J50: =SUM(J47:J49) -> 0 | K50: =SUM(K47:K49) -> 0 | L50: =SUM(L47:L49) -> 0 | ... Q50: =SUM(Q47:Q49) -> 0
A52: 8、投资性房地产本期公允价值变动
A53: 项目 | B53: 审定数 | C53: 抵消数 | D53: 汇总 | E53: 母公司审定 | F53: 子公司1 | G53: 子公司2 | H53: 子公司3 | I53: 子公司4 | J53: 子公司5 | K53: 子公司6 | L53: 子公司7 | M53: 子公司8 | N53: 子公司9 | O53: 子公司10 | P53: 子公司11 | Q53: 子公司12
A54: =A47 -> 房屋、建筑物 | B54: =D54-C54 -> 0 | D54: =SUM(E54:Q54) -> 0 | E54: 0
A55: =A48 -> 土地使用权 | B55: =D55-C55 -> 0 | D55: =SUM(E55:Q55) -> 0 | E55: 0
A56: =A49 -> 在建工程 | B56: =D56-C56 -> 0 | D56: =SUM(E56:Q56) -> 0 | E56: 0
A57: 合计 | B57: =SUM(B54:B56) -> 0 | C57: =SUM(C54:C56) -> 0 | D57: =SUM(E57:Q57) -> 0 | E57: =SUM(E54:E56) -> 0 | F57: =SUM(F54:F56) -> 0 | G57: =SUM(G54:G56) -> 0 | H57: =SUM(H54:H56) -> 0 | I57: =SUM(I54:I56) -> 0 | J57: =SUM(J54:J56) -> 0 | K57: =SUM(K54:K56) -> 0 | L57: =SUM(L54:L56) -> 0 | ... Q57: =SUM(Q54:Q56) -> 0
A59: 9、投资性房地产期末原值
A60: 项目 | B60: 审定数 | C60: 抵消数 | D60: 汇总 | E60: 母公司审定 | F60: 子公司1 | G60: 子公司2 | H60: 子公司3 | I60: 子公司4 | J60: 子公司5 | K60: 子公司6 | L60: 子公司7 | M60: 子公司8 | N60: 子公司9 | O60: 子公司10 | P60: 子公司11 | Q60: 子公司12
A61: =A54 -> 房屋、建筑物 | B61: =D61-C61 -> 0 | D61: =SUM(E61:Q61) -> 0 | E61: =E5+E19+E26+E33-E40-E47 -> 0 | F61: =F5+F19+F26+F33-F40-F47 -> 0 | G61: =G5+G19+G26+G33-G40-G47 -> 0 | H61: =H5+H19+H26+H33-H40-H47 -> 0 | I61: =I5+I19+I26+I33-I40-I47 -> 0 | J61: =J5+J19+J26+J33-J40-J47 -> 0 | K61: =K5+K19+K26+K33-K40-K47 -> 0 | L61: =L5+L19+L26+L33-L40-L47 -> 0 | ... Q61: =Q5+Q19+Q26+Q33-Q40-Q47 -> 0
A62: =A55 -> 土地使用权 | B62: =D62-C62 -> 0 | D62: =SUM(E62:Q62) -> 0 | E62: =E6+E20+E27+E34-E41-E48 -> 0 | F62: =F6+F20+F27+F34-F41-F48 -> 0 | G62: =G6+G20+G27+G34-G41-G48 -> 0 | H62: =H6+H20+H27+H34-H41-H48 -> 0 | I62: =I6+I20+I27+I34-I41-I48 -> 0 | J62: =J6+J20+J27+J34-J41-J48 -> 0 | K62: =K6+K20+K27+K34-K41-K48 -> 0 | L62: =L6+L20+L27+L34-L41-L48 -> 0 | ... Q62: =Q6+Q20+Q27+Q34-Q41-Q48 -> 0
A63: =A56 -> 在建工程 | B63: =D63-C63 -> 0 | D63: =SUM(E63:Q63) -> 0 | E63: =E7+E21+E28+E35-E42-E49 -> 0 | F63: =F7+F21+F28+F35-F42-F49 -> 0 | G63: =G7+G21+G28+G35-G42-G49 -> 0 | H63: =H7+H21+H28+H35-H42-H49 -> 0 | I63: =I7+I21+I28+I35-I42-I49 -> 0 | J63: =J7+J21+J28+J35-J42-J49 -> 0 | K63: =K7+K21+K28+K35-K42-K49 -> 0 | L63: =L7+L21+L28+L35-L42-L49 -> 0 | ... Q63: =Q7+Q21+Q28+Q35-Q42-Q49 -> 0
A64: 合计 | B64: =SUM(B61:B63) -> 0 | C64: =SUM(C61:C63) -> 0 | D64: =SUM(E64:Q64) -> 0 | E64: =SUM(E61:E63) -> 0 | F64: =SUM(F61:F63) -> 0 | G64: =SUM(G61:G63) -> 0 | H64: =SUM(H61:H63) -> 0 | I64: =SUM(I61:I63) -> 0 | J64: =SUM(J61:J63) -> 0 | K64: =SUM(K61:K63) -> 0 | L64: =SUM(L61:L63) -> 0 | ... Q64: =SUM(Q61:Q63) -> 0
A66: 10、投资性房地产期末公允价值变动
A67: 项目 | B67: 审定数 | C67: 抵消数 | D67: 汇总 | E67: 母公司审定 | F67: 子公司1 | G67: 子公司2 | H67: 子公司3 | I67: 子公司4 | J67: 子公司5 | K67: 子公司6 | L67: 子公司7 | M67: 子公司8 | N67: 子公司9 | O67: 子公司10 | P67: 子公司11 | Q67: 子公司12
A68: =A61 -> 房屋、建筑物 | B68: =D68-C68 -> 0 | D68: =SUM(E68:Q68) -> 0 | E68: =E12+E54 -> 0 | F68: =F12+F54 -> 0 | G68: =G12+G54 -> 0 | H68: =H12+H54 -> 0 | I68: =I12+I54 -> 0 | J68: =J12+J54 -> 0 | K68: =K12+K54 -> 0 | L68: =L12+L54 -> 0 | ... Q68: =Q12+Q54 -> 0
A69: =A62 -> 土地使用权 | B69: =D69-C69 -> 0 | D69: =SUM(E69:Q69) -> 0 | E69: =E13+E55 -> 0 | F69: =F13+F55 -> 0 | G69: =G13+G55 -> 0 | H69: =H13+H55 -> 0 | I69: =I13+I55 -> 0 | J69: =J13+J55 -> 0 | K69: =K13+K55 -> 0 | L69: =L13+L55 -> 0 | ... Q69: =Q13+Q55 -> 0
A70: =A63 -> 在建工程 | B70: =D70-C70 -> 0 | D70: =SUM(E70:Q70) -> 0 | E70: =E14+E56 -> 0 | F70: =F14+F56 -> 0 | G70: =G14+G56 -> 0 | H70: =H14+H56 -> 0 | I70: =I14+I56 -> 0 | J70: =J14+J56 -> 0 | K70: =K14+K56 -> 0 | L70: =L14+L56 -> 0 | ... Q70: =Q14+Q56 -> 0
A71: 合计 | B71: =SUM(B68:B70) -> 0 | C71: =SUM(C68:C70) -> 0 | D71: =SUM(E71:Q71) -> 0 | E71: =SUM(E68:E70) -> 0 | F71: =SUM(F68:F70) -> 0 | G71: =SUM(G68:G70) -> 0 | H71: =SUM(H68:H70) -> 0 | I71: =SUM(I68:I70) -> 0 | J71: =SUM(J68:J70) -> 0 | K71: =SUM(K68:K70) -> 0 | L71: =SUM(L68:L70) -> 0 | ... Q71: =SUM(Q68:Q70) -> 0
A72: 期末余额 | B72: =B64-B71 -> 0 | C72: =C64-C71 -> 0 | D72: =D64-D71 -> 0 | E72: =E64-E71 -> 0 | F72: =F64-F71 -> 0 | G72: =G64-G71 -> 0 | H72: =H64-H71 -> 0 | I72: =I64-I71 -> 0 | ... Q72: =Q64-Q71 -> 0
A73: 试算表链接： | B73: 0 | D73: =SUM(E73:Q73) -> 0 | E73: 0
A74: 差异 | B74: =B72-B73 -> 0 | D74: =D72-D73 -> 0 | E74: =E72-E73 -> 0 | F74: =F72-F73 -> 0 | G74: =G72-G73 -> 0 | H74: =H72-H73 -> 0 | I74: =I72-I73 -> 0 | J74: =J72-J73 -> 0 | K74: =K72-K73 -> 0 | ... Q74: =Q72-Q73 -> 0
A77: 未办妥产权证书的情况
A78: （披露未办妥产权证书的投资性房地产账面价值及原因。）
A79: 单位 | B79: 项 目 | C79: 账面价值 | D79: 未办妥产权证书原因
A80: 母公司
A81: 子公司1
A91: （4）房地产转换情况及改变计量模式的情况
A92: （说明报告期内房地产转换或改变计量模式的情况、理由，以及对损益或所有者权益的影响。
A93: 房地产开发企业列示出租开发产品时，应披露出租开发产品的成本、租赁合同主要条款等内容。对重要的出租房产应单项披露，非重要或零星的出租房产可采用合并披露。）

Sheet 固定资产及固定资产清理
A1: 固定资产附注汇总 | D1: 返回Excel目录 | E1: 返回word附注
A2: 项目 | B2: 审定数 | C2: 抵消数 | D2: 汇总 | E2: 母公司审定 | F2: 子公司1 | G2: 子公司2 | H2: 子公司3 | I2: 子公司4 | J2: 子公司5 | K2: 子公司6 | L2: 子公司7 | M2: 子公司8 | N2: 子公司9 | O2: 子公司10 | P2: 子公司11 | Q2: 子公司12
A3: 固定资产 | B3: =D3-C3 -> 0 | D3: =SUM(E3:Q3) -> 0 | E3: =固定资产!E191 -> 0 | F3: =固定资产!F191 -> 0 | G3: =固定资产!G191 -> 0 | H3: =固定资产!H191 -> 0 | I3: =固定资产!I191 -> 0 | J3: =固定资产!J191 -> 0 | K3: =固定资产!K191 -> 0 | L3: =固定资产!L191 -> 0 | ... Q3: =固定资产!Q191 -> 0
A4: 固定资产清理 | B4: =D4-C4 -> 0 | D4: =SUM(E4:Q4) -> 0 | E4: =固定资产清理!E9 -> 0 | F4: =固定资产清理!F9 -> 0 | G4: =固定资产清理!G9 -> 0 | H4: =固定资产清理!H9 -> 0 | I4: =固定资产清理!I9 -> 0 | J4: =固定资产清理!J9 -> 0 | K4: =固定资产清理!K9 -> 0 | L4: =固定资产清理!L9 -> 0 | ... Q4: =固定资产清理!Q9 -> 0
A5: 合计 | B5: =SUM(B3:B4) -> 0 | C5: =SUM(C3:C4) -> 0 | D5: =SUM(E5:Q5) -> 0 | E5: =SUM(E3:E4) -> 0 | F5: =SUM(F3:F4) -> 0 | G5: =SUM(G3:G4) -> 0 | H5: =SUM(H3:H4) -> 0 | I5: =SUM(I3:I4) -> 0 | J5: =SUM(J3:J4) -> 0 | K5: =SUM(K3:K4) -> 0 | L5: =SUM(L3:L4) -> 0 | ... Q5: =SUM(Q3:Q4) -> 0

Sheet 固定资产
A1: 固定资产附注汇总 | D1: 返回Excel目录 | E1: 返回word附注
A2: 1、固定资产原值期初数
A3: 项目 | B3: 审定数 | C3: 抵消数 | D3: 汇总 | E3: 母公司审定 | F3: 子公司1 | G3: 子公司2 | H3: 子公司3 | I3: 子公司4 | J3: 子公司5 | K3: 子公司6 | L3: 子公司7 | M3: 子公司8 | N3: 子公司9 | O3: 子公司10 | P3: 子公司11 | Q3: 子公司12
A4: 房屋及建筑物 | B4: =D4-C4 -> 0 | D4: =SUM(E4:Q4) -> 0 | E4: 0
A5: 机器设备 | B5: =D5-C5 -> 0 | D5: =SUM(E5:Q5) -> 0 | E5: 0
A6: 运输设备 | B6: =D6-C6 -> 0 | D6: =SUM(E6:Q6) -> 0 | E6: 0
A7: 电子设备 | B7: =D7-C7 -> 0 | D7: =SUM(E7:Q7) -> 0 | E7: 0
A8: 其他 | B8: =D8-C8 -> 0 | D8: =SUM(E8:Q8) -> 0 | E8: 0
A9: 合计 | B9: =SUM(B4:B8) -> 0 | C9: =SUM(C4:C8) -> 0 | D9: =SUM(E9:Q9) -> 0 | E9: =SUM(E4:E8) -> 0 | F9: =SUM(F4:F8) -> 0 | G9: =SUM(G4:G8) -> 0 | H9: =SUM(H4:H8) -> 0 | I9: =SUM(I4:I8) -> 0 | J9: =SUM(J4:J8) -> 0 | K9: =SUM(K4:K8) -> 0 | L9: =SUM(L4:L8) -> 0 | ... Q9: =SUM(Q4:Q8) -> 0
A11: 2、固定资产本期增加（外购）
A12: 项目 | B12: 审定数 | C12: 抵消数 | D12: 汇总 | E12: 母公司审定 | F12: 子公司1 | G12: 子公司2 | H12: 子公司3 | I12: 子公司4 | J12: 子公司5 | K12: 子公司6 | L12: 子公司7 | M12: 子公司8 | N12: 子公司9 | O12: 子公司10 | P12: 子公司11 | Q12: 子公司12
A13: =A4 -> 房屋及建筑物 | B13: =D13-C13 -> 0 | D13: =SUM(E13:Q13) -> 0 | E13: 0
A14: =A5 -> 机器设备 | B14: =D14-C14 -> 0 | D14: =SUM(E14:Q14) -> 0 | E14: 0
A15: =A6 -> 运输设备 | B15: =D15-C15 -> 0 | D15: =SUM(E15:Q15) -> 0 | E15: 0
A16: =A7 -> 电子设备 | B16: =D16-C16 -> 0 | D16: =SUM(E16:Q16) -> 0 | E16: 0
A17: =A8 -> 其他 | B17: =D17-C17 -> 0 | D17: =SUM(E17:Q17) -> 0 | E17: 0
A18: 合计 | B18: =SUM(B13:B17) -> 0 | C18: =SUM(C13:C17) -> 0 | D18: =SUM(E18:Q18) -> 0 | E18: =SUM(E13:E17) -> 0 | F18: =SUM(F13:F17) -> 0 | G18: =SUM(G13:G17) -> 0 | H18: =SUM(H13:H17) -> 0 | I18: =SUM(I13:I17) -> 0 | J18: =SUM(J13:J17) -> 0 | K18: =SUM(K13:K17) -> 0 | L18: =SUM(L13:L17) -> 0 | ... Q18: =SUM(Q13:Q17) -> 0
A20: 3、固定资产本期增加（在建工程转入）
A21: 项目 | B21: 审定数 | C21: 抵消数 | D21: 汇总 | E21: 母公司审定 | F21: 子公司1 | G21: 子公司2 | H21: 子公司3 | I21: 子公司4 | J21: 子公司5 | K21: 子公司6 | L21: 子公司7 | M21: 子公司8 | N21: 子公司9 | O21: 子公司10 | P21: 子公司11 | Q21: 子公司12
A22: =A13 -> 房屋及建筑物 | B22: =D22-C22 -> 0 | D22: =SUM(E22:Q22) -> 0 | E22: 0
A23: =A14 -> 机器设备 | B23: =D23-C23 -> 0 | D23: =SUM(E23:Q23) -> 0 | E23: 0
A24: =A15 -> 运输设备 | B24: =D24-C24 -> 0 | D24: =SUM(E24:Q24) -> 0 | E24: 0
A25: =A16 -> 电子设备 | B25: =D25-C25 -> 0 | D25: =SUM(E25:Q25) -> 0 | E25: 0
A26: =A17 -> 其他 | B26: =D26-C26 -> 0 | D26: =SUM(E26:Q26) -> 0 | E26: 0
A27: 合计 | B27: =SUM(B22:B26) -> 0 | C27: =SUM(C22:C26) -> 0 | D27: =SUM(E27:Q27) -> 0 | E27: =SUM(E22:E26) -> 0 | F27: =SUM(F22:F26) -> 0 | G27: =SUM(G22:G26) -> 0 | H27: =SUM(H22:H26) -> 0 | I27: =SUM(I22:I26) -> 0 | J27: =SUM(J22:J26) -> 0 | K27: =SUM(K22:K26) -> 0 | L27: =SUM(L22:L26) -> 0 | ... Q27: =SUM(Q22:Q26) -> 0
A29: 4、固定资产本期增加（企业合并增加）
A30: 项目 | B30: 审定数 | C30: 抵消数 | D30: 汇总 | E30: 母公司审定 | F30: 子公司1 | G30: 子公司2 | H30: 子公司3 | I30: 子公司4 | J30: 子公司5 | K30: 子公司6 | L30: 子公司7 | M30: 子公司8 | N30: 子公司9 | O30: 子公司10 | P30: 子公司11 | Q30: 子公司12
A31: =A22 -> 房屋及建筑物 | B31: =D31-C31 -> 0 | D31: =SUM(E31:Q31) -> 0 | E31: 0
A32: =A23 -> 机器设备 | B32: =D32-C32 -> 0 | D32: =SUM(E32:Q32) -> 0 | E32: 0
A33: =A24 -> 运输设备 | B33: =D33-C33 -> 0 | D33: =SUM(E33:Q33) -> 0 | E33: 0
A34: =A25 -> 电子设备 | B34: =D34-C34 -> 0 | D34: =SUM(E34:Q34) -> 0 | E34: 0
A35: =A26 -> 其他 | B35: =D35-C35 -> 0 | D35: =SUM(E35:Q35) -> 0 | E35: 0
A36: 合计 | B36: =SUM(B31:B35) -> 0 | C36: =SUM(C31:C35) -> 0 | D36: =SUM(E36:Q36) -> 0 | E36: =SUM(E31:E35) -> 0 | F36: =SUM(F31:F35) -> 0 | G36: =SUM(G31:G35) -> 0 | H36: =SUM(H31:H35) -> 0 | I36: =SUM(I31:I35) -> 0 | J36: =SUM(J31:J35) -> 0 | K36: =SUM(K31:K35) -> 0 | L36: =SUM(L31:L35) -> 0 | ... Q36: =SUM(Q31:Q35) -> 0
A38: 5、固定资产减少（处置或报废）
A39: 项目 | B39: 审定数 | C39: 抵消数 | D39: 汇总 | E39: 母公司审定 | F39: 子公司1 | G39: 子公司2 | H39: 子公司3 | I39: 子公司4 | J39: 子公司5 | K39: 子公司6 | L39: 子公司7 | M39: 子公司8 | N39: 子公司9 | O39: 子公司10 | P39: 子公司11 | Q39: 子公司12
A40: =A31 -> 房屋及建筑物 | B40: =D40-C40 -> 0 | D40: =SUM(E40:Q40) -> 0 | E40: 0
A41: =A32 -> 机器设备 | B41: =D41-C41 -> 0 | D41: =SUM(E41:Q41) -> 0 | E41: 0
A42: =A33 -> 运输设备 | B42: =D42-C42 -> 0 | D42: =SUM(E42:Q42) -> 0 | E42: 0
A43: =A34 -> 电子设备 | B43: =D43-C43 -> 0 | D43: =SUM(E43:Q43) -> 0 | E43: 0
A44: =A35 -> 其他 | B44: =D44-C44 -> 0 | D44: =SUM(E44:Q44) -> 0 | E44: 0
A45: 合计 | B45: =SUM(B40:B44) -> 0 | C45: =SUM(C40:C44) -> 0 | D45: =SUM(E45:Q45) -> 0 | E45: =SUM(E40:E44) -> 0 | F45: =SUM(F40:F44) -> 0 | G45: =SUM(G40:G44) -> 0 | H45: =SUM(H40:H44) -> 0 | I45: =SUM(I40:I44) -> 0 | J45: =SUM(J40:J44) -> 0 | K45: =SUM(K40:K44) -> 0 | L45: =SUM(L40:L44) -> 0 | ... Q45: =SUM(Q40:Q44) -> 0
A47: 6、固定资产减少（其他减少）
A48: 项目 | B48: 审定数 | C48: 抵消数 | D48: 汇总 | E48: 母公司审定 | F48: 子公司1 | G48: 子公司2 | H48: 子公司3 | I48: 子公司4 | J48: 子公司5 | K48: 子公司6 | L48: 子公司7 | M48: 子公司8 | N48: 子公司9 | O48: 子公司10 | P48: 子公司11 | Q48: 子公司12
A49: =A40 -> 房屋及建筑物 | B49: =D49-C49 -> 0 | D49: =SUM(E49:Q49) -> 0 | E49: 0
A50: =A41 -> 机器设备 | B50: =D50-C50 -> 0 | D50: =SUM(E50:Q50) -> 0 | E50: 0
A51: =A42 -> 运输设备 | B51: =D51-C51 -> 0 | D51: =SUM(E51:Q51) -> 0 | E51: 0
A52: =A43 -> 电子设备 | B52: =D52-C52 -> 0 | D52: =SUM(E52:Q52) -> 0 | E52: 0
A53: =A44 -> 其他 | B53: =D53-C53 -> 0 | D53: =SUM(E53:Q53) -> 0 | E53: 0
A54: 合计 | B54: =SUM(B49:B53) -> 0 | C54: =SUM(C49:C53) -> 0 | D54: =SUM(E54:Q54) -> 0 | E54: =SUM(E49:E53) -> 0 | F54: =SUM(F49:F53) -> 0 | G54: =SUM(G49:G53) -> 0 | H54: =SUM(H49:H53) -> 0 | I54: =SUM(I49:I53) -> 0 | J54: =SUM(J49:J53) -> 0 | K54: =SUM(K49:K53) -> 0 | L54: =SUM(L49:L53) -> 0 | ... Q54: =SUM(Q49:Q53) -> 0
A56: 7、固定资产原值期末数
A57: 项目 | B57: 审定数 | C57: 抵消数 | D57: 汇总 | E57: 母公司审定 | F57: 子公司1 | G57: 子公司2 | H57: 子公司3 | I57: 子公司4 | J57: 子公司5 | K57: 子公司6 | L57: 子公司7 | M57: 子公司8 | N57: 子公司9 | O57: 子公司10 | P57: 子公司11 | Q57: 子公司12
A58: =A49 -> 房屋及建筑物 | B58: =D58-C58 -> 0 | D58: =SUM(E58:Q58) -> 0 | E58: =E4+E13+E22+E31-E40-E49 -> 0 | F58: =F4+F13+F22+F31-F40-F49 -> 0 | G58: =G4+G13+G22+G31-G40-G49 -> 0 | H58: =H4+H13+H22+H31-H40-H49 -> 0 | I58: =I4+I13+I22+I31-I40-I49 -> 0 | J58: =J4+J13+J22+J31-J40-J49 -> 0 | K58: =K4+K13+K22+K31-K40-K49 -> 0 | L58: =L4+L13+L22+L31-L40-L49 -> 0 | ... Q58: =Q4+Q13+Q22+Q31-Q40-Q49 -> 0
A59: =A50 -> 机器设备 | B59: =D59-C59 -> 0 | D59: =SUM(E59:Q59) -> 0 | E59: =E5+E14+E23+E32-E41-E50 -> 0 | F59: =F5+F14+F23+F32-F41-F50 -> 0 | G59: =G5+G14+G23+G32-G41-G50 -> 0 | H59: =H5+H14+H23+H32-H41-H50 -> 0 | I59: =I5+I14+I23+I32-I41-I50 -> 0 | J59: =J5+J14+J23+J32-J41-J50 -> 0 | K59: =K5+K14+K23+K32-K41-K50 -> 0 | L59: =L5+L14+L23+L32-L41-L50 -> 0 | ... Q59: =Q5+Q14+Q23+Q32-Q41-Q50 -> 0
A60: =A51 -> 运输设备 | B60: =D60-C60 -> 0 | D60: =SUM(E60:Q60) -> 0 | E60: =E6+E15+E24+E33-E42-E51 -> 0 | F60: =F6+F15+F24+F33-F42-F51 -> 0 | G60: =G6+G15+G24+G33-G42-G51 -> 0 | H60: =H6+H15+H24+H33-H42-H51 -> 0 | I60: =I6+I15+I24+I33-I42-I51 -> 0 | J60: =J6+J15+J24+J33-J42-J51 -> 0 | K60: =K6+K15+K24+K33-K42-K51 -> 0 | L60: =L6+L15+L24+L33-L42-L51 -> 0 | ... Q60: =Q6+Q15+Q24+Q33-Q42-Q51 -> 0
A61: =A52 -> 电子设备 | B61: =D61-C61 -> 0 | D61: =SUM(E61:Q61) -> 0 | E61: =E7+E16+E25+E34-E43-E52 -> 0 | F61: =F7+F16+F25+F34-F43-F52 -> 0 | G61: =G7+G16+G25+G34-G43-G52 -> 0 | H61: =H7+H16+H25+H34-H43-H52 -> 0 | I61: =I7+I16+I25+I34-I43-I52 -> 0 | J61: =J7+J16+J25+J34-J43-J52 -> 0 | K61: =K7+K16+K25+K34-K43-K52 -> 0 | L61: =L7+L16+L25+L34-L43-L52 -> 0 | ... Q61: =Q7+Q16+Q25+Q34-Q43-Q52 -> 0
A62: =A53 -> 其他 | B62: =D62-C62 -> 0 | D62: =SUM(E62:Q62) -> 0 | E62: =E8+E17+E26+E35-E44-E53 -> 0 | F62: =F8+F17+F26+F35-F44-F53 -> 0 | G62: =G8+G17+G26+G35-G44-G53 -> 0 | H62: =H8+H17+H26+H35-H44-H53 -> 0 | I62: =I8+I17+I26+I35-I44-I53 -> 0 | J62: =J8+J17+J26+J35-J44-J53 -> 0 | K62: =K8+K17+K26+K35-K44-K53 -> 0 | L62: =L8+L17+L26+L35-L44-L53 -> 0 | ... Q62: =Q8+Q17+Q26+Q35-Q44-Q53 -> 0
A63: 合计 | B63: =SUM(B58:B62) -> 0 | C63: =SUM(C58:C62) -> 0 | D63: =SUM(E63:Q63) -> 0 | E63: =SUM(E58:E62) -> 0 | F63: =SUM(F58:F62) -> 0 | G63: =SUM(G58:G62) -> 0 | H63: =SUM(H58:H62) -> 0 | I63: =SUM(I58:I62) -> 0 | J63: =SUM(J58:J62) -> 0 | K63: =SUM(K58:K62) -> 0 | L63: =SUM(L58:L62) -> 0 | ... Q63: =SUM(Q58:Q62) -> 0
A65: 固定资产累计折旧
A66: 1、累计折旧期初数
A67: 项目 | B67: 审定数 | C67: 抵消数 | D67: 汇总 | E67: 母公司审定 | F67: 子公司1 | G67: 子公司2 | H67: 子公司3 | I67: 子公司4 | J67: 子公司5 | K67: 子公司6 | L67: 子公司7 | M67: 子公司8 | N67: 子公司9 | O67: 子公司10 | P67: 子公司11 | Q67: 子公司12
A68: =A58 -> 房屋及建筑物 | B68: =D68-C68 -> 0 | D68: =SUM(E68:Q68) -> 0 | E68: 0
A69: =A59 -> 机器设备 | B69: =D69-C69 -> 0 | D69: =SUM(E69:Q69) -> 0 | E69: 0
A70: =A60 -> 运输设备 | B70: =D70-C70 -> 0 | D70: =SUM(E70:Q70) -> 0 | E70: 0
A71: =A61 -> 电子设备 | B71: =D71-C71 -> 0 | D71: =SUM(E71:Q71) -> 0 | E71: 0
A72: =A62 -> 其他 | B72: =D72-C72 -> 0 | D72: =SUM(E72:Q72) -> 0 | E72: 0
A73: 合计 | B73: =SUM(B68:B72) -> 0 | C73: =SUM(C68:C72) -> 0 | D73: =SUM(E73:Q73) -> 0 | E73: =SUM(E68:E72) -> 0 | F73: =SUM(F68:F72) -> 0 | G73: =SUM(G68:G72) -> 0 | H73: =SUM(H68:H72) -> 0 | I73: =SUM(I68:I72) -> 0 | J73: =SUM(J68:J72) -> 0 | K73: =SUM(K68:K72) -> 0 | L73: =SUM(L68:L72) -> 0 | ... Q73: =SUM(Q68:Q72) -> 0
A75: 2、累计折旧本期增加（计提或摊销）
A76: 项目 | B76: 审定数 | C76: 抵消数 | D76: 汇总 | E76: 母公司审定 | F76: 子公司1 | G76: 子公司2 | H76: 子公司3 | I76: 子公司4 | J76: 子公司5 | K76: 子公司6 | L76: 子公司7 | M76: 子公司8 | N76: 子公司9 | O76: 子公司10 | P76: 子公司11 | Q76: 子公司12
A77: =A68 -> 房屋及建筑物 | B77: =D77-C77 -> 0 | D77: =SUM(E77:Q77) -> 0 | E77: 0
A78: =A69 -> 机器设备 | B78: =D78-C78 -> 0 | D78: =SUM(E78:Q78) -> 0 | E78: 0
A79: =A70 -> 运输设备 | B79: =D79-C79 -> 0 | D79: =SUM(E79:Q79) -> 0 | E79: 0
A80: =A71 -> 电子设备 | B80: =D80-C80 -> 0 | D80: =SUM(E80:Q80) -> 0 | E80: 0
A81: =A72 -> 其他 | B81: =D81-C81 -> 0 | D81: =SUM(E81:Q81) -> 0 | E81: 0
A82: 合计 | B82: =SUM(B77:B81) -> 0 | C82: =SUM(C77:C81) -> 0 | D82: =SUM(E82:Q82) -> 0 | E82: =SUM(E77:E81) -> 0 | F82: =SUM(F77:F81) -> 0 | G82: =SUM(G77:G81) -> 0 | H82: =SUM(H77:H81) -> 0 | I82: =SUM(I77:I81) -> 0 | J82: =SUM(J77:J81) -> 0 | K82: =SUM(K77:K81) -> 0 | L82: =SUM(L77:L81) -> 0 | ... Q82: =SUM(Q77:Q81) -> 0
A84: 3、累计折旧本期增加（其他增加）
A85: 项目 | B85: 审定数 | C85: 抵消数 | D85: 汇总 | E85: 母公司审定 | F85: 子公司1 | G85: 子公司2 | H85: 子公司3 | I85: 子公司4 | J85: 子公司5 | K85: 子公司6 | L85: 子公司7 | M85: 子公司8 | N85: 子公司9 | O85: 子公司10 | P85: 子公司11 | Q85: 子公司12
A86: =A68 -> 房屋及建筑物 | B86: =D86-C86 -> 0 | D86: =SUM(E86:Q86) -> 0 | E86: 0
A87: =A69 -> 机器设备 | B87: =D87-C87 -> 0 | D87: =SUM(E87:Q87) -> 0 | E87: 0
A88: =A70 -> 运输设备 | B88: =D88-C88 -> 0 | D88: =SUM(E88:Q88) -> 0 | E88: 0
A89: =A71 -> 电子设备 | B89: =D89-C89 -> 0 | D89: =SUM(E89:Q89) -> 0 | E89: 0
A90: =A72 -> 其他 | B90: =D90-C90 -> 0 | D90: =SUM(E90:Q90) -> 0 | E90: 0
A91: 合计 | B91: =SUM(B86:B90) -> 0 | C91: =SUM(C86:C90) -> 0 | D91: =SUM(E91:Q91) -> 0 | E91: =SUM(E86:E90) -> 0 | F91: =SUM(F86:F90) -> 0 | G91: =SUM(G86:G90) -> 0 | H91: =SUM(H86:H90) -> 0 | I91: =SUM(I86:I90) -> 0 | J91: =SUM(J86:J90) -> 0 | K91: =SUM(K86:K90) -> 0 | L91: =SUM(L86:L90) -> 0 | ... Q91: =SUM(Q86:Q90) -> 0
A93: 5、累计折旧本期减少（处置或报废）
A94: 项目 | B94: 审定数 | C94: 抵消数 | D94: 汇总 | E94: 母公司审定 | F94: 子公司1 | G94: 子公司2 | H94: 子公司3 | I94: 子公司4 | J94: 子公司5 | K94: 子公司6 | L94: 子公司7 | M94: 子公司8 | N94: 子公司9 | O94: 子公司10 | P94: 子公司11 | Q94: 子公司12
A95: =A86 -> 房屋及建筑物 | B95: =D95-C95 -> 0 | D95: =SUM(E95:Q95) -> 0 | E95: 0
A96: =A87 -> 机器设备 | B96: =D96-C96 -> 0 | D96: =SUM(E96:Q96) -> 0 | E96: 0
A97: =A88 -> 运输设备 | B97: =D97-C97 -> 0 | D97: =SUM(E97:Q97) -> 0 | E97: 0
A98: =A89 -> 电子设备 | B98: =D98-C98 -> 0 | D98: =SUM(E98:Q98) -> 0 | E98: 0
A99: =A90 -> 其他 | B99: =D99-C99 -> 0 | D99: =SUM(E99:Q99) -> 0 | E99: 0
A100: 合计 | B100: =SUM(B95:B99) -> 0 | C100: =SUM(C95:C99) -> 0 | D100: =SUM(E100:Q100) -> 0 | E100: =SUM(E95:E99) -> 0 | F100: =SUM(F95:F99) -> 0 | G100: =SUM(G95:G99) -> 0 | H100: =SUM(H95:H99) -> 0 | I100: =SUM(I95:I99) -> 0 | J100: =SUM(J95:J99) -> 0 | K100: =SUM(K95:K99) -> 0 | L100: =SUM(L95:L99) -> 0 | ... Q100: =SUM(Q95:Q99) -> 0
A102: 6、累计折旧本期减少（其他减少）
A103: 项目 | B103: 审定数 | C103: 抵消数 | D103: 汇总 | E103: 母公司审定 | F103: 子公司1 | G103: 子公司2 | H103: 子公司3 | I103: 子公司4 | J103: 子公司5 | K103: 子公司6 | L103: 子公司7 | M103: 子公司8 | N103: 子公司9 | O103: 子公司10 | P103: 子公司11 | Q103: 子公司12
A104: =A95 -> 房屋及建筑物 | B104: =D104-C104 -> 0 | D104: =SUM(E104:Q104) -> 0 | E104: 0
A105: =A96 -> 机器设备 | B105: =D105-C105 -> 0 | D105: =SUM(E105:Q105) -> 0 | E105: 0
A106: =A97 -> 运输设备 | B106: =D106-C106 -> 0 | D106: =SUM(E106:Q106) -> 0 | E106: 0
A107: =A98 -> 电子设备 | B107: =D107-C107 -> 0 | D107: =SUM(E107:Q107) -> 0 | E107: 0
A108: =A99 -> 其他 | B108: =D108-C108 -> 0 | D108: =SUM(E108:Q108) -> 0 | E108: 0
A109: 合计 | B109: =SUM(B104:B108) -> 0 | C109: =SUM(C104:C108) -> 0 | D109: =SUM(E109:Q109) -> 0 | E109: =SUM(E104:E108) -> 0 | F109: =SUM(F104:F108) -> 0 | G109: =SUM(G104:G108) -> 0 | H109: =SUM(H104:H108) -> 0 | I109: =SUM(I104:I108) -> 0 | J109: =SUM(J104:J108) -> 0 | K109: =SUM(K104:K108) -> 0 | L109: =SUM(L104:L108) -> 0 | ... Q109: =SUM(Q104:Q108) -> 0
A111: 7、累计折旧期末余额
A112: 项目 | B112: 审定数 | C112: 抵消数 | D112: 汇总 | E112: 母公司审定 | F112: 子公司1 | G112: 子公司2 | H112: 子公司3 | I112: 子公司4 | J112: 子公司5 | K112: 子公司6 | L112: 子公司7 | M112: 子公司8 | N112: 子公司9 | O112: 子公司10 | P112: 子公司11 | Q112: 子公司12
...

Sheet 固定资产清理
A1: 固定资产清理附注 | D1: 返回Excel目录 | E1: 返回word附注
A2: 项 目 | B2: 审定数 | C2: 抵消数 | D2: 汇总 | E2: 母公司审定 | F2: 子公司1 | G2: 子公司2 | H2: 子公司3 | I2: 子公司4 | J2: 子公司5 | K2: 子公司6 | L2: 子公司7 | M2: 子公司8 | N2: 子公司9 | O2: 子公司10 | P2: 子公司11 | Q2: 子公司12
B3: =D3-C3 -> 0 | D3: =SUM(E3:Q3) -> 0 | E3: 0
B4: =D4-C4 -> 0 | D4: =SUM(E4:Q4) -> 0 | E4: 0
B5: =D5-C5 -> 0 | D5: =SUM(E5:Q5) -> 0 | E5: 0
B6: =D6-C6 -> 0 | D6: =SUM(E6:Q6) -> 0 | E6: 0
B7: =D7-C7 -> 0 | D7: =SUM(E7:Q7) -> 0 | E7: 0
B8: =D8-C8 -> 0 | D8: =SUM(E8:Q8) -> 0 | E8: 0
A9: 合计 | B9: =SUM(B3:B8) -> 0 | C9: =SUM(C3:C8) -> 0 | D9: =SUM(D3:D8) -> 0 | E9: =SUM(E3:E8) -> 0 | F9: =SUM(F3:F8) -> 0 | G9: =SUM(G3:G8) -> 0 | H9: =SUM(H3:H8) -> 0 | I9: =SUM(I3:I8) -> 0 | ... Q9: =SUM(Q3:Q8) -> 0
A10: 试算表链接： | B10: 0 | D10: =SUM(E10:Q10) -> 0 | E10: 0
A11: 差异 | B11: =B9-B10 -> 0 | D11: =D9-D10 -> 0 | E11: =E9-E10 -> 0 | F11: =F9-F10 -> 0 | G11: =G9-G10 -> 0 | H11: =H9-H10 -> 0 | I11: =I9-I10 -> 0 | J11: =J9-J10 -> 0 | K11: =K9-K10 -> 0 | ... Q11: =Q9-Q10 -> 0
A14: 说明：（转入固定资产清理起始时间已超过1年的固定资产清理进展情况）

Sheet 在建工程及工程物资
A1: 在建工程附注汇总 | D1: 返回Excel目录 | E1: 返回word附注
A2: 项目 | B2: 审定数 | C2: 抵消数 | D2: 汇总 | E2: 母公司审定 | F2: 子公司1 | G2: 子公司2 | H2: 子公司3 | I2: 子公司4 | J2: 子公司5 | K2: 子公司6 | L2: 子公司7 | M2: 子公司8 | N2: 子公司9 | O2: 子公司10 | P2: 子公司11 | Q2: 子公司12
A3: 在建工程 | B3: =D3-C3 -> 0 | D3: =SUM(E3:Q3) -> 0 | E3: =在建工程!E27 -> 0 | F3: =在建工程!F27 -> 0 | G3: =在建工程!G27 -> 0 | H3: =在建工程!H27 -> 0 | I3: =在建工程!I27 -> 0 | J3: =在建工程!J27 -> 0 | K3: =在建工程!K27 -> 0 | L3: =在建工程!L27 -> 0 | ... Q3: =在建工程!Q27 -> 0
A4: 工程物资 | B4: =D4-C4 -> 0 | D4: =SUM(E4:Q4) -> 0 | E4: =工程物资!E93 -> 0 | F4: =工程物资!F93 -> 0 | G4: =工程物资!G93 -> 0 | H4: =工程物资!H93 -> 0 | I4: =工程物资!I93 -> 0 | J4: =工程物资!J93 -> 0 | K4: =工程物资!K93 -> 0 | L4: =工程物资!L93 -> 0 | ... Q4: =工程物资!Q93 -> 0
A5: 合计 | B5: =SUM(B3:B4) -> 0 | C5: =SUM(C3:C4) -> 0 | D5: =SUM(E5:Q5) -> 0 | E5: =SUM(E3:E4) -> 0 | F5: =SUM(F3:F4) -> 0 | G5: =SUM(G3:G4) -> 0 | H5: =SUM(H3:H4) -> 0 | I5: =SUM(I3:I4) -> 0 | J5: =SUM(J3:J4) -> 0 | K5: =SUM(K3:K4) -> 0 | L5: =SUM(L3:L4) -> 0 | ... Q5: =SUM(Q3:Q4) -> 0

Sheet 在建工程
A1: 在建工程附注汇总 | D1: 返回Excel目录 | E1: 返回word附注
A2: 1、在建工程期末账面原值
A3: 项目 | B3: 审定数 | C3: 抵消数 | D3: 汇总 | E3: 母公司审定 | F3: 子公司1 | G3: 子公司2 | H3: 子公司3 | I3: 子公司4 | J3: 子公司5 | K3: 子公司6 | L3: 子公司7 | M3: 子公司8 | N3: 子公司9 | O3: 子公司10 | P3: 子公司11 | Q3: 子公司12
B4: =D4-C4 -> 0 | D4: =SUM(E4:Q4) -> 0 | E4: 0
B5: =D5-C5 -> 0 | D5: =SUM(E5:Q5) -> 0 | E5: 0
B6: =D6-C6 -> 0 | D6: =SUM(E6:Q6) -> 0 | E6: 0
B7: =D7-C7 -> 0 | D7: =SUM(E7:Q7) -> 0 | E7: 0
B8: =D8-C8 -> 0 | D8: =SUM(E8:Q8) -> 0 | E8: 0
A9: 合计 | B9: =SUM(B4:B8) -> 0 | C9: =SUM(C4:C8) -> 0 | D9: =SUM(E9:Q9) -> 0 | E9: =SUM(E4:E8) -> 0 | F9: =SUM(F4:F8) -> 0 | G9: =SUM(G4:G8) -> 0 | H9: =SUM(H4:H8) -> 0 | I9: =SUM(I4:I8) -> 0 | J9: =SUM(J4:J8) -> 0 | K9: =SUM(K4:K8) -> 0 | L9: =SUM(L4:L8) -> 0 | ... Q9: =SUM(Q4:Q8) -> 0
A11: 2、在建工程期末减值准备
A12: 项目 | B12: 审定数 | C12: 抵消数 | D12: 汇总 | E12: 母公司审定 | F12: 子公司1 | G12: 子公司2 | H12: 子公司3 | I12: 子公司4 | J12: 子公司5 | K12: 子公司6 | L12: 子公司7 | M12: 子公司8 | N12: 子公司9 | O12: 子公司10 | P12: 子公司11 | Q12: 子公司12
B13: =D13-C13 -> 0 | D13: =SUM(E13:Q13) -> 0 | E13: 0
B14: =D14-C14 -> 0 | D14: =SUM(E14:Q14) -> 0 | E14: 0
B15: =D15-C15 -> 0 | D15: =SUM(E15:Q15) -> 0 | E15: 0
B16: =D16-C16 -> 0 | D16: =SUM(E16:Q16) -> 0 | E16: 0
B17: =D17-C17 -> 0 | D17: =SUM(E17:Q17) -> 0 | E17: 0
A18: 合计 | B18: =SUM(B13:B17) -> 0 | C18: =SUM(C13:C17) -> 0 | D18: =SUM(E18:Q18) -> 0 | E18: =SUM(E13:E17) -> 0 | F18: =SUM(F13:F17) -> 0 | G18: =SUM(G13:G17) -> 0 | H18: =SUM(H13:H17) -> 0 | I18: =SUM(I13:I17) -> 0 | J18: =SUM(J13:J17) -> 0 | K18: =SUM(K13:K17) -> 0 | L18: =SUM(L13:L17) -> 0 | ... Q18: =SUM(Q13:Q17) -> 0
A20: 3、在建工程期末账面净值
A21: 项目 | B21: 审定数 | C21: 抵消数 | D21: 汇总 | E21: 母公司审定 | F21: 子公司1 | G21: 子公司2 | H21: 子公司3 | I21: 子公司4 | J21: 子公司5 | K21: 子公司6 | L21: 子公司7 | M21: 子公司8 | N21: 子公司9 | O21: 子公司10 | P21: 子公司11 | Q21: 子公司12
B22: =D22-C22 -> 0 | D22: =SUM(E22:Q22) -> 0 | E22: =E4-E13 -> 0 | F22: =F4-F13 -> 0 | G22: =G4-G13 -> 0 | H22: =H4-H13 -> 0 | I22: =I4-I13 -> 0 | J22: =J4-J13 -> 0 | K22: =K4-K13 -> 0 | L22: =L4-L13 -> 0 | ... Q22: =Q4-Q13 -> 0
B23: =D23-C23 -> 0 | D23: =SUM(E23:Q23) -> 0 | E23: =E5-E14 -> 0 | F23: =F5-F14 -> 0 | G23: =G5-G14 -> 0 | H23: =H5-H14 -> 0 | I23: =I5-I14 -> 0 | J23: =J5-J14 -> 0 | K23: =K5-K14 -> 0 | L23: =L5-L14 -> 0 | ... Q23: =Q5-Q14 -> 0
B24: =D24-C24 -> 0 | D24: =SUM(E24:Q24) -> 0 | E24: =E6-E15 -> 0 | F24: =F6-F15 -> 0 | G24: =G6-G15 -> 0 | H24: =H6-H15 -> 0 | I24: =I6-I15 -> 0 | J24: =J6-J15 -> 0 | K24: =K6-K15 -> 0 | L24: =L6-L15 -> 0 | ... Q24: =Q6-Q15 -> 0
B25: =D25-C25 -> 0 | D25: =SUM(E25:Q25) -> 0 | E25: =E7-E16 -> 0 | F25: =F7-F16 -> 0 | G25: =G7-G16 -> 0 | H25: =H7-H16 -> 0 | I25: =I7-I16 -> 0 | J25: =J7-J16 -> 0 | K25: =K7-K16 -> 0 | L25: =L7-L16 -> 0 | ... Q25: =Q7-Q16 -> 0
B26: =D26-C26 -> 0 | D26: =SUM(E26:Q26) -> 0 | E26: =E8-E17 -> 0 | F26: =F8-F17 -> 0 | G26: =G8-G17 -> 0 | H26: =H8-H17 -> 0 | I26: =I8-I17 -> 0 | J26: =J8-J17 -> 0 | K26: =K8-K17 -> 0 | L26: =L8-L17 -> 0 | ... Q26: =Q8-Q17 -> 0
A27: 合计 | B27: =SUM(B22:B26) -> 0 | C27: =SUM(C22:C26) -> 0 | D27: =SUM(E27:Q27) -> 0 | E27: =SUM(E22:E26) -> 0 | F27: =SUM(F22:F26) -> 0 | G27: =SUM(G22:G26) -> 0 | H27: =SUM(H22:H26) -> 0 | I27: =SUM(I22:I26) -> 0 | J27: =SUM(J22:J26) -> 0 | K27: =SUM(K22:K26) -> 0 | L27: =SUM(L22:L26) -> 0 | ... Q27: =SUM(Q22:Q26) -> 0
A28: 试算表链接： | B28: 0 | D28: =SUM(E28:Q28) -> 0 | E28: 0
A29: 差异 | B29: =B27-B28 -> 0 | D29: =D27-D28 -> 0 | E29: =E27-E28 -> 0 | F29: =F27-F28 -> 0 | G29: =G27-G28 -> 0 | H29: =H27-H28 -> 0 | I29: =I27-I28 -> 0 | J29: =J27-J28 -> 0 | K29: =K27-K28 -> 0 | ... Q29: =Q27-Q28 -> 0
A32: （2）重要在建工程项目变动情况
A33: 单位 | B33: 工程名称 | C33: 期初数 | D33: 本期增加 | E33: 转入固定资产 | F33: 其他减少 | G33: 利息资本化累计金额 | H33: 其中：本期利息资本化金额 | I33: 本期利息资本化率% | J33: 期末数 | K33: 预算数 | L33: 工程累计投入占预算比例% | M33: 工程进度 | N33: 资金来源
A34: 母公司 | C34: A | D34: B | E34: C | F34: D | J34: E=A+B-C-D
A35: 子公司1
A43: 合 计 | C43: =SUM(C34:C42) -> 0 | D43: =SUM(D34:D42) -> 0 | E43: =SUM(E34:E42) -> 0 | F43: =SUM(F34:F42) -> 0 | G43: =SUM(G34:G42) -> 0 | H43: =SUM(H34:H42) -> 0 | I43: =SUM(I34:I42) -> 0 | J43: =SUM(J34:J42) -> 0 | ... N43: =SUM(N34:N42) -> 0
A45: （3）在建工程减值准备
A46: 单位 | B46: 项 目 | C46: 本期计提金额 | D46: 计提原因
A47: 母公司
A48: 子公司1
A53: 合 计 | C53: =SUM(C47:C52) -> 0

Sheet 工程物资
A1: 工程物资附注 | D1: 返回Excel目录 | E1: 返回word附注
A2: 工程物资原值
A3: 1、期初金额
A4: 项 目 | B4: 审定数 | C4: 抵消数 | D4: 汇总 | E4: 母公司审定 | F4: 子公司1 | G4: 子公司2 | H4: 子公司3 | I4: 子公司4 | J4: 子公司5 | K4: 子公司6 | L4: 子公司7 | M4: 子公司8 | N4: 子公司9 | O4: 子公司10 | P4: 子公司11 | Q4: 子公司12
A5: 专用材料 | B5: =D5-C5 -> 0 | D5: =SUM(E5:Q5) -> 0 | E5: 0
A6: 专用设备 | B6: =D6-C6 -> 0 | D6: =SUM(E6:Q6) -> 0 | E6: 0
A7: 工器具 | B7: =D7-C7 -> 0 | D7: =SUM(E7:Q7) -> 0 | E7: 0
A8: 合计 | B8: =SUM(B5:B7) -> 0 | C8: =SUM(C5:C7) -> 0 | D8: =SUM(D5:D7) -> 0 | E8: =SUM(E5:E7) -> 0 | F8: =SUM(F5:F7) -> 0 | G8: =SUM(G5:G7) -> 0 | H8: =SUM(H5:H7) -> 0 | I8: =SUM(I5:I7) -> 0 | ... Q8: =SUM(Q5:Q7) -> 0
A10: 2、本期增加
A11: 项 目 | B11: 审定数 | C11: 抵消数 | D11: 汇总 | E11: 母公司审定 | F11: 子公司1 | G11: 子公司2 | H11: 子公司3 | I11: 子公司4 | J11: 子公司5 | K11: 子公司6 | L11: 子公司7 | M11: 子公司8 | N11: 子公司9 | O11: 子公司10 | P11: 子公司11 | Q11: 子公司12
A12: =A5 -> 专用材料 | B12: =D12-C12 -> 0 | D12: =SUM(E12:Q12) -> 0 | E12: 0
A13: =A6 -> 专用设备 | B13: =D13-C13 -> 0 | D13: =SUM(E13:Q13) -> 0 | E13: 0
A14: =A7 -> 工器具 | B14: =D14-C14 -> 0 | D14: =SUM(E14:Q14) -> 0 | E14: 0
A15: 合计 | B15: =SUM(B12:B14) -> 0 | C15: =SUM(C12:C14) -> 0 | D15: =SUM(D12:D14) -> 0 | E15: =SUM(E12:E14) -> 0 | F15: =SUM(F12:F14) -> 0 | G15: =SUM(G12:G14) -> 0 | H15: =SUM(H12:H14) -> 0 | I15: =SUM(I12:I14) -> 0 | ... Q15: =SUM(Q12:Q14) -> 0
A17: 3、本期减少
A18: 项 目 | B18: 审定数 | C18: 抵消数 | D18: 汇总 | E18: 母公司审定 | F18: 子公司1 | G18: 子公司2 | H18: 子公司3 | I18: 子公司4 | J18: 子公司5 | K18: 子公司6 | L18: 子公司7 | M18: 子公司8 | N18: 子公司9 | O18: 子公司10 | P18: 子公司11 | Q18: 子公司12
A19: =A12 -> 专用材料 | B19: =D19-C19 -> 0 | D19: =SUM(E19:Q19) -> 0 | E19: 0
A20: =A13 -> 专用设备 | B20: =D20-C20 -> 0 | D20: =SUM(E20:Q20) -> 0 | E20: 0
A21: =A14 -> 工器具 | B21: =D21-C21 -> 0 | D21: =SUM(E21:Q21) -> 0 | E21: 0
A22: 合计 | B22: =SUM(B19:B21) -> 0 | C22: =SUM(C19:C21) -> 0 | D22: =SUM(D19:D21) -> 0 | E22: =SUM(E19:E21) -> 0 | F22: =SUM(F19:F21) -> 0 | G22: =SUM(G19:G21) -> 0 | H22: =SUM(H19:H21) -> 0 | I22: =SUM(I19:I21) -> 0 | ... Q22: =SUM(Q19:Q21) -> 0
A24: 4、期末金额
A25: 项 目 | B25: 审定数 | C25: 抵消数 | D25: 汇总 | E25: 母公司审定 | F25: 子公司1 | G25: 子公司2 | H25: 子公司3 | I25: 子公司4 | J25: 子公司5 | K25: 子公司6 | L25: 子公司7 | M25: 子公司8 | N25: 子公司9 | O25: 子公司10 | P25: 子公司11 | Q25: 子公司12
A26: =A19 -> 专用材料 | B26: =D26-C26 -> 0 | D26: =SUM(E26:Q26) -> 0 | E26: =E5+E12-E19 -> 0 | F26: =F5+F12-F19 -> 0 | G26: =G5+G12-G19 -> 0 | H26: =H5+H12-H19 -> 0 | I26: =I5+I12-I19 -> 0 | J26: =J5+J12-J19 -> 0 | K26: =K5+K12-K19 -> 0 | L26: =L5+L12-L19 -> 0 | ... Q26: =Q5+Q12-Q19 -> 0
A27: =A20 -> 专用设备 | B27: =D27-C27 -> 0 | D27: =SUM(E27:Q27) -> 0 | E27: =E6+E13-E20 -> 0 | F27: =F6+F13-F20 -> 0 | G27: =G6+G13-G20 -> 0 | H27: =H6+H13-H20 -> 0 | I27: =I6+I13-I20 -> 0 | J27: =J6+J13-J20 -> 0 | K27: =K6+K13-K20 -> 0 | L27: =L6+L13-L20 -> 0 | ... Q27: =Q6+Q13-Q20 -> 0
A28: =A21 -> 工器具 | B28: =D28-C28 -> 0 | D28: =SUM(E28:Q28) -> 0 | E28: =E7+E14-E21 -> 0 | F28: =F7+F14-F21 -> 0 | G28: =G7+G14-G21 -> 0 | H28: =H7+H14-H21 -> 0 | I28: =I7+I14-I21 -> 0 | J28: =J7+J14-J21 -> 0 | K28: =K7+K14-K21 -> 0 | L28: =L7+L14-L21 -> 0 | ... Q28: =Q7+Q14-Q21 -> 0
A29: 合计 | B29: =SUM(B26:B28) -> 0 | C29: =SUM(C26:C28) -> 0 | D29: =SUM(D26:D28) -> 0 | E29: =SUM(E26:E28) -> 0 | F29: =SUM(F26:F28) -> 0 | G29: =SUM(G26:G28) -> 0 | H29: =SUM(H26:H28) -> 0 | I29: =SUM(I26:I28) -> 0 | ... Q29: =SUM(Q26:Q28) -> 0
A31: 工程物资减值准备
A32: 1、期初金额
A33: 项 目 | B33: 审定数 | C33: 抵消数 | D33: 汇总 | E33: 母公司审定 | F33: 子公司1 | G33: 子公司2 | H33: 子公司3 | I33: 子公司4 | J33: 子公司5 | K33: 子公司6 | L33: 子公司7 | M33: 子公司8 | N33: 子公司9 | O33: 子公司10 | P33: 子公司11 | Q33: 子公司12
A34: 专用材料 | B34: =D34-C34 -> 0 | D34: =SUM(E34:Q34) -> 0 | E34: 0
A35: 专用设备 | B35: =D35-C35 -> 0 | D35: =SUM(E35:Q35) -> 0 | E35: 0
A36: 工器具 | B36: =D36-C36 -> 0 | D36: =SUM(E36:Q36) -> 0 | E36: 0
A37: 合计 | B37: =SUM(B34:B36) -> 0 | C37: =SUM(C34:C36) -> 0 | D37: =SUM(D34:D36) -> 0 | E37: =SUM(E34:E36) -> 0 | F37: =SUM(F34:F36) -> 0 | G37: =SUM(G34:G36) -> 0 | H37: =SUM(H34:H36) -> 0 | I37: =SUM(I34:I36) -> 0 | ... Q37: =SUM(Q34:Q36) -> 0
A39: 2、本期增加（计提）
A40: 项 目 | B40: 审定数 | C40: 抵消数 | D40: 汇总 | E40: 母公司审定 | F40: 子公司1 | G40: 子公司2 | H40: 子公司3 | I40: 子公司4 | J40: 子公司5 | K40: 子公司6 | L40: 子公司7 | M40: 子公司8 | N40: 子公司9 | O40: 子公司10 | P40: 子公司11 | Q40: 子公司12
A41: =A34 -> 专用材料 | B41: =D41-C41 -> 0 | D41: =SUM(E41:Q41) -> 0 | E41: 0
A42: =A35 -> 专用设备 | B42: =D42-C42 -> 0 | D42: =SUM(E42:Q42) -> 0 | E42: 0
A43: =A36 -> 工器具 | B43: =D43-C43 -> 0 | D43: =SUM(E43:Q43) -> 0 | E43: 0
A44: 合计 | B44: =SUM(B41:B43) -> 0 | C44: =SUM(C41:C43) -> 0 | D44: =SUM(D41:D43) -> 0 | E44: =SUM(E41:E43) -> 0 | F44: =SUM(F41:F43) -> 0 | G44: =SUM(G41:G43) -> 0 | H44: =SUM(H41:H43) -> 0 | I44: =SUM(I41:I43) -> 0 | ... Q44: =SUM(Q41:Q43) -> 0
A46: 3、本期增加（其他）
A47: 项 目 | B47: 审定数 | C47: 抵消数 | D47: 汇总 | E47: 母公司审定 | F47: 子公司1 | G47: 子公司2 | H47: 子公司3 | I47: 子公司4 | J47: 子公司5 | K47: 子公司6 | L47: 子公司7 | M47: 子公司8 | N47: 子公司9 | O47: 子公司10 | P47: 子公司11 | Q47: 子公司12
A48: =A41 -> 专用材料 | B48: =D48-C48 -> 0 | D48: =SUM(E48:Q48) -> 0 | E48: 0
A49: =A42 -> 专用设备 | B49: =D49-C49 -> 0 | D49: =SUM(E49:Q49) -> 0 | E49: 0
A50: =A43 -> 工器具 | B50: =D50-C50 -> 0 | D50: =SUM(E50:Q50) -> 0 | E50: 0
A51: 合计 | B51: =SUM(B48:B50) -> 0 | C51: =SUM(C48:C50) -> 0 | D51: =SUM(D48:D50) -> 0 | E51: =SUM(E48:E50) -> 0 | F51: =SUM(F48:F50) -> 0 | G51: =SUM(G48:G50) -> 0 | H51: =SUM(H48:H50) -> 0 | I51: =SUM(I48:I50) -> 0 | ... Q51: =SUM(Q48:Q50) -> 0
A53: 4、本期减少（转回）
A54: 项 目 | B54: 审定数 | C54: 抵消数 | D54: 汇总 | E54: 母公司审定 | F54: 子公司1 | G54: 子公司2 | H54: 子公司3 | I54: 子公司4 | J54: 子公司5 | K54: 子公司6 | L54: 子公司7 | M54: 子公司8 | N54: 子公司9 | O54: 子公司10 | P54: 子公司11 | Q54: 子公司12
A55: =A41 -> 专用材料 | B55: =D55-C55 -> 0 | D55: =SUM(E55:Q55) -> 0 | E55: 0
A56: =A42 -> 专用设备 | B56: =D56-C56 -> 0 | D56: =SUM(E56:Q56) -> 0 | E56: 0
A57: =A43 -> 工器具 | B57: =D57-C57 -> 0 | D57: =SUM(E57:Q57) -> 0 | E57: 0
A58: 合计 | B58: =SUM(B55:B57) -> 0 | C58: =SUM(C55:C57) -> 0 | D58: =SUM(D55:D57) -> 0 | E58: =SUM(E55:E57) -> 0 | F58: =SUM(F55:F57) -> 0 | G58: =SUM(G55:G57) -> 0 | H58: =SUM(H55:H57) -> 0 | I58: =SUM(I55:I57) -> 0 | ... Q58: =SUM(Q55:Q57) -> 0
A60: 5、本期减少（转销）
A61: 项 目 | B61: 审定数 | C61: 抵消数 | D61: 汇总 | E61: 母公司审定 | F61: 子公司1 | G61: 子公司2 | H61: 子公司3 | I61: 子公司4 | J61: 子公司5 | K61: 子公司6 | L61: 子公司7 | M61: 子公司8 | N61: 子公司9 | O61: 子公司10 | P61: 子公司11 | Q61: 子公司12
A62: =A48 -> 专用材料 | B62: =D62-C62 -> 0 | D62: =SUM(E62:Q62) -> 0 | E62: 0
A63: =A49 -> 专用设备 | B63: =D63-C63 -> 0 | D63: =SUM(E63:Q63) -> 0 | E63: 0
A64: =A50 -> 工器具 | B64: =D64-C64 -> 0 | D64: =SUM(E64:Q64) -> 0 | E64: 0
A65: 合计 | B65: =SUM(B62:B64) -> 0 | C65: =SUM(C62:C64) -> 0 | D65: =SUM(D62:D64) -> 0 | E65: =SUM(E62:E64) -> 0 | F65: =SUM(F62:F64) -> 0 | G65: =SUM(G62:G64) -> 0 | H65: =SUM(H62:H64) -> 0 | I65: =SUM(I62:I64) -> 0 | ... Q65: =SUM(Q62:Q64) -> 0
A67: 6、本期减少（其他）
A68: 项 目 | B68: 审定数 | C68: 抵消数 | D68: 汇总 | E68: 母公司审定 | F68: 子公司1 | G68: 子公司2 | H68: 子公司3 | I68: 子公司4 | J68: 子公司5 | K68: 子公司6 | L68: 子公司7 | M68: 子公司8 | N68: 子公司9 | O68: 子公司10 | P68: 子公司11 | Q68: 子公司12
A69: =A55 -> 专用材料 | B69: =D69-C69 -> 0 | D69: =SUM(E69:Q69) -> 0 | E69: 0
A70: =A56 -> 专用设备 | B70: =D70-C70 -> 0 | D70: =SUM(E70:Q70) -> 0 | E70: 0
A71: =A57 -> 工器具 | B71: =D71-C71 -> 0 | D71: =SUM(E71:Q71) -> 0 | E71: 0
A72: 合计 | B72: =SUM(B69:B71) -> 0 | C72: =SUM(C69:C71) -> 0 | D72: =SUM(D69:D71) -> 0 | E72: =SUM(E69:E71) -> 0 | F72: =SUM(F69:F71) -> 0 | G72: =SUM(G69:G71) -> 0 | H72: =SUM(H69:H71) -> 0 | I72: =SUM(I69:I71) -> 0 | ... Q72: =SUM(Q69:Q71) -> 0
A74: 7、期末金额
A75: 项 目 | B75: 审定数 | C75: 抵消数 | D75: 汇总 | E75: 母公司审定 | F75: 子公司1 | G75: 子公司2 | H75: 子公司3 | I75: 子公司4 | J75: 子公司5 | K75: 子公司6 | L75: 子公司7 | M75: 子公司8 | N75: 子公司9 | O75: 子公司10 | P75: 子公司11 | Q75: 子公司12
A76: =A55 -> 专用材料 | B76: =D76-C76 -> 0 | D76: =SUM(E76:Q76) -> 0 | E76: =E34+E41+E48-E55-E62-E69 -> 0 | F76: =F34+F41+F48-F55-F62-F69 -> 0 | G76: =G34+G41+G48-G55-G62-G69 -> 0 | H76: =H34+H41+H48-H55-H62-H69 -> 0 | I76: =I34+I41+I48-I55-I62-I69 -> 0 | J76: =J34+J41+J48-J55-J62-J69 -> 0 | K76: =K34+K41+K48-K55-K62-K69 -> 0 | L76: =L34+L41+L48-L55-L62-L69 -> 0 | ... Q76: =Q34+Q41+Q48-Q55-Q62-Q69 -> 0
A77: =A56 -> 专用设备 | B77: =D77-C77 -> 0 | D77: =SUM(E77:Q77) -> 0 | E77: =E35+E42+E49-E56-E63-E70 -> 0 | F77: =F35+F42+F49-F56-F63-F70 -> 0 | G77: =G35+G42+G49-G56-G63-G70 -> 0 | H77: =H35+H42+H49-H56-H63-H70 -> 0 | I77: =I35+I42+I49-I56-I63-I70 -> 0 | J77: =J35+J42+J49-J56-J63-J70 -> 0 | K77: =K35+K42+K49-K56-K63-K70 -> 0 | L77: =L35+L42+L49-L56-L63-L70 -> 0 | ... Q77: =Q35+Q42+Q49-Q56-Q63-Q70 -> 0
A78: =A57 -> 工器具 | B78: =D78-C78 -> 0 | D78: =SUM(E78:Q78) -> 0 | E78: =E36+E43+E50-E57-E64-E71 -> 0 | F78: =F36+F43+F50-F57-F64-F71 -> 0 | G78: =G36+G43+G50-G57-G64-G71 -> 0 | H78: =H36+H43+H50-H57-H64-H71 -> 0 | I78: =I36+I43+I50-I57-I64-I71 -> 0 | J78: =J36+J43+J50-J57-J64-J71 -> 0 | K78: =K36+K43+K50-K57-K64-K71 -> 0 | L78: =L36+L43+L50-L57-L64-L71 -> 0 | ... Q78: =Q36+Q43+Q50-Q57-Q64-Q71 -> 0
A79: 合计 | B79: =SUM(B76:B78) -> 0 | C79: =SUM(C76:C78) -> 0 | D79: =SUM(D76:D78) -> 0 | E79: =SUM(E76:E78) -> 0 | F79: =SUM(F76:F78) -> 0 | G79: =SUM(G76:G78) -> 0 | H79: =SUM(H76:H78) -> 0 | I79: =SUM(I76:I78) -> 0 | ... Q79: =SUM(Q76:Q78) -> 0
A81: 工程物资期初净值
A82: 项 目 | B82: 审定数 | C82: 抵消数 | D82: 汇总 | E82: 母公司审定 | F82: 子公司1 | G82: 子公司2 | H82: 子公司3 | I82: 子公司4 | J82: 子公司5 | K82: 子公司6 | L82: 子公司7 | M82: 子公司8 | N82: 子公司9 | O82: 子公司10 | P82: 子公司11 | Q82: 子公司12
A83: =A62 -> 专用材料 | B83: =D83-C83 -> 0 | D83: =SUM(E83:Q83) -> 0 | E83: =E5-E34 -> 0 | F83: =F5-F34 -> 0 | G83: =G5-G34 -> 0 | H83: =H5-H34 -> 0 | I83: =I5-I34 -> 0 | J83: =J5-J34 -> 0 | K83: =K5-K34 -> 0 | L83: =L5-L34 -> 0 | ... Q83: =Q5-Q34 -> 0
A84: =A63 -> 专用设备 | B84: =D84-C84 -> 0 | D84: =SUM(E84:Q84) -> 0 | E84: =E6-E35 -> 0 | F84: =F6-F35 -> 0 | G84: =G6-G35 -> 0 | H84: =H6-H35 -> 0 | I84: =I6-I35 -> 0 | J84: =J6-J35 -> 0 | K84: =K6-K35 -> 0 | L84: =L6-L35 -> 0 | ... Q84: =Q6-Q35 -> 0
A85: =A64 -> 工器具 | B85: =D85-C85 -> 0 | D85: =SUM(E85:Q85) -> 0 | E85: =E7-E36 -> 0 | F85: =F7-F36 -> 0 | G85: =G7-G36 -> 0 | H85: =H7-H36 -> 0 | I85: =I7-I36 -> 0 | J85: =J7-J36 -> 0 | K85: =K7-K36 -> 0 | L85: =L7-L36 -> 0 | ... Q85: =Q7-Q36 -> 0
A86: 合 计 | B86: =SUM(B83:B85) -> 0 | C86: =SUM(C83:C85) -> 0 | D86: =SUM(E86:Q86) -> 0 | E86: =SUM(E83:E85) -> 0 | F86: =SUM(F83:F85) -> 0 | G86: =SUM(G83:G85) -> 0 | H86: =SUM(H83:H85) -> 0 | I86: =SUM(I83:I85) -> 0 | J86: =SUM(J83:J85) -> 0 | K86: =SUM(K83:K85) -> 0 | L86: =SUM(L83:L85) -> 0 | ... Q86: =SUM(Q83:Q85) -> 0
A88: 工程物资期末净值
A89: 项 目 | B89: 审定数 | C89: 抵消数 | D89: 汇总 | E89: 母公司审定 | F89: 子公司1 | G89: 子公司2 | H89: 子公司3 | I89: 子公司4 | J89: 子公司5 | K89: 子公司6 | L89: 子公司7 | M89: 子公司8 | N89: 子公司9 | O89: 子公司10 | P89: 子公司11 | Q89: 子公司12
A90: =A83 -> 专用材料 | B90: =D90-C90 -> 0 | D90: =SUM(E90:Q90) -> 0 | E90: =E26-E76 -> 0 | F90: =F26-F76 -> 0 | G90: =G26-G76 -> 0 | H90: =H26-H76 -> 0 | I90: =I26-I76 -> 0 | J90: =J26-J76 -> 0 | K90: =K26-K76 -> 0 | L90: =L26-L76 -> 0 | ... Q90: =Q26-Q76 -> 0
A91: =A84 -> 专用设备 | B91: =D91-C91 -> 0 | D91: =SUM(E91:Q91) -> 0 | E91: =E27-E77 -> 0 | F91: =F27-F77 -> 0 | G91: =G27-G77 -> 0 | H91: =H27-H77 -> 0 | I91: =I27-I77 -> 0 | J91: =J27-J77 -> 0 | K91: =K27-K77 -> 0 | L91: =L27-L77 -> 0 | ... Q91: =Q27-Q77 -> 0
A92: =A85 -> 工器具 | B92: =D92-C92 -> 0 | D92: =SUM(E92:Q92) -> 0 | E92: =E28-E78 -> 0 | F92: =F28-F78 -> 0 | G92: =G28-G78 -> 0 | H92: =H28-H78 -> 0 | I92: =I28-I78 -> 0 | J92: =J28-J78 -> 0 | K92: =K28-K78 -> 0 | L92: =L28-L78 -> 0 | ... Q92: =Q28-Q78 -> 0
A93: 合 计 | B93: =SUM(B90:B92) -> 0 | C93: =SUM(C90:C92) -> 0 | D93: =SUM(E93:Q93) -> 0 | E93: =SUM(E90:E92) -> 0 | F93: =SUM(F90:F92) -> 0 | G93: =SUM(G90:G92) -> 0 | H93: =SUM(H90:H92) -> 0 | I93: =SUM(I90:I92) -> 0 | J93: =SUM(J90:J92) -> 0 | K93: =SUM(K90:K92) -> 0 | L93: =SUM(L90:L92) -> 0 | ... Q93: =SUM(Q90:Q92) -> 0
A94: 试算表链接： | B94: 0 | D94: =SUM(E94:Q94) -> 0 | E94: 0
A95: 差异 | B95: =B93-B94 -> 0 | D95: =D93-D94 -> 0 | E95: =E93-E94 -> 0 | F95: =F93-F94 -> 0 | G95: =G93-G94 -> 0 | H95: =H93-H94 -> 0 | I95: =I93-I94 -> 0 | J95: =J93-J94 -> 0 | K95: =K93-K94 -> 0 | ... Q95: =Q93-Q94 -> 0

Sheet 生产性生物资产（成本计量）
A1: 生产性生物资产附注 | D1: 返回Excel目录 | E1: 返回word附注
A2: （1）按成本计量的生产性生物资产
A3: 生产性生物资产账面原值
A4: 1、生产性生物资产原值期初数
A5: 项 目 | B5: 审定数 | C5: 抵消数 | D5: 汇总 | E5: 母公司审定 | F5: 子公司1 | G5: 子公司2 | H5: 子公司3 | I5: 子公司4 | J5: 子公司5 | K5: 子公司6 | L5: 子公司7 | M5: 子公司8 | N5: 子公司9 | O5: 子公司10 | P5: 子公司11 | Q5: 子公司12
A6: 种植业 | B6: =D6-C6 -> 0 | D6: =SUM(E6:Q6) -> 0 | E6: 0
A7: 畜牧养殖业 | B7: =D7-C7 -> 0 | D7: =SUM(E7:Q7) -> 0 | E7: 0
A8: 林业 | B8: =D8-C8 -> 0 | D8: =SUM(E8:Q8) -> 0 | E8: 0
A9: 水产业 | B9: =D9-C9 -> 0 | D9: =SUM(E9:Q9) -> 0 | E9: 0
A10: 其他 | B10: =D10-C10 -> 0 | D10: =SUM(E10:Q10) -> 0 | E10: 0
A11: 合计 | B11: =SUM(B6:B10) -> 0 | C11: =SUM(C6:C10) -> 0 | D11: =SUM(E11:Q11) -> 0 | E11: =SUM(E6:E10) -> 0 | F11: =SUM(F6:F10) -> 0 | G11: =SUM(G6:G10) -> 0 | H11: =SUM(H6:H10) -> 0 | I11: =SUM(I6:I10) -> 0 | J11: =SUM(J6:J10) -> 0 | K11: =SUM(K6:K10) -> 0 | L11: =SUM(L6:L10) -> 0 | ... Q11: =SUM(Q6:Q10) -> 0
A13: 2、生产性生物资产本期增加（外购）
A14: 项 目 | B14: 审定数 | C14: 抵消数 | D14: 汇总 | E14: 母公司审定 | F14: 子公司1 | G14: 子公司2 | H14: 子公司3 | I14: 子公司4 | J14: 子公司5 | K14: 子公司6 | L14: 子公司7 | M14: 子公司8 | N14: 子公司9 | O14: 子公司10 | P14: 子公司11 | Q14: 子公司12
A15: =A6 -> 种植业 | B15: =D15-C15 -> 0 | D15: =SUM(E15:Q15) -> 0 | E15: 0
A16: =A7 -> 畜牧养殖业 | B16: =D16-C16 -> 0 | D16: =SUM(E16:Q16) -> 0 | E16: 0
A17: =A8 -> 林业 | B17: =D17-C17 -> 0 | D17: =SUM(E17:Q17) -> 0 | E17: 0
A18: =A9 -> 水产业 | B18: =D18-C18 -> 0 | D18: =SUM(E18:Q18) -> 0 | E18: 0
A19: =A10 -> 其他 | B19: =D19-C19 -> 0 | D19: =SUM(E19:Q19) -> 0 | E19: 0
A20: 合计 | B20: =SUM(B15:B19) -> 0 | C20: =SUM(C15:C19) -> 0 | D20: =SUM(E20:Q20) -> 0 | E20: =SUM(E15:E19) -> 0 | F20: =SUM(F15:F19) -> 0 | G20: =SUM(G15:G19) -> 0 | H20: =SUM(H15:H19) -> 0 | I20: =SUM(I15:I19) -> 0 | J20: =SUM(J15:J19) -> 0 | K20: =SUM(K15:K19) -> 0 | L20: =SUM(L15:L19) -> 0 | ... Q20: =SUM(Q15:Q19) -> 0
A22: 3、生产性生物资产本期增加（自行培育）
A23: 项 目 | B23: 审定数 | C23: 抵消数 | D23: 汇总 | E23: 母公司审定 | F23: 子公司1 | G23: 子公司2 | H23: 子公司3 | I23: 子公司4 | J23: 子公司5 | K23: 子公司6 | L23: 子公司7 | M23: 子公司8 | N23: 子公司9 | O23: 子公司10 | P23: 子公司11 | Q23: 子公司12
A24: =A15 -> 种植业 | B24: =D24-C24 -> 0 | D24: =SUM(E24:Q24) -> 0 | E24: 0
A25: =A16 -> 畜牧养殖业 | B25: =D25-C25 -> 0 | D25: =SUM(E25:Q25) -> 0 | E25: 0
A26: =A17 -> 林业 | B26: =D26-C26 -> 0 | D26: =SUM(E26:Q26) -> 0 | E26: 0
A27: =A18 -> 水产业 | B27: =D27-C27 -> 0 | D27: =SUM(E27:Q27) -> 0 | E27: 0
A28: =A19 -> 其他 | B28: =D28-C28 -> 0 | D28: =SUM(E28:Q28) -> 0 | E28: 0
A29: 合计 | B29: =SUM(B24:B28) -> 0 | C29: =SUM(C24:C28) -> 0 | D29: =SUM(E29:Q29) -> 0 | E29: =SUM(E24:E28) -> 0 | F29: =SUM(F24:F28) -> 0 | G29: =SUM(G24:G28) -> 0 | H29: =SUM(H24:H28) -> 0 | I29: =SUM(I24:I28) -> 0 | J29: =SUM(J24:J28) -> 0 | K29: =SUM(K24:K28) -> 0 | L29: =SUM(L24:L28) -> 0 | ... Q29: =SUM(Q24:Q28) -> 0
A31: 4、生产性生物资产本期增加（其他增加）
A32: 项 目 | B32: 审定数 | C32: 抵消数 | D32: 汇总 | E32: 母公司审定 | F32: 子公司1 | G32: 子公司2 | H32: 子公司3 | I32: 子公司4 | J32: 子公司5 | K32: 子公司6 | L32: 子公司7 | M32: 子公司8 | N32: 子公司9 | O32: 子公司10 | P32: 子公司11 | Q32: 子公司12
A33: =A24 -> 种植业 | B33: =D33-C33 -> 0 | D33: =SUM(E33:Q33) -> 0 | E33: 0
A34: =A25 -> 畜牧养殖业 | B34: =D34-C34 -> 0 | D34: =SUM(E34:Q34) -> 0 | E34: 0
A35: =A26 -> 林业 | B35: =D35-C35 -> 0 | D35: =SUM(E35:Q35) -> 0 | E35: 0
A36: =A27 -> 水产业 | B36: =D36-C36 -> 0 | D36: =SUM(E36:Q36) -> 0 | E36: 0
A37: =A28 -> 其他 | B37: =D37-C37 -> 0 | D37: =SUM(E37:Q37) -> 0 | E37: 0
A38: 合计 | B38: =SUM(B33:B37) -> 0 | C38: =SUM(C33:C37) -> 0 | D38: =SUM(E38:Q38) -> 0 | E38: =SUM(E33:E37) -> 0 | F38: =SUM(F33:F37) -> 0 | G38: =SUM(G33:G37) -> 0 | H38: =SUM(H33:H37) -> 0 | I38: =SUM(I33:I37) -> 0 | J38: =SUM(J33:J37) -> 0 | K38: =SUM(K33:K37) -> 0 | L38: =SUM(L33:L37) -> 0 | ... Q38: =SUM(Q33:Q37) -> 0
A40: 5、生产性生物资产减少（处置）
A41: 项 目 | B41: 审定数 | C41: 抵消数 | D41: 汇总 | E41: 母公司审定 | F41: 子公司1 | G41: 子公司2 | H41: 子公司3 | I41: 子公司4 | J41: 子公司5 | K41: 子公司6 | L41: 子公司7 | M41: 子公司8 | N41: 子公司9 | O41: 子公司10 | P41: 子公司11 | Q41: 子公司12
A42: =A33 -> 种植业 | B42: =D42-C42 -> 0 | D42: =SUM(E42:Q42) -> 0 | E42: 0
A43: =A34 -> 畜牧养殖业 | B43: =D43-C43 -> 0 | D43: =SUM(E43:Q43) -> 0 | E43: 0
A44: =A35 -> 林业 | B44: =D44-C44 -> 0 | D44: =SUM(E44:Q44) -> 0 | E44: 0
A45: =A36 -> 水产业 | B45: =D45-C45 -> 0 | D45: =SUM(E45:Q45) -> 0 | E45: 0
A46: =A37 -> 其他 | B46: =D46-C46 -> 0 | D46: =SUM(E46:Q46) -> 0 | E46: 0
A47: 合计 | B47: =SUM(B42:B46) -> 0 | C47: =SUM(C42:C46) -> 0 | D47: =SUM(E47:Q47) -> 0 | E47: =SUM(E42:E46) -> 0 | F47: =SUM(F42:F46) -> 0 | G47: =SUM(G42:G46) -> 0 | H47: =SUM(H42:H46) -> 0 | I47: =SUM(I42:I46) -> 0 | J47: =SUM(J42:J46) -> 0 | K47: =SUM(K42:K46) -> 0 | L47: =SUM(L42:L46) -> 0 | ... Q47: =SUM(Q42:Q46) -> 0
A49: 6、生产性生物资产减少（其他减少）
A50: 项 目 | B50: 审定数 | C50: 抵消数 | D50: 汇总 | E50: 母公司审定 | F50: 子公司1 | G50: 子公司2 | H50: 子公司3 | I50: 子公司4 | J50: 子公司5 | K50: 子公司6 | L50: 子公司7 | M50: 子公司8 | N50: 子公司9 | O50: 子公司10 | P50: 子公司11 | Q50: 子公司12
A51: =A42 -> 种植业 | B51: =D51-C51 -> 0 | D51: =SUM(E51:Q51) -> 0 | E51: 0
A52: =A43 -> 畜牧养殖业 | B52: =D52-C52 -> 0 | D52: =SUM(E52:Q52) -> 0 | E52: 0
A53: =A44 -> 林业 | B53: =D53-C53 -> 0 | D53: =SUM(E53:Q53) -> 0 | E53: 0
A54: =A45 -> 水产业 | B54: =D54-C54 -> 0 | D54: =SUM(E54:Q54) -> 0 | E54: 0
A55: =A46 -> 其他 | B55: =D55-C55 -> 0 | D55: =SUM(E55:Q55) -> 0 | E55: 0
A56: 合计 | B56: =SUM(B51:B55) -> 0 | C56: =SUM(C51:C55) -> 0 | D56: =SUM(E56:Q56) -> 0 | E56: =SUM(E51:E55) -> 0 | F56: =SUM(F51:F55) -> 0 | G56: =SUM(G51:G55) -> 0 | H56: =SUM(H51:H55) -> 0 | I56: =SUM(I51:I55) -> 0 | J56: =SUM(J51:J55) -> 0 | K56: =SUM(K51:K55) -> 0 | L56: =SUM(L51:L55) -> 0 | ... Q56: =SUM(Q51:Q55) -> 0
A58: 7、生产性生物资产原值期末数
A59: 项 目 | B59: 审定数 | C59: 抵消数 | D59: 汇总 | E59: 母公司审定 | F59: 子公司1 | G59: 子公司2 | H59: 子公司3 | I59: 子公司4 | J59: 子公司5 | K59: 子公司6 | L59: 子公司7 | M59: 子公司8 | N59: 子公司9 | O59: 子公司10 | P59: 子公司11 | Q59: 子公司12
A60: =A51 -> 种植业 | B60: =D60-C60 -> 0 | D60: =SUM(E60:Q60) -> 0 | E60: =E6+E15+E24+E33-E42-E51 -> 0 | F60: =F6+F15+F24+F33-F42-F51 -> 0 | G60: =G6+G15+G24+G33-G42-G51 -> 0 | H60: =H6+H15+H24+H33-H42-H51 -> 0 | I60: =I6+I15+I24+I33-I42-I51 -> 0 | J60: =J6+J15+J24+J33-J42-J51 -> 0 | K60: =K6+K15+K24+K33-K42-K51 -> 0 | L60: =L6+L15+L24+L33-L42-L51 -> 0 | ... Q60: =Q6+Q15+Q24+Q33-Q42-Q51 -> 0
A61: =A52 -> 畜牧养殖业 | B61: =D61-C61 -> 0 | D61: =SUM(E61:Q61) -> 0 | E61: =E7+E16+E25+E34-E43-E52 -> 0 | F61: =F7+F16+F25+F34-F43-F52 -> 0 | G61: =G7+G16+G25+G34-G43-G52 -> 0 | H61: =H7+H16+H25+H34-H43-H52 -> 0 | I61: =I7+I16+I25+I34-I43-I52 -> 0 | J61: =J7+J16+J25+J34-J43-J52 -> 0 | K61: =K7+K16+K25+K34-K43-K52 -> 0 | L61: =L7+L16+L25+L34-L43-L52 -> 0 | ... Q61: =Q7+Q16+Q25+Q34-Q43-Q52 -> 0
A62: =A53 -> 林业 | B62: =D62-C62 -> 0 | D62: =SUM(E62:Q62) -> 0 | E62: =E8+E17+E26+E35-E44-E53 -> 0 | F62: =F8+F17+F26+F35-F44-F53 -> 0 | G62: =G8+G17+G26+G35-G44-G53 -> 0 | H62: =H8+H17+H26+H35-H44-H53 -> 0 | I62: =I8+I17+I26+I35-I44-I53 -> 0 | J62: =J8+J17+J26+J35-J44-J53 -> 0 | K62: =K8+K17+K26+K35-K44-K53 -> 0 | L62: =L8+L17+L26+L35-L44-L53 -> 0 | ... Q62: =Q8+Q17+Q26+Q35-Q44-Q53 -> 0
A63: =A54 -> 水产业 | B63: =D63-C63 -> 0 | D63: =SUM(E63:Q63) -> 0 | E63: =E9+E18+E27+E36-E45-E54 -> 0 | F63: =F9+F18+F27+F36-F45-F54 -> 0 | G63: =G9+G18+G27+G36-G45-G54 -> 0 | H63: =H9+H18+H27+H36-H45-H54 -> 0 | I63: =I9+I18+I27+I36-I45-I54 -> 0 | J63: =J9+J18+J27+J36-J45-J54 -> 0 | K63: =K9+K18+K27+K36-K45-K54 -> 0 | L63: =L9+L18+L27+L36-L45-L54 -> 0 | ... Q63: =Q9+Q18+Q27+Q36-Q45-Q54 -> 0
A64: =A55 -> 其他 | B64: =D64-C64 -> 0 | D64: =SUM(E64:Q64) -> 0 | E64: =E10+E19+E28+E37-E46-E55 -> 0 | F64: =F10+F19+F28+F37-F46-F55 -> 0 | G64: =G10+G19+G28+G37-G46-G55 -> 0 | H64: =H10+H19+H28+H37-H46-H55 -> 0 | I64: =I10+I19+I28+I37-I46-I55 -> 0 | J64: =J10+J19+J28+J37-J46-J55 -> 0 | K64: =K10+K19+K28+K37-K46-K55 -> 0 | L64: =L10+L19+L28+L37-L46-L55 -> 0 | ... Q64: =Q10+Q19+Q28+Q37-Q46-Q55 -> 0
A65: 合计 | B65: =SUM(B60:B64) -> 0 | C65: =SUM(C60:C64) -> 0 | D65: =SUM(E65:Q65) -> 0 | E65: =SUM(E60:E64) -> 0 | F65: =SUM(F60:F64) -> 0 | G65: =SUM(G60:G64) -> 0 | H65: =SUM(H60:H64) -> 0 | I65: =SUM(I60:I64) -> 0 | J65: =SUM(J60:J64) -> 0 | K65: =SUM(K60:K64) -> 0 | L65: =SUM(L60:L64) -> 0 | ... Q65: =SUM(Q60:Q64) -> 0
A67: 生产性生物资产累计折旧
A68: 1、累计折旧期初数
A69: 项 目 | B69: 审定数 | C69: 抵消数 | D69: 汇总 | E69: 母公司审定 | F69: 子公司1 | G69: 子公司2 | H69: 子公司3 | I69: 子公司4 | J69: 子公司5 | K69: 子公司6 | L69: 子公司7 | M69: 子公司8 | N69: 子公司9 | O69: 子公司10 | P69: 子公司11 | Q69: 子公司12
A70: =A60 -> 种植业 | B70: =D70-C70 -> 0 | D70: =SUM(E70:Q70) -> 0 | E70: 0
A71: =A61 -> 畜牧养殖业 | B71: =D71-C71 -> 0 | D71: =SUM(E71:Q71) -> 0 | E71: 0
A72: =A62 -> 林业 | B72: =D72-C72 -> 0 | D72: =SUM(E72:Q72) -> 0 | E72: 0
A73: =A63 -> 水产业 | B73: =D73-C73 -> 0 | D73: =SUM(E73:Q73) -> 0 | E73: 0
A74: =A64 -> 其他 | B74: =D74-C74 -> 0 | D74: =SUM(E74:Q74) -> 0 | E74: 0
A75: 合计 | B75: =SUM(B70:B74) -> 0 | C75: =SUM(C70:C74) -> 0 | D75: =SUM(E75:Q75) -> 0 | E75: =SUM(E70:E74) -> 0 | F75: =SUM(F70:F74) -> 0 | G75: =SUM(G70:G74) -> 0 | H75: =SUM(H70:H74) -> 0 | I75: =SUM(I70:I74) -> 0 | J75: =SUM(J70:J74) -> 0 | K75: =SUM(K70:K74) -> 0 | L75: =SUM(L70:L74) -> 0 | ... Q75: =SUM(Q70:Q74) -> 0
A77: 2、累计折旧本期增加（计提或摊销）
A78: 项 目 | B78: 审定数 | C78: 抵消数 | D78: 汇总 | E78: 母公司审定 | F78: 子公司1 | G78: 子公司2 | H78: 子公司3 | I78: 子公司4 | J78: 子公司5 | K78: 子公司6 | L78: 子公司7 | M78: 子公司8 | N78: 子公司9 | O78: 子公司10 | P78: 子公司11 | Q78: 子公司12
A79: =A70 -> 种植业 | B79: =D79-C79 -> 0 | D79: =SUM(E79:Q79) -> 0 | E79: 0
A80: =A71 -> 畜牧养殖业 | B80: =D80-C80 -> 0 | D80: =SUM(E80:Q80) -> 0 | E80: 0
A81: =A72 -> 林业 | B81: =D81-C81 -> 0 | D81: =SUM(E81:Q81) -> 0 | E81: 0
A82: =A73 -> 水产业 | B82: =D82-C82 -> 0 | D82: =SUM(E82:Q82) -> 0 | E82: 0
A83: =A74 -> 其他 | B83: =D83-C83 -> 0 | D83: =SUM(E83:Q83) -> 0 | E83: 0
A84: 合计 | B84: =SUM(B79:B83) -> 0 | C84: =SUM(C79:C83) -> 0 | D84: =SUM(E84:Q84) -> 0 | E84: =SUM(E79:E83) -> 0 | F84: =SUM(F79:F83) -> 0 | G84: =SUM(G79:G83) -> 0 | H84: =SUM(H79:H83) -> 0 | I84: =SUM(I79:I83) -> 0 | J84: =SUM(J79:J83) -> 0 | K84: =SUM(K79:K83) -> 0 | L84: =SUM(L79:L83) -> 0 | ... Q84: =SUM(Q79:Q83) -> 0
A86: 3、累计折旧本期增加（其他增加）
A87: 项 目 | B87: 审定数 | C87: 抵消数 | D87: 汇总 | E87: 母公司审定 | F87: 子公司1 | G87: 子公司2 | H87: 子公司3 | I87: 子公司4 | J87: 子公司5 | K87: 子公司6 | L87: 子公司7 | M87: 子公司8 | N87: 子公司9 | O87: 子公司10 | P87: 子公司11 | Q87: 子公司12
A88: =A70 -> 种植业 | B88: =D88-C88 -> 0 | D88: =SUM(E88:Q88) -> 0 | E88: 0
A89: =A71 -> 畜牧养殖业 | B89: =D89-C89 -> 0 | D89: =SUM(E89:Q89) -> 0 | E89: 0
A90: =A72 -> 林业 | B90: =D90-C90 -> 0 | D90: =SUM(E90:Q90) -> 0 | E90: 0
A91: =A73 -> 水产业 | B91: =D91-C91 -> 0 | D91: =SUM(E91:Q91) -> 0 | E91: 0
A92: =A74 -> 其他 | B92: =D92-C92 -> 0 | D92: =SUM(E92:Q92) -> 0 | E92: 0
A93: 合计 | B93: =SUM(B88:B92) -> 0 | C93: =SUM(C88:C92) -> 0 | D93: =SUM(E93:Q93) -> 0 | E93: =SUM(E88:E92) -> 0 | F93: =SUM(F88:F92) -> 0 | G93: =SUM(G88:G92) -> 0 | H93: =SUM(H88:H92) -> 0 | I93: =SUM(I88:I92) -> 0 | J93: =SUM(J88:J92) -> 0 | K93: =SUM(K88:K92) -> 0 | L93: =SUM(L88:L92) -> 0 | ... Q93: =SUM(Q88:Q92) -> 0
A95: 5、累计折旧本期减少（处置）
A96: 项 目 | B96: 审定数 | C96: 抵消数 | D96: 汇总 | E96: 母公司审定 | F96: 子公司1 | G96: 子公司2 | H96: 子公司3 | I96: 子公司4 | J96: 子公司5 | K96: 子公司6 | L96: 子公司7 | M96: 子公司8 | N96: 子公司9 | O96: 子公司10 | P96: 子公司11 | Q96: 子公司12
A97: =A88 -> 种植业 | B97: =D97-C97 -> 0 | D97: =SUM(E97:Q97) -> 0 | E97: 0
A98: =A89 -> 畜牧养殖业 | B98: =D98-C98 -> 0 | D98: =SUM(E98:Q98) -> 0 | E98: 0
A99: =A90 -> 林业 | B99: =D99-C99 -> 0 | D99: =SUM(E99:Q99) -> 0 | E99: 0
A100: =A91 -> 水产业 | B100: =D100-C100 -> 0 | D100: =SUM(E100:Q100) -> 0 | E100: 0
A101: =A92 -> 其他 | B101: =D101-C101 -> 0 | D101: =SUM(E101:Q101) -> 0 | E101: 0
A102: 合计 | B102: =SUM(B97:B101) -> 0 | C102: =SUM(C97:C101) -> 0 | D102: =SUM(E102:Q102) -> 0 | E102: =SUM(E97:E101) -> 0 | F102: =SUM(F97:F101) -> 0 | G102: =SUM(G97:G101) -> 0 | H102: =SUM(H97:H101) -> 0 | I102: =SUM(I97:I101) -> 0 | J102: =SUM(J97:J101) -> 0 | K102: =SUM(K97:K101) -> 0 | L102: =SUM(L97:L101) -> 0 | ... Q102: =SUM(Q97:Q101) -> 0
A104: 6、累计折旧本期减少（其他减少）
A105: 项 目 | B105: 审定数 | C105: 抵消数 | D105: 汇总 | E105: 母公司审定 | F105: 子公司1 | G105: 子公司2 | H105: 子公司3 | I105: 子公司4 | J105: 子公司5 | K105: 子公司6 | L105: 子公司7 | M105: 子公司8 | N105: 子公司9 | O105: 子公司10 | P105: 子公司11 | Q105: 子公司12
A106: =A97 -> 种植业 | B106: =D106-C106 -> 0 | D106: =SUM(E106:Q106) -> 0 | E106: 0
A107: =A98 -> 畜牧养殖业 | B107: =D107-C107 -> 0 | D107: =SUM(E107:Q107) -> 0 | E107: 0
A108: =A99 -> 林业 | B108: =D108-C108 -> 0 | D108: =SUM(E108:Q108) -> 0 | E108: 0
A109: =A100 -> 水产业 | B109: =D109-C109 -> 0 | D109: =SUM(E109:Q109) -> 0 | E109: 0
A110: =A101 -> 其他 | B110: =D110-C110 -> 0 | D110: =SUM(E110:Q110) -> 0 | E110: 0
A111: 合计 | B111: =SUM(B106:B110) -> 0 | C111: =SUM(C106:C110) -> 0 | D111: =SUM(E111:Q111) -> 0 | E111: =SUM(E106:E110) -> 0 | F111: =SUM(F106:F110) -> 0 | G111: =SUM(G106:G110) -> 0 | H111: =SUM(H106:H110) -> 0 | I111: =SUM(I106:I110) -> 0 | J111: =SUM(J106:J110) -> 0 | K111: =SUM(K106:K110) -> 0 | L111: =SUM(L106:L110) -> 0 | ... Q111: =SUM(Q106:Q110) -> 0
...

Sheet 生产性生物资产（公允价值计量）
A1: 生产性生物资产附注汇总 | D1: 返回Excel目录 | E1: 返回word附注
A2: （1）按公允价值计量的生产性生物资产
A3: 1、生产性生物资产期初原值
A4: 项 目 | B4: 审定数 | C4: 抵消数 | D4: 汇总 | E4: 母公司审定 | F4: 子公司1 | G4: 子公司2 | H4: 子公司3 | I4: 子公司4 | J4: 子公司5 | K4: 子公司6 | L4: 子公司7 | M4: 子公司8 | N4: 子公司9 | O4: 子公司10 | P4: 子公司11 | Q4: 子公司12
A5: 种植业 | B5: =D5-C5 -> 0 | D5: =SUM(E5:Q5) -> 0 | E5: 0
A6: 畜牧养殖业 | B6: =D6-C6 -> 0 | D6: =SUM(E6:Q6) -> 0 | E6: 0
A7: 林业 | B7: =D7-C7 -> 0 | D7: =SUM(E7:Q7) -> 0 | E7: 0
A8: 水产业 | B8: =D8-C8 -> 0 | D8: =SUM(E8:Q8) -> 0 | E8: 0
A9: 其他 | B9: =D9-C9 -> 0 | D9: =SUM(E9:Q9) -> 0 | E9: 0
A10: 合计 | B10: =SUM(B5:B9) -> 0 | C10: =SUM(C5:C9) -> 0 | D10: =SUM(E10:Q10) -> 0 | E10: =SUM(E5:E9) -> 0 | F10: =SUM(F5:F9) -> 0 | G10: =SUM(G5:G9) -> 0 | H10: =SUM(H5:H9) -> 0 | I10: =SUM(I5:I9) -> 0 | J10: =SUM(J5:J9) -> 0 | K10: =SUM(K5:K9) -> 0 | L10: =SUM(L5:L9) -> 0 | ... Q10: =SUM(Q5:Q9) -> 0
A12: 2、生产性生物资产期初公允价值变动
A13: 项 目 | B13: 审定数 | C13: 抵消数 | D13: 汇总 | E13: 母公司审定 | F13: 子公司1 | G13: 子公司2 | H13: 子公司3 | I13: 子公司4 | J13: 子公司5 | K13: 子公司6 | L13: 子公司7 | M13: 子公司8 | N13: 子公司9 | O13: 子公司10 | P13: 子公司11 | Q13: 子公司12
A14: =A5 -> 种植业 | B14: =D14-C14 -> 0 | D14: =SUM(E14:Q14) -> 0 | E14: 0
A15: =A6 -> 畜牧养殖业 | B15: =D15-C15 -> 0 | D15: =SUM(E15:Q15) -> 0 | E15: 0
A16: 林业 | B16: =D16-C16 -> 0 | D16: =SUM(E16:Q16) -> 0 | E16: 0
A17: 水产业 | B17: =D17-C17 -> 0 | D17: =SUM(E17:Q17) -> 0 | E17: 0
A18: =A9 -> 其他 | B18: =D18-C18 -> 0 | D18: =SUM(E18:Q18) -> 0 | E18: 0
A19: 合计 | B19: =SUM(B14:B18) -> 0 | C19: =SUM(C14:C18) -> 0 | D19: =SUM(E19:Q19) -> 0 | E19: =SUM(E14:E18) -> 0 | F19: =SUM(F14:F18) -> 0 | G19: =SUM(G14:G18) -> 0 | H19: =SUM(H14:H18) -> 0 | I19: =SUM(I14:I18) -> 0 | J19: =SUM(J14:J18) -> 0 | K19: =SUM(K14:K18) -> 0 | L19: =SUM(L14:L18) -> 0 | ... Q19: =SUM(Q14:Q18) -> 0
A21: 3、生产性生物资产本期原值增加（外购）
A22: 项 目 | B22: 审定数 | C22: 抵消数 | D22: 汇总 | E22: 母公司审定 | F22: 子公司1 | G22: 子公司2 | H22: 子公司3 | I22: 子公司4 | J22: 子公司5 | K22: 子公司6 | L22: 子公司7 | M22: 子公司8 | N22: 子公司9 | O22: 子公司10 | P22: 子公司11 | Q22: 子公司12
A23: =A14 -> 种植业 | B23: =D23-C23 -> 0 | D23: =SUM(E23:Q23) -> 0 | E23: 0
A24: =A15 -> 畜牧养殖业 | B24: =D24-C24 -> 0 | D24: =SUM(E24:Q24) -> 0 | E24: 0
A25: 林业 | B25: =D25-C25 -> 0 | D25: =SUM(E25:Q25) -> 0 | E25: 0
A26: 水产业 | B26: =D26-C26 -> 0 | D26: =SUM(E26:Q26) -> 0 | E26: 0
A27: =A18 -> 其他 | B27: =D27-C27 -> 0 | D27: =SUM(E27:Q27) -> 0 | E27: 0
A28: 合计 | B28: =SUM(B23:B27) -> 0 | C28: =SUM(C23:C27) -> 0 | D28: =SUM(E28:Q28) -> 0 | E28: =SUM(E23:E27) -> 0 | F28: =SUM(F23:F27) -> 0 | G28: =SUM(G23:G27) -> 0 | H28: =SUM(H23:H27) -> 0 | I28: =SUM(I23:I27) -> 0 | J28: =SUM(J23:J27) -> 0 | K28: =SUM(K23:K27) -> 0 | L28: =SUM(L23:L27) -> 0 | ... Q28: =SUM(Q23:Q27) -> 0
A30: 4、生产性生物资产本期原值增加（自行培育）
A31: 项 目 | B31: 审定数 | C31: 抵消数 | D31: 汇总 | E31: 母公司审定 | F31: 子公司1 | G31: 子公司2 | H31: 子公司3 | I31: 子公司4 | J31: 子公司5 | K31: 子公司6 | L31: 子公司7 | M31: 子公司8 | N31: 子公司9 | O31: 子公司10 | P31: 子公司11 | Q31: 子公司12
A32: =A23 -> 种植业 | B32: =D32-C32 -> 0 | D32: =SUM(E32:Q32) -> 0 | E32: 0
A33: =A24 -> 畜牧养殖业 | B33: =D33-C33 -> 0 | D33: =SUM(E33:Q33) -> 0 | E33: 0
A34: 林业 | B34: =D34-C34 -> 0 | D34: =SUM(E34:Q34) -> 0 | E34: 0
A35: 水产业 | B35: =D35-C35 -> 0 | D35: =SUM(E35:Q35) -> 0 | E35: 0
A36: =A27 -> 其他 | B36: =D36-C36 -> 0 | D36: =SUM(E36:Q36) -> 0 | E36: 0
A37: 合计 | B37: =SUM(B32:B36) -> 0 | C37: =SUM(C32:C36) -> 0 | D37: =SUM(E37:Q37) -> 0 | E37: =SUM(E32:E36) -> 0 | F37: =SUM(F32:F36) -> 0 | G37: =SUM(G32:G36) -> 0 | H37: =SUM(H32:H36) -> 0 | I37: =SUM(I32:I36) -> 0 | J37: =SUM(J32:J36) -> 0 | K37: =SUM(K32:K36) -> 0 | L37: =SUM(L32:L36) -> 0 | ... Q37: =SUM(Q32:Q36) -> 0
A39: 5、生产性生物资产本期原值增加（企业合并增加）
A40: 项 目 | B40: 审定数 | C40: 抵消数 | D40: 汇总 | E40: 母公司审定 | F40: 子公司1 | G40: 子公司2 | H40: 子公司3 | I40: 子公司4 | J40: 子公司5 | K40: 子公司6 | L40: 子公司7 | M40: 子公司8 | N40: 子公司9 | O40: 子公司10 | P40: 子公司11 | Q40: 子公司12
A41: =A32 -> 种植业 | B41: =D41-C41 -> 0 | D41: =SUM(E41:Q41) -> 0 | E41: 0
A42: =A33 -> 畜牧养殖业 | B42: =D42-C42 -> 0 | D42: =SUM(E42:Q42) -> 0 | E42: 0
A43: 林业 | B43: =D43-C43 -> 0 | D43: =SUM(E43:Q43) -> 0 | E43: 0
A44: 水产业 | B44: =D44-C44 -> 0 | D44: =SUM(E44:Q44) -> 0 | E44: 0
A45: =A36 -> 其他 | B45: =D45-C45 -> 0 | D45: =SUM(E45:Q45) -> 0 | E45: 0
A46: 合计 | B46: =SUM(B41:B45) -> 0 | C46: =SUM(C41:C45) -> 0 | D46: =SUM(E46:Q46) -> 0 | E46: =SUM(E41:E45) -> 0 | F46: =SUM(F41:F45) -> 0 | G46: =SUM(G41:G45) -> 0 | H46: =SUM(H41:H45) -> 0 | I46: =SUM(I41:I45) -> 0 | J46: =SUM(J41:J45) -> 0 | K46: =SUM(K41:K45) -> 0 | L46: =SUM(L41:L45) -> 0 | ... Q46: =SUM(Q41:Q45) -> 0
A48: 6、生产性生物资产本期原值减少（处置）
A49: 项 目 | B49: 审定数 | C49: 抵消数 | D49: 汇总 | E49: 母公司审定 | F49: 子公司1 | G49: 子公司2 | H49: 子公司3 | I49: 子公司4 | J49: 子公司5 | K49: 子公司6 | L49: 子公司7 | M49: 子公司8 | N49: 子公司9 | O49: 子公司10 | P49: 子公司11 | Q49: 子公司12
A50: =A41 -> 种植业 | B50: =D50-C50 -> 0 | D50: =SUM(E50:Q50) -> 0 | E50: 0
A51: =A42 -> 畜牧养殖业 | B51: =D51-C51 -> 0 | D51: =SUM(E51:Q51) -> 0 | E51: 0
A52: 林业 | B52: =D52-C52 -> 0 | D52: =SUM(E52:Q52) -> 0 | E52: 0
A53: 水产业 | B53: =D53-C53 -> 0 | D53: =SUM(E53:Q53) -> 0 | E53: 0
A54: =A45 -> 其他 | B54: =D54-C54 -> 0 | D54: =SUM(E54:Q54) -> 0 | E54: 0
A55: 合计 | B55: =SUM(B50:B54) -> 0 | C55: =SUM(C50:C54) -> 0 | D55: =SUM(E55:Q55) -> 0 | E55: =SUM(E50:E54) -> 0 | F55: =SUM(F50:F54) -> 0 | G55: =SUM(G50:G54) -> 0 | H55: =SUM(H50:H54) -> 0 | I55: =SUM(I50:I54) -> 0 | J55: =SUM(J50:J54) -> 0 | K55: =SUM(K50:K54) -> 0 | L55: =SUM(L50:L54) -> 0 | ... Q55: =SUM(Q50:Q54) -> 0
A57: 7、生产性生物资产本期原值减少（其他转出）
A58: 项 目 | B58: 审定数 | C58: 抵消数 | D58: 汇总 | E58: 母公司审定 | F58: 子公司1 | G58: 子公司2 | H58: 子公司3 | I58: 子公司4 | J58: 子公司5 | K58: 子公司6 | L58: 子公司7 | M58: 子公司8 | N58: 子公司9 | O58: 子公司10 | P58: 子公司11 | Q58: 子公司12
A59: =A50 -> 种植业 | B59: =D59-C59 -> 0 | D59: =SUM(E59:Q59) -> 0 | E59: 0
A60: =A51 -> 畜牧养殖业 | B60: =D60-C60 -> 0 | D60: =SUM(E60:Q60) -> 0 | E60: 0
A61: 林业 | B61: =D61-C61 -> 0 | D61: =SUM(E61:Q61) -> 0 | E61: 0
A62: 水产业 | B62: =D62-C62 -> 0 | D62: =SUM(E62:Q62) -> 0 | E62: 0
A63: =A54 -> 其他 | B63: =D63-C63 -> 0 | D63: =SUM(E63:Q63) -> 0 | E63: 0
A64: 合计 | B64: =SUM(B59:B63) -> 0 | C64: =SUM(C59:C63) -> 0 | D64: =SUM(E64:Q64) -> 0 | E64: =SUM(E59:E63) -> 0 | F64: =SUM(F59:F63) -> 0 | G64: =SUM(G59:G63) -> 0 | H64: =SUM(H59:H63) -> 0 | I64: =SUM(I59:I63) -> 0 | J64: =SUM(J59:J63) -> 0 | K64: =SUM(K59:K63) -> 0 | L64: =SUM(L59:L63) -> 0 | ... Q64: =SUM(Q59:Q63) -> 0
A66: 8、生产性生物资产本期公允价值变动
A67: 项 目 | B67: 审定数 | C67: 抵消数 | D67: 汇总 | E67: 母公司审定 | F67: 子公司1 | G67: 子公司2 | H67: 子公司3 | I67: 子公司4 | J67: 子公司5 | K67: 子公司6 | L67: 子公司7 | M67: 子公司8 | N67: 子公司9 | O67: 子公司10 | P67: 子公司11 | Q67: 子公司12
A68: =A59 -> 种植业 | B68: =D68-C68 -> 0 | D68: =SUM(E68:Q68) -> 0 | E68: 0
A69: =A60 -> 畜牧养殖业 | B69: =D69-C69 -> 0 | D69: =SUM(E69:Q69) -> 0 | E69: 0
A70: 林业 | B70: =D70-C70 -> 0 | D70: =SUM(E70:Q70) -> 0 | E70: 0
A71: 水产业 | B71: =D71-C71 -> 0 | D71: =SUM(E71:Q71) -> 0 | E71: 0
A72: =A63 -> 其他 | B72: =D72-C72 -> 0 | D72: =SUM(E72:Q72) -> 0 | E72: 0
A73: 合计 | B73: =SUM(B68:B72) -> 0 | C73: =SUM(C68:C72) -> 0 | D73: =SUM(E73:Q73) -> 0 | E73: =SUM(E68:E72) -> 0 | F73: =SUM(F68:F72) -> 0 | G73: =SUM(G68:G72) -> 0 | H73: =SUM(H68:H72) -> 0 | I73: =SUM(I68:I72) -> 0 | J73: =SUM(J68:J72) -> 0 | K73: =SUM(K68:K72) -> 0 | L73: =SUM(L68:L72) -> 0 | ... Q73: =SUM(Q68:Q72) -> 0
A75: 9、生产性生物资产期末原值
A76: 项 目 | B76: 审定数 | C76: 抵消数 | D76: 汇总 | E76: 母公司审定 | F76: 子公司1 | G76: 子公司2 | H76: 子公司3 | I76: 子公司4 | J76: 子公司5 | K76: 子公司6 | L76: 子公司7 | M76: 子公司8 | N76: 子公司9 | O76: 子公司10 | P76: 子公司11 | Q76: 子公司12
A77: =A68 -> 种植业 | B77: =D77-C77 -> 0 | D77: =SUM(E77:Q77) -> 0 | E77: =E5+E23+E32+E41-E50-E59 -> 0 | F77: =F5+F23+F32+F41-F50-F59 -> 0 | G77: =G5+G23+G32+G41-G50-G59 -> 0 | H77: =H5+H23+H32+H41-H50-H59 -> 0 | I77: =I5+I23+I32+I41-I50-I59 -> 0 | J77: =J5+J23+J32+J41-J50-J59 -> 0 | K77: =K5+K23+K32+K41-K50-K59 -> 0 | L77: =L5+L23+L32+L41-L50-L59 -> 0 | ... Q77: =Q5+Q23+Q32+Q41-Q50-Q59 -> 0
A78: =A69 -> 畜牧养殖业 | B78: =D78-C78 -> 0 | D78: =SUM(E78:Q78) -> 0 | E78: =E6+E24+E33+E42-E51-E60 -> 0 | F78: =F6+F24+F33+F42-F51-F60 -> 0 | G78: =G6+G24+G33+G42-G51-G60 -> 0 | H78: =H6+H24+H33+H42-H51-H60 -> 0 | I78: =I6+I24+I33+I42-I51-I60 -> 0 | J78: =J6+J24+J33+J42-J51-J60 -> 0 | K78: =K6+K24+K33+K42-K51-K60 -> 0 | L78: =L6+L24+L33+L42-L51-L60 -> 0 | ... Q78: =Q6+Q24+Q33+Q42-Q51-Q60 -> 0
A79: 林业 | B79: =D79-C79 -> 0 | D79: =SUM(E79:Q79) -> 0 | E79: =E7+E25+E34+E43-E52-E61 -> 0 | F79: =F7+F25+F34+F43-F52-F61 -> 0 | G79: =G7+G25+G34+G43-G52-G61 -> 0 | H79: =H7+H25+H34+H43-H52-H61 -> 0 | I79: =I7+I25+I34+I43-I52-I61 -> 0 | J79: =J7+J25+J34+J43-J52-J61 -> 0 | K79: =K7+K25+K34+K43-K52-K61 -> 0 | L79: =L7+L25+L34+L43-L52-L61 -> 0 | ... Q79: =Q7+Q25+Q34+Q43-Q52-Q61 -> 0
A80: 水产业 | B80: =D80-C80 -> 0 | D80: =SUM(E80:Q80) -> 0 | E80: =E8+E26+E35+E44-E53-E62 -> 0 | F80: =F8+F26+F35+F44-F53-F62 -> 0 | G80: =G8+G26+G35+G44-G53-G62 -> 0 | H80: =H8+H26+H35+H44-H53-H62 -> 0 | I80: =I8+I26+I35+I44-I53-I62 -> 0 | J80: =J8+J26+J35+J44-J53-J62 -> 0 | K80: =K8+K26+K35+K44-K53-K62 -> 0 | L80: =L8+L26+L35+L44-L53-L62 -> 0 | ... Q80: =Q8+Q26+Q35+Q44-Q53-Q62 -> 0
A81: =A72 -> 其他 | B81: =D81-C81 -> 0 | D81: =SUM(E81:Q81) -> 0 | E81: =E9+E27+E36+E45-E54-E63 -> 0 | F81: =F9+F27+F36+F45-F54-F63 -> 0 | G81: =G9+G27+G36+G45-G54-G63 -> 0 | H81: =H9+H27+H36+H45-H54-H63 -> 0 | I81: =I9+I27+I36+I45-I54-I63 -> 0 | J81: =J9+J27+J36+J45-J54-J63 -> 0 | K81: =K9+K27+K36+K45-K54-K63 -> 0 | L81: =L9+L27+L36+L45-L54-L63 -> 0 | ... Q81: =Q9+Q27+Q36+Q45-Q54-Q63 -> 0
A82: 合计 | B82: =SUM(B77:B81) -> 0 | C82: =SUM(C77:C81) -> 0 | D82: =SUM(E82:Q82) -> 0 | E82: =SUM(E77:E81) -> 0 | F82: =SUM(F77:F81) -> 0 | G82: =SUM(G77:G81) -> 0 | H82: =SUM(H77:H81) -> 0 | I82: =SUM(I77:I81) -> 0 | J82: =SUM(J77:J81) -> 0 | K82: =SUM(K77:K81) -> 0 | L82: =SUM(L77:L81) -> 0 | ... Q82: =SUM(Q77:Q81) -> 0
A84: 10、生产性生物资产期末公允价值变动
A85: 项 目 | B85: 审定数 | C85: 抵消数 | D85: 汇总 | E85: 母公司审定 | F85: 子公司1 | G85: 子公司2 | H85: 子公司3 | I85: 子公司4 | J85: 子公司5 | K85: 子公司6 | L85: 子公司7 | M85: 子公司8 | N85: 子公司9 | O85: 子公司10 | P85: 子公司11 | Q85: 子公司12
A86: =A77 -> 种植业 | B86: =D86-C86 -> 0 | D86: =SUM(E86:Q86) -> 0 | E86: =E14+E68 -> 0 | F86: =F14+F68 -> 0 | G86: =G14+G68 -> 0 | H86: =H14+H68 -> 0 | I86: =I14+I68 -> 0 | J86: =J14+J68 -> 0 | K86: =K14+K68 -> 0 | L86: =L14+L68 -> 0 | ... Q86: =Q14+Q68 -> 0
A87: =A78 -> 畜牧养殖业 | B87: =D87-C87 -> 0 | D87: =SUM(E87:Q87) -> 0 | E87: =E15+E69 -> 0 | F87: =F15+F69 -> 0 | G87: =G15+G69 -> 0 | H87: =H15+H69 -> 0 | I87: =I15+I69 -> 0 | J87: =J15+J69 -> 0 | K87: =K15+K69 -> 0 | L87: =L15+L69 -> 0 | ... Q87: =Q15+Q69 -> 0
A88: 林业 | B88: =D88-C88 -> 0 | D88: =SUM(E88:Q88) -> 0 | E88: =E16+E70 -> 0 | F88: =F16+F70 -> 0 | G88: =G16+G70 -> 0 | H88: =H16+H70 -> 0 | I88: =I16+I70 -> 0 | J88: =J16+J70 -> 0 | K88: =K16+K70 -> 0 | L88: =L16+L70 -> 0 | ... Q88: =Q16+Q70 -> 0
A89: 水产业 | B89: =D89-C89 -> 0 | D89: =SUM(E89:Q89) -> 0 | E89: =E17+E71 -> 0 | F89: =F17+F71 -> 0 | G89: =G17+G71 -> 0 | H89: =H17+H71 -> 0 | I89: =I17+I71 -> 0 | J89: =J17+J71 -> 0 | K89: =K17+K71 -> 0 | L89: =L17+L71 -> 0 | ... Q89: =Q17+Q71 -> 0
