Workbook
Name bs: {#N/A,#N/A,FALSE,"BBPREP"}
Name bs: {#N/A,#N/A,FALSE,"BBPREP"}
Name bs_1: {#N/A,#N/A,FALSE,"BBPREP"}
Name bs: {#N/A,#N/A,FALSE,"BBPREP"}
Name bs_1: {#N/A,#N/A,FALSE,"BBPREP"}
Name _?: #REF!
Name _??????: #REF!
Name __?: #REF!
Name __??????: #REF!
Name __2003002K8: #REF!
Name __2003002KA: #REF!
Name __2003002KC: #REF!
Name __2003002P1: #REF!
Name __2003007KA: #REF!
Name __2004001KF: #REF!
Name __2004001P1: #REF!
Name __2004009P1: #REF!
Name __2004012P1: #REF!
Name _1_?: #REF!
Name _10_2003002KA: #REF!
Name _10_2003002P1: #REF!
Name _10_2004009P1: #REF!
Name _11_2003002KC: #REF!
Name _11_2003007KA: #REF!
Name _11_2004012P1: #REF!
Name _12_??????: #REF!
Name _12_2003002P1: #REF!
Name _12_2004001KF: #REF!
Name _13_2003002K8: #REF!
Name _13_2003007KA: #REF!
Name _13_2004001P1: #REF!
Name _14_2003002KA: #REF!
Name _14_2004001KF: #REF!
Name _14_2004009P1: #REF!
Name _15_2003002KC: #REF!
Name _15_2004001P1: #REF!
Name _15_2004012P1: #REF!
Name _16_2003002P1: #REF!
Name _16_2004009P1: #REF!
Name _17_2003007KA: #REF!
Name _17_2004012P1: #REF!
Name _18_2004001KF: #REF!
Name _19_2004001P1: #REF!
Name _2_??????: #REF!
Name _20_2004009P1: #REF!
Name _2003002K8: #REF!
Name _2003002KA: #REF!
Name _2003002KC: #REF!
Name _2003002P1: #REF!
Name _2003007KA: #REF!
Name _2004001KF: #REF!
Name _2004001P1: #REF!
Name _2004009P1: #REF!
Name _2004012P1: #REF!
Name _21_2004012P1: #REF!
Name _3_?: #REF!
Name _3_2003002K8: #REF!
Name _4_?: #REF!
Name _4_2003002KA: #REF!
Name _5_2003002KC: #REF!

Sheet 底稿目录
A1: 底稿开列时，可先在以下单元格填写有关内容，以便其他底稿引用有关数据：
A2: 被审计单位： | D2: 序号 | E2: 内容 | F2: 索引号
A3: 截止日：202X年12月21日 | D3: 1 | E3: 存货实质性程序表 | F3: F2A
A4: 编制人： | D4: 2 | E4: 存货审定表 | F4: F2-1
A5: 编制日期： | D5: 3 | E5: 附注披露信息(上市公司） | G5: 无需打印
A6: 复核人： | D6: 4 | E6: 附注披露信息(国企） | G6: 无需打印
A7: 复核日期： | D7: 5 | E7: 存货明细汇总表 | F7: F2-2
D8: 6 | E8: 一、原材料明细表 | F8: F2-3
A9: 关于工作底稿与审计程序索引号对应的说明 | D9: 7 | E9: 二、材料采购、在途物资明细表 | F9: F2-4
A10: 1.编制的审计工作底稿应与审计程序对应。审计项目组应根据被审计单位实际情况和风险评估情况在实质性程序表中裁剪、修改或增加审计程序，根据实际执行的审计程序完成相应审计工作底稿，编制的工作底稿中应按自然顺序依次编制索引号，并通过唯一的索引号将与实质性程序表中的程序对应关联（即将工作底稿的索引号填入实质性程序表中的底稿索引号列）。 | D10: 8 | E10: 三、周转材料、低值易耗品，包装物明细表 | F10: F2-5
D11: 9 | E11: 四、自制半成品明细表 | F11: F2-6
D12: 10 | E12: 五、委托加工物资明细表 | F12: F2-7
D13: 11 | E13: 六、库存商品明细表 | F13: F2-8
A14: 2.获取的支持性证据应与审计底稿或程序对应。审计项目组在完成底稿时获取的支持性证据应根据底稿索引号编制下一级按自然顺序排序的索引号（如D1-2-1、D1-2-2、……），并在底稿中说明引用的支持性证据、关联索引号。 | D14: 12 | E14: 七、发出商品明细表 | F14: F2-9
D15: 13 | E15: 八、开发产品明细表 | F15: F2-10
D16: 14 | E16: 九、开发成本明细表 | F16: F2-11
A17: 3.工作底稿索引号的编码规则：实质性程序索引号按循环从“D”到“N”,循环内账户以顺序号排列，模板中底稿索引号按账户顺序+自然数顺序（即模板中索引号按二级自然顺序排列，如D1-1、D1-2、D1-3、……D1-N）。 | D17: 15 | E17: 十、合同履约成本明细表 | F17: F2-12
D18: 16 | E18: 十一、消耗性生物资产明细表 | F18: F2-13
D19: 17 | E19: 调整分录汇总 | F19: F2-14

Sheet 存货实质性程序表F2A
A1: 致同会计师事务所
A2: 存货实质性程序
A3: =[1]底稿目录!A2 -> 被审计单位： | D3: =[1]底稿目录!A4 -> 编制人： | F3: =[1]底稿目录!A5 -> 编制日期： | I3: 索引号： | J3: =[1]底稿目录!F3 -> F2A
A4: =[1]底稿目录!A3 -> 截止日：202X年12月21日 | D4: =[1]底稿目录!A6 -> 复核人： | F4: =[1]底稿目录!A7 -> 复核日期： | I4: 页 次：
A5: 一、本账户涉及的科目
A6: 存货及跌价准备
A7: 二、审计目标与认定的对应关系
A8: 审计目标 | H8: 财务报表的认定
A9: A. 资产负债表中记录的存货是存在的，且已经记录在恰当的账户中 | H9: 存在
A10: B. 所有应记录的存货均已记录，所有应当包括在财务报表中的相关披露均已包括 | H10: 完整性
A11: C. 记录的存货由被审计单位拥有或控制 | H11: 权利和义务
A12: D. 存货以恰当的金额包括在财务报表中，与之相关的计价或分摊调整已恰当记录，相关披露已得到恰当计量和描述 | H12: 准确性、计价和分摊
A13: E. 存货已被恰当地汇总或分解且表述清楚，相关披露在按照企业会计准则的编制基础下是相关的、可理解的 | H13: 列报
A14: 三、计划实施的实质性程序
A15: 序号 | B15: 与Leap对应 | C15: 审计程序 | D15: 程序分类 | E15: 财务报表的认定 | J15: 底稿索引号
E16: 存在 | F16: 完整性 | G16: 权利和 义务 | H16: 准确性、计价和分摊 | I16: 列报 | K16: 根据被审计单位实际情况和风险评估情况裁剪、修改或增加审计程序
A17: 1 | B17: 常规程序 | C17: 获取或编制存货的（收发存）明细表，完成以下工作，并编制审定表 （1）复核加计是否正确，与总账、明细账合计数核对是否相符，期初余额与上期审定期末余额是否相符； （2）获取管理层编制的存货库龄分析表，检查库龄划分是否正确； （3）检查存货明细表中是否有异常或负余额（包括数量为负或金额为负）的项目。 | D17: 常规★ | E17: √ | F17: √ | H17: √ | J17: F2-1/F2-2至F2-14
A18: 2 | B18: 常规程序 | C18: 抽查核对存货收发存明细账是否与仓储台账（ERP业务数据）、卡片记录相符（双向核对），存货是否及时入账，存货编号存在漏记、重复等。 | D18: 常规★ | E18: √ | F18: √ | H18: √ | J18: F2-24
A19: 3 | B19: IPE程序 | C19: 在使用手工编制、自定义信息报告、系统生成的非固定格式报告等由被审计单位生成的信息时，测试有关信息准确性和完整性，并考虑针对编制和维护由被审计单位生成的信息的相关控制实施控制测试，以评价该信息是否能够为实现审计目的提供基础。 | D19: 常规★ | F19: √ | H19: √ | J19: T1/ | K19: 可参见《审计手册》4.2.6，由被审计单位生成的信息可能是由系统生成的、或手工编制的、或二者兼而有之的方式生成的。例如，由被审计单位生成的信息可能包括： • 不涉及自定义的、由系统生成的报告（如，固定格式报告）； • 可能通过人工自定义的、由系统生成的报告，例如，（计算机）查询信息或特别定制的报告； • 手工编制的信息，例如，汇总信息的电子表格或用以支持分配、计算以及调节的电子表格； • 其他系统生成或手工编制的信息，例如，由被审计单位编制的客户发票； • 通过影印、拍摄、扫描或其他方式转换成电子形式的文件记录。
A20: 4 | B20: 期初余额程序 | C20: 对期初余额的审计，取得存货期初余额明细表复核加计是否正确，与总账、明细账合计数是否相符，检查期初存货在本期结转情况，取得上期存货盘点表核对差异，通过监盘当前的存货数量并调节至期初存货数量、对期初存货项目的计价实施审计程序、对毛利进行分析和存货截止实施审计程序。（适用于首次承接） | D20: 备选 | E20: √ | F20: √ | G20: √ | H20: √ | K20: 由被审计单位生成的信息不包括： • 总分类账或明细分类账、试算平衡表、或经审计的财务报表； • 第三方（除了服务机构）的报表或报告，例如，原始银行对账单，或函证的回函； • 外部数据（例如，第三方发布的数据，如，定价来源）。
A21: 5 | B21: 常规程序、应对措施-会计估计 | C21: 了解会计政策、会计估计合理性、一贯性，关注其是否利用会计政策和会计估计及其变更操纵利润。主要的会计政策和会计估计包括： （1）存货购入和发出的入账基础和计价方法、周转材料与固定资产的划分标准和摊销方法等； （2）生产工艺流程、辅助生产成本和制造费用摊销方法、自制半成品与完工产品的分配方法等； （3）存货跌价准备的计提方法、可变现净值的估计方法等； | D21: 常规★ | E21: √ | F21: √ | H21: √ | J21: F2-16
A22: 6 | B22: 应对措施-实质性/非实质性分析程序 | C22: 总体分析存货构成及重要指标： （1）分析本期及前期的构成，结构比变化情况； （2）分析整体存货周转率、存货跌价准备比率等存货关键指标的本期与前期变化、与同行业公司对比情况，主要产品的存货周转率本期与前期的变化情况； | D22: 常规★ | E22: √ | H22: √ | J22: F2-18
A23: 7 | B23: 应对措施-实质性/非实质性分析程序 | C23: 分析本期各月及前期主要产品的产量与销售量情况，分析前期及本期各月主要原材料本期采购与耗用情况，分析单位成本构成及变化情况，关注是否存在异常； | D23: 常规★ | E23: √ | H23: √ | J23: F2-19 /F2-20
A24: 8 | B24: 存货程序（选择“被审计单位执行定期盘点”“存货存放在多个地点”）、LEAP应对措施-检查（存货监盘） | C24: 实施存货监盘程序： （1）初步了解存货形态、存货存放地点等，初步确定监盘方式、时间和范围； （2）参与被审计单位存货盘点规划完成存货盘点问卷，获取盘点计划，评价被审计单位盘点内部控制、程序和指令是否恰当； （3）确定监盘时间、范围、人员、重点关注事项等，编制存货监盘计划； （4）观察被审计单位制定的盘点程序的执行情况，并检查存货的状况，是否存在过时、毁损或陈旧的存货； （5）执行抽盘，从存货盘点记录中选取项目追查至存货实物，以及从存货实物中选取项目追查至盘点记录，将抽盘结果与账面核对； （6）评价存货盘点结果，完成存货监盘小结。 | D24: 常规★ | E24: √ | F24: √ | G24: √ | H24: √ | J24: F2-21A
A25: 9 | B25: 存货程序（选择“被审计单位执行定期盘点”“存货存放在多个地点”）、LEAP应对措施-检查（存货监盘） | C25: 如果在存货盘点现场实施存货监盘不可行，实施替代审计程序。如果不能实施替代审计程序或实施替代审计程序无法获取有关存货的存在和状况的充分、适当的审计证据，考虑对审计意见的影响。替代程序主要包括： （1）检查进货交易凭证或生产记录以及其他相关资料； （2）检查资产负债表日后发生的销货交易凭证； （3）向顾客或供应商函证。 | D25: 常规★ | E25: √ | F25: √ | G25: √ | H25: √
A26: 10 | B26: 存货程序（选择“被审计单位存在由第三方保管或控制的存货”） | C26: 如果由第三方保管或控制的存货对财务报表是重要的，考虑： （1）现场盘点第三方保管或控制的存货； （2）向持有被审计单位存货的第三方函证存货的数量和状况； （3）实施检查或其他适合具体情况的审计程序。 | D26: 备选 | E26: √ | F26: √ | G26: √ | H26: √
A27: 11 | B27: 存货程序（选择“被审计单位存在寄售货物”） | C27: 如果存在他人委托被审计单位代售的商品（寄售商品），考虑： （1）该寄售商品未包含在被审计单位存货盘点范围内； （2）向寄售品所有者函证寄售商品； （3）检查受托代销的商品临近期末的重大销售，账务处理是否正确。 | D27: 备选 | E27: √ | F27: √ | G27: √ | H27: √
A28: 12 | B28: 应对措施-检查 | C28: 结合存货监盘程序，执行存货入库截止性测试： （1）从存货明细账借方发生额中抽取资产负债表日前后若干天、一定金额以上的凭证，与入库记录（如入库单，或购货发票，或运输单据）核对，以确定存货入库被记录在正确的会计期间； （2）从入库记录（如入库单或购货发票或运输单据）或其他表明所有权转移的单据中选取资产负债表日前后若干天、一定金额以上的凭据，与存货明细账的借方发生额进行核对，以确定存货人库被记录在正确的会计期间； （3）检查入库记录编号是否与执行存货监盘程序中获取的截止性资料编号存在冲突。 | D28: 常规★ | E28: √ | F28: √ | J28: F2-29 /F2-30
A29: 13 | B29: 应对措施-检查 | C29: 结合存货监盘、产成品结合营业收入截止程序，执行存货出库截止性测试： （1）从存货明细账贷方发生额中抽取资产负债表日前后若干张、一定金额以上的凭证，与出库记录（如出库单、原材料领用单）核对，以确定存货出库被记录在正确的会计期间； （2）从出库记录（如出库单、原材料领用单）中选取资产负债表日前后若干张、一定金额以上的凭据，与存货明细账的贷方发生额进行核对，以确定存货出库被记录在正确的会计期间； （3）检查出库记录编号是否与执行存货监盘程序中获取的截止性资料编号存在冲突。 | D29: 常规★ | E29: √ | F29: √ | J29: F2-31 /F2-32
A30: 14 | B30: 应对措施-检查 | C30: 采用恰当的抽样方法，从原材料、外购库存商品明细表中选择样本，检查入库单等支持性证据，确认会计处理是否正确。 | D30: 常规★ | E30: √ | G30: √ | H30: √ | J30: F2-33
A31: 15 | B31: 应对措施-检查 | C31: 采用恰当的抽样方法，从原材料发出明细账中选择样本，检查材料发出及领用的原始凭证，检查领料单的签发是否经过授权批准，手续是否齐全，会计处理是否正确。 | D31: 常规★ | E31: √ | F31: √ | H31: √ | J31: F2-34
A32: 16 | B32: 存货程序（存货成本） | C32: 采用恰当的抽样方法，从存货明细表中选择样本测试存货计价： （1）对原材料等外购存货，基于被审计单位原材料计价方法(如先进先出法，加权平均法等)，结合原材料的历史购买成本，测试其账面入库、出库、结存金额是否准确。 （2）对产成品，基于被审计单位产成品计价方法(如先进先出法，加权平均法等)，结合产成品入库成本，测试其账面入库、出库、结存金额是否准确。 | D32: 常规★ | H32: √ | J32: F2-38 /F2-39
A33: 17 | B33: 存货程序（存货成本） | C33: 在以标准成本计价时，应考虑标准成本的合理性并测试实际成本与标准成本差异的归集和分摊： （1）评价标准成本的合理性，检查标准成本在本期有无重大变动； （2）对直接材料结合采购等入库检查，测试材料成本差异的构成和分摊是否合理、正确；评估人工和间接费用分配方法和假设的合理性；评价标准制造费用中所包含的成本的适当性； （3）结合产成品成本计算单等，检查产成品实际价格与标准成本的差异分配是否正确； | D33: 备选 | H33: √ | J33: F2-40
A34: 18 | B34: 存货程序（存货成本） | C34: 检查生产成本/制造费用归集、分配是否合理、正确： （1）取得本期各月及前期的存货成本构成（料、工、费）明细情况，评价本期发生额和余额的总体合理性，将直接材料与材料耗用、直接人工与工资分配表等核对一致，检查生产成本分配方法，以及在完工产品与在产品间分配是否合理、一致、正确； （2）分析主要产品本期与上期的单位成本的变化，是否存在异常波动； （3）分析本期各月及前期产品计入生产成本的直接人工成本、单位人工成本情况，关注直接人工分摊是否合理，是否存在异常； （4）取得本期各月及前期制造费用明细情况，将资产折旧与折旧分配表、资产摊销与各项资产摊销分配表等核对一致，检查制造费用分配方法是否合理、适当，制造费用截止是否正确； （4）抽取成本计算单，检查直接材料、直接人工及制造费用的计算和分配是否正确。 | D34: 常规★ | H34: √ | J34: F2-41 /F2-20 /F2-42 /F2-43 /F2-44
A35: 19 | C35: 如果存在委托加工物资： （1）选取委托加工合同，检查有关发料凭证、加工费、运费结算凭证，关注所有权归属，核对其计费、计价是否正确，会计处理是否及时、正确； （2）检查加工完成物资的验收入库手续是否齐全，会计处理是否正确； （3）函证委托加工物资，必要时现场查看或利用其他注册会计师的工作。 | D35: 备选 | E35: √ | F35: √ | G35: √ | H35: √ | J35: F2-35 /F0
A36: 20 | B36: 存货程序（存货成本） | C36: 如果存在劳务成本： （1）选取劳务成本项目，检查有关劳务合同、劳务费结算等原始凭证，关注是否存在资本性支出，核对会计处理是否正确； （2）结合成本计算单等，检查劳务成本的分配是否合理、正确； （3）必要时对劳务成本实施截止测试，以确定被记录在正确的会计期间。 | D36: 备选 | H36: √
A37: 21 | B37: 存货程序（存货成本） | C37: 对于计入生产成本的借款费用，结合对长短期借款、应付债券或长期应付款等付息债务的审计，检查借款费用资本化的计算方法和资本化金额以及会计处理是否正确。 | D37: 备选 | H37: √
A38: 22 | B38: 存货程序（选择“期末存在在途货物”） | C38: 如果存在材料采购或在途物资： （1）选取期末物资采购或在途物资，检查有关原始单据； （2）抽取资产负债表日前后若干天物资采购或在途物资增减变动的有关账簿记录和收料报告单等资料，以确定被记录在正确的会计期间； （3）如采用标准成本计价，检查物资采购有关的材料成本差异归集和分配是否正确。 | D38: 备选 | E38: √ | F38: √ | G38: √ | H38: √
A39: 23 | C39: 如果存在周转材料（低值易耗品、包装物）： （1）检查周转材料的入库和领用的手续是否齐全，关注是否存在包装物押金，会计处理是否正确； （2）检查周转材料摊销方法是否正确，前后期是否一致； | D39: 备选 | E39: √ | F39: √ | G39: √ | H39: √
A40: 24 | B40: 应对措施-检查 | C40: 结合营业成本审计，检查发出库存商品的品种、数量和实际成本与“主营业务成本”是否相符。 | D40: 常规★ | E40: √ | F40: √ | H40: √ | J40: F5-6
A41: 25 | B41: 应对措施-会计估计 | C41: 存货跌价准备： （1）取得被审计单位存货跌价准备明细表、计算过程，评价存货跌价准备所依据的资料、假设及计提方法是否合理、是否符合会计准则的规定，会计处理是否正确； （2）分析存货的库龄、结合盘点结果识别滞销积压/停止经营/超出保质期或陈旧过时的存货； （3）选取样本重新计算期末存货跌价准备的金额； （4）检查存货跌价准备的转回是否合理，转回金额、会计处理是否正确。 | D41: 常规★ | H41: √ | J41: F2-47 /F2-48 /F2-49
A42: 26 | B42: 常规程序（选择“存在关联交易”） | C42: 检查关联方采购： （1）了解交易的商业理由、交易事项的目的、价格和条件，确定关联交易价格是否远高于或低于非关联方交易价格，考虑对关联方应付账款的合理性、合法性； （2）检查对关联方应付账款的真实性相关的支持性文件、检查会计处理是否正确； （3）考虑向关联方或其他注册会计师函证重大的关联采购交易和余额（包括担保和其他重要信息）； （4）必要时，向与交易相关的人员和机构（如银行、律师）函证或与其讨论有关信息； （5）考虑是否存在未识别的关联方，关联交易和余额披露是否正确。 | D42: 常规★ | E42: √ | F42: √ | G42: √ | H42: √ | I42: √ | J42: F2-52
A43: 27 | C43: 涉及异常或超出正常经营过程重大交易有关的存货项目（如债务重组、非货币性资产交换、企业合并等），询问管理层交易的性质和商业目的、期限和条件、交易对手，检查交易的支持性文件，考虑交易的商业理由是否合理，是否存在特别风险。 | D43: 备选 | E43: √ | F43: √ | H43: √
A44: 28 | C44: 针对涉及重大调整、销售退回、复杂交易、重大判断或估计、计量结果具有高度不确定性的存货项目考虑额外的审计程序 | D44: 备选 | E44: √ | F44: √ | H44: √
A45: 29 | C45: 如果存在合同履约成本，检查合同履约成本的构成是否合理、检查相关记账凭证和支持性证据、检查减值准备计提是否合理，考虑亏损合同等，检查合同履约成本的会计处理是否符合会计准则的规定等。 | D45: 备选 | J45: F2-55A
A46: 30 | C46: 关注或有、承诺事项： （1）询问管理层，检查有关合同协议、董事会会议记录等，确定存货是否存在用于抵押、担保的情况； （2）结合银行借款等科目的审计，了解是否有用于债务担保的存货，如有，则应取证并作相应的记录，同时核查被审计单位财务报表是否已作恰当披露。 | D46: 常规★ | G46: √ | H46: √ | I46: √
A47: 31 | C47: 根据评估的舞弊风险等因素增加的审计程序。 | D47: IPO/上市/新三板/重组/舞弊应对 | J47: F2-61A
A48: 32 | C48: 检查存货是否已按企业会计准则或其他适用的规定在财务报表中做出恰当列报和披露。 | D48: 常规★ | I48: √ | J48: A1-1/A1-15 /A1-16

Sheet 存货审定表F2-1
A1: 致同会计师事务所
A2: 存货及跌价准备审定表
A3: =[1]底稿目录!A2 -> 被审计单位： | B3: =[1]底稿目录!A4 -> 编制人： | C3: =[1]底稿目录!A5 -> 编制日期： | E3: 索引号： | F3: =[1]底稿目录!F4 -> F2-1
A4: =[1]底稿目录!A3 -> 截止日：202X年12月21日 | B4: =[1]底稿目录!A6 -> 复核人： | C4: =[1]底稿目录!A7 -> 复核日期： | E4: 页 次：
A5: 项目 | B5: 期初数 | C5: 本期增加 | D5: 本期减少 | E5: 期末数 | F5: 索引
A6: 一、原值
A7: 未审数 | B7: =SUM(B8:B20) -> 0 | C7: =SUM(C8:C20) -> 0 | D7: =SUM(D8:D20) -> 0 | E7: =SUM(E8:E20) -> 0
A8: ='[1]明细汇总表F2-2'!A17 -> 原材料 | B8: ='[1]明细汇总表F2-2'!B17 -> 0 | C8: ='[1]明细汇总表F2-2'!C17 -> 0 | D8: ='[1]明细汇总表F2-2'!D17 -> 0 | E8: =B8+C8-D8 -> 0
A9: ='[1]明细汇总表F2-2'!A18 -> 材料采购/在途物资 | B9: ='[1]明细汇总表F2-2'!B18 -> 0 | C9: ='[1]明细汇总表F2-2'!C18 -> 0 | D9: ='[1]明细汇总表F2-2'!D18 -> 0 | E9: =B9+C9-D9 -> 0
A10: ='[1]明细汇总表F2-2'!A19 -> 周转材料/低值易耗品/包装物 | B10: ='[1]明细汇总表F2-2'!B19 -> 0 | C10: ='[1]明细汇总表F2-2'!C19 -> 0 | D10: ='[1]明细汇总表F2-2'!D19 -> 0 | E10: =B10+C10-D10 -> 0
A11: ='[1]明细汇总表F2-2'!A20 -> 在产品 | B11: ='[1]明细汇总表F2-2'!B20 -> 0 | C11: ='[1]明细汇总表F2-2'!C20 -> 0 | D11: ='[1]明细汇总表F2-2'!D20 -> 0 | E11: =B11+C11-D11 -> 0
A12: ='[1]明细汇总表F2-2'!A21 -> 自制半成品 | B12: ='[1]明细汇总表F2-2'!B21 -> 0 | C12: ='[1]明细汇总表F2-2'!C21 -> 0 | D12: ='[1]明细汇总表F2-2'!D21 -> 0 | E12: =B12+C12-D12 -> 0
A13: ='[1]明细汇总表F2-2'!A22 -> 委托加工物资 | B13: ='[1]明细汇总表F2-2'!B22 -> 0 | C13: ='[1]明细汇总表F2-2'!C22 -> 0 | D13: ='[1]明细汇总表F2-2'!D22 -> 0 | E13: =B13+C13-D13 -> 0
A14: ='[1]明细汇总表F2-2'!A23 -> 库存商品 | B14: ='[1]明细汇总表F2-2'!B23 -> 0 | C14: ='[1]明细汇总表F2-2'!C23 -> 0 | D14: ='[1]明细汇总表F2-2'!D23 -> 0 | E14: =B14+C14-D14 -> 0
A15: ='[1]明细汇总表F2-2'!A24 -> 发出商品 | B15: ='[1]明细汇总表F2-2'!B24 -> 0 | C15: ='[1]明细汇总表F2-2'!C24 -> 0 | D15: ='[1]明细汇总表F2-2'!D24 -> 0 | E15: =B15+C15-D15 -> 0
A16: ='[1]明细汇总表F2-2'!A25 -> 开发产品 | B16: ='[1]明细汇总表F2-2'!B25 -> 0 | C16: ='[1]明细汇总表F2-2'!C25 -> 0 | D16: ='[1]明细汇总表F2-2'!D25 -> 0 | E16: =B16+C16-D16 -> 0
A17: ='[1]明细汇总表F2-2'!A26 -> 开发成本 | B17: ='[1]明细汇总表F2-2'!B26 -> 0 | C17: ='[1]明细汇总表F2-2'!C26 -> 0 | D17: ='[1]明细汇总表F2-2'!D26 -> 0 | E17: =B17+C17-D17 -> 0
A18: 合同履约成本 | B18: ='[1]明细汇总表F2-2'!B27 -> 0 | C18: ='[1]明细汇总表F2-2'!C27 -> 0 | D18: ='[1]明细汇总表F2-2'!D27 -> 0 | E18: =B18+C18-D18 -> 0
A19: ='[1]明细汇总表F2-2'!A28 -> 消耗性生物资产 | B19: ='[1]明细汇总表F2-2'!B28 -> 0 | C19: ='[1]明细汇总表F2-2'!C28 -> 0 | D19: ='[1]明细汇总表F2-2'!D28 -> 0 | E19: =B19+C19-D19 -> 0
A20: 数据资源 | B20: ='[1]明细汇总表F2-2'!B29 -> 0 | C20: ='[1]明细汇总表F2-2'!C29 -> 0 | D20: ='[1]明细汇总表F2-2'!D29 -> 0 | E20: =B20+C20-D20 -> 0
A21: 账项调整 | B21: =SUM(B22:B34) -> 0 | C21: =SUM(C22:C34) -> 0 | D21: =SUM(D22:D34) -> 0 | E21: =SUM(E22:E34) -> 0
A22: =A8 -> 原材料 | B22: ='[1]明细汇总表F2-2'!F17 -> 0 | C22: ='[1]明细汇总表F2-2'!G17 -> 0 | D22: ='[1]明细汇总表F2-2'!H17 -> 0 | E22: =B22+C22-D22 -> 0
A23: =A9 -> 材料采购/在途物资 | B23: ='[1]明细汇总表F2-2'!F18 -> 0 | C23: ='[1]明细汇总表F2-2'!G18 -> 0 | D23: ='[1]明细汇总表F2-2'!H18 -> 0 | E23: =B23+C23-D23 -> 0
A24: =A10 -> 周转材料/低值易耗品/包装物 | B24: ='[1]明细汇总表F2-2'!F19 -> 0 | C24: ='[1]明细汇总表F2-2'!G19 -> 0 | D24: ='[1]明细汇总表F2-2'!H19 -> 0 | E24: =B24+C24-D24 -> 0
A25: =A11 -> 在产品 | B25: ='[1]明细汇总表F2-2'!F20 -> 0 | C25: ='[1]明细汇总表F2-2'!G20 -> 0 | D25: ='[1]明细汇总表F2-2'!H20 -> 0 | E25: =B25+C25-D25 -> 0
A26: =A12 -> 自制半成品 | B26: ='[1]明细汇总表F2-2'!F21 -> 0 | C26: ='[1]明细汇总表F2-2'!G21 -> 0 | D26: ='[1]明细汇总表F2-2'!H21 -> 0 | E26: =B26+C26-D26 -> 0
A27: =A13 -> 委托加工物资 | B27: ='[1]明细汇总表F2-2'!F22 -> 0 | C27: ='[1]明细汇总表F2-2'!G22 -> 0 | D27: ='[1]明细汇总表F2-2'!H22 -> 0 | E27: =B27+C27-D27 -> 0
A28: =A14 -> 库存商品 | B28: ='[1]明细汇总表F2-2'!F23 -> 0 | C28: ='[1]明细汇总表F2-2'!G23 -> 0 | D28: ='[1]明细汇总表F2-2'!H23 -> 0 | E28: =B28+C28-D28 -> 0
A29: =A15 -> 发出商品 | B29: ='[1]明细汇总表F2-2'!F24 -> 0 | C29: ='[1]明细汇总表F2-2'!G24 -> 0 | D29: ='[1]明细汇总表F2-2'!H24 -> 0 | E29: =B29+C29-D29 -> 0
A30: =A16 -> 开发产品 | B30: ='[1]明细汇总表F2-2'!F25 -> 0 | C30: ='[1]明细汇总表F2-2'!G25 -> 0 | D30: ='[1]明细汇总表F2-2'!H25 -> 0 | E30: =B30+C30-D30 -> 0
A31: =A17 -> 开发成本 | B31: ='[1]明细汇总表F2-2'!F26 -> 0 | C31: ='[1]明细汇总表F2-2'!G26 -> 0 | D31: ='[1]明细汇总表F2-2'!H26 -> 0 | E31: =B31+C31-D31 -> 0
A32: =A18 -> 合同履约成本 | B32: ='[1]明细汇总表F2-2'!F27 -> 0 | C32: ='[1]明细汇总表F2-2'!G27 -> 0 | D32: ='[1]明细汇总表F2-2'!H27 -> 0 | E32: =B32+C32-D32 -> 0
A33: =A19 -> 消耗性生物资产 | B33: ='[1]明细汇总表F2-2'!F28 -> 0 | C33: ='[1]明细汇总表F2-2'!G28 -> 0 | D33: ='[1]明细汇总表F2-2'!H28 -> 0 | E33: =B33+C33-D33 -> 0
A34: 数据资源 | B34: ='[1]明细汇总表F2-2'!F29 -> 0 | C34: ='[1]明细汇总表F2-2'!G29 -> 0 | D34: ='[1]明细汇总表F2-2'!H29 -> 0 | E34: =B34+C34-D34 -> 0
A35: 审定数（原值） | B35: =SUM(B36:B48) -> 0 | C35: =SUM(C36:C48) -> 0 | D35: =SUM(D36:D48) -> 0 | E35: =SUM(E36:E48) -> 0
A36: =A8 -> 原材料 | B36: =B8+B22 -> 0 | C36: =C8+C22 -> 0 | D36: =D8+D22 -> 0 | E36: =E8+E22 -> 0
A37: =A9 -> 材料采购/在途物资 | B37: =B9+B23 -> 0 | C37: =C9+C23 -> 0 | D37: =D9+D23 -> 0 | E37: =E9+E23 -> 0
A38: =A10 -> 周转材料/低值易耗品/包装物 | B38: =B10+B24 -> 0 | C38: =C10+C24 -> 0 | D38: =D10+D24 -> 0 | E38: =E10+E24 -> 0
A39: =A11 -> 在产品 | B39: =B11+B25 -> 0 | C39: =C11+C25 -> 0 | D39: =D11+D25 -> 0 | E39: =E11+E25 -> 0
A40: =A12 -> 自制半成品 | B40: =B12+B26 -> 0 | C40: =C12+C26 -> 0 | D40: =D12+D26 -> 0 | E40: =E12+E26 -> 0
A41: =A13 -> 委托加工物资 | B41: =B13+B27 -> 0 | C41: =C13+C27 -> 0 | D41: =D13+D27 -> 0 | E41: =E13+E27 -> 0
A42: =A14 -> 库存商品 | B42: =B14+B28 -> 0 | C42: =C14+C28 -> 0 | D42: =D14+D28 -> 0 | E42: =E14+E28 -> 0
A43: =A15 -> 发出商品 | B43: =B15+B29 -> 0 | C43: =C15+C29 -> 0 | D43: =D15+D29 -> 0 | E43: =E15+E29 -> 0
A44: =A16 -> 开发产品 | B44: =B16+B30 -> 0 | C44: =C16+C30 -> 0 | D44: =D16+D30 -> 0 | E44: =E16+E30 -> 0
A45: =A17 -> 开发成本 | B45: =B17+B31 -> 0 | C45: =C17+C31 -> 0 | D45: =D17+D31 -> 0 | E45: =E17+E31 -> 0
A46: =A18 -> 合同履约成本 | B46: =B18+B32 -> 0 | C46: =C18+C32 -> 0 | D46: =D18+D32 -> 0 | E46: =E18+E32 -> 0
A47: =A19 -> 消耗性生物资产 | B47: =B19+B33 -> 0 | C47: =C19+C33 -> 0 | D47: =D19+D33 -> 0 | E47: =E19+E33 -> 0
A48: 数据资源 | B48: =B20+B34 -> 0 | C48: =C20+C34 -> 0 | D48: =D20+D34 -> 0 | E48: =E20+E34 -> 0
A49: 二、跌价准备
A50: 未审数 | B50: =SUM(B51:B63) -> 0 | C50: =SUM(C51:C63) -> 0 | D50: =SUM(D51:D63) -> 0 | E50: =SUM(E51:E63) -> 0
A51: =A8 -> 原材料 | B51: ='[1]明细汇总表F2-2'!B35 -> 0 | C51: ='[1]明细汇总表F2-2'!C35 -> 0 | D51: ='[1]明细汇总表F2-2'!D35 -> 0 | E51: =B51+C51-D51 -> 0
A52: =A9 -> 材料采购/在途物资 | B52: ='[1]明细汇总表F2-2'!B36 -> 0 | C52: ='[1]明细汇总表F2-2'!C36 -> 0 | D52: ='[1]明细汇总表F2-2'!D36 -> 0 | E52: =B52+C52-D52 -> 0
A53: =A10 -> 周转材料/低值易耗品/包装物 | B53: ='[1]明细汇总表F2-2'!B37 -> 0 | C53: ='[1]明细汇总表F2-2'!C37 -> 0 | D53: ='[1]明细汇总表F2-2'!D37 -> 0 | E53: =B53+C53-D53 -> 0
A54: =A11 -> 在产品 | B54: ='[1]明细汇总表F2-2'!B38 -> 0 | C54: ='[1]明细汇总表F2-2'!C38 -> 0 | D54: ='[1]明细汇总表F2-2'!D38 -> 0 | E54: =B54+C54-D54 -> 0
A55: =A12 -> 自制半成品 | B55: ='[1]明细汇总表F2-2'!B39 -> 0 | C55: ='[1]明细汇总表F2-2'!C39 -> 0 | D55: ='[1]明细汇总表F2-2'!D39 -> 0 | E55: =B55+C55-D55 -> 0
A56: =A13 -> 委托加工物资 | B56: ='[1]明细汇总表F2-2'!B40 -> 0 | C56: ='[1]明细汇总表F2-2'!C40 -> 0 | D56: ='[1]明细汇总表F2-2'!D40 -> 0 | E56: =B56+C56-D56 -> 0
A57: =A14 -> 库存商品 | B57: ='[1]明细汇总表F2-2'!B41 -> 0 | C57: ='[1]明细汇总表F2-2'!C41 -> 0 | D57: ='[1]明细汇总表F2-2'!D41 -> 0 | E57: =B57+C57-D57 -> 0
A58: =A15 -> 发出商品 | B58: ='[1]明细汇总表F2-2'!B42 -> 0 | C58: ='[1]明细汇总表F2-2'!C42 -> 0 | D58: ='[1]明细汇总表F2-2'!D42 -> 0 | E58: =B58+C58-D58 -> 0
A59: =A16 -> 开发产品 | B59: ='[1]明细汇总表F2-2'!B43 -> 0 | C59: ='[1]明细汇总表F2-2'!C43 -> 0 | D59: ='[1]明细汇总表F2-2'!D43 -> 0 | E59: =B59+C59-D59 -> 0
A60: =A17 -> 开发成本 | B60: ='[1]明细汇总表F2-2'!B44 -> 0 | C60: ='[1]明细汇总表F2-2'!C44 -> 0 | D60: ='[1]明细汇总表F2-2'!D44 -> 0 | E60: =B60+C60-D60 -> 0
A61: =A18 -> 合同履约成本 | B61: ='[1]明细汇总表F2-2'!B45 -> 0 | C61: ='[1]明细汇总表F2-2'!C45 -> 0 | D61: ='[1]明细汇总表F2-2'!D45 -> 0 | E61: =B61+C61-D61 -> 0
A62: =A19 -> 消耗性生物资产 | B62: ='[1]明细汇总表F2-2'!B46 -> 0 | C62: ='[1]明细汇总表F2-2'!C46 -> 0 | D62: ='[1]明细汇总表F2-2'!D46 -> 0 | E62: =B62+C62-D62 -> 0
A63: =A20 -> 数据资源 | B63: ='[1]明细汇总表F2-2'!B47 -> 0 | C63: ='[1]明细汇总表F2-2'!C47 -> 0 | D63: ='[1]明细汇总表F2-2'!D47 -> 0
A64: 账项调整 | B64: =SUM(B65:B77) -> 0 | C64: =SUM(C65:C77) -> 0 | D64: =SUM(D65:D77) -> 0 | E64: =SUM(E65:E77) -> 0
A65: =A22 -> 原材料 | B65: ='[1]明细汇总表F2-2'!F35 -> 0 | C65: ='[1]明细汇总表F2-2'!G35 -> 0 | D65: ='[1]明细汇总表F2-2'!H35 -> 0 | E65: =B65+C65-D65 -> 0
A66: =A23 -> 材料采购/在途物资 | B66: ='[1]明细汇总表F2-2'!F36 -> 0 | C66: ='[1]明细汇总表F2-2'!G36 -> 0 | D66: ='[1]明细汇总表F2-2'!H36 -> 0 | E66: =B66+C66-D66 -> 0
A67: =A24 -> 周转材料/低值易耗品/包装物 | B67: ='[1]明细汇总表F2-2'!F37 -> 0 | C67: ='[1]明细汇总表F2-2'!G37 -> 0 | D67: ='[1]明细汇总表F2-2'!H37 -> 0 | E67: =B67+C67-D67 -> 0
A68: =A25 -> 在产品 | B68: ='[1]明细汇总表F2-2'!F38 -> 0 | C68: ='[1]明细汇总表F2-2'!G38 -> 0 | D68: ='[1]明细汇总表F2-2'!H38 -> 0 | E68: =B68+C68-D68 -> 0
A69: =A26 -> 自制半成品 | B69: ='[1]明细汇总表F2-2'!F39 -> 0 | C69: ='[1]明细汇总表F2-2'!G39 -> 0 | D69: ='[1]明细汇总表F2-2'!H39 -> 0 | E69: =B69+C69-D69 -> 0
A70: =A27 -> 委托加工物资 | B70: ='[1]明细汇总表F2-2'!F40 -> 0 | C70: ='[1]明细汇总表F2-2'!G40 -> 0 | D70: ='[1]明细汇总表F2-2'!H40 -> 0 | E70: =B70+C70-D70 -> 0
A71: =A28 -> 库存商品 | B71: ='[1]明细汇总表F2-2'!F41 -> 0 | C71: ='[1]明细汇总表F2-2'!G41 -> 0 | D71: ='[1]明细汇总表F2-2'!H41 -> 0 | E71: =B71+C71-D71 -> 0
A72: =A29 -> 发出商品 | B72: ='[1]明细汇总表F2-2'!F42 -> 0 | C72: ='[1]明细汇总表F2-2'!G42 -> 0 | D72: ='[1]明细汇总表F2-2'!H42 -> 0 | E72: =B72+C72-D72 -> 0
A73: =A30 -> 开发产品 | B73: ='[1]明细汇总表F2-2'!F43 -> 0 | C73: ='[1]明细汇总表F2-2'!G43 -> 0 | D73: ='[1]明细汇总表F2-2'!H43 -> 0 | E73: =B73+C73-D73 -> 0
A74: =A31 -> 开发成本 | B74: ='[1]明细汇总表F2-2'!F44 -> 0 | C74: ='[1]明细汇总表F2-2'!G44 -> 0 | D74: ='[1]明细汇总表F2-2'!H44 -> 0 | E74: =B74+C74-D74 -> 0
A75: =A32 -> 合同履约成本 | B75: ='[1]明细汇总表F2-2'!F45 -> 0 | C75: ='[1]明细汇总表F2-2'!G45 -> 0 | D75: ='[1]明细汇总表F2-2'!H45 -> 0 | E75: =B75+C75-D75 -> 0
A76: =A33 -> 消耗性生物资产 | B76: ='[1]明细汇总表F2-2'!F46 -> 0 | C76: ='[1]明细汇总表F2-2'!G46 -> 0 | D76: ='[1]明细汇总表F2-2'!H46 -> 0 | E76: =B76+C76-D76 -> 0
A77: =A34 -> 数据资源 | B77: ='[1]明细汇总表F2-2'!F47 -> 0 | C77: ='[1]明细汇总表F2-2'!G47 -> 0 | D77: ='[1]明细汇总表F2-2'!H47 -> 0 | E77: =B77+C77-D77 -> 0
A78: 审定数（跌价准备） | B78: =SUM(B79:B91) -> 0 | C78: =SUM(C79:C91) -> 0 | D78: =SUM(D79:D91) -> 0 | E78: =SUM(E79:E91) -> 0
A79: =A36 -> 原材料 | B79: =B51+B65 -> 0 | C79: =C51+C65 -> 0 | D79: =D51+D65 -> 0 | E79: =E51+E65 -> 0
A80: =A37 -> 材料采购/在途物资 | B80: =B52+B66 -> 0 | C80: =C52+C66 -> 0 | D80: =D52+D66 -> 0 | E80: =E52+E66 -> 0
A81: =A38 -> 周转材料/低值易耗品/包装物 | B81: =B53+B67 -> 0 | C81: =C53+C67 -> 0 | D81: =D53+D67 -> 0 | E81: =E53+E67 -> 0
A82: =A39 -> 在产品 | B82: =B54+B68 -> 0 | C82: =C54+C68 -> 0 | D82: =D54+D68 -> 0 | E82: =E54+E68 -> 0
A83: =A40 -> 自制半成品 | B83: =B55+B69 -> 0 | C83: =C55+C69 -> 0 | D83: =D55+D69 -> 0 | E83: =E55+E69 -> 0
A84: =A41 -> 委托加工物资 | B84: =B56+B70 -> 0 | C84: =C56+C70 -> 0 | D84: =D56+D70 -> 0 | E84: =E56+E70 -> 0
A85: =A42 -> 库存商品 | B85: =B57+B71 -> 0 | C85: =C57+C71 -> 0 | D85: =D57+D71 -> 0 | E85: =E57+E71 -> 0
A86: =A43 -> 发出商品 | B86: =B58+B72 -> 0 | C86: =C58+C72 -> 0 | D86: =D58+D72 -> 0 | E86: =E58+E72 -> 0
A87: =A44 -> 开发产品 | B87: =B59+B73 -> 0 | C87: =C59+C73 -> 0 | D87: =D59+D73 -> 0 | E87: =E59+E73 -> 0
A88: =A45 -> 开发成本 | B88: =B60+B74 -> 0 | C88: =C60+C74 -> 0 | D88: =D60+D74 -> 0 | E88: =E60+E74 -> 0
A89: =A46 -> 合同履约成本 | B89: =B61+B75 -> 0 | C89: =C61+C75 -> 0 | D89: =D61+D75 -> 0 | E89: =E61+E75 -> 0
A90: =A47 -> 消耗性生物资产 | B90: =B62+B76 -> 0 | C90: =C62+C76 -> 0 | D90: =D62+D76 -> 0 | E90: =E62+E76 -> 0
A91: =A48 -> 数据资源 | B91: =B63+B77 -> 0 | C91: =C63+C77 -> 0 | D91: =D63+D77 -> 0 | E91: =E63+E77 -> 0
A92: 三、净值
A93: 审定数（净值） | B93: =SUM(B94:B106) -> 0 | C93: =SUM(C94:C106) -> 0 | D93: =SUM(D94:D106) -> 0 | E93: =SUM(E94:E106) -> 0
A94: =A8 -> 原材料 | B94: =B36-B79 -> 0 | C94: =C36-C79 -> 0 | D94: =D36-D79 -> 0 | E94: =E36-E79 -> 0
A95: =A9 -> 材料采购/在途物资 | B95: =B37-B80 -> 0 | C95: =C37-C80 -> 0 | D95: =D37-D80 -> 0 | E95: =E37-E80 -> 0
A96: =A10 -> 周转材料/低值易耗品/包装物 | B96: =B38-B81 -> 0 | C96: =C38-C81 -> 0 | D96: =D38-D81 -> 0 | E96: =E38-E81 -> 0
A97: =A11 -> 在产品 | B97: =B39-B82 -> 0 | C97: =C39-C82 -> 0 | D97: =D39-D82 -> 0 | E97: =E39-E82 -> 0
A98: =A12 -> 自制半成品 | B98: =B40-B83 -> 0 | C98: =C40-C83 -> 0 | D98: =D40-D83 -> 0 | E98: =E40-E83 -> 0
A99: =A13 -> 委托加工物资 | B99: =B41-B84 -> 0 | C99: =C41-C84 -> 0 | D99: =D41-D84 -> 0 | E99: =E41-E84 -> 0
A100: =A14 -> 库存商品 | B100: =B42-B85 -> 0 | C100: =C42-C85 -> 0 | D100: =D42-D85 -> 0 | E100: =E42-E85 -> 0
...

Sheet 附注披露信息（上市公司）
A1: 致同会计师事务所
A2: 存货附注披露信息（上市公司）
A3: =[1]底稿目录!A2 -> 被审计单位： | C3: =[1]底稿目录!A4 -> 编制人： | E3: =[1]底稿目录!A5 -> 编制日期： | G3: 索引号：
A4: =[1]底稿目录!A3 -> 截止日：202X年12月21日 | C4: =[1]底稿目录!A6 -> 复核人： | E4: =[1]底稿目录!A7 -> 复核日期： | G4: 页次：
A5: 存货附注披露信息：
A6: 存货
A7: （1）存货分类
A8: 存货种类 | B8: 期末数 | E8: 上年年末数
B9: 账面余额 | C9: 跌价准备/合同履约成本减值准备 | D9: 账面价值 | E9: 账面余额 | F9: 跌价准备/合同履约成本减值准备 | G9: 账面价值
A10: ='[1]存货审定表F2-1'!A36 -> 原材料 | B10: ='[1]存货审定表F2-1'!E36+'[1]存货审定表F2-1'!E37 -> 0 | C10: ='[1]存货审定表F2-1'!E79+'[1]存货审定表F2-1'!E80 -> 0 | D10: =B10-C10 -> 0 | E10: ='[1]存货审定表F2-1'!B36+'[1]存货审定表F2-1'!B37 -> 0 | F10: ='[1]存货审定表F2-1'!B79+'[1]存货审定表F2-1'!B80 -> 0 | G10: =E10-F10 -> 0
A11: ='[1]存货审定表F2-1'!A39 -> 在产品 | B11: ='[1]存货审定表F2-1'!E39+'[1]存货审定表F2-1'!E40 -> 0 | C11: ='[1]存货审定表F2-1'!E82+'[1]存货审定表F2-1'!E83 -> 0 | D11: =B11-C11 -> 0 | E11: ='[1]存货审定表F2-1'!B39+'[1]存货审定表F2-1'!B40 -> 0 | F11: ='[1]存货审定表F2-1'!B82+'[1]存货审定表F2-1'!B83 -> 0 | G11: =E11-F11 -> 0
A12: ='[1]存货审定表F2-1'!A41 -> 委托加工物资 | B12: ='[1]存货审定表F2-1'!E41 -> 0 | C12: ='[1]存货审定表F2-1'!E84 -> 0 | D12: =B12-C12 -> 0 | E12: ='[1]存货审定表F2-1'!B41 -> 0 | F12: ='[1]存货审定表F2-1'!B84 -> 0 | G12: =E12-F12 -> 0
A13: ='[1]存货审定表F2-1'!A42 -> 库存商品 | B13: ='[1]存货审定表F2-1'!E42 -> 0 | C13: ='[1]存货审定表F2-1'!E85 -> 0 | D13: =B13-C13 -> 0 | E13: ='[1]存货审定表F2-1'!B42 -> 0 | F13: ='[1]存货审定表F2-1'!B85 -> 0 | G13: =E13-F13 -> 0
A14: ='[1]存货审定表F2-1'!A43 -> 发出商品 | B14: ='[1]存货审定表F2-1'!E43 -> 0 | C14: ='[1]存货审定表F2-1'!E86 -> 0 | D14: =B14-C14 -> 0 | E14: ='[1]存货审定表F2-1'!B43 -> 0 | F14: ='[1]存货审定表F2-1'!B86 -> 0 | G14: =E14-F14 -> 0
A15: 周转材料 | B15: ='[1]存货审定表F2-1'!E38 -> 0 | C15: ='[1]存货审定表F2-1'!E81 -> 0 | D15: =B15-C15 -> 0 | E15: ='[1]存货审定表F2-1'!B38 -> 0 | F15: ='[1]存货审定表F2-1'!B81 -> 0 | G15: =E15-F15 -> 0
A16: 合同履约成本 | B16: ='[1]存货审定表F2-1'!E46 -> 0 | C16: ='[1]存货审定表F2-1'!E89 -> 0 | D16: =B16-C16 -> 0 | E16: ='[1]存货审定表F2-1'!B46 -> 0 | F16: ='[1]存货审定表F2-1'!B89 -> 0 | G16: =E16-F16 -> 0
A17: ='[1]存货审定表F2-1'!A47 -> 消耗性生物资产 | B17: ='[1]存货审定表F2-1'!E47 -> 0 | C17: ='[1]存货审定表F2-1'!E90 -> 0 | D17: =B17-C17 -> 0 | E17: ='[1]存货审定表F2-1'!B47 -> 0 | F17: ='[1]存货审定表F2-1'!B90 -> 0 | G17: =E17-F17 -> 0
A18: 数据资源 | B18: ='[1]存货审定表F2-1'!E48 -> 0 | C18: ='[1]存货审定表F2-1'!E91 -> 0 | D18: =B18-C18 -> 0 | E18: ='[1]存货审定表F2-1'!B48 -> 0 | F18: ='[1]存货审定表F2-1'!B91 -> 0 | G18: =E18-F18 -> 0
A19: 合 计 | B19: =SUM(B10:B18) -> 0 | C19: =SUM(C10:C18) -> 0 | D19: =SUM(D10:D18) -> 0 | E19: =SUM(E10:E18) -> 0 | F19: =SUM(F10:F18) -> 0 | G19: =SUM(G10:G18) -> 0
A20: （注：根据企业具体情况分类，房地产开发企业应增加“开发成本”、“开发产品”等种类）
A21: （2）存货跌价准备及合同履约成本减值准备
A22: 存货种类 | B22: 期初余额 | C22: 本期增加 | E22: 本期减少 | G22: 期末余额
C23: 计提 | D23: 其他 | E23: 转回或转销 | F23: 其他
A24: =A10 -> 原材料 | B24: ='[1]存货审定表F2-1'!B79+'[1]存货审定表F2-1'!B80 -> 0 | C24: ='[1]明细汇总表F2-2'!K35+'[1]明细汇总表F2-2'!K36 -> 0 | D24: ='[1]明细汇总表F2-2'!L35+'[1]明细汇总表F2-2'!L36 -> 0 | E24: ='[1]明细汇总表F2-2'!N35+'[1]明细汇总表F2-2'!O35+'[1]明细汇总表F2-2'!N36+'[1]明细汇总表F2-2'!O36 -> 0 | F24: ='[1]明细汇总表F2-2'!P35+'[1]明细汇总表F2-2'!P36 -> 0 | G24: =B24+C24+D24-E24-F24 -> 0
A25: =A11 -> 在产品 | B25: ='[1]存货审定表F2-1'!B82+'[1]存货审定表F2-1'!B83 -> 0 | C25: ='[1]明细汇总表F2-2'!K38+'[1]明细汇总表F2-2'!K39 -> 0 | D25: ='[1]明细汇总表F2-2'!L38+'[1]明细汇总表F2-2'!L39 -> 0 | E25: ='[1]明细汇总表F2-2'!N38+'[1]明细汇总表F2-2'!O38+'[1]明细汇总表F2-2'!N39+'[1]明细汇总表F2-2'!O39 -> 0 | F25: ='[1]明细汇总表F2-2'!P38+'[1]明细汇总表F2-2'!P39 -> 0 | G25: =B25+C25+D25-E25-F25 -> 0
A26: =A12 -> 委托加工物资 | B26: ='[1]存货审定表F2-1'!B84 -> 0 | C26: ='[1]明细汇总表F2-2'!K40 -> 0 | D26: ='[1]明细汇总表F2-2'!L40 -> 0 | E26: ='[1]明细汇总表F2-2'!N40+'[1]明细汇总表F2-2'!O40 -> 0 | F26: ='[1]明细汇总表F2-2'!P40 -> 0 | G26: =B26+C26+D26-E26-F26 -> 0
A27: =A13 -> 库存商品 | B27: ='[1]存货审定表F2-1'!B85 -> 0 | C27: ='[1]明细汇总表F2-2'!K41 -> 0 | D27: ='[1]明细汇总表F2-2'!L41 -> 0 | E27: ='[1]明细汇总表F2-2'!N41+'[1]明细汇总表F2-2'!O41 -> 0 | F27: ='[1]明细汇总表F2-2'!P41 -> 0 | G27: =B27+C27+D27-E27-F27 -> 0
A28: =A14 -> 发出商品 | B28: ='[1]存货审定表F2-1'!B86 -> 0 | C28: ='[1]明细汇总表F2-2'!K42 -> 0 | D28: ='[1]明细汇总表F2-2'!L42 -> 0 | E28: ='[1]明细汇总表F2-2'!N42+'[1]明细汇总表F2-2'!O42 -> 0 | F28: ='[1]明细汇总表F2-2'!P42 -> 0 | G28: =B28+C28+D28-E28-F28 -> 0
A29: =A15 -> 周转材料 | B29: ='[1]存货审定表F2-1'!B81 -> 0 | C29: ='[1]明细汇总表F2-2'!K37 -> 0 | D29: ='[1]明细汇总表F2-2'!L37 -> 0 | E29: ='[1]明细汇总表F2-2'!N37+'[1]明细汇总表F2-2'!O37 -> 0 | F29: ='[1]明细汇总表F2-2'!P37 -> 0 | G29: =B29+C29+D29-E29-F29 -> 0
A30: 合同履约成本 | B30: ='[1]存货审定表F2-1'!B89 -> 0 | C30: ='[1]明细汇总表F2-2'!K46 -> 0 | D30: ='[1]明细汇总表F2-2'!L46 -> 0 | E30: ='[1]明细汇总表F2-2'!N46+'[1]明细汇总表F2-2'!O46 -> 0 | F30: ='[1]明细汇总表F2-2'!P46 -> 0 | G30: =B30+C30+D30-E30-F30 -> 0
A31: =A17 -> 消耗性生物资产 | B31: ='[1]存货审定表F2-1'!B90 -> 0 | C31: ='[1]明细汇总表F2-2'!K46 -> 0 | D31: ='[1]明细汇总表F2-2'!L46 -> 0 | E31: ='[1]明细汇总表F2-2'!N46+'[1]明细汇总表F2-2'!O46 -> 0 | F31: ='[1]明细汇总表F2-2'!P46 -> 0 | G31: =B31+C31+D31-E31-F31 -> 0
A32: 数据资源 | B32: ='[1]存货审定表F2-1'!B91 -> 0 | C32: ='[1]明细汇总表F2-2'!K47 -> 0 | D32: ='[1]明细汇总表F2-2'!L47 -> 0 | E32: ='[1]明细汇总表F2-2'!N47+'[1]明细汇总表F2-2'!O47 -> 0 | F32: ='[1]明细汇总表F2-2'!P47 -> 0 | G32: =B32+C32+D32-E32-F32 -> 0
A33: 合 计 | B33: =SUM(B24:B32) -> 0 | C33: =SUM(C24:C32) -> 0 | D33: =SUM(D24:D32) -> 0 | E33: =SUM(E24:E32) -> 0 | F33: =SUM(F24:F32) -> 0 | G33: =SUM(G24:G32) -> 0
A34: 存货跌价准备及合同履约成本减值准备（续）
A35: 存货种类 | B35: 确定可变现净值/剩余对价与将要发生的成本的具体依据 | C35: 本期转回或转销存货跌价准备/合同履约成本减值准备的原因
A36: =A24 -> 原材料 | B36: ='[1]明细汇总表F2-2'!I53+'[1]明细汇总表F2-2'!I54 -> 0 | C36: ='[1]明细汇总表F2-2'!J53+'[1]明细汇总表F2-2'!J54 -> 0
A37: =A25 -> 在产品 | B37: ='[1]明细汇总表F2-2'!I56+'[1]明细汇总表F2-2'!I57 -> 0 | C37: ='[1]明细汇总表F2-2'!J56+'[1]明细汇总表F2-2'!J57 -> 0
A38: =A26 -> 委托加工物资 | B38: ='[1]明细汇总表F2-2'!I58 -> 0 | C38: ='[1]明细汇总表F2-2'!J58 -> 0
A39: =A27 -> 库存商品 | B39: ='[1]明细汇总表F2-2'!I59 -> 0 | C39: ='[1]明细汇总表F2-2'!J59 -> 0
A40: =A28 -> 发出商品 | B40: ='[1]明细汇总表F2-2'!I60 -> 0 | C40: ='[1]明细汇总表F2-2'!J60 -> 0
A41: =A29 -> 周转材料 | B41: ='[1]明细汇总表F2-2'!I55 -> 0 | C41: ='[1]明细汇总表F2-2'!J55 -> 0
A42: 合同履约成本 | B42: ='[1]明细汇总表F2-2'!I64 -> 0 | C42: ='[1]明细汇总表F2-2'!J64 -> 0
A43: =A31 -> 消耗性生物资产 | B43: ='[1]明细汇总表F2-2'!I64 -> 0 | C43: ='[1]明细汇总表F2-2'!J64 -> 0
A44: 数据资源 | B44: ='[1]明细汇总表F2-2'!I65 -> 0 | C44: ='[1]明细汇总表F2-2'!J65 -> 0
A45: 合 计 | B45: -- | C45: --
A46: 【披露确定可变现净值的具体依据及本期转回或转销存货跌价准备的原因。】
A47: （3）按组合计提存货跌价准备
A48: （15号文第十九条（六）按组合计提存货跌价准备的，应分类披露不同组合存货的期初余额、期末余额，对应的跌价准备的期初余额、期末余额、计提标准和比例。）
A49: 组 合 | B49: 期末余额
B50: 账面余额 | D50: 存货跌价准备 | G50: 账面价值
B51: 金额 | C51: 比例(%) | D51: 金额 | E51: 计提标准 | F51: 比例(%
C52: =B52/B54 -> #DIV/0! | F52: =D52/B52 -> #DIV/0! | G52: =B52-D52 -> 0
C53: =B53/B54 -> #DIV/0! | F53: =D53/B53 -> #DIV/0! | G53: =B53-D53 -> 0
A54: 合计 | B54: =SUM(B52:B53) -> 0 | C54: 1 | D54: =SUM(D52:D53) -> 0 | F54: =D54/B54 -> #DIV/0! | G54: =B54-D54 -> 0
A55: 续
A56: 组 合 | B56: 上年年末余额
B57: 账面余额 | D57: 存货跌价准备 | G57: 账面价值
B58: 金额 | C58: 比例(%) | D58: 金额 | E58: 计提标准 | F58: 比例(%
C59: =B59/B61 -> #DIV/0! | F59: =D59/B59 -> #DIV/0! | G59: =B59-D59 -> 0
C60: =B60/B61 -> #DIV/0! | F60: =D60/B60 -> #DIV/0! | G60: =B60-D60 -> 0
A61: 合计 | B61: =SUM(B59:B60) -> 0 | C61: 1 | D61: =SUM(D59:D60) -> 0 | F61: =D61/B61 -> #DIV/0! | G61: =B61-D61 -> 0
A63: （4）存货期末余额中含有借款费用资本化金额的说明：
A64: （15号文第十九条（六）披露存货期末余额中含有的借款费用资本化金额及其计算标准和依据。）
A65: （房地产开发企业，应按下列格式披露“开发成本”、“开发产品”等相关信息)
A66: （5）开发成本
A67: 项目名称 | B67: 开工时间 | C67: 预计竣工时间 | D67: 预计总投资 | E67: 期末数 | F67: 上年年末数 | G67: 期末跌价准备
A68: ='[1]九、开发成本F2-11'!B9 -> 0 | B68: ='[1]九、开发成本F2-11'!$D$9 -> 0 | C68: ='[1]九、开发成本F2-11'!E9 -> 0 | D68: ='[1]九、开发成本F2-11'!F9 -> 0 | E68: ='[1]九、开发成本F2-11'!J37 -> 0 | F68: ='[1]九、开发成本F2-11'!I37 -> 0 | G68: ='[1]九、开发成本F2-11'!T23 -> 0
A69: ='[1]九、开发成本F2-11'!B10 -> 0 | B69: ='[1]九、开发成本F2-11'!$D$9 -> 0 | C69: ='[1]九、开发成本F2-11'!E10 -> 0 | D69: ='[1]九、开发成本F2-11'!F10 -> 0 | E69: ='[1]九、开发成本F2-11'!J38 -> 0 | F69: ='[1]九、开发成本F2-11'!I38 -> 0 | G69: ='[1]九、开发成本F2-11'!T24 -> 0
A70: ='[1]九、开发成本F2-11'!B11 -> 0 | B70: ='[1]九、开发成本F2-11'!$D$9 -> 0 | C70: ='[1]九、开发成本F2-11'!E11 -> 0 | D70: ='[1]九、开发成本F2-11'!F11 -> 0 | E70: ='[1]九、开发成本F2-11'!J39 -> 0 | F70: ='[1]九、开发成本F2-11'!I39 -> 0 | G70: ='[1]九、开发成本F2-11'!T25 -> 0
A71: ='[1]九、开发成本F2-11'!B12 -> 0 | B71: ='[1]九、开发成本F2-11'!$D$9 -> 0 | C71: ='[1]九、开发成本F2-11'!E12 -> 0 | D71: ='[1]九、开发成本F2-11'!F12 -> 0 | E71: ='[1]九、开发成本F2-11'!J40 -> 0 | F71: ='[1]九、开发成本F2-11'!I40 -> 0 | G71: ='[1]九、开发成本F2-11'!T26 -> 0
A72: ='[1]九、开发成本F2-11'!B13 -> 0 | B72: ='[1]九、开发成本F2-11'!$D$9 -> 0 | C72: ='[1]九、开发成本F2-11'!E13 -> 0 | D72: ='[1]九、开发成本F2-11'!F13 -> 0 | E72: ='[1]九、开发成本F2-11'!J41 -> 0 | F72: ='[1]九、开发成本F2-11'!I41 -> 0 | G72: ='[1]九、开发成本F2-11'!T27 -> 0
A73: 合 计 | E73: =SUM(E68:E72) -> 0 | F73: =SUM(F68:F72) -> 0 | G73: =SUM(G68:G72) -> 0
A74: （6）开发产品
A75: 项目名称 | B75: 竣工时间 | C75: 期初余额 | D75: 本期增加 | E75: 本期减少 | F75: 期末余额 | G75: 期末跌价准备
A76: ='[1]八、开发产品F2-10'!$B$9 -> 0 | B76: ='[1]八、开发产品F2-10'!$E$9 -> 0 | C76: ='[1]八、开发产品F2-10'!H37 -> 0 | D76: ='[1]八、开发产品F2-10'!O9+'[1]八、开发产品F2-10'!V9+'[1]八、开发产品F2-10'!W9-'[1]八、开发产品F2-10'!I9-'[1]八、开发产品F2-10'!J9 -> 0 | E76: =C76+D76-F76 -> 0 | F76: ='[1]八、开发产品F2-10'!Q37 -> 0 | G76: ='[1]八、开发产品F2-10'!S23 -> 0
A77: ='[1]八、开发产品F2-10'!$B$9 -> 0 | B77: ='[1]八、开发产品F2-10'!$E$9 -> 0 | C77: ='[1]八、开发产品F2-10'!H45 -> 0 | D77: ='[1]八、开发产品F2-10'!O17+'[1]八、开发产品F2-10'!V17+'[1]八、开发产品F2-10'!W17-'[1]八、开发产品F2-10'!I17-'[1]八、开发产品F2-10'!J17 -> 0 | E77: =C77+D77-F77 -> 0 | F77: ='[1]八、开发产品F2-10'!Q45 -> 0 | G77: ='[1]八、开发产品F2-10'!S31 -> 0
A78: ='[1]八、开发产品F2-10'!$B$9 -> 0 | B78: ='[1]八、开发产品F2-10'!$E$9 -> 0 | C78: ='[1]八、开发产品F2-10'!H46 -> 0 | D78: ='[1]八、开发产品F2-10'!O18+'[1]八、开发产品F2-10'!V18+'[1]八、开发产品F2-10'!W18-'[1]八、开发产品F2-10'!I18-'[1]八、开发产品F2-10'!J18 -> 0 | E78: =C78+D78-F78 -> 0 | F78: ='[1]八、开发产品F2-10'!Q46 -> 0 | G78: ='[1]八、开发产品F2-10'!S32 -> 0
A79: ='[1]八、开发产品F2-10'!$B$9 -> 0 | B79: ='[1]八、开发产品F2-10'!$E$9 -> 0 | C79: ='[1]八、开发产品F2-10'!#REF! -> #REF! | D79: ='[1]八、开发产品F2-10'!#REF!+'[1]八、开发产品F2-10'!#REF!+'[1]八、开发产品F2-10'!#REF!-'[1]八、开发产品F2-10'!#REF!-'[1]八、开发产品F2-10'!#REF! -> #REF! | E79: =C79+D79-F79 -> #REF! | F79: ='[1]八、开发产品F2-10'!#REF! -> #REF! | G79: ='[1]八、开发产品F2-10'!#REF! -> #REF!
A80: ='[1]八、开发产品F2-10'!$B$9 -> 0 | B80: ='[1]八、开发产品F2-10'!$E$9 -> 0 | C80: ='[1]八、开发产品F2-10'!#REF! -> #REF! | D80: ='[1]八、开发产品F2-10'!#REF!+'[1]八、开发产品F2-10'!#REF!+'[1]八、开发产品F2-10'!#REF!-'[1]八、开发产品F2-10'!#REF!-'[1]八、开发产品F2-10'!#REF! -> #REF! | E80: =C80+D80-F80 -> #REF! | F80: ='[1]八、开发产品F2-10'!#REF! -> #REF! | G80: ='[1]八、开发产品F2-10'!#REF! -> #REF!
A81: ='[1]八、开发产品F2-10'!$B$9 -> 0 | B81: ='[1]八、开发产品F2-10'!$E$9 -> 0 | C81: ='[1]八、开发产品F2-10'!#REF! -> #REF! | D81: ='[1]八、开发产品F2-10'!#REF!+'[1]八、开发产品F2-10'!#REF!+'[1]八、开发产品F2-10'!#REF!-'[1]八、开发产品F2-10'!#REF!-'[1]八、开发产品F2-10'!#REF! -> #REF! | E81: =C81+D81-F81 -> #REF! | F81: ='[1]八、开发产品F2-10'!#REF! -> #REF! | G81: ='[1]八、开发产品F2-10'!#REF! -> #REF!
A82: 合 计 | C82: =SUM(C76:C81) -> #REF! | D82: =SUM(D76:D81) -> #REF! | E82: =SUM(E76:E81) -> #REF! | F82: =SUM(F76:F81) -> #REF! | G82: =SUM(G76:G81) -> #REF!
A83: （7）周转房
A84: 项目名称 | B84: 期初余额 | C84: 本期增加 | D84: 本期减少 | E84: 期末余额
A87: 合 计
A88: （房地产开发企业列示存货跌价准备时，对于开发中项目，可以合并列示。对“停工”、“烂尾”“空置”项目，如果不计提或计提跌价比例较低，应详细说明理由。）

Sheet 附注披露信息（国企）
A1: 致同会计师事务所
A2: 存货附注披露信息（国企）
A3: =[1]底稿目录!A2 -> 被审计单位： | B3: =[1]底稿目录!A4 -> 编制人： | E3: =[1]底稿目录!A5 -> 编制日期： | H3: 索引号：
A4: =[1]底稿目录!A3 -> 截止日：202X年12月21日 | B4: =[1]底稿目录!A6 -> 复核人： | E4: =[1]底稿目录!A7 -> 复核日期： | H4: 页次：
A5: 存货附注披露信息：
A6: （1）存货分类
A7: 项 目 | B7: 期末数 | E7: 期初数
B8: 账面余额 | C8: 跌价准备/合同履约成本减值准备 | D8: 账面价值 | E8: 账面余额 | F8: 跌价准备/合同履约成本减值准备 | G8: 账面价值
A9: ='[1]存货审定表F2-1'!A94 -> 原材料 | B9: ='[1]存货审定表F2-1'!E36+'[1]存货审定表F2-1'!E37 -> 0 | C9: ='[1]存货审定表F2-1'!E79+'[1]存货审定表F2-1'!E80 -> 0 | D9: =B9-C9 -> 0 | E9: ='[1]存货审定表F2-1'!B36+'[1]存货审定表F2-1'!B37 -> 0 | F9: ='[1]存货审定表F2-1'!B79+'[1]存货审定表F2-1'!B80 -> 0 | G9: =E9-F9 -> 0
A10: 自制半成品及在产品 | B10: ='[1]存货审定表F2-1'!E39+'[1]存货审定表F2-1'!E40+'[1]存货审定表F2-1'!E45 -> 0 | C10: ='[1]存货审定表F2-1'!E82+'[1]存货审定表F2-1'!E83+'[1]存货审定表F2-1'!E88 -> 0 | D10: =B10-C10 -> 0 | E10: ='[1]存货审定表F2-1'!B39+'[1]存货审定表F2-1'!B40+'[1]存货审定表F2-1'!B45 -> 0 | F10: ='[1]存货审定表F2-1'!B82+'[1]存货审定表F2-1'!B83+'[1]存货审定表F2-1'!B88 -> 0 | G10: =E10-F10 -> 0
A11: 其中：开发成本 | B11: ='[1]存货审定表F2-1'!E45 -> 0 | C11: ='[1]存货审定表F2-1'!E88 -> 0 | D11: =B11-C11 -> 0 | E11: ='[1]存货审定表F2-1'!B45 -> 0 | F11: ='[1]存货审定表F2-1'!B88 -> 0 | G11: =E11-F11 -> 0
A12: ='[1]存货审定表F2-1'!A99 -> 委托加工物资 | B12: ='[1]存货审定表F2-1'!E41 -> 0 | C12: ='[1]存货审定表F2-1'!E84 -> 0 | D12: =B12-C12 -> 0 | E12: ='[1]存货审定表F2-1'!B41 -> 0 | F12: ='[1]存货审定表F2-1'!B84 -> 0 | G12: =E12-F12 -> 0
A13: 库存商品（产成品） | B13: ='[1]存货审定表F2-1'!E42+'[1]存货审定表F2-1'!E44 -> 0 | C13: ='[1]存货审定表F2-1'!E85+'[1]存货审定表F2-1'!E87 -> 0 | D13: =B13-C13 -> 0 | E13: ='[1]存货审定表F2-1'!B42+'[1]存货审定表F2-1'!B44 -> 0 | F13: ='[1]存货审定表F2-1'!B85+'[1]存货审定表F2-1'!B87 -> 0 | G13: =E13-F13 -> 0
A14: 其中：开发产品 | B14: ='[1]存货审定表F2-1'!E44 -> 0 | C14: ='[1]存货审定表F2-1'!E87 -> 0 | D14: =B14-C14 -> 0 | E14: ='[1]存货审定表F2-1'!B44 -> 0 | F14: ='[1]存货审定表F2-1'!B87 -> 0 | G14: =E14-F14 -> 0
A15: 周转材料（包装物、低值易耗品等） | B15: ='[1]存货审定表F2-1'!E38 -> 0 | C15: ='[1]存货审定表F2-1'!E81 -> 0 | D15: =B15-C15 -> 0 | E15: ='[1]存货审定表F2-1'!B38 -> 0 | F15: ='[1]存货审定表F2-1'!B81 -> 0 | G15: =E15-F15 -> 0
A16: ='[1]存货审定表F2-1'!A101 -> 发出商品 | B16: ='[1]存货审定表F2-1'!E43 -> 0 | C16: ='[1]存货审定表F2-1'!E86 -> 0 | D16: =B16-C16 -> 0 | E16: ='[1]存货审定表F2-1'!B43 -> 0 | F16: ='[1]存货审定表F2-1'!B86 -> 0 | G16: =E16-F16 -> 0
A17: ='[1]存货审定表F2-1'!A105 -> 消耗性生物资产 | B17: ='[1]存货审定表F2-1'!E47 -> 0 | C17: ='[1]存货审定表F2-1'!E90 -> 0 | D17: =B17-C17 -> 0 | E17: ='[1]存货审定表F2-1'!B47 -> 0 | F17: ='[1]存货审定表F2-1'!B90 -> 0 | G17: =E17-F17 -> 0
A18: 合同履约成本 | B18: ='[1]存货审定表F2-1'!E46 -> 0 | C18: ='[1]存货审定表F2-1'!E89 -> 0 | D18: =B18-C18 -> 0 | E18: ='[1]存货审定表F2-1'!B46 -> 0 | F18: ='[1]存货审定表F2-1'!B89 -> 0 | G18: =E18-F18 -> 0
A19: 数据资源 | B19: ='[1]存货审定表F2-1'!E48 -> 0 | C19: ='[1]存货审定表F2-1'!E91 -> 0 | D19: =B19-C19 -> 0 | E19: ='[1]存货审定表F2-1'!B48 -> 0 | F19: ='[1]存货审定表F2-1'!B91 -> 0 | G19: =E19-F19 -> 0
A20: 其他
A21: 其中：尚未开发的土地储备(由房地产开发企业填列）
A22: 合 计 | B22: =SUM(B9:B21)-B11-B14-B21 -> 0 | C22: =SUM(C9:C21)-C11-C14-C21 -> 0 | D22: =SUM(D9:D21)-D11-D14-D21 -> 0 | E22: =SUM(E9:E21)-E11-E14-E21 -> 0 | F22: =SUM(F9:F21)-F11-F14-F21 -> 0 | G22: =SUM(G9:G21)-G11-G14-G21 -> 0
A23: （注：其他项中应说明房地产企业土地储备的情况，包括土地储备的面积、本期增加及土地储备年末余额。）
A24: （2）存货跌价准备及合同履约成本减值准备
A25: 存货种类 | B25: 期初数 | C25: 本期增加 | E25: 本期减少 | H25: 期末数
C26: 计提 | D26: 其他 | E26: 转回 | F26: 转销 | G26: 其他
A27: =A9 -> 原材料 | B27: ='[1]明细汇总表F2-2'!I35+'[1]明细汇总表F2-2'!I36 -> 0 | C27: ='[1]明细汇总表F2-2'!K35+'[1]明细汇总表F2-2'!K36 -> 0 | D27: ='[1]明细汇总表F2-2'!L35+'[1]明细汇总表F2-2'!L36 -> 0 | E27: ='[1]明细汇总表F2-2'!N35+'[1]明细汇总表F2-2'!N36 -> 0 | F27: ='[1]明细汇总表F2-2'!O35+'[1]明细汇总表F2-2'!O36 -> 0 | G27: ='[1]明细汇总表F2-2'!P35+'[1]明细汇总表F2-2'!P36 -> 0 | H27: =B27+C27+D27-E27-F27-G27 -> 0
A28: =A10 -> 自制半成品及在产品 | B28: ='[1]明细汇总表F2-2'!I38+'[1]明细汇总表F2-2'!I39+'[1]明细汇总表F2-2'!I44 -> 0 | C28: ='[1]明细汇总表F2-2'!K38+'[1]明细汇总表F2-2'!K39+'[1]明细汇总表F2-2'!K44 -> 0 | D28: ='[1]明细汇总表F2-2'!L38+'[1]明细汇总表F2-2'!L39+'[1]明细汇总表F2-2'!L44 -> 0 | E28: ='[1]明细汇总表F2-2'!N38+'[1]明细汇总表F2-2'!N39+'[1]明细汇总表F2-2'!N44 -> 0 | F28: ='[1]明细汇总表F2-2'!O38+'[1]明细汇总表F2-2'!O39+'[1]明细汇总表F2-2'!O44 -> 0 | G28: ='[1]明细汇总表F2-2'!P38+'[1]明细汇总表F2-2'!P39+'[1]明细汇总表F2-2'!P44 -> 0 | H28: =B28+C28+D28-E28-F28-G28 -> 0
A29: =A11 -> 其中：开发成本 | B29: ='[1]明细汇总表F2-2'!I44 -> 0 | C29: ='[1]明细汇总表F2-2'!K44 -> 0 | D29: ='[1]明细汇总表F2-2'!L44 -> 0 | E29: ='[1]明细汇总表F2-2'!N44 -> 0 | F29: ='[1]明细汇总表F2-2'!O44 -> 0 | G29: ='[1]明细汇总表F2-2'!P44 -> 0 | H29: =B29+C29+D29-E29-F29-G29 -> 0
A30: =A12 -> 委托加工物资 | B30: ='[1]明细汇总表F2-2'!I40 -> 0 | C30: ='[1]明细汇总表F2-2'!K40 -> 0 | D30: ='[1]明细汇总表F2-2'!L40 -> 0 | E30: ='[1]明细汇总表F2-2'!N40 -> 0 | F30: ='[1]明细汇总表F2-2'!O40 -> 0 | G30: ='[1]明细汇总表F2-2'!P40 -> 0 | H30: =B30+C30+D30-E30-F30-G30 -> 0
A31: =A13 -> 库存商品（产成品） | B31: ='[1]明细汇总表F2-2'!I41 -> 0 | C31: ='[1]明细汇总表F2-2'!K41 -> 0 | D31: ='[1]明细汇总表F2-2'!L41 -> 0 | E31: ='[1]明细汇总表F2-2'!N41 -> 0 | F31: ='[1]明细汇总表F2-2'!O41 -> 0 | G31: ='[1]明细汇总表F2-2'!P41 -> 0 | H31: =B31+C31+D31-E31-F31-G31 -> 0
A32: =A14 -> 其中：开发产品 | B32: ='[1]明细汇总表F2-2'!I43 -> 0 | C32: ='[1]明细汇总表F2-2'!K43 -> 0 | D32: ='[1]明细汇总表F2-2'!L43 -> 0 | E32: ='[1]明细汇总表F2-2'!N43 -> 0 | F32: ='[1]明细汇总表F2-2'!O43 -> 0 | G32: ='[1]明细汇总表F2-2'!P43 -> 0 | H32: =B32+C32+D32-E32-F32-G32 -> 0
A33: =A15 -> 周转材料（包装物、低值易耗品等） | B33: ='[1]明细汇总表F2-2'!I37 -> 0 | C33: ='[1]明细汇总表F2-2'!K37 -> 0 | D33: ='[1]明细汇总表F2-2'!L37 -> 0 | E33: ='[1]明细汇总表F2-2'!N37 -> 0 | F33: ='[1]明细汇总表F2-2'!O37 -> 0 | G33: ='[1]明细汇总表F2-2'!P37 -> 0 | H33: =B33+C33+D33-E33-F33-G33 -> 0
A34: =A16 -> 发出商品 | B34: ='[1]明细汇总表F2-2'!I42 -> 0 | C34: ='[1]明细汇总表F2-2'!K42 -> 0 | D34: ='[1]明细汇总表F2-2'!L42 -> 0 | E34: ='[1]明细汇总表F2-2'!N42 -> 0 | F34: ='[1]明细汇总表F2-2'!O42 -> 0 | G34: ='[1]明细汇总表F2-2'!P42 -> 0 | H34: =B34+C34+D34-E34-F34-G34 -> 0
A35: =A17 -> 消耗性生物资产 | B35: ='[1]明细汇总表F2-2'!I46 -> 0 | C35: ='[1]明细汇总表F2-2'!K46 -> 0 | D35: ='[1]明细汇总表F2-2'!L46 -> 0 | E35: ='[1]明细汇总表F2-2'!N46 -> 0 | F35: ='[1]明细汇总表F2-2'!O46 -> 0 | G35: ='[1]明细汇总表F2-2'!P46 -> 0 | H35: =B35+C35+D35-E35-F35-G35 -> 0
A36: =A18 -> 合同履约成本 | B36: ='[1]明细汇总表F2-2'!I45 -> 0 | C36: ='[1]明细汇总表F2-2'!K45 -> 0 | D36: ='[1]明细汇总表F2-2'!L45 -> 0 | E36: ='[1]明细汇总表F2-2'!N45 -> 0 | F36: ='[1]明细汇总表F2-2'!O45 -> 0 | G36: ='[1]明细汇总表F2-2'!P45 -> 0 | H36: =B36+C36+D36-E36-F36-G36 -> 0
A37: 数据资源 | B37: ='[1]明细汇总表F2-2'!I47 -> 0 | C37: ='[1]明细汇总表F2-2'!K47 -> 0 | D37: ='[1]明细汇总表F2-2'!L47 -> 0 | E37: ='[1]明细汇总表F2-2'!N47 -> 0 | F37: ='[1]明细汇总表F2-2'!O47 -> 0 | G37: ='[1]明细汇总表F2-2'!P47 -> 0 | H37: =B37+C37+D37-E37-F37-G37 -> 0
A38: =A20 -> 其他
A39: 其中：尚未开发的土地储备(由房地产开发企业填列）
A40: 合 计 | B40: =SUM(B27:B39)-B29-B32-B39 -> 0 | C40: =SUM(C27:C39)-C29-C32-C39 -> 0 | D40: =SUM(D27:D39)-D29-D32-D39 -> 0 | E40: =SUM(E27:E39)-E29-E32-E39 -> 0 | F40: =SUM(F27:F39)-F29-F32-F39 -> 0 | G40: =SUM(G27:G39)-G29-G32-G39 -> 0 | H40: =SUM(H27:H39)-H29-H32-H39 -> 0
A41: （3）借款费用资本化
A42: 存货期末余额中含有借款费用资本化金额为XXX元。
A43: （4）合同履约成本本期摊销金额的说明

Sheet 明细汇总表F2-2
A1: 致同会计师事务所
A2: 存货明细汇总表
A3: =[1]底稿目录!A2 -> 被审计单位： | F3: =[1]底稿目录!A4 -> 编制人： | K3: =[1]底稿目录!A5 -> 编制日期： | P3: 索引号： | Q3: =[1]底稿目录!F7 -> F2-2
A4: =[1]底稿目录!A3 -> 截止日：202X年12月21日 | F4: =[1]底稿目录!A6 -> 复核人： | K4: =[1]底稿目录!A7 -> 复核日期： | P4: 页 次：
A5: 一、审计目标：
A6: 1.资产负债表中记录的存货是存在的，且已经记录在恰当的账户中
A7: 2.所有应记录的存货均已记录，所有应当包括在财务报表中的相关披露均已包括
A8: 3.存货以恰当的金额包括在财务报表中，与之相关的计价或分摊调整已恰当记录，相关披露已得到恰当计量和描述
A9: 二、审计过程：
A10: 1.获取或编制存货（收发存）数量金额式明细表，复核加计正确，与总账、明细账合计数核对是否相符，期初余额与上期审定期末余额是否相符；
A11: 2.抽查核对存货收发存明细账是否与仓储台账（ERP业务数据）、卡片记录相符（双向核对），存货是否及时入账，存货编号存在漏记、重复等；
A12: 3.检查存货明细表中是否有异常或负余额（包括数量为负或金额为负）的项目；
A13: 4.获取管理层编制的存货库龄分析表，检查库龄划分是否正确；检查有无长期挂账的存货，如有，应查明原因，必要时作调整。
A14: （一）原值
A15: 项目 | B15: 未审数 | F15: 期初调整 | G15: 期末调整 | I15: 审定数 | M15: 备注 | N15: 索引号
B16: 期初余额 | C16: 本期增加 | D16: 本期减少 | E16: 期末数 | G16: 本期增加 | H16: 本期减少 | I16: 期初余额 | J16: 本期增加 | K16: 本期减少 | L16: 期末数
A17: 原材料 | B17: ='[1]一、原材料明细表F2-3'!$G$25 -> 0 | C17: ='[1]一、原材料明细表F2-3'!$J$25 -> 0 | D17: ='[1]一、原材料明细表F2-3'!$M$25 -> 0 | E17: =B17+C17-D17 -> 0 | I17: =B17+F17 -> 0 | J17: =C17+G17 -> 0 | K17: =D17+H17 -> 0 | L17: =I17+J17-K17 -> 0
A18: 材料采购/在途物资 | B18: ='[1]二、材料采购、在途物资明细表F2-4'!$F$25 -> 0 | C18: ='[1]二、材料采购、在途物资明细表F2-4'!$I$25 -> 0 | D18: ='[1]二、材料采购、在途物资明细表F2-4'!$L$25 -> 0 | E18: =B18+C18-D18 -> 0 | I18: =B18+F18 -> 0 | J18: =C18+G18 -> 0 | K18: =D18+H18 -> 0 | L18: =I18+J18-K18 -> 0
A19: 周转材料/低值易耗品/包装物 | B19: ='[1]三、周转材料、低值易耗品，包装物明细表F2-5'!$G$27 -> 0 | C19: ='[1]三、周转材料、低值易耗品，包装物明细表F2-5'!$J$27 -> 0 | D19: ='[1]三、周转材料、低值易耗品，包装物明细表F2-5'!$M$27 -> 0 | E19: =B19+C19-D19 -> 0 | I19: =B19+F19 -> 0 | J19: =C19+G19 -> 0 | K19: =D19+H19 -> 0 | L19: =I19+J19-K19 -> 0
A20: 在产品 | E20: =B20+C20-D20 -> 0 | I20: =B20+F20 -> 0 | J20: =C20+G20 -> 0 | K20: =D20+H20 -> 0 | L20: =I20+J20-K20 -> 0
A21: 自制半成品 | B21: ='[1]四、自制半成品明细表F2-6'!$G$25 -> 0 | C21: ='[1]四、自制半成品明细表F2-6'!$J$25 -> 0 | D21: ='[1]四、自制半成品明细表F2-6'!$M$25 -> 0 | E21: =B21+C21-D21 -> 0 | I21: =B21+F21 -> 0 | J21: =C21+G21 -> 0 | K21: =D21+H21 -> 0 | L21: =I21+J21-K21 -> 0
A22: 委托加工物资 | E22: =B22+C22-D22 -> 0 | I22: =B22+F22 -> 0 | J22: =C22+G22 -> 0 | K22: =D22+H22 -> 0 | L22: =I22+J22-K22 -> 0
A23: 库存商品 | B23: ='[1]六、库存商品明细表F2-8'!$G$25 -> 0 | C23: ='[1]六、库存商品明细表F2-8'!$J$25 -> 0 | D23: ='[1]六、库存商品明细表F2-8'!$M$25 -> 0 | E23: =B23+C23-D23 -> 0 | I23: =B23+F23 -> 0 | J23: =C23+G23 -> 0 | K23: =D23+H23 -> 0 | L23: =I23+J23-K23 -> 0
A24: 发出商品 | B24: ='[1]七、发出商品F2-9'!$F$25 -> 0 | C24: ='[1]七、发出商品F2-9'!$I$25 -> 0 | D24: ='[1]七、发出商品F2-9'!$L$25 -> 0 | E24: =B24+C24-D24 -> 0 | I24: =B24+F24 -> 0 | J24: =C24+G24 -> 0 | K24: =D24+H24 -> 0 | L24: =I24+J24-K24 -> 0
A25: 开发产品 | B25: ='[1]八、开发产品F2-10'!$H$19 -> 0 | C25: ='[1]八、开发产品F2-10'!$O$19 -> 0 | D25: ='[1]八、开发产品F2-10'!$R$19 -> 0 | E25: =B25+C25-D25 -> 0 | F25: ='[1]八、开发产品F2-10'!I19+'[1]八、开发产品F2-10'!J19 -> 0 | G25: ='[1]八、开发产品F2-10'!V19+'[1]八、开发产品F2-10'!W19 -> 0 | I25: =B25+F25 -> 0 | J25: =C25+G25 -> 0 | K25: =D25+H25 -> 0 | L25: =I25+J25-K25 -> 0
A26: 开发成本 | B26: ='[1]九、开发成本F2-11'!G19 -> 0 | C26: ='[1]九、开发成本F2-11'!H19 -> 0 | D26: ='[1]九、开发成本F2-11'!I19 -> 0 | E26: =B26+C26-D26 -> 0 | F26: ='[1]九、开发成本F2-11'!K19+'[1]九、开发成本F2-11'!L19 -> 0 | G26: ='[1]九、开发成本F2-11'!M19+'[1]九、开发成本F2-11'!O19 -> 0 | H26: ='[1]九、开发成本F2-11'!N19+'[1]九、开发成本F2-11'!P19 -> 0 | I26: =B26+F26 -> 0 | J26: =C26+G26 -> 0 | K26: =D26+H26 -> 0 | L26: =I26+J26-K26 -> 0
A27: 合同履约成本 | B27: ='[1]十、合同履约成本F2-12'!F20 -> 0 | C27: ='[1]十、合同履约成本F2-12'!G20 -> 0 | D27: ='[1]十、合同履约成本F2-12'!H20 -> 0 | E27: =B27+C27-D27 -> 0 | I27: =B27+F27 -> 0 | J27: =C27+G27 -> 0 | K27: =D27+H27 -> 0 | L27: =I27+J27-K27 -> 0
A28: 消耗性生物资产 | B28: ='[1]十一、消耗性生物资产F2-13'!$F$25 -> 0 | C28: ='[1]十一、消耗性生物资产F2-13'!$I$25 -> 0 | D28: ='[1]十一、消耗性生物资产F2-13'!$L$25 -> 0 | E28: =B28+C28-D28 -> 0 | I28: =B28+F28 -> 0 | J28: =C28+G28 -> 0 | K28: =D28+H28 -> 0 | L28: =I28+J28-K28 -> 0
A29: 数据资源 | E29: =B29+C29-D29 -> 0 | I29: =B29+F29 -> 0 | J29: =C29+G29 -> 0 | K29: =D29+H29 -> 0 | L29: =I29+J29-K29 -> 0
A30: …… | E30: =B30+C30-D30 -> 0 | I30: =B30+F30 -> 0 | J30: =C30+G30 -> 0 | K30: =D30+H30 -> 0 | L30: =I30+J30-K30 -> 0
A31: 合计 | B31: =SUM(B17:B30) -> 0 | C31: =SUM(C17:C30) -> 0 | D31: =SUM(D17:D30) -> 0 | E31: =SUM(E17:E30) -> 0 | F31: =SUM(F17:F30) -> 0 | G31: =SUM(G17:G30) -> 0 | H31: =SUM(H17:H30) -> 0 | I31: =SUM(I17:I30) -> 0 | ... L31: =SUM(L17:L30) -> 0
A32: （二）跌价准备
A33: 项目 | B33: 未审数 | F33: 期初调整 | G33: 期末调整 | I33: 审定数
B34: 期初余额 | C34: 本期增加 | D34: 本期减少 | E34: 期末数 | G34: 本期增加 | H34: 本期减少 | I34: 期初余额 | J34: 本期增加 | K34: 其中：(1)计提 | L34: (2)其他 | M34: 本期减少 | N34: 其中：(1)转回 | O34: (2)转销 | P34: (3)其他 | Q34: 期末数
A35: 原材料 | B35: ='[1]一、原材料明细表F2-3'!G26 -> 0 | C35: ='[1]一、原材料明细表F2-3'!J26 -> 0 | D35: ='[1]一、原材料明细表F2-3'!M26 -> 0 | E35: =B35+C35-D35 -> 0 | I35: =B35+F35 -> 0 | J35: =C35+G35 -> 0 | L35: =J35-K35 -> 0 | M35: =D35+H35 -> 0 | P35: =M35-N35-O35 -> 0 | Q35: =I35+J35-M35 -> 0
A36: 材料采购/在途物资 | B36: ='[1]二、材料采购、在途物资明细表F2-4'!F26 -> 0 | C36: ='[1]二、材料采购、在途物资明细表F2-4'!I26 -> 0 | D36: ='[1]二、材料采购、在途物资明细表F2-4'!L26 -> 0 | E36: =B36+C36-D36 -> 0 | I36: =B36+F36 -> 0 | J36: =C36+G36 -> 0 | L36: =J36-K36 -> 0 | M36: =D36+H36 -> 0 | P36: =M36-N36-O36 -> 0 | Q36: =I36+J36-M36 -> 0
A37: 周转材料/低值易耗品/包装物 | B37: ='[1]三、周转材料、低值易耗品，包装物明细表F2-5'!G28 -> 0 | C37: ='[1]三、周转材料、低值易耗品，包装物明细表F2-5'!J28 -> 0 | D37: ='[1]三、周转材料、低值易耗品，包装物明细表F2-5'!M28 -> 0 | E37: =B37+C37-D37 -> 0 | I37: =B37+F37 -> 0 | J37: =C37+G37 -> 0 | L37: =J37-K37 -> 0 | M37: =D37+H37 -> 0 | P37: =M37-N37-O37 -> 0 | Q37: =I37+J37-M37 -> 0
A38: 在产品 | E38: =B38+C38-D38 -> 0 | I38: =B38+F38 -> 0 | J38: =C38+G38 -> 0 | L38: =J38-K38 -> 0 | M38: =D38+H38 -> 0 | P38: =M38-N38-O38 -> 0 | Q38: =I38+J38-M38 -> 0
A39: 自制半成品 | B39: ='[1]四、自制半成品明细表F2-6'!G26 -> 0 | C39: ='[1]四、自制半成品明细表F2-6'!J26 -> 0 | D39: ='[1]四、自制半成品明细表F2-6'!M26 -> 0 | E39: =B39+C39-D39 -> 0 | I39: =B39+F39 -> 0 | J39: =C39+G39 -> 0 | L39: =J39-K39 -> 0 | M39: =D39+H39 -> 0 | P39: =M39-N39-O39 -> 0 | Q39: =I39+J39-M39 -> 0
A40: 委托加工物资 | E40: =B40+C40-D40 -> 0 | I40: =B40+F40 -> 0 | J40: =C40+G40 -> 0 | L40: =J40-K40 -> 0 | M40: =D40+H40 -> 0 | P40: =M40-N40-O40 -> 0 | Q40: =I40+J40-M40 -> 0
A41: 库存商品 | B41: ='[1]六、库存商品明细表F2-8'!G26 -> 0 | C41: ='[1]六、库存商品明细表F2-8'!J26 -> 0 | D41: ='[1]六、库存商品明细表F2-8'!M26 -> 0 | E41: =B41+C41-D41 -> 0 | I41: =B41+F41 -> 0 | J41: =C41+G41 -> 0 | L41: =J41-K41 -> 0 | M41: =D41+H41 -> 0 | P41: =M41-N41-O41 -> 0 | Q41: =I41+J41-M41 -> 0
A42: 发出商品 | B42: ='[1]七、发出商品F2-9'!F26 -> 0 | C42: ='[1]七、发出商品F2-9'!I26 -> 0 | D42: ='[1]七、发出商品F2-9'!L26 -> 0 | E42: =B42+C42-D42 -> 0 | I42: =B42+F42 -> 0 | J42: =C42+G42 -> 0 | L42: =J42-K42 -> 0 | M42: =D42+H42 -> 0 | P42: =M42-N42-O42 -> 0 | Q42: =I42+J42-M42 -> 0
A43: 开发产品 | B43: ='[1]八、开发产品F2-10'!F33 -> 0 | C43: ='[1]八、开发产品F2-10'!G33 -> 0 | D43: ='[1]八、开发产品F2-10'!H33 -> 0 | E43: =B43+C43-D43 -> 0 | F43: ='[1]八、开发产品F2-10'!J33+'[1]八、开发产品F2-10'!K33 -> 0 | G43: ='[1]八、开发产品F2-10'!L33+'[1]八、开发产品F2-10'!N33 -> 0 | H43: ='[1]八、开发产品F2-10'!M33+'[1]八、开发产品F2-10'!O33 -> 0 | I43: =B43+F43 -> 0 | J43: =C43+G43 -> 0 | L43: =J43-K43 -> 0 | M43: =D43+H43 -> 0 | P43: =M43-N43-O43 -> 0 | Q43: =I43+J43-M43 -> 0
A44: 开发成本 | B44: ='[1]九、开发成本F2-11'!G33 -> 0 | C44: ='[1]九、开发成本F2-11'!H33 -> 0 | D44: ='[1]九、开发成本F2-11'!I33 -> 0 | E44: =B44+C44-D44 -> 0 | F44: ='[1]九、开发成本F2-11'!K33+'[1]九、开发成本F2-11'!L33 -> 0 | G44: ='[1]九、开发成本F2-11'!M33+'[1]九、开发成本F2-11'!O33 -> 0 | H44: ='[1]九、开发成本F2-11'!N33+'[1]九、开发成本F2-11'!P33 -> 0 | I44: =B44+F44 -> 0 | J44: =C44+G44 -> 0 | L44: =J44-K44 -> 0 | M44: =D44+H44 -> 0 | P44: =M44-N44-O44 -> 0 | Q44: =I44+J44-M44 -> 0
A45: 合同履约成本 | B45: ='[1]十、合同履约成本F2-12'!F21 -> 0 | C45: ='[1]十、合同履约成本F2-12'!G21 -> 0 | D45: ='[1]十、合同履约成本F2-12'!H21 -> 0 | E45: =B45+C45-D45 -> 0 | I45: =B45+F45 -> 0 | J45: =C45+G45 -> 0 | L45: =J45-K45 -> 0 | M45: =D45+H45 -> 0 | P45: =M45-N45-O45 -> 0 | Q45: =I45+J45-M45 -> 0
A46: 消耗性生物资产 | B46: ='[1]十一、消耗性生物资产F2-13'!$C$40 -> 0 | C46: ='[1]十一、消耗性生物资产F2-13'!$D$40 -> 0 | D46: ='[1]十一、消耗性生物资产F2-13'!$E$40 -> 0 | E46: =B46+C46-D46 -> 0 | F46: ='[1]十一、消耗性生物资产F2-13'!G40+'[1]十一、消耗性生物资产F2-13'!H40 -> 0 | G46: ='[1]十一、消耗性生物资产F2-13'!I40+'[1]十一、消耗性生物资产F2-13'!K40 -> 0 | H46: ='[1]十一、消耗性生物资产F2-13'!J40+'[1]十一、消耗性生物资产F2-13'!L40 -> 0 | I46: =B46+F46 -> 0 | J46: =C46+G46 -> 0 | L46: =J46-K46 -> 0 | M46: =D46+H46 -> 0 | P46: =M46-N46-O46 -> 0 | Q46: =I46+J46-M46 -> 0
A47: 数据资源 | E47: =B47+C47-D47 -> 0 | I47: =B47+F47 -> 0 | J47: =C47+G47 -> 0 | L47: =J47-K47 -> 0 | M47: =D47+H47 -> 0 | P47: =M47-N47-O47 -> 0 | Q47: =I47+J47-M47 -> 0
A48: …… | E48: =B48+C48-D48 -> 0 | I48: =B48+F48 -> 0 | J48: =C48+G48 -> 0 | L48: =J48-K48 -> 0 | M48: =D48+H48 -> 0 | P48: =M48-N48-O48 -> 0 | Q48: =I48+J48-M48 -> 0
A49: 合计 | B49: =SUM(B35:B48) -> 0 | C49: =SUM(C35:C48) -> 0 | D49: =SUM(D35:D48) -> 0 | E49: =SUM(E35:E48) -> 0 | F49: =SUM(F35:F48) -> 0 | G49: =SUM(G35:G48) -> 0 | H49: =SUM(H35:H48) -> 0 | I49: =SUM(I35:I48) -> 0 | ... Q49: =SUM(Q35:Q48) -> 0
A50: （三）账面价值
A51: 项目 | B51: 未审数 | D51: 审定数 | F51: 变动率 | H51: 变动原因分析 | I51: 确定可变现净值的具体依据 | J51: 本期转回或转销存货跌价准备的原因 | K51: 索引号
B52: 期初数 | C52: 期末数 | D52: 期初数 | E52: 期末数 | F52: 未审变动率 | G52: 审定变动率
A53: 原材料 | B53: =B17-B35 -> 0 | C53: =E17-E35 -> 0 | D53: =I17-I35 -> 0 | E53: =L17-Q35 -> 0 | F53: =IF(B53=0,0,(C53-B53)/B53) -> 0 | G53: =IF(D53=0,0,(E53-D53)/D53) -> 0
A54: 材料采购/在途物资 | B54: =B18-B36 -> 0 | C54: =E18-E36 -> 0 | D54: =I18-I36 -> 0 | E54: =L18-Q36 -> 0 | F54: =IF(B54=0,0,(C54-B54)/B54) -> 0 | G54: =IF(D54=0,0,(E54-D54)/D54) -> 0
A55: 周转材料/低值易耗品/包装物 | B55: =B19-B37 -> 0 | C55: =E19-E37 -> 0 | D55: =I19-I37 -> 0 | E55: =L19-Q37 -> 0 | F55: =IF(B55=0,0,(C55-B55)/B55) -> 0 | G55: =IF(D55=0,0,(E55-D55)/D55) -> 0
A56: 在产品 | B56: =B20-B38 -> 0 | C56: =E20-E38 -> 0 | D56: =I20-I38 -> 0 | E56: =L20-Q38 -> 0 | F56: =IF(B56=0,0,(C56-B56)/B56) -> 0 | G56: =IF(D56=0,0,(E56-D56)/D56) -> 0
A57: 自制半成品 | B57: =B21-B39 -> 0 | C57: =E21-E39 -> 0 | D57: =I21-I39 -> 0 | E57: =L21-Q39 -> 0 | F57: =IF(B57=0,0,(C57-B57)/B57) -> 0 | G57: =IF(D57=0,0,(E57-D57)/D57) -> 0
A58: 委托加工物资 | B58: =B22-B40 -> 0 | C58: =E22-E40 -> 0 | D58: =I22-I40 -> 0 | E58: =L22-Q40 -> 0 | F58: =IF(B58=0,0,(C58-B58)/B58) -> 0 | G58: =IF(D58=0,0,(E58-D58)/D58) -> 0
A59: 库存商品 | B59: =B23-B41 -> 0 | C59: =E23-E41 -> 0 | D59: =I23-I41 -> 0 | E59: =L23-Q41 -> 0 | F59: =IF(B59=0,0,(C59-B59)/B59) -> 0 | G59: =IF(D59=0,0,(E59-D59)/D59) -> 0
A60: 发出商品 | B60: =B24-B42 -> 0 | C60: =E24-E42 -> 0 | D60: =I24-I42 -> 0 | E60: =L24-Q42 -> 0 | F60: =IF(B60=0,0,(C60-B60)/B60) -> 0 | G60: =IF(D60=0,0,(E60-D60)/D60) -> 0
A61: 开发产品 | B61: =B25-B43 -> 0 | C61: =E25-E43 -> 0 | D61: =I25-I43 -> 0 | E61: =L25-Q43 -> 0 | F61: =IF(B61=0,0,(C61-B61)/B61) -> 0 | G61: =IF(D61=0,0,(E61-D61)/D61) -> 0
A62: 开发成本 | B62: =B26-B44 -> 0 | C62: =E26-E44 -> 0 | D62: =I26-I44 -> 0 | E62: =L26-Q44 -> 0 | F62: =IF(B62=0,0,(C62-B62)/B62) -> 0 | G62: =IF(D62=0,0,(E62-D62)/D62) -> 0
A63: 合同履约成本 | B63: =B27-B45 -> 0 | C63: =E27-E45 -> 0 | D63: =I27-I45 -> 0 | E63: =L27-Q45 -> 0 | F63: =IF(B63=0,0,(C63-B63)/B63) -> 0 | G63: =IF(D63=0,0,(E63-D63)/D63) -> 0
A64: 消耗性生物资产 | B64: =B28-B46 -> 0 | C64: =E28-E46 -> 0 | D64: =I28-I46 -> 0 | E64: =L28-Q46 -> 0 | F64: =IF(B64=0,0,(C64-B64)/B64) -> 0 | G64: =IF(D64=0,0,(E64-D64)/D64) -> 0
... A66: …… | B66: =B30-B48 -> 0 | C66: =E30-E48 -> 0 | D66: =I30-I48 -> 0 | E66: =L30-Q48 -> 0 | F66: =IF(B66=0,0,(C66-B66)/B66) -> 0 | G66: =IF(D66=0,0,(E66-D66)/D66) -> 0
A67: 合计 | B67: =SUM(B53:B66) -> 0 | C67: =SUM(C53:C66) -> 0 | D67: =SUM(D53:D66) -> 0 | E67: =SUM(E53:E66) -> 0 | F67: =IF(B67=0,0,(C67-B67)/B67) -> 0 | G67: =IF(D67=0,0,(E67-D67)/D67) -> 0
A68: 三、审计说明：
A70: 四、审计结论：
A74: 提示：
A75: 1.审计说明可以概述：（1）程序的测试情况、结果；（2）拟调整事项及其调整分录、未调整事项及其影响，审计范围受到限制情况及其影响。
A76: 2.审计结论可参考：A、未见异常。 B、除上述重大不符事项应当作为调整事项予以调整外，其余未见异常。 C、由于存在以下重大未调整事项（或审计范围受到限制无法获取充分、适当证据），不可确认。

Sheet 一、原材料明细表F2-3
A1: 致同会计师事务所
A2: 存货明细表
A3: =[1]底稿目录!A2 -> 被审计单位： | F3: =[1]底稿目录!A4 -> 编制人： | M3: =[1]底稿目录!A5 -> 编制日期： | T3: 索引号： | U3: =[1]底稿目录!F8 -> F2-3
A4: =[1]底稿目录!A3 -> 截止日：202X年12月21日 | F4: =[1]底稿目录!A6 -> 复核人： | M4: =[1]底稿目录!A7 -> 复核日期： | T4: 页次：
A5: 一、原材料明细表
A6: 存货编码 | B6: 存货名称 | C6: 规格 | D6: 单位 | E6: 期初库存 | H6: 本期购进 | K6: 本期发出 | N6: 期末结存 | Q6: 库龄 | U6: 品质状况（正常、残次、毁损、滞销等）
E7: 数量 | F7: 单价 | G7: 金额 | H7: 数量 | I7: 单价 | J7: 金额 | K7: 数量 | L7: 单价 | M7: 金额 | N7: 数量 | O7: 单价 | P7: 金额 | Q7: 1年以内 | R7: 1-2年 | S7: 2-3年 | T7: 3年以上
F9: =IF(E9=0,0,G9/E9) -> 0 | I9: =IF(H9=0,0,J9/H9) -> 0 | L9: =IF(K9=0,0,M9/K9) -> 0 | N9: =E9+H9-K9 -> 0 | O9: =IF(N9=0,0,P9/N9) -> 0 | P9: =G9+J9-M9 -> 0
F10: =IF(E10=0,0,G10/E10) -> 0 | I10: =IF(H10=0,0,J10/H10) -> 0 | L10: =IF(K10=0,0,M10/K10) -> 0 | N10: =E10+H10-K10 -> 0 | O10: =IF(N10=0,0,P10/N10) -> 0 | P10: =G10+J10-M10 -> 0
F11: =IF(E11=0,0,G11/E11) -> 0 | I11: =IF(H11=0,0,J11/H11) -> 0 | L11: =IF(K11=0,0,M11/K11) -> 0 | N11: =E11+H11-K11 -> 0 | O11: =IF(N11=0,0,P11/N11) -> 0 | P11: =G11+J11-M11 -> 0
F12: =IF(E12=0,0,G12/E12) -> 0 | I12: =IF(H12=0,0,J12/H12) -> 0 | L12: =IF(K12=0,0,M12/K12) -> 0 | N12: =E12+H12-K12 -> 0 | O12: =IF(N12=0,0,P12/N12) -> 0 | P12: =G12+J12-M12 -> 0
F13: =IF(E13=0,0,G13/E13) -> 0 | I13: =IF(H13=0,0,J13/H13) -> 0 | L13: =IF(K13=0,0,M13/K13) -> 0 | N13: =E13+H13-K13 -> 0 | O13: =IF(N13=0,0,P13/N13) -> 0 | P13: =G13+J13-M13 -> 0
F14: =IF(E14=0,0,G14/E14) -> 0 | I14: =IF(H14=0,0,J14/H14) -> 0 | L14: =IF(K14=0,0,M14/K14) -> 0 | N14: =E14+H14-K14 -> 0 | O14: =IF(N14=0,0,P14/N14) -> 0 | P14: =G14+J14-M14 -> 0
F15: =IF(E15=0,0,G15/E15) -> 0 | I15: =IF(H15=0,0,J15/H15) -> 0 | L15: =IF(K15=0,0,M15/K15) -> 0 | N15: =E15+H15-K15 -> 0 | O15: =IF(N15=0,0,P15/N15) -> 0 | P15: =G15+J15-M15 -> 0
F16: =IF(E16=0,0,G16/E16) -> 0 | I16: =IF(H16=0,0,J16/H16) -> 0 | L16: =IF(K16=0,0,M16/K16) -> 0 | N16: =E16+H16-K16 -> 0 | O16: =IF(N16=0,0,P16/N16) -> 0 | P16: =G16+J16-M16 -> 0
F17: =IF(E17=0,0,G17/E17) -> 0 | I17: =IF(H17=0,0,J17/H17) -> 0 | L17: =IF(K17=0,0,M17/K17) -> 0 | N17: =E17+H17-K17 -> 0 | O17: =IF(N17=0,0,P17/N17) -> 0 | P17: =G17+J17-M17 -> 0
F18: =IF(E18=0,0,G18/E18) -> 0 | I18: =IF(H18=0,0,J18/H18) -> 0 | L18: =IF(K18=0,0,M18/K18) -> 0 | N18: =E18+H18-K18 -> 0 | O18: =IF(N18=0,0,P18/N18) -> 0 | P18: =G18+J18-M18 -> 0
F19: =IF(E19=0,0,G19/E19) -> 0 | I19: =IF(H19=0,0,J19/H19) -> 0 | L19: =IF(K19=0,0,M19/K19) -> 0 | N19: =E19+H19-K19 -> 0 | O19: =IF(N19=0,0,P19/N19) -> 0 | P19: =G19+J19-M19 -> 0
F20: =IF(E20=0,0,G20/E20) -> 0 | I20: =IF(H20=0,0,J20/H20) -> 0 | L20: =IF(K20=0,0,M20/K20) -> 0 | N20: =E20+H20-K20 -> 0 | O20: =IF(N20=0,0,P20/N20) -> 0 | P20: =G20+J20-M20 -> 0
... F23: =IF(E23=0,0,G23/E23) -> 0 | I23: =IF(H23=0,0,J23/H23) -> 0 | L23: =IF(K23=0,0,M23/K23) -> 0 | N23: =E23+H23-K23 -> 0 | O23: =IF(N23=0,0,P23/N23) -> 0 | P23: =G23+J23-M23 -> 0
B24: …… | F24: =IF(E24=0,0,G24/E24) -> 0 | I24: =IF(H24=0,0,J24/H24) -> 0 | L24: =IF(K24=0,0,M24/K24) -> 0 | N24: =E24+H24-K24 -> 0 | O24: =IF(N24=0,0,P24/N24) -> 0 | P24: =G24+J24-M24 -> 0
B25: 合计 | E25: -- | F25: -- | G25: =SUM(G9:G24) -> 0 | H25: -- | I25: -- | J25: =SUM(J9:J24) -> 0 | K25: -- | L25: -- | M25: =SUM(M9:M24) -> 0 | N25: -- | O25: -- | P25: =SUM(P9:P24) -> 0 | Q25: =SUM(Q9:Q24) -> 0 | R25: =SUM(R9:R24) -> 0 | S25: =SUM(S9:S24) -> 0 | T25: =SUM(T9:T24) -> 0
B26: 减：存货跌价准备
B27: 原材料净额 | E27: -- | F27: -- | G27: =G25-G26 -> 0 | H27: -- | I27: -- | J27: =J25-J26 -> 0 | K27: -- | L27: -- | M27: =M25-M26 -> 0 | N27: -- | O27: -- | P27: =P25-P26 -> 0 | Q27: =Q25-Q26 -> 0 | R27: =R25-R26 -> 0 | S27: =S25-S26 -> 0 | T27: =T25-T26 -> 0
A28: 审计说明： | P28: =IF((P25-Q25-R25-S25-T25)=0,"OK","库龄与期末金额不匹配") -> OK
A29: 1.原材料计价方法： | J29: 3.原材料——**库龄较长的原因：
A30: 2.原材料本期发生重大变动的原因： | J30: 4.计提跌价准备的主要项目及原因：

Sheet 二、材料采购、在途物资明细表F2-4
A1: 致同会计师事务所
A2: 存货明细表
A3: =[1]底稿目录!A2 -> 被审计单位： | F3: =[1]底稿目录!A4 -> 编制人： | N3: =[1]底稿目录!A5 -> 编制日期： | V3: 索引号： | W3: =[1]底稿目录!F9 -> F2-4
A4: =[1]底稿目录!A3 -> 截止日：202X年12月21日 | F4: =[1]底稿目录!A6 -> 复核人： | N4: =[1]底稿目录!A7 -> 复核日期： | V4: 页次：
A5: 二、材料采购/在途物资明细表
A6: 供货单位 | B6: 采购物资名称及规格 | C6: 单位 | D6: 期初库存 | G6: 本期购进 | J6: 本期转出 | M6: 期末结存 | P6: 期后结转 | S6: 库龄 | W6: 品质状况（正常、残次、毁损、滞销等）
D7: 数量 | E7: 单价 | F7: 金额 | G7: 数量 | H7: 单价 | I7: 金额 | J7: 数量 | K7: 单价 | L7: 金额 | M7: 数量 | N7: 单价 | O7: 金额 | P7: 数量 | Q7: 单价 | R7: 金额 | S7: 1年以内 | T7: 1-2年 | U7: 2-3年 | V7: 3年以上
E9: =IF(D9=0,0,F9/D9) -> 0 | H9: =IF(G9=0,0,I9/G9) -> 0 | K9: =IF(J9=0,0,L9/J9) -> 0 | M9: =D9+G9-J9 -> 0 | N9: =IF(M9=0,0,O9/M9) -> 0 | O9: =F9+I9-L9 -> 0 | Q9: =IF(P9=0,0,R9/P9) -> 0
E10: =IF(D10=0,0,F10/D10) -> 0 | H10: =IF(G10=0,0,I10/G10) -> 0 | K10: =IF(J10=0,0,L10/J10) -> 0 | M10: =D10+G10-J10 -> 0 | N10: =IF(M10=0,0,O10/M10) -> 0 | O10: =F10+I10-L10 -> 0 | Q10: =IF(P10=0,0,R10/P10) -> 0
E11: =IF(D11=0,0,F11/D11) -> 0 | H11: =IF(G11=0,0,I11/G11) -> 0 | K11: =IF(J11=0,0,L11/J11) -> 0 | M11: =D11+G11-J11 -> 0 | N11: =IF(M11=0,0,O11/M11) -> 0 | O11: =F11+I11-L11 -> 0 | Q11: =IF(P11=0,0,R11/P11) -> 0
E12: =IF(D12=0,0,F12/D12) -> 0 | H12: =IF(G12=0,0,I12/G12) -> 0 | K12: =IF(J12=0,0,L12/J12) -> 0 | M12: =D12+G12-J12 -> 0 | N12: =IF(M12=0,0,O12/M12) -> 0 | O12: =F12+I12-L12 -> 0 | Q12: =IF(P12=0,0,R12/P12) -> 0
E13: =IF(D13=0,0,F13/D13) -> 0 | H13: =IF(G13=0,0,I13/G13) -> 0 | K13: =IF(J13=0,0,L13/J13) -> 0 | M13: =D13+G13-J13 -> 0 | N13: =IF(M13=0,0,O13/M13) -> 0 | O13: =F13+I13-L13 -> 0 | Q13: =IF(P13=0,0,R13/P13) -> 0
E14: =IF(D14=0,0,F14/D14) -> 0 | H14: =IF(G14=0,0,I14/G14) -> 0 | K14: =IF(J14=0,0,L14/J14) -> 0 | M14: =D14+G14-J14 -> 0 | N14: =IF(M14=0,0,O14/M14) -> 0 | O14: =F14+I14-L14 -> 0 | Q14: =IF(P14=0,0,R14/P14) -> 0
E15: =IF(D15=0,0,F15/D15) -> 0 | H15: =IF(G15=0,0,I15/G15) -> 0 | K15: =IF(J15=0,0,L15/J15) -> 0 | M15: =D15+G15-J15 -> 0 | N15: =IF(M15=0,0,O15/M15) -> 0 | O15: =F15+I15-L15 -> 0 | Q15: =IF(P15=0,0,R15/P15) -> 0
E16: =IF(D16=0,0,F16/D16) -> 0 | H16: =IF(G16=0,0,I16/G16) -> 0 | K16: =IF(J16=0,0,L16/J16) -> 0 | M16: =D16+G16-J16 -> 0 | N16: =IF(M16=0,0,O16/M16) -> 0 | O16: =F16+I16-L16 -> 0 | Q16: =IF(P16=0,0,R16/P16) -> 0
E17: =IF(D17=0,0,F17/D17) -> 0 | H17: =IF(G17=0,0,I17/G17) -> 0 | K17: =IF(J17=0,0,L17/J17) -> 0 | M17: =D17+G17-J17 -> 0 | N17: =IF(M17=0,0,O17/M17) -> 0 | O17: =F17+I17-L17 -> 0 | Q17: =IF(P17=0,0,R17/P17) -> 0
E18: =IF(D18=0,0,F18/D18) -> 0 | H18: =IF(G18=0,0,I18/G18) -> 0 | K18: =IF(J18=0,0,L18/J18) -> 0 | M18: =D18+G18-J18 -> 0 | N18: =IF(M18=0,0,O18/M18) -> 0 | O18: =F18+I18-L18 -> 0 | Q18: =IF(P18=0,0,R18/P18) -> 0
E19: =IF(D19=0,0,F19/D19) -> 0 | H19: =IF(G19=0,0,I19/G19) -> 0 | K19: =IF(J19=0,0,L19/J19) -> 0 | M19: =D19+G19-J19 -> 0 | N19: =IF(M19=0,0,O19/M19) -> 0 | O19: =F19+I19-L19 -> 0 | Q19: =IF(P19=0,0,R19/P19) -> 0
E20: =IF(D20=0,0,F20/D20) -> 0 | H20: =IF(G20=0,0,I20/G20) -> 0 | K20: =IF(J20=0,0,L20/J20) -> 0 | M20: =D20+G20-J20 -> 0 | N20: =IF(M20=0,0,O20/M20) -> 0 | O20: =F20+I20-L20 -> 0 | Q20: =IF(P20=0,0,R20/P20) -> 0
... E23: =IF(D23=0,0,F23/D23) -> 0 | H23: =IF(G23=0,0,I23/G23) -> 0 | K23: =IF(J23=0,0,L23/J23) -> 0 | M23: =D23+G23-J23 -> 0 | N23: =IF(M23=0,0,O23/M23) -> 0 | O23: =F23+I23-L23 -> 0 | Q23: =IF(P23=0,0,R23/P23) -> 0
A24: …… | E24: =IF(D24=0,0,F24/D24) -> 0 | H24: =IF(G24=0,0,I24/G24) -> 0 | K24: =IF(J24=0,0,L24/J24) -> 0 | M24: =D24+G24-J24 -> 0 | N24: =IF(M24=0,0,O24/M24) -> 0 | O24: =F24+I24-L24 -> 0 | Q24: =IF(P24=0,0,R24/P24) -> 0
A25: 合计 | D25: -- | E25: -- | F25: =SUM(F9:F24) -> 0 | G25: -- | H25: -- | I25: =SUM(I9:I24) -> 0 | J25: -- | K25: -- | L25: =SUM(L9:L24) -> 0 | M25: -- | N25: -- | O25: =SUM(O9:O24) -> 0 | P25: -- | Q25: -- | R25: =SUM(R9:R24) -> 0 | S25: =SUM(S9:S24) -> 0 | T25: =SUM(T9:T24) -> 0 | U25: =SUM(U9:U24) -> 0 | V25: =SUM(V9:V24) -> 0
A26: 减：存货跌价准备
A27: 材料采购/在途物资净额 | D27: -- | E27: -- | F27: =F25-F26 -> 0 | G27: -- | H27: -- | I27: =I25-I26 -> 0 | J27: -- | K27: -- | L27: =L25-L26 -> 0 | M27: -- | N27: -- | O27: =O25-O26 -> 0 | P27: -- | Q27: -- | R27: =R25-R26 -> 0 | S27: =S25-S26 -> 0 | T27: =T25-T26 -> 0 | U27: =U25-U26 -> 0 | V27: =V25-V26 -> 0
A28: 审计说明： | O28: =IF((O25-S25-T25-U25-V25)=0,"OK","库龄与期末金额不匹配") -> OK
A29: 1.在途物资资产负债表日后入库情况： | J29: 3.物资采购/在途物资——**库龄较长的原因：
A30: 2.物资采购/在途物资本期发生重大变动的原因： | J30: 4.计提跌价准备的主要项目及原因：

Sheet 三、周转材料、低值易耗品，包装物明细表F2-5
A1: 致同会计师事务所
A2: 存货明细表
A3: =[1]底稿目录!A2 -> 被审计单位： | G3: =[1]底稿目录!A4 -> 编制人： | K3: =[1]底稿目录!A5 -> 编制日期： | T3: 索引号： | U3: =[1]底稿目录!F10 -> F2-5
A4: =[1]底稿目录!A3 -> 截止日：202X年12月21日 | G4: =[1]底稿目录!A6 -> 复核人： | K4: =[1]底稿目录!A7 -> 复核日期： | T4: 页次：
A5: 三、周转材料/低值易耗品/包装物明细表
A6: 类别 | B6: 存货编码 | C6: 名称及规格 | D6: 单位 | E6: 期初库存 | H6: 本期购进 | K6: 本期发出 | N6: 期末结存 | Q6: 库龄 | U6: 品质状况（正常、残次、毁损、滞销等）
E7: 数量 | F7: 单价 | G7: 金额 | H7: 数量 | I7: 单价 | J7: 金额 | K7: 数量 | L7: 单价 | M7: 金额 | N7: 数量 | O7: 单价 | P7: 金额 | Q7: 1年以内 | R7: 1-2年 | S7: 2-3年 | T7: 3年以上
A9: （一）周转材料
F10: =IF(E10=0,0,G10/E10) -> 0 | I10: =IF(H10=0,0,J10/H10) -> 0 | L10: =IF(K10=0,0,M10/K10) -> 0 | N10: =E10+H10-K10 -> 0 | O10: =IF(N10=0,0,P10/N10) -> 0 | P10: =G10+J10-M10 -> 0
A11: … | F11: =IF(E11=0,0,G11/E11) -> 0 | I11: =IF(H11=0,0,J11/H11) -> 0 | L11: =IF(K11=0,0,M11/K11) -> 0 | N11: =E11+H11-K11 -> 0 | O11: =IF(N11=0,0,P11/N11) -> 0 | P11: =G11+J11-M11 -> 0
A12: 小计 | E12: -- | F12: -- | G12: =SUM(G10:G11) -> 0 | H12: -- | I12: -- | J12: =SUM(J10:J11) -> 0 | K12: -- | L12: -- | M12: =SUM(M10:M11) -> 0 | N12: -- | O12: -- | P12: =SUM(P10:P11) -> 0 | Q12: =SUM(Q10:Q11) -> 0 | R12: =SUM(R10:R11) -> 0 | S12: =SUM(S10:S11) -> 0 | T12: =SUM(T10:T11) -> 0
A13: （二）低值易耗品
F14: =IF(E14=0,0,G14/E14) -> 0 | I14: =IF(H14=0,0,J14/H14) -> 0 | L14: =IF(K14=0,0,M14/K14) -> 0 | N14: =E14+H14-K14 -> 0 | O14: =IF(N14=0,0,P14/N14) -> 0 | P14: =G14+J14-M14 -> 0
A15: … | F15: =IF(E15=0,0,G15/E15) -> 0 | I15: =IF(H15=0,0,J15/H15) -> 0 | L15: =IF(K15=0,0,M15/K15) -> 0 | N15: =E15+H15-K15 -> 0 | O15: =IF(N15=0,0,P15/N15) -> 0 | P15: =G15+J15-M15 -> 0
A16: 小计 | E16: -- | F16: -- | G16: =SUM(G14:G15) -> 0 | H16: -- | I16: -- | J16: =SUM(J14:J15) -> 0 | K16: -- | L16: -- | M16: =SUM(M14:M15) -> 0 | N16: -- | O16: -- | P16: =SUM(P14:P15) -> 0 | Q16: =SUM(Q14:Q15) -> 0 | R16: =SUM(R14:R15) -> 0 | S16: =SUM(S14:S15) -> 0 | T16: =SUM(T14:T15) -> 0
A17: （三）包装物
A18: 1.生产过程中用于包装产品作为产品组成部分的包装物 | F18: =IF(E18=0,0,G18/E18) -> 0 | I18: =IF(H18=0,0,J18/H18) -> 0 | L18: =IF(K18=0,0,M18/K18) -> 0 | N18: =E18+H18-K18 -> 0 | O18: =IF(N18=0,0,P18/N18) -> 0 | P18: =G18+J18-M18 -> 0
A19: … | F19: =IF(E19=0,0,G19/E19) -> 0 | I19: =IF(H19=0,0,J19/H19) -> 0 | L19: =IF(K19=0,0,M19/K19) -> 0 | N19: =E19+H19-K19 -> 0 | O19: =IF(N19=0,0,P19/N19) -> 0 | P19: =G19+J19-M19 -> 0
A20: 2.随同商品出售而不单独计价的包装物 | F20: =IF(E20=0,0,G20/E20) -> 0 | I20: =IF(H20=0,0,J20/H20) -> 0 | L20: =IF(K20=0,0,M20/K20) -> 0 | N20: =E20+H20-K20 -> 0 | O20: =IF(N20=0,0,P20/N20) -> 0 | P20: =G20+J20-M20 -> 0
A21: … | F21: =IF(E21=0,0,G21/E21) -> 0 | I21: =IF(H21=0,0,J21/H21) -> 0 | L21: =IF(K21=0,0,M21/K21) -> 0 | N21: =E21+H21-K21 -> 0 | O21: =IF(N21=0,0,P21/N21) -> 0 | P21: =G21+J21-M21 -> 0
A22: 3.随同商品出售而单独计价的包装物 | F22: =IF(E22=0,0,G22/E22) -> 0 | I22: =IF(H22=0,0,J22/H22) -> 0 | L22: =IF(K22=0,0,M22/K22) -> 0 | N22: =E22+H22-K22 -> 0 | O22: =IF(N22=0,0,P22/N22) -> 0 | P22: =G22+J22-M22 -> 0
A23: … | F23: =IF(E23=0,0,G23/E23) -> 0 | I23: =IF(H23=0,0,J23/H23) -> 0 | L23: =IF(K23=0,0,M23/K23) -> 0 | N23: =E23+H23-K23 -> 0 | O23: =IF(N23=0,0,P23/N23) -> 0 | P23: =G23+J23-M23 -> 0
A24: 4.出租或出借给购买单位使用的包装物 | F24: =IF(E24=0,0,G24/E24) -> 0 | I24: =IF(H24=0,0,J24/H24) -> 0 | L24: =IF(K24=0,0,M24/K24) -> 0 | N24: =E24+H24-K24 -> 0 | O24: =IF(N24=0,0,P24/N24) -> 0 | P24: =G24+J24-M24 -> 0
A25: … | F25: =IF(E25=0,0,G25/E25) -> 0 | I25: =IF(H25=0,0,J25/H25) -> 0 | L25: =IF(K25=0,0,M25/K25) -> 0 | N25: =E25+H25-K25 -> 0 | O25: =IF(N25=0,0,P25/N25) -> 0 | P25: =G25+J25-M25 -> 0
A26: 小计 | E26: -- | F26: -- | G26: =G18+G20+G22+G24 -> 0 | H26: -- | I26: -- | J26: =J18+J20+J22+J24 -> 0 | K26: -- | L26: -- | M26: =M18+M20+M22+M24 -> 0 | N26: -- | O26: -- | P26: =P18+P20+P22+P24 -> 0 | Q26: =Q18+Q20+Q22+Q24 -> 0 | R26: =R18+R20+R22+R24 -> 0 | S26: =S18+S20+S22+S24 -> 0 | T26: =T18+T20+T22+T24 -> 0
A27: 合计 | E27: -- | F27: -- | G27: =SUM(G12,G16,G26) -> 0 | H27: -- | I27: -- | J27: =SUM(J12,J16,J26) -> 0 | K27: -- | L27: -- | M27: =SUM(M12,M16,M26) -> 0 | N27: -- | O27: -- | P27: =SUM(P12,P16,P26) -> 0 | Q27: =SUM(Q12,Q16,Q26) -> 0 | R27: =SUM(R12,R16,R26) -> 0 | S27: =SUM(S12,S16,S26) -> 0 | T27: =SUM(T12,T16,T26) -> 0
A28: 减：存货跌价准备
A29: 周转材料/低值易耗品/包装物净额 | E29: -- | F29: -- | G29: =G27-G28 -> 0 | H29: -- | I29: -- | J29: =J27-J28 -> 0 | K29: -- | L29: -- | M29: =M27-M28 -> 0 | N29: -- | O29: -- | P29: =P27-P28 -> 0 | Q29: =Q27-Q28 -> 0 | R29: =R27-R28 -> 0 | S29: =S27-S28 -> 0 | T29: =T27-T28 -> 0
A30: 审计说明： | P30: =IF((P27-Q27-R27-S27-T27)=0,"OK","库龄与期末金额不匹配") -> OK
A31: 1.摊销方法说明： | K31: 3.周转材料/低值易耗品/包装物——**库龄较长的原因：
A32: 2.周转材料/低值易耗品/包装物本期发生重大变动的原因： | K32: 4.计提跌价准备的主要项目及原因：
A34: 提示：摊销方法采用五五、分次摊销法摊销时，金额按摊余价值列示，并作出说明。

Sheet 四、自制半成品明细表F2-6
A1: 致同会计师事务所
A2: 存货明细表
A3: =[1]底稿目录!A2 -> 被审计单位： | G3: =[1]底稿目录!A4 -> 编制人： | K3: =[1]底稿目录!A5 -> 编制日期： | T3: 索引号： | U3: =[1]底稿目录!F11 -> F2-6
A4: =[1]底稿目录!A3 -> 截止日：202X年12月21日 | G4: =[1]底稿目录!A6 -> 复核人： | K4: =[1]底稿目录!A7 -> 复核日期： | T4: 页次：
A5: 四、自制半成品明细表
A6: 存货编码 | B6: 自制半成品名称 | C6: 规格 | D6: 单位 | E6: 期初库存 | H6: 本期购进 | K6: 本期发出 | N6: 期末结存 | Q6: 库龄 | U6: 品质状况（正常、残次、毁损、滞销等）
E7: 数量 | F7: 单价 | G7: 金额 | H7: 数量 | I7: 单价 | J7: 金额 | K7: 数量 | L7: 单价 | M7: 金额 | N7: 数量 | O7: 单价 | P7: 金额 | Q7: 1年以内 | R7: 1-2年 | S7: 2-3年 | T7: 3年以上
F9: =IF(E9=0,0,G9/E9) -> 0 | I9: =IF(H9=0,0,J9/H9) -> 0 | L9: =IF(K9=0,0,M9/K9) -> 0 | N9: =E9+H9-K9 -> 0 | O9: =IF(N9=0,0,P9/N9) -> 0 | P9: =G9+J9-M9 -> 0
F10: =IF(E10=0,0,G10/E10) -> 0 | I10: =IF(H10=0,0,J10/H10) -> 0 | L10: =IF(K10=0,0,M10/K10) -> 0 | N10: =E10+H10-K10 -> 0 | O10: =IF(N10=0,0,P10/N10) -> 0 | P10: =G10+J10-M10 -> 0
F11: =IF(E11=0,0,G11/E11) -> 0 | I11: =IF(H11=0,0,J11/H11) -> 0 | L11: =IF(K11=0,0,M11/K11) -> 0 | N11: =E11+H11-K11 -> 0 | O11: =IF(N11=0,0,P11/N11) -> 0 | P11: =G11+J11-M11 -> 0
F12: =IF(E12=0,0,G12/E12) -> 0 | I12: =IF(H12=0,0,J12/H12) -> 0 | L12: =IF(K12=0,0,M12/K12) -> 0 | N12: =E12+H12-K12 -> 0 | O12: =IF(N12=0,0,P12/N12) -> 0 | P12: =G12+J12-M12 -> 0
F13: =IF(E13=0,0,G13/E13) -> 0 | I13: =IF(H13=0,0,J13/H13) -> 0 | L13: =IF(K13=0,0,M13/K13) -> 0 | N13: =E13+H13-K13 -> 0 | O13: =IF(N13=0,0,P13/N13) -> 0 | P13: =G13+J13-M13 -> 0
F14: =IF(E14=0,0,G14/E14) -> 0 | I14: =IF(H14=0,0,J14/H14) -> 0 | L14: =IF(K14=0,0,M14/K14) -> 0 | N14: =E14+H14-K14 -> 0 | O14: =IF(N14=0,0,P14/N14) -> 0 | P14: =G14+J14-M14 -> 0
F15: =IF(E15=0,0,G15/E15) -> 0 | I15: =IF(H15=0,0,J15/H15) -> 0 | L15: =IF(K15=0,0,M15/K15) -> 0 | N15: =E15+H15-K15 -> 0 | O15: =IF(N15=0,0,P15/N15) -> 0 | P15: =G15+J15-M15 -> 0
F16: =IF(E16=0,0,G16/E16) -> 0 | I16: =IF(H16=0,0,J16/H16) -> 0 | L16: =IF(K16=0,0,M16/K16) -> 0 | N16: =E16+H16-K16 -> 0 | O16: =IF(N16=0,0,P16/N16) -> 0 | P16: =G16+J16-M16 -> 0
F17: =IF(E17=0,0,G17/E17) -> 0 | I17: =IF(H17=0,0,J17/H17) -> 0 | L17: =IF(K17=0,0,M17/K17) -> 0 | N17: =E17+H17-K17 -> 0 | O17: =IF(N17=0,0,P17/N17) -> 0 | P17: =G17+J17-M17 -> 0
F18: =IF(E18=0,0,G18/E18) -> 0 | I18: =IF(H18=0,0,J18/H18) -> 0 | L18: =IF(K18=0,0,M18/K18) -> 0 | N18: =E18+H18-K18 -> 0 | O18: =IF(N18=0,0,P18/N18) -> 0 | P18: =G18+J18-M18 -> 0
F19: =IF(E19=0,0,G19/E19) -> 0 | I19: =IF(H19=0,0,J19/H19) -> 0 | L19: =IF(K19=0,0,M19/K19) -> 0 | N19: =E19+H19-K19 -> 0 | O19: =IF(N19=0,0,P19/N19) -> 0 | P19: =G19+J19-M19 -> 0
F20: =IF(E20=0,0,G20/E20) -> 0 | I20: =IF(H20=0,0,J20/H20) -> 0 | L20: =IF(K20=0,0,M20/K20) -> 0 | N20: =E20+H20-K20 -> 0 | O20: =IF(N20=0,0,P20/N20) -> 0 | P20: =G20+J20-M20 -> 0
... F24: =IF(E24=0,0,G24/E24) -> 0 | I24: =IF(H24=0,0,J24/H24) -> 0 | L24: =IF(K24=0,0,M24/K24) -> 0 | N24: =E24+H24-K24 -> 0 | O24: =IF(N24=0,0,P24/N24) -> 0 | P24: =G24+J24-M24 -> 0
A25: 合计 | E25: -- | F25: -- | G25: =SUM(G9:G24) -> 0 | H25: -- | I25: -- | J25: =SUM(J9:J24) -> 0 | K25: -- | L25: -- | M25: =SUM(M9:M24) -> 0 | N25: -- | O25: -- | P25: =SUM(P9:P24) -> 0 | Q25: =SUM(Q9:Q24) -> 0 | R25: =SUM(R9:R24) -> 0 | S25: =SUM(S9:S24) -> 0 | T25: =SUM(T9:T24) -> 0
A26: 减：存货跌价准备
A27: 自制半成品净额 | E27: -- | F27: -- | G27: =G25-G26 -> 0 | H27: -- | I27: -- | J27: =J25-J26 -> 0 | K27: -- | L27: -- | M27: =M25-M26 -> 0 | N27: -- | O27: -- | P27: =P25-P26 -> 0 | Q27: =Q25-Q26 -> 0 | R27: =R25-R26 -> 0 | S27: =S25-S26 -> 0 | T27: =T25-T26 -> 0
A28: 审计说明： | P28: =IF((P25-Q25-R25-S25-T25)=0,"OK","库龄与期末金额不匹配") -> OK
A29: 1、自制半成品的计价方法： | K29: 3、自制半成品——**库龄较长的原因：
A30: 2、自制半成品本期发生重大变动的原因： | K30: 4、计提跌价准备的主要项目及原因：

Sheet 五、委托加工物资明细表F2-7
A1: 致同会计师事务所
A2: 存货明细表
A3: =[1]底稿目录!A2 -> 被审计单位： | E3: =[1]底稿目录!A4 -> 编制人： | J3: =[1]底稿目录!A5 -> 编制日期： | N3: 索引号： | O3: =[1]底稿目录!F12 -> F2-7
A4: =[1]底稿目录!A3 -> 截止日：202X年12月21日 | E4: =[1]底稿目录!A6 -> 复核人： | J4: =[1]底稿目录!A7 -> 复核日期： | N4: 页次：
A5: 五、委托加工物资明细表
A6: 加工单位名称 | C6: 加工合同号 | D6: 发出加工物资名称 | E6: 数量 | F6: 单价 | G6: 金额 | H6: 加工费用 | I6: 运杂费 | J6: 计入加工物资成本的税金 | K6: 加工物资成本 | L6: 库龄
L7: 1年以内 | M7: 1-2年 | N7: 2-3年 | O7: 3年以上
G8: =E8*F8 -> 0
G9: =E9*F9 -> 0
G10: =E10*F10 -> 0
G11: =E11*F11 -> 0
G12: =E12*F12 -> 0
G13: =E13*F13 -> 0
G14: =E14*F14 -> 0
G15: =E15*F15 -> 0
G16: =E16*F16 -> 0
A17: 合计 | G17: =SUM(G8:G16) -> 0 | H17: =SUM(H8:H16) -> 0 | I17: =SUM(I8:I16) -> 0 | J17: =SUM(J8:J16) -> 0 | K17: =SUM(K8:K16) -> 0 | L17: =SUM(L8:L16) -> 0 | M17: =SUM(M8:M16) -> 0 | N17: =SUM(N8:N16) -> 0 | O17: =SUM(O8:O16) -> 0
A18: 减：存货减值准备
A19: 存货净额 | G19: =G17-G18 -> 0 | L19: =L17-L18 -> 0 | M19: =M17-M18 -> 0 | N19: =N17-N18 -> 0 | O19: =O17-O18 -> 0
A20: 审计说明： | G20: =IF((G17-L17-M17-N17-O17)=0,"OK","库龄与期末金额不匹配") -> OK
A21: 1.委托加工物资的成本核算方法： | G21: 3.委托加工物资——**库龄较长的原因：
A22: 2.委托加工物资本期发生重大变动的原因： | G22: 4.计提跌价准备的主要项目及原因：

Sheet 六、库存商品明细表F2-8
A1: 致同会计师事务所
A2: 存货明细表
A3: =[1]底稿目录!A2 -> 被审计单位： | G3: =[1]底稿目录!A4 -> 编制人： | M3: =[1]底稿目录!A5 -> 编制日期： | W3: 索引号： | X3: =[1]底稿目录!F13 -> F2-8
A4: =[1]底稿目录!A3 -> 截止日：202X年12月21日 | G4: =[1]底稿目录!A6 -> 复核人： | M4: =[1]底稿目录!A7 -> 复核日期： | W4: 页次：
A5: 六、库存商品明细表
A6: 存货编码 | B6: 存货名称 | C6: 规格 | D6: 单位 | E6: 期初库存 | H6: 本期购进 | K6: 本期发出 | N6: 期末结存 | Q6: 库龄 | U6: 品质状况（正常、残次、毁损、滞销等） | V6: 是否有在手订单 | W6: 订单编号 | X6: 销售单价
E7: 数量 | F7: 单价 | G7: 金额 | H7: 数量 | I7: 单价 | J7: 金额 | K7: 数量 | L7: 单价 | M7: 金额 | N7: 数量 | O7: 单价 | P7: 金额 | Q7: 1年以内 | R7: 1-2年 | S7: 2-3年 | T7: 3年以上
F9: =IF(E9=0,0,G9/E9) -> 0 | I9: =IF(H9=0,0,J9/H9) -> 0 | L9: =IF(K9=0,0,M9/K9) -> 0 | N9: =E9+H9-K9 -> 0 | O9: =IF(N9=0,0,P9/N9) -> 0 | P9: =G9+J9-M9 -> 0
F10: =IF(E10=0,0,G10/E10) -> 0 | I10: =IF(H10=0,0,J10/H10) -> 0 | L10: =IF(K10=0,0,M10/K10) -> 0 | N10: =E10+H10-K10 -> 0 | O10: =IF(N10=0,0,P10/N10) -> 0 | P10: =G10+J10-M10 -> 0
F11: =IF(E11=0,0,G11/E11) -> 0 | I11: =IF(H11=0,0,J11/H11) -> 0 | L11: =IF(K11=0,0,M11/K11) -> 0 | N11: =E11+H11-K11 -> 0 | O11: =IF(N11=0,0,P11/N11) -> 0 | P11: =G11+J11-M11 -> 0
F12: =IF(E12=0,0,G12/E12) -> 0 | I12: =IF(H12=0,0,J12/H12) -> 0 | L12: =IF(K12=0,0,M12/K12) -> 0 | N12: =E12+H12-K12 -> 0 | O12: =IF(N12=0,0,P12/N12) -> 0 | P12: =G12+J12-M12 -> 0
F13: =IF(E13=0,0,G13/E13) -> 0 | I13: =IF(H13=0,0,J13/H13) -> 0 | L13: =IF(K13=0,0,M13/K13) -> 0 | N13: =E13+H13-K13 -> 0 | O13: =IF(N13=0,0,P13/N13) -> 0 | P13: =G13+J13-M13 -> 0
F14: =IF(E14=0,0,G14/E14) -> 0 | I14: =IF(H14=0,0,J14/H14) -> 0 | L14: =IF(K14=0,0,M14/K14) -> 0 | N14: =E14+H14-K14 -> 0 | O14: =IF(N14=0,0,P14/N14) -> 0 | P14: =G14+J14-M14 -> 0
F15: =IF(E15=0,0,G15/E15) -> 0 | I15: =IF(H15=0,0,J15/H15) -> 0 | L15: =IF(K15=0,0,M15/K15) -> 0 | N15: =E15+H15-K15 -> 0 | O15: =IF(N15=0,0,P15/N15) -> 0 | P15: =G15+J15-M15 -> 0
F16: =IF(E16=0,0,G16/E16) -> 0 | I16: =IF(H16=0,0,J16/H16) -> 0 | L16: =IF(K16=0,0,M16/K16) -> 0 | N16: =E16+H16-K16 -> 0 | O16: =IF(N16=0,0,P16/N16) -> 0 | P16: =G16+J16-M16 -> 0
F17: =IF(E17=0,0,G17/E17) -> 0 | I17: =IF(H17=0,0,J17/H17) -> 0 | L17: =IF(K17=0,0,M17/K17) -> 0 | N17: =E17+H17-K17 -> 0 | O17: =IF(N17=0,0,P17/N17) -> 0 | P17: =G17+J17-M17 -> 0
F18: =IF(E18=0,0,G18/E18) -> 0 | I18: =IF(H18=0,0,J18/H18) -> 0 | L18: =IF(K18=0,0,M18/K18) -> 0 | N18: =E18+H18-K18 -> 0 | O18: =IF(N18=0,0,P18/N18) -> 0 | P18: =G18+J18-M18 -> 0
F19: =IF(E19=0,0,G19/E19) -> 0 | I19: =IF(H19=0,0,J19/H19) -> 0 | L19: =IF(K19=0,0,M19/K19) -> 0 | N19: =E19+H19-K19 -> 0 | O19: =IF(N19=0,0,P19/N19) -> 0 | P19: =G19+J19-M19 -> 0
F20: =IF(E20=0,0,G20/E20) -> 0 | I20: =IF(H20=0,0,J20/H20) -> 0 | L20: =IF(K20=0,0,M20/K20) -> 0 | N20: =E20+H20-K20 -> 0 | O20: =IF(N20=0,0,P20/N20) -> 0 | P20: =G20+J20-M20 -> 0
... F23: =IF(E23=0,0,G23/E23) -> 0 | I23: =IF(H23=0,0,J23/H23) -> 0 | L23: =IF(K23=0,0,M23/K23) -> 0 | N23: =E23+H23-K23 -> 0 | O23: =IF(N23=0,0,P23/N23) -> 0 | P23: =G23+J23-M23 -> 0
A24: …… | F24: =IF(E24=0,0,G24/E24) -> 0 | I24: =IF(H24=0,0,J24/H24) -> 0 | L24: =IF(K24=0,0,M24/K24) -> 0 | N24: =E24+H24-K24 -> 0 | O24: =IF(N24=0,0,P24/N24) -> 0 | P24: =G24+J24-M24 -> 0
A25: 合计 | E25: -- | F25: -- | G25: =SUM(G9:G24) -> 0 | H25: -- | I25: -- | J25: =SUM(J9:J24) -> 0 | K25: =SUM(K9:K24) -> 0 | L25: -- | M25: =SUM(M9:M24) -> 0 | N25: -- | O25: -- | P25: =SUM(P9:P24) -> 0 | Q25: =SUM(Q9:Q24) -> 0 | R25: =SUM(R9:R24) -> 0 | S25: =SUM(S9:S24) -> 0 | T25: =SUM(T9:T24) -> 0
A26: 减：存货跌价准备
A27: 库存商品净额 | E27: -- | F27: -- | G27: =G25-G26 -> 0 | H27: -- | I27: -- | J27: =J25-J26 -> 0 | K27: -- | L27: -- | M27: =M25-M26 -> 0 | N27: -- | O27: -- | P27: =P25-P26 -> 0 | Q27: =Q25-Q26 -> 0 | R27: =R25-R26 -> 0 | S27: =S25-S26 -> 0 | T27: =T25-T26 -> 0
A28: 销售出库数量（销售台账） | P28: =IF((P25-Q25-R25-S25-T25)=0,"OK","库龄与期末金额不匹配") -> OK
A29: 差异 | K29: =K25-K28 -> 0
A30: 审计说明：
A31: 1.库存商品的计价方法： | K31: 3.库存商品——**库龄较长的原因：
A32: 2.库存商品本期发生重大变动的原因： | K32: 4.计提跌价准备的主要项目及原因：

Sheet 七、发出商品F2-9
A1: 致同会计师事务所
A2: 存货明细表
A3: =[1]底稿目录!A2 -> 被审计单位： | F3: =[1]底稿目录!A4 -> 编制人： | J3: =[1]底稿目录!A5 -> 编制日期： | V3: 索引号： | W3: =[1]底稿目录!F14 -> F2-9
A4: =[1]底稿目录!A3 -> 截止日：202X年12月21日 | F4: =[1]底稿目录!A6 -> 复核人： | J4: =[1]底稿目录!A7 -> 复核日期： | V4: 页次：
A5: 七、发出商品明细表
A6: 购货单位 | B6: 发出商品名称及规格 | C6: 单位 | D6: 期初库存 | G6: 本期转入 | J6: 本期转出 | M6: 期末结存 | P6: 期后结转 | S6: 库龄 | W6: 品质状况（正常、残次、毁损、滞销等）
D7: 数量 | E7: 单价 | F7: 金额 | G7: 数量 | H7: 单价 | I7: 金额 | J7: 数量 | K7: 单价 | L7: 金额 | M7: 数量 | N7: 单价 | O7: 金额 | P7: 数量 | Q7: 单价 | R7: 金额 | S7: 1年以内 | T7: 1-2年 | U7: 2-3年 | V7: 3年以上
E9: =IF(D9=0,0,F9/D9) -> 0 | H9: =IF(G9=0,0,I9/G9) -> 0 | K9: =IF(J9=0,0,L9/J9) -> 0 | M9: =D9+G9-J9 -> 0 | N9: =IF(M9=0,0,O9/M9) -> 0 | O9: =F9+I9-L9 -> 0 | Q9: =IF(P9=0,0,R9/P9) -> 0
E10: =IF(D10=0,0,F10/D10) -> 0 | H10: =IF(G10=0,0,I10/G10) -> 0 | K10: =IF(J10=0,0,L10/J10) -> 0 | M10: =D10+G10-J10 -> 0 | N10: =IF(M10=0,0,O10/M10) -> 0 | O10: =F10+I10-L10 -> 0 | Q10: =IF(P10=0,0,R10/P10) -> 0
E11: =IF(D11=0,0,F11/D11) -> 0 | H11: =IF(G11=0,0,I11/G11) -> 0 | K11: =IF(J11=0,0,L11/J11) -> 0 | M11: =D11+G11-J11 -> 0 | N11: =IF(M11=0,0,O11/M11) -> 0 | O11: =F11+I11-L11 -> 0 | Q11: =IF(P11=0,0,R11/P11) -> 0
E12: =IF(D12=0,0,F12/D12) -> 0 | H12: =IF(G12=0,0,I12/G12) -> 0 | K12: =IF(J12=0,0,L12/J12) -> 0 | M12: =D12+G12-J12 -> 0 | N12: =IF(M12=0,0,O12/M12) -> 0 | O12: =F12+I12-L12 -> 0 | Q12: =IF(P12=0,0,R12/P12) -> 0
E13: =IF(D13=0,0,F13/D13) -> 0 | H13: =IF(G13=0,0,I13/G13) -> 0 | K13: =IF(J13=0,0,L13/J13) -> 0 | M13: =D13+G13-J13 -> 0 | N13: =IF(M13=0,0,O13/M13) -> 0 | O13: =F13+I13-L13 -> 0 | Q13: =IF(P13=0,0,R13/P13) -> 0
E14: =IF(D14=0,0,F14/D14) -> 0 | H14: =IF(G14=0,0,I14/G14) -> 0 | K14: =IF(J14=0,0,L14/J14) -> 0 | M14: =D14+G14-J14 -> 0 | N14: =IF(M14=0,0,O14/M14) -> 0 | O14: =F14+I14-L14 -> 0 | Q14: =IF(P14=0,0,R14/P14) -> 0
E15: =IF(D15=0,0,F15/D15) -> 0 | H15: =IF(G15=0,0,I15/G15) -> 0 | K15: =IF(J15=0,0,L15/J15) -> 0 | M15: =D15+G15-J15 -> 0 | N15: =IF(M15=0,0,O15/M15) -> 0 | O15: =F15+I15-L15 -> 0 | Q15: =IF(P15=0,0,R15/P15) -> 0
E16: =IF(D16=0,0,F16/D16) -> 0 | H16: =IF(G16=0,0,I16/G16) -> 0 | K16: =IF(J16=0,0,L16/J16) -> 0 | M16: =D16+G16-J16 -> 0 | N16: =IF(M16=0,0,O16/M16) -> 0 | O16: =F16+I16-L16 -> 0 | Q16: =IF(P16=0,0,R16/P16) -> 0
E17: =IF(D17=0,0,F17/D17) -> 0 | H17: =IF(G17=0,0,I17/G17) -> 0 | K17: =IF(J17=0,0,L17/J17) -> 0 | M17: =D17+G17-J17 -> 0 | N17: =IF(M17=0,0,O17/M17) -> 0 | O17: =F17+I17-L17 -> 0 | Q17: =IF(P17=0,0,R17/P17) -> 0
E18: =IF(D18=0,0,F18/D18) -> 0 | H18: =IF(G18=0,0,I18/G18) -> 0 | K18: =IF(J18=0,0,L18/J18) -> 0 | M18: =D18+G18-J18 -> 0 | N18: =IF(M18=0,0,O18/M18) -> 0 | O18: =F18+I18-L18 -> 0 | Q18: =IF(P18=0,0,R18/P18) -> 0
E19: =IF(D19=0,0,F19/D19) -> 0 | H19: =IF(G19=0,0,I19/G19) -> 0 | K19: =IF(J19=0,0,L19/J19) -> 0 | M19: =D19+G19-J19 -> 0 | N19: =IF(M19=0,0,O19/M19) -> 0 | O19: =F19+I19-L19 -> 0 | Q19: =IF(P19=0,0,R19/P19) -> 0
E20: =IF(D20=0,0,F20/D20) -> 0 | H20: =IF(G20=0,0,I20/G20) -> 0 | K20: =IF(J20=0,0,L20/J20) -> 0 | M20: =D20+G20-J20 -> 0 | N20: =IF(M20=0,0,O20/M20) -> 0 | O20: =F20+I20-L20 -> 0 | Q20: =IF(P20=0,0,R20/P20) -> 0
... E23: =IF(D23=0,0,F23/D23) -> 0 | H23: =IF(G23=0,0,I23/G23) -> 0 | K23: =IF(J23=0,0,L23/J23) -> 0 | M23: =D23+G23-J23 -> 0 | N23: =IF(M23=0,0,O23/M23) -> 0 | O23: =F23+I23-L23 -> 0 | Q23: =IF(P23=0,0,R23/P23) -> 0
A24: …… | E24: =IF(D24=0,0,F24/D24) -> 0 | H24: =IF(G24=0,0,I24/G24) -> 0 | K24: =IF(J24=0,0,L24/J24) -> 0 | M24: =D24+G24-J24 -> 0 | N24: =IF(M24=0,0,O24/M24) -> 0 | O24: =F24+I24-L24 -> 0 | Q24: =IF(P24=0,0,R24/P24) -> 0
A25: 合计 | D25: -- | E25: -- | F25: =SUM(F9:F24) -> 0 | G25: -- | H25: -- | I25: =SUM(I9:I24) -> 0 | J25: =SUM(J9:J24) -> 0 | K25: -- | L25: =SUM(L9:L24) -> 0 | M25: -- | N25: -- | O25: =SUM(O9:O24) -> 0 | P25: -- | Q25: -- | R25: =SUM(R9:R24) -> 0 | S25: =SUM(S9:S24) -> 0 | T25: =SUM(T9:T24) -> 0 | U25: =SUM(U9:U24) -> 0 | V25: =SUM(V9:V24) -> 0
A26: 减：存货跌价准备
A27: 发出商品净额 | D27: -- | E27: -- | F27: =F25-F26 -> 0 | G27: -- | H27: -- | I27: =I25-I26 -> 0 | J27: -- | K27: -- | L27: =L25-L26 -> 0 | M27: -- | N27: -- | O27: =O25-O26 -> 0 | P27: -- | Q27: -- | R27: =R25-R26 -> 0 | S27: =S25-S26 -> 0 | T27: =T25-T26 -> 0 | U27: =U25-U26 -> 0 | V27: =V25-V26 -> 0
A28: 销售出库数量（销售台账） | O28: =IF((O25-S25-T25-U25-V25)=0,"OK","库龄与期末金额不匹配") -> OK
A29: 差异 | J29: =J25-J28 -> 0
A31: 审计说明：
A32: 1.发出商品资产负债表日后销售情况： | I32: 3.发出商品——**库龄较长的原因：
A33: 2.发出商品本期发生重大变动的原因： | I33: 4.计提跌价准备的主要项目及原因：
A35: 审计提示：
A36: 关注产品退换货情况

Sheet 八、开发产品F2-10
A1: 致同会计师事务所
A2: 存货明细表
A3: =[1]底稿目录!A2 -> 被审计单位： | H3: =[1]底稿目录!A4 -> 编制人： | Q3: =[1]底稿目录!A5 -> 编制日期： | Z3: 索引号： | AA3: =[1]底稿目录!F15 -> F2-10
A4: =[1]底稿目录!A3 -> 截止日：202X年12月21日 | H4: =[1]底稿目录!A6 -> 复核人： | Q4: =[1]底稿目录!A7 -> 复核日期： | Z4: 页次：
A5: 八、开发产品明细表
A6: （一）原值
A7: 序号 | B7: 项目名称 | C7: 总建筑面积/万平米 | D7: 开工时间 | E7: 竣工时间 | F7: 期初结存（未审） | I7: 期初调整 | K7: 期初审定 | M7: 本期转入 | P7: 本期转出 | S7: 期末结存（未审） | V7: 期末调整 | X7: 期末审定 | Z7: 库龄 | AA7: 品质状况（正常、停建、毁损、报废等）
F8: 面积 （平方米） | G8: 单位成本 | H8: 金额 | I8: 账项调整 | J8: 重分类调整 | K8: 单位成本 | L8: 金额 | M8: 面积 （平方米） | N8: 单位成本 | O8: 金额 | P8: 面积 （平方米） | Q8: 单位成本 | R8: 金额 | S8: 面积 （平方米） | T8: 单位成本 | U8: 金额 | V8: 账项调整 | W8: 重分类调整 | X8: 单位成本 | Y8: 金额
A9: 1 | G9: =IF(F9=0,0,H9/F9) -> 0 | K9: =IF(F9=0,0,L9/F9) -> 0 | L9: =H9+I9+J9 -> 0 | N9: =IF(M9=0,0,O9/M9) -> 0 | Q9: =IF(P9=0,0,R9/P9) -> 0 | S9: =F9+M9-P9 -> 0 | T9: =IF(S9=0,0,U9/S9) -> 0 | U9: =H9+O9-R9 -> 0 | X9: =IF(S9=0,0,Y9/S9) -> 0 | Y9: =U9+V9+W9 -> 0
A10: 2 | G10: =IF(F10=0,0,H10/F10) -> 0 | K10: =IF(F10=0,0,L10/F10) -> 0 | L10: =H10+I10+J10 -> 0 | N10: =IF(M10=0,0,O10/M10) -> 0 | Q10: =IF(P10=0,0,R10/P10) -> 0 | S10: =F10+M10-P10 -> 0 | T10: =IF(S10=0,0,U10/S10) -> 0 | U10: =H10+O10-R10 -> 0 | X10: =IF(S10=0,0,Y10/S10) -> 0 | Y10: =U10+V10+W10 -> 0
A11: 3 | G11: =IF(F11=0,0,H11/F11) -> 0 | K11: =IF(F11=0,0,L11/F11) -> 0 | L11: =H11+I11+J11 -> 0 | N11: =IF(M11=0,0,O11/M11) -> 0 | Q11: =IF(P11=0,0,R11/P11) -> 0 | S11: =F11+M11-P11 -> 0 | T11: =IF(S11=0,0,U11/S11) -> 0 | U11: =H11+O11-R11 -> 0 | X11: =IF(S11=0,0,Y11/S11) -> 0 | Y11: =U11+V11+W11 -> 0
A12: 4 | G12: =IF(F12=0,0,H12/F12) -> 0 | K12: =IF(F12=0,0,L12/F12) -> 0 | L12: =H12+I12+J12 -> 0 | N12: =IF(M12=0,0,O12/M12) -> 0 | Q12: =IF(P12=0,0,R12/P12) -> 0 | S12: =F12+M12-P12 -> 0 | T12: =IF(S12=0,0,U12/S12) -> 0 | U12: =H12+O12-R12 -> 0 | X12: =IF(S12=0,0,Y12/S12) -> 0 | Y12: =U12+V12+W12 -> 0
A13: 5 | G13: =IF(F13=0,0,H13/F13) -> 0 | K13: =IF(F13=0,0,L13/F13) -> 0 | L13: =H13+I13+J13 -> 0 | N13: =IF(M13=0,0,O13/M13) -> 0 | Q13: =IF(P13=0,0,R13/P13) -> 0 | S13: =F13+M13-P13 -> 0 | T13: =IF(S13=0,0,U13/S13) -> 0 | U13: =H13+O13-R13 -> 0 | X13: =IF(S13=0,0,Y13/S13) -> 0 | Y13: =U13+V13+W13 -> 0
A14: 6 | G14: =IF(F14=0,0,H14/F14) -> 0 | K14: =IF(F14=0,0,L14/F14) -> 0 | L14: =H14+I14+J14 -> 0 | N14: =IF(M14=0,0,O14/M14) -> 0 | Q14: =IF(P14=0,0,R14/P14) -> 0 | S14: =F14+M14-P14 -> 0 | T14: =IF(S14=0,0,U14/S14) -> 0 | U14: =H14+O14-R14 -> 0 | X14: =IF(S14=0,0,Y14/S14) -> 0 | Y14: =U14+V14+W14 -> 0
A15: 7 | G15: =IF(F15=0,0,H15/F15) -> 0 | K15: =IF(F15=0,0,L15/F15) -> 0 | L15: =H15+I15+J15 -> 0 | N15: =IF(M15=0,0,O15/M15) -> 0 | Q15: =IF(P15=0,0,R15/P15) -> 0 | S15: =F15+M15-P15 -> 0 | T15: =IF(S15=0,0,U15/S15) -> 0 | U15: =H15+O15-R15 -> 0 | X15: =IF(S15=0,0,Y15/S15) -> 0 | Y15: =U15+V15+W15 -> 0
A16: 8 | G16: =IF(F16=0,0,H16/F16) -> 0 | K16: =IF(F16=0,0,L16/F16) -> 0 | L16: =H16+I16+J16 -> 0 | N16: =IF(M16=0,0,O16/M16) -> 0 | Q16: =IF(P16=0,0,R16/P16) -> 0 | S16: =F16+M16-P16 -> 0 | T16: =IF(S16=0,0,U16/S16) -> 0 | U16: =H16+O16-R16 -> 0 | X16: =IF(S16=0,0,Y16/S16) -> 0 | Y16: =U16+V16+W16 -> 0
A17: 9 | G17: =IF(F17=0,0,H17/F17) -> 0 | K17: =IF(F17=0,0,L17/F17) -> 0 | L17: =H17+I17+J17 -> 0 | N17: =IF(M17=0,0,O17/M17) -> 0 | Q17: =IF(P17=0,0,R17/P17) -> 0 | S17: =F17+M17-P17 -> 0 | T17: =IF(S17=0,0,U17/S17) -> 0 | U17: =H17+O17-R17 -> 0 | X17: =IF(S17=0,0,Y17/S17) -> 0 | Y17: =U17+V17+W17 -> 0
A18: 10 | G18: =IF(F18=0,0,H18/F18) -> 0 | K18: =IF(F18=0,0,L18/F18) -> 0 | L18: =H18+I18+J18 -> 0 | N18: =IF(M18=0,0,O18/M18) -> 0 | Q18: =IF(P18=0,0,R18/P18) -> 0 | S18: =F18+M18-P18 -> 0 | T18: =IF(S18=0,0,U18/S18) -> 0 | U18: =H18+O18-R18 -> 0 | X18: =IF(S18=0,0,Y18/S18) -> 0 | Y18: =U18+V18+W18 -> 0
A19: 合计 | F19: =SUM(F9:F18) -> 0 | G19: =IF(F19=0,0,H19/F19) -> 0 | H19: =SUM(H9:H18) -> 0 | I19: =SUM(I9:I18) -> 0 | J19: =SUM(J9:J18) -> 0 | K19: =IF(F19=0,0,L19/F19) -> 0 | L19: =SUM(L9:L18) -> 0 | M19: =SUM(M9:M18) -> 0 | N19: =IF(M19=0,0,O19/M19) -> 0 | O19: =SUM(O9:O18) -> 0 | P19: =SUM(P9:P18) -> 0 | Q19: =IF(P19=0,0,R19/P19) -> 0 | R19: =SUM(R9:R18) -> 0 | S19: =SUM(S9:S18) -> 0 | T19: =IF(S19=0,0,U19/S19) -> 0 | U19: =SUM(U9:U18) -> 0 | V19: =SUM(V9:V18) -> 0 | W19: =SUM(W9:W18) -> 0 | X19: =IF(S19=0,0,Y19/S19) -> 0 | Y19: =SUM(Y9:Y18) -> 0
A20: （二）跌价准备
A21: 序号 | B21: 项目名称 | C21: 总建筑面积/万平米 | D21: 开工时间 | E21: 竣工时间 | F21: 未审数 | J21: 期初调整 | L21: 账项调整 | N21: 重分类调整 | P21: 审定数 | T21: 备注 | U21: 索引号
F22: 期初余额 | G22: 本期增加 | H22: 本期减少 | I22: 期末余额 | J22: 账项调整 | K22: 重分类调整 | L22: 本期增加 | M22: 本期减少 | N22: 本期增加 | O22: 本期减少 | P22: 期初余额 | Q22: 本期增加 | R22: 本期减少 | S22: 期末余额
A23: =A9 -> 1 | B23: =B9 -> 0 | C23: =C9 -> 0 | D23: =D9 -> 0 | E23: =E9 -> 0 | I23: =F23+G23-H23 -> 0 | P23: =F23+J23+K23 -> 0 | Q23: =G23+L23+N23 -> 0 | R23: =H23+M23+O23 -> 0 | S23: =P23+Q23-R23 -> 0
A24: =A10 -> 2 | B24: =B10 -> 0 | C24: =C10 -> 0 | D24: =D10 -> 0 | E24: =E10 -> 0 | I24: =F24+G24-H24 -> 0 | P24: =F24+J24+K24 -> 0 | Q24: =G24+L24+N24 -> 0 | R24: =H24+M24+O24 -> 0 | S24: =P24+Q24-R24 -> 0
A25: =A11 -> 3 | B25: =B11 -> 0 | C25: =C11 -> 0 | D25: =D11 -> 0 | E25: =E11 -> 0 | I25: =F25+G25-H25 -> 0 | P25: =F25+J25+K25 -> 0 | Q25: =G25+L25+N25 -> 0 | R25: =H25+M25+O25 -> 0 | S25: =P25+Q25-R25 -> 0
A26: =A12 -> 4 | B26: =B12 -> 0 | C26: =C12 -> 0 | D26: =D12 -> 0 | E26: =E12 -> 0 | I26: =F26+G26-H26 -> 0 | P26: =F26+J26+K26 -> 0 | Q26: =G26+L26+N26 -> 0 | R26: =H26+M26+O26 -> 0 | S26: =P26+Q26-R26 -> 0
A27: =A13 -> 5 | B27: =B13 -> 0 | C27: =C13 -> 0 | D27: =D13 -> 0 | E27: =E13 -> 0 | I27: =F27+G27-H27 -> 0 | P27: =F27+J27+K27 -> 0 | Q27: =G27+L27+N27 -> 0 | R27: =H27+M27+O27 -> 0 | S27: =P27+Q27-R27 -> 0
A28: =A14 -> 6 | B28: =B14 -> 0 | C28: =C14 -> 0 | D28: =D14 -> 0 | E28: =E14 -> 0 | I28: =F28+G28-H28 -> 0 | P28: =F28+J28+K28 -> 0 | Q28: =G28+L28+N28 -> 0 | R28: =H28+M28+O28 -> 0 | S28: =P28+Q28-R28 -> 0
A29: =A15 -> 7 | B29: =B15 -> 0 | C29: =C15 -> 0 | D29: =D15 -> 0 | E29: =E15 -> 0 | I29: =F29+G29-H29 -> 0 | P29: =F29+J29+K29 -> 0 | Q29: =G29+L29+N29 -> 0 | R29: =H29+M29+O29 -> 0 | S29: =P29+Q29-R29 -> 0
A30: =A16 -> 8 | B30: =B16 -> 0 | C30: =C16 -> 0 | D30: =D16 -> 0 | E30: =E16 -> 0 | I30: =F30+G30-H30 -> 0 | P30: =F30+J30+K30 -> 0 | Q30: =G30+L30+N30 -> 0 | R30: =H30+M30+O30 -> 0 | S30: =P30+Q30-R30 -> 0
A31: =A17 -> 9 | B31: =B17 -> 0 | C31: =C17 -> 0 | D31: =D17 -> 0 | E31: =E17 -> 0 | I31: =F31+G31-H31 -> 0 | P31: =F31+J31+K31 -> 0 | Q31: =G31+L31+N31 -> 0 | R31: =H31+M31+O31 -> 0 | S31: =P31+Q31-R31 -> 0
A32: =A18 -> 10 | B32: =B18 -> 0 | C32: =C18 -> 0 | D32: =D18 -> 0 | E32: =E18 -> 0 | I32: =F32+G32-H32 -> 0 | P32: =F32+J32+K32 -> 0 | Q32: =G32+L32+N32 -> 0 | R32: =H32+M32+O32 -> 0 | S32: =P32+Q32-R32 -> 0
A33: =A19 -> 合计 | F33: =SUM(F23:F32) -> 0 | G33: =SUM(G23:G32) -> 0 | H33: =SUM(H23:H32) -> 0 | I33: =SUM(I23:I32) -> 0 | J33: =SUM(J23:J32) -> 0 | K33: =SUM(K23:K32) -> 0 | L33: =SUM(L23:L32) -> 0 | M33: =SUM(M23:M32) -> 0 | ... S33: =SUM(S23:S32) -> 0
A34: （三）净值
A35: 序号 | B35: 项目名称 | C35: 总建筑面积/万平米 | D35: 开工时间 | E35: 竣工时间 | F35: 期初未审数 | I35: 期末未审数 | L35: 期初审定数 | O35: 期末审定数
F36: 面积 （平方米） | G36: 单位成本 | H36: 期初数 | I36: 面积 （平方米） | J36: 单位成本 | K36: 期末数 | L36: 面积 （平方米） | M36: 单位成本 | N36: 期初数 | O36: 面积 （平方米） | P36: 单位成本 | Q36: 期末数
A37: =A9 -> 1 | B37: =B9 -> 0 | C37: =C9 -> 0 | D37: =D9 -> 0 | E37: =E9 -> 0 | F37: =F9 -> 0 | G37: =IF(F37=0,0,H37/F37) -> 0 | H37: =H9-F23 -> 0 | I37: =S9 -> 0 | J37: =IF(I37=0,0,K37/I37) -> 0 | K37: =U9-I23 -> 0 | L37: =F37 -> 0 | M37: =IF(L37=0,0,N37/L37) -> 0 | N37: =L9-P23 -> 0 | O37: =I37 -> 0 | P37: =IF(O37=0,0,Q37/O37) -> 0 | Q37: =Y9-S23 -> 0
A38: =A10 -> 2 | B38: =B10 -> 0 | C38: =C10 -> 0 | D38: =D10 -> 0 | E38: =E10 -> 0 | F38: =F10 -> 0 | G38: =IF(F38=0,0,H38/F38) -> 0 | H38: =H10-F24 -> 0 | I38: =S10 -> 0 | J38: =IF(I38=0,0,K38/I38) -> 0 | K38: =U10-I24 -> 0 | L38: =F38 -> 0 | M38: =IF(L38=0,0,N38/L38) -> 0 | N38: =L10-P24 -> 0 | O38: =I38 -> 0 | P38: =IF(O38=0,0,Q38/O38) -> 0 | Q38: =Y10-S24 -> 0
A39: =A11 -> 3 | B39: =B11 -> 0 | C39: =C11 -> 0 | D39: =D11 -> 0 | E39: =E11 -> 0 | F39: =F11 -> 0 | G39: =IF(F39=0,0,H39/F39) -> 0 | H39: =H11-F25 -> 0 | I39: =S11 -> 0 | J39: =IF(I39=0,0,K39/I39) -> 0 | K39: =U11-I25 -> 0 | L39: =F39 -> 0 | M39: =IF(L39=0,0,N39/L39) -> 0 | N39: =L11-P25 -> 0 | O39: =I39 -> 0 | P39: =IF(O39=0,0,Q39/O39) -> 0 | Q39: =Y11-S25 -> 0
A40: =A12 -> 4 | B40: =B12 -> 0 | C40: =C12 -> 0 | D40: =D12 -> 0 | E40: =E12 -> 0 | F40: =F12 -> 0 | G40: =IF(F40=0,0,H40/F40) -> 0 | H40: =H12-F26 -> 0 | I40: =S12 -> 0 | J40: =IF(I40=0,0,K40/I40) -> 0 | K40: =U12-I26 -> 0 | L40: =F40 -> 0 | M40: =IF(L40=0,0,N40/L40) -> 0 | N40: =L12-P26 -> 0 | O40: =I40 -> 0 | P40: =IF(O40=0,0,Q40/O40) -> 0 | Q40: =Y12-S26 -> 0
A41: =A13 -> 5 | B41: =B13 -> 0 | C41: =C13 -> 0 | D41: =D13 -> 0 | E41: =E13 -> 0 | F41: =F13 -> 0 | G41: =IF(F41=0,0,H41/F41) -> 0 | H41: =H13-F27 -> 0 | I41: =S13 -> 0 | J41: =IF(I41=0,0,K41/I41) -> 0 | K41: =U13-I27 -> 0 | L41: =F41 -> 0 | M41: =IF(L41=0,0,N41/L41) -> 0 | N41: =L13-P27 -> 0 | O41: =I41 -> 0 | P41: =IF(O41=0,0,Q41/O41) -> 0 | Q41: =Y13-S27 -> 0
A42: =A14 -> 6 | B42: =B14 -> 0 | C42: =C14 -> 0 | D42: =D14 -> 0 | E42: =E14 -> 0 | F42: =F14 -> 0 | G42: =IF(F42=0,0,H42/F42) -> 0 | H42: =H14-F28 -> 0 | I42: =S14 -> 0 | J42: =IF(I42=0,0,K42/I42) -> 0 | K42: =U14-I28 -> 0 | L42: =F42 -> 0 | M42: =IF(L42=0,0,N42/L42) -> 0 | N42: =L14-P28 -> 0 | O42: =I42 -> 0 | P42: =IF(O42=0,0,Q42/O42) -> 0 | Q42: =Y14-S28 -> 0
A43: =A15 -> 7 | B43: =B15 -> 0 | C43: =C15 -> 0 | D43: =D15 -> 0 | E43: =E15 -> 0 | F43: =F15 -> 0 | G43: =IF(F43=0,0,H43/F43) -> 0 | H43: =H15-F29 -> 0 | I43: =S15 -> 0 | J43: =IF(I43=0,0,K43/I43) -> 0 | K43: =U15-I29 -> 0 | L43: =F43 -> 0 | M43: =IF(L43=0,0,N43/L43) -> 0 | N43: =L15-P29 -> 0 | O43: =I43 -> 0 | P43: =IF(O43=0,0,Q43/O43) -> 0 | Q43: =Y15-S29 -> 0
A44: =A16 -> 8 | B44: =B16 -> 0 | C44: =C16 -> 0 | D44: =D16 -> 0 | E44: =E16 -> 0 | F44: =F16 -> 0 | G44: =IF(F44=0,0,H44/F44) -> 0 | H44: =H16-F30 -> 0 | I44: =S16 -> 0 | J44: =IF(I44=0,0,K44/I44) -> 0 | K44: =U16-I30 -> 0 | L44: =F44 -> 0 | M44: =IF(L44=0,0,N44/L44) -> 0 | N44: =L16-P30 -> 0 | O44: =I44 -> 0 | P44: =IF(O44=0,0,Q44/O44) -> 0 | Q44: =Y16-S30 -> 0
A45: =A17 -> 9 | B45: =B17 -> 0 | C45: =C17 -> 0 | D45: =D17 -> 0 | E45: =E17 -> 0 | F45: =F17 -> 0 | G45: =IF(F45=0,0,H45/F45) -> 0 | H45: =H17-F31 -> 0 | I45: =S17 -> 0 | J45: =IF(I45=0,0,K45/I45) -> 0 | K45: =U17-I31 -> 0 | L45: =F45 -> 0 | M45: =IF(L45=0,0,N45/L45) -> 0 | N45: =L17-P31 -> 0 | O45: =I45 -> 0 | P45: =IF(O45=0,0,Q45/O45) -> 0 | Q45: =Y17-S31 -> 0
A46: =A18 -> 10 | B46: =B18 -> 0 | C46: =C18 -> 0 | D46: =D18 -> 0 | E46: =E18 -> 0 | F46: =F18 -> 0 | G46: =IF(F46=0,0,H46/F46) -> 0 | H46: =H18-F32 -> 0 | I46: =S18 -> 0 | J46: =IF(I46=0,0,K46/I46) -> 0 | K46: =U18-I32 -> 0 | L46: =F46 -> 0 | M46: =IF(L46=0,0,N46/L46) -> 0 | N46: =L18-P32 -> 0 | O46: =I46 -> 0 | P46: =IF(O46=0,0,Q46/O46) -> 0 | Q46: =Y18-S32 -> 0
A47: =A19 -> 合计 | F47: =SUM(F37:F46) -> 0 | G47: =IF(F47=0,0,H47/F47) -> 0 | H47: =SUM(H37:H46) -> 0 | I47: =SUM(I37:I46) -> 0 | J47: =IF(I47=0,0,K47/I47) -> 0 | K47: =SUM(K37:K46) -> 0 | L47: =SUM(L37:L46) -> 0 | M47: =IF(L47=0,0,N47/L47) -> 0 | N47: =SUM(N37:N46) -> 0 | O47: =SUM(O37:O46) -> 0 | P47: =IF(O47=0,0,Q47/O47) -> 0 | Q47: =SUM(Q37:Q46) -> 0
A48: 审计说明：
A49: 1.开发产品的计价方法： | N49: 3.开发产品——**库龄较长的原因：
A50: 2.开发产品本期发生重大变动的原因： | N50: 4.计提跌价准备的主要项目及原因：

Sheet 九、开发成本F2-11
A1: 致同会计师事务所
A2: 存货明细表
A3: =[1]底稿目录!A2 -> 被审计单位： | H3: =[1]底稿目录!A4 -> 编制人： | P3: =[1]底稿目录!A5 -> 编制日期： | U3: 索引号： | V3: =[1]底稿目录!F16 -> F2-11
A4: =[1]底稿目录!A3 -> 截止日：202X年12月21日 | H4: =[1]底稿目录!A6 -> 复核人： | P4: =[1]底稿目录!A7 -> 复核日期： | U4: 页 次：
A5: 九、开发成本
A6: （一）原值
A7: 序号 | B7: 项目名称 | C7: 总建筑面积/万平米 | D7: 开工时间 | E7: 预计竣工时间 | F7: 预计总投资 | G7: 未审数 | K7: 期初调整 | M7: 账项调整 | O7: 重分类调整 | Q7: 审定数 | U7: 库龄 | V7: 品质状况（正常、停建、毁损、报废等）
G8: 期初余额 | H8: 本期转入 | I8: 本期转出 | J8: 期末余额 | K8: 账项调整 | L8: 重分类调整 | M8: 本期转入 | N8: 本期转出 | O8: 本期转入 | P8: 本期转出 | Q8: 期初余额 | R8: 本期转入 | S8: 本期转出 | T8: 期末余额
A9: 1 | J9: =G9+H9-I9 -> 0 | Q9: =G9+K9+L9 -> 0 | R9: =H9+M9+O9 -> 0 | S9: =I9+N9+P9 -> 0 | T9: =Q9+R9-S9 -> 0
A10: 2 | J10: =G10+H10-I10 -> 0 | Q10: =G10+K10+L10 -> 0 | R10: =H10+M10+O10 -> 0 | S10: =I10+N10+P10 -> 0 | T10: =Q10+R10-S10 -> 0
A11: 3 | J11: =G11+H11-I11 -> 0 | Q11: =G11+K11+L11 -> 0 | R11: =H11+M11+O11 -> 0 | S11: =I11+N11+P11 -> 0 | T11: =Q11+R11-S11 -> 0
A12: 4 | J12: =G12+H12-I12 -> 0 | Q12: =G12+K12+L12 -> 0 | R12: =H12+M12+O12 -> 0 | S12: =I12+N12+P12 -> 0 | T12: =Q12+R12-S12 -> 0
A13: 5 | J13: =G13+H13-I13 -> 0 | Q13: =G13+K13+L13 -> 0 | R13: =H13+M13+O13 -> 0 | S13: =I13+N13+P13 -> 0 | T13: =Q13+R13-S13 -> 0
A14: 6 | J14: =G14+H14-I14 -> 0 | Q14: =G14+K14+L14 -> 0 | R14: =H14+M14+O14 -> 0 | S14: =I14+N14+P14 -> 0 | T14: =Q14+R14-S14 -> 0
A15: 7 | J15: =G15+H15-I15 -> 0 | Q15: =G15+K15+L15 -> 0 | R15: =H15+M15+O15 -> 0 | S15: =I15+N15+P15 -> 0 | T15: =Q15+R15-S15 -> 0
A16: 8 | J16: =G16+H16-I16 -> 0 | Q16: =G16+K16+L16 -> 0 | R16: =H16+M16+O16 -> 0 | S16: =I16+N16+P16 -> 0 | T16: =Q16+R16-S16 -> 0
A17: 9 | J17: =G17+H17-I17 -> 0 | Q17: =G17+K17+L17 -> 0 | R17: =H17+M17+O17 -> 0 | S17: =I17+N17+P17 -> 0 | T17: =Q17+R17-S17 -> 0
A18: 10 | J18: =G18+H18-I18 -> 0 | Q18: =G18+K18+L18 -> 0 | R18: =H18+M18+O18 -> 0 | S18: =I18+N18+P18 -> 0 | T18: =Q18+R18-S18 -> 0
A19: 合计 | F19: =SUM(F9:F18) -> 0 | G19: =SUM(G9:G18) -> 0 | H19: =SUM(H9:H18) -> 0 | I19: =SUM(I9:I18) -> 0 | J19: =SUM(J9:J18) -> 0 | K19: =SUM(K9:K18) -> 0 | L19: =SUM(L9:L18) -> 0 | M19: =SUM(M9:M18) -> 0 | ... T19: =SUM(T9:T18) -> 0
A20: （二）跌价准备
A21: 序号 | B21: 项目名称 | C21: 总建筑面积/万平米 | D21: 预计开工时间 | E21: 预计竣工时间 | F21: 预计总投资 | G21: 未审数 | K21: 期初调整 | M21: 账项调整 | O21: 重分类调整 | Q21: 审定数 | U21: 备注 | V21: 索引号
G22: 期初余额 | H22: 本期增加 | I22: 本期减少 | J22: 期末余额 | K22: 账项调整 | L22: 重分类调整 | M22: 本期增加 | N22: 本期减少 | O22: 本期增加 | P22: 本期减少 | Q22: 期初余额 | R22: 本期增加 | S22: 本期减少 | T22: 期末余额
A23: =A9 -> 1 | B23: =B9 -> 0 | C23: =C9 -> 0 | D23: =D9 -> 0 | E23: =E9 -> 0 | F23: =F9 -> 0 | J23: =G23+H23-I23 -> 0 | Q23: =G23+K23+L23 -> 0 | R23: =H23+M23+O23 -> 0 | S23: =I23+N23+P23 -> 0 | T23: =Q23+R23-S23 -> 0
A24: =A10 -> 2 | B24: =B10 -> 0 | C24: =C10 -> 0 | D24: =D10 -> 0 | E24: =E10 -> 0 | F24: =F10 -> 0 | J24: =G24+H24-I24 -> 0 | Q24: =G24+K24+L24 -> 0 | R24: =H24+M24+O24 -> 0 | S24: =I24+N24+P24 -> 0 | T24: =Q24+R24-S24 -> 0
A25: =A11 -> 3 | B25: =B11 -> 0 | C25: =C11 -> 0 | D25: =D11 -> 0 | E25: =E11 -> 0 | F25: =F11 -> 0 | J25: =G25+H25-I25 -> 0 | Q25: =G25+K25+L25 -> 0 | R25: =H25+M25+O25 -> 0 | S25: =I25+N25+P25 -> 0 | T25: =Q25+R25-S25 -> 0
A26: =A12 -> 4 | B26: =B12 -> 0 | C26: =C12 -> 0 | D26: =D12 -> 0 | E26: =E12 -> 0 | F26: =F12 -> 0 | J26: =G26+H26-I26 -> 0 | Q26: =G26+K26+L26 -> 0 | R26: =H26+M26+O26 -> 0 | S26: =I26+N26+P26 -> 0 | T26: =Q26+R26-S26 -> 0
A27: =A13 -> 5 | B27: =B13 -> 0 | C27: =C13 -> 0 | D27: =D13 -> 0 | E27: =E13 -> 0 | F27: =F13 -> 0 | J27: =G27+H27-I27 -> 0 | Q27: =G27+K27+L27 -> 0 | R27: =H27+M27+O27 -> 0 | S27: =I27+N27+P27 -> 0 | T27: =Q27+R27-S27 -> 0
A28: =A14 -> 6 | B28: =B14 -> 0 | C28: =C14 -> 0 | D28: =D14 -> 0 | E28: =E14 -> 0 | F28: =F14 -> 0 | J28: =G28+H28-I28 -> 0 | Q28: =G28+K28+L28 -> 0 | R28: =H28+M28+O28 -> 0 | S28: =I28+N28+P28 -> 0 | T28: =Q28+R28-S28 -> 0
A29: =A15 -> 7 | B29: =B15 -> 0 | C29: =C15 -> 0 | D29: =D15 -> 0 | E29: =E15 -> 0 | F29: =F15 -> 0 | J29: =G29+H29-I29 -> 0 | Q29: =G29+K29+L29 -> 0 | R29: =H29+M29+O29 -> 0 | S29: =I29+N29+P29 -> 0 | T29: =Q29+R29-S29 -> 0
A30: =A16 -> 8 | B30: =B16 -> 0 | C30: =C16 -> 0 | D30: =D16 -> 0 | E30: =E16 -> 0 | F30: =F16 -> 0 | J30: =G30+H30-I30 -> 0 | Q30: =G30+K30+L30 -> 0 | R30: =H30+M30+O30 -> 0 | S30: =I30+N30+P30 -> 0 | T30: =Q30+R30-S30 -> 0
A31: =A17 -> 9 | B31: =B17 -> 0 | C31: =C17 -> 0 | D31: =D17 -> 0 | E31: =E17 -> 0 | F31: =F17 -> 0 | J31: =G31+H31-I31 -> 0 | Q31: =G31+K31+L31 -> 0 | R31: =H31+M31+O31 -> 0 | S31: =I31+N31+P31 -> 0 | T31: =Q31+R31-S31 -> 0
A32: =A18 -> 10 | B32: =B18 -> 0 | C32: =C18 -> 0 | D32: =D18 -> 0 | E32: =E18 -> 0 | F32: =F18 -> 0 | J32: =G32+H32-I32 -> 0 | Q32: =G32+K32+L32 -> 0 | R32: =H32+M32+O32 -> 0 | S32: =I32+N32+P32 -> 0 | T32: =Q32+R32-S32 -> 0
A33: 合计 | F33: =SUM(F23:F32) -> 0 | G33: =SUM(G23:G32) -> 0 | H33: =SUM(H23:H32) -> 0 | I33: =SUM(I23:I32) -> 0 | J33: =SUM(J23:J32) -> 0 | K33: =SUM(K23:K32) -> 0 | L33: =SUM(L23:L32) -> 0 | M33: =SUM(M23:M32) -> 0 | ... T33: =SUM(T23:T32) -> 0
A34: （三）净值
A35: 序号 | B35: 项目名称 | C35: 总建筑面积/万平米 | D35: 预计开工时间 | E35: 预计竣工时间 | F35: 预计总投资 | G35: 未审数 | I35: 审定数
G36: 期初数 | H36: 期末数 | I36: 期初数 | J36: 期末数
A37: =A9 -> 1 | B37: =B9 -> 0 | C37: =C9 -> 0 | D37: =D9 -> 0 | E37: =E9 -> 0 | F37: =F9 -> 0 | G37: =G9-G23 -> 0 | H37: =J9-J23 -> 0 | I37: =Q9-Q23 -> 0 | J37: =T9-T23 -> 0
A38: =A10 -> 2 | B38: =B10 -> 0 | C38: =C10 -> 0 | D38: =D10 -> 0 | E38: =E10 -> 0 | F38: =F10 -> 0 | G38: =G10-G24 -> 0 | H38: =J10-J24 -> 0 | I38: =Q10-Q24 -> 0 | J38: =T10-T24 -> 0
A39: =A11 -> 3 | B39: =B11 -> 0 | C39: =C11 -> 0 | D39: =D11 -> 0 | E39: =E11 -> 0 | F39: =F11 -> 0 | G39: =G11-G25 -> 0 | H39: =J11-J25 -> 0 | I39: =Q11-Q25 -> 0 | J39: =T11-T25 -> 0
A40: =A12 -> 4 | B40: =B12 -> 0 | C40: =C12 -> 0 | D40: =D12 -> 0 | E40: =E12 -> 0 | F40: =F12 -> 0 | G40: =G12-G26 -> 0 | H40: =J12-J26 -> 0 | I40: =Q12-Q26 -> 0 | J40: =T12-T26 -> 0
A41: =A13 -> 5 | B41: =B13 -> 0 | C41: =C13 -> 0 | D41: =D13 -> 0 | E41: =E13 -> 0 | F41: =F13 -> 0 | G41: =G13-G27 -> 0 | H41: =J13-J27 -> 0 | I41: =Q13-Q27 -> 0 | J41: =T13-T27 -> 0
A42: =A14 -> 6 | B42: =B14 -> 0 | C42: =C14 -> 0 | D42: =D14 -> 0 | E42: =E14 -> 0 | F42: =F14 -> 0 | G42: =G14-G28 -> 0 | H42: =J14-J28 -> 0 | I42: =Q14-Q28 -> 0 | J42: =T14-T28 -> 0
A43: =A15 -> 7 | B43: =B15 -> 0 | C43: =C15 -> 0 | D43: =D15 -> 0 | E43: =E15 -> 0 | F43: =F15 -> 0 | G43: =G15-G29 -> 0 | H43: =J15-J29 -> 0 | I43: =Q15-Q29 -> 0 | J43: =T15-T29 -> 0
A44: =A16 -> 8 | B44: =B16 -> 0 | C44: =C16 -> 0 | D44: =D16 -> 0 | E44: =E16 -> 0 | F44: =F16 -> 0 | G44: =G16-G30 -> 0 | H44: =J16-J30 -> 0 | I44: =Q16-Q30 -> 0 | J44: =T16-T30 -> 0
A45: =A17 -> 9 | B45: =B17 -> 0 | C45: =C17 -> 0 | D45: =D17 -> 0 | E45: =E17 -> 0 | F45: =F17 -> 0 | G45: =G17-G31 -> 0 | H45: =J17-J31 -> 0 | I45: =Q17-Q31 -> 0 | J45: =T17-T31 -> 0
A46: =A18 -> 10 | B46: =B18 -> 0 | C46: =C18 -> 0 | D46: =D18 -> 0 | E46: =E18 -> 0 | F46: =F18 -> 0 | G46: =G18-G32 -> 0 | H46: =J18-J32 -> 0 | I46: =Q18-Q32 -> 0 | J46: =T18-T32 -> 0
A47: =A19 -> 合计 | F47: =SUM(F37:F46) -> 0 | G47: =SUM(G37:G46) -> 0 | H47: =SUM(H37:H46) -> 0 | I47: =SUM(I37:I46) -> 0 | J47: =SUM(J37:J46) -> 0
A48: 审计说明：
A49: 1.开发成本核算方法： | H49: 3.开发成本——**库龄较长的原因：
A50: 2.开发成本本期发生的重大变动及原因： | H50: 4.计提跌价准备的主要项目及原因：

Sheet 十、合同履约成本F2-12
A1: 致同会计师事务所
A2: 存货明细表
A3: =[1]底稿目录!A2 -> 被审计单位： | E3: =[1]底稿目录!A4 -> 编制人： | H3: =[1]底稿目录!A5 -> 编制日期： | M3: 索引号： | N3: =[1]底稿目录!F17 -> F2-12
A4: =[1]底稿目录!A3 -> 截止日：202X年12月21日 | E4: =[1]底稿目录!A6 -> 复核人： | H4: =[1]底稿目录!A7 -> 复核日期： | M4: 页 次：
A5: 十、合同履约成本
A6: 序号 | B6: 项目编码 | C6: 项目名称 | D6: 开工时间 | E6: 预计竣工时间 | F6: 期初金额 | G6: 本期转入 | H6: 本期转出 | I6: 期末余额 | J6: 库龄 | N6: 品质状况（正常、停建、毁损、报废等）
H7: 金额 | I7: 金额 | J7: 1年以内 | K7: 1-2年 | L7: 2-3年 | M7: 3年以上
A8: 1 | I8: =F8+G8-H8 -> 0
A9: 2 | I9: =F9+G9-H9 -> 0
A10: 3 | I10: =F10+G10-H10 -> 0
A11: 4 | I11: =F11+G11-H11 -> 0
A12: 5 | I12: =F12+G12-H12 -> 0
A13: 6 | I13: =F13+G13-H13 -> 0
I14: =F14+G14-H14 -> 0
I15: =F15+G15-H15 -> 0
I16: =F16+G16-H16 -> 0
I17: =F17+G17-H17 -> 0
I18: =F18+G18-H18 -> 0
I19: =F19+G19-H19 -> 0
A20: 合计 | F20: =SUM(F8:F19) -> 0 | G20: =SUM(G8:G19) -> 0 | H20: =SUM(H8:H19) -> 0 | I20: =SUM(I8:I19) -> 0 | J20: =SUM(J8:J19) -> 0 | K20: =SUM(K8:K19) -> 0 | L20: =SUM(L8:L19) -> 0 | M20: =SUM(M8:M19) -> 0
A21: 减：存货跌价准备
A22: 合同履约成本净额 | F22: =F20-F21 -> 0 | I22: =I20-I21 -> 0
A23: 审计说明： | I23: =IF((I20-J20-K20-L20-M20)=0,"OK","库龄与期末金额不匹配") -> OK
A24: 1.合同履约成本核算方法： | G24: 3.合同履约成本**停建的原因：
A25: 2.合同履约成本本期发生的重大变动及原因： | G25: 4.计提跌价准备的主要项目及原因：

Sheet 十一、消耗性生物资产F2-13
A1: 致同会计师事务所
A2: 消耗性生物资产明细表
A3: =[1]底稿目录!A2 -> 被审计单位： | F3: =[1]底稿目录!A4 -> 编制人： | L3: =[1]底稿目录!A5 -> 编制日期： | S3: 索引号： | T3: =[1]底稿目录!F18 -> F2-13
A4: =[1]底稿目录!A3 -> 截止日：202X年12月21日 | F4: =[1]底稿目录!A6 -> 复核人： | L4: =[1]底稿目录!A7 -> 复核日期： | S4: 页次：
A5: 十一、消耗性生物资产明细表
A6: 存货名称 | B6: 品种 | C6: 单位 | D6: 期初库存 | G6: 本期购进 | J6: 本期发出 | M6: 期末结存 | P6: 库龄 | T6: 状况
D7: 存栏数 | E7: 单价 | F7: 金额 | G7: 存栏数 | H7: 单价 | I7: 金额 | J7: 存栏数 | K7: 单价 | L7: 金额 | M7: 存栏数 | N7: 单价 | O7: 金额 | P7: 1年以内 | Q7: 1-2年 | R7: 2-3年 | S7: 3年以上
E9: =IF(D9=0,0,F9/D9) -> 0 | H9: =IF(G9=0,0,I9/G9) -> 0 | K9: =IF(J9=0,0,L9/J9) -> 0 | M9: =D9+G9-J9 -> 0 | N9: =IF(M9=0,0,O9/M9) -> 0 | O9: =F9+I9-L9 -> 0
E10: =IF(D10=0,0,F10/D10) -> 0 | H10: =IF(G10=0,0,I10/G10) -> 0 | K10: =IF(J10=0,0,L10/J10) -> 0 | M10: =D10+G10-J10 -> 0 | N10: =IF(M10=0,0,O10/M10) -> 0 | O10: =F10+I10-L10 -> 0
E11: =IF(D11=0,0,F11/D11) -> 0 | H11: =IF(G11=0,0,I11/G11) -> 0 | K11: =IF(J11=0,0,L11/J11) -> 0 | M11: =D11+G11-J11 -> 0 | N11: =IF(M11=0,0,O11/M11) -> 0 | O11: =F11+I11-L11 -> 0
E12: =IF(D12=0,0,F12/D12) -> 0 | H12: =IF(G12=0,0,I12/G12) -> 0 | K12: =IF(J12=0,0,L12/J12) -> 0 | M12: =D12+G12-J12 -> 0 | N12: =IF(M12=0,0,O12/M12) -> 0 | O12: =F12+I12-L12 -> 0
E13: =IF(D13=0,0,F13/D13) -> 0 | H13: =IF(G13=0,0,I13/G13) -> 0 | K13: =IF(J13=0,0,L13/J13) -> 0 | M13: =D13+G13-J13 -> 0 | N13: =IF(M13=0,0,O13/M13) -> 0 | O13: =F13+I13-L13 -> 0
E14: =IF(D14=0,0,F14/D14) -> 0 | H14: =IF(G14=0,0,I14/G14) -> 0 | K14: =IF(J14=0,0,L14/J14) -> 0 | M14: =D14+G14-J14 -> 0 | N14: =IF(M14=0,0,O14/M14) -> 0 | O14: =F14+I14-L14 -> 0
E15: =IF(D15=0,0,F15/D15) -> 0 | H15: =IF(G15=0,0,I15/G15) -> 0 | K15: =IF(J15=0,0,L15/J15) -> 0 | M15: =D15+G15-J15 -> 0 | N15: =IF(M15=0,0,O15/M15) -> 0 | O15: =F15+I15-L15 -> 0
E16: =IF(D16=0,0,F16/D16) -> 0 | H16: =IF(G16=0,0,I16/G16) -> 0 | K16: =IF(J16=0,0,L16/J16) -> 0 | M16: =D16+G16-J16 -> 0 | N16: =IF(M16=0,0,O16/M16) -> 0 | O16: =F16+I16-L16 -> 0
E17: =IF(D17=0,0,F17/D17) -> 0 | H17: =IF(G17=0,0,I17/G17) -> 0 | K17: =IF(J17=0,0,L17/J17) -> 0 | M17: =D17+G17-J17 -> 0 | N17: =IF(M17=0,0,O17/M17) -> 0 | O17: =F17+I17-L17 -> 0
E18: =IF(D18=0,0,F18/D18) -> 0 | H18: =IF(G18=0,0,I18/G18) -> 0 | K18: =IF(J18=0,0,L18/J18) -> 0 | M18: =D18+G18-J18 -> 0 | N18: =IF(M18=0,0,O18/M18) -> 0 | O18: =F18+I18-L18 -> 0
E19: =IF(D19=0,0,F19/D19) -> 0 | H19: =IF(G19=0,0,I19/G19) -> 0 | K19: =IF(J19=0,0,L19/J19) -> 0 | M19: =D19+G19-J19 -> 0 | N19: =IF(M19=0,0,O19/M19) -> 0 | O19: =F19+I19-L19 -> 0
E20: =IF(D20=0,0,F20/D20) -> 0 | H20: =IF(G20=0,0,I20/G20) -> 0 | K20: =IF(J20=0,0,L20/J20) -> 0 | M20: =D20+G20-J20 -> 0 | N20: =IF(M20=0,0,O20/M20) -> 0 | O20: =F20+I20-L20 -> 0
... E24: =IF(D24=0,0,F24/D24) -> 0 | H24: =IF(G24=0,0,I24/G24) -> 0 | K24: =IF(J24=0,0,L24/J24) -> 0 | M24: =D24+G24-J24 -> 0 | N24: =IF(M24=0,0,O24/M24) -> 0 | O24: =F24+I24-L24 -> 0
A25: 合计 | D25: -- | E25: -- | F25: =SUM(F9:F24) -> 0 | G25: -- | H25: -- | I25: =SUM(I9:I24) -> 0 | J25: -- | K25: -- | L25: =SUM(L9:L24) -> 0 | M25: -- | N25: -- | O25: =SUM(O9:O24) -> 0 | P25: =SUM(P9:P24) -> 0 | Q25: =SUM(Q9:Q24) -> 0 | R25: =SUM(R9:R24) -> 0 | S25: =SUM(S9:S24) -> 0
A26: （二）跌价准备 | O26: =IF((O25-P25-Q25-R25-S25)=0,"OK","库龄与期末金额不匹配") -> OK
A27: 存货名称 | B27: 品种 | C27: 未审数 | G27: 期初调整 | I27: 账项调整 | K27: 重分类调整 | M27: 审定数
C28: 期初余额 | D28: 本期增加 | E28: 本期减少 | F28: 期末余额 | G28: 账项调整 | H28: 重分类调整 | I28: 本期增加 | J28: 本期减少 | K28: 本期增加 | L28: 本期减少 | M28: 期初余额 | N28: 本期增加 | O28: 本期减少 | P28: 期末余额
A29: =A9 -> 0 | B29: =B9 -> 0 | F29: =C29+D29-E29 -> 0 | M29: =C29+G29+H29 -> 0 | N29: =D29+I29+K29 -> 0 | O29: =E29+J29+L29 -> 0 | P29: =M29+N29-O29 -> 0
A30: =A10 -> 0 | B30: =B10 -> 0 | F30: =C30+D30-E30 -> 0 | M30: =C30+G30+H30 -> 0 | N30: =D30+I30+K30 -> 0 | O30: =E30+J30+L30 -> 0 | P30: =M30+N30-O30 -> 0
A31: =A11 -> 0 | B31: =B11 -> 0 | F31: =C31+D31-E31 -> 0 | M31: =C31+G31+H31 -> 0 | N31: =D31+I31+K31 -> 0 | O31: =E31+J31+L31 -> 0 | P31: =M31+N31-O31 -> 0
A32: =A12 -> 0 | B32: =B12 -> 0 | F32: =C32+D32-E32 -> 0 | M32: =C32+G32+H32 -> 0 | N32: =D32+I32+K32 -> 0 | O32: =E32+J32+L32 -> 0 | P32: =M32+N32-O32 -> 0
A33: =A13 -> 0 | B33: =B13 -> 0 | F33: =C33+D33-E33 -> 0 | M33: =C33+G33+H33 -> 0 | N33: =D33+I33+K33 -> 0 | O33: =E33+J33+L33 -> 0 | P33: =M33+N33-O33 -> 0
A34: =A14 -> 0 | B34: =B14 -> 0 | F34: =C34+D34-E34 -> 0 | M34: =C34+G34+H34 -> 0 | N34: =D34+I34+K34 -> 0 | O34: =E34+J34+L34 -> 0 | P34: =M34+N34-O34 -> 0
A35: =A15 -> 0 | B35: =B15 -> 0 | F35: =C35+D35-E35 -> 0 | M35: =C35+G35+H35 -> 0 | N35: =D35+I35+K35 -> 0 | O35: =E35+J35+L35 -> 0 | P35: =M35+N35-O35 -> 0
A36: =A16 -> 0 | B36: =B16 -> 0 | F36: =C36+D36-E36 -> 0 | M36: =C36+G36+H36 -> 0 | N36: =D36+I36+K36 -> 0 | O36: =E36+J36+L36 -> 0 | P36: =M36+N36-O36 -> 0
A37: =A17 -> 0 | B37: =B17 -> 0 | F37: =C37+D37-E37 -> 0 | M37: =C37+G37+H37 -> 0 | N37: =D37+I37+K37 -> 0 | O37: =E37+J37+L37 -> 0 | P37: =M37+N37-O37 -> 0
A38: =A18 -> 0 | B38: =B18 -> 0 | F38: =C38+D38-E38 -> 0 | M38: =C38+G38+H38 -> 0 | N38: =D38+I38+K38 -> 0 | O38: =E38+J38+L38 -> 0 | P38: =M38+N38-O38 -> 0
A39: =A24 -> 0 | B39: =B19 -> 0 | F39: =C39+D39-E39 -> 0 | M39: =C39+G39+H39 -> 0 | N39: =D39+I39+K39 -> 0 | O39: =E39+J39+L39 -> 0 | P39: =M39+N39-O39 -> 0
A40: =A25 -> 合计 | B40: -- | C40: =SUM(C29:C39) -> 0 | D40: =SUM(D29:D39) -> 0 | E40: =SUM(E29:E39) -> 0 | F40: =C40+D40-E40 -> 0 | G40: =SUM(G29:G39) -> 0 | H40: =SUM(H29:H39) -> 0 | I40: =SUM(I29:I39) -> 0 | J40: =SUM(J29:J39) -> 0 | K40: =SUM(K29:K39) -> 0 | L40: =SUM(L29:L39) -> 0 | M40: =C40+G40+H40 -> 0 | N40: =D40+I40+K40 -> 0 | O40: =E40+J40+L40 -> 0 | P40: =M40+N40-O40 -> 0
A41: （三）净值
A42: 存货名称 | B42: 品种 | C42: 期初未审数 | F42: 期末未审数
C43: 存栏数 | D43: 单位成本 | E43: 期初数 | F43: 存栏数 | G43: 单位成本 | H43: 期末数
A44: =A29 -> 0 | B44: =B29 -> 0 | C44: =D9 -> 0 | D44: =IF(C44=0,0,E44/C44) -> 0 | E44: =F9-F29 -> 0 | F44: =M9 -> 0 | G44: =IF(F44=0,0,H44/F44) -> 0 | H44: =O9-P29 -> 0
A45: =A30 -> 0 | B45: =B30 -> 0 | C45: =D10 -> 0 | D45: =IF(C45=0,0,E45/C45) -> 0 | E45: =F10-F30 -> 0 | F45: =M10 -> 0 | G45: =IF(F45=0,0,H45/F45) -> 0 | H45: =O10-P30 -> 0
A46: =A31 -> 0 | B46: =B31 -> 0 | C46: =D11 -> 0 | D46: =IF(C46=0,0,E46/C46) -> 0 | E46: =F11-F31 -> 0 | F46: =M11 -> 0 | G46: =IF(F46=0,0,H46/F46) -> 0 | H46: =O11-P31 -> 0
A47: =A32 -> 0 | B47: =B32 -> 0 | C47: =D12 -> 0 | D47: =IF(C47=0,0,E47/C47) -> 0 | E47: =F12-F32 -> 0 | F47: =M12 -> 0 | G47: =IF(F47=0,0,H47/F47) -> 0 | H47: =O12-P32 -> 0
A48: =A33 -> 0 | B48: =B33 -> 0 | C48: =D13 -> 0 | D48: =IF(C48=0,0,E48/C48) -> 0 | E48: =F13-F33 -> 0 | F48: =M13 -> 0 | G48: =IF(F48=0,0,H48/F48) -> 0 | H48: =O13-P33 -> 0
A49: =A34 -> 0 | B49: =B34 -> 0 | C49: =D14 -> 0 | D49: =IF(C49=0,0,E49/C49) -> 0 | E49: =F14-F34 -> 0 | F49: =M14 -> 0 | G49: =IF(F49=0,0,H49/F49) -> 0 | H49: =O14-P34 -> 0
A50: =A35 -> 0 | B50: =B35 -> 0 | C50: =D15 -> 0 | D50: =IF(C50=0,0,E50/C50) -> 0 | E50: =F15-F35 -> 0 | F50: =M15 -> 0 | G50: =IF(F50=0,0,H50/F50) -> 0 | H50: =O15-P35 -> 0
A51: =A36 -> 0 | B51: =B36 -> 0 | C51: =D16 -> 0 | D51: =IF(C51=0,0,E51/C51) -> 0 | E51: =F16-F36 -> 0 | F51: =M16 -> 0 | G51: =IF(F51=0,0,H51/F51) -> 0 | H51: =O16-P36 -> 0
A52: =A37 -> 0 | B52: =B37 -> 0 | C52: =D17 -> 0 | D52: =IF(C52=0,0,E52/C52) -> 0 | E52: =F17-F37 -> 0 | F52: =M17 -> 0 | G52: =IF(F52=0,0,H52/F52) -> 0 | H52: =O17-P37 -> 0
A53: =A38 -> 0 | B53: =B38 -> 0 | C53: =D18 -> 0 | D53: =IF(C53=0,0,E53/C53) -> 0 | E53: =F18-F38 -> 0 | F53: =M18 -> 0 | G53: =IF(F53=0,0,H53/F53) -> 0 | H53: =O18-P38 -> 0
A54: =A39 -> 0 | B54: =B39 -> 0 | C54: =D19 -> 0 | D54: =IF(C54=0,0,E54/C54) -> 0 | E54: =F19-F39 -> 0 | F54: =M19 -> 0 | G54: =IF(F54=0,0,H54/F54) -> 0 | H54: =O19-P39 -> 0
A55: =A25 -> 合计 | B55: -- | C55: =SUM(C44:C54) -> 0 | D55: =SUM(D44:D54) -> 0 | E55: =SUM(E44:E54) -> 0 | F55: =SUM(F44:F54) -> 0 | G55: =SUM(G44:G54) -> 0 | H55: =SUM(H44:H54) -> 0
A56: 审计说明：

Sheet 调整分录汇总F2-14
A1: 致同会计师事务所
A2: 存货及跌价准备调整分录汇总表
A3: =[1]底稿目录!A2 -> 被审计单位： | D3: =[1]底稿目录!A4 -> 编制人： | G3: =[1]底稿目录!A5 -> 编制日期： | I3: 索引号： | J3: =[1]底稿目录!F19 -> F2-14
A4: =[1]底稿目录!A3 -> 截止日：202X年12月21日 | D4: =[1]底稿目录!A6 -> 复核人： | G4: =[1]底稿目录!A7 -> 复核日期： | I4: 页 次：
A5: 调整事项说明 | B5: 类别（报表调整/账项调整/其他） | C5: 报表项目 | D5: 科目名称 | E5: 附注项目 | F5: …… | G5: 借方调整金额 | H5: 贷方调整金额 | I5: 索引 | J5: 备注
A22: 提示：本底稿适用于调整分录较多、较复杂的项目，且仅列示与本报表项目相关的审计调整。项目组可根据项目实际情况选择是否使用该底稿。

Sheet 会计政策、核算流程F2-16
A1: 致同会计师事务所
A2: 存货会计政策、核算流程检查表
A3: 被审计单位： | C3: 编制人： | D3: 编制日期： | F3: 索引号：F2-16
A4: 截止日： | C4: 复核人： | D4: 复核日期： | F4: 页 次：
A5: 一、审计目标：
A6: 1.资产负债表中记录的存货是存在的，且已经记录在恰当的账户中
A7: 2.所有应记录的存货均已记录，所有应当包括在财务报表中的相关披露均已包括
A8: 3.存货以恰当的金额包括在财务报表中，与之相关的计价或分摊调整已恰当记录，相关披露已得到恰当计量和描述
A9: 二、审计过程：
A10: 1.了解、分析存货核算会计政策和会计估计是否符合准则要求、是否保持一惯性，关注是否利用会计政策估计及其变更操纵利润。
A11: 2.了解、分析成本核算（归集、分配、结转等）政策及流程的合理性，包括原材料的入账基础和计价方法，周转材料（低值易耗品、包装物）与固定资产的划分标准、计价方法，生产工艺流程和成本核算方法，自制半成品的计价方法，库存商品的计价方法。关注是否符合实际经营情况和会计准则的要求，并与前期进行对比，分析其是否保持一贯性。
A12: 3.检查主营业务成本的内容和计算方法是否符合会计准则规定，前后期是否一致。
A13: （一）存货会计政策、会计估计
A14: 项目 | C14: 被审计单位采用的方法 | D14: 是否符合准则 | E14: 是否一贯采用 | F14: 备注
A15: 发出存货的计价方法 | C15: 加权平均法（先进先出法、个别计价法）
A16: 存货可变现净值的确定依据 | C16: 存货的估计售价减去至完工时估计将要发生的成本、估计的销售费用以及相关税费后的金额
A17: 存货跌价准备的计提方法 | C17: 按照单个（类别、合并）存货项目计提存货跌价准备
A18: 存货的盘存制度 | C18: 永续盘存制（定期盘存制）
A19: 低值易耗品和包装物的摊销方法 | C19: 低值易耗品领用时采用一次转销法摊销；周转用包装物按照预计的使用次数分次计入成本费用。
A20: 在产品约当产量比例的确定方法 | C20: 投入的材料成本在全部材料成本中所占的比例
A21: （二）存货成本核算
A22: 1、工艺流程简述
A24: 2、成本核算流程
A25: （1）材料费用的归集与分配
A27: （2）职工薪酬的归集与分配
A29: （3）制造费用的归集与分配
A31: （4）其他费用的归集与分配
A33: （5）完工产品与在产品的成本分配
A35: （6）成本结转时点、方法与分配
A37: （7）会计核算图
A39: 三、审计说明：
A41: 四、审计结论：

Sheet 底稿目录 (2)
A1: 底稿开列时，可先在以下单元格填写有关内容，以便其他底稿引用有关数据： | D1: 序号 | E1: 内容 | F1: 索引号
A2: 被审计单位： | D2: 1 | E2: 存货总体分析表 | F2: F2-18
A3: 截止日：202X年12月31日 | D3: =D2+1 -> 2 | E3: 存货产销量变动分析表 | F3: F2-19
A4: 编制人： | D4: =D3+1 -> 3 | E4: 产成品单位成本年度比较表 | F4: F2-20
A5: 编制日期：
A6: 复核人：
A7: 复核日期：

Sheet 存货总体分析表F2-18
A1: 致同会计师事务所
A2: 存货总体分析表
A3: =[3]底稿目录!A2 -> 被审计单位： | C3: =[3]底稿目录!A4 -> 编制人： | E3: =[3]底稿目录!A5 -> 编制日期： | H3: 索引号： | I3: =[3]底稿目录!F2 -> F2-18
A4: =[3]底稿目录!A3 -> 截止日：202X年12月31日 | C4: =[3]底稿目录!A6 -> 复核人： | E4: =[3]底稿目录!A7 -> 复核日期： | H4: 页 次：
A5: 一、审计目标：
A6: 1.资产负债表中记录的存货是存在的，且已经记录在恰当的账户中
A7: 2.存货以恰当的金额包括在财务报表中，与之相关的计价或分摊调整已恰当记录，相关披露已得到恰当计量和描述
A8: 二、审计过程：
A9: A、存货构成分析
A10: 存货项目 | C10: 20X5/12/31 | E10: 20X4/12/31 | G10: 20X3/12/31 | I10: 是否异常
C11: 金额 | D11: 结构比 | E11: 金额 | F11: 结构比 | G11: 金额 | H11: 结构比
A12: ='[2]明细汇总表F2-2'!A17 -> 原材料 | D12: =IF($C$25=0,0,C12/$C$25) -> 0 | F12: =IF($E$25=0,0,E12/$E$25) -> 0 | H12: =IF($G$25=0,0,G12/$G$25) -> 0
A13: ='[2]明细汇总表F2-2'!A18 -> 材料采购/在途物资 | D13: =IF($C$25=0,0,C13/$C$25) -> 0 | F13: =IF($E$25=0,0,E13/$E$25) -> 0 | H13: =IF($G$25=0,0,#REF!/$G$25) -> 0
A14: ='[2]明细汇总表F2-2'!A19 -> 周转材料/低值易耗品/包装物 | D14: =IF($C$25=0,0,C14/$C$25) -> 0 | F14: =IF($E$25=0,0,E14/$E$25) -> 0 | H14: =IF($G$25=0,0,G29/$G$25) -> 0
A15: ='[2]明细汇总表F2-2'!A20 -> 在产品 | D15: =IF($C$25=0,0,C15/$C$25) -> 0 | F15: =IF($E$25=0,0,E15/$E$25) -> 0 | H15: =IF($G$25=0,0,G30/$G$25) -> 0
A16: ='[2]明细汇总表F2-2'!A21 -> 自制半成品 | D16: =IF($C$25=0,0,C16/$C$25) -> 0 | F16: =IF($E$25=0,0,E16/$E$25) -> 0 | H16: =IF($G$25=0,0,G32/$G$25) -> 0
A17: ='[2]明细汇总表F2-2'!A22 -> 委托加工物资 | D17: =IF($C$25=0,0,C17/$C$25) -> 0 | F17: =IF($E$25=0,0,E17/$E$25) -> 0 | H17: =IF($G$25=0,0,#REF!/$G$25) -> 0
A18: ='[2]明细汇总表F2-2'!A23 -> 库存商品 | D18: =IF($C$25=0,0,C18/$C$25) -> 0 | F18: =IF($E$25=0,0,E18/$E$25) -> 0 | H18: =IF($G$25=0,0,#REF!/$G$25) -> 0
A19: ='[2]明细汇总表F2-2'!A24 -> 发出商品 | D19: =IF($C$25=0,0,C19/$C$25) -> 0 | F19: =IF($E$25=0,0,E19/$E$25) -> 0 | H19: =IF($G$25=0,0,#REF!/$G$25) -> 0
A20: ='[2]明细汇总表F2-2'!A25 -> 开发产品 | D20: =IF($C$25=0,0,C20/$C$25) -> 0 | F20: =IF($E$25=0,0,E20/$E$25) -> 0 | H20: =IF($G$25=0,0,#REF!/$G$25) -> 0
A21: ='[2]明细汇总表F2-2'!A26 -> 开发成本 | D21: =IF($C$25=0,0,C21/$C$25) -> 0 | F21: =IF($E$25=0,0,E21/$E$25) -> 0 | H21: =IF($G$25=0,0,#REF!/$G$25) -> 0
A22: ='[2]明细汇总表F2-2'!A27 -> 合同履约成本 | D22: =IF($C$25=0,0,C22/$C$25) -> 0 | F22: =IF($E$25=0,0,E22/$E$25) -> 0 | H22: =IF($G$25=0,0,#REF!/$G$25) -> 0
A23: ='[2]明细汇总表F2-2'!A28 -> 消耗性生物资产 | D23: =IF($C$25=0,0,C23/$C$25) -> 0 | F23: =IF($E$25=0,0,E23/$E$25) -> 0 | H23: =IF($G$25=0,0,#REF!/$G$25) -> 0
A24: ='[2]明细汇总表F2-2'!A29 -> 数据资源 | D24: =IF($C$25=0,0,C24/$C$25) -> 0 | F24: =IF($E$25=0,0,E24/$E$25) -> 0 | H24: =IF($G$25=0,0,#REF!/$G$25) -> 0
A25: 合计 | C25: =SUM(C12:C23) -> 0 | D25: =SUM(D12:D23) -> 0 | E25: =SUM(E12:E23) -> 0 | F25: =SUM(F12:F23) -> 0 | G25: =SUM(G12:G23) -> 0 | H25: =SUM(H12:H23) -> 0 | I25: ——
A26: 审计说明：
A27: 异常原因
A29: B、存货指标分析（三期数据对比）
A30: 指标 | C30: 20X5年 | E30: 20X4年 | G30: 20X3年 | I30: 是否异常
C31: 指标值 | D31: 变动率 | E31: 指标值 | F31: 变动率 | G31: 指标值 | H31: 变动率
A32: 存货周转率（销售成本÷平均存货） | D32: =IF(E32=0,0,(C32-E32)/E32) -> 0 | F32: =IF(G32=0,0,(E32-G32)/G32) -> 0 | H32: ——
A33: 存货平均天数（365天÷存货周转率） | D33: =IF(E33=0,0,(C33-E33)/E33) -> 0 | F33: =IF(G33=0,0,(E33-G33)/G33) -> 0 | H33: ——
A34: 存货跌价准备占存货余额比例 （存货跌价准备÷存货余额） | D34: =IF(E34=0,0,(C34-E34)/E34) -> 0 | F34: =IF(G34=0,0,(E34-G34)/G34) -> 0 | H34: ——
A35: 存货占流动资产比例 （平均存货÷平均流动资产） | D35: =IF(E35=0,0,(C35-E35)/E35) -> 0 | F35: =IF(G35=0,0,(E35-G35)/G35) -> 0 | H35: ——
A36: 废率（核销存货/平均存货余额） | D36: =IF(E36=0,0,(C36-E36)/E36) -> 0 | F36: =IF(G36=0,0,(E36-G36)/G36) -> 0 | H36: ——
A37: 审计说明：
A38: 异常原因
A40: C、存货指标分析（与同行业数据对比）
A41: 指标 | C41: 20X5年 | E41: 行业平均 | F41: 行业公司A | G41: 行业公司B | H41: 行业公司C | I41: 是否异常
C42: 指标值 | D42: 偏离
A43: 存货周转率（销售成本÷平均存货） | D43: =IF(E43=0,0,(C43-E43)/E43) -> 0
A44: 存货平均天数（365天÷存货周转率） | D44: =IF(E44=0,0,(C44-E44)/E44) -> 0
A45: 存货跌价准备占存货余额比例 （存货跌价准备÷存货余额） | D45: =IF(E45=0,0,(C45-E45)/E45) -> 0 | J45: 对存货跌价准备错报风险高的项目，可拆分为原材料、产成品等跌价准备分别占原材料、产成品等余额的比例与同行业对比分析
A46: 存货占流动资产比例 （平均存货÷平均流动资产） | D46: =IF(E46=0,0,(C46-E46)/E46) -> 0
A47: 审计说明：
A48: 异常原因
A50: D、存货周转率分析（主要产品大类三期数对比）
A51: 产品名称 | B51: 20X5年平均存货 | C51: 20X5年销售成本 | D51: 20X5年 | F51: 20X4年 | H51: 20X3年存货周转率 | I51: 是否异常
D52: 存货周转率 | E52: 变动率 | F52: 存货周转率 | G52: 变动率
D53: =IF(C53=0,0,C53/B53) -> 0 | E53: =IF(F53=0,0,(D53-F53)/F53) -> 0 | G53: =IF(H53=0,0,(F53-H53)/H53) -> 0
D54: =IF(C54=0,0,C54/B54) -> 0 | E54: =IF(F54=0,0,(D54-F54)/F54) -> 0 | G54: =IF(H54=0,0,(F54-H54)/H54) -> 0
D55: =IF(C55=0,0,C55/B55) -> 0 | E55: =IF(F55=0,0,(D55-F55)/F55) -> 0 | G55: =IF(H55=0,0,(F55-H55)/H55) -> 0
D56: =IF(C56=0,0,C56/B56) -> 0 | E56: =IF(F56=0,0,(D56-F56)/F56) -> 0 | G56: =IF(H56=0,0,(F56-H56)/H56) -> 0
D57: =IF(C57=0,0,C57/B57) -> 0 | E57: =IF(F57=0,0,(D57-F57)/F57) -> 0 | G57: =IF(H57=0,0,(F57-H57)/H57) -> 0
D58: =IF(C58=0,0,C58/B58) -> 0 | E58: =IF(F58=0,0,(D58-F58)/F58) -> 0 | G58: =IF(H58=0,0,(F58-H58)/H58) -> 0
D59: =IF(C59=0,0,C59/B59) -> 0 | E59: =IF(F59=0,0,(D59-F59)/F59) -> 0 | G59: =IF(H59=0,0,(F59-H59)/H59) -> 0
D60: =IF(C60=0,0,C60/B60) -> 0 | E60: =IF(F60=0,0,(D60-F60)/F60) -> 0 | G60: =IF(H60=0,0,(F60-H60)/H60) -> 0
A61: 审计说明：
A62: 异常原因
A65: 四、审计结论：
A69: 提示：
A70: 1.计算结果可与同行业或以前期间对比。
A71: 2.存货周转天数的含义，就是从原材料购入开始，经过仓储、生产、再仓储到产成品售出那一天，大概是多少天。
A72: 可分别计算不同类别存货的周转率（原材料、半成品、产成品etc）。

Sheet 存货产销量变动分析表F2-19
A1: 致同会计师事务所
A2: 存货产销量变动分析表
A3: =[3]底稿目录!A2 -> 被审计单位： | E3: =[3]底稿目录!A4 -> 编制人： | K3: =[3]底稿目录!A5 -> 编制日期： | O3: 索引号： | P3: =[3]底稿目录!F3 -> F2-19
A4: =[3]底稿目录!A3 -> 截止日：202X年12月31日 | E4: =[3]底稿目录!A6 -> 复核人： | K4: =[3]底稿目录!A7 -> 复核日期： | O4: 页 次：
A5: 一、审计目标：
A6: 1.资产负债表中记录的存货是存在的，且已经记录在恰当的账户中
A7: 2.存货以恰当的金额包括在财务报表中，与之相关的计价或分摊调整已恰当记录，相关披露已得到恰当计量和描述
A8: 二、审计过程：
A9: 1.获取主要库存商品各月产量及原材料消耗量，测算报告期主要产品各月产耗比，与以前年度、可比公司、行业经验值进行比较，分析变动趋势及合理性；
A10: 2.结合存货监盘和对仓库实物账的核对，分析原材料实际投入量是否与财务账面记录一致。
A11: 库存商品各月产量统计
A12: 项目 | B12: 1月 | C12: 2月 | D12: 3月 | E12: 4月 | F12: 5月 | G12: 6月 | H12: 7月 | I12: 8月 | J12: 9月 | K12: 10月 | L12: 11月 | M12: 12月 | N12: 合计 | O12: 上年度 | P12: 变动率
N13: =SUM(B13:M13) -> 0 | P13: =IF(AND(O13=0,N13-O13=0),0,IF(AND(O13=0,N13-O13>0),1,(N13-O13)/O13)) -> 0
N14: =SUM(B14:M14) -> 0 | P14: =IF(AND(O14=0,N14-O14=0),0,IF(AND(O14=0,N14-O14>0),1,(N14-O14)/O14)) -> 0
N15: =SUM(B15:M15) -> 0 | P15: =IF(AND(O15=0,N15-O15=0),0,IF(AND(O15=0,N15-O15>0),1,(N15-O15)/O15)) -> 0
N16: =SUM(B16:M16) -> 0 | P16: =IF(AND(O16=0,N16-O16=0),0,IF(AND(O16=0,N16-O16>0),1,(N16-O16)/O16)) -> 0
N17: =SUM(B17:M17) -> 0 | P17: =IF(AND(O17=0,N17-O17=0),0,IF(AND(O17=0,N17-O17>0),1,(N17-O17)/O17)) -> 0
N18: =SUM(B18:M18) -> 0 | P18: =IF(AND(O18=0,N18-O18=0),0,IF(AND(O18=0,N18-O18>0),1,(N18-O18)/O18)) -> 0
A19: 合计 | B19: =SUM(B13:B18) -> 0 | C19: =SUM(C13:C18) -> 0 | D19: =SUM(D13:D18) -> 0 | E19: =SUM(E13:E18) -> 0 | F19: =SUM(F13:F18) -> 0 | G19: =SUM(G13:G18) -> 0 | H19: =SUM(H13:H18) -> 0 | I19: =SUM(I13:I18) -> 0 | ... M19: =SUM(M13:M18) -> 0 | N19: =SUM(B19:M19) -> 0 | O19: =SUM(C19:N19) -> 0 | P19: =IF(AND(O19=0,N19-O19=0),0,IF(AND(O19=0,N19-O19>0),1,(N19-O19)/O19)) -> 0
A20: 库存商品各月销售数量统计
A21: 项目 | B21: 1月 | C21: 2月 | D21: 3月 | E21: 4月 | F21: 5月 | G21: 6月 | H21: 7月 | I21: 8月 | J21: 9月 | K21: 10月 | L21: 11月 | M21: 12月 | N21: 合计 | O21: 上年度 | P21: 变动率
A22: =A13 -> 0 | N22: =SUM(B22:M22) -> 0 | P22: =IF(AND(O22=0,N22-O22=0),0,IF(AND(O22=0,N22-O22>0),1,(N22-O22)/O22)) -> 0
A23: =A14 -> 0 | N23: =SUM(B23:M23) -> 0 | P23: =IF(AND(O23=0,N23-O23=0),0,IF(AND(O23=0,N23-O23>0),1,(N23-O23)/O23)) -> 0
A24: =A15 -> 0 | N24: =SUM(B24:M24) -> 0 | P24: =IF(AND(O24=0,N24-O24=0),0,IF(AND(O24=0,N24-O24>0),1,(N24-O24)/O24)) -> 0
A25: =A16 -> 0 | N25: =SUM(B25:M25) -> 0 | P25: =IF(AND(O25=0,N25-O25=0),0,IF(AND(O25=0,N25-O25>0),1,(N25-O25)/O25)) -> 0
A26: =A17 -> 0 | N26: =SUM(B26:M26) -> 0 | P26: =IF(AND(O26=0,N26-O26=0),0,IF(AND(O26=0,N26-O26>0),1,(N26-O26)/O26)) -> 0
A27: =A18 -> 0 | N27: =SUM(B27:M27) -> 0 | P27: =IF(AND(O27=0,N27-O27=0),0,IF(AND(O27=0,N27-O27>0),1,(N27-O27)/O27)) -> 0
A28: 合计 | B28: =SUM(B22:B27) -> 0 | C28: =SUM(C22:C27) -> 0 | D28: =SUM(D22:D27) -> 0 | E28: =SUM(E22:E27) -> 0 | F28: =SUM(F22:F27) -> 0 | G28: =SUM(G22:G27) -> 0 | H28: =SUM(H22:H27) -> 0 | I28: =SUM(I22:I27) -> 0 | ... M28: =SUM(M22:M27) -> 0 | N28: =SUM(B28:M28) -> 0 | O28: =SUM(C28:N28) -> 0 | P28: =IF(AND(O28=0,N28-O28=0),0,IF(AND(O28=0,N28-O28>0),1,(N28-O28)/O28)) -> 0
A29: 库存商品各月销售量与产量占比分析
A30: 项目 | B30: 1月 | C30: 2月 | D30: 3月 | E30: 4月 | F30: 5月 | G30: 6月 | H30: 7月 | I30: 8月 | J30: 9月 | K30: 10月 | L30: 11月 | M30: 12月 | N30: 合计 | O30: 上年度 | P30: 变动率
A31: =A13 -> 0 | B31: =IF(B13=0,0,B22/B13) -> 0 | C31: =IF(C13=0,0,C22/C13) -> 0 | D31: =IF(D13=0,0,D22/D13) -> 0 | E31: =IF(E13=0,0,E22/E13) -> 0 | F31: =IF(F13=0,0,F22/F13) -> 0 | G31: =IF(G13=0,0,G22/G13) -> 0 | H31: =IF(H13=0,0,H22/H13) -> 0 | I31: =IF(I13=0,0,I22/I13) -> 0 | ... O31: =IF(O13=0,0,O22/O13) -> 0 | P31: =IF(AND(O31=0,N31-O31=0),0,IF(AND(O31=0,N31-O31>0),1,(N31-O31)/O31)) -> 0
A32: =A14 -> 0 | B32: =IF(B14=0,0,B23/B14) -> 0 | C32: =IF(C14=0,0,C23/C14) -> 0 | D32: =IF(D14=0,0,D23/D14) -> 0 | E32: =IF(E14=0,0,E23/E14) -> 0 | F32: =IF(F14=0,0,F23/F14) -> 0 | G32: =IF(G14=0,0,G23/G14) -> 0 | H32: =IF(H14=0,0,H23/H14) -> 0 | I32: =IF(I14=0,0,I23/I14) -> 0 | ... O32: =IF(O14=0,0,O23/O14) -> 0 | P32: =IF(AND(O32=0,N32-O32=0),0,IF(AND(O32=0,N32-O32>0),1,(N32-O32)/O32)) -> 0
A33: =A15 -> 0 | B33: =IF(B15=0,0,B24/B15) -> 0 | C33: =IF(C15=0,0,C24/C15) -> 0 | D33: =IF(D15=0,0,D24/D15) -> 0 | E33: =IF(E15=0,0,E24/E15) -> 0 | F33: =IF(F15=0,0,F24/F15) -> 0 | G33: =IF(G15=0,0,G24/G15) -> 0 | H33: =IF(H15=0,0,H24/H15) -> 0 | I33: =IF(I15=0,0,I24/I15) -> 0 | ... O33: =IF(O15=0,0,O24/O15) -> 0 | P33: =IF(AND(O33=0,N33-O33=0),0,IF(AND(O33=0,N33-O33>0),1,(N33-O33)/O33)) -> 0
A34: =A16 -> 0 | B34: =IF(B16=0,0,B25/B16) -> 0 | C34: =IF(C16=0,0,C25/C16) -> 0 | D34: =IF(D16=0,0,D25/D16) -> 0 | E34: =IF(E16=0,0,E25/E16) -> 0 | F34: =IF(F16=0,0,F25/F16) -> 0 | G34: =IF(G16=0,0,G25/G16) -> 0 | H34: =IF(H16=0,0,H25/H16) -> 0 | I34: =IF(I16=0,0,I25/I16) -> 0 | ... O34: =IF(O16=0,0,O25/O16) -> 0 | P34: =IF(AND(O34=0,N34-O34=0),0,IF(AND(O34=0,N34-O34>0),1,(N34-O34)/O34)) -> 0
A35: =A17 -> 0 | B35: =IF(B17=0,0,B26/B17) -> 0 | C35: =IF(C17=0,0,C26/C17) -> 0 | D35: =IF(D17=0,0,D26/D17) -> 0 | E35: =IF(E17=0,0,E26/E17) -> 0 | F35: =IF(F17=0,0,F26/F17) -> 0 | G35: =IF(G17=0,0,G26/G17) -> 0 | H35: =IF(H17=0,0,H26/H17) -> 0 | I35: =IF(I17=0,0,I26/I17) -> 0 | ... O35: =IF(O17=0,0,O26/O17) -> 0 | P35: =IF(AND(O35=0,N35-O35=0),0,IF(AND(O35=0,N35-O35>0),1,(N35-O35)/O35)) -> 0
A36: =A18 -> 0 | B36: =IF(B18=0,0,B27/B18) -> 0 | C36: =IF(C18=0,0,C27/C18) -> 0 | D36: =IF(D18=0,0,D27/D18) -> 0 | E36: =IF(E18=0,0,E27/E18) -> 0 | F36: =IF(F18=0,0,F27/F18) -> 0 | G36: =IF(G18=0,0,G27/G18) -> 0 | H36: =IF(H18=0,0,H27/H18) -> 0 | I36: =IF(I18=0,0,I27/I18) -> 0 | ... O36: =IF(O18=0,0,O27/O18) -> 0 | P36: =IF(AND(O36=0,N36-O36=0),0,IF(AND(O36=0,N36-O36>0),1,(N36-O36)/O36)) -> 0
A37: 合计 | B37: =IF(B19=0,0,B28/B19) -> 0 | C37: =IF(C19=0,0,C28/C19) -> 0 | D37: =IF(D19=0,0,D28/D19) -> 0 | E37: =IF(E19=0,0,E28/E19) -> 0 | F37: =IF(F19=0,0,F28/F19) -> 0 | G37: =IF(G19=0,0,G28/G19) -> 0 | H37: =IF(H19=0,0,H28/H19) -> 0 | I37: =IF(I19=0,0,I28/I19) -> 0 | ... O37: =IF(O19=0,0,O28/O19) -> 0 | P37: =IF(AND(O37=0,N37-O37=0),0,IF(AND(O37=0,N37-O37>0),1,(N37-O37)/O37)) -> 0
A38: 原材料各月采购统计
A39: 项目 | B39: 1月 | C39: 2月 | D39: 3月 | E39: 4月 | F39: 5月 | G39: 6月 | H39: 7月 | I39: 8月 | J39: 9月 | K39: 10月 | L39: 11月 | M39: 12月 | N39: 合计 | O39: 上年度 | P39: 变动率
A40: =A13 -> 0 | N40: =SUM(B40:M40) -> 0 | P40: =IF(AND(O40=0,N40-O40=0),0,IF(AND(O40=0,N40-O40>0),1,(N40-O40)/O40)) -> 0
A41: =A14 -> 0 | N41: =SUM(B41:M41) -> 0 | P41: =IF(AND(O41=0,N41-O41=0),0,IF(AND(O41=0,N41-O41>0),1,(N41-O41)/O41)) -> 0
A42: =A15 -> 0 | N42: =SUM(B42:M42) -> 0 | P42: =IF(AND(O42=0,N42-O42=0),0,IF(AND(O42=0,N42-O42>0),1,(N42-O42)/O42)) -> 0
A43: =A16 -> 0 | N43: =SUM(B43:M43) -> 0 | P43: =IF(AND(O43=0,N43-O43=0),0,IF(AND(O43=0,N43-O43>0),1,(N43-O43)/O43)) -> 0
A44: =A17 -> 0 | N44: =SUM(B44:M44) -> 0 | P44: =IF(AND(O44=0,N44-O44=0),0,IF(AND(O44=0,N44-O44>0),1,(N44-O44)/O44)) -> 0
A45: =A18 -> 0 | N45: =SUM(B45:M45) -> 0 | P45: =IF(AND(O45=0,N45-O45=0),0,IF(AND(O45=0,N45-O45>0),1,(N45-O45)/O45)) -> 0
A46: 合计 | B46: =SUM(B40:B45) -> 0 | C46: =SUM(C40:C45) -> 0 | D46: =SUM(D40:D45) -> 0 | E46: =SUM(E40:E45) -> 0 | F46: =SUM(F40:F45) -> 0 | G46: =SUM(G40:G45) -> 0 | H46: =SUM(H40:H45) -> 0 | I46: =SUM(I40:I45) -> 0 | ... M46: =SUM(M40:M45) -> 0 | N46: =SUM(B46:M46) -> 0 | O46: =SUM(C46:N46) -> 0 | P46: =IF(AND(O46=0,N46-O46=0),0,IF(AND(O46=0,N46-O46>0),1,(N46-O46)/O46)) -> 0
A47: 原材料各月耗用统计
A48: 项目 | B48: 1月 | C48: 2月 | D48: 3月 | E48: 4月 | F48: 5月 | G48: 6月 | H48: 7月 | I48: 8月 | J48: 9月 | K48: 10月 | L48: 11月 | M48: 12月 | N48: 合计 | O48: 上年度 | P48: 变动率
A49: =A13 -> 0 | N49: =SUM(B49:M49) -> 0 | P49: =IF(AND(O49=0,N49-O49=0),0,IF(AND(O49=0,N49-O49>0),1,(N49-O49)/O49)) -> 0
A50: =A14 -> 0 | N50: =SUM(B50:M50) -> 0 | P50: =IF(AND(O50=0,N50-O50=0),0,IF(AND(O50=0,N50-O50>0),1,(N50-O50)/O50)) -> 0
A51: =A15 -> 0 | N51: =SUM(B51:M51) -> 0 | P51: =IF(AND(O51=0,N51-O51=0),0,IF(AND(O51=0,N51-O51>0),1,(N51-O51)/O51)) -> 0
A52: =A16 -> 0 | N52: =SUM(B52:M52) -> 0 | P52: =IF(AND(O52=0,N52-O52=0),0,IF(AND(O52=0,N52-O52>0),1,(N52-O52)/O52)) -> 0
A53: =A17 -> 0 | N53: =SUM(B53:M53) -> 0 | P53: =IF(AND(O53=0,N53-O53=0),0,IF(AND(O53=0,N53-O53>0),1,(N53-O53)/O53)) -> 0
A54: =A18 -> 0 | N54: =SUM(B54:M54) -> 0 | P54: =IF(AND(O54=0,N54-O54=0),0,IF(AND(O54=0,N54-O54>0),1,(N54-O54)/O54)) -> 0
A55: 合计 | B55: =SUM(B49:B54) -> 0 | C55: =SUM(C49:C54) -> 0 | D55: =SUM(D49:D54) -> 0 | E55: =SUM(E49:E54) -> 0 | F55: =SUM(F49:F54) -> 0 | G55: =SUM(G49:G54) -> 0 | H55: =SUM(H49:H54) -> 0 | I55: =SUM(I49:I54) -> 0 | ... M55: =SUM(M49:M54) -> 0 | N55: =SUM(B55:M55) -> 0 | O55: =SUM(C55:N55) -> 0 | P55: =IF(AND(O55=0,N55-O55=0),0,IF(AND(O55=0,N55-O55>0),1,(N55-O55)/O55)) -> 0
A56: 原材料采购库存商品产量比
A57: 项目 | B57: 1月 | C57: 2月 | D57: 3月 | E57: 4月 | F57: 5月 | G57: 6月 | H57: 7月 | I57: 8月 | J57: 9月 | K57: 10月 | L57: 11月 | M57: 12月 | N57: 合计 | O57: 上年度 | P57: 变动率
A58: =A13 -> 0 | B58: =IF(B40=0,0,B40/B13) -> 0 | C58: =IF(C40=0,0,C40/C13) -> 0 | D58: =IF(D40=0,0,D40/D13) -> 0 | E58: =IF(E40=0,0,E40/E13) -> 0 | F58: =IF(F40=0,0,F40/F13) -> 0 | G58: =IF(G40=0,0,G40/G13) -> 0 | H58: =IF(H40=0,0,H40/H13) -> 0 | I58: =IF(I40=0,0,I40/I13) -> 0 | ... O58: =IF(O40=0,0,O40/O13) -> 0 | P58: =IF(AND(O58=0,N58-O58=0),0,IF(AND(O58=0,N58-O58>0),1,(N58-O58)/O58)) -> 0 | Q58: 对波动异常的产品应进一步执行舞弊应对程序中的产品生产成本及单耗分析<F2-64>
A59: =A14 -> 0 | B59: =IF(B41=0,0,B41/B14) -> 0 | C59: =IF(C41=0,0,C41/C14) -> 0 | D59: =IF(D41=0,0,D41/D14) -> 0 | E59: =IF(E41=0,0,E41/E14) -> 0 | F59: =IF(F41=0,0,F41/F14) -> 0 | G59: =IF(G41=0,0,G41/G14) -> 0 | H59: =IF(H41=0,0,H41/H14) -> 0 | I59: =IF(I41=0,0,I41/I14) -> 0 | ... O59: =IF(O41=0,0,O41/O14) -> 0 | P59: =IF(AND(O59=0,N59-O59=0),0,IF(AND(O59=0,N59-O59>0),1,(N59-O59)/O59)) -> 0
A60: =A15 -> 0 | B60: =IF(B42=0,0,B42/B15) -> 0 | C60: =IF(C42=0,0,C42/C15) -> 0 | D60: =IF(D42=0,0,D42/D15) -> 0 | E60: =IF(E42=0,0,E42/E15) -> 0 | F60: =IF(F42=0,0,F42/F15) -> 0 | G60: =IF(G42=0,0,G42/G15) -> 0 | H60: =IF(H42=0,0,H42/H15) -> 0 | I60: =IF(I42=0,0,I42/I15) -> 0 | ... O60: =IF(O42=0,0,O42/O15) -> 0 | P60: =IF(AND(O60=0,N60-O60=0),0,IF(AND(O60=0,N60-O60>0),1,(N60-O60)/O60)) -> 0
A61: =A16 -> 0 | B61: =IF(B43=0,0,B43/B16) -> 0 | D61: =IF(D43=0,0,D43/D16) -> 0 | E61: =IF(E43=0,0,E43/E16) -> 0 | F61: =IF(F43=0,0,F43/F16) -> 0 | G61: =IF(G43=0,0,G43/G16) -> 0 | H61: =IF(H43=0,0,H43/H16) -> 0 | I61: =IF(I43=0,0,I43/I16) -> 0 | J61: =IF(J43=0,0,J43/J16) -> 0 | K61: =IF(K43=0,0,K43/K16) -> 0 | ... O61: =IF(O43=0,0,O43/O16) -> 0 | P61: =IF(AND(O61=0,N61-O61=0),0,IF(AND(O61=0,N61-O61>0),1,(N61-O61)/O61)) -> 0
A62: =A17 -> 0 | B62: =IF(B44=0,0,B44/B17) -> 0 | C62: =IF(C44=0,0,C44/C17) -> 0 | D62: =IF(D44=0,0,D44/D17) -> 0 | E62: =IF(E44=0,0,E44/E17) -> 0 | F62: =IF(F44=0,0,F44/F17) -> 0 | G62: =IF(G44=0,0,G44/G17) -> 0 | H62: =IF(H44=0,0,H44/H17) -> 0 | I62: =IF(I44=0,0,I44/I17) -> 0 | ... O62: =IF(O44=0,0,O44/O17) -> 0 | P62: =IF(AND(O62=0,N62-O62=0),0,IF(AND(O62=0,N62-O62>0),1,(N62-O62)/O62)) -> 0
A63: =A18 -> 0 | B63: =IF(B45=0,0,B45/B18) -> 0 | C63: =IF(C45=0,0,C45/C18) -> 0 | D63: =IF(D45=0,0,D45/D18) -> 0 | E63: =IF(E45=0,0,E45/E18) -> 0 | F63: =IF(F45=0,0,F45/F18) -> 0 | G63: =IF(G45=0,0,G45/G18) -> 0 | H63: =IF(H45=0,0,H45/H18) -> 0 | I63: =IF(I45=0,0,I45/I18) -> 0 | ... O63: =IF(O45=0,0,O45/O18) -> 0 | P63: =IF(AND(O63=0,N63-O63=0),0,IF(AND(O63=0,N63-O63>0),1,(N63-O63)/O63)) -> 0
A64: 合计 | B64: =IF(B46=0,0,B46/B19) -> 0 | C64: =IF(C46=0,0,C46/C19) -> 0 | D64: =IF(D46=0,0,D46/D19) -> 0 | E64: =IF(E46=0,0,E46/E19) -> 0 | F64: =IF(F46=0,0,F46/F19) -> 0 | G64: =IF(G46=0,0,G46/G19) -> 0 | H64: =IF(H46=0,0,H46/H19) -> 0 | I64: =IF(I46=0,0,I46/I19) -> 0 | ... O64: =IF(O46=0,0,O46/O19) -> 0 | P64: =IF(AND(O64=0,N64-O64=0),0,IF(AND(O64=0,N64-O64>0),1,(N64-O64)/O64)) -> 0
A65: 产耗比
A66: 项目 | B66: 1月 | C66: 2月 | D66: 3月 | E66: 4月 | F66: 5月 | G66: 6月 | H66: 7月 | I66: 8月 | J66: 9月 | K66: 10月 | L66: 11月 | M66: 12月 | N66: 合计 | O66: 上年度 | P66: 变动率
A67: =A13 -> 0 | B67: =IF(B49=0,0,B13/B49) -> 0 | C67: =IF(C49=0,0,C13/C49) -> 0 | D67: =IF(D49=0,0,D13/D49) -> 0 | E67: =IF(E49=0,0,E13/E49) -> 0 | F67: =IF(F49=0,0,F13/F49) -> 0 | G67: =IF(G49=0,0,G13/G49) -> 0 | H67: =IF(H49=0,0,H13/H49) -> 0 | I67: =IF(I49=0,0,I13/I49) -> 0 | ... O67: =IF(O49=0,0,O13/O49) -> 0 | P67: =IF(AND(O67=0,N67-O67=0),0,IF(AND(O67=0,N67-O67>0),1,(N67-O67)/O67)) -> 0 | Q67: 对波动异常的产品应进一步执行舞弊应对程序中的产品生产成本及单耗分析<F2-64>
A68: =A14 -> 0 | B68: =IF(B50=0,0,B14/B50) -> 0 | C68: =IF(C50=0,0,C14/C50) -> 0 | D68: =IF(D50=0,0,D14/D50) -> 0 | E68: =IF(E50=0,0,E14/E50) -> 0 | F68: =IF(F50=0,0,F14/F50) -> 0 | G68: =IF(G50=0,0,G14/G50) -> 0 | H68: =IF(H50=0,0,H14/H50) -> 0 | I68: =IF(I50=0,0,I14/I50) -> 0 | ... O68: =IF(O50=0,0,O14/O50) -> 0 | P68: =IF(AND(O68=0,N68-O68=0),0,IF(AND(O68=0,N68-O68>0),1,(N68-O68)/O68)) -> 0
A69: =A15 -> 0 | B69: =IF(B51=0,0,B15/B51) -> 0 | C69: =IF(C51=0,0,C15/C51) -> 0 | D69: =IF(D51=0,0,D15/D51) -> 0 | E69: =IF(E51=0,0,E15/E51) -> 0 | F69: =IF(F51=0,0,F15/F51) -> 0 | G69: =IF(G51=0,0,G15/G51) -> 0 | H69: =IF(H51=0,0,H15/H51) -> 0 | I69: =IF(I51=0,0,I15/I51) -> 0 | ... O69: =IF(O51=0,0,O15/O51) -> 0 | P69: =IF(AND(O69=0,N69-O69=0),0,IF(AND(O69=0,N69-O69>0),1,(N69-O69)/O69)) -> 0
A70: =A16 -> 0 | B70: =IF(B52=0,0,B16/B52) -> 0 | C70: =IF(C52=0,0,C16/C52) -> 0 | D70: =IF(D52=0,0,D16/D52) -> 0 | E70: =IF(E52=0,0,E16/E52) -> 0 | F70: =IF(F52=0,0,F16/F52) -> 0 | G70: =IF(G52=0,0,G16/G52) -> 0 | H70: =IF(H52=0,0,H16/H52) -> 0 | I70: =IF(I52=0,0,I16/I52) -> 0 | ... O70: =IF(O52=0,0,O16/O52) -> 0 | P70: =IF(AND(O70=0,N70-O70=0),0,IF(AND(O70=0,N70-O70>0),1,(N70-O70)/O70)) -> 0
A71: =A17 -> 0 | B71: =IF(B53=0,0,B17/B53) -> 0 | C71: =IF(C53=0,0,C17/C53) -> 0 | D71: =IF(D53=0,0,D17/D53) -> 0 | E71: =IF(E53=0,0,E17/E53) -> 0 | F71: =IF(F53=0,0,F17/F53) -> 0 | G71: =IF(G53=0,0,G17/G53) -> 0 | H71: =IF(H53=0,0,H17/H53) -> 0 | I71: =IF(I53=0,0,I17/I53) -> 0 | ... O71: =IF(O53=0,0,O17/O53) -> 0 | P71: =IF(AND(O71=0,N71-O71=0),0,IF(AND(O71=0,N71-O71>0),1,(N71-O71)/O71)) -> 0
A72: =A18 -> 0 | B72: =IF(B54=0,0,B18/B54) -> 0 | C72: =IF(C54=0,0,C18/C54) -> 0 | D72: =IF(D54=0,0,D18/D54) -> 0 | E72: =IF(E54=0,0,E18/E54) -> 0 | F72: =IF(F54=0,0,F18/F54) -> 0 | G72: =IF(G54=0,0,G18/G54) -> 0 | H72: =IF(H54=0,0,H18/H54) -> 0 | I72: =IF(I54=0,0,I18/I54) -> 0 | ... O72: =IF(O54=0,0,O18/O54) -> 0 | P72: =IF(AND(O72=0,N72-O72=0),0,IF(AND(O72=0,N72-O72>0),1,(N72-O72)/O72)) -> 0
A73: 合计 | B73: =IF(B55=0,0,B19/B55) -> 0 | C73: =IF(C55=0,0,C19/C55) -> 0 | D73: =IF(D55=0,0,D19/D55) -> 0 | E73: =IF(E55=0,0,E19/E55) -> 0 | F73: =IF(F55=0,0,F19/F55) -> 0 | G73: =IF(G55=0,0,G19/G55) -> 0 | H73: =IF(H55=0,0,H19/H55) -> 0 | I73: =IF(I55=0,0,I19/I55) -> 0 | ... O73: =IF(O55=0,0,O19/O55) -> 0 | P73: =IF(AND(O73=0,N73-O73=0),0,IF(AND(O73=0,N73-O73>0),1,(N73-O73)/O73)) -> 0
A74: 三、审计说明
A75: 1.库存商品—***月产量变动异常的原因：
A76: 2.库存商品—**本年与上年相比变动较大的原因：
A77: 3.原材料—**本年与上年相比变动较大的原因：
A78: 4.库存商品—***采购与耗用比变动较大的原因：
A79: 5.产销量、产耗比异常变动的产品进一步进行生产成本及单耗分析见<F2-64>
A80: 四、审计结论
A84: 编制说明：
A85: 1、上述主要产品产耗比测算表假定一种库存商品仅耗用一种原料的情形；
A86: 2、如果耗用多种主要原料或耗用的主要原料计量单位不统一，请适当修改产耗比的测算过程。

Sheet 产品年度成本比较分析F2-20
A1: 致同会计师事务所
A2: 产成品单位成本年度比较分析表
A3: =[3]底稿目录!A2 -> 被审计单位： | F3: =[3]底稿目录!A4 -> 编制人： | L3: =[3]底稿目录!A5 -> 编制日期： | Q3: 索引号： | R3: =[3]底稿目录!F4 -> F2-20
A4: =[3]底稿目录!A3 -> 截止日：202X年12月31日 | F4: =[3]底稿目录!A6 -> 复核人： | L4: =[3]底稿目录!A7 -> 复核日期： | Q4: 页次：
A5: 产成品名称 | B5: 本年单位成本 | G5: 上年单位成本 | L5: 波动比例 | Q5: 是否存在异常波动 | R5: 进一步审验底稿索引
B6: 直接材料 | C6: 直接人工 | D6: 制造费用 | F6: 合计 | G6: 直接材料 | H6: 直接人工 | I6: 制造费用 | K6: 合计 | L6: 直接材料 | M6: 直接人工 | N6: 制造费用 | P6: 合计
F7: =SUM(B7:E7) -> 0 | K7: =SUM(G7:J7) -> 0 | L7: =IF(G7=0,0,(B7-G7)/G7) -> 0 | M7: =IF(H7=0,0,(C7-H7)/H7) -> 0 | N7: =IF(I7=0,0,(D7-I7)/I7) -> 0 | O7: =IF(J7=0,0,(E7-J7)/J7) -> 0 | P7: =IF(K7=0,0,(F7-K7)/K7) -> 0 | S7: 对波动异常的产品应进一步执行舞弊应对程序中原材料采购价格分析<F2-61>、产品生产成本及单耗分析<F2-64>
F8: =SUM(B8:E8) -> 0 | K8: =SUM(G8:J8) -> 0 | L8: =IF(G8=0,0,(B8-G8)/G8) -> 0 | M8: =IF(H8=0,0,(C8-H8)/H8) -> 0 | N8: =IF(I8=0,0,(D8-I8)/I8) -> 0 | O8: =IF(J8=0,0,(E8-J8)/J8) -> 0 | P8: =IF(K8=0,0,(F8-K8)/K8) -> 0
F9: =SUM(B9:E9) -> 0 | K9: =SUM(G9:J9) -> 0 | L9: =IF(G9=0,0,(B9-G9)/G9) -> 0 | M9: =IF(H9=0,0,(C9-H9)/H9) -> 0 | N9: =IF(I9=0,0,(D9-I9)/I9) -> 0 | O9: =IF(J9=0,0,(E9-J9)/J9) -> 0 | P9: =IF(K9=0,0,(F9-K9)/K9) -> 0
F10: =SUM(B10:E10) -> 0 | K10: =SUM(G10:J10) -> 0 | L10: =IF(G10=0,0,(B10-G10)/G10) -> 0 | M10: =IF(H10=0,0,(C10-H10)/H10) -> 0 | N10: =IF(I10=0,0,(D10-I10)/I10) -> 0 | O10: =IF(J10=0,0,(E10-J10)/J10) -> 0 | P10: =IF(K10=0,0,(F10-K10)/K10) -> 0
F11: =SUM(B11:E11) -> 0 | K11: =SUM(G11:J11) -> 0 | L11: =IF(G11=0,0,(B11-G11)/G11) -> 0 | M11: =IF(H11=0,0,(C11-H11)/H11) -> 0 | N11: =IF(I11=0,0,(D11-I11)/I11) -> 0 | O11: =IF(J11=0,0,(E11-J11)/J11) -> 0 | P11: =IF(K11=0,0,(F11-K11)/K11) -> 0
F12: =SUM(B12:E12) -> 0 | K12: =SUM(G12:J12) -> 0 | L12: =IF(G12=0,0,(B12-G12)/G12) -> 0 | M12: =IF(H12=0,0,(C12-H12)/H12) -> 0 | N12: =IF(I12=0,0,(D12-I12)/I12) -> 0 | O12: =IF(J12=0,0,(E12-J12)/J12) -> 0 | P12: =IF(K12=0,0,(F12-K12)/K12) -> 0
F13: =SUM(B13:E13) -> 0 | K13: =SUM(G13:J13) -> 0 | L13: =IF(G13=0,0,(B13-G13)/G13) -> 0 | M13: =IF(H13=0,0,(C13-H13)/H13) -> 0 | N13: =IF(I13=0,0,(D13-I13)/I13) -> 0 | O13: =IF(J13=0,0,(E13-J13)/J13) -> 0 | P13: =IF(K13=0,0,(F13-K13)/K13) -> 0
F14: =SUM(B14:E14) -> 0 | K14: =SUM(G14:J14) -> 0 | L14: =IF(G14=0,0,(B14-G14)/G14) -> 0 | M14: =IF(H14=0,0,(C14-H14)/H14) -> 0 | N14: =IF(I14=0,0,(D14-I14)/I14) -> 0 | O14: =IF(J14=0,0,(E14-J14)/J14) -> 0 | P14: =IF(K14=0,0,(F14-K14)/K14) -> 0
F15: =SUM(B15:E15) -> 0 | K15: =SUM(G15:J15) -> 0 | L15: =IF(G15=0,0,(B15-G15)/G15) -> 0 | M15: =IF(H15=0,0,(C15-H15)/H15) -> 0 | N15: =IF(I15=0,0,(D15-I15)/I15) -> 0 | O15: =IF(J15=0,0,(E15-J15)/J15) -> 0 | P15: =IF(K15=0,0,(F15-K15)/K15) -> 0
F16: =SUM(B16:E16) -> 0 | K16: =SUM(G16:J16) -> 0 | L16: =IF(G16=0,0,(B16-G16)/G16) -> 0 | M16: =IF(H16=0,0,(C16-H16)/H16) -> 0 | N16: =IF(I16=0,0,(D16-I16)/I16) -> 0 | O16: =IF(J16=0,0,(E16-J16)/J16) -> 0 | P16: =IF(K16=0,0,(F16-K16)/K16) -> 0
A18: 审计说明：
A19: 1.XX产品单位成本异常波动原因： 对XX产品进一步进行生产成本及单耗分析见<F2-64>
A20: 2.原材料采购价格进一步分析见<F2-61>
A22: 审计结论：

Sheet 底稿目录 (3)
A1: 底稿开列时，可先在以下单元格填写有关内容，以便其他底稿引用有关数据： | D1: 序号 | E1: 内容 | F1: 索引号
A2: 被审计单位： | D2: 1 | E2: 存货监盘程序表 | F2: F2-21A
A3: 截止日：202X年12月31日 | D3: 2 | E3: 存货盘点计划问卷 | F3: F2-21
A4: 编制人： | D4: 3 | E4: 存货监盘计划 | F4: F2-22
A5: 编制日期： | D5: 4 | E5: 存货监盘小结 | F5: F2-23
A6: 复核人： | D6: 5 | E6: 存货账面余额与仓储台账（ERP业务数据)核对记录 | F6: F2-24
A7: 复核日期： | D7: 6 | E7: 存货抽盘结果汇总表 | F7: F2-25
D8: 7 | E8: 存货盘点倒轧表 | F8: F2-26

Sheet 存货监盘程序表F2-21A
A1: 致同会计师事务所
A2: 存货监盘程序表
A3: =[4]底稿目录!A2 -> 被审计单位： | C3: =[4]底稿目录!A4 -> 编制人： | D3: =[4]底稿目录!A5 -> 编制日期： | E3: 索引号： | F3: =[4]底稿目录!F2 -> F2-21A
A4: =[4]底稿目录!A3 -> 截止日：202X年12月31日 | C4: =[4]底稿目录!A6 -> 复核人： | D4: =[4]底稿目录!A7 -> 复核日期： | E4: 页 次：
A5: 序号 | B5: 审计程序 | D5: 程序分类 | E5: 底稿索引号 | G5: 根据被审计单位实际情况和风险评估情况裁剪、修改或增加审计程序
A6: （一） | B6: 了解存货形态、取得存货存放地点清单等，确定是否实地监盘存货，并考虑： （1）存货存放地点、所有地点同时进行、在期末或接近期末执行监盘； （2）以不可预见的时间和方式进行，对特殊形态的存货是否利用专家工作。 | D6: 常规★
A7: （二） | B7: 评价被审计单位存货盘点内部控制、程序和指令，完成盘点计划调查问卷 | D7: 常规★ | E7: F2-21
A8: 1 | B8: 根据被审计单位的存货盘存制度和相关内部控制的有效性，与管理层讨论评价盘点时间是否合理： （1）盘点日是否与资产负债表一致，如果盘点日和资产负债表日不一致，评价对内部控制的信赖能否将盘点日的结论延伸至资产负债表日； （2）所有重要存货均列入盘点范围（包括在异地存放的重要存货）、不同地点存货是否同时盘点； | D8: 常规★
A9: 2 | B9: 获取被审计单位加盖公司印鉴的完整仓库清单或存货存放地点清单（包括期末库存量为零的仓库、租赁的仓库，以及第三方代被审计单位保管存货的仓库等）及按存放地点分类的存货明细表，结合询问、与前期仓库变动情况、存货出入库单中的仓库、支付的仓储租金、固定资产中仓库建筑物分析是否存在遗漏的仓库、遗漏存货存放地点。 | D9: 常规★
A10: 3 | B10: 获取被审计单位存货盘点计划及其他用以记录和控制存货盘点结果的指令和程序，与管理层讨论： （1）在盘点过程中是否存在无法停止移动的存货，所采取的控制程序和对存货收发截止影响的考虑； （2）盘点的计量工具和计量方法，对于盘点有困难的特殊存货，盘点方法的可行性和科学性，是否有专家参与盘点； （3）出入库单等与存货相关的单据是否连续编号，如何控制存货的完整性和截止性等。 | D10: 常规★
A11: 4 | B11: 与管理层讨论以前年度存货存在的问题以及目前存货的状况。 | D11: 常规★
A12: 5 | B12: 评价被审计单位的盘点计划是否恰当、是否存在缺陷。 | D12: 常规★
A13: （三） | B13: 编制存货监盘计划 | D13: 常规★ | E13: F2-22
A14: 1 | B14: 在获取完整的存货存放地点清单的基础上，根据不同地点所存放存货的重要性以及对各个地点与存货相关的重大错报风险的评估结果，选择适当的地点进行监盘，并记录选择这些地点的原因。在连续审计中，可考虑在不同期间的审计中变更所选择实施监盘的地点。 | D14: 常规★
A15: 2 | B15: 取得被审计单位永续盘存纪录（盘点表），选择对总体中特定项目（金额重大、性质特殊）全部进行抽盘，剩余部分可采用抽样的方式选择抽盘样本。 | D15: 常规★
A16: 3 | B16: 根据了解的被审计单位存货的形态及特点，制定存货监盘计划（考虑前期存货监盘对本期监盘的影响、前期监盘遇到的重大问题及存货监盘的改善建议、风险评估结果、特别风险、同时进行、具有不可预见性和针对性），并将计划传达给参与监盘的项目组成员，以明确监盘时间、监盘范围、监盘方式、抽盘范围、参与人员及分工等事项。 | D16: 常规★
A17: 4 | B17: 判断内部审计部门在盘点中的参与程度，考虑内部审计人员已执行或拟执行的特定工作的性质和范围、重大错报风险、专业胜任能力、客观性，以及是否利用内部审计的工作。 | D17: 备选
A18: 5 | B18: 如果管理层不允许在同一时间对所有存放地点的存货实施监盘，关注可能存在管理层操纵转移不同地点的存货以虚增或虚减存货的舞弊风险。 | D18: IPO/上市/新三板/重组/舞弊应对
A19: （四） | B19: 观察管理层制定的盘点程序的执行情况，并检查存货并检查存货的状况，是否存在过时、毁损或陈旧的存货； | D19: 常规★ | E19: F2-
A20: 1 | B20: 在被审计单位盘点存货前，观察盘点现场： （1）确定应纳入盘点范围的存货是否已经适当整理和排列，是否存在已经销售但仍存放在公司仓库或未确认收入已由客户代管的存货； （2）存货是否附有盘点标识/标签/编号，是否存在重复、是否有未纳入盘点范围的存货以及未纳入的原因； （3）存货是否已经停止流动，如未停止流动，如何对在不同存放地点之间的流动以及出入库情况进行控制。 （4）是否已经恰当区分所有毁损、陈旧、过时及残次的存货； （5）是否对计量用具（地秤、秤量器和其他计量器）进行校验； （6）是否对存货盘点表单的领用实施充分的控制，并通过连续编号确保没有遗漏或重复。 | D20: 常规★ | G20: 根据被审计单位实际情况裁剪程序
A21: 2 | B21: 在被审计单位盘点人员盘点过程中，进行观察： （1）被审计单位的实际盘点是否按照计划进行，盘点过程是否有独立于存货实物管理责任人员以外的人员参与； （2）盘点人员是否是否准确记录了存货实际的数量和状况； （3）是否使用复盘法（对相同的存货执行两次清点）进行盘点，如不是，如何确保所有存货盘点准确； （4）对于特殊类型的存货（如堆积型存货、液体、气体、生物资产等），用于估计数量的方法是否恰当； （5）关注存货发送和验收场所，确定这里的存货是否应包括在盘点范围内； （6）盘点人员是否记录了毁损、陈旧、残次和周转缓慢及可能毁损、陈旧、残次和周转缓慢的存货； （7）已填用、作废及未使用的盘点表单、标识/标签的号码是否完整记录； （8）是否特别关注在产品完工进度、金额重大存货、数量重大存货、可能报废/损毁/陈旧/残次存货、第三方存货、抵质押、所有权证据（如货运单价、商标）等； （9）盘点中发现的问题否是否得到适当的跟进与解决，对盘点结果的改动是否经过适当的授权审批 | D21: 常规★ | G21: 根据被审计单位实际情况裁剪程序
A22: 3 | B22: 已恰当识别所有权不属于被审计单位的存货（如寄售商品），并单独标识和存放，以确保这些存货没有被纳入盘点范围。 | D22: 常规★
A23: 4 | B23: 观察有关存货移动的控制程序是否得到执行，核实在不同地点间转移的库存产品未遗漏和重复。 | D23: 常规★
A24: 5 | B24: 盘点结束后，与适当人员巡回检查仓库，以确定所有的存货已被盘点、未被重复盘点；确定已发放的表单是否均已收回，取得签章的盘点控制文件（如：盘点清单、盘点汇总表、标签控制清单）及盘盈、盘亏处理意见等报告和管理部门的审批文件，并账面核对相符。 | D24: 常规★ | G24: 根据被审计单位实际情况裁剪程序
A25: （五） | B25: 根据监盘计划，执行抽盘，核对盘点结果并编制监盘小结 | D25: 常规★ | E25: F2-23
A26: 1 | B26: 抽查核对被审计单位存货明细账与仓库台账（仓储系统）的盘点日存货结存余额是否一致，不一致的查明原因。 | D26: 常规★ | E26: F2-24
A27: 2 | B27: 结合被审计单位实际盘点是否与计划存货监盘工作时的估计基本一致，如果存在较大差异，考虑修改抽盘范围。 （1）从存货盘点记录中选取项目追查至存货实物，以测试盘点记录的准确性； （2）从存货实物中选取项目追查至存货盘点记录，以测试存货盘点的完整性。 | D27: 常规★ | E27: F2-25
A28: 3 | B28: 对以包装箱等封存的存货，考虑要求打开箱子或挪开成堆的箱子。 | D28: 常规★
A29: 4 | B29: 对计量特殊、质量特征特殊等特殊类型的存货，考虑实施追加的审计程序或利用专家的工作。 | D29: 备选
A30: 5 | B30: 将抽盘结果与被审计单位盘点记录、资产负债表日账面记录核对，当抽盘中发现错报时应查明原因，考虑扩大抽盘范围以及是否应调整错报。 | D30: 常规★ | E30: F2-25
A31: 6 | B31: 如存货盘点日不是资产负债表日，检查盘点日与资产负债表日之间存货的变动是否已作正确的记录，并将抽盘结果进行存货倒轧，结合存货截止测试考虑存货在盘点日和财务报表日的截止是否正确。 | D31: 备选 | E31: F2-26
A32: 7 | B32: 核对存货监盘记录与存货明细账记录 （1）从明细账中选取具有代表性的样本，将明细账上的存货数量与经确认盘点报告的数量核对； （2）从经确认的盘点报告中抽取有代表性的样本，将盘点报告的数量与存货明细账核对。 | D32: 常规★ | E32: F2-25
A33: 8 | B33: 完成存货监盘程序表要求的各项工作，复核监盘结果汇总记录，编制存货监盘报告（监盘小结） | D33: 常规★ | E33: F2-23
A34: （六） | B34: 其他考虑
A35: 1 | B35: 如无法直接参与客户存货盘点的，则应在审计外勤日对被审计单位的存货内部控制的有效性进行评估，并对重要存货项目进行实地盘点，同时在测试有关存货项目资产负债表日至盘点日之间所有增减变动的会计记录的基础上进行存货倒轧。 | D35: 备选
A36: 2 | B36: 如果由第三方保管或控制的存货对财务报表是重要的，考虑现场盘点第三方保管或控制的存货 | D36: 备选
A37: 3 | B37: 如果认为被审计单位的盘点方式及其结果无效，提请被审计单位重新盘点。 | D37: 备选

Sheet 盘点计划问卷F2-21
A1: 致同会计师事务所
A2: 存货盘点计划问卷
A3: =[4]底稿目录!A2 -> 被审计单位： | D3: =[4]底稿目录!A4 -> 编制人： | F3: =[4]底稿目录!A5 -> 编制日期： | H3: 索引号： | I3: =[4]底稿目录!F3 -> F2-21
A4: =[4]底稿目录!A3 -> 截止日：202X年12月31日 | D4: =[4]底稿目录!A6 -> 复核人： | F4: =[4]底稿目录!A7 -> 复核日期： | H4: 页次：
A5: 本调查问卷旨在帮助注册会计师了解和评价被审计单位存货盘点计划。如果被审计单位有盘点的书面说明,本调查问卷也可作为有益的补充。需要说明的是,注册会计师在审计实务中,应当根据被审计单位所处行业的特点、内部控制和会计核算制度等具体情况,对本调查问卷进行修改。存货盘点需审计人员现场亲自监盘，如果因特殊情况需要视频盘点的，应详细说明视频盘点的原因和合理性，并详细记录监盘过程、项目地理位置和坐标信息，核实视频中盘点人员身份，确保视频监盘程序的有效性。 | K5: 提示1：如果被审计单位的存货存放在多个地点，注册会计师可以要求被审计单位提供一份完整的存货存放地点清单（包括期末库存量为零的仓库、租赁的仓库，以及第三方代被审计单位保管存货的仓库等），并考虑其完整性。根据具体情况下的风险评估结果，注册会计师可以考虑执行以下一项或多项审计程序： （1）询问被审计单位除管理层和财务部门以外的其他人员，如营销人员、仓库人员等，以了解有关存货存放地点的情况; （2）比较被审计单位不同时期的存货存放地点清单，关注仓库变动情况，以确定是否存在因仓库变动而未将存货纳入盘点范围的情况发生； （3）检查被审计单位存货的出、入库单，关注是否存在被审计单位尚未告知注册会计师的仓库（如期末库存量为零的仓库）； （4）检查费用支出明细账和租赁合同，关注被审计单位是否租赁仓库并支付租金，如果有，该仓库是否已包括在被审计单位提供的仓库清单中； （5）检查被审计单位“固定资产——房屋建筑物”明细清单，了解被审计单位可用于存放存货的房屋建筑物。
A6: 1.存货盘点的范围、盘点的场所以及盘点时间是如何确定的?填列以下表格。
A7: 地点 | B7: 存货类型 | C7: 占存货总额的大致比例 | D7: 盘点时间
A11: 2．盘点人员是如何组织分工的？是否具有胜任能力？填列以下表格。 | K11: 提示2：如果对存货数量存在舞弊风险，盘点时应考虑： （1）在不预先通知的情况下对特定存放地点的存货实施监盘，或在同一天对所有存放地点实施存货监盘； （2）要求被审计单位在报告期末或临近期末的时点实施存货盘点，如：更严格地检查包装箱中的货物、货物堆放方式（如堆为中空）或标记方式、液态物质（如香水、特殊的化学物质）的质量特征（如纯度、品级或浓度）或利用专家的工作； （3）按照存货的等级或类别、存放地点或其他分类标准，将本期存货数量与前期进行比较，或将盘点数量与永续盘存记录进行比较，如按标签号进行检索以测试存货的标签控制，或按照项目的顺序编号进行整理以检查是否存在漏记或重复编号。
A12: 人员 | B12: 地点 | C12: 职责 | D12: 胜任能力 | E12: 电话
A16: 3.盘点过程是否有专家参加?是否对专家参与盘点作出了适当的安排?
A18: 4.盘点前是否召开会议并布置任务?
A20: 5.在盘点过程中,存货是怎样整理和排列的?
A22: 6.是否存在代销存货等所有权不属于被审计单位的存货?如有,情况如何?
A24: 7.有哪些毁损、陈旧、过时、残次的存货?它们是如何区分和存放的?
A26: 8.半成品、原材料和产成品如何分开?
A28: 9.对于成堆堆放或分散在仓库中的存货,是否设置了专门的盘点程序或数量转换计算的方法?
A30: 10.分散在不同地方的相同存货项目如何汇总(这对于与后续盘点汇总保持一致很重要)?
A32: 11.存货盘点采用什么计量工具和计量方法?
A34: 12.在产品的完工程度如何确认?原材料、直接人工、制造费用等如何在产成品和在产品之间分配?
A36: 13.是否有存放在外单位的存货?如何进行盘点?
A38: 14.放在距离较远的地方的存货如何盘点?
... A58: 22.2盘点计划是否存在缺陷?如是,应建议被审计单位调整。

Sheet 监盘计划F2-22
B3: 存货监盘计划

Sheet 监盘小结F2-23
B3: 存货监盘小结

Sheet 存货账面余额与仓储台账（ERP业务数据)核对记录F2-24
A1: 致同会计师事务所
A2: 存货账面余额与仓储台账（ERP业务数据)核对记录
A3: =[4]底稿目录!A2 -> 被审计单位： | D3: =[4]底稿目录!A4 -> 编制人： | F3: =[4]底稿目录!A5 -> 编制日期： | H3: 索引号： | I3: =[4]底稿目录!F6 -> F2-24
A4: =[4]底稿目录!A3 -> 截止日：202X年12月31日 | D4: =[4]底稿目录!A6 -> 复核人： | F4: =[4]底稿目录!A7 -> 复核日期： | H4: 页 次：
A5: 一、资产负债表日存货账面余额与仓储台账（ERP业务数据)核对记录
A6: 提示1：结合存货常规程序：抽查核对存货收发存明细账是否与仓储台账（ERP业务数据）、卡片记录相符（双向核对）一致
A7: 提示2：如果数据量大可结合IT审计完成核对
A14: 二、盘点日存货账面余额与仓储台账（ERP业务数据)核对记录
A15: 提示1：只适用于监盘（抽盘）日不是资产负债表日的情况
A16: 提示2：如果数据量大可结合IT审计完成核对
A25: 三、审计说明：
A29: 四、审计结论：

Sheet 抽盘结果汇总表F2-25
A1: 致同会计师事务所
A2: 存货抽盘结果汇总表 | N2: 本表将抽盘结果录入并检查盘点差异，现场盘点时记录数量的纸质抽盘表作为本表的附件
A3: =[4]底稿目录!A2 -> 被审计单位： | D3: =[4]底稿目录!A4 -> 编制人： | H3: =[4]底稿目录!A5 -> 编制日期： | L3: 索引号： | M3: =[4]底稿目录!F7 -> F2-25
A4: =[4]底稿目录!A3 -> 截止日：202X年12月31日 | D4: =[4]底稿目录!A6 -> 复核人： | H4: =[4]底稿目录!A7 -> 复核日期： | L4: 页 次：
A5: 一、审计目标:
A6: 1. 资产负债表中记录的存货是存在的，且已经记录在恰当的账户中
A7: 2. 所有应记录的存货均已记录，所有应当包括在财务报表中的相关披露均已包括
A8: 3. 记录的存货由被审计单位拥有或控制
A9: 4. 存货以恰当的金额包括在财务报表中，与之相关的计价或分摊调整已恰当记录，相关披露已得到恰当计量和描述
A10: 二、审计过程:
A11: 仓库名称：_____________________ | F11: 盘点时间：__________________
A12: 监盘人员：（审计人员签字） | F12: 盘点人员：（被审计单位仓库盘点人和财务监盘人签字）
A13: （一）从存货盘点记录中选取项目追查至存货实物
A14: 存货编码 | B14: 存货名称/类别 | C14: 规格 | D14: 单位 | E14: 单价 | F14: 盘点前财务账面记录 | H14: 企业盘点记录数量 | I14: 抽盘数量 | J14: 抽盘与账面差异（+盈-亏） | K14: 抽盘与企业盘点差异 | L14: 企业盘点与账面差异 | M14: 品质状况（正常/残次/毁损/滞销等）
F15: 数量 | G15: 金额
J16: =I16-F16 -> 0 | K16: =I16-H16 -> 0 | L16: =H16-F16 -> 0
J17: =I17-F17 -> 0 | K17: =I17-H17 -> 0 | L17: =H17-F17 -> 0
J18: =I18-F18 -> 0 | K18: =I18-H18 -> 0 | L18: =H18-F18 -> 0
J19: =I19-F19 -> 0 | K19: =I19-H19 -> 0 | L19: =H19-F19 -> 0
J20: =I20-F20 -> 0 | K20: =I20-H20 -> 0 | L20: =H20-F20 -> 0
J21: =I21-F21 -> 0 | K21: =I21-H21 -> 0 | L21: =H21-F21 -> 0
J22: =I22-F22 -> 0 | K22: =I22-H22 -> 0 | L22: =H22-F22 -> 0
J23: =I23-F23 -> 0 | K23: =I23-H23 -> 0 | L23: =H23-F23 -> 0
J24: =I24-F24 -> 0 | K24: =I24-H24 -> 0 | L24: =H24-F24 -> 0
J25: =I25-F25 -> 0 | K25: =I25-H25 -> 0 | L25: =H25-F25 -> 0
J26: =I26-F26 -> 0 | K26: =I26-H26 -> 0 | L26: =H26-F26 -> 0
A27: 合计 | G27: =SUM(G16:G26) -> 0
A28: （二）从存货实物中选取项目追查至存货盘点记录
A29: 存货编码 | B29: 存货名称/类别 | C29: 规格 | D29: 单位 | E29: 单价 | F29: 盘点前财务账面记录 | H29: 企业盘点记录数量 | I29: 抽盘数量 | J29: 抽盘与账面差异（+盈-亏） | K29: 抽盘与企业盘点差异 | L29: 企业盘点与账面差异 | M29: 品质状况（正常/残次/毁损/滞销等）
F30: 数量 | G30: 金额
J31: =I31-F31 -> 0 | K31: =I31-H31 -> 0 | L31: =H31-F31 -> 0
J32: =I32-F32 -> 0 | K32: =I32-H32 -> 0 | L32: =H32-F32 -> 0
J33: =I33-F33 -> 0 | K33: =I33-H33 -> 0 | L33: =H33-F33 -> 0
J34: =I34-F34 -> 0 | K34: =I34-H34 -> 0 | L34: =H34-F34 -> 0
J35: =I35-F35 -> 0 | K35: =I35-H35 -> 0 | L35: =H35-F35 -> 0
J36: =I36-F36 -> 0 | K36: =I36-H36 -> 0 | L36: =H36-F36 -> 0
J37: =I37-F37 -> 0 | K37: =I37-H37 -> 0 | L37: =H37-F37 -> 0
J38: =I38-F38 -> 0 | K38: =I38-H38 -> 0 | L38: =H38-F38 -> 0
J39: =I39-F39 -> 0 | K39: =I39-H39 -> 0 | L39: =H39-F39 -> 0
J40: =I40-F40 -> 0 | K40: =I40-H40 -> 0 | L40: =H40-F40 -> 0
J41: =I41-F41 -> 0 | K41: =I41-H41 -> 0 | L41: =H41-F41 -> 0
A42: 合计 | G42: =SUM(G31:G41) -> 0
A43: 三、审计说明：
A45: 四、审计结论：
A48: 提示：
A49: 1.本表将抽盘结果录入并检查盘点差异，现场盘点时记录数量的纸质抽盘表作为本表的附件。
A50: 2.财务账面记录与仓库账面记录应一致，若存在差异应调整一致。
A51: 3.财务账面记录与实际盘点记录的差异构成盘盈/盘亏，应根据具体原因分析处理。应说明企业的处理结果。
A52: 4.盘点时应关注存货的品质状况（影响存货跌价准备的计提）。
A53: 5.抽盘应从存货盘点记录中选取项目追查至存货实物，以测试盘点记录的准确性；还应从存货实物中选取项目追查至存货盘点记录，以测试存货盘点的完整性
A54: 6.盘点过程中收集并保留盘点轨迹，例如：现场盘点照片、往返盘点现场车票、盘点现场定位截图等资料。
A55: 7.考虑（1）检查包装箱中的货物、货物堆放方式（如堆为中空）或标记方式；(2)液态物质（如香水、特殊的化学物质）的质量特征（如纯度、品级或浓度）或利用专家的工作；
A56: (3)按照存货的等级或类别、存放地点或其他分类标准，将本期存货数量与前期进行比较，或将盘点数量与永续盘存记录进行比较，如按标签号进行检索以测试存货的标签控制，
A57: 或按照项目的顺序编号进行整理以检查是否存在漏记或重复编号；

Sheet 盘点倒轧表F2-26
A1: 致同会计师事务所
A2: 存货盘点倒轧表
A3: =[4]底稿目录!A2 -> 被审计单位： | D3: =[4]底稿目录!A4 -> 编制人： | I3: =[4]底稿目录!A5 -> 编制日期： | N3: 索引号： | O3: =[4]底稿目录!F8 -> F2-26
A4: =[4]底稿目录!A3 -> 截止日：202X年12月31日 | D4: =[4]底稿目录!A6 -> 复核人： | I4: =[4]底稿目录!A7 -> 复核日期： | N4: 页次：
A5: （一）资产负债表日后盘点倒轧表
A6: 说明：针对有关入库或发出的调整，核对出入库单据是否与明细账记录一致。
A7: 存货类别 | B7: 存货编码 | C7: 品名及规格 | D7: 单位 | E7: 单价 | F7: 仓库 | G7: 监盘日实存数量 | H7: 加：资产负债表日至监盘日发出数量（经核对调节后） | I7: 减：资产负债表日至监盘日入库数量（经核对调节后） | J7: 资产负债表日实存数量 | K7: 资产负债表日账面数量 | L7: 数量差异 | M7: 金额差异 | N7: 差异原因 | O7: 是否调整
J8: =G8+H8-I8 -> 0 | L8: =J8-K8 -> 0 | M8: =L8*E8 -> 0
J9: =J2+H9-I9 -> 0 | L9: =J9-K9 -> 0 | M9: =L9*E9 -> 0
J10: =G10+H10-I10 -> 0 | L10: =J10-K10 -> 0 | M10: =L10*E10 -> 0
J11: =G11+H11-I11 -> 0 | L11: =J11-K11 -> 0 | M11: =L11*E11 -> 0
J12: =G12+H12-I12 -> 0 | L12: =J12-K12 -> 0 | M12: =L12*E12 -> 0
J13: =G13+H13-I13 -> 0 | L13: =J13-K13 -> 0 | M13: =L13*E13 -> 0
J14: =G14+H14-I14 -> 0 | L14: =J14-K14 -> 0 | M14: =L14*E14 -> 0
A15: （二）资产负债表日前盘点倒轧表
A16: 存货类别 | B16: 存货编码 | C16: 品名及规格 | D16: 单位 | E16: 单价 | F16: 仓库 | G16: 监盘日实存数量 | H16: 加：监盘日至资产负债表日入库数量 | I16: 减：监盘日至资产负债表日发出数量 | J16: 资产负债表日实存数量 | K16: 资产负债表日账面数量 | L16: 数量差异 | M16: 金额差异 | N16: 差异原因 | O16: 是否调整
J17: =G17+H17-I17 -> 0 | L17: =J17-K17 -> 0 | M17: =L17*E17 -> 0
J18: =G18+H18-I18 -> 0 | L18: =J18-K18 -> 0 | M18: =L18*E18 -> 0
J19: =G19+H19-I19 -> 0 | L19: =J19-K19 -> 0 | M19: =L19*E19 -> 0
J20: =G20+H20-I20 -> 0 | L20: =J20-K20 -> 0 | M20: =L20*E20 -> 0
J21: =G21+H21-I21 -> 0 | L21: =J21-K21 -> 0 | M21: =L21*E21 -> 0
J22: =G22+H22-I22 -> 0 | L22: =J22-K22 -> 0 | M22: =L22*E22 -> 0
J23: =G23+H23-I23 -> 0 | L23: =J23-K23 -> 0 | M23: =L23*E23 -> 0
A24: 审计说明：
A28: 审计结论：

Sheet 底稿目录 (4)
A1: 底稿开列时，可先在以下单元格填写有关内容，以便其他底稿引用有关数据：
A2: 被审计单位： | D2: 序号 | E2: 内容 | F2: 索引号
A3: 截止日：202X年12月31日 | D3: 1 | E3: 存货截止测试-入库（从记账凭证至原始凭证） | F3: F2-29
A4: 编制人： | D4: 2 | E4: 存货截止测试-入库（从原始凭证至记账凭证） | F4: F2-30
A5: 编制日期： | D5: 3 | E5: 存货截止测试-出库（记账凭证至原始凭证） | F5: F2-31
A6: 复核人： | D6: 4 | E6: 存货截止测试-出库（原始凭证至记账凭证） | F6: F2-32
A7: 复核日期： | D7: 5 | E7: 存货采购入库检查表 | F7: F2-33
D8: 6 | E8: 材料领用检查表 | F8: F2-34
D9: 7 | E9: 委托加工物资核查表 | F9: F2-35

Sheet 截止测试-入库（记账凭证至原始凭证）F2-29
A1: 致同会计师事务所
A2: 存货（原材料/产成品）截止测试-入库（从记账凭证至原始凭证）
A3: =[5]底稿目录!A2 -> 被审计单位： | E3: =[5]底稿目录!A4 -> 编制人： | G3: =[5]底稿目录!A5 -> 编制日期： | K3: 索引号： | L3: =[5]底稿目录!F3 -> F2-29
A4: =[5]底稿目录!A3 -> 截止日：202X年12月31日 | E4: =[5]底稿目录!A6 -> 复核人： | G4: =[5]底稿目录!A7 -> 复核日期： | K4: 页 次：
A5: 一、审计目标：
A6: 1.资产负债表中记录的存货是存在的，且已经记录在恰当的账户中
A7: 2.所有应记录的存货均已记录，所有应当包括在财务报表中的相关披露均已包括
A8: 二、审计过程：
A9: 1.从存货明细账借方发生额中抽取资产负债表日前（______）天、后（______）天，且金额大于______元的凭证，与入库记录（如入库单，或购货发票，或运输单据）核对；
A10: 2.结合存货监盘程序，检查入库记录编号是否与执行存货监盘程序中获取的截止性资料编号存在冲突。
A11: 提示：如果存在跨期舞弊风险或者所检查样本中发现有跨期的，应扩大测试期间和样本，甚至可以考虑将截止测试期间延长至审计报告日。同时考虑是否存在内控缺陷。
A12: 记账凭证 | F12: 入库单 | H12: 质检报告 | J12: …… | L12: 是否跨期√（×）
A13: 日期 | B13: 凭证编号 | C13: 业务内容 | D13: 存货名称 | E13: 金额 | F13: 编号 | G13: 日期 | H13: 编号 | I13: 日期 | J13: 编号 | K13: 日期
A27: ——————截止日期：202X年12月31日——————
A42: 三、审计说明：
A46: 四、审计结论：
A49: 提示：
A50: 1.应分别存货类别（如原材料、产成品）进行截止测试。
A51: 2.上述测试基于入库单作为存货入库的依据，如果存货入库的依据不是入库单，则相应调整。
A52: 3.审计说明可以概述：（1）程序的测试情况、结果；（2）拟调整事项及其调整分录、未调整事项及其影响，审计范围受到限制情况及其影响。
A53: 4.审计结论可参考：A、未见异常。 B、除上述重大不符事项应当作为调整事项予以调整外，其余未见异常。 C、由于存在以下重大未调整事项（或审计范围受到限制无法获取充分、适当证据），不可确认。

Sheet 截止测试-入库（原始凭证至记账凭证）F2-30
A1: 致同会计师事务所
A2: 存货（原材料/产成品）截止测试-入库（从原始凭证至记账凭证）
A3: =[5]底稿目录!A2 -> 被审计单位： | D3: =[5]底稿目录!A4 -> 编制人： | H3: =[5]底稿目录!A5 -> 编制日期： | K3: 索引号： | L3: =[5]底稿目录!F4 -> F2-30
A4: =[5]底稿目录!A3 -> 截止日：202X年12月31日 | D4: =[5]底稿目录!A6 -> 复核人： | H4: =[5]底稿目录!A7 -> 复核日期： | K4: 页 次：
A5: 一、审计目标：
A6: 1.资产负债表中记录的存货是存在的，且已经记录在恰当的账户中
A7: 2.所有应记录的存货均已记录，所有应当包括在财务报表中的相关披露均已包括
A8: 二、审计过程：
A9: 1.从入库记录中抽取资产负债表日前（______）天、后（______）天，且金额大于______元的的凭据，与存货明细账的借方发生额进行核对；
A10: 2.结合存货监盘程序，检查入库记录编号是否与执行存货监盘程序中获取的截止性资料编号存在冲突。
A11: 提示：如果存在跨期舞弊风险或者所检查样本中发现有跨期的，应扩大测试期间和样本，甚至可以考虑将截止测试期间延长至审计报告日。同时考虑是否存在内控缺陷。
A12: 入库单 | C12: 质检报告 | E12: …… | G12: 记账凭证 | L12: 是否跨期√（×）
A13: 编号 | B13: 日期 | C13: 编号 | D13: 日期 | E13: 编号 | F13: 日期 | G13: 日期 | H13: 凭证编号 | I13: 业务内容 | J13: 存货名称 | K13: 金额
A27: ——————截止日期：202X年12月31日——————
A42: 三、审计说明：
A46: 四、审计结论：
A49: 提示：
A50: 1.应分别存货类别（如原材料、产成品）进行截止测试。
A51: 2.上述测试基于入库单作为存货入库的依据，如果存货入库的依据不是入库单，则相应调整。

Sheet 截止测试-出库（记账凭证至原始凭证）F2-31
A1: 致同会计师事务所
A2: 存货（原材料/产成品）截止测试-出库（从记账凭证至原始凭证）
A3: =[5]底稿目录!A2 -> 被审计单位： | D3: =[5]底稿目录!A4 -> 编制人： | F3: =[5]底稿目录!A5 -> 编制日期： | I3: 索引号： | J3: =[5]底稿目录!F5 -> F2-31
A4: =[5]底稿目录!A3 -> 截止日：202X年12月31日 | D4: =[5]底稿目录!A6 -> 复核人： | F4: =[5]底稿目录!A7 -> 复核日期： | I4: 页 次：
A5: 一、审计目标：
A6: 1.资产负债表中记录的存货是存在的，且已经记录在恰当的账户中
A7: 2.所有应记录的存货均已记录，所有应当包括在财务报表中的相关披露均已包括
A8: 二、审计过程：
A9: 1.从存货明细账贷方发生额中抽取资产负债表日前（______）天、后（______）天，且金额大于______元的凭证，与出库记录（如出库单、原材料领用单、运输单据）核对；
A10: 2.结合存货监盘程序，检查出库记录编号是否与执行存货监盘程序中获取的截止性资料编号存在冲突。
A11: 3.产成品出库截止测试可与营业收入截止测试程序结合完成。
A12: 提示：如果存在跨期舞弊风险或者所检查样本中发现有跨期的，应扩大测试期间和样本，甚至可以考虑将截止测试期间延长至审计报告日。同时考虑是否存在内控缺陷。
A13: 记账凭证 | F13: 出库单/领料单 | H13: …… | J13: 是否跨期√（×）
A14: 日期 | B14: 凭证编号 | C14: 业务内容 | D14: 存货名称 | E14: 金额 | F14: 编号 | G14: 日期 | H14: 编号 | I14: 日期
A27: ='[5]截止测试-入库（记账凭证至原始凭证）F2-29'!A27 -> ——————截止日期：202X年12月31日——————
A40: 四、审计说明：
A44: 五、审计结论：
A48: 提示：
A49: 1.应分别存货类别（如原材料、产成品等）进行截止测试。
A50: 2.上述测试基于出库单作为存货出库的依据，如果存货出库的依据不是出库单，则相应调整。
A51: 3.如果公司核算发出商品或存在不符合收入确认而已经发出产品或消耗产品等，产成品的出库截止性测试相应调整。

Sheet 截止测试-出库（原始凭证至记账凭证）F2-32
A1: 致同会计师事务所
A2: 存货（原材料/产成品）截止测试-出库（从原始凭证至记账凭证）
A3: =[5]底稿目录!A2 -> 被审计单位： | D3: =[5]底稿目录!A4 -> 编制人： | G3: =[5]底稿目录!A5 -> 编制日期： | I3: 索引号： | J3: =[5]底稿目录!F6 -> F2-32
A4: =[5]底稿目录!A3 -> 截止日：202X年12月31日 | D4: =[5]底稿目录!A6 -> 复核人： | G4: =[5]底稿目录!A7 -> 复核日期： | I4: 页 次：
A5: 一、审计目标：
A6: 1.资产负债表中记录的存货是存在的，且已经记录在恰当的账户中
A7: 2.所有应记录的存货均已记录，所有应当包括在财务报表中的相关披露均已包括
A8: 二、审计过程：
A9: 1.从出库记录中抽取资产负债表日前（ ）天、后（ ）天，且金额大于 元的凭据，与存货明细账的贷方发生额进行核对；
A10: 2.结合存货监盘程序，检查出库记录编号是否与执行存货监盘程序中获取的截止性资料编号存在冲突。
A11: 3.产成品出库截止测试可与营业收入截止测试程序结合完成。
A12: 提示：如果存在跨期舞弊风险或者所检查样本中发现有跨期的，应扩大测试期间和样本，甚至可以考虑将截止测试期间延长至审计报告日。同时考虑是否存在内控缺陷。
A13: 出库单/领料单 | C13: …… | E13: 记账凭证 | J13: 是否跨期√（×）
A14: 编号 | B14: 日期 | C14: 编号 | D14: 日期 | E14: 日期 | F14: 凭证编号 | G14: 业务内容 | H14: 存货名称 | I14: 金额
A27: ='[5]截止测试-入库（记账凭证至原始凭证）F2-29'!A27 -> ——————截止日期：202X年12月31日——————
A40: 四、审计说明：
A44: 五、审计结论：
A48: 提示：
A49: 1.应分别存货类别（如原材料、产成品等）进行截止测试。
A50: 2.上述测试基于出库单作为存货出库的依据，如果存货出库的依据不是出库单，则相应调整。
A51: 3.如果公司核算发出商品或存在不符合收入确认而已经发出产品或消耗产品等，产成品的出库截止性测试相应调整。

Sheet 存货采购入库检查表F2-33-新增
A1: 致同会计师事务所
A2: 存货采购入库检查表
A3: =[5]底稿目录!A2 -> 被审计单位： | I3: =[5]底稿目录!A4 -> 编制人： | O3: =[5]底稿目录!A5 -> 编制日期： | U3: 索引号： | V3: =[5]底稿目录!F7 -> F2-33
A4: =[5]底稿目录!A3 -> 截止日：202X年12月31日 | I4: =[5]底稿目录!A6 -> 复核人： | O4: =[5]底稿目录!A7 -> 复核日期： | U4: 页 次：
A5: 一、审计目标：
A6: 1.资产负债表中记录的存货是存在的，且已经记录在恰当的账户中
A7: 2.记录的存货由被审计单位拥有或控制
A8: 3.存货以恰当的金额包括在财务报表中，与之相关的计价或分摊调整已恰当记录，相关披露已得到恰当计量和描述
A9: 二、样本选取标准与规模：
A10: 测试总体： | B10: 如存货借方发生额所有凭证共XX笔金额XX | J10: 特定样本： | K10: XX金额以上（大额）、关联方/关联交易形成的款项、XX异常款项全部测试，共XX笔
A11: 抽样总体： | B11: 测试总体扣除特定样本以外的样本，共XX笔、金额XX | J11: 确定的抽样样本量： | L11: 抽取XX笔 | M11: （如果使用了样本计算器计算样本量，样本量计算过程见<XX>底稿）
A12: 抽样方法： | B12: 随机选样/系统选样/货币单元抽样/随意选样（非统计抽样适用） | J12: 抽样过程： | K12: 使用IDEA（XX抽样工具）选择XX数量、金额XX的样本进行测试，抽样工具中的样本选择过程和结果见<XX>底稿
A13: 三、测试：
A14: 测试内容说明：1.原始凭证是否齐全； 2.记账凭证与原始凭证是否相符；3.账务处理是否正确；4.是否记录于恰当的会计期间；5.……
A15: 供应商名称 | B15: 存货类别 | C15: 记账凭证 | K15: 入库单/验收单 | M15: 质检报告 | N15: 物流单（运输单） | Q15: 采购发票 | T15: …… | U15: 索引号 | V15: 是否异常
C16: 凭证编号 | D16: 业务内容 | E16: 存货名称 | F16: 单位 | G16: 数量 | H16: 借方金额 | I16: 对方科目 | J16: 对方明细科目 | K16: 日期/编号 | L16: 数量 | M16: 日期/编号 | N16: 日期/编号 | O16: 物流单位 | P16: 数量 | Q16: 日期/编号 | R16: 对手方名称 | S16: 金额
A36: 合计 | H36: =SUM(H17:H35) -> 0 | S36: =SUM(S17:S35) -> 0
A37: 四、审计说明：
A38: 1.本期发生额、期末余额检查比例： | E38: 存货类别 | F38: 账面金额 | H38: 检查金额 | I38: 检查比例 | J38: 如果检查比例较低应扩大检查样本量或说明原因
I39: =ROUND(H39/F39,4) -> #DIV/0!
I40: =ROUND(H40/F40,2) -> #DIV/0!
I41: =ROUND(H41/F41,2) -> #DIV/0!
A42: 2.……
A43: 五、审计结论：

Sheet 材料领用检查表F2-34-新增
A1: 致同会计师事务所
A2: 材料领用检查表
A3: =[5]底稿目录!A2 -> 被审计单位： | F3: =[5]底稿目录!A4 -> 编制人： | I3: =[5]底稿目录!A5 -> 编制日期： | M3: 索引号： | N3: =[5]底稿目录!F8 -> F2-34
A4: =[5]底稿目录!A3 -> 截止日：202X年12月31日 | F4: =[5]底稿目录!A6 -> 复核人： | I4: =[5]底稿目录!A7 -> 复核日期： | M4: 页 次：
A5: 一、审计目标：
A6: 1.资产负债表中记录的存货是存在的，且已经记录在恰当的账户中；2.所有应记录的存货均已记录，所有应当包括在财务报表中的相关披露均已包括
A7: 3.存货以恰当的金额包括在财务报表中，与之相关的计价或分摊调整已恰当记录，相关披露已得到恰当计量和描述
A8: 二、样本选取标准与规模：
A9: 测试总体： | B9: 如原材料贷方发生额所有凭证共XX笔金额XX | F9: 特定样本： | G9: XX金额以上（大额）、关联方/关联交易形成的款项、XX异常款项全部测试，共XX笔
A10: 抽样总体： | B10: 测试总体扣除特定样本以外的样本，共XX笔、金额XX | F10: 确定的抽样样本量： | H10: 抽取XX笔 | I10: （如果使用了样本计算器计算样本量，样本量计算过程见<XX>底稿）
A11: 抽样方法： | B11: 随机选样/系统选样/货币单元抽样/随意选样（非统计抽样适用） | F11: 抽样过程： | G11: 使用IDEA（XX抽样工具）选择XX数量、金额XX的样本进行测试，抽样工具中的样本选择过程和结果见<XX>底稿
A12: 三、测试：
A13: 测试内容说明：1.原始凭证是否齐全； 2.记账凭证与原始凭证是否相符；3.账务处理是否正确；4.是否记录于恰当的会计期间；5.……
A14: 记账凭证 | I14: 出库单/领料单 | L14: …… | M14: 索引号 | N14: 是否异常
A15: 凭证编号 | B15: 业务内容 | C15: 存货名称 | D15: 单位 | E15: 数量 | F15: 贷方金额 | G15: 对方科目 | H15: 对方明细科目 | I15: 日期/编号 | J15: 领用部门 | K15: 数量
A32: 合计 | F32: =SUM(F16:F31) -> 0
A33: 四、审计说明：
A34: 1.本期发生额、期末余额检查比例： | D34: 项目 | F34: 账面金额 | G34: 检查金额 | H34: 检查比例 | I34: 如果检查比例较低应扩大检查样本量或说明原因
D35: 原材料贷方 | G35: =F32 -> 0 | H35: =ROUND(G35/F35,4) -> #DIV/0!
A36: 2.……
A37: 五、审计结论：

Sheet 委托加工物资核查表F2-35
A1: 致同会计师事务所
A2: 委托加工物资核查表
A3: =[5]底稿目录!A2 -> 被审计单位： | D3: =[5]底稿目录!A4 -> 编制人： | F3: =[5]底稿目录!A5 -> 编制日期： | H3: 索引号： | I3: =[5]底稿目录!F9 -> F2-35
A4: =[5]底稿目录!A3 -> 截止日：202X年12月31日 | D4: =[5]底稿目录!A6 -> 复核人： | F4: =[5]底稿目录!A7 -> 复核日期： | H4: 页次：
A5: 一、审计目标：
A6: 1.资产负债表中记录的存货是存在的，且已经记录在恰当的账户中
A7: 2.所有应记录的存货均已记录，所有应当包括在财务报表中的相关披露均已包括
A8: 3.记录的存货由被审计单位拥有或控制
A9: 4. 存货以恰当的金额包括在财务报表中，与之相关的计价或分摊调整已恰当记录，相关披露已得到恰当计量和描述
A10: 二、样本选取标准与规模：
A13: 三、审计过程：
A14: 1.获取或编制委托加工物资的明细表，抽查委托加工业务合同，检查有关发料凭证、加工费结算凭证。
A15: 2.针对当期加工工费及期末委托加工物资对被委托方进行函证。
A16: 3.……
A17: （一）委托加工物资基本情况
A18: 年度 | B18: 期初金额 | C18: 本期增加 | D18: 本期减少 | E18: 期末金额 | F18: 其中加工费发生额
A22: （二）主要委外供应商情况1
A23: 年度 | B23: 供应商名称 | C23: 主要加工工序 | D23: 委外加工入库数量 | E23: 委外加工入库金额 | F23: 加工费金额 | G23: 加工费结算单索引 | H23: 函证编号
A29: （三）主要委外供应商情况2
A30: 加工单位名称 | B30: 合同或协议号 | C30: 发出时间 | D30: 发出材料成本 | E30: 加工费 | F30: 收回材料成本 | G30: 未收回原因及是否需函证 | H30: 索引号 | I30: 备注
A36: 四、审计说明：
A39: 五、审计结论：

Sheet 底稿目录 (5)
A1: 底稿开列时，可先在以下单元格填写有关内容，以便其他底稿引用有关数据：
A2: 被审计单位： | D2: 序号 | E2: 内容 | F2: 索引号
A3: 截止日：202X年12月31日 | D3: 1 | E3: 计价方法测试表-平均 | F3: F2-38
A4: 编制人： | D4: 2 | E4: 计价方法测试表-先进先出 | F4: F2-39
A5: 编制日期： | D5: 3 | E5: 计价方法测试表-标准成本差异 | F5: F2-40
A6: 复核人： | D6: 4 | E6: 生产成本明细表 | F6: F2-41
A7: 复核日期： | D7: 5 | E7: 直接人工分析表 | F7: F2-42
D8: 6 | E8: 制造费用明细表 | F8: F2-43
D9: 7 | E9: 生产成本分配 | F9: F2-44

Sheet 计价方法测试表-平均F2-38
A1: 致同会计师事务所
A2: 存货计价方法测试表（月末一次加权平均法适用）
A3: =[6]底稿目录!A2 -> 被审计单位： | E3: =[6]底稿目录!A4 -> 编制人： | I3: =[6]底稿目录!A5 -> 编制日期： | M3: 索引号： | N3: =[6]底稿目录!F3 -> F2-38
A4: =[6]底稿目录!A3 -> 截止日：202X年12月31日 | E4: =[6]底稿目录!A6 -> 复核人： | I4: =[6]底稿目录!A7 -> 复核日期： | M4: 页 次：
A5: 一、测试目标：
A6: 存货以恰当的金额包括在财务报表中，与之相关的计价或分摊调整已恰当记录，相关披露已得到恰当计量和描述
A7: 二、样本选取标准与规模：
A9: 三、测试：
A10: （一）计价方法说明： | D10: 月末一次加权平均法
A11: （二）测试项目1： | C11: 品名：
A12: 月份 | B12: 本期生产（或购入） | E12: 本期销售（或发出） | H12: 期末结存 | K12: 应结转 | N12: 差异
B13: 数量 | C13: 单价 | D13: 金额 | E13: 数量 | F13: 单价 | G13: 金额 | H13: 数量 | I13: 单价 | J13: 金额 | K13: 单价 | L13: 金额 | M13: 结余 | N13: M=K-F
A14: 年初数 | B14: A | C14: B | D14: C | E14: D | F14: E | G14: F | I14: =IF(ISERROR(J14/H14),0,J14/H14) -> 0 | K14: J | L14: K | M14: =J14 -> 0 | N14: M
A15: 1月 | C15: =IF(ISERROR(D15/B15),0,D15/B15) -> 0 | F15: =IF(ISERROR(G15/E15),0,G15/E15) -> 0 | H15: =H14+B15-E15 -> 0 | I15: =IF(ISERROR(J15/H15),0,J15/H15) -> 0 | J15: =J14+D15-G15 -> 0 | K15: =IF(ISERROR((M14+D15)/(H14+B15)),0,(M14+D15)/(H14+B15)) -> 0 | L15: =K15*E15 -> 0 | M15: =M14+D15-L15 -> 0 | N15: =L15-G15 -> 0
A16: 2月 | C16: =IF(ISERROR(D16/B16),0,D16/B16) -> 0 | F16: =IF(ISERROR(G16/E16),0,G16/E16) -> 0 | H16: =H15+B16-E16 -> 0 | I16: =IF(ISERROR(J16/H16),0,J16/H16) -> 0 | J16: =J15+D16-G16 -> 0 | K16: =IF(ISERROR((M15+D16)/(H15+B16)),0,(M15+D16)/(H15+B16)) -> 0 | L16: =K16*E16 -> 0 | M16: =M15+D16-L16 -> 0 | N16: =L16-G16 -> 0
A17: 3月 | C17: =IF(ISERROR(D17/B17),0,D17/B17) -> 0 | F17: =IF(ISERROR(G17/E17),0,G17/E17) -> 0 | H17: =H16+B17-E17 -> 0 | I17: =IF(ISERROR(J17/H17),0,J17/H17) -> 0 | J17: =J16+D17-G17 -> 0 | K17: =IF(ISERROR((M16+D17)/(H16+B17)),0,(M16+D17)/(H16+B17)) -> 0 | L17: =K17*E17 -> 0 | M17: =M16+D17-L17 -> 0 | N17: =L17-G17 -> 0
A18: 4月 | C18: =IF(ISERROR(D18/B18),0,D18/B18) -> 0 | F18: =IF(ISERROR(G18/E18),0,G18/E18) -> 0 | H18: =H17+B18-E18 -> 0 | I18: =IF(ISERROR(J18/H18),0,J18/H18) -> 0 | J18: =J17+D18-G18 -> 0 | K18: =IF(ISERROR((M17+D18)/(H17+B18)),0,(M17+D18)/(H17+B18)) -> 0 | L18: =K18*E18 -> 0 | M18: =M17+D18-L18 -> 0 | N18: =L18-G18 -> 0
A19: 5月 | C19: =IF(ISERROR(D19/B19),0,D19/B19) -> 0 | F19: =IF(ISERROR(G19/E19),0,G19/E19) -> 0 | H19: =H18+B19-E19 -> 0 | I19: =IF(ISERROR(J19/H19),0,J19/H19) -> 0 | J19: =J18+D19-G19 -> 0 | K19: =IF(ISERROR((M18+D19)/(H18+B19)),0,(M18+D19)/(H18+B19)) -> 0 | L19: =K19*E19 -> 0 | M19: =M18+D19-L19 -> 0 | N19: =L19-G19 -> 0
A20: 6月 | C20: =IF(ISERROR(D20/B20),0,D20/B20) -> 0 | F20: =IF(ISERROR(G20/E20),0,G20/E20) -> 0 | H20: =H19+B20-E20 -> 0 | I20: =IF(ISERROR(J20/H20),0,J20/H20) -> 0 | J20: =J19+D20-G20 -> 0 | K20: =IF(ISERROR((M19+D20)/(H19+B20)),0,(M19+D20)/(H19+B20)) -> 0 | L20: =K20*E20 -> 0 | M20: =M19+D20-L20 -> 0 | N20: =L20-G20 -> 0
A21: 7月 | C21: =IF(ISERROR(D21/B21),0,D21/B21) -> 0 | F21: =IF(ISERROR(G21/E21),0,G21/E21) -> 0 | H21: =H20+B21-E21 -> 0 | I21: =IF(ISERROR(J21/H21),0,J21/H21) -> 0 | J21: =J20+D21-G21 -> 0 | K21: =IF(ISERROR((M20+D21)/(H20+B21)),0,(M20+D21)/(H20+B21)) -> 0 | L21: =K21*E21 -> 0 | M21: =M20+D21-L21 -> 0 | N21: =L21-G21 -> 0
A22: 8月 | C22: =IF(ISERROR(D22/B22),0,D22/B22) -> 0 | F22: =IF(ISERROR(G22/E22),0,G22/E22) -> 0 | H22: =H21+B22-E22 -> 0 | I22: =IF(ISERROR(J22/H22),0,J22/H22) -> 0 | J22: =J21+D22-G22 -> 0 | K22: =IF(ISERROR((M21+D22)/(H21+B22)),0,(M21+D22)/(H21+B22)) -> 0 | L22: =K22*E22 -> 0 | M22: =M21+D22-L22 -> 0 | N22: =L22-G22 -> 0
A23: 9月 | C23: =IF(ISERROR(D23/B23),0,D23/B23) -> 0 | F23: =IF(ISERROR(G23/E23),0,G23/E23) -> 0 | H23: =H22+B23-E23 -> 0 | I23: =IF(ISERROR(J23/H23),0,J23/H23) -> 0 | J23: =J22+D23-G23 -> 0 | K23: =IF(ISERROR((M22+D23)/(H22+B23)),0,(M22+D23)/(H22+B23)) -> 0 | L23: =K23*E23 -> 0 | M23: =M22+D23-L23 -> 0 | N23: =L23-G23 -> 0
A24: 10月 | C24: =IF(ISERROR(D24/B24),0,D24/B24) -> 0 | F24: =IF(ISERROR(G24/E24),0,G24/E24) -> 0 | H24: =H23+B24-E24 -> 0 | I24: =IF(ISERROR(J24/H24),0,J24/H24) -> 0 | J24: =J23+D24-G24 -> 0 | K24: =IF(ISERROR((M23+D24)/(H23+B24)),0,(M23+D24)/(H23+B24)) -> 0 | L24: =K24*E24 -> 0 | M24: =M23+D24-L24 -> 0 | N24: =L24-G24 -> 0
A25: 11月 | C25: =IF(ISERROR(D25/B25),0,D25/B25) -> 0 | F25: =IF(ISERROR(G25/E25),0,G25/E25) -> 0 | H25: =H24+B25-E25 -> 0 | I25: =IF(ISERROR(J25/H25),0,J25/H25) -> 0 | J25: =J24+D25-G25 -> 0 | K25: =IF(ISERROR((M24+D25)/(H24+B25)),0,(M24+D25)/(H24+B25)) -> 0 | L25: =K25*E25 -> 0 | M25: =M24+D25-L25 -> 0 | N25: =L25-G25 -> 0
A26: 12月 | C26: =IF(ISERROR(D26/B26),0,D26/B26) -> 0 | F26: =IF(ISERROR(G26/E26),0,G26/E26) -> 0 | H26: =H25+B26-E26 -> 0 | I26: =IF(ISERROR(J26/H26),0,J26/H26) -> 0 | J26: =J25+D26-G26 -> 0 | K26: =IF(ISERROR((M25+D26)/(H25+B26)),0,(M25+D26)/(H25+B26)) -> 0 | L26: =K26*E26 -> 0 | M26: =M25+D26-L26 -> 0 | N26: =L26-G26 -> 0
A27: 合计 | B27: =SUM(B14:B26) -> 0 | C27: =IF(ISERROR(D27/B27),0,D27/B27) -> 0 | D27: =SUM(D14:D26) -> 0 | E27: =SUM(E14:E26) -> 0 | F27: =IF(ISERROR(G27/E27),0,G27/E27) -> 0 | G27: =SUM(G24:G26) -> 0 | H27: =H26 -> 0 | I27: =IF(ISERROR(J27/H27),0,J27/H27) -> 0 | J27: =J26 -> 0 | L27: =SUM(L15:L26) -> 0 | M27: =M26 -> 0 | N27: =SUM(N15:N26) -> 0
A28: （二）测试项目2： | C28: 品名：
A29: 月份 | B29: 本期生产（或购入） | E29: 本期销售（或发出） | H29: 期末结存 | K29: 应结转 | N29: 差异
B30: 数量 | C30: 单价 | D30: 金额 | E30: 数量 | F30: 单价 | G30: 金额 | H30: 数量 | I30: 单价 | J30: 金额 | K30: 单价 | L30: 金额 | M30: 结余 | N30: M=K-F
A31: 年初数 | B31: A | C31: B | D31: C | E31: D | F31: E | G31: F | I31: =IF(ISERROR(J31/H31),0,J31/H31) -> 0 | K31: J | L31: K | M31: =J31 -> 0 | N31: M
A32: 1月 | C32: =IF(ISERROR(D32/B32),0,D32/B32) -> 0 | F32: =IF(ISERROR(G32/E32),0,G32/E32) -> 0 | H32: =H31+B32-E32 -> 0 | I32: =IF(ISERROR(J32/H32),0,J32/H32) -> 0 | J32: =J31+D32-G32 -> 0 | K32: =IF(ISERROR((M31+D32)/(H31+B32)),0,(M31+D32)/(H31+B32)) -> 0 | L32: =K32*E32 -> 0 | M32: =M31+D32-L32 -> 0 | N32: =L32-G32 -> 0
A33: 2月 | C33: =IF(ISERROR(D33/B33),0,D33/B33) -> 0 | F33: =IF(ISERROR(G33/E33),0,G33/E33) -> 0 | H33: =H32+B33-E33 -> 0 | I33: =IF(ISERROR(J33/H33),0,J33/H33) -> 0 | J33: =J32+D33-G33 -> 0 | K33: =IF(ISERROR((M32+D33)/(H32+B33)),0,(M32+D33)/(H32+B33)) -> 0 | L33: =K33*E33 -> 0 | M33: =M32+D33-L33 -> 0 | N33: =L33-G33 -> 0
A34: 3月 | C34: =IF(ISERROR(D34/B34),0,D34/B34) -> 0 | F34: =IF(ISERROR(G34/E34),0,G34/E34) -> 0 | H34: =H33+B34-E34 -> 0 | I34: =IF(ISERROR(J34/H34),0,J34/H34) -> 0 | J34: =J33+D34-G34 -> 0 | K34: =IF(ISERROR((M33+D34)/(H33+B34)),0,(M33+D34)/(H33+B34)) -> 0 | L34: =K34*E34 -> 0 | M34: =M33+D34-L34 -> 0 | N34: =L34-G34 -> 0
A35: 4月 | C35: =IF(ISERROR(D35/B35),0,D35/B35) -> 0 | F35: =IF(ISERROR(G35/E35),0,G35/E35) -> 0 | H35: =H34+B35-E35 -> 0 | I35: =IF(ISERROR(J35/H35),0,J35/H35) -> 0 | J35: =J34+D35-G35 -> 0 | K35: =IF(ISERROR((M34+D35)/(H34+B35)),0,(M34+D35)/(H34+B35)) -> 0 | L35: =K35*E35 -> 0 | M35: =M34+D35-L35 -> 0 | N35: =L35-G35 -> 0
A36: 5月 | C36: =IF(ISERROR(D36/B36),0,D36/B36) -> 0 | F36: =IF(ISERROR(G36/E36),0,G36/E36) -> 0 | H36: =H35+B36-E36 -> 0 | I36: =IF(ISERROR(J36/H36),0,J36/H36) -> 0 | J36: =J35+D36-G36 -> 0 | K36: =IF(ISERROR((M35+D36)/(H35+B36)),0,(M35+D36)/(H35+B36)) -> 0 | L36: =K36*E36 -> 0 | M36: =M35+D36-L36 -> 0 | N36: =L36-G36 -> 0
A37: 6月 | C37: =IF(ISERROR(D37/B37),0,D37/B37) -> 0 | F37: =IF(ISERROR(G37/E37),0,G37/E37) -> 0 | H37: =H36+B37-E37 -> 0 | I37: =IF(ISERROR(J37/H37),0,J37/H37) -> 0 | J37: =J36+D37-G37 -> 0 | K37: =IF(ISERROR((M36+D37)/(H36+B37)),0,(M36+D37)/(H36+B37)) -> 0 | L37: =K37*E37 -> 0 | M37: =M36+D37-L37 -> 0 | N37: =L37-G37 -> 0
A38: 7月 | C38: =IF(ISERROR(D38/B38),0,D38/B38) -> 0 | F38: =IF(ISERROR(G38/E38),0,G38/E38) -> 0 | H38: =H37+B38-E38 -> 0 | I38: =IF(ISERROR(J38/H38),0,J38/H38) -> 0 | J38: =J37+D38-G38 -> 0 | K38: =IF(ISERROR((M37+D38)/(H37+B38)),0,(M37+D38)/(H37+B38)) -> 0 | L38: =K38*E38 -> 0 | M38: =M37+D38-L38 -> 0 | N38: =L38-G38 -> 0
A39: 8月 | C39: =IF(ISERROR(D39/B39),0,D39/B39) -> 0 | F39: =IF(ISERROR(G39/E39),0,G39/E39) -> 0 | H39: =H38+B39-E39 -> 0 | I39: =IF(ISERROR(J39/H39),0,J39/H39) -> 0 | J39: =J38+D39-G39 -> 0 | K39: =IF(ISERROR((M38+D39)/(H38+B39)),0,(M38+D39)/(H38+B39)) -> 0 | L39: =K39*E39 -> 0 | M39: =M38+D39-L39 -> 0 | N39: =L39-G39 -> 0
A40: 9月 | C40: =IF(ISERROR(D40/B40),0,D40/B40) -> 0 | F40: =IF(ISERROR(G40/E40),0,G40/E40) -> 0 | H40: =H39+B40-E40 -> 0 | I40: =IF(ISERROR(J40/H40),0,J40/H40) -> 0 | J40: =J39+D40-G40 -> 0 | K40: =IF(ISERROR((M39+D40)/(H39+B40)),0,(M39+D40)/(H39+B40)) -> 0 | L40: =K40*E40 -> 0 | M40: =M39+D40-L40 -> 0 | N40: =L40-G40 -> 0
A41: 10月 | C41: =IF(ISERROR(D41/B41),0,D41/B41) -> 0 | F41: =IF(ISERROR(G41/E41),0,G41/E41) -> 0 | H41: =H40+B41-E41 -> 0 | I41: =IF(ISERROR(J41/H41),0,J41/H41) -> 0 | J41: =J40+D41-G41 -> 0 | K41: =IF(ISERROR((M40+D41)/(H40+B41)),0,(M40+D41)/(H40+B41)) -> 0 | L41: =K41*E41 -> 0 | M41: =M40+D41-L41 -> 0 | N41: =L41-G41 -> 0
A42: 11月 | C42: =IF(ISERROR(D42/B42),0,D42/B42) -> 0 | F42: =IF(ISERROR(G42/E42),0,G42/E42) -> 0 | H42: =H41+B42-E42 -> 0 | I42: =IF(ISERROR(J42/H42),0,J42/H42) -> 0 | J42: =J41+D42-G42 -> 0 | K42: =IF(ISERROR((M41+D42)/(H41+B42)),0,(M41+D42)/(H41+B42)) -> 0 | L42: =K42*E42 -> 0 | M42: =M41+D42-L42 -> 0 | N42: =L42-G42 -> 0
A43: 12月 | C43: =IF(ISERROR(D43/B43),0,D43/B43) -> 0 | F43: =IF(ISERROR(G43/E43),0,G43/E43) -> 0 | H43: =H42+B43-E43 -> 0 | I43: =IF(ISERROR(J43/H43),0,J43/H43) -> 0 | J43: =J42+D43-G43 -> 0 | K43: =IF(ISERROR((M42+D43)/(H42+B43)),0,(M42+D43)/(H42+B43)) -> 0 | L43: =K43*E43 -> 0 | M43: =M42+D43-L43 -> 0 | N43: =L43-G43 -> 0
A44: 合计 | B44: =SUM(B31:B43) -> 0 | C44: =IF(ISERROR(D44/B44),0,D44/B44) -> 0 | D44: =SUM(D31:D43) -> 0 | E44: =SUM(E31:E43) -> 0 | F44: =IF(ISERROR(G44/E44),0,G44/E44) -> 0 | G44: =SUM(G41:G43) -> 0 | H44: =H43 -> 0 | I44: =IF(ISERROR(J44/H44),0,J44/H44) -> 0 | J44: =J43 -> 0 | L44: =SUM(L32:L43) -> 0 | M44: =M43 -> 0 | N44: =SUM(N32:N43) -> 0
A45: （二）测试项目3： | C45: 品名：
A46: 月份 | B46: 本期生产（或购入） | E46: 本期销售（或发出） | H46: 期末结存 | K46: 应结转 | N46: 差异
B47: 数量 | C47: 单价 | D47: 金额 | E47: 数量 | F47: 单价 | G47: 金额 | H47: 数量 | I47: 单价 | J47: 金额 | K47: 单价 | L47: 金额 | M47: 结余 | N47: M=K-F
A48: 年初数 | B48: A | C48: B | D48: C | E48: D | F48: E | G48: F | I48: =IF(ISERROR(J48/H48),0,J48/H48) -> 0 | K48: J | L48: K | M48: =J48 -> 0 | N48: M
A49: 1月 | C49: =IF(ISERROR(D49/B49),0,D49/B49) -> 0 | F49: =IF(ISERROR(G49/E49),0,G49/E49) -> 0 | H49: =H48+B49-E49 -> 0 | I49: =IF(ISERROR(J49/H49),0,J49/H49) -> 0 | J49: =J48+D49-G49 -> 0 | K49: =IF(ISERROR((M48+D49)/(H48+B49)),0,(M48+D49)/(H48+B49)) -> 0 | L49: =K49*E49 -> 0 | M49: =M48+D49-L49 -> 0 | N49: =L49-G49 -> 0
A50: 2月 | C50: =IF(ISERROR(D50/B50),0,D50/B50) -> 0 | F50: =IF(ISERROR(G50/E50),0,G50/E50) -> 0 | H50: =H49+B50-E50 -> 0 | I50: =IF(ISERROR(J50/H50),0,J50/H50) -> 0 | J50: =J49+D50-G50 -> 0 | K50: =IF(ISERROR((M49+D50)/(H49+B50)),0,(M49+D50)/(H49+B50)) -> 0 | L50: =K50*E50 -> 0 | M50: =M49+D50-L50 -> 0 | N50: =L50-G50 -> 0
A51: 3月 | C51: =IF(ISERROR(D51/B51),0,D51/B51) -> 0 | F51: =IF(ISERROR(G51/E51),0,G51/E51) -> 0 | H51: =H50+B51-E51 -> 0 | I51: =IF(ISERROR(J51/H51),0,J51/H51) -> 0 | J51: =J50+D51-G51 -> 0 | K51: =IF(ISERROR((M50+D51)/(H50+B51)),0,(M50+D51)/(H50+B51)) -> 0 | L51: =K51*E51 -> 0 | M51: =M50+D51-L51 -> 0 | N51: =L51-G51 -> 0
A52: 4月 | C52: =IF(ISERROR(D52/B52),0,D52/B52) -> 0 | F52: =IF(ISERROR(G52/E52),0,G52/E52) -> 0 | H52: =H51+B52-E52 -> 0 | I52: =IF(ISERROR(J52/H52),0,J52/H52) -> 0 | J52: =J51+D52-G52 -> 0 | K52: =IF(ISERROR((M51+D52)/(H51+B52)),0,(M51+D52)/(H51+B52)) -> 0 | L52: =K52*E52 -> 0 | M52: =M51+D52-L52 -> 0 | N52: =L52-G52 -> 0
A53: 5月 | C53: =IF(ISERROR(D53/B53),0,D53/B53) -> 0 | F53: =IF(ISERROR(G53/E53),0,G53/E53) -> 0 | H53: =H52+B53-E53 -> 0 | I53: =IF(ISERROR(J53/H53),0,J53/H53) -> 0 | J53: =J52+D53-G53 -> 0 | K53: =IF(ISERROR((M52+D53)/(H52+B53)),0,(M52+D53)/(H52+B53)) -> 0 | L53: =K53*E53 -> 0 | M53: =M52+D53-L53 -> 0 | N53: =L53-G53 -> 0
A54: 6月 | C54: =IF(ISERROR(D54/B54),0,D54/B54) -> 0 | F54: =IF(ISERROR(G54/E54),0,G54/E54) -> 0 | H54: =H53+B54-E54 -> 0 | I54: =IF(ISERROR(J54/H54),0,J54/H54) -> 0 | J54: =J53+D54-G54 -> 0 | K54: =IF(ISERROR((M53+D54)/(H53+B54)),0,(M53+D54)/(H53+B54)) -> 0 | L54: =K54*E54 -> 0 | M54: =M53+D54-L54 -> 0 | N54: =L54-G54 -> 0
A55: 7月 | C55: =IF(ISERROR(D55/B55),0,D55/B55) -> 0 | F55: =IF(ISERROR(G55/E55),0,G55/E55) -> 0 | H55: =H54+B55-E55 -> 0 | I55: =IF(ISERROR(J55/H55),0,J55/H55) -> 0 | J55: =J54+D55-G55 -> 0 | K55: =IF(ISERROR((M54+D55)/(H54+B55)),0,(M54+D55)/(H54+B55)) -> 0 | L55: =K55*E55 -> 0 | M55: =M54+D55-L55 -> 0 | N55: =L55-G55 -> 0
A56: 8月 | C56: =IF(ISERROR(D56/B56),0,D56/B56) -> 0 | F56: =IF(ISERROR(G56/E56),0,G56/E56) -> 0 | H56: =H55+B56-E56 -> 0 | I56: =IF(ISERROR(J56/H56),0,J56/H56) -> 0 | J56: =J55+D56-G56 -> 0 | K56: =IF(ISERROR((M55+D56)/(H55+B56)),0,(M55+D56)/(H55+B56)) -> 0 | L56: =K56*E56 -> 0 | M56: =M55+D56-L56 -> 0 | N56: =L56-G56 -> 0
A57: 9月 | C57: =IF(ISERROR(D57/B57),0,D57/B57) -> 0 | F57: =IF(ISERROR(G57/E57),0,G57/E57) -> 0 | H57: =H56+B57-E57 -> 0 | I57: =IF(ISERROR(J57/H57),0,J57/H57) -> 0 | J57: =J56+D57-G57 -> 0 | K57: =IF(ISERROR((M56+D57)/(H56+B57)),0,(M56+D57)/(H56+B57)) -> 0 | L57: =K57*E57 -> 0 | M57: =M56+D57-L57 -> 0 | N57: =L57-G57 -> 0
A58: 10月 | C58: =IF(ISERROR(D58/B58),0,D58/B58) -> 0 | F58: =IF(ISERROR(G58/E58),0,G58/E58) -> 0 | H58: =H57+B58-E58 -> 0 | I58: =IF(ISERROR(J58/H58),0,J58/H58) -> 0 | J58: =J57+D58-G58 -> 0 | K58: =IF(ISERROR((M57+D58)/(H57+B58)),0,(M57+D58)/(H57+B58)) -> 0 | L58: =K58*E58 -> 0 | M58: =M57+D58-L58 -> 0 | N58: =L58-G58 -> 0
A59: 11月 | C59: =IF(ISERROR(D59/B59),0,D59/B59) -> 0 | F59: =IF(ISERROR(G59/E59),0,G59/E59) -> 0 | H59: =H58+B59-E59 -> 0 | I59: =IF(ISERROR(J59/H59),0,J59/H59) -> 0 | J59: =J58+D59-G59 -> 0 | K59: =IF(ISERROR((M58+D59)/(H58+B59)),0,(M58+D59)/(H58+B59)) -> 0 | L59: =K59*E59 -> 0 | M59: =M58+D59-L59 -> 0 | N59: =L59-G59 -> 0
A60: 12月 | C60: =IF(ISERROR(D60/B60),0,D60/B60) -> 0 | F60: =IF(ISERROR(G60/E60),0,G60/E60) -> 0 | H60: =H59+B60-E60 -> 0 | I60: =IF(ISERROR(J60/H60),0,J60/H60) -> 0 | J60: =J59+D60-G60 -> 0 | K60: =IF(ISERROR((M59+D60)/(H59+B60)),0,(M59+D60)/(H59+B60)) -> 0 | L60: =K60*E60 -> 0 | M60: =M59+D60-L60 -> 0 | N60: =L60-G60 -> 0
A61: 合计 | B61: =SUM(B48:B60) -> 0 | C61: =IF(ISERROR(D61/B61),0,D61/B61) -> 0 | D61: =SUM(D48:D60) -> 0 | E61: =SUM(E48:E60) -> 0 | F61: =IF(ISERROR(G61/E61),0,G61/E61) -> 0 | G61: =SUM(G58:G60) -> 0 | H61: =H60 -> 0 | I61: =IF(ISERROR(J61/H61),0,J61/H61) -> 0 | J61: =J60 -> 0 | L61: =SUM(L49:L60) -> 0 | M61: =M60 -> 0 | N61: =SUM(N49:N60) -> 0
A62: （二）测试项目4： | C62: 品名：
A63: 月份 | B63: 本期生产（或购入） | E63: 本期销售（或发出） | H63: 期末结存 | K63: 应结转 | N63: 差异
B64: 数量 | C64: 单价 | D64: 金额 | E64: 数量 | F64: 单价 | G64: 金额 | H64: 数量 | I64: 单价 | J64: 金额 | K64: 单价 | L64: 金额 | M64: 结余 | N64: M=K-F
A65: 年初数 | B65: A | C65: B | D65: C | E65: D | F65: E | G65: F | I65: =IF(ISERROR(J65/H65),0,J65/H65) -> 0 | K65: J | L65: K | M65: =J65 -> 0 | N65: M
A66: 1月 | C66: =IF(ISERROR(D66/B66),0,D66/B66) -> 0 | F66: =IF(ISERROR(G66/E66),0,G66/E66) -> 0 | H66: =H65+B66-E66 -> 0 | I66: =IF(ISERROR(J66/H66),0,J66/H66) -> 0 | J66: =J65+D66-G66 -> 0 | K66: =IF(ISERROR((M65+D66)/(H65+B66)),0,(M65+D66)/(H65+B66)) -> 0 | L66: =K66*E66 -> 0 | M66: =M65+D66-L66 -> 0 | N66: =L66-G66 -> 0
A67: 2月 | C67: =IF(ISERROR(D67/B67),0,D67/B67) -> 0 | F67: =IF(ISERROR(G67/E67),0,G67/E67) -> 0 | H67: =H66+B67-E67 -> 0 | I67: =IF(ISERROR(J67/H67),0,J67/H67) -> 0 | J67: =J66+D67-G67 -> 0 | K67: =IF(ISERROR((M66+D67)/(H66+B67)),0,(M66+D67)/(H66+B67)) -> 0 | L67: =K67*E67 -> 0 | M67: =M66+D67-L67 -> 0 | N67: =L67-G67 -> 0
A68: 3月 | C68: =IF(ISERROR(D68/B68),0,D68/B68) -> 0 | F68: =IF(ISERROR(G68/E68),0,G68/E68) -> 0 | H68: =H67+B68-E68 -> 0 | I68: =IF(ISERROR(J68/H68),0,J68/H68) -> 0 | J68: =J67+D68-G68 -> 0 | K68: =IF(ISERROR((M67+D68)/(H67+B68)),0,(M67+D68)/(H67+B68)) -> 0 | L68: =K68*E68 -> 0 | M68: =M67+D68-L68 -> 0 | N68: =L68-G68 -> 0
A69: 4月 | C69: =IF(ISERROR(D69/B69),0,D69/B69) -> 0 | F69: =IF(ISERROR(G69/E69),0,G69/E69) -> 0 | H69: =H68+B69-E69 -> 0 | I69: =IF(ISERROR(J69/H69),0,J69/H69) -> 0 | J69: =J68+D69-G69 -> 0 | K69: =IF(ISERROR((M68+D69)/(H68+B69)),0,(M68+D69)/(H68+B69)) -> 0 | L69: =K69*E69 -> 0 | M69: =M68+D69-L69 -> 0 | N69: =L69-G69 -> 0
A70: 5月 | C70: =IF(ISERROR(D70/B70),0,D70/B70) -> 0 | F70: =IF(ISERROR(G70/E70),0,G70/E70) -> 0 | H70: =H69+B70-E70 -> 0 | I70: =IF(ISERROR(J70/H70),0,J70/H70) -> 0 | J70: =J69+D70-G70 -> 0 | K70: =IF(ISERROR((M69+D70)/(H69+B70)),0,(M69+D70)/(H69+B70)) -> 0 | L70: =K70*E70 -> 0 | M70: =M69+D70-L70 -> 0 | N70: =L70-G70 -> 0
A71: 6月 | C71: =IF(ISERROR(D71/B71),0,D71/B71) -> 0 | F71: =IF(ISERROR(G71/E71),0,G71/E71) -> 0 | H71: =H70+B71-E71 -> 0 | I71: =IF(ISERROR(J71/H71),0,J71/H71) -> 0 | J71: =J70+D71-G71 -> 0 | K71: =IF(ISERROR((M70+D71)/(H70+B71)),0,(M70+D71)/(H70+B71)) -> 0 | L71: =K71*E71 -> 0 | M71: =M70+D71-L71 -> 0 | N71: =L71-G71 -> 0
A72: 7月 | C72: =IF(ISERROR(D72/B72),0,D72/B72) -> 0 | F72: =IF(ISERROR(G72/E72),0,G72/E72) -> 0 | H72: =H71+B72-E72 -> 0 | I72: =IF(ISERROR(J72/H72),0,J72/H72) -> 0 | J72: =J71+D72-G72 -> 0 | K72: =IF(ISERROR((M71+D72)/(H71+B72)),0,(M71+D72)/(H71+B72)) -> 0 | L72: =K72*E72 -> 0 | M72: =M71+D72-L72 -> 0 | N72: =L72-G72 -> 0
A73: 8月 | C73: =IF(ISERROR(D73/B73),0,D73/B73) -> 0 | F73: =IF(ISERROR(G73/E73),0,G73/E73) -> 0 | H73: =H72+B73-E73 -> 0 | I73: =IF(ISERROR(J73/H73),0,J73/H73) -> 0 | J73: =J72+D73-G73 -> 0 | K73: =IF(ISERROR((M72+D73)/(H72+B73)),0,(M72+D73)/(H72+B73)) -> 0 | L73: =K73*E73 -> 0 | M73: =M72+D73-L73 -> 0 | N73: =L73-G73 -> 0
A74: 9月 | C74: =IF(ISERROR(D74/B74),0,D74/B74) -> 0 | F74: =IF(ISERROR(G74/E74),0,G74/E74) -> 0 | H74: =H73+B74-E74 -> 0 | I74: =IF(ISERROR(J74/H74),0,J74/H74) -> 0 | J74: =J73+D74-G74 -> 0 | K74: =IF(ISERROR((M73+D74)/(H73+B74)),0,(M73+D74)/(H73+B74)) -> 0 | L74: =K74*E74 -> 0 | M74: =M73+D74-L74 -> 0 | N74: =L74-G74 -> 0
A75: 10月 | C75: =IF(ISERROR(D75/B75),0,D75/B75) -> 0 | F75: =IF(ISERROR(G75/E75),0,G75/E75) -> 0 | H75: =H74+B75-E75 -> 0 | I75: =IF(ISERROR(J75/H75),0,J75/H75) -> 0 | J75: =J74+D75-G75 -> 0 | K75: =IF(ISERROR((M74+D75)/(H74+B75)),0,(M74+D75)/(H74+B75)) -> 0 | L75: =K75*E75 -> 0 | M75: =M74+D75-L75 -> 0 | N75: =L75-G75 -> 0
A76: 11月 | C76: =IF(ISERROR(D76/B76),0,D76/B76) -> 0 | F76: =IF(ISERROR(G76/E76),0,G76/E76) -> 0 | H76: =H75+B76-E76 -> 0 | I76: =IF(ISERROR(J76/H76),0,J76/H76) -> 0 | J76: =J75+D76-G76 -> 0 | K76: =IF(ISERROR((M75+D76)/(H75+B76)),0,(M75+D76)/(H75+B76)) -> 0 | L76: =K76*E76 -> 0 | M76: =M75+D76-L76 -> 0 | N76: =L76-G76 -> 0
A77: 12月 | C77: =IF(ISERROR(D77/B77),0,D77/B77) -> 0 | F77: =IF(ISERROR(G77/E77),0,G77/E77) -> 0 | H77: =H76+B77-E77 -> 0 | I77: =IF(ISERROR(J77/H77),0,J77/H77) -> 0 | J77: =J76+D77-G77 -> 0 | K77: =IF(ISERROR((M76+D77)/(H76+B77)),0,(M76+D77)/(H76+B77)) -> 0 | L77: =K77*E77 -> 0 | M77: =M76+D77-L77 -> 0 | N77: =L77-G77 -> 0
A78: 合计 | B78: =SUM(B65:B77) -> 0 | C78: =IF(ISERROR(D78/B78),0,D78/B78) -> 0 | D78: =SUM(D65:D77) -> 0 | E78: =SUM(E65:E77) -> 0 | F78: =IF(ISERROR(G78/E78),0,G78/E78) -> 0 | G78: =SUM(G75:G77) -> 0 | H78: =H77 -> 0 | I78: =IF(ISERROR(J78/H78),0,J78/H78) -> 0 | J78: =J77 -> 0 | L78: =SUM(L66:L77) -> 0 | M78: =M77 -> 0 | N78: =SUM(N66:N77) -> 0
A79: 四、审计说明：
A83: 五、审计结论：
A88: 编制说明：
A89: 1.企业应当采用先进先出法、加权平均法或者个别计价法确定发出存货的实际成本。
A90: 2.对于性质和用途相似的存货，应当采用相同的成本计算方法确定发出存货的成本。
A91: 3.对于不能替代使用的存货、为特定项目专门购入或制造的存货以及提供劳务的成本，通常采用个别计价法确定发出存货的成本。
A92: 4.对进口原材料、进口库存商品应测试初始入账时的外币折算及相应的关税的会计处理。
A93: 5.关注前期减值项目的账面价值、运费、相关税费、返利和重大采购折扣（数量折扣除外）是否进行了调整。

Sheet 计价方法测试表-先进先出F2-39
A1: 致同会计师事务所
A2: 存货计价方法测试表（先进先出法/移动加权平均法适用）
A3: =[6]底稿目录!A2 -> 被审计单位： | F3: =[6]底稿目录!A4 -> 编制人： | J3: =[6]底稿目录!A5 -> 编制日期： | M3: 索引号： | N3: F2-39
A4: =[6]底稿目录!A3 -> 截止日：202X年12月31日 | F4: =[6]底稿目录!A6 -> 复核人： | J4: =[6]底稿目录!A7 -> 复核日期： | M4: 页 次：
A5: 一、测试目标：
A6: 存货以恰当的金额包括在财务报表中，与之相关的计价或分摊调整已恰当记录，相关披露已得到恰当计量和描述
A7: 二、样本选取标准与规模：
A9: 三、测试：
A10: （一）计价方法说明： | D10: 先进先出法/移动加权平均法
A11: （二）测试项目1： | C11: 品名：
A12: 日期 | B12: 本期生产（或购入） | E12: 本期销售（或发出） | H12: 期末结存 | K12: 应结转 | N12: 差异
B13: 数量 | C13: 单价 | D13: 金额 | E13: 数量 | F13: 单价 | G13: 金额 | H13: 数量 | I13: 单价 | J13: 金额 | K13: 单价 | L13: 金额 | M13: 结余 | N13: M=K-F
A14: 年初数 | B14: A | C14: B | D14: C | E14: D | F14: E | G14: F | I14: =IF(ISERROR(J14/H14),0,J14/H14) -> 0 | K14: J | L14: K | M14: =J14 -> 0 | N14: M
A28: 合计 | B28: =SUM(B14:B27) -> 0 | C28: =IF(ISERROR(D28/B28),0,D28/B28) -> 0 | D28: =SUM(D14:D27) -> 0 | E28: =SUM(E14:E27) -> 0 | F28: =IF(ISERROR(G28/E28),0,G28/E28) -> 0 | G28: =SUM(G24:G27) -> 0 | H28: =H27 -> 0 | I28: =IF(ISERROR(J28/H28),0,J28/H28) -> 0 | J28: =J27 -> 0 | L28: =SUM(L16:L27) -> 0 | M28: =M27 -> 0 | N28: =SUM(N16:N27) -> 0
A29: （二）测试项目2： | C29: 品名：
A30: 日期 | B30: 本期生产（或购入） | E30: 本期销售（或发出） | H30: 期末结存 | K30: 应结转 | N30: 差异
B31: 数量 | C31: 单价 | D31: 金额 | E31: 数量 | F31: 单价 | G31: 金额 | H31: 数量 | I31: 单价 | J31: 金额 | K31: 单价 | L31: 金额 | M31: 结余 | N31: M=K-F
A32: 年初数 | B32: A | C32: B | D32: C | E32: D | F32: E | G32: F | I32: =IF(ISERROR(J32/H32),0,J32/H32) -> 0 | K32: J | L32: K | M32: =J32 -> 0 | N32: M
A46: 合计 | B46: =SUM(B32:B45) -> 0 | C46: =IF(ISERROR(D46/B46),0,D46/B46) -> 0 | D46: =SUM(D32:D45) -> 0 | E46: =SUM(E32:E45) -> 0 | F46: =IF(ISERROR(G46/E46),0,G46/E46) -> 0 | G46: =SUM(G42:G45) -> 0 | H46: =H45 -> 0 | I46: =IF(ISERROR(J46/H46),0,J46/H46) -> 0 | J46: =J45 -> 0 | L46: =SUM(L34:L45) -> 0 | M46: =M45 -> 0 | N46: =SUM(N34:N45) -> 0
A47: （二）测试项目3： | C47: 品名：
A48: 日期 | B48: 本期生产（或购入） | E48: 本期销售（或发出） | H48: 期末结存 | K48: 应结转 | N48: 差异
B49: 数量 | C49: 单价 | D49: 金额 | E49: 数量 | F49: 单价 | G49: 金额 | H49: 数量 | I49: 单价 | J49: 金额 | K49: 单价 | L49: 金额 | M49: 结余 | N49: M=K-F
A50: 年初数 | B50: A | C50: B | D50: C | E50: D | F50: E | G50: F | I50: =IF(ISERROR(J50/H50),0,J50/H50) -> 0 | K50: J | L50: K | M50: =J50 -> 0 | N50: M
A64: 合计 | B64: =SUM(B50:B63) -> 0 | C64: =IF(ISERROR(D64/B64),0,D64/B64) -> 0 | D64: =SUM(D50:D63) -> 0 | E64: =SUM(E50:E63) -> 0 | F64: =IF(ISERROR(G64/E64),0,G64/E64) -> 0 | G64: =SUM(G60:G63) -> 0 | H64: =H63 -> 0 | I64: =IF(ISERROR(J64/H64),0,J64/H64) -> 0 | J64: =J63 -> 0 | L64: =SUM(L52:L63) -> 0 | M64: =M63 -> 0 | N64: =SUM(N52:N63) -> 0
A65: 四、审计说明：
A68: 五、审计结论：
A71: 提示：
A72: 企业应当采用先进先出法、加权平均法或者个别计价法确定发出存货的实际成本。
A73: 对于性质和用途相似的存货，应当采用相同的成本计算方法确定发出存货的成本。
A74: 对于不能替代使用的存货、为特定项目专门购入或制造的存货以及提供劳务的成本，通常采用个别计价法确定发出存货的成本。
A75: 对于已售存货，应当将其成本结转为当期损益，相应的存货跌价准备也应当予以结转。

Sheet 计价方法测试表-标准成本差异F2-40
A1: 致同会计师事务所
A2: 标准成本差异测试表
A3: =[6]底稿目录!A2 -> 被审计单位： | G3: =[6]底稿目录!A4 -> 编制人： | J3: =[6]底稿目录!A5 -> 编制日期： | N3: 索引号： | O3: =[6]底稿目录!F5 -> F2-40
A4: =[6]底稿目录!A3 -> 截止日：202X年12月31日 | G4: =[6]底稿目录!A6 -> 复核人： | J4: =[6]底稿目录!A7 -> 复核日期： | N4: 页 次：
A5: 一、测试目标：
A6: 存货以恰当的金额包括在财务报表中，与之相关的计价或分摊调整已恰当记录，相关披露已得到恰当计量和描述
A7: 二、样本选取标准与规模：
A9: 三、测试：
A10: 测试项目1： | D10: 品名：
A11: 月份 | B11: 本期生产（或购入） | F11: 本期销售（或发出）应结转 | I11: 期末应结存 | L11: 期末实际结存 | O11: 差异
B12: 数量 | C12: 标准单价 | D12: 标准成本 | E12: 标准成本差异 | F12: 数量 | G12: 标准成本 | H12: 标准成本差异 | I12: 数量 | J12: 标准成本 | K12: 标准成本差异 | L12: 数量 | M12: 标准成本 | N12: 标准成本差异
A13: 年初数 | D13: =B13*C13 -> 0 | I13: =B13 -> 0 | J13: =D13 -> 0 | K13: =E13 -> 0 | O13: =N13-K13 -> 0
A14: 1月 | D14: =B14*C14 -> 0 | G14: =F14*C14 -> 0 | H14: =(IF(ISERROR((K13+E14)/(I13+B14)),0,(K13+E14)/(I13+B14)))*G14 -> 0 | I14: =I13+B14-F14 -> 0 | J14: =J13+D14-G14 -> 0 | K14: =K13+E14-H14 -> 0 | O14: =N14-K14 -> 0
A15: 2月 | D15: =B15*C15 -> 0 | G15: =F15*C15 -> 0 | H15: =(IF(ISERROR((K14+E15)/(I14+B15)),0,(K14+E15)/(I14+B15)))*G15 -> 0 | I15: =I14+B15-F15 -> 0 | J15: =J14+D15-G15 -> 0 | K15: =K14+E15-H15 -> 0 | O15: =N15-K15 -> 0
A16: 3月 | D16: =B16*C16 -> 0 | G16: =F16*C16 -> 0 | H16: =(IF(ISERROR((K15+E16)/(I15+B16)),0,(K15+E16)/(I15+B16)))*G16 -> 0 | I16: =I15+B16-F16 -> 0 | J16: =J15+D16-G16 -> 0 | K16: =K15+E16-H16 -> 0 | O16: =N16-K16 -> 0
A17: 4月 | D17: =B17*C17 -> 0 | G17: =F17*C17 -> 0 | H17: =(IF(ISERROR((K16+E17)/(I16+B17)),0,(K16+E17)/(I16+B17)))*G17 -> 0 | I17: =I16+B17-F17 -> 0 | J17: =J16+D17-G17 -> 0 | K17: =K16+E17-H17 -> 0 | O17: =N17-K17 -> 0
A18: 5月 | D18: =B18*C18 -> 0 | G18: =F18*C18 -> 0 | H18: =(IF(ISERROR((K17+E18)/(I17+B18)),0,(K17+E18)/(I17+B18)))*G18 -> 0 | I18: =I17+B18-F18 -> 0 | J18: =J17+D18-G18 -> 0 | K18: =K17+E18-H18 -> 0 | O18: =N18-K18 -> 0
A19: 6月 | D19: =B19*C19 -> 0 | G19: =F19*C19 -> 0 | H19: =(IF(ISERROR((K18+E19)/(I18+B19)),0,(K18+E19)/(I18+B19)))*G19 -> 0 | I19: =I18+B19-F19 -> 0 | J19: =J18+D19-G19 -> 0 | K19: =K18+E19-H19 -> 0 | O19: =N19-K19 -> 0
A20: 7月 | D20: =B20*C20 -> 0 | G20: =F20*C20 -> 0 | H20: =(IF(ISERROR((K19+E20)/(I19+B20)),0,(K19+E20)/(I19+B20)))*G20 -> 0 | I20: =I19+B20-F20 -> 0 | J20: =J19+D20-G20 -> 0 | K20: =K19+E20-H20 -> 0 | O20: =N20-K20 -> 0
A21: 8月 | D21: =B21*C21 -> 0 | G21: =F21*C21 -> 0 | H21: =(IF(ISERROR((K20+E21)/(I20+B21)),0,(K20+E21)/(I20+B21)))*G21 -> 0 | I21: =I20+B21-F21 -> 0 | J21: =J20+D21-G21 -> 0 | K21: =K20+E21-H21 -> 0 | O21: =N21-K21 -> 0
A22: 9月 | D22: =B22*C22 -> 0 | G22: =F22*C22 -> 0 | H22: =(IF(ISERROR((K21+E22)/(I21+B22)),0,(K21+E22)/(I21+B22)))*G22 -> 0 | I22: =I21+B22-F22 -> 0 | J22: =J21+D22-G22 -> 0 | K22: =K21+E22-H22 -> 0 | O22: =N22-K22 -> 0
A23: 10月 | D23: =B23*C23 -> 0 | G23: =F23*C23 -> 0 | H23: =(IF(ISERROR((K22+E23)/(I22+B23)),0,(K22+E23)/(I22+B23)))*G23 -> 0 | I23: =I22+B23-F23 -> 0 | J23: =J22+D23-G23 -> 0 | K23: =K22+E23-H23 -> 0 | O23: =N23-K23 -> 0
A24: 11月 | D24: =B24*C24 -> 0 | G24: =F24*C24 -> 0 | H24: =(IF(ISERROR((K23+E24)/(I23+B24)),0,(K23+E24)/(I23+B24)))*G24 -> 0 | I24: =I23+B24-F24 -> 0 | J24: =J23+D24-G24 -> 0 | K24: =K23+E24-H24 -> 0 | O24: =N24-K24 -> 0
A25: 12月 | D25: =B25*C25 -> 0 | G25: =F25*C25 -> 0 | H25: =(IF(ISERROR((K24+E25)/(I24+B25)),0,(K24+E25)/(I24+B25)))*G25 -> 0 | I25: =I24+B25-F25 -> 0 | J25: =J24+D25-G25 -> 0 | K25: =K24+E25-H25 -> 0 | O25: =N25-K25 -> 0
A26: 测试项目2： | D26: 品名：
A27: 月份 | B27: 本期生产（或购入） | F27: 本期销售（或发出）应结转 | I27: 期末应结存 | L27: 期末实际结存 | O27: 差异
B28: 数量 | C28: 标准单价 | D28: 标准成本 | E28: 标准成本差异 | F28: 数量 | G28: 标准成本 | H28: 标准成本差异 | I28: 数量 | J28: 标准成本 | K28: 标准成本差异 | L28: 数量 | M28: 标准成本 | N28: 标准成本差异
A29: 年初数 | D29: =B29*C29 -> 0 | I29: =B29 -> 0 | J29: =D29 -> 0 | K29: =E29 -> 0 | O29: =N29-K29 -> 0
A30: 1月 | D30: =B30*C30 -> 0 | G30: =F30*C30 -> 0 | H30: =(IF(ISERROR((K29+E30)/(I29+B30)),0,(K29+E30)/(I29+B30)))*G30 -> 0 | I30: =I29+B30-F30 -> 0 | J30: =J29+D30-G30 -> 0 | K30: =K29+E30-H30 -> 0 | O30: =N30-K30 -> 0
A31: 2月 | D31: =B31*C31 -> 0 | G31: =F31*C31 -> 0 | H31: =(IF(ISERROR((K30+E31)/(I30+B31)),0,(K30+E31)/(I30+B31)))*G31 -> 0 | I31: =I30+B31-F31 -> 0 | J31: =J30+D31-G31 -> 0 | K31: =K30+E31-H31 -> 0 | O31: =N31-K31 -> 0
A32: 3月 | D32: =B32*C32 -> 0 | G32: =F32*C32 -> 0 | H32: =(IF(ISERROR((K31+E32)/(I31+B32)),0,(K31+E32)/(I31+B32)))*G32 -> 0 | I32: =I31+B32-F32 -> 0 | J32: =J31+D32-G32 -> 0 | K32: =K31+E32-H32 -> 0 | O32: =N32-K32 -> 0
A33: 4月 | D33: =B33*C33 -> 0 | G33: =F33*C33 -> 0 | H33: =(IF(ISERROR((K32+E33)/(I32+B33)),0,(K32+E33)/(I32+B33)))*G33 -> 0 | I33: =I32+B33-F33 -> 0 | J33: =J32+D33-G33 -> 0 | K33: =K32+E33-H33 -> 0 | O33: =N33-K33 -> 0
A34: 5月 | D34: =B34*C34 -> 0 | G34: =F34*C34 -> 0 | H34: =(IF(ISERROR((K33+E34)/(I33+B34)),0,(K33+E34)/(I33+B34)))*G34 -> 0 | I34: =I33+B34-F34 -> 0 | J34: =J33+D34-G34 -> 0 | K34: =K33+E34-H34 -> 0 | O34: =N34-K34 -> 0
A35: 6月 | D35: =B35*C35 -> 0 | G35: =F35*C35 -> 0 | H35: =(IF(ISERROR((K34+E35)/(I34+B35)),0,(K34+E35)/(I34+B35)))*G35 -> 0 | I35: =I34+B35-F35 -> 0 | J35: =J34+D35-G35 -> 0 | K35: =K34+E35-H35 -> 0 | O35: =N35-K35 -> 0
A36: 7月 | D36: =B36*C36 -> 0 | G36: =F36*C36 -> 0 | H36: =(IF(ISERROR((K35+E36)/(I35+B36)),0,(K35+E36)/(I35+B36)))*G36 -> 0 | I36: =I35+B36-F36 -> 0 | J36: =J35+D36-G36 -> 0 | K36: =K35+E36-H36 -> 0 | O36: =N36-K36 -> 0
A37: 8月 | D37: =B37*C37 -> 0 | G37: =F37*C37 -> 0 | H37: =(IF(ISERROR((K36+E37)/(I36+B37)),0,(K36+E37)/(I36+B37)))*G37 -> 0 | I37: =I36+B37-F37 -> 0 | J37: =J36+D37-G37 -> 0 | K37: =K36+E37-H37 -> 0 | O37: =N37-K37 -> 0
A38: 9月 | D38: =B38*C38 -> 0 | G38: =F38*C38 -> 0 | H38: =(IF(ISERROR((K37+E38)/(I37+B38)),0,(K37+E38)/(I37+B38)))*G38 -> 0 | I38: =I37+B38-F38 -> 0 | J38: =J37+D38-G38 -> 0 | K38: =K37+E38-H38 -> 0 | O38: =N38-K38 -> 0
A39: 10月 | D39: =B39*C39 -> 0 | G39: =F39*C39 -> 0 | H39: =(IF(ISERROR((K38+E39)/(I38+B39)),0,(K38+E39)/(I38+B39)))*G39 -> 0 | I39: =I38+B39-F39 -> 0 | J39: =J38+D39-G39 -> 0 | K39: =K38+E39-H39 -> 0 | O39: =N39-K39 -> 0
A40: 11月 | D40: =B40*C40 -> 0 | G40: =F40*C40 -> 0 | H40: =(IF(ISERROR((K39+E40)/(I39+B40)),0,(K39+E40)/(I39+B40)))*G40 -> 0 | I40: =I39+B40-F40 -> 0 | J40: =J39+D40-G40 -> 0 | K40: =K39+E40-H40 -> 0 | O40: =N40-K40 -> 0
A41: 12月 | D41: =B41*C41 -> 0 | G41: =F41*C41 -> 0 | H41: =(IF(ISERROR((K40+E41)/(I40+B41)),0,(K40+E41)/(I40+B41)))*G41 -> 0 | I41: =I40+B41-F41 -> 0 | J41: =J40+D41-G41 -> 0 | K41: =K40+E41-H41 -> 0 | O41: =N41-K41 -> 0
A42: 测试项目3： | D42: 品名：
A43: 月份 | B43: 本期生产（或购入） | F43: 本期销售（或发出）应结转 | I43: 期末应结存 | L43: 期末实际结存 | O43: 差异
B44: 数量 | C44: 标准单价 | D44: 标准成本 | E44: 标准成本差异 | F44: 数量 | G44: 标准成本 | H44: 标准成本差异 | I44: 数量 | J44: 标准成本 | K44: 标准成本差异 | L44: 数量 | M44: 标准成本 | N44: 标准成本差异
A45: 年初数 | D45: =B45*C45 -> 0 | I45: =B45 -> 0 | J45: =D45 -> 0 | K45: =E45 -> 0 | O45: =N45-K45 -> 0
A46: 1月 | D46: =B46*C46 -> 0 | G46: =F46*C46 -> 0 | H46: =(IF(ISERROR((K45+E46)/(I45+B46)),0,(K45+E46)/(I45+B46)))*G46 -> 0 | I46: =I45+B46-F46 -> 0 | J46: =J45+D46-G46 -> 0 | K46: =K45+E46-H46 -> 0 | O46: =N46-K46 -> 0
A47: 2月 | D47: =B47*C47 -> 0 | G47: =F47*C47 -> 0 | H47: =(IF(ISERROR((K46+E47)/(I46+B47)),0,(K46+E47)/(I46+B47)))*G47 -> 0 | I47: =I46+B47-F47 -> 0 | J47: =J46+D47-G47 -> 0 | K47: =K46+E47-H47 -> 0 | O47: =N47-K47 -> 0
A48: 3月 | D48: =B48*C48 -> 0 | G48: =F48*C48 -> 0 | H48: =(IF(ISERROR((K47+E48)/(I47+B48)),0,(K47+E48)/(I47+B48)))*G48 -> 0 | I48: =I47+B48-F48 -> 0 | J48: =J47+D48-G48 -> 0 | K48: =K47+E48-H48 -> 0 | O48: =N48-K48 -> 0
A49: 4月 | D49: =B49*C49 -> 0 | G49: =F49*C49 -> 0 | H49: =(IF(ISERROR((K48+E49)/(I48+B49)),0,(K48+E49)/(I48+B49)))*G49 -> 0 | I49: =I48+B49-F49 -> 0 | J49: =J48+D49-G49 -> 0 | K49: =K48+E49-H49 -> 0 | O49: =N49-K49 -> 0
A50: 5月 | D50: =B50*C50 -> 0 | G50: =F50*C50 -> 0 | H50: =(IF(ISERROR((K49+E50)/(I49+B50)),0,(K49+E50)/(I49+B50)))*G50 -> 0 | I50: =I49+B50-F50 -> 0 | J50: =J49+D50-G50 -> 0 | K50: =K49+E50-H50 -> 0 | O50: =N50-K50 -> 0
A51: 6月 | D51: =B51*C51 -> 0 | G51: =F51*C51 -> 0 | H51: =(IF(ISERROR((K50+E51)/(I50+B51)),0,(K50+E51)/(I50+B51)))*G51 -> 0 | I51: =I50+B51-F51 -> 0 | J51: =J50+D51-G51 -> 0 | K51: =K50+E51-H51 -> 0 | O51: =N51-K51 -> 0
A52: 7月 | D52: =B52*C52 -> 0 | G52: =F52*C52 -> 0 | H52: =(IF(ISERROR((K51+E52)/(I51+B52)),0,(K51+E52)/(I51+B52)))*G52 -> 0 | I52: =I51+B52-F52 -> 0 | J52: =J51+D52-G52 -> 0 | K52: =K51+E52-H52 -> 0 | O52: =N52-K52 -> 0
A53: 8月 | D53: =B53*C53 -> 0 | G53: =F53*C53 -> 0 | H53: =(IF(ISERROR((K52+E53)/(I52+B53)),0,(K52+E53)/(I52+B53)))*G53 -> 0 | I53: =I52+B53-F53 -> 0 | J53: =J52+D53-G53 -> 0 | K53: =K52+E53-H53 -> 0 | O53: =N53-K53 -> 0
A54: 9月 | D54: =B54*C54 -> 0 | G54: =F54*C54 -> 0 | H54: =(IF(ISERROR((K53+E54)/(I53+B54)),0,(K53+E54)/(I53+B54)))*G54 -> 0 | I54: =I53+B54-F54 -> 0 | J54: =J53+D54-G54 -> 0 | K54: =K53+E54-H54 -> 0 | O54: =N54-K54 -> 0
A55: 10月 | D55: =B55*C55 -> 0 | G55: =F55*C55 -> 0 | H55: =(IF(ISERROR((K54+E55)/(I54+B55)),0,(K54+E55)/(I54+B55)))*G55 -> 0 | I55: =I54+B55-F55 -> 0 | J55: =J54+D55-G55 -> 0 | K55: =K54+E55-H55 -> 0 | O55: =N55-K55 -> 0
A56: 11月 | D56: =B56*C56 -> 0 | G56: =F56*C56 -> 0 | H56: =(IF(ISERROR((K55+E56)/(I55+B56)),0,(K55+E56)/(I55+B56)))*G56 -> 0 | I56: =I55+B56-F56 -> 0 | J56: =J55+D56-G56 -> 0 | K56: =K55+E56-H56 -> 0 | O56: =N56-K56 -> 0
A57: 12月 | D57: =B57*C57 -> 0 | G57: =F57*C57 -> 0 | H57: =(IF(ISERROR((K56+E57)/(I56+B57)),0,(K56+E57)/(I56+B57)))*G57 -> 0 | I57: =I56+B57-F57 -> 0 | J57: =J56+D57-G57 -> 0 | K57: =K56+E57-H57 -> 0 | O57: =N57-K57 -> 0
A58: 四、审计说明：
A61: 五、审计结论：

Sheet 生产成本明细表F2-41
A1: 致同会计师事务所
A2: 生产成本明细表
A3: =[6]底稿目录!A2 -> 被审计单位： | G3: =[6]底稿目录!A4 -> 编制人： | K3: =[6]底稿目录!A5 -> 编制日期： | P3: 索引号： | Q3: =[6]底稿目录!F6 -> F2-41
A4: =[6]底稿目录!A3 -> 截止日：202X年12月31日 | G4: =[6]底稿目录!A6 -> 复核人： | K4: =[6]底稿目录!A7 -> 复核日期： | P4: 页 次：
A5: 月份 项目 | B5: 1月 | C5: 2月 | D5: 3月 | E5: 4月 | F5: 5月 | G5: 6月 | H5: 7月 | I5: 8月 | J5: 9月 | K5: 10月 | L5: 11月 | M5: 12月 | N5: 合计 | O5: 上年度 | P5: 变动率 | Q5: 变动原因
A6: 期初余额 | N6: =SUM(B6:M6) -> 0
A7: 本期增加：
A8: 原材料 | N8: =SUM(B8:M8) -> 0 | P8: =(N8-O8)/O8 -> #DIV/0!
A9: 燃料动力 | N9: =SUM(B9:M9) -> 0 | P9: =(N9-O9)/O9 -> #DIV/0!
A10: 人工费用 | N10: =SUM(B10:M10) -> 0 | P10: =(N10-O10)/O10 -> #DIV/0!
A11: 制造费用 | N11: =SUM(B11:M11) -> 0 | P11: =(N11-O11)/O11 -> #DIV/0!
A12: 其他 | N12: =SUM(B12:M12) -> 0 | P12: =(N12-O12)/O12 -> #DIV/0!
A13: 增加合计 | B13: =SUM(B8:B12) -> 0 | C13: =SUM(C8:C12) -> 0 | D13: =SUM(D8:D12) -> 0 | E13: =SUM(E8:E12) -> 0 | F13: =SUM(F8:F12) -> 0 | G13: =SUM(G8:G12) -> 0 | H13: =SUM(H8:H12) -> 0 | I13: =SUM(I8:I12) -> 0 | ... M13: =SUM(M8:M12) -> 0 | N13: =SUM(B13:M13) -> 0 | P13: =(N13-O13)/O13 -> #DIV/0!
A14: 本期结转产成品 | N14: =SUM(B14:M14) -> 0 | P14: =(N14-O14)/O14 -> #DIV/0!
A15: 本期结转半成本
A16: 月末余额 | B16: =B6+B13-B14-B15 -> 0 | C16: =C6+C13-C14-C15 -> 0 | D16: =D6+D13-D14-D15 -> 0 | E16: =E6+E13-E14-E15 -> 0 | F16: =F6+F13-F14-F15 -> 0 | G16: =G6+G13-G14-G15 -> 0 | H16: =H6+H13-H14-H15 -> 0 | I16: =I6+I13-I14-I15 -> 0 | ... N16: =N6+N13-N14-N15 -> 0 | P16: =(N16-O16)/O16 -> #DIV/0!
A17: 三、审计说明：
A21: 四、审计结论：
A24: 提示：
A25: 1.关注存货成本是否包含了应费用化的项目（如停工损失等非正常消耗的直接材料、直接人工和制造费用，完工后的仓储费用，与销售相关的运输费，超范围、超期的借款费用资本化，不能归属于使存货达到目前场所和状态的其他支出）
A26: 2.将直接材料与材料耗用汇总表、直接工资总额与工资分配表、制造费用总额与制造费用明细表及相关账项明细表核对一致，并作交叉索引
A27: 3.检查生产成本在完工产品与在产品间分配是否正确（包括评价被审计单位确定在产品完工程度的方法是否合理），分配标准和计算方法是否有重大变化，是否合理和适当。

Sheet 直接人工分析表F2-42
A1: 致同会计师事务所
A2: 直接人工分析表
A3: =[6]底稿目录!A2 -> 被审计单位： | F3: =[6]底稿目录!A4 -> 编制人： | K3: =[6]底稿目录!A5 -> 编制日期： | O3: 索引号： | P3: =[6]底稿目录!F7 -> F2-42
A4: =[6]底稿目录!A3 -> 截止日：202X年12月31日 | F4: =[6]底稿目录!A6 -> 复核人： | K4: =[6]底稿目录!A7 -> 复核日期： | O4: 页 次：
A5: 一、审计目标：
A6: 存货以恰当的金额包括在财务报表中，与之相关的计价或分摊调整已恰当记录，相关披露已得到恰当计量和描述
A7: 二、审计过程：
A8: 分析计入在产品和产成品中的直接人工成本、产量或工时和单位人工成本，关注否异常变化、各月之间波动及与上年度比较有无异常
A9: 各月发生的直接人工
A10: 产品 | B10: 1月 | C10: 2月 | D10: 3月 | E10: 4月 | F10: 5月 | G10: 6月 | H10: 7月 | I10: 8月 | J10: 9月 | K10: 10月 | L10: 11月 | M10: 12月 | N10: 合计 | O10: 上年度 | P10: 变动率
N11: =SUM(B11:M11) -> 0 | P11: =IF(AND(O11=0,N11-O11=0),0,IF(AND(O11=0,N11-O11>0),1,(N11-O11)/O11)) -> 0
N12: =SUM(B12:M12) -> 0 | P12: =IF(AND(O12=0,N12-O12=0),0,IF(AND(O12=0,N12-O12>0),1,(N12-O12)/O12)) -> 0
N13: =SUM(B13:M13) -> 0 | P13: =IF(AND(O13=0,N13-O13=0),0,IF(AND(O13=0,N13-O13>0),1,(N13-O13)/O13)) -> 0
N14: =SUM(B14:M14) -> 0 | P14: =IF(AND(O14=0,N14-O14=0),0,IF(AND(O14=0,N14-O14>0),1,(N14-O14)/O14)) -> 0
N15: =SUM(B15:M15) -> 0 | P15: =IF(AND(O15=0,N15-O15=0),0,IF(AND(O15=0,N15-O15>0),1,(N15-O15)/O15)) -> 0
N16: =SUM(B16:M16) -> 0 | P16: =IF(AND(O16=0,N16-O16=0),0,IF(AND(O16=0,N16-O16>0),1,(N16-O16)/O16)) -> 0
N17: =SUM(B17:M17) -> 0 | P17: =IF(AND(O17=0,N17-O17=0),0,IF(AND(O17=0,N17-O17>0),1,(N17-O17)/O17)) -> 0
N18: =SUM(B18:M18) -> 0 | P18: =IF(AND(O18=0,N18-O18=0),0,IF(AND(O18=0,N18-O18>0),1,(N18-O18)/O18)) -> 0
N19: =SUM(B19:M19) -> 0 | P19: =IF(AND(O19=0,N19-O19=0),0,IF(AND(O19=0,N19-O19>0),1,(N19-O19)/O19)) -> 0
A20: 各月产量/工时
A21: 产品 | B21: 1月 | C21: 2月 | D21: 3月 | E21: 4月 | F21: 5月 | G21: 6月 | H21: 7月 | I21: 8月 | J21: 9月 | K21: 10月 | L21: 11月 | M21: 12月 | N21: 合计 | O21: 上年度 | P21: 变动率
N22: =SUM(B22:M22) -> 0 | P22: =IF(AND(O22=0,N22-O22=0),0,IF(AND(O22=0,N22-O22>0),1,(N22-O22)/O22)) -> 0
N23: =SUM(B23:M23) -> 0 | P23: =IF(AND(O23=0,N23-O23=0),0,IF(AND(O23=0,N23-O23>0),1,(N23-O23)/O23)) -> 0
N24: =SUM(B24:M24) -> 0 | P24: =IF(AND(O24=0,N24-O24=0),0,IF(AND(O24=0,N24-O24>0),1,(N24-O24)/O24)) -> 0
N25: =SUM(B25:M25) -> 0 | P25: =IF(AND(O25=0,N25-O25=0),0,IF(AND(O25=0,N25-O25>0),1,(N25-O25)/O25)) -> 0
N26: =SUM(B26:M26) -> 0 | P26: =IF(AND(O26=0,N26-O26=0),0,IF(AND(O26=0,N26-O26>0),1,(N26-O26)/O26)) -> 0
N27: =SUM(B27:M27) -> 0 | P27: =IF(AND(O27=0,N27-O27=0),0,IF(AND(O27=0,N27-O27>0),1,(N27-O27)/O27)) -> 0
N28: =SUM(B28:M28) -> 0 | P28: =IF(AND(O28=0,N28-O28=0),0,IF(AND(O28=0,N28-O28>0),1,(N28-O28)/O28)) -> 0
N29: =SUM(B29:M29) -> 0 | P29: =IF(AND(O29=0,N29-O29=0),0,IF(AND(O29=0,N29-O29>0),1,(N29-O29)/O29)) -> 0
N30: =SUM(B30:M30) -> 0 | P30: =IF(AND(O30=0,N30-O30=0),0,IF(AND(O30=0,N30-O30>0),1,(N30-O30)/O30)) -> 0
A31: 单位人工成本（各月发生的直接人工/生产产量或工时）
A32: 产品 | B32: 1月 | C32: 2月 | D32: 3月 | E32: 4月 | F32: 5月 | G32: 6月 | H32: 7月 | I32: 8月 | J32: 9月 | K32: 10月 | L32: 11月 | M32: 12月 | N32: 平均值 | O32: 上年度 | P32: 变动率
B33: =IF(B22=0,0,B11/B22) -> 0 | C33: =IF(C22=0,0,C11/C22) -> 0 | D33: =IF(D22=0,0,D11/D22) -> 0 | E33: =IF(E22=0,0,E11/E22) -> 0 | F33: =IF(F22=0,0,F11/F22) -> 0 | G33: =IF(G22=0,0,G11/G22) -> 0 | H33: =IF(H22=0,0,H11/H22) -> 0 | I33: =IF(I22=0,0,I11/I22) -> 0 | ... N33: =IF(N22=0,0,N11/N22) -> 0 | O33: 2 | P33: =IF(AND(O33=0,N33-O33=0),0,IF(AND(O33=0,N33-O33>0),1,(N33-O33)/O33)) -> -1 | Q33: 对变动异常的产品应进一步执行舞弊应对程序中的产品生产成本及单耗分析
B34: =IF(B23=0,0,B12/B23) -> 0 | C34: =IF(C23=0,0,C12/C23) -> 0 | D34: =IF(D23=0,0,D12/D23) -> 0 | E34: =IF(E23=0,0,E12/E23) -> 0 | F34: =IF(F23=0,0,F12/F23) -> 0 | G34: =IF(G23=0,0,G12/G23) -> 0 | H34: =IF(H23=0,0,H12/H23) -> 0 | I34: =IF(I23=0,0,I12/I23) -> 0 | ... N34: =IF(N23=0,0,N12/N23) -> 0 | P34: =IF(AND(O34=0,N34-O34=0),0,IF(AND(O34=0,N34-O34>0),1,(N34-O34)/O34)) -> 0
B35: =IF(B24=0,0,B13/B24) -> 0 | C35: =IF(C24=0,0,C13/C24) -> 0 | D35: =IF(D24=0,0,D13/D24) -> 0 | E35: =IF(E24=0,0,E13/E24) -> 0 | F35: =IF(F24=0,0,F13/F24) -> 0 | G35: =IF(G24=0,0,G13/G24) -> 0 | H35: =IF(H24=0,0,H13/H24) -> 0 | I35: =IF(I24=0,0,I13/I24) -> 0 | ... N35: =IF(N24=0,0,N13/N24) -> 0 | P35: =IF(AND(O35=0,N35-O35=0),0,IF(AND(O35=0,N35-O35>0),1,(N35-O35)/O35)) -> 0
B36: =IF(B25=0,0,B14/B25) -> 0 | C36: =IF(C25=0,0,C14/C25) -> 0 | D36: =IF(D25=0,0,D14/D25) -> 0 | E36: =IF(E25=0,0,E14/E25) -> 0 | F36: =IF(F25=0,0,F14/F25) -> 0 | G36: =IF(G25=0,0,G14/G25) -> 0 | H36: =IF(H25=0,0,H14/H25) -> 0 | I36: =IF(I25=0,0,I14/I25) -> 0 | ... N36: =IF(N25=0,0,N14/N25) -> 0 | P36: =IF(AND(O36=0,N36-O36=0),0,IF(AND(O36=0,N36-O36>0),1,(N36-O36)/O36)) -> 0
B37: =IF(B26=0,0,B15/B26) -> 0 | C37: =IF(C26=0,0,C15/C26) -> 0 | D37: =IF(D26=0,0,D15/D26) -> 0 | E37: =IF(E26=0,0,E15/E26) -> 0 | F37: =IF(F26=0,0,F15/F26) -> 0 | G37: =IF(G26=0,0,G15/G26) -> 0 | H37: =IF(H26=0,0,H15/H26) -> 0 | I37: =IF(I26=0,0,I15/I26) -> 0 | ... N37: =IF(N26=0,0,N15/N26) -> 0 | P37: =IF(AND(O37=0,N37-O37=0),0,IF(AND(O37=0,N37-O37>0),1,(N37-O37)/O37)) -> 0
B38: =IF(B27=0,0,B16/B27) -> 0 | C38: =IF(C27=0,0,C16/C27) -> 0 | D38: =IF(D27=0,0,D16/D27) -> 0 | E38: =IF(E27=0,0,E16/E27) -> 0 | F38: =IF(F27=0,0,F16/F27) -> 0 | G38: =IF(G27=0,0,G16/G27) -> 0 | H38: =IF(H27=0,0,H16/H27) -> 0 | I38: =IF(I27=0,0,I16/I27) -> 0 | ... N38: =IF(N27=0,0,N16/N27) -> 0 | P38: =IF(AND(O38=0,N38-O38=0),0,IF(AND(O38=0,N38-O38>0),1,(N38-O38)/O38)) -> 0
B39: =IF(B28=0,0,B17/B28) -> 0 | C39: =IF(C28=0,0,C17/C28) -> 0 | D39: =IF(D28=0,0,D17/D28) -> 0 | E39: =IF(E28=0,0,E17/E28) -> 0 | F39: =IF(F28=0,0,F17/F28) -> 0 | G39: =IF(G28=0,0,G17/G28) -> 0 | H39: =IF(H28=0,0,H17/H28) -> 0 | I39: =IF(I28=0,0,I17/I28) -> 0 | ... N39: =IF(N28=0,0,N17/N28) -> 0 | P39: =IF(AND(O39=0,N39-O39=0),0,IF(AND(O39=0,N39-O39>0),1,(N39-O39)/O39)) -> 0
B40: =IF(B29=0,0,B18/B29) -> 0 | C40: =IF(C29=0,0,C18/C29) -> 0 | D40: =IF(D29=0,0,D18/D29) -> 0 | E40: =IF(E29=0,0,E18/E29) -> 0 | F40: =IF(F29=0,0,F18/F29) -> 0 | G40: =IF(G29=0,0,G18/G29) -> 0 | H40: =IF(H29=0,0,H18/H29) -> 0 | I40: =IF(I29=0,0,I18/I29) -> 0 | ... N40: =IF(N29=0,0,N18/N29) -> 0 | P40: =IF(AND(O40=0,N40-O40=0),0,IF(AND(O40=0,N40-O40>0),1,(N40-O40)/O40)) -> 0
B41: =IF(B30=0,0,B19/B30) -> 0 | C41: =IF(C30=0,0,C19/C30) -> 0 | D41: =IF(D30=0,0,D19/D30) -> 0 | E41: =IF(E30=0,0,E19/E30) -> 0 | F41: =IF(F30=0,0,F19/F30) -> 0 | G41: =IF(G30=0,0,G19/G30) -> 0 | H41: =IF(H30=0,0,H19/H30) -> 0 | I41: =IF(I30=0,0,I19/I30) -> 0 | ... N41: =IF(N30=0,0,N19/N30) -> 0 | P41: =IF(AND(O41=0,N41-O41=0),0,IF(AND(O41=0,N41-O41>0),1,(N41-O41)/O41)) -> 0
A42: 三、审计说明：
A45: 四、审计结论：
A48: 如果单位人工成本异常降低，关注是否存在其他方（如关联方）代付工资的情况

Sheet 制造费用明细表F2-43
A1: 致同会计师事务所
A2: 制造费用明细表
A3: =[6]底稿目录!A2 -> 被审计单位： | F3: =[6]底稿目录!A4 -> 编制人： | K3: =[6]底稿目录!A5 -> 编制日期： | O3: 索引号： | P3: F2-43
A4: =[6]底稿目录!A3 -> 截止日：202X年12月31日 | F4: =[6]底稿目录!A6 -> 复核人： | K4: =[6]底稿目录!A7 -> 复核日期： | O4: 页 次：
A5: 一、审计目标：
A6: 1.资产负债表中记录的存货是存在的，且已经记录在恰当的账户中
A7: 2.所有应记录的存货均已记录，所有应当包括在财务报表中的相关披露均已包括
A8: 3.存货以恰当的金额包括在财务报表中，与之相关的计价或分摊调整已恰当记录，相关披露已得到恰当计量和描述
A9: 二、审计过程：
A10: 取得本期各月及前期制造费用明细情况，将资产折旧与折旧分配表、资产摊销与各项资产摊销分配表等核对一致，关注制造费用分配方法是否合理、适当，本期各月与上期金额是否存在异常变动
A11: 月份 项目 | B11: 1月 | C11: 2月 | D11: 3月 | E11: 4月 | F11: 5月 | G11: 6月 | H11: 7月 | I11: 8月 | J11: 9月 | K11: 10月 | L11: 11月 | M11: 12月 | N11: 合计 | O11: 上年度 | P11: 变动率
A12: 工资 | N12: =SUM(B12:M12) -> 0 | P12: =(N12-O12)/O12 -> #DIV/0!
A13: 福利费 | N13: =SUM(B13:M13) -> 0 | P13: =(N13-O13)/O13 -> #DIV/0!
A14: 修理费 | N14: =SUM(B14:M14) -> 0 | P14: =(N14-O14)/O14 -> #DIV/0!
A15: 办公费 | N15: =SUM(B15:M15) -> 0 | P15: =(N15-O15)/O15 -> #DIV/0!
A16: 差旅费 | N16: =SUM(B16:M16) -> 0 | P16: =(N16-O16)/O16 -> #DIV/0!
A17: 运费 | N17: =SUM(B17:M17) -> 0 | P17: =(N17-O17)/O17 -> #DIV/0!
A18: 折旧费 | N18: =SUM(B18:M18) -> 0 | P18: =(N18-O18)/O18 -> #DIV/0!
A19: 劳动保护费 | N19: =SUM(B19:M19) -> 0 | P19: =(N19-O19)/O19 -> #DIV/0!
A20: 机物料消耗 | N20: =SUM(B20:M20) -> 0 | P20: =(N20-O20)/O20 -> #DIV/0!
A21: 低值易耗品摊销 | N21: =SUM(B21:M21) -> 0 | P21: =(N21-O21)/O21 -> #DIV/0!
A22: 水电费 | N22: =SUM(B22:M22) -> 0 | P22: =(N22-O22)/O22 -> #DIV/0!
A23: 租赁费 | N23: =SUM(B23:M23) -> 0 | P23: =(N23-O23)/O23 -> #DIV/0!
A24: 其他 | N24: =SUM(B24:M24) -> 0 | P24: =(N24-O24)/O24 -> #DIV/0!
A25: 合计 | B25: =SUM(B12:B24) -> 0 | C25: =SUM(C12:C24) -> 0 | D25: =SUM(D12:D24) -> 0 | E25: =SUM(E12:E24) -> 0 | F25: =SUM(F12:F24) -> 0 | G25: =SUM(G12:G24) -> 0 | H25: =SUM(H12:H24) -> 0 | I25: =SUM(I12:I24) -> 0 | ... M25: =SUM(M12:M24) -> 0 | N25: =SUM(B25:M25) -> 0 | O25: =SUM(O12:O24) -> 0 | P25: =(N25-O25)/O25 -> #DIV/0!
A26: 三、审计说明：
A29: 四、审计结论：
A32: 提示：
A33: 1.复核制造费用明细汇总表的正确性，将制造费用明细表中的材料发生额与材料耗用汇总表、工资发生额与工资分配表、折旧发生额与折旧分配表、资产摊销发生额与各项资产摊销分配表及相关账项明细表核对一致，并作交叉索引。
A34: 2.获取制造费用的分配标准和计算方法，评价有关分配标准和计算方法是否合理和适当，以确认在产品中所含直接人工和制造费用是合理的。必要时重新计算。
A35: 3.关注计入生产成本的制造费用是否已扣除非正常消耗的制造费用，如非正常的低生产量、闲置设备等产生的费用。
A36: 4.关注存货成本是否包含了应费用化的项目（如停工损失等非正常消耗的直接材料、直接人工和制造费用，完工后的仓储费用，与销售相关的运输费，超范围、超期的借款费用资本化，不能归属于使存货达到目前场所和状态的其他支出）

Sheet 生产成本分配F2-44
A1: 致同会计师事务所
A2: 抽查×月×车间生产成本分配表
A3: =[6]底稿目录!A2 -> 被审计单位： | E3: =[6]底稿目录!A4 -> 编制人： | I3: =[6]底稿目录!A5 -> 编制日期： | M3: 索引号： | N3: =[6]底稿目录!F9 -> F2-44
A4: =[6]底稿目录!A3 -> 截止日：202X年12月31日 | E4: =[6]底稿目录!A6 -> 复核人： | I4: =[6]底稿目录!A7 -> 复核日期： | M4: 页 次：
A5: ×月×车间生产成本发生额： | C5: 直接材料：
C6: 直接人工：
C7: 制造费用：
C8: 其他
C9: 合计： | D9: =SUM(D5:D8) -> 0
A10: 产成品名称 | B10: 产量 | C10: 入库产品成本单价 | D10: 分配标准（产量、工时、定额成本等） | E10: 直接材料分配率 | F10: 直接材料分配额 | G10: 直接人工分配率 | H10: 直接人工分配额 | I10: 制造费用分配率 | J10: 制造费用分配额 | K10: 其他分配率 | L10: 其他分配额 | M10: 应计单位成本 | N10: 核对
E11: =IF($D$23=0,0,$D$5/$D$23) -> 0 | F11: =E11*D11 -> 0 | G11: =IF($D$23=0,0,$D$6/$D$23) -> 0 | H11: =G11*D11 -> 0 | I11: =IF($D$23=0,0,$D$7/$D$23) -> 0 | J11: =I11*D11 -> 0 | K11: =IF($D$23=0,0,$D$8/$D$23) -> 0 | L11: =K11*D11 -> 0 | M11: =IF(B11=0,0,SUM(F11,H11,J11,L11)/B11) -> 0 | N11: =IF(M11=C11,"OK",M11-C11) -> OK
E12: =IF($D$23=0,0,$D$5/$D$23) -> 0 | F12: =E12*D12 -> 0 | G12: =IF($D$23=0,0,$D$6/$D$23) -> 0 | H12: =G12*D12 -> 0 | I12: =IF($D$23=0,0,$D$7/$D$23) -> 0 | J12: =I12*D12 -> 0 | K12: =IF($D$23=0,0,$D$8/$D$23) -> 0 | L12: =K12*D12 -> 0 | M12: =IF(B12=0,0,SUM(F12,H12,J12,L12)/B12) -> 0 | N12: =IF(M12=C12,"OK",M12-C12) -> OK
E13: =IF($D$23=0,0,$D$5/$D$23) -> 0 | F13: =E13*D13 -> 0 | G13: =IF($D$23=0,0,$D$6/$D$23) -> 0 | H13: =G13*D13 -> 0 | I13: =IF($D$23=0,0,$D$7/$D$23) -> 0 | J13: =I13*D13 -> 0 | K13: =IF($D$23=0,0,$D$8/$D$23) -> 0 | L13: =K13*D13 -> 0 | M13: =IF(B13=0,0,SUM(F13,H13,J13,L13)/B13) -> 0 | N13: =IF(M13=C13,"OK",M13-C13) -> OK
E14: =IF($D$23=0,0,$D$5/$D$23) -> 0 | F14: =E14*D14 -> 0 | G14: =IF($D$23=0,0,$D$6/$D$23) -> 0 | H14: =G14*D14 -> 0 | I14: =IF($D$23=0,0,$D$7/$D$23) -> 0 | J14: =I14*D14 -> 0 | K14: =IF($D$23=0,0,$D$8/$D$23) -> 0 | L14: =K14*D14 -> 0 | M14: =IF(B14=0,0,SUM(F14,H14,J14,L14)/B14) -> 0 | N14: =IF(M14=C14,"OK",M14-C14) -> OK
E15: =IF($D$23=0,0,$D$5/$D$23) -> 0 | F15: =E15*D15 -> 0 | G15: =IF($D$23=0,0,$D$6/$D$23) -> 0 | H15: =G15*D15 -> 0 | I15: =IF($D$23=0,0,$D$7/$D$23) -> 0 | J15: =I15*D15 -> 0 | K15: =IF($D$23=0,0,$D$8/$D$23) -> 0 | L15: =K15*D15 -> 0 | M15: =IF(B15=0,0,SUM(F15,H15,J15,L15)/B15) -> 0 | N15: =IF(M15=C15,"OK",M15-C15) -> OK
E16: =IF($D$23=0,0,$D$5/$D$23) -> 0 | F16: =E16*D16 -> 0 | G16: =IF($D$23=0,0,$D$6/$D$23) -> 0 | H16: =G16*D16 -> 0 | I16: =IF($D$23=0,0,$D$7/$D$23) -> 0 | J16: =I16*D16 -> 0 | K16: =IF($D$23=0,0,$D$8/$D$23) -> 0 | L16: =K16*D16 -> 0 | M16: =IF(B16=0,0,SUM(F16,H16,J16,L16)/B16) -> 0 | N16: =IF(M16=C16,"OK",M16-C16) -> OK
E17: =IF($D$23=0,0,$D$5/$D$23) -> 0 | F17: =E17*D17 -> 0 | G17: =IF($D$23=0,0,$D$6/$D$23) -> 0 | H17: =G17*D17 -> 0 | I17: =IF($D$23=0,0,$D$7/$D$23) -> 0 | J17: =I17*D17 -> 0 | K17: =IF($D$23=0,0,$D$8/$D$23) -> 0 | L17: =K17*D17 -> 0 | M17: =IF(B17=0,0,SUM(F17,H17,J17,L17)/B17) -> 0 | N17: =IF(M17=C17,"OK",M17-C17) -> OK
E18: =IF($D$23=0,0,$D$5/$D$23) -> 0 | F18: =E18*D18 -> 0 | G18: =IF($D$23=0,0,$D$6/$D$23) -> 0 | H18: =G18*D18 -> 0 | I18: =IF($D$23=0,0,$D$7/$D$23) -> 0 | J18: =I18*D18 -> 0 | K18: =IF($D$23=0,0,$D$8/$D$23) -> 0 | L18: =K18*D18 -> 0 | M18: =IF(B18=0,0,SUM(F18,H18,J18,L18)/B18) -> 0 | N18: =IF(M18=C18,"OK",M18-C18) -> OK
E19: =IF($D$23=0,0,$D$5/$D$23) -> 0 | F19: =E19*D19 -> 0 | G19: =IF($D$23=0,0,$D$6/$D$23) -> 0 | H19: =G19*D19 -> 0 | I19: =IF($D$23=0,0,$D$7/$D$23) -> 0 | J19: =I19*D19 -> 0 | K19: =IF($D$23=0,0,$D$8/$D$23) -> 0 | L19: =K19*D19 -> 0 | M19: =IF(B19=0,0,SUM(F19,H19,J19,L19)/B19) -> 0 | N19: =IF(M19=C19,"OK",M19-C19) -> OK
E20: =IF($D$23=0,0,$D$5/$D$23) -> 0 | F20: =E20*D20 -> 0 | G20: =IF($D$23=0,0,$D$6/$D$23) -> 0 | H20: =G20*D20 -> 0 | I20: =IF($D$23=0,0,$D$7/$D$23) -> 0 | J20: =I20*D20 -> 0 | K20: =IF($D$23=0,0,$D$8/$D$23) -> 0 | L20: =K20*D20 -> 0 | M20: =IF(B20=0,0,SUM(F20,H20,J20,L20)/B20) -> 0 | N20: =IF(M20=C20,"OK",M20-C20) -> OK
E21: =IF($D$23=0,0,$D$5/$D$23) -> 0 | F21: =E21*D21 -> 0 | G21: =IF($D$23=0,0,$D$6/$D$23) -> 0 | H21: =G21*D21 -> 0 | I21: =IF($D$23=0,0,$D$7/$D$23) -> 0 | J21: =I21*D21 -> 0 | K21: =IF($D$23=0,0,$D$8/$D$23) -> 0 | L21: =K21*D21 -> 0 | M21: =IF(B21=0,0,SUM(F21,H21,J21,L21)/B21) -> 0 | N21: =IF(M21=C21,"OK",M21-C21) -> OK
E22: =IF($D$23=0,0,$D$5/$D$23) -> 0 | F22: =E22*D22 -> 0 | G22: =IF($D$23=0,0,$D$6/$D$23) -> 0 | H22: =G22*D22 -> 0 | I22: =IF($D$23=0,0,$D$7/$D$23) -> 0 | J22: =I22*D22 -> 0 | K22: =IF($D$23=0,0,$D$8/$D$23) -> 0 | L22: =K22*D22 -> 0 | M22: =IF(B22=0,0,SUM(F22,H22,J22,L22)/B22) -> 0 | N22: =IF(M22=C22,"OK",M22-C22) -> OK
A23: 合计 | B23: =SUM(B11:B22) -> 0 | C23: =IF(COUNTA(C11:C22)=0,0,SUM(C11:C22)/COUNTA(C11:C22)) -> 0 | D23: =SUM(D11:D22) -> 0 | E23: =IF($D$23=0,0,$D$5/$D$23) -> 0 | F23: =SUM(F11:F22) -> 0 | G23: =IF($D$23=0,0,$D$6/$D$23) -> 0 | H23: =SUM(H11:H22) -> 0 | I23: =IF($D$23=0,0,$D$7/$D$23) -> 0 | J23: =SUM(J11:J22) -> 0 | K23: =IF($D$23=0,0,$D$8/$D$23) -> 0 | L23: =SUM(L11:L22) -> 0 | M23: ——
A24: 1、审计说明：
A27: 2、审计结论：

Sheet 底稿目录 (6)
A1: 底稿开列时，可先在以下单元格填写有关内容，以便其他底稿引用有关数据：
A2: 被审计单位： | D2: 序号 | E2: 内容 | F2: 索引号
A3: 截止日：202X年12月31日 | D3: 1 | E3: 存货跌价准备测试表 | F3: F2-47
A4: 编制人： | D4: 2 | E4: 长库龄/呆滞/超过保质期存货明细表 | F4: F2-48
A5: 编制日期： | D5: 3 | E5: 存货跌价准备转回核对表 | F5: F2-49
A6: 复核人：
A7: 复核日期：

Sheet 跌价准备测试表F2-47
A1: 致同会计师事务所
A2: 存货跌价准备测试表
A3: =[14]底稿目录!A2 -> 被审计单位： | K3: =[14]底稿目录!A4 -> 编制人： | U3: =[14]底稿目录!A5 -> 编制日期： | Z3: 索引号： | AA3: =[14]底稿目录!F3 -> F2-47
A4: =[14]底稿目录!A3 -> 截止日：202X年12月31日 | K4: =[14]底稿目录!A6 -> 复核人： | U4: =[14]底稿目录!A7 -> 复核日期： | Z4: 页次：
A5: 一、审计目标：
A6: 存货以恰当的金额包括在财务报表中，与之相关的计价或分摊调整已恰当记录，相关披露已得到恰当计量和描述
A7: 二、样本选取标准与规模：
A8: 测试总体： | B8: 如存货XX种类、XX数量、XX金额 | M8: 特定样本： | O8: XX金额以上（大额）、XX呆滞存货全部测试
A9: 抽样总体： | B9: 测试范围扣除特定样本以外的样本，共XX笔 | M9: 确定的抽样样本量： | P9: 抽取XX笔（如果使用了样本计算器计算样本量，样本量计算过程见<XX>底稿）
A10: 抽样方法： | B10: 随机选样/系统选样/货币单元抽样/随意选样 | M10: 抽样过程： | O10: 使用IDEA（XX抽样工具）选择XX数量、金额XX的样本进行测试，抽样工具中的样本选择过程和结果见<XX>底稿
A11: 三、审计过程：
A12: 1.检查存货跌价准备计提和核销的批准程序，取得书面报告等证明文件。获取企业支持性的（辅助性的）计算过程，并理解其应用的方法；
A13: 2.评价存货跌价准备所依据的资料、假设及计提方法，考虑是否有确凿证据为基础计算确定存货的可变现净值，检查其合理性；
A14: 3.对于用于生产而持有的原材料，检查是否以所生产的产成品的估计售价减去至完工时估计将要发生的成本、估计的销售费用和相关税费后的金额，作为其可变现净值的确定基础；
A15: 4.库存商品和用于出售而持有的原材料等直接用于出售的存货，检查是否以该存货的估计售价减去估计的销售费用和相关税费后的金额，作为其可变现净值的确定基础；
A16: 5.检查为执行销售合同而持有的库存商品等存货，是否以合同价格作为其可变现净值的确定基础；如果被审计单位持有库存商品的数量多于销售合同订购数量，超出部分的库存商品可变现净值是否以一般销售价格为计量基础；
A17: 6.根据取得存货明细表中的库龄分析；结合存货盘点观察识别滞销积压的、停止经营，或陈旧过时的项目、容易过期失效的项目、长期未结转产成品的在产品等。
A18: 存货类别 | B18: 存货编码 | C18: 存货名称 | D18: 单位 | E18: 结存数量 | F18: 账面成本 | G18: 账面单位成本 | H18: 库龄 | L18: 品质状况（正常、残次、毁损、滞销等） | M18: 持有目的 （出售/继续生产） | N18: 销售费用率 | O18: 税率 | P18: 可变现净值 | W18: 应计提准备数 | X18: 存货审定数 | Y18: 账面计提减值准备 | Z18: 应补提减值准备 | AA18: 备注
H19: 1年以内 | I19: 1-2年 | J19: 2-3年 | K19: 3年以上 | P19: 估计售价-单价 | Q19: 估计售价-总价 | R19: 售价依据及索引 | S19: 至完工时估计将要发生的成本 | T19: 估计的销售费用 | U19: 相关税费 | V19: 可变现净值
G20: =F20/E20 -> #DIV/0! | Q20: =P20*E20 -> 0 | T20: =N20*Q20 -> 0 | U20: =O20*Q20 -> 0 | V20: =Q20-S20-T20-U20 -> 0 | W20: =IF(V20<F20,F20-V20,0) -> 0 | X20: =MIN(F20,V20) -> 0 | Z20: =W20-Y20 -> 0 | AB20: 如果有合同的存货计提了存货跌价准备，应进一步考虑是否为亏损合同以及是否应计提亏损合同预计负债
G21: =F21/E21 -> #DIV/0! | Q21: =P21*E21 -> 0 | T21: =N21*Q21 -> 0 | U21: =O21*Q21 -> 0 | V21: =Q21-S21-T21-U21 -> 0 | W21: =IF(V21<F21,F21-V21,0) -> 0 | X21: =MIN(F21,V21) -> 0 | Z21: =W21-Y21 -> 0
G22: =F22/E22 -> #DIV/0! | Q22: =P22*E22 -> 0 | T22: =N22*Q22 -> 0 | U22: =O22*Q22 -> 0 | V22: =Q22-S22-T22-U22 -> 0 | W22: =IF(V22<F22,F22-V22,0) -> 0 | X22: =MIN(F22,V22) -> 0 | Z22: =W22-Y22 -> 0
G23: =F23/E23 -> #DIV/0! | Q23: =P23*E23 -> 0 | T23: =N23*Q23 -> 0 | U23: =O23*Q23 -> 0 | V23: =Q23-S23-T23-U23 -> 0 | W23: =IF(V23<F23,F23-V23,0) -> 0 | X23: =MIN(F23,V23) -> 0 | Z23: =W23-Y23 -> 0
G24: =F24/E24 -> #DIV/0! | Q24: =P24*E24 -> 0 | T24: =N24*Q24 -> 0 | U24: =O24*Q24 -> 0 | V24: =Q24-S24-T24-U24 -> 0 | W24: =IF(V24<F24,F24-V24,0) -> 0 | X24: =MIN(F24,V24) -> 0 | Z24: =W24-Y24 -> 0
