Workbook
Name _.dbf: #REF!
Name _00510: #REF!
Name _1、: #REF!
Name _1、受本循环影响的相关交易和账户余额: #REF!
Name _13: #REF!
Name _1w6_: #REF!
Name _1固定资产数据库_筛选打印: #REF!
Name _2、主要业务活动: #REF!
Name _2、注册会计师通常应在本循环中了解与上述业务活动相关的内部控制_如果计划在其他业务循环中对上述: #REF!
Name _2其他资产_开办费除外_明细表: #REF!
Name _3余额表_一级_.dbf: #REF!
Name _DAT1: #REF!
Name _DAT10: #REF!
Name _DAT11: #REF!
Name _DAT2: #REF!
Name _DAT3: #REF!
Name _DAT4: #REF!
Name _DAT5: #REF!
Name _DAT6: #REF!
Name _DAT7: #REF!
Name _DAT8: #REF!
Name _DAT9: #REF!
Name _YE1: #REF!
Name _YS1: #REF!
Name _YS2: '[1]YS02-02'!#REF!
Name a: #REF!
Name a1c1: #REF!,#REF!
Name aa: #REF!
Name aaa: #REF!
Name agmmt: #REF!
Name agmt: #REF!
Name agmt1: #REF!
Name al: #REF!
Name avg_days: [2]Sheet3!$A$2
Name a暗暗: [3]企业表一!$F$20
Name b: #REF!
Name BD: #REF!
Name beg_day: #REF!
Name beg_day1: #REF!
Name CarryKnown: #REF!
Name CarryKnownTable: #REF!
Name CarryLikely: #REF!
Name CarryLikelyTable: #REF!
Name Carryover_Effect_of_Prior_Year: #REF!
Name CarryoverTitle: #REF!
Name CC_Instruction: #REF!
Name CE_CarryKnownProtection: #REF!
Name CE_CarryKnownTable: #REF!
Name CE_CarryLikely1Protection: #REF!
Name CE_CarryLikely1Table: #REF!
Name CE_CarryLikely2Protection: #REF!
Name CE_CarryLikely2Table: #REF!
Name CE_CarryTaxable: #REF!
Name CE_Desc: #REF!
Name CE_Income: #REF!
Name CE_KeepFormat: #REF!
Name CE_KnownChange: #REF!
Name CE_KnownFormulaProtection: #REF!
Name CE_KnownImpact: #REF!
Name CE_Likely1Change: #REF!

Sheet 基本信息表
A1: 合并范围内的子企业基本信息表
A2: 序号 | B2: 最终控制方合并范围内的子企业名称 | C2: 企业代码 | D2: 核算科目 （长投、可供、交易性等） | E2: 核算方式 （长投可分成本法、权益法） | F2: 持股比例变动情况 | H2: 当期新增 | Q2: 当期减少
H3: 购买日 | I3: 合并类型 | J3: 首次合并日 | K3: 涉及合并 | O3: 不涉及合并 | Q3: 合并范围内投资情况 | V3: 出表日后减持情况
F4: 是否变动 | G4: 变动次数 | K4: 非同一控制首次合并 | M4: 同一控制首次合并 | O4: 投资成本 | P4: 持股比例 | Q4: 首次出表日情况 | T4: 出表日前减持情况
K5: 投资成本 | L5: 持股比例 | M5: 投资成本 | N5: 持股比例 | Q5: 首次出表日 | R5: 投资减少金额 | S5: 持股比例 | T5: 是否有减持 | U5: 减持次数 | V5: 是否有减持 | W5: 减持次数
A6: 1 | B6: 单位1
A7: 2 | B7: 单位2
A8: 3 | B8: 单位3
A9: 4 | B9: 单位4
A10: 5 | B10: ……
A11: 小计
D16: 下拉选项 | E16: 下拉选项 | F16: 下拉选项 | I16: 下拉选项
D17: 长期股权投资 | E17: 成本法 | F17: 是 | I17: 同控
D18: 可供出售金融资产 | E18: 权益法 | F18: 否 | I18: 非同控
D19: 交易性金融资产 | E19: 公允价值
D20: 其他权益工具投资
D21: 其他非流动金融资产
D22: 其他非流动资产

Sheet 投资明细-成本法和公允值
A1: 合并范围内的子企业明细
A2: （含非长投列报的所有合并范围内的企业，权益法核算的长投见下表）
A3: 序号 | B3: 最终控制方合并范围内的子企业名称 | C3: 企业代码 | D3: 本期现金红利 | E3: 期初余额 | J3: 本期增加 | N3: 本期减少 | R3: 期末余额
E4: 投资成本 | I4: 公允价值 | J4: 投资成本 | M4: 公允价值 | N4: 投资成本 | Q4: 公允价值 | R4: 投资成本 | V4: 公允价值
E5: 投资比例 | F5: 金额 | G5: 减值准备金额 | H5: 长投净额 | J5: 投资比例 | K5: 金额 | L5: 减值准备 | N5: 投资比例 | O5: 金额 | P5: 减值准备 | R5: 投资比例 | S5: 投资成本金额 | T5: 减值准备金额 | U5: 长投净额
A6: 1 | B6: 单位1 | H6: =F6-G6 -> 0 | R6: =E6+J6-N6 -> 0 | S6: =F6+K6-O6 -> 0 | T6: =G6+L6-P6 -> 0 | U6: =S6-T6 -> 0 | V6: =I6+M6-Q6 -> 0
A7: 2 | B7: 单位2 | H7: =F7-G7 -> 0 | R7: =E7+J7-N7 -> 0 | S7: =F7+K7-O7 -> 0 | T7: =G7+L7-P7 -> 0 | U7: =S7-T7 -> 0 | V7: =I7+M7-Q7 -> 0
A8: 3 | B8: 单位3 | H8: =F8-G8 -> 0 | R8: =E8+J8-N8 -> 0 | S8: =F8+K8-O8 -> 0 | T8: =G8+L8-P8 -> 0 | U8: =S8-T8 -> 0 | V8: =I8+M8-Q8 -> 0
A9: 4 | B9: 单位4 | H9: =F9-G9 -> 0 | R9: =E9+J9-N9 -> 0 | S9: =F9+K9-O9 -> 0 | T9: =G9+L9-P9 -> 0 | U9: =S9-T9 -> 0 | V9: =I9+M9-Q9 -> 0
B10: …… | H10: =F10-G10 -> 0 | R10: =E10+J10-N10 -> 0 | S10: =F10+K10-O10 -> 0 | T10: =G10+L10-P10 -> 0 | U10: =S10-T10 -> 0 | V10: =I10+M10-Q10 -> 0
A11: 成本法小计 | D11: =SUM(D6:D10) -> 0 | E11: -- | F11: =SUM(F6:F10) -> 0 | G11: =SUM(G6:G10) -> 0 | H11: =SUM(H6:H10) -> 0 | J11: -- | K11: =SUM(K6:K10) -> 0 | L11: =SUM(L6:L10) -> 0 | N11: -- | O11: =SUM(O6:O10) -> 0 | P11: =SUM(P6:P10) -> 0 | R11: -- | S11: =SUM(S6:S10) -> 0 | T11: =SUM(T6:T10) -> 0 | U11: =SUM(U6:U10) -> 0 | V11: =SUM(V6:V10) -> 0
A12: 说明：如果单位涉及公允值计量，需同步填投资比例、投资成本金额和公允价值，无需填写减值准备。

Sheet 投资明细-权益法
A1: 按权益法核算的长期股权投资
A2: 序号 | B2: 被投资单位名称 | C2: 企业代码 | D2: 期初余额 | G2: 本期增加 | O2: 本期减少 | T2: 期末余额
D3: 投资比例 | E3: 长投金额 | F3: 减值准备 | G3: 投资比例 | H3: 投资成本增加 | I3: 权益增加 | M3: 其他 | N3: 减值准备 | O3: 投资比例 | P3: 投资成本减少 | Q3: 本期分回利润 | R3: 其他 | S3: 减值准备 | T3: 投资比例 | U3: 长投金额 | V3: 减值准备
I4: 损益调整 | J4: 其他综合收益 | K4: 其他权益变动 | L4: 权益增加小计
A5: 1 | B5: 单位1 | L5: =SUM(I5:K5) -> 0 | T5: =D5+G5-O5 -> 0 | V5: =F5+H5+L5-P5-Q5+N5-S5 -> 0
A6: 2 | B6: 单位2 | L6: =SUM(I6:K6) -> 0 | T6: =D6+G6-O6 -> 0 | V6: =F6+H6+L6-P6-Q6+N6-S6 -> 0
A7: 3 | B7: 单位3 | L7: =SUM(I7:K7) -> 0 | T7: =D7+G7-O7 -> 0 | V7: =F7+H7+L7-P7-Q7+N7-S7 -> 0
A8: 4 | B8: 单位4 | L8: =SUM(I8:K8) -> 0 | T8: =D8+G8-O8 -> 0 | V8: =F8+H8+L8-P8-Q8+N8-S8 -> 0
A9: 5 | B9: …… | L9: =SUM(I9:K9) -> 0 | T9: =D9+G9-O9 -> 0 | V9: =F9+H9+L9-P9-Q9+N9-S9 -> 0
A10: 小计 | D10: -- | E10: =SUM(E5:E9) -> 0 | F10: =SUM(F5:F9) -> 0 | G10: -- | H10: =SUM(H5:H9) -> 0 | I10: =SUM(I5:I9) -> 0 | J10: =SUM(J5:J9) -> 0 | K10: =SUM(K5:K9) -> 0 | L10: =SUM(I10:K10) -> 0 | M10: =SUM(M5:M9) -> 0 | N10: =SUM(N5:N9) -> 0 | O10: =SUM(O5:O9) -> 0 | P10: =SUM(P5:P9) -> 0 | Q10: =SUM(Q5:Q9) -> 0 | R10: =SUM(R5:R9) -> 0 | S10: =SUM(S5:S9) -> 0 | T10: -- | U10: =SUM(U5:U9) -> 0 | V10: =SUM(V5:V9) -> 0

Sheet 净资产表
A1: 合并范围内的子企业净资产和损益变动表
A2: 序号 | B2: 项目 | C2: 合计 | D2: 母公司 | E2: 单位1 | F2: 单位2 | G2: 单位3 | H2: 单位4 | I2: 单位5 | J2: 单位6
D3: 1 | E3: 持股比例% | F3: 持股比例% | G3: 持股比例% | H3: 持股比例% | I3: 持股比例% | J3: 持股比例%
A4: 1 | B4: 所有者权益/股东权益
B5: 期初合计： | C5: =C6+C7+C8+C10+C11+C12+C13+C14-C9 -> 0 | E5: =E6+E7+E8+E10+E11+E12+E13+E14-E9 -> 0 | F5: =F6+F7+F8+F10+F11+F12+F13+F14-F9 -> 0 | G5: =G6+G7+G8+G10+G11+G12+G13+G14-G9 -> 0 | H5: =H6+H7+H8+H10+H11+H12+H13+H14-H9 -> 0 | I5: =I6+I7+I8+I10+I11+I12+I13+I14-I9 -> 0 | J5: =J6+J7+J8+J10+J11+J12+J13+J14-J9 -> 0
B6: 实收资本（或股本） | C6: =SUM(E6:J6) -> 0
B7: 其他权益工具 | C7: =SUM(E7:J7) -> 0
B8: 资本公积 | C8: =SUM(E8:J8) -> 0
B9: 减：库存股 | C9: =SUM(E9:J9) -> 0
B10: 其他综合收益 | C10: =SUM(E10:J10) -> 0
B11: 专项储备 | C11: =SUM(E11:J11) -> 0
B12: 盈余公积 | C12: =SUM(E12:J12) -> 0
B13: △一般风险准备 | C13: =SUM(E13:J13) -> 0
B14: 未分配利润 | C14: =SUM(E14:J14) -> 0
B15: 本期增加 | C15: =C16+C17+C18+C20+C21+C22+C23+C24-C19 -> 0 | E15: =E16+E17+E18+E20+E21+E22+E23+E24-E19 -> 0 | F15: =F16+F17+F18+F20+F21+F22+F23+F24-F19 -> 0 | G15: =G16+G17+G18+G20+G21+G22+G23+G24-G19 -> 0 | H15: =H16+H17+H18+H20+H21+H22+H23+H24-H19 -> 0 | I15: =I16+I17+I18+I20+I21+I22+I23+I24-I19 -> 0 | J15: =J16+J17+J18+J20+J21+J22+J23+J24-J19 -> 0
B16: 实收资本（或股本） | C16: =SUM(E16:J16) -> 0
B17: 其他权益工具 | C17: =SUM(E17:J17) -> 0
B18: 资本公积 | C18: =SUM(E18:J18) -> 0
B19: 减：库存股 | C19: =SUM(E19:J19) -> 0
B20: 其他综合收益 | C20: =SUM(E20:J20) -> 0
B21: 专项储备 | C21: =SUM(E21:J21) -> 0
B22: 盈余公积 | C22: =SUM(E22:J22) -> 0
B23: △一般风险准备 | C23: =SUM(E23:J23) -> 0
B24: 未分配利润 | C24: =SUM(E24:J24) -> 0
B25: 本期减少 | C25: =C26+C27+C28+C30+C31+C32+C33+C34-C29 -> 0 | E25: =E26+E27+E28+E30+E31+E32+E33+E34-E29 -> 0 | F25: =F26+F27+F28+F30+F31+F32+F33+F34-F29 -> 0 | G25: =G26+G27+G28+G30+G31+G32+G33+G34-G29 -> 0 | H25: =H26+H27+H28+H30+H31+H32+H33+H34-H29 -> 0 | I25: =I26+I27+I28+I30+I31+I32+I33+I34-I29 -> 0 | J25: =J26+J27+J28+J30+J31+J32+J33+J34-J29 -> 0
B26: 实收资本（或股本） | C26: =SUM(E26:J26) -> 0
B27: 其他权益工具 | C27: =SUM(E27:J27) -> 0
B28: 资本公积 | C28: =SUM(E28:J28) -> 0
B29: 减：库存股 | C29: =SUM(E29:J29) -> 0
B30: 其他综合收益 | C30: =SUM(E30:J30) -> 0
B31: 专项储备 | C31: =SUM(E31:J31) -> 0
B32: 盈余公积 | C32: =SUM(E32:J32) -> 0
B33: △一般风险准备 | C33: =SUM(E33:J33) -> 0
B34: 未分配利润 | C34: =SUM(E34:J34) -> 0
B35: 期末金额 | C35: =C36+C37+C38+C40+C41+C42+C43+C44-C39 -> 0 | E35: =E36+E37+E38+E40+E41+E42+E43+E44-E39 -> 0 | F35: =F36+F37+F38+F40+F41+F42+F43+F44-F39 -> 0 | G35: =G36+G37+G38+G40+G41+G42+G43+G44-G39 -> 0 | H35: =H36+H37+H38+H40+H41+H42+H43+H44-H39 -> 0 | I35: =I36+I37+I38+I40+I41+I42+I43+I44-I39 -> 0 | J35: =J36+J37+J38+J40+J41+J42+J43+J44-J39 -> 0
B36: 实收资本（或股本） | C36: =C6+C16-C26 -> 0 | E36: =E6+E16-E26 -> 0 | F36: =F6+F16-F26 -> 0 | G36: =G6+G16-G26 -> 0 | H36: =H6+H16-H26 -> 0 | I36: =I6+I16-I26 -> 0 | J36: =J6+J16-J26 -> 0
B37: 其他权益工具 | C37: =C7+C17-C27 -> 0 | E37: =E7+E17-E27 -> 0 | F37: =F7+F17-F27 -> 0 | G37: =G7+G17-G27 -> 0 | H37: =H7+H17-H27 -> 0 | I37: =I7+I17-I27 -> 0 | J37: =J7+J17-J27 -> 0
B38: 资本公积 | C38: =C8+C18-C28 -> 0 | E38: =E8+E18-E28 -> 0 | F38: =F8+F18-F28 -> 0 | G38: =G8+G18-G28 -> 0 | H38: =H8+H18-H28 -> 0 | I38: =I8+I18-I28 -> 0 | J38: =J8+J18-J28 -> 0
B39: 减：库存股 | C39: =C9+C19-C29 -> 0 | E39: =E9+E19-E29 -> 0 | F39: =F9+F19-F29 -> 0 | G39: =G9+G19-G29 -> 0 | H39: =H9+H19-H29 -> 0 | I39: =I9+I19-I29 -> 0 | J39: =J9+J19-J29 -> 0
B40: 其他综合收益 | C40: =C10+C20-C30 -> 0 | E40: =E10+E20-E30 -> 0 | F40: =F10+F20-F30 -> 0 | G40: =G10+G20-G30 -> 0 | H40: =H10+H20-H30 -> 0 | I40: =I10+I20-I30 -> 0 | J40: =J10+J20-J30 -> 0
B41: 专项储备 | C41: =C11+C21-C31 -> 0 | E41: =E11+E21-E31 -> 0 | F41: =F11+F21-F31 -> 0 | G41: =G11+G21-G31 -> 0 | H41: =H11+H21-H31 -> 0 | I41: =I11+I21-I31 -> 0 | J41: =J11+J21-J31 -> 0
B42: 盈余公积 | C42: =C12+C22-C32 -> 0 | E42: =E12+E22-E32 -> 0 | F42: =F12+F22-F32 -> 0 | G42: =G12+G22-G32 -> 0 | H42: =H12+H22-H32 -> 0 | I42: =I12+I22-I32 -> 0 | J42: =J12+J22-J32 -> 0
B43: △一般风险准备 | C43: =C13+C23-C33 -> 0 | E43: =E13+E23-E33 -> 0 | F43: =F13+F23-F33 -> 0 | G43: =G13+G23-G33 -> 0 | H43: =H13+H23-H33 -> 0 | I43: =I13+I23-I33 -> 0 | J43: =J13+J23-J33 -> 0
B44: 未分配利润 | C44: =C14+C24-C34 -> 0 | E44: =E14+E24-E34 -> 0 | F44: =F14+F24-F34 -> 0 | G44: =G14+G24-G34 -> 0 | H44: =H14+H24-H34 -> 0 | I44: =I14+I24-I34 -> 0 | J44: =J14+J24-J34 -> 0
A46: 2 | B46: 利润及利润分配表
B47: 一、期初金额 | C47: =SUM(E47:J47) -> 0 | E47: =E14 -> 0 | F47: =F14 -> 0 | G47: =G14 -> 0 | H47: =H14 -> 0 | I47: =I14 -> 0 | J47: =J14 -> 0
B48: 二、本年增减变动金额 | C48: =SUM(E48:J48) -> 0 | E48: =E49+E51+E56+E59+E69 -> 0 | F48: =F49+F51+F56+F59+F69 -> 0 | G48: =G49+G51+G56+G59+G69 -> 0 | H48: =H49+H51+H56+H59+H69 -> 0 | I48: =I49+I51+I56+I59+I69 -> 0 | J48: =J49+J51+J56+J59+J69 -> 0
B49: （一）综合收益总额 | C49: =SUM(E49:J49) -> 0
B50: 其中：当期归母净利润 | C50: =SUM(E50:J50) -> 0
B51: （二）所有者投入和减少资本 | C51: =SUM(E51:J51) -> 0 | E51: =E52+E53+E54+E55 -> 0 | F51: =F52+F53+F54+F55 -> 0 | G51: =G52+G53+G54+G55 -> 0 | H51: =H52+H53+H54+H55 -> 0 | I51: =I52+I53+I54+I55 -> 0 | J51: =J52+J53+J54+J55 -> 0
B52: 2-1所有者投入的普通股 | C52: =SUM(E52:J52) -> 0
B53: 2-2其他权益工具持有者投入资本 | C53: =SUM(E53:J53) -> 0
B54: 2-3股份支付计入所有者权益的金额 | C54: =SUM(E54:J54) -> 0
B55: 2-4其他 | C55: =SUM(E55:J55) -> 0
B56: （三）专项储备提取和使用 | C56: =SUM(E56:J56) -> 0 | E56: =E57-E58 -> 0 | F56: =F57-F58 -> 0 | G56: =G57-G58 -> 0 | H56: =H57-H58 -> 0 | I56: =I57-I58 -> 0 | J56: =J57-J58 -> 0
B57: 3-1提取专项储备 | C57: =SUM(E57:J57) -> 0
B58: 3-2使用专项储备 | C58: =SUM(E58:J58) -> 0
B59: （四）利润分配 | C59: =SUM(E59:J59) -> 0 | E59: =E60+E66+E67+E68 -> 0 | F59: =F60+F66+F67+F68 -> 0 | G59: =G60+G66+G67+G68 -> 0 | H59: =H60+H66+H67+H68 -> 0 | I59: =I60+I66+I67+I68 -> 0 | J59: =J60+J66+J67+J68 -> 0
B60: 4-1提取盈余公积 | C60: =SUM(E60:J60) -> 0 | E60: =E61+E62+E63+E64+E65 -> 0 | F60: =F61+F62+F63+F64+F65 -> 0 | G60: =G61+G62+G63+G64+G65 -> 0 | H60: =H61+H62+H63+H64+H65 -> 0 | I60: =I61+I62+I63+I64+I65 -> 0 | J60: =J61+J62+J63+J64+J65 -> 0
B61: 4-1-1法定公积金 | C61: =SUM(E61:J61) -> 0
B62: 4-1-2任意公积金 | C62: =SUM(E62:J62) -> 0
B63: 4-1-3#储备基金 | C63: =SUM(E63:J63) -> 0
B64: 4-1-4#企业发展基金 | C64: =SUM(E64:J64) -> 0
B65: 4-1-5#利润归还投资 | C65: =SUM(E65:J65) -> 0
B66: 4-2△提取一般风险准备 | C66: =SUM(E66:J66) -> 0
B67: 4-3对所有者（或股东）的分配 | C67: =SUM(E67:J67) -> 0
B68: 4-4其他 | C68: =SUM(E68:J68) -> 0
B69: （五）所有者权益内部结转 | C69: =SUM(E69:J69) -> 0 | E69: =E70+E71+E73+E72+E74+E75 -> 0 | F69: =F70+F71+F73+F72+F74+F75 -> 0 | G69: =G70+G71+G73+G72+G74+G75 -> 0 | H69: =H70+H71+H73+H72+H74+H75 -> 0 | I69: =I70+I71+I73+I72+I74+I75 -> 0 | J69: =J70+J71+J73+J72+J74+J75 -> 0
B70: 5-1资本公积转增资本（或股本） | C70: =SUM(E70:J70) -> 0
B71: 5-2盈余公积转增资本（或股本） | C71: =SUM(E71:J71) -> 0
B72: 5-3弥补亏损 | C72: =SUM(E72:J72) -> 0
B73: 5-4 设定受益计划变动额结转留存收益 | C73: =SUM(E73:J73) -> 0
B74: 5-5其他综合收益结转留存收益 | C74: =SUM(E74:J74) -> 0
B75: 5-6其他 | C75: =SUM(E75:J75) -> 0
B76: 三、本年年末余额 | C76: =SUM(E76:J76) -> 0 | E76: =E47+E48 -> 0 | F76: =F47+F48 -> 0 | G76: =G47+G48 -> 0 | H76: =H47+H48 -> 0 | I76: =I47+I48 -> 0 | J76: =J47+J48 -> 0
A78: 3 | B78: 资本公积变动表
B79: 期初金额
B80: 其中：国有独享资本公积
B81: 本期变动 | C81: =SUM(E81:J81) -> 0 | E81: =E82+E83+E84 -> 0 | F81: =F82+F83+F84 -> 0 | G81: =G82+G83+G84 -> 0 | H81: =H82+H83+H84 -> 0 | I81: =I82+I83+I84 -> 0 | J81: =J82+J83+J84 -> 0
B82: 其中：资本溢价
B83: 其他资本公积
B84: 国有独享资本公积
B85: 期末金额 | C85: =SUM(E85:J85) -> 0 | E85: =E79+E83 -> 0 | F85: =F79+F83 -> 0 | G85: =G79+G83 -> 0 | H85: =H79+H83 -> 0 | I85: =I79+I83 -> 0 | J85: =J79+J83 -> 0
B86: 其中：国有独享资本公积 | C86: =SUM(E86:J86) -> 0 | E86: =E80+E84 -> 0 | F86: =F80+F84 -> 0 | G86: =G80+G84 -> 0 | H86: =H80+H84 -> 0 | I86: =I80+I84 -> 0 | J86: =J80+J84 -> 0

Sheet 净资产表_股比变1次
A1: 合并范围内的子企业净资产和损益变动表
A2: 单位名称 | B2: 项目 | C2: 变动前 | D2: 变动后 | H2: 直接持股权益法模拟 | L2: 间接持股权益法模拟 | P2: 间接持股权益法模拟-单位2 | T2: 间接持股权益法模拟-单位3
A3: 单位7 | H3: 单位7 | L3: 单位甲 | P3: 单位乙 | T3: 单位丙
B4: 变动月份 | F4: 一级科目 | G4: 二级明细 | H4: 变动前 | J4: 变动后 | L4: 变动前 | N4: 变动后 | P4: 变动前 | R4: 变动后 | T4: 变动前 | V4: 变动后
B5: 所有者权益/股东权益 | F5: 1.基础信息整理 | H5: 借方 | I5: 贷方 | J5: 借方 | K5: 贷方 | L5: 借方 | M5: 贷方 | N5: 借方 | O5: 贷方 | P5: 借方 | Q5: 贷方 | R5: 借方 | S5: 贷方 | T5: 借方 | U5: 贷方 | V5: 借方 | W5: 贷方
B6: 期初合计： | C6: =C7+C8+C9+C11+C12+C13+C14+C15-C10 -> 0 | D6: =D7+D8+D9+D11+D12+D13+D14+D15-D10 -> 0 | F6: 持股比例
B7: 实收资本（或股本）
B8: 其他权益工具 | F8: 2.权益法模拟
B9: 资本公积
B10: 减：库存股 | F10: 2.1权益法模拟期初
B11: 其他综合收益 | F11: 长期股权投资 | G11: 损益调整
B12: 专项储备 | F12: 长期股权投资 | G12: 其他权益变动
B13: 盈余公积 | F13: 年初未分配利润
B14: △一般风险准备 | F14: 资本公积
B15: 未分配利润 | F15: 其他综合收益
B16: 本期增加 | C16: =C17+C18+C19+C21+C22+C23+C24+C25-C20 -> 0 | D16: =D17+D18+D19+D21+D22+D23+D24+D25-D20 -> 0 | F16: 专项储备
B17: 实收资本（或股本） | F17: 其他权益工具
B18: 其他权益工具 | F18: △一般风险准备
B19: 资本公积 | F19: ...
B20: 减：库存股
B21: 其他综合收益 | F21: 2.2权益法模拟当期变动
B22: 专项储备 | F22: 长期股权投资 | G22: 损益调整 | H22: =I24-I30-I31-I32-I33 -> 0 | J22: =K24-K30-K31-K32-K33 -> 0
B23: 盈余公积 | F23: 长期股权投资 | G23: 其他权益变动 | H23: =I25+I26+I27+I28+I29 -> 0 | J23: =K25+K26+K27+K28+K29 -> 0
B24: △一般风险准备 | F24: 投资收益 | I24: =C51*G8 -> 0 | K24: =E51*I8 -> 0
B25: 未分配利润 | F25: 资本公积 | I25: =C82*G8 -> 0 | K25: =E82*I8 -> 0
B26: 本期减少 | C26: =C27+C28+C29+C31+C32+C33+C34+C35-C30 -> 0 | D26: =D27+D28+D29+D31+D32+D33+D34+D35-D30 -> 0 | F26: 其他综合收益 | I26: =(C21-C31)*G8 -> 0 | K26: =(E21-E31)*I8 -> 0
B27: 实收资本（或股本） | F27: 专项储备 | I27: =(C22-C32)*G8 -> 0 | K27: =(E22-E32)*I8 -> 0
B28: 其他权益工具 | F28: 其他权益工具 | I28: =(C18-C28)*G8 -> 0 | K28: =(E18-E28)*I8 -> 0
B29: 资本公积 | F29: △一般风险准备 | I29: =(C24-C34)*G8 -> 0 | K29: =(E24-E34)*I8 -> 0
B30: 减：库存股 | F30: 2-3股份支付计入所有者权益的金额 | G30: （二）所有者投入和减少资本
B31: 其他综合收益 | F31: 2-4其他 | G31: （二）所有者投入和减少资本
B32: 专项储备 | F32: 4-3对所有者的分配 | G32: （四）利润分配
B33: 盈余公积 | F33: 4-4其他 | G33: （四）利润分配
B34: △一般风险准备 | F34: ...
B35: 未分配利润
B36: 期末金额 | C36: =C37+C38+C39+C41+C42+C43+C44+C45-C40 -> 0 | D36: =D37+D38+D39+D41+D42+D43+D44+D45-D40 -> 0 | F36: 3.分红影响考虑
B37: 实收资本（或股本） | C37: =C7+C17-C27 -> 0 | D37: =D7+D17-D27 -> 0 | F37: 投资收益 | G37: 需考虑分红时间，前or后 | H37: =C68*G6 -> 0 | J37: ='投资明细-成本法和公允值'!D6-H37 -> 0
B38: 其他权益工具 | C38: =C8+C18-C28 -> 0 | D38: =D8+D18-D28 -> 0 | F38: 长期股权投资 | G38: 损益调整 | I38: =H37 -> 0
B39: 资本公积 | C39: =C9+C19-C29 -> 0 | D39: =D9+D19-D29 -> 0
B40: 减：库存股 | C40: =C10+C20-C30 -> 0 | D40: =D10+D20-D30 -> 0
B41: 其他综合收益 | C41: =C11+C21-C31 -> 0 | D41: =D11+D21-D31 -> 0 | F41: 4.调整股比变动对享有净资产的影响
B42: 专项储备 | C42: =C12+C22-C32 -> 0 | D42: =D12+D22-D32 -> 0 | F42: 长期股权投资 | G42: 损益调整
B43: 盈余公积 | C43: =C13+C23-C33 -> 0 | D43: =D13+D23-D33 -> 0 | F43: 长期股权投资 | G43: 其他权益变动
B44: △一般风险准备 | C44: =C14+C24-C34 -> 0 | D44: =D14+D24-D34 -> 0 | F44: 资本公积
B45: 未分配利润 | C45: =C15+C25-C35 -> 0 | D45: =D15+D25-D35 -> 0 | F45: 投资收益
B47: 利润及利润分配表
B48: 一、期初金额 | C48: =C15 -> 0 | D48: =D15 -> 0 | F48: 模拟长期股权投资
B49: 二、本年增减变动金额 | C49: =C50+C52+C57+C60+C70 -> 0 | D49: =D50+D52+D57+D60+D70 -> 0 | F49: 长期股权投资 | G49: 投资成本 | H49: ='投资明细-成本法和公允值'!F6+'投资明细-成本法和公允值'!K6-'投资明细-成本法和公允值'!O6 -> 0 | J49: =H49 -> 0
B50: （一）综合收益总额 | F50: 长期股权投资 | G50: 损益调整 | H50: =H11+H22-I38+H42 -> 0 | J50: =H50+J22-K38+J42 -> 0
B51: 其中：当期归母净利润 | F51: 长期股权投资 | G51: 其他权益变动 | H51: =H12+H23+H43 -> 0 | J51: =H51+J23+J43 -> 0
B52: （二）所有者投入和减少资本 | C52: =C53+C54+C55+C56 -> 0 | D52: =D53+D54+D55+D56 -> 0 | F52: 长期股权投资 | G52: 资产减值准备 | H52: ='投资明细-成本法和公允值'!G6 -> 0 | J52: ='投资明细-成本法和公允值'!T6 -> 0
B53: 2-1所有者投入的普通股 | F53: 长期股权投资 | G53: 小计 | H53: =H49+H50+H51-H52 -> 0 | J53: =SUM(J49:J52) -> 0
B54: 2-2其他权益工具持有者投入资本
B55: 2-3股份支付计入所有者权益的金额 | F55: 按比例享有净资产 | H55: =C36*G7 -> 0 | J55: =D36*G7 -> 0
B56: 2-4其他 | F56: 差异金额（按比例享有净资产-模拟后长投） | H56: =H55-H53 -> 0 | J56: =J55-J53 -> 0
B57: （三）专项储备提取和使用 | C57: =C58-C59 -> 0 | D57: =D58-D59 -> 0 | F57: 差异原因
B58: 3-1提取专项储备
B59: 3-2使用专项储备
B60: （四）利润分配 | C60: =C61+C67+C68+C69 -> 0 | D60: =D61+D67+D68+D69 -> 0
B61: 4-1提取盈余公积 | C61: =C62+C63+C64+C65+C66 -> 0 | D61: =D62+D63+D64+D65+D66 -> 0
B62: 4-1-1法定公积金
B63: 4-1-2任意公积金
B64: 4-1-3#储备基金
B65: 4-1-4#企业发展基金
B66: 4-1-5#利润归还投资
B67: 4-2△提取一般风险准备
B68: 4-3对所有者（或股东）的分配
B69: 4-4其他
B70: （五）所有者权益内部结转 | C70: =C71+C72+C74+C73+C75+C76 -> 0 | D70: =D71+D72+D74+D73+D75+D76 -> 0
B71: 5-1资本公积转增资本（或股本）
B72: 5-2盈余公积转增资本（或股本）
B73: 5-3弥补亏损
B74: 5-4 设定受益计划变动额结转留存收益
B75: 5-5其他综合收益结转留存收益
B76: 5-6其他
B77: 三、本年年末余额 | C77: =C48+C49 -> 0 | D77: =D48+D49 -> 0
B79: 资本公积变动表
B80: 期初金额
B81: 其中：国有独享资本公积
B82: 本期变动 | C82: =C83+C84+C85 -> 0 | D82: =D83+D84+D85 -> 0
B83: 其中：资本溢价
B84: 其他资本公积
B85: 国有独享资本公积
B86: 期末金额 | C86: =C80+C84 -> 0 | D86: =D80+D84 -> 0
B87: 其中：国有独享资本公积 | C87: =C81+C85 -> 0 | D87: =D81+D85 -> 0
A89: 单位8
B90: 所有者权益/股东权益
B91: 期初合计： | C91: =C92+C93+C94+C96+C97+C98+C99+C100-C95 -> 0 | D91: =D92+D93+D94+D96+D97+D98+D99+D100-D95 -> 0
B92: 实收资本（或股本）
B93: 其他权益工具
B94: 资本公积
B95: 减：库存股
B96: 其他综合收益
B97: 专项储备
B98: 盈余公积
B99: △一般风险准备
B100: 未分配利润
B101: 本期增加 | C101: =C102+C103+C104+C106+C107+C108+C109+C110-C105 -> 0 | D101: =D102+D103+D104+D106+D107+D108+D109+D110-D105 -> 0
B102: 实收资本（或股本）
B103: 其他权益工具
...

Sheet 净资产表_股比变2次
A1: 合并范围内的子企业净资产和损益变动表
A2: 单位名称 | B2: 项目 | C2: 第1次 | E2: 第2次 | I2: 直接持股权益法模拟 | O2: 间接持股权益法模拟 | U2: 间接持股权益法模拟-单位2 | AA2: 间接持股权益法模拟-单位3
A3: 单位7 | C3: 变动前 | D3: 变动后 | E3: 变动后 | I3: 单位7 | O3: 单位甲 | U3: 单位乙 | AA3: 单位丙
B4: 变动月份 | G4: 一级科目 | H4: 二级明细 | I4: 变动前 | K4: 第1次变动后 | M4: 第2次变动后 | O4: 变动前 | Q4: 第1次变动后 | S4: 第2次变动后 | U4: 变动前 | W4: 第1次变动后 | Y4: 第2次变动后 | AA4: 变动前 | AC4: 第1次变动后 | AE4: 第2次变动后
B5: 所有者权益/股东权益 | G5: 1.基础信息整理 | I5: 借方 | J5: 贷方 | K5: 借方 | L5: 贷方 | M5: 借方 | N5: 贷方 | O5: 借方 | P5: 贷方 | Q5: 借方 | R5: 贷方 | S5: 借方 | T5: 贷方 | U5: 借方 | V5: 贷方 | W5: 借方 | X5: 贷方 | Y5: 借方 | Z5: 贷方 | AA5: 借方 | AB5: 贷方 | AC5: 借方 | AD5: 贷方 | AE5: 借方 | AF5: 贷方
B6: 期初合计： | C6: =C7+C8+C9+C11+C12+C13+C14+C15-C10 -> 0 | D6: =D7+D8+D9+D11+D12+D13+D14+D15-D10 -> 0 | E6: =E7+E8+E9+E11+E12+E13+E14+E15-E10 -> 0 | G6: 持股比例
B7: 实收资本（或股本）
B8: 其他权益工具 | G8: 2.权益法模拟
B9: 资本公积
B10: 减：库存股 | G10: 2.1权益法模拟期初
B11: 其他综合收益 | G11: 长期股权投资 | H11: 损益调整
B12: 专项储备 | G12: 长期股权投资 | H12: 其他权益变动
B13: 盈余公积 | G13: 年初未分配利润
B14: △一般风险准备 | G14: 资本公积
B15: 未分配利润 | G15: 其他综合收益
B16: 本期增加 | C16: =C17+C18+C19+C21+C22+C23+C24+C25-C20 -> 0 | D16: =D17+D18+D19+D21+D22+D23+D24+D25-D20 -> 0 | E16: =E17+E18+E19+E21+E22+E23+E24+E25-E20 -> 0 | G16: 专项储备
B17: 实收资本（或股本） | G17: 其他权益工具
B18: 其他权益工具 | G18: △一般风险准备
B19: 资本公积 | G19: ...
B20: 减：库存股
B21: 其他综合收益 | G21: 2.2权益法模拟当期变动
B22: 专项储备 | G22: 长期股权投资 | H22: 损益调整 | I22: =J24-J30-J31-J32-J33 -> 0 | K22: =L24-L30-L31-L32-L33 -> 0 | M22: =N24-N30-N31-N32-N33 -> 0 | Q22: =R24-R30-R31-R32-R33 -> 0 | W22: =X24-X30-X31-X32-X33 -> 0 | AC22: =AD24-AD30-AD31-AD32-AD33 -> 0
B23: 盈余公积 | G23: 长期股权投资 | H23: 其他权益变动 | I23: =J25+J26+J27+J28+J29 -> 0 | K23: =L25+L26+L27+L28+L29 -> 0 | M23: =N25+N26+N27+N28+N29 -> 0 | Q23: =R25+R26+R27+R28+R29 -> 0 | W23: =X25+X26+X27+X28+X29 -> 0 | AC23: =AD25+AD26+AD27+AD28+AD29 -> 0
B24: △一般风险准备 | G24: 投资收益 | J24: =C51*H8 -> 0 | L24: =D51*H8 -> 0 | N24: =F51*J8 -> 0 | R24: =J51*N8 -> 0 | X24: =P51*T8 -> 0 | AD24: =V51*Z8 -> 0
B25: 未分配利润 | G25: 资本公积 | J25: =C82*H8 -> 0 | L25: =D82*H8 -> 0 | N25: =F82*J8 -> 0 | R25: =J82*N8 -> 0 | X25: =P82*T8 -> 0 | AD25: =V82*Z8 -> 0
B26: 本期减少 | C26: =C27+C28+C29+C31+C32+C33+C34+C35-C30 -> 0 | D26: =D27+D28+D29+D31+D32+D33+D34+D35-D30 -> 0 | E26: =E27+E28+E29+E31+E32+E33+E34+E35-E30 -> 0 | G26: 其他综合收益 | J26: =(C21-C31)*H8 -> 0 | L26: =(D21-D31)*H8 -> 0 | N26: =(F21-F31)*J8 -> 0 | R26: =(J21-J31)*N8 -> 0 | X26: =(P21-P31)*T8 -> 0 | AD26: =(V21-V31)*Z8 -> 0
B27: 实收资本（或股本） | G27: 专项储备 | J27: =(C22-C32)*H8 -> 0 | L27: =(D22-D32)*H8 -> 0 | N27: =(F22-F32)*J8 -> 0 | R27: =(J22-J32)*N8 -> 0 | X27: =(P22-P32)*T8 -> 0 | AD27: =(V22-V32)*Z8 -> 0
B28: 其他权益工具 | G28: 其他权益工具 | J28: =(C18-C28)*H8 -> 0 | L28: =(D18-D28)*H8 -> 0 | N28: =(F18-F28)*J8 -> 0 | R28: =(J18-J28)*N8 -> 0 | X28: =(P18-P28)*T8 -> 0 | AD28: =(V18-V28)*Z8 -> 0
B29: 资本公积 | G29: △一般风险准备 | J29: =(C24-C34)*H8 -> 0 | L29: =(D24-D34)*H8 -> 0 | N29: =(F24-F34)*J8 -> 0 | R29: =(J24-J34)*N8 -> 0 | X29: =(P24-P34)*T8 -> 0 | AD29: =(V24-V34)*Z8 -> 0
B30: 减：库存股 | G30: 2-3股份支付计入所有者权益的金额 | H30: （二）所有者投入和减少资本
B31: 其他综合收益 | G31: 2-4其他 | H31: （二）所有者投入和减少资本
B32: 专项储备 | G32: 4-3对所有者的分配 | H32: （四）利润分配
B33: 盈余公积 | G33: 4-4其他 | H33: （四）利润分配
B34: △一般风险准备 | G34: ...
B35: 未分配利润
B36: 期末金额 | C36: =C37+C38+C39+C41+C42+C43+C44+C45-C40 -> 0 | D36: =D37+D38+D39+D41+D42+D43+D44+D45-D40 -> 0 | E36: =E37+E38+E39+E41+E42+E43+E44+E45-E40 -> 0 | G36: 3.分红影响考虑
B37: 实收资本（或股本） | C37: =C7+C17-C27 -> 0 | D37: =D7+D17-D27 -> 0 | E37: =E7+E17-E27 -> 0 | G37: 投资收益 | H37: 需考虑分红时间，前or后 | I37: =C68*H6 -> 0 | M37: ='投资明细-成本法和公允值'!D6-I37 -> 0 | Q37: ='投资明细-成本法和公允值'!H6-M37 -> 0 | W37: ='投资明细-成本法和公允值'!N6-S37 -> 0 | AC37: ='投资明细-成本法和公允值'!T6-Y37 -> 0
B38: 其他权益工具 | C38: =C8+C18-C28 -> 0 | D38: =D8+D18-D28 -> 0 | E38: =E8+E18-E28 -> 0 | G38: 长期股权投资 | H38: 损益调整 | J38: =I37 -> 0
B39: 资本公积 | C39: =C9+C19-C29 -> 0 | D39: =D9+D19-D29 -> 0 | E39: =E9+E19-E29 -> 0
B40: 减：库存股 | C40: =C10+C20-C30 -> 0 | D40: =D10+D20-D30 -> 0 | E40: =E10+E20-E30 -> 0
B41: 其他综合收益 | C41: =C11+C21-C31 -> 0 | D41: =D11+D21-D31 -> 0 | E41: =E11+E21-E31 -> 0 | G41: 4.调整股比变动对享有净资产的影响
B42: 专项储备 | C42: =C12+C22-C32 -> 0 | D42: =D12+D22-D32 -> 0 | E42: =E12+E22-E32 -> 0 | G42: 长期股权投资 | H42: 损益调整
B43: 盈余公积 | C43: =C13+C23-C33 -> 0 | D43: =D13+D23-D33 -> 0 | E43: =E13+E23-E33 -> 0 | G43: 长期股权投资 | H43: 其他权益变动
B44: △一般风险准备 | C44: =C14+C24-C34 -> 0 | D44: =D14+D24-D34 -> 0 | E44: =E14+E24-E34 -> 0 | G44: 资本公积
B45: 未分配利润 | C45: =C15+C25-C35 -> 0 | D45: =D15+D25-D35 -> 0 | E45: =E15+E25-E35 -> 0 | G45: 投资收益
B47: 利润及利润分配表
B48: 一、期初金额 | C48: =C15 -> 0 | D48: =D15 -> 0 | E48: =E15 -> 0 | G48: 模拟长期股权投资
B49: 二、本年增减变动金额 | C49: =C50+C52+C57+C60+C70 -> 0 | D49: =D50+D52+D57+D60+D70 -> 0 | E49: =E50+E52+E57+E60+E70 -> 0 | G49: 长期股权投资 | H49: 投资成本 | I49: ='投资明细-成本法和公允值'!F6+'投资明细-成本法和公允值'!K6-'投资明细-成本法和公允值'!O6 -> 0 | K49: =G49 -> 长期股权投资 | M49: =I49 -> 0 | Q49: =M49 -> 0 | W49: =S49 -> 0 | AC49: =Y49 -> 0
B50: （一）综合收益总额 | G50: 长期股权投资 | H50: 损益调整 | I50: =I11+I22-J38+I42 -> 0 | K50: =G50+K22-L38+K42 -> #VALUE! | M50: =I50+M22-N38+M42 -> 0 | Q50: =M50+Q22-R38+Q42 -> 0 | W50: =S50+W22-X38+W42 -> 0 | AC50: =Y50+AC22-AD38+AC42 -> 0
B51: 其中：当期归母净利润 | G51: 长期股权投资 | H51: 其他权益变动 | I51: =I12+I23+I43 -> 0 | K51: =G51+K23+K43 -> #VALUE! | M51: =I51+M23+M43 -> 0 | Q51: =M51+Q23+Q43 -> 0 | W51: =S51+W23+W43 -> 0 | AC51: =Y51+AC23+AC43 -> 0
B52: （二）所有者投入和减少资本 | C52: =C53+C54+C55+C56 -> 0 | D52: =D53+D54+D55+D56 -> 0 | E52: =E53+E54+E55+E56 -> 0 | G52: 长期股权投资 | H52: 资产减值准备 | I52: ='投资明细-成本法和公允值'!G6 -> 0 | K52: ='投资明细-成本法和公允值'!R6 -> 0 | M52: ='投资明细-成本法和公允值'!T6 -> 0 | Q52: ='投资明细-成本法和公允值'!X6 -> 0 | W52: ='投资明细-成本法和公允值'!AD6 -> 0 | AC52: ='投资明细-成本法和公允值'!AJ6 -> 0
B53: 2-1所有者投入的普通股 | G53: 长期股权投资 | H53: 小计 | I53: =I49+I50+I51-I52 -> 0 | K53: =SUM(K49:K52) -> #VALUE! | M53: =SUM(M49:M52) -> 0 | Q53: =SUM(Q49:Q52) -> 0 | W53: =SUM(W49:W52) -> 0 | AC53: =SUM(AC49:AC52) -> 0
B54: 2-2其他权益工具持有者投入资本
B55: 2-3股份支付计入所有者权益的金额 | G55: 按比例享有净资产 | I55: =C36*H7 -> 0 | K55: =B36*F7 -> #VALUE! | M55: =D36*H7 -> 0 | Q55: =H36*L7 -> 0 | W55: =N36*R7 -> 0 | AC55: =T36*X7 -> 0
B56: 2-4其他 | G56: 差异金额（按比例享有净资产-模拟后长投） | I56: =I55-I53 -> 0 | K56: =K55-K53 -> #VALUE! | M56: =M55-M53 -> 0 | Q56: =Q55-Q53 -> 0 | W56: =W55-W53 -> 0 | AC56: =AC55-AC53 -> 0
B57: （三）专项储备提取和使用 | C57: =C58-C59 -> 0 | D57: =D58-D59 -> 0 | E57: =E58-E59 -> 0 | G57: 差异原因
B58: 3-1提取专项储备
B59: 3-2使用专项储备
B60: （四）利润分配 | C60: =C61+C67+C68+C69 -> 0 | D60: =D61+D67+D68+D69 -> 0 | E60: =E61+E67+E68+E69 -> 0
B61: 4-1提取盈余公积 | C61: =C62+C63+C64+C65+C66 -> 0 | D61: =D62+D63+D64+D65+D66 -> 0 | E61: =E62+E63+E64+E65+E66 -> 0
B62: 4-1-1法定公积金
B63: 4-1-2任意公积金
B64: 4-1-3#储备基金
B65: 4-1-4#企业发展基金
B66: 4-1-5#利润归还投资
B67: 4-2△提取一般风险准备
B68: 4-3对所有者（或股东）的分配
B69: 4-4其他
B70: （五）所有者权益内部结转 | C70: =C71+C72+C74+C73+C75+C76 -> 0 | D70: =D71+D72+D74+D73+D75+D76 -> 0 | E70: =E71+E72+E74+E73+E75+E76 -> 0
B71: 5-1资本公积转增资本（或股本）
B72: 5-2盈余公积转增资本（或股本）
B73: 5-3弥补亏损
B74: 5-4 设定受益计划变动额结转留存收益
B75: 5-5其他综合收益结转留存收益
B76: 5-6其他
B77: 三、本年年末余额 | C77: =C48+C49 -> 0 | D77: =D48+D49 -> 0 | E77: =E48+E49 -> 0
B79: 资本公积变动表
B80: 期初金额
B81: 其中：国有独享资本公积
B82: 本期变动 | C82: =C83+C84+C85 -> 0 | D82: =D83+D84+D85 -> 0 | E82: =E83+E84+E85 -> 0
B83: 其中：资本溢价
B84: 其他资本公积
B85: 国有独享资本公积
B86: 期末金额 | C86: =C80+C84 -> 0 | D86: =D80+D84 -> 0 | E86: =E80+E84 -> 0
B87: 其中：国有独享资本公积 | C87: =C81+C85 -> 0 | D87: =D81+D85 -> 0 | E87: =E81+E85 -> 0
A89: 单位8
B90: 所有者权益/股东权益
B91: 期初合计： | C91: =C92+C93+C94+C96+C97+C98+C99+C100-C95 -> 0 | D91: =D92+D93+D94+D96+D97+D98+D99+D100-D95 -> 0 | E91: =E92+E93+E94+E96+E97+E98+E99+E100-E95 -> 0
B92: 实收资本（或股本）
B93: 其他权益工具
B94: 资本公积
B95: 减：库存股
B96: 其他综合收益
B97: 专项储备
B98: 盈余公积
B99: △一般风险准备
B100: 未分配利润
B101: 本期增加 | C101: =C102+C103+C104+C106+C107+C108+C109+C110-C105 -> 0 | D101: =D102+D103+D104+D106+D107+D108+D109+D110-D105 -> 0 | E101: =E102+E103+E104+E106+E107+E108+E109+E110-E105 -> 0
B102: 实收资本（或股本）
B103: 其他权益工具
...

Sheet 净资产表_股比变3次
A1: 合并范围内的子企业净资产和损益变动表
A2: 单位名称 | B2: 项目 | C2: 第1次 | E2: 第2次 | F2: 第3次 | J2: 直接持股权益法模拟 | R2: 间接持股权益法模拟 | Z2: 间接持股权益法模拟-单位2 | AH2: 间接持股权益法模拟-单位3
A3: 单位7 | C3: 变动前 | D3: 变动后 | E3: 变动后 | F3: 变动后 | J3: 单位7 | R3: 单位甲 | Z3: 单位乙 | AH3: 单位丙
B4: 变动月份 | H4: 一级科目 | I4: 二级明细 | J4: 变动前 | L4: 第1次变动后 | N4: 第2次变动后 | P4: 第3次变动后 | R4: 变动前 | T4: 第1次变动后 | V4: 第2次变动后 | X4: 第3次变动后 | Z4: 变动前 | AB4: 第1次变动后 | AD4: 第2次变动后 | AF4: 第3次变动后 | AH4: 变动前 | AJ4: 第1次变动后 | AL4: 第2次变动后 | AN4: 第3次变动后
B5: 所有者权益/股东权益 | H5: 1.基础信息整理 | J5: 借方 | K5: 贷方 | L5: 借方 | M5: 贷方 | N5: 借方 | O5: 贷方 | P5: 借方 | Q5: 贷方 | R5: 借方 | S5: 贷方 | T5: 借方 | U5: 贷方 | V5: 借方 | W5: 贷方 | X5: 借方 | Y5: 贷方 | Z5: 借方 | AA5: 贷方 | AB5: 借方 | AC5: 贷方 | AD5: 借方 | AE5: 贷方 | AF5: 借方 | AG5: 贷方 | AH5: 借方 | AI5: 贷方 | AJ5: 借方 | AK5: 贷方 | AL5: 借方 | AM5: 贷方 | AN5: 借方 | AO5: 贷方
B6: 期初合计： | C6: =C7+C8+C9+C11+C12+C13+C14+C15-C10 -> 0 | D6: =D7+D8+D9+D11+D12+D13+D14+D15-D10 -> 0 | E6: =E7+E8+E9+E11+E12+E13+E14+E15-E10 -> 0 | F6: =F7+F8+F9+F11+F12+F13+F14+F15-F10 -> 0 | H6: 持股比例
B7: 实收资本（或股本）
B8: 其他权益工具 | H8: 2.权益法模拟
B9: 资本公积
B10: 减：库存股 | H10: 2.1权益法模拟期初
B11: 其他综合收益 | H11: 长期股权投资 | I11: 损益调整
B12: 专项储备 | H12: 长期股权投资 | I12: 其他权益变动
B13: 盈余公积 | H13: 年初未分配利润
B14: △一般风险准备 | H14: 资本公积
B15: 未分配利润 | H15: 其他综合收益
B16: 本期增加 | C16: =C17+C18+C19+C21+C22+C23+C24+C25-C20 -> 0 | D16: =D17+D18+D19+D21+D22+D23+D24+D25-D20 -> 0 | E16: =E17+E18+E19+E21+E22+E23+E24+E25-E20 -> 0 | F16: =F17+F18+F19+F21+F22+F23+F24+F25-F20 -> 0 | H16: 专项储备
B17: 实收资本（或股本） | H17: 其他权益工具
B18: 其他权益工具 | H18: △一般风险准备
B19: 资本公积 | H19: ...
B20: 减：库存股
B21: 其他综合收益 | H21: 2.2权益法模拟当期变动
B22: 专项储备 | H22: 长期股权投资 | I22: 损益调整 | J22: =K24-K30-K31-K32-K33 -> 0 | L22: =M24-M30-M31-M32-M33 -> 0 | N22: =O24-O30-O31-O32-O33 -> 0 | P22: =Q24-Q30-Q31-Q32-Q33 -> 0 | T22: =U24-U30-U31-U32-U33 -> 0 | AB22: =AC24-AC30-AC31-AC32-AC33 -> 0 | AJ22: =AK24-AK30-AK31-AK32-AK33 -> 0
B23: 盈余公积 | H23: 长期股权投资 | I23: 其他权益变动 | J23: =K25+K26+K27+K28+K29 -> 0 | L23: =M25+M26+M27+M28+M29 -> 0 | N23: =O25+O26+O27+O28+O29 -> 0 | P23: =Q25+Q26+Q27+Q28+Q29 -> 0 | T23: =U25+U26+U27+U28+U29 -> 0 | AB23: =AC25+AC26+AC27+AC28+AC29 -> 0 | AJ23: =AK25+AK26+AK27+AK28+AK29 -> 0
B24: △一般风险准备 | H24: 投资收益 | K24: =C51*I8 -> 0 | M24: =D51*I8 -> 0 | O24: =E51*I8 -> 0 | Q24: =G51*K8 -> 0 | U24: =K51*Q8 -> 0 | AC24: =S51*Y8 -> 0 | AK24: =AA51*AG8 -> 0
B25: 未分配利润 | H25: 资本公积 | K25: =C82*I8 -> 0 | M25: =D82*I8 -> 0 | O25: =E82*I8 -> 0 | Q25: =G82*K8 -> 0 | U25: =K82*Q8 -> 0 | AC25: =S82*Y8 -> 0 | AK25: =AA82*AG8 -> 0
B26: 本期减少 | C26: =C27+C28+C29+C31+C32+C33+C34+C35-C30 -> 0 | D26: =D27+D28+D29+D31+D32+D33+D34+D35-D30 -> 0 | E26: =E27+E28+E29+E31+E32+E33+E34+E35-E30 -> 0 | F26: =F27+F28+F29+F31+F32+F33+F34+F35-F30 -> 0 | H26: 其他综合收益 | K26: =(C21-C31)*I8 -> 0 | M26: =(D21-D31)*I8 -> 0 | O26: =(E21-E31)*I8 -> 0 | Q26: =(G21-G31)*K8 -> 0 | U26: =(K21-K31)*Q8 -> 0 | AC26: =(S21-S31)*Y8 -> 0 | AK26: =(AA21-AA31)*AG8 -> 0
B27: 实收资本（或股本） | H27: 专项储备 | K27: =(C22-C32)*I8 -> 0 | M27: =(D22-D32)*I8 -> 0 | O27: =(E22-E32)*I8 -> 0 | Q27: =(G22-G32)*K8 -> 0 | U27: =(K22-K32)*Q8 -> 0 | AC27: =(S22-S32)*Y8 -> 0 | AK27: =(AA22-AA32)*AG8 -> 0
B28: 其他权益工具 | H28: 其他权益工具 | K28: =(C18-C28)*I8 -> 0 | M28: =(D18-D28)*I8 -> 0 | O28: =(E18-E28)*I8 -> 0 | Q28: =(G18-G28)*K8 -> 0 | U28: =(K18-K28)*Q8 -> 0 | AC28: =(S18-S28)*Y8 -> 0 | AK28: =(AA18-AA28)*AG8 -> 0
B29: 资本公积 | H29: △一般风险准备 | K29: =(C24-C34)*I8 -> 0 | M29: =(D24-D34)*I8 -> 0 | O29: =(E24-E34)*I8 -> 0 | Q29: =(G24-G34)*K8 -> 0 | U29: =(K24-K34)*Q8 -> 0 | AC29: =(S24-S34)*Y8 -> 0 | AK29: =(AA24-AA34)*AG8 -> 0
B30: 减：库存股 | H30: 2-3股份支付计入所有者权益的金额 | I30: （二）所有者投入和减少资本
B31: 其他综合收益 | H31: 2-4其他 | I31: （二）所有者投入和减少资本
B32: 专项储备 | H32: 4-3对所有者的分配 | I32: （四）利润分配
B33: 盈余公积 | H33: 4-4其他 | I33: （四）利润分配
B34: △一般风险准备 | H34: ...
B35: 未分配利润
B36: 期末金额 | C36: =C37+C38+C39+C41+C42+C43+C44+C45-C40 -> 0 | D36: =D37+D38+D39+D41+D42+D43+D44+D45-D40 -> 0 | E36: =E37+E38+E39+E41+E42+E43+E44+E45-E40 -> 0 | F36: =F37+F38+F39+F41+F42+F43+F44+F45-F40 -> 0 | H36: 3.分红影响考虑
B37: 实收资本（或股本） | C37: =C7+C17-C27 -> 0 | D37: =D7+D17-D27 -> 0 | E37: =E7+E17-E27 -> 0 | F37: =F7+F17-F27 -> 0 | H37: 投资收益 | I37: 需考虑分红时间，前or后 | J37: =C68*I6 -> 0 | N37: ='投资明细-成本法和公允值'!B6-H37 -> #VALUE! | P37: ='投资明细-成本法和公允值'!D6-J37 -> 0 | T37: ='投资明细-成本法和公允值'!H6-P37 -> 0 | AB37: ='投资明细-成本法和公允值'!N6-X37 -> 0 | AJ37: ='投资明细-成本法和公允值'!T6-AF37 -> 0
B38: 其他权益工具 | C38: =C8+C18-C28 -> 0 | D38: =D8+D18-D28 -> 0 | E38: =E8+E18-E28 -> 0 | F38: =F8+F18-F28 -> 0 | H38: 长期股权投资 | I38: 损益调整 | K38: =J37 -> 0
B39: 资本公积 | C39: =C9+C19-C29 -> 0 | D39: =D9+D19-D29 -> 0 | E39: =E9+E19-E29 -> 0 | F39: =F9+F19-F29 -> 0
B40: 减：库存股 | C40: =C10+C20-C30 -> 0 | D40: =D10+D20-D30 -> 0 | E40: =E10+E20-E30 -> 0 | F40: =F10+F20-F30 -> 0
B41: 其他综合收益 | C41: =C11+C21-C31 -> 0 | D41: =D11+D21-D31 -> 0 | E41: =E11+E21-E31 -> 0 | F41: =F11+F21-F31 -> 0 | H41: 4.调整股比变动对享有净资产的影响
B42: 专项储备 | C42: =C12+C22-C32 -> 0 | D42: =D12+D22-D32 -> 0 | E42: =E12+E22-E32 -> 0 | F42: =F12+F22-F32 -> 0 | H42: 长期股权投资 | I42: 损益调整
B43: 盈余公积 | C43: =C13+C23-C33 -> 0 | D43: =D13+D23-D33 -> 0 | E43: =E13+E23-E33 -> 0 | F43: =F13+F23-F33 -> 0 | H43: 长期股权投资 | I43: 其他权益变动
B44: △一般风险准备 | C44: =C14+C24-C34 -> 0 | D44: =D14+D24-D34 -> 0 | E44: =E14+E24-E34 -> 0 | F44: =F14+F24-F34 -> 0 | H44: 资本公积
B45: 未分配利润 | C45: =C15+C25-C35 -> 0 | D45: =D15+D25-D35 -> 0 | E45: =E15+E25-E35 -> 0 | F45: =F15+F25-F35 -> 0 | H45: 投资收益
B47: 利润及利润分配表
B48: 一、期初金额 | C48: =C15 -> 0 | D48: =D15 -> 0 | E48: =E15 -> 0 | F48: =F15 -> 0 | H48: 模拟长期股权投资
B49: 二、本年增减变动金额 | C49: =C50+C52+C57+C60+C70 -> 0 | D49: =D50+D52+D57+D60+D70 -> 0 | E49: =E50+E52+E57+E60+E70 -> 0 | F49: =F50+F52+F57+F60+F70 -> 0 | H49: 长期股权投资 | I49: 投资成本 | J49: ='投资明细-成本法和公允值'!F6+'投资明细-成本法和公允值'!K6-'投资明细-成本法和公允值'!O6 -> 0 | L49: =H49 -> 长期股权投资 | N49: =H49 -> 长期股权投资 | P49: =J49 -> 0 | T49: =P49 -> 0 | AB49: =X49 -> 0 | AJ49: =AF49 -> 0
B50: （一）综合收益总额 | H50: 长期股权投资 | I50: 损益调整 | J50: =J11+J22-K38+J42 -> 0 | L50: =H50+L22-M38+L42 -> #VALUE! | N50: =H50+N22-O38+N42 -> #VALUE! | P50: =J50+P22-Q38+P42 -> 0 | T50: =P50+T22-U38+T42 -> 0 | AB50: =X50+AB22-AC38+AB42 -> 0 | AJ50: =AF50+AJ22-AK38+AJ42 -> 0
B51: 其中：当期归母净利润 | H51: 长期股权投资 | I51: 其他权益变动 | J51: =J12+J23+J43 -> 0 | L51: =H51+L23+L43 -> #VALUE! | N51: =H51+N23+N43 -> #VALUE! | P51: =J51+P23+P43 -> 0 | T51: =P51+T23+T43 -> 0 | AB51: =X51+AB23+AB43 -> 0 | AJ51: =AF51+AJ23+AJ43 -> 0
B52: （二）所有者投入和减少资本 | C52: =C53+C54+C55+C56 -> 0 | D52: =D53+D54+D55+D56 -> 0 | E52: =E53+E54+E55+E56 -> 0 | F52: =F53+F54+F55+F56 -> 0 | H52: 长期股权投资 | I52: 资产减值准备 | J52: ='投资明细-成本法和公允值'!G6 -> 0 | L52: ='投资明细-成本法和公允值'!R6 -> 0 | N52: ='投资明细-成本法和公允值'!R6 -> 0 | P52: ='投资明细-成本法和公允值'!T6 -> 0 | T52: ='投资明细-成本法和公允值'!X6 -> 0 | AB52: ='投资明细-成本法和公允值'!AD6 -> 0 | AJ52: ='投资明细-成本法和公允值'!AJ6 -> 0
B53: 2-1所有者投入的普通股 | H53: 长期股权投资 | I53: 小计 | J53: =J49+J50+J51-J52 -> 0 | L53: =SUM(L49:L52) -> #VALUE! | N53: =SUM(N49:N52) -> #VALUE! | P53: =SUM(P49:P52) -> 0 | T53: =SUM(T49:T52) -> 0 | AB53: =SUM(AB49:AB52) -> 0 | AJ53: =SUM(AJ49:AJ52) -> 0
B54: 2-2其他权益工具持有者投入资本
B55: 2-3股份支付计入所有者权益的金额 | H55: 按比例享有净资产 | J55: =C36*I7 -> 0 | L55: =B36*G7 -> #VALUE! | N55: =B36*G7 -> #VALUE! | P55: =D36*I7 -> 0 | T55: =I36*M7 -> 0 | AB55: =Q36*U7 -> 0 | AJ55: =Y36*AC7 -> 0
B56: 2-4其他 | H56: 差异金额（按比例享有净资产-模拟后长投） | J56: =J55-J53 -> 0 | L56: =L55-L53 -> #VALUE! | N56: =N55-N53 -> #VALUE! | P56: =P55-P53 -> 0 | T56: =T55-T53 -> 0 | AB56: =AB55-AB53 -> 0 | AJ56: =AJ55-AJ53 -> 0
B57: （三）专项储备提取和使用 | C57: =C58-C59 -> 0 | D57: =D58-D59 -> 0 | E57: =E58-E59 -> 0 | F57: =F58-F59 -> 0 | H57: 差异原因
B58: 3-1提取专项储备
B59: 3-2使用专项储备
B60: （四）利润分配 | C60: =C61+C67+C68+C69 -> 0 | D60: =D61+D67+D68+D69 -> 0 | E60: =E61+E67+E68+E69 -> 0 | F60: =F61+F67+F68+F69 -> 0
B61: 4-1提取盈余公积 | C61: =C62+C63+C64+C65+C66 -> 0 | D61: =D62+D63+D64+D65+D66 -> 0 | E61: =E62+E63+E64+E65+E66 -> 0 | F61: =F62+F63+F64+F65+F66 -> 0
B62: 4-1-1法定公积金
B63: 4-1-2任意公积金
B64: 4-1-3#储备基金
B65: 4-1-4#企业发展基金
B66: 4-1-5#利润归还投资
B67: 4-2△提取一般风险准备
B68: 4-3对所有者（或股东）的分配
B69: 4-4其他
B70: （五）所有者权益内部结转 | C70: =C71+C72+C74+C73+C75+C76 -> 0 | D70: =D71+D72+D74+D73+D75+D76 -> 0 | E70: =E71+E72+E74+E73+E75+E76 -> 0 | F70: =F71+F72+F74+F73+F75+F76 -> 0
B71: 5-1资本公积转增资本（或股本）
B72: 5-2盈余公积转增资本（或股本）
B73: 5-3弥补亏损
B74: 5-4 设定受益计划变动额结转留存收益
B75: 5-5其他综合收益结转留存收益
B76: 5-6其他
B77: 三、本年年末余额 | C77: =C48+C49 -> 0 | D77: =D48+D49 -> 0 | E77: =E48+E49 -> 0 | F77: =F48+F49 -> 0
B79: 资本公积变动表
B80: 期初金额
B81: 其中：国有独享资本公积
B82: 本期变动 | C82: =C83+C84+C85 -> 0 | D82: =D83+D84+D85 -> 0 | E82: =E83+E84+E85 -> 0 | F82: =F83+F84+F85 -> 0
B83: 其中：资本溢价
B84: 其他资本公积
B85: 国有独享资本公积
B86: 期末金额 | C86: =C80+C84 -> 0 | D86: =D80+D84 -> 0 | E86: =E80+E84 -> 0 | F86: =F80+F84 -> 0
B87: 其中：国有独享资本公积 | C87: =C81+C85 -> 0 | D87: =D81+D85 -> 0 | E87: =E81+E85 -> 0 | F87: =F81+F85 -> 0
A89: 单位8
B90: 所有者权益/股东权益
B91: 期初合计： | C91: =C92+C93+C94+C96+C97+C98+C99+C100-C95 -> 0 | D91: =D92+D93+D94+D96+D97+D98+D99+D100-D95 -> 0 | E91: =E92+E93+E94+E96+E97+E98+E99+E100-E95 -> 0 | F91: =F92+F93+F94+F96+F97+F98+F99+F100-F95 -> 0
B92: 实收资本（或股本）
B93: 其他权益工具
B94: 资本公积
B95: 减：库存股
B96: 其他综合收益
B97: 专项储备
B98: 盈余公积
B99: △一般风险准备
B100: 未分配利润
B101: 本期增加 | C101: =C102+C103+C104+C106+C107+C108+C109+C110-C105 -> 0 | D101: =D102+D103+D104+D106+D107+D108+D109+D110-D105 -> 0 | E101: =E102+E103+E104+E106+E107+E108+E109+E110-E105 -> 0 | F101: =F102+F103+F104+F106+F107+F108+F109+F110-F105 -> 0
B102: 实收资本（或股本）
B103: 其他权益工具
...

Sheet 模拟权益法
A1: 模拟权益法调整表
A3: 序号 | C3: 借贷方向 | D3: 项目 | F3: 合计 | G3: 单位1 | H3: 单位2 | I3: 单位3 | J3: 单位4 | K3: 单位5 | L3: 单位6
E4: 期末持股比例 | G4: 0.51 | H4: 持股比例% | I4: 持股比例% | J4: 持股比例% | K4: 持股比例% | L4: 持股比例%
B5: 1.直接长期股权投资权益法模拟
A6: 1 | B6: 期初长投模拟 | C6: 借 | D6: 长期股权投资 | E6: 损益调整 | F6: =SUM(G6:L6) -> 0 | G6: =G8 -> 0 | H6: =H8 -> 0 | I6: =I8 -> 0 | J6: =J8 -> 0 | K6: =K8 -> 0 | L6: =L8 -> 0
C7: 借 | D7: 长期股权投资 | E7: 其他权益变动 | F7: =SUM(G7:L7) -> 0 | G7: =G9+G10+G11+G12+G13+G14 -> 0 | H7: =H9+H10+H11+H12+H13+H14 -> 0 | I7: =I9+I10+I11+I12+I13+I14 -> 0 | J7: =J9+J10+J11+J12+J13+J14 -> 0 | K7: =K9+K10+K11+K12+K13+K14 -> 0 | L7: =L9+L10+L11+L12+L13+L14 -> 0
C8: 贷 | D8: 年初未分配利润 | F8: =SUM(G8:L8) -> 0
C9: 贷 | D9: 资本公积 | F9: =SUM(G9:L9) -> 0
C10: 贷 | D10: 其他综合收益 | F10: =SUM(G10:L10) -> 0
C11: 贷 | D11: 专项储备 | F11: =SUM(G11:L11) -> 0
C12: 贷 | D12: 其他权益工具 | F12: =SUM(G12:L12) -> 0
C13: 贷 | D13: △一般风险准备 | F13: =SUM(G13:L13) -> 0
C14: 贷 | D14: ... | F14: =SUM(G14:L14) -> 0
A17: 2 | B17: 模拟当期长期股权投资 | C17: 借 | D17: 长期股权投资 | E17: 损益调整 | F17: =SUM(G17:L17) -> 0 | G17: =G19-G25-G26-G27-G28 -> 0 | H17: =H19-H25-H26-H27-H28 -> 0 | I17: =I19-I25-I26-I27-I28 -> 0 | J17: =J19-J25-J26-J27-J28 -> 0 | K17: =K19-K25-K26-K27-K28 -> 0 | L17: =L19-L25-L26-L27-L28 -> 0
C18: 借 | D18: 长期股权投资 | E18: 其他权益变动 | F18: =SUM(G18:L18) -> 0 | G18: =G20+G21+G23+G22+G24 -> 0 | H18: =H20+H21+H23+H22+H24 -> 0 | I18: =I20+I21+I23+I22+I24 -> 0 | J18: =J20+J21+J23+J22+J24 -> 0 | K18: =K20+K21+K23+K22+K24 -> 0 | L18: =L20+L21+L23+L22+L24 -> 0
C19: 贷 | D19: 投资收益 | F19: =SUM(G19:L19) -> 0
C20: 贷 | D20: 资本公积 | F20: =SUM(G20:L20) -> 0
C21: 贷 | D21: 其他综合收益 | F21: =SUM(G21:L21) -> 0
C22: 贷 | D22: 专项储备 | F22: =SUM(G22:L22) -> 0
C23: 贷 | D23: 其他权益工具 | F23: =SUM(G23:L23) -> 0
C24: 贷 | D24: △一般风险准备 | F24: =SUM(G24:L24) -> 0
C25: 贷 | D25: 2-3股份支付计入所有者权益的金额 | E25: （二）所有者投入和减少资本 | F25: =SUM(G25:L25) -> 0
C26: 贷 | D26: 2-4其他 | E26: （二）所有者投入和减少资本 | F26: =SUM(G26:L26) -> 0
C27: 贷 | D27: 4-3对所有者的分配 | E27: （四）利润分配 | F27: =SUM(G27:L27) -> 0
C28: 贷 | D28: 4-4其他 | E28: （四）利润分配 | F28: =SUM(G28:L28) -> 0
C29: 贷 | D29: ... | F29: =SUM(G29:L29) -> 0
A31: 3 | B31: 还原分红影响 | C31: 借 | D31: 投资收益 | F31: =SUM(G31:L31) -> 0 | G31: ='投资明细-成本法和公允值'!D6 -> 0 | H31: ='投资明细-成本法和公允值'!D7 -> 0 | I31: ='投资明细-成本法和公允值'!D8 -> 0 | J31: ='投资明细-成本法和公允值'!D9 -> 0
C32: 贷 | D32: 长期股权投资 | E32: 损益调整 | F32: =SUM(G32:L32) -> 0 | G32: =G31 -> 0 | H32: =H31 -> 0 | I32: =I31 -> 0 | J32: =J31 -> 0 | K32: =K31 -> 0 | L32: =L31 -> 0
A34: 4 | B34: 股比发生变动对享有净资产的影响 | C34: 借 | D34: 长期股权投资 | E34: 损益调整
C35: 借 | D35: 长期股权投资 | E35: 其他权益变动
C36: 贷 | D36: 资本公积
C37: 贷 | D37: 投资收益
C38: 贷 | D38: ...
B40: 模拟后期末长期股权投资 | C40: 借 | D40: 长期股权投资 | E40: 投资成本 | F40: =SUM(G40:L40) -> 0 | G40: ='投资明细-成本法和公允值'!F6 -> 0 | H40: ='投资明细-成本法和公允值'!G6 -> 0 | I40: ='投资明细-成本法和公允值'!H6 -> 0 | J40: ='投资明细-成本法和公允值'!I6 -> 0 | K40: ='投资明细-成本法和公允值'!J6 -> 0 | L40: ='投资明细-成本法和公允值'!K6 -> 0
C41: 借 | D41: 长期股权投资 | E41: 损益调整 | F41: =SUM(G41:L41) -> 0 | G41: =G6+G17-G32 -> 0 | H41: =H6+H17-H32 -> 0 | I41: =I6+I17-I32 -> 0 | J41: =J6+J17-J32 -> 0 | K41: =K6+K17-K32 -> 0 | L41: =L6+L17-L32 -> 0
C42: 借 | D42: 长期股权投资 | E42: 其他权益变动 | F42: =SUM(G42:L42) -> 0 | G42: =G7+G18 -> 0 | H42: =H7+H18 -> 0 | I42: =I7+I18 -> 0 | J42: =J7+J18 -> 0 | K42: =K7+K18 -> 0 | L42: =L7+L18 -> 0
C43: 借 | D43: 长期股权投资 | E43: 资产减值准备 | F43: =SUM(G43:L43) -> 0 | G43: ='投资明细-成本法和公允值'!G6 -> 0 | H43: ='投资明细-成本法和公允值'!H6 -> 0 | I43: ='投资明细-成本法和公允值'!I6 -> 0 | J43: ='投资明细-成本法和公允值'!J6 -> 0 | K43: ='投资明细-成本法和公允值'!K6 -> 0 | L43: ='投资明细-成本法和公允值'!L6 -> 0
D44: 长期股权投资 | E44: 小计 | F44: =SUM(G44:L44) -> 0 | G44: =G40+G41+G42-G43 -> 0 | H44: =H40+H41+H42-H43 -> 0 | I44: =I40+I41+I42-I43 -> 0 | J44: =J40+J41+J42-J43 -> 0 | K44: =K40+K41+K42-K43 -> 0 | L44: =L40+L41+L42-L43 -> 0
B46: 比对 | D46: 期末所有者权益金额 | G46: =净资产表!E35 -> 0 | H46: =净资产表!F35 -> 0 | I46: =净资产表!G35 -> 0 | J46: =净资产表!H35 -> 0 | K46: =净资产表!I35 -> 0 | L46: =净资产表!J35 -> 0 | M46: =净资产表!K35 -> 0
D47: 商誉金额
D48: 差异金额 | E48: 按比例享有净资产-长投 | G48: =G46*G4-G44+G47 -> 0 | H48: =H46*H4-H44+H47 -> #VALUE! | I48: =I46*I4-I44+I47 -> #VALUE! | J48: =J46*J4-J44+J47 -> #VALUE! | K48: =K46*K4-K44+K47 -> #VALUE! | L48: =L46*L4-L44+L47 -> #VALUE! | M48: =M46*M4-M44 -> 0
D49: 差异原因 | E49: 分析过程简要注明
A52: 单位A | G52: 持股比例
B53: 2.间接/交叉持股权益法模拟 | E53: 期末持股比例 | F53: 需要按信息表中提取
A55: 4 | B55: 期初长投还原 | C55: 借 | D55: 长期股权投资 | E55: 投资成本
C56: 贷 | D56: 可供出售金融资产
C57: 贷 | D57: 交易性金融资产 | E57: 公允值
C58: 贷 | D58: 其他权益工具投资
C59: 贷 | D59: 其他非流动金融资产
C60: 贷 | D60: 其他非流动资产
C61: 贷 | D61: 年初未分配利润 | E61: △（公允值-投资成本）
C62: 贷 | D62: 其他综合收益 | E62: △（可供-投资成本）
C63: 贷 | D63: ...
A65: 5 | B65: 期初长投模拟 | C65: 借 | D65: 长期股权投资 | E65: 损益调整
C66: 借 | D66: 长期股权投资 | E66: 其他权益变动
C67: 贷 | D67: 资本公积
C68: 贷 | D68: 其他综合收益
C69: 贷 | D69: 专项储备
C70: 贷 | D70: 其他权益工具
C71: 贷 | D71: △一般风险准备
C72: 贷 | D72: ...
A74: 6 | B74: 模拟当期长期股权投资 | C74: 借 | D74: 长期股权投资 | E74: 损益调整
C75: 借 | D75: 长期股权投资 | E75: 其他权益变动
C76: 贷 | D76: 投资收益
C77: 贷 | D77: 少数股东损益
C78: 贷 | D78: 资本公积
C79: 贷 | D79: 其他综合收益
C80: 贷 | D80: 专项储备
C81: 贷 | D81: 其他权益工具
C82: 贷 | D82: △一般风险准备
C83: 贷 | D83: 2-3股份支付计入所有者权益的金额 | E83: （二）所有者投入和减少资本
C84: 贷 | D84: 2-4其他 | E84: （二）所有者投入和减少资本
C85: 贷 | D85: 4-3对所有者的分配 | E85: （四）利润分配
C86: 贷 | D86: 4-4其他 | E86: （四）利润分配
C87: 借 | D87: 长期股权投资 | E87: 投资成本
A89: 7 | B89: 当期变动的长投还原 | C89: 借 | D89: 长期股权投资 | E89: 投资成本
C90: 贷 | D90: 可供出售金融资产
C91: 贷 | D91: 交易性金融资产 | E91: 公允值
C92: 贷 | D92: 其他权益工具投资
C93: 贷 | D93: 其他非流动金融资产
C94: 贷 | D94: 其他非流动资产
C95: 贷 | D95: 资本公积 | E95: △（可供/其他-投资成本）
C96: 贷 | D96: 投资收益 | E96: △（公允值-投资成本）
C97: 贷 | D97: 其他综合收益 | E97: △（可供-投资成本）
C98: 贷 | D98: ...
A100: 8 | B100: 还原分红影响 | C100: 借 | D100: 投资收益
C101: 贷 | D101: 长期股权投资 | E101: 损益调整
A103: 9 | B103: 股比发生变动对享有净资产的影响 | C103: 借 | D103: 长期股权投资 | E103: 损益调整
C104: 借 | D104: 长期股权投资 | E104: 其他权益变动
C105: 贷 | D105: 资本公积
C106: 贷 | D106: 投资收益
C107: 贷 | D107: ...
B109: 模拟后期末长期股权投资 | C109: 借 | D109: 长期股权投资 | E109: 投资成本
C110: 借 | D110: 长期股权投资 | E110: 损益调整
C111: 借 | D111: 长期股权投资 | E111: 其他权益变动
D112: 长期股权投资 | E112: 小计
B114: 比对 | D114: 期末所有者权益金额
D115: 差异金额 | E115: 按比例享有净资产-长投
D116: 差异原因 | E116: 分析过程简要注明
D118: 当期模拟的净资产明细变动 | E118: 资本公积 | F118: =SUM(G118:M118) -> 0 | G118: =G20+G78+G95 -> 0 | H118: =H20+H78+H95 -> 0 | I118: =I20+I78+I95 -> 0 | J118: =J20+J78+J95 -> 0 | K118: =K20+K78+K95 -> 0 | L118: =L20+L78+L95 -> 0 | M118: =M20+M78+M95 -> 0
...

Sheet 合并抵消分录
A1: 合并抵消分录明细表
A3: 序号 | B3: 借贷方向 | C3: 项目 | D3: 二级明细 | E3: 合计 | F3: 单位1 | G3: 单位2 | H3: 单位3 | I3: 单位4 | J3: 单位5 | K3: 单位6
F4: 持股比例% | G4: 持股比例% | H4: 持股比例% | I4: 持股比例% | J4: 持股比例% | K4: 持股比例%
A6: 1 | C6: 期末权益抵消
B7: 借 | C7: 实收资本（或股本） | E7: =SUM(F7:L7) -> 0 | F7: =净资产表!E36 -> 0 | G7: =净资产表!F36 -> 0 | H7: =净资产表!G36 -> 0 | I7: =净资产表!H36 -> 0 | J7: =净资产表!I36 -> 0 | K7: =净资产表!J36 -> 0
B8: 借 | C8: 其他权益工具 | E8: =SUM(F8:L8) -> 0 | F8: =净资产表!E37 -> 0 | G8: =净资产表!F37 -> 0 | H8: =净资产表!G37 -> 0 | I8: =净资产表!H37 -> 0 | J8: =净资产表!I37 -> 0 | K8: =净资产表!J37 -> 0
B9: 借 | C9: 资本公积 | E9: =SUM(F9:L9) -> 0 | F9: =净资产表!E38 -> 0 | G9: =净资产表!F38 -> 0 | H9: =净资产表!G38 -> 0 | I9: =净资产表!H38 -> 0 | J9: =净资产表!I38 -> 0 | K9: =净资产表!J38 -> 0
B10: 借 | C10: 减：库存股 | E10: =SUM(F10:L10) -> 0 | F10: =净资产表!E39 -> 0 | G10: =净资产表!F39 -> 0 | H10: =净资产表!G39 -> 0 | I10: =净资产表!H39 -> 0 | J10: =净资产表!I39 -> 0 | K10: =净资产表!J39 -> 0
B11: 借 | C11: 其他综合收益 | E11: =SUM(F11:L11) -> 0 | F11: =净资产表!E40 -> 0 | G11: =净资产表!F40 -> 0 | H11: =净资产表!G40 -> 0 | I11: =净资产表!H40 -> 0 | J11: =净资产表!I40 -> 0 | K11: =净资产表!J40 -> 0
B12: 借 | C12: 专项储备 | E12: =SUM(F12:L12) -> 0 | F12: =净资产表!E41 -> 0 | G12: =净资产表!F41 -> 0 | H12: =净资产表!G41 -> 0 | I12: =净资产表!H41 -> 0 | J12: =净资产表!I41 -> 0 | K12: =净资产表!J41 -> 0
B13: 借 | C13: 盈余公积 | E13: =SUM(F13:L13) -> 0 | F13: =净资产表!E42 -> 0 | G13: =净资产表!F42 -> 0 | H13: =净资产表!G42 -> 0 | I13: =净资产表!H42 -> 0 | J13: =净资产表!I42 -> 0 | K13: =净资产表!J42 -> 0
B14: 借 | C14: △一般风险准备 | E14: =SUM(F14:L14) -> 0 | F14: =净资产表!E43 -> 0 | G14: =净资产表!F43 -> 0 | H14: =净资产表!G43 -> 0 | I14: =净资产表!H43 -> 0 | J14: =净资产表!I43 -> 0 | K14: =净资产表!J43 -> 0
B15: 借 | C15: 未分配利润 | E15: =SUM(F15:L15) -> 0 | F15: =净资产表!E44 -> 0 | G15: =净资产表!F44 -> 0 | H15: =净资产表!G44 -> 0 | I15: =净资产表!H44 -> 0 | J15: =净资产表!I44 -> 0 | K15: =净资产表!J44 -> 0
B16: 借 | C16: 商誉 | E16: =SUM(F16:L16) -> 0 | F16: =模拟权益法!G47 -> 0 | G16: =模拟权益法!H47 -> 0 | H16: =模拟权益法!I47 -> 0 | I16: =模拟权益法!J47 -> 0 | J16: =模拟权益法!K47 -> 0 | K16: =模拟权益法!L47 -> 0
B17: 借 | C17: 长期股权投资 | D17: 减值准备 | E17: =SUM(F17:L17) -> 0 | F17: =模拟权益法!G44 -> 0 | G17: =模拟权益法!H44 -> 0 | H17: =模拟权益法!I44 -> 0 | I17: =模拟权益法!J44 -> 0 | J17: =模拟权益法!K44 -> 0 | K17: =模拟权益法!L44 -> 0
B18: 贷 | C18: 长期股权投资 | D18: 投资成本 | E18: =SUM(F18:L18) -> 0 | F18: =模拟权益法!G40 -> 0 | G18: =模拟权益法!H40 -> 0 | H18: =模拟权益法!I40 -> 0 | I18: =模拟权益法!J40 -> 0 | J18: =模拟权益法!K40 -> 0 | K18: =模拟权益法!L40 -> 0
B19: 贷 | C19: 长期股权投资 | D19: 损益调整 | E19: =SUM(F19:L19) -> 0 | F19: =模拟权益法!G41 -> 0 | G19: =模拟权益法!H41 -> 0 | H19: =模拟权益法!I41 -> 0 | I19: =模拟权益法!J41 -> 0 | J19: =模拟权益法!K41 -> 0 | K19: =模拟权益法!L41 -> 0
B20: 贷 | C20: 长期股权投资 | D20: 其他权益变动 | E20: =SUM(F20:L20) -> 0 | F20: =模拟权益法!G42 -> 0 | G20: =模拟权益法!H42 -> 0 | H20: =模拟权益法!I42 -> 0 | I20: =模拟权益法!J42 -> 0 | J20: =模拟权益法!K42 -> 0 | K20: =模拟权益法!L42 -> 0
B21: 贷 | C21: 少数股东权益 | E21: =SUM(F21:L21) -> 0 | F21: =SUM(F7:F17)-F18-F19-F20 -> 0 | G21: =SUM(G7:G17)-G18-G19-G20 -> 0 | H21: =SUM(H7:H17)-H18-H19-H20 -> 0 | I21: =SUM(I7:I17)-I18-I19-I20 -> 0 | J21: =SUM(J7:J17)-J18-J19-J20 -> 0 | K21: =SUM(K7:K17)-K18-K19-K20 -> 0
B22: 贷 | C22: ...
A24: 2 | C24: 当期损益抵消
B25: 借 | C25: 年初未分配利润 | E25: =SUM(F25:L25) -> 0 | F25: =净资产表!E47 -> 0 | G25: =净资产表!F47 -> 0 | H25: =净资产表!G47 -> 0 | I25: =净资产表!H47 -> 0 | J25: =净资产表!I47 -> 0 | K25: =净资产表!J47 -> 0
B26: 借 | C26: 投资收益 | E26: =SUM(F26:L26) -> 0 | F26: =模拟权益法!G19+模拟权益法!G76+'投资明细-权益法'!I5 -> 0
B27: 借 | C27: 少数股权损益 | E27: =SUM(F27:L27) -> 0 | F27: =净资产表!E50-F26 -> 0
B28: 贷 | C28: 2-3股份支付计入所有者权益的金额 | D28: （二）所有者投入和减少资本 | E28: =SUM(F28:L28) -> 0 | F28: =净资产表!E54 -> 0 | G28: =净资产表!F54 -> 0 | H28: =净资产表!G54 -> 0 | I28: =净资产表!H54 -> 0 | J28: =净资产表!I54 -> 0 | K28: =净资产表!J54 -> 0
B29: 贷 | C29: 2-4其他 | D29: （二）所有者投入和减少资本 | E29: =SUM(F29:L29) -> 0 | F29: =净资产表!E55 -> 0 | G29: =净资产表!F55 -> 0 | H29: =净资产表!G55 -> 0 | I29: =净资产表!H55 -> 0 | J29: =净资产表!I55 -> 0 | K29: =净资产表!J55 -> 0
B30: 贷 | C30: 4-1提取盈余公积 | D30: （四）利润分配 | E30: =SUM(F30:L30) -> 0 | F30: =净资产表!E60 -> 0 | G30: =净资产表!F60 -> 0 | H30: =净资产表!G60 -> 0 | I30: =净资产表!H60 -> 0 | J30: =净资产表!I60 -> 0 | K30: =净资产表!J60 -> 0
B31: 贷 | C31: 4-1-1法定公积金 | D31: （四）利润分配 | E31: =SUM(F31:L31) -> 0 | F31: =净资产表!E61 -> 0 | G31: =净资产表!F61 -> 0 | H31: =净资产表!G61 -> 0 | I31: =净资产表!H61 -> 0 | J31: =净资产表!I61 -> 0 | K31: =净资产表!J61 -> 0
B32: 贷 | C32: 4-1-2任意公积金 | D32: （四）利润分配 | E32: =SUM(F32:L32) -> 0 | F32: =净资产表!E62 -> 0 | G32: =净资产表!F62 -> 0 | H32: =净资产表!G62 -> 0 | I32: =净资产表!H62 -> 0 | J32: =净资产表!I62 -> 0 | K32: =净资产表!J62 -> 0
B33: 贷 | C33: 4-1-3#储备基金 | D33: （四）利润分配 | E33: =SUM(F33:L33) -> 0 | F33: =净资产表!E63 -> 0 | G33: =净资产表!F63 -> 0 | H33: =净资产表!G63 -> 0 | I33: =净资产表!H63 -> 0 | J33: =净资产表!I63 -> 0 | K33: =净资产表!J63 -> 0
B34: 贷 | C34: 4-1-4#企业发展基金 | D34: （四）利润分配 | E34: =SUM(F34:L34) -> 0 | F34: =净资产表!E64 -> 0 | G34: =净资产表!F64 -> 0 | H34: =净资产表!G64 -> 0 | I34: =净资产表!H64 -> 0 | J34: =净资产表!I64 -> 0 | K34: =净资产表!J64 -> 0
B35: 贷 | C35: 4-1-5#利润归还投资 | D35: （四）利润分配 | E35: =SUM(F35:L35) -> 0 | F35: =净资产表!E65 -> 0 | G35: =净资产表!F65 -> 0 | H35: =净资产表!G65 -> 0 | I35: =净资产表!H65 -> 0 | J35: =净资产表!I65 -> 0 | K35: =净资产表!J65 -> 0
B36: 贷 | C36: 4-2△提取一般风险准备 | D36: （四）利润分配 | E36: =SUM(F36:L36) -> 0 | F36: =净资产表!E66 -> 0 | G36: =净资产表!F66 -> 0 | H36: =净资产表!G66 -> 0 | I36: =净资产表!H66 -> 0 | J36: =净资产表!I66 -> 0 | K36: =净资产表!J66 -> 0
B37: 贷 | C37: 4-3对所有者（或股东）的分配 | D37: （四）利润分配 | E37: =SUM(F37:L37) -> 0 | F37: =净资产表!E67 -> 0 | G37: =净资产表!F67 -> 0 | H37: =净资产表!G67 -> 0 | I37: =净资产表!H67 -> 0 | J37: =净资产表!I67 -> 0 | K37: =净资产表!J67 -> 0
B38: 贷 | C38: 4-4其他 | D38: （四）利润分配 | E38: =SUM(F38:L38) -> 0 | F38: =净资产表!E68 -> 0 | G38: =净资产表!F68 -> 0 | H38: =净资产表!G68 -> 0 | I38: =净资产表!H68 -> 0 | J38: =净资产表!I68 -> 0 | K38: =净资产表!J68 -> 0
B39: 贷 | C39: ...
C43: 交叉持股的权益和损益抵消
B44: 借 | C44: 少数股权权益
B45: 贷 | C45: 长期股权投资
B47: 借 | C47: 投资收益
B48: 贷 | C48: 少数股权损益
C53: 抵销后的少数股东权益 | D53: 合并抵消环节产生 | E53: =SUM(F53:K53) -> 0 | F53: =F21-F44 -> 0 | G53: =G21-G44 -> 0 | H53: =H21-H44 -> 0 | I53: =I21-I44 -> 0 | J53: =J21-J44 -> 0 | K53: =K21-K44 -> 0
C54: 抵销后的少数股东损益 | D54: 合并抵消环节产生 | E54: =SUM(F54:K54) -> 0 | F54: =F27-F48 -> 0 | G54: =G27-G48 -> 0 | H54: =H27-H48 -> 0 | I54: =I27-I48 -> 0 | J54: =J27-J48 -> 0 | K54: =K27-K48 -> 0

Sheet 资本公积变动
A1: 资本公积变动核查表
A3: 资本公积 | B3: 合计 | C3: 合并抵消环节 | D3: 母公司 | E3: 单位1 | F3: 单位2 | G3: 单位3 | H3: 单位4 | I3: 单位5 | J3: 单位6
E4: 持股比例% | F4: 持股比例% | G4: 持股比例% | H4: 持股比例% | I4: 持股比例% | J4: 持股比例%
A5: 期初金额 | K5: 涂黑色为锁定，不让填充
A6: 当期变动 | B6: =SUM(C6:I6) -> 0 | C6: =C7+C8+C9+C10 -> 0 | D6: =D7+D8+D9+D10 -> 0 | E6: =E7+E8+E9+E10 -> 0 | F6: =F7+F8+F9+F10 -> 0 | G6: =G7+G8+G9+G10 -> 0 | H6: =H7+H8+H9+H10 -> 0 | I6: =I7+I8+I9+I10 -> 0
A7: "+权益法模拟 | B7: =SUM(C7:I7) -> 0 | E7: =模拟权益法!G118 -> 0 | F7: =模拟权益法!H118 -> 0 | G7: =模拟权益法!I118 -> 0 | H7: =模拟权益法!J118 -> 0 | I7: =模拟权益法!K118 -> 0 | J7: =模拟权益法!L118 -> 0
A8: "-合并抵消数 | B8: =SUM(C8:I8) -> 0 | E8: =合并抵消分录!F9 -> 0 | F8: =合并抵消分录!G9 -> 0 | G8: =合并抵消分录!H9 -> 0 | H8: =合并抵消分录!I9 -> 0 | I8: =合并抵消分录!J9 -> 0 | J8: =合并抵消分录!K9 -> 0
A9: "+自身报表变动 | B9: =SUM(C9:I9) -> 0 | D9: =净资产表!D81 -> 0 | E9: =净资产表!E81 -> 0 | F9: =净资产表!F81 -> 0 | G9: =净资产表!G81 -> 0 | H9: =净资产表!H81 -> 0 | I9: =净资产表!I81 -> 0 | J9: =净资产表!J81 -> 0
A10: 其他 | B10: =SUM(C10:I10) -> 0 | C10: =B16 -> 0
A11: 期末金额 | B11: =B5+B6 -> 0
A13: 期末合并报表金额 | C13: 取自合并后财务报表期末数
A14: 差异 | B14: =B13-B11 -> 0
A16: 合并抵消环节调整事项如下 | B16: =SUM(C17:C21) -> 0
A17: 1
A18: 2
A19: 3
A20: 4
A21: 5
