Workbook

Sheet 目录
A1: 底稿开列时，可先在以下单元格填写有关内容，以便其他底稿引用有关数据：
A2: 被审计单位：ABC公司 | D2: 序号 | E2: 内容 | F2: 索引号
A3: 编制人：张三 | D3: 1 | E3: 程序表 | F3: S34-16
A4: 编制日期：2025.X.X | D4: =D3+1 -> 2 | E4: 第三方回款情况检查表 | F4: S34-16-1
A5: 复核人：李四 | D5: =D4+1 -> 3 | E5: 同行业第三方回款对比表 | F5: S34-16-2
A6: 复核日期：2025.X.X
A7: 会计期间：202X年度

Sheet S34-16程序表
A1: 致同会计师事务所
A2: 针对证监会、沪深两交所首次公开发行、北交所公开发行并上市监管法规的核查程序—第三方回款
A3: =目录!A2 -> 被审计单位：ABC公司 | D3: =目录!A3 -> 编制人：张三 | F3: =目录!A4 -> 编制日期：2025.X.X | H3: 索引号： S34-16
A4: =目录!A7 -> 会计期间：202X年度 | D4: =目录!A5 -> 复核人：李四 | F4: =目录!A6 -> 复核日期：2025.X.X | H4: 页 次：
A6: 一、核查目标
B7: 根据《监管规则适用指引-发行类第5号》（以下简称监管规则指引发行类5号）、《上海证券交易所发行上市审核业务指南第4号——常见问题的信息披露和核查要求自查表 第1号首次公开发行》（以下简称上交所业务指南第4号-第1号）、《深圳证券交易所股票发行上市审核业务指南第3号——首次公开发行审核关注要点》（以下简称深交所业务指南3号）及《北京证券交易所向不特定合格投资者公开发行股票并上市业务规则适用指引第2号》（以下简称北交所适用指引第2号）的要求，严格遵守现行各项执业准则和信息披露规范要求，勤勉尽责，审慎执业，就《监管规则指引发行类5号》、《上交所业务指南第4号-第1号》、《深交所业务指南3号》及《北交所适用指引第2号》中提出的与注册会计师相关的问题进行逐项检查，核对已执行的审计程序和获取的审计证据是否已满足IPO申报财务报表审计中对第三方回款的核查要求。
B8: 提示：【使用时，请删除本段提示文字】 1、本核查程序表针对《监管规则指引发行类5号》“5-11、第三方回款”、《上交所业务指南第4号-第1号》“3-11、第三方回款”、《深交所业务指南3号》“26-7、是否存在第三方回款的情形”及《北交所适用指引第2号》“2-12、第三方回款”的要求厘定。 2、本核查程序表仅列示需完成的核查程序，取得的审计证据、凭证及其索引号，审计底稿的索引号。具体审计底稿可索引计划阶段、特项程序及各业务循环底稿，也可以增加单独的工作簿进行记录。 3、本程序表应根据被审计单位的实际情况进行适当的增删修改，以反映实际执行的审计工作情况。 | C8: 就这些事项的核查工作归集出一些常用的实质性程序，供项目组自查时核对参考。这些程序涉及的工作在执行项目审计时已经完成，本底稿用于项目组进行自查时，检查核对已完成的审计工作并进行汇总，以满足证监会单独形成自查底稿的要求。所列举的程序仅为常用程序，且主要是相关事项所涉及循环的实质性程序，项目组应当根据项目的实际情况进行适当的增删修改，以反映实际执行的审计工作情况。另外，有关内控了解测试、关联方、舞弊等审计工作，已在自查工作的其他部分反映，故此处未再复述。
A9: 序号 | B9: 程序 | E9: 取得证据、凭证 | F9: 取得证据、凭证索引号 | G9: 核查方式注 | H9: 审计程序索引
A10: 二、已执行的审计程序【项目小组应根据被审计单位实际情况修改、增减上述核查程序；修改、设计核查底稿】
A11: 《监管规则指引发行类5号》“5-11、第三方回款”、《上交所业务指南第4号-第1号》“3-11、第三方回款”、《深交所业务指南3号》“26-7、是否存在第三方回款的情形”、《北交所适用指引第2号》“2-12、第三方回款” | B11: 第三方回款通常是指发行人收到的销售回款的支付方（如银行汇款的汇款方、银行承兑汇票或商业承兑汇票的出票方或背书转让方）与签订经济合同的往来客户（或实际交易对手）不一致的情况。 核查要求： 如发行人报告期内存在由第三方回款的情形，保荐人和申报会计师应就以下事项进行重点核查： （1）第三方回款的真实性，是否存在虚构交易或调节账龄情形；中介机构需核查的内容包括但不限于：抽样选取不一致业务的明细样本和银行对账单回款记录，追查至相关业务合同、业务执行记录及资金流水凭证，获取相关客户代付款确认依据，以核实委托付款的真实性、代付金额的准确性及付款方和委托方之间的关系，说明合同签约方和付款方不一致的合理原因及第三方回款统计明细记录的完整性，并对第三方回款所对应营业收入的真实性发表明确意见； （2）第三方回款形成收入占营业收入的比例，相关金额及比例是否处于合理范围； （3）第三方回款的原因、必要性及商业合理性，是否与经营模式相关、符合行业经营特点，是否能够区分不同类别的第三方回款；与经营模式相关、符合行业经营特点的第三方回款情况包括但不限于：①客户为个体工商户或自然人通过家庭约定由直系亲属代为支付货款：②客户为自然人控制的企业，该企业的法定代表人、实际控制人代为支付货款：③客户所属集团通过集团财务公司或指定相关公司代客户统一对外付款④政府采购项目指定财政部门或专门部门统一付款⑤通过应收账款保理、供应链物流等合规方式或渠道完成付款：⑥境外客户指定付款。 （4）发行人及其实际控制人、董监高或其他关联方与第三方回款的支付方是否存在关联关系或其他利益安排； （5）境外销售涉及境外第三方回款的，第三方代付行为的商业合理性或合规性； （6）是否因第三方回款导致货款归属纠纷； （7）如合同明确约定第三方付款的，该交易安排是否合理； （8）资金流、实物流与合同约定及商业实质是否一致，第三方回款是否具有可验证性，是否影响销售循环内部控制有效性的认定。
A12: 1 | B12: 核查第三方回款相关销售收入统计的完整性
A13: （1） | B13: 结合了解内部控制和控制测试程序，考虑第三方回款统计明细记录的完整性，即发行人是否建立了有效的内部控制机制以识别并管理第三方回款。 | H13: B23-1/C2
A14: （2） | B14: 在细节测试中关注合同缔约方和回款的对方账户名称之间是否一致，判断是否还存在其他未记录的第三方回款； | H14: D4-24
A15: （3） | B15: 实际付款人和合同签订方不一致，但未纳入第三方回款统计的金额也应分析合理性、获取相关客户代付款确认依据。 | H15: D4-24
A16: 2 | B16: 分析第三方回款的必要性和合理性
A17: （1） | B17: 对管理层、销售负责人员和客户相关负责人员执行访谈程序，了解客户方实际控制人和关键经办人相关信息、实际从事业务、向企业采购的商业理由、货款结算模式以及通过第三方支付货款的原因等，判断其合理性。 | H17: S34-16-1
A18: （2） | B18: 获取并检查客户出具的委托付款说明，对第三方支付货款的原因、第三方付款人名称、付款明细、第三方付款人是否与发行人及其实际控制人、董监高或其他关联方具有关联关系等情况进行核实。 | H18: S34-16-1
A19: （3） | B19: 了解代付行为的商业合理性或合法合规性，报告期内是否存在因第三方回款导致的货款归属纠纷，必要时可咨询法律专家意见。 | H19: S34-16-1
A20: （4） | B20: 与与同行业公司第三方回款情况及原因进行对比，确认公司第三方回款是否符合公司所在的行业特点和经营模式。 | H20: S34-16-2
A21: 3 | B21: 核查第三方回款相关销售收入的真实性
A22: （1） | B22: 抽样选取实际付款人和合同签订方不一致业务的明细样本和银行对账单回款记录，追查至相关业务合同、业务执行记录及资金流水凭证，获取相关客户代付款确认依据，以核实和确认委托付款的真实性、代付金额的准确性及付款方和委托方之间的关系。 | H22: S34-16-1
A23: （2） | B23: 核对第三方回款业务的资金流、实物流与合同约定及商业实质是否一致。 | H23: S34-16-1
A24: 4 | B24: 核对发行人在招股说明书营业收入部分是否充分披露了第三方回款相关情况，以及所披露内容与执行审计程序时了解到的情况是否相符。
A27: 注—核查方式：
A28: 如：询问（口头、书面）、检查（记录或文件、有形资产）、观察、函证、重新计算、重新执行、分析程序；
A29: 以及实地走访、电话访谈、核查工商资料等。

Sheet S34-16-1第三方回款情况检查表
A1: 致同会计师事务所
A2: 第三方回款情况检查表
A3: =目录!A2 -> 被审计单位：ABC公司 | H3: =目录!A3 -> 编制人：张三 | J3: =目录!A4 -> 编制日期：2025.X.X | M3: 索引号： S34-16-1
A4: =目录!A7 -> 会计期间：202X年度 | H4: =目录!A5 -> 复核人：李四 | J4: =目录!A6 -> 复核日期：2025.X.X | M4: 页 次：
A6: 序号 | B6: 商品/服务名称 | C6: 合同缔约方名称 | D6: 付款方名称 | E6: 当期确认收入金额 | F6: 代付款金额 | G6: 第三方代付的原因 （此处简述，可索引访谈记录或者客户书面声明） | H6: 合理性分析 | K6: 真实性核查
H7: 代付原因是否合理 | I7: 是否存在合规风险 | J7: 是否存在商业纠纷 | K7: 交易实质是否一致 | L7: 实物流是否存在异常 | M7: 是否存在未披露的关联关系
A8: 1
A9: 2
A10: 3
A11: 4
A12: 5
E19: =SUM(E8:E18) -> 0 | F19: =SUM(F8:F18) -> 0
A21: 审计说明：
A23: 1、 | B23: 当期营业收入：
B24: 当期第三方回款总额： | C24: =F19 -> 0
B25: 第三方回款形成收入占营业收入的比例： | C25: =C24/C23 -> #DIV/0!
A27: 2、 | B27: ……

Sheet S34-16-2 同行业第三方回款对比表
A1: 致同会计师事务所
A2: 同行业第三方回款对比表
A3: =目录!A2 -> 被审计单位：ABC公司 | E3: =目录!A3 -> 编制人：张三 | G3: =目录!A4 -> 编制日期：2025.X.X | H3: 索引号： S34-16-1
A4: =目录!A7 -> 会计期间：202X年度 | E4: =目录!A5 -> 复核人：李四 | G4: =目录!A6 -> 复核日期：2025.X.X | H4: 页 次：
A6: 序号 | B6: 同行业名称 | C6: 期间 | D6: 商品/服务名称 | E6: 第三方回款金额 | F6: 占营业收入比例 | G6: 本公司第三方回款占营业收入占比 | H6: 信息来源
A8: 1 | B8: X公司 | C8: 2020 | D8: A产品
A9: 2 | B9: X公司 | C9: 2020 | D9: B产品
A10: 3 | B10: X公司 | C10: 2021 | D10: A产品
A11: 4 | B11: X公司 | C11: 2021 | D11: B产品
A12: 5
A13: 4
A14: 5
G19: =SUM(G8:G18) -> 0
A21: 审计说明：
A23: 1、 | B23: 当期营业收入：
B24: 当期第三方回款总额： | E24: =#REF! -> #REF!
B25: 第三方回款形成收入占营业收入的比例： | E25: =E24/E23 -> #REF!
A27: 2、 | B27: ……

Sheet GT_Custom
A1: C1 | B1: Custom 1
A2: C2 | B2: Custom 2
A3: C3 | B3: Custom 3
A4: C4 | B4: Custom 4
A5: C5 | B5: Custom 5
A6: C6 | B6: Custom 6
A7: C7 | B7: Custom 7
A8: C8 | B8: Custom 8
