Workbook

Sheet 底稿目录
A1: 底稿开列时，可先在以下单元格填写有关内容，以便其他底稿引用有关数据：
A2: 被审计单位： | D2: 序号 | E2: 内容 | F2: 索引号
A3: 截止日：202X年12月31日 | D3: 1 | E3: 递延所得税负债审计程序表 | F3: N3A
A4: 编制人： | D4: 2 | E4: 递延所得税负债审定表 | F4: N3-1
A5: 编制日期： | D5: 3 | E5: 递延所得税负债明细表 | F5: N3-2
A6: 复核人： | D6: 4 | E6: 调整分录汇总表 | F6: N3-3
A7: 复核日期：
A9: 关于工作底稿与审计程序索引号对应的说明
A10: 1.编制的审计工作底稿应与审计程序对应。审计项目组应根据被审计单位实际情况和风险评估情况在实质性程序表中裁剪、修改或增加审计程序，根据实际执行的审计程序完成相应审计工作底稿，编制的工作底稿中应按自然顺序依次编制索引号，并通过唯一的索引号将与实质性程序表中的程序对应关联（即将工作底稿的索引号填入实质性程序表中的底稿索引号列）。
A14: 2.获取的支持性证据应与审计底稿或程序对应。审计项目组在完成底稿时获取的支持性证据应根据底稿索引号编制下一级按自然顺序排序的索引号（如D1-2-1、D1-2-2、……），并在底稿中说明引用的支持性证据、关联索引号。
A17: 3.工作底稿索引号的编码规则：实质性程序索引号按循环从“D”到“N”,循环内账户以顺序号排列，模板中底稿索引号按账户顺序+自然数顺序（即模板中索引号按二级自然顺序排列，如D1-1、D1-2、D1-3、……D1-N）。

Sheet 递延所得税负债审计程序表的N3A
A1: 致同会计师事务所
A2: 递延所得税负债实质性程序表
A3: =底稿目录!A2 | D3: =底稿目录!A4 | F3: =底稿目录!A5 | I3: 索引号： | J3: N3A
A4: =底稿目录!A3 | D4: =底稿目录!A6 | F4: =底稿目录!A7 | I4: 页次：
A5: 一、本账户涉及的科目
A6: 递延所得税负债
A7: 二、审计目标与财务报表认定对应关系
A8: 审计目标 | H8: 财务报表的认定
A9: A.资产负债表中记录的递延所得税负债是存在的，且已经记录在恰当的账户中 | H9: 存在
A10: B.所有应记录的递延所得税负债均已记录，所有应当包括在财务报表中的相关披露均已包括 | H10: 完整性
A11: C.记录的递延所得税负债由被审计单位拥有或控制 | H11: 权利和义务
A12: D.递延所得税负债以恰当的金额包括在财务报表中，与之相关的计价或分摊调整已恰当记录，相关披露已得到恰当计量和描述 | H12: 准确性、计价和分摊
A13: E.递延所得税负债已被恰当地汇总或分解且表述清楚，相关披露在按照企业会计准则的编制基础下是相关的、可理解的 | H13: 列报
A14: 三、计划实施的实质性程序
A15: 序号 | B15: 对应LEAP程序 | C15: 审计程序 | D15: 程序分类 | E15: 审计目标 | J15: 底稿索引号
E16: 存在 | F16: 完整性 | G16: 权利和 义务 | H16: 准确性、计价和分摊 | I16: 列报 | K16: 根据被审计单位实际情况和风险评估情况裁剪、修改或增加审计程序
A17: 1 | B17: 常规程序 | C17: 获取递延所得税负债明细表，完成以下工作并编制审定表。 （1）复核加计正确 。 （2）将总金额与总账、明细账合计数核对相符。 （3）核对期初余额与上期审定期末余额、纳税申报表及税务机关的认定数是否相符。 （4）识别被审计单位期初递延所得税负债的项目及金额，以及对当期经营损失以及未来期间的影响。 | D17: 常规★ | E17: √ | F17: √ | H17: √ | J17: N3-1 /N3-2
A18: 2 | B18: 期初余额 | C18: 对于期初余额审计，获得并查阅账户余额明细表、前期纳税申报表和其他有持续影响的税收文件资料，确定采用的会计政策和程序是适当的、应纳税差异是否合理，必要时，向税务专家咨询。(适用于首次承接） | D18: 备选 | E18: √ | F18: √ | G18: √ | H18: √
A19: 3 | B19: 应对措施-检查 | C19: 确定具有持续性影响的相关税收规定和事项是否仍有效（例如，优惠政策、税率是否发生变化等）。检查被审计单位用于确认递延所得税负债的税率是否根据税法的规定，按照预期收回该资产期间的适用税率计量。 | D19: 常规★ | H19: √ | J19: N3-2
A20: 4 | B20: 应对措施-检查 | C20: 重新计算各项应纳税暂时性差异，检查其会计处理是否正确。 | D20: 常规★ | H20: √ | J20: N1-4
A21: 5 | C21: 根据评估的舞弊风险等因素增加的审计程序。 | D21: IPO/上市/新三板/重组/舞弊应对
A22: 6 | B22: 常规程序 | C22: 根据适用的会计准则及相关规定，确定财务报表的列报与披露是否恰当。 | D22: 常规★ | I22: √ | J22: A1-1/A1-15 /A1-16

Sheet 递延所得税负债审定表N3-1
A1: 致同会计师事务所
A2: 递延所得税负债审定表
A3: =底稿目录!A2 | E3: =底稿目录!A4 | I3: =底稿目录!A5 | M3: 索引号： | N3: N3-1
A4: =底稿目录!A3 | E4: =底稿目录!A6 | I4: =底稿目录!A7 | M4: 页次：
A5: 项目 | B5: 期初数 | F5: 期末数 | J5: 期末未审数与期初 未审数的比较 | L5: 期末审定数与期初 审定数的比较 | N5: 原因分析
B6: 未审数 | C6: 账项调整 | D6: 重分类调整 | E6: 审定数 | F6: 未审数 | G6: 账项调整 | H6: 重分类调整 | I6: 审定数 | J6: 变动额 | K6: 变动率 | L6: 变动额 | M6: 变动率
A7: 评估增值 | B7: =SUMIF('递延所得税负债明细表N3-2'!$B$11:$B$21,'递延所得税负债审定表N3-1'!$A7,'递延所得税负债明细表N3-2'!E$11:E$21) | C7: =SUMIF('递延所得税负债明细表N3-2'!$B$11:$B$21,'递延所得税负债审定表N3-1'!$A7,'递延所得税负债明细表N3-2'!F$11:F$21) | D7: =SUMIF('递延所得税负债明细表N3-2'!$B$11:$B$21,'递延所得税负债审定表N3-1'!$A7,'递延所得税负债明细表N3-2'!G$11:G$21) | E7: =B7+C7+D7 | F7: =SUMIF('递延所得税负债明细表N3-2'!$B$11:$B$21,'递延所得税负债审定表N3-1'!$A7,'递延所得税负债明细表N3-2'!K$11:K$21) | G7: =SUMIF('递延所得税负债明细表N3-2'!$B$11:$B$21,'递延所得税负债审定表N3-1'!$A7,'递延所得税负债明细表N3-2'!L$11:L$21) | H7: =SUMIF('递延所得税负债明细表N3-2'!$B$11:$B$21,'递延所得税负债审定表N3-1'!$A7,'递延所得税负债明细表N3-2'!M$11:M$21) | I7: =F7+G7+H7 | J7: =F7-B7 | K7: =IF(AND(B7=0,J7=0),0,IF(AND(B7=0,J7>0),1,J7/B7)) | L7: =I7-E7 | M7: =IF(AND(E7=0,L7=0),0,IF(AND(E7=0,L7>0),1,L7/E7))
A8: 公允价值变动 | B8: =SUMIF('递延所得税负债明细表N3-2'!$B$11:$B$21,'递延所得税负债审定表N3-1'!$A8,'递延所得税负债明细表N3-2'!E$11:E$21) | C8: =SUMIF('递延所得税负债明细表N3-2'!$B$11:$B$21,'递延所得税负债审定表N3-1'!$A8,'递延所得税负债明细表N3-2'!F$11:F$21) | D8: =SUMIF('递延所得税负债明细表N3-2'!$B$11:$B$21,'递延所得税负债审定表N3-1'!$A8,'递延所得税负债明细表N3-2'!G$11:G$21) | E8: =B8+C8+D8 | F8: =SUMIF('递延所得税负债明细表N3-2'!$B$11:$B$21,'递延所得税负债审定表N3-1'!$A8,'递延所得税负债明细表N3-2'!K$11:K$21) | G8: =SUMIF('递延所得税负债明细表N3-2'!$B$11:$B$21,'递延所得税负债审定表N3-1'!$A8,'递延所得税负债明细表N3-2'!L$11:L$21) | H8: =SUMIF('递延所得税负债明细表N3-2'!$B$11:$B$21,'递延所得税负债审定表N3-1'!$A8,'递延所得税负债明细表N3-2'!M$11:M$21) | I8: =F8+G8+H8 | J8: =F8-B8 | K8: =IF(AND(B8=0,J8=0),0,IF(AND(B8=0,J8>0),1,J8/B8)) | L8: =I8-E8 | M8: =IF(AND(E8=0,L8=0),0,IF(AND(E8=0,L8>0),1,L8/E8))
A9: 使用权资产 | B9: =SUMIF('递延所得税负债明细表N3-2'!$B$11:$B$21,'递延所得税负债审定表N3-1'!$A9,'递延所得税负债明细表N3-2'!E$11:E$21) | C9: =SUMIF('递延所得税负债明细表N3-2'!$B$11:$B$21,'递延所得税负债审定表N3-1'!$A9,'递延所得税负债明细表N3-2'!F$11:F$21) | D9: =SUMIF('递延所得税负债明细表N3-2'!$B$11:$B$21,'递延所得税负债审定表N3-1'!$A9,'递延所得税负债明细表N3-2'!G$11:G$21) | E9: =B9+C9+D9 | F9: =SUMIF('递延所得税负债明细表N3-2'!$B$11:$B$21,'递延所得税负债审定表N3-1'!$A9,'递延所得税负债明细表N3-2'!K$11:K$21) | G9: =SUMIF('递延所得税负债明细表N3-2'!$B$11:$B$21,'递延所得税负债审定表N3-1'!$A9,'递延所得税负债明细表N3-2'!L$11:L$21) | H9: =SUMIF('递延所得税负债明细表N3-2'!$B$11:$B$21,'递延所得税负债审定表N3-1'!$A9,'递延所得税负债明细表N3-2'!M$11:M$21) | I9: =F9+G9+H9 | J9: =F9-B9 | K9: =IF(AND(B9=0,J9=0),0,IF(AND(B9=0,J9>0),1,J9/B9)) | L9: =I9-E9 | M9: =IF(AND(E9=0,L9=0),0,IF(AND(E9=0,L9>0),1,L9/E9))
A10: 购入摊销年限大于税法规定的资产 | B10: =SUMIF('递延所得税负债明细表N3-2'!$B$11:$B$21,'递延所得税负债审定表N3-1'!$A10,'递延所得税负债明细表N3-2'!E$11:E$21) | C10: =SUMIF('递延所得税负债明细表N3-2'!$B$11:$B$21,'递延所得税负债审定表N3-1'!$A10,'递延所得税负债明细表N3-2'!F$11:F$21) | D10: =SUMIF('递延所得税负债明细表N3-2'!$B$11:$B$21,'递延所得税负债审定表N3-1'!$A10,'递延所得税负债明细表N3-2'!G$11:G$21) | E10: =B10+C10+D10 | F10: =SUMIF('递延所得税负债明细表N3-2'!$B$11:$B$21,'递延所得税负债审定表N3-1'!$A10,'递延所得税负债明细表N3-2'!K$11:K$21) | G10: =SUMIF('递延所得税负债明细表N3-2'!$B$11:$B$21,'递延所得税负债审定表N3-1'!$A10,'递延所得税负债明细表N3-2'!L$11:L$21) | H10: =SUMIF('递延所得税负债明细表N3-2'!$B$11:$B$21,'递延所得税负债审定表N3-1'!$A10,'递延所得税负债明细表N3-2'!M$11:M$21) | I10: =F10+G10+H10 | J10: =F10-B10 | K10: =IF(AND(B10=0,J10=0),0,IF(AND(B10=0,J10>0),1,J10/B10)) | L10: =I10-E10 | M10: =IF(AND(E10=0,L10=0),0,IF(AND(E10=0,L10>0),1,L10/E10))
A11: 其他 | B11: =SUMIF('递延所得税负债明细表N3-2'!$B$11:$B$21,'递延所得税负债审定表N3-1'!$A11,'递延所得税负债明细表N3-2'!E$11:E$21) | C11: =SUMIF('递延所得税负债明细表N3-2'!$B$11:$B$21,'递延所得税负债审定表N3-1'!$A11,'递延所得税负债明细表N3-2'!F$11:F$21) | D11: =SUMIF('递延所得税负债明细表N3-2'!$B$11:$B$21,'递延所得税负债审定表N3-1'!$A11,'递延所得税负债明细表N3-2'!G$11:G$21) | E11: =B11+C11+D11 | F11: =SUMIF('递延所得税负债明细表N3-2'!$B$11:$B$21,'递延所得税负债审定表N3-1'!$A11,'递延所得税负债明细表N3-2'!K$11:K$21) | G11: =SUMIF('递延所得税负债明细表N3-2'!$B$11:$B$21,'递延所得税负债审定表N3-1'!$A11,'递延所得税负债明细表N3-2'!L$11:L$21) | H11: =SUMIF('递延所得税负债明细表N3-2'!$B$11:$B$21,'递延所得税负债审定表N3-1'!$A11,'递延所得税负债明细表N3-2'!M$11:M$21) | I11: =F11+G11+H11 | J11: =F11-B11 | K11: =IF(AND(B11=0,J11=0),0,IF(AND(B11=0,J11>0),1,J11/B11)) | L11: =I11-E11 | M11: =IF(AND(E11=0,L11=0),0,IF(AND(E11=0,L11>0),1,L11/E11))
B12: =SUMIF('递延所得税负债明细表N3-2'!$B$11:$B$21,'递延所得税负债审定表N3-1'!$A12,'递延所得税负债明细表N3-2'!E$11:E$21) | C12: =SUMIF('递延所得税负债明细表N3-2'!$B$11:$B$21,'递延所得税负债审定表N3-1'!$A12,'递延所得税负债明细表N3-2'!F$11:F$21) | D12: =SUMIF('递延所得税负债明细表N3-2'!$B$11:$B$21,'递延所得税负债审定表N3-1'!$A12,'递延所得税负债明细表N3-2'!G$11:G$21) | E12: =B12+C12+D12 | F12: =SUMIF('递延所得税负债明细表N3-2'!$B$11:$B$21,'递延所得税负债审定表N3-1'!$A12,'递延所得税负债明细表N3-2'!K$11:K$21) | G12: =SUMIF('递延所得税负债明细表N3-2'!$B$11:$B$21,'递延所得税负债审定表N3-1'!$A12,'递延所得税负债明细表N3-2'!L$11:L$21) | H12: =SUMIF('递延所得税负债明细表N3-2'!$B$11:$B$21,'递延所得税负债审定表N3-1'!$A12,'递延所得税负债明细表N3-2'!M$11:M$21) | I12: =F12+G12+H12 | J12: =F12-B12 | K12: =IF(AND(B12=0,J12=0),0,IF(AND(B12=0,J12>0),1,J12/B12)) | L12: =I12-E12 | M12: =IF(AND(E12=0,L12=0),0,IF(AND(E12=0,L12>0),1,L12/E12))
A13: 合计 | B13: =SUM(B7:B12) | C13: =SUM(C7:C12) | D13: =SUM(D7:D12) | E13: =SUM(E7:E12) | F13: =SUM(F7:F12) | G13: =SUM(G7:G12) | H13: =SUM(H7:H12) | I13: =SUM(I7:I12) | J13: =SUM(J7:J12) | K13: =IF(AND(B13=0,J13=0),0,IF(AND(B13=0,J13>0),1,J13/B13)) | L13: =I13-E13 | M13: =IF(AND(E13=0,L13=0),0,IF(AND(E13=0,L13>0),1,L13/E13))
A14: 试算平衡表数
A15: 差异数 | E15: =E13-E14 | I15: =I13-I14
A16: 1.审计说明
A17: （1）期末余额较期初余额增加（负数为减少）：
A18: 主要原因（比例超过30%的）：
A19: （2）情况说明。
A21: 2.审计结论

Sheet 递延所得税负债明细表N3-2
A1: 致同会计师事务所
A2: 递延所得税负债明细表
A3: =底稿目录!A2 | C3: =底稿目录!A4 | H3: =底稿目录!A5 | M3: 索引号： | N3: N3-2
A4: =底稿目录!A3 | C4: =底稿目录!A6 | H4: =底稿目录!A7 | M4: 页次：
A5: 一、审计目标
A6: 递延所得税负债以恰当的金额包括在财务报表中，与之相关的计价调整已恰当记录。
A7: 二、审计过程
A8: 【项目组根据被审计单位税收情况增减项目】
A9: 项 目 | B9: 分类 | C9: 期初 | I9: 期末
C10: 暂时性差异 | D10: 适用税率 | E10: 递延所得税负债期初余额 | F10: 账项调整 | G10: 重分类调整 | H10: 递延所得税负债期初审定数 | I10: 暂时性差异 | J10: 适用税率 | K10: 递延所得税负债期末余额 | L10: 账项调整 | M10: 重分类调整 | N10: 递延所得税负债期末审定数
A11: 非同一控制企业合并资产评估增值 | B11: 评估增值 | E11: =ROUND(C11*D11,2) | H11: =E11+F11+G11 | K11: =ROUND(I11*J11,2) | N11: =K11+L11+M11
A12: 使用权资产 | B12: 使用权资产 | E12: =ROUND(C12*D12,2) | H12: =E12+F12+G12 | K12: =ROUND(I12*J12,2) | N12: =K12+L12+M12
A13: 交易性金融资产（公允价值与初始账面成本差异） | B13: 公允价值变动 | E13: =ROUND(C13*D13,2) | H13: =E13+F13+G13 | K13: =ROUND(I13*J13,2) | N13: =K13+L13+M13
A14: 其他权益工具投资（公允价值与初始账面成本差异） | B14: 公允价值变动 | E14: =ROUND(C14*D14,2) | H14: =E14+F14+G14 | K14: =ROUND(I14*J14,2) | N14: =K14+L14+M14
A15: 计入其他综合收益的应收款项融资公允价值变动 | B15: 公允价值变动 | E15: =ROUND(C15*D15,2) | H15: =E15+F15+G15 | K15: =ROUND(I15*J15,2) | N15: =K15+L15+M15
A16: 计入其他综合收益的其他债权投资公允价值变动 | B16: 公允价值变动 | E16: =ROUND(C16*D16,2) | H16: =E16+F16+G16 | K16: =ROUND(I16*J16,2) | N16: =K16+L16+M16
A17: 投资性房地产（公允价值与账面差异） | B17: 公允价值变动 | E17: =ROUND(C17*D17,2) | H17: =E17+F17+G17 | K17: =ROUND(I17*J17,2) | N17: =K17+L17+M17
A18: 交易性金融负债（公允价值与账面差异） | B18: 公允价值变动 | E18: =ROUND(C18*D18,2) | H18: =E18+F18+G18 | K18: =ROUND(I18*J18,2) | N18: =K18+L18+M18
A19: 购入摊销年限大于税法规定的资产 | B19: 购入摊销年限大于税法规定的资产 | E19: =ROUND(C19*D19,2) | H19: =E19+F19+G19 | K19: =ROUND(I19*J19,2) | N19: =K19+L19+M19
A20: 除上述项目以外的其他[注1] | B20: 其他 | E20: =ROUND(C20*D20,2) | H20: =E20+F20+G20 | K20: =ROUND(I20*J20,2) | N20: =K20+L20+M20
A21: ………… | E21: =ROUND(C21*D21,2) | H21: =E21+F21+G21 | K21: =ROUND(I21*J21,2) | N21: =K21+L21+M21
C23: =SUM(C11:C22) | E23: =SUM(E11:E22) | F23: =SUM(F11:F22) | G23: =SUM(G11:G22) | H23: =SUM(H11:H22) | I23: =SUM(I11:I22) | K23: =SUM(K11:K22) | L23: =SUM(L11:L22) | M23: =SUM(M11:M22) | N23: =SUM(N11:N22)
A24: 三、审计说明
A25: 递延所得税负债测算详见<递延所得税资产（负债）测算表N1-4>
A28: 四、审计结论
A30: [注1]若有其他项目，需详加说明内容。

Sheet 调整分录汇总表N3-3
A1: 致同会计师事务所
A2: 递延所得税资产调整分录汇总表
A3: =底稿目录!A2 | D3: =底稿目录!A4 | G3: =底稿目录!A4 | I3: 索引号： | J3: N3-3
A4: =底稿目录!A3 | D4: =底稿目录!A6 | G4: =底稿目录!A7 | I4: 页次：
A5: 调整事项说明 | B5: 类别（报表调整/账项调整/其他） | C5: 报表项目 | D5: 科目名称 | E5: 附注项目 | F5: …… | G5: 借方调整金额 | H5: 贷方调整金额 | I5: 索引 | J5: 备注
A21: 提示：本底稿适用于调整分录较多、较复杂的项目，且仅列示与本报表项目相关的审计调整。项目组可根据项目实际情况选择是否使用该底稿。

Sheet GT_Custom
A1: C1 | B1: Custom 1
A2: C2 | B2: Custom 2
A3: C3 | B3: Custom 3
A4: C4 | B4: Custom 4
A5: C5 | B5: Custom 5
A6: C6 | B6: Custom 6
A7: C7 | B7: Custom 7
A8: C8 | B8: Custom 8
