Workbook

Sheet 底稿目录
A1: 底稿开列时，可先在以下单元格填写有关内容，以便其他底稿引用有关数据：
A2: 被审计单位：
A3: 截止日：202X年12月31日 | D3: 序号 | E3: 内容 | F3: 索引号 | G3: 备注
A4: 编制人： | D4: 1 | E4: 实质性程序表 | F4: K2A
A5: 编制日期： | D5: 2 | E5: 审定表 | F5: K2-1
A6: 复核人： | D6: 3 | E6: 附注披露信息（国企） | H6: 无需打印
A7: 复核日期： | D7: 4 | E7: 附注披露信息（上市公司） | H7: 无需打印
D8: 5 | E8: 明细表 | F8: K2-2
A9: 关于工作底稿与审计程序索引号对应的说明 | D9: 6 | E9: 调整分录汇总 | F9: K2-3
A10: 1.编制的审计工作底稿应与审计程序对应。审计项目组应根据被审计单位实际情况和风险评估情况在实质性程序表中裁剪、修改或增加审计程序，根据实际执行的审计程序完成相应审计工作底稿，编制的工作底稿中应按自然顺序依次编制索引号，并通过唯一的索引号将与实质性程序表中的程序对应关联（即将工作底稿的索引号填入实质性程序表中的底稿索引号列）。 | D10: 7 | E10: 合同取得成本明细表 | F10: K2-4
D11: 8 | E11: 摊销测算表 | F11: K2-5
D12: 9 | E12: 其他流动资产检查表 | F12: K2-6
A14: 2.获取的支持性证据应与审计底稿或程序对应。审计项目组在完成底稿时获取的支持性证据应根据底稿索引号编制下一级按自然顺序排序的索引号（如D1-2-1、D1-2-2、……），并在底稿中说明引用的支持性证据、关联索引号。
A17: 3.工作底稿索引号的编码规则：实质性程序索引号按循环从“D”到“N”,循环内账户以顺序号排列，模板中底稿索引号按账户顺序+自然数顺序（即模板中索引号按二级自然顺序排列，如D1-1、D1-2、D1-3、……D1-N）。

Sheet 实质性程序表 K2A
A1: 致同会计师事务所
A2: 其他流动资产实质性程序
A3: =底稿目录!A2 | C3: =底稿目录!A4 | E3: =底稿目录!A5 | H3: 索引号： | I3: =底稿目录!F4
A4: =底稿目录!A3 | C4: =底稿目录!A6 | E4: =底稿目录!A7 | H4: 页 次：
A5: 一、本账户涉及的科目
A6: 其他流动资产
A7: 二、审计目标与认定的对应关系
A8: 审计目标 | G8: 财务报表的认定
A9: A. 资产负债表中记录的其他流动资产是存在的，且已记录于恰当的账户 | G9: 存在
A10: B. 所有应记录的其他流动资产均已记录，所有应当包括在财务报表中的相关披露均已包括 | G10: 完整性
A11: C. 记录的其他流动资产由被审计单位拥有或控制 | G11: 权利和义务
A12: D. 其他流动资产以恰当的金额包括在财务报表中，与之相关的计价或分摊调整已恰当记录，相关披露已得到恰当计量和描述 | G12: 准确性、计价和分摊
A13: E. 其他流动资产已被恰当地汇总或分解且表述清楚，相关披露在按照企业会计准则的编制基础下是相关的、可理解的 | G13: 列报
A14: 三、计划实施的实质性程序
A15: 序号 | B15: 审计程序 | C15: 程序分类 | D15: 财务报表的认定 | I15: 底稿索引号
D16: 存在 | E16: 完整性 | F16: 权利和 义务 | G16: 准确性、计价和分摊 | H16: 列报 | J16: 根据被审计单位实际情况和风险评估情况裁剪、修改或增加审计程序
A17: 1 | B17: 获取或编制明细表、执行下列程序，并编制审定表： （1）复核加计正确，并与总账数和明细账合计数核对是否相符，期初余额与上期审定期末余额是否相符； （2）识别重大的账户、识别账户中单项重大的明细项目； （3）了解明细项目的核算目的和用途； （4）检查其他流动资产减值准备计提（如需要）是否充分，会计处理是否正确。 | C17: 常规★ | D17: √ | E17: √ | G17: √ | I17: K2-1 /K2-2
A18: 2 | B18: 在使用手工编制、自定义信息报告、系统生成的非固定格式报告等由被审计单位生成的信息时，测试有关信息准确性和完整性，并考虑针对编制和维护由被审计单位生成的信息的相关控制实施控制测试，以评价该信息是否能够为实现审计目的提供基础。 | C18: 常规★ | E18: √ | G18: √ | I18: T1 / | J18: 可参见《审计手册》4.2.6，由被审计单位生成的信息可能是由系统生成的、或手工编制的、或二者兼而有之的方式生成的。例如，由被审计单位生成的信息可能包括： • 不涉及自定义的、由系统生成的报告（如，固定格式报告）； • 可能通过人工自定义的、由系统生成的报告，例如，（计算机）查询信息或特别定制的报告； • 手工编制的信息，例如，汇总信息的电子表格或用以支持分配、计算以及调节的电子表格； • 其他系统生成或手工编制的信息，例如，由被审计单位编制的客户发票； • 通过影印、拍摄、扫描或其他方式转换成电子形式的文件记录。
A19: 3 | B19: 获取上期期末的其他流动资产明细，复核加计正确，总账与明细账核对一致；识别重大的明细项目、查找异常项目并了解该明细项目的核算目的和用途；检查上期其他流动资产在本期摊销、使用或支付情况。（适用于首次承接） | C19: 备选 | D19: √ | E19: √ | G19: √ | J19: 由被审计单位生成的信息不包括： • 总分类账或明细分类账、试算平衡表、或经审计的财务报表； • 第三方（除了服务机构）的报表或报告，例如，原始银行对账单，或函证的回函； • 外部数据（例如，第三方发布的数据，如，定价来源）。
A20: 4 | B20: 关注会计政策、会计估计合理性、一贯性；关注其是否利用会计政策和会计估计及其变更操纵利润。 | C20: 常规★ | D20: √ | E20: √ | G20: √ | I20: K2-1 /K2-2
A21: 5 | B21: 检查关联交易： （1）了解关联交易的商业理由、交易事项的目的、价格和条件，考虑对关联交易形成的其他流动资产的合理性、合法性； （2）检查对关联交易形成的其他流动资产的真实性相关的支持性文件、检查会计处理是否正确； （3）考虑向关联方或其他注册会计师函证重大的关联交易和余额（包括担保和其他重要信息）； （4）必要时，向与交易相关的人员和机构（如银行、律师）函证或与其讨论有关信息； （5）考虑是否存在未识别的关联方，关联交易和余额披露是否正确。 | C21: 常规★ | D21: √ | E21: √ | F21: √ | G21: √ | H21: √
A22: 6 | B22: 合同取得成本： 结合相关销售合同检查取得合同成本是否是增量成本，会计处理是否正确；检查确定的分摊原则是否合理，是否与履约进度相匹配，测算分摊金额是否正确；考虑合同取得成本是否存在减值。 | C22: 备选 | D22: √ | G22: √ | I22: K2-4
A23: 7 | B23: 检查需摊销的其他流动资产摊销方法是否一致、确定摊销期限是否适当；重新测算摊销金额是否正确。 | C23: 常规★ | G23: √ | I23: K2-5
A24: 8 | B24: 检查与其他流动资产有关的的记账凭证和相应的支持性证据以确定交易的真实性，是否按规定进行相应的会计处理和披露。 | C24: 常规★ | D24: √ | F24: √ | G24: √ | I24: K2-6
A25: 9 | B25: 考虑是否存在超出被审计单位正常经营活动的重大、异常交易等，根据评估的舞弊风险等因素增加的审计程序。 | C25: IPO/上市/新三板/重组/舞弊应对
A26: 10 | B26: 检查其他流动资产是否已按企业会计准则或其他适用的规定在财务报表中做出恰当列报和披露。 | C26: 常规★ | H26: √ | I26: A1-1/A1-15 /A1-16

Sheet 审定表K2-1
A1: 致同会计师事务所
A2: 其他流动资产审定表
A3: =底稿目录!A2 | D3: =底稿目录!A4 | I3: =底稿目录!A5 | M3: 索引： | N3: =底稿目录!F5
A4: =底稿目录!A3 | D4: =底稿目录!A6 | I4: =底稿目录!A7 | M4: 页次：
A5: 项目 | B5: 期初数 | F5: 期末数 | J5: 本期未审数与上期 未审数的比较 | L5: 本期审定数与上期 审定数的比较 | N5: 原因分析
B6: 未审数 | C6: 账项调整 | D6: 重分类调整 | E6: 审定数 | F6: 未审数 | G6: 账项调整 | H6: 重分类调整 | I6: 审定数 | J6: 变动额 | K6: 变动率 | L6: 变动额 | M6: 变动率
A7: ='明细表K2-2'!A11 | B7: ='明细表K2-2'!B11 | C7: ='明细表K2-2'!F11 | D7: ='明细表K2-2'!G11 | E7: =B7+C7+D7 | F7: ='明细表K2-2'!E11 | G7: ='明细表K2-2'!F11+'明细表K2-2'!H11-'明细表K2-2'!I11 | H7: ='明细表K2-2'!G11+'明细表K2-2'!J11-'明细表K2-2'!K11 | I7: =F7+G7+H7 | J7: =F7-B7 | K7: =IF(AND(B7=0,J7=0),0,IF(AND(B7=0,J7>0),1,J7/B7)) | L7: =I7-E7 | M7: =IF(AND(E7=0,L7=0),0,IF(AND(E7=0,L7>0),1,L7/E7))
A8: ='明细表K2-2'!A12 | B8: ='明细表K2-2'!B12 | C8: ='明细表K2-2'!F12 | D8: ='明细表K2-2'!G12 | E8: =B8+C8+D8 | F8: ='明细表K2-2'!E12 | G8: ='明细表K2-2'!F12+'明细表K2-2'!H12-'明细表K2-2'!I12 | H8: ='明细表K2-2'!G12+'明细表K2-2'!J12-'明细表K2-2'!K12 | I8: =F8+G8+H8 | J8: =F8-B8 | K8: =IF(AND(B8=0,J8=0),0,IF(AND(B8=0,J8>0),1,J8/B8)) | L8: =I8-E8 | M8: =IF(AND(E8=0,L8=0),0,IF(AND(E8=0,L8>0),1,L8/E8))
A9: ='明细表K2-2'!A13 | B9: ='明细表K2-2'!B13 | C9: ='明细表K2-2'!F13 | D9: ='明细表K2-2'!G13 | E9: =B9+C9+D9 | F9: ='明细表K2-2'!E13 | G9: ='明细表K2-2'!F13+'明细表K2-2'!H13-'明细表K2-2'!I13 | H9: ='明细表K2-2'!G13+'明细表K2-2'!J13-'明细表K2-2'!K13 | I9: =F9+G9+H9 | J9: =F9-B9 | K9: =IF(AND(B9=0,J9=0),0,IF(AND(B9=0,J9>0),1,J9/B9)) | L9: =I9-E9 | M9: =IF(AND(E9=0,L9=0),0,IF(AND(E9=0,L9>0),1,L9/E9))
A10: ='明细表K2-2'!A14 | B10: ='明细表K2-2'!B14 | C10: ='明细表K2-2'!F14 | D10: ='明细表K2-2'!G14 | E10: =B10+C10+D10 | F10: ='明细表K2-2'!E14 | G10: ='明细表K2-2'!F14+'明细表K2-2'!H14-'明细表K2-2'!I14 | H10: ='明细表K2-2'!G14+'明细表K2-2'!J14-'明细表K2-2'!K14 | I10: =F10+G10+H10 | J10: =F10-B10 | K10: =IF(AND(B10=0,J10=0),0,IF(AND(B10=0,J10>0),1,J10/B10)) | L10: =I10-E10 | M10: =IF(AND(E10=0,L10=0),0,IF(AND(E10=0,L10>0),1,L10/E10))
A11: ='明细表K2-2'!A15 | B11: ='明细表K2-2'!B15 | C11: ='明细表K2-2'!F15 | D11: ='明细表K2-2'!G15 | E11: =B11+C11+D11 | F11: ='明细表K2-2'!E15 | G11: ='明细表K2-2'!F15+'明细表K2-2'!H15-'明细表K2-2'!I15 | H11: ='明细表K2-2'!G15+'明细表K2-2'!J15-'明细表K2-2'!K15 | I11: =F11+G11+H11 | J11: =F11-B11 | K11: =IF(AND(B11=0,J11=0),0,IF(AND(B11=0,J11>0),1,J11/B11)) | L11: =I11-E11 | M11: =IF(AND(E11=0,L11=0),0,IF(AND(E11=0,L11>0),1,L11/E11))
A12: ='明细表K2-2'!A16 | B12: ='明细表K2-2'!B16 | C12: ='明细表K2-2'!F16 | D12: ='明细表K2-2'!G16 | E12: =B12+C12+D12 | F12: ='明细表K2-2'!E16 | G12: ='明细表K2-2'!F16+'明细表K2-2'!H16-'明细表K2-2'!I16 | H12: ='明细表K2-2'!G16+'明细表K2-2'!J16-'明细表K2-2'!K16 | I12: =F12+G12+H12 | J12: =F12-B12 | K12: =IF(AND(B12=0,J12=0),0,IF(AND(B12=0,J12>0),1,J12/B12)) | L12: =I12-E12 | M12: =IF(AND(E12=0,L12=0),0,IF(AND(E12=0,L12>0),1,L12/E12))
A13: ='明细表K2-2'!A17 | B13: ='明细表K2-2'!B17 | C13: ='明细表K2-2'!F17 | D13: ='明细表K2-2'!G17 | E13: =B13+C13+D13 | F13: ='明细表K2-2'!E17 | G13: ='明细表K2-2'!F17+'明细表K2-2'!H17-'明细表K2-2'!I17 | H13: ='明细表K2-2'!G17+'明细表K2-2'!J17-'明细表K2-2'!K17 | I13: =F13+G13+H13 | J13: =F13-B13 | K13: =IF(AND(B13=0,J13=0),0,IF(AND(B13=0,J13>0),1,J13/B13)) | L13: =I13-E13 | M13: =IF(AND(E13=0,L13=0),0,IF(AND(E13=0,L13>0),1,L13/E13))
A15: 合计 | B15: =SUM(B7:B14) | C15: =SUM(C7:C14) | D15: =SUM(D7:D14) | E15: =SUM(E7:E14) | F15: =SUM(F7:F14) | G15: =SUM(G7:G14) | H15: =SUM(H7:H14) | I15: =SUM(I7:I14) | J15: =F15-B15 | K15: =IF(AND(B15=0,J15=0),0,IF(AND(B15=0,J15>0),1,J15/B15)) | L15: =I15-E15 | M15: =IF(AND(E15=0,L15=0),0,IF(AND(E15=0,L15>0),1,L15/E15))
A16: 1.审计说明
A17: （1）其他流动资产本期较上期增加（负数为减少）：
A18: 主要原因（比例超过30%的）：
A19: （2）情况说明。
A21: 2.审计结论

Sheet 附注披露信息（上市公司）
A1: 致同会计师事务所
A2: 附注披露信息(上市公司)
A3: =底稿目录!A2 | B3: =底稿目录!A4 | C3: =底稿目录!A5 | D3: 索引号： | E3: =底稿目录!F7
A4: =底稿目录!A3 | B4: =底稿目录!A6 | C4: =底稿目录!A7 | D4: 页次：
A5: 其他流动资产（注：根据实际情况列示；不存在的项目请删除）
A6: 项 目 | B6: 期末数 | C6: 期初数
A7: ='明细表K2-2'!A11 | B7: ='明细表K2-2'!O11 | C7: ='明细表K2-2'!L11
A8: ='明细表K2-2'!A12 | B8: ='明细表K2-2'!O12 | C8: ='明细表K2-2'!L12
A9: ='明细表K2-2'!A13 | B9: ='明细表K2-2'!O13 | C9: ='明细表K2-2'!L13
A10: ='明细表K2-2'!A14 | B10: ='明细表K2-2'!O14 | C10: ='明细表K2-2'!L14
A11: ='明细表K2-2'!A17 | B11: ='明细表K2-2'!O17 | C11: ='明细表K2-2'!L17
A12: 合 计 | B12: =SUM(B7:B11) | C12: =SUM(C7:C11)
A13: （金额较大的其他流动资产，应说明其内容、性质）

Sheet 附注披露信息（国企）
A1: 致同会计师事务所
A2: 附注披露信息（国企）
A3: =底稿目录!A2 | B3: =底稿目录!A4 | C3: =底稿目录!A5 | D3: 索引号： | E3: =底稿目录!F6
A4: =底稿目录!A3 | B4: =底稿目录!A6 | C4: =底稿目录!A7 | D4: 页次：
A5: 其他流动资产
A6: （根据性质选择披露方式）
A7: 项 目 | B7: 期末账面价值 | C7: 年初账面价值
A8: ='明细表K2-2'!A11 | B8: ='明细表K2-2'!O11 | C8: ='明细表K2-2'!L11
A9: ='明细表K2-2'!A12 | B9: ='明细表K2-2'!O12 | C9: ='明细表K2-2'!L12
A10: ='明细表K2-2'!A13 | B10: ='明细表K2-2'!O13 | C10: ='明细表K2-2'!L13
A11: ='明细表K2-2'!A14 | B11: ='明细表K2-2'!O14 | C11: ='明细表K2-2'!L14
A12: ='明细表K2-2'!A17 | B12: ='明细表K2-2'!O17 | C12: ='明细表K2-2'!L17
A13: 合 计 | B13: =SUM(B8:B12) | C13: =SUM(C8:C12)

Sheet 明细表K2-2
A1: 致同会计师事务所
A2: 其他流动资产明细表
A3: =底稿目录!A2 | D3: =底稿目录!A4 | J3: =底稿目录!A5 | O3: 索引号： | P3: =底稿目录!F8
A4: =底稿目录!A3 | D4: =底稿目录!A6 | J4: =底稿目录!A7 | O4: 页次：
A5: 一、审计目标:
A6: 1.资产负债表中记录的其他流动资产是存在的，且已记录于恰当的账户； | G6: 2.所有应记录的其他流动资产均已记录，所有应当包括在财务报表中的相关披露均已包括；
A7: 3.其他流动资产以恰当的金额包括在财务报表中，与之相关的计价或分摊调整已恰当记录，相关披露已得到恰当计量和描述。
A8: 二、审计过程：
A9: 项目 | B9: 未审数 | F9: 期初调整 | H9: 账项调整 | J9: 重分类调整 | L9: 审定数 | P9: 备注
B10: 期初数 | C10: 本期增加 | D10: 本期减少 | E10: 期末数 | F10: 账项调整 | G10: 重分类调整 | H10: 本期增加 | I10: 本期减少 | J10: 本期增加 | K10: 本期减少 | L10: 期初数 | M10: 本期增加 | N10: 本期减少 | O10: 期末数
A11: 待摊费用 | E11: =B11+C11-D11 | L11: =B11+F11+G11 | M11: =C11+H11+J11 | N11: =D11+I11+K11 | O11: =L11+M11-N11
A12: 待抵扣进项税 | E12: =B12+C12-D12 | L12: =B12+F12+G12 | M12: =C12+H12+J12 | N12: =D12+I12+K12 | O12: =L12+M12-N12
A13: 房租物业费 | E13: =B13+C13-D13 | L13: =B13+F13+G13 | M13: =C13+H13+J13 | N13: =D13+I13+K13 | O13: =L13+M13-N13
A14: 预缴企业所得税 | E14: =B14+C14-D14 | L14: =B14+F14+G14 | M14: =C14+H14+J14 | N14: =D14+I14+K14 | O14: =L14+M14-N14
A15: 委托贷款 | E15: =B15+C15-D15 | L15: =B15+F15+G15 | M15: =C15+H15+J15 | N15: =D15+I15+K15 | O15: =L15+M15-N15
A16: 预缴其他税费 | E16: =B16+C16-D16 | L16: =B16+F16+G16 | M16: =C16+H16+J16 | N16: =D16+I16+K16 | O16: =L16+M16-N16
A17: 应收退货成本 | E17: =B17+C17-D17 | L17: =B17+F17+G17 | M17: =C17+H17+J17 | N17: =D17+I17+K17 | O17: =L17+M17-N17
A18: 合同取得成本 | E18: =B18+C18-D18 | L18: =B18+F18+G18 | M18: =C18+H18+J18 | N18: =D18+I18+K18 | O18: =L18+M18-N18
E19: =B19+C19-D19 | L19: =B19+F19+G19 | M19: =C19+H19+J19 | N19: =D19+I19+K19 | O19: =L19+M19-N19
A20: 合计 | B20: =SUM(B11:B19) | C20: =SUM(C11:C19) | D20: =SUM(D11:D19) | E20: =SUM(E11:E19) | F20: =SUM(F11:F19) | G20: =SUM(G11:G19) | H20: =SUM(H11:H19) | I20: =SUM(I11:I19) | ... O20: =SUM(O11:O19)
A21: 三、审计说明：
A25: 四、审计结论：
A29: 编制说明：
A30: 财会〔2018〕15号指出：下列情况在其他流动资产列示：企业购入的一年内到期的债权投资（包括以摊余成本计量及以公允价值计量且其变动计入其他综合收益的债权投资）；合同取得成本，初始确认时摊销期限不超过一年或一个正常营业周期的项目；附有销售退回条款的销售，确认为资产的应收退货成本，在一年或一个正常营业周期内出售的项目；

Sheet 调整分录汇总K2-3
A1: 致同会计师事务所
A2: 其他应收款调整分录汇总表
A3: =底稿目录!A2 | C3: =底稿目录!A4 | F3: =底稿目录!A5 | I3: 索引号： | J3: =底稿目录!F9
A4: =底稿目录!A3 | C4: =底稿目录!A6 | F4: =底稿目录!A7 | I4: 页次：
A5: 调整事项说明 | B5: 类别（报表调整/账项调整/其他） | C5: 报表项目 | D5: 科目名称 | E5: 附注项目 | F5: …… | G5: 借方调整金额 | H5: 贷方调整金额 | I5: 索引 | J5: 备注
A22: 【注：本底稿适用于调整分录较多、较复杂的项目，且仅列示与本报表项目相关的审计调整。项目组可根据项目实际情况选择是否使用该底稿。】

Sheet 合同取得成本明细表K2-4
A1: 致同会计师事务所
A2: 合同取得成本明细表
A3: =底稿目录!A2 | I3: =底稿目录!A4 | O3: =底稿目录!A5 | V3: 索引号： | W3: =底稿目录!F10
A4: =底稿目录!A3 | I4: =底稿目录!A6 | O4: =底稿目录!A7 | V4: 页次：
A5: 收入合同名称 | B5: 类别 | C5: 初始确认金额 | D5: 是否为取得合同发生的增量成本 | E5: 是否预期能够收回 | F5: 初始摊销期限 | H5: 未审数 | L5: 期初调整 | N5: 账项调整 | P5: 重分类调整 | R5: 审定数 | V5: 截至期末履约义务的履约进度 | W5: 备注
F6: 未超过一年或一个正常营业周期 | G6: 超过一年或一个正常营业周期 | H6: 期初数 | I6: 本期增加 | J6: 本期减少 | K6: 期末数 | L6: 账项调整 | M6: 重分类调整 | N6: 本期增加 | O6: 本期减少 | P6: 本期增加 | Q6: 本期减少 | R6: 期初数 | S6: 本期增加 | T6: 本期减少 | U6: 期末数
A7: 账面原值合计 | H7: =SUM(H8:H10) | I7: =I8+I9+I10 | J7: =J8+J9+J10 | K7: =K8+K9+K10 | L7: =SUM(L8:L10) | M7: =M8+M9+M10 | N7: =N8+N9+N10 | O7: =O8+O9+O10 | P7: =P8+P9+P10 | Q7: =Q8+Q9+Q10 | R7: =SUM(R8:R10) | S7: =S8+S9+S10 | T7: =T8+T9+T10 | U7: =U8+U9+U10
A8: 合同1 | K8: =H8+I8-J8 | R8: =H8+L8+M8 | S8: =I8+N8+P8 | T8: =J8+O8+Q8 | U8: =R8+S8-T8
A9: 合同2 | K9: =H9+I9-J9 | R9: =H9+L9+M9 | S9: =I9+N9+P9 | T9: =J9+O9+Q9 | U9: =R9+S9-T9
A10: 合同3 | K10: =H10+I10-J10 | R10: =H10+L10+M10 | S10: =I10+N10+P10 | T10: =J10+O10+Q10 | U10: =R10+S10-T10
A11: 减值准备合计 | H11: =SUM(H12:H14) | I11: =I12+I13+I14 | J11: =J12+J13+J14 | K11: =K12+K13+K14 | L11: =SUM(L12:L14) | M11: =M12+M13+M14 | N11: =N12+N13+N14 | O11: =O12+O13+O14 | P11: =P12+P13+P14 | Q11: =Q12+Q13+Q14 | R11: =SUM(R12:R14) | S11: =S12+S13+S14 | T11: =T12+T13+T14 | U11: =U12+U13+U14
A12: =A8 | B12: =B8 | K12: =H12+I12-J12 | R12: =H12+L12+M12 | S12: =I12+N12+P12 | T12: =J12+O12+Q12 | U12: =R12+S12-T12
A13: =A9 | B13: =B9 | K13: =H13+I13-J13 | R13: =H13+L13+M13 | S13: =I13+N13+P13 | T13: =J13+O13+Q13 | U13: =R13+S13-T13
A14: =A10 | B14: =B10 | K14: =H14+I14-J14 | R14: =H14+L14+M14 | S14: =I14+N14+P14 | T14: =J14+O14+Q14 | U14: =R14+S14-T14
A15: 账面价值合计 | H15: =SUM(H16:H18) | I15: =I16+I17+I18 | J15: =J16+J17+J18 | K15: =K16+K17+K18 | L15: =L16+L17+L18 | M15: =M16+M17+M18 | N15: =N16+N17+N18 | O15: =O16+O17+O18 | P15: =P16+P17+P18 | Q15: =Q16+Q17+Q18 | R15: =SUM(R16:R18) | S15: =S16+S17+S18 | T15: =T16+T17+T18 | U15: =U16+U17+U18
A16: =A8 | B16: =B8 | H16: =H8-H12 | I16: =I8-I12 | J16: =J8-J12 | K16: =K8-K12 | L16: =L8-L12 | M16: =M8-M12 | N16: =N8-N12 | O16: =O8-O12 | ... Q16: =Q8-Q12 | R16: =H16+L16+M16 | S16: =I16+N16+P16 | T16: =J16+O16+Q16 | U16: =R16+S16-T16
A17: =A9 | B17: =B9 | H17: =H9-H13 | I17: =I9-I13 | J17: =J9-J13 | K17: =K9-K13 | L17: =L9-L13 | M17: =M9-M13 | N17: =N9-N13 | O17: =O9-O13 | ... Q17: =Q9-Q13 | R17: =H17+L17+M17 | S17: =I17+N17+P17 | T17: =J17+O17+Q17 | U17: =R17+S17-T17
A18: =A10 | B18: =B10 | H18: =H10-H14 | I18: =I10-I14 | J18: =J10-J14 | K18: =K10-K14 | L18: =L10-L14 | M18: =M10-M14 | N18: =N10-N14 | O18: =O10-O14 | ... Q18: =Q10-Q14 | R18: =H18+L18+M18 | S18: =I18+N18+P18 | T18: =J18+O18+Q18 | U18: =R18+S18-T18
A19: 三、审计说明：
A22: 四、审计结论：
A26: 提示：关注合同取得成本是否存在减值迹象，并结合存货跌价测试底稿或合同履约成本底稿进行减值测试。
A27: 编制说明：
A28: 1、本科目核算企业预期能够收回的为取得合同发生的增量成本。增量成本是指企业不取的合同就不会发生的成本，如销售佣金。在实物操作中该资产摊销期限不超过1年的，可在发生时计入当期损益。
A29: 本科目初始确认时摊销期限不超过一年或一个正常营业周期的，在资产负债表中计入“其他流动资产项目”；初始确认摊销期限在一年或一个正常营业周期以上的，在资产负债表中既然“其他非流动资产”
A30: 2、备注栏可填写项目内容及异常情况说明。
A31: 3、按照《企业会计准则第 14 号——收入》（2017 年修订）的相关规定确认为资产的合同取得成本，应当根据“合同取得成本”科目的明细科目初始确认时摊销期限是否超过一年或一个正常营业周期，在“其他流动资产”或“其他非流动资产”项目中填列，已计提减值准备的，还应减去“合同取得成本减值准备”科目中相关的期末余额后的金额填列。

Sheet 摊销测算表K2-5
A1: 致同会计师事务所
A2: 摊销测算表
A3: =底稿目录!A2 | E3: =底稿目录!A4 | L3: =底稿目录!A5 | P3: 索引号： | Q3: =底稿目录!F11
A4: =底稿目录!A3 | E4: =底稿目录!A6 | L4: =底稿目录!A7 | P4: 页 次：
A5: 一、审计目标:
A6: 其他流动资产以恰当的金额包括在财务报表中，与之相关的计价或分摊调整已恰当记录，相关披露已得到恰当计量和描述。
A7: 二、审计过程：
A8: 摊销期初： | B8: 45292 | C8: 摊销期末： | D8: 45657
A9: 类别名称 | B9: 明细项目 | C9: 原值 | D9: 累计摊销 | E9: 开始使用日期 | F9: 使用年限 | G9: 账面月摊销额 | H9: 使用月限 | I9: 测算到期日 | J9: 已摊销月份 | K9: 剩余摊销月份 | L9: 本期摊销月份 | M9: 测算月摊销额 | N9: 当期摊销 | O9: 月摊销额差异 | P9: 累计摊销费用 | Q9: 累计摊销额差异
A10: 类别A | B10: 取暖费 | H10: =IF(F10=0,0,IF(RIGHT(F10,1)<>"年",F10*12,IF(LEN(F10)=3,VALUE(LEFT(F10,2))*12,IF(LEN(F10)=2,VALUE(LEFT(F10,1))*12,"??")))) | I10: =IF(E10=0,0,DATE(YEAR(E10),MONTH(E10)+H10,DAY(E10)-1)) | J10: =IF(E10=0,0,IF(I10>$D$8,VALUE(DATEDIF(E10,MIN($D$8,I10),"m")+1),VALUE(DATEDIF(E10,MIN($D$8,I10),"m")+1))) | K10: =(H10-J10) | L10: =IF(E10=0,0,IF(AND(E10<=$B$8,I10>$D$8),VALUE(DATEDIF($B$8,$D$8,"m")+1),IF(AND(E10<=$B$8,I10<=$D$8),VALUE(DATEDIF($B$8,I10,"m")),IF(AND(E10>$B$8,I10>$D$8),VALUE(DATEDIF(E10,$D$8,"m")+1),IF(AND(E10>=$B$8,I10<=$D$8),VALUE(DATEDIF(E10,I10,"m")+1),))))) | M10: =IF(H10=0,0,ROUND(((1-0)/H10)*C10,4)) | N10: =ROUND(M10*L10,2) | O10: =ROUND(G10-M10,2) | P10: =ROUND(M10*J10,2) | Q10: =ROUND(D10-P10,2)
A11: 合同取得成本 | B11: 佣金-合同1 | H11: =IF(F11=0,0,IF(RIGHT(F11,1)<>"年",F11*12,IF(LEN(F11)=3,VALUE(LEFT(F11,2))*12,IF(LEN(F11)=2,VALUE(LEFT(F11,1))*12,"??")))) | I11: =IF(E11=0,0,DATE(YEAR(E11),MONTH(E11)+H11,DAY(E11)-1)) | J11: =IF(E11=0,0,IF(I11>$D$8,VALUE(DATEDIF(E11,MIN($D$8,I11),"m")+1),VALUE(DATEDIF(E11,MIN($D$8,I11),"m")+1))) | K11: =(H11-J11) | L11: =IF(E11=0,0,IF(AND(E11<=$B$8,I11>$D$8),VALUE(DATEDIF($B$8,$D$8,"m")+1),IF(AND(E11<=$B$8,I11<=$D$8),VALUE(DATEDIF($B$8,I11,"m")),IF(AND(E11>$B$8,I11>$D$8),VALUE(DATEDIF(E11,$D$8,"m")+1),IF(AND(E11>=$B$8,I11<=$D$8),VALUE(DATEDIF(E11,I11,"m")+1),))))) | M11: =IF(H11=0,0,ROUND(((1-0)/H11)*C11,4)) | N11: =ROUND(M11*L11,2) | O11: =ROUND(G11-M11,2) | P11: =ROUND(M11*J11,2) | Q11: =ROUND(D11-P11,2)
H12: =IF(F12=0,0,IF(RIGHT(F12,1)<>"年",F12*12,IF(LEN(F12)=3,VALUE(LEFT(F12,2))*12,IF(LEN(F12)=2,VALUE(LEFT(F12,1))*12,"??")))) | I12: =IF(E12=0,0,DATE(YEAR(E12),MONTH(E12)+H12,DAY(E12)-1)) | J12: =IF(E12=0,0,IF(I12>$D$8,VALUE(DATEDIF(E12,MIN($D$8,I12),"m")+1),VALUE(DATEDIF(E12,MIN($D$8,I12),"m")+1))) | K12: =(H12-J12) | L12: =IF(E12=0,0,IF(AND(E12<=$B$8,I12>$D$8),VALUE(DATEDIF($B$8,$D$8,"m")+1),IF(AND(E12<=$B$8,I12<=$D$8),VALUE(DATEDIF($B$8,I12,"m")),IF(AND(E12>$B$8,I12>$D$8),VALUE(DATEDIF(E12,$D$8,"m")+1),IF(AND(E12>=$B$8,I12<=$D$8),VALUE(DATEDIF(E12,I12,"m")+1),))))) | M12: =IF(H12=0,0,ROUND(((1-0)/H12)*C12,4)) | N12: =ROUND(M12*L12,2) | O12: =ROUND(G12-M12,2) | P12: =ROUND(M12*J12,2) | Q12: =ROUND(D12-P12,2)
H13: =IF(F13=0,0,IF(RIGHT(F13,1)<>"年",F13*12,IF(LEN(F13)=3,VALUE(LEFT(F13,2))*12,IF(LEN(F13)=2,VALUE(LEFT(F13,1))*12,"??")))) | I13: =IF(E13=0,0,DATE(YEAR(E13),MONTH(E13)+H13,DAY(E13)-1)) | J13: =IF(E13=0,0,IF(I13>$D$8,VALUE(DATEDIF(E13,MIN($D$8,I13),"m")+1),VALUE(DATEDIF(E13,MIN($D$8,I13),"m")+1))) | K13: =(H13-J13) | L13: =IF(E13=0,0,IF(AND(E13<=$B$8,I13>$D$8),VALUE(DATEDIF($B$8,$D$8,"m")+1),IF(AND(E13<=$B$8,I13<=$D$8),VALUE(DATEDIF($B$8,I13,"m")),IF(AND(E13>$B$8,I13>$D$8),VALUE(DATEDIF(E13,$D$8,"m")+1),IF(AND(E13>=$B$8,I13<=$D$8),VALUE(DATEDIF(E13,I13,"m")+1),))))) | M13: =IF(H13=0,0,ROUND(((1-0)/H13)*C13,4)) | N13: =ROUND(M13*L13,2) | O13: =ROUND(G13-M13,2) | P13: =ROUND(M13*J13,2) | Q13: =ROUND(D13-P13,2)
H14: =IF(F14=0,0,IF(RIGHT(F14,1)<>"年",F14*12,IF(LEN(F14)=3,VALUE(LEFT(F14,2))*12,IF(LEN(F14)=2,VALUE(LEFT(F14,1))*12,"??")))) | I14: =IF(E14=0,0,DATE(YEAR(E14),MONTH(E14)+H14,DAY(E14)-1)) | J14: =IF(E14=0,0,IF(I14>$D$8,VALUE(DATEDIF(E14,MIN($D$8,I14),"m")+1),VALUE(DATEDIF(E14,MIN($D$8,I14),"m")+1))) | K14: =(H14-J14) | L14: =IF(E14=0,0,IF(AND(E14<=$B$8,I14>$D$8),VALUE(DATEDIF($B$8,$D$8,"m")+1),IF(AND(E14<=$B$8,I14<=$D$8),VALUE(DATEDIF($B$8,I14,"m")),IF(AND(E14>$B$8,I14>$D$8),VALUE(DATEDIF(E14,$D$8,"m")+1),IF(AND(E14>=$B$8,I14<=$D$8),VALUE(DATEDIF(E14,I14,"m")+1),))))) | M14: =IF(H14=0,0,ROUND(((1-0)/H14)*C14,4)) | N14: =ROUND(M14*L14,2) | O14: =ROUND(G14-M14,2) | P14: =ROUND(M14*J14,2) | Q14: =ROUND(D14-P14,2)
H15: =IF(F15=0,0,IF(RIGHT(F15,1)<>"年",F15*12,IF(LEN(F15)=3,VALUE(LEFT(F15,2))*12,IF(LEN(F15)=2,VALUE(LEFT(F15,1))*12,"??")))) | I15: =IF(E15=0,0,DATE(YEAR(E15),MONTH(E15)+H15,DAY(E15)-1)) | J15: =IF(E15=0,0,IF(I15>$D$8,VALUE(DATEDIF(E15,MIN($D$8,I15),"m")+1),VALUE(DATEDIF(E15,MIN($D$8,I15),"m")+1))) | K15: =(H15-J15) | L15: =IF(E15=0,0,IF(AND(E15<=$B$8,I15>$D$8),VALUE(DATEDIF($B$8,$D$8,"m")+1),IF(AND(E15<=$B$8,I15<=$D$8),VALUE(DATEDIF($B$8,I15,"m")),IF(AND(E15>$B$8,I15>$D$8),VALUE(DATEDIF(E15,$D$8,"m")+1),IF(AND(E15>=$B$8,I15<=$D$8),VALUE(DATEDIF(E15,I15,"m")+1),))))) | M15: =IF(H15=0,0,ROUND(((1-0)/H15)*C15,4)) | N15: =ROUND(M15*L15,2) | O15: =ROUND(G15-M15,2) | P15: =ROUND(M15*J15,2) | Q15: =ROUND(D15-P15,2)
H16: =IF(F16=0,0,IF(RIGHT(F16,1)<>"年",F16*12,IF(LEN(F16)=3,VALUE(LEFT(F16,2))*12,IF(LEN(F16)=2,VALUE(LEFT(F16,1))*12,"??")))) | I16: =IF(E16=0,0,DATE(YEAR(E16),MONTH(E16)+H16,DAY(E16)-1)) | J16: =IF(E16=0,0,IF(I16>$D$8,VALUE(DATEDIF(E16,MIN($D$8,I16),"m")+1),VALUE(DATEDIF(E16,MIN($D$8,I16),"m")+1))) | K16: =(H16-J16) | L16: =IF(E16=0,0,IF(AND(E16<=$B$8,I16>$D$8),VALUE(DATEDIF($B$8,$D$8,"m")+1),IF(AND(E16<=$B$8,I16<=$D$8),VALUE(DATEDIF($B$8,I16,"m")),IF(AND(E16>$B$8,I16>$D$8),VALUE(DATEDIF(E16,$D$8,"m")+1),IF(AND(E16>=$B$8,I16<=$D$8),VALUE(DATEDIF(E16,I16,"m")+1),))))) | M16: =IF(H16=0,0,ROUND(((1-0)/H16)*C16,4)) | N16: =ROUND(M16*L16,2) | O16: =ROUND(G16-M16,2) | P16: =ROUND(M16*J16,2) | Q16: =ROUND(D16-P16,2)
H17: =IF(F17=0,0,IF(RIGHT(F17,1)<>"年",F17*12,IF(LEN(F17)=3,VALUE(LEFT(F17,2))*12,IF(LEN(F17)=2,VALUE(LEFT(F17,1))*12,"??")))) | I17: =IF(E17=0,0,DATE(YEAR(E17),MONTH(E17)+H17,DAY(E17)-1)) | J17: =IF(E17=0,0,IF(I17>$D$8,VALUE(DATEDIF(E17,MIN($D$8,I17),"m")+1),VALUE(DATEDIF(E17,MIN($D$8,I17),"m")+1))) | K17: =(H17-J17) | L17: =IF(E17=0,0,IF(AND(E17<=$B$8,I17>$D$8),VALUE(DATEDIF($B$8,$D$8,"m")+1),IF(AND(E17<=$B$8,I17<=$D$8),VALUE(DATEDIF($B$8,I17,"m")),IF(AND(E17>$B$8,I17>$D$8),VALUE(DATEDIF(E17,$D$8,"m")+1),IF(AND(E17>=$B$8,I17<=$D$8),VALUE(DATEDIF(E17,I17,"m")+1),))))) | M17: =IF(H17=0,0,ROUND(((1-0)/H17)*C17,4)) | N17: =ROUND(M17*L17,2) | O17: =ROUND(G17-M17,2) | P17: =ROUND(M17*J17,2) | Q17: =ROUND(D17-P17,2)
H18: =IF(F18=0,0,IF(RIGHT(F18,1)<>"年",F18*12,IF(LEN(F18)=3,VALUE(LEFT(F18,2))*12,IF(LEN(F18)=2,VALUE(LEFT(F18,1))*12,"??")))) | I18: =IF(E18=0,0,DATE(YEAR(E18),MONTH(E18)+H18,DAY(E18)-1)) | J18: =IF(E18=0,0,IF(I18>$D$8,VALUE(DATEDIF(E18,MIN($D$8,I18),"m")+1),VALUE(DATEDIF(E18,MIN($D$8,I18),"m")+1))) | K18: =(H18-J18) | L18: =IF(E18=0,0,IF(AND(E18<=$B$8,I18>$D$8),VALUE(DATEDIF($B$8,$D$8,"m")+1),IF(AND(E18<=$B$8,I18<=$D$8),VALUE(DATEDIF($B$8,I18,"m")),IF(AND(E18>$B$8,I18>$D$8),VALUE(DATEDIF(E18,$D$8,"m")+1),IF(AND(E18>=$B$8,I18<=$D$8),VALUE(DATEDIF(E18,I18,"m")+1),))))) | M18: =IF(H18=0,0,ROUND(((1-0)/H18)*C18,4)) | N18: =ROUND(M18*L18,2) | O18: =ROUND(G18-M18,2) | P18: =ROUND(M18*J18,2) | Q18: =ROUND(D18-P18,2)
H19: =IF(F19=0,0,IF(RIGHT(F19,1)<>"年",F19*12,IF(LEN(F19)=3,VALUE(LEFT(F19,2))*12,IF(LEN(F19)=2,VALUE(LEFT(F19,1))*12,"??")))) | I19: =IF(E19=0,0,DATE(YEAR(E19),MONTH(E19)+H19,DAY(E19)-1)) | J19: =IF(E19=0,0,IF(I19>$D$8,VALUE(DATEDIF(E19,MIN($D$8,I19),"m")+1),VALUE(DATEDIF(E19,MIN($D$8,I19),"m")+1))) | K19: =(H19-J19) | L19: =IF(E19=0,0,IF(AND(E19<=$B$8,I19>$D$8),VALUE(DATEDIF($B$8,$D$8,"m")+1),IF(AND(E19<=$B$8,I19<=$D$8),VALUE(DATEDIF($B$8,I19,"m")),IF(AND(E19>$B$8,I19>$D$8),VALUE(DATEDIF(E19,$D$8,"m")+1),IF(AND(E19>=$B$8,I19<=$D$8),VALUE(DATEDIF(E19,I19,"m")+1),))))) | M19: =IF(H19=0,0,ROUND(((1-0)/H19)*C19,4)) | N19: =ROUND(M19*L19,2) | O19: =ROUND(G19-M19,2) | P19: =ROUND(M19*J19,2) | Q19: =ROUND(D19-P19,2)
H20: =IF(F20=0,0,IF(RIGHT(F20,1)<>"年",F20*12,IF(LEN(F20)=3,VALUE(LEFT(F20,2))*12,IF(LEN(F20)=2,VALUE(LEFT(F20,1))*12,"??")))) | I20: =IF(E20=0,0,DATE(YEAR(E20),MONTH(E20)+H20,DAY(E20)-1)) | J20: =IF(E20=0,0,IF(I20>$D$8,VALUE(DATEDIF(E20,MIN($D$8,I20),"m")+1),VALUE(DATEDIF(E20,MIN($D$8,I20),"m")+1))) | K20: =(H20-J20) | L20: =IF(E20=0,0,IF(AND(E20<=$B$8,I20>$D$8),VALUE(DATEDIF($B$8,$D$8,"m")+1),IF(AND(E20<=$B$8,I20<=$D$8),VALUE(DATEDIF($B$8,I20,"m")),IF(AND(E20>$B$8,I20>$D$8),VALUE(DATEDIF(E20,$D$8,"m")+1),IF(AND(E20>=$B$8,I20<=$D$8),VALUE(DATEDIF(E20,I20,"m")+1),))))) | M20: =IF(H20=0,0,ROUND(((1-0)/H20)*C20,4)) | N20: =ROUND(M20*L20,2) | O20: =ROUND(G20-M20,2) | P20: =ROUND(M20*J20,2) | Q20: =ROUND(D20-P20,2)
H21: =IF(F21=0,0,IF(RIGHT(F21,1)<>"年",F21*12,IF(LEN(F21)=3,VALUE(LEFT(F21,2))*12,IF(LEN(F21)=2,VALUE(LEFT(F21,1))*12,"??")))) | I21: =IF(E21=0,0,DATE(YEAR(E21),MONTH(E21)+H21,DAY(E21)-1)) | J21: =IF(E21=0,0,IF(I21>$D$8,VALUE(DATEDIF(E21,MIN($D$8,I21),"m")+1),VALUE(DATEDIF(E21,MIN($D$8,I21),"m")+1))) | K21: =(H21-J21) | L21: =IF(E21=0,0,IF(AND(E21<=$B$8,I21>$D$8),VALUE(DATEDIF($B$8,$D$8,"m")+1),IF(AND(E21<=$B$8,I21<=$D$8),VALUE(DATEDIF($B$8,I21,"m")),IF(AND(E21>$B$8,I21>$D$8),VALUE(DATEDIF(E21,$D$8,"m")+1),IF(AND(E21>=$B$8,I21<=$D$8),VALUE(DATEDIF(E21,I21,"m")+1),))))) | M21: =IF(H21=0,0,ROUND(((1-0)/H21)*C21,4)) | N21: =ROUND(M21*L21,2) | O21: =ROUND(G21-M21,2) | P21: =ROUND(M21*J21,2) | Q21: =ROUND(D21-P21,2)
A22: 合计 | C22: =SUM(C10:C21) | D22: =SUM(D10:D21) | G22: =SUM(G10:G21) | M22: =SUM(M10:M21) | N22: =SUM(N10:N21) | O22: =SUM(O10:O21) | P22: =SUM(P10:P21) | Q22: =SUM(Q10:Q21)
A23: 其中：
A24: 类别A | C24: =SUMPRODUCT(($A$10:$A$21=$A24)*(C$10:C$21)) | D24: {=SUMPRODUCT(($A$10:$A$21=$A24)*(D$10:D$21))} | M24: =SUMPRODUCT(($A$10:$A$21=$A24)*(M$10:M$21)) | N24: =SUMPRODUCT(($A$10:$A$21=$A24)*(N$10:N$21)) | O24: {=SUMPRODUCT(($A$10:$A$21=$A24)*(O$10:O$21))} | P24: {=SUMPRODUCT(($A$10:$A$21=$A24)*(P$10:P$21))} | Q24: {=SUMPRODUCT(($A$10:$A$21=$A24)*(Q$10:Q$21))}
A25: 类别B | C25: {=SUMPRODUCT(($A$10:$A$21=$A25)*(C$10:C$21))} | D25: {=SUMPRODUCT(($A$10:$A$21=$A25)*(D$10:D$21))} | M25: {=SUMPRODUCT(($A$10:$A$21=$A25)*(M$10:M$21))} | N25: {=SUMPRODUCT(($A$10:$A$21=$A25)*(N$10:N$21))} | O25: {=SUMPRODUCT(($A$10:$A$21=$A25)*(O$10:O$21))} | P25: {=SUMPRODUCT(($A$10:$A$21=$A25)*(P$10:P$21))} | Q25: {=SUMPRODUCT(($A$10:$A$21=$A25)*(Q$10:Q$21))}
A26: 类别C | C26: {=SUMPRODUCT(($A$10:$A$21=$A26)*(C$10:C$21))} | D26: {=SUMPRODUCT(($A$10:$A$21=$A26)*(D$10:D$21))} | M26: {=SUMPRODUCT(($A$10:$A$21=$A26)*(M$10:M$21))} | N26: {=SUMPRODUCT(($A$10:$A$21=$A26)*(N$10:N$21))} | O26: {=SUMPRODUCT(($A$10:$A$21=$A26)*(O$10:O$21))} | P26: {=SUMPRODUCT(($A$10:$A$21=$A26)*(P$10:P$21))} | Q26: {=SUMPRODUCT(($A$10:$A$21=$A26)*(Q$10:Q$21))}
A27: …… | C27: {=SUMPRODUCT(($A$10:$A$21=$A27)*(C$10:C$21))} | D27: {=SUMPRODUCT(($A$10:$A$21=$A27)*(D$10:D$21))} | M27: {=SUMPRODUCT(($A$10:$A$21=$A27)*(M$10:M$21))} | N27: {=SUMPRODUCT(($A$10:$A$21=$A27)*(N$10:N$21))} | O27: {=SUMPRODUCT(($A$10:$A$21=$A27)*(O$10:O$21))} | P27: {=SUMPRODUCT(($A$10:$A$21=$A27)*(P$10:P$21))} | Q27: {=SUMPRODUCT(($A$10:$A$21=$A27)*(Q$10:Q$21))}
A28: 三、审计说明：
A30: 四、审计结论
A63: 《企业所得税法实施条例》
A64: 第六十七条 无形资产按照直线法计算的摊销费用，准予扣除。
A65: 无形资产的摊销年限不得低于10年。
A66: 作为投资或者受让的无形资产，有关法律规定或者合同约定了使用年限的，可以按照规定或者约定的使用年限分期摊销。

Sheet 其他流动资产检查表表K2-6
A1: 致同会计师事务所
A2: 其他流动资产检查表检查表
A3: =底稿目录!A2 | F3: =底稿目录!A4 | I3: =底稿目录!A5 | P3: 索引号： | Q3: =底稿目录!F12
A4: =底稿目录!A3 | F4: =底稿目录!A6 | I4: =底稿目录!A7 | P4: 页 次：
A5: 一、测试目标：
A6: 1.资产负债表中记录的其他流动资产是存在的，且已经记录在恰当的账户中； | H6: 2. 记录的其他流动资产由被审计单位拥有或控制
A7: 3.其他流动资产以恰当的金额包括在财务报表中，与之相关的计价或分摊调整已恰当记录，相关披露已得到恰当计量和描述。
A8: 二、测试：
A9: 测试内容说明：1.原始凭证是否齐全； 2.记账凭证与原始凭证是否相符；3.账务处理是否正确；4.是否记录于恰当的会计期间；5.……
A10: 明细项目 | B10: 记账凭证 | I10: 支持性文件 | J10: 核对内容 | O10: 索引号 | P10: 是否异常 | Q10: 备注说明
B11: 日期 | C11: 凭证编号 | D11: 业务内容 | E11: 对方科目 | F11: 对方明细科目 | G11: 借方金额 | H11: 贷方金额 | J11: 1 | K11: 2 | L11: 3 | M11: 4 | N11: 5
A25: 合计 | G25: =SUM(G12:G24) | H25: =SUM(H12:H24)
A26: 三、审计说明：
A27: 1.本期发生额、期末余额检查比例： | D27: 方向 | E27: 账面金额 | F27: 检查金额 | G27: 检查比例 | H27: 如果检查比例较低应扩大检查样本量或说明原因
D28: 本期借方 | E28: ='明细表K2-2'!M20 | F28: =G25 | G28: =ROUND(F28/E28,4)
D29: 本期贷方 | E29: ='明细表K2-2'!N20 | F29: =H25 | G29: =ROUND(F29/E29,2)
A30: 2.……
A31: 四、审计结论：

Sheet GT_Custom
A1: C1 | B1: Custom 1
A2: C2 | B2: Custom 2
A3: C3 | B3: Custom 3
A4: C4 | B4: Custom 4
A5: C5 | B5: Custom 5
A6: C6 | B6: Custom 6
A7: C7 | B7: Custom 7
A8: C8 | B8: Custom 8
