Workbook
Name _: #REF!
Name ___DAT1: #REF!
Name ___DAT10: #REF!
Name ___DAT11: #REF!
Name ___DAT2: #REF!
Name ___DAT3: #REF!
Name ___DAT4: #REF!
Name ___DAT5: #REF!
Name ___DAT6: #REF!
Name ___DAT7: #REF!
Name ___DAT8: #REF!
Name ___DAT9: #REF!
Name __C161100: #REF!
Name __DAT1: #REF!
Name __DAT10: #REF!
Name __DAT11: #REF!
Name __DAT2: #REF!
Name __DAT3: #REF!
Name __DAT4: #REF!
Name __DAT5: #REF!
Name __DAT6: #REF!
Name __DAT7: #REF!
Name __DAT8: #REF!
Name __DAT9: #REF!
Name _002存新: #REF!
Name _003新: #REF!
Name _01: #REF!
Name _011: #REF!
Name _012: #REF!
Name _013: #REF!
Name _014: #REF!
Name _015: #REF!
Name _016: #REF!
Name _01a: #REF!,#REF!,#REF!
Name _02: #REF!
Name _021: #REF!
Name _022: #REF!
Name _023: #REF!
Name _024: #REF!
Name _025: #REF!
Name _027: #REF!
Name _1: #REF!
Name _1_?: #REF!
Name _13102: #REF!
Name _13302: #REF!
Name _13398: #REF!
Name _18102: #REF!
Name _18198: #REF!
Name _2: #REF!
Name _2_??????: #REF!
Name _3查询_2001年4月余额表: #REF!
Name _412应收明细: #REF!
Name _99.dbf: [1]邻酮定乙酚发出测试!#REF!
Name _999年12月31日股份应收帐款.dbf: #REF!
Name _A1000: #REF!
Name _A1100: #REF!
Name _a1101: #REF!
Name _A1111: #REF!
Name _A1121: #REF!
Name _A1131: #REF!

Sheet 底稿目录
A1: 底稿开列时，可先在以下单元格填写有关内容，以便其他底稿引用有关数据：
A2: 被审计单位：ABC公司 | D2: 序号 | E2: 内容 | F2: 索引号
A3: 编制人：张三 | D3: 1 | E3: 程序表 | F3: S34-20
A4: 编制日期：2025.X.X | D4: =D3+1 -> 2 | E4: 重要劳务外包公司分析 | F4: S34-20-1
A5: 复核人：李四
A6: 复核日期：2025.X.X
A7: 会计期间：202X年度

Sheet S34-20程序表
A1: 致同会计师事务所
A2: 针对证监会、沪深两交所首次公开发行、北交所公开发行并上市监管法规的核查程序—劳务外包
A3: =底稿目录!A2 -> 被审计单位：ABC公司 | D3: =底稿目录!A3 -> 编制人：张三 | F3: =底稿目录!A4 -> 编制日期：2025.X.X | H3: 索引号： S34-20
A4: =底稿目录!A7 -> 会计期间：202X年度 | D4: =底稿目录!A5 -> 复核人：李四 | F4: =底稿目录!A6 -> 复核日期：2025.X.X | H4: 页 次：
A6: 一、核查目标
B7: 根据《上海证券交易所发行上市审核业务指南第4号——常见问题的信息披露和核查要求自查表 第1号首次公开发行》（以下简称上交所业务指南第4号-第1号）、《深圳证券交易所股票发行上市审核业务指南第3号——首次公开发行审核关注要点》（以下简称深交所业务指南3号）的要求，严格遵守现行各项执业准则和信息披露规范要求，勤勉尽责，审慎执业，就《上交所业务指南第4号-第1号》、《深交所业务指南3号》中提出的与注册会计师相关的问题进行逐项检查，核对已执行的审计程序和获取的审计证据是否已满足IPO申报财务报表审计中对劳务外包的核查要求。
B8: 提示：【使用时，请删除本段提示文字】 1、本核查程序表针对《上交所业务指南第4号-第1号》“3-22劳务外包”、《深交所业务指南3号》“27-2是否存在最近一个会计年度及最近一期劳务外包占比较高的情形”的要求厘定。 2、沪、深交易所针对劳务外包的核查要求存在个别差异，具体可见法规具体内容。 3、本核查程序表仅列示需完成的核查程序，取得的审计证据、凭证及其索引号，审计底稿的索引号。具体审计底稿索引至计划阶段、特项程序及各业务循环底稿，有些核查事项不能直接根据已有的各业务循环底稿等达到监管要求（例如监管要求回复数据一般为合并数据，实质性程序底稿可能为单体数据），建议参考相关实质性程序底稿中的内容在此文件中增加相应底稿，并同步修改索引号。 4、本程序表应根据被审计单位的实际情况进行适当的增删修改，以反映实际执行的审计工作情况。 | C8: 就这些事项的核查工作归集出一些常用的实质性程序，供项目组自查时核对参考。这些程序涉及的工作在执行项目审计时已经完成，本底稿用于项目组进行自查时，检查核对已完成的审计工作并进行汇总，以满足证监会单独形成自查底稿的要求。所列举的程序仅为常用程序，且主要是相关事项所涉及循环的实质性程序，项目组应当根据项目的实际情况进行适当的增删修改，以反映实际执行的审计工作情况。另外，有关内控了解测试、关联方、舞弊等审计工作，已在自查工作的其他部分反映，故此处未再复述。
A9: 序号 | B9: 程序 | E9: 取得证据、凭证 | F9: 取得证据、凭证索引号 | G9: 核查方式注 | H9: 审计程序索引
A10: 二、已执行的审计程序【项目小组应根据被审计单位实际情况修改、增减上述核查程序；修改、设计核查底稿】
A11: 《上交所业务指南第4号-第1号》3-22劳务外包 | B11: 如发行人存在将较多劳务活动交由专门劳务外包公司实施的情况，中介机构应当就以下事项进行核查、充分论证并发表明确意见： 申报会计师应当核查主要劳务公司的构成及变动情况，劳务外包合同的主要内容，劳务数量及费用变动是否与发行人经营业绩相匹配，劳务费用定价是否公允，是否存在跨期核算情形。
A12: 《深交所业务指南3号》“27-2是否存在最近一个会计年度及最近一期劳务外包占比较高的情形” | B12: 保荐人应当核查下列事项并 发表明确意见：（1）劳务外包金额较大的原 因、是否符合行业经营特点；（2）获取报告期各期劳务外 包金额及占当期营业成本比例、 劳务外包人数及占当期发行人员 工人数比例；（3）劳务公司的经营是否合法合规，是否专门或主要为发行 人服务，与发行人是否存在关联关系；（4）劳务公司是否存在较大变动，劳务费用定价是否公允，是否存在跨期核算情形，劳务数量及费用变动是否与发行人经营业绩相匹配。
A13: 1 | B13: 检查劳务外包占其当期人工费用的比例，当比例较高时执行下列程序
A14: （1） | B14: 取得劳务外包合同，核查发行人劳务外包人数、与发行人合作的劳务外包公司的基本情况，检查劳务公司的构成及变动情况。 | H14: S34-20-1
A15: （2） | B15: 检查劳务外包公司的结算单据及支付凭证，就资产负债表日前后记录的劳务费用，选取样本，检查相关合同、协议及其他支持性文 件，以评价是否存在跨期核算情形。
A16: （3） | B16: 检查劳务外包合同的主要内容，并分析劳务数量及费用变动是否与发行人经营业绩相匹配以及劳务费用定价是否公允。 | H16: S34-20-1
A17: 2 | B17: 对于劳务公司与发行人构成关联方的情况，检查财务报表附注中对相关关联方关系和关联交易的披露是否充分、恰当。 | H17: A7-2
A20: 注—核查方式：
A21: 如：询问（口头、书面）、检查（记录或文件、有形资产）、观察、函证、重新计算、重新执行、分析程序；
A22: 以及实地走访、电话访谈、核查工商资料等。

Sheet S34-20-1重要劳务外包公司分析
A1: 致同会计师事务所
A2: 重要劳务外包公司结构分析
A3: =底稿目录!A2 -> 被审计单位：ABC公司 | E3: =底稿目录!A3 -> 编制人：张三 | I3: =底稿目录!A4 -> 编制日期：2025.X.X | O3: 索引号： | P3: S34-20-1
A4: =底稿目录!A7 -> 会计期间：202X年度 | E4: =底稿目录!A5 -> 复核人：李四 | I4: =底稿目录!A6 -> 复核日期：2025.X.X | O4: 页 次：
A5: 一、审计目标：
A6: 1、分析劳务外包的合理性及价格公允性；
A7: 二、审计过程：
A8: 1、获取主要劳务外包公司的合同，查看劳务外包公司为被审计单位提供劳务的具体情况；
A9: 被审计单位劳务外包公司选择标准及方式
A10: 描述选择劳务外包公司的标准和具体方式
A13: 本年（期）总外包金额 | C13: 0 | D13: 本年（期）总外包金额 | G13: 0
A14: 序号 | B14: 本年（期）大额劳务外包公司名称 | C14: 外包金额 | D14: 占比 | E14: 人工成本 | F14: 占比 | G14: 上期排名 | H14: 合作年限 | I14: 合同主要条款 | M14: 合同执行情况 | N14: 是否关联方 | O14: 注册资本 | P14: 是否有相关资质
I15: 劳务外包金额 | J15: 信用期 | K15: 支付方式 | L15: 其他
A16: 1 | B16: XX劳务有限责任公司 | D16: =IF(ISERROR(C16/$C$13),0,C16/$C$13) -> 0 | F16: =IF(ISERROR(E16/$G$13),0,E16/$G$13) -> 0
A17: 2 | D17: =IF(ISERROR(C17/$C$13),0,C17/$C$13) -> 0 | F17: =IF(ISERROR(E17/$G$13),0,E17/$G$13) -> 0
A18: 3 | D18: =IF(ISERROR(C18/$C$13),0,C18/$C$13) -> 0 | F18: =IF(ISERROR(E18/$G$13),0,E18/$G$13) -> 0
A19: 4 | D19: =IF(ISERROR(C19/#REF!),0,C19/#REF!) -> 0 | F19: =IF(ISERROR(E19/#REF!),0,E19/#REF!) -> 0
A20: 5 | D20: =IF(ISERROR(C20/#REF!),0,C20/#REF!) -> 0 | F20: =IF(ISERROR(E20/#REF!),0,E20/#REF!) -> 0
B21: 合 计 | C21: =SUM(C16:C18) -> 0 | D21: =SUM(D16:D20) -> 0 | E21: =SUM(E16:E20) -> 0 | F21: =SUM(F16:F20) -> 0
A22: 2、对比重要劳务外包公司提供的劳务数量及费用变动是否与发行人经营业绩相匹配
A23: 月份 | B23: 本年（期）大额劳务外包公司名称 | C23: 劳务外包金额 | D23: 劳务外包人数 | E23: 销售收入
A24: 1 | B24: XX劳务有限公司
A25: 2
A26: 3
A27: 4
A28: 5
A29: 6
A30: 7
B31: 合计 | C31: =SUM(C24:C30) -> 0 | D31: =SUM(D24:D30) -> 0 | E31: =SUM(E24:E30) -> 0
A32: 3、与其他劳务外包公司的相同服务的人工单价进行对比，查看价格是否公允。
A33: 序号 | B33: 本年（期）大额劳务外包公司名称 | F33: 可比劳务公司名称 | J33: 价格差异
B34: 劳务外包服务内容 | C34: 劳务外包金额 | D34: 劳务外包人数 | E34: 劳务外包单价 | F34: 劳务外包服务内容 | G34: 劳务外包金额 | H34: 劳务外包人数 | I34: 劳务外包单价
A35: 1 | E35: =C35/D35 -> #DIV/0! | I35: =G35/H35 -> #DIV/0! | J35: =(E35-I35)/D35 -> #DIV/0!
A36: 2 | E36: =C36/D36 -> #DIV/0! | I36: =G36/H36 -> #DIV/0! | J36: =(E36-I36)/D36 -> #DIV/0!
A37: 3 | E37: =C37/D37 -> #DIV/0! | I37: =G37/H37 -> #DIV/0! | J37: =(E37-I37)/D37 -> #DIV/0!
A39: 三、审计说明：
A41: 四、审计结论：

Sheet GT_Custom
A1: C1 | B1: Custom 1
A2: C2 | B2: Custom 2
A3: C3 | B3: Custom 3
A4: C4 | B4: Custom 4
A5: C5 | B5: Custom 5
A6: C6 | B6: Custom 6
A7: C7 | B7: Custom 7
A8: C8 | B8: Custom 8
