Workbook
Name _13102: #REF!
Name _13102: #REF!
Name _13302: #REF!
Name _13302: #REF!
Name _13398: #REF!
Name _13398: #REF!
Name _18102: #REF!
Name _18102: #REF!
Name _18198: #REF!
Name _18198: #REF!
Name _1其他资产_开办费除外_明细表: #REF!
Name _2003附注: [1]附注汇总!$C$5:$AY$646
Name _2其他资产_开办费除外_明细表: #REF!
Name _scn11: #REF!
Name _scn11: #REF!
Name _scn15: #REF!
Name _scn15: #REF!
Name _scn16: #REF!
Name _scn16: #REF!
Name _scn17: #REF!
Name _scn17: #REF!
Name _scn19: #REF!
Name _scn19: #REF!
Name _scn2: #REF!
Name _scn2: #REF!
Name _scn20: #REF!
Name _scn20: #REF!
Name _scn3: #REF!
Name _scn3: #REF!
Name _scn4: #REF!
Name _scn4: #REF!
Name _scn5: #REF!
Name _scn5: #REF!
Name _scn6: #REF!
Name _scn6: #REF!
Name _scn7: #REF!
Name _scn7: #REF!
Name _scn8: #REF!
Name _scn8: #REF!
Name _scn9: #REF!
Name _scn9: #REF!
Name _scq1: #REF!
Name _scq1: #REF!
Name _scq11: #REF!
Name _scq11: #REF!
Name _scq15: #REF!
Name _scq15: #REF!
Name _scq16: #REF!
Name _scq16: #REF!
Name _scq17: #REF!
Name _scq17: #REF!
Name _scq19: #REF!
Name _scq19: #REF!
Name _scq2: #REF!
Name _scq2: #REF!
Name _scq20: #REF!
Name _scq20: #REF!
Name _scq3: #REF!
Name _scq3: #REF!
Name _scq4: #REF!

Sheet temp_temp__
AI36: =SUM(AI26)+SUM(AI27)-SUM(AI32) -> 0

Sheet 说明
B2: 使用说明： | L2: 序号 | M2: 目录
L3: 1 | M3: 说明
B4: 1 | C4: 本工作簿用于合并会计报表审计调整、试算平衡；审定报表的横向、纵向、比率分析。 | L4: 2 | M4: TEST
L5: 3 | M5: 报表格式
B6: 2 | C6: 本工作簿没有颜色的单元格可以根据需要进行修改， | L6: 4 | M6: 年初BS审定
C7: 修改时，请在拟修改的单元格直接输入新的内容，请不要使用剪切或拖拽填充功能。 | L7: 5 | M7: 上年PL审定
L8: 6 | M8: 期初核对BS
B9: 3 | C9: 请在 | D9: “基本参数” | E9: 中没有颜色的单元格中输入项目基本情况，其他工作表相应区域会随之改变。 | L9: 7 | M9: 期初核对PL
L10: 8 | M10: 母公司BS原报汇总
B11: 4 | C11: 未审报表、试算平衡表（TB）、审定报表、比较分析表的格式由 | G11: “报表格式” | H11: 链接控制； | L11: 9 | M11: 母公司PL原报汇总
C12: 如需修改报表科目，请在 | E12: “报表格式” | F12: 中没有颜色的单元格区域修改，其他报表会相应改变。 | L12: 10 | M12: 母公司CF原报汇总
L13: 11 | M13: 母公司汇总抵销
B14: 5 | C14: “权益抵销” | D14: “往来交易抵销” | E14: 可以根据需要插入行，请勿删除行；调整金额会自动链接到试算平衡表， | L14: 12 | M14: 母公司账项调整
C15: 若调整未全部链入试算平衡表，请检查调整分录的借贷方科目是否为报表科目。若需添加或更改报表科目， | L15: 13 | M15: 母公司报表调整
C16: 请在 | D16: “报表格式” | E16: 中没有颜色的单元格区域进行修改，并相应修改 | H16: “报表格式AA列” | L16: 14 | M16: 母公司TB资产
L17: 15 | M17: 母公司TB负债
L18: 16 | M18: 母公司TB损益
L19: 17 | M19: TB母公司CF
L20: 18 | M20: 合并BS汇总
C21: 基本参数： | L21: 19 | M21: 合并PL汇总
C22: 项 目 | E22: 参 数 | G22: 参考格式 | L22: 20 | M22: 合并CF汇总
C23: 客户情况 | D23: 单位名称： | G23: 北京二锅头有限责任公司 | L23: 21 | M23: 权益抵销
D24: 法定代表人： | G24: 张一二 | L24: 22 | M24: 往来交易抵销
D25: 财务负责人： | G25: 陈一二 | L25: 23 | M25: 合并报表调整
D26: 会计主管： | G26: 王一二 | L26: 24 | M26: 合并TB资产
L27: 25 | M27: 合并TB负债
C28: 会计报表 | D28: 报表类型 | E28: 股份有限公司 | G28: 股份有限公司或一般企业(执行统一会计制度) | J28: 股份有限公司 | L28: 26 | M28: 合并TB损益
D29: 会计年度（上期）： | E29: 2018年度 | G29: 1999年度 或 1997年10月20日～1998年8月10日 | J29: 非股份有限公司 | L29: 27 | M29: TB合并CF
D30: 会计年度（本期）： | E30: 2019年度 | G30: 2000年度 或 1998年8月10日～2000年10月20日 | L30: 28 | M30: 审定合并BS
D31: 会计截止（上期）： | E31: 43465 | G31: 1999年12月31日 或 1998年8月10日 | J31: =MONTH(E31) -> 12 | L31: 29 | M31: 审定合并PL
D32: 会计截止（本期）： | E32: 43830 | G32: 2000年12月31日 或 2000年10月20日 | J32: =MONTH(E32) -> 12 | L32: 30 | M32: 审定合并CF
D33: 金额单位： | E33: 人民币元 | G33: 人民币元 | L33: 31 | M33: 已审横向BS
C34: NB： | D34: 本表没有颜色的单元格可以根据需要进行修改 | L34: 32 | M34: 已审横向PL
L35: 33 | M35: 已审纵向BS
L36: 34 | M36: 已审纵向PL
L37: 35 | M37: 已审比率分析
L38: 36 | M38: EPS-ROE计算
L39: 37 | M39: 母已审横向BS
L40: 38 | M40: 母已审横向PL
L41: 39 | M41: 母已审纵向BS
L42: 40 | M42: 母已审纵向PL
L43: 41 | M43: 母已审比率分析

Sheet TEST
B3: 报表勾稽关系审核表
B4: No. | C4: 勾稽审核内容 | D4: 审核结果 | E4: 不符原因
B5: 1 | C5: 期末资产总计＝期末负债和股东权益总计 | D5: =IF(ABS(审定合并BS!C59-审定合并BS!C122)<0.01,TRUE,FALSE) -> TRUE | E5: =IF(D5=TRUE,"","期末资产负债表不平")
B6: 2 | C6: 期初资产总计＝期初负债和股东权益总计 | D6: =IF(ABS(审定合并BS!E59-审定合并BS!E122)<0.01,TRUE,FALSE) -> TRUE | E6: =IF(D6=TRUE,"","期初资产负债表不平")
B7: 3 | C7: B/S期末未分配利润＝P/L期末未分配利润 | D7: =IF(ABS(审定合并BS!C118-审定合并PL!C89)<0.01,TRUE,FALSE) -> TRUE | E7: =IF(D7=TRUE,"","期末利润分配表与资产负债表未分配利润勾稽不对")
B8: 4 | C8: B/S期初未分配利润＝P/L期初未分配利润 | D8: =IF(ABS(审定合并BS!E116-审定合并PL!E71)<0.01,TRUE,FALSE) -> TRUE | E8: =IF(D8=TRUE,"","期初利润分配表与资产负债表未分配利润勾稽不对")
B9: 5 | C9: 期末年初未分配利润＝期初未分配利润 | D9: =IF(ABS(审定合并PL!C79-审定合并PL!E89)<0.01,TRUE,FALSE) -> TRUE | E9: =IF(D9=TRUE,"","利润及利润分配表年初未分配利润与上期勾稽不对")
B10: 6 | C10: B/S期末货币资金＝Cashflow期末货币资金 | D10: =IF(ABS(审定合并BS!C7-审定合并CF!C64)<0.01,TRUE,FALSE) -> TRUE | E10: =IF(D10=TRUE,"","现金流量表与资产负债表期末货币资金勾稽不对")
B11: 7 | C11: B/S期初货币资金＝Cashflow期初货币资金 | D11: =IF(ABS(审定合并BS!E7-审定合并CF!C63)<0.01,TRUE,FALSE) -> TRUE | E11: =IF(D11=TRUE,"","现金流量表与资产负债表期初货币资金勾稽不对")
B12: 8 | C12: 直接法OperatingCF＝间接法OperatingCF | D12: =IF(ABS(审定合并CF!C31-审定合并CF!C91)<0.01,TRUE,FALSE) -> TRUE | E12: =IF(D12=TRUE,"","现金流量表主表与附表勾稽不对-经营活动现金净增加额")
B13: 9 | C13: 直接法NetCashflow＝间接法NetCashflow | D13: =IF(ABS(审定合并CF!C103-审定合并CF!C62)<0.01,TRUE,FALSE) -> TRUE | E13: =IF(D13=TRUE,"","现金流量表主表与附表勾稽不对-现金净增加额")
B14: 10 | C14: P/L净利润＝Cashflow间接法净利润 | D14: =IF(ABS(审定合并CF!C75-审定合并PL!C44)<0.01,TRUE,FALSE) -> TRUE | E14: =IF(D14=TRUE,"","现金流量表与利润表勾稽不对-净利润")
B15: 11 | C15: Cashflow存货的减少＝B/S存货的减少 | D15: =IF(ABS(审定合并CF!C87-(审定合并BS!E24-审定合并BS!C24))<0.01,TRUE,FALSE) -> TRUE | E15: =IF(D15=TRUE,"","现金流量表存货与资产负债表勾稽不对")
B16: 12 | C16: Cashflow投资收益＝P/L投资收益 | D16: =IF(ABS(审定合并CF!C84+审定合并PL!C33)<0.01,TRUE,FALSE) -> TRUE | E16: =IF(D16=TRUE,"","利润分配表与现金流量表投资收益勾稽不对")
B17: 13 | C17: 按净利润的10%提取法定盈余公积 | D17: =IF(ABS(审定合并PL!C53-审定合并PL!H45*0.1)<0.01,TRUE,FALSE) -> TRUE | E17: =IF(D17=TRUE,"","按照公司政策，公司提取的法定盈余公积不符")
B18: 14
B19: 15
B20: 16
B21: 17

Sheet 报表格式
A1: 会计报表格式及科目名称 | Q1: 会计报表格式及科目名称 | Z1: code | AA1: 报表项目
B2: 本表没有颜色的单元格可以根据需要进行修改，本系统的其它表格将随之改变。比如，可将“存货”改为“存货1”。正确的修改方法，是在拟修改的单元格直接输入新的内容，请不要使用剪切或拖拽功能。
B3: 资 产 类 | G3: 负债及所有者权益类 | L3: 损 益 类 | Q3: 现金流量表类 | U3: 现金流量表类
B4: 报表项目 | C4: 行 | D4: 调整年末科目名称 | E4: 调整年初科目名称 | G4: 报表项目 | H4: 行 | I4: 调整年末科目名称 | J4: 调整年初科目名称 | L4: 报表项目 | M4: 行 | N4: 调整本期科目名称 | O4: 调整上期科目名称 | Q4: 报表项目 | R4: 行 | S4: 科目名称 | U4: 补充资料 | V4: 行 | W4: 科目名称
B5: 流动资产： | C5: 1 | G5: 流动负债： | H5: =C58+1 -> 55 | L5: 一、营业收入 | M5: 1 | N5: 主营业务收入 | O5: =IF(N5="",0,CONCATENATE("上年",N5)) -> 上年主营业务收入 | Q5: 一、经营活动产生的现金流量 | R5: 1 | U5: 1、将净利润调节为经营活动现金流量： | V5: =R70+1 -> 1 | AA5: 流动资产：
B6: 货币资金 | C6: 2 | D6: 货币资金 | E6: =IF(D6="",0,CONCATENATE("年初",D6)) -> 年初货币资金 | G6: 短期借款 | H6: =H5+1 -> 56 | I6: 短期借款 | J6: =IF(I6="",0,CONCATENATE("年初",I6)) -> 年初短期借款 | L6: 其中：主营业务收入 | M6: 2 | Q6: 销售商品、提供劳务收到的现金 | R6: 2 | S6: 销售商品、提供劳务收到的现金 | U6: 净利润 | V6: =V5+1 -> 2 | W6: 净利润 | Z6: D1 | AA6: =B6 -> 货币资金
B7: 结算备付金 | C7: 3 | D7: 短期投资 | E7: =IF(D7="",0,CONCATENATE("年初",D7)) -> 年初短期投资 | G7: 向中央银行借款 | H7: =H6+1 -> 57 | I7: 应付票据 | J7: =IF(I7="",0,CONCATENATE("年初",I7)) -> 年初应付票据 | L7: 利息收入 | M7: 3 | Q7: 客户存款和同业存放款项净增加额 | R7: 3 | S7: 收到的税费返还 | V7: =V6+1 -> 3 | W7: 少数股东损益 | Z7: D41 | AA7: =B7 -> 结算备付金
B8: 拆出资金 | C8: 4 | D8: 应收票据 | E8: =IF(D8="",0,CONCATENATE("年初",D8)) -> 年初应收票据 | G8: 吸收存款及同业存放 | H8: =H7+1 -> 58 | I8: 应付账款 | J8: =IF(I8="",0,CONCATENATE("年初",I8)) -> 年初应付账款 | L8: 已赚保费 | M8: 4 | N8: 折扣与折让 | O8: =IF(N8="",0,CONCATENATE("上年",N8)) -> 上年折扣与折让 | Q8: 向中央银行借款净增加额 | R8: 4 | S8: 收到的其他与经营活动有关的现金 | V8: =V7+1 -> 4 | W8: 未确认的投资损失 | Z8: D42 | AA8: =B8 -> 拆出资金
B9: 交易性金融资产 | C9: 5 | D9: 应收股利 | E9: =IF(D9="",0,CONCATENATE("年初",D9)) -> 年初应收股利 | G9: 拆入资金 | H9: =H8+1 -> 59 | I9: 预收账款 | J9: =IF(I9="",0,CONCATENATE("年初",I9)) -> 年初预收账款 | L9: 手续费及佣金收入 | M9: 5 | Q9: 向其他金融机构拆入资金净增加额 | R9: 5 | U9: 加：资产减值损失 | V9: =V8+1 -> 5 | W9: 计提的资产减值准备 | Z9: D2 | AA9: =B9 -> 交易性金融资产
B10: 以公允价值计量且其变动计入当期损益的金融资产 | C10: 6 | D10: 应收利息 | E10: =IF(D10="",0,CONCATENATE("年初",D10)) -> 年初应收利息 | G10: 交易性金融负债 | H10: =H9+1 -> 60 | I10: 应付工资 | J10: =IF(I10="",0,CONCATENATE("年初",I10)) -> 年初应付工资 | L10: 其他业务收入 | M10: 6 | N10: 主营业务成本 | O10: =IF(N10="",0,CONCATENATE("上年",N10)) -> 上年主营业务成本 | Q10: 收到原保险合同保费取得的现金 | R10: 6 | U10: 信用减值损失 | V10: =V9+1 -> 6 | W10: 固定资产折旧 | Z10: D3 | AA10: =B10 -> 以公允价值计量且其变动计入当期损益的金融资产
B11: 衍生金融资产 | C11: 7 | D11: 应收账款 | E11: =IF(D11="",0,CONCATENATE("年初",D11)) -> 年初应收账款 | G11: 以公允价值计量且其变动计入当期损益的金融负债 | H11: =H10+1 -> 61 | I11: 应付福利费 | J11: =IF(I11="",0,CONCATENATE("年初",I11)) -> 年初应付福利费 | L11: 减：营业成本 | M11: 7 | Q11: 收到再保险业务现金净额 | R11: 7 | S11: 购买商品、接受劳务支付的现金 | U11: 固定资产折旧、油气资产折耗、生产性生物资产折旧 | V11: =V10+1 -> 7 | W11: 无形资产摊销 | Z11: D4 | AA11: =B11 -> 衍生金融资产
B12: 应收票据 | C12: 8 | D12: 其他应收款 | E12: =IF(D12="",0,CONCATENATE("年初",D12)) -> 年初其他应收款 | G12: 衍生金融负债 | H12: =H11+1 -> 62 | I12: 应付股利 | J12: =IF(I12="",0,CONCATENATE("年初",I12)) -> 年初应付股利 | L12: 其中：主营业务成本 | M12: 8 | N12: 主营业务税金及附加 | O12: =IF(N12="",0,CONCATENATE("上年",N12)) -> 上年主营业务税金及附加 | Q12: 保户储金及投资款净增加额 | R12: 8 | S12: 支付给职工以及为职工支付的现金 | U12: 无形资产摊销 | V12: =V11+1 -> 8 | W12: 长期待摊费用摊销 | Z12: D5 | AA12: =B12 -> 应收票据
B13: 应收账款 | C13: 9 | D13: 预付账款 | E13: =IF(D13="",0,CONCATENATE("年初",D13)) -> 年初预付账款 | G13: 应付票据 | H13: =H12+1 -> 63 | I13: 应交税金 | J13: =IF(I13="",0,CONCATENATE("年初",I13)) -> 年初应交税金 | L13: 利息支出 | M13: 9 | N13: 经营费用 | O13: =IF(N13="",0,CONCATENATE("上年",N13)) -> 上年经营费用 | Q13: 收取利息、手续费及佣金的现金 | R13: 9 | S13: 支付各项税费 | U13: 长期待摊费用摊销 | V13: =V12+1 -> 9 | W13: 待摊费用的减少（减：增加） | Z13: D6 | AA13: =B13 -> 应收账款
B14: 应收款项融资 | C14: 10 | D14: 期货保证金 | E14: =IF(D14="",0,CONCATENATE("年初",D14)) -> 年初期货保证金 | G14: 应付账款 | H14: =H13+1 -> 64 | I14: 其他未交款 | J14: =IF(I14="",0,CONCATENATE("年初",I14)) -> 年初其他未交款 | L14: 手续费及佣金支出 | M14: 10 | N14: 其他 | O14: =IF(N14="",0,CONCATENATE("上年",N14)) -> 上年其他 | Q14: 拆入资金净增加额 | R14: 10 | S14: 支付的其他与经营活动有关的现金 | U14: 处置固定资产、无形资产和其他长期资产的损失（收益以“－”号填列） | V14: =V13+1 -> 10 | W14: 预提费用的增加（减：减少） | Z14: D7 | AA14: =B14 -> 应收款项融资
B15: 预付款项 | C15: 11 | D15: 应收补贴款 | E15: =IF(D15="",0,CONCATENATE("年初",D15)) -> 年初应收补贴款 | G15: 预收款项 | H15: =H14+1 -> 65 | I15: 其他应付款 | J15: =IF(I15="",0,CONCATENATE("年初",I15)) -> 年初其他应付款 | L15: 退保金 | M15: 11 | N15: 递延收益 | O15: =IF(N15="",0,CONCATENATE("上年",N15)) -> 上年递延收益 | Q15: 回购业务资金净增加额 | R15: 11 | U15: 固定资产报废损失（收益以“－”号填列） | V15: =V14+1 -> 11 | W15: 处置固定资产、无形资产和其他长期资产的损失（减：收益） | Z15: D8 | AA15: =B15 -> 预付款项
B16: 应收保费 | C16: 12 | D16: 应收出口退税 | E16: =IF(D16="",0,CONCATENATE("年初",D16)) -> 年初应收出口退税 | G16: 卖出回购金融资产款 | H16: =H15+1 -> 66 | I16: 预提费用 | J16: =IF(I16="",0,CONCATENATE("年初",I16)) -> 年初预提费用 | L16: 赔付支出净额 | M16: 12 | N16: 代购代销收入 | O16: =IF(N16="",0,CONCATENATE("上年",N16)) -> 上年代购代销收入 | Q16: 收到的税费返还 | R16: 12 | U16: 公允价值变动损失（收益以“－”号填列） | V16: =V15+1 -> 12 | W16: 固定资产报废损失 | Z16: D43 | AA16: =B16 -> 应收保费
B17: 应收分保账款 | C17: 13 | D17: 存货 | E17: =IF(D17="",0,CONCATENATE("年初",D17)) -> 年初存货 | G17: 应付手续费及佣金 | H17: =H16+1 -> 67 | I17: 预计负债 | J17: =IF(I17="",0,CONCATENATE("年初",I17)) -> 年初预计负债 | L17: 提取保险合同准备金净额 | M17: 13 | N17: 其他 | O17: =IF(N17="",0,CONCATENATE("上年",N17)) -> 上年其他 | Q17: 收到的其他与经营活动有关的现金 | R17: 13 | U17: 财务费用（收益以“－”号填列） | V17: =V16+1 -> 13 | W17: 财务费用 | Z17: D44 | AA17: =B17 -> 应收分保账款
B18: 应收分保准备金 | C18: 14 | D18: 其中：原材料 | G18: 合同负债 | H18: =H17+1 -> 68 | I18: 一年内到期的长期负债 | J18: =IF(I18="",0,CONCATENATE("年初",I18)) -> 年初一年内到期的长期负债 | L18: 保单红利支出 | M18: 14 | O18: =IF(N18="",0,CONCATENATE("上年",N18)) -> 0 | R18: 14 | U18: 投资损失（收益以“－”号填列） | V18: =V17+1 -> 14 | Z18: D45 | AA18: =B18 -> 应收分保准备金
B19: 其他应收款 | C19: 15 | D19: 库存商品（产成品） | G19: 应付职工薪酬 | H19: =H18+1 -> 69 | I19: 其他流动负债 | J19: =IF(I19="",0,CONCATENATE("年初",I19)) -> 年初其他流动负债 | L19: 分保费用 | M19: 15 | N19: 其他业务利润 | O19: =IF(N19="",0,CONCATENATE("上年",N19)) -> 上年其他业务利润 | R19: 15 | U19: 递延所得税资产减少（增加以“－”号填列） | V19: =V18+1 -> 15 | Z19: D9 | AA19: =B19 -> 其他应收款
B20: 其中：应收利息 | C20: 16 | D20: 待摊费用 | E20: =IF(D20="",0,CONCATENATE("年初",D20)) -> 年初待摊费用 | G20: 应交税费 | H20: =H19+1 -> 70 | L20: 其他业务成本 | M20: 16 | N20: 营业费用 | O20: =IF(N20="",0,CONCATENATE("上年",N20)) -> 上年营业费用 | Q20: 经营活动现金流入小计 | R20: 16 | U20: 递延所得税负债增加（减少以“－”号填列） | V20: =V19+1 -> 16 | W20: 投资损失（减：收益） | AA20: =B20 -> 其中：应收利息
B21: 应收股利 | C21: 17 | D21: 待处理流动资产净损失 | E21: =IF(D21="",0,CONCATENATE("年初",D21)) -> 年初待处理流动资产净损失 | G21: 其他应付款 | H21: =H20+1 -> 71 | J21: =IF(I21="",0,CONCATENATE("年初",I21)) -> 0 | L21: 税金及附加 | M21: 17 | N21: 管理费用 | O21: =IF(N21="",0,CONCATENATE("上年",N21)) -> 上年管理费用 | Q21: 购买商品、接受劳务支付的现金 | R21: 17 | S21: 收回投资所收到的现金 | U21: 存货的减少（增加以“－”号填列） | V21: =V20+1 -> 17 | W21: 递延税款贷项（减：借项） | AA21: =B21 -> 应收股利
B22: 买入返售金融资产 | C22: 18 | D22: 一年内到期的长期债权投资 | E22: =IF(D22="",0,CONCATENATE("年初",D22)) -> 年初一年内到期的长期债权投资 | G22: 其中：应付利息 | H22: =H21+1 -> 72 | J22: =IF(I22="",0,CONCATENATE("年初",I22)) -> 0 | L22: 销售费用 | M22: 18 | N22: 财务费用 | O22: =IF(N22="",0,CONCATENATE("上年",N22)) -> 上年财务费用 | Q22: 客户贷款及垫款净增加额 | R22: 18 | U22: 经营性应收项目的减少（增加以“－”号填列） | V22: =V21+1 -> 18 | W22: 存货的减少（减：增加） | Z22: D46 | AA22: =B22 -> 买入返售金融资产
B23: 存货 | C23: 19 | D23: 其他流动资产 | E23: =IF(D23="",0,CONCATENATE("年初",D23)) -> 年初其他流动资产 | G23: 应付股利 | H23: =H22+1 -> 73 | J23: =IF(I23="",0,CONCATENATE("年初",I23)) -> 0 | L23: 管理费用 | M23: 19 | Q23: 存放中央银行和同业款项净增加额 | R23: 19 | S23: 取得投资收益所收到的现金 | U23: 经营性应付项目的增加（减少以“－”号填列） | V23: =V22+1 -> 19 | W23: 经营性应收项目的减少（减：增加） | Z23: D10 | AA23: =B23 -> 存货
B24: 合同资产 | C24: 20 | E24: =IF(D24="",0,CONCATENATE("年初",D24)) -> 0 | G24: 应付分保账款 | H24: =H23+1 -> 74 | J24: =IF(I24="",0,CONCATENATE("年初",I24)) -> 0 | L24: 研发费用 | M24: 20 | Q24: 支付原保险合同赔付款项的现金 | R24: 20 | S24: 处置固定资产、无形资产和其他长期资产所收回的现金净额 | U24: 其他 | V24: =V23+1 -> 20 | W24: 经营性应付项目的增加（减：减少） | Z24: D11 | AA24: =B24 -> 合同资产
B25: 持有待售资产 | C25: 21 | E25: =IF(D25="",0,CONCATENATE("年初",D25)) -> 0 | G25: 保险合同准备金 | H25: =H24+1 -> 75 | I25: 长期借款 | J25: =IF(I25="",0,CONCATENATE("年初",I25)) -> 年初长期借款 | L25: 财务费用 | M25: 21 | O25: =IF(N25="",0,CONCATENATE("上年",N25)) -> 0 | Q25: 支付利息、手续费及佣金的现金 | R25: 21 | S25: 收到的其他与投资活动有关的现金 | V25: =V24+1 -> 21 | W25: 其他 | Z25: D12 | AA25: =B25 -> 持有待售资产
B26: 一年内到期的非流动资产 | C26: 22 | E26: =IF(D26="",0,CONCATENATE("年初",D26)) -> 0 | G26: 代理买卖证券款 | H26: =H25+1 -> 76 | I26: 应付债券 | J26: =IF(I26="",0,CONCATENATE("年初",I26)) -> 年初应付债券 | L26: 其中：利息费用 | M26: 22 | N26: 其他 | O26: =IF(N26="",0,CONCATENATE("上年",N26)) -> 上年其他 | Q26: 支付保单红利的现金 | R26: 22 | U26: 经营活动产生的现金流量净额 | V26: =V25+1 -> 22 | Z26: D13 | AA26: =B26 -> 一年内到期的非流动资产
B27: 其他流动资产 | C27: 23 | E27: =IF(D27="",0,CONCATENATE("年初",D27)) -> 0 | G27: 代理承销证券款 | H27: =H26+1 -> 77 | I27: 长期应付款 | J27: =IF(I27="",0,CONCATENATE("年初",I27)) -> 年初长期应付款 | L27: 利息收入 | M27: 23 | O27: =IF(N27="",0,CONCATENATE("上年",N27)) -> 0 | Q27: 支付给职工以及为职工支付的现金 | R27: 23 | V27: =V26+1 -> 23 | Z27: D14 | AA27: =B27 -> 其他流动资产
C28: 24 | E28: =IF(D28="",0,CONCATENATE("年初",D28)) -> 0 | G28: 持有待售负债 | H28: =H27+1 -> 78 | I28: 专项应付款 | J28: =IF(I28="",0,CONCATENATE("年初",I28)) -> 年初专项应付款 | L28: 加：其他收益 | M28: 24 | N28: 投资收益 | O28: =IF(N28="",0,CONCATENATE("上年",N28)) -> 上年投资收益 | Q28: 支付各项税费 | R28: 24 | S28: 购置固定资产、无形资产和其他长期资产所支付的现金 | U28: 2、不涉及现金收支的投资和筹资活动： | V28: =V27+1 -> 24 | Z28: D15 | AA28: =B28 -> 0
C29: 25 | D29: 长期股权投资 | E29: =IF(D29="",0,CONCATENATE("年初",D29)) -> 年初长期股权投资 | G29: 一年内到期的非流动负债 | H29: =H28+1 -> 79 | I29: 其他长期负债 | J29: =IF(I29="",0,CONCATENATE("年初",I29)) -> 年初其他长期负债 | L29: 投资收益（损失以“－”号填列） | M29: 25 | N29: 期货收益 | Q29: 支付的其他与经营活动有关的现金 | R29: 25 | S29: 投资所支付的现金 | U29: 债务转为资本 | V29: =V28+1 -> 25 | Z29: D16 | AA29: =B29 -> 0
B30: 流动资产合计 | C30: 26 | D30: 长期债权投资 | E30: =IF(D30="",0,CONCATENATE("年初",D30)) -> 年初长期债权投资 | G30: 其他流动负债 | H30: =H29+1 -> 80 | I30: 其中：特准储备资金 | L30: 其中：对联营企业和合营企业的投资收益 | M30: 26 | N30: 补贴收入 | R30: 26 | U30: 一年内到期的可转换公司债券 | V30: =V29+1 -> 26 | AA30: =B30 -> 流动资产合计
B31: 非流动资产: | C31: 27 | D31: 合并价差 | E31: =IF(D31="",0,CONCATENATE("年初",D31)) -> 年初合并价差 | G31: 流动负债合计 | H31: =H30+1 -> 81 | L31: 以摊余成本计量的金融资产终止确认收益（损失以“-”号填列） | M31: 27 | Q31: 经营活动现金流出小计 | R31: 27 | S31: 支付的其他与投资活动有关的现金 | U31: 融资租入固定资产 | V31: =V30+1 -> 27 | W31: 债务转为资本 | AA31: =B31 -> 非流动资产:
B32: 发放贷款及垫款 | C32: 28 | G32: 非流动负债: | H32: =H31+1 -> 82 | J32: =IF(I32="",0,CONCATENATE("年初",I32)) -> 0 | L32: 净敞口套期收益（损失以“-”号填列） | M32: 28 | N32: 营业外收入 | O32: =IF(N32="",0,CONCATENATE("上年",N32)) -> 上年营业外收入 | Q32: 经营活动产生的现金流量净额 | R32: 28 | U32: 其他 | V32: =V31+1 -> 28 | W32: 一年内到期的可转换公司债券 | Z32: D47 | AA32: =B32 -> 发放贷款及垫款
B33: 债权投资 | C33: 29 | G33: 长期借款 | H33: =H32+1 -> 83 | J33: =IF(I33="",0,CONCATENATE("年初",I33)) -> 0 | L33: 公允价值变动收益（损失以“－”号填列） | M33: 29 | Q33: 二、投资活动产生的现金流量 | R33: 29 | V33: =V32+1 -> 29 | W33: 融资租入固定资产 | Z33: D17 | AA33: =B33 -> 债权投资
B34: 可供出售金融资产 | C34: 30 | E34: =IF(D34="",0,CONCATENATE("年初",D34)) -> 0 | G34: 应付债券 | H34: =H33+1 -> 84 | J34: =IF(I34="",0,CONCATENATE("年初",I34)) -> 0 | L34: 信用减值损失(损失以“-”号填列） | M34: 30 | Q34: 收回投资所收到的现金 | R34: 30 | V34: =V33+1 -> 30 | W34: 其他 | Z34: D18 | AA34: =B34 -> 可供出售金融资产
B35: 其他债权投资 | C35: 31 | E35: =IF(D35="",0,CONCATENATE("年初",D35)) -> 0 | G35: 其中：优先股 | H35: =H34+1 -> 85 | J35: =IF(I35="",0,CONCATENATE("年初",I35)) -> 0 | L35: 资产减值损失(损失以“-”号填列） | M35: 31 | Q35: 取得投资收益所收到的现金 | R35: 31 | U35: 3、现金及现金等价物净变动情况： | V35: =V34+1 -> 31 | Z35: D19 | AA35: =B35 -> 其他债权投资
B36: 持有至到期投资 | C36: 32 | E36: =IF(D36="",0,CONCATENATE("年初",D36)) -> 0 | G36: 永续债 | H36: =H35+1 -> 86 | I36: 递延税款贷项 | J36: =IF(I36="",0,CONCATENATE("年初",I36)) -> 年初递延税款贷项 | L36: 资产处置收益(损失以“-”号填列） | M36: 32 | Q36: 处置固定资产、无形资产和其他长期资产而收到的现金净额 | R36: 32 | S36: 吸收投资所收到的现金 | U36: 现金的期末余额 | V36: =V35+1 -> 32 | Z36: D20 | AA36: =B36 -> 持有至到期投资
B37: 长期应收款 | C37: 33 | D37: 固定资产 | E37: =IF(D37="",0,CONCATENATE("年初",D37)) -> 年初固定资产 | G37: 租赁负债 | H37: =H36+1 -> 87 | J37: =IF(I37="",0,CONCATENATE("年初",I37)) -> 0 | L37: 二、营业利润（亏损以“－”号填列） | M37: 33 | Q37: 处置子公司及其他营业单位收到的现金净额 | R37: 33 | S37: 取得借款所收到的现金 | U37: 减：现金的期初余额 | V37: =V36+1 -> 33 | W37: 现金的期末余额 | Z37: D21 | AA37: =B37 -> 长期应收款
B38: 设定受益计划净资产 | C38: 34 | D38: 累计折旧 | E38: =IF(D38="",0,CONCATENATE("年初",D38)) -> 年初累计折旧 | G38: 长期应付款 | H38: =H37+1 -> 88 | J38: =IF(I38="",0,CONCATENATE("年初",I38)) -> 0 | L38: 加：营业外收入 | M38: 34 | Q38: 收到其他与投资活动有关的现金 | R38: 34 | S38: 收到的其他与筹资活动有关的现金 | U38: 加：现金等价物的期末余额 | V38: =V37+1 -> 34 | W38: 现金的期初余额 | Z38: D22 | AA38: =B38 -> 设定受益计划净资产
B39: 长期股权投资 | C39: 35 | E39: =IF(D39="",0,CONCATENATE("年初",D39)) -> 0 | G39: 长期应付职工薪酬 | H39: =H38+1 -> 89 | J39: =IF(I39="",0,CONCATENATE("年初",I39)) -> 0 | L39: 减：营业外支出 | M39: 35 | O39: =IF(N39="",0,CONCATENATE("上年",N39)) -> 0 | R39: 35 | U39: 减：现金等价物的期初余额 | V39: =V38+1 -> 35 | W39: 现金等价物的期末余额 | Z39: D23 | AA39: =B39 -> 长期股权投资
B40: 其他权益工具投资 | C40: 36 | D40: 固定资产减值准备 | E40: =IF(D40="",0,CONCATENATE("年初",D40)) -> 年初固定资产减值准备 | G40: 预计负债 | H40: =H39+1 -> 90 | I40: 少数股东权益 | J40: =IF(I40="",0,CONCATENATE("年初",I40)) -> 年初少数股东权益 | L40: 三、利润总额（亏损总额以“－”号填列） | M40: 36 | N40: 营业外支出 | O40: =IF(N40="",0,CONCATENATE("上年",N40)) -> 上年营业外支出 | Q40: 投资活动现金流入小计 | R40: 36 | V40: =V39+1 -> 36 | W40: 现金等价物的期初余额 | Z40: D24 | AA40: =B40 -> 其他权益工具投资
B41: 其他非流动金融资产 | C41: 37 | E41: =IF(D41="",0,CONCATENATE("年初",D41)) -> 0 | G41: 递延收益 | H41: =H40+1 -> 91 | J41: =IF(I41="",0,CONCATENATE("年初",I41)) -> 0 | L41: 减：所得税费用 | M41: 37 | Q41: 购置固定资产、无形资产和其他长期资产所支付现金 | R41: 37 | S41: 偿还债务所支付的现金 | V41: =V40+1 -> 37 | Z41: D25 | AA41: =B41 -> 其他非流动金融资产
B42: 投资性房地产 | C42: 38 | D42: 固定资产清理 | E42: =IF(D42="",0,CONCATENATE("年初",D42)) -> 年初固定资产清理 | G42: 递延所得税负债 | H42: =H41+1 -> 92 | J42: =IF(I42="",0,CONCATENATE("年初",I42)) -> 0 | M42: 38 | Q42: 投资所支付的现金 | R42: 38 | S42: 分配股利、利润和偿付利息所支付的现金 | V42: =V41+1 -> 38 | Z42: D26 | AA42: =B42 -> 投资性房地产
B43: 固定资产 | C43: 39 | D43: 工程物资 | E43: =IF(D43="",0,CONCATENATE("年初",D43)) -> 年初工程物资 | G43: 其他非流动负债 | H43: =H42+1 -> 93 | I43: =IF(说明!E28="股份有限公司","股本",IF(说明!E28="非股份有限公司","实收资本","")) -> 股本 | J43: =IF(I43="",0,CONCATENATE("年初",I43)) -> 年初股本 | L43: 四、净利润（净亏损以“－”号填列） | M43: 39 | Q43: 质押贷款净增加额 | R43: 39 | S43: 支付的其他与筹资活动有关的现金 | V43: =V42+1 -> 39 | Z43: D27 | AA43: =B43 -> 固定资产
B44: 在建工程 | C44: 40 | D44: 在建工程 | E44: =IF(D44="",0,CONCATENATE("年初",D44)) -> 年初在建工程 | G44: 非流动负债合计 | H44: =H43+1 -> 94 | I44: 国家资本 | J44: =IF(I44="",0,CONCATENATE("年初",I44)) -> 年初国家资本 | L44: （一）按经营持续性分类 | M44: 40 | Q44: 取得子公司及其他营业单位支付的现金净额 | R44: 40 | V44: =V43+1 -> 40 | Z44: D28 | AA44: =B44 -> 在建工程
B45: 生产性生物资产 | C45: 41 | D45: 待处理固定资产净损失 | E45: =IF(D45="",0,CONCATENATE("年初",D45)) -> 年初待处理固定资产净损失 | G45: 负 债 合 计 | H45: =H44+1 -> 95 | I45: 集体资本 | J45: =IF(I45="",0,CONCATENATE("年初",I45)) -> 年初集体资本 | L45: 其中：持续经营净利润（净亏损以“-”号填列） | M45: 41 | N45: 其他支出 | O45: =IF(N45="",0,CONCATENATE("上年",N45)) -> 上年其他支出 | Q45: 支付其他与投资活动有关的现金 | R45: 41 | V45: =V44+1 -> 41 | Z45: D29 | AA45: =B45 -> 生产性生物资产
B46: 油气资产 | C46: 42 | G46: =IF(说明!E28="股份有限公司","股东权益：",IF(说明!E28="非股份有限公司","所有者权益：","")) -> 股东权益： | H46: =H45+1 -> 96 | I46: 法人资本 | J46: =IF(I46="",0,CONCATENATE("年初",I46)) -> 年初法人资本 | L46: 终止经营净利润（净亏损以“-”号填列） | M46: 42 | R46: 42 | V46: =V45+1 -> 42 | Z46: D30 | AA46: =B46 -> 油气资产
B47: 使用权资产 | C47: 43 | E47: =IF(D47="",0,CONCATENATE("年初",D47)) -> 0 | G47: =IF(说明!E28="股份有限公司","股本",IF(说明!E28="非股份有限公司","实收资本","")) -> 股本 | H47: =H46+1 -> 97 | I47: 其中：国有法人资本 | L47: （二）按所有权归属分类 | M47: 43 | O47: =IF(N47="",0,CONCATENATE("上年",N47)) -> 0 | Q47: 投资活动现金流出小计 | R47: 43 | V47: =V46+1 -> 43 | Z47: D31 | AA47: =B47 -> 使用权资产
B48: 无形资产 | C48: 44 | E48: =IF(D48="",0,CONCATENATE("年初",D48)) -> 0 | G48: 其他权益工具 | H48: =H47+1 -> 98 | I48: 集体法人资本 | L48: 其中：归属于母公司股东的净利润（净亏损以“-”号填列） | M48: 44 | O48: =IF(N48="",0,CONCATENATE("上年",N48)) -> 0 | Q48: 投资活动产生的现金流量净额 | R48: 44 | V48: =V47+1 -> 44 | Z48: D32 | AA48: =B48 -> 无形资产
B49: 开发支出 | C49: 45 | E49: =IF(D49="",0,CONCATENATE("年初",D49)) -> 0 | G49: 其中：优先股 | H49: =H48+1 -> 99 | I49: 个人资本 | J49: =IF(I49="",0,CONCATENATE("年初",I49)) -> 年初个人资本 | L49: 少数股东损益（净亏损以“-”号填列） | M49: 45 | O49: =IF(N49="",0,CONCATENATE("上年",N49)) -> 0 | Q49: 三、筹资活动产生的现金流量 | R49: 45 | V49: =V48+1 -> 45 | Z49: D33 | AA49: =B49 -> 开发支出
B50: 商誉 | C50: 46 | D50: 无形资产 | E50: =IF(D50="",0,CONCATENATE("年初",D50)) -> 年初无形资产 | G50: 永续债 | H50: =H49+1 -> 100 | I50: 外商资本 | J50: =IF(I50="",0,CONCATENATE("年初",I50)) -> 年初外商资本 | L50: 五、其他综合收益的税后净额 | M50: 46 | N50: 所得税 | O50: =IF(N50="",0,CONCATENATE("上年",N50)) -> 上年所得税 | Q50: 吸收投资所收到的现金 | R50: 46 | S50: 汇率变动对现金的影响额 | U50: 现金及现金等价物净增加额 | V50: =V49+1 -> 46 | Z50: D34 | AA50: =B50 -> 商誉
B51: 长期待摊费用 | C51: 47 | D51: 其中：土地使用权 | G51: 资本公积 | H51: =H50+1 -> 101 | I51: 资本公积 | J51: =IF(I51="",0,CONCATENATE("年初",I51)) -> 年初资本公积 | L51: 归属于母公司股东的其他综合收益的税后净额 | M51: 47 | N51: 少数股东收益 | O51: =IF(N51="",0,CONCATENATE("上年",N51)) -> 上年少数股东收益 | Q51: 其中：子公司吸收少数股东投资收到的现金 | R51: 47 | Z51: D35 | AA51: =B51 -> 长期待摊费用
B52: 递延所得税资产 | C52: 48 | D52: 长期待摊费用 | E52: =IF(D52="",0,CONCATENATE("年初",D52)) -> 年初长期待摊费用 | G52: 减：库存股 | H52: =H51+1 -> 102 | I52: 盈余公积━法定或任意公积 | J52: =IF(I52="",0,CONCATENATE("年初",I52)) -> 年初盈余公积━法定或任意公积 | L52: （一）不能重分类进损益的其他综合收益 | M52: 48 | Q52: 取得借款收到的现金 | R52: 48 | Z52: D36 | AA52: =B52 -> 递延所得税资产
B53: 其他非流动资产 | C53: 49 | D53: 其中：固定资产修理 | G53: 其他综合收益 | H53: =H52+1 -> 103 | I53: 盈余公积━法定公益金 | J53: =IF(I53="",0,CONCATENATE("年初",I53)) -> 年初盈余公积━法定公益金 | L53: 1.重新计量设定受益计划变动额 | M53: 49 | O53: =IF(N53="",0,CONCATENATE("上年",N53)) -> 0 | Q53: 收到的其他与筹资活动有关的现金 | R53: 49 | Z53: D37 | AA53: =B53 -> 其他非流动资产
C54: 50 | D54: 固定资产改良支出 | G54: 专项储备 | H54: =H53+1 -> 104 | I54: 未确认的投资损失 | J54: =IF(I54="",0,CONCATENATE("年初",I54)) -> 年初未确认的投资损失 | L54: 2.权益法下不能转损益的其他综合收益 | M54: 50 | N54: 年初未分配利润 | O54: =IF(N54="",0,CONCATENATE("上年",N54)) -> 上年年初未分配利润 | R54: 50 | Z54: D38 | AA54: =B54 -> 0
C55: 51 | D55: 其他长期资产 | E55: =IF(D55="",0,CONCATENATE("年初",D55)) -> 年初其他长期资产 | G55: 盈余公积 | H55: =H54+1 -> 105 | I55: 未分配利润 | J55: =IF(I55="",0,CONCATENATE("年初",I55)) -> 年初未分配利润 | L55: 3.其他权益工具投资公允价值变动 | M55: 51 | N55: 盈余公积金转入数 | O55: =IF(N55="",0,CONCATENATE("上年",N55)) -> 上年盈余公积金转入数 | Q55: 筹资活动现金流入小计 | R55: 51 | Z55: D39 | AA55: =B55 -> 0
C56: 52 | D56: 其中：特准储备物资 | G56: 一般风险准备 | H56: =H55+1 -> 106 | I56: 其中：现金股利 | L56: 4.企业自身信用风险公允价值变动 | M56: 52 | O56: =IF(N56="",0,CONCATENATE("上年",N56)) -> 0 | Q56: 偿还债务支付的现金 | R56: 52 | Z56: D40 | AA56: =B56 -> 0
B57: 非流动资产合计 | C57: 53 | G57: 未分配利润 | H57: =H56+1 -> 107 | I57: 外币报表折算差额 | J57: =IF(I57="",0,CONCATENATE("年初",I57)) -> 年初外币报表折算差额 | L57: 5.其他 | M57: 53 | O57: =IF(N57="",0,CONCATENATE("上年",N57)) -> 0 | Q57: 分配股利、利润或偿付利息支付的现金 | R57: 53 | AA57: =B57 -> 非流动资产合计
B58: 资 产 总 计 | C58: 54 | E58: =IF(D58="",0,CONCATENATE("年初",D58)) -> 0 | G58: 归属于母公司股东权益合计 | H58: =H57+1 -> 108 | L58: （二）将重分类进损益的其他综合收益 | M58: 54 | N58: 提取法定公积金 | O58: =IF(N58="",0,CONCATENATE("上年",N58)) -> 上年提取法定公积金 | Q58: 其中：子公司支付给少数股东的股利、利润 | R58: 54 | AA58: =B58 -> 资 产 总 计
E59: =IF(D59="",0,CONCATENATE("年初",D59)) -> 0 | G59: 少数股东权益 | H59: =H58+1 -> 109 | L59: 1.权益法下可转损益的其他综合收益 | M59: 55 | N59: 提取法定公益金 | O59: =IF(N59="",0,CONCATENATE("上年",N59)) -> 上年提取法定公益金 | Q59: 支付其他与筹资活动有关的现金 | R59: 55
E60: =IF(D60="",0,CONCATENATE("年初",D60)) -> 0 | G60: =IF(说明!E28="股份有限公司","股东权益合计",IF(说明!E28="非股份有限公司","所有者权益合计","")) -> 股东权益合计 | H60: =H59+1 -> 110 | J60: =IF(I60="",0,CONCATENATE("年初",I60)) -> 0 | L60: 2.其他债权投资公允价值变动 | M60: 56 | N60: 提取职工福利及奖励金 | O60: =IF(N60="",0,CONCATENATE("上年",N60)) -> 上年提取职工福利及奖励金 | R60: 56
D61: 递延税款借项 | E61: =IF(D61="",0,CONCATENATE("年初",D61)) -> 年初递延税款借项 | G61: =IF(说明!E28="股份有限公司","负债和股东权益合计",IF(说明!E28="非股份有限公司","负债和所有者权益合计","")) -> 负债和股东权益合计 | H61: =H60+1 -> 111 | L61: 3.可供出售金融资产公允价值变动损益 | M61: 57 | N61: 提取储备基金 | O61: =IF(N61="",0,CONCATENATE("上年",N61)) -> 上年提取储备基金 | Q61: 筹资活动现金流出小计 | R61: 57 | AA61: =G5 -> 流动负债：
J62: =IF(I62="",0,CONCATENATE("年初",I62)) -> 0 | L62: 4.金融资产重分类计入其他综合收益的金额 | M62: 58 | N62: 提取企业发展基金 | O62: =IF(N62="",0,CONCATENATE("上年",N62)) -> 上年提取企业发展基金 | Q62: 筹资活动产生的现金流量净额 | R62: 58 | Z62: E1 | AA62: =G6 -> 短期借款
L63: 5.持有至到期投资重分类为可供出售金融资产损益 | M63: 59 | N63: 利润归还投资 | O63: =IF(N63="",0,CONCATENATE("上年",N63)) -> 上年利润归还投资 | Q63: 四、汇率变动对现金及现金等价物的影响 | R63: 59 | Z63: E24 | AA63: =G7 -> 向中央银行借款
L64: 6.其他债权投资信用减值准备 | M64: 60 | N64: 补充流动资本 | O64: =IF(N64="",0,CONCATENATE("上年",N64)) -> 上年补充流动资本 | Q64: 五、现金及现金等价物净增加额 | R64: 60 | Z64: E25 | AA64: =G8 -> 吸收存款及同业存放
L65: 7.现金流量套期储备 | M65: 61 | N65: 单项留用的利润 | O65: =IF(N65="",0,CONCATENATE("上年",N65)) -> 上年单项留用的利润 | Q65: 加：期初现金及现金等价物余额 | R65: 61 | Z65: E26 | AA65: =G9 -> 拆入资金
L66: 8.外币财务报表折算差额 | M66: 62 | N66: 其他 | O66: =IF(N66="",0,CONCATENATE("上年",N66)) -> 上年其他 | Q66: 六、期末现金及现金等价物余额 | R66: 62 | Z66: E2 | AA66: =G10 -> 交易性金融负债
L67: 9.自用房地产或作为存货的房地产转换为以公允价值计量的投资性房地产在转换日公允价值大于账面价值部分 | M67: 63 | O67: =IF(N67="",0,CONCATENATE("上年",N67)) -> 0 | Z67: E3 | AA67: =G11 -> 以公允价值计量且其变动计入当期损益的金融负债
L68: 10.多次交易分步处置子公司股权构成一揽子交易的，丧失控制权之前各次交易处置价款与对应净资产账面价值份额的差额 | M68: 64 | N68: 应付优先股股利 | O68: =IF(N68="",0,CONCATENATE("上年",N68)) -> 上年应付优先股股利 | Z68: E4 | AA68: =G12 -> 衍生金融负债
L69: 11.其他 | M69: 65 | N69: 提取任意盈余公积金 | O69: =IF(N69="",0,CONCATENATE("上年",N69)) -> 上年提取任意盈余公积金 | Z69: E5 | AA69: =G13 -> 应付票据
L70: 归属于少数股东的其他综合收益的税后净额 | M70: 66 | N70: 应付普通股股利 | O70: =IF(N70="",0,CONCATENATE("上年",N70)) -> 上年应付普通股股利 | Z70: E6 | AA70: =G14 -> 应付账款
L71: 六、综合收益总额 | M71: 67 | N71: 转作资本的普通股股利 | O71: =IF(N71="",0,CONCATENATE("上年",N71)) -> 上年转作资本的普通股股利 | Z71: E7 | AA71: =G15 -> 预收款项
L72: 归属于母公司股东的综合收益总额 | M72: 68 | N72: 其他 | O72: =IF(N72="",0,CONCATENATE("上年",N72)) -> 上年其他 | Z72: E27 | AA72: =G16 -> 卖出回购金融资产款
E73: =IF(D73="",0,CONCATENATE("年初",D73)) -> 0 | L73: 归属于少数股东的综合收益总额 | M73: 69 | O73: =IF(N73="",0,CONCATENATE("上年",N73)) -> 0 | Z73: E28 | AA73: =G17 -> 应付手续费及佣金
E74: =IF(D74="",0,CONCATENATE("年初",D74)) -> 0 | J74: =IF(I74="",0,CONCATENATE("年初",I74)) -> 0 | L74: 七、每股收益 | M74: 70 | Z74: E8 | AA74: =G18 -> 合同负债
L75: （一）基本每股收益 | M75: 71 | Z75: E9 | AA75: =G19 -> 应付职工薪酬
L76: （二）稀释每股收益 | M76: 72 | Z76: E10 | AA76: =G20 -> 应交税费
L77: 八、利润分配 | M77: 73 | Z77: E11 | AA77: =G21 -> 其他应付款
L78: （一）年初未分配利润 | M78: 74 | AA78: =G22 -> 其中：应付利息
L79: （二）可供分配的利润 | M79: 75 | AA79: =G23 -> 应付股利
L80: 1、提取法定盈余公积 | M80: 76 | Z80: E29 | AA80: =G24 -> 应付分保账款
L81: 2、其他 | M81: 77 | Z81: E30 | AA81: =G25 -> 保险合同准备金
L82: （三）可供投资者分配的利润 | M82: 78 | Z82: E31 | AA82: =G26 -> 代理买卖证券款
L83: 1、应付优先股股利 | M83: 79 | Z83: E32 | AA83: =G27 -> 代理承销证券款
L84: 2、提取任意盈余公积 | M84: 80 | Z84: E12 | AA84: =G28 -> 持有待售负债
L85: 3、应付普通股股利（应付利润） | M85: 81 | Z85: E13 | AA85: =G29 -> 一年内到期的非流动负债
L86: 4、转作资本（或股本）的普通股股利 | M86: 82 | Z86: E14 | AA86: =G30 -> 其他流动负债
L87: 5、其他 | M87: 83 | AA87: =G31 -> 流动负债合计
L88: 九、未分配利润 | M88: 84 | AA88: =G32 -> 非流动负债:
Z89: E15 | AA89: =G33 -> 长期借款
Z90: E16 | AA90: =G34 -> 应付债券
AA91: =G35 -> 其中：优先股
AA92: =G36 -> 永续债
Z93: E17 | AA93: =G37 -> 租赁负债
Z94: E18 | AA94: =G38 -> 长期应付款
Z95: E19 | AA95: =G39 -> 长期应付职工薪酬
Z96: E20 | AA96: =G40 -> 预计负债
Z97: E21 | AA97: =G41 -> 递延收益
Z98: E22 | AA98: =G42 -> 递延所得税负债
Z99: E23 | AA99: =G43 -> 其他非流动负债
AA100: =G44 -> 非流动负债合计
...

Sheet 年初BS审定
A1: 年初资产负债表（审定数）
A2: =CONCATENATE("客户名称：",说明!E23) -> 客户名称：
A3: =CONCATENATE("会计时点：",TEXT(说明!E31+1,"yyyy.mm.dd")) -> 会计时点：2019.01.01
X4: 1 | Y4: 2 | Z4: 3 | AA4: 4 | AB4: 5 | AC4: 6 | AD4: 7 | AE4: 8 | AF4: 9 | AG4: 10 | AI4: XX
A5: =报表格式!B4 -> 报表项目 | B5: 合并审定数 | C5: 合并报表调整 | D5: 合并抵销 | E5: 合并汇总 | F5: 母公司审定数 | G5: 母公司报表调整 | H5: 母公司账项调整 | I5: 母公司汇总抵销 | J5: 母公司汇总 | K5: 母公司本部 | L5: 1分公司 | M5: 2分公司 | N5: 3分公司 | O5: 4分公司 | P5: 5分公司 | Q5: 6分公司 | R5: 7分公司 | S5: 8分公司 | T5: 9分公司 | U5: 10分公司 | W5: XX分公司 | X5: 子公司1 | Y5: 子公司2 | Z5: 子公司3 | AA5: 子公司4 | AB5: 子公司5 | AC5: 子公司6 | AD5: 子公司7 | AE5: 子公司8 | AF5: 子公司9 | AG5: 子公司10 | AI5: 子公司XX
A6: =报表格式!B5 -> 流动资产：
A7: =报表格式!B6 -> 货币资金 | B7: =SUM(C7:E7) -> 0 | E7: =SUM(F7,X7:AI7) -> 0 | F7: =SUM(G7:J7) -> 0 | J7: =SUM(K7:W7) -> 0
A8: =报表格式!B7 -> 结算备付金 | B8: =SUM(C8:E8) -> 0 | E8: =SUM(F8,X8:AI8) -> 0 | F8: =SUM(G8:J8) -> 0 | J8: =SUM(K8:W8) -> 0
A9: =报表格式!B8 -> 拆出资金 | B9: =SUM(C9:E9) -> 0 | E9: =SUM(F9,X9:AI9) -> 0 | F9: =SUM(G9:J9) -> 0 | J9: =SUM(K9:W9) -> 0
A10: =报表格式!B9 -> 交易性金融资产 | B10: =SUM(C10:E10) -> 0 | E10: =SUM(F10,X10:AI10) -> 0 | F10: =SUM(G10:J10) -> 0 | J10: =SUM(K10:W10) -> 0
A11: =报表格式!B10 -> 以公允价值计量且其变动计入当期损益的金融资产 | B11: =SUM(C11:E11) -> 0 | E11: =SUM(F11,X11:AI11) -> 0 | F11: =SUM(G11:J11) -> 0 | J11: =SUM(K11:W11) -> 0
A12: =报表格式!B11 -> 衍生金融资产 | B12: =SUM(C12:E12) -> 0 | E12: =SUM(F12,X12:AI12) -> 0 | F12: =SUM(G12:J12) -> 0 | J12: =SUM(K12:W12) -> 0
A13: =报表格式!B12 -> 应收票据 | B13: =SUM(C13:E13) -> 0 | E13: =SUM(F13,X13:AI13) -> 0 | F13: =SUM(G13:J13) -> 0 | J13: =SUM(K13:W13) -> 0
A14: =报表格式!B13 -> 应收账款 | B14: =SUM(C14:E14) -> 0 | E14: =SUM(F14,X14:AI14) -> 0 | F14: =SUM(G14:J14) -> 0 | J14: =SUM(K14:W14) -> 0
A15: =报表格式!B14 -> 应收款项融资 | B15: =SUM(C15:E15) -> 0 | E15: =SUM(F15,X15:AI15) -> 0 | F15: =SUM(G15:J15) -> 0 | J15: =SUM(K15:W15) -> 0
A16: =报表格式!B15 -> 预付款项 | B16: =SUM(C16:E16) -> 0 | E16: =SUM(F16,X16:AI16) -> 0 | F16: =SUM(G16:J16) -> 0 | J16: =SUM(K16:W16) -> 0
A17: =报表格式!B16 -> 应收保费 | B17: =SUM(C17:E17) -> 0 | E17: =SUM(F17,X17:AI17) -> 0 | F17: =SUM(G17:J17) -> 0 | J17: =SUM(K17:W17) -> 0
A18: =报表格式!B17 -> 应收分保账款 | B18: =SUM(C18:E18) -> 0 | E18: =SUM(F18,X18:AI18) -> 0 | F18: =SUM(G18:J18) -> 0 | J18: =SUM(K18:W18) -> 0
... A30: =报表格式!B29 -> 0 | B30: =SUM(C30:E30) -> 0 | E30: =SUM(F30,X30:AI30) -> 0 | F30: =SUM(G30:J30) -> 0 | J30: =SUM(K30:W30) -> 0
A31: =报表格式!B30 -> 流动资产合计 | B31: =SUM(C31:E31) -> 0 | C31: =SUM(C7:C30)-C21-C22 -> 0 | D31: =SUM(D7:D30)-D21-D22 -> 0 | E31: =SUM(F31,X31:AI31) -> 0 | F31: =SUM(G31:J31) -> 0 | G31: =SUM(G7:G30)-G21-G22 -> 0 | H31: =SUM(H7:H30)-H21-H22 -> 0 | I31: =SUM(I7:I30)-I21-I22 -> 0 | J31: =SUM(K31:W31) -> 0 | K31: =SUM(K7:K30)-K21-K22 -> 0 | L31: =SUM(L7:L30)-L21-L22 -> 0 | M31: =SUM(M7:M30)-M21-M22 -> 0 | N31: =SUM(N7:N30)-N21-N22 -> 0 | O31: =SUM(O7:O30)-O21-O22 -> 0 | P31: =SUM(P7:P30)-P21-P22 -> 0 | Q31: =SUM(Q7:Q30)-Q21-Q22 -> 0 | R31: =SUM(R7:R30)-R21-R22 -> 0 | ... AI31: =SUM(AI7:AI30)-AI21-AI22 -> 0
A32: =报表格式!B31 -> 非流动资产:
A33: =报表格式!B32 -> 发放贷款及垫款 | B33: =SUM(C33:E33) -> 0 | E33: =SUM(F33,X33:AI33) -> 0 | F33: =SUM(G33:J33) -> 0 | J33: =SUM(K33:W33) -> 0
A34: =报表格式!B33 -> 债权投资 | B34: =SUM(C34:E34) -> 0 | E34: =SUM(F34,X34:AI34) -> 0 | F34: =SUM(G34:J34) -> 0 | J34: =SUM(K34:W34) -> 0
A35: =报表格式!B34 -> 可供出售金融资产 | B35: =SUM(C35:E35) -> 0 | E35: =SUM(F35,X35:AI35) -> 0 | F35: =SUM(G35:J35) -> 0 | J35: =SUM(K35:W35) -> 0
A36: =报表格式!B35 -> 其他债权投资 | B36: =SUM(C36:E36) -> 0 | E36: =SUM(F36,X36:AI36) -> 0 | F36: =SUM(G36:J36) -> 0 | J36: =SUM(K36:W36) -> 0
A37: =报表格式!B36 -> 持有至到期投资 | B37: =SUM(C37:E37) -> 0 | E37: =SUM(F37,X37:AI37) -> 0 | F37: =SUM(G37:J37) -> 0 | J37: =SUM(K37:W37) -> 0
A38: =报表格式!B37 -> 长期应收款 | B38: =SUM(C38:E38) -> 0 | E38: =SUM(F38,X38:AI38) -> 0 | F38: =SUM(G38:J38) -> 0 | J38: =SUM(K38:W38) -> 0
A39: =报表格式!B38 -> 设定受益计划净资产 | B39: =SUM(C39:E39) -> 0 | E39: =SUM(F39,X39:AI39) -> 0 | F39: =SUM(G39:J39) -> 0 | J39: =SUM(K39:W39) -> 0
A40: =报表格式!B39 -> 长期股权投资 | B40: =SUM(C40:E40) -> 0 | E40: =SUM(F40,X40:AI40) -> 0 | F40: =SUM(G40:J40) -> 0 | J40: =SUM(K40:W40) -> 0
A41: =报表格式!B40 -> 其他权益工具投资 | B41: =SUM(C41:E41) -> 0 | E41: =SUM(F41,X41:AI41) -> 0 | F41: =SUM(G41:J41) -> 0 | J41: =SUM(K41:W41) -> 0
A42: =报表格式!B41 -> 其他非流动金融资产 | B42: =SUM(C42:E42) -> 0 | E42: =SUM(F42,X42:AI42) -> 0 | F42: =SUM(G42:J42) -> 0 | J42: =SUM(K42:W42) -> 0
A43: =报表格式!B42 -> 投资性房地产 | B43: =SUM(C43:E43) -> 0 | E43: =SUM(F43,X43:AI43) -> 0 | F43: =SUM(G43:J43) -> 0 | J43: =SUM(K43:W43) -> 0
A44: =报表格式!B43 -> 固定资产 | B44: =SUM(C44:E44) -> 0 | E44: =SUM(F44,X44:AI44) -> 0 | F44: =SUM(G44:J44) -> 0 | J44: =SUM(K44:W44) -> 0
... A57: =报表格式!B56 -> 0 | B57: =SUM(C57:E57) -> 0 | E57: =SUM(F57,X57:AI57) -> 0 | F57: =SUM(G57:J57) -> 0 | J57: =SUM(K57:W57) -> 0
A58: =报表格式!B57 -> 非流动资产合计 | B58: =SUM(C58:E58) -> 0 | C58: =SUM(C33:C57) -> 0 | D58: =SUM(D33:D57) -> 0 | E58: =SUM(F58,X58:AI58) -> 0 | F58: =SUM(F33:F57) -> 0 | G58: =SUM(G33:G57) -> 0 | H58: =SUM(H33:H57) -> 0 | I58: =SUM(I33:I57) -> 0 | J58: =SUM(J33:J57) -> 0 | K58: =SUM(K33:K57) -> 0 | L58: =SUM(L33:L57) -> 0 | M58: =SUM(M33:M57) -> 0 | ... AI58: =SUM(AI33:AI57) -> 0
A59: =报表格式!B58 -> 资 产 总 计 | B59: =SUM(C59:E59) -> 0 | C59: =SUM(C31,C58) -> 0 | D59: =SUM(D31,D58) -> 0 | E59: =SUM(E31,E58) -> 0 | F59: =SUM(F31,F58) -> 0 | G59: =SUM(G31,G58) -> 0 | H59: =SUM(H31,H58) -> 0 | I59: =SUM(I31,I58) -> 0 | J59: =SUM(J31,J58) -> 0 | ... AI59: =SUM(AI31,AI58) -> 0
J60: =SUM(K60:W60) -> 0
A61: =报表格式!G5 -> 流动负债：
A62: =报表格式!G6 -> 短期借款 | B62: =SUM(C62:E62) -> 0 | E62: =SUM(F62,X62:AI62) -> 0 | F62: =SUM(G62:J62) -> 0 | J62: =SUM(K62:W62) -> 0
A63: =报表格式!G7 -> 向中央银行借款 | B63: =SUM(C63:E63) -> 0 | E63: =SUM(F63,X63:AI63) -> 0 | F63: =SUM(G63:J63) -> 0 | J63: =SUM(K63:W63) -> 0
A64: =报表格式!G8 -> 吸收存款及同业存放 | B64: =SUM(C64:E64) -> 0 | E64: =SUM(F64,X64:AI64) -> 0 | F64: =SUM(G64:J64) -> 0 | J64: =SUM(K64:W64) -> 0
A65: =报表格式!G9 -> 拆入资金 | B65: =SUM(C65:E65) -> 0 | E65: =SUM(F65,X65:AI65) -> 0 | F65: =SUM(G65:J65) -> 0 | J65: =SUM(K65:W65) -> 0
A66: =报表格式!G10 -> 交易性金融负债 | B66: =SUM(C66:E66) -> 0 | E66: =SUM(F66,X66:AI66) -> 0 | F66: =SUM(G66:J66) -> 0 | J66: =SUM(K66:W66) -> 0
A67: =报表格式!G11 -> 以公允价值计量且其变动计入当期损益的金融负债 | B67: =SUM(C67:E67) -> 0 | E67: =SUM(F67,X67:AI67) -> 0 | F67: =SUM(G67:J67) -> 0 | J67: =SUM(K67:W67) -> 0
A68: =报表格式!G12 -> 衍生金融负债 | B68: =SUM(C68:E68) -> 0 | E68: =SUM(F68,X68:AI68) -> 0 | F68: =SUM(G68:J68) -> 0 | J68: =SUM(K68:W68) -> 0
A69: =报表格式!G13 -> 应付票据 | B69: =SUM(C69:E69) -> 0 | E69: =SUM(F69,X69:AI69) -> 0 | F69: =SUM(G69:J69) -> 0 | J69: =SUM(K69:W69) -> 0
A70: =报表格式!G14 -> 应付账款 | B70: =SUM(C70:E70) -> 0 | E70: =SUM(F70,X70:AI70) -> 0 | F70: =SUM(G70:J70) -> 0 | J70: =SUM(K70:W70) -> 0
A71: =报表格式!G15 -> 预收款项 | B71: =SUM(C71:E71) -> 0 | E71: =SUM(F71,X71:AI71) -> 0 | F71: =SUM(G71:J71) -> 0 | J71: =SUM(K71:W71) -> 0
A72: =报表格式!G16 -> 卖出回购金融资产款 | B72: =SUM(C72:E72) -> 0 | E72: =SUM(F72,X72:AI72) -> 0 | F72: =SUM(G72:J72) -> 0 | J72: =SUM(K72:W72) -> 0
A73: =报表格式!G17 -> 应付手续费及佣金 | B73: =SUM(C73:E73) -> 0 | E73: =SUM(F73,X73:AI73) -> 0 | F73: =SUM(G73:J73) -> 0 | J73: =SUM(K73:W73) -> 0
... A86: =报表格式!G30 -> 其他流动负债 | B86: =SUM(C86:E86) -> 0 | E86: =SUM(F86,X86:AI86) -> 0 | F86: =SUM(G86:J86) -> 0 | J86: =SUM(K86:W86) -> 0
A87: =报表格式!G31 -> 流动负债合计 | B87: =SUM(C87:E87) -> 0 | C87: =SUM(C62:C86)-C78-C79 -> 0 | D87: =SUM(D62:D86)-D78-D79 -> 0 | E87: =SUM(E62:E86)-E78-E79 -> 0 | F87: =SUM(F62:F86)-F78-F79 -> 0 | G87: =SUM(G62:G86)-G78-G79 -> 0 | H87: =SUM(H62:H86)-H78-H79 -> 0 | I87: =SUM(I62:I86)-I78-I79 -> 0 | J87: =SUM(J62:J86)-J78-J79 -> 0 | ... AI87: =SUM(AI62:AI86)-AI78-AI79 -> 0
A88: =报表格式!G32 -> 非流动负债:
A89: =报表格式!G33 -> 长期借款 | B89: =SUM(C89:E89) -> 0 | E89: =SUM(F89,X89:AI89) -> 0 | F89: =SUM(G89:J89) -> 0 | J89: =SUM(K89:W89) -> 0
A90: =报表格式!G34 -> 应付债券 | B90: =SUM(C90:E90) -> 0 | E90: =SUM(F90,X90:AI90) -> 0 | F90: =SUM(G90:J90) -> 0 | J90: =SUM(K90:W90) -> 0
A91: =报表格式!G35 -> 其中：优先股 | B91: =SUM(C91:E91) -> 0 | E91: =SUM(F91,X91:AI91) -> 0 | F91: =SUM(G91:J91) -> 0 | J91: =SUM(K91:W91) -> 0
A92: =报表格式!G36 -> 永续债 | B92: =SUM(C92:E92) -> 0 | E92: =SUM(F92,X92:AI92) -> 0 | F92: =SUM(G92:J92) -> 0 | J92: =SUM(K92:W92) -> 0
A93: =报表格式!G37 -> 租赁负债 | B93: =SUM(C93:E93) -> 0 | E93: =SUM(F93,X93:AI93) -> 0 | F93: =SUM(G93:J93) -> 0 | J93: =SUM(K93:W93) -> 0
A94: =报表格式!G38 -> 长期应付款 | B94: =SUM(C94:E94) -> 0 | E94: =SUM(F94,X94:AI94) -> 0 | F94: =SUM(G94:J94) -> 0 | J94: =SUM(K94:W94) -> 0
A95: =报表格式!G39 -> 长期应付职工薪酬 | B95: =SUM(C95:E95) -> 0 | E95: =SUM(F95,X95:AI95) -> 0 | F95: =SUM(G95:J95) -> 0 | J95: =SUM(K95:W95) -> 0
A96: =报表格式!G40 -> 预计负债 | B96: =SUM(C96:E96) -> 0 | E96: =SUM(F96,X96:AI96) -> 0 | F96: =SUM(G96:J96) -> 0 | J96: =SUM(K96:W96) -> 0
A97: =报表格式!G41 -> 递延收益 | B97: =SUM(C97:E97) -> 0 | E97: =SUM(F97,X97:AI97) -> 0 | F97: =SUM(G97:J97) -> 0 | J97: =SUM(K97:W97) -> 0
A98: =报表格式!G42 -> 递延所得税负债 | B98: =SUM(C98:E98) -> 0 | E98: =SUM(F98,X98:AI98) -> 0 | F98: =SUM(G98:J98) -> 0 | J98: =SUM(K98:W98) -> 0
A99: =报表格式!G43 -> 其他非流动负债 | B99: =SUM(C99:E99) -> 0 | E99: =SUM(F99,X99:AI99) -> 0 | F99: =SUM(G99:J99) -> 0 | J99: =SUM(K99:W99) -> 0
A100: =报表格式!G44 -> 非流动负债合计 | B100: =SUM(C100:E100) -> 0 | C100: =SUM(C89:C99)-C91-C92 -> 0 | D100: =SUM(D89:D99)-D91-D92 -> 0 | E100: =SUM(E89:E99)-E91-E92 -> 0 | F100: =SUM(F89:F99)-F91-F92 -> 0 | G100: =SUM(G89:G99)-G91-G92 -> 0 | H100: =SUM(H89:H99)-H91-H92 -> 0 | I100: =SUM(I89:I99)-I91-I92 -> 0 | J100: =SUM(J89:J99)-J91-J92 -> 0 | ... AI100: =SUM(AI89:AI99)-AI91-AI92 -> 0
A101: =报表格式!G45 -> 负 债 合 计 | B101: =SUM(C101:E101) -> 0 | C101: =SUM(C87,C100) -> 0 | D101: =SUM(D87,D100) -> 0 | E101: =SUM(E87,E100) -> 0 | F101: =SUM(F87,F100) -> 0 | G101: =SUM(G87,G100) -> 0 | H101: =SUM(H87,H100) -> 0 | I101: =SUM(I87,I100) -> 0 | J101: =SUM(J87,J100) -> 0 | ... AI101: =SUM(AI87,AI100) -> 0
A102: =报表格式!G46 -> 股东权益：
A103: =报表格式!G47 -> 股本 | B103: =SUM(C103:E103) -> 0 | E103: =SUM(F103,X103:AI103) -> 0 | F103: =SUM(G103:J103) -> 0 | J103: =SUM(K103:W103) -> 0
A104: =报表格式!G48 -> 其他权益工具 | B104: =SUM(C104:E104) -> 0 | E104: =SUM(F104,X104:AI104) -> 0 | F104: =SUM(G104:J104) -> 0 | J104: =SUM(K104:W104) -> 0
A105: =报表格式!G49 -> 其中：优先股 | B105: =SUM(C105:E105) -> 0 | E105: =SUM(F105,X105:AI105) -> 0 | F105: =SUM(G105:J105) -> 0 | J105: =SUM(K105:W105) -> 0
A106: =报表格式!G50 -> 永续债 | B106: =SUM(C106:E106) -> 0 | E106: =SUM(F106,X106:AI106) -> 0 | F106: =SUM(G106:J106) -> 0 | J106: =SUM(K106:W106) -> 0
A107: =报表格式!G51 -> 资本公积 | B107: =SUM(C107:E107) -> 0 | E107: =SUM(F107,X107:AI107) -> 0 | F107: =SUM(G107:J107) -> 0 | J107: =SUM(K107:W107) -> 0
A108: =报表格式!G52 -> 减：库存股 | B108: =SUM(C108:E108) -> 0 | E108: =SUM(F108,X108:AI108) -> 0 | F108: =SUM(G108:J108) -> 0 | J108: =SUM(K108:W108) -> 0
A109: =报表格式!G53 -> 其他综合收益 | B109: =SUM(C109:E109) -> 0 | E109: =SUM(F109,X109:AI109) -> 0 | F109: =SUM(G109:J109) -> 0 | J109: =SUM(K109:W109) -> 0
A110: =报表格式!G54 -> 专项储备 | B110: =SUM(C110:E110) -> 0 | E110: =SUM(F110,X110:AI110) -> 0 | F110: =SUM(G110:J110) -> 0 | J110: =SUM(K110:W110) -> 0
A111: =报表格式!G55 -> 盈余公积 | B111: =SUM(C111:E111) -> 0 | E111: =SUM(F111,X111:AI111) -> 0 | F111: =SUM(G111:J111) -> 0 | J111: =SUM(K111:W111) -> 0
A112: =报表格式!G56 -> 一般风险准备 | B112: =SUM(C112:E112) -> 0 | E112: =SUM(F112,X112:AI112) -> 0 | F112: =SUM(G112:J112) -> 0 | J112: =SUM(K112:W112) -> 0
A113: =报表格式!G57 -> 未分配利润 | B113: =SUM(C113:E113) -> 0 | E113: =SUM(F113,X113:AI113) -> 0 | F113: =SUM(G113:J113) -> 0 | J113: =SUM(K113:W113) -> 0
A114: =报表格式!G58 -> 归属于母公司股东权益合计 | B114: =SUM(C114:E114) -> 0 | C114: =SUM(C103:C104,C107,-C108,C109:C113) -> 0 | D114: =SUM(D103:D104,D107,-D108,D109:D113) -> 0 | E114: =SUM(E103:E104,E107,-E108,E109:E113) -> 0 | F114: =SUM(F103:F104,F107,-F108,F109:F113) -> 0 | G114: =SUM(G103:G104,G107,-G108,G109:G113) -> 0 | H114: =SUM(H103:H104,H107,-H108,H109:H113) -> 0 | I114: =SUM(I103:I104,I107,-I108,I109:I113) -> 0 | J114: =SUM(J103:J104,J107,-J108,J109:J113) -> 0 | ... AI114: =SUM(AI103:AI104,AI107,-AI108,AI109:AI113) -> 0
A115: =报表格式!G59 -> 少数股东权益 | B115: =SUM(C115:E115) -> 0 | E115: =SUM(F115,X115:AI115) -> 0 | F115: =SUM(G115:J115) -> 0 | J115: =SUM(K115:W115) -> 0
A116: =报表格式!G60 -> 股东权益合计 | B116: =SUM(C116:E116) -> 0 | C116: =SUM(C114:C115) -> 0 | D116: =SUM(D114:D115) -> 0 | E116: =SUM(E114:E115) -> 0 | F116: =SUM(F114:F115) -> 0 | G116: =SUM(G114:G115) -> 0 | H116: =SUM(H114:H115) -> 0 | I116: =SUM(I114:I115) -> 0 | J116: =SUM(J114:J115) -> 0 | ... AI116: =SUM(AI114:AI115) -> 0
A117: =报表格式!G61 -> 负债和股东权益合计 | B117: =SUM(C117:E117) -> 0 | C117: =SUM(C101,C116) -> 0 | D117: =SUM(D101,D116) -> 0 | E117: =SUM(E101,E116) -> 0 | F117: =SUM(F101,F116) -> 0 | G117: =SUM(G101,G116) -> 0 | H117: =SUM(H101,H116) -> 0 | I117: =SUM(I101,I116) -> 0 | J117: =SUM(J101,J116) -> 0 | ... AI117: =SUM(AI101,AI116) -> 0
A120: 勾稽核对：
A121: 资产负债平衡 | B121: =B59-B117 -> 0 | C121: =C59-C117 -> 0 | D121: =D59-D117 -> 0 | E121: =E59-E117 -> 0 | F121: =F59-F117 -> 0 | G121: =G59-G117 -> 0 | H121: =H59-H117 -> 0 | I121: =I59-I117 -> 0 | ... AI121: =AI59-AI117 -> 0
A122: 检验流动资产公式 | B122: =SUM(B7:B30)-B21-B22-B31 -> 0 | C122: =SUM(C7:C30)-C21-C22-C31 -> 0 | D122: =SUM(D7:D30)-D21-D22-D31 -> 0 | E122: =SUM(E7:E30)-E21-E22-E31 -> 0 | F122: =SUM(F7:F30)-F21-F22-F31 -> 0 | G122: =SUM(G7:G30)-G21-G22-G31 -> 0 | H122: =SUM(H7:H30)-H21-H22-H31 -> 0 | I122: =SUM(I7:I30)-I21-I22-I31 -> 0 | ... AI122: =SUM(AI7:AI30)-AI21-AI22-AI31 -> 0
A123: 检验非流动资产公式 | B123: =SUM(B33:B57)-B58 -> 0 | C123: =SUM(C33:C57)-C58 -> 0 | D123: =SUM(D33:D57)-D58 -> 0 | E123: =SUM(E33:E57)-E58 -> 0 | F123: =SUM(F33:F57)-F58 -> 0 | G123: =SUM(G33:G57)-G58 -> 0 | H123: =SUM(H33:H57)-H58 -> 0 | I123: =SUM(I33:I57)-I58 -> 0 | ... AI123: =SUM(AI33:AI57)-AI58 -> 0
A124: 检验总资产公式 | B124: =B31+B58-B59 -> 0 | C124: =C31+C58-C59 -> 0 | D124: =D31+D58-D59 -> 0 | E124: =E31+E58-E59 -> 0 | F124: =F31+F58-F59 -> 0 | G124: =G31+G58-G59 -> 0 | H124: =H31+H58-H59 -> 0 | I124: =I31+I58-I59 -> 0 | ... AI124: =AI31+AI58-AI59 -> 0
A125: 检验流动负债公式 | B125: =SUM(B62:B86)-B78-B79-B87 -> 0 | C125: =SUM(C62:C86)-C78-C79-C87 -> 0 | D125: =SUM(D62:D86)-D78-D79-D87 -> 0 | E125: =SUM(E62:E86)-E78-E79-E87 -> 0 | F125: =SUM(F62:F86)-F78-F79-F87 -> 0 | G125: =SUM(G62:G86)-G78-G79-G87 -> 0 | H125: =SUM(H62:H86)-H78-H79-H87 -> 0 | I125: =SUM(I62:I86)-I78-I79-I87 -> 0 | ... AI125: =SUM(AI62:AI86)-AI78-AI79-AI87 -> 0
A126: 检验非流动负债公式 | B126: =SUM(B89:B99)-B91-B92-B100 -> 0 | C126: =SUM(C89:C99)-C91-C92-C100 -> 0 | D126: =SUM(D89:D99)-D91-D92-D100 -> 0 | E126: =SUM(E89:E99)-E91-E92-E100 -> 0 | F126: =SUM(F89:F99)-F91-F92-F100 -> 0 | G126: =SUM(G89:G99)-G91-G92-G100 -> 0 | H126: =SUM(H89:H99)-H91-H92-H100 -> 0 | I126: =SUM(I89:I99)-I91-I92-I100 -> 0 | ... AI126: =SUM(AI89:AI99)-AI91-AI92-AI100 -> 0
A127: 检验总负债公式 | B127: =B87+B100-B101 -> 0 | C127: =C87+C100-C101 -> 0 | D127: =D87+D100-D101 -> 0 | E127: =E87+E100-E101 -> 0 | F127: =F87+F100-F101 -> 0 | G127: =G87+G100-G101 -> 0 | H127: =H87+H100-H101 -> 0 | I127: =I87+I100-I101 -> 0 | ... AI127: =AI87+AI100-AI101 -> 0
A128: 检验归属于母公司股东权益公式 | B128: =SUM(B103:B104,B107,-B108,B109:B113)-B114 -> 0 | C128: =SUM(C103:C104,C107,-C108,C109:C113)-C114 -> 0 | D128: =SUM(D103:D104,D107,-D108,D109:D113)-D114 -> 0 | E128: =SUM(E103:E104,E107,-E108,E109:E113)-E114 -> 0 | F128: =SUM(F103:F104,F107,-F108,F109:F113)-F114 -> 0 | G128: =SUM(G103:G104,G107,-G108,G109:G113)-G114 -> 0 | H128: =SUM(H103:H104,H107,-H108,H109:H113)-H114 -> 0 | I128: =SUM(I103:I104,I107,-I108,I109:I113)-I114 -> 0 | ... AI128: =SUM(AI103:AI104,AI107,-AI108,AI109:AI113)-AI114 -> 0
A129: 检验股东权益公式 | B129: =B114+B115-B116 -> 0 | C129: =C114+C115-C116 -> 0 | D129: =D114+D115-D116 -> 0 | E129: =E114+E115-E116 -> 0 | F129: =F114+F115-F116 -> 0 | G129: =G114+G115-G116 -> 0 | H129: =H114+H115-H116 -> 0 | I129: =I114+I115-I116 -> 0 | ... AI129: =AI114+AI115-AI116 -> 0
A130: 检验负债权益公式 | B130: =B101+B116-B117 -> 0 | C130: =C101+C116-C117 -> 0 | D130: =D101+D116-D117 -> 0 | E130: =E101+E116-E117 -> 0 | F130: =F101+F116-F117 -> 0 | G130: =G101+G116-G117 -> 0 | H130: =H101+H116-H117 -> 0 | I130: =I101+I116-I117 -> 0 | ... AI130: =AI101+AI116-AI117 -> 0

Sheet 上年PL审定
A1: 上年利润及利润分配表（审定数）
A2: =CONCATENATE("客户名称：",说明!E23) -> 客户名称：
A3: =CONCATENATE("会计期间：",说明!E29) -> 会计期间：2018年度
X4: 1 | Y4: 2 | Z4: 3 | AA4: 4 | AB4: 5 | AC4: 6 | AD4: 7 | AE4: 8 | AF4: 9 | AG4: 10 | AI4: XX
A5: =报表格式!L4 -> 报表项目 | B5: 合并审定数 | C5: 合并报表调整 | D5: 合并抵销 | E5: 合并汇总 | F5: 母公司审定数 | G5: 母公司报表调整 | H5: 母公司账项调整 | I5: 母公司汇总抵销 | J5: 母公司汇总 | K5: 母公司本部 | L5: 1分公司 | M5: 2分公司 | N5: 3分公司 | O5: 4分公司 | P5: 5分公司 | Q5: 6分公司 | R5: 7分公司 | S5: 8分公司 | T5: 9分公司 | U5: 10分公司 | W5: XX分公司 | X5: 子公司1 | Y5: 子公司2 | Z5: 子公司3 | AA5: 子公司4 | AB5: 子公司5 | AC5: 子公司6 | AD5: 子公司7 | AE5: 子公司8 | AF5: 子公司9 | AG5: 子公司10 | AI5: 子公司XX
A6: =报表格式!L5 -> 一、营业收入 | B6: =SUM(C6:E6) -> 0 | E6: =SUM(F6,X6:AI6) -> 0 | F6: =SUM(G6:J6) -> 0 | J6: =SUM(K6:W6) -> 0
A7: =报表格式!L6 -> 其中：主营业务收入 | B7: =SUM(C7:E7) -> 0 | E7: =SUM(F7,X7:AI7) -> 0 | F7: =SUM(G7:J7) -> 0 | J7: =SUM(K7:W7) -> 0
A8: =报表格式!L7 -> 利息收入 | B8: =SUM(C8:E8) -> 0 | E8: =SUM(F8,X8:AI8) -> 0 | F8: =SUM(G8:J8) -> 0 | J8: =SUM(K8:W8) -> 0
A9: =报表格式!L8 -> 已赚保费 | B9: =SUM(C9:E9) -> 0 | E9: =SUM(F9,X9:AI9) -> 0 | F9: =SUM(G9:J9) -> 0 | J9: =SUM(K9:W9) -> 0
A10: =报表格式!L9 -> 手续费及佣金收入 | B10: =SUM(C10:E10) -> 0 | E10: =SUM(F10,X10:AI10) -> 0 | F10: =SUM(G10:J10) -> 0 | J10: =SUM(K10:W10) -> 0
A11: =报表格式!L10 -> 其他业务收入 | B11: =SUM(C11:E11) -> 0 | E11: =SUM(F11,X11:AI11) -> 0 | F11: =SUM(G11:J11) -> 0 | J11: =SUM(K11:W11) -> 0
A12: =报表格式!L11 -> 减：营业成本 | B12: =SUM(C12:E12) -> 0 | E12: =SUM(F12,X12:AI12) -> 0 | F12: =SUM(G12:J12) -> 0 | J12: =SUM(K12:W12) -> 0
A13: =报表格式!L12 -> 其中：主营业务成本 | B13: =SUM(C13:E13) -> 0 | E13: =SUM(F13,X13:AI13) -> 0 | F13: =SUM(G13:J13) -> 0 | J13: =SUM(K13:W13) -> 0
A14: =报表格式!L13 -> 利息支出 | B14: =SUM(C14:E14) -> 0 | E14: =SUM(F14,X14:AI14) -> 0 | F14: =SUM(G14:J14) -> 0 | J14: =SUM(K14:W14) -> 0
A15: =报表格式!L14 -> 手续费及佣金支出 | B15: =SUM(C15:E15) -> 0 | E15: =SUM(F15,X15:AI15) -> 0 | F15: =SUM(G15:J15) -> 0 | J15: =SUM(K15:W15) -> 0
A16: =报表格式!L15 -> 退保金 | B16: =SUM(C16:E16) -> 0 | E16: =SUM(F16,X16:AI16) -> 0 | F16: =SUM(G16:J16) -> 0 | J16: =SUM(K16:W16) -> 0
A17: =报表格式!L16 -> 赔付支出净额 | B17: =SUM(C17:E17) -> 0 | E17: =SUM(F17,X17:AI17) -> 0 | F17: =SUM(G17:J17) -> 0 | J17: =SUM(K17:W17) -> 0
... A37: =报表格式!L36 -> 资产处置收益(损失以“-”号填列） | B37: =SUM(C37:E37) -> 0 | E37: =SUM(F37,X37:AI37) -> 0 | F37: =SUM(G37:J37) -> 0 | J37: =SUM(K37:W37) -> 0
A38: =报表格式!L37 -> 二、营业利润（亏损以“－”号填列） | B38: =SUM(C38:E38) -> 0 | C38: =SUM(C6)-SUM(C12,C22:C26)+SUM(C29,C30)+SUM(C33:C37) -> 0 | D38: =SUM(D6)-SUM(D12,D22:D26)+SUM(D29,D30)+SUM(D33:D37) -> 0 | E38: =SUM(F38,X38:AI38) -> 0 | F38: =SUM(F6)-SUM(F12,F22:F26)+SUM(F29,F30)+SUM(F33:F37) -> 0 | G38: =SUM(G6)-SUM(G12,G22:G26)+SUM(G29,G30)+SUM(G33:G37) -> 0 | H38: =SUM(H6)-SUM(H12,H22:H26)+SUM(H29,H30)+SUM(H33:H37) -> 0 | I38: =SUM(I6)-SUM(I12,I22:I26)+SUM(I29,I30)+SUM(I33:I37) -> 0 | J38: =SUM(J6)-SUM(J12,J22:J26)+SUM(J29,J30)+SUM(J33:J37) -> 0 | K38: =SUM(K6)-SUM(K12,K22:K26)+SUM(K29,K30)+SUM(K33:K37) -> 0 | L38: =SUM(L6)-SUM(L12,L22:L26)+SUM(L29,L30)+SUM(L33:L37) -> 0 | M38: =SUM(M6)-SUM(M12,M22:M26)+SUM(M29,M30)+SUM(M33:M37) -> 0 | ... AI38: =SUM(AI6)-SUM(AI12,AI22:AI26)+SUM(AI29,AI30)+SUM(AI33:AI37) -> 0
A39: =报表格式!L38 -> 加：营业外收入 | B39: =SUM(C39:E39) -> 0 | E39: =SUM(F39,X39:AI39) -> 0 | F39: =SUM(G39:J39) -> 0 | J39: =SUM(K39:W39) -> 0
A40: =报表格式!L39 -> 减：营业外支出 | B40: =SUM(C40:E40) -> 0 | E40: =SUM(F40,X40:AI40) -> 0 | F40: =SUM(G40:J40) -> 0 | J40: =SUM(K40:W40) -> 0
A41: =报表格式!L40 -> 三、利润总额（亏损总额以“－”号填列） | B41: =SUM(C41:E41) -> 0 | C41: =SUM(C38)+SUM(C39)-SUM(C40) -> 0 | D41: =SUM(D38)+SUM(D39)-SUM(D40) -> 0 | E41: =SUM(F41,X41:AI41) -> 0 | F41: =SUM(F38)+SUM(F39)-SUM(F40) -> 0 | G41: =SUM(G38)+SUM(G39)-SUM(G40) -> 0 | H41: =SUM(H38)+SUM(H39)-SUM(H40) -> 0 | I41: =SUM(I38)+SUM(I39)-SUM(I40) -> 0 | J41: =SUM(J38)+SUM(J39)-SUM(J40) -> 0 | K41: =SUM(K38)+SUM(K39)-SUM(K40) -> 0 | L41: =SUM(L38)+SUM(L39)-SUM(L40) -> 0 | M41: =SUM(M38)+SUM(M39)-SUM(M40) -> 0 | ... AI41: =SUM(AI38)+SUM(AI39)-SUM(AI40) -> 0
A42: =报表格式!L41 -> 减：所得税费用 | B42: =SUM(C42:E42) -> 0 | E42: =SUM(F42,X42:AI42) -> 0 | F42: =SUM(G42:J42) -> 0 | J42: =SUM(K42:W42) -> 0
A43: =报表格式!L42 -> 0 | B43: =SUM(C43:E43) -> 0 | E43: =SUM(F43,X43:AI43) -> 0 | F43: =SUM(G43:J43) -> 0 | J43: =SUM(K43:W43) -> 0
A44: =报表格式!L43 -> 四、净利润（净亏损以“－”号填列） | B44: =SUM(C44:E44) -> 0 | C44: =C41-C42-C43 -> 0 | D44: =D41-D42-D43 -> 0 | E44: =SUM(F44,X44:AI44) -> 0 | F44: =F41-F42-F43 -> 0 | G44: =G41-G42-G43 -> 0 | H44: =H41-H42-H43 -> 0 | I44: =I41-I42-I43 -> 0 | J44: =J41-J42-J43 -> 0 | K44: =K41-K42-K43 -> 0 | L44: =L41-L42-L43 -> 0 | M44: =M41-M42-M43 -> 0 | ... AI44: =AI41-AI42-AI43 -> 0
A45: =报表格式!L44 -> （一）按经营持续性分类 | E45: =SUM(F45,X45:AI45) -> 0
A46: =报表格式!L45 -> 其中：持续经营净利润（净亏损以“-”号填列） | B46: =SUM(C46:E46) -> 0 | E46: =SUM(F46,X46:AI46) -> 0 | F46: =SUM(G46:J46) -> 0 | J46: =SUM(K46:W46) -> 0
A47: =报表格式!L46 -> 终止经营净利润（净亏损以“-”号填列） | B47: =SUM(C47:E47) -> 0 | E47: =SUM(F47,X47:AI47) -> 0 | F47: =SUM(G47:J47) -> 0 | J47: =SUM(K47:W47) -> 0
A48: =报表格式!L47 -> （二）按所有权归属分类 | E48: =SUM(F48,X48:AI48) -> 0
A49: =报表格式!L48 -> 其中：归属于母公司股东的净利润（净亏损以“-”号填列） | B49: =SUM(C49:E49) -> 0 | C49: =C44-C50 -> 0 | D49: =D44-D50 -> 0 | E49: =SUM(F49,X49:AI49) -> 0 | F49: =SUM(G49:J49) -> 0 | G49: =G44-G50 -> 0 | H49: =H44-H50 -> 0 | I49: =I44-I50 -> 0 | J49: =SUM(K49:W49) -> 0 | K49: =K44-K50 -> 0 | L49: =L44-L50 -> 0 | M49: =M44-M50 -> 0 | N49: =N44-N50 -> 0 | O49: =O44-O50 -> 0 | P49: =P44-P50 -> 0 | Q49: =Q44-Q50 -> 0 | R49: =R44-R50 -> 0 | ... AI49: =AI44-AI50 -> 0
A50: =报表格式!L49 -> 少数股东损益（净亏损以“-”号填列） | B50: =SUM(C50:E50) -> 0 | E50: =SUM(F50,X50:AI50) -> 0 | F50: =SUM(G50:J50) -> 0 | J50: =SUM(K50:W50) -> 0
A51: =报表格式!L50 -> 五、其他综合收益的税后净额 | B51: =SUM(C51:E51) -> 0 | C51: =C52+C59 -> 0 | D51: =D52+D59 -> 0 | E51: =SUM(F51,X51:AI51) -> 0 | F51: =SUM(G51:J51) -> 0 | G51: =G52+G71 -> 0 | H51: =H52+H71 -> 0 | I51: =I52+I71 -> 0 | J51: =SUM(K51:W51) -> 0 | K51: =K52+K71 -> 0 | L51: =L52+L71 -> 0 | M51: =M52+M71 -> 0 | N51: =N52+N71 -> 0 | O51: =O52+O71 -> 0 | P51: =P52+P71 -> 0 | Q51: =Q52+Q71 -> 0 | R51: =R52+R71 -> 0 | ... AI51: =AI52+AI71 -> 0
A52: =报表格式!L51 -> 归属于母公司股东的其他综合收益的税后净额 | B52: =SUM(C52:E52) -> 0 | C52: =C53+C59 -> 0 | D52: =D53+D59 -> 0 | E52: =SUM(F52,X52:AI52) -> 0 | F52: =SUM(G52:J52) -> 0 | G52: =G53+G59 -> 0 | H52: =H53+H59 -> 0 | I52: =I53+I59 -> 0 | J52: =SUM(K52:W52) -> 0 | K52: =K53+K59 -> 0 | L52: =L53+L59 -> 0 | M52: =M53+M59 -> 0 | N52: =N53+N59 -> 0 | O52: =O53+O59 -> 0 | P52: =P53+P59 -> 0 | Q52: =Q53+Q59 -> 0 | R52: =R53+R59 -> 0 | ... AI52: =AI53+AI59 -> 0
A53: =报表格式!L52 -> （一）不能重分类进损益的其他综合收益 | B53: =SUM(C53:E53) -> 0 | C53: =SUM(C54:C58) -> 0 | D53: =SUM(D54:D58) -> 0 | E53: =SUM(F53,X53:AI53) -> 0 | F53: =SUM(G53:J53) -> 0 | G53: =SUM(G54:G58) -> 0 | H53: =SUM(H54:H58) -> 0 | I53: =SUM(I54:I58) -> 0 | J53: =SUM(K53:W53) -> 0 | K53: =SUM(K54:K58) -> 0 | L53: =SUM(L54:L58) -> 0 | M53: =SUM(M54:M58) -> 0 | N53: =SUM(N54:N58) -> 0 | O53: =SUM(O54:O58) -> 0 | P53: =SUM(P54:P58) -> 0 | Q53: =SUM(Q54:Q58) -> 0 | R53: =SUM(R54:R58) -> 0 | ... AI53: =SUM(AI54:AI58) -> 0
A54: =报表格式!L53 -> 1.重新计量设定受益计划变动额 | B54: =SUM(C54:E54) -> 0 | E54: =SUM(F54,X54:AI54) -> 0 | F54: =SUM(G54:J54) -> 0 | J54: =SUM(K54:W54) -> 0
A55: =报表格式!L54 -> 2.权益法下不能转损益的其他综合收益 | B55: =SUM(C55:E55) -> 0 | E55: =SUM(F55,X55:AI55) -> 0 | F55: =SUM(G55:J55) -> 0 | J55: =SUM(K55:W55) -> 0
A56: =报表格式!L55 -> 3.其他权益工具投资公允价值变动 | B56: =SUM(C56:E56) -> 0 | E56: =SUM(F56,X56:AI56) -> 0 | F56: =SUM(G56:J56) -> 0 | J56: =SUM(K56:W56) -> 0
A57: =报表格式!L56 -> 4.企业自身信用风险公允价值变动 | B57: =SUM(C57:E57) -> 0 | E57: =SUM(F57,X57:AI57) -> 0 | F57: =SUM(G57:J57) -> 0 | J57: =SUM(K57:W57) -> 0
A58: =报表格式!L57 -> 5.其他 | B58: =SUM(C58:E58) -> 0 | E58: =SUM(F58,X58:AI58) -> 0 | F58: =SUM(G58:J58) -> 0 | J58: =SUM(K58:W58) -> 0
A59: =报表格式!L58 -> （二）将重分类进损益的其他综合收益 | B59: =SUM(C59:E59) -> 0 | C59: =SUM(C60:C70) -> 0 | D59: =SUM(D60:D70) -> 0 | E59: =SUM(F59,X59:AI59) -> 0 | F59: =SUM(G59:J59) -> 0 | G59: =SUM(G60:G70) -> 0 | H59: =SUM(H60:H70) -> 0 | I59: =SUM(I60:I70) -> 0 | J59: =SUM(K59:W59) -> 0 | K59: =SUM(K60:K70) -> 0 | L59: =SUM(L60:L70) -> 0 | M59: =SUM(M60:M70) -> 0 | N59: =SUM(N60:N70) -> 0 | O59: =SUM(O60:O70) -> 0 | P59: =SUM(P60:P70) -> 0 | Q59: =SUM(Q60:Q70) -> 0 | R59: =SUM(R60:R70) -> 0 | ... AI59: =SUM(AI60:AI70) -> 0
A60: =报表格式!L59 -> 1.权益法下可转损益的其他综合收益 | B60: =SUM(C60:E60) -> 0 | E60: =SUM(F60,X60:AI60) -> 0 | F60: =SUM(G60:J60) -> 0 | J60: =SUM(K60:W60) -> 0
A61: =报表格式!L60 -> 2.其他债权投资公允价值变动 | B61: =SUM(C61:E61) -> 0 | E61: =SUM(F61,X61:AI61) -> 0 | F61: =SUM(G61:J61) -> 0 | J61: =SUM(K61:W61) -> 0
A62: =报表格式!L61 -> 3.可供出售金融资产公允价值变动损益 | B62: =SUM(C62:E62) -> 0 | E62: =SUM(F62,X62:AI62) -> 0 | F62: =SUM(G62:J62) -> 0 | J62: =SUM(K62:W62) -> 0
A63: =报表格式!L62 -> 4.金融资产重分类计入其他综合收益的金额 | B63: =SUM(C63:E63) -> 0 | E63: =SUM(F63,X63:AI63) -> 0 | F63: =SUM(G63:J63) -> 0 | J63: =SUM(K63:W63) -> 0
A64: =报表格式!L63 -> 5.持有至到期投资重分类为可供出售金融资产损益 | B64: =SUM(C64:E64) -> 0 | E64: =SUM(F64,X64:AI64) -> 0 | F64: =SUM(G64:J64) -> 0 | J64: =SUM(K64:W64) -> 0
A65: =报表格式!L64 -> 6.其他债权投资信用减值准备 | B65: =SUM(C65:E65) -> 0 | E65: =SUM(F65,X65:AI65) -> 0 | F65: =SUM(G65:J65) -> 0 | J65: =SUM(K65:W65) -> 0
A66: =报表格式!L65 -> 7.现金流量套期储备 | B66: =SUM(C66:E66) -> 0 | E66: =SUM(F66,X66:AI66) -> 0 | F66: =SUM(G66:J66) -> 0 | J66: =SUM(K66:W66) -> 0
A67: =报表格式!L66 -> 8.外币财务报表折算差额 | B67: =SUM(C67:E67) -> 0 | E67: =SUM(F67,X67:AI67) -> 0 | F67: =SUM(G67:J67) -> 0 | J67: =SUM(K67:W67) -> 0
A68: =报表格式!L67 -> 9.自用房地产或作为存货的房地产转换为以公允价值计量的投资性房地产在转换日公允价值大于账面价值部分 | B68: =SUM(C68:E68) -> 0 | E68: =SUM(F68,X68:AI68) -> 0 | F68: =SUM(G68:J68) -> 0 | J68: =SUM(K68:W68) -> 0
A69: =报表格式!L68 -> 10.多次交易分步处置子公司股权构成一揽子交易的，丧失控制权之前各次交易处置价款与对应净资产账面价值份额的差额 | B69: =SUM(C69:E69) -> 0 | E69: =SUM(F69,X69:AI69) -> 0 | F69: =SUM(G69:J69) -> 0 | J69: =SUM(K69:W69) -> 0
A70: =报表格式!L69 -> 11.其他 | B70: =SUM(C70:E70) -> 0 | E70: =SUM(F70,X70:AI70) -> 0 | F70: =SUM(G70:J70) -> 0 | J70: =SUM(K70:W70) -> 0
A71: =报表格式!L70 -> 归属于少数股东的其他综合收益的税后净额 | B71: =SUM(C71:E71) -> 0 | E71: =SUM(F71,X71:AI71) -> 0 | F71: =SUM(G71:J71) -> 0 | J71: =SUM(K71:W71) -> 0
A72: =报表格式!L71 -> 六、综合收益总额 | B72: =SUM(C72:E72) -> 0 | C72: =C44+C51 -> 0 | D72: =D44+D51 -> 0 | E72: =SUM(F72,X72:AI72) -> 0 | F72: =SUM(G72:J72) -> 0 | G72: =G44+G51 -> 0 | H72: =H44+H51 -> 0 | I72: =I44+I51 -> 0 | J72: =SUM(K72:W72) -> 0 | K72: =K44+K51 -> 0 | L72: =L44+L51 -> 0 | M72: =M44+M51 -> 0 | N72: =N44+N51 -> 0 | O72: =O44+O51 -> 0 | P72: =P44+P51 -> 0 | Q72: =Q44+Q51 -> 0 | R72: =R44+R51 -> 0 | ... AI72: =AI44+AI51 -> 0
A73: =报表格式!L72 -> 归属于母公司股东的综合收益总额 | B73: =SUM(C73:E73) -> 0 | C73: =C49+C52 -> 0 | D73: =D49+D52 -> 0 | E73: =E72-E74 -> 0 | F73: =F72-F74 -> 0 | G73: =G49+G52 -> 0 | H73: =H49+H52 -> 0 | I73: =I49+I52 -> 0 | J73: =J72-J74 -> 0 | K73: =K49+K52 -> 0 | L73: =L49+L52 -> 0 | M73: =M49+M52 -> 0 | N73: =N49+N52 -> 0 | O73: =O49+O52 -> 0 | P73: =P49+P52 -> 0 | Q73: =Q49+Q52 -> 0 | R73: =R49+R52 -> 0 | ... AI73: =AI49+AI52 -> 0
A74: =报表格式!L73 -> 归属于少数股东的综合收益总额 | B74: =SUM(C74:E74) -> 0 | C74: =C50+C71 -> 0 | D74: =D50+D71 -> 0 | E74: =SUM(F74,X74:AI74) -> 0 | F74: =SUM(G74:J74) -> 0 | G74: =G50+G71 -> 0 | H74: =H50+H71 -> 0 | I74: =I50+I71 -> 0 | J74: =SUM(K74:W74) -> 0 | K74: =K50+K71 -> 0 | L74: =L50+L71 -> 0 | M74: =M50+M71 -> 0 | N74: =N50+N71 -> 0 | O74: =O50+O71 -> 0 | P74: =P50+P71 -> 0 | Q74: =Q50+Q71 -> 0 | R74: =R50+R71 -> 0 | ... AI74: =AI50+AI71 -> 0
A75: =报表格式!L74 -> 七、每股收益 | B75: =SUM(C75:E75) -> 0 | E75: =SUM(F75,X75:AI75) -> 0 | F75: =SUM(G75:J75) -> 0 | J75: =SUM(K75:W75) -> 0
A76: =报表格式!L75 -> （一）基本每股收益 | B76: =SUM(C76:E76) -> 0 | E76: =SUM(F76,X76:AI76) -> 0 | F76: =SUM(G76:J76) -> 0 | J76: =SUM(K76:W76) -> 0
A77: =报表格式!L76 -> （二）稀释每股收益 | B77: =SUM(C77:E77) -> 0 | E77: =SUM(F77,X77:AI77) -> 0 | F77: =SUM(G77:J77) -> 0 | J77: =SUM(K77:W77) -> 0
A78: =报表格式!L77 -> 八、利润分配 | B78: =SUM(C78:E78) -> 0 | E78: =SUM(F78,X78:AI78) -> 0 | F78: =SUM(G78:J78) -> 0 | J78: =SUM(K78:W78) -> 0
A79: =报表格式!L78 -> （一）年初未分配利润 | B79: =SUM(C79:E79) -> 0 | E79: =SUM(F79,X79:AI79) -> 0 | F79: =SUM(G79:J79) -> 0 | J79: =SUM(K79:W79) -> 0
A80: =报表格式!L79 -> （二）可供分配的利润 | B80: =SUM(C80:E80) -> 0 | C80: =C49+C79 -> 0 | D80: =D49+D79 -> 0 | E80: =SUM(F80,X80:AI80) -> 0 | F80: =SUM(G80:J80) -> 0 | G80: =G49+G79 -> 0 | H80: =H49+H79 -> 0 | I80: =I49+I79 -> 0 | J80: =SUM(K80:W80) -> 0 | K80: =K49+K79 -> 0 | L80: =L49+L79 -> 0 | M80: =M49+M79 -> 0 | N80: =N49+N79 -> 0 | O80: =O49+O79 -> 0 | P80: =P49+P79 -> 0 | Q80: =Q49+Q79 -> 0 | R80: =R49+R79 -> 0 | ... AI80: =AI49+AI79 -> 0
A81: =报表格式!L80 -> 1、提取法定盈余公积 | B81: =SUM(C81:E81) -> 0 | E81: =SUM(F81,X81:AI81) -> 0 | F81: =SUM(G81:J81) -> 0 | J81: =SUM(K81:W81) -> 0
A82: =报表格式!L81 -> 2、其他 | B82: =SUM(C82:E82) -> 0 | E82: =SUM(F82,X82:AI82) -> 0 | F82: =SUM(G82:J82) -> 0 | J82: =SUM(K82:W82) -> 0
A83: =报表格式!L82 -> （三）可供投资者分配的利润 | B83: =SUM(C83:E83) -> 0 | C83: =C80-C81-C82 -> 0 | D83: =D80-D81-D82 -> 0 | E83: =SUM(F83,X83:AI83) -> 0 | F83: =SUM(G83:J83) -> 0 | G83: =G80-G81-G82 -> 0 | H83: =H80-H81-H82 -> 0 | I83: =I80-I81-I82 -> 0 | J83: =SUM(K83:W83) -> 0 | K83: =K80-K81-K82 -> 0 | L83: =L80-L81-L82 -> 0 | M83: =M80-M81-M82 -> 0 | N83: =N80-N81-N82 -> 0 | O83: =O80-O81-O82 -> 0 | P83: =P80-P81-P82 -> 0 | Q83: =Q80-Q81-Q82 -> 0 | R83: =R80-R81-R82 -> 0 | ... AI83: =AI80-AI81-AI82 -> 0
A84: =报表格式!L83 -> 1、应付优先股股利 | B84: =SUM(C84:E84) -> 0 | E84: =SUM(F84,X84:AI84) -> 0 | F84: =SUM(G84:J84) -> 0 | J84: =SUM(K84:W84) -> 0
A85: =报表格式!L84 -> 2、提取任意盈余公积 | B85: =SUM(C85:E85) -> 0 | E85: =SUM(F85,X85:AI85) -> 0 | F85: =SUM(G85:J85) -> 0 | J85: =SUM(K85:W85) -> 0
A86: =报表格式!L85 -> 3、应付普通股股利（应付利润） | B86: =SUM(C86:E86) -> 0 | E86: =SUM(F86,X86:AI86) -> 0 | F86: =SUM(G86:J86) -> 0 | J86: =SUM(K86:W86) -> 0
A87: =报表格式!L86 -> 4、转作资本（或股本）的普通股股利 | B87: =SUM(C87:E87) -> 0 | E87: =SUM(F87,X87:AI87) -> 0 | F87: =SUM(G87:J87) -> 0 | J87: =SUM(K87:W87) -> 0
A88: =报表格式!L87 -> 5、其他 | B88: =SUM(C88:E88) -> 0 | E88: =SUM(F88,X88:AI88) -> 0 | F88: =SUM(G88:J88) -> 0 | J88: =SUM(K88:W88) -> 0
A89: =报表格式!L88 -> 九、未分配利润 | B89: =SUM(C89:E89) -> 0 | C89: =C83-SUM(C84:C88) -> 0 | D89: =D83-SUM(D84:D88) -> 0 | E89: =SUM(F89,X89:AI89) -> 0 | F89: =SUM(G89:J89) -> 0 | G89: =G83-SUM(G84:G88) -> 0 | H89: =H83-SUM(H84:H88) -> 0 | I89: =I83-SUM(I84:I88) -> 0 | J89: =SUM(K89:W89) -> 0 | K89: =K83-SUM(K84:K88) -> 0 | L89: =L83-SUM(L84:L88) -> 0 | M89: =M83-SUM(M84:M88) -> 0 | N89: =N83-SUM(N84:N88) -> 0 | O89: =O83-SUM(O84:O88) -> 0 | P89: =P83-SUM(P84:P88) -> 0 | Q89: =Q83-SUM(Q84:Q88) -> 0 | R89: =R83-SUM(R84:R88) -> 0 | ... AI89: =AI83-SUM(AI84:AI88) -> 0
A92: 勾稽核对：
A93: 检验营业利润公式 | B93: =SUM(B6)-SUM(B12,B22:B26)+SUM(B29:B37,-B31-B32)-B38 -> 0 | C93: =SUM(C6)-SUM(C12,C22:C26)+SUM(C29:C37,-C31-C32)-C38 -> 0 | D93: =SUM(D6)-SUM(D12,D22:D26)+SUM(D29:D37,-D31-D32)-D38 -> 0 | E93: =SUM(E6)-SUM(E12,E22:E26)+SUM(E29:E37,-E31-E32)-E38 -> 0 | F93: =SUM(F6)-SUM(F12,F22:F26)+SUM(F29:F37,-F31-F32)-F38 -> 0 | G93: =SUM(G6)-SUM(G12,G22:G26)+SUM(G29:G37,-G31-G32)-G38 -> 0 | H93: =SUM(H6)-SUM(H12,H22:H26)+SUM(H29:H37,-H31-H32)-H38 -> 0 | I93: =SUM(I6)-SUM(I12,I22:I26)+SUM(I29:I37,-I31-I32)-I38 -> 0 | ... AI93: =SUM(AI6)-SUM(AI12,AI22:AI26)+SUM(AI29:AI37,-AI31-AI32)-AI38 -> 0
A94: 检验利润总额公式 | B94: =SUM(B38,B39,-B40)-B41 -> 0 | C94: =SUM(C38,C39,-C40)-C41 -> 0 | D94: =SUM(D38,D39,-D40)-D41 -> 0 | E94: =SUM(E38,E39,-E40)-E41 -> 0 | F94: =SUM(F38,F39,-F40)-F41 -> 0 | G94: =SUM(G38,G39,-G40)-G41 -> 0 | H94: =SUM(H38,H39,-H40)-H41 -> 0 | I94: =SUM(I38,I39,-I40)-I41 -> 0 | ... AI94: =SUM(AI38,AI39,-AI40)-AI41 -> 0
A95: 检验净利润公式 | B95: =SUM(B41,-B42,-B43)-B44 -> 0 | C95: =SUM(C41,-C42,-C43)-C44 -> 0 | D95: =SUM(D41,-D42,-D43)-D44 -> 0 | E95: =SUM(E41,-E42,-E43)-E44 -> 0 | F95: =SUM(F41,-F42,-F43)-F44 -> 0 | G95: =SUM(G41,-G42,-G43)-G44 -> 0 | H95: =SUM(H41,-H42,-H43)-H44 -> 0 | I95: =SUM(I41,-I42,-I43)-I44 -> 0 | ... AI95: =SUM(AI41,-AI42,-AI43)-AI44 -> 0
A96: 检验归属于母公司所有者的净利润公式 | B96: =SUM(B44,-B50)-B49 -> 0 | C96: =SUM(C44,-C50)-C49 -> 0 | D96: =SUM(D44,-D50)-D49 -> 0 | E96: =SUM(E44,-E50)-E49 -> 0 | F96: =SUM(F44,-F50)-F49 -> 0 | G96: =SUM(G44,-G50)-G49 -> 0 | H96: =SUM(H44,-H50)-H49 -> 0 | I96: =SUM(I44,-I50)-I49 -> 0 | ... AI96: =SUM(AI44,-AI50)-AI49 -> 0
A97: 检验归属于母公司其他综合收益公式 | B97: =SUM(B54:B58,B60:B70)-B52 -> 0 | C97: =SUM(C54:C58,C60:C70)-C52 -> 0 | D97: =SUM(D54:D58,D60:D70)-D52 -> 0 | E97: =SUM(E54:E58,E60:E70)-E52 -> 0 | F97: =SUM(F54:F58,F60:F70)-F52 -> 0 | G97: =SUM(G54:G58,G60:G70)-G52 -> 0 | H97: =SUM(H54:H58,H60:H70)-H52 -> 0 | I97: =SUM(I54:I58,I60:I70)-I52 -> 0 | ... AI97: =SUM(AI54:AI58,AI60:AI70)-AI52 -> 0
A98: 检验综合收益总额公式 | B98: =SUM(B44,B51)-B72 -> 0 | C98: =SUM(C44,C51)-C72 -> 0 | D98: =SUM(D44,D51)-D72 -> 0 | E98: =SUM(E44,E51)-E72 -> 0 | F98: =SUM(F44,F51)-F72 -> 0 | G98: =SUM(G44,G51)-G72 -> 0 | H98: =SUM(H44,H51)-H72 -> 0 | I98: =SUM(I44,I51)-I72 -> 0 | ... AI98: =SUM(AI44,AI51)-AI72 -> 0
A100: 检验营业收入公式 | B100: =SUM(B7:B11)-B6 -> 0 | C100: =SUM(C7:C11)-C6 -> 0 | D100: =SUM(D7:D11)-D6 -> 0 | E100: =SUM(E7:E11)-E6 -> 0 | F100: =SUM(F7:F11)-F6 -> 0 | G100: =SUM(G7:G11)-G6 -> 0 | H100: =SUM(H7:H11)-H6 -> 0 | I100: =SUM(I7:I11)-I6 -> 0 | ... AI100: =SUM(AI7:AI11)-AI6 -> 0
A101: 检验营业成本公式 | B101: =SUM(B13:B21)-B12 -> 0 | C101: =SUM(C13:C21)-C12 -> 0 | D101: =SUM(D13:D21)-D12 -> 0 | E101: =SUM(E13:E21)-E12 -> 0 | F101: =SUM(F13:F21)-F12 -> 0 | G101: =SUM(G13:G21)-G12 -> 0 | H101: =SUM(H13:H21)-H12 -> 0 | I101: =SUM(I13:I21)-I12 -> 0 | ... AI101: =SUM(AI13:AI21)-AI12 -> 0

Sheet 期初核对BS
A1: =IF(AND(ABS(F60)<0.005,ABS(F119)<0.005),"期初合并金额核对一致","期初合并金额核对不符！") -> 期初合并金额核对一致 | G1: =IF(AND(ABS(J60)<0.005,ABS(J119)<0.005),"期初母公司金额核对一致","期初母公司金额核对不符！") -> 期初母公司金额核对一致
A2: 资产负债表期初核对
C3: =说明!$E$32 -> 43830
A4: =IF(报表格式!G58=""," 对不起，请到参数表中确定报表类型！",CONCATENATE(" 客户名称：",说明!E23)) -> 客户名称： | H4: =CONCATENATE("金额单位：",说明!$E$33) -> 金额单位：人民币元
A5: =IF(E60<=0.005,"资 产","资产明细核对不符！") -> 资 产 | B5: 行次 | C5: 合并数 | G5: 母公司数
C6: 本年期初数 ① | D6: 上期审定数 ② | E6: 辅助列 | F6: 差异 ①-② | G6: 本年期初数 ① | H6: 上期审定数 ② | I6: 辅助列 | J6: 差异 ①-②
A7: =报表格式!B5 -> 流动资产： | B7: 1
A8: =报表格式!B6 -> 货币资金 | B8: =B7+1 -> 2 | D8: =年初BS审定!B7 -> 0 | E8: =ABS(F8) -> 0 | F8: =C8-D8 -> 0 | H8: =年初BS审定!F7 -> 0 | I8: =ABS(J8) -> 0 | J8: =G8-H8 -> 0
A9: =报表格式!B7 -> 结算备付金 | B9: =B8+1 -> 3 | D9: =年初BS审定!B8 -> 0 | E9: =ABS(F9) -> 0 | F9: =C9-D9 -> 0 | H9: =年初BS审定!F8 -> 0 | I9: =ABS(J9) -> 0 | J9: =G9-H9 -> 0
A10: =报表格式!B8 -> 拆出资金 | B10: =B9+1 -> 4 | D10: =年初BS审定!B9 -> 0 | E10: =ABS(F10) -> 0 | F10: =C10-D10 -> 0 | H10: =年初BS审定!F9 -> 0 | I10: =ABS(J10) -> 0 | J10: =G10-H10 -> 0
A11: =报表格式!B9 -> 交易性金融资产 | B11: =B10+1 -> 5 | D11: =年初BS审定!B10 -> 0 | E11: =ABS(F11) -> 0 | F11: =C11-D11 -> 0 | H11: =年初BS审定!F10 -> 0 | I11: =ABS(J11) -> 0 | J11: =G11-H11 -> 0
A12: =报表格式!B10 -> 以公允价值计量且其变动计入当期损益的金融资产 | B12: =B11+1 -> 6 | D12: =年初BS审定!B11 -> 0 | E12: =ABS(F12) -> 0 | F12: =C12-D12 -> 0 | H12: =年初BS审定!F11 -> 0 | I12: =ABS(J12) -> 0 | J12: =G12-H12 -> 0
A13: =报表格式!B11 -> 衍生金融资产 | B13: =B12+1 -> 7 | D13: =年初BS审定!B12 -> 0 | E13: =ABS(F13) -> 0 | F13: =C13-D13 -> 0 | H13: =年初BS审定!F12 -> 0 | I13: =ABS(J13) -> 0 | J13: =G13-H13 -> 0
A14: =报表格式!B12 -> 应收票据 | B14: =B13+1 -> 8 | D14: =年初BS审定!B13 -> 0 | E14: =ABS(F14) -> 0 | F14: =C14-D14 -> 0 | H14: =年初BS审定!F13 -> 0 | I14: =ABS(J14) -> 0 | J14: =G14-H14 -> 0
A15: =报表格式!B13 -> 应收账款 | B15: =B14+1 -> 9 | D15: =年初BS审定!B14 -> 0 | E15: =ABS(F15) -> 0 | F15: =C15-D15 -> 0 | H15: =年初BS审定!F14 -> 0 | I15: =ABS(J15) -> 0 | J15: =G15-H15 -> 0
A16: =报表格式!B14 -> 应收款项融资 | B16: =B15+1 -> 10 | D16: =年初BS审定!B15 -> 0 | E16: =ABS(F16) -> 0 | F16: =C16-D16 -> 0 | H16: =年初BS审定!F15 -> 0 | I16: =ABS(J16) -> 0 | J16: =G16-H16 -> 0
A17: =报表格式!B15 -> 预付款项 | B17: =B16+1 -> 11 | D17: =年初BS审定!B16 -> 0 | E17: =ABS(F17) -> 0 | F17: =C17-D17 -> 0 | H17: =年初BS审定!F16 -> 0 | I17: =ABS(J17) -> 0 | J17: =G17-H17 -> 0
A18: =报表格式!B16 -> 应收保费 | B18: =B17+1 -> 12 | D18: =年初BS审定!B17 -> 0 | E18: =ABS(F18) -> 0 | F18: =C18-D18 -> 0 | H18: =年初BS审定!F17 -> 0 | I18: =ABS(J18) -> 0 | J18: =G18-H18 -> 0
A19: =报表格式!B17 -> 应收分保账款 | B19: =B18+1 -> 13 | D19: =年初BS审定!B18 -> 0 | E19: =ABS(F19) -> 0 | F19: =C19-D19 -> 0 | H19: =年初BS审定!F18 -> 0 | I19: =ABS(J19) -> 0 | J19: =G19-H19 -> 0
... A31: =报表格式!B29 -> 0 | B31: =B30+1 -> 25 | D31: =年初BS审定!B30 -> 0 | E31: =ABS(F31) -> 0 | F31: =C31-D31 -> 0 | H31: =年初BS审定!F30 -> 0 | I31: =ABS(J31) -> 0 | J31: =G31-H31 -> 0
A32: =报表格式!B30 -> 流动资产合计 | B32: =B31+1 -> 26 | C32: =SUM(C8:C31)-C22-C23 -> 0 | D32: =SUM(D8:D31)-D22-D23 -> 0 | E32: =ABS(F32) -> 0 | F32: =C32-D32 -> 0 | G32: =SUM(G8:G31)-G22-G23 -> 0 | H32: =SUM(H8:H31)-H22-H23 -> 0 | I32: =ABS(J32) -> 0 | J32: =G32-H32 -> 0
A33: =报表格式!B31 -> 非流动资产: | B33: =B32+1 -> 27
A34: =报表格式!B32 -> 发放贷款及垫款 | B34: =B33+1 -> 28 | D34: =年初BS审定!B33 -> 0 | E34: =ABS(F34) -> 0 | F34: =C34-D34 -> 0 | H34: =年初BS审定!F33 -> 0 | I34: =ABS(J34) -> 0 | J34: =G34-H34 -> 0
A35: =报表格式!B33 -> 债权投资 | B35: =B34+1 -> 29 | D35: =年初BS审定!B34 -> 0 | E35: =ABS(F35) -> 0 | F35: =C35-D35 -> 0 | H35: =年初BS审定!F34 -> 0 | I35: =ABS(J35) -> 0 | J35: =G35-H35 -> 0
A36: =报表格式!B34 -> 可供出售金融资产 | B36: =B35+1 -> 30 | D36: =年初BS审定!B35 -> 0 | E36: =ABS(F36) -> 0 | F36: =C36-D36 -> 0 | H36: =年初BS审定!F35 -> 0 | I36: =ABS(J36) -> 0 | J36: =G36-H36 -> 0
A37: =报表格式!B35 -> 其他债权投资 | B37: =B36+1 -> 31 | D37: =年初BS审定!B36 -> 0 | E37: =ABS(F37) -> 0 | F37: =C37-D37 -> 0 | H37: =年初BS审定!F36 -> 0 | I37: =ABS(J37) -> 0 | J37: =G37-H37 -> 0
A38: =报表格式!B36 -> 持有至到期投资 | B38: =B37+1 -> 32 | D38: =年初BS审定!B37 -> 0 | E38: =ABS(F38) -> 0 | F38: =C38-D38 -> 0 | H38: =年初BS审定!F37 -> 0 | I38: =ABS(J38) -> 0 | J38: =G38-H38 -> 0
A39: =报表格式!B37 -> 长期应收款 | B39: =B38+1 -> 33 | D39: =年初BS审定!B38 -> 0 | E39: =ABS(F39) -> 0 | F39: =C39-D39 -> 0 | H39: =年初BS审定!F38 -> 0 | I39: =ABS(J39) -> 0 | J39: =G39-H39 -> 0
A40: =报表格式!B38 -> 设定受益计划净资产 | B40: =B39+1 -> 34 | D40: =年初BS审定!B39 -> 0 | E40: =ABS(F40) -> 0 | F40: =C40-D40 -> 0 | H40: =年初BS审定!F39 -> 0 | I40: =ABS(J40) -> 0 | J40: =G40-H40 -> 0
A41: =报表格式!B39 -> 长期股权投资 | B41: =B40+1 -> 35 | D41: =年初BS审定!B40 -> 0 | E41: =ABS(F41) -> 0 | F41: =C41-D41 -> 0 | H41: =年初BS审定!F40 -> 0 | I41: =ABS(J41) -> 0 | J41: =G41-H41 -> 0
A42: =报表格式!B40 -> 其他权益工具投资 | B42: =B41+1 -> 36 | D42: =年初BS审定!B41 -> 0 | E42: =ABS(F42) -> 0 | F42: =C42-D42 -> 0 | H42: =年初BS审定!F41 -> 0 | I42: =ABS(J42) -> 0 | J42: =G42-H42 -> 0
A43: =报表格式!B41 -> 其他非流动金融资产 | B43: =B42+1 -> 37 | D43: =年初BS审定!B42 -> 0 | E43: =ABS(F43) -> 0 | F43: =C43-D43 -> 0 | H43: =年初BS审定!F42 -> 0 | I43: =ABS(J43) -> 0 | J43: =G43-H43 -> 0
A44: =报表格式!B42 -> 投资性房地产 | B44: =B43+1 -> 38 | D44: =年初BS审定!B43 -> 0 | E44: =ABS(F44) -> 0 | F44: =C44-D44 -> 0 | H44: =年初BS审定!F43 -> 0 | I44: =ABS(J44) -> 0 | J44: =G44-H44 -> 0
A45: =报表格式!B43 -> 固定资产 | B45: =B44+1 -> 39 | D45: =年初BS审定!B44 -> 0 | E45: =ABS(F45) -> 0 | F45: =C45-D45 -> 0 | H45: =年初BS审定!F44 -> 0 | I45: =ABS(J45) -> 0 | J45: =G45-H45 -> 0
... A58: =报表格式!B56 -> 0 | B58: =B57+1 -> 52 | D58: =年初BS审定!B57 -> 0 | E58: =ABS(F58) -> 0 | F58: =C58-D58 -> 0 | H58: =年初BS审定!F57 -> 0 | I58: =ABS(J58) -> 0 | J58: =G58-H58 -> 0
A59: =报表格式!B57 -> 非流动资产合计 | B59: =B58+1 -> 53 | C59: =SUM(C35:C58) -> 0 | D59: =SUM(D34:D58) -> 0 | E59: =ABS(F59) -> 0 | F59: =C59-D59 -> 0 | G59: =SUM(G35:G58) -> 0 | H59: =SUM(H34:H58) -> 0 | I59: =ABS(J59) -> 0 | J59: =G59-H59 -> 0
A60: =报表格式!B58 -> 资 产 总 计 | B60: =B59+1 -> 54 | C60: =SUM(C32,C59) -> 0 | D60: =SUM(D32,D59) -> 0 | E60: =ABS(F60) -> 0 | F60: =C60-D60 -> 0 | G60: =SUM(G32,G59) -> 0 | H60: =SUM(H32,H59) -> 0 | I60: =ABS(J60) -> 0 | J60: =G60-H60 -> 0
A61: =IF(E119<=0.005,IF(说明!E28="一般企业（执行统一会计制度）","负债及所有者权益","负债及股东权益"),"负债明细核对不符！") -> 负债及股东权益 | B61: 行次 | C61: 合并数 | G61: 母公司数
C62: 本年期初数 ① | D62: 上期审定数 ② | E62: 辅助列 | F62: 差异 ①-② | G62: 本年期初数 ① | H62: 上期审定数 ② | I62: 辅助列 | J62: 差异 ①-②
A63: =报表格式!G5 -> 流动负债： | B63: =B60+1 -> 55
A64: =报表格式!G6 -> 短期借款 | B64: =B63+1 -> 56 | D64: =年初BS审定!B62 -> 0 | E64: =ABS(F64) -> 0 | F64: =C64-D64 -> 0 | H64: =年初BS审定!F62 -> 0 | I64: =ABS(J64) -> 0 | J64: =G64-H64 -> 0
A65: =报表格式!G7 -> 向中央银行借款 | B65: =B64+1 -> 57 | D65: =年初BS审定!B63 -> 0 | E65: =ABS(F65) -> 0 | F65: =C65-D65 -> 0 | H65: =年初BS审定!F63 -> 0 | I65: =ABS(J65) -> 0 | J65: =G65-H65 -> 0
A66: =报表格式!G8 -> 吸收存款及同业存放 | B66: =B65+1 -> 58 | D66: =年初BS审定!B64 -> 0 | E66: =ABS(F66) -> 0 | F66: =C66-D66 -> 0 | H66: =年初BS审定!F64 -> 0 | I66: =ABS(J66) -> 0 | J66: =G66-H66 -> 0
A67: =报表格式!G9 -> 拆入资金 | B67: =B66+1 -> 59 | D67: =年初BS审定!B65 -> 0 | E67: =ABS(F67) -> 0 | F67: =C67-D67 -> 0 | H67: =年初BS审定!F65 -> 0 | I67: =ABS(J67) -> 0 | J67: =G67-H67 -> 0
A68: =报表格式!G10 -> 交易性金融负债 | B68: =B67+1 -> 60 | D68: =年初BS审定!B66 -> 0 | E68: =ABS(F68) -> 0 | F68: =C68-D68 -> 0 | H68: =年初BS审定!F66 -> 0 | I68: =ABS(J68) -> 0 | J68: =G68-H68 -> 0
A69: =报表格式!G11 -> 以公允价值计量且其变动计入当期损益的金融负债 | B69: =B68+1 -> 61 | D69: =年初BS审定!B67 -> 0 | E69: =ABS(F69) -> 0 | F69: =C69-D69 -> 0 | H69: =年初BS审定!F67 -> 0 | I69: =ABS(J69) -> 0 | J69: =G69-H69 -> 0
A70: =报表格式!G12 -> 衍生金融负债 | B70: =B69+1 -> 62 | D70: =年初BS审定!B68 -> 0 | E70: =ABS(F70) -> 0 | F70: =C70-D70 -> 0 | H70: =年初BS审定!F68 -> 0 | I70: =ABS(J70) -> 0 | J70: =G70-H70 -> 0
A71: =报表格式!G13 -> 应付票据 | B71: =B70+1 -> 63 | D71: =年初BS审定!B69 -> 0 | E71: =ABS(F71) -> 0 | F71: =C71-D71 -> 0 | H71: =年初BS审定!F69 -> 0 | I71: =ABS(J71) -> 0 | J71: =G71-H71 -> 0
A72: =报表格式!G14 -> 应付账款 | B72: =B71+1 -> 64 | D72: =年初BS审定!B70 -> 0 | E72: =ABS(F72) -> 0 | F72: =C72-D72 -> 0 | H72: =年初BS审定!F70 -> 0 | I72: =ABS(J72) -> 0 | J72: =G72-H72 -> 0
A73: =报表格式!G15 -> 预收款项 | B73: =B72+1 -> 65 | D73: =年初BS审定!B71 -> 0 | E73: =ABS(F73) -> 0 | F73: =C73-D73 -> 0 | H73: =年初BS审定!F71 -> 0 | I73: =ABS(J73) -> 0 | J73: =G73-H73 -> 0
A74: =报表格式!G16 -> 卖出回购金融资产款 | B74: =B73+1 -> 66 | D74: =年初BS审定!B72 -> 0 | E74: =ABS(F74) -> 0 | F74: =C74-D74 -> 0 | H74: =年初BS审定!F72 -> 0 | I74: =ABS(J74) -> 0 | J74: =G74-H74 -> 0
A75: =报表格式!G17 -> 应付手续费及佣金 | B75: =B74+1 -> 67 | D75: =年初BS审定!B73 -> 0 | E75: =ABS(F75) -> 0 | F75: =C75-D75 -> 0 | H75: =年初BS审定!F73 -> 0 | I75: =ABS(J75) -> 0 | J75: =G75-H75 -> 0
... A88: =报表格式!G30 -> 其他流动负债 | B88: =B87+1 -> 80 | D88: =年初BS审定!B86 -> 0 | E88: =ABS(F88) -> 0 | F88: =C88-D88 -> 0 | H88: =年初BS审定!F86 -> 0 | I88: =ABS(J88) -> 0 | J88: =G88-H88 -> 0
A89: =报表格式!G31 -> 流动负债合计 | B89: =B88+1 -> 81 | C89: =SUM(C64:C88)-C80-C81 -> 0 | D89: =SUM(D64:D88)-D80-D81 -> 0 | E89: =ABS(F89) -> 0 | F89: =C89-D89 -> 0 | G89: =SUM(G64:G88)-G80-G81 -> 0 | H89: =SUM(H64:H88)-H80-H81 -> 0 | I89: =ABS(J89) -> 0 | J89: =G89-H89 -> 0
A90: =报表格式!G32 -> 非流动负债: | B90: =B89+1 -> 82
A91: =报表格式!G33 -> 长期借款 | B91: =B90+1 -> 83 | D91: =年初BS审定!B89 -> 0 | E91: =ABS(F91) -> 0 | F91: =C91-D91 -> 0 | H91: =年初BS审定!F89 -> 0 | I91: =ABS(J91) -> 0 | J91: =G91-H91 -> 0
A92: =报表格式!G34 -> 应付债券 | B92: =B91+1 -> 84 | D92: =年初BS审定!B90 -> 0 | E92: =ABS(F92) -> 0 | F92: =C92-D92 -> 0 | H92: =年初BS审定!F90 -> 0 | I92: =ABS(J92) -> 0 | J92: =G92-H92 -> 0
A93: =报表格式!G35 -> 其中：优先股 | B93: =B92+1 -> 85 | D93: =年初BS审定!B91 -> 0 | E93: =ABS(F93) -> 0 | F93: =C93-D93 -> 0 | H93: =年初BS审定!F91 -> 0 | I93: =ABS(J93) -> 0 | J93: =G93-H93 -> 0
A94: =报表格式!G36 -> 永续债 | B94: =B93+1 -> 86 | D94: =年初BS审定!B92 -> 0 | E94: =ABS(F94) -> 0 | F94: =C94-D94 -> 0 | H94: =年初BS审定!F92 -> 0 | I94: =ABS(J94) -> 0 | J94: =G94-H94 -> 0
A95: =报表格式!G37 -> 租赁负债 | B95: =B94+1 -> 87 | D95: =年初BS审定!B93 -> 0 | E95: =ABS(F95) -> 0 | F95: =C95-D95 -> 0 | H95: =年初BS审定!F93 -> 0 | I95: =ABS(J95) -> 0 | J95: =G95-H95 -> 0
A96: =报表格式!G38 -> 长期应付款 | B96: =B95+1 -> 88 | D96: =年初BS审定!B94 -> 0 | E96: =ABS(F96) -> 0 | F96: =C96-D96 -> 0 | H96: =年初BS审定!F94 -> 0 | I96: =ABS(J96) -> 0 | J96: =G96-H96 -> 0
A97: =报表格式!G39 -> 长期应付职工薪酬 | B97: =B96+1 -> 89 | D97: =年初BS审定!B95 -> 0 | E97: =ABS(F97) -> 0 | F97: =C97-D97 -> 0 | H97: =年初BS审定!F95 -> 0 | I97: =ABS(J97) -> 0 | J97: =G97-H97 -> 0
A98: =报表格式!G40 -> 预计负债 | B98: =B97+1 -> 90 | D98: =年初BS审定!B96 -> 0 | E98: =ABS(F98) -> 0 | F98: =C98-D98 -> 0 | H98: =年初BS审定!F96 -> 0 | I98: =ABS(J98) -> 0 | J98: =G98-H98 -> 0
A99: =报表格式!G41 -> 递延收益 | B99: =B98+1 -> 91 | D99: =年初BS审定!B97 -> 0 | E99: =ABS(F99) -> 0 | F99: =C99-D99 -> 0 | H99: =年初BS审定!F97 -> 0 | I99: =ABS(J99) -> 0 | J99: =G99-H99 -> 0
A100: =报表格式!G42 -> 递延所得税负债 | B100: =B99+1 -> 92 | D100: =年初BS审定!B98 -> 0 | E100: =ABS(F100) -> 0 | F100: =C100-D100 -> 0 | H100: =年初BS审定!F98 -> 0 | I100: =ABS(J100) -> 0 | J100: =G100-H100 -> 0
A101: =报表格式!G43 -> 其他非流动负债 | B101: =B100+1 -> 93 | D101: =年初BS审定!B99 -> 0 | E101: =ABS(F101) -> 0 | F101: =C101-D101 -> 0 | H101: =年初BS审定!F99 -> 0 | I101: =ABS(J101) -> 0 | J101: =G101-H101 -> 0
A102: =报表格式!G44 -> 非流动负债合计 | B102: =B101+1 -> 94 | C102: =SUM(C91:C101)-C93-C94 -> 0 | D102: =SUM(D91:D101)-D93-D94 -> 0 | E102: =ABS(F102) -> 0 | F102: =C102-D102 -> 0 | G102: =SUM(G91:G101)-G93-G94 -> 0 | H102: =SUM(H91:H101)-H93-H94 -> 0 | I102: =ABS(J102) -> 0 | J102: =G102-H102 -> 0
A103: =报表格式!G45 -> 负 债 合 计 | B103: =B102+1 -> 95 | C103: =SUM(C89,C102) -> 0 | D103: =SUM(D89,D102) -> 0 | E103: =ABS(F103) -> 0 | F103: =C103-D103 -> 0 | G103: =SUM(G89,G102) -> 0 | H103: =SUM(H89,H102) -> 0 | I103: =ABS(J103) -> 0 | J103: =G103-H103 -> 0
A104: =报表格式!G46 -> 股东权益： | B104: =B103+1 -> 96
A105: =报表格式!G47 -> 股本 | B105: =B104+1 -> 97 | D105: =年初BS审定!B103 -> 0 | E105: =ABS(F105) -> 0 | F105: =C105-D105 -> 0 | H105: =年初BS审定!F103 -> 0 | I105: =ABS(J105) -> 0 | J105: =G105-H105 -> 0
A106: =报表格式!G48 -> 其他权益工具 | B106: =B105+1 -> 98 | D106: =年初BS审定!B104 -> 0 | E106: =ABS(F106) -> 0 | F106: =C106-D106 -> 0 | H106: =年初BS审定!F104 -> 0 | I106: =ABS(J106) -> 0 | J106: =G106-H106 -> 0
A107: =报表格式!G49 -> 其中：优先股 | B107: =B106+1 -> 99 | D107: =年初BS审定!B105 -> 0 | E107: =ABS(F107) -> 0 | F107: =C107-D107 -> 0 | H107: =年初BS审定!F105 -> 0 | I107: =ABS(J107) -> 0 | J107: =G107-H107 -> 0
A108: =报表格式!G50 -> 永续债 | B108: =B107+1 -> 100 | D108: =年初BS审定!B106 -> 0 | E108: =ABS(F108) -> 0 | F108: =C108-D108 -> 0 | H108: =年初BS审定!F106 -> 0 | I108: =ABS(J108) -> 0 | J108: =G108-H108 -> 0
A109: =报表格式!G51 -> 资本公积 | B109: =B108+1 -> 101 | D109: =年初BS审定!B107 -> 0 | E109: =ABS(F109) -> 0 | F109: =C109-D109 -> 0 | H109: =年初BS审定!F107 -> 0 | I109: =ABS(J109) -> 0 | J109: =G109-H109 -> 0
A110: =报表格式!G52 -> 减：库存股 | B110: =B109+1 -> 102 | D110: =年初BS审定!B108 -> 0 | E110: =ABS(F110) -> 0 | F110: =C110-D110 -> 0 | H110: =年初BS审定!F108 -> 0 | I110: =ABS(J110) -> 0 | J110: =G110-H110 -> 0
A111: =报表格式!G53 -> 其他综合收益 | B111: =B110+1 -> 103 | D111: =年初BS审定!B109 -> 0 | E111: =ABS(F111) -> 0 | F111: =C111-D111 -> 0 | H111: =年初BS审定!F109 -> 0 | I111: =ABS(J111) -> 0 | J111: =G111-H111 -> 0
A112: =报表格式!G54 -> 专项储备 | B112: =B111+1 -> 104 | D112: =年初BS审定!B110 -> 0 | E112: =ABS(F112) -> 0 | F112: =C112-D112 -> 0 | H112: =年初BS审定!F110 -> 0 | I112: =ABS(J112) -> 0 | J112: =G112-H112 -> 0
A113: =报表格式!G55 -> 盈余公积 | B113: =B112+1 -> 105 | D113: =年初BS审定!B111 -> 0 | E113: =ABS(F113) -> 0 | F113: =C113-D113 -> 0 | H113: =年初BS审定!F111 -> 0 | I113: =ABS(J113) -> 0 | J113: =G113-H113 -> 0
A114: =报表格式!G56 -> 一般风险准备 | B114: =B113+1 -> 106 | D114: =年初BS审定!B112 -> 0 | E114: =ABS(F114) -> 0 | F114: =C114-D114 -> 0 | H114: =年初BS审定!F112 -> 0 | I114: =ABS(J114) -> 0 | J114: =G114-H114 -> 0
A115: =报表格式!G57 -> 未分配利润 | B115: =B114+1 -> 107 | D115: =年初BS审定!B113 -> 0 | E115: =ABS(F115) -> 0 | F115: =C115-D115 -> 0 | H115: =年初BS审定!F113 -> 0 | I115: =ABS(J115) -> 0 | J115: =G115-H115 -> 0
A116: =报表格式!G58 -> 归属于母公司股东权益合计 | B116: =B115+1 -> 108 | C116: =SUM(C105:C106,C109,-C110,C111:C115) -> 0 | D116: =SUM(D105:D106,D109,-D110,D111:D115) -> 0 | E116: =ABS(F116) -> 0 | F116: =C116-D116 -> 0 | G116: =SUM(G105:G106,G109,-G110,G111:G115) -> 0 | H116: =SUM(H105:H106,H109,-H110,H111:H115) -> 0 | I116: =ABS(J116) -> 0 | J116: =G116-H116 -> 0
A117: =报表格式!G59 -> 少数股东权益 | B117: =B116+1 -> 109 | D117: =年初BS审定!B115 -> 0 | E117: =ABS(F117) -> 0 | F117: =C117-D117 -> 0 | H117: =年初BS审定!F115 -> 0 | I117: =ABS(J117) -> 0 | J117: =G117-H117 -> 0
A118: =报表格式!G60 -> 股东权益合计 | B118: =B117+1 -> 110 | C118: =SUM(C116:C117) -> 0 | D118: =SUM(D116:D117) -> 0 | E118: =ABS(F118) -> 0 | F118: =C118-D118 -> 0 | G118: =SUM(G116:G117) -> 0 | H118: =SUM(H116:H117) -> 0 | I118: =ABS(J118) -> 0 | J118: =G118-H118 -> 0
A119: =报表格式!G61 -> 负债和股东权益合计 | B119: =B118+1 -> 111 | C119: =SUM(C103,C118) -> 0 | D119: =SUM(D103,D118) -> 0 | E119: =ABS(F119) -> 0 | F119: =C119-D119 -> 0 | G119: =SUM(G103,G118) -> 0 | H119: =SUM(H103,H118) -> 0 | I119: =ABS(J119) -> 0 | J119: =G119-H119 -> 0
A122: 资产负债平衡 | C122: =C60-C119 -> 0 | D122: =D60-D119 -> 0 | E122: =E60-E119 -> 0 | F122: =F60-F119 -> 0 | G122: =G60-G119 -> 0 | H122: =H60-H119 -> 0 | I122: =I60-I119 -> 0 | J122: =J60-J119 -> 0
A123: 未分配利润B/S与P/L核对 | C123: =C115-期初核对PL!C89 -> 0 | D123: =D115-期初核对PL!D89 -> 0 | E123: =E115-期初核对PL!E89 -> 0 | F123: =F115-期初核对PL!F89 -> 0 | G123: =G115-期初核对PL!C178 -> 0 | H123: =H115-期初核对PL!D178 -> 0 | I123: =I115-期初核对PL!E178 -> 0 | J123: =J115-期初核对PL!F178 -> 0

Sheet 期初核对PL
A1: =IF(AND(ABS(F72)<0.005,ABS(F89)<0.005),"期初合并金额核对一致","期初合并金额核对不符！") -> 期初合并金额核对一致 | C1: =IF(AND(ABS(F161)<0.005,ABS(F178)<0.005),"期初母公司金额核对一致","期初母公司金额核对不符！") -> 期初母公司金额核对一致
A2: 利润及利润分配表期初核对－合并
A4: =IF(报表格式!G58=""," 对不起，请到参数表中确定报表类型！",CONCATENATE(" 客户名称：",说明!E23)) -> 客户名称： | B4: =说明!$E$30 -> 2019年度 | F4: =CONCATENATE("金额单位：",说明!$E$33) -> 金额单位：人民币元
A5: =IF(AND(E69<0.005,E70<0.005),"项 目","合并明细项目不符！") -> 项 目 | B5: 行次 | C5: 本年上期数 ① | D5: 上期审定数 ② | E5: 辅助列 | F5: 差异 ①-②
A6: =报表格式!L5 -> 一、营业收入 | B6: 1 | D6: =上年PL审定!B6 -> 0 | E6: =ABS(F6) -> 0 | F6: =C6-D6 -> 0
A7: =报表格式!L6 -> 其中：主营业务收入 | B7: 2 | D7: =上年PL审定!B7 -> 0 | E7: =ABS(F7) -> 0 | F7: =C7-D7 -> 0
A8: =报表格式!L7 -> 利息收入 | B8: 3 | D8: =上年PL审定!B8 -> 0 | E8: =ABS(F8) -> 0 | F8: =C8-D8 -> 0
A9: =报表格式!L8 -> 已赚保费 | B9: 4 | D9: =上年PL审定!B9 -> 0 | E9: =ABS(F9) -> 0 | F9: =C9-D9 -> 0
A10: =报表格式!L9 -> 手续费及佣金收入 | B10: 5 | D10: =上年PL审定!B10 -> 0 | E10: =ABS(F10) -> 0 | F10: =C10-D10 -> 0
A11: =报表格式!L10 -> 其他业务收入 | B11: 6 | D11: =上年PL审定!B11 -> 0 | E11: =ABS(F11) -> 0 | F11: =C11-D11 -> 0
A12: =报表格式!L11 -> 减：营业成本 | B12: 7 | D12: =上年PL审定!B12 -> 0 | E12: =ABS(F12) -> 0 | F12: =C12-D12 -> 0
A13: =报表格式!L12 -> 其中：主营业务成本 | B13: 8 | D13: =上年PL审定!B13 -> 0 | E13: =ABS(F13) -> 0 | F13: =C13-D13 -> 0
A14: =报表格式!L13 -> 利息支出 | B14: 9 | D14: =上年PL审定!B14 -> 0 | E14: =ABS(F14) -> 0 | F14: =C14-D14 -> 0
A15: =报表格式!L14 -> 手续费及佣金支出 | B15: 10 | D15: =上年PL审定!B15 -> 0 | E15: =ABS(F15) -> 0 | F15: =C15-D15 -> 0
A16: =报表格式!L15 -> 退保金 | B16: 11 | D16: =上年PL审定!B16 -> 0 | E16: =ABS(F16) -> 0 | F16: =C16-D16 -> 0
A17: =报表格式!L16 -> 赔付支出净额 | B17: 12 | D17: =上年PL审定!B17 -> 0 | E17: =ABS(F17) -> 0 | F17: =C17-D17 -> 0
... A37: =报表格式!L36 -> 资产处置收益(损失以“-”号填列） | B37: 32 | D37: =上年PL审定!B37 -> 0 | E37: =ABS(F37) -> 0 | F37: =C37-D37 -> 0
A38: =报表格式!L37 -> 二、营业利润（亏损以“－”号填列） | B38: 33 | C38: =SUM(C6)-SUM(C12,C22:C26)+SUM(C29:C30)+SUM(C33:C37) -> 0 | D38: =SUM(D6)-SUM(D12,D22:D26)+SUM(D29:D30)+SUM(D33:D37) -> 0 | E38: =SUM(E6)-SUM(E12,E22:E26)+SUM(E29:E30)+SUM(E33:E37) -> 0 | F38: =SUM(F6)-SUM(F12,F22:F26)+SUM(F29:F30)+SUM(F33:F37) -> 0
A39: =报表格式!L38 -> 加：营业外收入 | B39: 34 | D39: =上年PL审定!B39 -> 0 | E39: =ABS(F39) -> 0 | F39: =C39-D39 -> 0
A40: =报表格式!L39 -> 减：营业外支出 | B40: 35 | D40: =上年PL审定!B40 -> 0 | E40: =ABS(F40) -> 0 | F40: =C40-D40 -> 0
A41: =报表格式!L40 -> 三、利润总额（亏损总额以“－”号填列） | B41: 36 | C41: =SUM(C38)+SUM(C39)-SUM(C40) -> 0 | D41: =SUM(D38)+SUM(D39)-SUM(D40) -> 0 | E41: =ABS(F41) -> 0 | F41: =C41-D41 -> 0
A42: =报表格式!L41 -> 减：所得税费用 | B42: 37 | D42: =上年PL审定!B42 -> 0 | E42: =ABS(F42) -> 0 | F42: =C42-D42 -> 0
A43: =报表格式!L42 -> 0 | B43: 38 | D43: =上年PL审定!B43 -> 0 | E43: =ABS(F43) -> 0 | F43: =C43-D43 -> 0
A44: =报表格式!L43 -> 四、净利润（净亏损以“－”号填列） | B44: 39 | C44: =C41-C42-C43 -> 0 | D44: =D41-D42-D43 -> 0 | E44: =ABS(F44) -> 0 | F44: =C44-D44 -> 0
A45: =报表格式!L44 -> （一）按经营持续性分类 | B45: 40
A46: =报表格式!L45 -> 其中：持续经营净利润（净亏损以“-”号填列） | B46: 41 | D46: =上年PL审定!B46 -> 0 | E46: =ABS(F46) -> 0 | F46: =C46-D46 -> 0
A47: =报表格式!L46 -> 终止经营净利润（净亏损以“-”号填列） | B47: 42 | D47: =上年PL审定!B47 -> 0 | E47: =ABS(F47) -> 0 | F47: =C47-D47 -> 0
A48: =报表格式!L47 -> （二）按所有权归属分类 | B48: 43
A49: =报表格式!L48 -> 其中：归属于母公司股东的净利润（净亏损以“-”号填列） | B49: 44 | C49: =C44-C50 -> 0 | D49: =上年PL审定!B49 -> 0 | E49: =ABS(F49) -> 0 | F49: =C49-D49 -> 0
A50: =报表格式!L49 -> 少数股东损益（净亏损以“-”号填列） | B50: 45 | D50: =上年PL审定!B50 -> 0 | E50: =ABS(F50) -> 0 | F50: =C50-D50 -> 0
A51: =报表格式!L50 -> 五、其他综合收益的税后净额 | B51: 46 | C51: =C52+C71 -> 0 | D51: =D52+D71 -> 0 | F51: =C51-D51 -> 0
A52: =报表格式!L51 -> 归属于母公司股东的其他综合收益的税后净额 | B52: 47 | C52: =C53+C59 -> 0 | D52: =D53+D59 -> 0 | E52: =ABS(F52) -> 0 | F52: =C52-D52 -> 0
A53: =报表格式!L52 -> （一）不能重分类进损益的其他综合收益 | B53: 48 | C53: =SUM(C54:C58) -> 0 | D53: =SUM(D54:D58) -> 0 | E53: =ABS(F53) -> 0 | F53: =C53-D53 -> 0
A54: =报表格式!L53 -> 1.重新计量设定受益计划变动额 | B54: 49 | D54: =上年PL审定!B54 -> 0 | E54: =ABS(F54) -> 0 | F54: =C54-D54 -> 0
A55: =报表格式!L54 -> 2.权益法下不能转损益的其他综合收益 | B55: 50 | D55: =上年PL审定!B55 -> 0 | E55: =ABS(F55) -> 0 | F55: =C55-D55 -> 0
A56: =报表格式!L55 -> 3.其他权益工具投资公允价值变动 | B56: 51 | D56: =上年PL审定!B56 -> 0 | E56: =ABS(F56) -> 0 | F56: =C56-D56 -> 0
A57: =报表格式!L56 -> 4.企业自身信用风险公允价值变动 | B57: 52 | D57: =上年PL审定!B57 -> 0 | E57: =ABS(F57) -> 0 | F57: =C57-D57 -> 0
A58: =报表格式!L57 -> 5.其他 | B58: 53 | D58: =上年PL审定!B58 -> 0 | E58: =ABS(F58) -> 0 | F58: =C58-D58 -> 0
A59: =报表格式!L58 -> （二）将重分类进损益的其他综合收益 | B59: 54 | C59: =SUM(C60:C70) -> 0 | D59: =SUM(D60:D70) -> 0 | E59: =ABS(F59) -> 0 | F59: =C59-D59 -> 0
A60: =报表格式!L59 -> 1.权益法下可转损益的其他综合收益 | B60: 55 | D60: =上年PL审定!B60 -> 0 | E60: =ABS(F60) -> 0 | F60: =C60-D60 -> 0
A61: =报表格式!L60 -> 2.其他债权投资公允价值变动 | B61: 56 | D61: =上年PL审定!B61 -> 0 | E61: =ABS(F61) -> 0 | F61: =C61-D61 -> 0
A62: =报表格式!L61 -> 3.可供出售金融资产公允价值变动损益 | B62: 57 | D62: =上年PL审定!B62 -> 0 | E62: =ABS(F62) -> 0 | F62: =C62-D62 -> 0
A63: =报表格式!L62 -> 4.金融资产重分类计入其他综合收益的金额 | B63: 58 | D63: =上年PL审定!B63 -> 0 | E63: =ABS(F63) -> 0 | F63: =C63-D63 -> 0
A64: =报表格式!L63 -> 5.持有至到期投资重分类为可供出售金融资产损益 | B64: 59 | D64: =上年PL审定!B64 -> 0 | E64: =ABS(F64) -> 0 | F64: =C64-D64 -> 0
A65: =报表格式!L64 -> 6.其他债权投资信用减值准备 | B65: 60 | D65: =上年PL审定!B65 -> 0 | E65: =ABS(F65) -> 0 | F65: =C65-D65 -> 0
A66: =报表格式!L65 -> 7.现金流量套期储备 | B66: 61 | D66: =上年PL审定!B66 -> 0 | E66: =ABS(F66) -> 0 | F66: =C66-D66 -> 0
A67: =报表格式!L66 -> 8.外币财务报表折算差额 | B67: 62 | D67: =上年PL审定!B67 -> 0 | E67: =ABS(F67) -> 0 | F67: =C67-D67 -> 0
A68: =报表格式!L67 -> 9.自用房地产或作为存货的房地产转换为以公允价值计量的投资性房地产在转换日公允价值大于账面价值部分 | B68: 63 | D68: =上年PL审定!B68 -> 0 | E68: =ABS(F68) -> 0 | F68: =C68-D68 -> 0
A69: =报表格式!L68 -> 10.多次交易分步处置子公司股权构成一揽子交易的，丧失控制权之前各次交易处置价款与对应净资产账面价值份额的差额 | B69: 64 | D69: =上年PL审定!B69 -> 0 | E69: =ABS(F69) -> 0 | F69: =C69-D69 -> 0
A70: =报表格式!L69 -> 11.其他 | B70: 65 | D70: =上年PL审定!B70 -> 0 | E70: =ABS(F70) -> 0 | F70: =C70-D70 -> 0
A71: =报表格式!L70 -> 归属于少数股东的其他综合收益的税后净额 | B71: 66 | D71: =上年PL审定!B71 -> 0 | E71: =ABS(F71) -> 0 | F71: =C71-D71 -> 0
A72: =报表格式!L71 -> 六、综合收益总额 | B72: 67 | C72: =C44+C51 -> 0 | D72: =D44+D51 -> 0 | E72: =ABS(F72) -> 0 | F72: =C72-D72 -> 0
A73: =报表格式!L72 -> 归属于母公司股东的综合收益总额 | B73: 68 | C73: =C49+C52 -> 0 | D73: =D49+D52 -> 0 | F73: =C73-D73 -> 0
A74: =报表格式!L73 -> 归属于少数股东的综合收益总额 | B74: 69 | C74: =C50+C71 -> 0 | D74: =D50+D71 -> 0 | F74: =C74-D74 -> 0
A75: =报表格式!L74 -> 七、每股收益 | B75: 70 | F75: =C75-D75 -> 0
A76: =报表格式!L75 -> （一）基本每股收益 | B76: 71 | D76: =上年PL审定!B76 -> 0 | E76: =ABS(F76) -> 0 | F76: =C76-D76 -> 0
A77: =报表格式!L76 -> （二）稀释每股收益 | B77: 72 | D77: =上年PL审定!B77 -> 0 | E77: =ABS(F77) -> 0 | F77: =C77-D77 -> 0
A78: =报表格式!L77 -> 八、利润分配 | B78: 73 | D78: =上年PL审定!B78 -> 0 | E78: =ABS(F78) -> 0 | F78: =C78-D78 -> 0
A79: =报表格式!L78 -> （一）年初未分配利润 | B79: 74 | D79: =上年PL审定!B79 -> 0 | E79: =ABS(F79) -> 0 | F79: =C79-D79 -> 0
A80: =报表格式!L79 -> （二）可供分配的利润 | B80: 75 | C80: =C49+C79 -> 0 | D80: =D49+D79 -> 0 | E80: =ABS(F80) -> 0 | F80: =C80-D80 -> 0
A81: =报表格式!L80 -> 1、提取法定盈余公积 | B81: 76 | D81: =上年PL审定!B81 -> 0 | E81: =ABS(F81) -> 0 | F81: =C81-D81 -> 0
A82: =报表格式!L81 -> 2、其他 | B82: 77 | D82: =上年PL审定!B82 -> 0 | E82: =ABS(F82) -> 0 | F82: =C82-D82 -> 0
A83: =报表格式!L82 -> （三）可供投资者分配的利润 | B83: 78 | C83: =C80-C81-C82 -> 0 | D83: =D80-D81-D82 -> 0 | E83: =ABS(F83) -> 0 | F83: =C83-D83 -> 0
A84: =报表格式!L83 -> 1、应付优先股股利 | B84: 79 | D84: =上年PL审定!B84 -> 0 | E84: =ABS(F84) -> 0 | F84: =C84-D84 -> 0
A85: =报表格式!L84 -> 2、提取任意盈余公积 | B85: 80 | D85: =上年PL审定!B85 -> 0 | E85: =ABS(F85) -> 0 | F85: =C85-D85 -> 0
A86: =报表格式!L85 -> 3、应付普通股股利（应付利润） | B86: 81 | D86: =上年PL审定!B86 -> 0 | E86: =ABS(F86) -> 0 | F86: =C86-D86 -> 0
A87: =报表格式!L86 -> 4、转作资本（或股本）的普通股股利 | B87: 82 | D87: =上年PL审定!B87 -> 0 | E87: =ABS(F87) -> 0 | F87: =C87-D87 -> 0
A88: =报表格式!L87 -> 5、其他 | B88: 83 | D88: =上年PL审定!B88 -> 0 | E88: =ABS(F88) -> 0 | F88: =C88-D88 -> 0
A89: =报表格式!L88 -> 九、未分配利润 | B89: 84 | C89: =C83-SUM(C84:C88) -> 0 | D89: =D83-SUM(D84:D88) -> 0 | E89: =ABS(F89) -> 0 | F89: =C89-D89 -> 0
A91: 利润及利润分配表期初核对－母公司
A93: =IF(报表格式!G58=""," 对不起，请到参数表中确定报表类型！",CONCATENATE(" 客户名称：",说明!E23)) -> 客户名称： | B93: =说明!$E$30 -> 2019年度 | F93: =CONCATENATE("金额单位：",说明!$E$33) -> 金额单位：人民币元
A94: =IF(AND(E163<0.005,E164<0.005),"项 目","母公司明细项目不符！") -> 项 目 | B94: 行次 | C94: 本年上期数 ① | D94: 上期审定数 ② | E94: 辅助列 | F94: 差异 ①-②
A95: =报表格式!L5 -> 一、营业收入 | B95: 1 | D95: =上年PL审定!F6 -> 0 | E95: =ABS(F95) -> 0 | F95: =C95-D95 -> 0
A96: =报表格式!L6 -> 其中：主营业务收入 | B96: 2 | D96: =上年PL审定!F7 -> 0 | E96: =ABS(F96) -> 0 | F96: =C96-D96 -> 0
A97: =报表格式!L7 -> 利息收入 | B97: 3 | D97: =上年PL审定!F8 -> 0 | E97: =ABS(F97) -> 0 | F97: =C97-D97 -> 0
A98: =报表格式!L8 -> 已赚保费 | B98: 4 | D98: =上年PL审定!F9 -> 0 | E98: =ABS(F98) -> 0 | F98: =C98-D98 -> 0
A99: =报表格式!L9 -> 手续费及佣金收入 | B99: 5 | D99: =上年PL审定!F10 -> 0 | E99: =ABS(F99) -> 0 | F99: =C99-D99 -> 0
A100: =报表格式!L10 -> 其他业务收入 | B100: 6 | D100: =上年PL审定!F11 -> 0 | E100: =ABS(F100) -> 0 | F100: =C100-D100 -> 0
A101: =报表格式!L11 -> 减：营业成本 | B101: 7 | D101: =上年PL审定!F12 -> 0 | E101: =ABS(F101) -> 0 | F101: =C101-D101 -> 0
A102: =报表格式!L12 -> 其中：主营业务成本 | B102: 8 | D102: =上年PL审定!F13 -> 0 | E102: =ABS(F102) -> 0 | F102: =C102-D102 -> 0
A103: =报表格式!L13 -> 利息支出 | B103: 9 | D103: =上年PL审定!F14 -> 0 | E103: =ABS(F103) -> 0 | F103: =C103-D103 -> 0
A104: =报表格式!L14 -> 手续费及佣金支出 | B104: 10 | D104: =上年PL审定!F15 -> 0 | E104: =ABS(F104) -> 0 | F104: =C104-D104 -> 0
A105: =报表格式!L15 -> 退保金 | B105: 11 | D105: =上年PL审定!F16 -> 0 | E105: =ABS(F105) -> 0 | F105: =C105-D105 -> 0
A106: =报表格式!L16 -> 赔付支出净额 | B106: 12 | D106: =上年PL审定!F17 -> 0 | E106: =ABS(F106) -> 0 | F106: =C106-D106 -> 0
... A126: =报表格式!L36 -> 资产处置收益(损失以“-”号填列） | B126: 32 | D126: =上年PL审定!F37 -> 0 | E126: =ABS(F126) -> 0 | F126: =C126-D126 -> 0
A127: =报表格式!L37 -> 二、营业利润（亏损以“－”号填列） | B127: 33 | C127: =SUM(C95)-SUM(C101,C111:C115,C119,C120)+SUM(C121,C122,C124:C126) -> 0 | D127: =SUM(D95)-SUM(D101,D111:D115,D119,D120)+SUM(D121,D122,D124:D126) -> 0 | E127: =ABS(F127) -> 0 | F127: =SUM(F95)-SUM(F101,F111:F115,F119,F120)+SUM(F121,F122,F124:F126) -> 0
A128: =报表格式!L38 -> 加：营业外收入 | B128: 34 | D128: =上年PL审定!F39 -> 0 | E128: =ABS(F128) -> 0 | F128: =C128-D128 -> 0
A129: =报表格式!L39 -> 减：营业外支出 | B129: 35 | D129: =上年PL审定!F40 -> 0 | E129: =ABS(F129) -> 0 | F129: =C129-D129 -> 0
A130: =报表格式!L40 -> 三、利润总额（亏损总额以“－”号填列） | B130: 36 | C130: =SUM(C127)+SUM(C128)-SUM(C129) -> 0 | D130: =SUM(D127)+SUM(D128)-SUM(D129) -> 0 | E130: =ABS(F130) -> 0 | F130: =C130-D130 -> 0
A131: =报表格式!L41 -> 减：所得税费用 | B131: 37 | D131: =上年PL审定!F42 -> 0 | E131: =ABS(F131) -> 0 | F131: =C131-D131 -> 0
A132: =报表格式!L42 -> 0 | B132: 38 | D132: =上年PL审定!F43 -> 0 | E132: =ABS(F132) -> 0 | F132: =C132-D132 -> 0
A133: =报表格式!L43 -> 四、净利润（净亏损以“－”号填列） | B133: 39 | C133: =C130-C131-C132 -> 0 | D133: =D130-D131-D132 -> 0 | E133: =ABS(F133) -> 0 | F133: =C133-D133 -> 0
A134: =报表格式!L44 -> （一）按经营持续性分类 | B134: 40
A135: =报表格式!L45 -> 其中：持续经营净利润（净亏损以“-”号填列） | B135: 41 | D135: =上年PL审定!F46 -> 0 | E135: =ABS(F135) -> 0 | F135: =C135-D135 -> 0
A136: =报表格式!L46 -> 终止经营净利润（净亏损以“-”号填列） | B136: 42 | D136: =上年PL审定!F47 -> 0 | E136: =ABS(F136) -> 0 | F136: =C136-D136 -> 0
A137: =报表格式!L47 -> （二）按所有权归属分类 | B137: 43
A138: =报表格式!L48 -> 其中：归属于母公司股东的净利润（净亏损以“-”号填列） | B138: 44 | C138: =C133-C139 -> 0 | D138: =上年PL审定!F49 -> 0 | E138: =ABS(F138) -> 0 | F138: =C138-D138 -> 0
A139: =报表格式!L49 -> 少数股东损益（净亏损以“-”号填列） | B139: 45 | D139: =上年PL审定!F50 -> 0 | E139: =ABS(F139) -> 0 | F139: =C139-D139 -> 0
A140: =报表格式!L50 -> 五、其他综合收益的税后净额 | B140: 46 | C140: =C141+C160 -> 0 | D140: =上年PL审定!F51 -> 0 | E140: =ABS(F140) -> 0 | F140: =C140-D140 -> 0
A141: =报表格式!L51 -> 归属于母公司股东的其他综合收益的税后净额 | B141: 47 | C141: =C142+C148 -> 0 | D141: =D142+D148 -> 0 | E141: =ABS(F141) -> 0 | F141: =C141-D141 -> 0
...

Sheet 母公司BS汇总
A1: 母公司资产负债表汇总（审定数）
A2: =CONCATENATE("客户名称：",说明!E23) -> 客户名称：
A3: =CONCATENATE("会计时点：",TEXT(说明!E32,"yyyy.mm.dd")) -> 会计时点：2019.12.31
D4: 1 | E4: 2 | F4: 3 | G4: 4 | H4: 5 | I4: 6 | J4: 7 | K4: 8 | L4: 9 | M4: 10
A5: =报表格式!B4 -> 报表项目 | B5: 母公司汇总 | C5: 母公司本部 | D5: 1分公司 | E5: 2分公司 | F5: 3分公司 | G5: 4分公司 | H5: 5分公司 | I5: 6分公司 | J5: 7分公司 | K5: 8分公司 | L5: 9分公司 | M5: 10分公司 | O5: XX分公司
A6: =报表格式!B5 -> 流动资产：
A7: =报表格式!B6 -> 货币资金 | B7: =SUM(C7:O7) -> 0
A8: =报表格式!B7 -> 结算备付金 | B8: =SUM(C8:O8) -> 0
A9: =报表格式!B8 -> 拆出资金 | B9: =SUM(C9:O9) -> 0
A10: =报表格式!B9 -> 交易性金融资产 | B10: =SUM(C10:O10) -> 0
A11: =报表格式!B10 -> 以公允价值计量且其变动计入当期损益的金融资产 | B11: =SUM(C11:O11) -> 0
A12: =报表格式!B11 -> 衍生金融资产 | B12: =SUM(C12:O12) -> 0
A13: =报表格式!B12 -> 应收票据 | B13: =SUM(C13:O13) -> 0
A14: =报表格式!B13 -> 应收账款 | B14: =SUM(C14:O14) -> 0
A15: =报表格式!B14 -> 应收款项融资 | B15: =SUM(C15:O15) -> 0
A16: =报表格式!B15 -> 预付款项 | B16: =SUM(C16:O16) -> 0
A17: =报表格式!B16 -> 应收保费 | B17: =SUM(C17:O17) -> 0
A18: =报表格式!B17 -> 应收分保账款 | B18: =SUM(C18:O18) -> 0
... A30: =报表格式!B29 -> 0 | B30: =SUM(C30:O30) -> 0
A31: =报表格式!B30 -> 流动资产合计 | B31: =SUM(C31:O31) -> 0 | C31: =SUM(C7:C30)-C21-C22 -> 0 | D31: =SUM(D7:D29)-D21-D22 -> 0 | E31: =SUM(E7:E29)-E21-E22 -> 0 | F31: =SUM(F7:F29)-F21-F22 -> 0 | G31: =SUM(G7:G29)-G21-G22 -> 0 | H31: =SUM(H7:H29)-H21-H22 -> 0 | I31: =SUM(I7:I29)-I21-I22 -> 0 | J31: =SUM(J7:J29)-J21-J22 -> 0 | K31: =SUM(K7:K29)-K21-K22 -> 0 | ... O31: =SUM(O7:O29)-O21-O22 -> 0
A32: =报表格式!B31 -> 非流动资产:
A33: =报表格式!B32 -> 发放贷款及垫款 | B33: =SUM(C33:O33) -> 0
A34: =报表格式!B33 -> 债权投资 | B34: =SUM(C34:O34) -> 0
A35: =报表格式!B34 -> 可供出售金融资产 | B35: =SUM(C35:O35) -> 0
A36: =报表格式!B35 -> 其他债权投资 | B36: =SUM(C36:O36) -> 0
A37: =报表格式!B36 -> 持有至到期投资 | B37: =SUM(C37:O37) -> 0
A38: =报表格式!B37 -> 长期应收款 | B38: =SUM(C38:O38) -> 0
A39: =报表格式!B38 -> 设定受益计划净资产 | B39: =SUM(C39:O39) -> 0
A40: =报表格式!B39 -> 长期股权投资 | B40: =SUM(C40:O40) -> 0
A41: =报表格式!B40 -> 其他权益工具投资 | B41: =SUM(C41:O41) -> 0
A42: =报表格式!B41 -> 其他非流动金融资产 | B42: =SUM(C42:O42) -> 0
A43: =报表格式!B42 -> 投资性房地产 | B43: =SUM(C43:O43) -> 0
A44: =报表格式!B43 -> 固定资产 | B44: =SUM(C44:O44) -> 0
... A57: =报表格式!B56 -> 0 | B57: =SUM(C57:O57) -> 0
A58: =报表格式!B57 -> 非流动资产合计 | B58: =SUM(C58:O58) -> 0 | C58: =SUM(C33:C57) -> 0 | D58: =SUM(D34:D57) -> 0 | E58: =SUM(E34:E57) -> 0 | F58: =SUM(F34:F57) -> 0 | G58: =SUM(G34:G57) -> 0 | H58: =SUM(H34:H57) -> 0 | I58: =SUM(I34:I57) -> 0 | J58: =SUM(J34:J57) -> 0 | K58: =SUM(K34:K57) -> 0 | ... O58: =SUM(O34:O57) -> 0
A59: =报表格式!B58 -> 资 产 总 计 | B59: =SUM(C59:O59) -> 0 | C59: =SUM(C31,C58) -> 0 | D59: =SUM(D31,D58) -> 0 | E59: =SUM(E31,E58) -> 0 | F59: =SUM(F31,F58) -> 0 | G59: =SUM(G31,G58) -> 0 | H59: =SUM(H31,H58) -> 0 | I59: =SUM(I31,I58) -> 0 | J59: =SUM(J31,J58) -> 0 | ... O59: =SUM(O31,O58) -> 0
A61: =报表格式!G5 -> 流动负债：
A62: =报表格式!G6 -> 短期借款 | B62: =SUM(C62:O62) -> 0
A63: =报表格式!G7 -> 向中央银行借款 | B63: =SUM(C63:O63) -> 0
A64: =报表格式!G8 -> 吸收存款及同业存放 | B64: =SUM(C64:O64) -> 0
A65: =报表格式!G9 -> 拆入资金 | B65: =SUM(C65:O65) -> 0
A66: =报表格式!G10 -> 交易性金融负债 | B66: =SUM(C66:O66) -> 0
A67: =报表格式!G11 -> 以公允价值计量且其变动计入当期损益的金融负债 | B67: =SUM(C67:O67) -> 0
A68: =报表格式!G12 -> 衍生金融负债 | B68: =SUM(C68:O68) -> 0
A69: =报表格式!G13 -> 应付票据 | B69: =SUM(C69:O69) -> 0
A70: =报表格式!G14 -> 应付账款 | B70: =SUM(C70:O70) -> 0
A71: =报表格式!G15 -> 预收款项 | B71: =SUM(C71:O71) -> 0
A72: =报表格式!G16 -> 卖出回购金融资产款 | B72: =SUM(C72:O72) -> 0
A73: =报表格式!G17 -> 应付手续费及佣金 | B73: =SUM(C73:O73) -> 0
... A86: =报表格式!G30 -> 其他流动负债 | B86: =SUM(C86:O86) -> 0
A87: =报表格式!G31 -> 流动负债合计 | B87: =SUM(C87:O87) -> 0 | C87: =SUM(C62:C86)-C78-C79 -> 0 | D87: =SUM(D62:D86)-D78-D79 -> 0 | E87: =SUM(E62:E86)-E78-E79 -> 0 | F87: =SUM(F62:F86)-F78-F79 -> 0 | G87: =SUM(G62:G86)-G78-G79 -> 0 | H87: =SUM(H62:H86)-H78-H79 -> 0 | I87: =SUM(I62:I86)-I78-I79 -> 0 | J87: =SUM(J62:J86)-J78-J79 -> 0 | ... O87: =SUM(O62:O86)-O78-O79 -> 0
A88: =报表格式!G32 -> 非流动负债:
A89: =报表格式!G33 -> 长期借款 | B89: =SUM(C89:O89) -> 0
A90: =报表格式!G34 -> 应付债券 | B90: =SUM(C90:O90) -> 0
A91: =报表格式!G35 -> 其中：优先股 | B91: =SUM(C91:O91) -> 0
A92: =报表格式!G36 -> 永续债 | B92: =SUM(C92:O92) -> 0
A93: =报表格式!G37 -> 租赁负债 | B93: =SUM(C93:O93) -> 0
A94: =报表格式!G38 -> 长期应付款 | B94: =SUM(C94:O94) -> 0
A95: =报表格式!G39 -> 长期应付职工薪酬 | B95: =SUM(C95:O95) -> 0
A96: =报表格式!G40 -> 预计负债 | B96: =SUM(C96:O96) -> 0
A97: =报表格式!G41 -> 递延收益 | B97: =SUM(C97:O97) -> 0
A98: =报表格式!G42 -> 递延所得税负债 | B98: =SUM(C98:O98) -> 0
A99: =报表格式!G43 -> 其他非流动负债 | B99: =SUM(C99:O99) -> 0
A100: =报表格式!G44 -> 非流动负债合计 | B100: =SUM(C100:O100) -> 0 | C100: =SUM(C89:C99)-C91-C92 -> 0 | D100: =SUM(D89:D99)-D91-D92 -> 0 | E100: =SUM(E89:E99)-E91-E92 -> 0 | F100: =SUM(F89:F99)-F91-F92 -> 0 | G100: =SUM(G89:G99)-G91-G92 -> 0 | H100: =SUM(H89:H99)-H91-H92 -> 0 | I100: =SUM(I89:I99)-I91-I92 -> 0 | J100: =SUM(J89:J99)-J91-J92 -> 0 | ... O100: =SUM(O89:O99)-O91-O92 -> 0
A101: =报表格式!G45 -> 负 债 合 计 | B101: =SUM(C101:O101) -> 0 | C101: =SUM(C87,C100) -> 0 | D101: =SUM(D87,D100) -> 0 | E101: =SUM(E87,E100) -> 0 | F101: =SUM(F87,F100) -> 0 | G101: =SUM(G87,G100) -> 0 | H101: =SUM(H87,H100) -> 0 | I101: =SUM(I87,I100) -> 0 | J101: =SUM(J87,J100) -> 0 | ... O101: =SUM(O87,O100) -> 0
A102: =报表格式!G46 -> 股东权益： | B102: =SUM(C102:O102) -> 0
A103: =报表格式!G47 -> 股本 | B103: =SUM(C103:O103) -> 0
A104: =报表格式!G48 -> 其他权益工具 | B104: =SUM(C104:O104) -> 0
A105: =报表格式!G49 -> 其中：优先股 | B105: =SUM(C105:O105) -> 0
A106: =报表格式!G50 -> 永续债 | B106: =SUM(C106:O106) -> 0
A107: =报表格式!G51 -> 资本公积 | B107: =SUM(C107:O107) -> 0
A108: =报表格式!G52 -> 减：库存股 | B108: =SUM(C108:O108) -> 0
A109: =报表格式!G53 -> 其他综合收益 | B109: =SUM(C109:O109) -> 0
A110: =报表格式!G54 -> 专项储备 | B110: =SUM(C110:O110) -> 0
A111: =报表格式!G55 -> 盈余公积 | B111: =SUM(C111:O111) -> 0
A112: =报表格式!G56 -> 一般风险准备 | B112: =SUM(C112:O112) -> 0
A113: =报表格式!G57 -> 未分配利润 | B113: =SUM(C113:O113) -> 0
A114: =报表格式!G58 -> 归属于母公司股东权益合计 | B114: =SUM(C114:O114) -> 0 | C114: =SUM(C103:C104,C107,-C108,C109:C113) -> 0 | D114: =SUM(D103:D104,D107,-D108,D109:D113) -> 0 | E114: =SUM(E103:E104,E107,-E108,E109:E113) -> 0 | F114: =SUM(F103:F104,F107,-F108,F109:F113) -> 0 | G114: =SUM(G103:G104,G107,-G108,G109:G113) -> 0 | H114: =SUM(H103:H104,H107,-H108,H109:H113) -> 0 | I114: =SUM(I103:I104,I107,-I108,I109:I113) -> 0 | J114: =SUM(J103:J104,J107,-J108,J109:J113) -> 0 | ... O114: =SUM(O103:O104,O107,-O108,O109:O113) -> 0
A115: =报表格式!G59 -> 少数股东权益 | B115: =SUM(C115:O115) -> 0
A116: =报表格式!G60 -> 股东权益合计 | B116: =SUM(C116:O116) -> 0 | C116: =SUM(C114:C115) -> 0 | D116: =SUM(D114:D115) -> 0 | E116: =SUM(E114:E115) -> 0 | F116: =SUM(F114:F115) -> 0 | G116: =SUM(G114:G115) -> 0 | H116: =SUM(H114:H115) -> 0 | I116: =SUM(I114:I115) -> 0 | J116: =SUM(J114:J115) -> 0 | ... O116: =SUM(O114:O115) -> 0
A117: =报表格式!G61 -> 负债和股东权益合计 | B117: =SUM(C117:O117) -> 0 | C117: =SUM(C101,C116) -> 0 | D117: =SUM(D101,D116) -> 0 | E117: =SUM(E101,E116) -> 0 | F117: =SUM(F101,F116) -> 0 | G117: =SUM(G101,G116) -> 0 | H117: =SUM(H101,H116) -> 0 | I117: =SUM(I101,I116) -> 0 | J117: =SUM(J101,J116) -> 0 | ... O117: =SUM(O101,O116) -> 0
A120: 勾稽核对：
A121: 资产负债平衡 | B121: =B59-B117 -> 0 | C121: =C59-C117 -> 0 | D121: =D59-D117 -> 0 | E121: =E59-E117 -> 0 | F121: =F59-F117 -> 0 | G121: =G59-G117 -> 0 | H121: =H59-H117 -> 0 | I121: =I59-I117 -> 0 | ... O121: =O59-O117 -> 0
A122: 检验流动资产公式 | B122: =SUM(B7:B30)-B21-B22-B31 -> 0 | C122: =SUM(C7:C30)-C21-C22-C31 -> 0 | D122: =SUM(D7:D30)-D21-D22-D31 -> 0 | E122: =SUM(E7:E30)-E21-E22-E31 -> 0 | F122: =SUM(F7:F30)-F21-F22-F31 -> 0 | G122: =SUM(G7:G30)-G21-G22-G31 -> 0 | H122: =SUM(H7:H30)-H21-H22-H31 -> 0 | I122: =SUM(I7:I30)-I21-I22-I31 -> 0 | ... O122: =SUM(O7:O30)-O21-O22-O31 -> 0
A123: 检验非流动资产公式 | B123: =SUM(B33:B57)-B58 -> 0 | C123: =SUM(C33:C57)-C58 -> 0 | D123: =SUM(D33:D57)-D58 -> 0 | E123: =SUM(E33:E57)-E58 -> 0 | F123: =SUM(F33:F57)-F58 -> 0 | G123: =SUM(G33:G57)-G58 -> 0 | H123: =SUM(H33:H57)-H58 -> 0 | I123: =SUM(I33:I57)-I58 -> 0 | ... O123: =SUM(O33:O57)-O58 -> 0
A124: 检验总资产公式 | B124: =B31+B58-B59 -> 0 | C124: =C31+C58-C59 -> 0 | D124: =D31+D58-D59 -> 0 | E124: =E31+E58-E59 -> 0 | F124: =F31+F58-F59 -> 0 | G124: =G31+G58-G59 -> 0 | H124: =H31+H58-H59 -> 0 | I124: =I31+I58-I59 -> 0 | ... O124: =O31+O58-O59 -> 0
A125: 检验流动负债公式 | B125: =SUM(B62:B86)-B78-B79-B87 -> 0 | C125: =SUM(C62:C86)-C78-C79-C87 -> 0 | D125: =SUM(D62:D86)-D78-D79-D87 -> 0 | E125: =SUM(E62:E86)-E78-E79-E87 -> 0 | F125: =SUM(F62:F86)-F78-F79-F87 -> 0 | G125: =SUM(G62:G86)-G78-G79-G87 -> 0 | H125: =SUM(H62:H86)-H78-H79-H87 -> 0 | I125: =SUM(I62:I86)-I78-I79-I87 -> 0 | ... O125: =SUM(O62:O86)-O78-O79-O87 -> 0
A126: 检验非流动负债公式 | B126: =SUM(B89:B99)-B91-B92-B100 -> 0 | C126: =SUM(C89:C99)-C91-C92-C100 -> 0 | D126: =SUM(D89:D99)-D91-D92-D100 -> 0 | E126: =SUM(E89:E99)-E91-E92-E100 -> 0 | F126: =SUM(F89:F99)-F91-F92-F100 -> 0 | G126: =SUM(G89:G99)-G91-G92-G100 -> 0 | H126: =SUM(H89:H99)-H91-H92-H100 -> 0 | I126: =SUM(I89:I99)-I91-I92-I100 -> 0 | ... O126: =SUM(O89:O99)-O91-O92-O100 -> 0
A127: 检验总负债公式 | B127: =B87+B100-B101 -> 0 | C127: =C87+C100-C101 -> 0 | D127: =D87+D100-D101 -> 0 | E127: =E87+E100-E101 -> 0 | F127: =F87+F100-F101 -> 0 | G127: =G87+G100-G101 -> 0 | H127: =H87+H100-H101 -> 0 | I127: =I87+I100-I101 -> 0 | ... O127: =O87+O100-O101 -> 0
A128: 检验归属于母公司股东权益公式 | B128: =SUM(B103:B104,B107,-B108,B109:B113)-B114 -> 0 | C128: =SUM(C103:C104,C107,-C108,C109:C113)-C114 -> 0 | D128: =SUM(D103:D104,D107,-D108,D109:D113)-D114 -> 0 | E128: =SUM(E103:E104,E107,-E108,E109:E113)-E114 -> 0 | F128: =SUM(F103:F104,F107,-F108,F109:F113)-F114 -> 0 | G128: =SUM(G103:G104,G107,-G108,G109:G113)-G114 -> 0 | H128: =SUM(H103:H104,H107,-H108,H109:H113)-H114 -> 0 | I128: =SUM(I103:I104,I107,-I108,I109:I113)-I114 -> 0 | ... O128: =SUM(O103:O104,O107,-O108,O109:O113)-O114 -> 0
A129: 检验股东权益公式 | B129: =B114+B115-B116 -> 0 | C129: =C114+C115-C116 -> 0 | D129: =D114+D115-D116 -> 0 | E129: =E114+E115-E116 -> 0 | F129: =F114+F115-F116 -> 0 | G129: =G114+G115-G116 -> 0 | H129: =H114+H115-H116 -> 0 | I129: =I114+I115-I116 -> 0 | ... O129: =O114+O115-O116 -> 0
A130: 检验负债权益公式 | B130: =B101+B116-B117 -> 0 | C130: =C101+C116-C117 -> 0 | D130: =D101+D116-D117 -> 0 | E130: =E101+E116-E117 -> 0 | F130: =F101+F116-F117 -> 0 | G130: =G101+G116-G117 -> 0 | H130: =H101+H116-H117 -> 0 | I130: =I101+I116-I117 -> 0 | ... O130: =O101+O116-O117 -> 0

Sheet 母公司PL汇总
A1: 母公司利润及利润分配表汇总（审定数）
A2: =CONCATENATE("客户名称：",说明!E23) -> 客户名称：
A3: =CONCATENATE("会计期间：",说明!E30) -> 会计期间：2019年度
D4: 1 | E4: 2 | F4: 3 | G4: 4 | H4: 5 | I4: 6 | J4: 7 | K4: 8 | L4: 9 | M4: 10
A5: =报表格式!L4 -> 报表项目 | B5: 母公司汇总 | C5: 母公司本部 | D5: 1分公司 | E5: 2分公司 | F5: 3分公司 | G5: 4分公司 | H5: 5分公司 | I5: 6分公司 | J5: 7分公司 | K5: 8分公司 | L5: 9分公司 | M5: 10分公司 | O5: XX分公司
A6: =报表格式!L5 -> 一、营业收入 | B6: =SUM(C6:O6) -> 0
A7: =报表格式!L6 -> 其中：主营业务收入 | B7: =SUM(C7:O7) -> 0
A8: =报表格式!L7 -> 利息收入 | B8: =SUM(C8:O8) -> 0
A9: =报表格式!L8 -> 已赚保费 | B9: =SUM(C9:O9) -> 0
A10: =报表格式!L9 -> 手续费及佣金收入 | B10: =SUM(C10:O10) -> 0
A11: =报表格式!L10 -> 其他业务收入 | B11: =SUM(C11:O11) -> 0
A12: =报表格式!L11 -> 减：营业成本 | B12: =SUM(C12:O12) -> 0
A13: =报表格式!L12 -> 其中：主营业务成本 | B13: =SUM(C13:O13) -> 0
A14: =报表格式!L13 -> 利息支出 | B14: =SUM(C14:O14) -> 0
A15: =报表格式!L14 -> 手续费及佣金支出 | B15: =SUM(C15:O15) -> 0
A16: =报表格式!L15 -> 退保金 | B16: =SUM(C16:O16) -> 0
A17: =报表格式!L16 -> 赔付支出净额 | B17: =SUM(C17:O17) -> 0
... A37: =报表格式!L36 -> 资产处置收益(损失以“-”号填列） | B37: =SUM(C37:O37) -> 0
A38: =报表格式!L37 -> 二、营业利润（亏损以“－”号填列） | B38: =SUM(C38:O38) -> 0 | C38: =SUM(C6)-SUM(C12,C22:C26)+SUM(C29:C30,C33:C37) -> 0 | D38: =SUM(D6)-SUM(D12,D22:D26)+SUM(D29:D30,D33:D37) -> 0 | E38: =SUM(E6)-SUM(E12,E22:E26)+SUM(E29:E30,E33:E37) -> 0 | F38: =SUM(F6)-SUM(F12,F22:F26)+SUM(F29:F30,F33:F37) -> 0 | G38: =SUM(G6)-SUM(G12,G22:G26)+SUM(G29:G30,G33:G37) -> 0 | H38: =SUM(H6)-SUM(H12,H22:H26)+SUM(H29:H30,H33:H37) -> 0 | I38: =SUM(I6)-SUM(I12,I22:I26)+SUM(I29:I30,I33:I37) -> 0 | J38: =SUM(J6)-SUM(J12,J22:J26)+SUM(J29:J30,J33:J37) -> 0 | ... O38: =SUM(O6)-SUM(O12,O22:O26)+SUM(O29:O30,O33:O37) -> 0
A39: =报表格式!L38 -> 加：营业外收入 | B39: =SUM(C39:O39) -> 0
A40: =报表格式!L39 -> 减：营业外支出 | B40: =SUM(C40:O40) -> 0
A41: =报表格式!L40 -> 三、利润总额（亏损总额以“－”号填列） | B41: =SUM(C41:O41) -> 0 | C41: =SUM(C38)+SUM(C39)-SUM(C40) -> 0 | D41: =SUM(D38)+SUM(D39)-SUM(D40) -> 0 | E41: =SUM(E38)+SUM(E39)-SUM(E40) -> 0 | F41: =SUM(F38)+SUM(F39)-SUM(F40) -> 0 | G41: =SUM(G38)+SUM(G39)-SUM(G40) -> 0 | H41: =SUM(H38)+SUM(H39)-SUM(H40) -> 0 | I41: =SUM(I38)+SUM(I39)-SUM(I40) -> 0 | J41: =SUM(J38)+SUM(J39)-SUM(J40) -> 0 | ... O41: =SUM(O38)+SUM(O39)-SUM(O40) -> 0
A42: =报表格式!L41 -> 减：所得税费用 | B42: =SUM(C42:O42) -> 0
A43: =报表格式!L42 -> 0 | B43: =SUM(C43:O43) -> 0
A44: =报表格式!L43 -> 四、净利润（净亏损以“－”号填列） | B44: =SUM(C44:O44) -> 0 | C44: =C41-C42-C43 -> 0 | D44: =D41-D42-D43 -> 0 | E44: =E41-E42-E43 -> 0 | F44: =F41-F42-F43 -> 0 | G44: =G41-G42-G43 -> 0 | H44: =H41-H42-H43 -> 0 | I44: =I41-I42-I43 -> 0 | J44: =J41-J42-J43 -> 0 | ... O44: =O41-O42-O43 -> 0
A45: =报表格式!L44 -> （一）按经营持续性分类 | B45: =SUM(C45:O45) -> 0
A46: =报表格式!L45 -> 其中：持续经营净利润（净亏损以“-”号填列） | B46: =SUM(C46:O46) -> 0
A47: =报表格式!L46 -> 终止经营净利润（净亏损以“-”号填列） | B47: =SUM(C47:O47) -> 0
A48: =报表格式!L47 -> （二）按所有权归属分类 | B48: =SUM(C48:O48) -> 0
A49: =报表格式!L48 -> 其中：归属于母公司股东的净利润（净亏损以“-”号填列） | B49: =SUM(C49:O49) -> 0 | C49: =C44-C50 -> 0 | D49: =D44-D50 -> 0 | E49: =E44-E50 -> 0 | F49: =F44-F50 -> 0 | G49: =G44-G50 -> 0 | H49: =H44-H50 -> 0 | I49: =I44-I50 -> 0 | J49: =J44-J50 -> 0 | ... O49: =O44-O50 -> 0
A50: =报表格式!L49 -> 少数股东损益（净亏损以“-”号填列） | B50: =SUM(C50:O50) -> 0
A51: =报表格式!L50 -> 五、其他综合收益的税后净额 | B51: =SUM(C51:O51) -> 0 | C51: =C52+C71 -> 0 | D51: =D52+D71 -> 0 | E51: =E52+E71 -> 0 | F51: =F52+F71 -> 0 | G51: =G52+G71 -> 0 | H51: =H52+H71 -> 0 | I51: =I52+I71 -> 0 | J51: =J52+J71 -> 0 | ... O51: =O52+O71 -> 0
A52: =报表格式!L51 -> 归属于母公司股东的其他综合收益的税后净额 | B52: =SUM(C52:O52) -> 0 | C52: =C53+C59 -> 0 | D52: =D53+D59 -> 0 | E52: =E53+E59 -> 0 | F52: =F53+F59 -> 0 | G52: =G53+G59 -> 0 | H52: =H53+H59 -> 0 | I52: =I53+I59 -> 0 | J52: =J53+J59 -> 0 | ... O52: =O53+O59 -> 0
A53: =报表格式!L52 -> （一）不能重分类进损益的其他综合收益 | B53: =SUM(C53:O53) -> 0 | C53: =SUM(C54:C58) -> 0 | D53: =SUM(D54:D58) -> 0 | E53: =SUM(E54:E58) -> 0 | F53: =SUM(F54:F58) -> 0 | G53: =SUM(G54:G58) -> 0 | H53: =SUM(H54:H58) -> 0 | I53: =SUM(I54:I58) -> 0 | J53: =SUM(J54:J58) -> 0 | ... O53: =SUM(O54:O58) -> 0
A54: =报表格式!L53 -> 1.重新计量设定受益计划变动额 | B54: =SUM(C54:O54) -> 0
A55: =报表格式!L54 -> 2.权益法下不能转损益的其他综合收益 | B55: =SUM(C55:O55) -> 0
A56: =报表格式!L55 -> 3.其他权益工具投资公允价值变动 | B56: =SUM(C56:O56) -> 0
A57: =报表格式!L56 -> 4.企业自身信用风险公允价值变动 | B57: =SUM(C57:O57) -> 0
A58: =报表格式!L57 -> 5.其他 | B58: =SUM(C58:O58) -> 0
A59: =报表格式!L58 -> （二）将重分类进损益的其他综合收益 | B59: =SUM(C59:O59) -> 0 | C59: =SUM(C60:C70) -> 0 | D59: =SUM(D60:D70) -> 0 | E59: =SUM(E60:E70) -> 0 | F59: =SUM(F60:F70) -> 0 | G59: =SUM(G60:G70) -> 0 | H59: =SUM(H60:H70) -> 0 | I59: =SUM(I60:I70) -> 0 | J59: =SUM(J60:J70) -> 0 | ... O59: =SUM(O60:O70) -> 0
A60: =报表格式!L59 -> 1.权益法下可转损益的其他综合收益 | B60: =SUM(C60:O60) -> 0
A61: =报表格式!L60 -> 2.其他债权投资公允价值变动 | B61: =SUM(C61:O61) -> 0
A62: =报表格式!L61 -> 3.可供出售金融资产公允价值变动损益 | B62: =SUM(C62:O62) -> 0
A63: =报表格式!L62 -> 4.金融资产重分类计入其他综合收益的金额 | B63: =SUM(C63:O63) -> 0
A64: =报表格式!L63 -> 5.持有至到期投资重分类为可供出售金融资产损益 | B64: =SUM(C64:O64) -> 0
A65: =报表格式!L64 -> 6.其他债权投资信用减值准备 | B65: =SUM(C65:O65) -> 0
A66: =报表格式!L65 -> 7.现金流量套期储备 | B66: =SUM(C66:O66) -> 0
A67: =报表格式!L66 -> 8.外币财务报表折算差额 | B67: =SUM(C67:O67) -> 0
A68: =报表格式!L67 -> 9.自用房地产或作为存货的房地产转换为以公允价值计量的投资性房地产在转换日公允价值大于账面价值部分 | B68: =SUM(C68:O68) -> 0
A69: =报表格式!L68 -> 10.多次交易分步处置子公司股权构成一揽子交易的，丧失控制权之前各次交易处置价款与对应净资产账面价值份额的差额 | B69: =SUM(C69:O69) -> 0
A70: =报表格式!L69 -> 11.其他 | B70: =SUM(C70:O70) -> 0
A71: =报表格式!L70 -> 归属于少数股东的其他综合收益的税后净额 | B71: =SUM(C71:O71) -> 0
A72: =报表格式!L71 -> 六、综合收益总额 | B72: =SUM(C72:O72) -> 0 | C72: =C44+C51 -> 0 | D72: =D44+D51 -> 0 | E72: =E44+E51 -> 0 | F72: =F44+F51 -> 0 | G72: =G44+G51 -> 0 | H72: =H44+H51 -> 0 | I72: =I44+I51 -> 0 | J72: =J44+J51 -> 0 | ... O72: =O44+O51 -> 0
A73: =报表格式!L72 -> 归属于母公司股东的综合收益总额 | B73: =SUM(C73:O73) -> 0 | C73: =C49+C52 -> 0 | D73: =D49+D52 -> 0 | E73: =E49+E52 -> 0 | F73: =F49+F52 -> 0 | G73: =G49+G52 -> 0 | H73: =H49+H52 -> 0 | I73: =I49+I52 -> 0 | J73: =J49+J52 -> 0 | ... O73: =O49+O52 -> 0
A74: =报表格式!L73 -> 归属于少数股东的综合收益总额 | B74: =SUM(C74:O74) -> 0 | C74: =C50+C71 -> 0 | D74: =D50+D71 -> 0 | E74: =E50+E71 -> 0 | F74: =F50+F71 -> 0 | G74: =G50+G71 -> 0 | H74: =H50+H71 -> 0 | I74: =I50+I71 -> 0 | J74: =J50+J71 -> 0 | ... O74: =O50+O71 -> 0
A75: =报表格式!L74 -> 七、每股收益 | B75: =SUM(C75:O75) -> 0
A76: =报表格式!L75 -> （一）基本每股收益 | B76: =SUM(C76:O76) -> 0
A77: =报表格式!L76 -> （二）稀释每股收益 | B77: =SUM(C77:O77) -> 0
A78: =报表格式!L77 -> 八、利润分配 | B78: =SUM(C78:O78) -> 0
A79: =报表格式!L78 -> （一）年初未分配利润 | B79: =SUM(C79:O79) -> 0
A80: =报表格式!L79 -> （二）可供分配的利润 | B80: =SUM(C80:O80) -> 0 | C80: =C49+C79 -> 0 | D80: =D49+D79 -> 0 | E80: =E49+E79 -> 0 | F80: =F49+F79 -> 0 | G80: =G49+G79 -> 0 | H80: =H49+H79 -> 0 | I80: =I49+I79 -> 0 | J80: =J49+J79 -> 0 | ... O80: =O49+O79 -> 0
A81: =报表格式!L80 -> 1、提取法定盈余公积 | B81: =SUM(C81:O81) -> 0
A82: =报表格式!L81 -> 2、其他 | B82: =SUM(C82:O82) -> 0
A83: =报表格式!L82 -> （三）可供投资者分配的利润 | B83: =SUM(C83:O83) -> 0 | C83: =C80-C81-C82 -> 0 | D83: =D80-D81-D82 -> 0 | E83: =E80-E81-E82 -> 0 | F83: =F80-F81-F82 -> 0 | G83: =G80-G81-G82 -> 0 | H83: =H80-H81-H82 -> 0 | I83: =I80-I81-I82 -> 0 | J83: =J80-J81-J82 -> 0 | ... O83: =O80-O81-O82 -> 0
A84: =报表格式!L83 -> 1、应付优先股股利 | B84: =SUM(C84:O84) -> 0
A85: =报表格式!L84 -> 2、提取任意盈余公积 | B85: =SUM(C85:O85) -> 0
A86: =报表格式!L85 -> 3、应付普通股股利（应付利润） | B86: =SUM(C86:O86) -> 0
A87: =报表格式!L86 -> 4、转作资本（或股本）的普通股股利 | B87: =SUM(C87:O87) -> 0
A88: =报表格式!L87 -> 5、其他 | B88: =SUM(C88:O88) -> 0
A89: =报表格式!L88 -> 九、未分配利润 | B89: =SUM(C89:O89) -> 0 | C89: =C83-SUM(C84:C88) -> 0 | D89: =D83-SUM(D84:D88) -> 0 | E89: =E83-SUM(E84:E88) -> 0 | F89: =F83-SUM(F84:F88) -> 0 | G89: =G83-SUM(G84:G88) -> 0 | H89: =H83-SUM(H84:H88) -> 0 | I89: =I83-SUM(I84:I88) -> 0 | J89: =J83-SUM(J84:J88) -> 0 | ... O89: =O83-SUM(O84:O88) -> 0
A92: 勾稽核对：
A93: 检验营业利润公式 | B93: =SUM(B6)-SUM(B12,B22:B26)+SUM(B29:B30,B33:B37)-B38 -> 0 | C93: =SUM(C6)-SUM(C12,C22:C26)+SUM(C29:C30,C33:C37)-C38 -> 0 | D93: =SUM(D6)-SUM(D12,D22:D26)+SUM(D29:D30,D33:D37)-D38 -> 0 | E93: =SUM(E6)-SUM(E12,E22:E26)+SUM(E29:E30,E33:E37)-E38 -> 0 | F93: =SUM(F6)-SUM(F12,F22:F26)+SUM(F29:F30,F33:F37)-F38 -> 0 | G93: =SUM(G6)-SUM(G12,G22:G26)+SUM(G29:G30,G33:G37)-G38 -> 0 | H93: =SUM(H6)-SUM(H12,H22:H26)+SUM(H29:H30,H33:H37)-H38 -> 0 | I93: =SUM(I6)-SUM(I12,I22:I26)+SUM(I29:I30,I33:I37)-I38 -> 0 | ... O93: =SUM(O6)-SUM(O12,O22:O26)+SUM(O29:O30,O33:O37)-O38 -> 0
A94: 检验利润总额公式 | B94: =SUM(B38,B39,-B40)-B41 -> 0 | C94: =SUM(C38,C39,-C40)-C41 -> 0 | D94: =SUM(D38,D39,-D40)-D41 -> 0 | E94: =SUM(E38,E39,-E40)-E41 -> 0 | F94: =SUM(F38,F39,-F40)-F41 -> 0 | G94: =SUM(G38,G39,-G40)-G41 -> 0 | H94: =SUM(H38,H39,-H40)-H41 -> 0 | I94: =SUM(I38,I39,-I40)-I41 -> 0 | ... O94: =SUM(O38,O39,-O40)-O41 -> 0
A95: 检验净利润公式 | B95: =SUM(B41,-B42,-B43)-B44 -> 0 | C95: =SUM(C41,-C42,-C43)-C44 -> 0 | D95: =SUM(D41,-D42,-D43)-D44 -> 0 | E95: =SUM(E41,-E42,-E43)-E44 -> 0 | F95: =SUM(F41,-F42,-F43)-F44 -> 0 | G95: =SUM(G41,-G42,-G43)-G44 -> 0 | H95: =SUM(H41,-H42,-H43)-H44 -> 0 | I95: =SUM(I41,-I42,-I43)-I44 -> 0 | ... O95: =SUM(O41,-O42,-O43)-O44 -> 0
A96: 检验归属于母公司所有者的净利润公式 | B96: =SUM(B44,-B50)-B49 -> 0 | C96: =SUM(C44,-C50)-C49 -> 0 | D96: =SUM(D44,-D50)-D49 -> 0 | E96: =SUM(E44,-E50)-E49 -> 0 | F96: =SUM(F44,-F50)-F49 -> 0 | G96: =SUM(G44,-G50)-G49 -> 0 | H96: =SUM(H44,-H50)-H49 -> 0 | I96: =SUM(I44,-I50)-I49 -> 0 | ... O96: =SUM(O44,-O50)-O49 -> 0
A97: 检验过属于母公司其他综合收益公式 | B97: =SUM(B54:B58,B60:B70)-B52 -> 0 | C97: =SUM(C54:C58,C60:C70)-C52 -> 0 | D97: =SUM(D54:D58,D60:D70)-D52 -> 0 | E97: =SUM(E54:E58,E60:E70)-E52 -> 0 | F97: =SUM(F54:F58,F60:F70)-F52 -> 0 | G97: =SUM(G54:G58,G60:G70)-G52 -> 0 | H97: =SUM(H54:H58,H60:H70)-H52 -> 0 | I97: =SUM(I54:I58,I60:I70)-I52 -> 0 | ... O97: =SUM(O54:O58,O60:O70)-O52 -> 0
A98: 检验综合收益总额公式 | B98: =SUM(B44,B51)-B72 -> 0 | C98: =SUM(C44,C51)-C72 -> 0 | D98: =SUM(D44,D51)-D72 -> 0 | E98: =SUM(E44,E51)-E72 -> 0 | F98: =SUM(F44,F51)-F72 -> 0 | G98: =SUM(G44,G51)-G72 -> 0 | H98: =SUM(H44,H51)-H72 -> 0 | I98: =SUM(I44,I51)-I72 -> 0 | ... O98: =SUM(O44,O51)-O72 -> 0
A100: 检验营业收入公式 | B100: =SUM(B7:B11)-B6 -> 0 | C100: =SUM(C7:C11)-C6 -> 0 | D100: =SUM(D7:D11)-D6 -> 0 | E100: =SUM(E7:E11)-E6 -> 0 | F100: =SUM(F7:F11)-F6 -> 0 | G100: =SUM(G7:G11)-G6 -> 0 | H100: =SUM(H7:H11)-H6 -> 0 | I100: =SUM(I7:I11)-I6 -> 0 | ... O100: =SUM(O7:O11)-O6 -> 0
A101: 检验营业成本公式 | B101: =SUM(B13:B21)-B12 -> 0 | C101: =SUM(C13:C21)-C12 -> 0 | D101: =SUM(D13:D21)-D12 -> 0 | E101: =SUM(E13:E21)-E12 -> 0 | F101: =SUM(F13:F21)-F12 -> 0 | G101: =SUM(G13:G21)-G12 -> 0 | H101: =SUM(H13:H21)-H12 -> 0 | I101: =SUM(I13:I21)-I12 -> 0 | ... O101: =SUM(O13:O21)-O12 -> 0

Sheet 母公司CF汇总
A1: 母公司现金流量表汇总（审定数）
A2: =CONCATENATE("客户名称：",说明!E23) -> 客户名称：
A3: =CONCATENATE("会计期间：",说明!E30) -> 会计期间：2019年度
D4: 1 | E4: 2 | F4: 3 | G4: 4 | H4: 5 | I4: 6 | J4: 7 | K4: 8 | L4: 9 | M4: 10
A5: =报表格式!Q4 -> 报表项目 | B5: 母公司汇总 | C5: 母公司本部 | D5: 1分公司 | E5: 2分公司 | F5: 3分公司 | G5: 4分公司 | H5: 5分公司 | I5: 6分公司 | J5: 7分公司 | K5: 8分公司 | L5: 9分公司 | M5: 10分公司 | O5: XX分公司
A6: =报表格式!Q5 -> 一、经营活动产生的现金流量
A7: =报表格式!Q6 -> 销售商品、提供劳务收到的现金 | B7: =SUM(C7:O7) -> 0
A8: =报表格式!Q7 -> 客户存款和同业存放款项净增加额 | B8: =SUM(C8:O8) -> 0
A9: =报表格式!Q8 -> 向中央银行借款净增加额 | B9: =SUM(C9:O9) -> 0
A10: =报表格式!Q9 -> 向其他金融机构拆入资金净增加额 | B10: =SUM(C10:O10) -> 0
A11: =报表格式!Q10 -> 收到原保险合同保费取得的现金 | B11: =SUM(C11:O11) -> 0
A12: =报表格式!Q11 -> 收到再保险业务现金净额 | B12: =SUM(C12:O12) -> 0
A13: =报表格式!Q12 -> 保户储金及投资款净增加额 | B13: =SUM(C13:O13) -> 0
A14: =报表格式!Q13 -> 收取利息、手续费及佣金的现金 | B14: =SUM(C14:O14) -> 0
A15: =报表格式!Q14 -> 拆入资金净增加额 | B15: =SUM(C15:O15) -> 0
A16: =报表格式!Q15 -> 回购业务资金净增加额 | B16: =SUM(C16:O16) -> 0
A17: =报表格式!Q16 -> 收到的税费返还 | B17: =SUM(C17:O17) -> 0
A18: =报表格式!Q17 -> 收到的其他与经营活动有关的现金 | B18: =SUM(C18:O18) -> 0
A19: =报表格式!Q18 -> 0 | B19: =SUM(C19:O19) -> 0
A20: =报表格式!Q20 -> 经营活动现金流入小计 | B20: =SUM(C20:O20) -> 0 | C20: =SUM(C7:C19) -> 0 | D20: =SUM(D7:D19) -> 0 | E20: =SUM(E7:E19) -> 0 | F20: =SUM(F7:F19) -> 0 | G20: =SUM(G7:G19) -> 0 | H20: =SUM(H7:H19) -> 0 | I20: =SUM(I7:I19) -> 0 | J20: =SUM(J7:J19) -> 0 | ... O20: =SUM(O7:O19) -> 0
A21: =报表格式!Q21 -> 购买商品、接受劳务支付的现金 | B21: =SUM(C21:O21) -> 0
A22: =报表格式!Q22 -> 客户贷款及垫款净增加额 | B22: =SUM(C22:O22) -> 0
A23: =报表格式!Q23 -> 存放中央银行和同业款项净增加额 | B23: =SUM(C23:O23) -> 0
A24: =报表格式!Q24 -> 支付原保险合同赔付款项的现金 | B24: =SUM(C24:O24) -> 0
A25: =报表格式!Q25 -> 支付利息、手续费及佣金的现金 | B25: =SUM(C25:O25) -> 0
A26: =报表格式!Q26 -> 支付保单红利的现金 | B26: =SUM(C26:O26) -> 0
A27: =报表格式!Q27 -> 支付给职工以及为职工支付的现金 | B27: =SUM(C27:O27) -> 0
A28: =报表格式!Q28 -> 支付各项税费 | B28: =SUM(C28:O28) -> 0
A29: =报表格式!Q29 -> 支付的其他与经营活动有关的现金 | B29: =SUM(C29:O29) -> 0
A30: =报表格式!Q31 -> 经营活动现金流出小计 | B30: =SUM(C30:O30) -> 0 | C30: =SUM(C21:C29) -> 0 | D30: =SUM(D21:D29) -> 0 | E30: =SUM(E21:E29) -> 0 | F30: =SUM(F21:F29) -> 0 | G30: =SUM(G21:G29) -> 0 | H30: =SUM(H21:H29) -> 0 | I30: =SUM(I21:I29) -> 0 | J30: =SUM(J21:J29) -> 0 | ... O30: =SUM(O21:O29) -> 0
A31: =报表格式!Q32 -> 经营活动产生的现金流量净额 | B31: =SUM(C31:O31) -> 0 | C31: =C20-C30 -> 0 | D31: =D20-D30 -> 0 | E31: =E20-E30 -> 0 | F31: =F20-F30 -> 0 | G31: =G20-G30 -> 0 | H31: =H20-H30 -> 0 | I31: =I20-I30 -> 0 | J31: =J20-J30 -> 0 | ... O31: =O20-O30 -> 0
A32: =报表格式!Q33 -> 二、投资活动产生的现金流量
A33: =报表格式!Q34 -> 收回投资所收到的现金 | B33: =SUM(C33:O33) -> 0
A34: =报表格式!Q35 -> 取得投资收益所收到的现金 | B34: =SUM(C34:O34) -> 0
A35: =报表格式!Q36 -> 处置固定资产、无形资产和其他长期资产而收到的现金净额 | B35: =SUM(C35:O35) -> 0
A36: =报表格式!Q37 -> 处置子公司及其他营业单位收到的现金净额 | B36: =SUM(C36:O36) -> 0
A37: =报表格式!Q38 -> 收到其他与投资活动有关的现金 | B37: =SUM(C37:O37) -> 0
A38: =报表格式!Q40 -> 投资活动现金流入小计 | B38: =SUM(B33:B37) -> 0 | C38: =SUM(C33:C37) -> 0 | D38: =SUM(D33:D37) -> 0 | E38: =SUM(E33:E37) -> 0 | F38: =SUM(F33:F37) -> 0 | G38: =SUM(G33:G37) -> 0 | H38: =SUM(H33:H37) -> 0 | I38: =SUM(I33:I37) -> 0 | ... O38: =SUM(O33:O37) -> 0
A39: =报表格式!Q41 -> 购置固定资产、无形资产和其他长期资产所支付现金 | B39: =SUM(C39:O39) -> 0
A40: =报表格式!Q42 -> 投资所支付的现金 | B40: =SUM(C40:O40) -> 0
A41: =报表格式!Q43 -> 质押贷款净增加额 | B41: =SUM(C41:O41) -> 0
A42: =报表格式!Q44 -> 取得子公司及其他营业单位支付的现金净额 | B42: =SUM(C42:O42) -> 0
A43: =报表格式!Q45 -> 支付其他与投资活动有关的现金 | B43: =SUM(C43:O43) -> 0
A44: =报表格式!Q47 -> 投资活动现金流出小计 | B44: =SUM(C44:O44) -> 0 | C44: =SUM(C39:C43) -> 0 | D44: =SUM(D39:D43) -> 0 | E44: =SUM(E39:E43) -> 0 | F44: =SUM(F39:F43) -> 0 | G44: =SUM(G39:G43) -> 0 | H44: =SUM(H39:H43) -> 0 | I44: =SUM(I39:I43) -> 0 | J44: =SUM(J39:J43) -> 0 | ... O44: =SUM(O39:O43) -> 0
A45: =报表格式!Q48 -> 投资活动产生的现金流量净额 | B45: =SUM(C45:O45) -> 0 | C45: =C38-C44 -> 0 | D45: =D38-D44 -> 0 | E45: =E38-E44 -> 0 | F45: =F38-F44 -> 0 | G45: =G38-G44 -> 0 | H45: =H38-H44 -> 0 | I45: =I38-I44 -> 0 | J45: =J38-J44 -> 0 | ... O45: =O38-O44 -> 0
A46: =报表格式!Q49 -> 三、筹资活动产生的现金流量
A47: =报表格式!Q50 -> 吸收投资所收到的现金 | B47: =SUM(C47:O47) -> 0
A48: =报表格式!Q51 -> 其中：子公司吸收少数股东投资收到的现金 | B48: =SUM(C48:O48) -> 0
A49: =报表格式!Q52 -> 取得借款收到的现金 | B49: =SUM(C49:O49) -> 0
A50: =报表格式!Q53 -> 收到的其他与筹资活动有关的现金 | B50: =SUM(C50:O50) -> 0
A51: =报表格式!Q54 -> 0 | B51: =SUM(C51:O51) -> 0
A52: =报表格式!Q55 -> 筹资活动现金流入小计 | B52: =SUM(C52:O52) -> 0 | C52: =SUM(C47:C51)-C48 -> 0 | D52: =SUM(D47:D51)-D48 -> 0 | E52: =SUM(E47:E51)-E48 -> 0 | F52: =SUM(F47:F51)-F48 -> 0 | G52: =SUM(G47:G51)-G48 -> 0 | H52: =SUM(H47:H51)-H48 -> 0 | I52: =SUM(I47:I51)-I48 -> 0 | J52: =SUM(J47:J51)-J48 -> 0 | ... O52: =SUM(O47:O51)-O48 -> 0
A53: =报表格式!Q56 -> 偿还债务支付的现金 | B53: =SUM(C53:O53) -> 0
A54: =报表格式!Q57 -> 分配股利、利润或偿付利息支付的现金 | B54: =SUM(C54:O54) -> 0
A55: =报表格式!Q58 -> 其中：子公司支付给少数股东的股利、利润 | B55: =SUM(C55:O55) -> 0
A56: =报表格式!Q59 -> 支付其他与筹资活动有关的现金 | B56: =SUM(C56:O56) -> 0
A57: =报表格式!Q60 -> 0 | B57: =SUM(C57:O57) -> 0
A58: =报表格式!Q61 -> 筹资活动现金流出小计 | B58: =SUM(C58:O58) -> 0 | C58: =SUM(C53:C57)-C55-C57 -> 0 | D58: =SUM(D53:D57)-D55-D57 -> 0 | E58: =SUM(E53:E57)-E55-E57 -> 0 | F58: =SUM(F53:F57)-F55-F57 -> 0 | G58: =SUM(G53:G57)-G55-G57 -> 0 | H58: =SUM(H53:H57)-H55-H57 -> 0 | I58: =SUM(I53:I57)-I55-I57 -> 0 | J58: =SUM(J53:J57)-J55-J57 -> 0 | ... O58: =SUM(O53:O57)-O55-O57 -> 0
A59: =报表格式!Q62 -> 筹资活动产生的现金流量净额 | B59: =SUM(C59:O59) -> 0 | C59: =C52-C58 -> 0 | D59: =D52-D58 -> 0 | E59: =E52-E58 -> 0 | F59: =F52-F58 -> 0 | G59: =G52-G58 -> 0 | H59: =H52-H58 -> 0 | I59: =I52-I58 -> 0 | J59: =J52-J58 -> 0 | ... O59: =O52-O58 -> 0
A61: =报表格式!Q63 -> 四、汇率变动对现金及现金等价物的影响 | B61: =SUM(C61:O61) -> 0
A62: =报表格式!Q64 -> 五、现金及现金等价物净增加额 | B62: =SUM(C62:O62) -> 0 | C62: =SUM(C31,C45,C59,C61) -> 0 | D62: =SUM(D31,D45,D59,D61) -> 0 | E62: =SUM(E31,E45,E59,E61) -> 0 | F62: =SUM(F31,F45,F59,F61) -> 0 | G62: =SUM(G31,G45,G59,G61) -> 0 | H62: =SUM(H31,H45,H59,H61) -> 0 | I62: =SUM(I31,I45,I59,I61) -> 0 | J62: =SUM(J31,J45,J59,J61) -> 0 | ... O62: =SUM(O31,O45,O59,O61) -> 0
A63: =报表格式!Q65 -> 加：期初现金及现金等价物余额 | B63: =SUM(C63:O63) -> 0
A64: =报表格式!Q66 -> 六、期末现金及现金等价物余额 | B64: =SUM(C64:O64) -> 0 | C64: =C62+C63 -> 0 | D64: =D62+D63 -> 0 | E64: =E62+E63 -> 0 | F64: =F62+F63 -> 0 | G64: =G62+G63 -> 0 | H64: =H62+H63 -> 0 | I64: =I62+I63 -> 0 | J64: =J62+J63 -> 0 | ... O64: =O62+O63 -> 0
A67: =报表格式!U4 -> 补充资料
A68: =报表格式!U5 -> 1、将净利润调节为经营活动现金流量：
A69: =报表格式!U6 -> 净利润 | B69: =SUM(C69:O69) -> 0
A70: =报表格式!U9 -> 加：资产减值损失 | B70: =SUM(C70:O70) -> 0
A71: =报表格式!U10 -> 信用减值损失 | B71: =SUM(C71:O71) -> 0
A72: =报表格式!U11 -> 固定资产折旧、油气资产折耗、生产性生物资产折旧 | B72: =SUM(C72:O72) -> 0
A73: =报表格式!U12 -> 无形资产摊销 | B73: =SUM(C73:O73) -> 0
A74: =报表格式!U13 -> 长期待摊费用摊销 | B74: =SUM(C74:O74) -> 0
A75: =报表格式!U14 -> 处置固定资产、无形资产和其他长期资产的损失（收益以“－”号填列） | B75: =SUM(C75:O75) -> 0
A76: =报表格式!U15 -> 固定资产报废损失（收益以“－”号填列） | B76: =SUM(C76:O76) -> 0
A77: =报表格式!U16 -> 公允价值变动损失（收益以“－”号填列） | B77: =SUM(C77:O77) -> 0
A78: =报表格式!U17 -> 财务费用（收益以“－”号填列） | B78: =SUM(C78:O78) -> 0
A79: =报表格式!U18 -> 投资损失（收益以“－”号填列） | B79: =SUM(C79:O79) -> 0
A80: =报表格式!U19 -> 递延所得税资产减少（增加以“－”号填列） | B80: =SUM(C80:O80) -> 0
A81: =报表格式!U20 -> 递延所得税负债增加（减少以“－”号填列） | B81: =SUM(C81:O81) -> 0
... A84: =报表格式!U23 -> 经营性应付项目的增加（减少以“－”号填列） | B84: =SUM(C84:O84) -> 0
A85: =报表格式!U26 -> 经营活动产生的现金流量净额 | B85: =SUM(B69:B84) -> 0 | C85: =SUM(C69:C84) -> 0 | D85: =SUM(D69:D84) -> 0 | E85: =SUM(E69:E84) -> 0 | F85: =SUM(F69:F84) -> 0 | G85: =SUM(G69:G84) -> 0 | H85: =SUM(H69:H84) -> 0 | I85: =SUM(I69:I84) -> 0 | ... O85: =SUM(O69:O84) -> 0
A86: =报表格式!U27 -> 0
A87: =报表格式!U28 -> 2、不涉及现金收支的投资和筹资活动：
A88: =报表格式!U29 -> 债务转为资本 | B88: =SUM(C88:O88) -> 0
A89: =报表格式!U30 -> 一年内到期的可转换公司债券 | B89: =SUM(C89:O89) -> 0
A90: =报表格式!U31 -> 融资租入固定资产 | B90: =SUM(C90:O90) -> 0
A91: =报表格式!U32 -> 其他 | B91: =SUM(C91:O91) -> 0
A92: =报表格式!U34 -> 0 | B92: =SUM(C92:O92) -> 0
A93: =报表格式!U35 -> 3、现金及现金等价物净变动情况：
A94: =报表格式!U36 -> 现金的期末余额 | B94: =SUM(C94:O94) -> 0
A95: =报表格式!U37 -> 减：现金的期初余额 | B95: =SUM(C95:O95) -> 0
A96: =报表格式!U38 -> 加：现金等价物的期末余额 | B96: =SUM(C96:O96) -> 0
A97: =报表格式!U39 -> 减：现金等价物的期初余额 | B97: =SUM(C97:O97) -> 0
A98: =报表格式!U50 -> 现金及现金等价物净增加额 | B98: =B94-B95+B96-B97 -> 0 | C98: =C94-C95+C96-C97 -> 0 | D98: =D94-D95+D96-D97 -> 0 | E98: =E94-E95+E96-E97 -> 0 | F98: =F94-F95+F96-F97 -> 0 | G98: =G94-G95+G96-G97 -> 0 | H98: =H94-H95+H96-H97 -> 0 | I98: =I94-I95+I96-I97 -> 0 | ... O98: =O94-O95+O96-O97 -> 0
A101: 勾稽核对：
A102: 主表经营活动现金净流量公式 | B102: =SUM(B7:B19)-SUM(B21:B29)-B31 -> 0 | C102: =SUM(C7:C19)-SUM(C21:C29)-C31 -> 0 | D102: =SUM(D7:D19)-SUM(D21:D29)-D31 -> 0 | E102: =SUM(E7:E19)-SUM(E21:E29)-E31 -> 0 | F102: =SUM(F7:F19)-SUM(F21:F29)-F31 -> 0 | G102: =SUM(G7:G19)-SUM(G21:G29)-G31 -> 0 | H102: =SUM(H7:H19)-SUM(H21:H29)-H31 -> 0 | I102: =SUM(I7:I19)-SUM(I21:I29)-I31 -> 0 | ... O102: =SUM(O7:O19)-SUM(O21:O29)-O31 -> 0
A103: 主表投资活动现金净流量公式 | B103: =SUM(B33:B37)-SUM(B39:B43)-B45 -> 0 | C103: =SUM(C33:C37)-SUM(C39:C43)-C45 -> 0 | D103: =SUM(D33:D37)-SUM(D39:D43)-D45 -> 0 | E103: =SUM(E33:E37)-SUM(E39:E43)-E45 -> 0 | F103: =SUM(F33:F37)-SUM(F39:F43)-F45 -> 0 | G103: =SUM(G33:G37)-SUM(G39:G43)-G45 -> 0 | H103: =SUM(H33:H37)-SUM(H39:H43)-H45 -> 0 | I103: =SUM(I33:I37)-SUM(I39:I43)-I45 -> 0 | ... O103: =SUM(O33:O37)-SUM(O39:O43)-O45 -> 0
A104: 主表筹资活动现金净流量公式 | B104: =SUM(B47,B49:B51)-SUM(B53:B54,B56)-B59 -> 0 | C104: =SUM(C47,C49:C51)-SUM(C53:C54,C56)-C59 -> 0 | D104: =SUM(D47,D49:D51)-SUM(D53:D54,D56)-D59 -> 0 | E104: =SUM(E47,E49:E51)-SUM(E53:E54,E56)-E59 -> 0 | F104: =SUM(F47,F49:F51)-SUM(F53:F54,F56)-F59 -> 0 | G104: =SUM(G47,G49:G51)-SUM(G53:G54,G56)-G59 -> 0 | H104: =SUM(H47,H49:H51)-SUM(H53:H54,H56)-H59 -> 0 | I104: =SUM(I47,I49:I51)-SUM(I53:I54,I56)-I59 -> 0 | ... O104: =SUM(O47,O49:O51)-SUM(O53:O54,O56)-O59 -> 0
A105: 主表现金及现金等价物净增加额公式 | B105: =SUM(B31,B45,B59,B61)-B62 -> 0 | C105: =SUM(C31,C45,C59,C61)-C62 -> 0 | D105: =SUM(D31,D45,D59,D61)-D62 -> 0 | E105: =SUM(E31,E45,E59,E61)-E62 -> 0 | F105: =SUM(F31,F45,F59,F61)-F62 -> 0 | G105: =SUM(G31,G45,G59,G61)-G62 -> 0 | H105: =SUM(H31,H45,H59,H61)-H62 -> 0 | I105: =SUM(I31,I45,I59,I61)-I62 -> 0 | ... O105: =SUM(O31,O45,O59,O61)-O62 -> 0
A106: 主表期末现金及现金等价物余额公式 | B106: =B62+B63-B64 -> 0 | C106: =C62+C63-C64 -> 0 | D106: =D62+D63-D64 -> 0 | E106: =E62+E63-E64 -> 0 | F106: =F62+F63-F64 -> 0 | G106: =G62+G63-G64 -> 0 | H106: =H62+H63-H64 -> 0 | I106: =I62+I63-I64 -> 0 | ... O106: =O62+O63-O64 -> 0
A107: 附表经营活动现金流量净额公式 | B107: =SUM(B69:B84)-B85 -> 0 | C107: =SUM(C69:C84)-C85 -> 0 | D107: =SUM(D69:D84)-D85 -> 0 | E107: =SUM(E69:E84)-E85 -> 0 | F107: =SUM(F69:F84)-F85 -> 0 | G107: =SUM(G69:G84)-G85 -> 0 | H107: =SUM(H69:H84)-H85 -> 0 | I107: =SUM(I69:I84)-I85 -> 0 | ... O107: =SUM(O69:O84)-O85 -> 0
...

Sheet 母公司汇总抵销
A1: =IF((L2-(母公司TB资产!C60+母公司TB负债!C63+母公司TB损益!C90)-IF(COUNTIF(E5:E668,"未分配利润")>=1,VLOOKUP("未分配利润",E5:J668,6,0),0))<0.005,"母公司汇总抵销","调整事项未全部链入试算平衡表，请检查调整科目是否为报表项目!") -> 母公司汇总抵销 | K1: =SUM(L2:L3) -> 0 | N1: code | O1: 报表项目
A2: =CONCATENATE("客户名称：",说明!E23) -> 客户名称： | E2: =CONCATENATE("编制人：",说明!E36) -> 编制人： | H2: =CONCATENATE("日期：",TEXT(NOW(),"yyyy.mm.dd")) -> 日期：2019.12.31 | J2: 索引： | K2: 借方调整累计 | L2: =SUMIF(E5:E65538,"?*",J5:J65538) -> 0
A3: =CONCATENATE("会计期间：",说明!E30) -> 会计期间：2019年度 | E3: =CONCATENATE("复核人：",说明!E37) -> 复核人： | H3: 日期： | J3: 页码： | K3: 贷方调整累计 | L3: =SUMIF(H5:H65538,"?*",J5:J65538) -> 0
A4: 序号 | B4: 索引号 | C4: 抵销说明 | D4: code | E4: 借方科目 | F4: 二级科目 | G4: code | H4: 贷方科目 | I4: 二级科目 | J4: 金额 | L4: =L2-L3 -> 0
A5: 1 | E5: =IF(D5=0,"",VLOOKUP(D5,$N:$O,2,0)) | H5: =IF(G5=0,"",VLOOKUP(G5,$N:$O,2,0)) | K5: 本表可根据需要插入行， | N5: =报表格式!Z5 -> 0 | O5: =IF(OR(MID(TRIM(报表格式!AA5),2,1)="：",MID(TRIM(报表格式!AA5),2,1)="、"),REPLACEB(TRIM(报表格式!AA5),1,4,""),TRIM(报表格式!AA5)) -> 流动资产：
E6: =IF(D6=0,"",VLOOKUP(D6,$N:$O,2,0)) | H6: =IF(G6=0,"",VLOOKUP(G6,$N:$O,2,0)) | K6: 请勿删除行。 | N6: =报表格式!Z6 -> D1 | O6: =IF(OR(MID(TRIM(报表格式!AA6),2,1)="：",MID(TRIM(报表格式!AA6),2,1)="、"),REPLACEB(TRIM(报表格式!AA6),1,4,""),TRIM(报表格式!AA6)) -> 货币资金
E7: =IF(D7=0,"",VLOOKUP(D7,$N:$O,2,0)) | H7: =IF(G7=0,"",VLOOKUP(G7,$N:$O,2,0)) | N7: =报表格式!Z7 -> D41 | O7: =IF(OR(MID(TRIM(报表格式!AA7),2,1)="：",MID(TRIM(报表格式!AA7),2,1)="、"),REPLACEB(TRIM(报表格式!AA7),1,4,""),TRIM(报表格式!AA7)) -> 结算备付金
E8: =IF(D8=0,"",VLOOKUP(D8,$N:$O,2,0)) | H8: =IF(G8=0,"",VLOOKUP(G8,$N:$O,2,0)) | N8: =报表格式!Z8 -> D42 | O8: =IF(OR(MID(TRIM(报表格式!AA8),2,1)="：",MID(TRIM(报表格式!AA8),2,1)="、"),REPLACEB(TRIM(报表格式!AA8),1,4,""),TRIM(报表格式!AA8)) -> 拆出资金
E9: =IF(D9=0,"",VLOOKUP(D9,$N:$O,2,0)) | H9: =IF(G9=0,"",VLOOKUP(G9,$N:$O,2,0)) | N9: =报表格式!Z9 -> D2 | O9: =IF(OR(MID(TRIM(报表格式!AA9),2,1)="：",MID(TRIM(报表格式!AA9),2,1)="、"),REPLACEB(TRIM(报表格式!AA9),1,4,""),TRIM(报表格式!AA9)) -> 交易性金融资产
E10: =IF(D10=0,"",VLOOKUP(D10,$N:$O,2,0)) | H10: =IF(G10=0,"",VLOOKUP(G10,$N:$O,2,0)) | N10: =报表格式!Z10 -> D3 | O10: =IF(OR(MID(TRIM(报表格式!AA10),2,1)="：",MID(TRIM(报表格式!AA10),2,1)="、"),REPLACEB(TRIM(报表格式!AA10),1,4,""),TRIM(报表格式!AA10)) -> 以公允价值计量且其变动计入当期损益的金融资产
E11: =IF(D11=0,"",VLOOKUP(D11,$N:$O,2,0)) | H11: =IF(G11=0,"",VLOOKUP(G11,$N:$O,2,0)) | N11: =报表格式!Z11 -> D4 | O11: =IF(OR(MID(TRIM(报表格式!AA11),2,1)="：",MID(TRIM(报表格式!AA11),2,1)="、"),REPLACEB(TRIM(报表格式!AA11),1,4,""),TRIM(报表格式!AA11)) -> 衍生金融资产
E12: =IF(D12=0,"",VLOOKUP(D12,$N:$O,2,0)) | H12: =IF(G12=0,"",VLOOKUP(G12,$N:$O,2,0)) | N12: =报表格式!Z12 -> D5 | O12: =IF(OR(MID(TRIM(报表格式!AA12),2,1)="：",MID(TRIM(报表格式!AA12),2,1)="、"),REPLACEB(TRIM(报表格式!AA12),1,4,""),TRIM(报表格式!AA12)) -> 应收票据
J13: =IF(ABS((SUMIF(E5:E12,"?*",J5:J12)-SUMIF(H5:H12,"?*",J5:J12)))<0.005,"","借贷不等") | N13: =报表格式!Z13 -> D6 | O13: =IF(OR(MID(TRIM(报表格式!AA13),2,1)="：",MID(TRIM(报表格式!AA13),2,1)="、"),REPLACEB(TRIM(报表格式!AA13),1,4,""),TRIM(报表格式!AA13)) -> 应收账款
A14: 2 | E14: =IF(D14=0,"",VLOOKUP(D14,$N:$O,2,0)) | H14: =IF(G14=0,"",VLOOKUP(G14,$N:$O,2,0)) | N14: =报表格式!Z14 -> D7 | O14: =IF(OR(MID(TRIM(报表格式!AA14),2,1)="：",MID(TRIM(报表格式!AA14),2,1)="、"),REPLACEB(TRIM(报表格式!AA14),1,4,""),TRIM(报表格式!AA14)) -> 应收款项融资
E15: =IF(D15=0,"",VLOOKUP(D15,$N:$O,2,0)) | H15: =IF(G15=0,"",VLOOKUP(G15,$N:$O,2,0)) | N15: =报表格式!Z15 -> D8 | O15: =IF(OR(MID(TRIM(报表格式!AA15),2,1)="：",MID(TRIM(报表格式!AA15),2,1)="、"),REPLACEB(TRIM(报表格式!AA15),1,4,""),TRIM(报表格式!AA15)) -> 预付款项
E16: =IF(D16=0,"",VLOOKUP(D16,$N:$O,2,0)) | H16: =IF(G16=0,"",VLOOKUP(G16,$N:$O,2,0)) | N16: =报表格式!Z16 -> D43 | O16: =IF(OR(MID(TRIM(报表格式!AA16),2,1)="：",MID(TRIM(报表格式!AA16),2,1)="、"),REPLACEB(TRIM(报表格式!AA16),1,4,""),TRIM(报表格式!AA16)) -> 应收保费
E17: =IF(D17=0,"",VLOOKUP(D17,$N:$O,2,0)) | H17: =IF(G17=0,"",VLOOKUP(G17,$N:$O,2,0)) | N17: =报表格式!Z17 -> D44 | O17: =IF(OR(MID(TRIM(报表格式!AA17),2,1)="：",MID(TRIM(报表格式!AA17),2,1)="、"),REPLACEB(TRIM(报表格式!AA17),1,4,""),TRIM(报表格式!AA17)) -> 应收分保账款
E18: =IF(D18=0,"",VLOOKUP(D18,$N:$O,2,0)) | H18: =IF(G18=0,"",VLOOKUP(G18,$N:$O,2,0)) | N18: =报表格式!Z18 -> D45 | O18: =IF(OR(MID(TRIM(报表格式!AA18),2,1)="：",MID(TRIM(报表格式!AA18),2,1)="、"),REPLACEB(TRIM(报表格式!AA18),1,4,""),TRIM(报表格式!AA18)) -> 应收分保准备金
E19: =IF(D19=0,"",VLOOKUP(D19,$N:$O,2,0)) | H19: =IF(G19=0,"",VLOOKUP(G19,$N:$O,2,0)) | N19: =报表格式!Z19 -> D9 | O19: =IF(OR(MID(TRIM(报表格式!AA19),2,1)="：",MID(TRIM(报表格式!AA19),2,1)="、"),REPLACEB(TRIM(报表格式!AA19),1,4,""),TRIM(报表格式!AA19)) -> 其他应收款
J20: =IF(ABS((SUMIF(E14:E19,"?*",J14:J19)-SUMIF(H14:H19,"?*",J14:J19)))<0.005,"","借贷不等") | N20: =报表格式!Z20 -> 0 | O20: =IF(OR(MID(TRIM(报表格式!AA20),3,1)="：",MID(TRIM(报表格式!AA20),2,1)="、"),REPLACEB(TRIM(报表格式!AA20),1,6,""),TRIM(报表格式!AA20)) -> 应收利息
A21: 3 | E21: =IF(D21=0,"",VLOOKUP(D21,$N:$O,2,0)) | H21: =IF(G21=0,"",VLOOKUP(G21,$N:$O,2,0)) | N21: =报表格式!Z21 -> 0 | O21: =IF(OR(MID(TRIM(报表格式!AA21),2,1)="：",MID(TRIM(报表格式!AA21),2,1)="、"),REPLACEB(TRIM(报表格式!AA21),1,4,""),TRIM(报表格式!AA21)) -> 应收股利
E22: =IF(D22=0,"",VLOOKUP(D22,$N:$O,2,0)) | H22: =IF(G22=0,"",VLOOKUP(G22,$N:$O,2,0)) | N22: =报表格式!Z22 -> D46 | O22: =IF(OR(MID(TRIM(报表格式!AA22),2,1)="：",MID(TRIM(报表格式!AA22),2,1)="、"),REPLACEB(TRIM(报表格式!AA22),1,4,""),TRIM(报表格式!AA22)) -> 买入返售金融资产
E23: =IF(D23=0,"",VLOOKUP(D23,$N:$O,2,0)) | H23: =IF(G23=0,"",VLOOKUP(G23,$N:$O,2,0)) | N23: =报表格式!Z23 -> D10 | O23: =IF(OR(MID(TRIM(报表格式!AA23),2,1)="：",MID(TRIM(报表格式!AA23),2,1)="、"),REPLACEB(TRIM(报表格式!AA23),1,4,""),TRIM(报表格式!AA23)) -> 存货
E24: =IF(D24=0,"",VLOOKUP(D24,$N:$O,2,0)) | H24: =IF(G24=0,"",VLOOKUP(G24,$N:$O,2,0)) | N24: =报表格式!Z24 -> D11 | O24: =IF(OR(MID(TRIM(报表格式!AA24),3,1)="：",MID(TRIM(报表格式!AA24),2,1)="、"),REPLACEB(TRIM(报表格式!AA24),1,6,""),TRIM(报表格式!AA24)) -> 合同资产
E25: =IF(D25=0,"",VLOOKUP(D25,$N:$O,2,0)) | H25: =IF(G25=0,"",VLOOKUP(G25,$N:$O,2,0)) | N25: =报表格式!Z25 -> D12 | O25: =IF(OR(MID(TRIM(报表格式!AA25),2,1)="：",MID(TRIM(报表格式!AA25),2,1)="、"),REPLACEB(TRIM(报表格式!AA25),1,4,""),TRIM(报表格式!AA25)) -> 持有待售资产
E26: =IF(D26=0,"",VLOOKUP(D26,$N:$O,2,0)) | H26: =IF(G26=0,"",VLOOKUP(G26,$N:$O,2,0)) | N26: =报表格式!Z26 -> D13 | O26: =IF(OR(MID(TRIM(报表格式!AA26),2,1)="：",MID(TRIM(报表格式!AA26),2,1)="、"),REPLACEB(TRIM(报表格式!AA26),1,4,""),TRIM(报表格式!AA26)) -> 一年内到期的非流动资产
J27: =IF(ABS((SUMIF(E21:E26,"?*",J21:J26)-SUMIF(H21:H26,"?*",J21:J26)))<0.005,"","借贷不等") | N27: =报表格式!Z27 -> D14 | O27: =IF(OR(MID(TRIM(报表格式!AA27),2,1)="：",MID(TRIM(报表格式!AA27),2,1)="、"),REPLACEB(TRIM(报表格式!AA27),1,4,""),TRIM(报表格式!AA27)) -> 其他流动资产
A28: 4 | E28: =IF(D28=0,"",VLOOKUP(D28,$N:$O,2,0)) | H28: =IF(G28=0,"",VLOOKUP(G28,$N:$O,2,0)) | N28: =报表格式!Z28 -> D15 | O28: =IF(OR(MID(TRIM(报表格式!AA28),2,1)="：",MID(TRIM(报表格式!AA28),2,1)="、"),REPLACEB(TRIM(报表格式!AA28),1,4,""),TRIM(报表格式!AA28)) -> 0
E29: =IF(D29=0,"",VLOOKUP(D29,$N:$O,2,0)) | H29: =IF(G29=0,"",VLOOKUP(G29,$N:$O,2,0)) | N29: =报表格式!Z29 -> D16 | O29: =IF(OR(MID(TRIM(报表格式!AA29),2,1)="：",MID(TRIM(报表格式!AA29),2,1)="、"),REPLACEB(TRIM(报表格式!AA29),1,4,""),TRIM(报表格式!AA29)) -> 0
E30: =IF(D30=0,"",VLOOKUP(D30,$N:$O,2,0)) | H30: =IF(G30=0,"",VLOOKUP(G30,$N:$O,2,0)) | N30: =报表格式!Z30 -> 0 | O30: =IF(OR(MID(TRIM(报表格式!AA30),2,1)="：",MID(TRIM(报表格式!AA30),2,1)="、"),REPLACEB(TRIM(报表格式!AA30),1,4,""),TRIM(报表格式!AA30)) -> 流动资产合计
E31: =IF(D31=0,"",VLOOKUP(D31,$N:$O,2,0)) | H31: =IF(G31=0,"",VLOOKUP(G31,$N:$O,2,0)) | N31: =报表格式!Z31 -> 0 | O31: =IF(OR(MID(TRIM(报表格式!AA31),2,1)="：",MID(TRIM(报表格式!AA31),2,1)="、"),REPLACEB(TRIM(报表格式!AA31),1,4,""),TRIM(报表格式!AA31)) -> 非流动资产:
E32: =IF(D32=0,"",VLOOKUP(D32,$N:$O,2,0)) | H32: =IF(G32=0,"",VLOOKUP(G32,$N:$O,2,0)) | N32: =报表格式!Z32 -> D47 | O32: =IF(OR(MID(TRIM(报表格式!AA32),2,1)="：",MID(TRIM(报表格式!AA32),2,1)="、"),REPLACEB(TRIM(报表格式!AA32),1,4,""),TRIM(报表格式!AA32)) -> 发放贷款及垫款
E33: =IF(D33=0,"",VLOOKUP(D33,$N:$O,2,0)) | H33: =IF(G33=0,"",VLOOKUP(G33,$N:$O,2,0)) | N33: =报表格式!Z33 -> D17 | O33: =IF(OR(MID(TRIM(报表格式!AA33),2,1)="：",MID(TRIM(报表格式!AA33),2,1)="、"),REPLACEB(TRIM(报表格式!AA33),1,4,""),TRIM(报表格式!AA33)) -> 债权投资
J34: =IF(ABS((SUMIF(E28:E33,"?*",J28:J33)-SUMIF(H28:H33,"?*",J28:J33)))<0.005,"","借贷不等") | N34: =报表格式!Z34 -> D18 | O34: =IF(OR(MID(TRIM(报表格式!AA34),2,1)="：",MID(TRIM(报表格式!AA34),2,1)="、"),REPLACEB(TRIM(报表格式!AA34),1,4,""),TRIM(报表格式!AA34)) -> 可供出售金融资产
A35: 5 | E35: =IF(D35=0,"",VLOOKUP(D35,$N:$O,2,0)) | H35: =IF(G35=0,"",VLOOKUP(G35,$N:$O,2,0)) | N35: =报表格式!Z35 -> D19 | O35: =IF(OR(MID(TRIM(报表格式!AA35),2,1)="：",MID(TRIM(报表格式!AA35),2,1)="、"),REPLACEB(TRIM(报表格式!AA35),1,4,""),TRIM(报表格式!AA35)) -> 其他债权投资
E36: =IF(D36=0,"",VLOOKUP(D36,$N:$O,2,0)) | H36: =IF(G36=0,"",VLOOKUP(G36,$N:$O,2,0)) | N36: =报表格式!Z36 -> D20 | O36: =IF(OR(MID(TRIM(报表格式!AA36),2,1)="：",MID(TRIM(报表格式!AA36),2,1)="、"),REPLACEB(TRIM(报表格式!AA36),1,4,""),TRIM(报表格式!AA36)) -> 持有至到期投资
E37: =IF(D37=0,"",VLOOKUP(D37,$N:$O,2,0)) | H37: =IF(G37=0,"",VLOOKUP(G37,$N:$O,2,0)) | N37: =报表格式!Z37 -> D21 | O37: =IF(OR(MID(TRIM(报表格式!AA37),2,1)="：",MID(TRIM(报表格式!AA37),2,1)="、"),REPLACEB(TRIM(报表格式!AA37),1,4,""),TRIM(报表格式!AA37)) -> 长期应收款
E38: =IF(D38=0,"",VLOOKUP(D38,$N:$O,2,0)) | H38: =IF(G38=0,"",VLOOKUP(G38,$N:$O,2,0)) | N38: =报表格式!Z38 -> D22 | O38: =IF(OR(MID(TRIM(报表格式!AA38),2,1)="：",MID(TRIM(报表格式!AA38),2,1)="、"),REPLACEB(TRIM(报表格式!AA38),1,4,""),TRIM(报表格式!AA38)) -> 设定受益计划净资产
E39: =IF(D39=0,"",VLOOKUP(D39,$N:$O,2,0)) | H39: =IF(G39=0,"",VLOOKUP(G39,$N:$O,2,0)) | N39: =报表格式!Z39 -> D23 | O39: =IF(OR(MID(TRIM(报表格式!AA39),2,1)="：",MID(TRIM(报表格式!AA39),2,1)="、"),REPLACEB(TRIM(报表格式!AA39),1,4,""),TRIM(报表格式!AA39)) -> 长期股权投资
E40: =IF(D40=0,"",VLOOKUP(D40,$N:$O,2,0)) | H40: =IF(G40=0,"",VLOOKUP(G40,$N:$O,2,0)) | N40: =报表格式!Z40 -> D24 | O40: =IF(OR(MID(TRIM(报表格式!AA40),2,1)="：",MID(TRIM(报表格式!AA40),2,1)="、"),REPLACEB(TRIM(报表格式!AA40),1,4,""),TRIM(报表格式!AA40)) -> 其他权益工具投资
J41: =IF(ABS((SUMIF(E35:E40,"?*",J35:J40)-SUMIF(H35:H40,"?*",J35:J40)))<0.005,"","借贷不等") | N41: =报表格式!Z41 -> D25 | O41: =IF(OR(MID(TRIM(报表格式!AA41),2,1)="：",MID(TRIM(报表格式!AA41),2,1)="、"),REPLACEB(TRIM(报表格式!AA41),1,4,""),TRIM(报表格式!AA41)) -> 其他非流动金融资产
A42: 6 | E42: =IF(D42=0,"",VLOOKUP(D42,$N:$O,2,0)) | H42: =IF(G42=0,"",VLOOKUP(G42,$N:$O,2,0)) | N42: =报表格式!Z42 -> D26 | O42: =IF(OR(MID(TRIM(报表格式!AA42),2,1)="：",MID(TRIM(报表格式!AA42),2,1)="、"),REPLACEB(TRIM(报表格式!AA42),1,4,""),TRIM(报表格式!AA42)) -> 投资性房地产
E43: =IF(D43=0,"",VLOOKUP(D43,$N:$O,2,0)) | H43: =IF(G43=0,"",VLOOKUP(G43,$N:$O,2,0)) | N43: =报表格式!Z43 -> D27 | O43: =IF(OR(MID(TRIM(报表格式!AA43),2,1)="：",MID(TRIM(报表格式!AA43),2,1)="、"),REPLACEB(TRIM(报表格式!AA43),1,4,""),TRIM(报表格式!AA43)) -> 固定资产
E44: =IF(D44=0,"",VLOOKUP(D44,$N:$O,2,0)) | H44: =IF(G44=0,"",VLOOKUP(G44,$N:$O,2,0)) | N44: =报表格式!Z44 -> D28 | O44: =IF(OR(MID(TRIM(报表格式!AA44),2,1)="：",MID(TRIM(报表格式!AA44),2,1)="、"),REPLACEB(TRIM(报表格式!AA44),1,4,""),TRIM(报表格式!AA44)) -> 在建工程
E45: =IF(D45=0,"",VLOOKUP(D45,$N:$O,2,0)) | H45: =IF(G45=0,"",VLOOKUP(G45,$N:$O,2,0)) | N45: =报表格式!Z45 -> D29 | O45: =IF(OR(MID(TRIM(报表格式!AA45),2,1)="：",MID(TRIM(报表格式!AA45),2,1)="、"),REPLACEB(TRIM(报表格式!AA45),1,4,""),TRIM(报表格式!AA45)) -> 生产性生物资产
E46: =IF(D46=0,"",VLOOKUP(D46,$N:$O,2,0)) | H46: =IF(G46=0,"",VLOOKUP(G46,$N:$O,2,0)) | N46: =报表格式!Z46 -> D30 | O46: =IF(OR(MID(TRIM(报表格式!AA46),2,1)="：",MID(TRIM(报表格式!AA46),2,1)="、"),REPLACEB(TRIM(报表格式!AA46),1,4,""),TRIM(报表格式!AA46)) -> 油气资产
E47: =IF(D47=0,"",VLOOKUP(D47,$N:$O,2,0)) | H47: =IF(G47=0,"",VLOOKUP(G47,$N:$O,2,0)) | N47: =报表格式!Z47 -> D31 | O47: =IF(OR(MID(TRIM(报表格式!AA47),2,1)="：",MID(TRIM(报表格式!AA47),2,1)="、"),REPLACEB(TRIM(报表格式!AA47),1,4,""),TRIM(报表格式!AA47)) -> 使用权资产
J48: =IF(ABS((SUMIF(E42:E47,"?*",J42:J47)-SUMIF(H42:H47,"?*",J42:J47)))<0.005,"","借贷不等") | N48: =报表格式!Z48 -> D32 | O48: =IF(OR(MID(TRIM(报表格式!AA48),2,1)="：",MID(TRIM(报表格式!AA48),2,1)="、"),REPLACEB(TRIM(报表格式!AA48),1,4,""),TRIM(报表格式!AA48)) -> 无形资产
A49: 7 | E49: =IF(D49=0,"",VLOOKUP(D49,$N:$O,2,0)) | H49: =IF(G49=0,"",VLOOKUP(G49,$N:$O,2,0)) | N49: =报表格式!Z49 -> D33 | O49: =IF(OR(MID(TRIM(报表格式!AA49),2,1)="：",MID(TRIM(报表格式!AA49),2,1)="、"),REPLACEB(TRIM(报表格式!AA49),1,4,""),TRIM(报表格式!AA49)) -> 开发支出
E50: =IF(D50=0,"",VLOOKUP(D50,$N:$O,2,0)) | H50: =IF(G50=0,"",VLOOKUP(G50,$N:$O,2,0)) | N50: =报表格式!Z50 -> D34 | O50: =IF(OR(MID(TRIM(报表格式!AA50),2,1)="：",MID(TRIM(报表格式!AA50),2,1)="、"),REPLACEB(TRIM(报表格式!AA50),1,4,""),TRIM(报表格式!AA50)) -> 商誉
E51: =IF(D51=0,"",VLOOKUP(D51,$N:$O,2,0)) | H51: =IF(G51=0,"",VLOOKUP(G51,$N:$O,2,0)) | N51: =报表格式!Z51 -> D35 | O51: =IF(OR(MID(TRIM(报表格式!AA51),2,1)="：",MID(TRIM(报表格式!AA51),2,1)="、"),REPLACEB(TRIM(报表格式!AA51),1,4,""),TRIM(报表格式!AA51)) -> 长期待摊费用
E52: =IF(D52=0,"",VLOOKUP(D52,$N:$O,2,0)) | H52: =IF(G52=0,"",VLOOKUP(G52,$N:$O,2,0)) | N52: =报表格式!Z52 -> D36 | O52: =IF(OR(MID(TRIM(报表格式!AA52),2,1)="：",MID(TRIM(报表格式!AA52),2,1)="、"),REPLACEB(TRIM(报表格式!AA52),1,4,""),TRIM(报表格式!AA52)) -> 递延所得税资产
E53: =IF(D53=0,"",VLOOKUP(D53,$N:$O,2,0)) | H53: =IF(G53=0,"",VLOOKUP(G53,$N:$O,2,0)) | N53: =报表格式!Z53 -> D37 | O53: =IF(OR(MID(TRIM(报表格式!AA53),2,1)="：",MID(TRIM(报表格式!AA53),2,1)="、"),REPLACEB(TRIM(报表格式!AA53),1,4,""),TRIM(报表格式!AA53)) -> 其他非流动资产
E54: =IF(D54=0,"",VLOOKUP(D54,$N:$O,2,0)) | H54: =IF(G54=0,"",VLOOKUP(G54,$N:$O,2,0)) | N54: =报表格式!Z54 -> D38 | O54: =IF(OR(MID(TRIM(报表格式!AA54),2,1)="：",MID(TRIM(报表格式!AA54),2,1)="、"),REPLACEB(TRIM(报表格式!AA54),1,4,""),TRIM(报表格式!AA54)) -> 0
J55: =IF(ABS((SUMIF(E49:E54,"?*",J49:J54)-SUMIF(H49:H54,"?*",J49:J54)))<0.005,"","借贷不等") | N55: =报表格式!Z55 -> D39 | O55: =IF(OR(MID(TRIM(报表格式!AA55),2,1)="：",MID(TRIM(报表格式!AA55),2,1)="、"),REPLACEB(TRIM(报表格式!AA55),1,4,""),TRIM(报表格式!AA55)) -> 0
A56: 8 | E56: =IF(D56=0,"",VLOOKUP(D56,$N:$O,2,0)) | H56: =IF(G56=0,"",VLOOKUP(G56,$N:$O,2,0)) | N56: =报表格式!Z56 -> D40 | O56: =IF(OR(MID(TRIM(报表格式!AA56),2,1)="：",MID(TRIM(报表格式!AA56),2,1)="、"),REPLACEB(TRIM(报表格式!AA56),1,4,""),TRIM(报表格式!AA56)) -> 0
E57: =IF(D57=0,"",VLOOKUP(D57,$N:$O,2,0)) | H57: =IF(G57=0,"",VLOOKUP(G57,$N:$O,2,0)) | N57: =报表格式!Z57 -> 0 | O57: =IF(OR(MID(TRIM(报表格式!AA57),2,1)="：",MID(TRIM(报表格式!AA57),2,1)="、"),REPLACEB(TRIM(报表格式!AA57),1,4,""),TRIM(报表格式!AA57)) -> 非流动资产合计
E58: =IF(D58=0,"",VLOOKUP(D58,$N:$O,2,0)) | H58: =IF(G58=0,"",VLOOKUP(G58,$N:$O,2,0)) | N58: =报表格式!Z58 -> 0 | O58: =IF(OR(MID(TRIM(报表格式!AA58),2,1)="：",MID(TRIM(报表格式!AA58),2,1)="、"),REPLACEB(TRIM(报表格式!AA58),1,4,""),TRIM(报表格式!AA58)) -> 资 产 总 计
E59: =IF(D59=0,"",VLOOKUP(D59,$N:$O,2,0)) | H59: =IF(G59=0,"",VLOOKUP(G59,$N:$O,2,0)) | N59: =报表格式!Z59 -> 0 | O59: =IF(OR(MID(TRIM(报表格式!AA59),2,1)="：",MID(TRIM(报表格式!AA59),2,1)="、"),REPLACEB(TRIM(报表格式!AA59),1,4,""),TRIM(报表格式!AA59))
E60: =IF(D60=0,"",VLOOKUP(D60,$N:$O,2,0)) | H60: =IF(G60=0,"",VLOOKUP(G60,$N:$O,2,0)) | N60: =报表格式!Z60 -> 0 | O60: =IF(OR(MID(TRIM(报表格式!AA60),2,1)="：",MID(TRIM(报表格式!AA60),2,1)="、"),REPLACEB(TRIM(报表格式!AA60),1,4,""),TRIM(报表格式!AA60))
E61: =IF(D61=0,"",VLOOKUP(D61,$N:$O,2,0)) | H61: =IF(G61=0,"",VLOOKUP(G61,$N:$O,2,0)) | N61: =报表格式!Z61 -> 0 | O61: =IF(OR(MID(TRIM(报表格式!AA61),2,1)="：",MID(TRIM(报表格式!AA61),2,1)="、"),REPLACEB(TRIM(报表格式!AA61),1,4,""),TRIM(报表格式!AA61)) -> 流动负债：
J62: =IF(ABS((SUMIF(E56:E61,"?*",J56:J61)-SUMIF(H56:H61,"?*",J56:J61)))<0.005,"","借贷不等") | N62: =报表格式!Z62 -> E1 | O62: =IF(OR(MID(TRIM(报表格式!AA62),2,1)="：",MID(TRIM(报表格式!AA62),2,1)="、"),REPLACEB(TRIM(报表格式!AA62),1,4,""),TRIM(报表格式!AA62)) -> 短期借款
A63: 9 | E63: =IF(D63=0,"",VLOOKUP(D63,$N:$O,2,0)) | H63: =IF(G63=0,"",VLOOKUP(G63,$N:$O,2,0)) | N63: =报表格式!Z63 -> E24 | O63: =IF(OR(MID(TRIM(报表格式!AA63),2,1)="：",MID(TRIM(报表格式!AA63),2,1)="、"),REPLACEB(TRIM(报表格式!AA63),1,4,""),TRIM(报表格式!AA63)) -> 向中央银行借款
E64: =IF(D64=0,"",VLOOKUP(D64,$N:$O,2,0)) | H64: =IF(G64=0,"",VLOOKUP(G64,$N:$O,2,0)) | N64: =报表格式!Z64 -> E25 | O64: =IF(OR(MID(TRIM(报表格式!AA64),2,1)="：",MID(TRIM(报表格式!AA64),2,1)="、"),REPLACEB(TRIM(报表格式!AA64),1,4,""),TRIM(报表格式!AA64)) -> 吸收存款及同业存放
E65: =IF(D65=0,"",VLOOKUP(D65,$N:$O,2,0)) | H65: =IF(G65=0,"",VLOOKUP(G65,$N:$O,2,0)) | N65: =报表格式!Z65 -> E26 | O65: =IF(OR(MID(TRIM(报表格式!AA65),2,1)="：",MID(TRIM(报表格式!AA65),2,1)="、"),REPLACEB(TRIM(报表格式!AA65),1,4,""),TRIM(报表格式!AA65)) -> 拆入资金
E66: =IF(D66=0,"",VLOOKUP(D66,$N:$O,2,0)) | H66: =IF(G66=0,"",VLOOKUP(G66,$N:$O,2,0)) | N66: =报表格式!Z66 -> E2 | O66: =IF(OR(MID(TRIM(报表格式!AA66),2,1)="：",MID(TRIM(报表格式!AA66),2,1)="、"),REPLACEB(TRIM(报表格式!AA66),1,4,""),TRIM(报表格式!AA66)) -> 交易性金融负债
E67: =IF(D67=0,"",VLOOKUP(D67,$N:$O,2,0)) | H67: =IF(G67=0,"",VLOOKUP(G67,$N:$O,2,0)) | N67: =报表格式!Z67 -> E3 | O67: =IF(OR(MID(TRIM(报表格式!AA67),2,1)="：",MID(TRIM(报表格式!AA67),2,1)="、"),REPLACEB(TRIM(报表格式!AA67),1,4,""),TRIM(报表格式!AA67)) -> 以公允价值计量且其变动计入当期损益的金融负债
E68: =IF(D68=0,"",VLOOKUP(D68,$N:$O,2,0)) | H68: =IF(G68=0,"",VLOOKUP(G68,$N:$O,2,0)) | N68: =报表格式!Z68 -> E4 | O68: =IF(OR(MID(TRIM(报表格式!AA68),2,1)="：",MID(TRIM(报表格式!AA68),2,1)="、"),REPLACEB(TRIM(报表格式!AA68),1,4,""),TRIM(报表格式!AA68)) -> 衍生金融负债
J69: =IF(ABS((SUMIF(E63:E68,"?*",J63:J68)-SUMIF(H63:H68,"?*",J63:J68)))<0.005,"","借贷不等") | N69: =报表格式!Z69 -> E5 | O69: =IF(OR(MID(TRIM(报表格式!AA69),2,1)="：",MID(TRIM(报表格式!AA69),2,1)="、"),REPLACEB(TRIM(报表格式!AA69),1,4,""),TRIM(报表格式!AA69)) -> 应付票据
A70: 10 | E70: =IF(D70=0,"",VLOOKUP(D70,$N:$O,2,0)) | H70: =IF(G70=0,"",VLOOKUP(G70,$N:$O,2,0)) | N70: =报表格式!Z70 -> E6 | O70: =IF(OR(MID(TRIM(报表格式!AA70),2,1)="：",MID(TRIM(报表格式!AA70),2,1)="、"),REPLACEB(TRIM(报表格式!AA70),1,4,""),TRIM(报表格式!AA70)) -> 应付账款
E71: =IF(D71=0,"",VLOOKUP(D71,$N:$O,2,0)) | H71: =IF(G71=0,"",VLOOKUP(G71,$N:$O,2,0)) | N71: =报表格式!Z71 -> E7 | O71: =IF(OR(MID(TRIM(报表格式!AA71),2,1)="：",MID(TRIM(报表格式!AA71),2,1)="、"),REPLACEB(TRIM(报表格式!AA71),1,4,""),TRIM(报表格式!AA71)) -> 预收款项
E72: =IF(D72=0,"",VLOOKUP(D72,$N:$O,2,0)) | H72: =IF(G72=0,"",VLOOKUP(G72,$N:$O,2,0)) | N72: =报表格式!Z72 -> E27 | O72: =IF(OR(MID(TRIM(报表格式!AA72),2,1)="：",MID(TRIM(报表格式!AA72),2,1)="、"),REPLACEB(TRIM(报表格式!AA72),1,4,""),TRIM(报表格式!AA72)) -> 卖出回购金融资产款
E73: =IF(D73=0,"",VLOOKUP(D73,$N:$O,2,0)) | H73: =IF(G73=0,"",VLOOKUP(G73,$N:$O,2,0)) | N73: =报表格式!Z73 -> E28 | O73: =IF(OR(MID(TRIM(报表格式!AA73),2,1)="：",MID(TRIM(报表格式!AA73),2,1)="、"),REPLACEB(TRIM(报表格式!AA73),1,4,""),TRIM(报表格式!AA73)) -> 应付手续费及佣金
E74: =IF(D74=0,"",VLOOKUP(D74,$N:$O,2,0)) | H74: =IF(G74=0,"",VLOOKUP(G74,$N:$O,2,0)) | N74: =报表格式!Z74 -> E8 | O74: =IF(OR(MID(TRIM(报表格式!AA74),2,1)="：",MID(TRIM(报表格式!AA74),2,1)="、"),REPLACEB(TRIM(报表格式!AA74),1,4,""),TRIM(报表格式!AA74)) -> 合同负债
E75: =IF(D75=0,"",VLOOKUP(D75,$N:$O,2,0)) | H75: =IF(G75=0,"",VLOOKUP(G75,$N:$O,2,0)) | N75: =报表格式!Z75 -> E9 | O75: =IF(OR(MID(TRIM(报表格式!AA75),2,1)="：",MID(TRIM(报表格式!AA75),2,1)="、"),REPLACEB(TRIM(报表格式!AA75),1,4,""),TRIM(报表格式!AA75)) -> 应付职工薪酬
J76: =IF(ABS((SUMIF(E70:E75,"?*",J70:J75)-SUMIF(H70:H75,"?*",J70:J75)))<0.005,"","借贷不等") | N76: =报表格式!Z76 -> E10 | O76: =IF(OR(MID(TRIM(报表格式!AA76),2,1)="：",MID(TRIM(报表格式!AA76),2,1)="、"),REPLACEB(TRIM(报表格式!AA76),1,4,""),TRIM(报表格式!AA76)) -> 应交税费
A77: 11 | E77: =IF(D77=0,"",VLOOKUP(D77,$N:$O,2,0)) | H77: =IF(G77=0,"",VLOOKUP(G77,$N:$O,2,0)) | N77: =报表格式!Z77 -> E11 | O77: =IF(OR(MID(TRIM(报表格式!AA77),2,1)="：",MID(TRIM(报表格式!AA77),2,1)="、"),REPLACEB(TRIM(报表格式!AA77),1,4,""),TRIM(报表格式!AA77)) -> 其他应付款
E78: =IF(D78=0,"",VLOOKUP(D78,$N:$O,2,0)) | H78: =IF(G78=0,"",VLOOKUP(G78,$N:$O,2,0)) | N78: =报表格式!Z78 -> 0 | O78: =IF(OR(MID(TRIM(报表格式!AA78),3,1)="：",MID(TRIM(报表格式!AA78),2,1)="、"),REPLACEB(TRIM(报表格式!AA78),1,6,""),TRIM(报表格式!AA78)) -> 应付利息
E79: =IF(D79=0,"",VLOOKUP(D79,$N:$O,2,0)) | H79: =IF(G79=0,"",VLOOKUP(G79,$N:$O,2,0)) | N79: =报表格式!Z79 -> 0 | O79: =IF(OR(MID(TRIM(报表格式!AA79),2,1)="：",MID(TRIM(报表格式!AA79),2,1)="、"),REPLACEB(TRIM(报表格式!AA79),1,4,""),TRIM(报表格式!AA79)) -> 应付股利
E80: =IF(D80=0,"",VLOOKUP(D80,$N:$O,2,0)) | H80: =IF(G80=0,"",VLOOKUP(G80,$N:$O,2,0)) | N80: =报表格式!Z80 -> E29 | O80: =IF(OR(MID(TRIM(报表格式!AA80),2,1)="：",MID(TRIM(报表格式!AA80),2,1)="、"),REPLACEB(TRIM(报表格式!AA80),1,4,""),TRIM(报表格式!AA80)) -> 应付分保账款
E81: =IF(D81=0,"",VLOOKUP(D81,$N:$O,2,0)) | H81: =IF(G81=0,"",VLOOKUP(G81,$N:$O,2,0)) | N81: =报表格式!Z81 -> E30 | O81: =IF(OR(MID(TRIM(报表格式!AA81),2,1)="：",MID(TRIM(报表格式!AA81),2,1)="、"),REPLACEB(TRIM(报表格式!AA81),1,4,""),TRIM(报表格式!AA81)) -> 保险合同准备金
E82: =IF(D82=0,"",VLOOKUP(D82,$N:$O,2,0)) | H82: =IF(G82=0,"",VLOOKUP(G82,$N:$O,2,0)) | N82: =报表格式!Z82 -> E31 | O82: =IF(OR(MID(TRIM(报表格式!AA82),2,1)="：",MID(TRIM(报表格式!AA82),2,1)="、"),REPLACEB(TRIM(报表格式!AA82),1,4,""),TRIM(报表格式!AA82)) -> 代理买卖证券款
J83: =IF(ABS((SUMIF(E77:E82,"?*",J77:J82)-SUMIF(H77:H82,"?*",J77:J82)))<0.005,"","借贷不等") | N83: =报表格式!Z83 -> E32 | O83: =IF(OR(MID(TRIM(报表格式!AA83),2,1)="：",MID(TRIM(报表格式!AA83),2,1)="、"),REPLACEB(TRIM(报表格式!AA83),1,4,""),TRIM(报表格式!AA83)) -> 代理承销证券款
A84: 12 | E84: =IF(D84=0,"",VLOOKUP(D84,$N:$O,2,0)) | H84: =IF(G84=0,"",VLOOKUP(G84,$N:$O,2,0)) | N84: =报表格式!Z84 -> E12 | O84: =IF(OR(MID(TRIM(报表格式!AA84),2,1)="：",MID(TRIM(报表格式!AA84),2,1)="、"),REPLACEB(TRIM(报表格式!AA84),1,4,""),TRIM(报表格式!AA84)) -> 持有待售负债
E85: =IF(D85=0,"",VLOOKUP(D85,$N:$O,2,0)) | H85: =IF(G85=0,"",VLOOKUP(G85,$N:$O,2,0)) | N85: =报表格式!Z85 -> E13 | O85: =IF(OR(MID(TRIM(报表格式!AA85),2,1)="：",MID(TRIM(报表格式!AA85),2,1)="、"),REPLACEB(TRIM(报表格式!AA85),1,4,""),TRIM(报表格式!AA85)) -> 一年内到期的非流动负债
E86: =IF(D86=0,"",VLOOKUP(D86,$N:$O,2,0)) | H86: =IF(G86=0,"",VLOOKUP(G86,$N:$O,2,0)) | N86: =报表格式!Z86 -> E14 | O86: =IF(OR(MID(TRIM(报表格式!AA86),2,1)="：",MID(TRIM(报表格式!AA86),2,1)="、"),REPLACEB(TRIM(报表格式!AA86),1,4,""),TRIM(报表格式!AA86)) -> 其他流动负债
E87: =IF(D87=0,"",VLOOKUP(D87,$N:$O,2,0)) | H87: =IF(G87=0,"",VLOOKUP(G87,$N:$O,2,0)) | N87: =报表格式!Z87 -> 0 | O87: =IF(OR(MID(TRIM(报表格式!AA87),2,1)="：",MID(TRIM(报表格式!AA87),2,1)="、"),REPLACEB(TRIM(报表格式!AA87),1,4,""),TRIM(报表格式!AA87)) -> 流动负债合计
E88: =IF(D88=0,"",VLOOKUP(D88,$N:$O,2,0)) | H88: =IF(G88=0,"",VLOOKUP(G88,$N:$O,2,0)) | N88: =报表格式!Z88 -> 0 | O88: =IF(OR(MID(TRIM(报表格式!AA88),2,1)="：",MID(TRIM(报表格式!AA88),2,1)="、"),REPLACEB(TRIM(报表格式!AA88),1,4,""),TRIM(报表格式!AA88)) -> 非流动负债:
E89: =IF(D89=0,"",VLOOKUP(D89,$N:$O,2,0)) | H89: =IF(G89=0,"",VLOOKUP(G89,$N:$O,2,0)) | N89: =报表格式!Z89 -> E15 | O89: =IF(OR(MID(TRIM(报表格式!AA89),2,1)="：",MID(TRIM(报表格式!AA89),2,1)="、"),REPLACEB(TRIM(报表格式!AA89),1,4,""),TRIM(报表格式!AA89)) -> 长期借款
J90: =IF(ABS((SUMIF(E84:E89,"?*",J84:J89)-SUMIF(H84:H89,"?*",J84:J89)))<0.005,"","借贷不等") | N90: =报表格式!Z90 -> E16 | O90: =IF(OR(MID(TRIM(报表格式!AA90),2,1)="：",MID(TRIM(报表格式!AA90),2,1)="、"),REPLACEB(TRIM(报表格式!AA90),1,4,""),TRIM(报表格式!AA90)) -> 应付债券
A91: 13 | E91: =IF(D91=0,"",VLOOKUP(D91,$N:$O,2,0)) | H91: =IF(G91=0,"",VLOOKUP(G91,$N:$O,2,0)) | N91: =报表格式!Z91 -> 0 | O91: =IF(OR(MID(TRIM(报表格式!AA91),3,1)="：",MID(TRIM(报表格式!AA91),2,1)="、"),REPLACEB(TRIM(报表格式!AA91),1,6,""),TRIM(报表格式!AA91)) -> 优先股
E92: =IF(D92=0,"",VLOOKUP(D92,$N:$O,2,0)) | H92: =IF(G92=0,"",VLOOKUP(G92,$N:$O,2,0)) | N92: =报表格式!Z92 -> 0 | O92: =IF(OR(MID(TRIM(报表格式!AA92),2,1)="：",MID(TRIM(报表格式!AA92),2,1)="、"),REPLACEB(TRIM(报表格式!AA92),1,4,""),TRIM(报表格式!AA92)) -> 永续债
E93: =IF(D93=0,"",VLOOKUP(D93,$N:$O,2,0)) | H93: =IF(G93=0,"",VLOOKUP(G93,$N:$O,2,0)) | N93: =报表格式!Z93 -> E17 | O93: =IF(OR(MID(TRIM(报表格式!AA93),2,1)="：",MID(TRIM(报表格式!AA93),2,1)="、"),REPLACEB(TRIM(报表格式!AA93),1,4,""),TRIM(报表格式!AA93)) -> 租赁负债
E94: =IF(D94=0,"",VLOOKUP(D94,$N:$O,2,0)) | H94: =IF(G94=0,"",VLOOKUP(G94,$N:$O,2,0)) | N94: =报表格式!Z94 -> E18 | O94: =IF(OR(MID(TRIM(报表格式!AA94),2,1)="：",MID(TRIM(报表格式!AA94),2,1)="、"),REPLACEB(TRIM(报表格式!AA94),1,4,""),TRIM(报表格式!AA94)) -> 长期应付款
E95: =IF(D95=0,"",VLOOKUP(D95,$N:$O,2,0)) | H95: =IF(G95=0,"",VLOOKUP(G95,$N:$O,2,0)) | N95: =报表格式!Z95 -> E19 | O95: =IF(OR(MID(TRIM(报表格式!AA95),2,1)="：",MID(TRIM(报表格式!AA95),2,1)="、"),REPLACEB(TRIM(报表格式!AA95),1,4,""),TRIM(报表格式!AA95)) -> 长期应付职工薪酬
E96: =IF(D96=0,"",VLOOKUP(D96,$N:$O,2,0)) | H96: =IF(G96=0,"",VLOOKUP(G96,$N:$O,2,0)) | N96: =报表格式!Z96 -> E20 | O96: =IF(OR(MID(TRIM(报表格式!AA96),2,1)="：",MID(TRIM(报表格式!AA96),2,1)="、"),REPLACEB(TRIM(报表格式!AA96),1,4,""),TRIM(报表格式!AA96)) -> 预计负债
J97: =IF(ABS((SUMIF(E91:E96,"?*",J91:J96)-SUMIF(H91:H96,"?*",J91:J96)))<0.005,"","借贷不等") | N97: =报表格式!Z97 -> E21 | O97: =IF(OR(MID(TRIM(报表格式!AA97),2,1)="：",MID(TRIM(报表格式!AA97),2,1)="、"),REPLACEB(TRIM(报表格式!AA97),1,4,""),TRIM(报表格式!AA97)) -> 递延收益
A98: 14 | E98: =IF(D98=0,"",VLOOKUP(D98,$N:$O,2,0)) | H98: =IF(G98=0,"",VLOOKUP(G98,$N:$O,2,0)) | N98: =报表格式!Z98 -> E22 | O98: =IF(OR(MID(TRIM(报表格式!AA98),2,1)="：",MID(TRIM(报表格式!AA98),2,1)="、"),REPLACEB(TRIM(报表格式!AA98),1,4,""),TRIM(报表格式!AA98)) -> 递延所得税负债
E99: =IF(D99=0,"",VLOOKUP(D99,$N:$O,2,0)) | H99: =IF(G99=0,"",VLOOKUP(G99,$N:$O,2,0)) | N99: =报表格式!Z99 -> E23 | O99: =IF(OR(MID(TRIM(报表格式!AA99),2,1)="：",MID(TRIM(报表格式!AA99),2,1)="、"),REPLACEB(TRIM(报表格式!AA99),1,4,""),TRIM(报表格式!AA99)) -> 其他非流动负债
E100: =IF(D100=0,"",VLOOKUP(D100,$N:$O,2,0)) | H100: =IF(G100=0,"",VLOOKUP(G100,$N:$O,2,0)) | N100: =报表格式!Z100 -> 0 | O100: =IF(OR(MID(TRIM(报表格式!AA100),2,1)="：",MID(TRIM(报表格式!AA100),2,1)="、"),REPLACEB(TRIM(报表格式!AA100),1,4,""),TRIM(报表格式!AA100)) -> 非流动负债合计
...

Sheet 母公司账项调整
A1: =IF((L2-(母公司TB资产!E60+母公司TB负债!E63+母公司TB损益!E90)-IF(COUNTIF(E5:E666,"未分配利润")>=1,VLOOKUP("未分配利润",E5:J666,6,0),0))<0.005,"母公司账项调整事项汇总表","调整事项未全部链入试算平衡表，请检查调整科目是否为报表项目!") -> 母公司账项调整事项汇总表 | K1: =SUM(L2:L3) -> 0 | N1: =母公司汇总抵销!N1 -> code | O1: =母公司汇总抵销!O1 -> 报表项目
A2: =CONCATENATE("客户名称：",说明!E23) -> 客户名称： | E2: =CONCATENATE("编制人：",说明!E36) -> 编制人： | H2: =CONCATENATE("日期：",TEXT(NOW(),"yyyy.mm.dd")) -> 日期：2019.12.31 | J2: 索引： | K2: 借方调整累计 | L2: =SUMIF(E5:E65536,"?*",J5:J65536) -> 0 | N2: =母公司汇总抵销!N2 -> 0 | O2: =母公司汇总抵销!O2 -> 0
A3: =CONCATENATE("会计期间：",说明!E30) -> 会计期间：2019年度 | E3: =CONCATENATE("复核人：",说明!E37) -> 复核人： | H3: 日期： | J3: 页码： | K3: 贷方调整累计 | L3: =SUMIF(H5:H65536,"?*",J5:J65536) -> 0 | N3: =母公司汇总抵销!N3 -> 0 | O3: =母公司汇总抵销!O3 -> 0
A4: 序号 | B4: 索引号 | C4: 调整说明 | D4: code | E4: 借方科目 | F4: 二级科目 | G4: code | H4: 贷方科目 | I4: 二级科目 | J4: 金额 | L4: =L2-L3 -> 0 | N4: =母公司汇总抵销!N4 -> 0 | O4: =母公司汇总抵销!O4 -> 0
A5: 1 | E5: =IF(D5=0,"",VLOOKUP(D5,$N:$O,2,0)) | H5: =IF(G5=0,"",VLOOKUP(G5,$N:$O,2,0)) | K5: 本表可根据需要插入行， | N5: =母公司汇总抵销!N5 -> 0 | O5: =母公司汇总抵销!O5 -> 流动资产：
E6: =IF(D6=0,"",VLOOKUP(D6,$N:$O,2,0)) | H6: =IF(G6=0,"",VLOOKUP(G6,$N:$O,2,0)) | K6: 请勿删除行。 | N6: =母公司汇总抵销!N6 -> D1 | O6: =母公司汇总抵销!O6 -> 货币资金
E7: =IF(D7=0,"",VLOOKUP(D7,$N:$O,2,0)) | H7: =IF(G7=0,"",VLOOKUP(G7,$N:$O,2,0)) | N7: =母公司汇总抵销!N7 -> D41 | O7: =母公司汇总抵销!O7 -> 结算备付金
E8: =IF(D8=0,"",VLOOKUP(D8,$N:$O,2,0)) | H8: =IF(G8=0,"",VLOOKUP(G8,$N:$O,2,0)) | N8: =母公司汇总抵销!N8 -> D42 | O8: =母公司汇总抵销!O8 -> 拆出资金
E9: =IF(D9=0,"",VLOOKUP(D9,$N:$O,2,0)) | H9: =IF(G9=0,"",VLOOKUP(G9,$N:$O,2,0)) | N9: =母公司汇总抵销!N9 -> D2 | O9: =母公司汇总抵销!O9 -> 交易性金融资产
E10: =IF(D10=0,"",VLOOKUP(D10,$N:$O,2,0)) | H10: =IF(G10=0,"",VLOOKUP(G10,$N:$O,2,0)) | N10: =母公司汇总抵销!N10 -> D3 | O10: =母公司汇总抵销!O10 -> 以公允价值计量且其变动计入当期损益的金融资产
N11: =母公司汇总抵销!N11 -> D4 | O11: =母公司汇总抵销!O11 -> 衍生金融资产
A12: 2 | E12: =IF(D12=0,"",VLOOKUP(D12,$N:$O,2,0)) | H12: =IF(G12=0,"",VLOOKUP(G12,$N:$O,2,0)) | N12: =母公司汇总抵销!N12 -> D5 | O12: =母公司汇总抵销!O12 -> 应收票据
E13: =IF(D13=0,"",VLOOKUP(D13,$N:$O,2,0)) | H13: =IF(G13=0,"",VLOOKUP(G13,$N:$O,2,0)) | N13: =母公司汇总抵销!N13 -> D6 | O13: =母公司汇总抵销!O13 -> 应收账款
E14: =IF(D14=0,"",VLOOKUP(D14,$N:$O,2,0)) | H14: =IF(G14=0,"",VLOOKUP(G14,$N:$O,2,0)) | N14: =母公司汇总抵销!N14 -> D7 | O14: =母公司汇总抵销!O14 -> 应收款项融资
E15: =IF(D15=0,"",VLOOKUP(D15,$N:$O,2,0)) | H15: =IF(G15=0,"",VLOOKUP(G15,$N:$O,2,0)) | N15: =母公司汇总抵销!N15 -> D8 | O15: =母公司汇总抵销!O15 -> 预付款项
E16: =IF(D16=0,"",VLOOKUP(D16,$N:$O,2,0)) | H16: =IF(G16=0,"",VLOOKUP(G16,$N:$O,2,0)) | N16: =母公司汇总抵销!N16 -> D43 | O16: =母公司汇总抵销!O16 -> 应收保费
E17: =IF(D17=0,"",VLOOKUP(D17,$N:$O,2,0)) | H17: =IF(G17=0,"",VLOOKUP(G17,$N:$O,2,0)) | N17: =母公司汇总抵销!N17 -> D44 | O17: =母公司汇总抵销!O17 -> 应收分保账款
N18: =母公司汇总抵销!N18 -> D45 | O18: =母公司汇总抵销!O18 -> 应收分保准备金
A19: 3 | E19: =IF(D19=0,"",VLOOKUP(D19,$N:$O,2,0)) | H19: =IF(G19=0,"",VLOOKUP(G19,$N:$O,2,0)) | N19: =母公司汇总抵销!N19 -> D9 | O19: =母公司汇总抵销!O19 -> 其他应收款
E20: =IF(D20=0,"",VLOOKUP(D20,$N:$O,2,0)) | H20: =IF(G20=0,"",VLOOKUP(G20,$N:$O,2,0)) | N20: =母公司汇总抵销!N20 -> 0 | O20: =母公司汇总抵销!O20 -> 应收利息
E21: =IF(D21=0,"",VLOOKUP(D21,$N:$O,2,0)) | H21: =IF(G21=0,"",VLOOKUP(G21,$N:$O,2,0)) | N21: =母公司汇总抵销!N21 -> 0 | O21: =母公司汇总抵销!O21 -> 应收股利
E22: =IF(D22=0,"",VLOOKUP(D22,$N:$O,2,0)) | H22: =IF(G22=0,"",VLOOKUP(G22,$N:$O,2,0)) | N22: =母公司汇总抵销!N22 -> D46 | O22: =母公司汇总抵销!O22 -> 买入返售金融资产
E23: =IF(D23=0,"",VLOOKUP(D23,$N:$O,2,0)) | H23: =IF(G23=0,"",VLOOKUP(G23,$N:$O,2,0)) | N23: =母公司汇总抵销!N23 -> D10 | O23: =母公司汇总抵销!O23 -> 存货
E24: =IF(D24=0,"",VLOOKUP(D24,$N:$O,2,0)) | H24: =IF(G24=0,"",VLOOKUP(G24,$N:$O,2,0)) | N24: =母公司汇总抵销!N24 -> D11 | O24: =母公司汇总抵销!O24 -> 合同资产
J25: =IF(ABS((SUMIF(E19:E24,"?*",J19:J24)-SUMIF(H19:H24,"?*",J19:J24)))<0.005,"","借贷不等") | N25: =母公司汇总抵销!N25 -> D12 | O25: =母公司汇总抵销!O25 -> 持有待售资产
A26: 4 | E26: =IF(D26=0,"",VLOOKUP(D26,$N:$O,2,0)) | H26: =IF(G26=0,"",VLOOKUP(G26,$N:$O,2,0)) | N26: =母公司汇总抵销!N26 -> D13 | O26: =母公司汇总抵销!O26 -> 一年内到期的非流动资产
E27: =IF(D27=0,"",VLOOKUP(D27,$N:$O,2,0)) | H27: =IF(G27=0,"",VLOOKUP(G27,$N:$O,2,0)) | N27: =母公司汇总抵销!N27 -> D14 | O27: =母公司汇总抵销!O27 -> 其他流动资产
E28: =IF(D28=0,"",VLOOKUP(D28,$N:$O,2,0)) | H28: =IF(G28=0,"",VLOOKUP(G28,$N:$O,2,0)) | N28: =母公司汇总抵销!N28 -> D15 | O28: =母公司汇总抵销!O28 -> 0
E29: =IF(D29=0,"",VLOOKUP(D29,$N:$O,2,0)) | H29: =IF(G29=0,"",VLOOKUP(G29,$N:$O,2,0)) | N29: =母公司汇总抵销!N29 -> D16 | O29: =母公司汇总抵销!O29 -> 0
E30: =IF(D30=0,"",VLOOKUP(D30,$N:$O,2,0)) | H30: =IF(G30=0,"",VLOOKUP(G30,$N:$O,2,0)) | N30: =母公司汇总抵销!N30 -> 0 | O30: =母公司汇总抵销!O30 -> 流动资产合计
E31: =IF(D31=0,"",VLOOKUP(D31,$N:$O,2,0)) | H31: =IF(G31=0,"",VLOOKUP(G31,$N:$O,2,0)) | N31: =母公司汇总抵销!N31 -> 0 | O31: =母公司汇总抵销!O31 -> 非流动资产:
J32: =IF(ABS((SUMIF(E26:E31,"?*",J26:J31)-SUMIF(H26:H31,"?*",J26:J31)))<0.005,"","借贷不等") | N32: =母公司汇总抵销!N32 -> D47 | O32: =母公司汇总抵销!O32 -> 发放贷款及垫款
A33: 5 | E33: =IF(D33=0,"",VLOOKUP(D33,$N:$O,2,0)) | H33: =IF(G33=0,"",VLOOKUP(G33,$N:$O,2,0)) | N33: =母公司汇总抵销!N33 -> D17 | O33: =母公司汇总抵销!O33 -> 债权投资
E34: =IF(D34=0,"",VLOOKUP(D34,$N:$O,2,0)) | H34: =IF(G34=0,"",VLOOKUP(G34,$N:$O,2,0)) | N34: =母公司汇总抵销!N34 -> D18 | O34: =母公司汇总抵销!O34 -> 可供出售金融资产
E35: =IF(D35=0,"",VLOOKUP(D35,$N:$O,2,0)) | H35: =IF(G35=0,"",VLOOKUP(G35,$N:$O,2,0)) | N35: =母公司汇总抵销!N35 -> D19 | O35: =母公司汇总抵销!O35 -> 其他债权投资
E36: =IF(D36=0,"",VLOOKUP(D36,$N:$O,2,0)) | H36: =IF(G36=0,"",VLOOKUP(G36,$N:$O,2,0)) | N36: =母公司汇总抵销!N36 -> D20 | O36: =母公司汇总抵销!O36 -> 持有至到期投资
E37: =IF(D37=0,"",VLOOKUP(D37,$N:$O,2,0)) | H37: =IF(G37=0,"",VLOOKUP(G37,$N:$O,2,0)) | N37: =母公司汇总抵销!N37 -> D21 | O37: =母公司汇总抵销!O37 -> 长期应收款
E38: =IF(D38=0,"",VLOOKUP(D38,$N:$O,2,0)) | H38: =IF(G38=0,"",VLOOKUP(G38,$N:$O,2,0)) | N38: =母公司汇总抵销!N38 -> D22 | O38: =母公司汇总抵销!O38 -> 设定受益计划净资产
J39: =IF(ABS((SUMIF(E33:E38,"?*",J33:J38)-SUMIF(H33:H38,"?*",J33:J38)))<0.005,"","借贷不等") | N39: =母公司汇总抵销!N39 -> D23 | O39: =母公司汇总抵销!O39 -> 长期股权投资
A40: 6 | E40: =IF(D40=0,"",VLOOKUP(D40,$N:$O,2,0)) | H40: =IF(G40=0,"",VLOOKUP(G40,$N:$O,2,0)) | N40: =母公司汇总抵销!N40 -> D24 | O40: =母公司汇总抵销!O40 -> 其他权益工具投资
E41: =IF(D41=0,"",VLOOKUP(D41,$N:$O,2,0)) | H41: =IF(G41=0,"",VLOOKUP(G41,$N:$O,2,0)) | N41: =母公司汇总抵销!N41 -> D25 | O41: =母公司汇总抵销!O41 -> 其他非流动金融资产
E42: =IF(D42=0,"",VLOOKUP(D42,$N:$O,2,0)) | H42: =IF(G42=0,"",VLOOKUP(G42,$N:$O,2,0)) | N42: =母公司汇总抵销!N42 -> D26 | O42: =母公司汇总抵销!O42 -> 投资性房地产
E43: =IF(D43=0,"",VLOOKUP(D43,$N:$O,2,0)) | H43: =IF(G43=0,"",VLOOKUP(G43,$N:$O,2,0)) | N43: =母公司汇总抵销!N43 -> D27 | O43: =母公司汇总抵销!O43 -> 固定资产
E44: =IF(D44=0,"",VLOOKUP(D44,$N:$O,2,0)) | H44: =IF(G44=0,"",VLOOKUP(G44,$N:$O,2,0)) | N44: =母公司汇总抵销!N44 -> D28 | O44: =母公司汇总抵销!O44 -> 在建工程
E45: =IF(D45=0,"",VLOOKUP(D45,$N:$O,2,0)) | H45: =IF(G45=0,"",VLOOKUP(G45,$N:$O,2,0)) | N45: =母公司汇总抵销!N45 -> D29 | O45: =母公司汇总抵销!O45 -> 生产性生物资产
J46: =IF(ABS((SUMIF(E40:E45,"?*",J40:J45)-SUMIF(H40:H45,"?*",J40:J45)))<0.005,"","借贷不等") | N46: =母公司汇总抵销!N46 -> D30 | O46: =母公司汇总抵销!O46 -> 油气资产
A47: 7 | E47: =IF(D47=0,"",VLOOKUP(D47,$N:$O,2,0)) | H47: =IF(G47=0,"",VLOOKUP(G47,$N:$O,2,0)) | N47: =母公司汇总抵销!N47 -> D31 | O47: =母公司汇总抵销!O47 -> 使用权资产
E48: =IF(D48=0,"",VLOOKUP(D48,$N:$O,2,0)) | H48: =IF(G48=0,"",VLOOKUP(G48,$N:$O,2,0)) | N48: =母公司汇总抵销!N48 -> D32 | O48: =母公司汇总抵销!O48 -> 无形资产
E49: =IF(D49=0,"",VLOOKUP(D49,$N:$O,2,0)) | H49: =IF(G49=0,"",VLOOKUP(G49,$N:$O,2,0)) | N49: =母公司汇总抵销!N49 -> D33 | O49: =母公司汇总抵销!O49 -> 开发支出
E50: =IF(D50=0,"",VLOOKUP(D50,$N:$O,2,0)) | H50: =IF(G50=0,"",VLOOKUP(G50,$N:$O,2,0)) | N50: =母公司汇总抵销!N50 -> D34 | O50: =母公司汇总抵销!O50 -> 商誉
E51: =IF(D51=0,"",VLOOKUP(D51,$N:$O,2,0)) | H51: =IF(G51=0,"",VLOOKUP(G51,$N:$O,2,0)) | N51: =母公司汇总抵销!N51 -> D35 | O51: =母公司汇总抵销!O51 -> 长期待摊费用
E52: =IF(D52=0,"",VLOOKUP(D52,$N:$O,2,0)) | H52: =IF(G52=0,"",VLOOKUP(G52,$N:$O,2,0)) | N52: =母公司汇总抵销!N52 -> D36 | O52: =母公司汇总抵销!O52 -> 递延所得税资产
J53: =IF(ABS((SUMIF(E47:E52,"?*",J47:J52)-SUMIF(H47:H52,"?*",J47:J52)))<0.005,"","借贷不等") | N53: =母公司汇总抵销!N53 -> D37 | O53: =母公司汇总抵销!O53 -> 其他非流动资产
A54: 8 | E54: =IF(D54=0,"",VLOOKUP(D54,$N:$O,2,0)) | H54: =IF(G54=0,"",VLOOKUP(G54,$N:$O,2,0)) | N54: =母公司汇总抵销!N54 -> D38 | O54: =母公司汇总抵销!O54 -> 0
E55: =IF(D55=0,"",VLOOKUP(D55,$N:$O,2,0)) | H55: =IF(G55=0,"",VLOOKUP(G55,$N:$O,2,0)) | N55: =母公司汇总抵销!N55 -> D39 | O55: =母公司汇总抵销!O55 -> 0
E56: =IF(D56=0,"",VLOOKUP(D56,$N:$O,2,0)) | H56: =IF(G56=0,"",VLOOKUP(G56,$N:$O,2,0)) | N56: =母公司汇总抵销!N56 -> D40 | O56: =母公司汇总抵销!O56 -> 0
E57: =IF(D57=0,"",VLOOKUP(D57,$N:$O,2,0)) | H57: =IF(G57=0,"",VLOOKUP(G57,$N:$O,2,0)) | N57: =母公司汇总抵销!N57 -> 0 | O57: =母公司汇总抵销!O57 -> 非流动资产合计
E58: =IF(D58=0,"",VLOOKUP(D58,$N:$O,2,0)) | H58: =IF(G58=0,"",VLOOKUP(G58,$N:$O,2,0)) | N58: =母公司汇总抵销!N58 -> 0 | O58: =母公司汇总抵销!O58 -> 资 产 总 计
E59: =IF(D59=0,"",VLOOKUP(D59,$N:$O,2,0)) | H59: =IF(G59=0,"",VLOOKUP(G59,$N:$O,2,0)) | N59: =母公司汇总抵销!N59 -> 0 | O59: =母公司汇总抵销!O59
J60: =IF(ABS((SUMIF(E54:E59,"?*",J54:J59)-SUMIF(H54:H59,"?*",J54:J59)))<0.005,"","借贷不等") | N60: =母公司汇总抵销!N60 -> 0 | O60: =母公司汇总抵销!O60
A61: 9 | E61: =IF(D61=0,"",VLOOKUP(D61,$N:$O,2,0)) | H61: =IF(G61=0,"",VLOOKUP(G61,$N:$O,2,0)) | N61: =母公司汇总抵销!N61 -> 0 | O61: =母公司汇总抵销!O61 -> 流动负债：
E62: =IF(D62=0,"",VLOOKUP(D62,$N:$O,2,0)) | H62: =IF(G62=0,"",VLOOKUP(G62,$N:$O,2,0)) | N62: =母公司汇总抵销!N62 -> E1 | O62: =母公司汇总抵销!O62 -> 短期借款
E63: =IF(D63=0,"",VLOOKUP(D63,$N:$O,2,0)) | H63: =IF(G63=0,"",VLOOKUP(G63,$N:$O,2,0)) | N63: =母公司汇总抵销!N63 -> E24 | O63: =母公司汇总抵销!O63 -> 向中央银行借款
E64: =IF(D64=0,"",VLOOKUP(D64,$N:$O,2,0)) | H64: =IF(G64=0,"",VLOOKUP(G64,$N:$O,2,0)) | N64: =母公司汇总抵销!N64 -> E25 | O64: =母公司汇总抵销!O64 -> 吸收存款及同业存放
E65: =IF(D65=0,"",VLOOKUP(D65,$N:$O,2,0)) | H65: =IF(G65=0,"",VLOOKUP(G65,$N:$O,2,0)) | N65: =母公司汇总抵销!N65 -> E26 | O65: =母公司汇总抵销!O65 -> 拆入资金
E66: =IF(D66=0,"",VLOOKUP(D66,$N:$O,2,0)) | H66: =IF(G66=0,"",VLOOKUP(G66,$N:$O,2,0)) | N66: =母公司汇总抵销!N66 -> E2 | O66: =母公司汇总抵销!O66 -> 交易性金融负债
J67: =IF(ABS((SUMIF(E61:E66,"?*",J61:J66)-SUMIF(H61:H66,"?*",J61:J66)))<0.005,"","借贷不等") | N67: =母公司汇总抵销!N67 -> E3 | O67: =母公司汇总抵销!O67 -> 以公允价值计量且其变动计入当期损益的金融负债
A68: 10 | E68: =IF(D68=0,"",VLOOKUP(D68,$N:$O,2,0)) | H68: =IF(G68=0,"",VLOOKUP(G68,$N:$O,2,0)) | N68: =母公司汇总抵销!N68 -> E4 | O68: =母公司汇总抵销!O68 -> 衍生金融负债
E69: =IF(D69=0,"",VLOOKUP(D69,$N:$O,2,0)) | H69: =IF(G69=0,"",VLOOKUP(G69,$N:$O,2,0)) | N69: =母公司汇总抵销!N69 -> E5 | O69: =母公司汇总抵销!O69 -> 应付票据
E70: =IF(D70=0,"",VLOOKUP(D70,$N:$O,2,0)) | H70: =IF(G70=0,"",VLOOKUP(G70,$N:$O,2,0)) | N70: =母公司汇总抵销!N70 -> E6 | O70: =母公司汇总抵销!O70 -> 应付账款
E71: =IF(D71=0,"",VLOOKUP(D71,$N:$O,2,0)) | H71: =IF(G71=0,"",VLOOKUP(G71,$N:$O,2,0)) | N71: =母公司汇总抵销!N71 -> E7 | O71: =母公司汇总抵销!O71 -> 预收款项
E72: =IF(D72=0,"",VLOOKUP(D72,$N:$O,2,0)) | H72: =IF(G72=0,"",VLOOKUP(G72,$N:$O,2,0)) | N72: =母公司汇总抵销!N72 -> E27 | O72: =母公司汇总抵销!O72 -> 卖出回购金融资产款
E73: =IF(D73=0,"",VLOOKUP(D73,$N:$O,2,0)) | H73: =IF(G73=0,"",VLOOKUP(G73,$N:$O,2,0)) | N73: =母公司汇总抵销!N73 -> E28 | O73: =母公司汇总抵销!O73 -> 应付手续费及佣金
J74: =IF(ABS((SUMIF(E68:E73,"?*",J68:J73)-SUMIF(H68:H73,"?*",J68:J73)))<0.005,"","借贷不等") | N74: =母公司汇总抵销!N74 -> E8 | O74: =母公司汇总抵销!O74 -> 合同负债
A75: 11 | E75: =IF(D75=0,"",VLOOKUP(D75,$N:$O,2,0)) | H75: =IF(G75=0,"",VLOOKUP(G75,$N:$O,2,0)) | N75: =母公司汇总抵销!N75 -> E9 | O75: =母公司汇总抵销!O75 -> 应付职工薪酬
E76: =IF(D76=0,"",VLOOKUP(D76,$N:$O,2,0)) | H76: =IF(G76=0,"",VLOOKUP(G76,$N:$O,2,0)) | N76: =母公司汇总抵销!N76 -> E10 | O76: =母公司汇总抵销!O76 -> 应交税费
E77: =IF(D77=0,"",VLOOKUP(D77,$N:$O,2,0)) | H77: =IF(G77=0,"",VLOOKUP(G77,$N:$O,2,0)) | N77: =母公司汇总抵销!N77 -> E11 | O77: =母公司汇总抵销!O77 -> 其他应付款
E78: =IF(D78=0,"",VLOOKUP(D78,$N:$O,2,0)) | H78: =IF(G78=0,"",VLOOKUP(G78,$N:$O,2,0)) | N78: =母公司汇总抵销!N78 -> 0 | O78: =母公司汇总抵销!O78 -> 应付利息
E79: =IF(D79=0,"",VLOOKUP(D79,$N:$O,2,0)) | H79: =IF(G79=0,"",VLOOKUP(G79,$N:$O,2,0)) | N79: =母公司汇总抵销!N79 -> 0 | O79: =母公司汇总抵销!O79 -> 应付股利
E80: =IF(D80=0,"",VLOOKUP(D80,$N:$O,2,0)) | H80: =IF(G80=0,"",VLOOKUP(G80,$N:$O,2,0)) | N80: =母公司汇总抵销!N80 -> E29 | O80: =母公司汇总抵销!O80 -> 应付分保账款
J81: =IF(ABS((SUMIF(E75:E80,"?*",J75:J80)-SUMIF(H75:H80,"?*",J75:J80)))<0.005,"","借贷不等") | N81: =母公司汇总抵销!N81 -> E30 | O81: =母公司汇总抵销!O81 -> 保险合同准备金
A82: 12 | E82: =IF(D82=0,"",VLOOKUP(D82,$N:$O,2,0)) | H82: =IF(G82=0,"",VLOOKUP(G82,$N:$O,2,0)) | N82: =母公司汇总抵销!N82 -> E31 | O82: =母公司汇总抵销!O82 -> 代理买卖证券款
E83: =IF(D83=0,"",VLOOKUP(D83,$N:$O,2,0)) | H83: =IF(G83=0,"",VLOOKUP(G83,$N:$O,2,0)) | N83: =母公司汇总抵销!N83 -> E32 | O83: =母公司汇总抵销!O83 -> 代理承销证券款
E84: =IF(D84=0,"",VLOOKUP(D84,$N:$O,2,0)) | H84: =IF(G84=0,"",VLOOKUP(G84,$N:$O,2,0)) | N84: =母公司汇总抵销!N84 -> E12 | O84: =母公司汇总抵销!O84 -> 持有待售负债
E85: =IF(D85=0,"",VLOOKUP(D85,$N:$O,2,0)) | H85: =IF(G85=0,"",VLOOKUP(G85,$N:$O,2,0)) | N85: =母公司汇总抵销!N85 -> E13 | O85: =母公司汇总抵销!O85 -> 一年内到期的非流动负债
E86: =IF(D86=0,"",VLOOKUP(D86,$N:$O,2,0)) | H86: =IF(G86=0,"",VLOOKUP(G86,$N:$O,2,0)) | N86: =母公司汇总抵销!N86 -> E14 | O86: =母公司汇总抵销!O86 -> 其他流动负债
E87: =IF(D87=0,"",VLOOKUP(D87,$N:$O,2,0)) | H87: =IF(G87=0,"",VLOOKUP(G87,$N:$O,2,0)) | N87: =母公司汇总抵销!N87 -> 0 | O87: =母公司汇总抵销!O87 -> 流动负债合计
J88: =IF(ABS((SUMIF(E82:E87,"?*",J82:J87)-SUMIF(H82:H87,"?*",J82:J87)))<0.005,"","借贷不等") | N88: =母公司汇总抵销!N88 -> 0 | O88: =母公司汇总抵销!O88 -> 非流动负债:
A89: 13 | E89: =IF(D89=0,"",VLOOKUP(D89,$N:$O,2,0)) | H89: =IF(G89=0,"",VLOOKUP(G89,$N:$O,2,0)) | N89: =母公司汇总抵销!N89 -> E15 | O89: =母公司汇总抵销!O89 -> 长期借款
E90: =IF(D90=0,"",VLOOKUP(D90,$N:$O,2,0)) | H90: =IF(G90=0,"",VLOOKUP(G90,$N:$O,2,0)) | N90: =母公司汇总抵销!N90 -> E16 | O90: =母公司汇总抵销!O90 -> 应付债券
E91: =IF(D91=0,"",VLOOKUP(D91,$N:$O,2,0)) | H91: =IF(G91=0,"",VLOOKUP(G91,$N:$O,2,0)) | N91: =母公司汇总抵销!N91 -> 0 | O91: =母公司汇总抵销!O91 -> 优先股
E92: =IF(D92=0,"",VLOOKUP(D92,$N:$O,2,0)) | H92: =IF(G92=0,"",VLOOKUP(G92,$N:$O,2,0)) | N92: =母公司汇总抵销!N92 -> 0 | O92: =母公司汇总抵销!O92 -> 永续债
E93: =IF(D93=0,"",VLOOKUP(D93,$N:$O,2,0)) | H93: =IF(G93=0,"",VLOOKUP(G93,$N:$O,2,0)) | N93: =母公司汇总抵销!N93 -> E17 | O93: =母公司汇总抵销!O93 -> 租赁负债
E94: =IF(D94=0,"",VLOOKUP(D94,$N:$O,2,0)) | H94: =IF(G94=0,"",VLOOKUP(G94,$N:$O,2,0)) | N94: =母公司汇总抵销!N94 -> E18 | O94: =母公司汇总抵销!O94 -> 长期应付款
J95: =IF(ABS((SUMIF(E89:E94,"?*",J89:J94)-SUMIF(H89:H94,"?*",J89:J94)))<0.005,"","借贷不等") | N95: =母公司汇总抵销!N95 -> E19 | O95: =母公司汇总抵销!O95 -> 长期应付职工薪酬
A96: 14 | E96: =IF(D96=0,"",VLOOKUP(D96,$N:$O,2,0)) | H96: =IF(G96=0,"",VLOOKUP(G96,$N:$O,2,0)) | N96: =母公司汇总抵销!N96 -> E20 | O96: =母公司汇总抵销!O96 -> 预计负债
E97: =IF(D97=0,"",VLOOKUP(D97,$N:$O,2,0)) | H97: =IF(G97=0,"",VLOOKUP(G97,$N:$O,2,0)) | N97: =母公司汇总抵销!N97 -> E21 | O97: =母公司汇总抵销!O97 -> 递延收益
E98: =IF(D98=0,"",VLOOKUP(D98,$N:$O,2,0)) | H98: =IF(G98=0,"",VLOOKUP(G98,$N:$O,2,0)) | N98: =母公司汇总抵销!N98 -> E22 | O98: =母公司汇总抵销!O98 -> 递延所得税负债
E99: =IF(D99=0,"",VLOOKUP(D99,$N:$O,2,0)) | H99: =IF(G99=0,"",VLOOKUP(G99,$N:$O,2,0)) | N99: =母公司汇总抵销!N99 -> E23 | O99: =母公司汇总抵销!O99 -> 其他非流动负债
E100: =IF(D100=0,"",VLOOKUP(D100,$N:$O,2,0)) | H100: =IF(G100=0,"",VLOOKUP(G100,$N:$O,2,0)) | N100: =母公司汇总抵销!N100 -> 0 | O100: =母公司汇总抵销!O100 -> 非流动负债合计
...

Sheet 母公司报表调整
A1: =IF((L2-(母公司TB资产!G60+母公司TB负债!G63+母公司TB损益!G90)-IF(COUNTIF(E5:E666,"未分配利润")>=1,VLOOKUP("未分配利润",E5:J666,6,0),0))<0.005,"母公司报表调整事项汇总表","调整事项未全部链入试算平衡表，请检查调整科目是否为报表项目!") -> 母公司报表调整事项汇总表 | K1: =SUM(L2:L3) -> 0 | N1: =母公司汇总抵销!N1 -> code | O1: =母公司汇总抵销!O1 -> 报表项目
A2: =CONCATENATE("客户名称：",说明!E23) -> 客户名称： | E2: =CONCATENATE("编制人：",说明!E36) -> 编制人： | H2: =CONCATENATE("日期：",TEXT(NOW(),"yyyy.mm.dd")) -> 日期：2019.12.31 | J2: 索引： | K2: 借方调整累计 | L2: =SUMIF(E5:E65536,"?*",J5:J65536) -> 0 | N2: =母公司汇总抵销!N2 -> 0 | O2: =母公司汇总抵销!O2 -> 0
A3: =CONCATENATE("会计期间：",说明!E30) -> 会计期间：2019年度 | E3: =CONCATENATE("复核人：",说明!E37) -> 复核人： | H3: 日期： | J3: 页码： | K3: 贷方调整累计 | L3: =SUMIF(H5:H65536,"?*",J5:J65536) -> 0 | N3: =母公司汇总抵销!N3 -> 0 | O3: =母公司汇总抵销!O3 -> 0
A4: 序号 | B4: 索引号 | C4: 调整说明 | D4: code | E4: 借方科目 | F4: 二级科目 | G4: code | H4: 贷方科目 | I4: 二级科目 | J4: 金额 | L4: =L2-L3 -> 0 | N4: =母公司汇总抵销!N4 -> 0 | O4: =母公司汇总抵销!O4 -> 0
A5: 1 | E5: =IF(D5=0,"",VLOOKUP(D5,$N:$O,2,0)) | H5: =IF(G5=0,"",VLOOKUP(G5,$N:$O,2,0)) | K5: 本表可根据需要插入行， | N5: =母公司汇总抵销!N5 -> 0 | O5: =母公司汇总抵销!O5 -> 流动资产：
E6: =IF(D6=0,"",VLOOKUP(D6,$N:$O,2,0)) | H6: =IF(G6=0,"",VLOOKUP(G6,$N:$O,2,0)) | K6: 请勿删除行。 | N6: =母公司汇总抵销!N6 -> D1 | O6: =母公司汇总抵销!O6 -> 货币资金
E7: =IF(D7=0,"",VLOOKUP(D7,$N:$O,2,0)) | N7: =母公司汇总抵销!N7 -> D41 | O7: =母公司汇总抵销!O7 -> 结算备付金
H8: =IF(G8=0,"",VLOOKUP(G8,$N:$O,2,0)) | N8: =母公司汇总抵销!N8 -> D42 | O8: =母公司汇总抵销!O8 -> 拆出资金
E9: =IF(D9=0,"",VLOOKUP(D9,$N:$O,2,0)) | H9: =IF(G9=0,"",VLOOKUP(G9,$N:$O,2,0)) | N9: =母公司汇总抵销!N9 -> D2 | O9: =母公司汇总抵销!O9 -> 交易性金融资产
E10: =IF(D10=0,"",VLOOKUP(D10,$N:$O,2,0)) | H10: =IF(G10=0,"",VLOOKUP(G10,$N:$O,2,0)) | N10: =母公司汇总抵销!N10 -> D3 | O10: =母公司汇总抵销!O10 -> 以公允价值计量且其变动计入当期损益的金融资产
J11: =IF(ABS((SUMIF(E5:E10,"?*",J5:J10)-SUMIF(H5:H10,"?*",J5:J10)))<0.005,"","借贷不等") | N11: =母公司汇总抵销!N11 -> D4 | O11: =母公司汇总抵销!O11 -> 衍生金融资产
A12: 2 | E12: =IF(D12=0,"",VLOOKUP(D12,$N:$O,2,0)) | H12: =IF(G12=0,"",VLOOKUP(G12,$N:$O,2,0)) | N12: =母公司汇总抵销!N12 -> D5 | O12: =母公司汇总抵销!O12 -> 应收票据
E13: =IF(D13=0,"",VLOOKUP(D13,$N:$O,2,0)) | H13: =IF(G13=0,"",VLOOKUP(G13,$N:$O,2,0)) | N13: =母公司汇总抵销!N13 -> D6 | O13: =母公司汇总抵销!O13 -> 应收账款
E14: =IF(D14=0,"",VLOOKUP(D14,$N:$O,2,0)) | H14: =IF(G14=0,"",VLOOKUP(G14,$N:$O,2,0)) | N14: =母公司汇总抵销!N14 -> D7 | O14: =母公司汇总抵销!O14 -> 应收款项融资
E15: =IF(D15=0,"",VLOOKUP(D15,$N:$O,2,0)) | H15: =IF(G15=0,"",VLOOKUP(G15,$N:$O,2,0)) | N15: =母公司汇总抵销!N15 -> D8 | O15: =母公司汇总抵销!O15 -> 预付款项
E16: =IF(D16=0,"",VLOOKUP(D16,$N:$O,2,0)) | H16: =IF(G16=0,"",VLOOKUP(G16,$N:$O,2,0)) | N16: =母公司汇总抵销!N16 -> D43 | O16: =母公司汇总抵销!O16 -> 应收保费
E17: =IF(D17=0,"",VLOOKUP(D17,$N:$O,2,0)) | H17: =IF(G17=0,"",VLOOKUP(G17,$N:$O,2,0)) | N17: =母公司汇总抵销!N17 -> D44 | O17: =母公司汇总抵销!O17 -> 应收分保账款
J18: =IF(ABS((SUMIF(E12:E17,"?*",J12:J17)-SUMIF(H12:H17,"?*",J12:J17)))<0.005,"","借贷不等") | N18: =母公司汇总抵销!N18 -> D45 | O18: =母公司汇总抵销!O18 -> 应收分保准备金
A19: 3 | E19: =IF(D19=0,"",VLOOKUP(D19,$N:$O,2,0)) | H19: =IF(G19=0,"",VLOOKUP(G19,$N:$O,2,0)) | N19: =母公司汇总抵销!N19 -> D9 | O19: =母公司汇总抵销!O19 -> 其他应收款
E20: =IF(D20=0,"",VLOOKUP(D20,$N:$O,2,0)) | H20: =IF(G20=0,"",VLOOKUP(G20,$N:$O,2,0)) | N20: =母公司汇总抵销!N20 -> 0 | O20: =母公司汇总抵销!O20 -> 应收利息
E21: =IF(D21=0,"",VLOOKUP(D21,$N:$O,2,0)) | H21: =IF(G21=0,"",VLOOKUP(G21,$N:$O,2,0)) | N21: =母公司汇总抵销!N21 -> 0 | O21: =母公司汇总抵销!O21 -> 应收股利
E22: =IF(D22=0,"",VLOOKUP(D22,$N:$O,2,0)) | H22: =IF(G22=0,"",VLOOKUP(G22,$N:$O,2,0)) | N22: =母公司汇总抵销!N22 -> D46 | O22: =母公司汇总抵销!O22 -> 买入返售金融资产
E23: =IF(D23=0,"",VLOOKUP(D23,$N:$O,2,0)) | H23: =IF(G23=0,"",VLOOKUP(G23,$N:$O,2,0)) | N23: =母公司汇总抵销!N23 -> D10 | O23: =母公司汇总抵销!O23 -> 存货
E24: =IF(D24=0,"",VLOOKUP(D24,$N:$O,2,0)) | H24: =IF(G24=0,"",VLOOKUP(G24,$N:$O,2,0)) | N24: =母公司汇总抵销!N24 -> D11 | O24: =母公司汇总抵销!O24 -> 合同资产
J25: =IF(ABS((SUMIF(E19:E24,"?*",J19:J24)-SUMIF(H19:H24,"?*",J19:J24)))<0.005,"","借贷不等") | N25: =母公司汇总抵销!N25 -> D12 | O25: =母公司汇总抵销!O25 -> 持有待售资产
A26: 4 | E26: =IF(D26=0,"",VLOOKUP(D26,$N:$O,2,0)) | H26: =IF(G26=0,"",VLOOKUP(G26,$N:$O,2,0)) | N26: =母公司汇总抵销!N26 -> D13 | O26: =母公司汇总抵销!O26 -> 一年内到期的非流动资产
E27: =IF(D27=0,"",VLOOKUP(D27,$N:$O,2,0)) | H27: =IF(G27=0,"",VLOOKUP(G27,$N:$O,2,0)) | N27: =母公司汇总抵销!N27 -> D14 | O27: =母公司汇总抵销!O27 -> 其他流动资产
E28: =IF(D28=0,"",VLOOKUP(D28,$N:$O,2,0)) | H28: =IF(G28=0,"",VLOOKUP(G28,$N:$O,2,0)) | N28: =母公司汇总抵销!N28 -> D15 | O28: =母公司汇总抵销!O28 -> 0
E29: =IF(D29=0,"",VLOOKUP(D29,$N:$O,2,0)) | H29: =IF(G29=0,"",VLOOKUP(G29,$N:$O,2,0)) | N29: =母公司汇总抵销!N29 -> D16 | O29: =母公司汇总抵销!O29 -> 0
E30: =IF(D30=0,"",VLOOKUP(D30,$N:$O,2,0)) | H30: =IF(G30=0,"",VLOOKUP(G30,$N:$O,2,0)) | N30: =母公司汇总抵销!N30 -> 0 | O30: =母公司汇总抵销!O30 -> 流动资产合计
E31: =IF(D31=0,"",VLOOKUP(D31,$N:$O,2,0)) | H31: =IF(G31=0,"",VLOOKUP(G31,$N:$O,2,0)) | N31: =母公司汇总抵销!N31 -> 0 | O31: =母公司汇总抵销!O31 -> 非流动资产:
J32: =IF(ABS((SUMIF(E26:E31,"?*",J26:J31)-SUMIF(H26:H31,"?*",J26:J31)))<0.005,"","借贷不等") | N32: =母公司汇总抵销!N32 -> D47 | O32: =母公司汇总抵销!O32 -> 发放贷款及垫款
A33: 5 | E33: =IF(D33=0,"",VLOOKUP(D33,$N:$O,2,0)) | H33: =IF(G33=0,"",VLOOKUP(G33,$N:$O,2,0)) | N33: =母公司汇总抵销!N33 -> D17 | O33: =母公司汇总抵销!O33 -> 债权投资
E34: =IF(D34=0,"",VLOOKUP(D34,$N:$O,2,0)) | H34: =IF(G34=0,"",VLOOKUP(G34,$N:$O,2,0)) | N34: =母公司汇总抵销!N34 -> D18 | O34: =母公司汇总抵销!O34 -> 可供出售金融资产
E35: =IF(D35=0,"",VLOOKUP(D35,$N:$O,2,0)) | H35: =IF(G35=0,"",VLOOKUP(G35,$N:$O,2,0)) | N35: =母公司汇总抵销!N35 -> D19 | O35: =母公司汇总抵销!O35 -> 其他债权投资
E36: =IF(D36=0,"",VLOOKUP(D36,$N:$O,2,0)) | H36: =IF(G36=0,"",VLOOKUP(G36,$N:$O,2,0)) | N36: =母公司汇总抵销!N36 -> D20 | O36: =母公司汇总抵销!O36 -> 持有至到期投资
E37: =IF(D37=0,"",VLOOKUP(D37,$N:$O,2,0)) | H37: =IF(G37=0,"",VLOOKUP(G37,$N:$O,2,0)) | N37: =母公司汇总抵销!N37 -> D21 | O37: =母公司汇总抵销!O37 -> 长期应收款
E38: =IF(D38=0,"",VLOOKUP(D38,$N:$O,2,0)) | H38: =IF(G38=0,"",VLOOKUP(G38,$N:$O,2,0)) | N38: =母公司汇总抵销!N38 -> D22 | O38: =母公司汇总抵销!O38 -> 设定受益计划净资产
J39: =IF(ABS((SUMIF(E33:E38,"?*",J33:J38)-SUMIF(H33:H38,"?*",J33:J38)))<0.005,"","借贷不等") | N39: =母公司汇总抵销!N39 -> D23 | O39: =母公司汇总抵销!O39 -> 长期股权投资
A40: 6 | E40: =IF(D40=0,"",VLOOKUP(D40,$N:$O,2,0)) | H40: =IF(G40=0,"",VLOOKUP(G40,$N:$O,2,0)) | N40: =母公司汇总抵销!N40 -> D24 | O40: =母公司汇总抵销!O40 -> 其他权益工具投资
E41: =IF(D41=0,"",VLOOKUP(D41,$N:$O,2,0)) | H41: =IF(G41=0,"",VLOOKUP(G41,$N:$O,2,0)) | N41: =母公司汇总抵销!N41 -> D25 | O41: =母公司汇总抵销!O41 -> 其他非流动金融资产
E42: =IF(D42=0,"",VLOOKUP(D42,$N:$O,2,0)) | H42: =IF(G42=0,"",VLOOKUP(G42,$N:$O,2,0)) | N42: =母公司汇总抵销!N42 -> D26 | O42: =母公司汇总抵销!O42 -> 投资性房地产
E43: =IF(D43=0,"",VLOOKUP(D43,$N:$O,2,0)) | H43: =IF(G43=0,"",VLOOKUP(G43,$N:$O,2,0)) | N43: =母公司汇总抵销!N43 -> D27 | O43: =母公司汇总抵销!O43 -> 固定资产
E44: =IF(D44=0,"",VLOOKUP(D44,$N:$O,2,0)) | H44: =IF(G44=0,"",VLOOKUP(G44,$N:$O,2,0)) | N44: =母公司汇总抵销!N44 -> D28 | O44: =母公司汇总抵销!O44 -> 在建工程
E45: =IF(D45=0,"",VLOOKUP(D45,$N:$O,2,0)) | H45: =IF(G45=0,"",VLOOKUP(G45,$N:$O,2,0)) | N45: =母公司汇总抵销!N45 -> D29 | O45: =母公司汇总抵销!O45 -> 生产性生物资产
J46: =IF(ABS((SUMIF(E40:E45,"?*",J40:J45)-SUMIF(H40:H45,"?*",J40:J45)))<0.005,"","借贷不等") | N46: =母公司汇总抵销!N46 -> D30 | O46: =母公司汇总抵销!O46 -> 油气资产
A47: 7 | E47: =IF(D47=0,"",VLOOKUP(D47,$N:$O,2,0)) | H47: =IF(G47=0,"",VLOOKUP(G47,$N:$O,2,0)) | N47: =母公司汇总抵销!N47 -> D31 | O47: =母公司汇总抵销!O47 -> 使用权资产
E48: =IF(D48=0,"",VLOOKUP(D48,$N:$O,2,0)) | H48: =IF(G48=0,"",VLOOKUP(G48,$N:$O,2,0)) | N48: =母公司汇总抵销!N48 -> D32 | O48: =母公司汇总抵销!O48 -> 无形资产
E49: =IF(D49=0,"",VLOOKUP(D49,$N:$O,2,0)) | H49: =IF(G49=0,"",VLOOKUP(G49,$N:$O,2,0)) | N49: =母公司汇总抵销!N49 -> D33 | O49: =母公司汇总抵销!O49 -> 开发支出
E50: =IF(D50=0,"",VLOOKUP(D50,$N:$O,2,0)) | H50: =IF(G50=0,"",VLOOKUP(G50,$N:$O,2,0)) | N50: =母公司汇总抵销!N50 -> D34 | O50: =母公司汇总抵销!O50 -> 商誉
E51: =IF(D51=0,"",VLOOKUP(D51,$N:$O,2,0)) | H51: =IF(G51=0,"",VLOOKUP(G51,$N:$O,2,0)) | N51: =母公司汇总抵销!N51 -> D35 | O51: =母公司汇总抵销!O51 -> 长期待摊费用
E52: =IF(D52=0,"",VLOOKUP(D52,$N:$O,2,0)) | H52: =IF(G52=0,"",VLOOKUP(G52,$N:$O,2,0)) | N52: =母公司汇总抵销!N52 -> D36 | O52: =母公司汇总抵销!O52 -> 递延所得税资产
J53: =IF(ABS((SUMIF(E47:E52,"?*",J47:J52)-SUMIF(H47:H52,"?*",J47:J52)))<0.005,"","借贷不等") | N53: =母公司汇总抵销!N53 -> D37 | O53: =母公司汇总抵销!O53 -> 其他非流动资产
A54: 8 | E54: =IF(D54=0,"",VLOOKUP(D54,$N:$O,2,0)) | H54: =IF(G54=0,"",VLOOKUP(G54,$N:$O,2,0)) | N54: =母公司汇总抵销!N54 -> D38 | O54: =母公司汇总抵销!O54 -> 0
E55: =IF(D55=0,"",VLOOKUP(D55,$N:$O,2,0)) | H55: =IF(G55=0,"",VLOOKUP(G55,$N:$O,2,0)) | N55: =母公司汇总抵销!N55 -> D39 | O55: =母公司汇总抵销!O55 -> 0
E56: =IF(D56=0,"",VLOOKUP(D56,$N:$O,2,0)) | H56: =IF(G56=0,"",VLOOKUP(G56,$N:$O,2,0)) | N56: =母公司汇总抵销!N56 -> D40 | O56: =母公司汇总抵销!O56 -> 0
E57: =IF(D57=0,"",VLOOKUP(D57,$N:$O,2,0)) | H57: =IF(G57=0,"",VLOOKUP(G57,$N:$O,2,0)) | N57: =母公司汇总抵销!N57 -> 0 | O57: =母公司汇总抵销!O57 -> 非流动资产合计
E58: =IF(D58=0,"",VLOOKUP(D58,$N:$O,2,0)) | H58: =IF(G58=0,"",VLOOKUP(G58,$N:$O,2,0)) | N58: =母公司汇总抵销!N58 -> 0 | O58: =母公司汇总抵销!O58 -> 资 产 总 计
E59: =IF(D59=0,"",VLOOKUP(D59,$N:$O,2,0)) | H59: =IF(G59=0,"",VLOOKUP(G59,$N:$O,2,0)) | N59: =母公司汇总抵销!N59 -> 0 | O59: =母公司汇总抵销!O59
J60: =IF(ABS((SUMIF(E54:E59,"?*",J54:J59)-SUMIF(H54:H59,"?*",J54:J59)))<0.005,"","借贷不等") | N60: =母公司汇总抵销!N60 -> 0 | O60: =母公司汇总抵销!O60
A61: 9 | E61: =IF(D61=0,"",VLOOKUP(D61,$N:$O,2,0)) | H61: =IF(G61=0,"",VLOOKUP(G61,$N:$O,2,0)) | N61: =母公司汇总抵销!N61 -> 0 | O61: =母公司汇总抵销!O61 -> 流动负债：
E62: =IF(D62=0,"",VLOOKUP(D62,$N:$O,2,0)) | H62: =IF(G62=0,"",VLOOKUP(G62,$N:$O,2,0)) | N62: =母公司汇总抵销!N62 -> E1 | O62: =母公司汇总抵销!O62 -> 短期借款
E63: =IF(D63=0,"",VLOOKUP(D63,$N:$O,2,0)) | H63: =IF(G63=0,"",VLOOKUP(G63,$N:$O,2,0)) | N63: =母公司汇总抵销!N63 -> E24 | O63: =母公司汇总抵销!O63 -> 向中央银行借款
E64: =IF(D64=0,"",VLOOKUP(D64,$N:$O,2,0)) | H64: =IF(G64=0,"",VLOOKUP(G64,$N:$O,2,0)) | N64: =母公司汇总抵销!N64 -> E25 | O64: =母公司汇总抵销!O64 -> 吸收存款及同业存放
E65: =IF(D65=0,"",VLOOKUP(D65,$N:$O,2,0)) | H65: =IF(G65=0,"",VLOOKUP(G65,$N:$O,2,0)) | N65: =母公司汇总抵销!N65 -> E26 | O65: =母公司汇总抵销!O65 -> 拆入资金
E66: =IF(D66=0,"",VLOOKUP(D66,$N:$O,2,0)) | H66: =IF(G66=0,"",VLOOKUP(G66,$N:$O,2,0)) | N66: =母公司汇总抵销!N66 -> E2 | O66: =母公司汇总抵销!O66 -> 交易性金融负债
J67: =IF(ABS((SUMIF(E61:E66,"?*",J61:J66)-SUMIF(H61:H66,"?*",J61:J66)))<0.005,"","借贷不等") | N67: =母公司汇总抵销!N67 -> E3 | O67: =母公司汇总抵销!O67 -> 以公允价值计量且其变动计入当期损益的金融负债
A68: 10 | E68: =IF(D68=0,"",VLOOKUP(D68,$N:$O,2,0)) | H68: =IF(G68=0,"",VLOOKUP(G68,$N:$O,2,0)) | N68: =母公司汇总抵销!N68 -> E4 | O68: =母公司汇总抵销!O68 -> 衍生金融负债
E69: =IF(D69=0,"",VLOOKUP(D69,$N:$O,2,0)) | H69: =IF(G69=0,"",VLOOKUP(G69,$N:$O,2,0)) | N69: =母公司汇总抵销!N69 -> E5 | O69: =母公司汇总抵销!O69 -> 应付票据
E70: =IF(D70=0,"",VLOOKUP(D70,$N:$O,2,0)) | H70: =IF(G70=0,"",VLOOKUP(G70,$N:$O,2,0)) | N70: =母公司汇总抵销!N70 -> E6 | O70: =母公司汇总抵销!O70 -> 应付账款
E71: =IF(D71=0,"",VLOOKUP(D71,$N:$O,2,0)) | H71: =IF(G71=0,"",VLOOKUP(G71,$N:$O,2,0)) | N71: =母公司汇总抵销!N71 -> E7 | O71: =母公司汇总抵销!O71 -> 预收款项
E72: =IF(D72=0,"",VLOOKUP(D72,$N:$O,2,0)) | H72: =IF(G72=0,"",VLOOKUP(G72,$N:$O,2,0)) | N72: =母公司汇总抵销!N72 -> E27 | O72: =母公司汇总抵销!O72 -> 卖出回购金融资产款
E73: =IF(D73=0,"",VLOOKUP(D73,$N:$O,2,0)) | H73: =IF(G73=0,"",VLOOKUP(G73,$N:$O,2,0)) | N73: =母公司汇总抵销!N73 -> E28 | O73: =母公司汇总抵销!O73 -> 应付手续费及佣金
J74: =IF(ABS((SUMIF(E68:E73,"?*",J68:J73)-SUMIF(H68:H73,"?*",J68:J73)))<0.005,"","借贷不等") | N74: =母公司汇总抵销!N74 -> E8 | O74: =母公司汇总抵销!O74 -> 合同负债
A75: 11 | E75: =IF(D75=0,"",VLOOKUP(D75,$N:$O,2,0)) | H75: =IF(G75=0,"",VLOOKUP(G75,$N:$O,2,0)) | N75: =母公司汇总抵销!N75 -> E9 | O75: =母公司汇总抵销!O75 -> 应付职工薪酬
E76: =IF(D76=0,"",VLOOKUP(D76,$N:$O,2,0)) | H76: =IF(G76=0,"",VLOOKUP(G76,$N:$O,2,0)) | N76: =母公司汇总抵销!N76 -> E10 | O76: =母公司汇总抵销!O76 -> 应交税费
E77: =IF(D77=0,"",VLOOKUP(D77,$N:$O,2,0)) | H77: =IF(G77=0,"",VLOOKUP(G77,$N:$O,2,0)) | N77: =母公司汇总抵销!N77 -> E11 | O77: =母公司汇总抵销!O77 -> 其他应付款
E78: =IF(D78=0,"",VLOOKUP(D78,$N:$O,2,0)) | H78: =IF(G78=0,"",VLOOKUP(G78,$N:$O,2,0)) | N78: =母公司汇总抵销!N78 -> 0 | O78: =母公司汇总抵销!O78 -> 应付利息
E79: =IF(D79=0,"",VLOOKUP(D79,$N:$O,2,0)) | H79: =IF(G79=0,"",VLOOKUP(G79,$N:$O,2,0)) | N79: =母公司汇总抵销!N79 -> 0 | O79: =母公司汇总抵销!O79 -> 应付股利
E80: =IF(D80=0,"",VLOOKUP(D80,$N:$O,2,0)) | H80: =IF(G80=0,"",VLOOKUP(G80,$N:$O,2,0)) | N80: =母公司汇总抵销!N80 -> E29 | O80: =母公司汇总抵销!O80 -> 应付分保账款
J81: =IF(ABS((SUMIF(E75:E80,"?*",J75:J80)-SUMIF(H75:H80,"?*",J75:J80)))<0.005,"","借贷不等") | N81: =母公司汇总抵销!N81 -> E30 | O81: =母公司汇总抵销!O81 -> 保险合同准备金
A82: 12 | E82: =IF(D82=0,"",VLOOKUP(D82,$N:$O,2,0)) | H82: =IF(G82=0,"",VLOOKUP(G82,$N:$O,2,0)) | N82: =母公司汇总抵销!N82 -> E31 | O82: =母公司汇总抵销!O82 -> 代理买卖证券款
E83: =IF(D83=0,"",VLOOKUP(D83,$N:$O,2,0)) | H83: =IF(G83=0,"",VLOOKUP(G83,$N:$O,2,0)) | N83: =母公司汇总抵销!N83 -> E32 | O83: =母公司汇总抵销!O83 -> 代理承销证券款
E84: =IF(D84=0,"",VLOOKUP(D84,$N:$O,2,0)) | H84: =IF(G84=0,"",VLOOKUP(G84,$N:$O,2,0)) | N84: =母公司汇总抵销!N84 -> E12 | O84: =母公司汇总抵销!O84 -> 持有待售负债
E85: =IF(D85=0,"",VLOOKUP(D85,$N:$O,2,0)) | H85: =IF(G85=0,"",VLOOKUP(G85,$N:$O,2,0)) | N85: =母公司汇总抵销!N85 -> E13 | O85: =母公司汇总抵销!O85 -> 一年内到期的非流动负债
E86: =IF(D86=0,"",VLOOKUP(D86,$N:$O,2,0)) | H86: =IF(G86=0,"",VLOOKUP(G86,$N:$O,2,0)) | N86: =母公司汇总抵销!N86 -> E14 | O86: =母公司汇总抵销!O86 -> 其他流动负债
E87: =IF(D87=0,"",VLOOKUP(D87,$N:$O,2,0)) | H87: =IF(G87=0,"",VLOOKUP(G87,$N:$O,2,0)) | N87: =母公司汇总抵销!N87 -> 0 | O87: =母公司汇总抵销!O87 -> 流动负债合计
J88: =IF(ABS((SUMIF(E82:E87,"?*",J82:J87)-SUMIF(H82:H87,"?*",J82:J87)))<0.005,"","借贷不等") | N88: =母公司汇总抵销!N88 -> 0 | O88: =母公司汇总抵销!O88 -> 非流动负债:
A89: 13 | E89: =IF(D89=0,"",VLOOKUP(D89,$N:$O,2,0)) | H89: =IF(G89=0,"",VLOOKUP(G89,$N:$O,2,0)) | N89: =母公司汇总抵销!N89 -> E15 | O89: =母公司汇总抵销!O89 -> 长期借款
E90: =IF(D90=0,"",VLOOKUP(D90,$N:$O,2,0)) | H90: =IF(G90=0,"",VLOOKUP(G90,$N:$O,2,0)) | N90: =母公司汇总抵销!N90 -> E16 | O90: =母公司汇总抵销!O90 -> 应付债券
E91: =IF(D91=0,"",VLOOKUP(D91,$N:$O,2,0)) | H91: =IF(G91=0,"",VLOOKUP(G91,$N:$O,2,0)) | N91: =母公司汇总抵销!N91 -> 0 | O91: =母公司汇总抵销!O91 -> 优先股
E92: =IF(D92=0,"",VLOOKUP(D92,$N:$O,2,0)) | H92: =IF(G92=0,"",VLOOKUP(G92,$N:$O,2,0)) | N92: =母公司汇总抵销!N92 -> 0 | O92: =母公司汇总抵销!O92 -> 永续债
E93: =IF(D93=0,"",VLOOKUP(D93,$N:$O,2,0)) | H93: =IF(G93=0,"",VLOOKUP(G93,$N:$O,2,0)) | N93: =母公司汇总抵销!N93 -> E17 | O93: =母公司汇总抵销!O93 -> 租赁负债
E94: =IF(D94=0,"",VLOOKUP(D94,$N:$O,2,0)) | H94: =IF(G94=0,"",VLOOKUP(G94,$N:$O,2,0)) | N94: =母公司汇总抵销!N94 -> E18 | O94: =母公司汇总抵销!O94 -> 长期应付款
J95: =IF(ABS((SUMIF(E89:E94,"?*",J89:J94)-SUMIF(H89:H94,"?*",J89:J94)))<0.005,"","借贷不等") | N95: =母公司汇总抵销!N95 -> E19 | O95: =母公司汇总抵销!O95 -> 长期应付职工薪酬
A96: 14 | E96: =IF(D96=0,"",VLOOKUP(D96,$N:$O,2,0)) | H96: =IF(G96=0,"",VLOOKUP(G96,$N:$O,2,0)) | N96: =母公司汇总抵销!N96 -> E20 | O96: =母公司汇总抵销!O96 -> 预计负债
E97: =IF(D97=0,"",VLOOKUP(D97,$N:$O,2,0)) | H97: =IF(G97=0,"",VLOOKUP(G97,$N:$O,2,0)) | N97: =母公司汇总抵销!N97 -> E21 | O97: =母公司汇总抵销!O97 -> 递延收益
E98: =IF(D98=0,"",VLOOKUP(D98,$N:$O,2,0)) | H98: =IF(G98=0,"",VLOOKUP(G98,$N:$O,2,0)) | N98: =母公司汇总抵销!N98 -> E22 | O98: =母公司汇总抵销!O98 -> 递延所得税负债
E99: =IF(D99=0,"",VLOOKUP(D99,$N:$O,2,0)) | H99: =IF(G99=0,"",VLOOKUP(G99,$N:$O,2,0)) | N99: =母公司汇总抵销!N99 -> E23 | O99: =母公司汇总抵销!O99 -> 其他非流动负债
E100: =IF(D100=0,"",VLOOKUP(D100,$N:$O,2,0)) | H100: =IF(G100=0,"",VLOOKUP(G100,$N:$O,2,0)) | N100: =母公司汇总抵销!N100 -> 0 | O100: =母公司汇总抵销!O100 -> 非流动负债合计
...

Sheet 母公司TB资产
A1: 母公司汇总资产负债表试算平衡
A2: =CONCATENATE("客户名称：",说明!E23) -> 客户名称： | D2: =CONCATENATE("编制：",说明!E36) -> 编制： | F2: =CONCATENATE("复核：",说明!E37) -> 复核： | K2: 索引：
A3: =CONCATENATE("会计时点：",TEXT(说明!E32,"yyyy.mm.dd")) -> 会计时点：2019.12.31 | D3: =CONCATENATE("日期：",TEXT(NOW(),"yyyy.mm.dd")) -> 日期：2019.12.31 | F3: 日期： | K3: 分页：
A4: =IF((ROUND(K59,2))=(ROUND(母公司TB负债!K62,2)),"资 产","报表未调平!") -> 资 产 | B4: 母公司汇总 | C4: 汇总抵销 | E4: 账项调整 | G4: 报表调整 | I4: 调后数 | J4: 剥离调整 | K4: 母公司审定数
C5: 借方 | D5: 贷方 | E5: 借方 | F5: 贷方 | G5: 借方 | H5: 贷方
A6: =报表格式!B5 -> 流动资产：
A7: =报表格式!B6 -> 货币资金 | B7: =母公司BS汇总!B7 -> 0 | C7: =SUMIF(母公司汇总抵销!$E$5:$E$65538,IF(OR(MID(TRIM($A7),2,1)="：",MID(TRIM($A7),2,1)="、"),REPLACEB(TRIM($A7),1,4,""),TRIM($A7)),母公司汇总抵销!$J$5:$J$65538) -> 0 | D7: =SUMIF(母公司汇总抵销!$H$5:$H$65538,IF(OR(MID(TRIM($A7),2,1)="：",MID(TRIM($A7),2,1)="、"),REPLACEB(TRIM($A7),1,4,""),TRIM($A7)),母公司汇总抵销!$J$5:$J$65538) -> 0 | E7: =SUMIF(母公司账项调整!$E$5:$E$65536,IF(OR(MID(TRIM($A7),2,1)="：",MID(TRIM($A7),2,1)="、"),REPLACEB(TRIM($A7),1,4,""),TRIM($A7)),母公司账项调整!$J$5:$J$65536) -> 0 | F7: =SUMIF(母公司账项调整!$H$5:$H$65536,IF(OR(MID(TRIM($A7),2,1)="：",MID(TRIM($A7),2,1)="、"),REPLACEB(TRIM($A7),1,4,""),TRIM($A7)),母公司账项调整!$J$5:$J$65536) -> 0 | G7: =SUMIF(母公司报表调整!$E$5:$E$65536,IF(OR(MID(TRIM($A7),2,1)="：",MID(TRIM($A7),2,1)="、"),REPLACEB(TRIM($A7),1,4,""),TRIM($A7)),母公司报表调整!$J$5:$J$65536) -> 0 | H7: =SUMIF(母公司报表调整!$H$5:$H$65536,IF(OR(MID(TRIM($A7),2,1)="：",MID(TRIM($A7),2,1)="、"),REPLACEB(TRIM($A7),1,4,""),TRIM($A7)),母公司报表调整!$J$5:$J$65536) -> 0 | I7: =B7+E7+G7-F7-H7+C7-D7 -> 0 | K7: =SUM(I7:J7) -> 0
A8: =报表格式!B7 -> 结算备付金 | B8: =母公司BS汇总!B8 -> 0 | C8: =SUMIF(母公司汇总抵销!$E$5:$E$65538,IF(OR(MID(TRIM($A8),2,1)="：",MID(TRIM($A8),2,1)="、"),REPLACEB(TRIM($A8),1,4,""),TRIM($A8)),母公司汇总抵销!$J$5:$J$65538) -> 0 | D8: =SUMIF(母公司汇总抵销!$H$5:$H$65538,IF(OR(MID(TRIM($A8),2,1)="：",MID(TRIM($A8),2,1)="、"),REPLACEB(TRIM($A8),1,4,""),TRIM($A8)),母公司汇总抵销!$J$5:$J$65538) -> 0 | E8: =SUMIF(母公司账项调整!$E$5:$E$65536,IF(OR(MID(TRIM($A8),2,1)="：",MID(TRIM($A8),2,1)="、"),REPLACEB(TRIM($A8),1,4,""),TRIM($A8)),母公司账项调整!$J$5:$J$65536) -> 0 | F8: =SUMIF(母公司账项调整!$H$5:$H$65536,IF(OR(MID(TRIM($A8),2,1)="：",MID(TRIM($A8),2,1)="、"),REPLACEB(TRIM($A8),1,4,""),TRIM($A8)),母公司账项调整!$J$5:$J$65536) -> 0 | G8: =SUMIF(母公司报表调整!$E$5:$E$65536,IF(OR(MID(TRIM($A8),2,1)="：",MID(TRIM($A8),2,1)="、"),REPLACEB(TRIM($A8),1,4,""),TRIM($A8)),母公司报表调整!$J$5:$J$65536) -> 0 | H8: =SUMIF(母公司报表调整!$H$5:$H$65536,IF(OR(MID(TRIM($A8),2,1)="：",MID(TRIM($A8),2,1)="、"),REPLACEB(TRIM($A8),1,4,""),TRIM($A8)),母公司报表调整!$J$5:$J$65536) -> 0 | I8: =B8+E8+G8-F8-H8+C8-D8 -> 0 | K8: =SUM(I8:J8) -> 0
A9: =报表格式!B8 -> 拆出资金 | B9: =母公司BS汇总!B9 -> 0 | C9: =SUMIF(母公司汇总抵销!$E$5:$E$65538,IF(OR(MID(TRIM($A9),2,1)="：",MID(TRIM($A9),2,1)="、"),REPLACEB(TRIM($A9),1,4,""),TRIM($A9)),母公司汇总抵销!$J$5:$J$65538) -> 0 | D9: =SUMIF(母公司汇总抵销!$H$5:$H$65538,IF(OR(MID(TRIM($A9),2,1)="：",MID(TRIM($A9),2,1)="、"),REPLACEB(TRIM($A9),1,4,""),TRIM($A9)),母公司汇总抵销!$J$5:$J$65538) -> 0 | E9: =SUMIF(母公司账项调整!$E$5:$E$65536,IF(OR(MID(TRIM($A9),2,1)="：",MID(TRIM($A9),2,1)="、"),REPLACEB(TRIM($A9),1,4,""),TRIM($A9)),母公司账项调整!$J$5:$J$65536) -> 0 | F9: =SUMIF(母公司账项调整!$H$5:$H$65536,IF(OR(MID(TRIM($A9),2,1)="：",MID(TRIM($A9),2,1)="、"),REPLACEB(TRIM($A9),1,4,""),TRIM($A9)),母公司账项调整!$J$5:$J$65536) -> 0 | G9: =SUMIF(母公司报表调整!$E$5:$E$65536,IF(OR(MID(TRIM($A9),2,1)="：",MID(TRIM($A9),2,1)="、"),REPLACEB(TRIM($A9),1,4,""),TRIM($A9)),母公司报表调整!$J$5:$J$65536) -> 0 | H9: =SUMIF(母公司报表调整!$H$5:$H$65536,IF(OR(MID(TRIM($A9),2,1)="：",MID(TRIM($A9),2,1)="、"),REPLACEB(TRIM($A9),1,4,""),TRIM($A9)),母公司报表调整!$J$5:$J$65536) -> 0 | I9: =B9+E9+G9-F9-H9+C9-D9 -> 0 | K9: =SUM(I9:J9) -> 0
A10: =报表格式!B9 -> 交易性金融资产 | B10: =母公司BS汇总!B10 -> 0 | C10: =SUMIF(母公司汇总抵销!$E$5:$E$65538,IF(OR(MID(TRIM($A10),2,1)="：",MID(TRIM($A10),2,1)="、"),REPLACEB(TRIM($A10),1,4,""),TRIM($A10)),母公司汇总抵销!$J$5:$J$65538) -> 0 | D10: =SUMIF(母公司汇总抵销!$H$5:$H$65538,IF(OR(MID(TRIM($A10),2,1)="：",MID(TRIM($A10),2,1)="、"),REPLACEB(TRIM($A10),1,4,""),TRIM($A10)),母公司汇总抵销!$J$5:$J$65538) -> 0 | E10: =SUMIF(母公司账项调整!$E$5:$E$65536,IF(OR(MID(TRIM($A10),2,1)="：",MID(TRIM($A10),2,1)="、"),REPLACEB(TRIM($A10),1,4,""),TRIM($A10)),母公司账项调整!$J$5:$J$65536) -> 0 | F10: =SUMIF(母公司账项调整!$H$5:$H$65536,IF(OR(MID(TRIM($A10),2,1)="：",MID(TRIM($A10),2,1)="、"),REPLACEB(TRIM($A10),1,4,""),TRIM($A10)),母公司账项调整!$J$5:$J$65536) -> 0 | G10: =SUMIF(母公司报表调整!$E$5:$E$65536,IF(OR(MID(TRIM($A10),2,1)="：",MID(TRIM($A10),2,1)="、"),REPLACEB(TRIM($A10),1,4,""),TRIM($A10)),母公司报表调整!$J$5:$J$65536) -> 0 | H10: =SUMIF(母公司报表调整!$H$5:$H$65536,IF(OR(MID(TRIM($A10),2,1)="：",MID(TRIM($A10),2,1)="、"),REPLACEB(TRIM($A10),1,4,""),TRIM($A10)),母公司报表调整!$J$5:$J$65536) -> 0 | I10: =B10+E10+G10-F10-H10+C10-D10 -> 0 | K10: =SUM(I10:J10) -> 0
A11: =报表格式!B10 -> 以公允价值计量且其变动计入当期损益的金融资产 | B11: =母公司BS汇总!B11 -> 0 | C11: =SUMIF(母公司汇总抵销!$E$5:$E$65538,IF(OR(MID(TRIM($A11),2,1)="：",MID(TRIM($A11),2,1)="、"),REPLACEB(TRIM($A11),1,4,""),TRIM($A11)),母公司汇总抵销!$J$5:$J$65538) -> 0 | D11: =SUMIF(母公司汇总抵销!$H$5:$H$65538,IF(OR(MID(TRIM($A11),2,1)="：",MID(TRIM($A11),2,1)="、"),REPLACEB(TRIM($A11),1,4,""),TRIM($A11)),母公司汇总抵销!$J$5:$J$65538) -> 0 | E11: =SUMIF(母公司账项调整!$E$5:$E$65536,IF(OR(MID(TRIM($A11),2,1)="：",MID(TRIM($A11),2,1)="、"),REPLACEB(TRIM($A11),1,4,""),TRIM($A11)),母公司账项调整!$J$5:$J$65536) -> 0 | F11: =SUMIF(母公司账项调整!$H$5:$H$65536,IF(OR(MID(TRIM($A11),2,1)="：",MID(TRIM($A11),2,1)="、"),REPLACEB(TRIM($A11),1,4,""),TRIM($A11)),母公司账项调整!$J$5:$J$65536) -> 0 | G11: =SUMIF(母公司报表调整!$E$5:$E$65536,IF(OR(MID(TRIM($A11),2,1)="：",MID(TRIM($A11),2,1)="、"),REPLACEB(TRIM($A11),1,4,""),TRIM($A11)),母公司报表调整!$J$5:$J$65536) -> 0 | H11: =SUMIF(母公司报表调整!$H$5:$H$65536,IF(OR(MID(TRIM($A11),2,1)="：",MID(TRIM($A11),2,1)="、"),REPLACEB(TRIM($A11),1,4,""),TRIM($A11)),母公司报表调整!$J$5:$J$65536) -> 0 | I11: =B11+E11+G11-F11-H11+C11-D11 -> 0 | K11: =SUM(I11:J11) -> 0
A12: =报表格式!B11 -> 衍生金融资产 | B12: =母公司BS汇总!B12 -> 0 | C12: =SUMIF(母公司汇总抵销!$E$5:$E$65538,IF(OR(MID(TRIM($A12),2,1)="：",MID(TRIM($A12),2,1)="、"),REPLACEB(TRIM($A12),1,4,""),TRIM($A12)),母公司汇总抵销!$J$5:$J$65538) -> 0 | D12: =SUMIF(母公司汇总抵销!$H$5:$H$65538,IF(OR(MID(TRIM($A12),2,1)="：",MID(TRIM($A12),2,1)="、"),REPLACEB(TRIM($A12),1,4,""),TRIM($A12)),母公司汇总抵销!$J$5:$J$65538) -> 0 | E12: =SUMIF(母公司账项调整!$E$5:$E$65536,IF(OR(MID(TRIM($A12),2,1)="：",MID(TRIM($A12),2,1)="、"),REPLACEB(TRIM($A12),1,4,""),TRIM($A12)),母公司账项调整!$J$5:$J$65536) -> 0 | F12: =SUMIF(母公司账项调整!$H$5:$H$65536,IF(OR(MID(TRIM($A12),2,1)="：",MID(TRIM($A12),2,1)="、"),REPLACEB(TRIM($A12),1,4,""),TRIM($A12)),母公司账项调整!$J$5:$J$65536) -> 0 | G12: =SUMIF(母公司报表调整!$E$5:$E$65536,IF(OR(MID(TRIM($A12),2,1)="：",MID(TRIM($A12),2,1)="、"),REPLACEB(TRIM($A12),1,4,""),TRIM($A12)),母公司报表调整!$J$5:$J$65536) -> 0 | H12: =SUMIF(母公司报表调整!$H$5:$H$65536,IF(OR(MID(TRIM($A12),2,1)="：",MID(TRIM($A12),2,1)="、"),REPLACEB(TRIM($A12),1,4,""),TRIM($A12)),母公司报表调整!$J$5:$J$65536) -> 0 | I12: =B12+E12+G12-F12-H12+C12-D12 -> 0 | K12: =SUM(I12:J12) -> 0
A13: =报表格式!B12 -> 应收票据 | B13: =母公司BS汇总!B13 -> 0 | C13: =SUMIF(母公司汇总抵销!$E$5:$E$65538,IF(OR(MID(TRIM($A13),2,1)="：",MID(TRIM($A13),2,1)="、"),REPLACEB(TRIM($A13),1,4,""),TRIM($A13)),母公司汇总抵销!$J$5:$J$65538) -> 0 | D13: =SUMIF(母公司汇总抵销!$H$5:$H$65538,IF(OR(MID(TRIM($A13),2,1)="：",MID(TRIM($A13),2,1)="、"),REPLACEB(TRIM($A13),1,4,""),TRIM($A13)),母公司汇总抵销!$J$5:$J$65538) -> 0 | E13: =SUMIF(母公司账项调整!$E$5:$E$65536,IF(OR(MID(TRIM($A13),2,1)="：",MID(TRIM($A13),2,1)="、"),REPLACEB(TRIM($A13),1,4,""),TRIM($A13)),母公司账项调整!$J$5:$J$65536) -> 0 | F13: =SUMIF(母公司账项调整!$H$5:$H$65536,IF(OR(MID(TRIM($A13),2,1)="：",MID(TRIM($A13),2,1)="、"),REPLACEB(TRIM($A13),1,4,""),TRIM($A13)),母公司账项调整!$J$5:$J$65536) -> 0 | G13: =SUMIF(母公司报表调整!$E$5:$E$65536,IF(OR(MID(TRIM($A13),2,1)="：",MID(TRIM($A13),2,1)="、"),REPLACEB(TRIM($A13),1,4,""),TRIM($A13)),母公司报表调整!$J$5:$J$65536) -> 0 | H13: =SUMIF(母公司报表调整!$H$5:$H$65536,IF(OR(MID(TRIM($A13),2,1)="：",MID(TRIM($A13),2,1)="、"),REPLACEB(TRIM($A13),1,4,""),TRIM($A13)),母公司报表调整!$J$5:$J$65536) -> 0 | I13: =B13+E13+G13-F13-H13+C13-D13 -> 0 | K13: =SUM(I13:J13) -> 0
A14: =报表格式!B13 -> 应收账款 | B14: =母公司BS汇总!B14 -> 0 | C14: =SUMIF(母公司汇总抵销!$E$5:$E$65538,IF(OR(MID(TRIM($A14),2,1)="：",MID(TRIM($A14),2,1)="、"),REPLACEB(TRIM($A14),1,4,""),TRIM($A14)),母公司汇总抵销!$J$5:$J$65538) -> 0 | D14: =SUMIF(母公司汇总抵销!$H$5:$H$65538,IF(OR(MID(TRIM($A14),2,1)="：",MID(TRIM($A14),2,1)="、"),REPLACEB(TRIM($A14),1,4,""),TRIM($A14)),母公司汇总抵销!$J$5:$J$65538) -> 0 | E14: =SUMIF(母公司账项调整!$E$5:$E$65536,IF(OR(MID(TRIM($A14),2,1)="：",MID(TRIM($A14),2,1)="、"),REPLACEB(TRIM($A14),1,4,""),TRIM($A14)),母公司账项调整!$J$5:$J$65536) -> 0 | F14: =SUMIF(母公司账项调整!$H$5:$H$65536,IF(OR(MID(TRIM($A14),2,1)="：",MID(TRIM($A14),2,1)="、"),REPLACEB(TRIM($A14),1,4,""),TRIM($A14)),母公司账项调整!$J$5:$J$65536) -> 0 | G14: =SUMIF(母公司报表调整!$E$5:$E$65536,IF(OR(MID(TRIM($A14),2,1)="：",MID(TRIM($A14),2,1)="、"),REPLACEB(TRIM($A14),1,4,""),TRIM($A14)),母公司报表调整!$J$5:$J$65536) -> 0 | H14: =SUMIF(母公司报表调整!$H$5:$H$65536,IF(OR(MID(TRIM($A14),2,1)="：",MID(TRIM($A14),2,1)="、"),REPLACEB(TRIM($A14),1,4,""),TRIM($A14)),母公司报表调整!$J$5:$J$65536) -> 0 | I14: =B14+E14+G14-F14-H14+C14-D14 -> 0 | K14: =SUM(I14:J14) -> 0
A15: =报表格式!B14 -> 应收款项融资 | B15: =母公司BS汇总!B15 -> 0 | C15: =SUMIF(母公司汇总抵销!$E$5:$E$65538,IF(OR(MID(TRIM($A15),2,1)="：",MID(TRIM($A15),2,1)="、"),REPLACEB(TRIM($A15),1,4,""),TRIM($A15)),母公司汇总抵销!$J$5:$J$65538) -> 0 | D15: =SUMIF(母公司汇总抵销!$H$5:$H$65538,IF(OR(MID(TRIM($A15),2,1)="：",MID(TRIM($A15),2,1)="、"),REPLACEB(TRIM($A15),1,4,""),TRIM($A15)),母公司汇总抵销!$J$5:$J$65538) -> 0 | E15: =SUMIF(母公司账项调整!$E$5:$E$65536,IF(OR(MID(TRIM($A15),2,1)="：",MID(TRIM($A15),2,1)="、"),REPLACEB(TRIM($A15),1,4,""),TRIM($A15)),母公司账项调整!$J$5:$J$65536) -> 0 | F15: =SUMIF(母公司账项调整!$H$5:$H$65536,IF(OR(MID(TRIM($A15),2,1)="：",MID(TRIM($A15),2,1)="、"),REPLACEB(TRIM($A15),1,4,""),TRIM($A15)),母公司账项调整!$J$5:$J$65536) -> 0 | G15: =SUMIF(母公司报表调整!$E$5:$E$65536,IF(OR(MID(TRIM($A15),2,1)="：",MID(TRIM($A15),2,1)="、"),REPLACEB(TRIM($A15),1,4,""),TRIM($A15)),母公司报表调整!$J$5:$J$65536) -> 0 | H15: =SUMIF(母公司报表调整!$H$5:$H$65536,IF(OR(MID(TRIM($A15),2,1)="：",MID(TRIM($A15),2,1)="、"),REPLACEB(TRIM($A15),1,4,""),TRIM($A15)),母公司报表调整!$J$5:$J$65536) -> 0 | I15: =B15+E15+G15-F15-H15+C15-D15 -> 0 | K15: =SUM(I15:J15) -> 0
A16: =报表格式!B15 -> 预付款项 | B16: =母公司BS汇总!B16 -> 0 | C16: =SUMIF(母公司汇总抵销!$E$5:$E$65538,IF(OR(MID(TRIM($A16),2,1)="：",MID(TRIM($A16),2,1)="、"),REPLACEB(TRIM($A16),1,4,""),TRIM($A16)),母公司汇总抵销!$J$5:$J$65538) -> 0 | D16: =SUMIF(母公司汇总抵销!$H$5:$H$65538,IF(OR(MID(TRIM($A16),2,1)="：",MID(TRIM($A16),2,1)="、"),REPLACEB(TRIM($A16),1,4,""),TRIM($A16)),母公司汇总抵销!$J$5:$J$65538) -> 0 | E16: =SUMIF(母公司账项调整!$E$5:$E$65536,IF(OR(MID(TRIM($A16),2,1)="：",MID(TRIM($A16),2,1)="、"),REPLACEB(TRIM($A16),1,4,""),TRIM($A16)),母公司账项调整!$J$5:$J$65536) -> 0 | F16: =SUMIF(母公司账项调整!$H$5:$H$65536,IF(OR(MID(TRIM($A16),2,1)="：",MID(TRIM($A16),2,1)="、"),REPLACEB(TRIM($A16),1,4,""),TRIM($A16)),母公司账项调整!$J$5:$J$65536) -> 0 | G16: =SUMIF(母公司报表调整!$E$5:$E$65536,IF(OR(MID(TRIM($A16),2,1)="：",MID(TRIM($A16),2,1)="、"),REPLACEB(TRIM($A16),1,4,""),TRIM($A16)),母公司报表调整!$J$5:$J$65536) -> 0 | H16: =SUMIF(母公司报表调整!$H$5:$H$65536,IF(OR(MID(TRIM($A16),2,1)="：",MID(TRIM($A16),2,1)="、"),REPLACEB(TRIM($A16),1,4,""),TRIM($A16)),母公司报表调整!$J$5:$J$65536) -> 0 | I16: =B16+E16+G16-F16-H16+C16-D16 -> 0 | K16: =SUM(I16:J16) -> 0
A17: =报表格式!B16 -> 应收保费 | B17: =母公司BS汇总!B17 -> 0 | C17: =SUMIF(母公司汇总抵销!$E$5:$E$65538,IF(OR(MID(TRIM($A17),2,1)="：",MID(TRIM($A17),2,1)="、"),REPLACEB(TRIM($A17),1,4,""),TRIM($A17)),母公司汇总抵销!$J$5:$J$65538) -> 0 | D17: =SUMIF(母公司汇总抵销!$H$5:$H$65538,IF(OR(MID(TRIM($A17),2,1)="：",MID(TRIM($A17),2,1)="、"),REPLACEB(TRIM($A17),1,4,""),TRIM($A17)),母公司汇总抵销!$J$5:$J$65538) -> 0 | E17: =SUMIF(母公司账项调整!$E$5:$E$65536,IF(OR(MID(TRIM($A17),2,1)="：",MID(TRIM($A17),2,1)="、"),REPLACEB(TRIM($A17),1,4,""),TRIM($A17)),母公司账项调整!$J$5:$J$65536) -> 0 | F17: =SUMIF(母公司账项调整!$H$5:$H$65536,IF(OR(MID(TRIM($A17),2,1)="：",MID(TRIM($A17),2,1)="、"),REPLACEB(TRIM($A17),1,4,""),TRIM($A17)),母公司账项调整!$J$5:$J$65536) -> 0 | G17: =SUMIF(母公司报表调整!$E$5:$E$65536,IF(OR(MID(TRIM($A17),2,1)="：",MID(TRIM($A17),2,1)="、"),REPLACEB(TRIM($A17),1,4,""),TRIM($A17)),母公司报表调整!$J$5:$J$65536) -> 0 | H17: =SUMIF(母公司报表调整!$H$5:$H$65536,IF(OR(MID(TRIM($A17),2,1)="：",MID(TRIM($A17),2,1)="、"),REPLACEB(TRIM($A17),1,4,""),TRIM($A17)),母公司报表调整!$J$5:$J$65536) -> 0 | I17: =B17+E17+G17-F17-H17+C17-D17 -> 0 | K17: =SUM(I17:J17) -> 0
A18: =报表格式!B17 -> 应收分保账款 | B18: =母公司BS汇总!B18 -> 0 | C18: =SUMIF(母公司汇总抵销!$E$5:$E$65538,IF(OR(MID(TRIM($A18),2,1)="：",MID(TRIM($A18),2,1)="、"),REPLACEB(TRIM($A18),1,4,""),TRIM($A18)),母公司汇总抵销!$J$5:$J$65538) -> 0 | D18: =SUMIF(母公司汇总抵销!$H$5:$H$65538,IF(OR(MID(TRIM($A18),2,1)="：",MID(TRIM($A18),2,1)="、"),REPLACEB(TRIM($A18),1,4,""),TRIM($A18)),母公司汇总抵销!$J$5:$J$65538) -> 0 | E18: =SUMIF(母公司账项调整!$E$5:$E$65536,IF(OR(MID(TRIM($A18),2,1)="：",MID(TRIM($A18),2,1)="、"),REPLACEB(TRIM($A18),1,4,""),TRIM($A18)),母公司账项调整!$J$5:$J$65536) -> 0 | F18: =SUMIF(母公司账项调整!$H$5:$H$65536,IF(OR(MID(TRIM($A18),2,1)="：",MID(TRIM($A18),2,1)="、"),REPLACEB(TRIM($A18),1,4,""),TRIM($A18)),母公司账项调整!$J$5:$J$65536) -> 0 | G18: =SUMIF(母公司报表调整!$E$5:$E$65536,IF(OR(MID(TRIM($A18),2,1)="：",MID(TRIM($A18),2,1)="、"),REPLACEB(TRIM($A18),1,4,""),TRIM($A18)),母公司报表调整!$J$5:$J$65536) -> 0 | H18: =SUMIF(母公司报表调整!$H$5:$H$65536,IF(OR(MID(TRIM($A18),2,1)="：",MID(TRIM($A18),2,1)="、"),REPLACEB(TRIM($A18),1,4,""),TRIM($A18)),母公司报表调整!$J$5:$J$65536) -> 0 | I18: =B18+E18+G18-F18-H18+C18-D18 -> 0 | K18: =SUM(I18:J18) -> 0
... A20: =报表格式!B19 -> 其他应收款 | B20: =母公司BS汇总!B20 -> 0 | C20: =SUMIF(母公司汇总抵销!$E$5:$E$65538,IF(OR(MID(TRIM($A20),2,1)="：",MID(TRIM($A20),2,1)="、"),REPLACEB(TRIM($A20),1,4,""),TRIM($A20)),母公司汇总抵销!$J$5:$J$65538) -> 0 | D20: =SUMIF(母公司汇总抵销!$H$5:$H$65538,IF(OR(MID(TRIM($A20),2,1)="：",MID(TRIM($A20),2,1)="、"),REPLACEB(TRIM($A20),1,4,""),TRIM($A20)),母公司汇总抵销!$J$5:$J$65538) -> 0 | E20: =SUMIF(母公司账项调整!$E$5:$E$65536,IF(OR(MID(TRIM($A20),2,1)="：",MID(TRIM($A20),2,1)="、"),REPLACEB(TRIM($A20),1,4,""),TRIM($A20)),母公司账项调整!$J$5:$J$65536) -> 0 | F20: =SUMIF(母公司账项调整!$H$5:$H$65536,IF(OR(MID(TRIM($A20),2,1)="：",MID(TRIM($A20),2,1)="、"),REPLACEB(TRIM($A20),1,4,""),TRIM($A20)),母公司账项调整!$J$5:$J$65536) -> 0 | G20: =SUMIF(母公司报表调整!$E$5:$E$65536,IF(OR(MID(TRIM($A20),2,1)="：",MID(TRIM($A20),2,1)="、"),REPLACEB(TRIM($A20),1,4,""),TRIM($A20)),母公司报表调整!$J$5:$J$65536) -> 0 | H20: =SUMIF(母公司报表调整!$H$5:$H$65536,IF(OR(MID(TRIM($A20),2,1)="：",MID(TRIM($A20),2,1)="、"),REPLACEB(TRIM($A20),1,4,""),TRIM($A20)),母公司报表调整!$J$5:$J$65536) -> 0 | I20: =B20+E20+G20-F20-H20+C20-D20 -> 0 | K20: =SUM(I20:J20) -> 0
A21: =报表格式!B20 -> 其中：应收利息 | B21: =母公司BS汇总!B21 -> 0 | C21: =SUMIF(母公司汇总抵销!$F$5:$F$65538,IF(OR(MID(TRIM($A21),3,1)="：",MID(TRIM($A21),2,1)="、"),REPLACEB(TRIM($A21),1,6,""),TRIM($A21)),母公司汇总抵销!$J$5:$J$65538) -> 0 | D21: =SUMIF(母公司汇总抵销!$I$5:$I$65538,IF(OR(MID(TRIM($A21),3,1)="：",MID(TRIM($A21),2,1)="、"),REPLACEB(TRIM($A21),1,6,""),TRIM($A21)),母公司汇总抵销!$J$5:$J$65538) -> 0 | E21: =SUMIF(母公司账项调整!$F$5:$F$65536,IF(OR(MID(TRIM($A21),3,1)="：",MID(TRIM($A21),2,1)="、"),REPLACEB(TRIM($A21),1,6,""),TRIM($A21)),母公司账项调整!$J$5:$J$65536) -> 0 | F21: =SUMIF(母公司账项调整!$I$5:$I$65536,IF(OR(MID(TRIM($A21),3,1)="：",MID(TRIM($A21),2,1)="、"),REPLACEB(TRIM($A21),1,6,""),TRIM($A21)),母公司账项调整!$J$5:$J$65536) -> 0 | G21: =SUMIF(母公司报表调整!$F$5:$F$65536,IF(OR(MID(TRIM($A21),3,1)="：",MID(TRIM($A21),2,1)="、"),REPLACEB(TRIM($A21),1,6,""),TRIM($A21)),母公司报表调整!$J$5:$J$65536) -> 0 | H21: =SUMIF(母公司报表调整!$I$5:$I$65536,IF(OR(MID(TRIM($A21),3,1)="：",MID(TRIM($A21),2,1)="、"),REPLACEB(TRIM($A21),1,6,""),TRIM($A21)),母公司报表调整!$J$5:$J$65536) -> 0 | I21: =B21+E21+G21-F21-H21+C21-D21 -> 0 | K21: =SUM(I21:J21) -> 0
A22: =报表格式!B21 -> 应收股利 | B22: =母公司BS汇总!B22 -> 0 | C22: =SUMIF(母公司汇总抵销!$F$5:$F$65538,IF(OR(MID(TRIM($A22),2,1)="：",MID(TRIM($A22),2,1)="、"),REPLACEB(TRIM($A22),1,4,""),TRIM($A22)),母公司汇总抵销!$J$5:$J$65538) -> 0 | D22: =SUMIF(母公司汇总抵销!$I$5:$I$65538,IF(OR(MID(TRIM($A22),2,1)="：",MID(TRIM($A22),2,1)="、"),REPLACEB(TRIM($A22),1,4,""),TRIM($A22)),母公司汇总抵销!$J$5:$J$65538) -> 0 | E22: =SUMIF(母公司账项调整!$F$5:$F$65536,IF(OR(MID(TRIM($A22),2,1)="：",MID(TRIM($A22),2,1)="、"),REPLACEB(TRIM($A22),1,4,""),TRIM($A22)),母公司账项调整!$J$5:$J$65536) -> 0 | F22: =SUMIF(母公司账项调整!$I$5:$I$65536,IF(OR(MID(TRIM($A22),2,1)="：",MID(TRIM($A22),2,1)="、"),REPLACEB(TRIM($A22),1,4,""),TRIM($A22)),母公司账项调整!$J$5:$J$65536) -> 0 | G22: =SUMIF(母公司报表调整!$F$5:$F$65536,IF(OR(MID(TRIM($A22),2,1)="：",MID(TRIM($A22),2,1)="、"),REPLACEB(TRIM($A22),1,4,""),TRIM($A22)),母公司报表调整!$J$5:$J$65536) -> 0 | H22: =SUMIF(母公司报表调整!$I$5:$I$65536,IF(OR(MID(TRIM($A22),2,1)="：",MID(TRIM($A22),2,1)="、"),REPLACEB(TRIM($A22),1,4,""),TRIM($A22)),母公司报表调整!$J$5:$J$65536) -> 0 | I22: =B22+E22+G22-F22-H22+C22-D22 -> 0 | K22: =SUM(I22:J22) -> 0
A23: =报表格式!B22 -> 买入返售金融资产 | B23: =母公司BS汇总!B23 -> 0 | C23: =SUMIF(母公司汇总抵销!$E$5:$E$65538,IF(OR(MID(TRIM($A23),2,1)="：",MID(TRIM($A23),2,1)="、"),REPLACEB(TRIM($A23),1,4,""),TRIM($A23)),母公司汇总抵销!$J$5:$J$65538) -> 0 | D23: =SUMIF(母公司汇总抵销!$H$5:$H$65538,IF(OR(MID(TRIM($A23),2,1)="：",MID(TRIM($A23),2,1)="、"),REPLACEB(TRIM($A23),1,4,""),TRIM($A23)),母公司汇总抵销!$J$5:$J$65538) -> 0 | E23: =SUMIF(母公司账项调整!$E$5:$E$65536,IF(OR(MID(TRIM($A23),2,1)="：",MID(TRIM($A23),2,1)="、"),REPLACEB(TRIM($A23),1,4,""),TRIM($A23)),母公司账项调整!$J$5:$J$65536) -> 0 | F23: =SUMIF(母公司账项调整!$H$5:$H$65536,IF(OR(MID(TRIM($A23),2,1)="：",MID(TRIM($A23),2,1)="、"),REPLACEB(TRIM($A23),1,4,""),TRIM($A23)),母公司账项调整!$J$5:$J$65536) -> 0 | G23: =SUMIF(母公司报表调整!$E$5:$E$65536,IF(OR(MID(TRIM($A23),2,1)="：",MID(TRIM($A23),2,1)="、"),REPLACEB(TRIM($A23),1,4,""),TRIM($A23)),母公司报表调整!$J$5:$J$65536) -> 0 | H23: =SUMIF(母公司报表调整!$H$5:$H$65536,IF(OR(MID(TRIM($A23),2,1)="：",MID(TRIM($A23),2,1)="、"),REPLACEB(TRIM($A23),1,4,""),TRIM($A23)),母公司报表调整!$J$5:$J$65536) -> 0 | I23: =B23+E23+G23-F23-H23+C23-D23 -> 0 | K23: =SUM(I23:J23) -> 0
A24: =报表格式!B23 -> 存货 | B24: =母公司BS汇总!B24 -> 0 | C24: =SUMIF(母公司汇总抵销!$E$5:$E$65538,IF(OR(MID(TRIM($A24),2,1)="：",MID(TRIM($A24),2,1)="、"),REPLACEB(TRIM($A24),1,4,""),TRIM($A24)),母公司汇总抵销!$J$5:$J$65538) -> 0 | D24: =SUMIF(母公司汇总抵销!$H$5:$H$65538,IF(OR(MID(TRIM($A24),2,1)="：",MID(TRIM($A24),2,1)="、"),REPLACEB(TRIM($A24),1,4,""),TRIM($A24)),母公司汇总抵销!$J$5:$J$65538) -> 0 | E24: =SUMIF(母公司账项调整!$E$5:$E$65536,IF(OR(MID(TRIM($A24),2,1)="：",MID(TRIM($A24),2,1)="、"),REPLACEB(TRIM($A24),1,4,""),TRIM($A24)),母公司账项调整!$J$5:$J$65536) -> 0 | F24: =SUMIF(母公司账项调整!$H$5:$H$65536,IF(OR(MID(TRIM($A24),2,1)="：",MID(TRIM($A24),2,1)="、"),REPLACEB(TRIM($A24),1,4,""),TRIM($A24)),母公司账项调整!$J$5:$J$65536) -> 0 | G24: =SUMIF(母公司报表调整!$E$5:$E$65536,IF(OR(MID(TRIM($A24),2,1)="：",MID(TRIM($A24),2,1)="、"),REPLACEB(TRIM($A24),1,4,""),TRIM($A24)),母公司报表调整!$J$5:$J$65536) -> 0 | H24: =SUMIF(母公司报表调整!$H$5:$H$65536,IF(OR(MID(TRIM($A24),2,1)="：",MID(TRIM($A24),2,1)="、"),REPLACEB(TRIM($A24),1,4,""),TRIM($A24)),母公司报表调整!$J$5:$J$65536) -> 0 | I24: =B24+E24+G24-F24-H24+C24-D24 -> 0 | K24: =SUM(I24:J24) -> 0
A25: =报表格式!B24 -> 合同资产 | B25: =母公司BS汇总!B25 -> 0 | C25: =SUMIF(母公司汇总抵销!$E$5:$E$65538,IF(OR(MID(TRIM($A25),2,1)="：",MID(TRIM($A25),2,1)="、"),REPLACEB(TRIM($A25),1,4,""),TRIM($A25)),母公司汇总抵销!$J$5:$J$65538) -> 0 | D25: =SUMIF(母公司汇总抵销!$H$5:$H$65538,IF(OR(MID(TRIM($A25),2,1)="：",MID(TRIM($A25),2,1)="、"),REPLACEB(TRIM($A25),1,4,""),TRIM($A25)),母公司汇总抵销!$J$5:$J$65538) -> 0 | E25: =SUMIF(母公司账项调整!$E$5:$E$65536,IF(OR(MID(TRIM($A25),2,1)="：",MID(TRIM($A25),2,1)="、"),REPLACEB(TRIM($A25),1,4,""),TRIM($A25)),母公司账项调整!$J$5:$J$65536) -> 0 | F25: =SUMIF(母公司账项调整!$H$5:$H$65536,IF(OR(MID(TRIM($A25),2,1)="：",MID(TRIM($A25),2,1)="、"),REPLACEB(TRIM($A25),1,4,""),TRIM($A25)),母公司账项调整!$J$5:$J$65536) -> 0 | G25: =SUMIF(母公司报表调整!$E$5:$E$65536,IF(OR(MID(TRIM($A25),2,1)="：",MID(TRIM($A25),2,1)="、"),REPLACEB(TRIM($A25),1,4,""),TRIM($A25)),母公司报表调整!$J$5:$J$65536) -> 0 | H25: =SUMIF(母公司报表调整!$H$5:$H$65536,IF(OR(MID(TRIM($A25),2,1)="：",MID(TRIM($A25),2,1)="、"),REPLACEB(TRIM($A25),1,4,""),TRIM($A25)),母公司报表调整!$J$5:$J$65536) -> 0 | I25: =B25+E25+G25-F25-H25+C25-D25 -> 0 | K25: =SUM(I25:J25) -> 0
A26: =报表格式!B25 -> 持有待售资产 | B26: =母公司BS汇总!B26 -> 0 | C26: =SUMIF(母公司汇总抵销!$E$5:$E$65538,IF(OR(MID(TRIM($A26),2,1)="：",MID(TRIM($A26),2,1)="、"),REPLACEB(TRIM($A26),1,4,""),TRIM($A26)),母公司汇总抵销!$J$5:$J$65538) -> 0 | D26: =SUMIF(母公司汇总抵销!$H$5:$H$65538,IF(OR(MID(TRIM($A26),2,1)="：",MID(TRIM($A26),2,1)="、"),REPLACEB(TRIM($A26),1,4,""),TRIM($A26)),母公司汇总抵销!$J$5:$J$65538) -> 0 | E26: =SUMIF(母公司账项调整!$E$5:$E$65536,IF(OR(MID(TRIM($A26),2,1)="：",MID(TRIM($A26),2,1)="、"),REPLACEB(TRIM($A26),1,4,""),TRIM($A26)),母公司账项调整!$J$5:$J$65536) -> 0 | F26: =SUMIF(母公司账项调整!$H$5:$H$65536,IF(OR(MID(TRIM($A26),2,1)="：",MID(TRIM($A26),2,1)="、"),REPLACEB(TRIM($A26),1,4,""),TRIM($A26)),母公司账项调整!$J$5:$J$65536) -> 0 | G26: =SUMIF(母公司报表调整!$E$5:$E$65536,IF(OR(MID(TRIM($A26),2,1)="：",MID(TRIM($A26),2,1)="、"),REPLACEB(TRIM($A26),1,4,""),TRIM($A26)),母公司报表调整!$J$5:$J$65536) -> 0 | H26: =SUMIF(母公司报表调整!$H$5:$H$65536,IF(OR(MID(TRIM($A26),2,1)="：",MID(TRIM($A26),2,1)="、"),REPLACEB(TRIM($A26),1,4,""),TRIM($A26)),母公司报表调整!$J$5:$J$65536) -> 0 | I26: =B26+E26+G26-F26-H26+C26-D26 -> 0 | K26: =SUM(I26:J26) -> 0
A27: =报表格式!B26 -> 一年内到期的非流动资产 | B27: =母公司BS汇总!B27 -> 0 | C27: =SUMIF(母公司汇总抵销!$E$5:$E$65538,IF(OR(MID(TRIM($A27),2,1)="：",MID(TRIM($A27),2,1)="、"),REPLACEB(TRIM($A27),1,4,""),TRIM($A27)),母公司汇总抵销!$J$5:$J$65538) -> 0 | D27: =SUMIF(母公司汇总抵销!$H$5:$H$65538,IF(OR(MID(TRIM($A27),2,1)="：",MID(TRIM($A27),2,1)="、"),REPLACEB(TRIM($A27),1,4,""),TRIM($A27)),母公司汇总抵销!$J$5:$J$65538) -> 0 | E27: =SUMIF(母公司账项调整!$E$5:$E$65536,IF(OR(MID(TRIM($A27),2,1)="：",MID(TRIM($A27),2,1)="、"),REPLACEB(TRIM($A27),1,4,""),TRIM($A27)),母公司账项调整!$J$5:$J$65536) -> 0 | F27: =SUMIF(母公司账项调整!$H$5:$H$65536,IF(OR(MID(TRIM($A27),2,1)="：",MID(TRIM($A27),2,1)="、"),REPLACEB(TRIM($A27),1,4,""),TRIM($A27)),母公司账项调整!$J$5:$J$65536) -> 0 | G27: =SUMIF(母公司报表调整!$E$5:$E$65536,IF(OR(MID(TRIM($A27),2,1)="：",MID(TRIM($A27),2,1)="、"),REPLACEB(TRIM($A27),1,4,""),TRIM($A27)),母公司报表调整!$J$5:$J$65536) -> 0 | H27: =SUMIF(母公司报表调整!$H$5:$H$65536,IF(OR(MID(TRIM($A27),2,1)="：",MID(TRIM($A27),2,1)="、"),REPLACEB(TRIM($A27),1,4,""),TRIM($A27)),母公司报表调整!$J$5:$J$65536) -> 0 | I27: =B27+E27+G27-F27-H27+C27-D27 -> 0 | K27: =SUM(I27:J27) -> 0
A28: =报表格式!B27 -> 其他流动资产 | B28: =母公司BS汇总!B28 -> 0 | C28: =SUMIF(母公司汇总抵销!$E$5:$E$65538,IF(OR(MID(TRIM($A28),2,1)="：",MID(TRIM($A28),2,1)="、"),REPLACEB(TRIM($A28),1,4,""),TRIM($A28)),母公司汇总抵销!$J$5:$J$65538) -> 0 | D28: =SUMIF(母公司汇总抵销!$H$5:$H$65538,IF(OR(MID(TRIM($A28),2,1)="：",MID(TRIM($A28),2,1)="、"),REPLACEB(TRIM($A28),1,4,""),TRIM($A28)),母公司汇总抵销!$J$5:$J$65538) -> 0 | E28: =SUMIF(母公司账项调整!$E$5:$E$65536,IF(OR(MID(TRIM($A28),2,1)="：",MID(TRIM($A28),2,1)="、"),REPLACEB(TRIM($A28),1,4,""),TRIM($A28)),母公司账项调整!$J$5:$J$65536) -> 0 | F28: =SUMIF(母公司账项调整!$H$5:$H$65536,IF(OR(MID(TRIM($A28),2,1)="：",MID(TRIM($A28),2,1)="、"),REPLACEB(TRIM($A28),1,4,""),TRIM($A28)),母公司账项调整!$J$5:$J$65536) -> 0 | G28: =SUMIF(母公司报表调整!$E$5:$E$65536,IF(OR(MID(TRIM($A28),2,1)="：",MID(TRIM($A28),2,1)="、"),REPLACEB(TRIM($A28),1,4,""),TRIM($A28)),母公司报表调整!$J$5:$J$65536) -> 0 | H28: =SUMIF(母公司报表调整!$H$5:$H$65536,IF(OR(MID(TRIM($A28),2,1)="：",MID(TRIM($A28),2,1)="、"),REPLACEB(TRIM($A28),1,4,""),TRIM($A28)),母公司报表调整!$J$5:$J$65536) -> 0 | I28: =B28+E28+G28-F28-H28+C28-D28 -> 0 | K28: =SUM(I28:J28) -> 0
A29: =报表格式!B28 -> 0 | B29: =母公司BS汇总!B29 -> 0 | C29: =SUMIF(母公司汇总抵销!$E$5:$E$65538,IF(OR(MID(TRIM($A29),2,1)="：",MID(TRIM($A29),2,1)="、"),REPLACEB(TRIM($A29),1,4,""),TRIM($A29)),母公司汇总抵销!$J$5:$J$65538) -> 0 | D29: =SUMIF(母公司汇总抵销!$H$5:$H$65538,IF(OR(MID(TRIM($A29),2,1)="：",MID(TRIM($A29),2,1)="、"),REPLACEB(TRIM($A29),1,4,""),TRIM($A29)),母公司汇总抵销!$J$5:$J$65538) -> 0 | E29: =SUMIF(母公司账项调整!$E$5:$E$65536,IF(OR(MID(TRIM($A29),2,1)="：",MID(TRIM($A29),2,1)="、"),REPLACEB(TRIM($A29),1,4,""),TRIM($A29)),母公司账项调整!$J$5:$J$65536) -> 0 | F29: =SUMIF(母公司账项调整!$H$5:$H$65536,IF(OR(MID(TRIM($A29),2,1)="：",MID(TRIM($A29),2,1)="、"),REPLACEB(TRIM($A29),1,4,""),TRIM($A29)),母公司账项调整!$J$5:$J$65536) -> 0 | G29: =SUMIF(母公司报表调整!$E$5:$E$65536,IF(OR(MID(TRIM($A29),2,1)="：",MID(TRIM($A29),2,1)="、"),REPLACEB(TRIM($A29),1,4,""),TRIM($A29)),母公司报表调整!$J$5:$J$65536) -> 0 | H29: =SUMIF(母公司报表调整!$H$5:$H$65536,IF(OR(MID(TRIM($A29),2,1)="：",MID(TRIM($A29),2,1)="、"),REPLACEB(TRIM($A29),1,4,""),TRIM($A29)),母公司报表调整!$J$5:$J$65536) -> 0 | I29: =B29+E29+G29-F29-H29+C29-D29 -> 0 | K29: =SUM(I29:J29) -> 0
A30: =报表格式!B29 -> 0 | B30: =母公司BS汇总!B30 -> 0 | C30: =SUMIF(母公司汇总抵销!$E$5:$E$65538,IF(OR(MID(TRIM($A30),2,1)="：",MID(TRIM($A30),2,1)="、"),REPLACEB(TRIM($A30),1,4,""),TRIM($A30)),母公司汇总抵销!$J$5:$J$65538) -> 0 | D30: =SUMIF(母公司汇总抵销!$H$5:$H$65538,IF(OR(MID(TRIM($A30),2,1)="：",MID(TRIM($A30),2,1)="、"),REPLACEB(TRIM($A30),1,4,""),TRIM($A30)),母公司汇总抵销!$J$5:$J$65538) -> 0 | E30: =SUMIF(母公司账项调整!$E$5:$E$65536,IF(OR(MID(TRIM($A30),2,1)="：",MID(TRIM($A30),2,1)="、"),REPLACEB(TRIM($A30),1,4,""),TRIM($A30)),母公司账项调整!$J$5:$J$65536) -> 0 | F30: =SUMIF(母公司账项调整!$H$5:$H$65536,IF(OR(MID(TRIM($A30),2,1)="：",MID(TRIM($A30),2,1)="、"),REPLACEB(TRIM($A30),1,4,""),TRIM($A30)),母公司账项调整!$J$5:$J$65536) -> 0 | G30: =SUMIF(母公司报表调整!$E$5:$E$65536,IF(OR(MID(TRIM($A30),2,1)="：",MID(TRIM($A30),2,1)="、"),REPLACEB(TRIM($A30),1,4,""),TRIM($A30)),母公司报表调整!$J$5:$J$65536) -> 0 | H30: =SUMIF(母公司报表调整!$H$5:$H$65536,IF(OR(MID(TRIM($A30),2,1)="：",MID(TRIM($A30),2,1)="、"),REPLACEB(TRIM($A30),1,4,""),TRIM($A30)),母公司报表调整!$J$5:$J$65536) -> 0 | I30: =B30+E30+G30-F30-H30+C30-D30 -> 0 | K30: =SUM(I30:J30) -> 0
A31: =报表格式!B30 -> 流动资产合计 | B31: =SUM(B7:B30)-B21-B22 -> 0 | C31: =SUM(C7:C30)-C21-C22 -> 0 | D31: =SUM(D7:D30)-D21-D22 -> 0 | E31: =SUM(E7:E30)-E21-E22 -> 0 | F31: =SUM(F7:F30)-F21-F22 -> 0 | G31: =SUM(G7:G30)-G21-G22 -> 0 | H31: =SUM(H7:H30)-H21-H22 -> 0 | I31: =B31+E31+G31-F31-H31+C31-D31 -> 0 | J31: =SUM(J7:J30)-J21-J22 -> 0 | K31: =SUM(I31:J31) -> 0
A32: =报表格式!B31 -> 非流动资产:
A33: =报表格式!B32 -> 发放贷款及垫款 | B33: =母公司BS汇总!B33 -> 0 | C33: =SUMIF(母公司汇总抵销!$E$5:$E$65538,IF(OR(MID(TRIM($A33),2,1)="：",MID(TRIM($A33),2,1)="、"),REPLACEB(TRIM($A33),1,4,""),TRIM($A33)),母公司汇总抵销!$J$5:$J$65538) -> 0 | D33: =SUMIF(母公司汇总抵销!$H$5:$H$65538,IF(OR(MID(TRIM($A33),2,1)="：",MID(TRIM($A33),2,1)="、"),REPLACEB(TRIM($A33),1,4,""),TRIM($A33)),母公司汇总抵销!$J$5:$J$65538) -> 0 | E33: =SUMIF(母公司账项调整!$E$5:$E$65536,IF(OR(MID(TRIM($A33),2,1)="：",MID(TRIM($A33),2,1)="、"),REPLACEB(TRIM($A33),1,4,""),TRIM($A33)),母公司账项调整!$J$5:$J$65536) -> 0 | F33: =SUMIF(母公司账项调整!$H$5:$H$65536,IF(OR(MID(TRIM($A33),2,1)="：",MID(TRIM($A33),2,1)="、"),REPLACEB(TRIM($A33),1,4,""),TRIM($A33)),母公司账项调整!$J$5:$J$65536) -> 0 | G33: =SUMIF(母公司报表调整!$E$5:$E$65536,IF(OR(MID(TRIM($A33),2,1)="：",MID(TRIM($A33),2,1)="、"),REPLACEB(TRIM($A33),1,4,""),TRIM($A33)),母公司报表调整!$J$5:$J$65536) -> 0 | H33: =SUMIF(母公司报表调整!$H$5:$H$65536,IF(OR(MID(TRIM($A33),2,1)="：",MID(TRIM($A33),2,1)="、"),REPLACEB(TRIM($A33),1,4,""),TRIM($A33)),母公司报表调整!$J$5:$J$65536) -> 0 | I33: =B33+E33+G33-F33-H33+C33-D33 -> 0 | K33: =SUM(I33:J33) -> 0
A34: =报表格式!B33 -> 债权投资 | B34: =母公司BS汇总!B34 -> 0 | C34: =SUMIF(母公司汇总抵销!$E$5:$E$65538,IF(OR(MID(TRIM($A34),2,1)="：",MID(TRIM($A34),2,1)="、"),REPLACEB(TRIM($A34),1,4,""),TRIM($A34)),母公司汇总抵销!$J$5:$J$65538) -> 0 | D34: =SUMIF(母公司汇总抵销!$H$5:$H$65538,IF(OR(MID(TRIM($A34),2,1)="：",MID(TRIM($A34),2,1)="、"),REPLACEB(TRIM($A34),1,4,""),TRIM($A34)),母公司汇总抵销!$J$5:$J$65538) -> 0 | E34: =SUMIF(母公司账项调整!$E$5:$E$65536,IF(OR(MID(TRIM($A34),2,1)="：",MID(TRIM($A34),2,1)="、"),REPLACEB(TRIM($A34),1,4,""),TRIM($A34)),母公司账项调整!$J$5:$J$65536) -> 0 | F34: =SUMIF(母公司账项调整!$H$5:$H$65536,IF(OR(MID(TRIM($A34),2,1)="：",MID(TRIM($A34),2,1)="、"),REPLACEB(TRIM($A34),1,4,""),TRIM($A34)),母公司账项调整!$J$5:$J$65536) -> 0 | G34: =SUMIF(母公司报表调整!$E$5:$E$65536,IF(OR(MID(TRIM($A34),2,1)="：",MID(TRIM($A34),2,1)="、"),REPLACEB(TRIM($A34),1,4,""),TRIM($A34)),母公司报表调整!$J$5:$J$65536) -> 0 | H34: =SUMIF(母公司报表调整!$H$5:$H$65536,IF(OR(MID(TRIM($A34),2,1)="：",MID(TRIM($A34),2,1)="、"),REPLACEB(TRIM($A34),1,4,""),TRIM($A34)),母公司报表调整!$J$5:$J$65536) -> 0 | I34: =B34+E34+G34-F34-H34+C34-D34 -> 0 | K34: =SUM(I34:J34) -> 0
