Workbook

Sheet 底稿目录
A1: 底稿开列时，可先在以下单元格填写有关内容，以便其他底稿引用有关数据：
A2: 被审计单位：ABC公司 | D2: 序号 | E2: 内容 | F2: 索引号
A3: 截止日：202X年12月31日 | D3: 1 | E3: 错报程序表 | F3: A13
A4: 编制人：张三 | D4: =D3+1 -> 2 | E4: 未更正错报汇总表（不含披露错报） | F4: A13-1
A5: 编制日期：2025.X.X | D5: =D4+1 -> 3 | E5: 未更正披露错报汇总表 | F5: A13-2
A6: 复核人：李四 | D6: =D5+1 -> 4 | E6: 评价识别出的错报 | F6: A13-3
A7: 复核日期：2025.X.X | D7: =D6+1 -> 5 | E7: 评价错报的性质 | F7: A13-4
A8: 会计期间：202X年度 | D8: =D7+1 -> 6 | E8: 对错报的沟通 | F8: A13-5
A9: 截止日/会计期间：202X年X月X日/202X年度

Sheet A13错报程序表
B1: 致同会计师事务所
B2: 错报程序表
A3: =底稿目录!A2 -> 被审计单位：ABC公司 | D3: =底稿目录!A4 -> 编制人：张三 | F3: =底稿目录!A5 -> 编制日期：2025.X.X | I3: 索引号： | K3: A13
A4: =底稿目录!A8 -> 会计期间：202X年度 | D4: =底稿目录!A6 -> 复核人：李四 | F4: =底稿目录!A7 -> 复核日期：2025.X.X | I4: 页 次：
A5: 序号 | B5: 程序 | H5: 是否适用 | I5: 执行人 | J5: 执行情况说明 | K5: 索引号 | L5: 开机启动项
A6: 1 | B6: 确定所有的调整和重分类会计分录已被恰当地插入适当的审定表中。
A7: 2 | B7: 考虑这些建议的审计调整是否对本年中期财务报告产生影响，若有。 | L7: 上市公司
A8: 2.1 | B8: 与项目合伙人讨论调整问题。 | L8: 上市公司
A9: 2.2 | B9: 与合适的客户人员讨论调整事宜。 | L9: 上市公司
A10: 2.3 | B10: 确定本年中期报表是否需要修改 。 | L10: 上市公司
A11: 3 | B11: 总结未更正错报，包括遗漏的披露，加总于未更正错报汇总表中。. | K11: A13-1
A12: 3.1 | B12: 与适当的管理层复核未调整的错报。 | K12: A13-3,A13-5
A13: 3.2 | B13: 要求管理层记录所有讨论过的错报。
A14: 3.3 | B14: 对于管理层认为不重大的项目，单独或汇总评估其重要性：
A15: 3.3.1 | B15: 了解管理层不进行更正的原因。
A16: 3.3.2 | B16: 确定是否单独，或在总量上，这些差异对财务报表有量化重要性。
A17: 3.3.3 | B17: 从质量上考虑财务报表重要性（如个别项目，小计，总计和对财务报表隐含的比率）。
A18: 3.3.4 | B18: 确定任何差异对财务报表来说是否性质重要。
A19: 3.3.5 | B19: 如果不调整差异金额汇总是重大的话，找出个别项目作为调整分录，使不调整差异金额汇总小于财务报表的重要性水平。
A20: 3.3.6 | B20: 考虑以前年度错报的累积影响。
A21: 3.4 | B21: 确定剩下的未更正错报对财务报表是否是不重大的。
A22: 4 | B22: 判断已确认错报是否存在舞弊，如果是，与项目合伙人商讨。 | K22: A13-4
A23: 5 | B23: 确定导致错报的控制缺陷是否在相应的内部控制缺陷评价底稿中予以评估（记录在相关的控制缺陷评估底稿）并汇总至“内部控制缺陷汇总表”中。（说明：发现非微小错报一般认为至少是一项重要缺陷，但是可能是重大缺陷。） | K23: A13-4

Sheet A13-1 未更正错报汇总表
A1: 致同会计师事务所
A2: 未更正错报汇总表（不包括列报和披露错报）
A3: =底稿目录!A2 -> 被审计单位：ABC公司 | E3: =底稿目录!A4 -> 编制人：张三 | G3: =底稿目录!A5 -> 编制日期：2025.X.X | I3: 索引号 | J3: A13-1
A4: =底稿目录!A9 -> 截止日/会计期间：202X年X月X日/202X年度 | E4: =底稿目录!A6 -> 复核人：李四 | G4: =底稿目录!A7 -> 复核日期：2025.X.X | I4: 页 次 1
A5: 序号 | B5: 内容及说明 | D5: 索引号 | E5: 调整内容 | I5: 错报 | J5: 管理层不予
E6: 借方科目 | F6: 借方金额 | G6: 贷方科目 | H6: 贷方金额 | I6: 性质 | J6: 更正的原因
A7: 一 | B7: 以前期间识别出的影响本期财务报表的前期未更正错报
A8: 1
A9: 2
A10: 3
A12: 二 | B12: 本期识别出的影响本期财务报表的前期未更正错报
A13: 1
A14: 2
A15: 3
A17: 三 | B17: 本期识别出的影响本期财务报表的未更正错报
A18: 1
A19: 2
A20: 3
A22: 1、前期未更正错报影响合计（第一项和第二项合计）
C23: 序号 | D23: 项目 | E23: 借方金额 | F23: 贷方金额 | G23: 合计 | H23: 财务报表列报金额 | I23: 备注
C24: (1) | D24: 资产 | G24: =E24-F24 -> 0
C25: (2) | D25: 负债 | G25: =F25-E25 -> 0
C26: (3) | D26: 权益 | G26: =F26-E26 -> 0
C27: (4) | D27: 损益 | G27: =F27-E27 -> 0
A29: 2、未更正错报影响合计（第一项、第二项和第三项合计）
C30: 序号 | D30: 项目 | E30: 借方金额 | F30: 贷方金额 | G30: 合计 | H30: 财务报表列报金额 | I30: 备注
C31: (1) | D31: 资产 | G31: =E31-F31 -> 0
C32: (2) | D32: 负债 | G32: =F32-E32 -> 0
C33: (3) | D33: 权益 | G33: =F33-E33 -> 0
C34: (4) | D34: 损益 | G34: =F34-E34 -> 0
A36: 备注：
A37: 1 | B37: 错报性质包括：舞弊、错误
A38: 2 | B38: 错报行数不够可通过插入行增加；对已更正错报实施的检查程序行数不够可通过插入行增加

Sheet A13-2 未更正的列报和披露错报
A1: 致同会计师事务所
A2: 未更正的列报和披露错报汇总表
A3: =底稿目录!A2 -> 被审计单位：ABC公司 | D3: =底稿目录!A4 -> 编制人：张三 | F3: =底稿目录!A5 -> 编制日期：2025.X.X | H3: 索引号 | I3: A13-2
A4: =底稿目录!A9 -> 截止日/会计期间：202X年X月X日/202X年度 | D4: =底稿目录!A6 -> 复核人：李四 | F4: =底稿目录!A7 -> 复核日期：2025.X.X | H4: 页 次 1
A5: 序号 | B5: 错报说明 | D5: 索引号 | E5: 相关披露和列报要求 | G5: 金额(如适用) | H5: 错报性质 | I5: 管理层不予更正的原因
A6: 1
A7: 2
A8: 3
A9: 4
A10: 5
A11: 6
A12: 7
A13: 8
A14: 9
A15: 10
A16: 11
A17: 12
... A23: 18
A24: 备注：
A25: 1 | B25: 错报性质包括：舞弊、错误
A26: 2 | B26: 错报行数不够可通过插入行增加

Sheet A13-3 评价识别出的错报
A1: 致同会计师事务所
A2: 评价识别出的错报
A3: =A13错报程序表!A3 -> 被审计单位：ABC公司 | E3: =底稿目录!A4 -> 编制人：张三 | G3: =底稿目录!A5 -> 编制日期：2025.X.X | I3: 索引号 | J3: A13-3
A4: =底稿目录!A9 -> 截止日/会计期间：202X年X月X日/202X年度 | E4: =底稿目录!A6 -> 复核人：李四 | G4: =底稿目录!A7 -> 复核日期：2025.X.X | I4: 页 次 1
A5: 一、识别出的错报对审计的影响
B6: 1、错报合计
A7: 项目 | C7: 金额
C8: 资产(+) | D8: 资产(-) | E8: 负债(+) | F8: 负债(-) | G8: 权益(+) | H8: 权益(-) | I8: 损益(+) | J8: 损益(-)
A9: 已更正错报合计
A10: 未更正错报合计
B11: 2、本期财务报表整体重要性：
B12: 3、评价：
A13: (1)审计过程中累积的错报合计数是否接近重要性（是/否）：
A14: (2)识别出的错报的性质以及错报发生的环境是否表明可能存在其他错报，并且可能存在的其他错报与审计过程中累积的错报合计起来可能是重大的（是/否）：
B15: 4、结论：
A16: 无需修改总体审计策略和具体审计计划
A17: 或者：需要修改总体审计策略和具体审计计划，详见【工作底稿索引】
A18: 二、前期未更正错报对前期财务报表的影响
B19: 1、前期未更正错报：
A20: 项目 | C20: 金额
C21: 资产(+) | D21: 资产(-) | E21: 负债(+) | F21: 负债(-) | G21: 权益(+) | H21: 权益(-) | I21: 损益(+) | J21: 损益(-)
A22: 未更正错报合计
B23: 2、前期财务报表整体重要性：
B24: 3、结论：
A25: 与以前期间相关的未更正错报对前期财务报表的影响不重大，不需要重述财务报表
A26: 或者：与以前期间相关的未更正错报对前期财务报表的影响重大，需要重述财务报表
A27: 三、未更正错报对本期财务报表的影响
B28: 1、未更正错报：
A29: 项目 | C29: 金额
C30: 资产(+) | D30: 资产(-) | E30: 负债(+) | F30: 负债(-) | G30: 权益(+) | H30: 权益(-) | I30: 损益(+) | J30: 损益(-)
A31: 未更正错报合计
B32: 2、本期财务报表整体重要性:
B33: 3、结论：
A34: 未更正错报单独或汇总起来不构成重大错报
A35: 或者：未更正错报单独或汇总起来构成重大错报
A36: 备注：
A37: 1 | B37: 在“3、结论：”的方框中选择一种结论，不适用的结论请删除。

Sheet A13-4 评价错报的性质
A1: 致同会计师事务所
A2: 评价错报的性质
A3: =底稿目录!A2 -> 被审计单位：ABC公司 | D3: =底稿目录!A4 -> 编制人：张三 | G3: =底稿目录!A5 -> 编制日期：2025.X.X | I3: 索引号 | J3: A13-4
A4: =底稿目录!A9 -> 截止日/会计期间：202X年X月X日/202X年度 | D4: =底稿目录!A6 -> 复核人：李四 | G4: =A13错报程序表!F4 -> 复核日期：2025.X.X | I4: 页 次 1
A5: —、错报性质——错误
A6: 索引号 | B6: 导致错报的具体原因 | D6: 是否为内部控制缺陷(是/否) | E6: 是否为值得关注的内部控制缺陷(是/否) | G6: 对缺陷的描述 | I6: 潜在影响
A11: 二、错报性质——舞弊
A12: 索引号 | B12: 导致错报的具体原因 | D12: 是否为内部控制缺陷(是/否) | E12: 是否为值得关注的内部控制缺陷(是/否) | G12: 对缺陷的描述 | I12: 潜在影响
A17: 三、评价舞弊对审计的影响
B18: 1、重新评价对由于舞弊导致的重大错报风险的评估结果
B22: 2、对审计程序的性质、时间安排和范围的影响
B26: 3、对此前获取的审计证据的可靠性的影响
B30: 4、对管理层声明的可靠性的影响
A36: 备注：
A37: 1 | B37: 错报可能由下列事项导致：
B38: （1）收集或处理用以编制财务报表的数据时出现错误；
B39: （2）遗漏某项金额或披露，包括不充分或不完整的披露，以及为满足特定财务报告编制基础的披露目标而被要求作出的披露（如适用）；
B40: （3）由于疏忽或明显误解有关事实导致作出不正确的会计估计；
B41: （4）注册会计师认为管理层对会计估计作出不合理的判断或对会计政策作出不恰当的选择和运用。
B42: （5）信息的分类、汇总或分解不恰当。
B43: 《〈中国注册会计师审计准则第1141号——财务报表审计中与舞弊相关的责任〉应用指南》列举了由于舞弊导致的错报的例子。
A44: 2 | B44: 披露中的错报也可能表明存在舞弊，例如，导致这些错报的原因可能包括：
B45: （1）管理层的判断出现偏向导致的误导性披露；
B46: （2）意图阻碍正确理解财务报表的大量重复披露或缺乏信息含量的披露。
B47: 在考虑各类交易、账户余额及披露中存在的错报的影响时，注册会计师需要按照《中国注册会计师审计准则第1101号——注册会计师的总体目标和审计工作的基本要求》的规定运用职业怀疑。

Sheet GT_Custom
A1: C1 | B1: Custom 1
A2: C2 | B2: Custom 2
A3: C3 | B3: Custom 3
A4: C4 | B4: Custom 4
A5: C5 | B5: Custom 5
A6: C6 | B6: Custom 6
A7: C7 | B7: Custom 7
A8: C8 | B8: Custom 8

Sheet A13-5对错报的沟通
A1: 致同会计师事务所
A2: 对错报的沟通记录
A3: =底稿目录!A2 -> 被审计单位：ABC公司 | B3: =底稿目录!A4 -> 编制人：张三 | C3: =底稿目录!A5 -> 编制日期：2025.X.X | D3: 索引号： | E3: A13-5
A4: =底稿目录!A8 -> 会计期间：202X年度 | B4: =底稿目录!A6 -> 复核人：李四 | C4: =底稿目录!A7 -> 复核日期：2025.X.X | D4: 页 次：
A5: —、与管理层的沟通
B6: 沟通时间
B7: 管理层成员
B8: 项目组成员
B9: 沟通事项
B14: 管理层意见
B19: 书面声明索引
A21: 二、与治理层的沟通
B22: 沟通时间
B23: 治理层成员
B24: 项目组成员
B25: 沟通事项
B30: 治理层意见
B35: 书面声明索引
