Workbook

Sheet S12 利用专家的工作程序表
A1: 致同会计师事务所
A2: 利用专家（注册会计师的专家）的工作程序表
A3: 客户名称： | D3: 编制人： | G3: 日期： | I3: 索引号： | J3: S12
A4: 截止日：202X年12月31日 | D4: 复核人： | G4: 日期： | I4: 页 次：
A5: 序号 | B5: 程序 | G5: 是否适用 | H5: 执行人 | I5: 执行情况说明 | J5: 索引号
A6: 1 | B6: 确定是否利用专家的工作，考虑下列因素： | J6: B24
A7:  | B7: 管理层在编制财务报表时是否利用了管理层的专家的工作；
A8:  | B8: 事项的性质和重要性，包括复杂程度；
A9:  | B9: 事项存在的重大错报风险；
A10:  | B10: 应对识别出的风险的预期程序的性质，包括注册会计师对与这些事项相关的专家工作的了解和具有的经验，以及是否可以获得替代性的审计证据。
A11: 2 | B11: 确定内部专家（若适用）遵守会计师事务所的质量控制政策和程序（包括独立性要求）。
A12: 3 | B12: 评价专家的胜任能力、专业素质和客观性 | G12: 是 | J12: S12-1
A13: 3.1 | B13: 考虑以前与专家交往的个人经验；
A14: 3.2 | B14: 与专家进行讨论；
A15: 3.3 | B15: 与熟悉专家工作的其他注册会计师、其他机构或人员进行讨论；
A16: 3.4 | B16: 对专家的资格、会员身份、执业资格或其他形式的外部认证进行了解； | K16: 特殊领域需考虑专家资格要求，如：珠宝鉴定师、土地和房地产造价师、司法鉴定
A17: 3.5 | B17: 阅读专家发表的论文或出版的书籍（若适用）；
A18: 3.6 | B18: 评价外部专家的客观性
A19:  | B19: 向被审计单位询问是否存在可能影响外部专家客观性的任何已知的利益或关系；
A20:  | B20: 与专家讨论各种适用的防范措施（包括适用于专家的职业规范），并评价这些防范措施是否足以将不利影响降至可接受的水平；
A21:  | B21: 记录利用与被审计单位存在关联关系的专家的理由，并考虑影响该专家客观性的风险； | J21: S12-1-1
A22:  | B22: 考虑针对外部专家已知的、与被审计单位存在的任何利益或关系，从外部专家获取书面声明。
A23: 3.7 | B23: 如果询问导致了对专家胜任能力或客观性存在疑虑：
A24:  | B24: 与管理层讨论相关问题；
A25:  | B25: 对于专家的工作，考虑能否获取充分、适当的审计证据，并且适当的剪裁审计程序。
A26: 4 | B26: 了解专家的专长领域 | G26: 是 | J26: S12-2
A27: 4.1 | B27: 考虑以前向其他在编制财务报表时需要专家专长的被审计单位提供审计服务时获取的经验；
A28: 4.2 | B28: 与专家进行讨论；
A29: 4.3 | B29: 专家在特定领域中的教育或职业发展；
A30: 4.4 | B30: 与执行过类似业务的注册会计师进行讨论。
A31: 5 | B31: 与专家达成一致意见 | G31: 是 | J31: S12-2
A32: 5.1 | B32: 明确专家工作的性质、范围和目标；
A33: 5.2 | B33: 明确各自的角色和责任；
A34: 5.3 | B34: 确定适用于专家的保密条款。
A35: 6 | B35: 评价专家工作的恰当性 | G35: 是 | J35: S12-3
A36: 6.1 | B36: 取得注册会计师的专家的报告或评价底稿 | J36: S12-3-1/S12-3-2
A37: 6.2 | B37: 评价专家工作是否足以实现审计目的：
A38:  | B38: 询问专家；
A39:  | B39: 复核专家的工作底稿和报告；
A40:  | B40: 实施用于证实的程序，例如观察专家的工作，检查已公布的数据（如来源于信誉高、权威的渠道的统计报告），向第三方询证相关事项，执行详细的分析程序，重新计算；
A41:  | B41: 必要时（如当专家的工作结果或结论与其他审计证据不一致时）与具有相关专长的其他专家讨论；
A42:  | B42: 与管理层讨论专家的报告。
A43: 6.3 | B43: 评价专家使用的重要假设和方法的相关性和合理性
A44:  | B44: 评价专家是否已经充分复核了管理层使用的假设和方法； | K44: 如果专家的工作是评价管理层作出会计估计时使用的基础假设和方法（包括模型，如适用）
A45:  | B45: 评价专家使用的假设和方法（包括专家使用的模型，如适用）； | K45: 如果专家的工作是形成注册会计师的点估计，或是形成注册会计师用来与管理层的点估计进行比较的范围
A46:  | B46: 对专家工作过程及其所作的重要职业判断（尤其是数据引用、参数选取、假设认定等）进行复核，以判断专家工作的恰当性； | K46: 证监会《会计监管风险提示第8号—商誉减值》
A47:  | B47: 将方法和假设同以前年度所用的进行比较。
A48: 6.4 | B48: 评价专家使用的重要原始数据的相关性、完整性和准确性
A49:  | B49: 核实数据的来源，包括了解和测试（适用时）针对数据的内部控制以及向专家传送数据的方式（如相关）；
A50:  | B50: 询问专家是如何认定所使用数据的适当性；
A51:  | B51: 将此类数据与我们获取的信息进行比较，复核数据的完整性和内在一致性；
A52:  | B52: 考虑提供给专家的任何非财务数据的可靠性；
A53:  | B53: 测试原始数据，或者通过询问专家、监督或复核专家的测试来评价数据的相关性、完整性和准确性。
A54: 7 | B54: 比较专家以前期间的发现（若适用）与实际结果
A55: 8 | B55: 如果确定专家的工作不足以实现审计目的，注册会计师应当采取下列措施之一：
A56:  | B56: 就专家拟执行的进一步工作的性质和范围，与专家达成一致意见；
A57:  | B57: 根据具体情况，实施追加的审计程序；
A58:  | B58: 如果没有获取充分、适当的审计证据，按照《中国注册会计师审计准则第1502号——在审计报告中发表非无保留意见》的规定发表非无保留意见。
B60: 如果注册会计师认为专家的工作不足以实现审计目的，且注册会计师通过实施本准则第十四条规定的追加的审计程序（如专家和注册会计师执行进一步工作），或者通过雇用、聘请其他专家仍不能解决问题，则没有获取充分、适当的审计证据。

Sheet S12-1 评价胜任能力、专业素质和客观性
A1: 致同会计师事务所
A2: 评价专家的胜任能力、专业素质和客观性
A3: ='S12 利用专家的工作程序表'!A3 -> 客户名称： | E3: 编制人： | H3: 日期： | J3: 索引号： | K3: S12-1
A4: ='S12 利用专家的工作程序表'!A4 -> 截止日：202X年12月31日 | E4: 复核人： | H4: 日期： | J4: 页 次：
A5: 一、审计目标
B6: 在获取审计证据时利用专家的工作，确定注册会计师的专家的工作是否足以实现审计目的。 | L6: 专家，即注册会计师的专家，是指在会计或审计以外的某一领域具有专长的个人或组织，并且其工作被注册会计师利用，以协助注册会计师获取充分、适当的审计证据。专家既可能是会计师事务所内部专家（如会计师事务所或其网络事务所的合伙人或员工，包括临时员工），也可能是会计师事务所外部专家。
A7: 二、审计过程：
A8: 评价专家的胜任能力、专业素质和客观性
B9: 项目 | H9: 记录
B10: 专家的姓名/组织名称
B11: 专家在其领域的专长 | L11: 专家的胜任能力与其专长的性质和水平有关。
B12: 体现专家胜任能力的证书、执业资质或专业组织的认可文件
B13: 专家的行业声誉
B14: 专家在专业领域中的经验 | L14: 专家的专业素质与在业务的具体情况下对胜任能力的发挥相关。影响专业素质发挥的因素包括地理位置（专家所在的国家或地区）、可用的时间和资源等。
B15: 专家需要遵守的技术标准、职业准则或行业要求（如职业团体或行业协会的职业道德守则和其他会员要求，特许机构提出的认证标准）以及法律法规的要求等
B16: 影响专家客观性的情况（如自身利益、自我评价、过度推介、密切关系和外在压力等）及防范措施（如专家所属的职业团体、法律法规的要求、质量控制政策和程序） | H16: 不存在。或详见S12-1-1 | L16: 专家的客观性与其偏见、利益冲突及其他可能影响其职业判断或商业判断的因素相关。
B17: 影响外部专家客观性的情况（如经济利益、商业关系和私人关系、提供的其他服务等）及防范措施（如专家所属的职业团体、法律法规的要求，质量控制政策和程序）是否适当 | H17: 不存在。或详见S12-1-1
B19: 结论：未识别出导致对专家的胜任能力、专业素质和客观性产生疑虑的事项或情况。

Sheet S12-1-1 评价专家的客观性
A1: 致同会计师事务所
A2: 评价专家的客观性
A3: ='S12 利用专家的工作程序表'!A3 -> 客户名称： | E3: 编制人： | H3: 日期： | J3: 索引号： | K3: S12-1-1
A4: ='S12 利用专家的工作程序表'!A4 -> 截止日：202X年12月31日 | E4: 复核人： | H4: 日期： | J4: 页 次：
A5: 一、审计目标
B6: 在专家与被审计单位存在关联方关系、经济利益、商业关系或私人关系时，评价专家的客观性。
A7: 二、审计过程：
A8: 评价专家的客观性
B9: 项目 | H9: 记录（若下述前三项均无，则无需本底稿）
B10: 专家与被审计单位的关联方关系
B11: 影响专家（内外部）客观性的情况（如自身利益、自我评价、过度推介、密切关系和外在压力等） | H11: 与致同网络存在独立性冲突的专业机构（具体清单咨询质控部门），不能被致同审计客户聘请为管理层的专家、用以协助管理层编制财务报表 | L11: 专家的客观性与其偏见、利益冲突及其他可能影响其职业判断或商业判断的因素相关。
B12: 影响外部专家客观性的情况（如经济利益、商业关系和私人关系、提供的其他服务等）
B13: 对影响专家客观性的任何已知的利益或关系（如自身利益、自我评价、过度推介、密切关系和外在压力等）的防范措施 | H13: 如专家所属的职业团体的要求、法律法规的要求、质量控制政策和程序、专门针对审计业务的防范措施等
B14: 对影响外部专家客观性的情况（如经济利益、商业关系和私人关系、提供的其他服务等）的防范措施 | H14: 如专家所属的职业团体的要求、法律法规的要求，质量控制政策和程序 | L14: 在某些情况下，采取防范措施不能将不利影响降至可接受的水平。例如，注册会计师拟聘请的专家是管理层的专家，在编制将作为审计对象的信息的过程中该专家发挥了重要作用。
B15: 上述防范措施是否足以将不利影响降至可接受的水平
B16: 以前与专家交往的个人经验是否表明专家存在偏见
B17: 与熟悉专家工作的其他注册会计师、其他机构或人员进行讨论，分析专家是否存在偏见、利益冲突
B20: 结论：未识别出导致对专家的客观性产生疑虑的事项或情况。

Sheet S12-2 了解专家的专长领域
A1: 致同会计师事务所
A2: 了解专家的专长领域并与专家达成一致意见
A3: ='S12-1 评价胜任能力、专业素质和客观性'!A3 -> 客户名称： | E3: ='S12-1 评价胜任能力、专业素质和客观性'!E3 -> 编制人： | H3: ='S12-1 评价胜任能力、专业素质和客观性'!H3 -> 日期： | J3: 索引号： | K3: S12-2
A4: ='S12-1 评价胜任能力、专业素质和客观性'!A4 -> 截止日：202X年12月31日 | E4: 复核人： | H4: 日期： | J4: 页 次：
A5: 一、审计目标
B6: 在获取审计证据时利用专家的工作，确定注册会计师的专家的工作是否足以实现审计目的。
A7: 二、审计过程：
A8: （一）了解专家的专长领域
B9: 项目 | D9: 记录
B10: 与审计相关的、专家专长领域的进一步细分信息
B11: 职业准则或其他准则以及法律法规是否适用
B12: 专家使用的假设和方法（包括模型）
B13: 上述假设和方法在该专家的专长领域是否得到普遍认可
B14: 专家使用的内外部数据或信息的性质
B15: 结论：专家的工作对实现财务报告目的是适当的。
A16: （二）与专家达成一致意见
B17: 项目 | D17: 记录
B18: 注册会计师与外部专家的约定书或协议的名称和索引 | L18: 达成一致意见的证据可能包括：业务约定书或其他形式的协议；总体审计策略、具体审计计划或其他相关审计工作底稿；会计师事务所的政策和程序。
B19: 专家工作的性质、范围和目标 | L19: 通常需要与专家讨论需要遵守的相关技术标准、其他职业准则或行业要求。
B20: 注册会计师和专家各自的角色和责任 | L20: 【可能包括：由注册会计师还是专家对原始数据实施细节测试；将注册会计师对专家工作形成的结论告知专家；就各自的工作底稿的使用和保管达成的一致意见】
B21: 与专家的沟通 | D21: 如果专家的工作与注册会计师针对某项特别风险形成的结论相关，专家不仅要在工作结束时提交一份正式的书面报告，而且要随着工作的推进随时作出口头报告。 | L21: 如果专家的工作与注册会计师针对某项特别风险形成的结论相关，专家不仅要在工作结束时提交一份正式的书面报告，而且要随着工作的推进随时作出口头报告。
B22: 对专家遵守保密规定的要求 | L22: 【说明：适用于注册会计师的相关职业道德要求中的保密条款同样也适用于专家。】
B23: 结论：与专家达成一致意见。

Sheet S12-3 评价专家工作的恰当性
A1: 致同会计师事务所
A2: 评价专家工作的恰当性
A3: ='S12-1 评价胜任能力、专业素质和客观性'!A3 -> 客户名称： | E3: ='S12-1 评价胜任能力、专业素质和客观性'!E3 -> 编制人： | H3: ='S12-1 评价胜任能力、专业素质和客观性'!H3 -> 日期： | J3: 索引号： | K3: S12-3
A4: ='S12-1 评价胜任能力、专业素质和客观性'!A4 -> 截止日：202X年12月31日 | E4: 复核人： | H4: 日期： | J4: 页 次：
A5: 一、审计目标
B6: 在获取审计证据时利用专家的工作，确定注册会计师的专家的工作是否足以实现审计目的。
A7: 二、审计过程：
A8: 评价专家工作的恰当性
B9: 项目 | D9: 记录
B10: 专家的工作结果或结论的相关性和合理性 | L10: 专家的工作结果或结论是否得到清楚地表述，包括提及与注册会计师达成一致的目标，执行工作的范围和运用的标准；专家的工作结果或结论在使用方面是否有任何保留、限制或约束，如果有，是否对注册会计师的工作产生影响。
B11: 专家的工作结果或结论与其他审计证据的一致性（专家工作对审计工作的支持程度） | L11: 专家的工作结果或结论是否与历史数据、运营计划、商业机会、行业数据、行业研究报告、宏观经济运行状况，以及利用观察、询问、访谈、核对、函证、监盘、勘查、书面审查、实地调查等方式取得的证据相符。
B12: 如果专家的工作涉及使用重要的假设和方法，这些假设和方法在具体情况下的相关性和合理性 | D12: 详见S12-3-1/S12-3-2/S12-3-3/S12-3-4 | L12: 评价专家是否已经充分复核管理层（或管理层的专家）的假设和方法；评价专家使用的假设和方法（包括专家使用的模型，如适用）是否普遍使用，是否与管理层的假设、方法相一致，是否与适用的财务报告编制基础的要求相一致。
B13: 如果专家的工作涉及使用相当程度的原始数据，这些原始数据的相关性、完整性和准确性 | D13: 详见S12-3-1/S12-3-2/S12-3-3/S12-3-4 | L13: 核实数据的来源，包括了解和测试（适用时）针对数据的内部控制以及向专家传送数据的方式（如相关）；复核数据的完整性和内在一致性。
A14: 三、审计说明：
A16: 四、审计结论：
B17: 专家的工作可以实现审计目的。或者：专家的工作不足以实现审计目的。
B18: （如果认为专家的工作不足以实现审计目的，应说明原因并考虑是否追加适当的审计程序）

Sheet S12-3-1 注册会计师的专家的报告
A1: 致同会计师事务所
A2: 注册会计师的专家的报告
A3: ='S12 利用专家的工作程序表'!A3 -> 客户名称： | E3: ='S12 利用专家的工作程序表'!D3 -> 编制人： | H3: ='S12 利用专家的工作程序表'!G3 -> 日期： | J3: 索引号： | K3: S12-3-1
A4: ='S12 利用专家的工作程序表'!A4 -> 截止日：202X年12月31日 | E4: 复核人： | H4: 日期： | J4: 页 次：
A5: 一、注册会计师的专家提交的报告
B6: 若取得专家的报告，则专家评价的内容应完整（参考S12-3-2/S12-3-3/S12-3-4）。
B7: 【专家工作总结或专家报告结论中要求明确对相关模型/方法的参数和假设合理性发表意见】
B8: 也可以由专家完成底稿S12-3-2/S12-3-3/S12-3-4。
A10: 二、注册会计师的专家对管理层的专家工作的评价结论
B11: 评估结论基本合理。 【若认为管理层的专家的工作不能作为审计证据（如评估过程或结论不合理），则需考虑要求管理层重新评估或/并考虑对审计意见类型的影响。】

Sheet S12-3-2 利用专家评价管理层的工作的适当性
A1: 致同会计师事务所
A2: 利用专家评价管理层或管理层专家的工作的适当性
A3: ='S12 利用专家的工作程序表'!A3 -> 客户名称： | E3: ='S12 利用专家的工作程序表'!D3 -> 编制人： | H3: ='S12 利用专家的工作程序表'!G3 -> 日期： | J3: 索引号： | K3: S12-3-2
A4: ='S12 利用专家的工作程序表'!A4 -> 截止日：202X年12月31日 | E4: 复核人： | H4: 日期： | J4: 页 次：
A5: 一、利用注册会计师的专家的工作
B6: 序号 | C6: 项目 | I6: 索引号
B7: 1 | C7: 利用专家（注册会计师的专家）的工作 | I7: S12
A10: 二、评价管理层或管理层专家的工作过程及其结果或结论（主要适用于减值测试及公允价值计量）
B11: 也可以取得专家（注册会计师的专家）的工作报告（S12-3-1），但专家评价的内容应完整。
B12: 1、评估对象及评估范围是否与评估目的相匹配
L13: 评估机构应明确将用于商誉减值测试目的的评估事项约定为以财务报告为目的的评估。不得以股权、企业价值的评估报告代替以财务报告为目的的评估报告。
B15: 2、评估结果或价值类型是否与报告目的相符 | L15: （如商誉减值测试、公允价值计量）
B16: 将原收购的标的公司“全部资产和全部负债组成的资产组（股东权益）”界定为评估对象采用股东权益价值方法，不符合会计准则的要求。商誉减值测试的范围不是原标的公司的股权，而是被分摊商誉的资产组或资产组组合。 | L16: 当聘请的资产评估机构未对商誉所在资产组或资产组组合的可收回金额发表专门意见时，会计师事务所应着重考虑专家工作对审计工作的支持程度，并对专家工作成果进行必要调整，以适应财务报表审计目的。
B18: 3、评估基准日是否符合经济行为需要
B21: 4、评估假设与评估目的、评估方法的选择是否相符，是否合理
B24: 5、评估方法及其选择是否合理
L25: 将原收购的标的公司“全部资产和全部负债组成的资产组（股东权益）”界定为评估对象采用股东权益价值方法，不符合会计准则的要求。商誉减值测试的范围不是原标的公司的股权，而是被分摊商誉的资产组或资产组组合。
B27: 6、评价收益法/使用价值选用的参数和具体处理
B28: （1）盈利预测是否有可靠的数据来源，是否与历史数据、运营计划、商业机会、行业数据、行业研究报告、宏观经济运行状况相符
L29: 对未来现金净流量预测时，应以资产的当前状况为基础，以税前口径为预测依据，并充分关注选取的关键参数（包括但不限于销量、价格、成本、费用、预测期增长率、稳定期增长率）是否有可靠的数据来源，是否与历史数据、运营计划、商业机会、行业数据、行业研究报告、宏观经济运行状况相符；与此相关的重大假设是否与可获取的内部、外部信息相符，在不符时是否有合理理由支持。
B31: （2）对于营运资金的口径判断是否与非经营性资产负债一致
L32: 资产组价值=企业自由现金流评估值（经营性资产价值）－期初营运资金（为了便于评估资产组的未来现金流量，可以将营运资金纳入其现金流预测模型不予扣除，那么此时用于对比的包含商誉的资产组账面价值中也应包含营运资金）
B34: （3）资本性支出预测是否与预算、运营计划一致
L35: 资本性支出=资产性更新投资+新增长期资产投资（新增固定资产或其他长期资产）
B37: （4）折旧摊销费用预测是否合理
B40: （5）收益期（增长期及永续期）选择是否合理
L41: 在确定未来现金净流量的预测期时，应建立在经管理层批准的最近财务预算或预测数据基础上，原则上最多涵盖5年。
B43: （6）可比公司或可比交易的选择是否合理
B46: （7）折现率计算是否合理
L47: 对折现率预测时，是否与相应的宏观、行业、地域、特定市场、特定市场主体的风险因素相匹配，是否与未来现金净流量均一致采用税前口径。
B49: （8）终值的处理是否合理
B52: （9）对关键假设（如增长率、毛利率、折现率等）的敏感性分析结果
B58: 7、评价市场法选用的参数和具体处理
B59: （1）价值乘数的选择是否合理
B62: （2）可比公司或可比交易的选择是否与收益法中一致，是否合理
B65: （3）价值乘数的计算时间是否合理
B68: （4）对价值乘数的调整是否合理
B71: （5）对关键假设的敏感性分析结果
B74: 8、评价成本法选用的参数和具体处理
B75: （1）采用成本法是否恰当
B78: （2）重置成本的来源
B81: （3）评估对象的实体性贬值、功能性贬值及经济性贬值
... B88: （1）公允价值的确定是否合理
L89: 公司应恰当选用交易案例或估值技术确定商誉所在资产组或资产组组合的公允价值，合理分析并确定相关处置费用
B91: （2）处置费用的预测是否合理，是否有充分、适当的证据支持
L92: 处置费用是指可以直接归属于资产组处置的增量费用，包括与资产组处置有关的法律费用、相关税费、搬运费以及为使资产组达到可销售状态所发生的直接费用等。
B94: 10、最终选择评估方法的理由是否合理
B95: 应对专家工作过程及其所作的重要职业判断（尤其是数据引用、参数选取、假设认定等）进行复核，以判断专家工作的恰当性，不得直接将专家工作成果作为判断商誉是否减值的依据。
B97: 12、评价资产组的确定及商誉的分摊【涉及商誉减值测试时】
B98: （1）商誉所在资产组或资产组组合的划分是否合理
L99: 公司在认定资产组或资产组组合时，应充分考虑管理层对生产经营活动的管理或监控方式和对资产的持续使用或处置的决策方式，认定的资产组或资产组组合应能够独立产生现金流量。
B101: （2）将商誉分摊至相关的资产组的方法是否合理
L102: 公司应在充分考虑能够受益于企业合并的协同效应的资产组或资产组组合基础上，将商誉账面价值按各资产组或资产组组合的公允价值所占比例进行分摊。
B104: （3）资产组或资产组组合的可收回金额与其账面价值的确定基础是否一致
L105: 资产组或资产组组合的可收回金额与其账面价值的确定基础应保持一致，即二者应包括相同的资产和负债，且应按照与资产组或资产组组合内资产和负债一致的基础预测未来现金流量
B107: （4）是否将归属于少数股东的商誉调整计入相关资产组或资产组组合账面价值
L108: 公司在将商誉分摊至相关资产组或资产组组合时，应充分关注归属于少数股东的商誉，先将归属于母公司股东的商誉账面价值调整为全部商誉账面价值，再合理分摊至相关资产组或资产组组合
B110: （5）商誉所在资产组或资产组组合的构成发生改变时，是否重新对商誉账面价值进行合理分摊
L111: 因重组等原因，公司经营组成部分发生变化，继而影响到已分摊商誉所在的资产组或资产组组合构成的，应将商誉账面价值重新分摊至受影响的资产组或资产组组合，并充分披露相关理由及依据
B113: （6）商誉减值的分配是否合理
L114: 减值损失金额应当先抵减分摊至资产组或者资产组组合中商誉的账面价值，再根据资产组或者资产组组合中除商誉之外的其他各项资产的账面价值所占比重，按比例抵减其他各项资产的账面价值，并合理确定归属于母公司股东的商誉和归属于少数股东的商誉的减值金额。
B116: 13、评价管理层的专家的工作
B117: （1）是否分两步进行商誉减值测试【涉及商誉减值测试时】
B118: 如与商誉相关的资产组存在减值迹象的，首先对不包含商誉的资产组进行减值测试，计算可收回金额，并与相关账面价值相比较，确认相应的减值损失；然后再对包含商誉的资产组进行减值测试，比较这些相关资产组的账面价值（包括所分摊的商誉，减去了已经在上一步中确认的减值损失）与其可收回金额。
B120: （2）资产评估机构（若有）的报告是否考虑期后事项的影响
L121: 应关注评估基准日至评估报告日之间发生的与评估对象相关的重大期后事项，包括但不限于内外部环境的重大变化、重大诉讼与仲裁的最新进展等，并在评估报告中详细披露该事项及其对评估结论的影响。
B123: （3）与以前期间方法是否一致
L124: 后续期间商誉减值测试的评估方法应与以前期间的保持一致，除非有证据显示变更新的评估方法所得出的评估结论更具代表性，或原有的评估方法不再适用。若以前期间对商誉进行减值测试时，有关预测参数与期后实际情况存在重大偏差的，应充分关注管理层是否识别出导致偏差的主要因素，是否在本期商誉减值测试时充分考虑了相关因素的影响，并适当调整预测思路。
A126: 三、评价管理层或管理层的专家工作的结果或结论
B127: 评估结论基本合理； 【若认为管理层的专家的工作不能作为审计证据（如评估过程或结论不合理），则需考虑要求管理层重新评估或/并考虑对审计意见类型的影响。】
B129: 【专家工作总结或专家报告结论中要求明确对相关模型/方法的参数和假设合理性发表意见】

Sheet S12-3-3 利用专家评价管理层的工作(股份支付)
A1: 致同会计师事务所
A2: 利用专家评价管理层或管理层专家的工作的适当性
A3: ='S12 利用专家的工作程序表'!A3 -> 客户名称： | E3: ='S12 利用专家的工作程序表'!D3 -> 编制人： | H3: ='S12 利用专家的工作程序表'!G3 -> 日期： | J3: 索引号： | K3: S12-3-3
A4: ='S12 利用专家的工作程序表'!A4 -> 截止日：202X年12月31日 | E4: 复核人： | H4: 日期： | J4: 页 次：
A5: 一、利用注册会计师的专家的工作
B6: 序号 | C6: 项目 | I6: 索引号
B7: 1 | C7: 利用专家（注册会计师的专家）的工作 | I7: S12
A10: 二、评价管理层或管理层专家的工作过程及其结果或结论（主要适用于股份支付）
B11: 也可以取得专家（注册会计师的专家）的工作报告（S12-3-1），但专家评价的内容应完整。
B12: 1、估值方法是否与估值对象相匹配
B13: 对于股票期权，通常使用期权定价模型计算看涨期权的价值。 对于限制性股票，非市场可行权条件（服务条件、业绩条件等）不应在确定授予日公允价值时予以考虑，因此限制性股票的锁定因素并不影响其公允价值的确定。但解锁后，对于部分高管人员所持股份的限售条款则属于非可行权条件，可以在计量公允价值时予以考虑。
B15: 2、估值基准日是否符合经济行为需要
B16: 应评估权益工具授予日的公允价值。授予日，是指股份支付协议获得批准的日期，是企业和另一方（包括职工）同意一项以股份为基础的支付安排的日期，即企业和交易对方对安排的条款和条件有着共同理解的日期。
B18: 3、是否恰当划分为多个独立的期权估值
B19: 对于“一次授予、分期行权”的股份支付，其在授予日一次授予职工若干权益工具，之后每期分批达到可行权。每个批次是否可行权的结果通常是相对独立的，即每一期是否达到可行权条件并不会直接决定其他几期是否能够达到可行权条件，在会计处理时应将其作为几个独立的股份支付计划处理。即此时需要分别计算各个期权的公允价值。
B21: 4、评价期权定价模型选用的参数和具体处理
B22: （1）标的股份的现行价格是否合理
B23: 对于上市公司股份，应来自于授予日的收盘价（即期权对应标的股份在活跃市场中的报价）； 对于非上市股权（包括交易不活跃的新三板股票），应合理考虑入股时间阶段、业绩基础与变动预期、市场环境变化、行业特点及市盈率与市净率等因素的影响；可优先参考熟悉情况并按公平原则自愿交易的各方最近达成的入股价格或相似股权价格确定公允价值，如近期合理的PE入股价；也可采用恰当的估值技术确定公允价值，但要避免采取有争议的、结果显失公平的估值技术或公允价值确定方法，如明显增长预期下按照成本法评估的每股净资产价值或账面净资产。
B25: （2）期权的行权价格是否激励计划中的约定一致
B28: （3）期权有效期的确定是否合理
... B31: （4）股价预计波动率的计算是否合理
B32: 期权定价模型中所用的波动率的度量，是一段时间内股份的连续复利回报率的年度标准差。股价预计波动率通常根据与期权的预计期限（考虑期权剩余期限和预计提早行权的影响）大体相当的最近一个时期内企业股价的历史波动率计算。 如果企业因新近上市而没有历史波动率的充分信息，应按可获得交易活动数据的最长期间计算历史波动率，也可考虑类似企业在类似阶段可比期间的历史波动率。如果企业是非上市企业，在估计预计波动率时没有历史信息可循，可考虑类似上市企业股价的历史或内含波动率。 | L32: 历史波动率是为了模拟未来，若公司自身股票价格有较长的历史记录，且波动率变化不大，应使用自身波动率，而不是所属板块的波动率。
B34: （5）股份的预计股利率的计算是否合理
B35: 预计股利应以公开可获取的信息为基础。不支付股利且没有支付股利计划的企业应假设预计股利收益率为零。
B37: （6）期权有效期内的无风险利率的选择是否合理
B38: 无风险利率应当用无违约风险的固定证券收益来估计，例如与期权到期日相同的国债利率，如果没有相同期限的，可选择期间最接近的国债的利率。
B40: 5、限制性股票是否恰当考虑锁定因素的影响
B41: （1）锁定期限制的是否恰当处理
B42: 按照我国上市公司限制性股票股权激励的常见条款，锁定期实质上相当于等待期，解锁日为可行权日，解锁条件为非市场可行权条件（服务条件、业绩条件等）。根据股份支付准则，非市场可行权条件不应在确定授予日公允价值时予以考虑，因此限制性股票的锁定因素并不影响其公允价值的确定。 | L42: 限制性股票的单位成本＝限制性股票的公允价值－授予价格。对于非董事、高级管理人员的激励，限制性股票的公允价值＝授予日收盘价；对于董事、高级管理人员的激励，限制性股票的公允价值 = 授予日收盘价－限制性因素。
B44: （2）解锁后限售条款的是否恰当处理
B45: 解锁后，对于部分高管人员所持股份的限售条款则属于非可行权条件，可以在计量公允价值时予以考虑。
B47: 6、评价股份支付成本费用的分摊
B48: （1）是否恰当划分为多个独立的期权分摊费用
B49: 对于“一次授予、分期行权”的股份支付，每个批次是否可行权的结果通常是相对独立的，即每一期是否达到可行权条件并不会直接决定其他几期是否能够达到可行权条件，在会计处理时应将其作为几个独立的股份支付计划处理。相当于职工同时在为多个期权工作，各年费用递减。每年按当年等待时间长度占总等待期长度的比例分摊各期的成本费用。
B51: （2）是否恰当考虑可行权人数的变动
B52: 在各个资产负债表日，应根据最新取得的可行权人数变动、业绩指标完成情况等后续信息，修正预计可行权的股票期权数量，并以此为依据确认各期应分摊的费用。
B54: （3）等待期内费用分摊是否正确
B55: 等待期是指可行权条件得到满足的期间，对于可行权条件为规定服务期间的股份支付，等待期为授予日至可行权日的期间（假设服务从授予日开始）。
B57: 7、作废与主动取消的会计处理是否正确
B58: （1）被动作废的会计处理是否正确
B59: 如果权益工具由于一项服务条件或者非市场的业绩条件的结果未被授予，则对于接受的商品或服务累计确认的费用为零。
... B68: （2）与同行业惯例是否一致
A71: 三、评价管理层或管理层的专家工作的结果或结论
B72: 评估结论基本合理； 【若认为管理层的专家的工作不能作为审计证据（如评估过程或结论不合理），则需考虑要求管理层重新评估或/并考虑对审计意见类型的影响。】
B74: 【专家工作总结或专家报告结论中要求明确对相关模型/方法的参数和假设合理性发表意见】

Sheet S12-3-4 利用专家评价管理层的工作(金融工具公允价值）
A1: 致同会计师事务所
A2: 利用专家评价管理层或管理层专家的工作的适当性
A3: ='S12 利用专家的工作程序表'!A3 -> 客户名称： | E3: ='S12 利用专家的工作程序表'!D3 -> 编制人： | H3: ='S12 利用专家的工作程序表'!G3 -> 日期： | J3: 索引号： | K3: S12-3-4
A4: ='S12 利用专家的工作程序表'!A4 -> 截止日：202X年12月31日 | E4: 复核人： | H4: 日期： | J4: 页 次：
A5: 一、利用注册会计师的专家的工作
B6: 序号 | C6: 项目 | I6: 索引号
B7: 1 | C7: 利用专家（注册会计师的专家）的工作 | I7: S12
A10: 二、评价管理层或管理层专家的工作过程及其结果或结论（主要适用于金融工具公允价值）
B11: 也可以取得专家（注册会计师的专家）的工作报告（S12-3-1），但专家评价的内容应完整。
B12: 1、估值方法是否与估值对象相匹配
B15: 2、估值基准日是否符合经济行为需要
B16: 公允价值，是指市场参与者在计量日发生的有序交易中，出售一项资产所能收到或者转移一项负债所需支付的价格。
B18: 3、是否恰当考虑流动性折扣
B19: 根据《证券公司金融工具估值指引》（中证协发〔2018〕216号），通过公开、非公开等方式取得且有明确限售期的股票，在限售期内，应以证券交易所上市交易的同一股票的公允价值为基础，引入流动性折扣进行估值。流动性折扣可依据第三方估值机构提供的数据，或采用看跌期权法以及其他合理的估值方法分析确定。 | L19: 直线摊销（即根据《关于证券投资基金执行<企业会计准则>估值业务及份额净值计价有关事项的通知（证监会计字[2007]21号）》中的公式）已被《中国证监会关于证券投资基金估值业务的指导意见》（公告〔2017〕13号）废止。
B21: 4、评价期权定价模型选用的参数和具体处理
B22: （1）标的股份的现行价格是否合理
B23: 对于上市公司股份，应来自于授予日的收盘价（即期权对应标的股份在活跃市场中的报价）； 对于非上市股权（包括交易不活跃的新三板股票），应合理考虑入股时间阶段、业绩基础与变动预期、市场环境变化、行业特点及市盈率与市净率等因素的影响；可优先参考熟悉情况并按公平原则自愿交易的各方最近达成的入股价格或相似股权价格确定公允价值，如近期合理的PE入股价；也可采用恰当的估值技术确定公允价值，但要避免采取有争议的、结果显失公平的估值技术或公允价值确定方法，如明显增长预期下按照成本法评估的每股净资产价值或账面净资产。 | L23: 看跌期权价值的估算根据《证券投资基金投资流通受限股票估值指引（试行）》（中基协发〔2017〕6号），可以使用平均价格亚式期权模型（“AAP模型”）。
B25: （2）期权的行权价格是否恰当选择
B28: （3）期权有效期的确定是否合理
B31: （4）股价预计波动率的计算是否合理
B32: 期权定价模型中所用的波动率的度量，是一段时间内股份的连续复利回报率的年度标准差。股价预计波动率通常根据与期权的预计期限（考虑期权剩余期限和预计提早行权的影响）大体相当的最近一个时期内企业股价的历史波动率计算。 如果企业因新近上市而没有历史波动率的充分信息，应按可获得交易活动数据的最长期间计算历史波动率，也可考虑类似企业在类似阶段可比期间的历史波动率。如果企业是非上市企业，在估计预计波动率时没有历史信息可循，可考虑类似上市企业股价的历史或内含波动率。 | L32: 历史波动率是为了模拟未来，若公司自身股票价格有较长的历史记录，且波动率变化不大，应使用自身波动率，而不是所属板块的波动率。
B34: （5）股份的预计股利率的计算是否合理
B35: 预计股利应以公开可获取的信息为基础。不支付股利且没有支付股利计划的企业应假设预计股利收益率为零。
B37: （6）期权有效期内的无风险利率的选择是否合理
B38: 无风险利率应当用无违约风险的固定证券收益来估计，例如与期权到期日相同的国债利率，如果没有相同期限的，可选择期间最接近的国债的利率。
B40: 5、评价收益法选用的参数和具体处理
B41: （1）未来现金流是否与对本金和利息的预期一致，或盈利预测是否有可靠的数据来源，是否与历史数据、运营计划、商业机会、行业数据、行业研究报告、宏观经济运行状况相符
L42: 对未来现金净流量预测时，应以资产的当前状况为基础，以税前口径为预测依据，并充分关注选取的关键参数（包括但不限于销量、价格、成本、费用、预测期增长率、稳定期增长率）是否有可靠的数据来源，是否与历史数据、运营计划、商业机会、行业数据、行业研究报告、宏观经济运行状况相符；与此相关的重大假设是否与可获取的内部、外部信息相符，在不符时是否有合理理由支持。
B44: （2）对于营运资金的口径判断是否与非经营性资产负债一致（若适用）
B47: （3）资本性支出预测是否与预算、运营计划一致（若适用）
B50: （4）折旧摊销费用预测是否合理（若适用）
B53: （5）收益期（增长期及永续期）选择是否合理（若适用）
L54: 在确定未来现金净流量的预测期时，应建立在经管理层批准的最近财务预算或预测数据基础上，原则上最多涵盖5年。
B56: （6）可比公司或可比交易的选择是否合理
B59: （7）市场收益率/折现率计算是否合理
L60: 对折现率预测时，是否与相应的宏观、行业、地域、特定市场、特定市场主体的风险因素相匹配，是否与未来现金净流量均一致采用税前口径。
B62: （8）终值的处理是否合理
B65: （9）是否恰当考虑持股情况、流动性折扣等因素
B68: （10）对关键假设（如增长率、毛利率、折现率等）的敏感性分析结果
B71: 6、评价市场法选用的参数和具体处理
B72: （1）价值乘数的选择是否合理
B75: （2）可比公司或可比交易的选择是否与收益法中一致，是否合理
L76: 采用最近融资价格法评估非上市公司股权公允价值时，需充分考虑时间因素。 如果被投资单位近期进行过新一轮融资的，可以最近融资价格作为非上市公司股权估值。
B78: （3）价值乘数的计算时间是否合理
B81: （4）对价值乘数的调整是否合理
B84: （5）对关键假设的敏感性分析结果
B87: 7、评价成本法选用的参数和具体处理
B88: （1）采用成本法是否恰当
B89: 重置成本法适用于企业价值主要来源于其资产的公允价值的情形。
B91: （2）重置成本的来源
B94: （3）评估对象的实体性贬值、功能性贬值及经济性贬值
B97: （4）对关键假设的敏感性分析结果
B100: 8、停牌股票公允价值的确定是否合理
B101: 长期停牌股票应根据停牌原因、停牌时间及停牌公司公告等信息，采用市场法、收益法、成本法等估值技术确定公允价值，具体估值方法包括指数收益法、可比公司法、市场价格模型法、现金流折现法、市场乘数法、重置成本法等。
B103: 9、评价管理层的专家的工作
B104: （1）与以前期间方法是否一致
A107: 三、评价管理层或管理层的专家工作的结果或结论
B108: 评估结论基本合理； 【若认为管理层的专家的工作不能作为审计证据（如评估过程或结论不合理），则需考虑要求管理层重新评估或/并考虑对审计意见类型的影响。】
B110: 【专家工作总结或专家报告结论中要求明确对相关模型/方法的参数和假设合理性发表意见】
