Workbook
Name _1、: #REF!
Name _1、: #REF!
Name _1、: #REF!
Name _1、: #REF!
Name _1、: #REF!
Name _1、: #REF!
Name _1、: #REF!
Name _1、受本循环影响的相关交易和账户余额: #REF!
Name _1、受本循环影响的相关交易和账户余额: #REF!
Name _1、受本循环影响的相关交易和账户余额: #REF!
Name _1、受本循环影响的相关交易和账户余额: #REF!
Name _1、受本循环影响的相关交易和账户余额: #REF!
Name _1、受本循环影响的相关交易和账户余额: #REF!
Name _1、受本循环影响的相关交易和账户余额: #REF!
Name _2、主要业务活动: #REF!
Name _2、主要业务活动: #REF!
Name _2、主要业务活动: #REF!
Name _2、主要业务活动: #REF!
Name _2、主要业务活动: #REF!
Name _2、主要业务活动: #REF!
Name _2、主要业务活动: #REF!
Name _2、注册会计师通常应在本循环中了解与上述业务活动相关的内部控制_如果计划在其他业务循环中对上述: #REF!
Name _2、注册会计师通常应在本循环中了解与上述业务活动相关的内部控制_如果计划在其他业务循环中对上述: #REF!
Name _2、注册会计师通常应在本循环中了解与上述业务活动相关的内部控制_如果计划在其他业务循环中对上述: #REF!
Name _2、注册会计师通常应在本循环中了解与上述业务活动相关的内部控制_如果计划在其他业务循环中对上述: #REF!
Name _2、注册会计师通常应在本循环中了解与上述业务活动相关的内部控制_如果计划在其他业务循环中对上述: #REF!
Name _2、注册会计师通常应在本循环中了解与上述业务活动相关的内部控制_如果计划在其他业务循环中对上述: #REF!
Name _2、注册会计师通常应在本循环中了解与上述业务活动相关的内部控制_如果计划在其他业务循环中对上述: #REF!
Name _DAT1: #REF!
Name _DAT1: #REF!
Name _DAT1: #REF!
Name _DAT1: #REF!
Name _DAT1: #REF!
Name _DAT1: #REF!
Name _DAT1: #REF!
Name _DAT10: #REF!
Name _DAT10: #REF!
Name _DAT10: #REF!
Name _DAT10: #REF!
Name _DAT10: #REF!
Name _DAT10: #REF!
Name _DAT10: #REF!
Name _DAT11: #REF!
Name _DAT11: #REF!
Name _DAT11: #REF!
Name _DAT11: #REF!
Name _DAT11: #REF!
Name _DAT11: #REF!
Name _DAT11: #REF!
Name _DAT2: #REF!
Name _DAT2: #REF!
Name _DAT2: #REF!
Name _DAT2: #REF!
Name _DAT2: #REF!
Name _DAT2: #REF!
Name _DAT2: #REF!
Name _DAT3: #REF!
Name _DAT3: #REF!
Name _DAT3: #REF!
Name _DAT3: #REF!

Sheet 表头（请先填写）
A1: 底稿开列时，可先在以下单元格填写有关内容，以便其他底稿引用有关数据：
A2: 客户名称： | D2: 序号 | E2: 内 容
A3: 会计期间：2023年度 | D3: 1 | E3: 表头（请先填写）
A4: 编制人： | D4: 2 | E4: 审定表
A5: 日期： | D5: 3 | E5: 会计政策变更和前期差错更正S2-1
D6: 4 | E6: 会计估计变更审计程序S2-2
D7: 5 | E7: 首次执行新金融工具准则的调整S-4
D8: 6 | E8: 首次执行新收入准则的调整S-6
A9: 关于工作底稿索引号的编制方法的说明 | D9: 7 | E9: 首次执行新租赁准则的调整S-8
A10: 1、 工作底稿的分类 | D10: 8 | E10: 简化的追溯调整法（1）S3-9
D11: 9 | E11: 简化的追溯调整法（2）S3-10
A12: 作为具体审计程序的支持性工作底稿，共有三类，分别为审定表，明细表，检查表。 | D12: 10 | E12: 参考-简化的追溯调整法（首次执行日） | F12: 按月份计算
A13: 2、 工作底稿与审计程序的对应与索引
A14: 为提高工作底稿编制的针对性，各项目负责人提供的所有支持性工作底稿，均应当
A15: 按自然顺序依次编制索引号，并通过唯一的索引号将审计程序表中的特定程序与相关
A16: 支持性工作底稿进行一一对应。
A17: 3、 工作底稿索引号的编码规则（以销售循环为例，假设D为项目名称代码）
A18: 索引号的说明：实质性程序索引号从“D”到“N”,循环内账户以顺序号排列，如：销售循环的程序表即为D，D1为应收票据审定表，D1-1为附注披露信息，D1-2为明细表........

Sheet 审定表
A1: 致同会计师事务所
A2: 审定表
A3: ='表头（请先填写）'!A2 -> 客户名称： | B3: ='表头（请先填写）'!A4 -> 编制人： | D3: ='表头（请先填写）'!A5 -> 日期： | F3: 索引号： | G3: S3-1
A4: ='表头（请先填写）'!A3 -> 会计期间：2023年度 | B4: 复核人： | D4: 日期： | F4: 页 次： | G4: 1
A6: 1、重大事项说明
A11: 2、审计结论
A16: 3、披露内容

Sheet 会计政策变更和前期差错更正S3-1
A1: 致同会计师事务所
A2: 会计政策变更和前期差错更正
A3: ='表头（请先填写）'!A2 -> 客户名称： | B3: ='表头（请先填写）'!A4 -> 编制人： | C3: ='表头（请先填写）'!A5 -> 日期： | D3: 索引号： | E3: S3-1
A4: ='表头（请先填写）'!A3 -> 会计期间：2023年度 | B4: 复核人： | C4: 日期： | D4: 页 次： | E4: 1
A5: 一、审计目标
A6: 1、确定会计政策变更是否合法、合理；确定前期差错更正是否合理；
A7: 2、确定会计政策变更和前期差错更正的会计处理是否正确；
A8: 3、确定会计政策变更和前期差错更正的披露是否恰当。
A10: 二、审计程序 | D10: 执行人 | E10: 索引号
A11: 1．获取被审计单位提供的会计政策说明，与前期采用的会计政策进行比较，以识别会计政策的变更。
A12: 2．查阅法规或会计准则等行政法规、规章以及被审计单位董事会、管理当局有关会议记录，根据会计准则规定和被审计单位实际情况，判断会计政策变更的合法性和合理性，会计处理的正确性。
A13: 2.1检查是否对相同或者相似的交易或者事项采用相同的会计政策进行处理。但是，其他会计准则另有规定的除外。
A14: 2.2 被审计单位采用的会计政策，在每一会计期间和前后各期应当保持一致，不得随意变更。但是，满足下列条件之一的，可以变更会计政策：法律、行政法规或者国家统一的会计制度等要求变更。会计政策变更能够提供更可靠、更相关的会计信息。
A15: 2.3如果根据法律、行政法规或者国家统一的会计制度等要求变更会计政策的，检查是否按照国家相关会计规定执行。
A16: 2.4重点关注被审计单位首次执行《企业会计准则》（2006）的有关会计政策变更的会计处理，首次执行企业会计准则对会计要素的确认、计量和财务报表列报，检查是否根据《企业会计准则第38号——首次执行企业会计准则》的规定办理；首次执行企业会计准则后发生的会计政策变更，检查是否适用《企业会计准则第28 号——会计政策、会计估计变更和差错更正》的规定办理。
A17: 2.5会计政策变更能够提供更可靠、更相关的会计信息的，检查是否采用追溯调整法处理，将会计政策变更累积影响数调整列报前期最早期初留存收益，其他相关项目的期初余额和列报前期披露的其他比较数据也应当一并调整，但确定该项会计政策变更累积影响数不切实可行的除外。
A18: 3．获取并审查前期差错更正相关的资料，根据会计准则规定和被审计单位实际情况，判断前期差错更正合理性，会计处理的正确性。
A19: 3.1检查被审计单位是否采用追溯重述法更正重要的前期差错，但确定前期差错累积影响数不切实可行的除外。
A20: 3.2 确定前期差错影响数不切实可行的，可以从可追溯重述的最早期间开始调整留存收益的期初余额，财务报表其他相关项目的期初余额也应当一并调整，也可以采用未来适用法。
A21: 3.3 检查被审计单位是否在重要的前期差错发现当期的财务报表中，调整前期比较数据。
A22: 4．审查与会计政策变更和前期差错更正相关的会计记录，确定其会计处理是否正确。
... A25: 7．验明会计政策变更和前期差错更正的披露是否恰当。

Sheet 会计估计变更审计程序S3-2
A1: 致同会计师事务所
A2: 会计估计变更
A3: ='表头（请先填写）'!A2 -> 客户名称： | B3: ='表头（请先填写）'!A4 -> 编制人： | C3: ='表头（请先填写）'!A5 -> 日期： | D3: 索引号： | E3: S3-2
A4: ='表头（请先填写）'!A3 -> 会计期间：2023年度 | B4: 复核人 | C4: 日期： | D4: 页 次： | E4: 1
A5: 一、审计目标
A6: 1．确定会计估计是否合理；
A7: 2. 确定会计估计变更是否合理、合法；
A8: 3．确定会计估计变更的会计处理是否正确；
A9: 4. 确定会计估计及其变更的披露是否恰当。
A11: 二、审计程序 | D11: 执行人 | E11: 索引号
A12: 1.向被审计单位管理当局了解其作出会计估计的程序、方法和相关内部控制。
A13: 2.获取被审计单位提供的会计估计说明，并复核和测试被审计单位作出会计估计的过程：
A14: 2.1评价会计估计依据的数据的准确性、完整性和相关性、假设的合理性和使用的公式的正确性；当会计估计依据的数据是会计数据时，应判断其是否与会计系统的相关数据一致，必要时，可以考虑从被审计单位外部获取审计证据；
A15: 2.2测试会计估计的计算过程；
A16: 2.3如有可能，将以前期间作出的会计估计与其实际结果进行比较；
A17: 2.4考虑被审计单位管理当局对会计估计的批准程序。
A18: 3.利用独立估计与被审计单位作出的会计估计进行比较，如存在明显差异应查明原因，分析判断该差异是否合理,如果该项差异不合理，应当予以调整。
A19: 4.复核能够证实会计估计的资产负债表日后事项。
A20: 5.获取并审查与会计估计变更的相关资料, 根据会计准则规定和被审计单位实际情况，审查与会计估计变更相关的会计记录，确定其会计处理是否正确，判断会计估计变更的合法性和合理性：
A21: 5.1检查是否在被审计单位据以进行估计的基础发生了变化，或者由于取得新信息、积累更多经验以及后来的发展变化，需要对会计估计进行修订。会计估计变更的依据应当真实、可靠。
A22: 5.2被审计单位对会计估计变更应当采用未来适用法处理。
A23: 5.3难以对某项变更区分为会计政策变更或会计估计变更的，检查是否将其作为会计估计变更处理。
... A26: 8.验明会计估计及其变更的披露是否恰当。

Sheet 首次执行新金融工具准则的调整S3-4
A1: 致同会计师事务所
A2: 首次执行新金融工具准则的调整
A3: =审定表!A3 -> 客户名称： | E3: ='表头（请先填写）'!A4 -> 编制人： | G3: ='表头（请先填写）'!A5 -> 日期： | I3: 索引：S3-4
A4: =审定表!A4 -> 会计期间：2023年度 | E4: 复核人： | G4: 日期： | I4: 页次：
A5: 一、审计目标： | J5: 在境内外同时上市的企业以及在境外上市并采用国际财务报告准则或企业会计准则编制财务报告的企业，自2018年1月1日起施行；
A6: 确定首次执行日的调整。 | J6: 其他境内上市企业自2019年1月1日起施行；
A7: 二、审计过程： | J7: 执行企业会计准则的非上市企业自2021年1月1日起施行。
A8: 1. 首次执行日重分类及调整
A9: 原核算科目与列报项目 | B9: 新准则核算项目 | C9: 准则依据及转换要求 | F9: 重分类分录 | G9: 金额 | H9: 调整分录 | I9: 金额
A10: 以公允价值计量且其变动计入当期损益的金融资产 | B10: 交易性金融资产 | C10: 《关于修订印发2019年度一般企业财务报表格式的通知》（财会〔2019〕6号）： “交易性金融资产”项目，反映资产负债表日企业分类为以公允价值计量且其变动计入当期损益的金融资产，以及企业持有的指定为以公允价值计量且其变动计入当期损益的金融资产的期末账面价值。 | F10: 借：交易性金融资产--成本
F11: 借：交易性金融资产--公允价值变动
F12: 贷：以公允价值计量且其变动计入当期损益的金融资产--成本
F13: 贷：以公允价值计量且其变动计入当期损益的金融资产--公允价值变动
A14: 其他流动资产 其他非流动资产 | B14: 交易性金融资产 其他非流动金融资产 | C14: 按照本准则第十七条分类为以摊余成本计量的金融资产和按照本准则第十八条分类为以公允价值计量且其变动计入其他综合收益的金融资产之外的金融资产，企业应当将其分类为以公允价值计量且其变动计入当期损益的金融资产。 通不过SPPI测试的理财产品投资或结构性存款，重分类为交易性金融资产/其他非流动金融资产 | F14: 借：交易性金融资产--成本
F15: 借：交易性金融资产--公允价值变动
F16: 贷：其他流动资产
F17: 借：其他非流动金融资产--成本
F18: 借：其他非流动金融资产--公允价值变动
F19: 贷：其他非流动资产
A21: 可供出售金融资产 | B21: 交易性金融资产 其他非流动金融资产 | C21: 通不过SPPI测试的可供出售金融资产、长期应收款，重分类为交易性金融资产/其他非流动金融资产 | F21: 借：交易性金融资产--成本 | H21: 借：交易性金融资产--成本
F22: 借：交易性金融资产--公允价值变动 | H22: 借：交易性金融资产--公允价值变动
F23: 贷：可供出售金融资产--成本 | H23: 贷：可供出售金融资产--成本
F24: 贷：可供出售金融资产--公允价值变动 | H24: 贷：盈余公积 | J24: 【原账面价值与公允价值之差×10%】
F25: 借：其他非流动金融资产--成本 | H25: 贷：利润分配——未分配利润 | J25: 【原账面价值与公允价值之差×90%】
F26: 借：其他非流动金融资产--公允价值变动 | H26: 借：盈余公积
F27: 贷：可供出售金融资产--成本 | H27: 借：利润分配——未分配利润
F28: 贷：可供出售金融资产--公允价值变动 | H28: 贷：递延所得税负债 | J28: 确认递延所得税影响
A29: 可供出售金融资产 | B29: 其他权益工具投资 | C29: 原以成本法计量的可供出售权益工具，满足条件时指定为其他权益工具投资 | H29: 借：其他权益工具投资
H30: 贷：可供出售金融资产——成本
H31: 贷：其他综合收益 | J31: 【原账面价值与公允价值之差】
H32: 借：其他综合收益
H33: 贷：递延所得税负债 | J33: 确认递延所得税影响
H35: 借：其他综合收益
H36: 贷：盈余公积 | J36: 【原计提的减值（若有）×10%】
H37: 贷：利润分配——未分配利润 | J37: 【原计提的减值（若有）×90%】
A38: 坏账准备 | B38: 坏账准备 | C38: 应收账款按预期信用损失法补提坏账准备（若涉及） | H38: 借：盈余公积 | J38: 【补提部分×10%】
H39: 借：利润分配——未分配利润 | J39: 【补提部分×90%】
H40: 贷：坏账准备
H41: 借：递延所得税资产 | J41: 确认递延所得税影响
H42: 贷：盈余公积
H43: 贷：利润分配——未分配利润
A44: 应收票据 应收账款 | B44: 应收款项融资 | C44: “应收款项融资”项目，反映资产负债表日以公允价值计量且其变动计入其他综合收益的应收票据和应收账款等。 | F44: 借：应收款项融资 | H44: 借：盈余公积 | J44: 【补提部分×10%】
F45: 借：其他综合收益——其他债权投资公允价值变动 | H45: 借：利润分配——未分配利润 | J45: 【补提部分×90%】
F46: 贷：应收票据 | H46: 贷：其他综合收益——信用减值准备
F47: 借：递延所得税资产 | H47: 借：递延所得税资产 | J47: 确认递延所得税影响
F48: 贷：其他综合收益 | H48: 贷：盈余公积
H49: 贷：利润分配——未分配利润
A50: 长期应收款 持有至到期投资 其他非流动资产 | B50: 债权投资 | C50: 持有至到期投资中能通过SPPI测试，且业务模式是以收取合同现金流量为目标的，应当分类为以摊余成本计量的金融资产。 “1501债权投资”。本科目核算企业以摊余成本计量的债权投资的账面余额。本科目可按债权投资的类别和品种，分别“面值”“利息调整”“应计利息”等进行明细核算。 | F50: 借：债权投资--成本 | H50: 借：盈余公积 | J50: 【补提部分×10%】
F51: 借：债权投资--应计利息 | H51: 借：利润分配——未分配利润 | J51: 【补提部分×90%】
F52: 贷：持有至到期投资--成本 | H52: 贷：债权投资减值准备
F53: 贷：持有至到期投资--应计利息 | H53: 借：递延所得税资产 | J53: 确认递延所得税影响
H54: 贷：盈余公积
H55: 贷：利润分配——未分配利润
A56: 长期应收款 持有至到期投资 可供出售金融资产 其他非流动资产 | B56: 其他债权投资 | C56: 可供出售债务工具中能通过SPPI测试，且业务模式既以收取合同现金流量为目标又以出售该金融资产为目标的，应当分类为以公允价值计量且其变动计入其他综合收益的金融资产。 “1503其他债权投资”。本科目核算企业按照本准则第十八条分类为以公允价值计量且其变动计入其他综合收益的金融资产。本科目可按金融资产类别和品种，分别“成本”“利息调整”“公允价值变动”等进行明细核算。 | F56: 借：其他债权投资--成本 | H56: 借：盈余公积 | J56: 【补提部分×10%】
F57: 借：其他债权投资--公允价值变动 | H57: 借：利润分配——未分配利润 | J57: 【补提部分×90%】
F58: 贷：可供出售金融资产--利息调整 | H58: 贷：其他综合收益——信用减值准备
F59: 贷：可供出售金融资产--成本 | H59: 借：递延所得税资产 | J59: 确认递延所得税影响
F60: 贷：可供出售金融资产--公允价值变动 | H60: 贷：盈余公积
F61: 贷：其他债权投资--利息调整 | H61: 贷：利润分配——未分配利润
A62: 以公允价值计量且其变动计入当期损益的金融负债 | B62: 交易性金融负债 | C62: “交易性金融负债”项目，反映资产负债表日企业承担的交易性金融负债，以及企业持有的指定为以公允价值计量且其变动计入当期损益的金融负债的期末账面价值。 | F62: 借：以公允价值计量且其变动计入当期损益的金融负债--成本
F63: 借：以公允价值计量且其变动计入当期损益的金融负债--公允价值变动
F64: 贷：交易性金融负债--成本
F65: 贷：交易性金融负债--公允价值变动
A66: 应收利息 | B66: 相关项目本金 应收利息 | C66: 《关于修订印发2019年度一般企业财务报表格式的通知》（财会〔2019〕6号）： “应收利息”仅反映相关金融工具已到期可收取但于资产负债表日尚未收到的利息。基于实际利率法计提的金融工具的利息应包含在相应金融工具的账面余额中。 | F66: 借：银行存款——应计利息
F67: 贷：其他应收款——应收利息
F68: 借：一年内到期的非流动资产 | J68: 【分期收息的委托贷款、长期债权投资应计利息】
F69: 贷：其他应收款——应收利息
A70: 应付利息 | B70: 相关项目本金 应付利息 | C70: 《关于修订印发2019年度一般企业财务报表格式的通知》（财会〔2019〕6号）： “应付利息”仅反映相关金融工具已到期应支付但于资产负债表日尚未支付的利息。基于实际利率法计提的金融工具的利息应包含在相应金融工具的账面余额中。 | F70: 借：其他应付款——应付利息
F71: 贷：短期借款
F72: 借：其他应付款——应付利息
F73: 贷：一年内到期的非流动负债——长期借款应计利息 | J73: 【分期付息的长期借款应计利息】
A76: 2. 于首次执行日，按照原金融工具准则和新金融工具准则的规定进行分类和计量的结果对比
A77: 原金融工具准则 | G77: 新金融工具准则
A78: 项 目 | C78: 类别 | F78: 账面价值 | G78: 项 目 | H78: 类别 | I78: 账面价值
A79: 以公允价值计量且其变动计入当期损益的金融资产 | C79: 以公允价值计量且其变动计入当期损益 | G79: 交易性金融资产 | H79: 以公允价值计量且其变动计入当期损益
G80: 衍生金融资产 | H80: 以公允价值计量且其变动计入当期损益
A81: 可供出售金融资产 | C81: 以公允价值计量且其变动计入其他综合收益（债务工具） | G81: 其他非流动金融资产 | H81: 以公允价值计量且其变动计入当期损益
C82: 以公允价值计量且其变动计入其他综合收益（权益工具） | G82: 交易性金融资产 | H82: 以公允价值计量且其变动计入当期损益
G83: 其他权益工具投资 | H83: 以公允价值计量且其变动计入其他综合收益
C84: 以成本计量（权益工具） | G84: 其他非流动金融资产 | H84: 以公允价值计量且其变动计入当期损益
G85: 其他权益工具投资 | H85: 以公允价值计量且其变动计入其他综合收益
A86: 应收票据 | C86: 摊余成本 | G86: 应收票据 | H86: 摊余成本
G87: 应收款项融资 | H87: 以公允价值计量且其变动计入其他综合收益
A88: 应收账款 | C88: 摊余成本 | G88: 应收账款 | H88: 摊余成本
G89: 应收款项融资 | H89: 以公允价值计量且其变动计入其他综合收益
A90: 其他应收款 | C90: 摊余成本 | G90: 其他应收款 | H90: 摊余成本
G91: 其他流动资产 | H91: 摊余成本
A92: 长期应收款 | C92: 摊余成本 | G92: 长期应收款 | H92: 摊余成本
G93: 其他非流动金融资产 | H93: 以公允价值计量且其变动计入当期损益
G94: 债权投资 | H94: 摊余成本
A95: 应收利息 | C95: 摊余成本 | G95: 银行存款 | H95: 摊余成本
A96: 应付利息 | C96: 摊余成本 | G96: 短期借款 | H96: 摊余成本
G97: 一年内到期的非流动负债 | H97: 摊余成本 | J97: 如分期付息的长期借款计提的利息
A101: 3. 于首次执行日（2021年1月1日），执行新金融工具准则时金融工具分类和账面价值调节
A102: 项 目 | C102: 注 | D102: 调整前账面金额 （2020年12月31日） | F102: 重分类 | G102: 重新计量 | H102: 调整后账面金额 （2021年1月1日） | I102: 备注
A103: 资产：
A104: 货币资金
A105: 以公允价值计量且其变动计入当期损益的金融资产 | G105: — | H105: —
A106: 交易性金融资产 | D106: —
A107: 应收票据
...

Sheet 首次执行新收入准则的调整S3-6
A1: 致同会计师事务所
A2: 首次执行新收入准则的调整
A3: =审定表!A3 -> 客户名称： | E3: ='表头（请先填写）'!A4 -> 编制人： | G3: ='表头（请先填写）'!A5 -> 日期： | I3: 索引：S3-6
A4: =审定表!A4 -> 会计期间：2023年度 | E4: 复核人： | G4: 日期： | I4: 页次：
A5: 一、审计目标： | J5: 在境内外同时上市的企业以及在境外上市并采用国际财务报告准则或企业会计准则编制财务报表的企业，自2018年1月1日起施行；
A6: 确定首次执行日的调整。 | J6: 其他境内上市企业，自2020年1月1日起施行；
A7: 二、审计过程： | J7: 执行企业会计准则的非上市企业，自2021年1月1日起施行。
A8: 1. 首次执行日重分类及调整
A9: 原核算科目与列报项目 | B9: 新准则核算项目 | C9: 准则依据及转换要求 | F9: 重分类分录 | G9: 金额 | H9: 调整分录 | I9: 金额
A10: 应收账款 其他应收款 长期应收款 存货 | B10: 合同资产 | C10: 资产负债表日“合同结算”科目的期末余额在借方的[收入结转（业务收入）>价款结算]，根据其流动性，在资产负债表中分别列示为“合同资产”或“其他非流动资产”项目；工程质保金，需等到客户于保质期结束且未发生重大质量问题后方能收款，应当在资产负债表中作为合同资产列示。 | F10: 借：合同资产 | H10: 借：盈余公积
F11: 借：其他非流动资产 | H11: 借：利润分配——未分配利润 | J11: 同一合同下的合同资产和合同负债应当以净额列示，不同合同下的合同资产和合同负债不能互相抵销。
F12: 贷：应收账款 | H12: 贷：合同资产减值准备
F13: 贷：存货
F14: 贷：其他应收款
A15: 预收账款 递延收益 其他应付款 其他流动负债 | B15: 合同负债 | C15: 合同负债，是指企业已收或应收客户对价而应向客户转让商品的义务。如企业在转让承诺的商品之前已收取的款项。 企业因转让商品收到的预收款适用本准则进行会计处理时，不再使用“预收账款”科目及“递延收益”科目。 | F15: 借：预收账款
F16: 借：递延收益
F17: 贷：合同负债
F18: 贷：其他非流动负债
F19: 贷：应交税费——待转销项税额 | J19: 合同负债不含税。《收入准则应用案例——合同负债（涉及不同增值税率的储值卡）》
A20: 无形资产 长期待摊费用 | B20: 合同履约成本、合同取得成本 | C20: 确认为资产的合同履约成本，初始确认时摊销期限不超过一年或一个正常营业周期的，在资产负债表中计入“存货”项目；初始确认时摊销期限在一年或一个正常营业周期以上的，在资产负债表中计入“其他非流动资产”项目。 确认为资产的合同取得成本，初始确认时摊销期限不超过一年或一个正常营业周期的，在资产负债表中计入“其他流动资产”项目；初始确认时摊销期限在一年或一个正常营业周期以上的，在资产负债表中计入“其他非流动资产”项目。 | F20: 借：存货
F21: 借：其他非流动资产
F22: 贷：长期待摊费用
F23: 借：其他流动资产
F24: 借：其他非流动资产
F25: 贷：长期待摊费用
A26: 合同预计损失准备 | B26: 预计负债 | C26: 根据《企业会计准则第13号——或有事项》的相关规定，待执行合同变成亏损合同的，该亏损合同产生的义务满足相关条件的，则应当对亏损合同确认预计负债。 | F26: 借：存货跌价准备—合同预计损失准备 | J26: 《收入准则应用案例——亏损合同案例》
F27: 贷：预计负债
A28: 注：资产负债表日“合同结算”科目的期末余额在借方的，根据其流动性，在资产负债表中分别列示为“合同资产”或“其他非流动资产”项目；
A29: 期末余额在贷方的，根据其流动性，在资产负债表中分别列示为“合同负债”或“其他非流动负债”项目。
A31: 2.尚未完成的合同 | E31: 是否适用 | F31: 是
A32: 合同项目及编号 | B32: 合同履行情况说明 | F32: 是否尚未完成 | G32: 审计证据及说明 | I32: 索引
F33: 是 | J33: 已完成的合同，是指企业按照与收入相关会计准则制度的原规定已完成合同中全部商品的转让的合同。尚未完成的合同，是指除已完成的合同之外的其他合同。
F34: 是
A35: 商品销售合同【合同编号：XXX】 | B35: 于2019年12月31日向客户销售商品，并立即交付。要求该客户预付一半的对价，另外一半在60天内付款。由于客户历史信用记录较差，公司认为“相关的经济利益很可能流入企业”的条件不满足，因此未确认销售收入。 | F35: 否 | G35: 因为商品在首次执行日（2020年1月1日）前交付，所以在新收入准则下该合同视为已完成。
A36: 注：可以仅对在首次执行日尚未完成的合同的累积影响数进行调整。
A38: 3.尚未完成的合同的累积影响数
A39: 3.1 重新认定单项履约义务 | J39: 累积影响数的来源：
A40: 合同项目及编号 | B40: 原处理方式 | E40: 新准则下会计处理 | G40: 审计证据及说明 | I40: 索引 | J40: 新收入准则下识别的履约义务，与原准则下识别的要素/交付物可能不同；
J41: 新收入准则下按单独售价相对比例分配交易价格，可能与以往分配的金额不同； 新收入准则下对在某一时段内履行的履约义务的判断与原准则下可能不同；
A42: 汽车保养服务 | B42: 销售汽车时一次性确认收入 | E42: 将为客户提供的保养服务识别为影响单项履约义务 | J42: 新收入准则下对主要责任人与代理人的判断与原准则下可能不同； 新收入准则下对可变对价的处理与原准则下可能不同……
A43: 工程总承包(EPC)合同 | B43: 以每个单独签署的合同为基础分别确认相关收入 | E43: 存在重大整合，将该等合同合并为一份合同并在履行单项履约义务时确认收入 | J43: 通常“设计”、“采购”、“施工”存在重大整合（尤其是非标准化的项目）。因此，设计通常不可单独区分。但是对于比较成熟的设计方案，可能“设计”可单独区分，从而“设计”与“采购及施工”会成为两项单独的履约义务。
A45: 3.2 收入确认时点或时段变化
A46: 合同项目及编号 | B46: 原处理方式 | E46: 新准则下会计处理 | G46: 审计证据及说明 | I46: 索引
A49: 勘察设计服务合同 | B49: 按照完工百分比法确认提供劳务收入 | E49: 在客户取得相关商品或服务控制权时点确认收入
A51: 3.3 应付客户对价冲减交易价格
A52: 合同项目及编号 | B52: 原处理方式 | E52: 新准则下会计处理 | G52: 审计证据及说明 | I52: 索引
A55: 现金折扣 | B55: 计入财务费用 | E55: 抵减营业收入 | J55: 合同中存在可变对价的，企业应当按照期望值或最可能发生金额确定可变对价的最佳估计数，但包含可变对价的交易价格，应当不超过在相关不确定性消除时累计已确认收入极可能不会发生重大转回的金额。
A56: 支付给经销商的市场助销投入 | B56: 计入销售费用 | E56: 抵减营业收入 | J56: 企业应付客户（或向客户购买本企业商品的第三方，本条下同）对价的，应当将该应付对价冲减交易价格，并在确认相关收入与支付（或承诺支付）客户对价二者孰晚的时点冲减当期收入，但应付客户对价是为了向客户取得其他可明确区分商品的除外。
A58: 3.4 各单项履约义务分摊的交易价格变化
A59: 合同项目及编号 | B59: 原处理方式 | E59: 新准则下会计处理 | G59: 审计证据及说明 | I59: 索引
A62: 捆绑销售 | B62: 购机赠费与存费优惠购机的会计处理不同，通常按余值法分摊 | E62: 统一按单独售价的比例分摊交易价格 | J62: 合同中包含两项或多项履约义务的，企业应当在合同开始日，按照各单项履约义务所承诺商品的单独售价的相对比例，将交易价格分摊至各单项履约义务。
A64: 3.5 收入确认总额法净额法调整
A65: 合同项目及编号 | B65: 原处理方式 | E65: 新准则下会计处理 | G65: 审计证据及说明 | I65: 索引
A68: 大宗商品交易 | B68: 由于面临重大客户信用风险，公司按总额确认销售收入 | E68: 由于在将货物转让给客户之前未获得对该货物的控制权，公司的身份是作为代理人为另一方安排提供商品交易服务，应按净额确认收入 | J68: 企业应当根据其在向客户转让商品前是否拥有对该商品的控制权，来判断其从事交易时的身份是主要责任人还是代理人。
A70: 3.6 重大融资成分调整
A71: 合同项目及编号 | B71: 原处理方式 | E71: 新准则下会计处理 | G71: 审计证据及说明 | I71: 索引
A74: 预收客户款项的销售 | B74: 未确认向客户的融资费用 | E74: 存在重大融资成分的，确认利息费用，并调整收入确认金额 | J74: 合同中存在重大融资成分的，企业应当按照假定客户在取得商品控制权时即以现金支付的应付金额确定交易价格。该交易价格与合同对价之间的差额，应当在合同期间内采用实际利率法摊销。
A76: 3.7 合同取得成本、合同履约成本
A77: 合同项目及编号 | B77: 原处理方式 | E77: 新准则下会计处理 | G77: 审计证据及说明 | I77: 索引
A80: 销售佣金、印花税 | B80: 计入销售费用 | E80: 符合资本化条件时，将销售佣金、印花税等合同取得成本确认为一项资产；后续采用与该资产相关的商品收入确认相同的基础进行摊销，计入当期损益（销售费用） | J80: 企业为取得合同发生的增量成本预期能够收回的，应当作为合同取得成本确认为一项资产；但是，该资产摊销期限不超过一年的，可以在发生时计入当期损益。 增量成本，是指企业不取得合同就不会发生的成本（如销售佣金等）。
A82: 3.8 客户退货权的确认
A83: 合同项目及编号 | B83: 原处理方式 | E83: 新准则下会计处理 | G83: 审计证据及说明 | I83: 索引
A86: 退货权 | B86: 估计的销售退回确认相关毛利预计负债 | E86: 预计退回的部分不确认收入，按照预期因销售退回将退还的金额确认负债 ；预计退货收回产品的权利确认为资产
A88: 4. 合同变更的简化处理 | J88: 对于最早可比期间期初之前或首次执行本准则当年年初之前发生的合同变更，企业可予以简化处理，即无需按照本准则第八条规定进行追溯调整，而是根据合同变更的最终安排，识别已履行的和尚未履行的履约义务、确定交易价格以及在已履行的和尚未履行的履约义务之间分摊交易价格。
A89: 合同项目及编号 | B89: 合同履行及变更情况说明 | F89: 合同变更的简化处理 | I89: 索引
A92: 销售合同变更 | B92: 公司原售出100件产品，价款共2,000元。 2019年5月合同变更，增加10件，共120元。合同变更时已经转移10件。全部未收款。 2019年10月再次合同变更，增加40件，共400元。合同变更时已经转移60件。全部未收款。 新收入准则首次施行日2020年1月1日。 截止2019年12月31日共转让70件。2020年转移其余的80件。 原准则不会考虑2019年10月的变更，2019年确认收入1,400元（70×20），剩余对价1,120元（2,000-1,400+120+400），剩余80件商品。 | F92: 2019年两次合同变更后，对每件剩余产品确认的收入金额应为综合价格14.67元。 ［（20元× 尚未根据原合同转让的40件产品）＋（12元× 尚未根据第一次修订后的合同转让的10件产品）＋（10元×拟根据第二次合同变更转让的40件产品）］÷90件剩余产品 2019年应确认收入：合同变更前转移（60×20）+合同变更后转移（10×14.67）=1,346.67元。 新准则下2019年应确认1,346.67元，调整首次执行本准则当年年初（2020年1月1日）留存收益及应收账款-53.33元
A94: 5. 执行新收入准则的影响 | J94: 企业应当在附注中披露，与收入相关会计准则制度的原规定相比，执行本准则对当期财务报表相关项目的影响金额，如有重大影响的，还需披露其原因。
A95: 5.1 新收入准则对首次执行日（2020年1月1日）合并资产负债表的影响
A96: 项 目 | C96: 注 | D96: 43830 | F96: 重分类 | G96: 重新计量 | H96: 43831 | I96: 备注
A97: 流动资产：
A98: 应收账款
A99: 其他应收款
A100: 存货
A101: 合同资产
A102: 其他流动资产
A103: 非流动资产：
A104: 长期应收款
A105: 其他非流动资产
A106: 流动负债：
A107: 预收款项
A108: 合同负债
... A117: 5.2.1 合并资产负债表
A118: 项 目 | C118: 注 | D118: 新收入准则下2020年12月31日余额 | F118: 调整 | G118: 说明 | H118: 原收入准则下2020年12月31日余额 | I118: 备注 | J118: 企业需要在首次执行新收入准则当年保留两套记录，以便按照规定披露假定按照原准则编制的财务报表中所有项目的重大变化。
A119: 流动资产：
A120: 应收账款
A121: 其他应收款
A122: 存货
A123: 合同资产
A124: 其他流动资产
A125: 流动负债：
A126: 预收款项
A127: 合同负债
A128: 应交税费
A129: ……
A132: 5.2.2 合并利润表
A133: 项 目 | C133: 注 | D133: 新收入准则下2020年度发生额 | F133: 调整 | G133: 说明 | H133: 原收入准则下2020年度发生额 | I133: 备注
A134: 营业收入
A135: 营业成本
A136: 销售费用
A138: ……
...

Sheet 首次执行新租赁准则的调整S3-8
A1: 致同会计师事务所
A2: 首次执行新租赁准则的调整
A3: =审定表!A3 -> 客户名称： | E3: ='表头（请先填写）'!A4 -> 编制人： | G3: ='表头（请先填写）'!A5 -> 日期： | I3: 索引：S3-8
A4: =审定表!A4 -> 会计期间：2023年度 | E4: 复核人： | G4: 日期： | I4: 页次：
A5: 一、审计目标： | J5: 在境内外同时上市的企业以及在境外上市并采用国际财务报告准则或企业会计准则编制财务报表的企业，自2019年1月1日起施行；
A6: 确定首次执行日的调整。 | J6: 其他执行企业会计准则的企业自2021年1月1日起施行。
A7: 二、审计过程：
A8: 1. 首次执行日重分类及调整
A9: 原核算科目与列报项目 | B9: 新准则核算项目 | C9: 准则依据及转换要求 | F9: 重分类分录 | G9: 金额 | H9: 调整分录 | I9: 金额
A10: 固定资产 | B10: 使用权资产 | C10: 对于首次执行日前的融资租赁，承租人在首次执行日应当按照融资租入资产和应付融资租赁款的原账面价值，分别计量使用权资产和租赁负债 | F10: 借：使用权资产—原值
F11: 借：融资租入固定资产—累计折旧
F12: 贷：融资租入固定资产—原值
F13: 贷：使用权资产—累计折旧
A14: 长期应付款 | B14: 租赁负债 | C14: 对于首次执行日前的融资租赁，承租人在首次执行日应当按照融资租入资产和应付融资租赁款的原账面价值，分别计量使用权资产和租赁负债 | F14: 借：长期应付款—应付融资租赁款
F15: 借：租赁负债—未确认融资费用
F16: 贷：未确认融资费用
F17: 贷：租赁负债—租赁付款额
A18: N/A | B18: 使用权资产 | C18: 对于首次执行日前的经营租赁，承租人在首次执行日应当根据剩余租赁付款额按首次执行日承租人增量借款利率折现的现值计量租赁负债，并根据每项租赁选择按照下列两者之一计量使用权资产： （1）假设自租赁期开始日即采用本准则的账面价值（采用首次执行日的承租人增量借款利率作为折现率）； （2）与租赁负债相等的金额，并根据预付租金进行必要调整。 | F18: “简化的追溯调整法”下按（1）处理时： | H18: 借：使用权资产——原值 | J18: 对于首次执行日前的经营租赁，承租人在首次执行日应当根据剩余租赁付款额按首次执行日承租人增量借款利率折现的现值计量租赁负债，并根据每项租赁选择按照下列两者之一计量使用权资产
H19: 借：盈余公积
H20: 借：利润分配——未分配利润
H21: 借：租赁负债——未确认融资费用
H22: 贷：使用权资产——累计折旧
H23: 贷： 租赁负债——租赁付款额
A24: N/A | B24: 使用权资产 | C24: 对于首次执行日前的经营租赁，承租人在首次执行日应当根据剩余租赁付款额按首次执行日承租人增量借款利率折现的现值计量租赁负债，并根据每项租赁选择按照下列两者之一计量使用权资产： （1）假设自租赁期开始日即采用本准则的账面价值（采用首次执行日的承租人增量借款利率作为折现率）； （2）与租赁负债相等的金额，并根据预付租金进行必要调整。 | F24: “简化的追溯调整法”下按（2）处理时：
H25: 借：使用权资产——原值
H26: 借：租赁负债——未确认融资费用
H27: 贷：租赁负债——租赁付款额
A34: 2. 新租赁准则对首次执行日（2021年1月1日）合并资产负债表的影响
A35: 项 目 | C35: 注 | D35: 44196 | F35: 重分类 | G35: 重新计量 | H35: 44197 | I35: 备注
A36: 资产：
A37: 固定资产
A38: 使用权资产 | D38: —
A39: 长期待摊费用
A41: 资产总额
A42: 负债：
A43: 一年内到期的非流动负债
A44: 租赁负债 | D44: —
A45: 长期应付款
A46: 预计负债
A48: 负债总额
A51: 3. 首次执行日前一年度报告期末披露的重大经营租赁的尚未支付的最低租赁付款额与计入首次执行日资产负债表的租赁负债的调节
A52: 项目 | F52: 金额 | G52: 备注 | I52: 索引号
A53: 一、2020年12月31日经营租赁承诺
A54: 减：增值税影响
A55: 二、2020年12月31日经营租赁承诺（不含增值税） | F55: =F53-F54 -> 0
A56: 按首次执行日增量借款利率折现计算的租赁负债 | G56: 2021年1月1日增量借款利率加权平均值：
A57: 加：合理确定将行使的续租选择权
A58: 加：2020年12月31日融资租赁最低租赁付款额
A59: 减：确认豁免——短期租赁
A60: 减：确认豁免——低价值资产租赁
A61: 减：自首次执行日起剩余租赁期间短于12个月
A62: 减：取决于指数或比率的可变租赁付款额调节
A63: 执行新租赁准则确认的与原经营租赁相关的租赁负债 | F63: =F56+F57+F58-F59-F60-F61-F62 -> 0
A64: 三、2021年1月1日租赁负债
A65: 列示为：一年内到期的非流动负债
A66: 租赁负债
A69: 4. 与原租赁准则相比，执行新租赁准则对当期财务报表相关项目的影响 | J69: 准则未强制要求披露该信息
A70: 4.1 合并资产负债表
A71: 项 目 | C71: 注 | D71: 新租赁准则下2021年12月31日余额 | F71: 调整 | G71: 说明 | H71: 原租赁准则下2021年12月31日余额 | I71: 备注
A72: 资产：
A73: 固定资产
A74: 使用权资产
A75: 长期待摊费用
A77: 资产总额
A78: 负债：
A79: 一年内到期的非流动负债
A80: 租赁负债
A81: 长期应付款
A82: 预计负债
A84: 负债总额
A87: 4.2 合并利润表
A88: 项 目 | C88: 注 | D88: 新租赁准则下2021年度发生额 | F88: 调整 | G88: 说明 | H88: 原租赁准则下2021年度发生额 | I88: 备注
A89: 营业成本
A90: 财务费用
A91: 管理费用
A92: 所得税费用
A93: ……
A96: 三、审计说明：
A99: 四、审计结论：
A102: 编制说明：
A103: 对于首次执行日前已存在的合同，企业在首次执行日可以选择不重新评估其是否为租赁或者包含租赁。选择不重新评估的，企业应当在财务报表附注中披露这一事实，并一致应用于前述所有合同。
A105: 承租人应当选择下列方法之一对租赁进行衔接会计处理，并一致应用于其作为承租人的所有租赁：
A106: （一）按照《企业会计准则第28号——会计政策、会计估计变更和差错更正》的规定采用追溯调整法处理。
A107: （二）根据首次执行本准则的累积影响数，调整首次执行本准则当年年初留存收益及财务报表其他相关项目金额，不调整可比期间信息。采用该方法时，应当按照下列规定进行衔接处理：
... A115: （二）首次执行日前一年度报告期末披露的重大经营租赁的尚未支付的最低租赁付款额按首次执行日承租人增量借款利率折现的现值，与计入首次执行日资产负债表的租赁负债的差额。

Sheet 简化的追溯调整法（1）S3-9
A1: 致同会计师事务所
A2: 首次执行日承租人使用简化的追溯调整法（1）
A3: =审定表!A3 -> 客户名称： | D3: ='表头（请先填写）'!A4 -> 编制人： | G3: ='表头（请先填写）'!A5 -> 日期： | I3: 索引：S3-9
A4: =审定表!A4 -> 会计期间：2023年度 | D4: 复核人： | G4: 日期： | I4: 页次：
A5: 一、审计目标：
A6: 确定首次执行日（2021年1月1日）承租人简化的追溯调整法——使用权资产假设自租赁期开始日即采用本准则。
A7: 二、审计过程：
A8: 1. 租赁合同的基本信息 | G8: 44197
A9: 使用权资产名称 | B9: 租赁期开始日 | C9: 合同约定初始期满日 | D9: 续租期（年） | E9: 租赁期（考虑续租可能后） | F9: 租赁期截止日期 | G9: 首次执行日剩余租期 | H9: 增量借款年利率 | I9: 使用权资产摊销期限（年） | J9: 租赁期是指承租人有权使用租赁资产且不可撤销的期间;承租人有续租选择权，即有权选择续租该资产，且合理确定将行使该选择权的，租赁期还应当包含续租选择权涵盖的期间；承租人有终止租赁选择权即有权选择终止租赁该资产，但合理确定将不会行使该选择权的，租赁期应当包含终止租赁选择权涵盖的期间。
A10: XX设备 | B10: 43466 | C10: 46387 | D10: =2 -> 2 | E10: =(YEAR(C10)-YEAR(B10))+D10+(MONTH(C10)-MONTH(B10)+1)/12 -> 10 | F10: =DATE(YEAR(C10)+D10,MONTH(C10),DAY(C10)) -> 47118 | G10: =(YEAR(C10)-YEAR(G8))+D10+(MONTH(C10)-MONTH(G8)+1)/12 -> 8 | H10: 0.05 | I10: 10
A13: 2. 计算租赁负债及使用权资产余额
A14: 租金支付日期 | B14: 合同租金（不含税） | C14: 租赁付款额原值 | D14: 租赁负债折现期(年） | E14: 租赁负债折现系数 | F14: 租赁付款额现值 | G14: 折现期(年） | H14: 折现系数 | I14: 使用权资产初始确认金额 | J14: 本示例假设期初支付租金
A15: 43466 | B15: 50000 | G15: 0 | H15: =1/(1+$H$10)^G15 -> 1 | I15: =B15*H15 -> 50000
A16: 43831 | B16: 50000 | G16: 1 | H16: =1/(1+$H$10)^G16 -> 0.95238095 | I16: =B16*H16 -> 47619.048
A17: 44197 | B17: 50000 | C17: =IF(E17=1,0,B17) -> 0 | D17: 0 | E17: =1/(1+$H$10)^D17 -> 1 | F17: =IF(E17=1,0,B17*E17) -> 0 | G17: 2 | H17: =1/(1+$H$10)^G17 -> 0.90702948 | I17: =B17*H17 -> 45351.474
A18: 44562 | B18: 50000 | C18: =IF(E18=1,0,B18) -> 50000 | D18: =D17+1 -> 1 | E18: =1/(1+$H$10)^D18 -> 0.95238095 | F18: =IF(E18=1,0,B18*E18) -> 47619.048 | G18: 3 | H18: =1/(1+$H$10)^G18 -> 0.8638376 | I18: =B18*H18 -> 43191.88
A19: 44927 | B19: 50000 | C19: =IF(E19=1,0,B19) -> 50000 | D19: =D18+1 -> 2 | E19: =1/(1+$H$10)^D19 -> 0.90702948 | F19: =IF(E19=1,0,B19*E19) -> 45351.474 | G19: 4 | H19: =1/(1+$H$10)^G19 -> 0.82270247 | I19: =B19*H19 -> 41135.124
A20: 45292 | B20: 50000 | C20: =IF(E20=1,0,B20) -> 50000 | D20: =D19+1 -> 3 | E20: =1/(1+$H$10)^D20 -> 0.8638376 | F20: =IF(E20=1,0,B20*E20) -> 43191.88 | G20: 5 | H20: =1/(1+$H$10)^G20 -> 0.78352617 | I20: =B20*H20 -> 39176.308
A21: 45658 | B21: 50000 | C21: =IF(E21=1,0,B21) -> 50000 | D21: =D20+1 -> 4 | E21: =1/(1+$H$10)^D21 -> 0.82270247 | F21: =IF(E21=1,0,B21*E21) -> 41135.124 | G21: 6 | H21: =1/(1+$H$10)^G21 -> 0.7462154 | I21: =B21*H21 -> 37310.77
A22: 46023 | B22: 50000 | C22: =IF(E22=1,0,B22) -> 50000 | D22: =D21+1 -> 5 | E22: =1/(1+$H$10)^D22 -> 0.78352617 | F22: =IF(E22=1,0,B22*E22) -> 39176.308 | G22: 7 | H22: =1/(1+$H$10)^G22 -> 0.71068133 | I22: =B22*H22 -> 35534.067
A23: 46388 | B23: 50000 | C23: =IF(E23=1,0,B23) -> 50000 | D23: =D22+1 -> 6 | E23: =1/(1+$H$10)^D23 -> 0.7462154 | F23: =IF(E23=1,0,B23*E23) -> 37310.77 | G23: 8 | H23: =1/(1+$H$10)^G23 -> 0.67683936 | I23: =B23*H23 -> 33841.968
A24: 46753 | B24: 50000 | C24: =IF(E24=1,0,B24) -> 50000 | D24: =D23+1 -> 7 | E24: =1/(1+$H$10)^D24 -> 0.71068133 | F24: =IF(E24=1,0,B24*E24) -> 35534.067 | G24: 9 | H24: =1/(1+$H$10)^G24 -> 0.64460892 | I24: =B24*H24 -> 32230.446
A25: 合计 | B25: =SUM(B15:B24) -> 500000 | C25: =SUM(C15:C24) -> 350000 | F25: =SUM(F17:F24) -> 289318.67 | I25: =SUM(I15:I24) -> 405391.08
A27: 3. 首次执行日调整分录
A28: 借：使用权资产——原值 | C28: =I25 -> 405391.08 | E28: 【假设自租赁期开始日即采用本准则的账面价值】
A29: 借：盈余公积 | C29: =(B41-(G41-D34))*10% -> 1500.5803
A30: 借：利润分配——未分配利润 | C30: =(B41-(G41-D34))*90% -> 13505.223
A31: 借：租赁负债——未确认融资费用 | C31: =E49 -> 60681.33
A32: 贷：使用权资产——累计折旧 | D32: =H39+H40 -> 81078.217
A33: 贷：租赁负债——租赁付款额 | D33: =C25 -> 350000 | E33: 【剩余租赁付款额原值】
A34: 贷：预付款项/其他流动资产 | D34: =SUM(B17:B24)-SUM(C17:C24) -> 50000 | E34: 【预付租金】
C35: =SUM(C28:C34) -> 481078.22 | D35: =SUM(D28:D34) -> 481078.22
A36: 4. 租赁负债及使用权资产后续计量
A37: 期间 | B37: 租赁负债 | G37: 使用权资产
B38: 期初余额 | C38: 租赁付款额 | D38: 支付月份 | E38: 利息费用 | F38: 期末余额 | G38: 期初余额 | H38: 折旧费用 | I38: 期末余额 | J38: 本示例假设期初支付租金
A39: 2019年度 | G39: =I25 -> 405391.08 | H39: =$I$25/$I$10 -> 40539.108 | I39: =G39-H39 -> 364851.98
A40: 2020年度 | G40: =I39 -> 364851.98 | H40: =$I$25/$I$10 -> 40539.108 | I40: =G40-H40 -> 324312.87
A41: 2021年度 | B41: =F25 -> 289318.67 | C41: =C17 -> 0 | D41: 1 | E41: =(B41-C41)*$H$10 -> 14465.933 | F41: =B41-C41+E41 -> 303784.6 | G41: =I40 -> 324312.87 | H41: =$I$25/$I$10 -> 40539.108 | I41: =G41-H41 -> 283773.76
A42: 2022年度 | B42: =B41-C41+E41 -> 303784.6 | C42: =C18 -> 50000 | D42: 1 | E42: =(B42-C42)*$H$10 -> 12689.23 | F42: =B42-C42+E42 -> 266473.83 | G42: =I41 -> 283773.76 | H42: =$I$25/$I$10 -> 40539.108 | I42: =G42-H42 -> 243234.65
A43: 2023年度 | B43: =B42-C42+E42 -> 266473.83 | C43: =C19 -> 50000 | D43: 1 | E43: =(B43-C43)*$H$10 -> 10823.692 | F43: =B43-C43+E43 -> 227297.53 | G43: =I42 -> 243234.65 | H43: =$I$25/$I$10 -> 40539.108 | I43: =G43-H43 -> 202695.54
A44: 2024年度 | B44: =B43-C43+E43 -> 227297.53 | C44: =C20 -> 50000 | D44: 1 | E44: =(B44-C44)*$H$10 -> 8864.8763 | F44: =B44-C44+E44 -> 186162.4 | G44: =I43 -> 202695.54 | H44: =$I$25/$I$10 -> 40539.108 | I44: =G44-H44 -> 162156.43
A45: 2025年度 | B45: =B44-C44+E44 -> 186162.4 | C45: =C21 -> 50000 | D45: 1 | E45: =(B45-C45)*$H$10 -> 6808.1201 | F45: =B45-C45+E45 -> 142970.52 | G45: =I44 -> 162156.43 | H45: =$I$25/$I$10 -> 40539.108 | I45: =G45-H45 -> 121617.33
A46: 2026年度 | B46: =B45-C45+E45 -> 142970.52 | C46: =C22 -> 50000 | D46: 1 | E46: =(B46-C46)*$H$10 -> 4648.5261 | F46: =B46-C46+E46 -> 97619.048 | G46: =I45 -> 121617.33 | H46: =$I$25/$I$10 -> 40539.108 | I46: =G46-H46 -> 81078.217
A47: 2027年度 | B47: =B46-C46+E46 -> 97619.048 | C47: =C23 -> 50000 | D47: 1 | E47: =(B47-C47)*$H$10 -> 2380.9524 | F47: =B47-C47+E47 -> 50000 | G47: =I46 -> 81078.217 | H47: =$I$25/$I$10 -> 40539.108 | I47: =G47-H47 -> 40539.108
A48: 2028年度 | B48: =B47-C47+E47 -> 50000 | C48: =C24 -> 50000 | D48: 1 | E48: =(B48-C48)*$H$10 -> -1.4551915e-12 | F48: =B48-C48+E48 -> -3.0559022e-11 | G48: =I47 -> 40539.108 | H48: =$I$25/$I$10 -> 40539.108 | I48: =G48-H48 -> 0
A49: 合计 | C49: =SUM(C41:C48) -> 350000 | E49: =SUM(E41:E48) -> 60681.33 | H49: =SUM(H39:H48) -> 405391.08
A51: 三、审计说明：
A54: 四、审计结论：
A57: 编制说明：
A58: 承租人应当选择下列方法之一对租赁进行衔接会计处理，并一致应用于其作为承租人的所有租赁：
A59: （一）按照《企业会计准则第28号——会计政策、会计估计变更和差错更正》的规定采用追溯调整法处理。
A60: （二）根据首次执行本准则的累积影响数，调整首次执行本准则当年年初留存收益及财务报表其他相关项目金额，不调整可比期间信息。采用该方法时，应当按照下列规定进行衔接处理：
A61: 1. 对于首次执行日前的融资租赁，承租人在首次执行日应当按照融资租入资产和应付融资租赁款的原账面价值，分别计量使用权资产和租赁负债。
A62: 2. 对于首次执行日前的经营租赁，承租人在首次执行日应当根据剩余租赁付款额按首次执行日承租人增量借款利率折现的现值计量租赁负债，并根据每项租赁选择按照下列两者之一计量使用权资产：
A63: （1）假设自租赁期开始日即采用本准则的账面价值（采用首次执行日的承租人增量借款利率作为折现率）；
A64: （2）与租赁负债相等的金额，并根据预付租金进行必要调整。
A66: 承租人选择按照本准则第六十一条第（二）项规定对租赁进行衔接会计处理的，还应当在首次执行日披露以下信息：
A67: （一）首次执行日计入资产负债表的租赁负债所采用的承租人增量借款利率的加权平均值；
A68: （二）首次执行日前一年度报告期末披露的重大经营租赁的尚未支付的最低租赁付款额按首次执行日承租人增量借款利率折现的现值，与计入首次执行日资产负债表的租赁负债的差额。

Sheet 简化的追溯调整法（2）S3-10
A1: 致同会计师事务所
A2: 首次执行日承租人使用简化的追溯调整法（2）
A3: =审定表!A3 -> 客户名称： | D3: ='表头（请先填写）'!A4 -> 编制人： | G3: ='表头（请先填写）'!A5 -> 日期： | I3: 索引：S3-10
A4: =审定表!A4 -> 会计期间：2023年度 | D4: 复核人： | G4: 日期： | I4: 页次：
A5: 一、审计目标：
A6: 确定首次执行日（2021年1月1日）承租人简化的追溯调整法——使用权资产与租赁负债（调整预付租金）相等。
A7: 二、审计过程：
A8: 1. 租赁合同的基本信息 | G8: 44197
A9: 使用权资产名称 | B9: 租赁期开始日 | C9: 合同约定初始期满日 | D9: 续租期（年） | E9: 租赁期（考虑续租可能后） | F9: 租赁期截止日期 | G9: 首次执行日剩余租期 | H9: 增量借款年利率 | I9: 使用权资产摊销期限（年） | J9: 租赁期是指承租人有权使用租赁资产且不可撤销的期间;承租人有续租选择权，即有权选择续租该资产，且合理确定将行使该选择权的，租赁期还应当包含续租选择权涵盖的期间；承租人有终止租赁选择权即有权选择终止租赁该资产，但合理确定将不会行使该选择权的，租赁期应当包含终止租赁选择权涵盖的期间。
A10: XX设备 | B10: 43466 | C10: 46387 | D10: =2 -> 2 | E10: =(YEAR(C10)-YEAR(B10))+D10+(MONTH(C10)-MONTH(B10)+1)/12 -> 10 | F10: =DATE(YEAR(C10)+D10,MONTH(C10),DAY(C10)) -> 47118 | G10: =(YEAR(C10)-YEAR(G8))+D10+(MONTH(C10)-MONTH(G8)+1)/12 -> 8 | H10: 0.05 | I10: 8
A13: 2. 计算租赁负债余额
A14: 租金支付日期 | B14: 剩余合同租金（不含税） | C14: 租赁付款额原值 | D14: 租赁负债折现期(年） | E14: 租赁负债折现系数 | F14: 租赁付款额现值 | G14: 折现期(年） | H14: 折现系数 | I14: 使用权资产初始确认金额 | J14: 本示例假设期初支付租金
A15: 43466
A16: 43831
A17: 44197 | B17: 50000 | C17: =IF(E17=1,0,B17) -> 0 | D17: 0 | E17: =1/(1+$H$10)^D17 -> 1 | F17: =IF(E17=1,0,B17*E17) -> 0 | G17: =D17 -> 0 | H17: =E17 -> 1 | I17: =B17*H17 -> 50000
A18: 44562 | B18: 50000 | C18: =IF(E18=1,0,B18) -> 50000 | D18: =D17+1 -> 1 | E18: =1/(1+$H$10)^D18 -> 0.95238095 | F18: =IF(E18=1,0,B18*E18) -> 47619.048 | G18: =D18 -> 1 | H18: =E18 -> 0.95238095 | I18: =B18*H18 -> 47619.048
A19: 44927 | B19: 50000 | C19: =IF(E19=1,0,B19) -> 50000 | D19: =D18+1 -> 2 | E19: =1/(1+$H$10)^D19 -> 0.90702948 | F19: =IF(E19=1,0,B19*E19) -> 45351.474 | G19: =D19 -> 2 | H19: =E19 -> 0.90702948 | I19: =B19*H19 -> 45351.474
A20: 45292 | B20: 50000 | C20: =IF(E20=1,0,B20) -> 50000 | D20: =D19+1 -> 3 | E20: =1/(1+$H$10)^D20 -> 0.8638376 | F20: =IF(E20=1,0,B20*E20) -> 43191.88 | G20: =D20 -> 3 | H20: =E20 -> 0.8638376 | I20: =B20*H20 -> 43191.88
A21: 45658 | B21: 50000 | C21: =IF(E21=1,0,B21) -> 50000 | D21: =D20+1 -> 4 | E21: =1/(1+$H$10)^D21 -> 0.82270247 | F21: =IF(E21=1,0,B21*E21) -> 41135.124 | G21: =D21 -> 4 | H21: =E21 -> 0.82270247 | I21: =B21*H21 -> 41135.124
A22: 46023 | B22: 50000 | C22: =IF(E22=1,0,B22) -> 50000 | D22: =D21+1 -> 5 | E22: =1/(1+$H$10)^D22 -> 0.78352617 | F22: =IF(E22=1,0,B22*E22) -> 39176.308 | G22: =D22 -> 5 | H22: =E22 -> 0.78352617 | I22: =B22*H22 -> 39176.308
A23: 46388 | B23: 50000 | C23: =IF(E23=1,0,B23) -> 50000 | D23: =D22+1 -> 6 | E23: =1/(1+$H$10)^D23 -> 0.7462154 | F23: =IF(E23=1,0,B23*E23) -> 37310.77 | G23: =D23 -> 6 | H23: =E23 -> 0.7462154 | I23: =B23*H23 -> 37310.77
A24: 46753 | B24: 50000 | C24: =IF(E24=1,0,B24) -> 50000 | D24: =D23+1 -> 7 | E24: =1/(1+$H$10)^D24 -> 0.71068133 | F24: =IF(E24=1,0,B24*E24) -> 35534.067 | G24: =D24 -> 7 | H24: =E24 -> 0.71068133 | I24: =B24*H24 -> 35534.067
A25: 合计 | B25: =SUM(B17:B24) -> 400000 | C25: =SUM(C15:C24) -> 350000 | F25: =SUM(F17:F24) -> 289318.67 | I25: =SUM(I17:I24) -> 339318.67
A27: 3. 首次执行日调整分录
A28: 借：使用权资产——原值 | C28: =I25 -> 339318.67 | E28: 【租赁负债+预付租金】
A29: 借：租赁负债——未确认融资费用 | C29: =E46 -> 60681.33
A30: 贷：租赁负债——租赁付款额 | D30: =C25 -> 350000 | E30: 【剩余租赁付款额原值】
A31: 贷：预付款项/其他流动资产 | D31: =B25-C25 -> 50000 | E31: 【预付租金】
C32: =SUM(C28:C31) -> 400000 | D32: =SUM(D28:D31) -> 400000
A33: 4. 租赁负债及使用权资产后续计量
A34: 期间 | B34: 租赁负债 | G34: 使用权资产
B35: 期初余额 | C35: 租赁付款额 | D35: 支付月份 | E35: 利息费用 | F35: 期末余额 | G35: 期初余额 | H35: 折旧费用 | I35: 期末余额 | J35: 本示例假设期初支付租金
A36: 2019年度
A37: 2020年度
A38: 2021年度 | B38: =F25 -> 289318.67 | C38: =C17 -> 0 | D38: 1 | E38: =(B38-C38)*$H$10 -> 14465.933 | F38: =B38-C38+E38 -> 303784.6 | G38: =I25 -> 339318.67 | H38: =$I$25/$I$10 -> 42414.834 | I38: =G38-H38 -> 296903.84
A39: 2022年度 | B39: =B38-C38+E38 -> 303784.6 | C39: =C18 -> 50000 | D39: 1 | E39: =(B39-C39)*$H$10 -> 12689.23 | F39: =B39-C39+E39 -> 266473.83 | G39: =I38 -> 296903.84 | H39: =H38 -> 42414.834 | I39: =G39-H39 -> 254489
A40: 2023年度 | B40: =B39-C39+E39 -> 266473.83 | C40: =C19 -> 50000 | D40: 1 | E40: =(B40-C40)*$H$10 -> 10823.692 | F40: =B40-C40+E40 -> 227297.53 | G40: =I39 -> 254489 | H40: =H39 -> 42414.834 | I40: =G40-H40 -> 212074.17
A41: 2024年度 | B41: =B40-C40+E40 -> 227297.53 | C41: =C20 -> 50000 | D41: 1 | E41: =(B41-C41)*$H$10 -> 8864.8763 | F41: =B41-C41+E41 -> 186162.4 | G41: =I40 -> 212074.17 | H41: =H40 -> 42414.834 | I41: =G41-H41 -> 169659.33
A42: 2025年度 | B42: =B41-C41+E41 -> 186162.4 | C42: =C21 -> 50000 | D42: 1 | E42: =(B42-C42)*$H$10 -> 6808.1201 | F42: =B42-C42+E42 -> 142970.52 | G42: =I41 -> 169659.33 | H42: =H41 -> 42414.834 | I42: =G42-H42 -> 127244.5
A43: 2026年度 | B43: =B42-C42+E42 -> 142970.52 | C43: =C22 -> 50000 | D43: 1 | E43: =(B43-C43)*$H$10 -> 4648.5261 | F43: =B43-C43+E43 -> 97619.048 | G43: =I42 -> 127244.5 | H43: =H42 -> 42414.834 | I43: =G43-H43 -> 84829.667
A44: 2027年度 | B44: =B43-C43+E43 -> 97619.048 | C44: =C23 -> 50000 | D44: 1 | E44: =(B44-C44)*$H$10 -> 2380.9524 | F44: =B44-C44+E44 -> 50000 | G44: =I43 -> 84829.667 | H44: =H43 -> 42414.834 | I44: =G44-H44 -> 42414.834
A45: 2028年度 | B45: =B44-C44+E44 -> 50000 | C45: =C24 -> 50000 | D45: 1 | E45: =(B45-C45)*$H$10 -> -1.4551915e-12 | F45: =B45-C45+E45 -> -3.0559022e-11 | G45: =I44 -> 42414.834 | H45: =H44 -> 42414.834 | I45: =G45-H45 -> 5.8207661e-11
A46: 合计 | C46: =SUM(C38:C45) -> 350000 | E46: =SUM(E38:E45) -> 60681.33 | H46: =SUM(H38:H45) -> 339318.67
A48: 三、审计说明：
A51: 四、审计结论：
A54: 编制说明：
A55: 承租人应当选择下列方法之一对租赁进行衔接会计处理，并一致应用于其作为承租人的所有租赁：
A56: （一）按照《企业会计准则第28号——会计政策、会计估计变更和差错更正》的规定采用追溯调整法处理。
A57: （二）根据首次执行本准则的累积影响数，调整首次执行本准则当年年初留存收益及财务报表其他相关项目金额，不调整可比期间信息。采用该方法时，应当按照下列规定进行衔接处理：
A58: 1. 对于首次执行日前的融资租赁，承租人在首次执行日应当按照融资租入资产和应付融资租赁款的原账面价值，分别计量使用权资产和租赁负债。
A59: 2. 对于首次执行日前的经营租赁，承租人在首次执行日应当根据剩余租赁付款额按首次执行日承租人增量借款利率折现的现值计量租赁负债，并根据每项租赁选择按照下列两者之一计量使用权资产：
A60: （1）假设自租赁期开始日即采用本准则的账面价值（采用首次执行日的承租人增量借款利率作为折现率）；
A61: （2）与租赁负债相等的金额，并根据预付租金进行必要调整。
A63: 承租人选择按照本准则第六十一条第（二）项规定对租赁进行衔接会计处理的，还应当在首次执行日披露以下信息：
A64: （一）首次执行日计入资产负债表的租赁负债所采用的承租人增量借款利率的加权平均值；
A65: （二）首次执行日前一年度报告期末披露的重大经营租赁的尚未支付的最低租赁付款额按首次执行日承租人增量借款利率折现的现值，与计入首次执行日资产负债表的租赁负债的差额。

Sheet 简化的追溯调整法（2）S3-10 (2)
A1: 致同会计师事务所
A2: 首次执行日承租人使用简化的追溯调整法（2）
A3: =审定表!A3 -> 客户名称： | D3: ='表头（请先填写）'!A4 -> 编制人： | G3: ='表头（请先填写）'!A5 -> 日期： | I3: 索引：S3-10
A4: =审定表!A4 -> 会计期间：2023年度 | D4: 复核人： | G4: 日期： | I4: 页次：
A5: 一、审计目标：
A6: 确定首次执行日（2021年1月1日）承租人简化的追溯调整法——使用权资产与租赁负债（调整预付租金）相等。
A7: 二、审计过程：
A8: 1. 租赁合同的基本信息 | G8: 44197
A9: 使用权资产名称 | B9: 租赁期开始日 | C9: 合同约定初始期满日 | D9: 续租期（年） | E9: 租赁期（考虑续租可能后） | F9: 租赁期截止日期 | G9: 首次执行日剩余租期 | H9: 增量借款年利率 | I9: 使用权资产摊销期限（年） | J9: 租赁期是指承租人有权使用租赁资产且不可撤销的期间;承租人有续租选择权，即有权选择续租该资产，且合理确定将行使该选择权的，租赁期还应当包含续租选择权涵盖的期间；承租人有终止租赁选择权即有权选择终止租赁该资产，但合理确定将不会行使该选择权的，租赁期应当包含终止租赁选择权涵盖的期间。
A10: XX设备 | B10: 43739 | C10: 46660 | D10: =2 -> 2 | E10: =(YEAR(C10)-YEAR(B10))+D10+(MONTH(C10)-MONTH(B10)+1)/12 -> 10 | F10: =DATE(YEAR(C10)+D10,MONTH(C10),DAY(C10)) -> 47391 | G10: =(YEAR(C10)-YEAR(G8))+D10+(MONTH(C10)-MONTH(G8)+1)/12 -> 8.75 | H10: 0.05 | I10: 8.75
A13: 2. 计算租赁负债余额
A14: 租金支付日期 | B14: 剩余合同租金（不含税） | C14: 租赁付款额原值 | D14: 租赁负债折现期(年） | E14: 租赁负债折现系数 | F14: 租赁付款额现值 | G14: 折现期(年） | H14: 折现系数 | I14: 使用权资产初始确认金额 | J14: 本示例假设期初支付租金
A15: 43739
A16: 44105
A17: 44470 | B17: 50000 | C17: =IF(E17=1,0,B17) -> 50000 | D17: =9/12 -> 0.75 | E17: =1/(1+$H$10)^D17 -> 0.96406879 | F17: =IF(E17=1,0,B17*E17) -> 48203.44 | G17: =D17 -> 0.75 | H17: =E17 -> 0.96406879 | I17: =B17*H17 -> 48203.44
A18: 44835 | B18: 50000 | C18: =IF(E18=1,0,B18) -> 50000 | D18: =D17+1 -> 1.75 | E18: =1/(1+$H$10)^D18 -> 0.91816076 | F18: =IF(E18=1,0,B18*E18) -> 45908.038 | G18: =D18 -> 1.75 | H18: =E18 -> 0.91816076 | I18: =B18*H18 -> 45908.038
A19: 45200 | B19: 50000 | C19: =IF(E19=1,0,B19) -> 50000 | D19: =D18+1 -> 2.75 | E19: =1/(1+$H$10)^D19 -> 0.87443882 | F19: =IF(E19=1,0,B19*E19) -> 43721.941 | G19: =D19 -> 2.75 | H19: =E19 -> 0.87443882 | I19: =B19*H19 -> 43721.941
A20: 45566 | B20: 50000 | C20: =IF(E20=1,0,B20) -> 50000 | D20: =D19+1 -> 3.75 | E20: =1/(1+$H$10)^D20 -> 0.83279887 | F20: =IF(E20=1,0,B20*E20) -> 41639.944 | G20: =D20 -> 3.75 | H20: =E20 -> 0.83279887 | I20: =B20*H20 -> 41639.944
A21: 45931 | B21: 50000 | C21: =IF(E21=1,0,B21) -> 50000 | D21: =D20+1 -> 4.75 | E21: =1/(1+$H$10)^D21 -> 0.79314178 | F21: =IF(E21=1,0,B21*E21) -> 39657.089 | G21: =D21 -> 4.75 | H21: =E21 -> 0.79314178 | I21: =B21*H21 -> 39657.089
A22: 46296 | B22: 50000 | C22: =IF(E22=1,0,B22) -> 50000 | D22: =D21+1 -> 5.75 | E22: =1/(1+$H$10)^D22 -> 0.75537313 | F22: =IF(E22=1,0,B22*E22) -> 37768.656 | G22: =D22 -> 5.75 | H22: =E22 -> 0.75537313 | I22: =B22*H22 -> 37768.656
A23: 46661 | B23: 50000 | C23: =IF(E23=1,0,B23) -> 50000 | D23: =D22+1 -> 6.75 | E23: =1/(1+$H$10)^D23 -> 0.71940298 | F23: =IF(E23=1,0,B23*E23) -> 35970.149 | G23: =D23 -> 6.75 | H23: =E23 -> 0.71940298 | I23: =B23*H23 -> 35970.149
A24: 47027 | B24: 50000 | C24: =IF(E24=1,0,B24) -> 50000 | D24: =D23+1 -> 7.75 | E24: =1/(1+$H$10)^D24 -> 0.68514569 | F24: =IF(E24=1,0,B24*E24) -> 34257.285 | G24: =D24 -> 7.75 | H24: =E24 -> 0.68514569 | I24: =B24*H24 -> 34257.285
A25: 合计 | B25: =SUM(B17:B24) -> 400000 | C25: =SUM(C15:C24) -> 400000 | F25: =SUM(F17:F24) -> 327126.54 | I25: =SUM(I17:I24) -> 327126.54
A27: 3. 首次执行日调整分录
A28: 借：使用权资产——原值 | C28: =I25+D31 -> 364626.54 | E28: 【租赁负债+预付租金】
A29: 借：租赁负债——未确认融资费用 | C29: =E47 -> 72873.459
A30: 贷：租赁负债——租赁付款额 | D30: =C25 -> 400000 | E30: 【剩余租赁付款额原值】
A31: 贷：预付款项/其他流动资产 | D31: =50000/12*9 -> 37500 | E31: 【预付租金】
C32: =SUM(C28:C31) -> 437500 | D32: =SUM(D28:D31) -> 437500
A33: 4. 租赁负债及使用权资产后续计量
A34: 期间 | B34: 租赁负债 | G34: 使用权资产
B35: 期初余额 | C35: 租赁付款额 | D35: 支付月份 | E35: 利息费用 | F35: 期末余额 | G35: 期初余额 | H35: 折旧费用 | I35: 期末余额 | J35: 本示例假设期初支付租金
A36: 2019年10-12月
A37: 2020年度
A38: 2021年度 | B38: =F25 -> 327126.54 | C38: 50000 | D38: 10 | E38: =B38*$H$10/12*(10-1)+(B38-C38)*$H$10/12*(12-D38+1) -> 15731.327 | F38: =B38-C38+E38 -> 292857.87 | G38: =I25 -> 327126.54 | H38: =($I$25/$I$10)/12*12 -> 37385.89 | I38: =G38-H38 -> 289740.65
A39: 2022年度 | B39: =B38-C38+E38 -> 292857.87 | C39: 50000 | D39: 10 | E39: =B39*$H$10/12*(10-1)+(B39-C39)*$H$10/12*(12-D39+1) -> 14017.893 | F39: =B39-C39+E39 -> 256875.76 | G39: =I38 -> 289740.65 | H39: =($I$25/$I$10)/12*12 -> 37385.89 | I39: =G39-H39 -> 252354.76
A40: 2023年度 | B40: =B39-C39+E39 -> 256875.76 | C40: 50000 | D40: 10 | E40: =B40*$H$10/12*(10-1)+(B40-C40)*$H$10/12*(12-D40+1) -> 12218.788 | F40: =B40-C40+E40 -> 219094.55 | G40: =I39 -> 252354.76 | H40: =($I$25/$I$10)/12*12 -> 37385.89 | I40: =G40-H40 -> 214968.87
A41: 2024年度 | B41: =B40-C40+E40 -> 219094.55 | C41: 50000 | D41: 10 | E41: =B41*$H$10/12*(10-1)+(B41-C41)*$H$10/12*(12-D41+1) -> 10329.727 | F41: =B41-C41+E41 -> 179424.28 | G41: =I40 -> 214968.87 | H41: =($I$25/$I$10)/12*12 -> 37385.89 | I41: =G41-H41 -> 177582.98
A42: 2025年度 | B42: =B41-C41+E41 -> 179424.28 | C42: 50000 | D42: 10 | E42: =B42*$H$10/12*(10-1)+(B42-C42)*$H$10/12*(12-D42+1) -> 8346.2139 | F42: =B42-C42+E42 -> 137770.49 | G42: =I41 -> 177582.98 | H42: =($I$25/$I$10)/12*12 -> 37385.89 | I42: =G42-H42 -> 140197.09
A43: 2026年度 | B43: =B42-C42+E42 -> 137770.49 | C43: 50000 | D43: 10 | E43: =B43*$H$10/12*(10-1)+(B43-C43)*$H$10/12*(12-D43+1) -> 6263.5245 | F43: =B43-C43+E43 -> 94034.015 | G43: =I42 -> 140197.09 | H43: =($I$25/$I$10)/12*12 -> 37385.89 | I43: =G43-H43 -> 102811.2
A44: 2027年度 | B44: =B43-C43+E43 -> 94034.015 | C44: 50000 | D44: 10 | E44: =B44*$H$10/12*(10-1)+(B44-C44)*$H$10/12*(12-D44+1) -> 4076.7008 | F44: =B44-C44+E44 -> 48110.716 | G44: =I43 -> 102811.2 | H44: =($I$25/$I$10)/12*12 -> 37385.89 | I44: =G44-H44 -> 65425.308
A45: 2028年度 | B45: =B44-C44+E44 -> 48110.716 | C45: 50000 | D45: 10 | E45: =C45-B45 -> 1889.2837 | F45: =B45-C45+E45 -> 0 | G45: =I44 -> 65425.308 | H45: =($I$25/$I$10)/12*12 -> 37385.89 | I45: =G45-H45 -> 28039.418
A46: 2029年1-9月 | B46: =B45-C45+E45 -> 0 | E46: =B46*$H$10/12*(10-1) -> 0 | F46: =B46-C46+E46 -> 0 | G46: =I45 -> 28039.418 | H46: =($I$25/$I$10)/12*9 -> 28039.418 | I46: =G46-H46 -> -2.910383e-11
A47: 合计 | C47: =SUM(C38:C46) -> 400000 | E47: =SUM(E38:E46) -> 72873.459 | H47: =SUM(H38:H46) -> 327126.54
A49: 三、审计说明：
A52: 四、审计结论：
A55: 编制说明：
A56: 承租人应当选择下列方法之一对租赁进行衔接会计处理，并一致应用于其作为承租人的所有租赁：
A57: （一）按照《企业会计准则第28号——会计政策、会计估计变更和差错更正》的规定采用追溯调整法处理。
A58: （二）根据首次执行本准则的累积影响数，调整首次执行本准则当年年初留存收益及财务报表其他相关项目金额，不调整可比期间信息。采用该方法时，应当按照下列规定进行衔接处理：
A59: 1. 对于首次执行日前的融资租赁，承租人在首次执行日应当按照融资租入资产和应付融资租赁款的原账面价值，分别计量使用权资产和租赁负债。
A60: 2. 对于首次执行日前的经营租赁，承租人在首次执行日应当根据剩余租赁付款额按首次执行日承租人增量借款利率折现的现值计量租赁负债，并根据每项租赁选择按照下列两者之一计量使用权资产：
A61: （1）假设自租赁期开始日即采用本准则的账面价值（采用首次执行日的承租人增量借款利率作为折现率）；
A62: （2）与租赁负债相等的金额，并根据预付租金进行必要调整。
A64: 承租人选择按照本准则第六十一条第（二）项规定对租赁进行衔接会计处理的，还应当在首次执行日披露以下信息：
A65: （一）首次执行日计入资产负债表的租赁负债所采用的承租人增量借款利率的加权平均值；
A66: （二）首次执行日前一年度报告期末披露的重大经营租赁的尚未支付的最低租赁付款额按首次执行日承租人增量借款利率折现的现值，与计入首次执行日资产负债表的租赁负债的差额。

Sheet 参考-简化的追溯调整法（首次执行日）
A1: 致同会计师事务所
A2: 首次执行日承租人使用简化的追溯调整法
A3: ='表头（请先填写）'!A2 -> 客户名称： | D3: ='表头（请先填写）'!A4 -> 编制人： | F3: ='表头（请先填写）'!A5 -> 日期： | I3: 索引号：
A4: ='表头（请先填写）'!A3 -> 会计期间：2023年度 | D4: 复核人： | F4: 日期： | I4: 页 次：
A6: 填表说明：
A7: 1、 | B7: 租赁期开始日*(必填） | C7: 必填项，实际移交日，填写格式为YY-MM-DD 如：2019-01-01
A8: 2、 | B8: 约满日期*(必填） | C8: 必填项，合同/协议约定的合同期满日，填写格式为YY-MM-DD 如：2024-09-30
A9: 3、 | B9: 折现率*(必填） | C9: 按承租人首次执行日增量借款利率确定折现率。
A10: 4、 | B10: 摊销期限 | C10: 已设定公式。在整个租赁期内摊销的月份。
A11: 5、 | B11: 月折旧额 | C11: 假设采用直线法计提折旧，如采用其他折旧方法，请自行修改公式。
A13: 输 入 区 域 | D13: 计 算 区 域【新租赁准则首次执行日（2021年1月1日）会计处理】
A14: 使用权资产名称 | E14: 简化（1） | H14: 简化（2）
A15: 租赁期开始日 | C15: 43739 | D15: =INDEX($B$21:B346,COUNTIF($B$21:B346,"<2021年1月")+1) -> 44197 | E15: 借 | F15: 贷 | H15: 借 | I15: 贷
A16: 约满日期(考虑续租可能后） | C16: 47391 | D16: 使用权资产 | E16: =VLOOKUP($D$15,$B$21:H347,7,0)-VLOOKUP($D$15,$B$21:G347,6,0) -> 349299.36 | H16: =I18+I19 -> 363185.6
A17: 本合同折现率（例） | C17: 0.05 | D17: 留存收益 | E17: =F18+F19-E16 -> 13886.245
A18: 摊销期限 | C18: =(YEAR($C$16)-YEAR($C$15))*12+MONTH($C$16)-MONTH($C$15)+1 -> 120 | D18: 租赁负债 | F18: =I348 -> 325685.6 | I18: =I348 -> 325685.6
D19: 预付租金余额 | F19: =C33/12*9 -> 37500 | I19: =F19 -> 37500
A20: 期数 | B20: 月份 | C20: 合同租金 （不含税） | D20: 复原成本、终止租赁罚金等 | E20: 租赁付款额现值(折现到租赁期开始日) | F20: 使用权资产调整 （租赁期开始日前支付的租金、复原成本等） | G20: 月折旧额（次月起计提） | H20: 使用权资产余值 | I20: 租赁付款额现值(折现到2021年1月1日)
A21: 1 | B21: =C15 -> 43739 | E21: =(D21+C21)/(POWER((1+$C$17/12),A21-1)) -> 0 | F21: 50000 | H21: =$E$348+$F$348-G21 -> 403559.45 | I21: =IF(YEAR(B21)<2021,0,C21/(POWER((1+$C$17/12),IF(YEAR($C$15)<2021,DATEDIF("2021年1月",$B21,"M"),$A21)))) -> 0
A22: =A21+1 -> 2 | B22: =EDATE(B21,1) -> 43770 | E22: =(D22+C22)/(POWER((1+$C$17/12),A22-1)) -> 0 | G22: =IF($A22>$C$18,0,($E$348+$F$348)/($C$18-1)) -> 3391.2559 | H22: =H21-G22 -> 400168.19 | I22: =IF(YEAR(B22)<2021,0,C22/(POWER((1+$C$17/12),IF(YEAR($C$15)<2021,DATEDIF("2021年1月",$B22,"M"),$A22)))) -> 0
A23: =A22+1 -> 3 | B23: =EDATE(B22,1) -> 43800 | E23: =(D23+C23)/(POWER((1+$C$17/12),A23-1)) -> 0 | G23: =IF($A23>$C$18,0,($E$348+$F$348)/($C$18-1)) -> 3391.2559 | H23: =H22-G23 -> 396776.94 | I23: =IF(YEAR(B23)<2021,0,C23/(POWER((1+$C$17/12),IF(YEAR($C$15)<2021,DATEDIF("2021年1月",$B23,"M"),$A23)))) -> 0
A24: =A23+1 -> 4 | B24: =EDATE(B23,1) -> 43831 | E24: =(D24+C24)/(POWER((1+$C$17/12),A24-1)) -> 0 | G24: =IF($A24>$C$18,0,($E$348+$F$348)/($C$18-1)) -> 3391.2559 | H24: =H23-G24 -> 393385.68 | I24: =IF(YEAR(B24)<2021,0,C24/(POWER((1+$C$17/12),IF(YEAR($C$15)<2021,DATEDIF("2021年1月",$B24,"M"),$A24)))) -> 0
A25: =A24+1 -> 5 | B25: =EDATE(B24,1) -> 43862 | E25: =(D25+C25)/(POWER((1+$C$17/12),A25-1)) -> 0 | G25: =IF($A25>$C$18,0,($E$348+$F$348)/($C$18-1)) -> 3391.2559 | H25: =H24-G25 -> 389994.43 | I25: =IF(YEAR(B25)<2021,0,C25/(POWER((1+$C$17/12),IF(YEAR($C$15)<2021,DATEDIF("2021年1月",$B25,"M"),$A25)))) -> 0
A26: =A25+1 -> 6 | B26: =EDATE(B25,1) -> 43891 | E26: =(D26+C26)/(POWER((1+$C$17/12),A26-1)) -> 0 | G26: =IF($A26>$C$18,0,($E$348+$F$348)/($C$18-1)) -> 3391.2559 | H26: =H25-G26 -> 386603.17 | I26: =IF(YEAR(B26)<2021,0,C26/(POWER((1+$C$17/12),IF(YEAR($C$15)<2021,DATEDIF("2021年1月",$B26,"M"),$A26)))) -> 0
A27: =A26+1 -> 7 | B27: =EDATE(B26,1) -> 43922 | E27: =(D27+C27)/(POWER((1+$C$17/12),A27-1)) -> 0 | G27: =IF($A27>$C$18,0,($E$348+$F$348)/($C$18-1)) -> 3391.2559 | H27: =H26-G27 -> 383211.91 | I27: =IF(YEAR(B27)<2021,0,C27/(POWER((1+$C$17/12),IF(YEAR($C$15)<2021,DATEDIF("2021年1月",$B27,"M"),$A27)))) -> 0
A28: =A27+1 -> 8 | B28: =EDATE(B27,1) -> 43952 | E28: =(D28+C28)/(POWER((1+$C$17/12),A28-1)) -> 0 | G28: =IF($A28>$C$18,0,($E$348+$F$348)/($C$18-1)) -> 3391.2559 | H28: =H27-G28 -> 379820.66 | I28: =IF(YEAR(B28)<2021,0,C28/(POWER((1+$C$17/12),IF(YEAR($C$15)<2021,DATEDIF("2021年1月",$B28,"M"),$A28)))) -> 0
A29: =A28+1 -> 9 | B29: =EDATE(B28,1) -> 43983 | E29: =(D29+C29)/(POWER((1+$C$17/12),A29-1)) -> 0 | G29: =IF($A29>$C$18,0,($E$348+$F$348)/($C$18-1)) -> 3391.2559 | H29: =H28-G29 -> 376429.4 | I29: =IF(YEAR(B29)<2021,0,C29/(POWER((1+$C$17/12),IF(YEAR($C$15)<2021,DATEDIF("2021年1月",$B29,"M"),$A29)))) -> 0
A30: =A29+1 -> 10 | B30: =EDATE(B29,1) -> 44013 | E30: =(D30+C30)/(POWER((1+$C$17/12),A30-1)) -> 0 | G30: =IF($A30>$C$18,0,($E$348+$F$348)/($C$18-1)) -> 3391.2559 | H30: =H29-G30 -> 373038.15 | I30: =IF(YEAR(B30)<2021,0,C30/(POWER((1+$C$17/12),IF(YEAR($C$15)<2021,DATEDIF("2021年1月",$B30,"M"),$A30)))) -> 0
A31: =A30+1 -> 11 | B31: =EDATE(B30,1) -> 44044 | E31: =(D31+C31)/(POWER((1+$C$17/12),A31-1)) -> 0 | G31: =IF($A31>$C$18,0,($E$348+$F$348)/($C$18-1)) -> 3391.2559 | H31: =H30-G31 -> 369646.89 | I31: =IF(YEAR(B31)<2021,0,C31/(POWER((1+$C$17/12),IF(YEAR($C$15)<2021,DATEDIF("2021年1月",$B31,"M"),$A31)))) -> 0
A32: =A31+1 -> 12 | B32: =EDATE(B31,1) -> 44075 | E32: =(D32+C32)/(POWER((1+$C$17/12),A32-1)) -> 0 | G32: =IF($A32>$C$18,0,($E$348+$F$348)/($C$18-1)) -> 3391.2559 | H32: =H31-G32 -> 366255.63 | I32: =IF(YEAR(B32)<2021,0,C32/(POWER((1+$C$17/12),IF(YEAR($C$15)<2021,DATEDIF("2021年1月",$B32,"M"),$A32)))) -> 0
A33: =A32+1 -> 13 | B33: =EDATE(B32,1) -> 44105 | C33: 50000 | E33: =(D33+C33)/(POWER((1+$C$17/12),A33-1)) -> 47566.412 | G33: =IF($A33>$C$18,0,($E$348+$F$348)/($C$18-1)) -> 3391.2559 | H33: =H32-G33 -> 362864.38 | I33: =IF(YEAR(B33)<2021,0,C33/(POWER((1+$C$17/12),IF(YEAR($C$15)<2021,DATEDIF("2021年1月",$B33,"M"),$A33)))) -> 0
A34: =A33+1 -> 14 | B34: =EDATE(B33,1) -> 44136 | E34: =(D34+C34)/(POWER((1+$C$17/12),A34-1)) -> 0 | G34: =IF($A34>$C$18,0,($E$348+$F$348)/($C$18-1)) -> 3391.2559 | H34: =H33-G34 -> 359473.12 | I34: =IF(YEAR(B34)<2021,0,C34/(POWER((1+$C$17/12),IF(YEAR($C$15)<2021,DATEDIF("2021年1月",$B34,"M"),$A34)))) -> 0
A35: =A34+1 -> 15 | B35: =EDATE(B34,1) -> 44166 | E35: =(D35+C35)/(POWER((1+$C$17/12),A35-1)) -> 0 | G35: =IF($A35>$C$18,0,($E$348+$F$348)/($C$18-1)) -> 3391.2559 | H35: =H34-G35 -> 356081.87 | I35: =IF(YEAR(B35)<2021,0,C35/(POWER((1+$C$17/12),IF(YEAR($C$15)<2021,DATEDIF("2021年1月",$B35,"M"),$A35)))) -> 0
A36: =A35+1 -> 16 | B36: =EDATE(B35,1) -> 44197 | E36: =(D36+C36)/(POWER((1+$C$17/12),A36-1)) -> 0 | G36: =IF($A36>$C$18,0,($E$348+$F$348)/($C$18-1)) -> 3391.2559 | H36: =H35-G36 -> 352690.61 | I36: =IF(YEAR(B36)<2021,0,C36/(POWER((1+$C$17/12),IF(YEAR($C$15)<2021,DATEDIF("2021年1月",$B36,"M"),$A36)))) -> 0
A37: =A36+1 -> 17 | B37: =EDATE(B36,1) -> 44228 | E37: =(D37+C37)/(POWER((1+$C$17/12),A37-1)) -> 0 | G37: =IF($A37>$C$18,0,($E$348+$F$348)/($C$18-1)) -> 3391.2559 | H37: =H36-G37 -> 349299.36 | I37: =IF(YEAR(B37)<2021,0,C37/(POWER((1+$C$17/12),IF(YEAR($C$15)<2021,DATEDIF("2021年1月",$B37,"M"),$A37)))) -> 0
A38: =A37+1 -> 18 | B38: =EDATE(B37,1) -> 44256 | E38: =(D38+C38)/(POWER((1+$C$17/12),A38-1)) -> 0 | G38: =IF($A38>$C$18,0,($E$348+$F$348)/($C$18-1)) -> 3391.2559 | H38: =H37-G38 -> 345908.1 | I38: =IF(YEAR(B38)<2021,0,C38/(POWER((1+$C$17/12),IF(YEAR($C$15)<2021,DATEDIF("2021年1月",$B38,"M"),$A38)))) -> 0
A39: =A38+1 -> 19 | B39: =EDATE(B38,1) -> 44287 | E39: =(D39+C39)/(POWER((1+$C$17/12),A39-1)) -> 0 | G39: =IF($A39>$C$18,0,($E$348+$F$348)/($C$18-1)) -> 3391.2559 | H39: =H38-G39 -> 342516.84 | I39: =IF(YEAR(B39)<2021,0,C39/(POWER((1+$C$17/12),IF(YEAR($C$15)<2021,DATEDIF("2021年1月",$B39,"M"),$A39)))) -> 0
A40: =A39+1 -> 20 | B40: =EDATE(B39,1) -> 44317 | E40: =(D40+C40)/(POWER((1+$C$17/12),A40-1)) -> 0 | G40: =IF($A40>$C$18,0,($E$348+$F$348)/($C$18-1)) -> 3391.2559 | H40: =H39-G40 -> 339125.59 | I40: =IF(YEAR(B40)<2021,0,C40/(POWER((1+$C$17/12),IF(YEAR($C$15)<2021,DATEDIF("2021年1月",$B40,"M"),$A40)))) -> 0
A41: =A40+1 -> 21 | B41: =EDATE(B40,1) -> 44348 | E41: =(D41+C41)/(POWER((1+$C$17/12),A41-1)) -> 0 | G41: =IF($A41>$C$18,0,($E$348+$F$348)/($C$18-1)) -> 3391.2559 | H41: =H40-G41 -> 335734.33 | I41: =IF(YEAR(B41)<2021,0,C41/(POWER((1+$C$17/12),IF(YEAR($C$15)<2021,DATEDIF("2021年1月",$B41,"M"),$A41)))) -> 0
A42: =A41+1 -> 22 | B42: =EDATE(B41,1) -> 44378 | E42: =(D42+C42)/(POWER((1+$C$17/12),A42-1)) -> 0 | G42: =IF($A42>$C$18,0,($E$348+$F$348)/($C$18-1)) -> 3391.2559 | H42: =H41-G42 -> 332343.08 | I42: =IF(YEAR(B42)<2021,0,C42/(POWER((1+$C$17/12),IF(YEAR($C$15)<2021,DATEDIF("2021年1月",$B42,"M"),$A42)))) -> 0
A43: =A42+1 -> 23 | B43: =EDATE(B42,1) -> 44409 | E43: =(D43+C43)/(POWER((1+$C$17/12),A43-1)) -> 0 | G43: =IF($A43>$C$18,0,($E$348+$F$348)/($C$18-1)) -> 3391.2559 | H43: =H42-G43 -> 328951.82 | I43: =IF(YEAR(B43)<2021,0,C43/(POWER((1+$C$17/12),IF(YEAR($C$15)<2021,DATEDIF("2021年1月",$B43,"M"),$A43)))) -> 0
A44: =A43+1 -> 24 | B44: =EDATE(B43,1) -> 44440 | E44: =(D44+C44)/(POWER((1+$C$17/12),A44-1)) -> 0 | G44: =IF($A44>$C$18,0,($E$348+$F$348)/($C$18-1)) -> 3391.2559 | H44: =H43-G44 -> 325560.56 | I44: =IF(YEAR(B44)<2021,0,C44/(POWER((1+$C$17/12),IF(YEAR($C$15)<2021,DATEDIF("2021年1月",$B44,"M"),$A44)))) -> 0
A45: =A44+1 -> 25 | B45: =EDATE(B44,1) -> 44470 | C45: 50000 | E45: =(D45+C45)/(POWER((1+$C$17/12),A45-1)) -> 45251.271 | G45: =IF($A45>$C$18,0,($E$348+$F$348)/($C$18-1)) -> 3391.2559 | H45: =H44-G45 -> 322169.31 | I45: =IF(YEAR(B45)<2021,0,C45/(POWER((1+$C$17/12),IF(YEAR($C$15)<2021,DATEDIF("2021年1月",$B45,"M"),$A45)))) -> 48163.473
A46: =A45+1 -> 26 | B46: =EDATE(B45,1) -> 44501 | E46: =(D46+C46)/(POWER((1+$C$17/12),A46-1)) -> 0 | G46: =IF($A46>$C$18,0,($E$348+$F$348)/($C$18-1)) -> 3391.2559 | H46: =H45-G46 -> 318778.05 | I46: =IF(YEAR(B46)<2021,0,C46/(POWER((1+$C$17/12),IF(YEAR($C$15)<2021,DATEDIF("2021年1月",$B46,"M"),$A46)))) -> 0
A47: =A46+1 -> 27 | B47: =EDATE(B46,1) -> 44531 | E47: =(D47+C47)/(POWER((1+$C$17/12),A47-1)) -> 0 | G47: =IF($A47>$C$18,0,($E$348+$F$348)/($C$18-1)) -> 3391.2559 | H47: =H46-G47 -> 315386.8 | I47: =IF(YEAR(B47)<2021,0,C47/(POWER((1+$C$17/12),IF(YEAR($C$15)<2021,DATEDIF("2021年1月",$B47,"M"),$A47)))) -> 0
A48: =A47+1 -> 28 | B48: =EDATE(B47,1) -> 44562 | E48: =(D48+C48)/(POWER((1+$C$17/12),A48-1)) -> 0 | G48: =IF($A48>$C$18,0,($E$348+$F$348)/($C$18-1)) -> 3391.2559 | H48: =H47-G48 -> 311995.54 | I48: =IF(YEAR(B48)<2021,0,C48/(POWER((1+$C$17/12),IF(YEAR($C$15)<2021,DATEDIF("2021年1月",$B48,"M"),$A48)))) -> 0
A49: =A48+1 -> 29 | B49: =EDATE(B48,1) -> 44593 | E49: =(D49+C49)/(POWER((1+$C$17/12),A49-1)) -> 0 | G49: =IF($A49>$C$18,0,($E$348+$F$348)/($C$18-1)) -> 3391.2559 | H49: =H48-G49 -> 308604.28 | I49: =IF(YEAR(B49)<2021,0,C49/(POWER((1+$C$17/12),IF(YEAR($C$15)<2021,DATEDIF("2021年1月",$B49,"M"),$A49)))) -> 0
A50: =A49+1 -> 30 | B50: =EDATE(B49,1) -> 44621 | E50: =(D50+C50)/(POWER((1+$C$17/12),A50-1)) -> 0 | G50: =IF($A50>$C$18,0,($E$348+$F$348)/($C$18-1)) -> 3391.2559 | H50: =H49-G50 -> 305213.03 | I50: =IF(YEAR(B50)<2021,0,C50/(POWER((1+$C$17/12),IF(YEAR($C$15)<2021,DATEDIF("2021年1月",$B50,"M"),$A50)))) -> 0
A51: =A50+1 -> 31 | B51: =EDATE(B50,1) -> 44652 | E51: =(D51+C51)/(POWER((1+$C$17/12),A51-1)) -> 0 | G51: =IF($A51>$C$18,0,($E$348+$F$348)/($C$18-1)) -> 3391.2559 | H51: =H50-G51 -> 301821.77 | I51: =IF(YEAR(B51)<2021,0,C51/(POWER((1+$C$17/12),IF(YEAR($C$15)<2021,DATEDIF("2021年1月",$B51,"M"),$A51)))) -> 0
A52: =A51+1 -> 32 | B52: =EDATE(B51,1) -> 44682 | E52: =(D52+C52)/(POWER((1+$C$17/12),A52-1)) -> 0 | G52: =IF($A52>$C$18,0,($E$348+$F$348)/($C$18-1)) -> 3391.2559 | H52: =H51-G52 -> 298430.52 | I52: =IF(YEAR(B52)<2021,0,C52/(POWER((1+$C$17/12),IF(YEAR($C$15)<2021,DATEDIF("2021年1月",$B52,"M"),$A52)))) -> 0
A53: =A52+1 -> 33 | B53: =EDATE(B52,1) -> 44713 | E53: =(D53+C53)/(POWER((1+$C$17/12),A53-1)) -> 0 | G53: =IF($A53>$C$18,0,($E$348+$F$348)/($C$18-1)) -> 3391.2559 | H53: =H52-G53 -> 295039.26 | I53: =IF(YEAR(B53)<2021,0,C53/(POWER((1+$C$17/12),IF(YEAR($C$15)<2021,DATEDIF("2021年1月",$B53,"M"),$A53)))) -> 0
A54: =A53+1 -> 34 | B54: =EDATE(B53,1) -> 44743 | E54: =(D54+C54)/(POWER((1+$C$17/12),A54-1)) -> 0 | G54: =IF($A54>$C$18,0,($E$348+$F$348)/($C$18-1)) -> 3391.2559 | H54: =H53-G54 -> 291648.01 | I54: =IF(YEAR(B54)<2021,0,C54/(POWER((1+$C$17/12),IF(YEAR($C$15)<2021,DATEDIF("2021年1月",$B54,"M"),$A54)))) -> 0
A55: =A54+1 -> 35 | B55: =EDATE(B54,1) -> 44774 | E55: =(D55+C55)/(POWER((1+$C$17/12),A55-1)) -> 0 | G55: =IF($A55>$C$18,0,($E$348+$F$348)/($C$18-1)) -> 3391.2559 | H55: =H54-G55 -> 288256.75 | I55: =IF(YEAR(B55)<2021,0,C55/(POWER((1+$C$17/12),IF(YEAR($C$15)<2021,DATEDIF("2021年1月",$B55,"M"),$A55)))) -> 0
A56: =A55+1 -> 36 | B56: =EDATE(B55,1) -> 44805 | E56: =(D56+C56)/(POWER((1+$C$17/12),A56-1)) -> 0 | G56: =IF($A56>$C$18,0,($E$348+$F$348)/($C$18-1)) -> 3391.2559 | H56: =H55-G56 -> 284865.49 | I56: =IF(YEAR(B56)<2021,0,C56/(POWER((1+$C$17/12),IF(YEAR($C$15)<2021,DATEDIF("2021年1月",$B56,"M"),$A56)))) -> 0
A57: =A56+1 -> 37 | B57: =EDATE(B56,1) -> 44835 | C57: 50000 | E57: =(D57+C57)/(POWER((1+$C$17/12),A57-1)) -> 43048.812 | G57: =IF($A57>$C$18,0,($E$348+$F$348)/($C$18-1)) -> 3391.2559 | H57: =H56-G57 -> 281474.24 | I57: =IF(YEAR(B57)<2021,0,C57/(POWER((1+$C$17/12),IF(YEAR($C$15)<2021,DATEDIF("2021年1月",$B57,"M"),$A57)))) -> 45819.272
A58: =A57+1 -> 38 | B58: =EDATE(B57,1) -> 44866 | E58: =(D58+C58)/(POWER((1+$C$17/12),A58-1)) -> 0 | G58: =IF($A58>$C$18,0,($E$348+$F$348)/($C$18-1)) -> 3391.2559 | H58: =H57-G58 -> 278082.98 | I58: =IF(YEAR(B58)<2021,0,C58/(POWER((1+$C$17/12),IF(YEAR($C$15)<2021,DATEDIF("2021年1月",$B58,"M"),$A58)))) -> 0
A59: =A58+1 -> 39 | B59: =EDATE(B58,1) -> 44896 | E59: =(D59+C59)/(POWER((1+$C$17/12),A59-1)) -> 0 | G59: =IF($A59>$C$18,0,($E$348+$F$348)/($C$18-1)) -> 3391.2559 | H59: =H58-G59 -> 274691.73 | I59: =IF(YEAR(B59)<2021,0,C59/(POWER((1+$C$17/12),IF(YEAR($C$15)<2021,DATEDIF("2021年1月",$B59,"M"),$A59)))) -> 0
A60: =A59+1 -> 40 | B60: =EDATE(B59,1) -> 44927 | E60: =(D60+C60)/(POWER((1+$C$17/12),A60-1)) -> 0 | G60: =IF($A60>$C$18,0,($E$348+$F$348)/($C$18-1)) -> 3391.2559 | H60: =H59-G60 -> 271300.47 | I60: =IF(YEAR(B60)<2021,0,C60/(POWER((1+$C$17/12),IF(YEAR($C$15)<2021,DATEDIF("2021年1月",$B60,"M"),$A60)))) -> 0
A61: =A60+1 -> 41 | B61: =EDATE(B60,1) -> 44958 | E61: =(D61+C61)/(POWER((1+$C$17/12),A61-1)) -> 0 | G61: =IF($A61>$C$18,0,($E$348+$F$348)/($C$18-1)) -> 3391.2559 | H61: =H60-G61 -> 267909.21 | I61: =IF(YEAR(B61)<2021,0,C61/(POWER((1+$C$17/12),IF(YEAR($C$15)<2021,DATEDIF("2021年1月",$B61,"M"),$A61)))) -> 0
A62: =A61+1 -> 42 | B62: =EDATE(B61,1) -> 44986 | E62: =(D62+C62)/(POWER((1+$C$17/12),A62-1)) -> 0 | G62: =IF($A62>$C$18,0,($E$348+$F$348)/($C$18-1)) -> 3391.2559 | H62: =H61-G62 -> 264517.96 | I62: =IF(YEAR(B62)<2021,0,C62/(POWER((1+$C$17/12),IF(YEAR($C$15)<2021,DATEDIF("2021年1月",$B62,"M"),$A62)))) -> 0
A63: =A62+1 -> 43 | B63: =EDATE(B62,1) -> 45017 | E63: =(D63+C63)/(POWER((1+$C$17/12),A63-1)) -> 0 | G63: =IF($A63>$C$18,0,($E$348+$F$348)/($C$18-1)) -> 3391.2559 | H63: =H62-G63 -> 261126.7 | I63: =IF(YEAR(B63)<2021,0,C63/(POWER((1+$C$17/12),IF(YEAR($C$15)<2021,DATEDIF("2021年1月",$B63,"M"),$A63)))) -> 0
A64: =A63+1 -> 44 | B64: =EDATE(B63,1) -> 45047 | E64: =(D64+C64)/(POWER((1+$C$17/12),A64-1)) -> 0 | G64: =IF($A64>$C$18,0,($E$348+$F$348)/($C$18-1)) -> 3391.2559 | H64: =H63-G64 -> 257735.45 | I64: =IF(YEAR(B64)<2021,0,C64/(POWER((1+$C$17/12),IF(YEAR($C$15)<2021,DATEDIF("2021年1月",$B64,"M"),$A64)))) -> 0
A65: =A64+1 -> 45 | B65: =EDATE(B64,1) -> 45078 | E65: =(D65+C65)/(POWER((1+$C$17/12),A65-1)) -> 0 | G65: =IF($A65>$C$18,0,($E$348+$F$348)/($C$18-1)) -> 3391.2559 | H65: =H64-G65 -> 254344.19 | I65: =IF(YEAR(B65)<2021,0,C65/(POWER((1+$C$17/12),IF(YEAR($C$15)<2021,DATEDIF("2021年1月",$B65,"M"),$A65)))) -> 0
A66: =A65+1 -> 46 | B66: =EDATE(B65,1) -> 45108 | E66: =(D66+C66)/(POWER((1+$C$17/12),A66-1)) -> 0 | G66: =IF($A66>$C$18,0,($E$348+$F$348)/($C$18-1)) -> 3391.2559 | H66: =H65-G66 -> 250952.93 | I66: =IF(YEAR(B66)<2021,0,C66/(POWER((1+$C$17/12),IF(YEAR($C$15)<2021,DATEDIF("2021年1月",$B66,"M"),$A66)))) -> 0
A67: =A66+1 -> 47 | B67: =EDATE(B66,1) -> 45139 | E67: =(D67+C67)/(POWER((1+$C$17/12),A67-1)) -> 0 | G67: =IF($A67>$C$18,0,($E$348+$F$348)/($C$18-1)) -> 3391.2559 | H67: =H66-G67 -> 247561.68 | I67: =IF(YEAR(B67)<2021,0,C67/(POWER((1+$C$17/12),IF(YEAR($C$15)<2021,DATEDIF("2021年1月",$B67,"M"),$A67)))) -> 0
A68: =A67+1 -> 48 | B68: =EDATE(B67,1) -> 45170 | E68: =(D68+C68)/(POWER((1+$C$17/12),A68-1)) -> 0 | G68: =IF($A68>$C$18,0,($E$348+$F$348)/($C$18-1)) -> 3391.2559 | H68: =H67-G68 -> 244170.42 | I68: =IF(YEAR(B68)<2021,0,C68/(POWER((1+$C$17/12),IF(YEAR($C$15)<2021,DATEDIF("2021年1月",$B68,"M"),$A68)))) -> 0
A69: =A68+1 -> 49 | B69: =EDATE(B68,1) -> 45200 | C69: 50000 | E69: =(D69+C69)/(POWER((1+$C$17/12),A69-1)) -> 40953.551 | G69: =IF($A69>$C$18,0,($E$348+$F$348)/($C$18-1)) -> 3391.2559 | H69: =H68-G69 -> 240779.17 | I69: =IF(YEAR(B69)<2021,0,C69/(POWER((1+$C$17/12),IF(YEAR($C$15)<2021,DATEDIF("2021年1月",$B69,"M"),$A69)))) -> 43589.168
A70: =A69+1 -> 50 | B70: =EDATE(B69,1) -> 45231 | E70: =(D70+C70)/(POWER((1+$C$17/12),A70-1)) -> 0 | G70: =IF($A70>$C$18,0,($E$348+$F$348)/($C$18-1)) -> 3391.2559 | H70: =H69-G70 -> 237387.91 | I70: =IF(YEAR(B70)<2021,0,C70/(POWER((1+$C$17/12),IF(YEAR($C$15)<2021,DATEDIF("2021年1月",$B70,"M"),$A70)))) -> 0
A71: =A70+1 -> 51 | B71: =EDATE(B70,1) -> 45261 | E71: =(D71+C71)/(POWER((1+$C$17/12),A71-1)) -> 0 | G71: =IF($A71>$C$18,0,($E$348+$F$348)/($C$18-1)) -> 3391.2559 | H71: =H70-G71 -> 233996.66 | I71: =IF(YEAR(B71)<2021,0,C71/(POWER((1+$C$17/12),IF(YEAR($C$15)<2021,DATEDIF("2021年1月",$B71,"M"),$A71)))) -> 0
A72: =A71+1 -> 52 | B72: =EDATE(B71,1) -> 45292 | E72: =(D72+C72)/(POWER((1+$C$17/12),A72-1)) -> 0 | G72: =IF($A72>$C$18,0,($E$348+$F$348)/($C$18-1)) -> 3391.2559 | H72: =H71-G72 -> 230605.4 | I72: =IF(YEAR(B72)<2021,0,C72/(POWER((1+$C$17/12),IF(YEAR($C$15)<2021,DATEDIF("2021年1月",$B72,"M"),$A72)))) -> 0
A73: =A72+1 -> 53 | B73: =EDATE(B72,1) -> 45323 | E73: =(D73+C73)/(POWER((1+$C$17/12),A73-1)) -> 0 | G73: =IF($A73>$C$18,0,($E$348+$F$348)/($C$18-1)) -> 3391.2559 | H73: =H72-G73 -> 227214.14 | I73: =IF(YEAR(B73)<2021,0,C73/(POWER((1+$C$17/12),IF(YEAR($C$15)<2021,DATEDIF("2021年1月",$B73,"M"),$A73)))) -> 0
A74: =A73+1 -> 54 | B74: =EDATE(B73,1) -> 45352 | E74: =(D74+C74)/(POWER((1+$C$17/12),A74-1)) -> 0 | G74: =IF($A74>$C$18,0,($E$348+$F$348)/($C$18-1)) -> 3391.2559 | H74: =H73-G74 -> 223822.89 | I74: =IF(YEAR(B74)<2021,0,C74/(POWER((1+$C$17/12),IF(YEAR($C$15)<2021,DATEDIF("2021年1月",$B74,"M"),$A74)))) -> 0
A75: =A74+1 -> 55 | B75: =EDATE(B74,1) -> 45383 | E75: =(D75+C75)/(POWER((1+$C$17/12),A75-1)) -> 0 | G75: =IF($A75>$C$18,0,($E$348+$F$348)/($C$18-1)) -> 3391.2559 | H75: =H74-G75 -> 220431.63 | I75: =IF(YEAR(B75)<2021,0,C75/(POWER((1+$C$17/12),IF(YEAR($C$15)<2021,DATEDIF("2021年1月",$B75,"M"),$A75)))) -> 0
A76: =A75+1 -> 56 | B76: =EDATE(B75,1) -> 45413 | E76: =(D76+C76)/(POWER((1+$C$17/12),A76-1)) -> 0 | G76: =IF($A76>$C$18,0,($E$348+$F$348)/($C$18-1)) -> 3391.2559 | H76: =H75-G76 -> 217040.38 | I76: =IF(YEAR(B76)<2021,0,C76/(POWER((1+$C$17/12),IF(YEAR($C$15)<2021,DATEDIF("2021年1月",$B76,"M"),$A76)))) -> 0
A77: =A76+1 -> 57 | B77: =EDATE(B76,1) -> 45444 | E77: =(D77+C77)/(POWER((1+$C$17/12),A77-1)) -> 0 | G77: =IF($A77>$C$18,0,($E$348+$F$348)/($C$18-1)) -> 3391.2559 | H77: =H76-G77 -> 213649.12 | I77: =IF(YEAR(B77)<2021,0,C77/(POWER((1+$C$17/12),IF(YEAR($C$15)<2021,DATEDIF("2021年1月",$B77,"M"),$A77)))) -> 0
A78: =A77+1 -> 58 | B78: =EDATE(B77,1) -> 45474 | E78: =(D78+C78)/(POWER((1+$C$17/12),A78-1)) -> 0 | G78: =IF($A78>$C$18,0,($E$348+$F$348)/($C$18-1)) -> 3391.2559 | H78: =H77-G78 -> 210257.86 | I78: =IF(YEAR(B78)<2021,0,C78/(POWER((1+$C$17/12),IF(YEAR($C$15)<2021,DATEDIF("2021年1月",$B78,"M"),$A78)))) -> 0
A79: =A78+1 -> 59 | B79: =EDATE(B78,1) -> 45505 | E79: =(D79+C79)/(POWER((1+$C$17/12),A79-1)) -> 0 | G79: =IF($A79>$C$18,0,($E$348+$F$348)/($C$18-1)) -> 3391.2559 | H79: =H78-G79 -> 206866.61 | I79: =IF(YEAR(B79)<2021,0,C79/(POWER((1+$C$17/12),IF(YEAR($C$15)<2021,DATEDIF("2021年1月",$B79,"M"),$A79)))) -> 0
A80: =A79+1 -> 60 | B80: =EDATE(B79,1) -> 45536 | E80: =(D80+C80)/(POWER((1+$C$17/12),A80-1)) -> 0 | G80: =IF($A80>$C$18,0,($E$348+$F$348)/($C$18-1)) -> 3391.2559 | H80: =H79-G80 -> 203475.35 | I80: =IF(YEAR(B80)<2021,0,C80/(POWER((1+$C$17/12),IF(YEAR($C$15)<2021,DATEDIF("2021年1月",$B80,"M"),$A80)))) -> 0
A81: =A80+1 -> 61 | B81: =EDATE(B80,1) -> 45566 | C81: 50000 | E81: =(D81+C81)/(POWER((1+$C$17/12),A81-1)) -> 38960.27 | G81: =IF($A81>$C$18,0,($E$348+$F$348)/($C$18-1)) -> 3391.2559 | H81: =H80-G81 -> 200084.1 | I81: =IF(YEAR(B81)<2021,0,C81/(POWER((1+$C$17/12),IF(YEAR($C$15)<2021,DATEDIF("2021年1月",$B81,"M"),$A81)))) -> 41467.606
A82: =A81+1 -> 62 | B82: =EDATE(B81,1) -> 45597 | E82: =(D82+C82)/(POWER((1+$C$17/12),A82-1)) -> 0 | G82: =IF($A82>$C$18,0,($E$348+$F$348)/($C$18-1)) -> 3391.2559 | H82: =H81-G82 -> 196692.84 | I82: =IF(YEAR(B82)<2021,0,C82/(POWER((1+$C$17/12),IF(YEAR($C$15)<2021,DATEDIF("2021年1月",$B82,"M"),$A82)))) -> 0
A83: =A82+1 -> 63 | B83: =EDATE(B82,1) -> 45627 | E83: =(D83+C83)/(POWER((1+$C$17/12),A83-1)) -> 0 | G83: =IF($A83>$C$18,0,($E$348+$F$348)/($C$18-1)) -> 3391.2559 | H83: =H82-G83 -> 193301.58 | I83: =IF(YEAR(B83)<2021,0,C83/(POWER((1+$C$17/12),IF(YEAR($C$15)<2021,DATEDIF("2021年1月",$B83,"M"),$A83)))) -> 0
A84: =A83+1 -> 64 | B84: =EDATE(B83,1) -> 45658 | E84: =(D84+C84)/(POWER((1+$C$17/12),A84-1)) -> 0 | G84: =IF($A84>$C$18,0,($E$348+$F$348)/($C$18-1)) -> 3391.2559 | H84: =H83-G84 -> 189910.33 | I84: =IF(YEAR(B84)<2021,0,C84/(POWER((1+$C$17/12),IF(YEAR($C$15)<2021,DATEDIF("2021年1月",$B84,"M"),$A84)))) -> 0
A85: =A84+1 -> 65 | B85: =EDATE(B84,1) -> 45689 | E85: =(D85+C85)/(POWER((1+$C$17/12),A85-1)) -> 0 | G85: =IF($A85>$C$18,0,($E$348+$F$348)/($C$18-1)) -> 3391.2559 | H85: =H84-G85 -> 186519.07 | I85: =IF(YEAR(B85)<2021,0,C85/(POWER((1+$C$17/12),IF(YEAR($C$15)<2021,DATEDIF("2021年1月",$B85,"M"),$A85)))) -> 0
A86: =A85+1 -> 66 | B86: =EDATE(B85,1) -> 45717 | E86: =(D86+C86)/(POWER((1+$C$17/12),A86-1)) -> 0 | G86: =IF($A86>$C$18,0,($E$348+$F$348)/($C$18-1)) -> 3391.2559 | H86: =H85-G86 -> 183127.82 | I86: =IF(YEAR(B86)<2021,0,C86/(POWER((1+$C$17/12),IF(YEAR($C$15)<2021,DATEDIF("2021年1月",$B86,"M"),$A86)))) -> 0
A87: =A86+1 -> 67 | B87: =EDATE(B86,1) -> 45748 | E87: =(D87+C87)/(POWER((1+$C$17/12),A87-1)) -> 0 | G87: =IF($A87>$C$18,0,($E$348+$F$348)/($C$18-1)) -> 3391.2559 | H87: =H86-G87 -> 179736.56 | I87: =IF(YEAR(B87)<2021,0,C87/(POWER((1+$C$17/12),IF(YEAR($C$15)<2021,DATEDIF("2021年1月",$B87,"M"),$A87)))) -> 0
A88: =A87+1 -> 68 | B88: =EDATE(B87,1) -> 45778 | E88: =(D88+C88)/(POWER((1+$C$17/12),A88-1)) -> 0 | G88: =IF($A88>$C$18,0,($E$348+$F$348)/($C$18-1)) -> 3391.2559 | H88: =H87-G88 -> 176345.31 | I88: =IF(YEAR(B88)<2021,0,C88/(POWER((1+$C$17/12),IF(YEAR($C$15)<2021,DATEDIF("2021年1月",$B88,"M"),$A88)))) -> 0
A89: =A88+1 -> 69 | B89: =EDATE(B88,1) -> 45809 | E89: =(D89+C89)/(POWER((1+$C$17/12),A89-1)) -> 0 | G89: =IF($A89>$C$18,0,($E$348+$F$348)/($C$18-1)) -> 3391.2559 | H89: =H88-G89 -> 172954.05 | I89: =IF(YEAR(B89)<2021,0,C89/(POWER((1+$C$17/12),IF(YEAR($C$15)<2021,DATEDIF("2021年1月",$B89,"M"),$A89)))) -> 0
A90: =A89+1 -> 70 | B90: =EDATE(B89,1) -> 45839 | E90: =(D90+C90)/(POWER((1+$C$17/12),A90-1)) -> 0 | G90: =IF($A90>$C$18,0,($E$348+$F$348)/($C$18-1)) -> 3391.2559 | H90: =H89-G90 -> 169562.79 | I90: =IF(YEAR(B90)<2021,0,C90/(POWER((1+$C$17/12),IF(YEAR($C$15)<2021,DATEDIF("2021年1月",$B90,"M"),$A90)))) -> 0
A91: =A90+1 -> 71 | B91: =EDATE(B90,1) -> 45870 | E91: =(D91+C91)/(POWER((1+$C$17/12),A91-1)) -> 0 | G91: =IF($A91>$C$18,0,($E$348+$F$348)/($C$18-1)) -> 3391.2559 | H91: =H90-G91 -> 166171.54 | I91: =IF(YEAR(B91)<2021,0,C91/(POWER((1+$C$17/12),IF(YEAR($C$15)<2021,DATEDIF("2021年1月",$B91,"M"),$A91)))) -> 0
A92: =A91+1 -> 72 | B92: =EDATE(B91,1) -> 45901 | E92: =(D92+C92)/(POWER((1+$C$17/12),A92-1)) -> 0 | G92: =IF($A92>$C$18,0,($E$348+$F$348)/($C$18-1)) -> 3391.2559 | H92: =H91-G92 -> 162780.28 | I92: =IF(YEAR(B92)<2021,0,C92/(POWER((1+$C$17/12),IF(YEAR($C$15)<2021,DATEDIF("2021年1月",$B92,"M"),$A92)))) -> 0
A93: =A92+1 -> 73 | B93: =EDATE(B92,1) -> 45931 | C93: 50000 | E93: =(D93+C93)/(POWER((1+$C$17/12),A93-1)) -> 37064.005 | G93: =IF($A93>$C$18,0,($E$348+$F$348)/($C$18-1)) -> 3391.2559 | H93: =H92-G93 -> 159389.03 | I93: =IF(YEAR(B93)<2021,0,C93/(POWER((1+$C$17/12),IF(YEAR($C$15)<2021,DATEDIF("2021年1月",$B93,"M"),$A93)))) -> 39449.305
A94: =A93+1 -> 74 | B94: =EDATE(B93,1) -> 45962 | E94: =(D94+C94)/(POWER((1+$C$17/12),A94-1)) -> 0 | G94: =IF($A94>$C$18,0,($E$348+$F$348)/($C$18-1)) -> 3391.2559 | H94: =H93-G94 -> 155997.77 | I94: =IF(YEAR(B94)<2021,0,C94/(POWER((1+$C$17/12),IF(YEAR($C$15)<2021,DATEDIF("2021年1月",$B94,"M"),$A94)))) -> 0
A95: =A94+1 -> 75 | B95: =EDATE(B94,1) -> 45992 | E95: =(D95+C95)/(POWER((1+$C$17/12),A95-1)) -> 0 | G95: =IF($A95>$C$18,0,($E$348+$F$348)/($C$18-1)) -> 3391.2559 | H95: =H94-G95 -> 152606.51 | I95: =IF(YEAR(B95)<2021,0,C95/(POWER((1+$C$17/12),IF(YEAR($C$15)<2021,DATEDIF("2021年1月",$B95,"M"),$A95)))) -> 0
A96: =A95+1 -> 76 | B96: =EDATE(B95,1) -> 46023 | E96: =(D96+C96)/(POWER((1+$C$17/12),A96-1)) -> 0 | G96: =IF($A96>$C$18,0,($E$348+$F$348)/($C$18-1)) -> 3391.2559 | H96: =H95-G96 -> 149215.26 | I96: =IF(YEAR(B96)<2021,0,C96/(POWER((1+$C$17/12),IF(YEAR($C$15)<2021,DATEDIF("2021年1月",$B96,"M"),$A96)))) -> 0
A97: =A96+1 -> 77 | B97: =EDATE(B96,1) -> 46054 | E97: =(D97+C97)/(POWER((1+$C$17/12),A97-1)) -> 0 | G97: =IF($A97>$C$18,0,($E$348+$F$348)/($C$18-1)) -> 3391.2559 | H97: =H96-G97 -> 145824 | I97: =IF(YEAR(B97)<2021,0,C97/(POWER((1+$C$17/12),IF(YEAR($C$15)<2021,DATEDIF("2021年1月",$B97,"M"),$A97)))) -> 0
A98: =A97+1 -> 78 | B98: =EDATE(B97,1) -> 46082 | E98: =(D98+C98)/(POWER((1+$C$17/12),A98-1)) -> 0 | G98: =IF($A98>$C$18,0,($E$348+$F$348)/($C$18-1)) -> 3391.2559 | H98: =H97-G98 -> 142432.75 | I98: =IF(YEAR(B98)<2021,0,C98/(POWER((1+$C$17/12),IF(YEAR($C$15)<2021,DATEDIF("2021年1月",$B98,"M"),$A98)))) -> 0
A99: =A98+1 -> 79 | B99: =EDATE(B98,1) -> 46113 | E99: =(D99+C99)/(POWER((1+$C$17/12),A99-1)) -> 0 | G99: =IF($A99>$C$18,0,($E$348+$F$348)/($C$18-1)) -> 3391.2559 | H99: =H98-G99 -> 139041.49 | I99: =IF(YEAR(B99)<2021,0,C99/(POWER((1+$C$17/12),IF(YEAR($C$15)<2021,DATEDIF("2021年1月",$B99,"M"),$A99)))) -> 0
A100: =A99+1 -> 80 | B100: =EDATE(B99,1) -> 46143 | E100: =(D100+C100)/(POWER((1+$C$17/12),A100-1)) -> 0 | G100: =IF($A100>$C$18,0,($E$348+$F$348)/($C$18-1)) -> 3391.2559 | H100: =H99-G100 -> 135650.23 | I100: =IF(YEAR(B100)<2021,0,C100/(POWER((1+$C$17/12),IF(YEAR($C$15)<2021,DATEDIF("2021年1月",$B100,"M"),$A100)))) -> 0
A101: =A100+1 -> 81 | B101: =EDATE(B100,1) -> 46174 | E101: =(D101+C101)/(POWER((1+$C$17/12),A101-1)) -> 0 | G101: =IF($A101>$C$18,0,($E$348+$F$348)/($C$18-1)) -> 3391.2559 | H101: =H100-G101 -> 132258.98 | I101: =IF(YEAR(B101)<2021,0,C101/(POWER((1+$C$17/12),IF(YEAR($C$15)<2021,DATEDIF("2021年1月",$B101,"M"),$A101)))) -> 0
A102: =A101+1 -> 82 | B102: =EDATE(B101,1) -> 46204 | E102: =(D102+C102)/(POWER((1+$C$17/12),A102-1)) -> 0 | G102: =IF($A102>$C$18,0,($E$348+$F$348)/($C$18-1)) -> 3391.2559 | H102: =H101-G102 -> 128867.72 | I102: =IF(YEAR(B102)<2021,0,C102/(POWER((1+$C$17/12),IF(YEAR($C$15)<2021,DATEDIF("2021年1月",$B102,"M"),$A102)))) -> 0
...
