Workbook
Name _1、: #REF!
Name _1、: #REF!
Name _1、受本循环影响的相关交易和账户余额: #REF!
Name _1、受本循环影响的相关交易和账户余额: #REF!
Name _2、主要业务活动: #REF!
Name _2、主要业务活动: #REF!
Name _2、注册会计师通常应在本循环中了解与上述业务活动相关的内部控制_如果计划在其他业务循环中对上述: #REF!
Name _2、注册会计师通常应在本循环中了解与上述业务活动相关的内部控制_如果计划在其他业务循环中对上述: #REF!
Name a暗暗: [1]企业表一!$F$20
Name CarryKnown: #REF!
Name CarryKnown: #REF!
Name CarryKnown: #REF!
Name CarryKnown: #REF!
Name CarryKnownTable: #REF!
Name CarryKnownTable: #REF!
Name CarryKnownTable: #REF!
Name CarryKnownTable: #REF!
Name CarryLikely: #REF!
Name CarryLikely: #REF!
Name CarryLikely: #REF!
Name CarryLikely: #REF!
Name CarryLikelyTable: #REF!
Name CarryLikelyTable: #REF!
Name CarryLikelyTable: #REF!
Name CarryLikelyTable: #REF!
Name Carryover_Effect_of_Prior_Year: #REF!
Name Carryover_Effect_of_Prior_Year: #REF!
Name Carryover_Effect_of_Prior_Year: #REF!
Name Carryover_Effect_of_Prior_Year: #REF!
Name CarryoverTitle: #REF!
Name CarryoverTitle: #REF!
Name CarryoverTitle: #REF!
Name CarryoverTitle: #REF!
Name CC_Instruction: #REF!
Name CC_Instruction: #REF!
Name CC_Instruction: #REF!
Name CC_Instruction: #REF!
Name CE_CarryKnownProtection: #REF!
Name CE_CarryKnownProtection: #REF!
Name CE_CarryKnownProtection: #REF!
Name CE_CarryKnownProtection: #REF!
Name CE_CarryKnownTable: #REF!
Name CE_CarryKnownTable: #REF!
Name CE_CarryKnownTable: #REF!
Name CE_CarryKnownTable: #REF!
Name CE_CarryLikely1Protection: #REF!
Name CE_CarryLikely1Protection: #REF!
Name CE_CarryLikely1Protection: #REF!
Name CE_CarryLikely1Protection: #REF!
Name CE_CarryLikely1Table: #REF!
Name CE_CarryLikely1Table: #REF!
Name CE_CarryLikely1Table: #REF!
Name CE_CarryLikely1Table: #REF!
Name CE_CarryLikely2Protection: #REF!
Name CE_CarryLikely2Protection: #REF!
Name CE_CarryLikely2Protection: #REF!
Name CE_CarryLikely2Protection: #REF!
Name CE_CarryLikely2Table: #REF!
Name CE_CarryLikely2Table: #REF!
Name CE_CarryLikely2Table: #REF!

Sheet 表头（请先填写）
A1: 底稿开列时，可先在以下单元格填写有关内容，以便其他底稿引用有关数据： | B1: 序号 | C1: 目录
A2: 客户名称： | B2: 1 | C2: B23-8了解无形资产循环流程和内部控制记录表
A3: 会计期间：2013年度 | B3: 2 | C3: B23-8-1链接-企业对财务报表风险的应对
A4: 编制人： | B4: 3 | C4: B23-8-2穿行测试
A5: 日 期： | B5: 4 | C5: B23-8-3关键控制点选择表（财报审计适用）
B6: 5 | C6: B23-8-4关键控制点选择表（整合审计适用）
A8: 附录、关于工作底稿索引号的编制方法
A9: 1、 工作底稿与审计程序的对应与索引
A10: 为提高工作底稿编制的针对性，各项目负责人提供的所有支持性工作底稿，均应当按自然顺序依次编制索引号，并通过唯一的索引号将审计程序表中的特定程序与相关支持性工作底稿进行一一对应。
A11: 2、 工作底稿索引号的编码规则
A12: （1）索引号的结构：包括三要素，即“项目名称代码”、“—”和“索引顺序号”，如“B23-1”、“B23-2”、........
A13: （2）索引顺序号的分层：可分为多层，如“B23-1-1”；“B23-1-2”；........

Sheet B23-8了解无形资产循环流程和内部控制记录表
A1: 致同会计师事务所
A2: 了解无形资产循环流程和内部控制记录表
A3: ='表头（请先填写）'!A2 -> 客户名称： | C3: ='表头（请先填写）'!A4 -> 编制人： | D3: ='表头（请先填写）'!A5 -> 日 期： | E3: 索引号：B23-8
A4: ='表头（请先填写）'!A3 -> 会计期间：2013年度 | C4: 复核人： | D4: 日期： | E4: 页 次：
A6: 一、本循环涉及的交易、账户及相关业务活动
A7: 1、受本循环影响的相关交易和账户余额
A8: 无形资产、累计摊销及减值准备、开发支出、商誉及减值准备、长期待摊费用、其他非流动资产
A9: 2、本循环涉及的主要业务活动
A10: 序号 | B10: 主要业务活动 | C10: 是否在本循环中进行了解 | D10: 未了解的原因
A11: 1 | B11: 购置Acquisitions | C11: 是 | D11: N/A
A12: 2 | B12: 重新评价Revaluation | C12: 是 | D12: N/A
A13: 3 | B13: 与无形资产有关的调整Intangibles related adjustments | C13: 是 | D13: N/A
B14: ……
A16: 二、本循环业务涉及的主要人员及其职责
A17: 层级或部门 | B17: 姓名 | C17: 职务 | D17: 职责及权限 | E17: 备注
A18: 治理层
A22: 高级管理层
A26: 财务人员
A30: 相关职能部门人员
A35: 二、主要业务活动介绍/无形资产及其他长期资产流程图（需标注容易出错的领域）
A36: 1、购置Acquisitions
A39: 2、重新评价Revaluation
A42: 3、与无形资产有关的调整Intangibles related adjustments

Sheet B23-8-1链接-企业对财务报表风险的应对
A1: 致同会计师事务所
A2: 链接-企业对财务报表风险的应对
A3: ='表头（请先填写）'!A2 -> 客户名称： | B3: ='表头（请先填写）'!A4 -> 编制人： | C3: ='表头（请先填写）'!A5 -> 日 期： | E3: 索引号：B23-8-1
A4: ='表头（请先填写）'!A3 -> 会计期间：2013年度 | B4: 复核人： | C4: 日期： | E4: 页次：
A5: 认定 | B5: 风险（来自于B22-1/B22-2） | C5: 是否适用 | D5: 应对风险的活动 | E5: 应对风险的控制
A6: 价值-毛值 Valuation - Gross | B6: 重估方式不正确 Revaluation measurements not correct | D6: 1.**** | E6: 1.**** 2.****
D7: 2.****
A8: 价值-毛值 Valuation - Gross | B8: 无效的无形资产活动 Intangible asset activity not valid
A9: 价值-净值 Valuation - Net | B9: 无形资产账面价值超过公允价值 Intangible assets carrying value exceeds fair value
A12: 编制说明：
A13: 1、该底稿用于判断选取与风险相关的控制。
A14: 2、加黑的流程为特定风险下推荐的必选流程。如审计项目组认为还有其他的流程需要进一步选择，请打开组合“+”进行选取。
A15: 3、底稿模板中列示的为全部建议风险及流程，如果某些风险被审计单位不适用，请删除该风险及相关控制。
A16: 4、对于适用的流程，请在G列选择“√”。
A26: √
A27: ×

Sheet B23-8-2穿行测试
A1: 致同会计师事务所
A2: 穿行测试（无形资产循环）
A3: ='表头（请先填写）'!A2 -> 客户名称： | E3: ='表头（请先填写）'!A4 -> 编制人： | G3: ='表头（请先填写）'!A5 -> 日 期： | J3: 索引号：B23-8-2
A4: ='表头（请先填写）'!A3 -> 会计期间：2013年度 | E4: 复核人： | G4: 日 期： | J4: 页次：
A5: 活动 | B5: 控制 | D5: 穿行测试方法 （检查/观察） | E5: 所检查（取得）文件名称 | F5: 所检查（取得）文件索引号 | G5: 简述如何执行 | H5: 是否得到执行，未得到执行请解释 | I5: 是否为偏差 并解释原因 （是/否/N/A） | J5: 缺陷评价 索引号
A6: 购置Acquisitions
B7: 1
B8: 2
B9: 3
B10: ……
A12: 重新评价Revaluation
B13: 1
B14: 2
B15: 3
B16: ……
A18: 与无形资产有关的调整Intangibles related adjustments
B19: 1
B20: 2
B21: 3
B22: ……
A28: 编制说明：
A29: 1、根据对被审计单位的了解，选择检查或观察的方法，选取1个样本，填写穿行测试获得的结果。审计人员应该对之前了解的相关内控中企业已有的控制点执行穿行测试。
A30: 2、根据穿行测试的结果判断是否得到执行，如果未得到执行，说明原因，并判断是否为偏差。如果确定为偏差，应对缺陷进行评价，并索引内控缺陷评价表。
A31: 3、穿行测试的方法分为观察和检查。
A32: （1）观察：观察所执行的控制，并确定控制已得到执行。
A33: （2）检查：检查原始文件、单据，提出探求性问题，并确定控制得到执行。
A34: （3）选择穿行测试方法时的考虑因素：
A35: 观察
A36: 通常是无文件证明的控制；
A37: 自动化控制；
A38: 固有风险越低；
A82: 检查
A83: 观察

Sheet B23-8-3关键控制点选择表（财报审计适用）
A1: 致同会计师事务所
A2: 关键控制点选择（无形资产循环）
A3: ='B23-8了解无形资产循环流程和内部控制记录表'!A3 -> 客户名称： | C3: ='B23-8了解无形资产循环流程和内部控制记录表'!C3 -> 编制人： | E3: ='B23-8了解无形资产循环流程和内部控制记录表'!D3 -> 日 期： | I3: 索引号：B23-8-3
A4: ='B23-8了解无形资产循环流程和内部控制记录表'!A4 -> 会计期间：2013年度 | C4: 复核人： | E4: 日 期： | I4: 页次：
A6: 风险、相关的“流程”和“活动”须根据具体情况分析填列，下表列示内容不适用须删除。
A7: 认定 | B7: 风险 | C7: 与风险相关的活动 | D7: 拟测试的控制 | F7: 关键控制点数量（D=A+B+C） | G7: 直接测试方法（询问观察/CAAT/抽样（检查）/重新执行)-A | H7: 管理层-重新执行-B | I7: 管理层-仅复核-C
A8: 价值-毛值 Valuation - Gross
B9: 重估方式不正确 Revaluation measurements not correct | D9: 1 | F9: =IF(OR(G9<>0,H9<>0,I9<>0),1,0) -> 0
D10: 2 | F10: =IF(OR(G10<>0,H10<>0,I10<>0),1,0) -> 0
D11: …… | F11: =IF(OR(G11<>0,H11<>0,I11<>0),1,0) -> 0
B12: 无效的无形资产活动 Intangible asset activity not valid | F12: =IF(OR(G12<>0,H12<>0,I12<>0),1,0) -> 0
F13: =IF(OR(G13<>0,H13<>0,I13<>0),1,0) -> 0
A14: 价值-净值 Valuation - Net | F14: =IF(OR(G14<>0,H14<>0,I14<>0),1,0) -> 0
B15: 无形资产账面价值超过公允价值 Intangible assets carrying value exceeds fair value | F15: =IF(OR(G15<>0,H15<>0,I15<>0),1,0) -> 0
F16: =IF(OR(G16<>0,H16<>0,I16<>0),1,0) -> 0
F17: =IF(OR(G17<>0,H17<>0,I17<>0),1,0) -> 0
C18: 合计 | F18: =SUM(F9:F17) -> 0 | G18: =COUNTA(G9:G17) -> 0 | H18: =COUNTA(H9:H17) -> 0 | I18: =COUNTA(I9:I17) -> 0
G19: =G18/F18 -> #DIV/0! | H19: =H18/F18 -> #DIV/0! | I19: =I18/F18 -> #DIV/0!
F20: 各种测试方法所占比例 | G20: 50-70 | H20: 20-50 | I20: 0-30
A21: 编制说明：
A22: 1、审计人员应根据风险评估的结果（B22-1）确定是否进行控制测试。
A23: 2、选择关键控制点
A24: a.关键控制点的特点：
A25: （1）和将减少测试范围的实质性审计程序强调的风险相同―如果控制有效运行，将减少一些实质性审计程序的范围。如许多被审计单位针对定期存货盘点制定了有效的控制程序，这些控制程序可以直接减少该项目记录在存在性方面发生错误的可能性。相应地，通过控制测试可减少实质程序（存货实地观察）的使用；
A26: （2）设计目的是防止或发现财务报表具体的重大错报风险（旨在实现该目标的控制会因业务性质的不同而不同）；
A27: （3）证据有书面记录；可以通过询问、观察、抽样、重新执行或使用计算机辅助审计技术进行测试；
A28: （4） 包含适当的属性（自动或人工、预防性或检查性、操作性或基础性、有文件记录或无文件记录）以便进行最有效率和效果的测试。
A29: b.关键控制点主要选择原则如下：
A30: （1）对于采用综合性方案以应对的风险，应确保每个风险都有效率并能达到效果的控制点进行测试；
A31: （2）对于每个非常重要的流程，都应当选择关键控制点进行控制测试；
A32: （3）并不一定必须对每一个“比较重要”的流程都进行控制测试，但对于“比较重要”的流程，都不选择关键控制点进行控制测试的情况也是比较罕见。
... A39: 对应关系表如下：
A40: 序号 | B40: PRC
A41: 1 | B41: 询问
A42: 2 | B42: 观察
A43: 3 | B43: 检查
A44: 4 | B44: 重新执行
A45: 10.47 测试方式因控制的性质（是否被记录）以及审计项目组的判断而不同。Voyager中有如下测试方法供审计项目组选择运行有效性评估： • 询问和观察； • 抽样； • 重新执行； • 计算机辅助审计技术（CAAT）； • 管理层―重新执行； •管理层―仅复核； • 服务机构注册会计师。
A46: （1）询问和观察
A47: 10.55在执行询问和观察程序时，审计项目组会通过对被审计单位适当人员的询问和对控制应用情况的观察，以评估控制的执行效果。在Voyager中，使用询问和观察进行控制测试时，经常包括重新执行。因此，审计项目组可通过检查相关数据、文件、报告或电子文件，评价该项控制信息的正确性。
A48: （2）抽样
A49: 10.59 抽样是一种用来测试有文件记录的人工控制运行有效性的测试方法。抽样通常不适于每月和定期执行的控制（例如，各类对账），因为在此期间控制执行的次数较少。此外，由于计算机处理流程固有的一贯性，抽样通常也不用于测试自动化控制。
A50: 10.60 运用抽样测试方法时，针对每个样本所做的工作包括控制执行和此控制附带的信息的正确性两部分。控制执行测试通过复核文件记录，而信息正确性测试则通过重新执行控制程序实现。Voyager可根据预期的控制信赖程度以及实质性程序的计划执行的时间安排（如资产负债表日或接近资产负债表日，资产负债表日后两个月，资产负债表日前超过两个月），以帮助确认样本量。
A51: 10.61在控制测试中采用抽样方法属于属性测试。审计项目组对具体属性进行测试，以确定控制是否得到有效执行。进行此类测试时，测试前，审计项目组应精确界定“错误”或“偏差”的含义。为将风险降至可接受的水平，样本应具有代表性，因此在样本选择上应不偏不倚。
A52: （3）重新执行
A53: 10.63 在采用重新执行测试方法时，审计项目组应通过执行（或重新执行）该控制以测试控制的执行。换言之，审计项目组应选出该控制的运用对象，通过重新执行以确定该控制能否有效运行。在Voyager中，重新执行方法一般用于不经常运行的人工控制。如重新执行可用于测试每月银行存款余额调节的运行有效性。此类测试的主要目的是： • ascertaining whether twelve timely reconciliations were performed 确定是否十二个月每个月都进行了余额调节 testing or reviewing certain of the reconciling items 测试或复核某些对账项目； • testing at least one reconciliation to determine how the control was performed and the correctness of the information subject to the control, including appropriate follow-up of amounts in the reconciliation 至少对一次余额调节进行测试，以确定控制如何执行和与控制相关信息的正确性，包括追踪余额调节中的项目。
A54: 10.64 询问和观察、抽样和计算机辅助审计技术程序中也包括重新执行。
A55: （4）计算机辅助审计技术（CAAT）
A56: 10.65 在自动化环境中，计算机辅助审计技术可用于控制测试。计算机辅助审计技术程序可能各不相同，但均涉及使用IDEA等软件程序查询电子数据。在Voyager中，审计项目组可使用的计算机辅助审计技术程序有两类。
... A66: 财报审计中，通常100%进行直接测试，如拟利用他人工作，各测试方法的分配比例如下：
B67: How Audit Team Tests Key Controls审计项目组如何测试关键控制点 | C67: 重大错报风险
B68: Direct testing 直接测试 | C68: 50% to 70%
B69: Reperform testing performed by others重新执行他人的测试 | C69: 20% to 50%
B70: Review testing performed by others 复核他人的测试 | C70: 0% to 30%
A113: √
A114: ×
A120: 询问&观察
A121: 抽样
A122: 重新执行
A123: CAAT

Sheet B23-8-4关键控制点选择表（整合审计适用）
A1: 致同会计师事务所
A2: 关键控制点选择（无形资产循环）
A3: ='B23-8了解无形资产循环流程和内部控制记录表'!A3 -> 客户名称： | C3: ='B23-8了解无形资产循环流程和内部控制记录表'!C3 -> 编制人： | E3: ='B23-8了解无形资产循环流程和内部控制记录表'!D3 -> 日 期： | I3: 索引号：B23-8-4
A4: ='B23-8了解无形资产循环流程和内部控制记录表'!A4 -> 会计期间：2013年度 | C4: 复核人： | E4: 日 期： | I4: 页次：
A6: 风险、相关的“流程”和“活动”须根据具体情况分析填列，下表列示内容不适用须删除。
A7: 认定 | B7: 风险 | C7: 与风险相关的活动 | D7: 拟测试的控制 | F7: 关键控制点数量（D=A+B+C） | G7: 直接测试方法（询问观察/CAAT/抽样（检查）/重新执行)-A | H7: 管理层-重新执行-B | I7: 管理层-仅复核-C
A8: 存在合理可能的重大错报 Reasonably Possisble
A9: 价值-毛值 Valuation - Gross
B10: 重估方式不正确 Revaluation measurements not correct | D10: 1 | F10: =IF(OR(G10<>0,H10<>0,I10<>0),1,0) -> 0
D11: 2 | F11: =IF(OR(G11<>0,H11<>0,I11<>0),1,0) -> 0
D12: …… | F12: =IF(OR(G12<>0,H12<>0,I12<>0),1,0) -> 0
B13: 无效的无形资产活动 Intangible asset activity not valid | F13: =IF(OR(G13<>0,H13<>0,I13<>0),1,0) -> 0
F14: =IF(OR(G14<>0,H14<>0,I14<>0),1,0) -> 0
A15: 价值-净值 Valuation - Net | F15: =IF(OR(G15<>0,H15<>0,I15<>0),1,0) -> 0
B16: 无形资产账面价值超过公允价值 Intangible assets carrying value exceeds fair value | F16: =IF(OR(G16<>0,H16<>0,I16<>0),1,0) -> 0
F17: =IF(OR(G17<>0,H17<>0,I17<>0),1,0) -> 0
F18: =IF(OR(G18<>0,H18<>0,I18<>0),1,0) -> 0
C19: 合计 | F19: =SUM(F10:F18) -> 0 | G19: =COUNTA(G10:G18) -> 0 | H19: =COUNTA(H10:H18) -> 0 | I19: =COUNTA(I10:I18) -> 0
G20: =G19/F19 -> #DIV/0! | H20: =H19/F19 -> #DIV/0! | I20: =I19/F19 -> #DIV/0!
F21: 各种测试方法所占比例 | G21: 50-70 | H21: 20-50 | I21: 0-30
A22: 不存在合理可能的重大错报 Reasonably Possisble
A23: 价值-毛值 Valuation - Gross
B24: 重估方式不正确 Revaluation measurements not correct | D24: 1 | F24: =IF(OR(G24<>0,H24<>0,I24<>0),1,0) -> 0
D25: 2 | F25: =IF(OR(G25<>0,H25<>0,I25<>0),1,0) -> 0
D26: …… | F26: =IF(OR(G26<>0,H26<>0,I26<>0),1,0) -> 0
B27: 无效的无形资产活动 Intangible asset activity not valid | F27: =IF(OR(G27<>0,H27<>0,I27<>0),1,0) -> 0
F28: =IF(OR(G28<>0,H28<>0,I28<>0),1,0) -> 0
A29: 价值-净值 Valuation - Net | F29: =IF(OR(G29<>0,H29<>0,I29<>0),1,0) -> 0
B30: 无形资产账面价值超过公允价值 Intangible assets carrying value exceeds fair value | F30: =IF(OR(G30<>0,H30<>0,I30<>0),1,0) -> 0
F31: =IF(OR(G31<>0,H31<>0,I31<>0),1,0) -> 0
F32: =IF(OR(G32<>0,H32<>0,I32<>0),1,0) -> 0
C33: 合计 | F33: =SUM(F24:F32) -> 0 | G33: =COUNTA(G24:G32) -> 0 | H33: =COUNTA(H24:H32) -> 0 | I33: =COUNTA(I24:I32) -> 0
G34: =G33/F33 -> #DIV/0! | H34: =H33/F33 -> #DIV/0! | I34: =I33/F33 -> #DIV/0!
F35: 各种测试方法所占比例 | G35: 0-50 | H35: 0-50 | I35: 0-50
A36: 编制说明：
A37: 1、审计人员应根据风险评估的结果（B22-2）确定是否进行控制测试。
A38: 2、选择关键控制点
A39: a.关键控制点的特点：
A40: （1）和将减少测试范围的实质性审计程序强调的风险相同―如果控制有效运行，将减少一些实质性审计程序的范围。如许多被审计单位针对定期存货盘点制定了有效的控制程序，这些控制程序可以直接减少该项目记录在存在性方面发生错误的可能性。相应地，通过控制测试可减少实质程序（存货实地观察）的使用；
A41: （2）设计目的是防止或发现财务报表具体的重大错报风险（旨在实现该目标的控制会因业务性质的不同而不同）；
A42: （3）证据有书面记录；可以通过询问、观察、抽样、重新执行或使用计算机辅助审计技术进行测试；
A43: （4） 包含适当的属性（自动或人工、预防性或检查性、操作性或基础性、有文件记录或无文件记录）以便进行最有效率和效果的测试。
A44: b.关键控制点主要选择原则如下：
A45: （1）对于采用综合性方案以应对的风险，应确保每个风险都有效率并能达到效果的控制点进行测试；
A46: （2）对于每个非常重要的流程，都应当选择关键控制点进行控制测试；
A47: （3）并不一定必须对每一个“比较重要”的流程都进行控制测试，但对于“比较重要”的流程，都不选择关键控制点进行控制测试的情况也是比较罕见。
... A54: 对应关系表如下：
A55: 序号 | B55: PRC
A56: 1 | B56: 询问
A57: 2 | B57: 观察
A58: 3 | B58: 检查
A59: 4 | B59: 重新执行
A60: 10.47 测试方式因控制的性质（是否被记录）以及审计项目组的判断而不同。Voyager中有如下测试方法供审计项目组选择运行有效性评估： • 询问和观察； • 抽样； • 重新执行； • 计算机辅助审计技术（CAAT）； • 管理层―重新执行； •管理层―仅复核； • 服务机构注册会计师。
A61: （1）询问和观察
A62: 10.55在执行询问和观察程序时，审计项目组会通过对被审计单位适当人员的询问和对控制应用情况的观察，以评估控制的执行效果。在Voyager中，使用询问和观察进行控制测试时，经常包括重新执行。因此，审计项目组可通过检查相关数据、文件、报告或电子文件，评价该项控制信息的正确性。
A63: （2）抽样
A64: 10.59 抽样是一种用来测试有文件记录的人工控制运行有效性的测试方法。抽样通常不适于每月和定期执行的控制（例如，各类对账），因为在此期间控制执行的次数较少。此外，由于计算机处理流程固有的一贯性，抽样通常也不用于测试自动化控制。
A65: 10.60 运用抽样测试方法时，针对每个样本所做的工作包括控制执行和此控制附带的信息的正确性两部分。控制执行测试通过复核文件记录，而信息正确性测试则通过重新执行控制程序实现。Voyager可根据预期的控制信赖程度以及实质性程序的计划执行的时间安排（如资产负债表日或接近资产负债表日，资产负债表日后两个月，资产负债表日前超过两个月），以帮助确认样本量。
A66: 10.61在控制测试中采用抽样方法属于属性测试。审计项目组对具体属性进行测试，以确定控制是否得到有效执行。进行此类测试时，测试前，审计项目组应精确界定“错误”或“偏差”的含义。为将风险降至可接受的水平，样本应具有代表性，因此在样本选择上应不偏不倚。
A67: （3）重新执行
A68: 10.63 在采用重新执行测试方法时，审计项目组应通过执行（或重新执行）该控制以测试控制的执行。换言之，审计项目组应选出该控制的运用对象，通过重新执行以确定该控制能否有效运行。在Voyager中，重新执行方法一般用于不经常运行的人工控制。如重新执行可用于测试每月银行存款余额调节的运行有效性。此类测试的主要目的是： • ascertaining whether twelve timely reconciliations were performed 确定是否十二个月每个月都进行了余额调节 testing or reviewing certain of the reconciling items 测试或复核某些对账项目； • testing at least one reconciliation to determine how the control was performed and the correctness of the information subject to the control, including appropriate follow-up of amounts in the reconciliation 至少对一次余额调节进行测试，以确定控制如何执行和与控制相关信息的正确性，包括追踪余额调节中的项目。
A69: 10.64 询问和观察、抽样和计算机辅助审计技术程序中也包括重新执行。
A70: （4）计算机辅助审计技术（CAAT）
A71: 10.65 在自动化环境中，计算机辅助审计技术可用于控制测试。计算机辅助审计技术程序可能各不相同，但均涉及使用IDEA等软件程序查询电子数据。在Voyager中，审计项目组可使用的计算机辅助审计技术程序有两类。
... A81: 在整合审计中，各测试方法的分配比例如下：
B82: How Audit Team Tests Key Controls审计项目组如何测试关键控制点 | C82: Risk of material misstatement 重大错报风险
C83: Reasonably possible 存在合理可能性 | E83: Not reasonably possible存在合理可能性
B84: Direct testing 直接测试 | C84: 50% to 70% | E84: 0% to 50%
B85: Reperform testing performed by others重新执行他人的测试 | C85: 20% to 50% | E85: 0% to 50%
B86: Review testing performed by others 复核他人的测试 | C86: 0% to 30% | E86: 0% to 50%
B87: Note: For not reasonably possible risks, the audit team should ordinarily select 50% of the key controls for testing. The table above reflects this by showing that the maximum number of key controls tested by the audit team would be 50% of the total key controls.
B88: 注： 对于不存在合理可能性的风险，审计项目组通常应选择50%的关键控制点进行测试。上表中，审计项目组测试的关键控制点的数量不超过总数的50%，即为说明了这一点。
A131: √
A132: ×
A138: 询问&观察
A139: 抽样
A140: 重新执行
A141: CAAT
