Workbook
Name _1、: #REF!
Name _1、: #REF!
Name _1、受本循环影响的相关交易和账户余额: #REF!
Name _1、受本循环影响的相关交易和账户余额: #REF!
Name _2、主要业务活动: #REF!
Name _2、主要业务活动: #REF!
Name _2、注册会计师通常应在本循环中了解与上述业务活动相关的内部控制_如果计划在其他业务循环中对上述: #REF!
Name _2、注册会计师通常应在本循环中了解与上述业务活动相关的内部控制_如果计划在其他业务循环中对上述: #REF!
Name a暗暗: [1]企业表一!$F$20
Name CarryKnown: #REF!
Name CarryKnown: #REF!
Name CarryKnown: #REF!
Name CarryKnown: #REF!
Name CarryKnownTable: #REF!
Name CarryKnownTable: #REF!
Name CarryKnownTable: #REF!
Name CarryKnownTable: #REF!
Name CarryLikely: #REF!
Name CarryLikely: #REF!
Name CarryLikely: #REF!
Name CarryLikely: #REF!
Name CarryLikelyTable: #REF!
Name CarryLikelyTable: #REF!
Name CarryLikelyTable: #REF!
Name CarryLikelyTable: #REF!
Name Carryover_Effect_of_Prior_Year: #REF!
Name Carryover_Effect_of_Prior_Year: #REF!
Name Carryover_Effect_of_Prior_Year: #REF!
Name Carryover_Effect_of_Prior_Year: #REF!
Name CarryoverTitle: #REF!
Name CarryoverTitle: #REF!
Name CarryoverTitle: #REF!
Name CarryoverTitle: #REF!
Name CC_Instruction: #REF!
Name CC_Instruction: #REF!
Name CC_Instruction: #REF!
Name CC_Instruction: #REF!
Name CE_CarryKnownProtection: #REF!
Name CE_CarryKnownProtection: #REF!
Name CE_CarryKnownProtection: #REF!
Name CE_CarryKnownProtection: #REF!
Name CE_CarryKnownTable: #REF!
Name CE_CarryKnownTable: #REF!
Name CE_CarryKnownTable: #REF!
Name CE_CarryKnownTable: #REF!
Name CE_CarryLikely1Protection: #REF!
Name CE_CarryLikely1Protection: #REF!
Name CE_CarryLikely1Protection: #REF!
Name CE_CarryLikely1Protection: #REF!
Name CE_CarryLikely1Table: #REF!
Name CE_CarryLikely1Table: #REF!
Name CE_CarryLikely1Table: #REF!
Name CE_CarryLikely1Table: #REF!
Name CE_CarryLikely2Protection: #REF!
Name CE_CarryLikely2Protection: #REF!
Name CE_CarryLikely2Protection: #REF!
Name CE_CarryLikely2Protection: #REF!
Name CE_CarryLikely2Table: #REF!
Name CE_CarryLikely2Table: #REF!
Name CE_CarryLikely2Table: #REF!

Sheet 表头（请先填写）
A1: 底稿开列时，可先在以下单元格填写有关内容，以便其他底稿引用有关数据： | B1: 序号 | C1: 目录
A2: 客户名称： | B2: 1 | C2: B23-1了解收入循环流程和内部控制记录表
A3: 会计期间：2013年度 | B3: 2 | C3: B23-1-1链接-企业对财务报表风险的应对
A4: 编制人： | B4: 3 | C4: B23-1-2穿行测试
A5: 日 期： | B5: 4 | C5: B23-1-3关键控制点选择表（财报审计适用）
B6: 5 | C6: B23-1-4关键控制点选择表（整合审计适用）
A8: 附录、关于工作底稿索引号的编制方法
A9: 1、 工作底稿与审计程序的对应与索引
A10: 为提高工作底稿编制的针对性，各项目负责人提供的所有支持性工作底稿，均应当按自然顺序依次编制索引号，并通过唯一的索引号将审计程序表中的特定程序与相关支持性工作底稿进行一一对应。
A11: 2、 工作底稿索引号的编码规则
A12: （1）索引号的结构：包括三要素，即“项目名称代码”、“—”和“索引顺序号”，如“B23-1”、“B23-2”、........
A13: （2）索引顺序号的分层：可分为多层，如“B23-1-1”；“B23-1-2”；........

Sheet B23-1了解收入循环流程和内部控制记录表
A1: 致同会计师事务所
A2: 了解收入循环流程和内部控制记录表
A3: ='表头（请先填写）'!A2 -> 客户名称： | C3: ='表头（请先填写）'!A4 -> 编制人： | D3: ='表头（请先填写）'!A5 -> 日 期： | E3: 索引号：B23-1
A4: ='表头（请先填写）'!A3 -> 会计期间：2013年度 | C4: 复核人： | D4: 日期： | E4: 页 次：
A6: 一、本循环涉及的交易、账户及相关业务活动
A7: 1、受本循环影响的相关交易和账户余额
A8: 应收票据及坏账准备、应收账款及坏账准备、预收款项、主营业务收入
A9: 2、本循环涉及的主要业务活动
A10: 序号 | B10: 主要业务活动 | C10: 是否在本循环中进行了解 | D10: 未了解的原因
A11: 1 | B11: 新合约/变更订单 New contract/change orders | C11: 是 | D11: N/A
A12: 2 | B12: 销售订单 Sales order | C12: 是 | D12: N/A
A13: 3 | B13: 开具发票 Invoicing | C13: 是 | D13: N/A
A14: 4 | B14: 对客户的收款 Customer collections | C14: 是 | D14: N/A
A15: 5 | B15: 嵌入式衍生工具 Embedded derivatives | C15: 是 | D15: N/A
A16: 6 | B16: 与销售相关的调整、准备 Sales-related adjustments and allowances | C16: 是 | D16: N/A
B17: ……
A19: 二、本循环业务涉及的主要人员及其职责
A20: 层级或部门 | B20: 姓名 | C20: 职务 | D20: 职责及权限 | E20: 备注
A21: 治理层
A25: 高级管理层
A29: 财务人员
A33: 相关职能部门人员
A38: 三、主要业务活动介绍/销售业务流程图（需标注容易出错的领域）
A39: 1、新合约/变更单 New contract/change orders
A42: 2、销售订单 Sales order
A45: 3、开具发票 Invoicing
A49: 4、收款 Customer collections
A52: 5、嵌入式衍生工具 Embedded derivatives
A55: 6、与销售相关的调整、准备 Sales-related adjustments and allowances
A60: 参考事例：

Sheet B23-1-1链接-企业对财务报表风险的应对
A1: 致同会计师事务所
A2: 链接-企业对财务报表风险的应对
A3: ='表头（请先填写）'!A2 -> 客户名称： | B3: ='表头（请先填写）'!A4 -> 编制人： | C3: ='表头（请先填写）'!A5 -> 日 期： | E3: 索引号：B23-1-1
A4: ='表头（请先填写）'!A3 -> 会计期间：2013年度 | B4: 复核人： | C4: 日期： | E4: 页次：
A5: 认定 | B5: 风险（来自于B22-1/B22-2） | C5: 是否适用 | D5: 应对风险的活动 | E5: 应对风险的控制
A6: 完整性 Completeness | B6: 未记录的收入交易 Revenue transactions not recorded | D6: 1.**** | E6: 1.**** 2.****
D7: 2.****
A8: 完整性 Completeness | B8: 协议包含未识别的嵌入衍生工具。Agreements contain unidentified embedded derivatives
A9: 完整性 Completeness | B9: 通过增加客户信用及应收款项的方式隐藏从客户那里收回的款项，从而进行盗窃。 Theft of customer collections concealed by issuing credits
A10: 截止 Cutoff | B10: 未正确计入恰当期间的收入 Revenue not recorded in correct period
A11: 截止 Cutoff | B11: 无效的已接单但未出货的收入 Bill and hold revenue not valid
A12: 存在和发生 Existence/Occurrence | B12: 已记录应收款项不存在 Recorded receivables not valid
A13: 存在和发生 Existence/Occurrence | B13: 为隐藏舞弊而虚构客户 Fictitious customers created to conceal fraud；包括舞弊交易的销售 Revenues fraudulently recognized
A14: 存在和发生 Existence/Occurrence | B14: 包括舞弊交易的销售 Revenues fraudulently recognized
A15: 存在和发生 Existence/Occurrence | B15: 挪用客户收款 Customer collections misappropriated；
A16: 存在和发生 Existence/Occurrence | B16: 未记录的现销 Cash sales not recorded
A17: 存在和发生 Existence/Occurrence | B17: 对于合同的会计记录不符合合同条款 Contract accounting not consistent with terms
A18: 价值-毛值 Valuation - Gross | B18: 错误定价 Products sold not priced correctly
A19: 价值-毛值 Valuation - Gross | B19: 外币计量不恰当 Foreign currency measurements not proper
... A26: 权利/义务 Rights/Obligations | B26: 已完成合同的担保或持续性义务未得到适当的会计处理 Warranties or continuing obligations on completed contracts not accounted for properly
A29: 编制说明：
A30: 1、该底稿用于判断选取与风险相关的控制。
A31: 2、加黑的流程为特定风险下推荐的必选流程。如审计项目组认为还有其他的流程需要进一步选择，请打开组合“+”进行选取。
A32: 3、底稿模板中列示的为全部建议风险及流程，如果某些风险被审计单位不适用，请删除该风险及相关控制。
A33: 4、对于适用的流程，请在G列选择“√”。
A43: √
A44: ×

Sheet B23-1-2穿行测试
A1: 致同会计师事务所
A2: 穿行测试（收入循环）
A3: ='表头（请先填写）'!A2 -> 客户名称： | E3: ='表头（请先填写）'!A4 -> 编制人： | G3: ='表头（请先填写）'!A5 -> 日 期： | J3: 索引号：B23-1-2
A4: ='表头（请先填写）'!A3 -> 会计期间：2013年度 | E4: 复核人： | G4: 日 期： | J4: 页次：
A5: 活动 | B5: 控制 | D5: 穿行测试方法 （检查/观察） | E5: 所检查（取得）文件名称 | F5: 所检查（取得）文件索引号 | G5: 简述如何执行 | H5: 是否得到执行，未得到执行请解释 | I5: 是否为偏差 并解释原因 （是/否/N/A） | J5: 缺陷评价 索引号
A6: 新合约/变更单 New contract/change orders
B7: 1
B8: 2
B9: 3
B10: ……
A12: 销售订单 Sales order
B13: 1
B14: 2
B15: 3
B16: ……
A18: 开具发票 Invoicing
B19: 1
B20: 2
B21: 3
B22: ……
A24: 收款 Customer collections
B25: 1
B26: 2
B27: 3
B28: ……
A30: 嵌入式衍生工具 Embedded derivatives
B31: 1
B32: 2
B33: 3
B34: ……
A36: 与销售相关的调整、准备 Sales-related adjustments and allowances
B37: 1
B38: 2
B39: 3
B40: ……
A45: 编制说明：
A46: 1、根据对被审计单位的了解，选择检查或观察的方法，选取1个样本，填写穿行测试获得的结果。审计人员应该对之前了解的相关内控中企业已有的控制点执行穿行测试。
A47: 2、根据穿行测试的结果判断是否得到执行，如果未得到执行，说明原因，并判断是否为偏差。如果确定为偏差，应对缺陷进行评价，并索引内控缺陷评价表。
A48: 3、穿行测试的方法分为观察和检查。
A49: （1）观察：观察所执行的控制，并确定控制已得到执行。
A50: （2）检查：检查原始文件、单据，提出探求性问题，并确定控制得到执行。
A51: （3）选择穿行测试方法时的考虑因素：
A52: 观察
A53: 通常是无文件证明的控制；
A54: 自动化控制；
A55: 固有风险越低；
A69: 检查
A70: 观察

Sheet B23-1-3关键控制点选择表（财报审计适用）
A1: 致同会计师事务所
A2: 关键控制点选择（收入循环）
A3: ='B23-1了解收入循环流程和内部控制记录表'!A3 -> 客户名称： | C3: ='B23-1了解收入循环流程和内部控制记录表'!C3 -> 编制人： | F3: ='B23-1了解收入循环流程和内部控制记录表'!D3 -> 日 期： | I3: 索引号：B23-1-3
A4: ='B23-1了解收入循环流程和内部控制记录表'!A4 -> 会计期间：2013年度 | C4: 复核人： | F4: 日 期： | I4: 页次：
A6: 风险、相关的“流程”和“活动”须根据具体情况分析填列，下表列示内容不适用须删除。
A7: 认定 | B7: 风险 | C7: 与风险相关的活动 | D7: 拟测试的控制 | F7: 关键控制点数量（D=A+B+C） | G7: 直接测试方法（询问观察/CAAT/抽样（检查）/重新执行)-A | H7: 管理层-重新执行-B | I7: 管理层-仅复核-C
A8: 截止性 Cutoff
B9: 未正确计入恰当期间的收入 Revenue not recorded in correct period | D9: 1 | F9: =IF(OR(G9<>0,H9<>0,I9<>0),1,0) -> 1 | G9: 抽样
D10: 2 | F10: =IF(OR(G10<>0,H10<>0,I10<>0),1,0) -> 0
D11: …… | F11: =IF(OR(G11<>0,H11<>0,I11<>0),1,0) -> 0
B12: 无效的已接单但未出货的收入 Bill and hold revenue not valid | F12: =IF(OR(G12<>0,H12<>0,I12<>0),1,0) -> 1 | G12: CAAT
A13: 存在和发生 Existence/Occurrence | F13: =IF(OR(G13<>0,H13<>0,I13<>0),1,0) -> 0
B14: 虚构客户以隐藏舞弊动机 Fictitious customers created to conceal fraud | D14: 1 | E14: 客户主文档是否定期复核，相关事项得到适当审批 | F14: =IF(OR(G14<>0,H14<>0,I14<>0),1,0) -> 1 | G14: 重新执行
D15: 2 | E15: 在客户主文档中新增项目时，录入信息恰当的与原始资料核对 | F15: =IF(OR(G15<>0,H15<>0,I15<>0),1,0) -> 1 | G15: 抽样
F16: =IF(OR(G16<>0,H16<>0,I16<>0),1,0) -> 0
B17: 包括舞弊交易的销售 Revenues fraudulently recognized | F17: =IF(OR(G17<>0,H17<>0,I17<>0),1,0) -> 0
B18: 挪用客户收款 Customer collections misappropriated | F18: =IF(OR(G18<>0,H18<>0,I18<>0),1,0) -> 0
B19: 已记录应收款项不存在 Recorded receivables not valid | F19: =IF(OR(G19<>0,H19<>0,I19<>0),1,0) -> 0
B20: 未记录的现销 Cash sales not recorded | F20: =IF(OR(G20<>0,H20<>0,I20<>0),1,0) -> 0
B21: 对于合同的会计记录不符合合同条款 Contract accounting not consistent with terms | F21: =IF(OR(G21<>0,H21<>0,I21<>0),1,0) -> 0
F22: =IF(OR(G22<>0,H22<>0,I22<>0),1,0) -> 0
A23: 准确性 - 净值 Valuation - Net | F23: =IF(OR(G23<>0,H23<>0,I23<>0),1,0) -> 0
B24: 坏账准备计提不充分 Allowance for doubtful accounts not adequate | F24: =IF(OR(G24<>0,H24<>0,I24<>0),1,0) -> 0
B25: 退货和客户索赔负债不足够 Goods returned and customer claims liabilities not adequate | F25: =IF(OR(G25<>0,H25<>0,I25<>0),1,0) -> 0
B26: 不恰当的利息计算 Imputed interest not proper | F26: =IF(OR(G26<>0,H26<>0,I26<>0),1,0) -> 0
F27: =IF(OR(G27<>0,H27<>0,I27<>0),1,0) -> 0
A28: 准确性 - 毛值 Valuation - Gross | F28: =IF(OR(G28<>0,H28<>0,I28<>0),1,0) -> 0
B29: 计价不正确 Pricing not correct | F29: =IF(OR(G29<>0,H29<>0,I29<>0),1,0) -> 0
B30: 估计的合同收入不准确 Contract estimates not accurate | F30: =IF(OR(G30<>0,H30<>0,I30<>0),1,0) -> 0
B31: 外币计量不恰当 Foreign currency measurements not proper | F31: =IF(OR(G31<>0,H31<>0,I31<>0),1,0) -> 0
B32: 多重要素安排会计核算不恰当 Multiple-element arrangements not accounted for properly | F32: =IF(OR(G32<>0,H32<>0,I32<>0),1,0) -> 0
F33: =IF(OR(G33<>0,H33<>0,I33<>0),1,0) -> 0
A34: 完整性 Completeness | F34: =IF(OR(G34<>0,H34<>0,I34<>0),1,0) -> 0
B35: 收入记录不完整 Revenue transactions not recorded | F35: =IF(OR(G35<>0,H35<>0,I35<>0),1,0) -> 0
B36: 协议包含未识别的嵌入衍生工具 Agreements contain unidentified embedded derivatives | F36: =IF(OR(G36<>0,H36<>0,I36<>0),1,0) -> 0
B37: 通过操纵客户信用额度，盗用客户收款 Theft of customer collections concealed by issuing credits | F37: =IF(OR(G37<>0,H37<>0,I37<>0),1,0) -> 0
F38: =IF(OR(G38<>0,H38<>0,I38<>0),1,0) -> 0
A39: 权利/义务 Rights/Obligations | F39: =IF(OR(G39<>0,H39<>0,I39<>0),1,0) -> 0
B40: 应收帐款销售和折扣记录不恰当 Receivables discounted or sold not accounted for properly | F40: =IF(OR(G40<>0,H40<>0,I40<>0),1,0) -> 0
B41: 已完成合同的担保或持续性义务未得到适当的会计处理 Warranties or continuing obligations on completed contracts not accounted for properly | F41: =IF(OR(G41<>0,H41<>0,I41<>0),1,0) -> 0
F42: =IF(OR(G42<>0,H42<>0,I42<>0),1,0) -> 0
F43: =IF(OR(G43<>0,H43<>0,I43<>0),1,0) -> 0
C44: 合计 | F44: =SUM(F9:F43) -> 4 | G44: =COUNTA(G9:G43) -> 4 | H44: =COUNTA(H9:H43) -> 0 | I44: =COUNTA(I9:I43) -> 0
G45: =G44/F44 -> 1 | H45: =H44/F44 -> 0 | I45: =I44/F44 -> 0
F46: 各种测试方法所占比例 | G46: 50-70 | H46: 20-50 | I46: 0-30
A47: 编制说明：
A48: 1、审计人员应根据风险评估的结果（B22-1）确定是否进行控制测试。
A49: 2、选择关键控制点
A50: a.关键控制点的特点：
A51: （1）和将减少测试范围的实质性审计程序强调的风险相同―如果控制有效运行，将减少一些实质性审计程序的范围。如许多被审计单位针对定期存货盘点制定了有效的控制程序，这些控制程序可以直接减少该项目记录在存在性方面发生错误的可能性。相应地，通过控制测试可减少实质程序（存货实地观察）的使用；
A52: （2）设计目的是防止或发现财务报表具体的重大错报风险（旨在实现该目标的控制会因业务性质的不同而不同）；
A53: （3）证据有书面记录；可以通过询问、观察、抽样、重新执行或使用计算机辅助审计技术进行测试；
A54: （4） 包含适当的属性（自动或人工、预防性或检查性、操作性或基础性、有文件记录或无文件记录）以便进行最有效率和效果的测试。
A55: b.关键控制点主要选择原则如下：
A56: （1）对于采用综合性方案以应对的风险，应确保每个风险都有效率并能达到效果的控制点进行测试；
A57: （2）对于每个非常重要的流程，都应当选择关键控制点进行控制测试；
A58: （3）并不一定必须对每一个“比较重要”的流程都进行控制测试，但对于“比较重要”的流程，都不选择关键控制点进行控制测试的情况也是比较罕见。
... A65: 对应关系表如下：
A66: 序号 | B66: PRC
A67: 1 | B67: 询问
A68: 2 | B68: 观察
A69: 3 | B69: 检查
A70: 4 | B70: 重新执行
A71: 10.47 测试方式因控制的性质（是否被记录）以及审计项目组的判断而不同。Voyager中有如下测试方法供审计项目组选择运行有效性评估： • 询问和观察； • 抽样； • 重新执行； • 计算机辅助审计技术（CAAT）； • 管理层―重新执行； •管理层―仅复核； • 服务机构注册会计师。
A72: （1）询问和观察
A73: 10.55在执行询问和观察程序时，审计项目组会通过对被审计单位适当人员的询问和对控制应用情况的观察，以评估控制的执行效果。在Voyager中，使用询问和观察进行控制测试时，经常包括重新执行。因此，审计项目组可通过检查相关数据、文件、报告或电子文件，评价该项控制信息的正确性。
A74: （2）抽样
A75: 10.59 抽样是一种用来测试有文件记录的人工控制运行有效性的测试方法。抽样通常不适于每月和定期执行的控制（例如，各类对账），因为在此期间控制执行的次数较少。此外，由于计算机处理流程固有的一贯性，抽样通常也不用于测试自动化控制。
A76: 10.60 运用抽样测试方法时，针对每个样本所做的工作包括控制执行和此控制附带的信息的正确性两部分。控制执行测试通过复核文件记录，而信息正确性测试则通过重新执行控制程序实现。Voyager可根据预期的控制信赖程度以及实质性程序的计划执行的时间安排（如资产负债表日或接近资产负债表日，资产负债表日后两个月，资产负债表日前超过两个月），以帮助确认样本量。
A77: 10.61在控制测试中采用抽样方法属于属性测试。审计项目组对具体属性进行测试，以确定控制是否得到有效执行。进行此类测试时，测试前，审计项目组应精确界定“错误”或“偏差”的含义。为将风险降至可接受的水平，样本应具有代表性，因此在样本选择上应不偏不倚。
A78: （3）重新执行
A79: 10.63 在采用重新执行测试方法时，审计项目组应通过执行（或重新执行）该控制以测试控制的执行。换言之，审计项目组应选出该控制的运用对象，通过重新执行以确定该控制能否有效运行。在Voyager中，重新执行方法一般用于不经常运行的人工控制。如重新执行可用于测试每月银行存款余额调节的运行有效性。此类测试的主要目的是： • ascertaining whether twelve timely reconciliations were performed 确定是否十二个月每个月都进行了余额调节 testing or reviewing certain of the reconciling items 测试或复核某些对账项目； • testing at least one reconciliation to determine how the control was performed and the correctness of the information subject to the control, including appropriate follow-up of amounts in the reconciliation 至少对一次余额调节进行测试，以确定控制如何执行和与控制相关信息的正确性，包括追踪余额调节中的项目。
A80: 10.64 询问和观察、抽样和计算机辅助审计技术程序中也包括重新执行。
A81: （4）计算机辅助审计技术（CAAT）
A82: 10.65 在自动化环境中，计算机辅助审计技术可用于控制测试。计算机辅助审计技术程序可能各不相同，但均涉及使用IDEA等软件程序查询电子数据。在Voyager中，审计项目组可使用的计算机辅助审计技术程序有两类。
... A92: 财报审计中，通常100%进行直接测试，如拟利用他人工作，各测试方法的分配比例如下：
B93: How Audit Team Tests Key Controls审计项目组如何测试关键控制点 | C93: 重大错报风险
B94: Direct testing 直接测试 | C94: 50% to 70%
B95: Reperform testing performed by others重新执行他人的测试 | C95: 20% to 50%
B96: Review testing performed by others 复核他人的测试 | C96: 0% to 30%
A139: √
A140: ×
A146: 询问&观察
A147: 抽样
A148: 重新执行
A149: CAAT

Sheet B23-1-4关键控制点选择表（整合审计适用）
A1: 致同会计师事务所
A2: 关键控制点选择（收入循环）
A3: ='B23-1了解收入循环流程和内部控制记录表'!A3 -> 客户名称： | C3: ='B23-1了解收入循环流程和内部控制记录表'!C3 -> 编制人： | F3: ='B23-1了解收入循环流程和内部控制记录表'!D3 -> 日 期： | I3: 索引号：B23-1-4
A4: ='B23-1了解收入循环流程和内部控制记录表'!A4 -> 会计期间：2013年度 | C4: 复核人： | F4: 日 期： | I4: 页次：
A6: 风险、相关的“流程”和“活动”须根据具体情况分析填列，下表列示内容不适用须删除。
A7: 认定 | B7: 风险 | C7: 与风险相关的活动 | D7: 拟测试的控制 | F7: 关键控制点数量（D=A+B+C） | G7: 直接测试方法（询问观察/CAAT/抽样（检查）/重新执行)-A | H7: 管理层-重新执行-B | I7: 管理层-仅复核-C
A8: 存在合理可能的重大错报 Reasonably Possisble
A9: 截止性 Cutoff
B10: 未正确计入恰当期间的收入 Revenue not recorded in correct period | D10: 1 | F10: =IF(OR(G10<>0,H10<>0,I10<>0),1,0) -> 0
D11: 2 | F11: =IF(OR(G11<>0,H11<>0,I11<>0),1,0) -> 0
D12: …… | F12: =IF(OR(G12<>0,H12<>0,I12<>0),1,0) -> 0
B13: 无效的已接单但未出货的收入 Bill and hold revenue not valid | F13: =IF(OR(G13<>0,H13<>0,I13<>0),1,0) -> 0
A14: 存在和发生 Existence/Occurrence | F14: =IF(OR(G14<>0,H14<>0,I14<>0),1,0) -> 0
B15: 虚构客户以隐藏舞弊动机 Fictitious customers created to conceal fraud | D15: 1 | F15: =IF(OR(G15<>0,H15<>0,I15<>0),1,0) -> 0
D16: 2 | F16: =IF(OR(G16<>0,H16<>0,I16<>0),1,0) -> 0
F17: =IF(OR(G17<>0,H17<>0,I17<>0),1,0) -> 0
B18: 包括舞弊交易的销售 Revenues fraudulently recognized | F18: =IF(OR(G18<>0,H18<>0,I18<>0),1,0) -> 0
B19: 挪用客户收款 Customer collections misappropriated | F19: =IF(OR(G19<>0,H19<>0,I19<>0),1,0) -> 0
B20: 已记录应收款项不存在 Recorded receivables not valid | F20: =IF(OR(G20<>0,H20<>0,I20<>0),1,0) -> 0
B21: 未记录的现销 Cash sales not recorded | F21: =IF(OR(G21<>0,H21<>0,I21<>0),1,0) -> 0
B22: 对于合同的会计记录不符合合同条款 Contract accounting not consistent with terms | F22: =IF(OR(G22<>0,H22<>0,I22<>0),1,0) -> 0
F23: =IF(OR(G23<>0,H23<>0,I23<>0),1,0) -> 0
A24: 准确性 - 净值 Valuation - Net | F24: =IF(OR(G24<>0,H24<>0,I24<>0),1,0) -> 0
B25: 坏账准备计提不充分 Allowance for doubtful accounts not adequate | F25: =IF(OR(G25<>0,H25<>0,I25<>0),1,0) -> 0
B26: 退货和客户索赔负债不足够 Goods returned and customer claims liabilities not adequate | F26: =IF(OR(G26<>0,H26<>0,I26<>0),1,0) -> 0
B27: 不恰当的利息计算 Imputed interest not proper | F27: =IF(OR(G27<>0,H27<>0,I27<>0),1,0) -> 0
F28: =IF(OR(G28<>0,H28<>0,I28<>0),1,0) -> 0
A29: 准确性 - 毛值 Valuation - Gross | F29: =IF(OR(G29<>0,H29<>0,I29<>0),1,0) -> 0
B30: 计价不正确 Pricing not correct | F30: =IF(OR(G30<>0,H30<>0,I30<>0),1,0) -> 0
B31: 估计的合同收入不准确 Contract estimates not accurate | F31: =IF(OR(G31<>0,H31<>0,I31<>0),1,0) -> 0
B32: 外币计量不恰当 Foreign currency measurements not proper | F32: =IF(OR(G32<>0,H32<>0,I32<>0),1,0) -> 0
B33: 多重要素安排会计核算不恰当 Multiple-element arrangements not accounted for properly | F33: =IF(OR(G33<>0,H33<>0,I33<>0),1,0) -> 0
F34: =IF(OR(G34<>0,H34<>0,I34<>0),1,0) -> 0
A35: 完整性 Completeness | F35: =IF(OR(G35<>0,H35<>0,I35<>0),1,0) -> 0
B36: 收入记录不完整 Revenue transactions not recorded | F36: =IF(OR(G36<>0,H36<>0,I36<>0),1,0) -> 0
B37: 协议包含未识别的嵌入衍生工具 Agreements contain unidentified embedded derivatives | F37: =IF(OR(G37<>0,H37<>0,I37<>0),1,0) -> 0
B38: 通过操纵客户信用额度，盗用客户收款 Theft of customer collections concealed by issuing credits | F38: =IF(OR(G38<>0,H38<>0,I38<>0),1,0) -> 0
F39: =IF(OR(G39<>0,H39<>0,I39<>0),1,0) -> 0
A40: 权利/义务 Rights/Obligations | F40: =IF(OR(G40<>0,H40<>0,I40<>0),1,0) -> 0
B41: 应收帐款销售和折扣记录不恰当 Receivables discounted or sold not accounted for properly | F41: =IF(OR(G41<>0,H41<>0,I41<>0),1,0) -> 0
B42: 已完成合同的担保或持续性义务未得到适当的会计处理 Warranties or continuing obligations on completed contracts not accounted for properly | F42: =IF(OR(G42<>0,H42<>0,I42<>0),1,0) -> 0
F43: =IF(OR(G43<>0,H43<>0,I43<>0),1,0) -> 0
F44: =IF(OR(G44<>0,H44<>0,I44<>0),1,0) -> 0
C45: 合计 | F45: =SUM(F10:F44) -> 0 | G45: =COUNTA(G10:G44) -> 0 | H45: =COUNTA(H10:H44) -> 0 | I45: =COUNTA(I10:I44) -> 0
G46: =G45/F45 -> #DIV/0! | H46: =H45/F45 -> #DIV/0! | I46: =I45/F45 -> #DIV/0!
F47: 各种测试方法所占比例 | G47: 50-70 | H47: 20-50 | I47: 0-30
A48: 不存在合理可能的重大错报 Reasonably Possisble
A49: 截止性 Cutoff
B50: 未正确计入恰当期间的收入 Revenue not recorded in correct period | D50: 1 | F50: =IF(OR(G50<>0,H50<>0,I50<>0),1,0) -> 0
D51: 2 | F51: =IF(OR(G51<>0,H51<>0,I51<>0),1,0) -> 0
D52: …… | F52: =IF(OR(G52<>0,H52<>0,I52<>0),1,0) -> 0
B53: 无效的已接单但未出货的收入 Bill and hold revenue not valid | F53: =IF(OR(G53<>0,H53<>0,I53<>0),1,0) -> 0
A54: 存在和发生 Existence/Occurrence | F54: =IF(OR(G54<>0,H54<>0,I54<>0),1,0) -> 0
B55: 虚构客户以隐藏舞弊动机 Fictitious customers created to conceal fraud | F55: =IF(OR(G55<>0,H55<>0,I55<>0),1,0) -> 0
B56: 包括舞弊交易的销售 Revenues fraudulently recognized | F56: =IF(OR(G56<>0,H56<>0,I56<>0),1,0) -> 0
B57: 挪用客户收款 Customer collections misappropriated | F57: =IF(OR(G57<>0,H57<>0,I57<>0),1,0) -> 0
B58: 已记录应收款项不存在 Recorded receivables not valid | F58: =IF(OR(G58<>0,H58<>0,I58<>0),1,0) -> 0
B59: 未记录的现销 Cash sales not recorded | F59: =IF(OR(G59<>0,H59<>0,I59<>0),1,0) -> 0
B60: 对于合同的会计记录不符合合同条款 Contract accounting not consistent with terms | F60: =IF(OR(G60<>0,H60<>0,I60<>0),1,0) -> 0
F61: =IF(OR(G61<>0,H61<>0,I61<>0),1,0) -> 0
A62: 准确性 - 净值 Valuation - Net | F62: =IF(OR(G62<>0,H62<>0,I62<>0),1,0) -> 0
B63: 坏账准备计提不充分 Allowance for doubtful accounts not adequate | F63: =IF(OR(G63<>0,H63<>0,I63<>0),1,0) -> 0
B64: 退货和客户索赔负债不足够 Goods returned and customer claims liabilities not adequate | F64: =IF(OR(G64<>0,H64<>0,I64<>0),1,0) -> 0
B65: 不恰当的利息计算 Imputed interest not proper | F65: =IF(OR(G65<>0,H65<>0,I65<>0),1,0) -> 0
F66: =IF(OR(G66<>0,H66<>0,I66<>0),1,0) -> 0
A67: 准确性 - 毛值 Valuation - Gross | F67: =IF(OR(G67<>0,H67<>0,I67<>0),1,0) -> 0
B68: 计价不正确 Pricing not correct | F68: =IF(OR(G68<>0,H68<>0,I68<>0),1,0) -> 0
B69: 估计的合同收入不准确 Contract estimates not accurate | F69: =IF(OR(G69<>0,H69<>0,I69<>0),1,0) -> 0
B70: 外币计量不恰当 Foreign currency measurements not proper | F70: =IF(OR(G70<>0,H70<>0,I70<>0),1,0) -> 0
B71: 多重要素安排会计核算不恰当 Multiple-element arrangements not accounted for properly | F71: =IF(OR(G71<>0,H71<>0,I71<>0),1,0) -> 0
F72: =IF(OR(G72<>0,H72<>0,I72<>0),1,0) -> 0
A73: 完整性 Completeness | F73: =IF(OR(G73<>0,H73<>0,I73<>0),1,0) -> 0
B74: 收入记录不完整 Revenue transactions not recorded | F74: =IF(OR(G74<>0,H74<>0,I74<>0),1,0) -> 0
B75: 协议包含未识别的嵌入衍生工具 Agreements contain unidentified embedded derivatives | F75: =IF(OR(G75<>0,H75<>0,I75<>0),1,0) -> 0
B76: 通过操纵客户信用额度，盗用客户收款 Theft of customer collections concealed by issuing credits | F76: =IF(OR(G76<>0,H76<>0,I76<>0),1,0) -> 0
F77: =IF(OR(G77<>0,H77<>0,I77<>0),1,0) -> 0
A78: 权利/义务 Rights/Obligations | F78: =IF(OR(G78<>0,H78<>0,I78<>0),1,0) -> 0
B79: 应收帐款销售和折扣记录不恰当 Receivables discounted or sold not accounted for properly | F79: =IF(OR(G79<>0,H79<>0,I79<>0),1,0) -> 0
B80: 已完成合同的担保或持续性义务未得到适当的会计处理 Warranties or continuing obligations on completed contracts not accounted for properly | F80: =IF(OR(G80<>0,H80<>0,I80<>0),1,0) -> 0
C83: 合计 | F83: =SUM(F50:F82) -> 0 | G83: =COUNTA(G50:G82) -> 0 | H83: =COUNTA(H50:H82) -> 0 | I83: =COUNTA(I50:I82) -> 0
G84: =G83/F83 -> #DIV/0! | H84: =H83/F83 -> #DIV/0! | I84: =I83/F83 -> #DIV/0!
F85: 各种测试方法所占比例 | G85: 0-50 | H85: 0-50 | I85: 0-50
A86: 编制说明：
A87: 1、审计人员应根据风险评估的结果（B22-2）确定是否进行控制测试。
A88: 2、选择关键控制点
A89: a.关键控制点的特点：
A90: （1）和将减少测试范围的实质性审计程序强调的风险相同―如果控制有效运行，将减少一些实质性审计程序的范围。如许多被审计单位针对定期存货盘点制定了有效的控制程序，这些控制程序可以直接减少该项目记录在存在性方面发生错误的可能性。相应地，通过控制测试可减少实质程序（存货实地观察）的使用；
A91: （2）设计目的是防止或发现财务报表具体的重大错报风险（旨在实现该目标的控制会因业务性质的不同而不同）；
A92: （3）证据有书面记录；可以通过询问、观察、抽样、重新执行或使用计算机辅助审计技术进行测试；
A93: （4） 包含适当的属性（自动或人工、预防性或检查性、操作性或基础性、有文件记录或无文件记录）以便进行最有效率和效果的测试。
A94: b.关键控制点主要选择原则如下：
A95: （1）对于采用综合性方案以应对的风险，应确保每个风险都有效率并能达到效果的控制点进行测试；
A96: （2）对于每个非常重要的流程，都应当选择关键控制点进行控制测试；
A97: （3）并不一定必须对每一个“比较重要”的流程都进行控制测试，但对于“比较重要”的流程，都不选择关键控制点进行控制测试的情况也是比较罕见。
... A104: 对应关系表如下：
A105: 序号 | B105: PRC
A106: 1 | B106: 询问
A107: 2 | B107: 观察
A108: 3 | B108: 检查
A109: 4 | B109: 重新执行
...
