Workbook
Name Current: Lists!$A$8:$A$9
Name NA: Lists!$A$11:$A$13
Name Type: Lists!$A$4:$A$6
Name YesNo: Lists!$A$1:$A$2

Sheet Sheet5
A1: 9 | B1: 18 | C1: A | D1: A | E1: I | F1: Evaluation of PAJEs
C2: 1 | D2: 7 | E2: 27

Sheet GT_Custom
A1: C1 | B1: Custom 1
A2: C2 | B2: Custom 2
A3: C3 | B3: Custom 3
A4: C4 | B4: Custom 4
A5: C5 | B5: Custom 5
A6: C6 | B6: Custom 6
A7: C7 | B7: Custom 7
A8: C8 | B8: Custom 8

Sheet B30-12 指令—已识别组成部分错报汇总表
B1: 致同会计师事务所
B2: 指令—已识别组成部分错报汇总表
B3: 客户名称： | C3: 编制人： | D3: 日期： | E3: 索 引 号： | F3: B30-12
B4: 会计期间： | C4: 复核人： | D4: 日期： | E4: 页 次：
B6: 指令—已识别组成部分错报汇总表
B8: 45352
B9: 适用于自2023年12月15日或之后开始的期间的集团财务报表审计。
B10: 致集团注册会计师的指导性说明：本模板用于组成部分注册会计师（无论是否为成员所）沟通已识别错报。只要能提供必要信息，可使用不同的模板或格式。
B11: 致组成部分注册会计师的指导性说明：本模板仅用于沟通已识别错报。只要能向集团注册会计师沟通必要信息，可使用不同的模板或格式。浅灰色标注的单元格可能包括下拉选项或公式。可删除不适用的工作表（如没有披露错报）。
B12: 整体发现 | C12: 本工作表用于沟通任何已识别错报，单独或汇总，表明舞弊或可能存在其他错报。注意：本工作表填充的集团与组成部分信息会自动填充到其他工作表。
B13: 已更正错报 | C13: 本工作表用于汇总组成部分注册会计师识别并由组成部分管理层更正的错报。该错报可能与当期或前期相关。与账户有关的信息可能需要多行，其他项目可能只需要输入一次。
B14: 未更正错报 | C14: 本工作表用于概括组成部分注册会计师识别但组成部分管理层未更正的错报。该错报可能当期或前期相关。本工作表包括评估未更正错报对组成部分财务信息的影响。账户有关信息可能需要多行，其他项目可能只需要输入一次。
B15: 披露错报 | C15: 本工作表用于汇总披露错误，无论是否更正。通常仅当组成部分财务信息按照通用目的框架（如国际会计准则理事会颁布的国际财务报告框架）编制或组成部分财务信息以其他方式包含披露时有关。

Sheet B30-12-1 整体发现
B1: 致同会计师事务所
B2: 已识别组成部分错报汇总表—整体发现
B3: 客户名称： | C3: 编制人： | D3: 日期： | E3: 索引号：B30-12-1
B4: 会计期间： | C4: 复核人： | D4: 日期： | E4: 页 次：
B6: 已识别组成部分错报汇总表—整体发现
B8: 集团名称
B9: 集团报表日
B10: 组成部分名称
B11: 组成部分报表日
B12: 集团微小错报金额
B13: 组成部分记账本位币
B14: 组成部分列报货币
C17: 结论 | E17: 如果是，描述（可选其他批注）
B18: 基于你的职业判断，是否任何已识别错报，单独或汇总，表明可能存在其他错报？
B19: 基于你的职业判断，是否任何已识别错报，单独或汇总，表明存在舞弊?

Sheet B30-12-2 已更正错报
B2: 致同会计师事务所
B3: 已识别组成部分错报汇总表—已更正错报
B4: 客户名称： | D4: 编制人： | E4: 日期： | H4: 索引号： | I4: B30-12-2
B5: 会计期间： | D5: 复核人： | E5: 日期： | H5: 页 次：
B6: 已识别组成部分错报汇总表—已更正错报
B8: 集团名称 | C8: ='B30-12-1 整体发现'!C8 -> 0
B9: 集团报表日 | C9: ='B30-12-1 整体发现'!C9 -> 0
B10: 组成部分名称 | C10: ='B30-12-1 整体发现'!C10 -> 0
B11: 组成部分报表日 | C11: ='B30-12-1 整体发现'!C11 -> 0
B12: 集团微小错报金额 | C12: ='B30-12-1 整体发现'!C12 -> 0
B13: 组成部分记账本位币 | C13: ='B30-12-1 整体发现'!C13 -> 0
B14: 组成部分列报货币 | C14: ='B30-12-1 整体发现'!C14 -> 0
B17: 错报描述 | C17: 当期/前期？ | D17: 错报类型 | E17: 科目编码（如果适用） | F17: 科目名称或财务报表项目 | G17: 借 | H17: 贷 | I17: 错报原因和相关控制缺陷

Sheet B30-12-3 未更正错报
B2: 致同会计师事务所
B3: 已识别组成部分错报汇总表—未更正错报
B4: 客户名称： | E4: 编制人： | H4: 日期： | M4: 索引号： | N4: B30-12-3
B5: 会计期间： | E5: 复核人： | H5: 日期： | M5: 页 次：
B6: 已识别组成部分错报汇总表—未更正错报
B8: 集团名称 | C8: ='B30-12-1 整体发现'!C8 -> 0
B9: 集团报表日 | C9: ='B30-12-1 整体发现'!C9 -> 0
B10: 组成部分名称 | C10: ='B30-12-1 整体发现'!C10 -> 0
B11: 组成部分报表日 | C11: ='B30-12-1 整体发现'!C11 -> 0
B12: 集团微小错报金额 | C12: ='B30-12-1 整体发现'!C12 -> 0
B13: 组成部分记账本位币 | C13: ='B30-12-1 整体发现'!C13 -> 0
B14: 组成部分列报货币 | C14: ='B30-12-1 整体发现'!C14 -> 0
I16: 增加（减少）
B17: 错报描述 | C17: 当期/前期？ | D17: 错报类型 | E17: 科目编码（如果适用） | F17: 科目名称或财务报表项目 | G17: 借 | H17: 贷 | I17: 资产 | J17: 负债 | K17: 权益 | L17: 收入 | M17: 管理层不更正的原因 | N17: 错报原因和相关控制缺陷
I29: 资产 | J29: 负债 | K29: 权益 | L29: 收入
F30: 未更正错报总金额 | I30: =SUM(I18:I26) -> 0 | J30: =SUM(J18:J26) -> 0 | K30: =SUM(K18:K26) -> 0 | L30: =SUM(L18:L26) -> 0
F31: 税费影响
F32: 税后未更正错报 | I32: =I30-I31 -> 0 | J32: =J30-J31 -> 0 | K32: =K30-K31 -> 0 | L32: =L30-L31 -> 0
F34: 组成部分财务信息金额
H35: 影响比例 | I35: =I32/I34 -> #DIV/0! | J35: =J32/J34 -> #DIV/0! | K35: =K32/K34 -> #DIV/0! | L35: =L32/L34 -> #DIV/0!
F37: 未更正错报单独或汇总是否重大的结论（包括定性与定量因素）

Sheet B30-12-4 披露错报
B2: 致同会计师事务所
B3: 已识别组成部分错报汇总—披露错报
B4: 客户名称： | D4: 编制人： | E4: 日期： | F4: 索引号： | G4: B30-12-4
B5: 会计期间： | D5: 复核人： | E5: 日期： | F5: 页 次：
B6: 已识别组成部分错报汇总—披露错报
B8: 集团名称 | C8: ='B30-12-1 整体发现'!C8 -> 0
B9: 集团报表日 | C9: ='B30-12-1 整体发现'!C9 -> 0
B10: 组成部分名称 | C10: ='B30-12-1 整体发现'!C10 -> 0
B11: 组成部分报表日 | C11: ='B30-12-1 整体发现'!C11 -> 0
B12: 集团微小错报金额 | C12: ='B30-12-1 整体发现'!C12 -> 0
B13: 组成部分记账本位币 | C13: ='B30-12-1 整体发现'!C13 -> 0
B14: 组成部分列报货币 | C14: ='B30-12-1 整体发现'!C14 -> 0
B17: 错报描述 | C17: 当期/前期？ | D17: 金额（如果适用） | E17: 是/否更正？ | F17: 管理层不更正的原因（如果未更正） | G17: 错报原因和相关控制缺陷
B26: 未更正错报单独或汇总是否重大的结论（包括定性与定量因素）

Sheet Lists
A1: Yes
A2: No
A4: Factual
A5: Judgmental
A6: Projected
A8: Current
A9: Prior
A11: Yes
A12: No
A13: N/A
