Workbook

Sheet 底稿目录
A1: 底稿开列时，可先在以下单元格填写有关内容，以便其他底稿引用有关数据：
A2: 被审计单位： | D2: 序号 | E2: 内容 | F2: 索引号
A3: 截止日：202X年12月31日 | D3: 1 | E3: 长期应付款实质性程序表 | F3: L5A
A4: 编制人： | D4: 2 | E4: 审定表 | F4: L5-1
A5: 编制日期： | D5: 3 | E5: 附注披露信息（上市公司） | G5: 无需打印
A6: 复核人： | D6: 4 | E6: 附注披露信息（国企） | G6: 无需打印
A7: 复核日期： | D7: 5 | E7: 明细表 | F7: L5-2
D8: 6 | E8: 明细表（未确认融资费用） | F8: L5-3
A9: 关于工作底稿与审计程序索引号对应的说明 | D9: 7 | E9: 调整分录汇总 | F9: L5-4
A10: 1.编制的审计工作底稿应与审计程序对应。审计项目组应根据被审计单位实际情况和风险评估情况在实质性程序表中裁剪、修改或增加审计程序，根据实际执行的审计程序完成相应审计工作底稿，编制的工作底稿中应按自然顺序依次编制索引号，并通过唯一的索引号将与实质性程序表中的程序对应关联（即将工作底稿的索引号填入实质性程序表中的底稿索引号列）。 | D10: 8 | E10: 未确认融资费用测算表 | F10: L5-5
D11: 9 | E11: 函证结果汇总表 | F11: L0-1
D12: 10 | E12: 核实被函证单位信息 | F12: L0-2
D13: 11 | E13: 跟函函证过程控制 | F13: L0-3
A14: 2.获取的支持性证据应与审计底稿或程序对应。审计项目组在完成底稿时获取的支持性证据应根据底稿索引号编制下一级按自然顺序排序的索引号（如D1-2-1、D1-2-2、……），并在底稿中说明引用的支持性证据、关联索引号。 | D14: 12 | E14: 函证差异调节表 | F14: L0-4
D15: 13 | E15: 长期应付款替代程序检查表 | F15: L0-5
D16: 14 | E16: 邮件传真回函可靠性验证 | F16: L0-6
A17: 3.工作底稿索引号的编码规则：实质性程序索引号按循环从“D”到“N”,循环内账户以顺序号排列，模板中底稿索引号按账户顺序+自然数顺序（即模板中索引号按二级自然顺序排列，如D1-1、D1-2、D1-3、……D1-N）。 | D17: 15 | E17: 函证程序舞弊风险评价表 | F17: L0-7
D18: 16 | E18: ='关联方及交易检查表L5-6'!A2 | F18: L5-6
D19: 17 | E19: 长期应付款检查表 | F19: L5-7

Sheet 长期应付款实质性程序表L5A
A1: 致同会计师事务所
A2: 长期应付款实质性程序
A3: =底稿目录!A2 | C3: =底稿目录!A4 | E3: =底稿目录!A5 | H3: 索引号： | I3: L5A
A4: =底稿目录!A3 | C4: =底稿目录!A6 | E4: =底稿目录!A7 | H4: 页 次：
A5: 一、本账户涉及的科目
A6: 长期应付款
A7: 二、审计目标与认定的对应关系
A8: 审计目标 | G8: 财务报表的认定
A9: A. 资产负债表中记录的长期应付款是存在的，且已记录于恰当的账户 | G9: 存在
A10: B. 所有应记录的长期应付款均已记录，所有应当包括在财务报表中的相关披露均已包括 | G10: 完整性
A11: C. 记录的长期应付款是被审计单位应当履行的偿还义务 | G11: 权利和义务
A12: D. 长期应付款以恰当的金额包括在财务报表中，与之相关的计价或分摊调整已恰当记录，相关披露已得到恰当计量和描述 | G12: 准确性、计价和分摊
A13: E. 长期应付款已被恰当地汇总或分解且表述清楚，相关披露在按照企业会计准则的编制基础下是相关的、可理解的 | G13: 列报
A14: 三、计划实施的实质性程序
A15: 序号 | B15: 审计程序 | C15: 程序分类 | D15: 财务报表的认定 | I15: 底稿索引号
D16: 存在 | E16: 完整性 | F16: 权利和义务 | G16: 准确性、计价和分摊 | H16: 列报 | J16: 根据被审计单位实际情况和风险评估情况裁剪、修改或增加审计程序
A17: 1 | B17: 获取或编制长期应付款明细表，完成以下工作，并编制审定表 （1）复核加计是否正确，与总账、明细账合计数核对是否相符，期初余额与上期审定期末余额是否相符； （2）获取管理层编制的应付账款账龄分析表，检查账龄划分是否正确； （2）确定流动负债和非流动负债的划分是否正确 。 | C17: 常规★ | D17: √ | E17: √ | G17: √ | I17: L5-1 /L5-2
A18: 2 | B18: 在使用手工编制、自定义信息报告、系统生成的非固定格式报告等由被审计单位生成的信息时，测试有关信息准确性和完整性，并针对编制和维护由被审计单位生成的信息的相关控制实施控制测试，以评价该信息是否能够为实现审计目的提供基础。 | C18: 常规★ | E18: √ | G18: √ | I18: T1 / | J18: 可参见《审计手册》4.2.6，由被审计单位生成的信息可能是由系统生成的、或手工编制的、或二者兼而有之的方式生成的。例如，由被审计单位生成的信息可能包括： • 不涉及自定义的、由系统生成的报告（如，固定格式报告）； • 可能通过人工自定义的、由系统生成的报告，例如，（计算机）查询信息或特别定制的报告； • 手工编制的信息，例如，汇总信息的电子表格或用以支持分配、计算以及调节的电子表格； • 其他系统生成或手工编制的信息，例如，由被审计单位编制的客户发票； • 通过影印、拍摄、扫描或其他方式转换成电子形式的文件记录。
A19: 3 | B19: 对期初余额的审计，取得长期应付款期初余额明细表复核加计是否正确，与总账、明细账合计数是否相符，检查上期长期应付款在本期支付情况，函证期初余额以及其他必要追加的审计程序。（适用于首次承接） | C19: 备选 | D19: √ | E19: √ | F19: √ | G19: √ | J19: 由被审计单位生成的信息不包括： • 总分类账或明细分类账、试算平衡表、或经审计的财务报表； • 第三方（除了服务机构）的报表或报告，例如，原始银行对账单，或函证的回函； • 外部数据（例如，第三方发布的数据，如，定价来源）。
A20: 4 | B20: 关注会计政策、会计估计合理性、一贯性，关注其是否利用会计政策和会计估计及其变更操纵利润。 | C20: 常规★ | D20: √ | E20: √ | G20: √ | I20: L5-1 /L5-2
A21: 5 | B21: 检查长期应付款长期挂账的原因并作出记录，分析账龄较长的原因，是否双方有纠纷等，考虑负债计提是否充分，对确实无需支付的应付款的会计处理是否正确。 | C21: 常规★ | D21: √ | G21: √ | I21: L5-2
A22: 6 | B22: 对长期应付款的利息费用执行如下程序： （1）与被审计单位讨论确定实际利率或经信用调整的实际利率确定依据是否充分，复核实际利率或经信用调整的实际利率是否与前期一致； （2）重新计算占有期间的利息，与被审计单位账面记录核对，如果存在差异，应查明原因并考虑进行审计调整； | C22: 常规★ | G22: √ | I22: L5-3 /L5-5
A23: 7 | B23: 实施函证程序： （1）以积极方式对长期应付款进行函证，设计询证函、发函前核实被函证单位信息； （2）注册会计师独立收发询证函； （3）编制函证结果汇总表，检查发函、回函物流信息和轨迹、比对回函印章和签字等以核实回函的真实性，检查回函是否相符，对不符事项查明原因确定是否存在错报； （4）如果未收到回函，应当考虑与被询证者联系，要求对方作出回应或再次寄发询证函，无法收到的回函实施替代程序； （5）如果管理层不允许寄发询证函的，询问管理层不允许寄发的原因，并就其原因的正当、合理性收集证据；考虑实施替代审计程序以获取相关、可靠的审计证据； （6）如果管理层不允许寄发询证函的原因不合理、或者认为回函不可靠，评价对评估的重大错报风险以及其他审计程序的性质、时间安排和范围的影响，并确定其对审计工作和审计意见的影响。 | C23: 常规★ | D23: √ | E23: √ | F23: √ | G23: √ | I23: L0
A24: 8 | B24: 检查长期应付关联方款项： （1）了解交易的商业理由、交易事项的目的、价格和条件，确定关联交易价格是否远高于或低于非关联方交易价格，考虑对关联方应付账款的合理性、合法性； （2）检查对关联方长期应付款的真实性相关的支持性文件、检查会计处理是否正确； （3）考虑向关联方或其他注册会计师函证重大的关联采购交易和余额（包括担保和其他重要信息）； （4）必要时，向与交易相关的人员和机构（如银行、律师）函证或与其讨论有关信息； （5）考虑是否存在未识别的关联方，关联交易和余额披露是否正确。 | C24: 常规★ | D24: √ | E24: √ | F24: √ | G24: √ | H24: √ | I24: L5-6
A25: 9 | B25: 检查与长期应付款有关的的记账凭证和相应的支持性证据以确定交易的真实性，是否按规定进行相应的会计处理和披露。 | C25: 常规★ | D25: √ | F25: √ | G25: √ | I25: L5-7
A26: 10 | B26: 根据评估的舞弊风险等因素增加的审计程序。 | C26: IPO/上市/新三板/重组/舞弊应对
A27: 11 | B27: 检查长期应付款是否已按企业会计准则或其他适用的规定在财务报表中做出恰当列报和披露。 | C27: 常规★ | H27: √ | I27: A1-1/A1-15 /A1-16

Sheet 审定表L5-1
A1: 致同会计师事务所
A2: 长期应付款审定表
A3: =底稿目录!A2 | E3: =底稿目录!A4 | J3: =底稿目录!A5 | N3: 索引号： | O3: =底稿目录!F4
A4: =底稿目录!A3 | E4: =底稿目录!A6 | J4: =底稿目录!A7 | N4: 页次：
A5: 项目 | B5: 期初数 | H5: 期末数 | N5: 本期审定数与上期 审定数的比较
B6: 未审数 | C6: 账项调整 | D6: 重分类调整 | E6: 审定数 | F6: 减：一年内到期的长期应付款 | G6: 最终审定数 | H6: 未审数 | I6: 账项调整 | J6: 重分类调整 | K6: 审定数 | L6: 减：一年内到期的长期应付款 | M6: 最终审定数 | N6: 变动额 | O6: 变动率
A7: 一、原值
A8: 应付融资租赁款 | B8: ='明细表L5-2'!B16 | C8: ='明细表L5-2'!F16 | D8: ='明细表L5-2'!G16 | E8: =B8+C8+D8 | F8: ='明细表L5-2'!P16 | G8: =E8-F8 | H8: ='明细表L5-2'!E16 | I8: ='明细表L5-2'!F16+'明细表L5-2'!I16-'明细表L5-2'!H16 | J8: ='明细表L5-2'!G16+'明细表L5-2'!K16-'明细表L5-2'!J16 | K8: =H8+I8+J8 | L8: ='明细表L5-2'!Q16 | M8: =K8-L8 | N8: =K8-E8 | O8: =IF(AND(E8=0,N8=0),0,IF(AND(E8=0,N8>0),1,N8/E8))
A9: 分期付款方式购入固定资产 | B9: ='明细表L5-2'!B23 | C9: ='明细表L5-2'!F23 | D9: ='明细表L5-2'!G23 | E9: =B9+C9+D9 | F9: ='明细表L5-2'!P23 | G9: =E9-F9 | H9: ='明细表L5-2'!E23 | I9: ='明细表L5-2'!F23+'明细表L5-2'!I23-'明细表L5-2'!H23 | J9: ='明细表L5-2'!G23+'明细表L5-2'!K23-'明细表L5-2'!J23 | K9: =H9+I9+J9 | L9: ='明细表L5-2'!Q23 | M9: =K9-L9 | N9: =K9-E9 | O9: =IF(AND(E9=0,N9=0),0,IF(AND(E9=0,N9>0),1,N9/E9))
A10: 其他 | B10: ='明细表L5-2'!B24 | C10: ='明细表L5-2'!F24 | D10: ='明细表L5-2'!G24 | E10: =B10+C10+D10 | F10: ='明细表L5-2'!P24 | G10: =E10-F10 | H10: ='明细表L5-2'!E24 | I10: ='明细表L5-2'!F24+'明细表L5-2'!I24-'明细表L5-2'!H24 | J10: ='明细表L5-2'!G24+'明细表L5-2'!K24-'明细表L5-2'!J24 | K10: =H10+I10+J10 | L10: ='明细表L5-2'!Q24 | M10: =K10-L10 | N10: =K10-E10 | O10: =IF(AND(E10=0,N10=0),0,IF(AND(E10=0,N10>0),1,N10/E10))
A11: 合计 | B11: =SUM(B8:B10) | C11: =SUM(C8:C10) | D11: =SUM(D8:D10) | E11: =SUM(E8:E10) | F11: =SUM(F8:F10) | G11: =SUM(G8:G10) | H11: =SUM(H8:H10) | I11: =SUM(I8:I10) | ... M11: =SUM(M8:M10) | N11: =K11-E11 | O11: =IF(AND(E11=0,N11=0),0,IF(AND(E11=0,N11>0),1,N11/E11))
A12: 二、未确认融资费用
A13: 应付融资租赁款 | B13: ='未确认融资费用明细表L5-3'!B17 | C13: ='未确认融资费用明细表L5-3'!F17 | D13: ='未确认融资费用明细表L5-3'!G17 | E13: =B13+C13+D13 | F13: ='未确认融资费用明细表L5-3'!P17 | G13: =E13-F13 | H13: ='未确认融资费用明细表L5-3'!E17 | I13: ='未确认融资费用明细表L5-3'!F17+'未确认融资费用明细表L5-3'!I17-'未确认融资费用明细表L5-3'!H17 | J13: ='未确认融资费用明细表L5-3'!G17+'未确认融资费用明细表L5-3'!K17-'未确认融资费用明细表L5-3'!J17 | K13: =H13+I13+J13 | L13: ='未确认融资费用明细表L5-3'!Q17 | M13: =K13-L13 | N13: =K13-E13 | O13: =IF(AND(E13=0,N13=0),0,IF(AND(E13=0,N13>0),1,N13/E13))
A14: 分期付款方式购入固定资产 | B14: ='未确认融资费用明细表L5-3'!B24 | C14: ='未确认融资费用明细表L5-3'!F24 | D14: ='未确认融资费用明细表L5-3'!G24 | E14: =B14+C14+D14 | F14: ='未确认融资费用明细表L5-3'!P24 | G14: =E14-F14 | H14: ='未确认融资费用明细表L5-3'!E24 | I14: ='未确认融资费用明细表L5-3'!F24+'未确认融资费用明细表L5-3'!I24-'未确认融资费用明细表L5-3'!H24 | J14: ='未确认融资费用明细表L5-3'!G24+'未确认融资费用明细表L5-3'!K24-'未确认融资费用明细表L5-3'!J24 | K14: =H14+I14+J14 | L14: ='未确认融资费用明细表L5-3'!Q24 | M14: =K14-L14 | N14: =K14-E14 | O14: =IF(AND(E14=0,N14=0),0,IF(AND(E14=0,N14>0),1,N14/E14))
A15: 其他 | B15: ='未确认融资费用明细表L5-3'!B25 | C15: ='未确认融资费用明细表L5-3'!F25 | D15: ='未确认融资费用明细表L5-3'!G25 | E15: =B15+C15+D15 | F15: ='未确认融资费用明细表L5-3'!P25 | G15: =E15-F15 | H15: ='未确认融资费用明细表L5-3'!E25 | I15: ='未确认融资费用明细表L5-3'!F25+'未确认融资费用明细表L5-3'!I25-'未确认融资费用明细表L5-3'!H25 | J15: ='未确认融资费用明细表L5-3'!G25+'未确认融资费用明细表L5-3'!K25-'未确认融资费用明细表L5-3'!J25 | K15: =H15+I15+J15 | L15: ='未确认融资费用明细表L5-3'!Q25 | M15: =K15-L15 | N15: =K15-E15 | O15: =IF(AND(E15=0,N15=0),0,IF(AND(E15=0,N15>0),1,N15/E15))
A16: 合计 | B16: =SUM(B13:B15) | C16: =SUM(C13:C15) | D16: =SUM(D13:D15) | E16: =SUM(E13:E15) | F16: =SUM(F13:F15) | G16: =SUM(G13:G15) | H16: =SUM(H13:H15) | I16: =SUM(I13:I15) | ... M16: =SUM(M13:M15) | N16: =K16-E16 | O16: =IF(AND(E16=0,N16=0),0,IF(AND(E16=0,N16>0),1,N16/E16))
A17: 三、净值
A18: 应付融资租赁款 | B18: =B8-B13 | C18: =C8-C13 | D18: =D8-D13 | E18: =E8-E13 | F18: =F8-F13 | G18: =G8-G13 | H18: =H8-H13 | I18: =I8-I13 | ... M18: =M8-M13 | N18: =K18-E18 | O18: =IF(AND(E18=0,N18=0),0,IF(AND(E18=0,N18>0),1,N18/E18))
A19: 分期付款方式购入固定资产 | B19: =B9-B14 | C19: =C9-C14 | D19: =D9-D14 | E19: =E9-E14 | F19: =F9-F14 | G19: =G9-G14 | H19: =H9-H14 | I19: =I9-I14 | ... M19: =M9-M14 | N19: =K19-E19 | O19: =IF(AND(E19=0,N19=0),0,IF(AND(E19=0,N19>0),1,N19/E19))
A20: 其他 | B20: =B10-B15 | C20: =C10-C15 | D20: =D10-D15 | E20: =E10-E15 | F20: =F10-F15 | G20: =G10-G15 | H20: =H10-H15 | I20: =I10-I15 | ... M20: =M10-M15 | N20: =K20-E20 | O20: =IF(AND(E20=0,N20=0),0,IF(AND(E20=0,N20>0),1,N20/E20))
A21: 合计 | B21: =SUM(B18:B20) | C21: =SUM(C18:C20) | D21: =SUM(D18:D20) | E21: =SUM(E18:E20) | F21: =SUM(F18:F20) | G21: =SUM(G18:G20) | H21: =SUM(H18:H20) | I21: =SUM(I18:I20) | ... M21: =SUM(M18:M20) | N21: =K21-E21 | O21: =IF(AND(E21=0,N21=0),0,IF(AND(E21=0,N21>0),1,N21/E21))
A22: 1、审计说明：
A23: （1）长期应付款期末净值较期初净值增加（负数为减少）：
A24: 主要原因（比例超过30%的）：
A26: （2）与经审计的财务报表核对
B27: 期末数 | C27: 期初数
A28: 长期应付款审定数 | B28: =M21 | C28: =G21
A29: 专项应付款审定数
A30: 长期应付款与专项应付款合计数 | B30: =B28+B29 | C30: =C28+C29
A31: 报表数
A32: 差异 | B32: =B30-B31 | C32: =C30-C31
A34: 2、审计结论：

Sheet 附注披露信息（上市公司）
A1: 致同会计师事务所
A2: 长期应付款附注披露信息 | E2: 返回目录
A3: =底稿目录!A2 | B3: =底稿目录!A4 | C3: =底稿目录!A5 | D3: 索引号：
A4: =底稿目录!A3 | B4: =底稿目录!A6 | C4: =底稿目录!A7 | D4: 页次：
A5: 36、长期应付款
A6: 项目 | B6: 期末数 | C6: 上年年末余额
A7: 长期应付款 | B7: =B21 | C7: =C21
A8: 专项应付款
A9: 合计 | B9: =SUM(B7:B8) | C9: =SUM(C7:C8)
A10: （1）长期应付款（按款项性质列示）
A11: 项 目 | B11: 期末数 | C11: 上年年末余额
A12: ='明细表L5-2'!A10 | B12: ='明细表L5-2'!O16 | C12: ='明细表L5-2'!L16
A13: ='明细表L5-2'!A17 | B13: ='明细表L5-2'!O23 | C13: ='明细表L5-2'!L23
A14: ='明细表L5-2'!A24 | B14: ='明细表L5-2'!O24 | C14: ='明细表L5-2'!L24
A15: 减：未确认融资费用：
A16: ='未确认融资费用明细表L5-3'!A11 | B16: ='未确认融资费用明细表L5-3'!O17 | C16: ='未确认融资费用明细表L5-3'!L17
A17: ='未确认融资费用明细表L5-3'!A18 | B17: ='未确认融资费用明细表L5-3'!O24 | C17: ='未确认融资费用明细表L5-3'!L24
A18: ='未确认融资费用明细表L5-3'!A25 | B18: ='未确认融资费用明细表L5-3'!O25 | C18: ='未确认融资费用明细表L5-3'!L25
A19: 小计 | B19: =SUM(B12:B14)-SUM(B16:B18) | C19: =SUM(C12:C14)-SUM(C16:C18)
A20: 减：一年内到期长期应付款 | B20: ='明细表L5-2'!Q25-'未确认融资费用明细表L5-3'!Q26 | C20: ='明细表L5-2'!P25-'未确认融资费用明细表L5-3'!P26
A21: 合 计 | B21: =B19-B20 | C21: =C19-C20
A22: 说明：由独立第三方为公司融资租赁提供担保的金额XX元。

Sheet 附注披露信息（国企）
A1: 致同会计师事务所
A2: 长期应付款附注披露信息 | E2: 返回目录
A3: =底稿目录!A2 | B3: =底稿目录!A4 | C3: =底稿目录!A5 | D3: 索引号：
A4: =底稿目录!A3 | B4: =底稿目录!A6 | C4: =底稿目录!A7 | D4: 页次：
A5: 长期应付款
A6: 项目 | B6: 期末数 | C6: 期初数
A7: 长期应付款 | B7: =B20 | C7: =C20
A8: 专项应付款
A9: 合计 | B9: =SUM(B7:B8) | C9: =SUM(C7:C8)
A10: 长期应付款（说明：分项披露长期应付款期末余额最大的前五项）
A11: 项 目 | B11: 期末余额 | C11: 年初余额
A12: ='关联方及交易检查表L5-6'!A8
A13: ='关联方及交易检查表L5-6'!A9
A14: ='关联方及交易检查表L5-6'!A10
A15: ='关联方及交易检查表L5-6'!A11
A16: ='关联方及交易检查表L5-6'!A12
A17: 其他 | B17: ='明细表L5-2'!O25-SUM(B12:B16) | C17: ='明细表L5-2'!L25-SUM(C12:C16)
A18: 小 计 | B18: =SUM(B12:B17) | C18: =SUM(C12:C17)
A19: 减：一年内到期长期应付款 | B19: ='明细表L5-2'!Q25-'未确认融资费用明细表L5-3'!Q26 | C19: ='明细表L5-2'!P25-'未确认融资费用明细表L5-3'!P26
A20: 合 计 | B20: =B18-B19 | C20: =C18-C19

Sheet 明细表L5-2
A1: 致同会计师事务所 | P1: 致同会计师事务所
A2: 长期应付款明细表 | P2: 长期应付款明细表
A3: =底稿目录!A2 | E3: =底稿目录!A4 | J3: =底稿目录!A5 | N3: 索引号： | O3: =底稿目录!F7 | R3: =E3 | U3: =J3 | AB3: 索引号： | AC3: =底稿目录!F7
A4: =底稿目录!A3 | E4: =底稿目录!A6 | J4: =底稿目录!A7 | N4: 页次： | R4: =E4 | U4: =J4 | AB4: 页次：
A5: 一、审计目标:
B6: 1、资产负债表中记录的长期应付款是存在的，且已经记录在恰当的账户中；2、 所有应记录的短期借款均已记录，所有应当包括在财务报表中的相关披露均已包括；3、长期应付款以恰当的金额包括在财务报表中，与之相关的计价或分摊调整已恰当记录，相关披露已得到恰当计量和描述 | P6: 1、资产负债表中记录的长期应付款是存在的，且已经记录在恰当的账户中；2、 所有应记录的短期借款均已记录，所有应当包括在财务报表中的相关披露均已包括；3、长期应付款以恰当的金额包括在财务报表中，与之相关的计价或分摊调整已恰当记录，相关披露已得到恰当计量和描述
A7: 二、审计过程：
A8: 债权人名称 | B8: 未审数 | F8: 期初调整 | H8: 账项调整 | J8: 重分类调整 | L8: 审定数 | P8: 减：期初一年内到期长期应付款 | Q8: 减：期末一年内到期长期应付款 | R8: 披露审定数 | T8: 期末到期日分析 | Y8: 是否是关联方 | Z8: 发函情况 | AA8: 期后付款 | AB8: 合同索引号 | AC8: 备注
B9: 期初余额 | C9: 借方发生 | D9: 贷方发生 | E9: 期末余额 | F9: 账项调整 | G9: 重分类调整 | H9: 借方发生 | I9: 贷方发生 | J9: 借方发生 | K9: 贷方发生 | L9: 期初余额 | M9: 借方发生 | N9: 贷方发生 | O9: 期末余额 | R9: 期初余额 | S9: 期末余额 | T9: 6个月以内 | U9: 6-12月 | V9: 1～2年 | W9: ２～3年 | X9: 3年以上
A10: 售后租回业务形成的融资
E11: =B11-C11+D11 | L11: =B11+F11+G11 | M11: =C11+H11+J11 | N11: =D11+I11+K11 | O11: =L11-M11+N11 | R11: =L11-P11 | S11: =O11-Q11
E12: =B12-C12+D12 | L12: =B12+F12+G12 | M12: =C12+H12+J12 | N12: =D12+I12+K12 | O12: =L12-M12+N12 | R12: =L12-P12 | S12: =O12-Q12
E13: =B13-C13+D13 | L13: =B13+F13+G13 | M13: =C13+H13+J13 | N13: =D13+I13+K13 | O13: =L13-M13+N13 | R13: =L13-P13 | S13: =O13-Q13
E14: =B14-C14+D14 | L14: =B14+F14+G14 | M14: =C14+H14+J14 | N14: =D14+I14+K14 | O14: =L14-M14+N14 | R14: =L14-P14 | S14: =O14-Q14
E15: =B15-C15+D15 | L15: =B15+F15+G15 | M15: =C15+H15+J15 | N15: =D15+I15+K15 | O15: =L15-M15+N15 | R15: =L15-P15 | S15: =O15-Q15
A16: 小计 | B16: =SUM(B11:B15) | C16: =SUM(C11:C15) | D16: =SUM(D11:D15) | E16: =SUM(E11:E15) | F16: =SUM(F11:F15) | G16: =SUM(G11:G15) | H16: =SUM(H11:H15) | I16: =SUM(I11:I15) | ... S16: =SUM(S11:S15) | V16: =SUM(V11:V15) | W16: =SUM(W11:W15) | X16: =SUM(X11:X15) | Y16: -- | Z16: -- | AA16: =SUM(AA11:AA15) | AB16: -- | AC16: --
A17: 分期付款方式购入固定资产
E18: =B18-C18+D18 | L18: =B18+F18+G18 | M18: =C18+H18+J18 | N18: =D18+I18+K18 | O18: =L18-M18+N18 | R18: =L18-P18 | S18: =O18-Q18
E19: =B19-C19+D19 | L19: =B19+F19+G19 | M19: =C19+H19+J19 | N19: =D19+I19+K19 | O19: =L19-M19+N19 | R19: =L19-P19 | S19: =O19-Q19
E20: =B20-C20+D20 | L20: =B20+F20+G20 | M20: =C20+H20+J20 | N20: =D20+I20+K20 | O20: =L20-M20+N20 | R20: =L20-P20 | S20: =O20-Q20
E21: =B21-C21+D21 | L21: =B21+F21+G21 | M21: =C21+H21+J21 | N21: =D21+I21+K21 | O21: =L21-M21+N21 | R21: =L21-P21 | S21: =O21-Q21
E22: =B22-C22+D22 | L22: =B22+F22+G22 | M22: =C22+H22+J22 | N22: =D22+I22+K22 | O22: =L22-M22+N22 | R22: =L22-P22 | S22: =O22-Q22
A23: 小计 | B23: =SUM(B18:B22) | C23: =SUM(C18:C22) | D23: =SUM(D18:D22) | E23: =SUM(E18:E22) | F23: =SUM(F18:F22) | G23: =SUM(G18:G22) | H23: =SUM(H18:H22) | I23: =SUM(I18:I22) | ... S23: =SUM(S18:S22) | V23: =SUM(V18:V22) | W23: =SUM(W18:W22) | X23: =SUM(X18:X22) | Y23: -- | Z23: -- | AA23: =SUM(AA18:AA22) | AB23: -- | AC23: --
A24: … | E24: =B24-C24+D24 | L24: =B24+F24+G24 | M24: =C24+H24+J24 | N24: =D24+I24+K24 | O24: =L24-M24+N24 | R24: =L24-P24 | S24: =O24-Q24
A25: 合计 | B25: =SUM(B16,B23,B24) | C25: =SUM(C16,C23,C24) | D25: =SUM(D16,D23,D24) | E25: =SUM(E16,E23,E24) | F25: =SUM(F16,F23,F24) | G25: =SUM(G16,G23,G24) | H25: =SUM(H16,H23,H24) | I25: =SUM(I16,I23,I24) | ... S25: =SUM(S16,S23,S24) | V25: =SUM(V16,V23,V24) | W25: =SUM(W16,W23,W24) | X25: =SUM(X16,X23,X24) | Y25: -- | Z25: -- | AA25: =SUM(AA16,AA23,AA24) | AB25: -- | AC25: --
A26: 1、审计说明：
A29: 2、审计结论：
A31: 提示：
A32: 1.本科目核算企业除长期借款和应付债券以外的其他各种长期应付款项，包括应付融资租入固定资产的租赁费.以分期付款方式购入固定资产等发生的应付款项等。
A33: 2.一年内到期长期应付款，应重分类至一年内到期的非流动负债。
A34: 3.审计说明可以概述：（1）程序的测试情况、结果；（2）拟调整事项及其调整分录、未调整事项及其影响，审计范围受到限制情况及其影响。
A35: 4.审计结论可参考：A、未见异常。 B、除上述重大不符事项应当作为调整事项予以调整外，其余未见异常。 C、由于存在以下重大未调整事项（或审计范围受到限制无法获取充分、适当证据），不可确认。

Sheet 未确认融资费用明细表L5-3
A1: 致同会计师事务所 | P1: 致同会计师事务所
A2: 未确认融资费用明细表 | P2: 未确认融资费用明细表
A3: =底稿目录!A2 | E3: =底稿目录!A4 | I3: =底稿目录!A5 | N3: 索引号： | O3: =底稿目录!F8 | Q3: =E3 | U3: =I3 | Z3: 索引号： | AA3: =底稿目录!F8
A4: =底稿目录!A3 | E4: =底稿目录!A6 | I4: =底稿目录!A7 | N4: 页次： | Q4: =E4 | U4: =I4 | Z4: 页次：
A5: 一、审计目标:
B6: 1、资产负债表中记录的应付债券是存在的，且已经记录在恰当的账户中；2、 所有应记录的短期借款均已记录，所有应当包括在财务报表中的相关披露均已包括；3、应付债券以恰当的金额包括在财务报表中，与之相关的计价或分摊调整已恰当记录，相关披露已得到恰当计量和描述 | P6: 1、资产负债表中记录的应付债券是存在的，且已经记录在恰当的账户中；2、 所有应记录的短期借款均已记录，所有应当包括在财务报表中的相关披露均已包括；3、应付债券以恰当的金额包括在财务报表中，与之相关的计价或分摊调整已恰当记录，相关披露已得到恰当计量和描述
A7: 二、审计过程：
B8: 获取或编制长期应付款明细表，复核加计正确,将总金额与报表、总账、明细账合计数核对相符。 | P8: 获取或编制长期应付款明细表，复核加计正确,将总金额与报表、总账、明细账合计数核对相符。
A9: 债权人名称 | B9: 未审数 | F9: 期初调整 | H9: 账项调整 | J9: 重分类调整 | L9: 审定数 | P9: 减：期初一年内到期未确认融资费用 | Q9: 减：期末一年内到期未确认融资费用 | R9: 披露审定数 | T9: 到期日 | Z9: 是否是关联方 | AA9: 备注
B10: 期初余额 | C10: 借方发生 | D10: 贷方发生 | E10: 期末余额 | F10: 账项调整 | G10: 重分类调整 | H10: 借方发生 | I10: 贷方发生 | J10: 借方发生 | K10: 贷方发生 | L10: 期初余额 | M10: 借方发生 | N10: 贷方发生 | O10: 期末余额 | R10: 期初余额 | S10: 期末余额 | T10: 6个月以内 | U10: 6-12月 | V10: 1年以下 | W10: 1～2年 | X10: ２～3年 | Y10: 3年以上
A11: ='明细表L5-2'!A10
A12: ='明细表L5-2'!A11 | E12: =B12-C12+D12 | L12: =B12+F12+G12 | M12: =C12+H12+J12 | N12: =D12+I12+K12 | O12: =L12-M12+N12 | R12: =L12-P12 | S12: =O12-Q12
A13: ='明细表L5-2'!A12 | E13: =B13-C13+D13 | L13: =B13+F13+G13 | M13: =C13+H13+J13 | N13: =D13+I13+K13 | O13: =L13-M13+N13 | R13: =L13-P13 | S13: =O13-Q13
A14: ='明细表L5-2'!A13 | E14: =B14-C14+D14 | L14: =B14+F14+G14 | M14: =C14+H14+J14 | N14: =D14+I14+K14 | O14: =L14-M14+N14 | R14: =L14-P14 | S14: =O14-Q14
A15: ='明细表L5-2'!A14 | E15: =B15-C15+D15 | L15: =B15+F15+G15 | M15: =C15+H15+J15 | N15: =D15+I15+K15 | O15: =L15-M15+N15 | R15: =L15-P15 | S15: =O15-Q15
A16: ='明细表L5-2'!A15 | E16: =B16-C16+D16 | L16: =B16+F16+G16 | M16: =C16+H16+J16 | N16: =D16+I16+K16 | O16: =L16-M16+N16 | R16: =L16-P16 | S16: =O16-Q16
A17: 小计 | B17: =SUM(B12:B16) | C17: =SUM(C12:C16) | D17: =SUM(D12:D16) | E17: =SUM(E12:E16) | F17: =SUM(F12:F16) | G17: =SUM(G12:G16) | H17: =SUM(H12:H16) | I17: =SUM(I12:I16) | ... S17: =SUM(S12:S16) | V17: =SUM(V12:V16) | W17: =SUM(W12:W16) | X17: =SUM(X12:X16) | Y17: =SUM(Y12:Y16)
A18: 分期付款方式购入固定资产
A19: ='明细表L5-2'!A18 | E19: =B19-C19+D19 | L19: =B19+F19+G19 | M19: =C19+H19+J19 | N19: =D19+I19+K19 | O19: =L19-M19+N19 | R19: =L19-P19 | S19: =O19-Q19
A20: ='明细表L5-2'!A19 | E20: =B20-C20+D20 | L20: =B20+F20+G20 | M20: =C20+H20+J20 | N20: =D20+I20+K20 | O20: =L20-M20+N20 | R20: =L20-P20 | S20: =O20-Q20
A21: ='明细表L5-2'!A20 | E21: =B21-C21+D21 | L21: =B21+F21+G21 | M21: =C21+H21+J21 | N21: =D21+I21+K21 | O21: =L21-M21+N21 | R21: =L21-P21 | S21: =O21-Q21
A22: ='明细表L5-2'!A21 | E22: =B22-C22+D22 | L22: =B22+F22+G22 | M22: =C22+H22+J22 | N22: =D22+I22+K22 | O22: =L22-M22+N22 | R22: =L22-P22 | S22: =O22-Q22
A23: ='明细表L5-2'!A22 | E23: =B23-C23+D23 | L23: =B23+F23+G23 | M23: =C23+H23+J23 | N23: =D23+I23+K23 | O23: =L23-M23+N23 | R23: =L23-P23 | S23: =O23-Q23
A24: 小计 | B24: =SUM(B19:B23) | C24: =SUM(C19:C23) | D24: =SUM(D19:D23) | E24: =SUM(E19:E23) | F24: =SUM(F19:F23) | G24: =SUM(G19:G23) | H24: =SUM(H19:H23) | I24: =SUM(I19:I23) | ... S24: =SUM(S19:S23) | V24: =SUM(V19:V23) | W24: =SUM(W19:W23) | X24: =SUM(X19:X23) | Y24: =SUM(Y19:Y23)
A25: ='明细表L5-2'!A24 | E25: =B25-C25+D25 | L25: =B25+F25+G25 | M25: =C25+H25+J25 | N25: =D25+I25+K25 | O25: =L25-M25+N25 | R25: =L25-P25 | S25: =O25-Q25
A26: 合计 | B26: =SUM(B17,B24,B25) | C26: =SUM(C17,C24,C25) | D26: =SUM(D17,D24,D25) | E26: =SUM(E17,E24,E25) | F26: =SUM(F17,F24,F25) | G26: =SUM(G17,G24,G25) | H26: =SUM(H17,H24,H25) | I26: =SUM(I17,I24,I25) | ... S26: =SUM(S17,S24,S25) | V26: =SUM(V17,V24,V25) | W26: =SUM(W17,W24,W25) | X26: =SUM(X17,X24,X25) | Y26: =SUM(Y17,Y24,Y25)
A27: 三、审计说明：
A29: 四、审计结论：

Sheet 调整分录汇总L5-4
A1: 致同会计师事务所
A2: 长期应付款调整分录汇总表
A3: 客户名称： | C3: 编制人： | G3: 编制日期： | I3: 索引： | J3: =底稿目录!F9
A4: 截止日：202X年12月31日 | C4: 复核人： | G4: 复核日期： | I4: 页次：
A5: 调整事项说明 | B5: 类别（报表调整/账项调整/其他） | C5: 报表项目 | D5: 科目名称 | E5: 附注项目 | F5: …… | G5: 借方调整金额 | H5: 贷方调整金额 | I5: 索引 | J5: 备注
A22: 注：本底稿适用于调整分录较多、较复杂的项目，且仅列示与本报表项目相关的审计调整。项目组可根据项目实际情况选择是否使用该底稿。

Sheet 未确认融资费用测算表L5-5
A1: 致同会计师事务所
A2: 未确认融资费用测算表
A3: =底稿目录!A2 | E3: =底稿目录!A4 | H3: =底稿目录!A5 | J3: 索引号： | K3: =底稿目录!F10
A4: =底稿目录!A3 | E4: =底稿目录!A6 | H4: =底稿目录!A7 | J4: 页次：
A5: 一、审计目标：
A6: 确定被审计单位长期应付款与未确认融资费用准确性。
A7: 二、审计过程：
A8: 1.检查各项长期应付款本息的计算是否准确，会计处理是否正确。2.检查未确认融资费用,重新计算实际利率，并与被审计单位的所计算确定的实际利率进行比较，检查被审计单位是否按照实际利率分摊未确认融资费用，分摊是否正确，相应的会计处理是否正确等。
A9: 长期应付款初始确认金额 | C9: 实际利率 | D9: 长期应付款现值 | E9: 未确认融资费用 | G9: 应付本金 | I9: 年末账面余额 | J9: 差异 | K9: 差异原因
A10: 年份 | B10: 各期付款金额 | E10: 尚未确认的未确认融资费用 | F10: 确认的融资费用 | G10: 应付本金减少额 | H10: 应付本金余额
A11: （1） | B11: （2） | C11: （6） | F11: （3）=期初（5）×（6） | G11: （4）=（2）-（3） | H11: 期末（5）=期初（5）-（4）
G12: =B12-F12 | J12: =H12-I12
F13: =H12*C12 | G13: =B13-F13 | H13: =H12-G13 | J13: =H13-I13
F14: =H13*C13 | G14: =B14-F14 | H14: =H13-G14 | J14: =H14-I14
F15: =H14*C14 | G15: =B15-F15 | H15: =H14-G15 | J15: =H15-I15
F16: =H15*C15 | G16: =B16-F16 | H16: =H15-G16 | J16: =H16-I16
F17: =H16*C16 | G17: =B17-F17 | H17: =H16-G17 | J17: =H17-I17
F18: =H17*C17 | G18: =B18-F18 | H18: =H17-G18 | J18: =H18-I18
F19: =H18*C18 | G19: =B19-F19 | H19: =H18-G19 | J19: =H19-I19
F20: =H19*C19 | G20: =B20-F20 | H20: =H19-G20 | J20: =H20-I20
F21: =H20*C20 | G21: =B21-F21 | H21: =H20-G21 | J21: =H21-I21
F22: =H21*C21 | G22: =B22-F22 | H22: =H21-G22 | J22: =H22-I22
A23: 合计 | B23: =SUM(B12:B22) | C23: -- | D23: =SUM(D12:D22) | E23: =SUM(E12:E22) | F23: =SUM(F12:F22) | G23: =SUM(G12:G22) | H23: =SUM(H12:H22) | I23: =SUM(I12:I22) | J23: =SUM(J12:J22)
A24: 三、审计说明：
A26: 四、审计结论：

Sheet 关联方及交易检查表L5-6
A1: 致同会计师事务所
A2: 关联方及交易检查表
A3: =底稿目录!A2 | F3: =底稿目录!A4 | J3: =底稿目录!A5 | N3: 索引号： | O3: =底稿目录!F18
A4: =底稿目录!A3 | F4: =底稿目录!A6 | J4: =底稿目录!A7 | N4: 页次：
A5: 关注对关联方的预付款项的真实性、合理性、合法性、会计处理是否正确，考虑是否存在未识别的关联方，检查关联交易和余额披露是否正确。
A6: 考虑发生在企业与关联方之间的交易是否得到适当的会计处理。了解关联交易事项的目的、价格和条件，检查交易的支持性文件，同时向关联方或其他注册会计师函证重大的交易（包括担保和其他重要信息），以确认交易的真实性；必要时，向与交易相关的人员和机构（如银行、律师）函证或与其讨论有关信息。
A7: 项目 | B7: 关联方名称 | C7: 关联关系 | D7: 长期应付款 | E7: 未确认融资费用 | F7: 账面余额 | G7: 减：期末一年内到期长期应付款 | H7: 减：期末一年内到期未确认融资费用 | I7: 期末一年内到期长期应付款余额 | J7: 审定数 | K7: 发生时间及账龄 | L7: 到期日 | M7: 发生原因（款项性质） | N7: 索引号 | O7: 备注
F8: =D8-E8 | I8: =G8-H8 | J8: =F8-I8
F9: =D9-E9 | I9: =G9-H9 | J9: =F9-I9
F10: =D10-E10 | I10: =G10-H10 | J10: =F10-I10
F11: =D11-E11 | I11: =G11-H11 | J11: =F11-I11
F12: =D12-E12 | I12: =G12-H12 | J12: =F12-I12
A13: 小计 | D13: =SUM(D8:D12) | E13: =SUM(E8:E12) | F13: =SUM(F8:F12) | G13: =SUM(G8:G12) | H13: =SUM(H8:H12) | I13: =SUM(I8:I12) | J13: =SUM(J8:J12) | N13: —— | O13: ——
A14: 一、审计说明：
A17: 二、审计结论：
I18: 勿删、勿改 | J18: 实际控制人
J19: 控股股东
J20: 控股股东、实际控制人的附属企业
J21: 持有5%以上股份的法人或其他组织
J22: 联营企业
J23: 合营企业
J24: 董高监等关键管理人员
J25: 其他关联方

Sheet 长期应付款检查表L5-7
A1: 致同会计师事务所
A2: 长期应付款检查表
A3: =底稿目录!A2 | D3: =底稿目录!A4 | G3: =底稿目录!A5 | O3: 索引号： | P3: =底稿目录!F19
A4: =底稿目录!A3 | D4: =底稿目录!A6 | G4: =底稿目录!A7 | O4: 页次：
A5: 一、审计目标：
A6: 1.资产负债表中记录的长期应付款是存在的，且已经记录在恰当的账户中； 2.记录的长期应付款由被审计单位拥有或控制；
A7: 3.长期应付款以恰当的金额包括在财务报表中，与之相关的计价或分摊调整已恰当记录，相关披露已得到恰当计量和描述
A8: 二、测试： | C8: 测试原因：大额（）关联方（）大额交易频繁（）异常（）其他（）
A9: 测试内容说明：1.原始凭证是否齐全； 2.记账凭证与原始凭证是否相符；3.账务处理是否正确；4.是否记录于恰当的会计期间；5.……
A10: 记账凭证 | H10: 支持性文件 | I10: 核对内容 | N10: 索引号 | O10: 是否异常 | P10: 备注说明
A11: 日期 | B11: 凭证编号 | C11: 业务内容 | D11: 对方科目 | E11: 对方明细科目 | F11: 借方金额 | G11: 贷方金额 | I11: 1 | J11: 2 | K11: 3 | L11: 4 | M11: 5
A21: 合计 | F21: =SUM(F12:F20) | G21: =SUM(G12:G20)
A22: 本期发生额 | F22: ='明细表L5-2'!M25 | G22: ='明细表L5-2'!N25
A23: 检查比例 | F23: =F21/F22 | G23: =G21/G22
A24: 三、审计说明：
A26: 四、审计结论：

Sheet GT_Custom
A1: C1 | B1: Custom 1
A2: C2 | B2: Custom 2
A3: C3 | B3: Custom 3
A4: C4 | B4: Custom 4
A5: C5 | B5: Custom 5
A6: C6 | B6: Custom 6
A7: C7 | B7: Custom 7
A8: C8 | B8: Custom 8
