Workbook

Sheet 底稿目录
A1: 底稿开列时，可先在以下单元格填写有关内容，以便其他底稿引用有关数据：
A2: 被审计单位：
A3: 截止日：202X年12月31日 | D3: 序号 | E3: 内容 | F3: 索引号 | G3: 备注
A4: 编制人： | D4: 1 | E4: 实收资本实质性程序表 | F4: M2A
A5: 编制日期： | D5: 2 | E5: 审定表 | F5: M2-1
A6: 复核人： | D6: 3 | E6: 附注披露信息(上市公司) | H6: 无需打印
A7: 复核日期： | D7: 4 | E7: 附注披露信息(国企) | H7: 无需打印
D8: 5 | E8: 明细表（上市公司） | F8: M2-2
A9: 关于工作底稿与审计程序索引号对应的说明 | D9: 6 | E9: 明细表（非上市公司） | F9: M2-2
A10: 1.编制的审计工作底稿应与审计程序对应。审计项目组应根据被审计单位实际情况和风险评估情况在实质性程序表中裁剪、修改或增加审计程序，根据实际执行的审计程序完成相应审计工作底稿，编制的工作底稿中应按自然顺序依次编制索引号，并通过唯一的索引号将与实质性程序表中的程序对应关联（即将工作底稿的索引号填入实质性程序表中的底稿索引号列）。 | D10: 7 | E10: 调整分录汇总 | F10: M2-3
D11: 8 | E11: 外币投资汇率测算表 | F11: M2-4
D12: 9 | E12: 实收资本（股本）检查表 | F12: M2-5
A14: 2.获取的支持性证据应与审计底稿或程序对应。审计项目组在完成底稿时获取的支持性证据应根据底稿索引号编制下一级按自然顺序排序的索引号（如D1-2-1、D1-2-2、……），并在底稿中说明引用的支持性证据、关联索引号。
A17: 3.工作底稿索引号的编码规则：实质性程序索引号按循环从“D”到“N”,循环内账户以顺序号排列，模板中底稿索引号按账户顺序+自然数顺序（即模板中索引号按二级自然顺序排列，如D1-1、D1-2、D1-3、……D1-N）。

Sheet  实收资本实质性程序表 M2A
A1: 致同会计师事务所
A2: 实收资本实质性程序
A3: =底稿目录!A2 -> 被审计单位： | C3: =底稿目录!A4 -> 编制人： | E3: =底稿目录!A5 -> 编制日期： | H3: 索引号： | I3: =底稿目录!F4 -> M2A
A4: =底稿目录!A3 -> 截止日：202X年12月31日 | C4: =底稿目录!A6 -> 复核人： | E4: =底稿目录!A7 -> 复核日期： | H4: 页 次：
A5: 一、本账户涉及的科目
A6: 实收资本
A7: 二、审计目标与认定的对应关系
A8: 审计目标 | G8: 财务报表的认定
A9: A. 资产负债表中记录的实收资本是存在的，且已经记录在恰当的账户中 | G9: 存在
A10: B. 所有应记录的实收资本均已记录，所有应当包括在财务报表中的相关披露均已包括 | G10: 完整性
A11: C. 记录的实收资本由被审计单位拥有或控制 | G11: 权利和义务
A12: D. 实收资本以恰当的金额包括在财务报表中，与之相关的计价或分摊调整已恰当记录，相关披露已得到恰当计量和描述 | G12: 准确性、计价和分摊
A13: E. 实收资本已被恰当地汇总或分解且表述清楚，相关披露在按照企业会计准则的编制基础下是相关的、可理解的 | G13: 列报
A14: 三、计划实施的实质性程序
A15: 序号 | B15: 审计程序 | C15: 程序分类 | D15: 财务报表的认定 | I15: 底稿索引号
D16: 存在 | E16: 完整性 | F16: 权利和 义务 | G16: 准确性、计价和分摊 | H16: 列报 | J16: 根据被审计单位实际情况和风险评估情况裁剪、修改或增加审计程序
A17: 1 | B17: 获取或编制实收资本（股本）明细表，完成以下工作，并编制审定表 （1）复核加计是否正确，与总账、明细账合计数核对是否相符，期初余额与上期审定期末余额是否相符； （2）以非记账本位币出资的，检查其折算汇率是否符合规定，折算差额的会计处理是否正确。 | C17: 常规★ | D17: √ | E17: √ | G17: √ | I17: M2-1 /M2-2 /M2-4
A18: 2 | B18: 在使用手工编制、自定义信息报告、系统生成的非固定格式报告等由被审计单位生成的信息时，测试有关信息准确性和完整性，并考虑针对编制和维护由被审计单位生成的信息的相关控制实施控制测试，以评价该信息是否能够为实现审计目的提供基础。 | C18: 常规★ | E18: √ | G18: √ | I18: T1 / | J18: 可参见《审计手册》4.2.6，由被审计单位生成的信息可能是由系统生成的、或手工编制的、或二者兼而有之的方式生成的。例如，由被审计单位生成的信息可能包括： • 不涉及自定义的、由系统生成的报告（如，固定格式报告）； • 可能通过人工自定义的、由系统生成的报告，例如，（计算机）查询信息或特别定制的报告； • 手工编制的信息，例如，汇总信息的电子表格或用以支持分配、计算以及调节的电子表格； • 其他系统生成或手工编制的信息，例如，由被审计单位编制的客户发票； • 通过影印、拍摄、扫描或其他方式转换成电子形式的文件记录。
A19: 3 | B19: 对于上期实收资本的期末余额，取得企业成立时的文件、投资/合伙协议、历次股本变化相关文件、验资报告等，检查与账面记录是否相符；必要时与证券结算中介机构股票登记簿核对、向每位股东函证出资金额及比例。（适用于首次承接） | C19: 备选 | D19: √ | E19: √ | F19: √ | G19: √ | J19: 由被审计单位生成的信息不包括： • 总分类账或明细分类账、试算平衡表、或经审计的财务报表； • 第三方（除了服务机构）的报表或报告，例如，原始银行对账单，或函证的回函； • 外部数据（例如，第三方发布的数据，如，定价来源）。
A20: 4 | B20: 对本期实收资本（股本）发生的增减变动： （1）对本期发生的实收资本（股本）的增减变动，获取公司章程、股东（大）会/董事会决议、验资报告、政府主管部门批复等相关文件，检查出资期限和出资方式、出资额，检查投资者是否按合同、协议、章程约定的时间和方式缴付出资额，实物资产是否转移、是否为生产经营所需。 （2）检查与投入资本有关的原始凭证、会计处理是否正确，必要时，向投资者函证实缴资本额，对有关财产和实物价值进行鉴定，以确定投入资本的真实性。结合往来款审计等关注有无抽资或变相抽资的情况。 | C20: 常规★ | D20: √ | E20: √ | F20: √ | I20: M2-2 /M2-5
A21: 5 | B21: 检查股权协议，考虑是否有需要单独确认的嵌入式衍生工具。如果有，完成金融工具审计程序。 | C21: 备选 | D21: √ | E21: √ | F21: √
A22: 6 | B22: 如果存在库存股交易： （1）检查股票回购的交易活动。检查的内容包括已发行股票的登记簿、回购的股票、银行对账单、会计账面记录等； （2）以回购股票以及其他法定程序报经批准减资的，检查股东会决议以及相关的法律文件，手续是否办理，检查其是否按注销的股票面值总额和所注销的库存股的账面余额，冲减资本公积，会计处理是否正确. | C22: 备选 | D22: √ | E22: √ | F22: √
A23: 7 | B23: 对可转换公司债券持有人行使转换权利转为股本和形成的股本溢价，结合长期债券的审计，检查相关的法律文件，手续是否办理，检查入账金额和会计处理是否正确。 | C23: 备选 | D23: √ | E23: √ | F23: √
A24: 8 | B24: 对重组债务转为资本和形成的资本溢价，结合债务重组的审计，检查相关合同协议，并确定会计处理是否正确。 | C24: 备选 | D24: √ | E24: √ | F24: √
A25: 9 | B25: 中外合资经营企业在合作期间归还投资的，获取与归还投资变动有关的公司章程、合同、董事会会议纪要、政府部门的批准文件等资料，查明其是否合规、合法，并更新永久性档案，并对已归还投资的发生额逐项审计至原始凭证，检查应用的折算汇率和会计处理是否符合相关规定。 | C25: 备选 | D25: √ | E25: √ | F25: √ | G25: √
A26: 10 | B26: 复核普通股基本每股收益和稀释每股收益计算的准确性，将金额和股数与财务报表核对。 | C26: 备选 | G26: √
A27: 11 | B27: 考虑PE等投资者入股价格的合理性，关注是否存在PE等投资者串通发行人虚增收入、代垫成本费用等利益输送行为。 | C27: IPO/上市/新三板/重组/舞弊应对
A28: 12 | B28: 根据评估的舞弊风险等因素增加的审计程序。 | C28: IPO/上市/新三板/重组/舞弊应对
A29: 13 | B29: 检查实收资本是否已按企业会计准则或其他适用的规定在财务报表中做出恰当列报和披露。 | C29: 常规★ | H29: √ | I29: A1-1/A1-15 /A1-16

Sheet 审定表M2-1
A1: 致同会计师事务所
A2: 实收资本（或股本）审定表
A3: =底稿目录!A2 -> 被审计单位： | E3: =底稿目录!A4 -> 编制人： | H3: =底稿目录!A5 -> 编制日期： | K3: 索引号： | L3: =底稿目录!F5 -> M2-1
A4: =底稿目录!A3 -> 截止日：202X年12月31日 | E4: =底稿目录!A6 -> 复核人： | H4: =底稿目录!A7 -> 复核日期： | K4: 页 次：
A5: 项目名称 | B5: 期初数 | F5: 期末数 | J5: 本期审定数与上期 审定数的比较 | L5: 原因分析
B6: 未审数 | C6: 账项调整 | D6: 重分类调整 | E6: 审定数 | F6: 未审数 | G6: 账项调整 | H6: 重分类调整 | I6: 审定数 | J6: 变动额 | K6: 变动率
A7: ='明细表（非上市公司）M2-2'!A13 -> 0 | B7: ='明细表（非上市公司）M2-2'!C13 -> 0 | C7: ='明细表（非上市公司）M2-2'!J13 -> 0 | D7: ='明细表（非上市公司）M2-2'!K13 -> 0 | E7: ='明细表（非上市公司）M2-2'!P13 -> 0 | F7: ='明细表（非上市公司）M2-2'!H13 -> 0 | G7: ='明细表（非上市公司）M2-2'!J13+'明细表（非上市公司）M2-2'!L13-'明细表（非上市公司）M2-2'!M13 -> 0 | H7: ='明细表（非上市公司）M2-2'!K13+'明细表（非上市公司）M2-2'!N13-'明细表（非上市公司）M2-2'!O13 -> 0 | I7: ='明细表（非上市公司）M2-2'!T13 -> 0 | J7: =I7-E7 -> 0 | K7: =IF(AND(E7=0,J7=0),0,IF(AND(E7=0,J7>0),1,J7/E7)) -> 0
A8: ='明细表（非上市公司）M2-2'!A14 -> 0 | B8: ='明细表（非上市公司）M2-2'!C14 -> 0 | C8: ='明细表（非上市公司）M2-2'!J14 -> 0 | D8: ='明细表（非上市公司）M2-2'!K14 -> 0 | E8: ='明细表（非上市公司）M2-2'!P14 -> 0 | F8: ='明细表（非上市公司）M2-2'!H14 -> 0 | G8: ='明细表（非上市公司）M2-2'!J14+'明细表（非上市公司）M2-2'!L14-'明细表（非上市公司）M2-2'!M14 -> 0 | H8: ='明细表（非上市公司）M2-2'!K14+'明细表（非上市公司）M2-2'!N14-'明细表（非上市公司）M2-2'!O14 -> 0 | I8: ='明细表（非上市公司）M2-2'!T14 -> 0 | J8: =I8-E8 -> 0 | K8: =IF(AND(E8=0,J8=0),0,IF(AND(E8=0,J8>0),1,J8/E8)) -> 0
A9: ='明细表（非上市公司）M2-2'!A15 -> 0 | B9: ='明细表（非上市公司）M2-2'!C15 -> 0 | C9: ='明细表（非上市公司）M2-2'!J15 -> 0 | D9: ='明细表（非上市公司）M2-2'!K15 -> 0 | E9: ='明细表（非上市公司）M2-2'!P15 -> 0 | F9: ='明细表（非上市公司）M2-2'!H15 -> 0 | G9: ='明细表（非上市公司）M2-2'!J15+'明细表（非上市公司）M2-2'!L15-'明细表（非上市公司）M2-2'!M15 -> 0 | H9: ='明细表（非上市公司）M2-2'!K15+'明细表（非上市公司）M2-2'!N15-'明细表（非上市公司）M2-2'!O15 -> 0 | I9: ='明细表（非上市公司）M2-2'!T15 -> 0 | J9: =I9-E9 -> 0 | K9: =IF(AND(E9=0,J9=0),0,IF(AND(E9=0,J9>0),1,J9/E9)) -> 0
A10: ='明细表（非上市公司）M2-2'!A16 -> 0 | B10: ='明细表（非上市公司）M2-2'!C16 -> 0 | C10: ='明细表（非上市公司）M2-2'!J16 -> 0 | D10: ='明细表（非上市公司）M2-2'!K16 -> 0 | E10: ='明细表（非上市公司）M2-2'!P16 -> 0 | F10: ='明细表（非上市公司）M2-2'!H16 -> 0 | G10: ='明细表（非上市公司）M2-2'!J16+'明细表（非上市公司）M2-2'!L16-'明细表（非上市公司）M2-2'!M16 -> 0 | H10: ='明细表（非上市公司）M2-2'!K16+'明细表（非上市公司）M2-2'!N16-'明细表（非上市公司）M2-2'!O16 -> 0 | I10: ='明细表（非上市公司）M2-2'!T16 -> 0 | J10: =I10-E10 -> 0 | K10: =IF(AND(E10=0,J10=0),0,IF(AND(E10=0,J10>0),1,J10/E10)) -> 0
A11: ='明细表（非上市公司）M2-2'!A17 -> 0 | B11: ='明细表（非上市公司）M2-2'!C17 -> 0 | C11: ='明细表（非上市公司）M2-2'!J17 -> 0 | D11: ='明细表（非上市公司）M2-2'!K17 -> 0 | E11: ='明细表（非上市公司）M2-2'!P17 -> 0 | F11: ='明细表（非上市公司）M2-2'!H17 -> 0 | G11: ='明细表（非上市公司）M2-2'!J17+'明细表（非上市公司）M2-2'!L17-'明细表（非上市公司）M2-2'!M17 -> 0 | H11: ='明细表（非上市公司）M2-2'!K17+'明细表（非上市公司）M2-2'!N17-'明细表（非上市公司）M2-2'!O17 -> 0 | I11: ='明细表（非上市公司）M2-2'!T17 -> 0 | J11: =I11-E11 -> 0 | K11: =IF(AND(E11=0,J11=0),0,IF(AND(E11=0,J11>0),1,J11/E11)) -> 0
A12: ='明细表（非上市公司）M2-2'!A18 -> 0 | B12: ='明细表（非上市公司）M2-2'!C18 -> 0 | C12: ='明细表（非上市公司）M2-2'!J18 -> 0 | D12: ='明细表（非上市公司）M2-2'!K18 -> 0 | E12: ='明细表（非上市公司）M2-2'!P18 -> 0 | F12: ='明细表（非上市公司）M2-2'!H18 -> 0 | G12: ='明细表（非上市公司）M2-2'!J18+'明细表（非上市公司）M2-2'!L18-'明细表（非上市公司）M2-2'!M18 -> 0 | H12: ='明细表（非上市公司）M2-2'!K18+'明细表（非上市公司）M2-2'!N18-'明细表（非上市公司）M2-2'!O18 -> 0 | I12: ='明细表（非上市公司）M2-2'!T18 -> 0 | J12: =I12-E12 -> 0 | K12: =IF(AND(E12=0,J12=0),0,IF(AND(E12=0,J12>0),1,J12/E12)) -> 0
A13: ='明细表（非上市公司）M2-2'!A19 -> 0 | B13: ='明细表（非上市公司）M2-2'!C19 -> 0 | C13: ='明细表（非上市公司）M2-2'!J19 -> 0 | D13: ='明细表（非上市公司）M2-2'!K19 -> 0 | E13: ='明细表（非上市公司）M2-2'!P19 -> 0 | F13: ='明细表（非上市公司）M2-2'!H19 -> 0 | G13: ='明细表（非上市公司）M2-2'!J19+'明细表（非上市公司）M2-2'!L19-'明细表（非上市公司）M2-2'!M19 -> 0 | H13: ='明细表（非上市公司）M2-2'!K19+'明细表（非上市公司）M2-2'!N19-'明细表（非上市公司）M2-2'!O19 -> 0 | I13: ='明细表（非上市公司）M2-2'!T19 -> 0 | J13: =I13-E13 -> 0 | K13: =IF(AND(E13=0,J13=0),0,IF(AND(E13=0,J13>0),1,J13/E13)) -> 0
A14: ='明细表（非上市公司）M2-2'!A20 -> 0 | B14: ='明细表（非上市公司）M2-2'!C20 -> 0 | C14: ='明细表（非上市公司）M2-2'!J20 -> 0 | D14: ='明细表（非上市公司）M2-2'!K20 -> 0 | E14: ='明细表（非上市公司）M2-2'!P20 -> 0 | F14: ='明细表（非上市公司）M2-2'!H20 -> 0 | G14: ='明细表（非上市公司）M2-2'!J20+'明细表（非上市公司）M2-2'!L20-'明细表（非上市公司）M2-2'!M20 -> 0 | H14: ='明细表（非上市公司）M2-2'!K20+'明细表（非上市公司）M2-2'!N20-'明细表（非上市公司）M2-2'!O20 -> 0 | I14: ='明细表（非上市公司）M2-2'!T20 -> 0 | J14: =I14-E14 -> 0 | K14: =IF(AND(E14=0,J14=0),0,IF(AND(E14=0,J14>0),1,J14/E14)) -> 0
A15: ='明细表（非上市公司）M2-2'!A21 -> 0 | B15: ='明细表（非上市公司）M2-2'!C21 -> 0 | C15: ='明细表（非上市公司）M2-2'!J21 -> 0 | D15: ='明细表（非上市公司）M2-2'!K21 -> 0 | E15: ='明细表（非上市公司）M2-2'!P21 -> 0 | F15: ='明细表（非上市公司）M2-2'!H21 -> 0 | G15: ='明细表（非上市公司）M2-2'!J21+'明细表（非上市公司）M2-2'!L21-'明细表（非上市公司）M2-2'!M21 -> 0 | H15: ='明细表（非上市公司）M2-2'!K21+'明细表（非上市公司）M2-2'!N21-'明细表（非上市公司）M2-2'!O21 -> 0 | I15: ='明细表（非上市公司）M2-2'!T21 -> 0 | J15: =I15-E15 -> 0 | K15: =IF(AND(E15=0,J15=0),0,IF(AND(E15=0,J15>0),1,J15/E15)) -> 0
A16: ='明细表（非上市公司）M2-2'!A22 -> 0 | B16: ='明细表（非上市公司）M2-2'!C22 -> 0 | C16: ='明细表（非上市公司）M2-2'!J22 -> 0 | D16: ='明细表（非上市公司）M2-2'!K22 -> 0 | E16: ='明细表（非上市公司）M2-2'!P22 -> 0 | F16: ='明细表（非上市公司）M2-2'!H22 -> 0 | G16: ='明细表（非上市公司）M2-2'!J22+'明细表（非上市公司）M2-2'!L22-'明细表（非上市公司）M2-2'!M22 -> 0 | H16: ='明细表（非上市公司）M2-2'!K22+'明细表（非上市公司）M2-2'!N22-'明细表（非上市公司）M2-2'!O22 -> 0 | I16: ='明细表（非上市公司）M2-2'!T22 -> 0 | J16: =I16-E16 -> 0 | K16: =IF(AND(E16=0,J16=0),0,IF(AND(E16=0,J16>0),1,J16/E16)) -> 0
A17: 合计 | B17: =SUM(B7:B16) -> 0 | C17: =SUM(C7:C16) -> 0 | D17: =SUM(D7:D16) -> 0 | E17: =SUM(E7:E16) -> 0 | F17: =SUM(F7:F16) -> 0 | G17: =SUM(G7:G16) -> 0 | H17: =SUM(H7:H16) -> 0 | I17: =SUM(I7:I16) -> 0 | J17: =I17-E17 -> 0 | K17: =IF(AND(E17=0,J17=0),0,IF(AND(E17=0,J17>0),1,J17/E17)) -> 0
A18: 试算平衡表数
A19: 差异数 | E19: =E17-E18 -> 0 | I19: =I17-I18 -> 0
A20: 1、审计说明
A21: （1）期末余额较期初余额增加（负数为减少）：
A22: 主要原因（比例超过30%的）：
A23: （2）情况说明。
A24: 2、审计结论

Sheet 附注披露信息（上市公司）
A1: 致同会计师事务所
A2: 实收资本（股本）附注披露信息（上市公司）
A3: =底稿目录!A2 -> 被审计单位： | C3: =底稿目录!A4 -> 编制人： | E3: =底稿目录!A5 -> 编制日期： | G3: 索引号： | H3: M2-1
A4: =底稿目录!A3 -> 截止日：202X年12月31日 | C4: =底稿目录!A6 -> 复核人： | E4: =底稿目录!A7 -> 复核日期： | G4: 页次：
A5: 股本（单位：万股）
A6: 项 目 | B6: 期初余额 | C6: 本期增减（+、-） | H6: 期末余额
C7: 发行新股 | D7: 送股 | E7: 公积金转股 | F7: 其他 | G7: 小计
A8: 股份总数 | B8: ='明细表（上市公司）M2-2'!Y23 -> 0 | C8: ='明细表（上市公司）M2-2'!AA23 -> 0 | D8: ='明细表（上市公司）M2-2'!AB23 -> 0 | E8: ='明细表（上市公司）M2-2'!AC23 -> 0 | F8: ='明细表（上市公司）M2-2'!AD23 -> 0 | G8: ='明细表（上市公司）M2-2'!AE23 -> 0 | H8: ='明细表（上市公司）M2-2'!AF23 -> 0
A9: 说明：（如果报告期内有增资或减资行为的，应披露执行验资的会计师事务所名称和验资报告文号；运行不足3年的股份有限公司，设立前的年份只需说明净资产情况；有限责任公司整体变更为股份公司应说明公司设立时的验资情况。）

Sheet 附注披露信息（国有企业）
A1: 致同会计师事务所
A2: 实收资本（股本）附注披露信息（国有企业）
A3: =底稿目录!A2 -> 被审计单位： | C3: =底稿目录!A4 -> 编制人： | E3: =底稿目录!A5 -> 编制日期： | G3: 索引号：M2-1
A4: =底稿目录!A3 -> 截止日：202X年12月31日 | C4: =底稿目录!A6 -> 复核人： | E4: =底稿目录!A7 -> 复核日期： | G4: 页次：
A5: 实收资本
A6: 投资者名称 | B6: 年初余额 | D6: 本期增加 | E6: 本期减少 | F6: 期末余额
B7: 投资金额 | C7: 所占比例（%） | F7: 投资金额 | G7: 所占比例（%）
A8: ='明细表（非上市公司）M2-2'!A13 -> 0 | B8: ='明细表（非上市公司）M2-2'!P13 -> 0 | C8: ='明细表（非上市公司）M2-2'!Q13 -> 0 | D8: ='明细表（非上市公司）M2-2'!R13 -> 0 | E8: ='明细表（非上市公司）M2-2'!S13 -> 0 | F8: ='明细表（非上市公司）M2-2'!T13 -> 0 | G8: ='明细表（非上市公司）M2-2'!U13 -> 0
A9: ='明细表（非上市公司）M2-2'!A14 -> 0 | B9: ='明细表（非上市公司）M2-2'!P14 -> 0 | C9: ='明细表（非上市公司）M2-2'!Q14 -> 0 | D9: ='明细表（非上市公司）M2-2'!R14 -> 0 | E9: ='明细表（非上市公司）M2-2'!S14 -> 0 | F9: ='明细表（非上市公司）M2-2'!T14 -> 0 | G9: ='明细表（非上市公司）M2-2'!U14 -> 0
A10: ='明细表（非上市公司）M2-2'!A15 -> 0 | B10: ='明细表（非上市公司）M2-2'!P15 -> 0 | C10: ='明细表（非上市公司）M2-2'!Q15 -> 0 | D10: ='明细表（非上市公司）M2-2'!R15 -> 0 | E10: ='明细表（非上市公司）M2-2'!S15 -> 0 | F10: ='明细表（非上市公司）M2-2'!T15 -> 0 | G10: ='明细表（非上市公司）M2-2'!U15 -> 0
A11: ='明细表（非上市公司）M2-2'!A16 -> 0 | B11: ='明细表（非上市公司）M2-2'!P16 -> 0 | C11: ='明细表（非上市公司）M2-2'!Q16 -> 0 | D11: ='明细表（非上市公司）M2-2'!R16 -> 0 | E11: ='明细表（非上市公司）M2-2'!S16 -> 0 | F11: ='明细表（非上市公司）M2-2'!T16 -> 0 | G11: ='明细表（非上市公司）M2-2'!U16 -> 0
A12: ='明细表（非上市公司）M2-2'!A17 -> 0 | B12: ='明细表（非上市公司）M2-2'!P17 -> 0 | C12: ='明细表（非上市公司）M2-2'!Q17 -> 0 | D12: ='明细表（非上市公司）M2-2'!R17 -> 0 | E12: ='明细表（非上市公司）M2-2'!S17 -> 0 | F12: ='明细表（非上市公司）M2-2'!T17 -> 0 | G12: ='明细表（非上市公司）M2-2'!U17 -> 0
A13: ='明细表（非上市公司）M2-2'!A18 -> 0 | B13: ='明细表（非上市公司）M2-2'!P18 -> 0 | C13: ='明细表（非上市公司）M2-2'!Q18 -> 0 | D13: ='明细表（非上市公司）M2-2'!R18 -> 0 | E13: ='明细表（非上市公司）M2-2'!S18 -> 0 | F13: ='明细表（非上市公司）M2-2'!T18 -> 0 | G13: ='明细表（非上市公司）M2-2'!U18 -> 0
A14: ='明细表（非上市公司）M2-2'!A19 -> 0 | B14: ='明细表（非上市公司）M2-2'!P19 -> 0 | C14: ='明细表（非上市公司）M2-2'!Q19 -> 0 | D14: ='明细表（非上市公司）M2-2'!R19 -> 0 | E14: ='明细表（非上市公司）M2-2'!S19 -> 0 | F14: ='明细表（非上市公司）M2-2'!T19 -> 0 | G14: ='明细表（非上市公司）M2-2'!U19 -> 0
A15: ='明细表（非上市公司）M2-2'!A20 -> 0 | B15: ='明细表（非上市公司）M2-2'!P20 -> 0 | C15: ='明细表（非上市公司）M2-2'!Q20 -> 0 | D15: ='明细表（非上市公司）M2-2'!R20 -> 0 | E15: ='明细表（非上市公司）M2-2'!S20 -> 0 | F15: ='明细表（非上市公司）M2-2'!T20 -> 0 | G15: ='明细表（非上市公司）M2-2'!U20 -> 0
A16: ='明细表（非上市公司）M2-2'!A21 -> 0 | B16: ='明细表（非上市公司）M2-2'!P21 -> 0 | C16: ='明细表（非上市公司）M2-2'!Q21 -> 0 | D16: ='明细表（非上市公司）M2-2'!R21 -> 0 | E16: ='明细表（非上市公司）M2-2'!S21 -> 0 | F16: ='明细表（非上市公司）M2-2'!T21 -> 0 | G16: ='明细表（非上市公司）M2-2'!U21 -> 0
A17: ='明细表（非上市公司）M2-2'!A22 -> 0 | B17: ='明细表（非上市公司）M2-2'!P22 -> 0 | C17: ='明细表（非上市公司）M2-2'!Q22 -> 0 | D17: ='明细表（非上市公司）M2-2'!R22 -> 0 | E17: ='明细表（非上市公司）M2-2'!S22 -> 0 | F17: ='明细表（非上市公司）M2-2'!T22 -> 0 | G17: ='明细表（非上市公司）M2-2'!U22 -> 0
A18: 合 计 | B18: =SUM(B8:B17) -> 0 | C18: =SUM(C8:C17) -> 0 | D18: =SUM(D8:D17) -> 0 | E18: =SUM(E8:E17) -> 0 | F18: =SUM(F8:F17) -> 0 | G18: =SUM(G8:G17) -> 0
A19: （如果报告期内有增减变动行为的，应披露执行验资的会计师事务所名称和验资报告文号。）
A20: （企业所有者权益中，国家所有者权益各项目的变化数额及其变化原因（参照国有资产变动情况表）

Sheet 明细表（上市公司）M2-2
A1: 致同会计师事务所
A2: 实收资本（或股本）明细表
A3: =底稿目录!A2 -> 被审计单位： | G3: =底稿目录!A4 -> 编制人： | X3: =底稿目录!A5 -> 编制日期： | AI3: 索引号： | AJ3: =底稿目录!F9 -> M2-2
A4: =底稿目录!A3 -> 截止日：202X年12月31日 | G4: =底稿目录!A6 -> 复核人： | X4: =底稿目录!A7 -> 复核日期： | AI4: 页 次：
A5: 一、审计目标:
A6: 1.资产负债表中记录的实收资本（股本）是存在的，且已经记录在恰当的账户中；
A7: 2.所有应记录的实收资本（股本）均已记录，所有应当包括在财务报表中的相关披露均已包括；
A8: 3.实收资本（股本）以恰当的金额包括在财务报表中，与之相关的计价或分摊调整已恰当记录，相关披露已得到恰当计量和描述 ；
A9: 二、审计过程：
A10: 投资方名称 | B10: 公司代码 | C10: 未审数 | M10: 期初调整（本位币） | O10: 账项调整（本位币） | T10: 重分类调整（本位币） | Y10: 审定数（本位币） | AH10: 是否经过验资 | AI10: 验资报告索引号 | AJ10: 备注
C11: 期初数 | F11: 本期增减（+、-） | K11: 期末数 | M11: 账项调整 | N11: 重分类调整 | O11: 本期增减（+、-） | T11: 本期增减（+、-） | Y11: 期初数 | AA11: 本期增减（+、-） | AF11: 期末数
C12: 出资方式 | D12: 出资金额 | E12: 比例% | F12: 发行新股 | G12: 送股 | H12: 公积金转股 | I12: 其他 | J12: 小计 | K12: 出资金额 | L12: 比例% | O12: 发行新股 | P12: 送股 | Q12: 公积金转股 | R12: 其他 | S12: 小计 | T12: 发行新股 | U12: 送股 | V12: 公积金转股 | W12: 其他 | X12: 小计 | Y12: 出资金额 | Z12: 比例% | AA12: 发行新股 | AB12: 送股 | AC12: 公积金转股 | AD12: 其他 | AE12: 小计 | AF12: 出资金额 | AG12: 比例%
E13: =IF(D13=0,0,D13/$D$23) -> 0 | J13: =SUM(F13:I13) -> 0 | K13: =D13+F13-J13 -> 0 | L13: =IF(K13=0,0,K13/$K$23) -> 0 | S13: =SUM(O13:R13) -> 0 | X13: =SUM(T13:W13) -> 0 | Y13: =D13+M13+N13 -> 0 | Z13: =IF(Y13=0,0,Y13/$Y$23) -> 0 | AA13: =F13+O13+T13 -> 0 | AB13: =G13+P13+U13 -> 0 | AC13: =H13+Q13+V13 -> 0 | AD13: =I13+R13+W13 -> 0 | AE13: =SUM(AA13:AD13) -> 0 | AF13: =Y13+AE13 -> 0 | AG13: =IF(AF13=0,0,AF13/$AF$23) -> 0
E14: =IF(D14=0,0,D14/$D$23) -> 0 | J14: =SUM(F14:I14) -> 0 | K14: =D14+F14-J14 -> 0 | L14: =IF(K14=0,0,K14/$K$23) -> 0 | S14: =SUM(O14:R14) -> 0 | X14: =SUM(T14:W14) -> 0 | Y14: =D14+M14+N14 -> 0 | Z14: =IF(Y14=0,0,Y14/$Y$23) -> 0 | AA14: =F14+O14+T14 -> 0 | AB14: =G14+P14+U14 -> 0 | AC14: =H14+Q14+V14 -> 0 | AD14: =I14+R14+W14 -> 0 | AE14: =SUM(AA14:AD14) -> 0 | AF14: =Y14+AE14 -> 0 | AG14: =IF(AF14=0,0,AF14/$AF$23) -> 0
E15: =IF(D15=0,0,D15/$D$23) -> 0 | J15: =SUM(F15:I15) -> 0 | K15: =D15+F15-J15 -> 0 | L15: =IF(K15=0,0,K15/$K$23) -> 0 | S15: =SUM(O15:R15) -> 0 | X15: =SUM(T15:W15) -> 0 | Y15: =D15+M15+N15 -> 0 | Z15: =IF(Y15=0,0,Y15/$Y$23) -> 0 | AA15: =F15+O15+T15 -> 0 | AB15: =G15+P15+U15 -> 0 | AC15: =H15+Q15+V15 -> 0 | AD15: =I15+R15+W15 -> 0 | AE15: =SUM(AA15:AD15) -> 0 | AF15: =Y15+AE15 -> 0 | AG15: =IF(AF15=0,0,AF15/$AF$23) -> 0
E16: =IF(D16=0,0,D16/$D$23) -> 0 | J16: =SUM(F16:I16) -> 0 | K16: =D16+F16-J16 -> 0 | L16: =IF(K16=0,0,K16/$K$23) -> 0 | S16: =SUM(O16:R16) -> 0 | X16: =SUM(T16:W16) -> 0 | Y16: =D16+M16+N16 -> 0 | Z16: =IF(Y16=0,0,Y16/$Y$23) -> 0 | AA16: =F16+O16+T16 -> 0 | AB16: =G16+P16+U16 -> 0 | AC16: =H16+Q16+V16 -> 0 | AD16: =I16+R16+W16 -> 0 | AE16: =SUM(AA16:AD16) -> 0 | AF16: =Y16+AE16 -> 0 | AG16: =IF(AF16=0,0,AF16/$AF$23) -> 0
E17: =IF(D17=0,0,D17/$D$23) -> 0 | J17: =SUM(F17:I17) -> 0 | K17: =D17+F17-J17 -> 0 | L17: =IF(K17=0,0,K17/$K$23) -> 0 | S17: =SUM(O17:R17) -> 0 | X17: =SUM(T17:W17) -> 0 | Y17: =D17+M17+N17 -> 0 | Z17: =IF(Y17=0,0,Y17/$Y$23) -> 0 | AA17: =F17+O17+T17 -> 0 | AB17: =G17+P17+U17 -> 0 | AC17: =H17+Q17+V17 -> 0 | AD17: =I17+R17+W17 -> 0 | AE17: =SUM(AA17:AD17) -> 0 | AF17: =Y17+AE17 -> 0 | AG17: =IF(AF17=0,0,AF17/$AF$23) -> 0
E18: =IF(D18=0,0,D18/$D$23) -> 0 | J18: =SUM(F18:I18) -> 0 | K18: =D18+F18-J18 -> 0 | L18: =IF(K18=0,0,K18/$K$23) -> 0 | S18: =SUM(O18:R18) -> 0 | X18: =SUM(T18:W18) -> 0 | Y18: =D18+M18+N18 -> 0 | Z18: =IF(Y18=0,0,Y18/$Y$23) -> 0 | AA18: =F18+O18+T18 -> 0 | AB18: =G18+P18+U18 -> 0 | AC18: =H18+Q18+V18 -> 0 | AD18: =I18+R18+W18 -> 0 | AE18: =SUM(AA18:AD18) -> 0 | AF18: =Y18+AE18 -> 0 | AG18: =IF(AF18=0,0,AF18/$AF$23) -> 0
E19: =IF(D19=0,0,D19/$D$23) -> 0 | J19: =SUM(F19:I19) -> 0 | K19: =D19+F19-J19 -> 0 | L19: =IF(K19=0,0,K19/$K$23) -> 0 | S19: =SUM(O19:R19) -> 0 | X19: =SUM(T19:W19) -> 0 | Y19: =D19+M19+N19 -> 0 | Z19: =IF(Y19=0,0,Y19/$Y$23) -> 0 | AA19: =F19+O19+T19 -> 0 | AB19: =G19+P19+U19 -> 0 | AC19: =H19+Q19+V19 -> 0 | AD19: =I19+R19+W19 -> 0 | AE19: =SUM(AA19:AD19) -> 0 | AF19: =Y19+AE19 -> 0 | AG19: =IF(AF19=0,0,AF19/$AF$23) -> 0
E20: =IF(D20=0,0,D20/$D$23) -> 0 | J20: =SUM(F20:I20) -> 0 | K20: =D20+F20-J20 -> 0 | L20: =IF(K20=0,0,K20/$K$23) -> 0 | S20: =SUM(O20:R20) -> 0 | X20: =SUM(T20:W20) -> 0 | Y20: =D20+M20+N20 -> 0 | Z20: =IF(Y20=0,0,Y20/$Y$23) -> 0 | AA20: =F20+O20+T20 -> 0 | AB20: =G20+P20+U20 -> 0 | AC20: =H20+Q20+V20 -> 0 | AD20: =I20+R20+W20 -> 0 | AE20: =SUM(AA20:AD20) -> 0 | AF20: =Y20+AE20 -> 0 | AG20: =IF(AF20=0,0,AF20/$AF$23) -> 0
E21: =IF(D21=0,0,D21/$D$23) -> 0 | J21: =SUM(F21:I21) -> 0 | K21: =D21+F21-J21 -> 0 | L21: =IF(K21=0,0,K21/$K$23) -> 0 | S21: =SUM(O21:R21) -> 0 | X21: =SUM(T21:W21) -> 0 | Y21: =D21+M21+N21 -> 0 | Z21: =IF(Y21=0,0,Y21/$Y$23) -> 0 | AA21: =F21+O21+T21 -> 0 | AB21: =G21+P21+U21 -> 0 | AC21: =H21+Q21+V21 -> 0 | AD21: =I21+R21+W21 -> 0 | AE21: =SUM(AA21:AD21) -> 0 | AF21: =Y21+AE21 -> 0 | AG21: =IF(AF21=0,0,AF21/$AF$23) -> 0
E22: =IF(D22=0,0,D22/$D$23) -> 0 | J22: =SUM(F22:I22) -> 0 | K22: =D22+F22-J22 -> 0 | L22: =IF(K22=0,0,K22/$K$23) -> 0 | S22: =SUM(O22:R22) -> 0 | X22: =SUM(T22:W22) -> 0 | Y22: =D22+M22+N22 -> 0 | Z22: =IF(Y22=0,0,Y22/$Y$23) -> 0 | AA22: =F22+O22+T22 -> 0 | AB22: =G22+P22+U22 -> 0 | AC22: =H22+Q22+V22 -> 0 | AD22: =I22+R22+W22 -> 0 | AE22: =SUM(AA22:AD22) -> 0 | AF22: =Y22+AE22 -> 0 | AG22: =IF(AF22=0,0,AF22/$AF$23) -> 0
A23: 合计 | D23: =SUM(D13:D22) -> 0 | E23: =SUM(E13:E22) -> 0 | F23: =SUM(F13:F22) -> 0 | G23: =SUM(G13:G22) -> 0 | H23: =SUM(H13:H22) -> 0 | I23: =SUM(I13:I22) -> 0 | J23: =SUM(J13:J22) -> 0 | K23: =SUM(K13:K22) -> 0 | ... AG23: =SUM(AG13:AG22) -> 0
A24: 三、审计说明：
A25: 1、章程中重要条款：
A27: 2、期间变更情况：
A29: 四、审计结论：
A31: 提示：
A32: 1.本科目核算企业接受投资者投入的实收资本。股份有限公司应将本科目改为“股本”科目。
A33: 2.企业收到投资者出资超过其在注册资本或股本中所占份额的部分，作为资本溢价或股本溢价，在“资本公积”科目核算。
A34: 3.对于股票发行检查的文件包括已发行股票的登记簿、募股清单、银行对账单、会计账面记录等，可向证券交易所和金融机构函证股票发行的数量。关注股票发行费用的会计处理是否正确。
A35: 4.以交付商品和劳务为对价的股票发行（如股份支付），完成股份支付底稿；
A36: 5.关注是否权益为负、经营性业务是否连续亏损或资不抵债的情况，考虑对持续经营的影响。
A37: 6.审计说明可以概述：（1）程序的测试情况、结果；（2）拟调整事项及其调整分录、未调整事项及其影响，审计范围受到限制情况及其影响。
A38: 7.审计结论可参考：A、未见异常。B、除上述重大不符事项应当作为调整事项予以调整外，其余未见异常。C、由于存在以下重大未调整事项(或审计范围受到限制无法获取充分、适当证据），不可确认。

Sheet 明细表（非上市公司）M2-2
A1: 致同会计师事务所
A2: 实收资本（或股本）明细表
A3: =底稿目录!A2 -> 被审计单位： | F3: =底稿目录!A4 -> 编制人： | O3: =底稿目录!A5 -> 编制日期： | W3: 索引号： | X3: =底稿目录!F9 -> M2-2
A4: =底稿目录!A3 -> 截止日：202X年12月31日 | F4: =底稿目录!A6 -> 复核人： | O4: =底稿目录!A7 -> 复核日期： | W4: 页次：
A5: 一、审计目标:
A6: 1.资产负债表中记录的实收资本（股本）是存在的，且已经记录在恰当的账户中；
A7: 2.所有应记录的实收资本（股本）均已记录，所有应当包括在财务报表中的相关披露均已包括；
A8: 3.实收资本（股本）以恰当的金额包括在财务报表中，与之相关的计价或分摊调整已恰当记录，相关披露已得到恰当计量和描述 ；
A9: 二、审计过程：
A10: 投资方名称 | B10: 未审数 | J10: 期初调整（本位币） | L10: 账项调整（本位币） | N10: 重分类调整（本位币） | P10: 审定数（本位币） | V10: 是否经过验资 | W10: 验资报告索引号 | X10: 备注
B11: 期初数 | E11: 本期增加 | G11: 本期减少 | H11: 期末数 | J11: 账项调整 | K11: 重分类调整 | L11: 本期增加 | M11: 本期减少 | N11: 本期增加 | O11: 本期减少 | P11: 期初数 | R11: 本期增加 | S11: 本期减少 | T11: 期末数
B12: 出资方式 | C12: 出资金额 | D12: 比例% | E12: 出资金额 | F12: 出资方式 | H12: 出资金额 | I12: 比例% | P12: 出资金额 | Q12: 比例% | T12: 出资金额 | U12: 比例%
D13: =IF(C13=0,0,C13/$C$23) -> 0 | H13: =C13+E13-G13 -> 0 | I13: =IF(H13=0,0,H13/$H$23) -> 0 | P13: =C13+J13+K13 -> 0 | Q13: =IF(P13=0,0,P13/$P$23) -> 0 | R13: =E13+L13+N13 -> 0 | S13: =G13+M13+O13 -> 0 | T13: =P13+R13-S13 -> 0 | U13: =IF(T13=0,0,T13/$T$23) -> 0
D14: =IF(C14=0,0,C14/$C$23) -> 0 | H14: =C14+E14-G14 -> 0 | I14: =IF(H14=0,0,H14/$H$23) -> 0 | P14: =C14+J14+K14 -> 0 | Q14: =IF(P14=0,0,P14/$P$23) -> 0 | R14: =E14+L14+N14 -> 0 | S14: =G14+M14+O14 -> 0 | T14: =P14+R14-S14 -> 0 | U14: =IF(T14=0,0,T14/$T$23) -> 0
D15: =IF(C15=0,0,C15/$C$23) -> 0 | H15: =C15+E15-G15 -> 0 | I15: =IF(H15=0,0,H15/$H$23) -> 0 | P15: =C15+J15+K15 -> 0 | Q15: =IF(P15=0,0,P15/$P$23) -> 0 | R15: =E15+L15+N15 -> 0 | S15: =G15+M15+O15 -> 0 | T15: =P15+R15-S15 -> 0 | U15: =IF(T15=0,0,T15/$T$23) -> 0
D16: =IF(C16=0,0,C16/$C$23) -> 0 | H16: =C16+E16-G16 -> 0 | I16: =IF(H16=0,0,H16/$H$23) -> 0 | P16: =C16+J16+K16 -> 0 | Q16: =IF(P16=0,0,P16/$P$23) -> 0 | R16: =E16+L16+N16 -> 0 | S16: =G16+M16+O16 -> 0 | T16: =P16+R16-S16 -> 0 | U16: =IF(T16=0,0,T16/$T$23) -> 0
D17: =IF(C17=0,0,C17/$C$23) -> 0 | H17: =C17+E17-G17 -> 0 | I17: =IF(H17=0,0,H17/$H$23) -> 0 | P17: =C17+J17+K17 -> 0 | Q17: =IF(P17=0,0,P17/$P$23) -> 0 | R17: =E17+L17+N17 -> 0 | S17: =G17+M17+O17 -> 0 | T17: =P17+R17-S17 -> 0 | U17: =IF(T17=0,0,T17/$T$23) -> 0
D18: =IF(C18=0,0,C18/$C$23) -> 0 | H18: =C18+E18-G18 -> 0 | I18: =IF(H18=0,0,H18/$H$23) -> 0 | P18: =C18+J18+K18 -> 0 | Q18: =IF(P18=0,0,P18/$P$23) -> 0 | R18: =E18+L18+N18 -> 0 | S18: =G18+M18+O18 -> 0 | T18: =P18+R18-S18 -> 0 | U18: =IF(T18=0,0,T18/$T$23) -> 0
D19: =IF(C19=0,0,C19/$C$23) -> 0 | H19: =C19+E19-G19 -> 0 | I19: =IF(H19=0,0,H19/$H$23) -> 0 | P19: =C19+J19+K19 -> 0 | Q19: =IF(P19=0,0,P19/$P$23) -> 0 | R19: =E19+L19+N19 -> 0 | S19: =G19+M19+O19 -> 0 | T19: =P19+R19-S19 -> 0 | U19: =IF(T19=0,0,T19/$T$23) -> 0
D20: =IF(C20=0,0,C20/$C$23) -> 0 | H20: =C20+E20-G20 -> 0 | I20: =IF(H20=0,0,H20/$H$23) -> 0 | P20: =C20+J20+K20 -> 0 | Q20: =IF(P20=0,0,P20/$P$23) -> 0 | R20: =E20+L20+N20 -> 0 | S20: =G20+M20+O20 -> 0 | T20: =P20+R20-S20 -> 0 | U20: =IF(T20=0,0,T20/$T$23) -> 0
D21: =IF(C21=0,0,C21/$C$23) -> 0 | H21: =C21+E21-G21 -> 0 | I21: =IF(H21=0,0,H21/$H$23) -> 0 | P21: =C21+J21+K21 -> 0 | Q21: =IF(P21=0,0,P21/$P$23) -> 0 | R21: =E21+L21+N21 -> 0 | S21: =G21+M21+O21 -> 0 | T21: =P21+R21-S21 -> 0 | U21: =IF(T21=0,0,T21/$T$23) -> 0
D22: =IF(C22=0,0,C22/$C$23) -> 0 | H22: =C22+E22-G22 -> 0 | I22: =IF(H22=0,0,H22/$H$23) -> 0 | P22: =C22+J22+K22 -> 0 | Q22: =IF(P22=0,0,P22/$P$23) -> 0 | R22: =E22+L22+N22 -> 0 | S22: =G22+M22+O22 -> 0 | T22: =P22+R22-S22 -> 0 | U22: =IF(T22=0,0,T22/$T$23) -> 0
A23: 合计 | C23: =SUM(C13:C22) -> 0 | D23: =SUM(D13:D22) -> 0 | E23: =SUM(E13:E22) -> 0 | G23: =SUM(G13:G22) -> 0 | H23: =SUM(H13:H22) -> 0 | I23: =SUM(I13:I22) -> 0 | J23: =SUM(J13:J22) -> 0 | K23: =SUM(K13:K22) -> 0 | L23: =SUM(L13:L22) -> 0 | M23: =SUM(M13:M22) -> 0 | N23: =SUM(N13:N22) -> 0 | O23: =SUM(O13:O22) -> 0 | P23: =C23+J23+K23 -> 0 | Q23: =SUM(Q13:Q22) -> 0 | R23: =E23+L23+N23 -> 0 | S23: =G23+M23+O23 -> 0 | T23: =P23+R23-S23 -> 0 | U23: =SUM(U13:U22) -> 0
A24: 三、审计说明：
A25: 1、章程中重要条款：
A27: 2、期间变更情况：
A29: 四、审计结论：
A31: 提示：
A32: 1.本科目核算企业接受投资者投入的实收资本。股份有限公司应将本科目改为“股本”科目。
A33: 2.企业收到投资者出资超过其在注册资本或股本中所占份额的部分，作为资本溢价或股本溢价，在“资本公积”科目核算。
A34: 3.以交付商品和劳务为对价的股票发行（如股份支付），完成股份支付底稿；
A35: 4.关注是否权益为负、经营性业务是否连续亏损或资不抵债的情况，考虑对持续经营的影响。
A36: 5.审计说明可以概述：（1）程序的测试情况、结果；（2）拟调整事项及其调整分录、未调整事项及其影响，审计范围受到限制情况及其影响。
A37: 6.审计结论可参考：A、未见异常。B、除上述重大不符事项应当作为调整事项予以调整外，其余未见异常。C、由于存在以下重大未调整事项(或审计范围受到限制无法获取充分、适当证据），不可确认。

Sheet 调整分录汇总M2-3
A1: 致同会计师事务所
A2: 实收资本调整分录汇总表
A3: =底稿目录!A2 -> 被审计单位： | D3: =底稿目录!A4 -> 编制人： | G3: =底稿目录!A5 -> 编制日期： | I3: 索引号： | J3: =底稿目录!F10 -> M2-3
A4: =底稿目录!A3 -> 截止日：202X年12月31日 | D4: =底稿目录!A6 -> 复核人： | G4: =底稿目录!A7 -> 复核日期： | I4: 页 次：
A5: 调整事项说明 | B5: 类别（报表调整/账项调整/其他） | C5: 报表项目 | D5: 科目名称 | E5: 附注项目 | F5: …… | G5: 借方调整金额 | H5: 贷方调整金额 | I5: 索引 | J5: 备注
A21: 【注：本底稿适用于调整分录较多、较复杂的项目，且仅列示与本报表项目相关的审计调整。项目组可根据项目实际情况选择是否使用该底稿。】

Sheet 外币投资汇率测算表M2-4
A1: 致同会计师事务所
A2: 外币投资汇率测算表
A3: =底稿目录!A2 -> 被审计单位： | C3: =底稿目录!A4 -> 编制人： | E3: =底稿目录!A5 -> 编制日期： | F3: 索引号： | G3: =底稿目录!F11 -> M2-4
A4: =底稿目录!A3 -> 截止日：202X年12月31日 | C4: =底稿目录!A6 -> 复核人： | E4: =底稿目录!A7 -> 复核日期： | F4: 页 次：
A5: 一、审计目标:
A6: 1.实收资本以恰当的金额包括在财务报表中，与之相关的计价或分摊调整已恰当记录，相关披露已得到恰当计量和描述。
A7: 二、审计过程：
A8: 投资者 | B8: 币种 | C8: 期末投资额
C9: 原币金额 | D9: 折算汇率 | E9: 折合人民币 | F9: 账面数 | G9: 差额
E10: =C10*D10 -> 0 | G10: =E10-F10 -> 0
E11: =C11*D11 -> 0 | G11: =E11-F11 -> 0
E12: =C12*D12 -> 0 | G12: =E12-F12 -> 0
E13: =C13*D13 -> 0 | G13: =E13-F13 -> 0
E14: =C14*D14 -> 0 | G14: =E14-F14 -> 0
E15: =C15*D15 -> 0 | G15: =E15-F15 -> 0
A16: 合计 | C16: =SUM(C10:C15) -> 0 | E16: =SUM(E10:E15) -> 0 | F16: =SUM(F10:F15) -> 0 | G16: =SUM(G10:G15) -> 0
A17: 三、审计说明：
A19: 四、审计结论：

Sheet 实收资本（股本）检查表M2-5
A1: 致同会计师事务所
A2: 实收资本（或股本）检查表
A3: =底稿目录!A2 -> 被审计单位： | E3: =底稿目录!A4 -> 编制人： | H3: =底稿目录!A5 -> 编制日期： | O3: 索引号： | P3: =底稿目录!F12 -> M2-5
A4: =底稿目录!A3 -> 截止日：202X年12月31日 | E4: =底稿目录!A6 -> 复核人： | H4: =底稿目录!A7 -> 复核日期： | O4: 页 次：
A5: 一、测试目标：
A6: 1.资产负债表中记录的实收资本是存在的； | E6: 2.记录的实收资本由被审计单位拥有或控制；
A7: 3.实收资本以恰当的金额包括在财务报表中，与之相关的计价或分摊调整已恰当记录，相关披露已得到恰当计量和描述。
A8: 二、测试：
A9: 测试内容说明：1.原始凭证是否齐全； 2.记账凭证与原始凭证是否相符；3.账务处理是否正确；4.是否记录于恰当的会计期间；5.……
A10: 记账凭证 | H10: 支持性文件 | I10: 核对内容 | N10: 索引号 | O10: 是否异常 | P10: 备注说明
A11: 日期 | B11: 凭证编号 | C11: 业务内容 | D11: 对方科目 | E11: 对方明细科目 | F11: 借方金额 | G11: 贷方金额 | I11: 1 | J11: 2 | K11: 3 | L11: 4 | M11: 5
A18: 合计 | F18: =SUM(F12:F17) -> 0 | G18: =SUM(G12:G17) -> 0
A19: 本期增加金额 | G19: ='明细表（上市公司）M2-2'!AA23 -> 0
A20: 检查比例 | G20: =G18/G19 -> #DIV/0!
A21: 三、审计说明：
A23: 四、审计结论：
A25: 提示：
A26: 审阅公司章程、股东（大）会、董事会会议记录中相关规定。收集与所有者权益账户变动有关的董股东（大）会决议、事会会议纪要、合同、协议、公司章程及营业执照，公司设立批文、验资报告以及政府主管部门、财政部门批复、资产评估报告等文件资料，并更新永久性档案。

Sheet GT_Custom
A1: C1 | B1: Custom 1
A2: C2 | B2: Custom 2
A3: C3 | B3: Custom 3
A4: C4 | B4: Custom 4
A5: C5 | B5: Custom 5
A6: C6 | B6: Custom 6
A7: C7 | B7: Custom 7
A8: C8 | B8: Custom 8
