Workbook

Sheet 底稿目录
A1: 底稿开列时，可先在以下单元格填写有关内容，以便其他底稿引用有关数据：
A2: 被审计单位：
A3: 截止日：202X年12月31日 | D3: 序号 | E3: 内容 | F3: 索引号 | G3: 备注
A4: 编制人： | D4: 1 | E4: 一般风险准备实质性程序表 | F4: M8A
A5: 编制日期： | D5: 2 | E5: 审定表 | F5: M8-1
A6: 复核人： | D6: 3 | E6: 附注披露信息(上市公司) | H6: 无需打印
A7: 复核日期： | D7: 3 | E7: 附注披露信息(国企) | H7: 无需打印
D8: 4 | E8: 明细表 | F8: M8-2
A9: 关于工作底稿与审计程序索引号对应的说明 | D9: 5 | E9: 调整分录汇总 | F9: M8-3
A10: 1.编制的审计工作底稿应与审计程序对应。审计项目组应根据被审计单位实际情况和风险评估情况在实质性程序表中裁剪、修改或增加审计程序，根据实际执行的审计程序完成相应审计工作底稿，编制的工作底稿中应按自然顺序依次编制索引号，并通过唯一的索引号将与实质性程序表中的程序对应关联（即将工作底稿的索引号填入实质性程序表中的底稿索引号列）。 | D10: 6 | E10: 一般风险准备测试表 | F10: M8-4
A14: 2.获取的支持性证据应与审计底稿或程序对应。审计项目组在完成底稿时获取的支持性证据应根据底稿索引号编制下一级按自然顺序排序的索引号（如D1-2-1、D1-2-2、……），并在底稿中说明引用的支持性证据、关联索引号。
A17: 3.工作底稿索引号的编码规则：实质性程序索引号按循环从“D”到“N”,循环内账户以顺序号排列，模板中底稿索引号按账户顺序+自然数顺序（即模板中索引号按二级自然顺序排列，如D1-1、D1-2、D1-3、……D1-N）。

Sheet 一般风险准备实质性程序表 M8A 
A1: 致同会计师事务所
A2: 一般风险准备实质性程序
A3: =底稿目录!A2 -> 被审计单位： | C3: =底稿目录!A4 -> 编制人： | E3: =底稿目录!A5 -> 编制日期： | H3: 索引号： | I3: =底稿目录!F4 -> M8A
A4: =底稿目录!A3 -> 截止日：202X年12月31日 | C4: =底稿目录!A6 -> 复核人： | E4: =底稿目录!A7 -> 复核日期： | H4: 页 次：
A5: 一、本账户涉及的科目
A6: 一般风险准备
A7: 二、审计目标与认定的对应关系
A8: 审计目标 | G8: 财务报表的认定
A9: A. 资产负债表中记录的一般风险准备是存在的，且已经记录在恰当的账户中 | G9: 存在
A10: B. 所有应记录的一般风险准备均已记录，所有应当包括在财务报表中的相关披露均已包括 | G10: 完整性
A11: C. 记录的一般风险准备由被审计单位拥有或控制 | G11: 权利和义务
A12: D. 一般风险准备以恰当的金额包括在财务报表中，与之相关的计价或分摊调整已恰当记录，相关披露已得到恰当计量和描述 | G12: 准确性、计价和分摊
A13: E. 一般风险准备已被恰当地汇总或分解且表述清楚，相关披露在按照企业会计准则的编制基础下是相关的、可理解的 | G13: 列报
A14: 三、计划实施的实质性程序
A15: 序号 | B15: 审计程序 | C15: 程序分类 | D15: 财务报表的认定 | I15: 底稿索引号
D16: 存在 | E16: 完整性 | F16: 权利和义务 | G16: 准确性、计价和分摊 | H16: 列报 | J16: 根据被审计单位实际情况和风险评估情况裁剪、修改或增加审计程序
A17: 1 | B17: 获取或编制专项储备明细表，完成以下工作，并编制审定表 复核加计是否正确，与总账、明细账合计数核对是否相符，期初余额与上期审定期末余额是否相符； | C17: 常规★ | D17: √ | E17: √ | G17: √ | I17: M8-1 /M8-2
A18: 2 | B18: 在使用手工编制、自定义信息报告、系统生成的非固定格式报告等由被审计单位生成的信息时，测试有关信息准确性和完整性，并考虑针对编制和维护由被审计单位生成的信息的相关控制实施控制测试，以评价该信息是否能够为实现审计目的提供基础。 | C18: 常规★ | E18: √ | G18: √ | I18: T1/ | J18: 可参见《审计手册》4.2.6，由被审计单位生成的信息可能是由系统生成的、或手工编制的、或二者兼而有之的方式生成的。例如，由被审计单位生成的信息可能包括： • 不涉及自定义的、由系统生成的报告（如，固定格式报告）； • 可能通过人工自定义的、由系统生成的报告，例如，（计算机）查询信息或特别定制的报告； • 手工编制的信息，例如，汇总信息的电子表格或用以支持分配、计算以及调节的电子表格； • 其他系统生成或手工编制的信息，例如，由被审计单位编制的客户发票； • 通过影印、拍摄、扫描或其他方式转换成电子形式的文件记录。
A19: 3 | B19: 对于上期一般风险储备末余额，取得一般风险储备明细表复核加计是否正确，与总账、明细账合计数是否相符，检查被审计单位一般风险储备计提政策等文件。（适用于首次承接） | C19: 备选 | D19: √ | E19: √ | F19: √ | G19: √ | J19: 由被审计单位生成的信息不包括： • 总分类账或明细分类账、试算平衡表、或经审计的财务报表； • 第三方（除了服务机构）的报表或报告，例如，原始银行对账单，或函证的回函； • 外部数据（例如，第三方发布的数据，如，定价来源）。
A20: 4 | B20: 获取一般风险储备的计提及标准的相关文件，检查是否已按照相关行业规定计提一般风险储备，判断其分类为是否恰当、计提金额是否正确、会计处理是否正确。 | C20: 常规★ | D20: √ | E20: √ | F20: √ | G20: √ | H20: √ | I20: M8-4
A21: 5 | B21: 检查一般风险准备是否已按企业会计准则或其他适用的规定在财务报表中做出恰当列报和披露。 | C21: 常规★ | H21: √ | I21: A1-1/A1-15 /A1-16

Sheet 一般风险准备实质性程序表 Q8A  (修订前)
A1: 致同会计师事务所
A2: 一般风险准备实质性程序
A3: =底稿目录!A2 -> 被审计单位： | C3: =底稿目录!A4 -> 编制人： | F3: =底稿目录!A5 -> 编制日期： | I3: 索引号： | J3: QA
A4: =底稿目录!A3 -> 截止日：202X年12月31日 | C4: =底稿目录!A6 -> 复核人： | F4: =底稿目录!A7 -> 复核日期： | I4: 页 次：
A5: 一、本账户涉及的科目
A6: 一般风险准备
A7: 二、重大错报风险需从实质性程序获取的保证程度
A8: 审计目标与认定对应关系 | C8: 财务报表的认定 | H8: 信赖/不信赖/不适用 | I8: 索引号
C9: 存在 | D9: 完整性 | E9: 权利和义务 | F9: 计价和分摊 | G9: 列报与披露
A10: A. 资产负债表中记录的一般风险准备是存在的。 | C10: √
A11: B. 所有应记录的一般风险准备均已记录，一般风险准备的增减变动符合法律、法规和合同、章程的规定。 | D11: √
A12: C. 一般风险准备以恰当的金额包括在财务报表中。 | F12: √
A13: D. 一般风险准备已按照企业会计准则的规定在财务报表中作出恰当列报和披露。 | G13: √
A15: 三、计划实施的实质性程序
A16: 序号 | B16: 审计程序 | D16: 程序分类 | E16: 对应的认定/风险 | I16: 执行情况说明 （含底稿索引）
A17: （一） | B17: 编制审定表 | D17: 常规★ | E17: B | I17: Q8 | K17: 整合 | L17: 获取或编制专项储备明细表，完成以下工作，并编制审定表 复核加计是否正确，与总账、明细账合计数核对是否相符，期初余额与上期审定期末余额是否相符；
A18: （二） | B18: 获取或编制一般风险准备明细表，并完成以下工作： | D18: 常规★ | E18: C | I18: Q8-1 | K18: 整合
A19: 1 | B19: 复核加计正确 。 | D19: 常规★ | E19: C | K19: 整合
A20: 2 | B20: 将总金额与总账核对。 | D20: 常规★ | E20: C | K20: 整合
A21: 3 | B21: 确定计算的准确性。 | D21: 常规 | E21: C | K21: 整合
A22: 4 | B22: 将期初额与上年度工作底稿或前期财务报表核对。 | D22: 常规 | E22: C | K22: 整合
A23: 5 | B23: 将期末余额与总分类账核对一致。 | D23: 常规 | E23: C | K23: 整合
A24: 6 | B24: 以非记账本位币出资的，检查其折算汇率是否符合规定，折算差额的会计处理是否正确。 | D24: 常规★ | E24: C | K24: 整合
A25: （三） | B25: 在使用被审计单位生成的信息（IPE）时，应当评价该信息对实现审计目的是否足够可靠，包括根据具体情况在必要时实施下列程序： | D25: 常规★ | E25: B | I25: T1 | K25: 保留 | L25: 在使用手工编制、自定义信息报告、系统生成的非固定格式报告等由被审计单位生成的信息时，测试有关信息准确性和完整性，并考虑针对编制和维护由被审计单位生成的信息的相关控制实施控制测试，以评价该信息是否能够为实现审计目的提供基础。
A26: 1 | B26: 获取有关信息准确性和完整性的审计证据。 | K26: 保留
A27: 2 | B27: 评价信息对实现审计目的是否足够准确和详细。 | K27: 保留
A28: （四） | B28: 对于上期一般风险准备账户的期末余额（适用于首次承接时对期初余额的审计）： | D28: 备选 | E28: AB | I28: Q8-1 | K28: 保留 | L28: 对于上期一般风险储备末余额，取得一般风险储备明细表复核加计是否正确，与总账、明细账合计数是否相符，检查被审计单位一般风险储备计提政策等文件。（适用于首次承接）
A29: 1 | B29: 取得企业成立时的文件、合伙协议等并摘录相关章节。 | D29: 备选 | E29: AB | K29: 保留
A30: 2 | B30: 向证券结算中介机构并与股票登记簿核对，或向每位合伙人函证以确认股本账户期初金额。 | D30: 备选 | E30: AB | K30: 保留
A31: （五） | B31: 获取董事会/股东会会议记录，执行下列审计程序。 | D31: 常规 | E31: AB | I31: Q8-2 | K31: 删除
A32: 1 | B32: 确定会议纪要是否包含权益交易。包括：现金股利、股票股利、股票分割；权益回购；已出售的权益性工具。 | D32: 常规 | E32: AB | K32: 删除
A33: 2 | B33: 对于识别出的交易，确认交易是否经过授权并且得到适当会计处理。 | D33: 常规 | E33: AB | K33: 删除
A34: （六） | B34: 取得一般风险准备账户当期交易活动的明细表，检查增减变动的原因，对每一项增加或减少，关注有关交易的性质，检查法律性文件是否齐全，相关的手续是否办理，以及其会计处理是否正确： | D34: 常规★ | E34: AB | I34: Q8-2 | K34: 修改 | L34: 获取一般风险储备的计提及标准的相关文件，检查是否已按照相关行业规定计提一般风险储备，判断其分类为是否恰当、计提金额是否正确、会计处理是否正确。
A35: 1 | B35: 对于每一增减变动，确定交易的是否恰当，会计处理是否正确。 | D35: 常规★ | E35: AB | K35: 修改
A36: 2 | B36: 通过查阅上述会议记录，确定每笔交易是否都已通过授权。 | D36: 常规 | E36: AB | K36: 修改
A37: 3 | B37: 审阅公司章程、股东（大）会、董事会会议记录中相关规定。收集与所有者权益账户变动有关的董股东（大）会决议、事会会议纪要、合同、协议、公司章程及营业执照，公司设立批文、验资报告以及政府主管部门、财政部门批复、资产评估报告等文件资料，并更新永久性档案。 | D37: 常规★ | E37: AB | K37: 修改
A38: 4 | B38: 获取所有者权益账户结转明细，并确认入账是否恰当。 | D38: 常规 | E38: AB | K38: 修改
A39: （七） | B39: 确定需在财务报表中单独披露的信息已被记录。 | D39: 常规★ | E39: E | K39: 保留

Sheet 审定表M8-1
A1: 致同会计师事务所
A2: 一般风险准备审定表
A3: =底稿目录!A2 -> 被审计单位： | D3: =底稿目录!A4 -> 编制人： | G3: =底稿目录!A5 -> 编制日期： | K3: 索引号： | L3: =底稿目录!F5 -> M8-1
A4: =底稿目录!A3 -> 截止日：202X年12月31日 | D4: =底稿目录!A6 -> 复核人： | G4: =底稿目录!A7 -> 复核日期： | K4: 页 次：
A5: 项目名称 | B5: 期初数 | F5: 期末数 | J5: 本期审定数与上期 审定数的比较 | L5: 原因分析
B6: 未审数 | C6: 账项调整 | D6: 重分类调整 | E6: 审定数 | F6: 未审数 | G6: 账项调整 | H6: 重分类调整 | I6: 审定数 | J6: 变动额 | K6: 变动率
A7: ='明细表M8-2'!A10 -> 一般风险准备 | B7: ='明细表M8-2'!B10 -> 0 | C7: ='明细表M8-2'!F10 -> 0 | D7: ='明细表M8-2'!G10 -> 0 | E7: ='明细表M8-2'!L10 -> 0 | F7: ='明细表M8-2'!E10 -> 0 | G7: ='明细表M8-2'!F10+'明细表M8-2'!H10-'明细表M8-2'!I10 -> 0 | H7: ='明细表M8-2'!G10+'明细表M8-2'!J10-'明细表M8-2'!K10 -> 0 | I7: ='明细表M8-2'!O10 -> 0 | J7: =I7-E7 -> 0 | K7: =IF(AND(E7=0,J7=0),0,IF(AND(E7=0,J7>0),1,J7/E7)) -> 0
A8: ='明细表M8-2'!A11 -> 0 | B8: ='明细表M8-2'!B11 -> 0 | C8: ='明细表M8-2'!F11 -> 0 | D8: ='明细表M8-2'!G11 -> 0 | E8: ='明细表M8-2'!L11 -> 0 | F8: ='明细表M8-2'!E11 -> 0 | G8: ='明细表M8-2'!F11+'明细表M8-2'!H11-'明细表M8-2'!I11 -> 0 | H8: ='明细表M8-2'!G11+'明细表M8-2'!J11-'明细表M8-2'!K11 -> 0 | I8: ='明细表M8-2'!O11 -> 0 | J8: =I8-E8 -> 0 | K8: =IF(AND(E8=0,J8=0),0,IF(AND(E8=0,J8>0),1,J8/E8)) -> 0
A9: ='明细表M8-2'!A12 -> 0 | B9: ='明细表M8-2'!B12 -> 0 | C9: ='明细表M8-2'!F12 -> 0 | D9: ='明细表M8-2'!G12 -> 0 | E9: ='明细表M8-2'!L12 -> 0 | F9: ='明细表M8-2'!E12 -> 0 | G9: ='明细表M8-2'!F12+'明细表M8-2'!H12-'明细表M8-2'!I12 -> 0 | H9: ='明细表M8-2'!G12+'明细表M8-2'!J12-'明细表M8-2'!K12 -> 0 | I9: ='明细表M8-2'!O12 -> 0 | J9: =I9-E9 -> 0 | K9: =IF(AND(E9=0,J9=0),0,IF(AND(E9=0,J9>0),1,J9/E9)) -> 0
A10: ='明细表M8-2'!A13 -> 0 | B10: ='明细表M8-2'!B13 -> 0 | C10: ='明细表M8-2'!F13 -> 0 | D10: ='明细表M8-2'!G13 -> 0 | E10: ='明细表M8-2'!L13 -> 0 | F10: ='明细表M8-2'!E13 -> 0 | G10: ='明细表M8-2'!F13+'明细表M8-2'!H13-'明细表M8-2'!I13 -> 0 | H10: ='明细表M8-2'!G13+'明细表M8-2'!J13-'明细表M8-2'!K13 -> 0 | I10: ='明细表M8-2'!O13 -> 0 | J10: =I10-E10 -> 0 | K10: =IF(AND(E10=0,J10=0),0,IF(AND(E10=0,J10>0),1,J10/E10)) -> 0
A11: ='明细表M8-2'!A14 -> 0 | B11: ='明细表M8-2'!B14 -> 0 | C11: ='明细表M8-2'!F14 -> 0 | D11: ='明细表M8-2'!G14 -> 0 | E11: ='明细表M8-2'!L14 -> 0 | F11: ='明细表M8-2'!E14 -> 0 | G11: ='明细表M8-2'!F14+'明细表M8-2'!H14-'明细表M8-2'!I14 -> 0 | H11: ='明细表M8-2'!G14+'明细表M8-2'!J14-'明细表M8-2'!K14 -> 0 | I11: ='明细表M8-2'!O14 -> 0 | J11: =I11-E11 -> 0 | K11: =IF(AND(E11=0,J11=0),0,IF(AND(E11=0,J11>0),1,J11/E11)) -> 0
B12: ='明细表M8-2'!B15 -> 0 | C12: ='明细表M8-2'!F15 -> 0 | D12: ='明细表M8-2'!G15 -> 0 | E12: ='明细表M8-2'!L15 -> 0 | F12: ='明细表M8-2'!E15 -> 0 | G12: ='明细表M8-2'!F15+'明细表M8-2'!H15-'明细表M8-2'!I15 -> 0 | H12: ='明细表M8-2'!G15+'明细表M8-2'!J15-'明细表M8-2'!K15 -> 0 | I12: ='明细表M8-2'!O15 -> 0 | J12: =I12-E12 -> 0 | K12: =IF(AND(E12=0,J12=0),0,IF(AND(E12=0,J12>0),1,J12/E12)) -> 0
A13: 合计 | B13: =SUM(B7:B12) -> 0 | C13: =SUM(C7:C12) -> 0 | D13: =SUM(D7:D12) -> 0 | E13: =SUM(E7:E12) -> 0 | F13: =SUM(F7:F12) -> 0 | G13: =SUM(G7:G12) -> 0 | H13: =SUM(H7:H12) -> 0 | I13: =SUM(I7:I12) -> 0 | J13: =I13-E13 -> 0 | K13: =IF(AND(E13=0,J13=0),0,IF(AND(E13=0,J13>0),1,J13/E13)) -> 0
A14: 试算平衡表数
A15: 差异数 | E15: =E13-E14 -> 0 | I15: =I13-I14 -> 0
A16: 1、审计说明
A17: （1）期末余额较期初余额增加（负数为减少）：
A18: 主要原因（比例超过30%的）：
A21: （2）一般风险准备变动的原因、依据。
A24: 2、审计结论

Sheet 附注披露信息（上市公司）
A1: 致同会计师事务所
A2: 一般风险准备附注披露信息（上市公司）
A3: =底稿目录!A2 -> 被审计单位： | C3: =底稿目录!A4 -> 编制人： | E3: =底稿目录!A5 -> 编制日期： | G3: 索引号：
A4: =底稿目录!A3 -> 截止日：202X年12月31日 | C4: =底稿目录!A6 -> 复核人： | E4: =底稿目录!A7 -> 复核日期： | G4: 页次：
A5: 一般风险准备
A6: 项目 | B6: 期初余额 | C6: 本期增加 | D6: 本期减少 | E6: 期末余额
B7: ='明细表M8-2'!L10 -> 0 | C7: ='明细表M8-2'!M10 -> 0 | D7: ='明细表M8-2'!N10 -> 0 | E7: =B7+C7-D7 -> 0
E8: =B8+C8-D8 -> 0
E9: =B9+C9-D9 -> 0
A10: 合计 | B10: =SUM(B7:B9) -> 0 | C10: =SUM(C7:C9) -> 0 | D10: =SUM(D7:D9) -> 0 | E10: =SUM(E7:E9) -> 0
A11: 说明：

Sheet 附注披露信息（国有企业）
A1: 致同会计师事务所
A2: 一般风险准备附注披露信息（国有企业）
A3: =底稿目录!A2 -> 被审计单位： | C3: =底稿目录!A4 -> 编制人： | E3: =底稿目录!A5 -> 编制日期： | G3: 索引号：
A4: =底稿目录!A3 -> 截止日：202X年12月31日 | C4: =底稿目录!A6 -> 复核人： | E4: =底稿目录!A7 -> 复核日期： | G4: 页次：
A5: 一般风险准备
A6: 项目 | B6: 期初余额 | C6: 本期增加 | D6: 本期减少 | E6: 期末余额
B7: ='明细表M8-2'!L10 -> 0 | C7: ='明细表M8-2'!M10 -> 0 | D7: ='明细表M8-2'!N10 -> 0 | E7: =B7+C7-D7 -> 0
E8: =B8+C8-D8 -> 0
E9: =B9+C9-D9 -> 0
A10: 合计 | B10: =SUM(B7:B9) -> 0 | C10: =SUM(C7:C9) -> 0 | D10: =SUM(D7:D9) -> 0 | E10: =SUM(E7:E9) -> 0
A11: 说明：

Sheet 明细表M8-2
A1: 致同会计师事务所
A2: 一般风险准备明细表
A3: =底稿目录!A2 -> 被审计单位： | E3: =底稿目录!A4 -> 编制人： | K3: =底稿目录!A5 -> 编制日期： | Q3: 索引号： | R3: =底稿目录!F8 -> M8-2
A4: =底稿目录!A3 -> 截止日：202X年12月31日 | E4: =底稿目录!A6 -> 复核人： | K4: =底稿目录!A7 -> 复核日期： | Q4: 页 次：
A5: 一、审计目标:
A6: 1.一般风险准备以恰当的金额包括在财务报表中，与之相关的计价或分摊调整已恰当记录，相关披露已得到恰当计量和描述。
A7: 二、审计过程：
A8: 项目 | B8: 未审数 | F8: 期初调整 | H8: 账项调整 | J8: 重分类调整 | L8: 审定数 | P8: 文件依据
B9: 期初数 | C9: 本期增加 | D9: 本期减少 | E9: 期末数 | F9: 账项调整 | G9: 重分类调整 | H9: 本期增加 | I9: 本期减少 | J9: 本期增加 | K9: 本期减少 | L9: 期初数 | M9: 本期增加 | N9: 本期减少 | O9: 期末数 | Q9: 索引号 | R9: 备注
A10: 一般风险准备 | E10: =B10+C10-D10 -> 0 | L10: =B10+F10+G10 -> 0 | M10: =C10+H10+J10 -> 0 | N10: =D10+I10+K10 -> 0 | O10: =L10+M10-N10 -> 0
E11: =B11+C11-D11 -> 0 | L11: =B11+F11+G11 -> 0 | M11: =C11+H11+J11 -> 0 | N11: =D11+I11+K11 -> 0 | O11: =L11+M11-N11 -> 0
E12: =B12+C12-D12 -> 0 | L12: =B12+F12+G12 -> 0 | M12: =C12+H12+J12 -> 0 | N12: =D12+I12+K12 -> 0 | O12: =L12+M12-N12 -> 0
E13: =B13+C13-D13 -> 0 | L13: =B13+F13+G13 -> 0 | M13: =C13+H13+J13 -> 0 | N13: =D13+I13+K13 -> 0 | O13: =L13+M13-N13 -> 0
E14: =B14+C14-D14 -> 0 | L14: =B14+F14+G14 -> 0 | M14: =C14+H14+J14 -> 0 | N14: =D14+I14+K14 -> 0 | O14: =L14+M14-N14 -> 0
E15: =B15+C15-D15 -> 0 | L15: =B15+F15+G15 -> 0 | M15: =C15+H15+J15 -> 0 | N15: =D15+I15+K15 -> 0 | O15: =L15+M15-N15 -> 0
E16: =B16+C16-D16 -> 0 | L16: =B16+F16+G16 -> 0 | M16: =C16+H16+J16 -> 0 | N16: =D16+I16+K16 -> 0 | O16: =L16+M16-N16 -> 0
A17: 合计 | B17: =SUM(B10:B16) -> 0 | C17: =SUM(C10:C16) -> 0 | D17: =SUM(D10:D16) -> 0 | E17: =SUM(E10:E16) -> 0 | F17: =SUM(F10:F16) -> 0 | G17: =SUM(G10:G16) -> 0 | H17: =SUM(H10:H16) -> 0 | I17: =SUM(I10:I16) -> 0 | ... O17: =SUM(O10:O16) -> 0
A18: 三、审计说明：
A20: 四、审计结论：
A23: 1、审计说明可以概述：（1）程序的测试情况、结果；（2）拟调整事项及其调整分录、未调整事项及其影响，审计范围受到限制情况及其影响。
A24: 2、审计结论可参考：A、未见异常。B、除上述重大不符事项应当作为调整事项予以调整外，其余未见异常。C、由于存在以下重大未调整事项(或审计范围受到限制无法获取充分、适当证据），不可确认。

Sheet 调整分录汇总M8-3
A1: 致同会计师事务所
A2: 一般风险准备调整分录汇总表
A3: =底稿目录!A2 -> 被审计单位： | D3: =底稿目录!A4 -> 编制人： | F3: =底稿目录!A5 -> 编制日期： | I3: 索引号： | J3: =底稿目录!F9 -> M8-3
A4: =底稿目录!A3 -> 截止日：202X年12月31日 | D4: =底稿目录!A6 -> 复核人： | F4: =底稿目录!A7 -> 复核日期： | I4: 页 次：
A5: 调整事项说明 | B5: 类别（报表调整/账项调整/其他） | C5: 报表项目 | D5: 科目名称 | E5: 附注项目 | F5: …… | G5: 借方调整金额 | H5: 贷方调整金额 | I5: 索引 | J5: 备注

Sheet 一般风险准备测试表M8-4
A1: 致同会计师事务所
A2: 一般风险准备测试表
A3: =底稿目录!A2 -> 被审计单位： | D3: =底稿目录!A4 -> 编制人： | G3: =底稿目录!A5 -> 编制日期： | J3: 索引号： | K3: =底稿目录!F10 -> M8-4
A4: =底稿目录!A3 -> 截止日：202X年12月31日 | D4: =底稿目录!A6 -> 复核人： | G4: =底稿目录!A7 -> 复核日期： | J4: 页 次：
A5: 一、审计目标：
A6: 1.一般风险准备以恰当的金额包括在财务报表中，与之相关的计价或分摊调整已恰当记录，相关披露已得到恰当计量和描述。
A7: 二、审计过程：
A8: 项目 | B8: 本期增加额 | D8: 提取 | G8: 应计金额 | H8: 差异 | I8: 差异原因 | J8: 相关依据索引号 | K8: 相关数据来源索引号
B9: 计提 | C9: 其它 | D9: 标准 | E9: 基数 | F9: 比例（注）
A10: 一般风险准备 | G10: =E10*F10 -> 0 | H10: =B10-G10 -> 0
G11: =E11*F11 -> 0 | H11: =B11-G11 -> 0
G12: =E12*F12 -> 0 | H12: =B12-G12 -> 0
G13: =E13*F13 -> 0 | H13: =B13-G13 -> 0
G14: =E14*F14 -> 0 | H14: =B14-G14 -> 0
G15: =E15*F15 -> 0 | H15: =B15-G15 -> 0
G16: =E16*F16 -> 0 | H16: =B16-G16 -> 0
G17: =E17*F17 -> 0 | H17: =B17-G17 -> 0
G18: =E18*F18 -> 0 | H18: =B18-G18 -> 0
A19: 合 计 | B19: =SUM(B10:B18) -> 0 | C19: =SUM(C10:C18) -> 0 | G19: =SUM(G10:G18) -> 0 | H19: =SUM(H10:H18) -> 0
A20: 三、审计说明：
A25: 四、审计结论：

Sheet 针对性测试M8-5-删除
A1: 致同会计师事务所
A2: 针对性测试
A3: =底稿目录!A2 -> 被审计单位： | E3: =底稿目录!A4 -> 编制人： | H3: =底稿目录!A5 -> 编制日期： | L3: 索引号：M8-5
A4: =底稿目录!A3 -> 截止日：202X年12月31日 | E4: =底稿目录!A6 -> 复核人： | H4: =底稿目录!A7 -> 复核日期： | L4: 页次：
A5: 一、测试目标：
A6: 1.通过选取一般风险准备的样本进行测试检查，验证一般风险准备项目的存在/发生、计价和分摊。
A7: 二、样本选取标准与规模：
A8: 测试总体： | B8: 如盈余公积借方发生额所有凭证共XX笔金额XX、贷方发生额所有凭证共XX笔金额XX | G8: 特定样本： | H8: XX金额以上（大额）、关联方/关联交易形成的款项、XX异常款项全部测试，共XX笔；
A9: 抽样总体： | B9: 测试总体扣除特定样本以外的样本，共XX笔、金额XX | G9: 确定的抽样样本量： | H9: 抽取XX笔 | I9: （如果使用了样本计算器计算样本量，样本量计算过程见<XX>底稿）
A10: 抽样方法： | B10: 随机选样/系统选样/货币单元抽样/随意选样 | G10: 抽样过程： | H10: 使用IDEA（XX抽样工具）选择XX数量、金额XX的样本进行测试，抽样工具中的样本选择过程和结果见<XX>底稿
A11: 三、测试：
A12: 测试内容说明：1.原始凭证是否齐全； 2.记账凭证与原始凭证是否相符；3.账务处理是否正确；4.是否记录于恰当的会计期间；5.……
A13: 记账凭证 | G13: 董事会/股东会会议纪要 | J13: …… | K13: 索引号 | L13: 备注说明
A14: 日期 | B14: 凭证编号 | C14: 业务内容 | D14: 对方科目 | E14: 明细科目 | F14: 借/贷方金额 | G14: 日期 | H14: 会议编号 | I14: 一般风险准备计提方案
A25: 【注：“备注说明”栏主要填写有必要做出进一步说明，且其他字段和审计证据中未记录的内容；由项目组根据需要选择是否需要填写。】
A26: 四、审计说明：
A31: 五、审计结论：

Sheet GT_Custom
A1: C1 | B1: Custom 1
A2: C2 | B2: Custom 2
A3: C3 | B3: Custom 3
A4: C4 | B4: Custom 4
A5: C5 | B5: Custom 5
A6: C6 | B6: Custom 6
A7: C7 | B7: Custom 7
A8: C8 | B8: Custom 8
