Workbook

Sheet 目录
A1: 底稿开列时，可先在以下单元格填写有关内容，以便其他底稿引用有关数据：
A2: 被审计单位：ABC有限公司
A3: 会计期间：202X年度 | C3: 序号 | D3: 内容 | E3: 索引号
A4: 编制人：张XX | C4: 1 | D4: 与管理层访谈程序 | E4: B12A
A5: 编制日期：2025-4-2 | C5: =C4+1 -> 2 | D5: 与管理层访谈记录 | E5: B12A-1
A6: 复核人：李XX | C6: =C5+1 -> 3 | D6: 与治理层访谈程序 | E6: B12B
A7: 复核日期：2025-4-20 | C7: =C6+1 -> 4 | D7: 与治理层访谈记录 | E7: B12B-1
C8: =C7+1 -> 5 | D8: 与其他人员访谈程序 | E8: B12C
C9: =C8+1 -> 6 | D9: 与其他人员访谈记录 | E9: B12C-1

Sheet B12A 与管理层访谈程序
A1: 致同会计师事务所
A2: 与管理层访谈程序表
A3: =目录!A2 -> 被审计单位：ABC有限公司 | D3: =目录!A4 -> 编制人：张XX | E3: =目录!A5 -> 编制日期：2025-4-2 | G3: 索引号： | H3: B12A
A4: =目录!A3 -> 会计期间：202X年度 | D4: =目录!A6 -> 复核人：李XX | E4: =目录!A7 -> 复核日期：2025-4-20 | G4: 页 次：
A5: 序号 | B5: 程序 | E5: 是否适用 | F5: 执行人 | G5: 执行情况说明 | H5: 索引号
A6: 一 | B6: 询问客户管理层并记录他们的反馈： | H6: B12A-1
A7: 1 | B7: 获取管理层针对初步分析程序发现的重大或异常变动的解释，并考虑其是否表明存在潜在的错误或舞弊。
A8: 2 | B8: 在当期发生的，可能影响审计策略或企业财务报表的问题和事项。
A9: 3 | B9: 所采用的会计政策的适当性，以及有关经营活动的变化是否需要更新相关会计政策。
A10: 4 | B10: 管理层对可能影响财务报告的新法律法规、会计准则和监管要求的认识。
A11: 5 | B11: 管理层对企业控制环境的看法，包括复核内控系统有效性的流程和所有复核结果。
A12: 6 | B12: 管理层对与财务报告相关的企业风险评估流程的看法。
A13: 7 | B13: 管理层对舞弊风险的看法，包括：
A14: （1） | B14: 识别和应对舞弊风险的流程，包括相关控制及对这些控制的监督 。
A15: （2） | B15: 上述流程的结果。
A16: （3） | B16: 识别出的与舞弊风险相关的账户、交易类别或披露 。
A17: （4） | B17: 可能存在与舞弊风险相关的账户、交易类别或披露 。
A18: 8 | B18: 关注举报或投诉以及管理层的回应。
... A38: （3） | B38: 未更正的错报
A39: 二 | B39: 了解管理层内部控制评价流程，并考虑： （适用于内部控制审计） | H39: B12A-1
A40: 1 | B40: 评价方法（如人员、时间、工作性质）
A41: 2 | B41: 重大缺陷的认定方法
A42: 3 | B42: 评价的结果和状态
A43: 三 | B43: 询问管理层企业层面控制中关于监督控制的有效性： （适用于内部控制审计） | H43: B12A-1
A44: 1 | B44: 审计委员会
A45: 2 | B45: 内部审计职能
A46: 3 | B46: 自我评价
A47: 四 | B47: 汇总识别出的风险因素。 | H47: B50-1
A126: 是
A127: 否

Sheet B12A-1与管理层访谈记录
A1: 致同会计师事务所
A2: 与管理层访谈记录
A3: =目录!A2 -> 被审计单位：ABC有限公司 | C3: =目录!A4 -> 编制人：张XX | E3: =目录!A5 -> 编制日期：2025-4-2 | F3: 索引号：B12A-1
A4: =目录!A3 -> 会计期间：202X年度 | C4: =目录!A6 -> 复核人：李XX | E4: =目录!A7 -> 复核日期：2025-4-20 | F4: 页 次：
A5: 一、 | B5: 询问管理层
A6: 管理层姓名 | C6: 职务 | E6: 询问人 | F6: 询问日期
A13: 询问内容 | E13: 询问结果
A14: （一）舞弊事项
A15: 管理层对财务报表可能存在由于舞弊导致的重大错报风险是否进行了评估？如果进行了评估，请管理层介绍评估的性质、范围和频率等。
A16: 管理层是如何识别舞弊风险的？管理层是否识别出或注意到特定舞弊风险？管理层是否识别出或注意到可能存在舞弊风险的各类交易、账户余额或披露？
A17: 管理层如何应对识别出的风险？
A18: 管理层是否就就其对舞弊风险的识别和应对过程向治理层的通报？
A19: 管理层是否知悉任何影响被审计单位的舞弊事实、舞弊嫌疑或舞弊指控？
A20: ……
A21: （二）持续经营
A22: ……
A24: ……

Sheet B12B 与治理层访谈程序
A1: 致同会计师事务所
A2: 与治理层的讨论程序表
A3: =目录!A2 -> 被审计单位：ABC有限公司 | D3: =目录!A4 -> 编制人：张XX | G3: =目录!A5 -> 编制日期：2025-4-2 | I3: 索引号： | J3: B12B
A4: =目录!A3 -> 会计期间：202X年度 | D4: =目录!A6 -> 复核人：李XX | G4: =目录!A7 -> 复核日期：2025-4-20 | I4: 页 次：
A5: 序号 | B5: 程序 | G5: 是否适用 | H5: 执行人 | I5: 执行情况说明 | J5: 索引号
A6: 一 | B6: 就下列事项，询问审计委员会主席或成员（治理层任命的其他机构）： | J6: B12B-1
A7: 1 | B7: 注册会计师与财务报表审计相关的责任
A8: （1） | B8: 注册会计师负责对管理层在治理层监督下编制的财务报表形成和发表意见。
A9: （2） | B9: 财务报表审计并不减轻管理层或治理层的责任。
A10: （3） | B10: 确定并在审计报告中沟通关键审计事项的责任（如适用）。
A11: （4） | B11: 依据法律法规的规定、与被审计单位的协议或适用于该业务的其他规定，注册会计师沟通特定事项的责任（如适用）。
A12: （5） | B12: 与被审计单位的协议可能要求沟通会计师事务所或网络事务所在提供除财务报表审计以外的其他服务时发现的特定事项（如适用）。
A13: （6） | B13: 授权对公共部门实体进行审计的文件可能要求注册会计师沟通其执行其他工作时（如绩效审计）注意到的事项（如适用）。
A14: 2 | B14: 事务所质量管理体系
A15: （1） | B15: 强调质量至上文化，坚持安全前行方针，采取风险导向的方法，根据自身的具体情况，设计、实施和运行事务所的质量管理体系。
A16: （2） | B16: 每年对质量管理体系作出评价，针对识别出的需改进领域，并采取适当行动以使其能够得到整改。
A17: （3） | B17: 通过完善面试流程招聘专业人员，提供培训课程以确保员工掌握最新的专业技术知识并具备执行工作的必要技能
A18: （4） | B18: 制定审计/会计提示、政策和程序模版以使项目组能够一贯遵守适用的职业标准和法律法规的要求，通过技术支持和咨询为项目组提供协助
... A48: （2） | B48: 法律法规和职业规范规定的防范措施、被审计单位采取的防范措施，以及会计师事务所内部自身的防范措施。
A49: 二 | B49: 汇总识别出的风险因素。 | J49: B50-1
A129: 是
A130: 否

Sheet B12B-1与治理层访谈记录
A1: 致同会计师事务所
A2: 与治理层访谈记录
A3: =目录!A2 -> 被审计单位：ABC有限公司 | C3: =目录!A4 -> 编制人：张XX | E3: =目录!A5 -> 编制日期：2025-4-2 | F3: 索引号：B12B-1
A4: =目录!A3 -> 会计期间：202X年度 | C4: =目录!A6 -> 复核人：李XX | E4: =目录!A7 -> 复核日期：2025-4-20 | F4: 页 次：
A6: 治理层姓名 | C6: 职务 | E6: 询问人 | F6: 询问日期
A13: 沟通事项 | C13: 沟通结果
A14: 一、注册会计师与财务报表审计相关的责任
A15: （一）注册会计师负责对管理层在治理层监督下编制的财务报表形成和发表意见
A16: （二）财务报表审计并不减轻管理层或治理层的责任
A17: （三）确定并在审计报告中沟通关键审计事项的责任（如适用） | H17: B18
A18: （四）依据法律法规的规定、与被审计单位的协议或适用于该业务的其他规定，注册会计师沟通特定事项的责任（如适用）
A19: （五）与被审计单位的协议可能要求沟通会计师事务所或网络事务所在提供除财务报表审计以外的其他服务时发现的特定事项（如适用）
A20: （六）授权对公共部门实体进行审计的文件可能要求注册会计师沟通其执行其他工作时（如绩效审计）注意到的事项（如适用）
A21: 二、计划的审计范围和时间安排
A22: （一）特别风险
A23: （二）重大错报风险评估水平较高的领域
A24: （三）对与审计相关的内部控制采取的方案
A25: （四）重要性
A26: （五）利用注册会计师的专家的工作（如适用）
A27: （六）可能构成关键审计事项所作的初步判断
A28: （七）利用内部审计工作，以及拟利用内部审计人员提供直接帮助的性质和程度（如适用）
A29: （八）治理层对下列问题的看法：
... A38: 结论：

Sheet B12C 与其他人员访谈程序
A1: 致同会计师事务所
A2: 与其他人员访谈程序表
A3: =目录!A2 -> 被审计单位：ABC有限公司 | D3: =目录!A4 -> 编制人：张XX | E3: =目录!A5 -> 编制日期：2025-4-2 | G3: 索引号： | H3: B12C
A4: =目录!A3 -> 会计期间：202X年度 | D4: =目录!A6 -> 复核人：李XX | E4: =目录!A7 -> 复核日期：2025-4-20 | G4: 页 次：
A5: 序号 | B5: 程序 | E5: 是否适用 | F5: 执行人 | G5: 执行情况说明 | H5: 索引号
A6: 一 | B6: 列出被审计单位内的人员（除管理层，治理层或内部审计师，如有）被审计小组讨论中确定需要对其进行访谈有关舞弊或潜在舞弊的情况。 | H6: B12C-1
A7: 1 | B7: 在下列审计过程中，审计师与企业的员工取得联系，并获取相关信息。
A8: 2 | B8: 在了解企业运营体系与内部控制的过程中。
A9: 3 | B9: 在执行存货监盘程序或执行截止性测试程序的过程中。
A10: 4 | B10: 在执行分析性程序时，对所发现的波动获取解释的过程中。
A11: 5 | B11: 未直接参与财务报告流程的运营人员。
A12: 6 | B12: 在复杂或异常交易中负责生成、记录或处理（如，涉及多重要素的销售交易或重大关联交易）的员工 。
A13: 7 | B13: 负责离职面谈的人力资源部的员工 。
A14: 8 | B14: 内部法律顾问。
A15: 9 | B15: 询问风险管理职能部门（或担任该角色的人员），了解可能影响财务报告的运营和监管风险。
A16: 10 | B16: 询问信息系统人员，了解系统变更、系统或控制失效情况，或与系统相关的其他风险。
A17: 二 | B17: 向内部审计人员询问下列事项： （适用于有内审部门） | H17: B18
A18: 1 | B18: 他们对企业内部控制以及重大错报风险的看法。
A19: 2 | B19: 内审人员对舞弊风险的看法。
A20: 3 | B20: 执行程序以识别或发现期间内的舞弊。
A21: 4 | B21: 通过执行上述程序所发现的问题，管理层是否给出令人满意的应对。
A22: 5 | B22: 内审人员是否了解已经发生的舞弊或舞弊嫌疑。
A23: 6 | B23: 内审人员是否知悉管理层凌驾于控制之上的行为；若有，这种行为的性质。
A24: 三 | B24: 获取前任会计计师的相关信息。（适用于首次审计） | H24: B1-3
A25: 1 | B25: 要求客户向前任注册会计师寄发授权书，以便前任全面答复我们的调查，并允许我们查阅所有相关审计工作底稿。 （适用于首次审计）
A26: 四 | B26: 向客户的律师寄发律师询证函，包括关于诉讼、索赔和评估的信息。 | H26: A12-1
A27: 五 | B27: 如被审计单位利用服务机构，考虑安排与服务机构进行访谈。
A28: 六 | B28: 汇总识别出的风险因素。 | H28: B50-1
A108: 是
A109: 否

Sheet B12C-1 与其他人员访谈记录
A1: 致同会计师事务所
A2: 与被审计单位内部的其他人员访谈记录
A3: =目录!A2 -> 被审计单位：ABC有限公司 | C3: =目录!A4 -> 编制人：张XX | E3: =目录!A5 -> 编制日期：2025-4-2 | F3: 索引号：B12C-1
A4: =目录!A3 -> 会计期间：202X年度 | C4: =目录!A6 -> 复核人：李XX | E4: =目录!A7 -> 复核日期：2025-4-20 | F4: 页 次：
A5: 一、 | B5: 询问其他人员
A6: 其他人员姓名 | C6: 职务 | E6: 询问人 | F6: 询问日期
A12: 询问内容 | E12: 询问结果
A13: 是否知悉任何影响被审计单位的舞弊事实、舞弊嫌疑或舞弊指控？
A14: ……
A15: ……
A16: ……
A17: …… | H17: B18
A18: ……
A19: ……
A20: ……
