Workbook
Name _13102: #REF!
Name _13302: #REF!
Name _13398: #REF!
Name _18102: #REF!
Name _18198: #REF!
Name a: #REF!
Name as: #REF!
Name b: #REF!
Name bv: #REF!
Name d: #REF!
Name df: #REF!
Name dfs: #REF!
Name e: #REF!
Name er: #REF!
Name f: #REF!
Name fg: #REF!
Name fgd: #REF!
Name fgh: #REF!
Name g: #REF!
Name h: #REF!
Name hv: #REF!
Name i: #REF!
Name jk: #REF!
Name k: #REF!
Name kj: #REF!
Name kl: #REF!
Name KMDM: #REF!
Name l: #REF!
Name lk: #REF!
Name m: #REF!
Name mn: #REF!
Name n: #REF!
Name nm: #REF!
Name o: #REF!
Name op: #REF!
Name p: #REF!
Name q: #REF!
Name rt: #REF!
Name rty: #REF!
Name s: #REF!
Name sa: #REF!
Name scn: #REF!
Name _scn11: #REF!
Name _scn15: #REF!
Name _scn16: #REF!
Name _scn17: #REF!
Name _scn19: #REF!
Name _scn2: #REF!
Name _scn20: #REF!
Name _scn3: #REF!
Name _scn4: #REF!
Name _scn5: #REF!
Name _scn6: #REF!
Name _scn7: #REF!
Name _scn8: #REF!
Name _scn9: #REF!
Name scq: #REF!
Name _scq1: #REF!
Name _scq11: #REF!
Name _scq15: #REF!

Sheet temp_temp__
C5: 38717

Sheet 说明
B2: 使用说明： | L2: 序号 | M2: 目录
L3: 1 | M3: 说明
B4: 1 | C4: 本工作簿用于单项会计报表审计调整、试算平衡；未审报表及审定报表的横向、纵向、比率分析。 | L4: 2 | M4: 参数
L5: 3 | M5: 报表格式
B6: 2 | C6: 本工作簿没有颜色的单元格可以根据需要进行修改， | L6: 4 | M6: 未审BS
C7: 修改时，请在拟修改的单元格直接输入新的内容，请不要使用剪切或拖拽填充功能。 | L7: 5 | M7: 未审PL
L8: 6 | M8: 未审CF
B9: 3 | C9: 请在 | D9: “参数表” | E9: 中没有颜色的单元格中输入项目基本情况，其他工作表相应区域会随之改变。 | L9: 7 | M9: 期初核对BS
L10: 8 | M10: 期初核对PL
B11: 4 | C11: 未审报表、试算平衡表（TB）、审定报表、比较分析表的格式由 | G11: “报表格式” | H11: 链接控制； | L11: 9 | M11: 账项调整
C12: 如需修改报表科目，请在 | E12: “报表格式” | F12: 中没有颜色的单元格区域修改，其他报表会相应改变。 | L12: 10 | M12: 报表调整
L13: 11 | M13: CF调整
B14: 5 | C14: “账项调整”、 | D14: “报表调整” | E14: 可以根据需要插入行，请勿删除行；调整金额会自动链接到试算平衡表， | L14: 12 | M14: TB资产
C15: 若调整未全部链入试算平衡表，请检查调整分录的借贷方科目是否为报表科目。若需添加或更改报表科目， | L15: 13 | M15: TB负债
C16: 请在 | D16: “报表格式” | E16: 中没有颜色的单元格区域进行修改，并相应修改 | H16: “报表格式AA列” | L16: 14 | M16: TB损益
L17: 15 | M17: 审定BS
L18: 16 | M18: 审定PL
L19: 17 | M19: 审定CF
L20: 18 | M20: 未审横向BS
L21: 19 | M21: 未审横向PL
L22: 20 | M22: 未审纵向BS
L23: 21 | M23: 未审纵向PL
L24: 22 | M24: 未审比率分析
L25: 23 | M25: 已审横向BS
L26: 24 | M26: 已审横向PL
L27: 25 | M27: 已审纵向BS
L28: 26 | M28: 已审纵向PL
... L37: 35 | M37: 审定CF(上期)

Sheet 参数
B2: 项 目 | D2: 参 数 | E2: 参考格式
B3: 客户情况 | C3: 单位名称： | E3: 北京二锅头有限责任公司
C4: 法定代表人： | E4: 张一二
C5: 财务负责人： | E5: 陈一二
C6: 会计主管： | E6: 王一二
B8: 会计报表 | C8: 报表类型 | D8: 一般企业（执行统一会计制度） | E8: 股份有限公司或一般企业(执行统一会计制度)
C9: 会计年度（上期）： | D9: 2006年度 | E9: 1999年度 或 1997年10月20日～1998年8月10日 | H9: 股份有限公司
C10: 会计年度（本期）： | D10: 2007年度 | E10: 2000年度 或 1998年8月10日～2000年10月20日 | H10: 一般企业（执行统一会计制度）
C11: 会计截止（上期）： | D11: 39082 | E11: 1999年12月31日 或 1998年8月10日 | I11: =MONTH(D11) -> 12
C12: 会计截止（本期）： | D12: 39447 | E12: 2000年12月31日 或 2000年10月20日 | I12: =MONTH(D12) -> 12
C13: 金额单位： | D13: 人民币元 | E13: 人民币元
B15: 审计单位 | C15: 审计单位名称： | D15: 北京京都会计师事务所 | E15: 北京京都会计师事务所
C16: 项目负责人：
C17: 底稿编制人： | E17: 刘一二
C18: 底稿复核人： | E18: 周一二
B20: NB | C20: 本表没有颜色的单元格可以根据需要进行修改
B24: 报表勾稽关系审核表
B25: No. | C25: 勾稽审核内容 | D25: 审核结果 | E25: 不符原因
B26: 1 | C26: 期末资产总计＝期末负债和股东权益总计 | D26: =IF(ABS(审定BS!C62-审定BS!C125)<0.01,TRUE,FALSE) -> TRUE | E26: =IF(D26=TRUE,"","期末资产负债表不平")
B27: 2 | C27: 期初资产总计＝期初负债和股东权益总计 | D27: =IF(ABS(审定BS!E62-审定BS!E125)<0.01,TRUE,FALSE) -> TRUE | E27: =IF(D27=TRUE,"","期初资产负债表不平")
B28: 3 | C28: B/S期末未分配利润＝P/L期末未分配利润 | D28: =IF(ABS(审定BS!C118-审定PL!C73)<0.01,TRUE,FALSE) -> TRUE | E28: =IF(D28=TRUE,"","期末利润分配表与资产负债表未分配利润勾稽不对")
B29: 4 | C29: B/S期初未分配利润＝P/L期初未分配利润 | D29: =IF(ABS(审定BS!E118-审定PL!E73)<0.01,TRUE,FALSE) -> TRUE | E29: =IF(D29=TRUE,"","期初利润分配表与资产负债表未分配利润勾稽不对")
B30: 5 | C30: 期末年初未分配利润＝期初未分配利润 | D30: =IF(ABS(审定PL!C54-审定PL!E73)<0.01,TRUE,FALSE) -> TRUE | E30: =IF(D30=TRUE,"","利润及利润分配表年初未分配利润与上期勾稽不对")
B31: 6 | C31: B/S期末货币资金＝Cashflow期末货币资金 | D31: =IF(ABS(审定BS!C7-审定CF!C82)<0.01,TRUE,FALSE) -> TRUE | E31: =IF(D31=TRUE,"","现金流量表与资产负债表期末货币资金勾稽不对")
B32: 7 | C32: B/S期初货币资金＝Cashflow期初货币资金 | D32: =IF(ABS(审定BS!E7-审定CF!C83)<0.01,TRUE,FALSE) -> TRUE | E32: =IF(D32=TRUE,"","现金流量表与资产负债表期初货币资金勾稽不对")
B33: 8 | C33: 直接法OperatingCF＝间接法OperatingCF | D33: =IF(ABS(审定CF!C16-审定CF!C74)<0.01,TRUE,FALSE) -> TRUE | E33: =IF(D33=TRUE,"","现金流量表主表与附表勾稽不对-经营活动现金净增加额")
B34: 9 | C34: 直接法NetCashflow＝间接法NetCashflow | D34: =IF(ABS(审定CF!C45-审定CF!C86)<0.01,TRUE,FALSE) -> TRUE | E34: =IF(D34=TRUE,"","现金流量表主表与附表勾稽不对-现金净增加额")
B35: 10 | C35: P/L净利润＝Cashflow间接法净利润 | D35: =IF(ABS(审定PL!C53-审定CF!C56)<0.01,TRUE,FALSE) -> TRUE | E35: =IF(D35=TRUE,"","现金流量表与利润表勾稽不对-净利润")
B36: 11 | C36: Cashflow待摊费用减少＝B/S待摊费用减少 | D36: =IF(ABS(审定CF!C63-(审定BS!E21-审定BS!C21))<0.01,TRUE,FALSE) -> TRUE | E36: =IF(D36=TRUE,"","现金流量表待摊费用与资产负债表勾稽不对")
B37: 12 | C37: Cashflow预提费用增加＝B/S预提费用增加 | D37: =IF(ABS(审定CF!C64-(审定BS!C81-审定BS!E81))<0.01,TRUE,FALSE) -> TRUE | E37: =IF(D37=TRUE,"","现金流量表预提费用与资产负债表勾稽不对")
B38: 13 | C38: Cashflow存货的减少＝B/S存货的减少 | D38: =IF(ABS(审定CF!C70-(审定BS!E18-审定BS!C18))<0.01,TRUE,FALSE) -> TRUE | E38: =IF(D38=TRUE,"","现金流量表存货与资产负债表勾稽不对")
B39: 14 | C39: Cashflow投资收益＝P/L投资收益 | D39: =IF(ABS(审定CF!C68+审定PL!C31)<0.01,TRUE,FALSE) -> TRUE | E39: =IF(D39=TRUE,"","2005年利润分配表与现金流量表投资收益勾稽不对")
B40: 15 | C40: Cashflow少数股东损益＝P/L少数股东损益 | D40: =IF(ABS(审定CF!C57-审定PL!C51)<0.01,TRUE,FALSE) -> TRUE | E40: =IF(D40=TRUE,"","利润分配表与现金流量表少数股东损益勾稽不对")
B41: 16 | C41: 按净利润的10%提取法定盈余公积 | D41: =IF(ABS(审定PL!C58-审定PL!C53*0.1)<0.01,TRUE,FALSE) -> TRUE | E41: =IF(D41=TRUE,"","按照公司政策，公司提取的法定盈余公积不符")
B42: 17 | C42: 法定公益金余额结转盈余公积后余额为零 | D42: =IF(审定BS!C116=0,TRUE,FALSE) -> TRUE | E42: =IF(D42=TRUE,"","法定公益金结转盈余公积后无余额")
B43: 18
B44: 19
B45: 20 | C45: 待处理流动资产净损益科目年末余额为零 | D45: =IF(审定BS!C22=0,TRUE,FALSE) -> TRUE | E45: =IF(D45=TRUE,"","按照新制度规定，待处理流动资产净损益科目年末不应有余额")
B46: 21 | C46: 待处理固定资产净损益科目年末余额为零 | D46: =IF(审定BS!C44=0,TRUE,FALSE) -> TRUE | E46: =IF(D46=TRUE,"","按照新制度规定，待处理固定资产净损益科目年末不应有余额")

Sheet 报表格式
A1: 会计报表格式及科目名称 | Q1: 会计报表格式及科目名称 | Z1: code | AA1: 报表项目
B2: 本表没有颜色的单元格可以根据需要进行修改，本系统的其它表格将随之改变。比如，可将“存货”改为“存货1”。正确的修改方法，是在拟修改的单元格直接输入新的内容，请不要使用剪切或拖拽功能。
B3: 资 产 类 | G3: 负债及所有者权益类 | L3: 损 益 类 | Q3: 现金流量表类 | U3: 现金流量表类
B4: 报表项目 | C4: 行 | D4: 调整年末科目名称 | E4: 调整年初科目名称 | G4: 报表项目 | H4: 行 | I4: 调整年末科目名称 | J4: 调整年初科目名称 | L4: 报表项目 | M4: 行 | N4: 调整本期科目名称 | O4: 调整上期科目名称 | Q4: 报表项目 | R4: 行 | S4: 科目名称 | U4: 补充资料 | V4: 行 | W4: 科目名称
B5: 流动资产： | C5: 1 | G5: 流动负债： | H5: =C72+1 -> 58 | L5: 一、主营业务收入 | M5: 1 | N5: 主营业务收入 | O5: =IF(N5="",0,CONCATENATE("上年",N5)) -> 上年主营业务收入 | Q5: 一、经营活动产生的现金流量 | R5: 1 | U5: 1、将净利润调节为经营活动现金流量 | V5: =R78+1 -> 1 | AA5: 流动资产：
B6: 货币资金 | C6: 2 | D6: 货币资金 | E6: =IF(D6="",0,CONCATENATE("年初",D6)) -> 年初货币资金 | G6: 短期借款 | H6: =H5+1 -> 59 | I6: 短期借款 | J6: =IF(I6="",0,CONCATENATE("年初",I6)) -> 年初短期借款 | L6: 其中：进口产品（商品）销售收入 | M6: 2 | Q6: 销售商品、提供劳务收到的现金 | R6: 2 | S6: 销售商品、提供劳务收到的现金 | U6: 净利润 | V6: =V5+1 -> 2 | W6: 净利润 | Z6: G123 | AA6: =B6 -> 货币资金
B7: 短期投资 | C7: 3 | D7: 短期投资 | E7: =IF(D7="",0,CONCATENATE("年初",D7)) -> 年初短期投资 | G7: 应付票据 | H7: =H6+1 -> 60 | I7: 应付票据 | J7: =IF(I7="",0,CONCATENATE("年初",I7)) -> 年初应付票据 | L7: 出口产品（商品）销售收入 | M7: 3 | Q7: 收到的税费返还 | R7: 3 | S7: 收到的税费返还 | U7: 加：*少数股东损益 | V7: =V6+1 -> 3 | W7: 少数股东损益 | Z7: F1 | AA7: =B7 -> 短期投资
B8: 应收票据 | C8: 4 | D8: 应收票据 | E8: =IF(D8="",0,CONCATENATE("年初",D8)) -> 年初应收票据 | G8: 应付账款 | H8: =H7+1 -> 61 | I8: 应付账款 | J8: =IF(I8="",0,CONCATENATE("年初",I8)) -> 年初应付账款 | L8: 减：折扣与折让 | M8: 4 | N8: 折扣与折让 | O8: =IF(N8="",0,CONCATENATE("上年",N8)) -> 上年折扣与折让 | Q8: 收到的其他与经营活动有关的现金 | R8: 4 | S8: 收到的其他与经营活动有关的现金 | U8: 减：*未确认的投资损失 | V8: =V7+1 -> 4 | W8: 未确认的投资损失 | Z8: D3 | AA8: =B8 -> 应收票据
B9: 应收股利 | C9: 5 | D9: 应收股利 | E9: =IF(D9="",0,CONCATENATE("年初",D9)) -> 年初应收股利 | G9: 预收账款 | H9: =H8+1 -> 62 | I9: 预收账款 | J9: =IF(I9="",0,CONCATENATE("年初",I9)) -> 年初预收账款 | L9: 二、主营业务收入净额 | M9: 5 | R9: 5 | U9: 加：计提的资产减值准备 | V9: =V8+1 -> 5 | W9: 计提的资产减值准备 | Z9: F5 | AA9: =B9 -> 应收股利
B10: 应收利息 | C10: 6 | D10: 应收利息 | E10: =IF(D10="",0,CONCATENATE("年初",D10)) -> 年初应收利息 | G10: 应付工资 | H10: =H9+1 -> 63 | I10: 应付工资 | J10: =IF(I10="",0,CONCATENATE("年初",I10)) -> 年初应付工资 | L10: 减：（一）主营业务成本 | M10: 6 | N10: 主营业务成本 | O10: =IF(N10="",0,CONCATENATE("上年",N10)) -> 上年主营业务成本 | Q10: 现金流入小计 | R10: 6 | U10: 固定资产折旧 | V10: =V9+1 -> 6 | W10: 固定资产折旧 | Z10: F6 | AA10: =B10 -> 应收利息
B11: 应收账款 | C11: 7 | D11: 应收账款 | E11: =IF(D11="",0,CONCATENATE("年初",D11)) -> 年初应收账款 | G11: 应付福利费 | H11: =H10+1 -> 64 | I11: 应付福利费 | J11: =IF(I11="",0,CONCATENATE("年初",I11)) -> 年初应付福利费 | L11: 其中：出口产品（商品）销售成本 | M11: 7 | Q11: 购买商品、接受劳务支付的现金 | R11: 7 | S11: 购买商品、接受劳务支付的现金 | U11: 无形资产摊销 | V11: =V10+1 -> 7 | W11: 无形资产摊销 | Z11: D1 | AA11: =B11 -> 应收账款
B12: 其他应收款 | C12: 8 | D12: 其他应收款 | E12: =IF(D12="",0,CONCATENATE("年初",D12)) -> 年初其他应收款 | G12: 应付股利（利润） | H12: =H11+1 -> 65 | I12: 应付股利 | J12: =IF(I12="",0,CONCATENATE("年初",I12)) -> 年初应付股利 | L12: （二）主营业务税金及附加 | M12: 8 | N12: 主营业务税金及附加 | O12: =IF(N12="",0,CONCATENATE("上年",N12)) -> 上年主营业务税金及附加 | Q12: 支付给职工以及为职工支付的现金 | R12: 8 | S12: 支付给职工以及为职工支付的现金 | U12: 长期待摊费用摊销 | V12: =V11+1 -> 8 | W12: 长期待摊费用摊销 | Z12: G4 | AA12: =B12 -> 其他应收款
B13: 预付账款 | C13: 9 | D13: 预付账款 | E13: =IF(D13="",0,CONCATENATE("年初",D13)) -> 年初预付账款 | G13: 应付利息 | H13: =H12+1 -> 66 | I13: 应交税金 | J13: =IF(I13="",0,CONCATENATE("年初",I13)) -> 年初应交税金 | L13: （三）经营费用 | M13: 9 | N13: 经营费用 | O13: =IF(N13="",0,CONCATENATE("上年",N13)) -> 上年经营费用 | Q13: 支付各项税费 | R13: 9 | S13: 支付各项税费 | U13: 待摊费用的减少（减：增加） | V13: =V12+1 -> 9 | W13: 待摊费用的减少（减：增加） | Z13: E3 | AA13: =B13 -> 预付账款
B14: 期货保证金 | C14: 10 | D14: 期货保证金 | E14: =IF(D14="",0,CONCATENATE("年初",D14)) -> 年初期货保证金 | G14: 应交税金 | H14: =H13+1 -> 67 | I14: 其他未交款 | J14: =IF(I14="",0,CONCATENATE("年初",I14)) -> 年初其他未交款 | L14: （四）其他 | M14: 10 | N14: 其他 | O14: =IF(N14="",0,CONCATENATE("上年",N14)) -> 上年其他 | Q14: 支付的其他与经营活动有关的现金 | R14: 10 | S14: 支付的其他与经营活动有关的现金 | U14: 预提费用的增加（减：减少） | V14: =V13+1 -> 10 | W14: 预提费用的增加（减：减少） | AA14: =B14 -> 期货保证金
B15: 应收补贴款 | C15: 11 | D15: 应收补贴款 | E15: =IF(D15="",0,CONCATENATE("年初",D15)) -> 年初应收补贴款 | G15: 其他应交款 | H15: =H14+1 -> 68 | I15: 其他应付款 | J15: =IF(I15="",0,CONCATENATE("年初",I15)) -> 年初其他应付款 | L15: 加：（一）递延收益 | M15: 11 | N15: 递延收益 | O15: =IF(N15="",0,CONCATENATE("上年",N15)) -> 上年递延收益 | R15: 11 | U15: 处置固定资产、无形资产和其他长期资产的损失（减：收益） | V15: =V14+1 -> 11 | W15: 处置固定资产、无形资产和其他长期资产的损失（减：收益） | Z15: I1 | AA15: =B15 -> 应收补贴款
B16: 应收出口退税 | C16: 12 | D16: 应收出口退税 | E16: =IF(D16="",0,CONCATENATE("年初",D16)) -> 年初应收出口退税 | G16: 其他应付款 | H16: =H15+1 -> 69 | I16: 预提费用 | J16: =IF(I16="",0,CONCATENATE("年初",I16)) -> 年初预提费用 | L16: （二）代购代销收入 | M16: 12 | N16: 代购代销收入 | O16: =IF(N16="",0,CONCATENATE("上年",N16)) -> 上年代购代销收入 | R16: 12 | U16: 固定资产报废损失 | V16: =V15+1 -> 12 | W16: 固定资产报废损失 | AA16: =B16 -> 应收出口退税
B17: 存货 | C17: 13 | D17: 存货 | E17: =IF(D17="",0,CONCATENATE("年初",D17)) -> 年初存货 | G17: 预提费用 | H17: =H16+1 -> 70 | I17: 预计负债 | J17: =IF(I17="",0,CONCATENATE("年初",I17)) -> 年初预计负债 | L17: （三）其他 | M17: 13 | N17: 其他 | O17: =IF(N17="",0,CONCATENATE("上年",N17)) -> 上年其他 | R17: 13 | U17: 财务费用 | V17: =V16+1 -> 13 | W17: 财务费用 | Z17: E1 | AA17: =B17 -> 存货
B18: 其中：原材料 | C18: 14 | D18: 其中：原材料 | G18: 预计负债 | H18: =H17+1 -> 71 | I18: 一年内到期的长期负债 | J18: =IF(I18="",0,CONCATENATE("年初",I18)) -> 年初一年内到期的长期负债 | L18: 三、主营业务利润 | M18: 14 | O18: =IF(N18="",0,CONCATENATE("上年",N18)) -> 0 | Q18: 现金流出小计 | R18: 14 | U18: 投资损失（减：收益） | V18: =V17+1 -> 14
B19: 库存商品（产成品） | C19: 15 | D19: 库存商品（产成品） | G19: 递延收益 | H19: =H18+1 -> 72 | I19: 其他流动负债 | J19: =IF(I19="",0,CONCATENATE("年初",I19)) -> 年初其他流动负债 | L19: 加：其他业务利润 | M19: 15 | N19: 其他业务利润 | O19: =IF(N19="",0,CONCATENATE("上年",N19)) -> 上年其他业务利润 | Q19: 经营活动产生的现金流量净额 | R19: 15 | U19: 递延税款贷项（减：借项） | V19: =V18+1 -> 15
B20: 待摊费用 | C20: 16 | D20: 待摊费用 | E20: =IF(D20="",0,CONCATENATE("年初",D20)) -> 年初待摊费用 | G20: 一年内到期的长期负债 | H20: =H19+1 -> 73 | L20: 减：（一）营业费用 | M20: 16 | N20: 营业费用 | O20: =IF(N20="",0,CONCATENATE("上年",N20)) -> 上年营业费用 | Q20: 二、投资活动产生的现金流量 | R20: 16 | U20: 存货的减少（减：增加） | V20: =V19+1 -> 16 | W20: 投资损失（减：收益） | Z20: I4 | AA20: =B20 -> 待摊费用
B21: 待处理流动资产净损失 | C21: 17 | D21: 待处理流动资产净损失 | E21: =IF(D21="",0,CONCATENATE("年初",D21)) -> 年初待处理流动资产净损失 | G21: 应付权证 | H21: =H20+1 -> 74 | J21: =IF(I21="",0,CONCATENATE("年初",I21)) -> 0 | L21: （二）管理费用 | M21: 17 | N21: 管理费用 | O21: =IF(N21="",0,CONCATENATE("上年",N21)) -> 上年管理费用 | Q21: 收回投资所收到的现金 | R21: 17 | S21: 收回投资所收到的现金 | U21: 经营性应收项目的减少（减：增加） | V21: =V20+1 -> 17 | W21: 递延税款贷项（减：借项） | Z21: I6 | AA21: =B21 -> 待处理流动资产净损失
B22: 一年内到期的长期债权投资 | C22: 18 | D22: 一年内到期的长期债权投资 | E22: =IF(D22="",0,CONCATENATE("年初",D22)) -> 年初一年内到期的长期债权投资 | G22: 其他流动负债 | H22: =H21+1 -> 75 | J22: =IF(I22="",0,CONCATENATE("年初",I22)) -> 0 | L22: 其中：业务招待费 | M22: 18 | N22: 财务费用 | O22: =IF(N22="",0,CONCATENATE("上年",N22)) -> 上年财务费用 | Q22: 其中：出售子公司所收到的现金 | R22: 18 | U22: 经营性应付项目的增加（减：减少） | V22: =V21+1 -> 18 | W22: 存货的减少（减：增加） | AA22: =B22 -> 一年内到期的长期债权投资
B23: 其他流动资产 | C23: 19 | D23: 其他流动资产 | E23: =IF(D23="",0,CONCATENATE("年初",D23)) -> 年初其他流动资产 | H23: =H22+1 -> 76 | J23: =IF(I23="",0,CONCATENATE("年初",I23)) -> 0 | L23: 研究与开发费 | M23: 19 | Q23: 取得投资收益所收到的现金 | R23: 19 | S23: 取得投资收益所收到的现金 | U23: 其他 | V23: =V22+1 -> 19 | W23: 经营性应收项目的减少（减：增加） | AA23: =B23 -> 其他流动资产
C24: 20 | E24: =IF(D24="",0,CONCATENATE("年初",D24)) -> 0 | H24: =H23+1 -> 77 | J24: =IF(I24="",0,CONCATENATE("年初",I24)) -> 0 | L24: （三）财务费用 | M24: 20 | Q24: 处置固定资产、无形资产和其他长期资产所收回的现金净额 | R24: 20 | S24: 处置固定资产、无形资产和其他长期资产所收回的现金净额 | V24: =V23+1 -> 20 | W24: 经营性应付项目的增加（减：减少） | AA24: =B24 -> 0
C25: 21 | E25: =IF(D25="",0,CONCATENATE("年初",D25)) -> 0 | G25: 流动负债合计 | H25: =H24+1 -> 78 | I25: 长期借款 | J25: =IF(I25="",0,CONCATENATE("年初",I25)) -> 年初长期借款 | L25: 其中：利息支出 | M25: 21 | O25: =IF(N25="",0,CONCATENATE("上年",N25)) -> 0 | Q25: 收到的其他与投资活动有关的现金 | R25: 21 | S25: 收到的其他与投资活动有关的现金 | V25: =V24+1 -> 21 | W25: 其他 | AA25: =B25 -> 0
B26: 流动资产合计 | C26: 22 | E26: =IF(D26="",0,CONCATENATE("年初",D26)) -> 0 | G26: 长期负债： | H26: =H25+1 -> 79 | I26: 应付债券 | J26: =IF(I26="",0,CONCATENATE("年初",I26)) -> 年初应付债券 | L26: 利息收入 | M26: 22 | N26: 其他 | O26: =IF(N26="",0,CONCATENATE("上年",N26)) -> 上年其他 | R26: 22 | U26: 经营活动产生的现金流量净额 | V26: =V25+1 -> 22 | AA26: 流动资产合计
B27: 长期投资 | C27: 23 | E27: =IF(D27="",0,CONCATENATE("年初",D27)) -> 0 | G27: 长期借款 | H27: =H26+1 -> 80 | I27: 长期应付款 | J27: =IF(I27="",0,CONCATENATE("年初",I27)) -> 年初长期应付款 | L27: 汇兑净损失 | M27: 23 | O27: =IF(N27="",0,CONCATENATE("上年",N27)) -> 0 | Q27: 现金流入小计 | R27: 23 | V27: =V26+1 -> 23
B28: 其中：长期股权投资 | C28: 24 | E28: =IF(D28="",0,CONCATENATE("年初",D28)) -> 0 | G28: 应付债券 | H28: =H27+1 -> 81 | I28: 专项应付款 | J28: =IF(I28="",0,CONCATENATE("年初",I28)) -> 年初专项应付款 | L28: （四）其他 | M28: 24 | N28: 投资收益 | O28: =IF(N28="",0,CONCATENATE("上年",N28)) -> 上年投资收益 | Q28: 购置固定资产、无形资产和其他长期资产所支付的现金 | R28: 24 | S28: 购置固定资产、无形资产和其他长期资产所支付的现金 | U28: 2、不涉及现金收支的投资和筹资活动 | V28: =V27+1 -> 24 | AA28: 长期投资：
B29: 长期债权投资 | C29: 25 | D29: 长期股权投资 | E29: =IF(D29="",0,CONCATENATE("年初",D29)) -> 年初长期股权投资 | G29: 长期应付款 | H29: =H28+1 -> 82 | I29: 其他长期负债 | J29: =IF(I29="",0,CONCATENATE("年初",I29)) -> 年初其他长期负债 | L29: 四、营业利润 | M29: 25 | N29: 期货收益 | Q29: 投资所支付的现金 | R29: 25 | S29: 投资所支付的现金 | U29: 债务转为资本 | V29: =V28+1 -> 25 | Z29: F2 | AA29: 长期股权投资
B30: *合并价差 | C30: 26 | D30: 长期债权投资 | E30: =IF(D30="",0,CONCATENATE("年初",D30)) -> 年初长期债权投资 | G30: 专项应付款 | H30: =H29+1 -> 83 | I30: 其中：特准储备资金 | L30: 加：（一）投资收益 | M30: 26 | N30: 补贴收入 | Q30: 其中：购买子公司所支付的现金 | R30: 26 | U30: 一年内到期的可转换公司债券 | V30: =V29+1 -> 26 | Z30: F3 | AA30: 长期债权投资
C31: 27 | D31: 合并价差 | E31: =IF(D31="",0,CONCATENATE("年初",D31)) -> 年初合并价差 | G31: 其他长期负债 | H31: =H30+1 -> 84 | L31: （二）期货收益 | M31: 27 | Q31: 支付的其他与投资活动有关的现金 | R31: 27 | S31: 支付的其他与投资活动有关的现金 | U31: 融资租入固定资产 | V31: =V30+1 -> 27 | W31: 债务转为资本 | AA31: 合并价差
C32: 28 | G32: 其中：特准储备资金 | H32: =H31+1 -> 85 | J32: =IF(I32="",0,CONCATENATE("年初",I32)) -> 0 | L32: （三）补贴收入 | M32: 28 | N32: 营业外收入 | O32: =IF(N32="",0,CONCATENATE("上年",N32)) -> 上年营业外收入 | R32: 28 | U32: 其他 | V32: =V31+1 -> 28 | W32: 一年内到期的可转换公司债券 | AA32: =B31 -> 0
B33: 长期投资合计 | C33: 29 | H33: =H32+1 -> 86 | J33: =IF(I33="",0,CONCATENATE("年初",I33)) -> 0 | L33: 其中：补贴前亏损的企业补贴收入 | M33: 29 | Q33: 现金流出小计 | R33: 29 | V33: =V32+1 -> 29 | W33: 融资租入固定资产 | AA33: =B32 -> 0
B34: 固定资产： | C34: 30 | E34: =IF(D34="",0,CONCATENATE("年初",D34)) -> 0 | H34: =H33+1 -> 87 | J34: =IF(I34="",0,CONCATENATE("年初",I34)) -> 0 | L34: （四）营业外收入 | M34: 30 | Q34: 投资活动产生的现金流量净额 | R34: 30 | U34: 3、现金及现金等价物净增加情况 | V34: =V33+1 -> 30 | W34: 其他 | AA34: 长期投资合计
B35: 固定资产原价 | C35: 31 | E35: =IF(D35="",0,CONCATENATE("年初",D35)) -> 0 | G35: 长期负债合计 | H35: =H34+1 -> 88 | J35: =IF(I35="",0,CONCATENATE("年初",I35)) -> 0 | L35: 其中：处置固定资产净收益 | M35: 31 | Q35: 三、筹资活动产生的现金流量 | R35: 31 | U35: 现金的期末余额 | V35: =V34+1 -> 31
B36: 减：累计折旧 | C36: 32 | E36: =IF(D36="",0,CONCATENATE("年初",D36)) -> 0 | G36: 递延税项： | H36: =H35+1 -> 89 | I36: 递延税款贷项 | J36: =IF(I36="",0,CONCATENATE("年初",I36)) -> 年初递延税款贷项 | L36: 非货币性交易收益 | M36: 32 | Q36: 吸收投资所收到的现金 | R36: 32 | S36: 吸收投资所收到的现金 | U36: 减：现金的期初余额 | V36: =V35+1 -> 32 | AA36: 固定资产：
B37: 固定资产净值 | C37: 33 | D37: 固定资产 | E37: =IF(D37="",0,CONCATENATE("年初",D37)) -> 年初固定资产 | G37: 递延税款贷项 | H37: =H36+1 -> 90 | J37: =IF(I37="",0,CONCATENATE("年初",I37)) -> 0 | L37: 出售无形资产收益 | M37: 33 | Q37: 取得借款所收到的现金 | R37: 33 | S37: 取得借款所收到的现金 | U37: 加：现金等价物的期末余额 | V37: =V36+1 -> 33 | W37: 现金的期末余额 | Z37: H1 | AA37: 固定资产原价
B38: 减：固定资产减值准备 | C38: 34 | D38: 累计折旧 | E38: =IF(D38="",0,CONCATENATE("年初",D38)) -> 年初累计折旧 | G38: 负 债 合 计 | H38: =H37+1 -> 91 | J38: =IF(I38="",0,CONCATENATE("年初",I38)) -> 0 | L38: 罚款净收入 | M38: 34 | Q38: 收到的其他与筹资活动有关的现金 | R38: 34 | S38: 收到的其他与筹资活动有关的现金 | U38: 减：现金等价物的期初余额 | V38: =V37+1 -> 34 | W38: 现金的期初余额 | Z38: H2 | AA38: 累计折旧
B39: 固定资产净额 | C39: 35 | E39: =IF(D39="",0,CONCATENATE("年初",D39)) -> 0 | G39: *少数股东权益 | H39: =H38+1 -> 92 | J39: =IF(I39="",0,CONCATENATE("年初",I39)) -> 0 | L39: （五）其他 | M39: 35 | O39: =IF(N39="",0,CONCATENATE("上年",N39)) -> 0 | R39: 35 | V39: =V38+1 -> 35 | W39: 现金等价物的期末余额
B40: 工程物资 | C40: 36 | D40: 固定资产减值准备 | E40: =IF(D40="",0,CONCATENATE("年初",D40)) -> 年初固定资产减值准备 | H40: =H39+1 -> 93 | I40: 少数股东权益 | J40: =IF(I40="",0,CONCATENATE("年初",I40)) -> 年初少数股东权益 | L40: 其中：用以前年度含量工资结余弥补利润 | M40: 36 | N40: 营业外支出 | O40: =IF(N40="",0,CONCATENATE("上年",N40)) -> 上年营业外支出 | Q40: 现金流入小计 | R40: 36 | V40: =V39+1 -> 36 | W40: 现金等价物的期初余额 | Z40: H3 | AA40: 固定资产减值准备
B41: 在建工程 | C41: 37 | E41: =IF(D41="",0,CONCATENATE("年初",D41)) -> 0 | G41: =IF(参数!D$8="股份有限公司","股东权益：",IF(参数!D$8="一般企业（执行统一会计制度）","所有者权益：","")) -> 所有者权益： | H41: =H40+1 -> 94 | J41: =IF(I41="",0,CONCATENATE("年初",I41)) -> 0 | L41: 减：（一）营业外支出 | M41: 37 | Q41: 偿还债务所支付的现金 | R41: 37 | S41: 偿还债务所支付的现金 | V41: =V40+1 -> 37
B42: 固定资产清理 | C42: 38 | D42: 固定资产清理 | E42: =IF(D42="",0,CONCATENATE("年初",D42)) -> 年初固定资产清理 | G42: =IF(参数!D$8="股份有限公司","股本",IF(参数!D$8="一般企业（执行统一会计制度）","实收资本","")) -> 实收资本 | H42: =H41+1 -> 95 | J42: =IF(I42="",0,CONCATENATE("年初",I42)) -> 0 | L42: 其中：处置固定资产净损失 | M42: 38 | Q42: 分配股利、利润和偿付利息所支付的现金 | R42: 38 | S42: 分配股利、利润和偿付利息所支付的现金 | V42: =V41+1 -> 38 | Z42: H4 | AA42: 固定资产清理
B43: 待处理固定资产净损失 | C43: 39 | D43: 工程物资 | E43: =IF(D43="",0,CONCATENATE("年初",D43)) -> 年初工程物资 | G43: 国家资本 | H43: =H42+1 -> 96 | I43: =IF(参数!D$8="股份有限公司","股本",IF(参数!D$8="一般企业（执行统一会计制度）","实收资本","")) -> 实收资本 | J43: =IF(I43="",0,CONCATENATE("年初",I43)) -> 年初实收资本 | L43: 出售无形资产损失 | M43: 39 | Q43: 支付的其他与筹资活动有关的现金 | R43: 39 | S43: 支付的其他与筹资活动有关的现金 | V43: =V42+1 -> 39 | Z43: H7 | AA43: 工程物资
C44: 40 | D44: 在建工程 | E44: =IF(D44="",0,CONCATENATE("年初",D44)) -> 年初在建工程 | G44: 集体资本 | H44: =H43+1 -> 97 | I44: 国家资本 | J44: =IF(I44="",0,CONCATENATE("年初",I44)) -> 年初国家资本 | L44: 罚款支出 | M44: 40 | R44: 40 | V44: =V43+1 -> 40 | Z44: H6 | AA44: 在建工程
C45: 41 | D45: 待处理固定资产净损失 | E45: =IF(D45="",0,CONCATENATE("年初",D45)) -> 年初待处理固定资产净损失 | G45: 法人资本 | H45: =H44+1 -> 98 | I45: 集体资本 | J45: =IF(I45="",0,CONCATENATE("年初",I45)) -> 年初集体资本 | L45: 捐赠支出 | M45: 41 | N45: 其他支出 | O45: =IF(N45="",0,CONCATENATE("上年",N45)) -> 上年其他支出 | R45: 41 | V45: =V44+1 -> 41 | Z45: H5 | AA45: 待处理固定资产净损失
B46: 固定资产合计 | C46: 42 | G46: 其中：国有法人资本 | H46: =H45+1 -> 99 | I46: 法人资本 | J46: =IF(I46="",0,CONCATENATE("年初",I46)) -> 年初法人资本 | L46: （二）其他支出 | M46: 42 | R46: 42 | V46: =V45+1 -> 42 | AA46: =B44 -> 0
B47: 无形资产及其他资产： | C47: 43 | E47: =IF(D47="",0,CONCATENATE("年初",D47)) -> 0 | G47: 集体法人资本 | H47: =H46+1 -> 100 | I47: 其中：国有法人资本 | L47: 其中：结转的含量工资包干结余 | M47: 43 | O47: =IF(N47="",0,CONCATENATE("上年",N47)) -> 0 | R47: 43 | V47: =V46+1 -> 43 | AA47: =B45 -> 0
B48: 无形资产 | C48: 44 | E48: =IF(D48="",0,CONCATENATE("年初",D48)) -> 0 | G48: 个人资本 | H48: =H47+1 -> 101 | I48: 集体法人资本 | L48: 五、利润总额 | M48: 44 | O48: =IF(N48="",0,CONCATENATE("上年",N48)) -> 0 | Q48: 现金流出小计 | R48: 44 | V48: =V47+1 -> 44 | AA48: 固定资产合计
B49: 其中：土地使用权 | C49: 45 | E49: =IF(D49="",0,CONCATENATE("年初",D49)) -> 0 | G49: 外商资本 | H49: =H48+1 -> 102 | I49: 个人资本 | J49: =IF(I49="",0,CONCATENATE("年初",I49)) -> 年初个人资本 | L49: 减：所得税 | M49: 45 | O49: =IF(N49="",0,CONCATENATE("上年",N49)) -> 0 | Q49: 筹资活动产生的现金流量净额 | R49: 45 | V49: =V48+1 -> 45 | AA49: 无形资产及其他资产：
B50: 长期待摊费用 | C50: 46 | D50: 无形资产 | E50: =IF(D50="",0,CONCATENATE("年初",D50)) -> 年初无形资产 | G50: 资本公积 | H50: =H49+1 -> 103 | I50: 外商资本 | J50: =IF(I50="",0,CONCATENATE("年初",I50)) -> 年初外商资本 | L50: *少数股东损益 | M50: 46 | N50: 所得税 | O50: =IF(N50="",0,CONCATENATE("上年",N50)) -> 上年所得税 | Q50: 四、汇率变动对现金的影响额 | R50: 46 | S50: 汇率变动对现金的影响额 | V50: =V49+1 -> 46 | Z50: I2 | AA50: =B48 -> 无形资产
B51: 其中：固定资产修理 | C51: 47 | D51: 其中：土地使用权 | G51: 盈余公积 | H51: =H50+1 -> 104 | I51: 资本公积 | J51: =IF(I51="",0,CONCATENATE("年初",I51)) -> 年初资本公积 | L51: 加：*未确认的投资损失 | M51: 47 | N51: 少数股东收益 | O51: =IF(N51="",0,CONCATENATE("上年",N51)) -> 上年少数股东收益 | Q51: 五、现金及现金等价物净增加额 | R51: 47 | U51: 现金及现金等价物净增加额 | V51: =V50+1 -> 47
B52: 固定资产改良支出 | C52: 48 | D52: 长期待摊费用 | E52: =IF(D52="",0,CONCATENATE("年初",D52)) -> 年初长期待摊费用 | G52: 其中：法定公益金 | H52: =H51+1 -> 105 | I52: 盈余公积━法定或任意公积 | J52: =IF(I52="",0,CONCATENATE("年初",I52)) -> 年初盈余公积━法定或任意公积 | L52: 六、净利润 | M52: 48 | R52: 48 | V52: =V51+1 -> 48 | Z52: I5 | AA52: =B50 -> 长期待摊费用
B53: 股权分置流通权 | C53: 49 | D53: 其中：固定资产修理 | G53: *未确认的投资损失（以“-”号填列） | H53: =H52+1 -> 106 | I53: 盈余公积━法定公益金 | J53: =IF(I53="",0,CONCATENATE("年初",I53)) -> 年初盈余公积━法定公益金 | L53: 加：（一）年初未分配利润 | M53: 49 | O53: =IF(N53="",0,CONCATENATE("上年",N53)) -> 0 | R53: 49 | V53: =V52+1 -> 49
B54: 其他长期资产 | C54: 50 | D54: 固定资产改良支出 | G54: 未分配利润 | H54: =H53+1 -> 107 | I54: 未确认的投资损失 | J54: =IF(I54="",0,CONCATENATE("年初",I54)) -> 年初未确认的投资损失 | L54: （二）盈余公积补亏 | M54: 50 | N54: 年初未分配利润 | O54: =IF(N54="",0,CONCATENATE("上年",N54)) -> 上年年初未分配利润 | R54: 50 | V54: =V53+1 -> 50
B55: 其中：特准储备物资 | C55: 51 | D55: 其他长期资产 | E55: =IF(D55="",0,CONCATENATE("年初",D55)) -> 年初其他长期资产 | G55: 其中：现金股利 | H55: =H54+1 -> 108 | I55: 未分配利润 | J55: =IF(I55="",0,CONCATENATE("年初",I55)) -> 年初未分配利润 | L55: （三）其他调整因素 | M55: 51 | N55: 盈余公积金转入数 | O55: =IF(N55="",0,CONCATENATE("上年",N55)) -> 上年盈余公积金转入数 | R55: 51 | V55: =V54+1 -> 51 | AA55: =B53 -> 股权分置流通权
C56: 52 | D56: 其中：特准储备物资 | G56: 外币报表折算差额 | H56: =H55+1 -> 109 | I56: 其中：现金股利 | L56: 七、可供分配的利润 | M56: 52 | O56: =IF(N56="",0,CONCATENATE("上年",N56)) -> 0 | R56: 52 | V56: =V55+1 -> 52 | AA56: =B54 -> 其他长期资产
B57: 无形资产及其他资产合计 | C57: 53 | H57: =H56+1 -> 110 | I57: 外币报表折算差额 | J57: =IF(I57="",0,CONCATENATE("年初",I57)) -> 年初外币报表折算差额 | L57: 减：（一）提取法定盈余公积 | M57: 53 | O57: =IF(N57="",0,CONCATENATE("上年",N57)) -> 0 | R57: 53 | V57: =V56+1 -> 53
B58: 递延税项： | C58: 54 | E58: =IF(D58="",0,CONCATENATE("年初",D58)) -> 0 | G58: =IF(参数!D$8="股份有限公司","股东权益小计",IF(参数!D$8="一般企业（执行统一会计制度）","所有者权益小计","")) -> 所有者权益小计 | H58: =H57+1 -> 111 | L58: （二）提取法定公益金 | M58: 54 | N58: 提取法定公积金 | O58: =IF(N58="",0,CONCATENATE("上年",N58)) -> 上年提取法定公积金 | R58: 54 | V58: =V57+1 -> 54 | AA58: =B56 -> 0
B59: 递延税款借项 | C59: 55 | E59: =IF(D59="",0,CONCATENATE("年初",D59)) -> 0 | G59: 减：未处理资产损失 | H59: =H58+1 -> 112 | L59: （三）提取职工奖励及福利基金 | M59: 55 | N59: 提取法定公益金 | O59: =IF(N59="",0,CONCATENATE("上年",N59)) -> 上年提取法定公益金 | R59: 55 | V59: =V58+1 -> 55 | AA59: 无形资产及其他资产合计
C60: 56 | E60: =IF(D60="",0,CONCATENATE("年初",D60)) -> 0 | G60: =IF(参数!D$8="股份有限公司","股东权益合计(剔除未处理资产损失后的金额)",IF(参数!D$8="一般企业（执行统一会计制度）","所有者权益合计(剔除未处理资产损失后的金额)","")) -> 所有者权益合计(剔除未处理资产损失后的金额) | H60: =H59+1 -> 113 | J60: =IF(I60="",0,CONCATENATE("年初",I60)) -> 0 | L60: （四）提取储备基金 | M60: 56 | N60: 提取职工福利及奖励金 | O60: =IF(N60="",0,CONCATENATE("上年",N60)) -> 上年提取职工福利及奖励金 | R60: 56 | V60: =V59+1 -> 56 | AA60: 递延税项：
C61: 57 | D61: 递延税款借项 | E61: =IF(D61="",0,CONCATENATE("年初",D61)) -> 年初递延税款借项 | H61: =H60+1 -> 114 | L61: （五）提取企业发展基金 | M61: 57 | N61: 提取储备基金 | O61: =IF(N61="",0,CONCATENATE("上年",N61)) -> 上年提取储备基金 | R61: 57 | V61: =V60+1 -> 57 | Z61: I18-1 | AA61: 递延税款借项
C62: 57 | H62: =H61 -> 114 | J62: =IF(I62="",0,CONCATENATE("年初",I62)) -> 0 | L62: （六）利润归还投资 | M62: 58 | N62: 提取企业发展基金 | O62: =IF(N62="",0,CONCATENATE("上年",N62)) -> 上年提取企业发展基金 | R62: 58 | V62: =V61+1 -> 58
C63: 57 | H63: =H62 -> 114 | L63: （七）补充流动资本 | M63: 59 | N63: 利润归还投资 | O63: =IF(N63="",0,CONCATENATE("上年",N63)) -> 上年利润归还投资 | R63: 59 | V63: =V62+1 -> 59 | AA63: 资产总计
C64: 57 | H64: =H63 -> 114 | L64: （八）单项留用的利润 | M64: 60 | N64: 补充流动资本 | O64: =IF(N64="",0,CONCATENATE("上年",N64)) -> 上年补充流动资本 | R64: 60 | V64: =V63+1 -> 60
C65: 57 | H65: =H64 -> 114 | L65: （九）其他 | M65: 61 | N65: 单项留用的利润 | O65: =IF(N65="",0,CONCATENATE("上年",N65)) -> 上年单项留用的利润 | R65: 61 | V65: =V64+1 -> 61 | AA65: 流动负债：
C66: 57 | H66: =H65 -> 114 | L66: 八、可供投资者分配的利润 | M66: 62 | N66: 其他 | O66: =IF(N66="",0,CONCATENATE("上年",N66)) -> 上年其他 | R66: 62 | V66: =V65+1 -> 62 | Z66: F11 | AA66: =G6 -> 短期借款
C67: 57 | H67: =H66 -> 114 | L67: 减：（一）应付优先股股利 | M67: 63 | O67: =IF(N67="",0,CONCATENATE("上年",N67)) -> 0 | R67: 63 | V67: =V66+1 -> 63 | Z67: E12 | AA67: =G7 -> 应付票据
C68: 57 | H68: =H67 -> 114 | L68: （二）提取任意盈余公积 | M68: 64 | N68: 应付优先股股利 | O68: =IF(N68="",0,CONCATENATE("上年",N68)) -> 上年应付优先股股利 | R68: 64 | V68: =V67+1 -> 64 | Z68: E11 | AA68: =G8 -> 应付账款
C69: 57 | H69: =H68 -> 114 | L69: （三）应付普通股股利（应付利润） | M69: 65 | N69: 提取任意盈余公积金 | O69: =IF(N69="",0,CONCATENATE("上年",N69)) -> 上年提取任意盈余公积金 | R69: 65 | V69: =V68+1 -> 65 | Z69: D11 | AA69: =G9 -> 预收账款
C70: 57 | H70: =H69 -> 114 | L70: （四）转作资本（股本）的普通股股利 | M70: 66 | N70: 应付普通股股利 | O70: =IF(N70="",0,CONCATENATE("上年",N70)) -> 上年应付普通股股利 | R70: 66 | V70: =V69+1 -> 66 | Z70: E16 | AA70: =G10 -> 应付工资
C71: 57 | H71: =H70 -> 114 | L71: （五）其他 | M71: 67 | N71: 转作资本的普通股股利 | O71: =IF(N71="",0,CONCATENATE("上年",N71)) -> 上年转作资本的普通股股利 | R71: 67 | V71: =V70+1 -> 67 | Z71: E17 | AA71: =G11 -> 应付福利费
C72: 57 | H72: =H71 -> 114 | L72: 九、未分配利润 | M72: 68 | N72: 其他 | O72: =IF(N72="",0,CONCATENATE("上年",N72)) -> 上年其他 | R72: 68 | V72: =V71+1 -> 68 | Z72: F15 | AA72: =G12 -> 应付股利（利润）
B73: 资 产 总 计 | C73: 57 | E73: =IF(D73="",0,CONCATENATE("年初",D73)) -> 0 | G73: =IF(参数!D8="股份有限公司","负债及股东权益合计",IF(参数!D8="一般企业（执行统一会计制度）","负债及所有者权益合计","")) -> 负债及所有者权益合计 | H73: =H72 -> 114 | L73: 其中：应由以后年度税前利润弥补的亏损（以“+”号填列） | M73: 69 | O73: =IF(N73="",0,CONCATENATE("上年",N73)) -> 0 | R73: 69 | V73: =V72+1 -> 69 | Z73: F14 | AA73: =G13 -> 应付利息
E74: =IF(D74="",0,CONCATENATE("年初",D74)) -> 0 | J74: =IF(I74="",0,CONCATENATE("年初",I74)) -> 0 | Z74: I16 | AA74: =G14 -> 应交税金
Z75: I17 | AA75: =G15 -> 其他应交款
Z76: G11 | AA76: =G16 -> 其他应付款
Z77: I11 | AA77: =G17 -> 预提费用
Z78: I19 | AA78: =G18 -> 预计负债
Z79: D12 | AA79: =G19 -> 递延收益
AA80: =G20 -> 一年内到期的长期负债
AA81: =G21 -> 应付权证
AA82: =G22 -> 其他流动负债
AA83: =G23 -> 0
AA84: =G24 -> 0
AA85: 流动负债合计
AA87: 长期负债：
Z88: F12 | AA88: =G27 -> 长期借款
Z89: F13 | AA89: =G28 -> 应付债券
Z90: G12 | AA90: =G29 -> 长期应付款
Z91: G13 | AA91: =G30 -> 专项应付款
AA92: =G31 -> 其他长期负债
AA94: =G33 -> 0
AA95: =G34 -> 0
AA96: 长期负债合计
AA98: 递延税项：
Z99: I18-2 | AA99: 递延税款贷项
AA101: 负债合计
AA103: 少数股东权益
AA105: 所有者权益：
Z106: F16 | AA106: =G42 -> 实收资本
...

Sheet 未审BS
A1: =IF(ABS(G55-未审PL!C73)<0.005,"","年初未分配利润勾稽有误！") | C1: =IF(ABS(H55-未审PL!D73)<0.005,"","年末未分配利润勾稽有误！") | F1: 索引号： | H1: 页次：
A2: 资产负债表
A3: =IF(ABS(C62-G62)<0.005,0,"年初数不平，差额为：") -> 0 | C3: =IF(ABS(C62-G62)<0.005,0,C62-G62) -> 0 | E3: =IF(ABS(D62-H62)<0.005,0,"年末数不平，差额为：") -> 0 | G3: =IF(ABS(D62-H62)<0.005," 财企01表",D62-H62) -> 财企01表
A4: =IF(报表格式!G41=""," 对不起，请到参数表中确定报表类型！",CONCATENATE(" 编制单位：",参数!D3)) -> 编制单位： | D4: =参数!$D$12 -> 39447 | G4: =CONCATENATE("金额单位：",参数!$D$13) -> 金额单位：人民币元
A5: 资 产 | B5: 行次 | C5: =参数!D11 -> 39082 | D5: =参数!D12 -> 39447 | E5: =IF(参数!D8="一般企业（执行统一会计制度）","负债及所有者权益","负债及股东权益") -> 负债及所有者权益 | F5: 行次 | G5: =C5 -> 39082 | H5: =D5 -> 39447
A6: =报表格式!B5 -> 流动资产： | B6: 1 | E6: =报表格式!G5 -> 流动负债： | F6: =B62+1 -> 58
A7: =报表格式!B6 -> 货币资金 | B7: 2 | E7: =报表格式!G6 -> 短期借款 | F7: =F6+1 -> 59
A8: =报表格式!B7 -> 短期投资 | B8: 3 | E8: =报表格式!G7 -> 应付票据 | F8: =F7+1 -> 60
A9: =报表格式!B8 -> 应收票据 | B9: 4 | E9: =报表格式!G8 -> 应付账款 | F9: =F8+1 -> 61
A10: =报表格式!B9 -> 应收股利 | B10: 5 | E10: =报表格式!G9 -> 预收账款 | F10: =F9+1 -> 62
A11: =报表格式!B10 -> 应收利息 | B11: 6 | E11: =报表格式!G10 -> 应付工资 | F11: =F10+1 -> 63
A12: =报表格式!B11 -> 应收账款 | B12: 7 | E12: =报表格式!G11 -> 应付福利费 | F12: =F11+1 -> 64
A13: =报表格式!B12 -> 其他应收款 | B13: 8 | E13: =报表格式!G12 -> 应付股利（利润） | F13: =F12+1 -> 65
A14: =报表格式!B13 -> 预付账款 | B14: 9 | E14: =报表格式!G13 -> 应付利息 | F14: =F13+1 -> 66
A15: =报表格式!B14 -> 期货保证金 | B15: 10 | E15: =报表格式!G14 -> 应交税金 | F15: =F14+1 -> 67
A16: =报表格式!B15 -> 应收补贴款 | B16: 11 | E16: =报表格式!G15 -> 其他应交款 | F16: =F15+1 -> 68
A17: =报表格式!B16 -> 应收出口退税 | B17: 12 | E17: =报表格式!G16 -> 其他应付款 | F17: =F16+1 -> 69
A18: =报表格式!B17 -> 存货 | B18: 13 | E18: =报表格式!G17 -> 预提费用 | F18: =F17+1 -> 70
... A25: =报表格式!B24 -> 0 | B25: 20 | E25: =报表格式!G24 -> 0 | F25: =F24+1 -> 77
A26: =报表格式!B25 -> 0 | B26: 21 | E26: =报表格式!G25 -> 流动负债合计 | F26: =F25+1 -> 78 | G26: =SUM(G7:G25) -> 0 | H26: =SUM(H7:H25) -> 0
A27: =报表格式!B26 -> 流动资产合计 | B27: 22 | C27: =SUM(C7:C26)-C19-C20 -> 0 | D27: =SUM(D7:D26)-D19-D20 -> 0 | E27: =报表格式!G26 -> 长期负债： | F27: =F26+1 -> 79
A28: =报表格式!B27 -> 长期投资 | B28: 23 | C28: =SUM(C29:C30) -> 0 | D28: =SUM(D29:D30) -> 0 | E28: =报表格式!G27 -> 长期借款 | F28: =F27+1 -> 80
A29: =报表格式!B28 -> 其中：长期股权投资 | B29: 24 | E29: =报表格式!G28 -> 应付债券 | F29: =F28+1 -> 81
A30: =报表格式!B29 -> 长期债权投资 | B30: 25 | E30: =报表格式!G29 -> 长期应付款 | F30: =F29+1 -> 82
A31: =报表格式!B30 -> *合并价差 | B31: 26 | E31: =报表格式!G30 -> 专项应付款 | F31: =F30+1 -> 83
A32: =报表格式!B31 -> 0 | B32: 27 | E32: =报表格式!G31 -> 其他长期负债 | F32: =F31+1 -> 84
A33: =报表格式!B32 -> 0 | B33: 28 | E33: =报表格式!G32 -> 其中：特准储备资金 | F33: =F32+1 -> 85
A34: =报表格式!B33 -> 长期投资合计 | B34: 29 | C34: =SUM(C28,C31:C33) -> 0 | D34: =SUM(D28,D31:D33) -> 0 | E34: =报表格式!G33 -> 0 | F34: =F33+1 -> 86
A35: =报表格式!B34 -> 固定资产： | B35: 30 | E35: =报表格式!G34 -> 0 | F35: =F34+1 -> 87
A36: =报表格式!B35 -> 固定资产原价 | B36: 31 | E36: =报表格式!G35 -> 长期负债合计 | F36: =F35+1 -> 88 | G36: =SUM(G28:G32,G34:G35) -> 0 | H36: =SUM(H28:H32,H34:H35) -> 0
A37: =报表格式!B36 -> 减：累计折旧 | B37: 32 | E37: =报表格式!G36 -> 递延税项： | F37: =F36+1 -> 89
A38: =报表格式!B37 -> 固定资产净值 | B38: 33 | C38: =C36-C37 -> 0 | D38: =D36-D37 -> 0 | E38: =报表格式!G37 -> 递延税款贷项 | F38: =F37+1 -> 90
A39: =报表格式!B38 -> 减：固定资产减值准备 | B39: 34 | E39: =报表格式!G38 -> 负 债 合 计 | F39: =F38+1 -> 91 | G39: =SUM(G26,G36,G38:G38) -> 0 | H39: =SUM(H26,H36,H38:H38) -> 0
A40: =报表格式!B39 -> 固定资产净额 | B40: 35 | C40: =C38-C39 -> 0 | D40: =D38-D39 -> 0 | E40: =报表格式!G39 -> *少数股东权益 | F40: =F39+1 -> 92
A41: =报表格式!B40 -> 工程物资 | B41: 36 | E41: =报表格式!G40 -> 0 | F41: =F40+1 -> 93
A42: =报表格式!B41 -> 在建工程 | B42: 37 | E42: =报表格式!G41 -> 所有者权益： | F42: =F41+1 -> 94
A43: =报表格式!B42 -> 固定资产清理 | B43: 38 | E43: =报表格式!G42 -> 实收资本 | F43: =F42+1 -> 95
A44: =报表格式!B43 -> 待处理固定资产净损失 | B44: 39 | E44: =报表格式!G43 -> 国家资本 | F44: =F43+1 -> 96
A45: =报表格式!B44 -> 0 | B45: 40 | E45: =报表格式!G44 -> 集体资本 | F45: =F44+1 -> 97
A46: =报表格式!B45 -> 0 | B46: 41 | E46: =报表格式!G45 -> 法人资本 | F46: =F45+1 -> 98
A47: =报表格式!B46 -> 固定资产合计 | B47: 42 | C47: =SUM(C40:C46) -> 0 | D47: =SUM(D40:D46) -> 0 | E47: =报表格式!G46 -> 其中：国有法人资本 | F47: =F46+1 -> 99
A48: =报表格式!B47 -> 无形资产及其他资产： | B48: 43 | E48: =报表格式!G47 -> 集体法人资本 | F48: =F47+1 -> 100
A49: =报表格式!B48 -> 无形资产 | B49: 44 | E49: =报表格式!G48 -> 个人资本 | F49: =F48+1 -> 101
A50: =报表格式!B49 -> 其中：土地使用权 | B50: 45 | E50: =报表格式!G49 -> 外商资本 | F50: =F49+1 -> 102
A51: =报表格式!B50 -> 长期待摊费用 | B51: 46 | E51: =报表格式!G50 -> 资本公积 | F51: =F50+1 -> 103
A52: =报表格式!B51 -> 其中：固定资产修理 | B52: 47 | E52: =报表格式!G51 -> 盈余公积 | F52: =F51+1 -> 104
A53: =报表格式!B52 -> 固定资产改良支出 | B53: 48 | E53: =报表格式!G52 -> 其中：法定公益金 | F53: =F52+1 -> 105
A54: =报表格式!B53 -> 股权分置流通权 | B54: 49 | E54: =报表格式!G53 -> *未确认的投资损失（以“-”号填列） | F54: =F53+1 -> 106
A55: =报表格式!B54 -> 其他长期资产 | B55: 50 | E55: =报表格式!G54 -> 未分配利润 | F55: =F54+1 -> 107
A56: =报表格式!B55 -> 其中：特准储备物资 | B56: 51 | E56: =报表格式!G55 -> 其中：现金股利 | F56: =F55+1 -> 108
A57: =报表格式!B56 -> 0 | B57: 52 | E57: =报表格式!G56 -> 外币报表折算差额 | F57: =F56+1 -> 109
A58: =报表格式!B57 -> 无形资产及其他资产合计 | B58: 53 | C58: =SUM(C49,C51,C54:C55,C57) -> 0 | D58: =SUM(D49,D51,D54:D55,D57) -> 0 | E58: =报表格式!G57 -> 0 | F58: =F57+1 -> 110
A59: =报表格式!B58 -> 递延税项： | B59: 54 | E59: =报表格式!G58 -> 所有者权益小计 | F59: =F58+1 -> 111 | G59: =SUM(G43,G51,G52,G54,G55,G57:G58) -> 0 | H59: =SUM(H43,H51,H52,H54,H55,H57:H58) -> 0
A60: =报表格式!B59 -> 递延税款借项 | B60: 55 | E60: =报表格式!G59 -> 减：未处理资产损失 | F60: =F59+1 -> 112
A61: =报表格式!B60 -> 0 | B61: 56 | E61: =报表格式!G60 -> 所有者权益合计(剔除未处理资产损失后的金额) | F61: =F60+1 -> 113 | G61: =G59-G60 -> 0 | H61: =H59-H60 -> 0
A62: =报表格式!B73 -> 资 产 总 计 | B62: 57 | C62: =C27+C34+C47+C58+C60+C61 -> 0 | D62: =D27+D34+D47+D58+D60+D61 -> 0 | E62: =报表格式!G73 -> 负债及所有者权益合计 | F62: =F61+1 -> 114 | G62: =G39+G40+G41+G61 -> 0 | H62: =H39+H40+H41+H61 -> 0
A63: =CONCATENATE(参数!C4,参数!D4) -> 法定代表人： | D63: =CONCATENATE(参数!C5,参数!D5) -> 财务负责人： | F63: =CONCATENATE(参数!C6,参数!D6) -> 会计主管：
A65: BS平衡 | C65: =C62-G62 -> 0 | D65: =D62-H62 -> 0 | E65: BS/PL未分配利润平衡 | G65: =G55-未审PL!C73 -> 0 | H65: =H55-未审PL!D73 -> 0
E66: 两年未分配利润勾稽 | G66: =未审PL!C73-未审PL!D54 -> 0

Sheet 未审PL
A1: =IF(ABS(C73-D54)<0.005,"","年初未分配利润勾稽有误！") | D1: 索引号： 页次：
A2: 利润表及利润分配表
A3: =IF(ABS(C73-未审BS!G55)<0.005,IF(ABS(D73-未审BS!H55)<0.005,0,"“未分配利润”栏与资产负债表不平,差额为:"),"“未分配利润”栏与资产负债表不平,差额为:") -> 0 | C3: =IF(ABS(C73-未审BS!G55)<0.005,0,C73-未审BS!G55) -> 0 | D3: =IF(ABS(D73-未审BS!H55)<0.005," 财企02表",D73-未审BS!H55) -> 财企02表
A4: =IF(报表格式!G41=""," 对不起，请到参数表中确定报表类型！",CONCATENATE(" 编制单位：",参数!D3)) -> 编制单位： | B4: =参数!$D$10 -> 2007年度 | D4: =CONCATENATE("金额单位：",参数!$D$13) -> 金额单位：人民币元
A5: 项 目 | B5: 行次 | C5: =参数!D9 -> 2006年度 | D5: =参数!D10 -> 2007年度
A6: =报表格式!L5 -> 一、主营业务收入 | B6: 1
A7: =报表格式!L6 -> 其中：进口产品（商品）销售收入 | B7: 2
A8: =报表格式!L7 -> 出口产品（商品）销售收入 | B8: 3
A9: =报表格式!L8 -> 减：折扣与折让 | B9: 4
A10: =报表格式!L9 -> 二、主营业务收入净额 | B10: 5 | C10: =C6-C9 -> 0 | D10: =D6-D9 -> 0
A11: =报表格式!L10 -> 减：（一）主营业务成本 | B11: 6
A12: =报表格式!L11 -> 其中：出口产品（商品）销售成本 | B12: 7
A13: =报表格式!L12 -> （二）主营业务税金及附加 | B13: 8
A14: =报表格式!L13 -> （三）经营费用 | B14: 9
A15: =报表格式!L14 -> （四）其他 | B15: 10
A16: =报表格式!L15 -> 加：（一）递延收益 | B16: 11
A17: =报表格式!L16 -> （二）代购代销收入 | B17: 12
A18: =报表格式!L17 -> （三）其他 | B18: 13
A19: =报表格式!L18 -> 三、主营业务利润 | B19: 14 | C19: =C10-C11-C13-C14-C15+C16+C17+C18 -> 0 | D19: =D10-D11-D13-D14-D15+D16+D17+D18 -> 0
A20: =报表格式!L19 -> 加：其他业务利润 | B20: 15
A21: =报表格式!L20 -> 减：（一）营业费用 | B21: 16
A22: =报表格式!L21 -> （二）管理费用 | B22: 17
A23: =报表格式!L22 -> 其中：业务招待费 | B23: 18
A24: =报表格式!L23 -> 研究与开发费 | B24: 19
A25: =报表格式!L24 -> （三）财务费用 | B25: 20
A26: =报表格式!L25 -> 其中：利息支出 | B26: 21
A27: =报表格式!L26 -> 利息收入 | B27: 22
A28: =报表格式!L27 -> 汇兑净损失 | B28: 23
A29: =报表格式!L28 -> （四）其他 | B29: 24
A30: =报表格式!L29 -> 四、营业利润 | B30: 25 | C30: =C19+C20-C21-C22-C25-C29 -> 0 | D30: =D19+D20-D21-D22-D25-D29 -> 0
A31: =报表格式!L30 -> 加：（一）投资收益 | B31: 26
A32: =报表格式!L31 -> （二）期货收益 | B32: 27
A33: =报表格式!L32 -> （三）补贴收入 | B33: 28
A34: =报表格式!L33 -> 其中：补贴前亏损的企业补贴收入 | B34: 29
A35: =报表格式!L34 -> （四）营业外收入 | B35: 30
A36: =报表格式!L35 -> 其中：处置固定资产净收益 | B36: 31
A37: =报表格式!L36 -> 非货币性交易收益 | B37: 32
A38: =报表格式!L37 -> 出售无形资产收益 | B38: 33
A39: =报表格式!L38 -> 罚款净收入 | B39: 34
A40: =报表格式!L39 -> （五）其他 | B40: 35
A41: =报表格式!L40 -> 其中：用以前年度含量工资结余弥补利润 | B41: 36
A42: =报表格式!L41 -> 减：（一）营业外支出 | B42: 37
... A48: =报表格式!L47 -> 其中：结转的含量工资包干结余 | B48: 43
A49: =报表格式!L48 -> 五、利润总额 | B49: 44 | C49: =C30+C31+C32+C33+C35+C40-C42-C47 -> 0 | D49: =D30+D31+D32+D33+D35+D40-D42-D47 -> 0
A50: =报表格式!L49 -> 减：所得税 | B50: 45
A51: =报表格式!L50 -> *少数股东损益 | B51: 46
A52: =报表格式!L51 -> 加：*未确认的投资损失 | B52: 47
A53: =报表格式!L52 -> 六、净利润 | B53: 48 | C53: =C49-C50-C51+C52 -> 0 | D53: =D49-D50-D51+D52 -> 0
A54: =报表格式!L53 -> 加：（一）年初未分配利润 | B54: 49
A55: =报表格式!L54 -> （二）盈余公积补亏 | B55: 50
A56: =报表格式!L55 -> （三）其他调整因素 | B56: 51
A57: =报表格式!L56 -> 七、可供分配的利润 | B57: 52 | C57: =C53+C54+C55+C56 -> 0 | D57: =D53+D54+D55+D56 -> 0
A58: =报表格式!L57 -> 减：（一）提取法定盈余公积 | B58: 53
A59: =报表格式!L58 -> （二）提取法定公益金 | B59: 54
A60: =报表格式!L59 -> （三）提取职工奖励及福利基金 | B60: 55
A61: =报表格式!L60 -> （四）提取储备基金 | B61: 56
A62: =报表格式!L61 -> （五）提取企业发展基金 | B62: 57
A63: =报表格式!L62 -> （六）利润归还投资 | B63: 58
A64: =报表格式!L63 -> （七）补充流动资本 | B64: 59
A65: =报表格式!L64 -> （八）单项留用的利润 | B65: 60
A66: =报表格式!L65 -> （九）其他 | B66: 61
A67: =报表格式!L66 -> 八、可供投资者分配的利润 | B67: 62 | C67: =C57-C58-C59-C60-C61-C62-C63-C64-C65-C66 -> 0 | D67: =D57-D58-D59-D60-D61-D62-D63-D64-D65-D66 -> 0
A68: =报表格式!L67 -> 减：（一）应付优先股股利 | B68: 63
A69: =报表格式!L68 -> （二）提取任意盈余公积 | B69: 64
A70: =报表格式!L69 -> （三）应付普通股股利（应付利润） | B70: 65
A71: =报表格式!L70 -> （四）转作资本（股本）的普通股股利 | B71: 66
A72: =报表格式!L71 -> （五）其他 | B72: 67
A73: =报表格式!L72 -> 九、未分配利润 | B73: 68 | C73: =C67-C68-C69-C70-C71-C72 -> 0 | D73: =D67-D68-D69-D70-D71-D72 -> 0
A74: =报表格式!L73 -> 其中：应由以后年度税前利润弥补的亏损（以“+”号填列） | B74: 69
A75: =CONCATENATE(参数!C4,参数!D4," ",参数!C5,参数!D5) -> 法定代表人： 财务负责人： | D75: =CONCATENATE(参数!C6,参数!D6) -> 会计主管：

Sheet 未审CF
A1: =IF(AND(ABS(C18-F27)<0.005,ABS(C47-F47)<0.005),"","未审现金流量表不平！") | D1: 索引号： | F1: 页次：
A2: 现 金 流 量 表
A3: =IF(ABS(C18-F27)<0.005,0,"“经营活动产生的现金流量”左右不平，差额为:") -> 0 | C3: =IF(ABS(C18-F27)<0.005,0,C18-F27) -> 0 | D3: =IF(ABS(C47-F47)<0.005,0,"“现金及现金等价物净增加额”左右不平，差额为：") -> 0 | F3: =IF(ABS(C47-F47)<0.005," 财企03表",C47-F47) -> 财企03表
A4: =IF(报表格式!G41=""," 对不起，请到参数表中确定报表类型！",CONCATENATE(" 编制单位：",参数!D3)) -> 编制单位： | C4: =参数!$D$10 -> 2007年度 | E4: =CONCATENATE("金额单位：",参数!$D$13) -> 金额单位：人民币元
A5: 报 表 项 目 | B5: 行次 | C5: 金 额 | D5: 补 充 资 料 | E5: 行次 | F5: 金 额
A6: =报表格式!Q5 -> 一、经营活动产生的现金流量 | B6: 1 | D6: =报表格式!U5 -> 1、将净利润调节为经营活动现金流量 | E6: 1
A7: =报表格式!Q6 -> 销售商品、提供劳务收到的现金 | B7: 2 | D7: =报表格式!U6 -> 净利润 | E7: 2 | F7: =未审PL!D53 -> 0
A8: =报表格式!Q7 -> 收到的税费返还 | B8: 3 | D8: =报表格式!U7 -> 加：*少数股东损益 | E8: 3
A9: =报表格式!Q8 -> 收到的其他与经营活动有关的现金 | B9: 4 | D9: =报表格式!U8 -> 减：*未确认的投资损失 | E9: 4
A10: =报表格式!Q9 -> 0 | B10: 5 | D10: =报表格式!U9 -> 加：计提的资产减值准备 | E10: 5
A11: =报表格式!Q10 -> 现金流入小计 | B11: 6 | C11: =SUM(C7:C10) -> 0 | D11: =报表格式!U10 -> 固定资产折旧 | E11: 6
A12: =报表格式!Q11 -> 购买商品、接受劳务支付的现金 | B12: 7 | D12: =报表格式!U11 -> 无形资产摊销 | E12: 7
A13: =报表格式!Q12 -> 支付给职工以及为职工支付的现金 | B13: 8 | D13: =报表格式!U12 -> 长期待摊费用摊销 | E13: 8
A14: =报表格式!Q13 -> 支付各项税费 | B14: 9 | D14: =报表格式!U13 -> 待摊费用的减少（减：增加） | E14: 9
A15: =报表格式!Q14 -> 支付的其他与经营活动有关的现金 | B15: 10 | D15: =报表格式!U14 -> 预提费用的增加（减：减少） | E15: 10
A16: =报表格式!Q15 -> 0 | B16: 11 | D16: =报表格式!U15 -> 处置固定资产、无形资产和其他长期资产的损失（减：收益） | E16: 11
A17: =报表格式!Q18 -> 现金流出小计 | B17: 12 | C17: =SUM(C12:C16) -> 0 | D17: =报表格式!U16 -> 固定资产报废损失 | E17: 12
A18: =报表格式!Q19 -> 经营活动产生的现金流量净额 | B18: 13 | C18: =C11-C17 -> 0 | D18: =报表格式!U17 -> 财务费用 | E18: 13
A19: =报表格式!Q20 -> 二、投资活动产生的现金流量 | B19: 14 | D19: =报表格式!U18 -> 投资损失（减：收益） | E19: 14
A20: =报表格式!Q21 -> 收回投资所收到的现金 | B20: 15 | D20: =报表格式!U19 -> 递延税款贷项（减：借项） | E20: 15
A21: =报表格式!Q22 -> 其中：出售子公司所收到的现金 | B21: 16 | D21: =报表格式!U20 -> 存货的减少（减：增加） | E21: 16
A22: =报表格式!Q23 -> 取得投资收益所收到的现金 | B22: 17 | D22: =报表格式!U21 -> 经营性应收项目的减少（减：增加） | E22: 17
A23: =报表格式!Q24 -> 处置固定资产、无形资产和其他长期资产所收回的现金净额 | B23: 18 | D23: =报表格式!U22 -> 经营性应付项目的增加（减：减少） | E23: 18
A24: =报表格式!Q25 -> 收到的其他与投资活动有关的现金 | B24: 19 | D24: =报表格式!U23 -> 其他 | E24: 19
A25: =报表格式!Q26 -> 0 | B25: 20 | D25: =报表格式!U24 -> 0 | E25: 20
A26: =报表格式!Q27 -> 现金流入小计 | B26: 21 | C26: =SUM(C20:C25)-C21 -> 0 | D26: =报表格式!U25 -> 0 | E26: 21
A27: =报表格式!Q28 -> 购置固定资产、无形资产和其他长期资产所支付的现金 | B27: 22 | D27: =报表格式!U26 -> 经营活动产生的现金流量净额 | E27: 22 | F27: =SUM(F7:F8,F10:F26)-F9 -> 0
A28: =报表格式!Q29 -> 投资所支付的现金 | B28: 23 | D28: =IF(报表格式!U27="","",报表格式!U27) | E28: 23
A29: =报表格式!Q30 -> 其中：购买子公司所支付的现金 | B29: 24 | D29: =报表格式!U28 -> 2、不涉及现金收支的投资和筹资活动 | E29: 24
A30: =报表格式!Q31 -> 支付的其他与投资活动有关的现金 | B30: 25 | D30: =报表格式!U29 -> 债务转为资本 | E30: 25
A31: =报表格式!Q32 -> 0 | B31: 26 | D31: =报表格式!U30 -> 一年内到期的可转换公司债券 | E31: 26
A32: =报表格式!Q33 -> 现金流出小计 | B32: 27 | C32: =SUM(C27:C31)-C29 -> 0 | D32: =报表格式!U31 -> 融资租入固定资产 | E32: 27
A33: =报表格式!Q34 -> 投资活动产生的现金流量净额 | B33: 28 | C33: =C26-C32 -> 0 | D33: =报表格式!U32 -> 其他 | E33: 28
A34: =报表格式!Q35 -> 三、筹资活动产生的现金流量 | B34: 29 | D34: =报表格式!U33 -> 0 | E34: 29
A35: =报表格式!Q36 -> 吸收投资所收到的现金 | B35: 30 | D35: =报表格式!U34 -> 3、现金及现金等价物净增加情况 | E35: 30
A36: =报表格式!Q37 -> 取得借款所收到的现金 | B36: 31 | D36: =报表格式!U35 -> 现金的期末余额 | E36: 31 | F36: =未审BS!D7 -> 0
A37: =报表格式!Q38 -> 收到的其他与筹资活动有关的现金 | B37: 32 | D37: =报表格式!U36 -> 减：现金的期初余额 | E37: 32 | F37: =未审BS!C7 -> 0
A38: =报表格式!Q39 -> 0 | B38: 33 | D38: =报表格式!U37 -> 加：现金等价物的期末余额 | E38: 33
A39: =报表格式!Q40 -> 现金流入小计 | B39: 34 | C39: =SUM(C35:C38) -> 0 | D39: =报表格式!U38 -> 减：现金等价物的期初余额 | E39: 34
A40: =报表格式!Q41 -> 偿还债务所支付的现金 | B40: 35 | D40: =IF(报表格式!U39="","",报表格式!U39) | E40: 35
A41: =报表格式!Q42 -> 分配股利、利润和偿付利息所支付的现金 | B41: 36 | D41: =IF(报表格式!U40="","",报表格式!U40) | E41: 36
A42: =报表格式!Q43 -> 支付的其他与筹资活动有关的现金 | B42: 37 | D42: =IF(报表格式!U41="","",报表格式!U41) | E42: 37
A43: =报表格式!Q44 -> 0 | B43: 38 | D43: =IF(报表格式!U42="","",报表格式!U42) | E43: 38
A44: =报表格式!Q48 -> 现金流出小计 | B44: 39 | C44: =SUM(C40:C43) -> 0 | D44: =IF(报表格式!U47="","",报表格式!U47) | E44: 39
A45: =报表格式!Q49 -> 筹资活动产生的现金流量净额 | B45: 40 | C45: =C39-C44 -> 0 | E45: 40
A46: =报表格式!Q50 -> 四、汇率变动对现金的影响额 | B46: 41 | D46: =IF(报表格式!U48="","",报表格式!U48) | E46: 41
A47: =报表格式!Q51 -> 五、现金及现金等价物净增加额 | B47: 42 | C47: =C18+C33+C45+C46 -> 0 | D47: =报表格式!U51 -> 现金及现金等价物净增加额 | E47: 42 | F47: =F36-F37+F38-F39 -> 0
A49: =CONCATENATE(参数!C4,参数!D4) -> 法定代表人： | C49: =CONCATENATE(参数!C5,参数!D5) -> 财务负责人： | E49: =CONCATENATE(参数!C6,参数!D6) -> 会计主管：
A51: Ope.CashFlow | C51: =C18-F27 -> 0 | D51: 期初现金勾稽 | F51: =F37-未审BS!C7 -> 0
A52: Net CashFlow | C52: =C47-F47 -> 0 | D52: 期末现金勾稽 | F52: =F36-未审BS!D7 -> 0

Sheet 期初核对BS
A1: =IF(AND(ABS(F62)<0.005,ABS(L62)<0.005),"期初金额核对一致","期初金额核对不符！") -> 期初金额核对一致
A2: 资产负债表期初核对
A4: =IF(报表格式!G41=""," 对不起，请到参数表中确定报表类型！",CONCATENATE(" 客户名称：",参数!D3)) -> 客户名称： | D4: =参数!$D$12 -> 39447 | J4: =CONCATENATE("金额单位：",参数!$D$13) -> 金额单位：人民币元
A5: =IF(E62<=0.005,"资 产","资产明细核对不符！") -> 资 产 | B5: 行次 | C5: 上期审定数 ① | D5: 本年期初数 ② | E5: 辅助列 | F5: 差异 ①-② | G5: =IF(K62<=0.005,IF(参数!D8="一般企业（执行统一会计制度）","负债及所有者权益","负债及股东权益"),"负债明细核对不符！") -> 负债及所有者权益 | H5: 行次 | I5: 上期审定数 ① | J5: 本年期初数 ② | K5: 辅助列 | L5: 差异 ①-②
A6: =报表格式!B5 -> 流动资产： | B6: 1 | G6: =报表格式!G5 -> 流动负债： | H6: =B62+1 -> 58
A7: =报表格式!B6 -> 货币资金 | B7: 2 | D7: =未审BS!C7 -> 0 | E7: =ABS(F7) -> 0 | F7: =C7-D7 -> 0 | G7: =报表格式!G6 -> 短期借款 | H7: =H6+1 -> 59 | J7: =未审BS!G7 -> 0 | K7: =ABS(L7) -> 0 | L7: =I7-J7 -> 0
A8: =报表格式!B7 -> 短期投资 | B8: 3 | D8: =未审BS!C8 -> 0 | E8: =ABS(F8) -> 0 | F8: =C8-D8 -> 0 | G8: =报表格式!G7 -> 应付票据 | H8: =H7+1 -> 60 | J8: =未审BS!G8 -> 0 | K8: =ABS(L8) -> 0 | L8: =I8-J8 -> 0
A9: =报表格式!B8 -> 应收票据 | B9: 4 | D9: =未审BS!C9 -> 0 | E9: =ABS(F9) -> 0 | F9: =C9-D9 -> 0 | G9: =报表格式!G8 -> 应付账款 | H9: =H8+1 -> 61 | J9: =未审BS!G9 -> 0 | K9: =ABS(L9) -> 0 | L9: =I9-J9 -> 0
A10: =报表格式!B9 -> 应收股利 | B10: 5 | D10: =未审BS!C10 -> 0 | E10: =ABS(F10) -> 0 | F10: =C10-D10 -> 0 | G10: =报表格式!G9 -> 预收账款 | H10: =H9+1 -> 62 | J10: =未审BS!G10 -> 0 | K10: =ABS(L10) -> 0 | L10: =I10-J10 -> 0
A11: =报表格式!B10 -> 应收利息 | B11: 6 | D11: =未审BS!C11 -> 0 | E11: =ABS(F11) -> 0 | F11: =C11-D11 -> 0 | G11: =报表格式!G10 -> 应付工资 | H11: =H10+1 -> 63 | J11: =未审BS!G11 -> 0 | K11: =ABS(L11) -> 0 | L11: =I11-J11 -> 0
A12: =报表格式!B11 -> 应收账款 | B12: 7 | D12: =未审BS!C12 -> 0 | E12: =ABS(F12) -> 0 | F12: =C12-D12 -> 0 | G12: =报表格式!G11 -> 应付福利费 | H12: =H11+1 -> 64 | J12: =未审BS!G12 -> 0 | K12: =ABS(L12) -> 0 | L12: =I12-J12 -> 0
A13: =报表格式!B12 -> 其他应收款 | B13: 8 | D13: =未审BS!C13 -> 0 | E13: =ABS(F13) -> 0 | F13: =C13-D13 -> 0 | G13: =报表格式!G12 -> 应付股利（利润） | H13: =H12+1 -> 65 | J13: =未审BS!G13 -> 0 | K13: =ABS(L13) -> 0 | L13: =I13-J13 -> 0
A14: =报表格式!B13 -> 预付账款 | B14: 9 | D14: =未审BS!C14 -> 0 | E14: =ABS(F14) -> 0 | F14: =C14-D14 -> 0 | G14: =报表格式!G13 -> 应付利息 | H14: =H13+1 -> 66 | J14: =未审BS!G14 -> 0 | K14: =ABS(L14) -> 0 | L14: =I14-J14 -> 0
A15: =报表格式!B14 -> 期货保证金 | B15: 10 | D15: =未审BS!C15 -> 0 | E15: =ABS(F15) -> 0 | F15: =C15-D15 -> 0 | G15: =报表格式!G14 -> 应交税金 | H15: =H14+1 -> 67 | J15: =未审BS!G15 -> 0 | K15: =ABS(L15) -> 0 | L15: =I15-J15 -> 0
A16: =报表格式!B15 -> 应收补贴款 | B16: 11 | D16: =未审BS!C16 -> 0 | E16: =ABS(F16) -> 0 | F16: =C16-D16 -> 0 | G16: =报表格式!G15 -> 其他应交款 | H16: =H15+1 -> 68 | J16: =未审BS!G16 -> 0 | K16: =ABS(L16) -> 0 | L16: =I16-J16 -> 0
A17: =报表格式!B16 -> 应收出口退税 | B17: 12 | D17: =未审BS!C17 -> 0 | E17: =ABS(F17) -> 0 | F17: =C17-D17 -> 0 | G17: =报表格式!G16 -> 其他应付款 | H17: =H16+1 -> 69 | J17: =未审BS!G17 -> 0 | K17: =ABS(L17) -> 0 | L17: =I17-J17 -> 0
A18: =报表格式!B17 -> 存货 | B18: 13 | D18: =未审BS!C18 -> 0 | E18: =ABS(F18) -> 0 | F18: =C18-D18 -> 0 | G18: =报表格式!G17 -> 预提费用 | H18: =H17+1 -> 70 | J18: =未审BS!G18 -> 0 | K18: =ABS(L18) -> 0 | L18: =I18-J18 -> 0
... A25: =报表格式!B24 -> 0 | B25: 20 | D25: =未审BS!C25 -> 0 | E25: =ABS(F25) -> 0 | F25: =C25-D25 -> 0 | G25: =报表格式!G24 -> 0 | H25: =H24+1 -> 77 | J25: =未审BS!G25 -> 0 | K25: =ABS(L25) -> 0 | L25: =I25-J25 -> 0
A26: =报表格式!B25 -> 0 | B26: 21 | D26: =未审BS!C26 -> 0 | E26: =ABS(F26) -> 0 | F26: =C26-D26 -> 0 | G26: =报表格式!G25 -> 流动负债合计 | H26: =H25+1 -> 78 | I26: =SUM(I7:I25) -> 0 | J26: =SUM(J7:J25) -> 0 | K26: =SUM(K7:K25) -> 0 | L26: =I26-J26 -> 0
A27: =报表格式!B26 -> 流动资产合计 | B27: 22 | C27: =SUM(C7:C26)-C19-C20 -> 0 | D27: =SUM(D7:D26)-D19-D20 -> 0 | E27: =SUM(E7:E26)-E19-E20 -> 0 | F27: =C27-D27 -> 0 | G27: =报表格式!G26 -> 长期负债： | H27: =H26+1 -> 79 | K27: =ABS(L27) -> 0
A28: =报表格式!B27 -> 长期投资 | B28: 23 | C28: =SUM(C29:C30) -> 0 | D28: =SUM(D29:D30) -> 0 | E28: =ABS(F28) -> 0 | F28: =C28-D28 -> 0 | G28: =报表格式!G27 -> 长期借款 | H28: =H27+1 -> 80 | J28: =未审BS!G28 -> 0 | K28: =ABS(L28) -> 0 | L28: =I28-J28 -> 0
A29: =报表格式!B28 -> 其中：长期股权投资 | B29: 24 | D29: =未审BS!C29 -> 0 | E29: =ABS(F29) -> 0 | F29: =C29-D29 -> 0 | G29: =报表格式!G28 -> 应付债券 | H29: =H28+1 -> 81 | J29: =未审BS!G29 -> 0 | K29: =ABS(L29) -> 0 | L29: =I29-J29 -> 0
A30: =报表格式!B29 -> 长期债权投资 | B30: 25 | D30: =未审BS!C30 -> 0 | E30: =ABS(F30) -> 0 | F30: =C30-D30 -> 0 | G30: =报表格式!G29 -> 长期应付款 | H30: =H29+1 -> 82 | J30: =未审BS!G30 -> 0 | K30: =ABS(L30) -> 0 | L30: =I30-J30 -> 0
A31: =报表格式!B30 -> *合并价差 | B31: 26 | D31: =未审BS!C31 -> 0 | E31: =ABS(F31) -> 0 | F31: =C31-D31 -> 0 | G31: =报表格式!G30 -> 专项应付款 | H31: =H30+1 -> 83 | J31: =未审BS!G31 -> 0 | K31: =ABS(L31) -> 0 | L31: =I31-J31 -> 0
A32: =报表格式!B31 -> 0 | B32: 27 | D32: =未审BS!C32 -> 0 | E32: =ABS(F32) -> 0 | F32: =C32-D32 -> 0 | G32: =报表格式!G31 -> 其他长期负债 | H32: =H31+1 -> 84 | J32: =未审BS!G32 -> 0 | K32: =ABS(L32) -> 0 | L32: =I32-J32 -> 0
A33: =报表格式!B32 -> 0 | B33: 28 | D33: =未审BS!C33 -> 0 | E33: =ABS(F33) -> 0 | F33: =C33-D33 -> 0 | G33: =报表格式!G32 -> 其中：特准储备资金 | H33: =H32+1 -> 85 | J33: =未审BS!G33 -> 0 | K33: =ABS(L33) -> 0 | L33: =I33-J33 -> 0
A34: =报表格式!B33 -> 长期投资合计 | B34: 29 | C34: =SUM(C28,C31:C33) -> 0 | D34: =SUM(D28,D31:D33) -> 0 | E34: =SUM(E29:E33) -> 0 | F34: =C34-D34 -> 0 | G34: =报表格式!G33 -> 0 | H34: =H33+1 -> 86 | J34: =未审BS!G34 -> 0 | K34: =ABS(L34) -> 0 | L34: =I34-J34 -> 0
A35: =报表格式!B34 -> 固定资产： | B35: 30 | E35: =ABS(F35) -> 0 | G35: =报表格式!G34 -> 0 | H35: =H34+1 -> 87 | J35: =未审BS!G35 -> 0 | K35: =ABS(L35) -> 0 | L35: =I35-J35 -> 0
A36: =报表格式!B35 -> 固定资产原价 | B36: 31 | D36: =未审BS!C36 -> 0 | E36: =ABS(F36) -> 0 | F36: =C36-D36 -> 0 | G36: =报表格式!G35 -> 长期负债合计 | H36: =H35+1 -> 88 | I36: =SUM(I28:I33)-I33+SUM(I34:I35) -> 0 | J36: =SUM(J28:J33)-J33+SUM(J34:J35) -> 0 | K36: =SUM(K28:K33)-K33+SUM(K34:K35) -> 0 | L36: =I36-J36 -> 0
A37: =报表格式!B36 -> 减：累计折旧 | B37: 32 | D37: =未审BS!C37 -> 0 | E37: =ABS(F37) -> 0 | F37: =C37-D37 -> 0 | G37: =报表格式!G36 -> 递延税项： | H37: =H36+1 -> 89 | K37: =ABS(L37) -> 0
A38: =报表格式!B37 -> 固定资产净值 | B38: 33 | C38: =C36-C37 -> 0 | D38: =D36-D37 -> 0 | E38: =ABS(F38) -> 0 | F38: =C38-D38 -> 0 | G38: =报表格式!G37 -> 递延税款贷项 | H38: =H37+1 -> 90 | J38: =未审BS!G38 -> 0 | K38: =ABS(L38) -> 0 | L38: =I38-J38 -> 0
A39: =报表格式!B38 -> 减：固定资产减值准备 | B39: 34 | D39: =未审BS!C39 -> 0 | E39: =ABS(F39) -> 0 | F39: =C39-D39 -> 0 | G39: =报表格式!G38 -> 负 债 合 计 | H39: =H38+1 -> 91 | I39: =I26+I36+I38 -> 0 | J39: =J26+J36+J38 -> 0 | K39: =K26+K36+K38 -> 0 | L39: =I39-J39 -> 0
A40: =报表格式!B39 -> 固定资产净额 | B40: 35 | C40: =C38-C39 -> 0 | D40: =D38-D39 -> 0 | E40: =ABS(F40) -> 0 | F40: =C40-D40 -> 0 | G40: =报表格式!G39 -> *少数股东权益 | H40: =H39+1 -> 92 | J40: =未审BS!G40 -> 0 | K40: =ABS(L40) -> 0 | L40: =I40-J40 -> 0
A41: =报表格式!B40 -> 工程物资 | B41: 36 | D41: =未审BS!C41 -> 0 | E41: =ABS(F41) -> 0 | F41: =C41-D41 -> 0 | G41: =报表格式!G40 -> 0 | H41: =H40+1 -> 93 | K41: =ABS(L41) -> 0 | L41: =I41-J41 -> 0
A42: =报表格式!B41 -> 在建工程 | B42: 37 | D42: =未审BS!C42 -> 0 | E42: =ABS(F42) -> 0 | F42: =C42-D42 -> 0 | G42: =报表格式!G41 -> 所有者权益： | H42: =H41+1 -> 94 | K42: =ABS(L42) -> 0
A43: =报表格式!B42 -> 固定资产清理 | B43: 38 | D43: =未审BS!C43 -> 0 | E43: =ABS(F43) -> 0 | F43: =C43-D43 -> 0 | G43: =报表格式!G42 -> 实收资本 | H43: =H42+1 -> 95 | J43: =未审BS!G43 -> 0 | K43: =ABS(L43) -> 0 | L43: =I43-J43 -> 0
A44: =报表格式!B43 -> 待处理固定资产净损失 | B44: 39 | D44: =未审BS!C44 -> 0 | E44: =ABS(F44) -> 0 | F44: =C44-D44 -> 0 | G44: =报表格式!G43 -> 国家资本 | H44: =H43+1 -> 96 | J44: =未审BS!G44 -> 0 | K44: =ABS(L44) -> 0 | L44: =I44-J44 -> 0
A45: =报表格式!B44 -> 0 | B45: 40 | D45: =未审BS!C45 -> 0 | E45: =ABS(F45) -> 0 | F45: =C45-D45 -> 0 | G45: =报表格式!G44 -> 集体资本 | H45: =H44+1 -> 97 | J45: =未审BS!G45 -> 0 | K45: =ABS(L45) -> 0 | L45: =I45-J45 -> 0
A46: =报表格式!B45 -> 0 | B46: 41 | D46: =未审BS!C46 -> 0 | E46: =ABS(F46) -> 0 | F46: =C46-D46 -> 0 | G46: =报表格式!G45 -> 法人资本 | H46: =H45+1 -> 98 | J46: =未审BS!G46 -> 0 | K46: =ABS(L46) -> 0 | L46: =I46-J46 -> 0
A47: =报表格式!B46 -> 固定资产合计 | B47: 42 | C47: =SUM(C40:C46) -> 0 | D47: =SUM(D40:D46) -> 0 | E47: =SUM(E40:E46) -> 0 | F47: =C47-D47 -> 0 | G47: =报表格式!G46 -> 其中：国有法人资本 | H47: =H46+1 -> 99 | J47: =未审BS!G47 -> 0 | K47: =ABS(L47) -> 0 | L47: =I47-J47 -> 0
A48: =报表格式!B47 -> 无形资产及其他资产： | B48: 43 | E48: =ABS(F48) -> 0 | G48: =报表格式!G47 -> 集体法人资本 | H48: =H47+1 -> 100 | J48: =未审BS!G48 -> 0 | K48: =ABS(L48) -> 0 | L48: =I48-J48 -> 0
A49: =报表格式!B48 -> 无形资产 | B49: 44 | D49: =未审BS!C49 -> 0 | E49: =ABS(F49) -> 0 | F49: =C49-D49 -> 0 | G49: =报表格式!G48 -> 个人资本 | H49: =H48+1 -> 101 | J49: =未审BS!G49 -> 0 | K49: =ABS(L49) -> 0 | L49: =I49-J49 -> 0
A50: =报表格式!B49 -> 其中：土地使用权 | B50: 45 | D50: =未审BS!C50 -> 0 | E50: =ABS(F50) -> 0 | F50: =C50-D50 -> 0 | G50: =报表格式!G49 -> 外商资本 | H50: =H49+1 -> 102 | J50: =未审BS!G50 -> 0 | K50: =ABS(L50) -> 0 | L50: =I50-J50 -> 0
A51: =报表格式!B50 -> 长期待摊费用 | B51: 46 | D51: =未审BS!C51 -> 0 | E51: =ABS(F51) -> 0 | F51: =C51-D51 -> 0 | G51: =报表格式!G50 -> 资本公积 | H51: =H50+1 -> 103 | J51: =未审BS!G51 -> 0 | K51: =ABS(L51) -> 0 | L51: =I51-J51 -> 0
A52: =报表格式!B51 -> 其中：固定资产修理 | B52: 47 | D52: =未审BS!C52 -> 0 | E52: =ABS(F52) -> 0 | F52: =C52-D52 -> 0 | G52: =报表格式!G51 -> 盈余公积 | H52: =H51+1 -> 104 | J52: =未审BS!G52 -> 0 | K52: =ABS(L52) -> 0 | L52: =I52-J52 -> 0
A53: =报表格式!B52 -> 固定资产改良支出 | B53: 48 | D53: =未审BS!C53 -> 0 | E53: =ABS(F53) -> 0 | F53: =C53-D53 -> 0 | G53: =报表格式!G52 -> 其中：法定公益金 | H53: =H52+1 -> 105 | J53: =未审BS!G53 -> 0 | K53: =ABS(L53) -> 0 | L53: =I53-J53 -> 0
A54: =报表格式!B53 -> 股权分置流通权 | B54: 49 | D54: =未审BS!C54 -> 0 | E54: =ABS(F54) -> 0 | F54: =C54-D54 -> 0 | G54: =报表格式!G53 -> *未确认的投资损失（以“-”号填列） | H54: =H53+1 -> 106 | J54: =未审BS!G54 -> 0 | K54: =ABS(L54) -> 0 | L54: =I54-J54 -> 0
A55: =报表格式!B54 -> 其他长期资产 | B55: 50 | D55: =未审BS!C55 -> 0 | E55: =ABS(F55) -> 0 | F55: =C55-D55 -> 0 | G55: =报表格式!G54 -> 未分配利润 | H55: =H54+1 -> 107 | J55: =未审BS!G55 -> 0 | K55: =ABS(L55) -> 0 | L55: =I55-J55 -> 0
A56: =报表格式!B55 -> 其中：特准储备物资 | B56: 51 | D56: =未审BS!C56 -> 0 | E56: =ABS(F56) -> 0 | F56: =C56-D56 -> 0 | G56: =报表格式!G55 -> 其中：现金股利 | H56: =H55+1 -> 108 | J56: =未审BS!G56 -> 0 | K56: =ABS(L56) -> 0 | L56: =I56-J56 -> 0
A57: =报表格式!B56 -> 0 | B57: 52 | D57: =未审BS!C57 -> 0 | E57: =ABS(F57) -> 0 | F57: =C57-D57 -> 0 | G57: =报表格式!G56 -> 外币报表折算差额 | H57: =H56+1 -> 109 | J57: =未审BS!G57 -> 0 | K57: =ABS(L57) -> 0 | L57: =I57-J57 -> 0
A58: =报表格式!B57 -> 无形资产及其他资产合计 | B58: 53 | C58: =SUM(C49,C51,C54:C55,C57) -> 0 | D58: =SUM(D49,D51,D54:D55,D57) -> 0 | E58: =SUM(E49:E55)-E50-E52-E53-E55+SUM(E56:E57) -> 0 | F58: =C58-D58 -> 0 | G58: =报表格式!G57 -> 0 | H58: =H57+1 -> 110 | J58: =未审BS!G58 -> 0 | K58: =ABS(L58) -> 0 | L58: =I58-J58 -> 0
A59: =报表格式!B58 -> 递延税项： | B59: 54 | E59: =ABS(F59) -> 0 | G59: =报表格式!G58 -> 所有者权益小计 | H59: =H58+1 -> 111 | I59: =SUM(I43,I51,I52,I54,I55,I57,I58) -> 0 | J59: =SUM(J43,J51,J52,J54,J55,J57,J58) -> 0 | K59: =SUM(K43,K51,K52,K54,K55,K57,K58) -> 0 | L59: =I59-J59 -> 0
A60: =报表格式!B59 -> 递延税款借项 | B60: 55 | D60: =未审BS!C60 -> 0 | E60: =ABS(F60) -> 0 | F60: =C60-D60 -> 0 | G60: =报表格式!G59 -> 减：未处理资产损失 | H60: =H59+1 -> 112 | J60: =未审BS!G60 -> 0 | K60: =ABS(L60) -> 0 | L60: =I60-J60 -> 0
A61: =报表格式!B60 -> 0 | B61: 56 | D61: =未审BS!C61 -> 0 | E61: =ABS(F61) -> 0 | F61: =C61-D61 -> 0 | G61: =报表格式!G60 -> 所有者权益合计(剔除未处理资产损失后的金额) | H61: =H60+1 -> 113 | I61: =I59-I60 -> 0 | J61: =J59-J60 -> 0 | K61: =K59-K60 -> 0 | L61: =I61-J61 -> 0
A62: =报表格式!B73 -> 资 产 总 计 | B62: 57 | C62: =C27+C34+C47+C58+C60+C61 -> 0 | D62: =D27+D34+D47+D58+D60+D61 -> 0 | E62: =E27+E34+E47+E58+E60 -> 0 | F62: =C62-D62 -> 0 | G62: =报表格式!G73 -> 负债及所有者权益合计 | H62: =H61+1 -> 114 | I62: =I39+I40+I41+I61 -> 0 | J62: =J39+J40+J41+J61 -> 0 | K62: =K39+K40+K61 -> 0 | L62: =I62-J62 -> 0
A64: 上期审定BS平衡 | C64: =C62-I62 -> 0 | G64: 上期审定未分配利润勾稽 | I64: =I55-期初核对PL!C73 -> 0
A65: 本年期初BS平衡 | C65: =D62-J62 -> 0 | G65: 本年期初未分配利润勾稽 | I65: =J55-期初核对PL!D73 -> 0

Sheet 期初核对PL
A1: =IF(AND(ABS(F73)<0.005,ABS(F74)<0.005),"期初金额核对一致","期初金额核对不符！") -> 期初金额核对一致
A2: 利润表及利润分配表期初核对
A4: =IF(报表格式!G41=""," 对不起，请到参数表中确定报表类型！",CONCATENATE(" 客户名称：",参数!D3)) -> 客户名称： | B4: =参数!$D$10 -> 2007年度 | F4: =CONCATENATE("金额单位：",参数!$D$13) -> 金额单位：人民币元
A5: =IF(AND(E73<0.005,E74<0.005),"项 目","明细项目不符！") -> 项 目 | B5: 行次 | C5: 上期审定数 ① | D5: 本期上期数 ② | E5: 辅助列 | F5: 差异 ①-②
A6: =报表格式!L5 -> 一、主营业务收入 | B6: 1 | D6: =未审PL!C6 -> 0 | E6: =ABS(F6) -> 0 | F6: =C6-D6 -> 0
A7: =报表格式!L6 -> 其中：进口产品（商品）销售收入 | B7: 2 | D7: =未审PL!C7 -> 0 | E7: =ABS(F7) -> 0 | F7: =C7-D7 -> 0
A8: =报表格式!L7 -> 出口产品（商品）销售收入 | B8: 3 | D8: =未审PL!C8 -> 0 | E8: =ABS(F8) -> 0 | F8: =C8-D8 -> 0
A9: =报表格式!L8 -> 减：折扣与折让 | B9: 4 | D9: =未审PL!C9 -> 0 | E9: =ABS(F9) -> 0 | F9: =C9-D9 -> 0
A10: =报表格式!L9 -> 二、主营业务收入净额 | B10: 5 | C10: =C6-C9 -> 0 | D10: =D6-D9 -> 0 | E10: =ABS(F10) -> 0 | F10: =C10-D10 -> 0
A11: =报表格式!L10 -> 减：（一）主营业务成本 | B11: 6 | D11: =未审PL!C11 -> 0 | E11: =ABS(F11) -> 0 | F11: =C11-D11 -> 0
A12: =报表格式!L11 -> 其中：出口产品（商品）销售成本 | B12: 7 | D12: =未审PL!C12 -> 0 | E12: =ABS(F12) -> 0 | F12: =C12-D12 -> 0
A13: =报表格式!L12 -> （二）主营业务税金及附加 | B13: 8 | D13: =未审PL!C13 -> 0 | E13: =ABS(F13) -> 0 | F13: =C13-D13 -> 0
A14: =报表格式!L13 -> （三）经营费用 | B14: 9 | D14: =未审PL!C14 -> 0 | E14: =ABS(F14) -> 0 | F14: =C14-D14 -> 0
A15: =报表格式!L14 -> （四）其他 | B15: 10 | D15: =未审PL!C15 -> 0 | E15: =ABS(F15) -> 0 | F15: =C15-D15 -> 0
A16: =报表格式!L15 -> 加：（一）递延收益 | B16: 11 | D16: =未审PL!C16 -> 0 | E16: =ABS(F16) -> 0 | F16: =C16-D16 -> 0
A17: =报表格式!L16 -> （二）代购代销收入 | B17: 12 | D17: =未审PL!C17 -> 0 | E17: =ABS(F17) -> 0 | F17: =C17-D17 -> 0
A18: =报表格式!L17 -> （三）其他 | B18: 13 | D18: =未审PL!C18 -> 0 | E18: =ABS(F18) -> 0 | F18: =C18-D18 -> 0
A19: =报表格式!L18 -> 三、主营业务利润 | B19: 14 | C19: =C10-C11-C13-C14-C15+C16+C17+C18 -> 0 | D19: =D10-D11-D13-D14-D15+D16+D17+D18 -> 0 | E19: =ABS(F19) -> 0 | F19: =C19-D19 -> 0
A20: =报表格式!L19 -> 加：其他业务利润 | B20: 15 | D20: =未审PL!C20 -> 0 | E20: =ABS(F20) -> 0 | F20: =C20-D20 -> 0
A21: =报表格式!L20 -> 减：（一）营业费用 | B21: 16 | D21: =未审PL!C21 -> 0 | E21: =ABS(F21) -> 0 | F21: =C21-D21 -> 0
A22: =报表格式!L21 -> （二）管理费用 | B22: 17 | D22: =未审PL!C22 -> 0 | E22: =ABS(F22) -> 0 | F22: =C22-D22 -> 0
A23: =报表格式!L22 -> 其中：业务招待费 | B23: 18 | D23: =未审PL!C23 -> 0 | F23: =C23-D23 -> 0
A24: =报表格式!L23 -> 研究与开发费 | B24: 19 | D24: =未审PL!C24 -> 0 | F24: =C24-D24 -> 0
A25: =报表格式!L24 -> （三）财务费用 | B25: 20 | D25: =未审PL!C25 -> 0 | E25: =ABS(F25) -> 0 | F25: =C25-D25 -> 0
A26: =报表格式!L25 -> 其中：利息支出 | B26: 21 | D26: =未审PL!C26 -> 0 | E26: =ABS(F26) -> 0 | F26: =C26-D26 -> 0
A27: =报表格式!L26 -> 利息收入 | B27: 22 | D27: =未审PL!C27 -> 0 | E27: =ABS(F27) -> 0 | F27: =C27-D27 -> 0
A28: =报表格式!L27 -> 汇兑净损失 | B28: 23 | D28: =未审PL!C28 -> 0 | E28: =ABS(F28) -> 0 | F28: =C28-D28 -> 0
A29: =报表格式!L28 -> （四）其他 | B29: 24 | D29: =未审PL!C29 -> 0 | E29: =ABS(F29) -> 0 | F29: =C29-D29 -> 0
A30: =报表格式!L29 -> 四、营业利润 | B30: 25 | C30: =C19+C20-C21-C22-C25-C29 -> 0 | D30: =D19+D20-D21-D22-D25-D29 -> 0 | E30: =ABS(F30) -> 0 | F30: =C30-D30 -> 0
A31: =报表格式!L30 -> 加：（一）投资收益 | B31: 26 | D31: =未审PL!C31 -> 0 | E31: =ABS(F31) -> 0 | F31: =C31-D31 -> 0
A32: =报表格式!L31 -> （二）期货收益 | B32: 27 | D32: =未审PL!C32 -> 0 | E32: =ABS(F32) -> 0 | F32: =C32-D32 -> 0
A33: =报表格式!L32 -> （三）补贴收入 | B33: 28 | D33: =未审PL!C33 -> 0 | E33: =ABS(F33) -> 0 | F33: =C33-D33 -> 0
A34: =报表格式!L33 -> 其中：补贴前亏损的企业补贴收入 | B34: 29 | D34: =未审PL!C34 -> 0 | E34: =ABS(F34) -> 0 | F34: =C34-D34 -> 0
A35: =报表格式!L34 -> （四）营业外收入 | B35: 30 | D35: =未审PL!C35 -> 0 | E35: =ABS(F35) -> 0 | F35: =C35-D35 -> 0
A36: =报表格式!L35 -> 其中：处置固定资产净收益 | B36: 31 | D36: =未审PL!C36 -> 0 | E36: =ABS(F36) -> 0 | F36: =C36-D36 -> 0
A37: =报表格式!L36 -> 非货币性交易收益 | B37: 32 | D37: =未审PL!C37 -> 0 | E37: =ABS(F37) -> 0 | F37: =C37-D37 -> 0
A38: =报表格式!L37 -> 出售无形资产收益 | B38: 33 | D38: =未审PL!C38 -> 0 | E38: =ABS(F38) -> 0 | F38: =C38-D38 -> 0
A39: =报表格式!L38 -> 罚款净收入 | B39: 34 | D39: =未审PL!C39 -> 0 | E39: =ABS(F39) -> 0 | F39: =C39-D39 -> 0
A40: =报表格式!L39 -> （五）其他 | B40: 35 | D40: =未审PL!C40 -> 0 | E40: =ABS(F40) -> 0 | F40: =C40-D40 -> 0
A41: =报表格式!L40 -> 其中：用以前年度含量工资结余弥补利润 | B41: 36 | D41: =未审PL!C41 -> 0 | E41: =ABS(F41) -> 0 | F41: =C41-D41 -> 0
A42: =报表格式!L41 -> 减：（一）营业外支出 | B42: 37 | D42: =未审PL!C42 -> 0 | E42: =ABS(F42) -> 0 | F42: =C42-D42 -> 0
... A48: =报表格式!L47 -> 其中：结转的含量工资包干结余 | B48: 43 | D48: =未审PL!C48 -> 0 | E48: =ABS(F48) -> 0 | F48: =C48-D48 -> 0
A49: =报表格式!L48 -> 五、利润总额 | B49: 44 | C49: =C30+C31+C32+C33+C35+C40-C42-C47 -> 0 | D49: =D30+D31+D32+D33+D35+D40-D42-D47 -> 0 | E49: =ABS(F49) -> 0 | F49: =C49-D49 -> 0
A50: =报表格式!L49 -> 减：所得税 | B50: 45 | D50: =未审PL!C50 -> 0 | E50: =ABS(F50) -> 0 | F50: =C50-D50 -> 0
A51: =报表格式!L50 -> *少数股东损益 | B51: 46 | D51: =未审PL!C51 -> 0 | E51: =ABS(F51) -> 0 | F51: =C51-D51 -> 0
A52: =报表格式!L51 -> 加：*未确认的投资损失 | B52: 47 | D52: =未审PL!C52 -> 0 | E52: =ABS(F52) -> 0 | F52: =C52-D52 -> 0
A53: =报表格式!L52 -> 六、净利润 | B53: 48 | C53: =C49-C50-C51+C52 -> 0 | D53: =D49-D50-D51+D52 -> 0 | E53: =ABS(F53) -> 0 | F53: =C53-D53 -> 0
A54: =报表格式!L53 -> 加：（一）年初未分配利润 | B54: 49 | D54: =未审PL!C54 -> 0 | E54: =ABS(F54) -> 0 | F54: =C54-D54 -> 0
A55: =报表格式!L54 -> （二）盈余公积补亏 | B55: 50 | D55: =未审PL!C55 -> 0 | E55: =ABS(F55) -> 0 | F55: =C55-D55 -> 0
A56: =报表格式!L55 -> （三）其他调整因素 | B56: 51 | D56: =未审PL!C56 -> 0 | E56: =ABS(F56) -> 0 | F56: =C56-D56 -> 0
A57: =报表格式!L56 -> 七、可供分配的利润 | B57: 52 | C57: =C53+C54+C55+C56 -> 0 | D57: =D53+D54+D55+D56 -> 0 | E57: =ABS(F57) -> 0 | F57: =C57-D57 -> 0
A58: =报表格式!L57 -> 减：（一）提取法定盈余公积 | B58: 53 | D58: =未审PL!C58 -> 0 | E58: =ABS(F58) -> 0 | F58: =C58-D58 -> 0
A59: =报表格式!L58 -> （二）提取法定公益金 | B59: 54 | D59: =未审PL!C59 -> 0 | E59: =ABS(F59) -> 0 | F59: =C59-D59 -> 0
A60: =报表格式!L59 -> （三）提取职工奖励及福利基金 | B60: 55 | D60: =未审PL!C60 -> 0 | E60: =ABS(F60) -> 0 | F60: =C60-D60 -> 0
A61: =报表格式!L60 -> （四）提取储备基金 | B61: 56 | D61: =未审PL!C61 -> 0 | E61: =ABS(F61) -> 0 | F61: =C61-D61 -> 0
A62: =报表格式!L61 -> （五）提取企业发展基金 | B62: 57 | D62: =未审PL!C62 -> 0 | E62: =ABS(F62) -> 0 | F62: =C62-D62 -> 0
A63: =报表格式!L62 -> （六）利润归还投资 | B63: 58 | D63: =未审PL!C63 -> 0 | E63: =ABS(F63) -> 0 | F63: =C63-D63 -> 0
A64: =报表格式!L63 -> （七）补充流动资本 | B64: 59 | D64: =未审PL!C64 -> 0 | E64: =ABS(F64) -> 0 | F64: =C64-D64 -> 0
A65: =报表格式!L64 -> （八）单项留用的利润 | B65: 60 | D65: =未审PL!C65 -> 0 | E65: =ABS(F65) -> 0 | F65: =C65-D65 -> 0
A66: =报表格式!L65 -> （九）其他 | B66: 61 | D66: =未审PL!C66 -> 0 | E66: =ABS(F66) -> 0 | F66: =C66-D66 -> 0
A67: =报表格式!L66 -> 八、可供投资者分配的利润 | B67: 62 | C67: =C57-C58-C59-C60-C61-C62-C63-C64-C65-C66 -> 0 | D67: =D57-D58-D59-D60-D61-D62-D63-D64-D65-D66 -> 0 | E67: =ABS(F67) -> 0 | F67: =C67-D67 -> 0
A68: =报表格式!L67 -> 减：（一）应付优先股股利 | B68: 63 | D68: =未审PL!C68 -> 0 | E68: =ABS(F68) -> 0 | F68: =C68-D68 -> 0
A69: =报表格式!L68 -> （二）提取任意盈余公积 | B69: 64 | D69: =未审PL!C69 -> 0 | E69: =ABS(F69) -> 0 | F69: =C69-D69 -> 0
A70: =报表格式!L69 -> （三）应付普通股股利（应付利润） | B70: 65 | D70: =未审PL!C70 -> 0 | E70: =ABS(F70) -> 0 | F70: =C70-D70 -> 0
A71: =报表格式!L70 -> （四）转作资本（股本）的普通股股利 | B71: 66 | D71: =未审PL!C71 -> 0 | E71: =ABS(F71) -> 0 | F71: =C71-D71 -> 0
A72: =报表格式!L71 -> （五）其他 | B72: 67 | D72: =未审PL!C72 -> 0 | E72: =ABS(F72) -> 0 | F72: =C72-D72 -> 0
A73: =报表格式!L72 -> 九、未分配利润 | B73: 68 | C73: =C67-C68-C69-C70-C71-C72 -> 0 | D73: =D67-D68-D69-D70-D71-D72 -> 0 | E73: =ABS(F73) -> 0 | F73: =C73-D73 -> 0
A74: =报表格式!L73 -> 其中：应由以后年度税前利润弥补的亏损（以“+”号填列） | B74: 69 | D74: =未审PL!C74 -> 0 | E74: =SUM(E6:E73) -> 0 | F74: =C74-D74 -> 0

Sheet 账项调整
A1: =IF((L2-(TB资产!C63+TB负债!C63+TB损益!C75)-IF(COUNTIF(E5:E666,"未分配利润")>=1,VLOOKUP("未分配利润",E5:J666,6,0),0))<0.005,"账项调整事项汇总表","调整事项未全部链入试算平衡表，请检查调整科目是否为报表项目!") -> 账项调整事项汇总表 | K1: =SUM(L2:L3) -> 0 | N1: code | O1: 报表项目
A2: =CONCATENATE("客户名称：",参数!D3) -> 客户名称： | E2: =CONCATENATE("编制人：",参数!D17) -> 编制人： | H2: =CONCATENATE("日期：",TEXT(NOW(),"yyyy.mm.dd")) -> 日期：2023.08.14 | J2: 索引： | K2: 借方调整累计 | L2: =SUMIF(E5:E65536,"?*",J5:J65536) -> 0
A3: =CONCATENATE("会计期间：",参数!D10) -> 会计期间：2007年度 | E3: =CONCATENATE("复核人：",参数!D18) -> 复核人： | H3: 日期： | J3: 页码： | K3: 贷方调整累计 | L3: =SUMIF(H5:H65536,"?*",J5:J65536) -> 0
A4: 序号 | B4: 索引号 | C4: 调整说明 | D4: code | E4: 借方科目 | F4: 二级科目 | G4: code | H4: 贷方科目 | I4: 二级科目 | J4: 金额 | L4: =L2-L3 -> 0
A5: 1 | E5: =IF(D5=0,"",VLOOKUP(D5,$N:$O,2,0)) | H5: =IF(G5=0,"",VLOOKUP(G5,$N:$O,2,0)) | K5: 本表可根据需要插入行， | N5: =报表格式!Z5 -> 0 | O5: =报表格式!AA5 -> 流动资产：
E6: =IF(D6=0,"",VLOOKUP(D6,$N:$O,2,0)) | H6: =IF(G6=0,"",VLOOKUP(G6,$N:$O,2,0)) | K6: 请勿删除行。 | N6: =报表格式!Z6 -> G123 | O6: =报表格式!AA6 -> 货币资金
E7: =IF(D7=0,"",VLOOKUP(D7,$N:$O,2,0)) | H7: =IF(G7=0,"",VLOOKUP(G7,$N:$O,2,0)) | N7: =报表格式!Z7 -> F1 | O7: =报表格式!AA7 -> 短期投资
E8: =IF(D8=0,"",VLOOKUP(D8,$N:$O,2,0)) | H8: =IF(G8=0,"",VLOOKUP(G8,$N:$O,2,0)) | N8: =报表格式!Z8 -> D3 | O8: =报表格式!AA8 -> 应收票据
J9: =IF(ABS((SUMIF(E5:E8,"?*",J5:J8)-SUMIF(H5:H8,"?*",J5:J8)))<0.005,"","借贷不等") | N9: =报表格式!Z9 -> F5 | O9: =报表格式!AA9 -> 应收股利
A10: 2 | E10: =IF(D10=0,"",VLOOKUP(D10,$N:$O,2,0)) | H10: =IF(G10=0,"",VLOOKUP(G10,$N:$O,2,0)) | N10: =报表格式!Z10 -> F6 | O10: =报表格式!AA10 -> 应收利息
E11: =IF(D11=0,"",VLOOKUP(D11,$N:$O,2,0)) | H11: =IF(G11=0,"",VLOOKUP(G11,$N:$O,2,0)) | N11: =报表格式!Z11 -> D1 | O11: =报表格式!AA11 -> 应收账款
E12: =IF(D12=0,"",VLOOKUP(D12,$N:$O,2,0)) | H12: =IF(G12=0,"",VLOOKUP(G12,$N:$O,2,0)) | N12: =报表格式!Z12 -> G4 | O12: =报表格式!AA12 -> 其他应收款
E13: =IF(D13=0,"",VLOOKUP(D13,$N:$O,2,0)) | H13: =IF(G13=0,"",VLOOKUP(G13,$N:$O,2,0)) | N13: =报表格式!Z13 -> E3 | O13: =报表格式!AA13 -> 预付账款
J14: =IF(ABS((SUMIF(E10:E13,"?*",J10:J13)-SUMIF(H10:H13,"?*",J10:J13)))<0.005,"","借贷不等") | N14: =报表格式!Z14 -> 0 | O14: =报表格式!AA14 -> 期货保证金
A15: 3 | E15: =IF(D15=0,"",VLOOKUP(D15,$N:$O,2,0)) | H15: =IF(G15=0,"",VLOOKUP(G15,$N:$O,2,0)) | N15: =报表格式!Z15 -> I1 | O15: =报表格式!AA15 -> 应收补贴款
E16: =IF(D16=0,"",VLOOKUP(D16,$N:$O,2,0)) | H16: =IF(G16=0,"",VLOOKUP(G16,$N:$O,2,0)) | N16: =报表格式!Z16 -> 0 | O16: =报表格式!AA16 -> 应收出口退税
E17: =IF(D17=0,"",VLOOKUP(D17,$N:$O,2,0)) | H17: =IF(G17=0,"",VLOOKUP(G17,$N:$O,2,0)) | N17: =报表格式!Z17 -> E1 | O17: =报表格式!AA17 -> 存货
E18: =IF(D18=0,"",VLOOKUP(D18,$N:$O,2,0)) | H18: =IF(G18=0,"",VLOOKUP(G18,$N:$O,2,0)) | N18: =报表格式!Z18 -> 0 | O18: =报表格式!AA18 -> 0
J19: =IF(ABS((SUMIF(E15:E18,"?*",J15:J18)-SUMIF(H15:H18,"?*",J15:J18)))<0.005,"","借贷不等") | N19: =报表格式!Z19 -> 0 | O19: =报表格式!AA19 -> 0
A20: 4 | E20: =IF(D20=0,"",VLOOKUP(D20,$N:$O,2,0)) | H20: =IF(G20=0,"",VLOOKUP(G20,$N:$O,2,0)) | N20: =报表格式!Z20 -> I4 | O20: =报表格式!AA20 -> 待摊费用
E21: =IF(D21=0,"",VLOOKUP(D21,$N:$O,2,0)) | H21: =IF(G21=0,"",VLOOKUP(G21,$N:$O,2,0)) | N21: =报表格式!Z21 -> I6 | O21: =报表格式!AA21 -> 待处理流动资产净损失
E22: =IF(D22=0,"",VLOOKUP(D22,$N:$O,2,0)) | H22: =IF(G22=0,"",VLOOKUP(G22,$N:$O,2,0)) | N22: =报表格式!Z22 -> 0 | O22: =报表格式!AA22 -> 一年内到期的长期债权投资
E23: =IF(D23=0,"",VLOOKUP(D23,$N:$O,2,0)) | H23: =IF(G23=0,"",VLOOKUP(G23,$N:$O,2,0)) | N23: =报表格式!Z23 -> 0 | O23: =报表格式!AA23 -> 其他流动资产
J24: =IF(ABS((SUMIF(E20:E23,"?*",J20:J23)-SUMIF(H20:H23,"?*",J20:J23)))<0.005,"","借贷不等") | N24: =报表格式!Z24 -> 0 | O24: =报表格式!AA24 -> 0
A25: 5 | E25: =IF(D25=0,"",VLOOKUP(D25,$N:$O,2,0)) | H25: =IF(G25=0,"",VLOOKUP(G25,$N:$O,2,0)) | N25: =报表格式!Z25 -> 0 | O25: =报表格式!AA25 -> 0
E26: =IF(D26=0,"",VLOOKUP(D26,$N:$O,2,0)) | H26: =IF(G26=0,"",VLOOKUP(G26,$N:$O,2,0)) | N26: =报表格式!Z26 -> 0 | O26: =报表格式!AA26 -> 流动资产合计
E27: =IF(D27=0,"",VLOOKUP(D27,$N:$O,2,0)) | H27: =IF(G27=0,"",VLOOKUP(G27,$N:$O,2,0)) | N27: =报表格式!Z27 -> 0 | O27: =报表格式!AA27 -> 0
E28: =IF(D28=0,"",VLOOKUP(D28,$N:$O,2,0)) | H28: =IF(G28=0,"",VLOOKUP(G28,$N:$O,2,0)) | N28: =报表格式!Z28 -> 0 | O28: =报表格式!AA28 -> 长期投资：
J29: =IF(ABS((SUMIF(E25:E28,"?*",J25:J28)-SUMIF(H25:H28,"?*",J25:J28)))<0.005,"","借贷不等") | N29: =报表格式!Z29 -> F2 | O29: =报表格式!AA29 -> 长期股权投资
A30: 6 | E30: =IF(D30=0,"",VLOOKUP(D30,$N:$O,2,0)) | H30: =IF(G30=0,"",VLOOKUP(G30,$N:$O,2,0)) | N30: =报表格式!Z30 -> F3 | O30: =报表格式!AA30 -> 长期债权投资
E31: =IF(D31=0,"",VLOOKUP(D31,$N:$O,2,0)) | H31: =IF(G31=0,"",VLOOKUP(G31,$N:$O,2,0)) | N31: =报表格式!Z31 -> 0 | O31: =报表格式!AA31 -> 合并价差
E32: =IF(D32=0,"",VLOOKUP(D32,$N:$O,2,0)) | H32: =IF(G32=0,"",VLOOKUP(G32,$N:$O,2,0)) | N32: =报表格式!Z32 -> 0 | O32: =报表格式!AA32 -> 0
E33: =IF(D33=0,"",VLOOKUP(D33,$N:$O,2,0)) | H33: =IF(G33=0,"",VLOOKUP(G33,$N:$O,2,0)) | N33: =报表格式!Z33 -> 0 | O33: =报表格式!AA33 -> 0
J34: =IF(ABS((SUMIF(E30:E33,"?*",J30:J33)-SUMIF(H30:H33,"?*",J30:J33)))<0.005,"","借贷不等") | N34: =报表格式!Z34 -> 0 | O34: =报表格式!AA34 -> 长期投资合计
A35: 7 | E35: =IF(D35=0,"",VLOOKUP(D35,$N:$O,2,0)) | H35: =IF(G35=0,"",VLOOKUP(G35,$N:$O,2,0)) | N35: =报表格式!Z35 -> 0 | O35: =报表格式!AA35 -> 0
E36: =IF(D36=0,"",VLOOKUP(D36,$N:$O,2,0)) | H36: =IF(G36=0,"",VLOOKUP(G36,$N:$O,2,0)) | N36: =报表格式!Z36 -> 0 | O36: =报表格式!AA36 -> 固定资产：
E37: =IF(D37=0,"",VLOOKUP(D37,$N:$O,2,0)) | H37: =IF(G37=0,"",VLOOKUP(G37,$N:$O,2,0)) | N37: =报表格式!Z37 -> H1 | O37: =报表格式!AA37 -> 固定资产原价
E38: =IF(D38=0,"",VLOOKUP(D38,$N:$O,2,0)) | H38: =IF(G38=0,"",VLOOKUP(G38,$N:$O,2,0)) | N38: =报表格式!Z38 -> H2 | O38: =报表格式!AA38 -> 累计折旧
J39: =IF(ABS((SUMIF(E35:E38,"?*",J35:J38)-SUMIF(H35:H38,"?*",J35:J38)))<0.005,"","借贷不等") | N39: =报表格式!Z39 -> 0 | O39: =报表格式!AA39 -> 0
A40: 8 | E40: =IF(D40=0,"",VLOOKUP(D40,$N:$O,2,0)) | H40: =IF(G40=0,"",VLOOKUP(G40,$N:$O,2,0)) | N40: =报表格式!Z40 -> H3 | O40: =报表格式!AA40 -> 固定资产减值准备
E41: =IF(D41=0,"",VLOOKUP(D41,$N:$O,2,0)) | H41: =IF(G41=0,"",VLOOKUP(G41,$N:$O,2,0)) | N41: =报表格式!Z41 -> 0 | O41: =报表格式!AA41 -> 0
E42: =IF(D42=0,"",VLOOKUP(D42,$N:$O,2,0)) | H42: =IF(G42=0,"",VLOOKUP(G42,$N:$O,2,0)) | N42: =报表格式!Z42 -> H4 | O42: =报表格式!AA42 -> 固定资产清理
E43: =IF(D43=0,"",VLOOKUP(D43,$N:$O,2,0)) | H43: =IF(G43=0,"",VLOOKUP(G43,$N:$O,2,0)) | N43: =报表格式!Z43 -> H7 | O43: =报表格式!AA43 -> 工程物资
J44: =IF(ABS((SUMIF(E40:E43,"?*",J40:J43)-SUMIF(H40:H43,"?*",J40:J43)))<0.005,"","借贷不等") | N44: =报表格式!Z44 -> H6 | O44: =报表格式!AA44 -> 在建工程
A45: 9 | E45: =IF(D45=0,"",VLOOKUP(D45,$N:$O,2,0)) | H45: =IF(G45=0,"",VLOOKUP(G45,$N:$O,2,0)) | N45: =报表格式!Z45 -> H5 | O45: =报表格式!AA45 -> 待处理固定资产净损失
E46: =IF(D46=0,"",VLOOKUP(D46,$N:$O,2,0)) | H46: =IF(G46=0,"",VLOOKUP(G46,$N:$O,2,0)) | N46: =报表格式!Z46 -> 0 | O46: =报表格式!AA46 -> 0
E47: =IF(D47=0,"",VLOOKUP(D47,$N:$O,2,0)) | H47: =IF(G47=0,"",VLOOKUP(G47,$N:$O,2,0)) | N47: =报表格式!Z47 -> 0 | O47: =报表格式!AA47 -> 0
E48: =IF(D48=0,"",VLOOKUP(D48,$N:$O,2,0)) | H48: =IF(G48=0,"",VLOOKUP(G48,$N:$O,2,0)) | N48: =报表格式!Z48 -> 0 | O48: =报表格式!AA48 -> 固定资产合计
J49: =IF(ABS((SUMIF(E45:E48,"?*",J45:J48)-SUMIF(H45:H48,"?*",J45:J48)))<0.005,"","借贷不等") | N49: =报表格式!Z49 -> 0 | O49: =报表格式!AA49 -> 无形资产及其他资产：
A50: 10 | E50: =IF(D50=0,"",VLOOKUP(D50,$N:$O,2,0)) | H50: =IF(G50=0,"",VLOOKUP(G50,$N:$O,2,0)) | N50: =报表格式!Z50 -> I2 | O50: =报表格式!AA50 -> 无形资产
E51: =IF(D51=0,"",VLOOKUP(D51,$N:$O,2,0)) | H51: =IF(G51=0,"",VLOOKUP(G51,$N:$O,2,0)) | N51: =报表格式!Z51 -> 0 | O51: =报表格式!AA51 -> 0
E52: =IF(D52=0,"",VLOOKUP(D52,$N:$O,2,0)) | H52: =IF(G52=0,"",VLOOKUP(G52,$N:$O,2,0)) | N52: =报表格式!Z52 -> I5 | O52: =报表格式!AA52 -> 长期待摊费用
E53: =IF(D53=0,"",VLOOKUP(D53,$N:$O,2,0)) | H53: =IF(G53=0,"",VLOOKUP(G53,$N:$O,2,0)) | N53: =报表格式!Z53 -> 0 | O53: =报表格式!AA53 -> 0
J54: =IF(ABS((SUMIF(E50:E53,"?*",J50:J53)-SUMIF(H50:H53,"?*",J50:J53)))<0.005,"","借贷不等") | N54: =报表格式!Z54 -> 0 | O54: =报表格式!AA54 -> 0
A55: 11 | E55: =IF(D55=0,"",VLOOKUP(D55,$N:$O,2,0)) | H55: =IF(G55=0,"",VLOOKUP(G55,$N:$O,2,0)) | N55: =报表格式!Z55 -> 0 | O55: =报表格式!AA55 -> 股权分置流通权
E56: =IF(D56=0,"",VLOOKUP(D56,$N:$O,2,0)) | H56: =IF(G56=0,"",VLOOKUP(G56,$N:$O,2,0)) | N56: =报表格式!Z56 -> 0 | O56: =报表格式!AA56 -> 其他长期资产
E57: =IF(D57=0,"",VLOOKUP(D57,$N:$O,2,0)) | H57: =IF(G57=0,"",VLOOKUP(G57,$N:$O,2,0)) | N57: =报表格式!Z57 -> 0 | O57: =报表格式!AA57 -> 0
E58: =IF(D58=0,"",VLOOKUP(D58,$N:$O,2,0)) | H58: =IF(G58=0,"",VLOOKUP(G58,$N:$O,2,0)) | N58: =报表格式!Z58 -> 0 | O58: =报表格式!AA58 -> 0
J59: =IF(ABS((SUMIF(E55:E58,"?*",J55:J58)-SUMIF(H55:H58,"?*",J55:J58)))<0.005,"","借贷不等") | N59: =报表格式!Z59 -> 0 | O59: =报表格式!AA59 -> 无形资产及其他资产合计
A60: 12 | E60: =IF(D60=0,"",VLOOKUP(D60,$N:$O,2,0)) | H60: =IF(G60=0,"",VLOOKUP(G60,$N:$O,2,0)) | N60: =报表格式!Z60 -> 0 | O60: =报表格式!AA60 -> 递延税项：
E61: =IF(D61=0,"",VLOOKUP(D61,$N:$O,2,0)) | H61: =IF(G61=0,"",VLOOKUP(G61,$N:$O,2,0)) | N61: =报表格式!Z61 -> I18-1 | O61: =报表格式!AA61 -> 递延税款借项
E62: =IF(D62=0,"",VLOOKUP(D62,$N:$O,2,0)) | H62: =IF(G62=0,"",VLOOKUP(G62,$N:$O,2,0)) | N62: =报表格式!Z62 -> 0 | O62: =报表格式!AA62 -> 0
E63: =IF(D63=0,"",VLOOKUP(D63,$N:$O,2,0)) | H63: =IF(G63=0,"",VLOOKUP(G63,$N:$O,2,0)) | N63: =报表格式!Z63 -> 0 | O63: =报表格式!AA63 -> 资产总计
J64: =IF(ABS((SUMIF(E60:E63,"?*",J60:J63)-SUMIF(H60:H63,"?*",J60:J63)))<0.005,"","借贷不等") | N64: =报表格式!Z64 -> 0 | O64: =报表格式!AA64 -> 0
A65: 13 | E65: =IF(D65=0,"",VLOOKUP(D65,$N:$O,2,0)) | H65: =IF(G65=0,"",VLOOKUP(G65,$N:$O,2,0)) | N65: =报表格式!Z65 -> 0 | O65: =报表格式!AA65 -> 流动负债：
E66: =IF(D66=0,"",VLOOKUP(D66,$N:$O,2,0)) | H66: =IF(G66=0,"",VLOOKUP(G66,$N:$O,2,0)) | N66: =报表格式!Z66 -> F11 | O66: =报表格式!AA66 -> 短期借款
E67: =IF(D67=0,"",VLOOKUP(D67,$N:$O,2,0)) | H67: =IF(G67=0,"",VLOOKUP(G67,$N:$O,2,0)) | N67: =报表格式!Z67 -> E12 | O67: =报表格式!AA67 -> 应付票据
E68: =IF(D68=0,"",VLOOKUP(D68,$N:$O,2,0)) | H68: =IF(G68=0,"",VLOOKUP(G68,$N:$O,2,0)) | N68: =报表格式!Z68 -> E11 | O68: =报表格式!AA68 -> 应付账款
J69: =IF(ABS((SUMIF(E65:E68,"?*",J65:J68)-SUMIF(H65:H68,"?*",J65:J68)))<0.005,"","借贷不等") | N69: =报表格式!Z69 -> D11 | O69: =报表格式!AA69 -> 预收账款
A70: 14 | E70: =IF(D70=0,"",VLOOKUP(D70,$N:$O,2,0)) | H70: =IF(G70=0,"",VLOOKUP(G70,$N:$O,2,0)) | N70: =报表格式!Z70 -> E16 | O70: =报表格式!AA70 -> 应付工资
E71: =IF(D71=0,"",VLOOKUP(D71,$N:$O,2,0)) | H71: =IF(G71=0,"",VLOOKUP(G71,$N:$O,2,0)) | N71: =报表格式!Z71 -> E17 | O71: =报表格式!AA71 -> 应付福利费
E72: =IF(D72=0,"",VLOOKUP(D72,$N:$O,2,0)) | H72: =IF(G72=0,"",VLOOKUP(G72,$N:$O,2,0)) | N72: =报表格式!Z72 -> F15 | O72: =报表格式!AA72 -> 应付股利（利润）
E73: =IF(D73=0,"",VLOOKUP(D73,$N:$O,2,0)) | H73: =IF(G73=0,"",VLOOKUP(G73,$N:$O,2,0)) | N73: =报表格式!Z73 -> F14 | O73: =报表格式!AA73 -> 应付利息
J74: =IF(ABS((SUMIF(E70:E73,"?*",J70:J73)-SUMIF(H70:H73,"?*",J70:J73)))<0.005,"","借贷不等") | N74: =报表格式!Z74 -> I16 | O74: =报表格式!AA74 -> 应交税金
A75: 15 | E75: =IF(D75=0,"",VLOOKUP(D75,$N:$O,2,0)) | H75: =IF(G75=0,"",VLOOKUP(G75,$N:$O,2,0)) | N75: =报表格式!Z75 -> I17 | O75: =报表格式!AA75 -> 其他应交款
E76: =IF(D76=0,"",VLOOKUP(D76,$N:$O,2,0)) | H76: =IF(G76=0,"",VLOOKUP(G76,$N:$O,2,0)) | N76: =报表格式!Z76 -> G11 | O76: =报表格式!AA76 -> 其他应付款
E77: =IF(D77=0,"",VLOOKUP(D77,$N:$O,2,0)) | H77: =IF(G77=0,"",VLOOKUP(G77,$N:$O,2,0)) | N77: =报表格式!Z77 -> I11 | O77: =报表格式!AA77 -> 预提费用
E78: =IF(D78=0,"",VLOOKUP(D78,$N:$O,2,0)) | H78: =IF(G78=0,"",VLOOKUP(G78,$N:$O,2,0)) | N78: =报表格式!Z78 -> I19 | O78: =报表格式!AA78 -> 预计负债
J79: =IF(ABS((SUMIF(E75:E78,"?*",J75:J78)-SUMIF(H75:H78,"?*",J75:J78)))<0.005,"","借贷不等") | N79: =报表格式!Z79 -> D12 | O79: =报表格式!AA79 -> 递延收益
A80: 16 | E80: =IF(D80=0,"",VLOOKUP(D80,$N:$O,2,0)) | H80: =IF(G80=0,"",VLOOKUP(G80,$N:$O,2,0)) | N80: =报表格式!Z80 -> 0 | O80: =报表格式!AA80 -> 一年内到期的长期负债
E81: =IF(D81=0,"",VLOOKUP(D81,$N:$O,2,0)) | H81: =IF(G81=0,"",VLOOKUP(G81,$N:$O,2,0)) | N81: =报表格式!Z81 -> 0 | O81: =报表格式!AA81 -> 应付权证
E82: =IF(D82=0,"",VLOOKUP(D82,$N:$O,2,0)) | H82: =IF(G82=0,"",VLOOKUP(G82,$N:$O,2,0)) | N82: =报表格式!Z82 -> 0 | O82: =报表格式!AA82 -> 其他流动负债
E83: =IF(D83=0,"",VLOOKUP(D83,$N:$O,2,0)) | H83: =IF(G83=0,"",VLOOKUP(G83,$N:$O,2,0)) | N83: =报表格式!Z83 -> 0 | O83: =报表格式!AA83 -> 0
J84: =IF(ABS((SUMIF(E80:E83,"?*",J80:J83)-SUMIF(H80:H83,"?*",J80:J83)))<0.005,"","借贷不等") | N84: =报表格式!Z84 -> 0 | O84: =报表格式!AA84 -> 0
A85: 17 | E85: =IF(D85=0,"",VLOOKUP(D85,$N:$O,2,0)) | H85: =IF(G85=0,"",VLOOKUP(G85,$N:$O,2,0)) | N85: =报表格式!Z85 -> 0 | O85: =报表格式!AA85 -> 流动负债合计
E86: =IF(D86=0,"",VLOOKUP(D86,$N:$O,2,0)) | H86: =IF(G86=0,"",VLOOKUP(G86,$N:$O,2,0)) | N86: =报表格式!Z86 -> 0 | O86: =报表格式!AA86 -> 0
E87: =IF(D87=0,"",VLOOKUP(D87,$N:$O,2,0)) | H87: =IF(G87=0,"",VLOOKUP(G87,$N:$O,2,0)) | N87: =报表格式!Z87 -> 0 | O87: =报表格式!AA87 -> 长期负债：
E88: =IF(D88=0,"",VLOOKUP(D88,$N:$O,2,0)) | H88: =IF(G88=0,"",VLOOKUP(G88,$N:$O,2,0)) | N88: =报表格式!Z88 -> F12 | O88: =报表格式!AA88 -> 长期借款
J89: =IF(ABS((SUMIF(E85:E88,"?*",J85:J88)-SUMIF(H85:H88,"?*",J85:J88)))<0.005,"","借贷不等") | N89: =报表格式!Z89 -> F13 | O89: =报表格式!AA89 -> 应付债券
A90: 18 | E90: =IF(D90=0,"",VLOOKUP(D90,$N:$O,2,0)) | H90: =IF(G90=0,"",VLOOKUP(G90,$N:$O,2,0)) | N90: =报表格式!Z90 -> G12 | O90: =报表格式!AA90 -> 长期应付款
E91: =IF(D91=0,"",VLOOKUP(D91,$N:$O,2,0)) | H91: =IF(G91=0,"",VLOOKUP(G91,$N:$O,2,0)) | N91: =报表格式!Z91 -> G13 | O91: =报表格式!AA91 -> 专项应付款
E92: =IF(D92=0,"",VLOOKUP(D92,$N:$O,2,0)) | H92: =IF(G92=0,"",VLOOKUP(G92,$N:$O,2,0)) | N92: =报表格式!Z92 -> 0 | O92: =报表格式!AA92 -> 其他长期负债
E93: =IF(D93=0,"",VLOOKUP(D93,$N:$O,2,0)) | H93: =IF(G93=0,"",VLOOKUP(G93,$N:$O,2,0)) | N93: =报表格式!Z93 -> 0 | O93: =报表格式!AA93 -> 0
J94: =IF(ABS((SUMIF(E90:E93,"?*",J90:J93)-SUMIF(H90:H93,"?*",J90:J93)))<0.005,"","借贷不等") | N94: =报表格式!Z94 -> 0 | O94: =报表格式!AA94 -> 0
A95: 19 | E95: =IF(D95=0,"",VLOOKUP(D95,$N:$O,2,0)) | H95: =IF(G95=0,"",VLOOKUP(G95,$N:$O,2,0)) | N95: =报表格式!Z95 -> 0 | O95: =报表格式!AA95 -> 0
E96: =IF(D96=0,"",VLOOKUP(D96,$N:$O,2,0)) | H96: =IF(G96=0,"",VLOOKUP(G96,$N:$O,2,0)) | N96: =报表格式!Z96 -> 0 | O96: =报表格式!AA96 -> 长期负债合计
E97: =IF(D97=0,"",VLOOKUP(D97,$N:$O,2,0)) | H97: =IF(G97=0,"",VLOOKUP(G97,$N:$O,2,0)) | N97: =报表格式!Z97 -> 0 | O97: =报表格式!AA97 -> 0
E98: =IF(D98=0,"",VLOOKUP(D98,$N:$O,2,0)) | H98: =IF(G98=0,"",VLOOKUP(G98,$N:$O,2,0)) | N98: =报表格式!Z98 -> 0 | O98: =报表格式!AA98 -> 递延税项：
J99: =IF(ABS((SUMIF(E95:E98,"?*",J95:J98)-SUMIF(H95:H98,"?*",J95:J98)))<0.005,"","借贷不等") | N99: =报表格式!Z99 -> I18-2 | O99: =报表格式!AA99 -> 递延税款贷项
A100: 20 | E100: =IF(D100=0,"",VLOOKUP(D100,$N:$O,2,0)) | H100: =IF(G100=0,"",VLOOKUP(G100,$N:$O,2,0)) | N100: =报表格式!Z100 -> 0 | O100: =报表格式!AA100 -> 0
...

Sheet 报表调整
A1: =IF((L2-(TB资产!E63+TB负债!E63+TB损益!E75)-IF(COUNTIF(E5:E666,"未分配利润")>=1,VLOOKUP("未分配利润",E5:J666,6,0),0))<0.005,"报表调整事项汇总表","调整事项未全部链入试算平衡表，请检查调整科目是否为报表项目!") -> 报表调整事项汇总表 | K1: =SUM(L2:L3) -> 0 | N1: code | O1: 报表项目
A2: =CONCATENATE("客户名称：",参数!D3) -> 客户名称： | E2: =CONCATENATE("编制人：",参数!D17) -> 编制人： | H2: =CONCATENATE("日期：",TEXT(NOW(),"yyyy.mm.dd")) -> 日期：2023.08.14 | J2: 索引： | K2: 借方调整累计 | L2: =SUMIF(E5:E65536,"?*",J5:J65536) -> 0
A3: =CONCATENATE("会计期间：",参数!D10) -> 会计期间：2007年度 | E3: =CONCATENATE("复核人：",参数!D18) -> 复核人： | H3: 日期： | J3: 页码： | K3: 贷方调整累计 | L3: =SUMIF(H5:H65536,"?*",J5:J65536) -> 0
A4: 序号 | B4: 索引号 | C4: 调整说明 | D4: code | E4: 借方科目 | F4: 二级科目 | G4: code | H4: 贷方科目 | I4: 二级科目 | J4: 金额 | L4: =L2-L3 -> 0
A5: 1 | E5: =IF(D5=0,"",VLOOKUP(D5,$N:$O,2,0)) | H5: =IF(G5=0,"",VLOOKUP(G5,$N:$O,2,0)) | K5: 本表可根据需要插入行， | N5: =报表格式!Z5 -> 0 | O5: =报表格式!AA5 -> 流动资产：
E6: =IF(D6=0,"",VLOOKUP(D6,$N:$O,2,0)) | H6: =IF(G6=0,"",VLOOKUP(G6,$N:$O,2,0)) | K6: 请勿删除行。 | N6: =报表格式!Z6 -> G123 | O6: =报表格式!AA6 -> 货币资金
E7: =IF(D7=0,"",VLOOKUP(D7,$N:$O,2,0)) | H7: =IF(G7=0,"",VLOOKUP(G7,$N:$O,2,0)) | N7: =报表格式!Z7 -> F1 | O7: =报表格式!AA7 -> 短期投资
E8: =IF(D8=0,"",VLOOKUP(D8,$N:$O,2,0)) | H8: =IF(G8=0,"",VLOOKUP(G8,$N:$O,2,0)) | N8: =报表格式!Z8 -> D3 | O8: =报表格式!AA8 -> 应收票据
J9: =IF(ABS((SUMIF(E5:E8,"?*",J5:J8)-SUMIF(H5:H8,"?*",J5:J8)))<0.005,"","借贷不等") | N9: =报表格式!Z9 -> F5 | O9: =报表格式!AA9 -> 应收股利
A10: 2 | E10: =IF(D10=0,"",VLOOKUP(D10,$N:$O,2,0)) | H10: =IF(G10=0,"",VLOOKUP(G10,$N:$O,2,0)) | N10: =报表格式!Z10 -> F6 | O10: =报表格式!AA10 -> 应收利息
E11: =IF(D11=0,"",VLOOKUP(D11,$N:$O,2,0)) | H11: =IF(G11=0,"",VLOOKUP(G11,$N:$O,2,0)) | N11: =报表格式!Z11 -> D1 | O11: =报表格式!AA11 -> 应收账款
E12: =IF(D12=0,"",VLOOKUP(D12,$N:$O,2,0)) | H12: =IF(G12=0,"",VLOOKUP(G12,$N:$O,2,0)) | N12: =报表格式!Z12 -> G4 | O12: =报表格式!AA12 -> 其他应收款
E13: =IF(D13=0,"",VLOOKUP(D13,$N:$O,2,0)) | H13: =IF(G13=0,"",VLOOKUP(G13,$N:$O,2,0)) | N13: =报表格式!Z13 -> E3 | O13: =报表格式!AA13 -> 预付账款
J14: =IF(ABS((SUMIF(E10:E13,"?*",J10:J13)-SUMIF(H10:H13,"?*",J10:J13)))<0.005,"","借贷不等") | N14: =报表格式!Z14 -> 0 | O14: =报表格式!AA14 -> 期货保证金
A15: 3 | E15: =IF(D15=0,"",VLOOKUP(D15,$N:$O,2,0)) | H15: =IF(G15=0,"",VLOOKUP(G15,$N:$O,2,0)) | N15: =报表格式!Z15 -> I1 | O15: =报表格式!AA15 -> 应收补贴款
E16: =IF(D16=0,"",VLOOKUP(D16,$N:$O,2,0)) | H16: =IF(G16=0,"",VLOOKUP(G16,$N:$O,2,0)) | N16: =报表格式!Z16 -> 0 | O16: =报表格式!AA16 -> 应收出口退税
E17: =IF(D17=0,"",VLOOKUP(D17,$N:$O,2,0)) | H17: =IF(G17=0,"",VLOOKUP(G17,$N:$O,2,0)) | N17: =报表格式!Z17 -> E1 | O17: =报表格式!AA17 -> 存货
E18: =IF(D18=0,"",VLOOKUP(D18,$N:$O,2,0)) | H18: =IF(G18=0,"",VLOOKUP(G18,$N:$O,2,0)) | N18: =报表格式!Z18 -> 0 | O18: =报表格式!AA18 -> 0
J19: =IF(ABS((SUMIF(E15:E18,"?*",J15:J18)-SUMIF(H15:H18,"?*",J15:J18)))<0.005,"","借贷不等") | N19: =报表格式!Z19 -> 0 | O19: =报表格式!AA19 -> 0
A20: 4 | E20: =IF(D20=0,"",VLOOKUP(D20,$N:$O,2,0)) | H20: =IF(G20=0,"",VLOOKUP(G20,$N:$O,2,0)) | N20: =报表格式!Z20 -> I4 | O20: =报表格式!AA20 -> 待摊费用
E21: =IF(D21=0,"",VLOOKUP(D21,$N:$O,2,0)) | H21: =IF(G21=0,"",VLOOKUP(G21,$N:$O,2,0)) | N21: =报表格式!Z21 -> I6 | O21: =报表格式!AA21 -> 待处理流动资产净损失
E22: =IF(D22=0,"",VLOOKUP(D22,$N:$O,2,0)) | H22: =IF(G22=0,"",VLOOKUP(G22,$N:$O,2,0)) | N22: =报表格式!Z22 -> 0 | O22: =报表格式!AA22 -> 一年内到期的长期债权投资
E23: =IF(D23=0,"",VLOOKUP(D23,$N:$O,2,0)) | H23: =IF(G23=0,"",VLOOKUP(G23,$N:$O,2,0)) | N23: =报表格式!Z23 -> 0 | O23: =报表格式!AA23 -> 其他流动资产
J24: =IF(ABS((SUMIF(E20:E23,"?*",J20:J23)-SUMIF(H20:H23,"?*",J20:J23)))<0.005,"","借贷不等") | N24: =报表格式!Z24 -> 0 | O24: =报表格式!AA24 -> 0
A25: 5 | E25: =IF(D25=0,"",VLOOKUP(D25,$N:$O,2,0)) | H25: =IF(G25=0,"",VLOOKUP(G25,$N:$O,2,0)) | N25: =报表格式!Z25 -> 0 | O25: =报表格式!AA25 -> 0
E26: =IF(D26=0,"",VLOOKUP(D26,$N:$O,2,0)) | H26: =IF(G26=0,"",VLOOKUP(G26,$N:$O,2,0)) | N26: =报表格式!Z26 -> 0 | O26: =报表格式!AA26 -> 流动资产合计
E27: =IF(D27=0,"",VLOOKUP(D27,$N:$O,2,0)) | H27: =IF(G27=0,"",VLOOKUP(G27,$N:$O,2,0)) | N27: =报表格式!Z27 -> 0 | O27: =报表格式!AA27 -> 0
E28: =IF(D28=0,"",VLOOKUP(D28,$N:$O,2,0)) | H28: =IF(G28=0,"",VLOOKUP(G28,$N:$O,2,0)) | N28: =报表格式!Z28 -> 0 | O28: =报表格式!AA28 -> 长期投资：
J29: =IF(ABS((SUMIF(E25:E28,"?*",J25:J28)-SUMIF(H25:H28,"?*",J25:J28)))<0.005,"","借贷不等") | N29: =报表格式!Z29 -> F2 | O29: =报表格式!AA29 -> 长期股权投资
A30: 6 | E30: =IF(D30=0,"",VLOOKUP(D30,$N:$O,2,0)) | H30: =IF(G30=0,"",VLOOKUP(G30,$N:$O,2,0)) | N30: =报表格式!Z30 -> F3 | O30: =报表格式!AA30 -> 长期债权投资
E31: =IF(D31=0,"",VLOOKUP(D31,$N:$O,2,0)) | H31: =IF(G31=0,"",VLOOKUP(G31,$N:$O,2,0)) | N31: =报表格式!Z31 -> 0 | O31: =报表格式!AA31 -> 合并价差
E32: =IF(D32=0,"",VLOOKUP(D32,$N:$O,2,0)) | H32: =IF(G32=0,"",VLOOKUP(G32,$N:$O,2,0)) | N32: =报表格式!Z32 -> 0 | O32: =报表格式!AA32 -> 0
E33: =IF(D33=0,"",VLOOKUP(D33,$N:$O,2,0)) | H33: =IF(G33=0,"",VLOOKUP(G33,$N:$O,2,0)) | N33: =报表格式!Z33 -> 0 | O33: =报表格式!AA33 -> 0
J34: =IF(ABS((SUMIF(E30:E33,"?*",J30:J33)-SUMIF(H30:H33,"?*",J30:J33)))<0.005,"","借贷不等") | N34: =报表格式!Z34 -> 0 | O34: =报表格式!AA34 -> 长期投资合计
A35: 7 | E35: =IF(D35=0,"",VLOOKUP(D35,$N:$O,2,0)) | H35: =IF(G35=0,"",VLOOKUP(G35,$N:$O,2,0)) | N35: =报表格式!Z35 -> 0 | O35: =报表格式!AA35 -> 0
E36: =IF(D36=0,"",VLOOKUP(D36,$N:$O,2,0)) | H36: =IF(G36=0,"",VLOOKUP(G36,$N:$O,2,0)) | N36: =报表格式!Z36 -> 0 | O36: =报表格式!AA36 -> 固定资产：
E37: =IF(D37=0,"",VLOOKUP(D37,$N:$O,2,0)) | H37: =IF(G37=0,"",VLOOKUP(G37,$N:$O,2,0)) | N37: =报表格式!Z37 -> H1 | O37: =报表格式!AA37 -> 固定资产原价
E38: =IF(D38=0,"",VLOOKUP(D38,$N:$O,2,0)) | H38: =IF(G38=0,"",VLOOKUP(G38,$N:$O,2,0)) | N38: =报表格式!Z38 -> H2 | O38: =报表格式!AA38 -> 累计折旧
J39: =IF(ABS((SUMIF(E35:E38,"?*",J35:J38)-SUMIF(H35:H38,"?*",J35:J38)))<0.005,"","借贷不等") | N39: =报表格式!Z39 -> 0 | O39: =报表格式!AA39 -> 0
A40: 8 | E40: =IF(D40=0,"",VLOOKUP(D40,$N:$O,2,0)) | H40: =IF(G40=0,"",VLOOKUP(G40,$N:$O,2,0)) | N40: =报表格式!Z40 -> H3 | O40: =报表格式!AA40 -> 固定资产减值准备
E41: =IF(D41=0,"",VLOOKUP(D41,$N:$O,2,0)) | H41: =IF(G41=0,"",VLOOKUP(G41,$N:$O,2,0)) | N41: =报表格式!Z41 -> 0 | O41: =报表格式!AA41 -> 0
E42: =IF(D42=0,"",VLOOKUP(D42,$N:$O,2,0)) | H42: =IF(G42=0,"",VLOOKUP(G42,$N:$O,2,0)) | N42: =报表格式!Z42 -> H4 | O42: =报表格式!AA42 -> 固定资产清理
E43: =IF(D43=0,"",VLOOKUP(D43,$N:$O,2,0)) | H43: =IF(G43=0,"",VLOOKUP(G43,$N:$O,2,0)) | N43: =报表格式!Z43 -> H7 | O43: =报表格式!AA43 -> 工程物资
J44: =IF(ABS((SUMIF(E40:E43,"?*",J40:J43)-SUMIF(H40:H43,"?*",J40:J43)))<0.005,"","借贷不等") | N44: =报表格式!Z44 -> H6 | O44: =报表格式!AA44 -> 在建工程
A45: 9 | E45: =IF(D45=0,"",VLOOKUP(D45,$N:$O,2,0)) | H45: =IF(G45=0,"",VLOOKUP(G45,$N:$O,2,0)) | N45: =报表格式!Z45 -> H5 | O45: =报表格式!AA45 -> 待处理固定资产净损失
E46: =IF(D46=0,"",VLOOKUP(D46,$N:$O,2,0)) | H46: =IF(G46=0,"",VLOOKUP(G46,$N:$O,2,0)) | N46: =报表格式!Z46 -> 0 | O46: =报表格式!AA46 -> 0
E47: =IF(D47=0,"",VLOOKUP(D47,$N:$O,2,0)) | H47: =IF(G47=0,"",VLOOKUP(G47,$N:$O,2,0)) | N47: =报表格式!Z47 -> 0 | O47: =报表格式!AA47 -> 0
E48: =IF(D48=0,"",VLOOKUP(D48,$N:$O,2,0)) | H48: =IF(G48=0,"",VLOOKUP(G48,$N:$O,2,0)) | N48: =报表格式!Z48 -> 0 | O48: =报表格式!AA48 -> 固定资产合计
J49: =IF(ABS((SUMIF(E45:E48,"?*",J45:J48)-SUMIF(H45:H48,"?*",J45:J48)))<0.005,"","借贷不等") | N49: =报表格式!Z49 -> 0 | O49: =报表格式!AA49 -> 无形资产及其他资产：
A50: 10 | E50: =IF(D50=0,"",VLOOKUP(D50,$N:$O,2,0)) | H50: =IF(G50=0,"",VLOOKUP(G50,$N:$O,2,0)) | N50: =报表格式!Z50 -> I2 | O50: =报表格式!AA50 -> 无形资产
E51: =IF(D51=0,"",VLOOKUP(D51,$N:$O,2,0)) | H51: =IF(G51=0,"",VLOOKUP(G51,$N:$O,2,0)) | N51: =报表格式!Z51 -> 0 | O51: =报表格式!AA51 -> 0
E52: =IF(D52=0,"",VLOOKUP(D52,$N:$O,2,0)) | H52: =IF(G52=0,"",VLOOKUP(G52,$N:$O,2,0)) | N52: =报表格式!Z52 -> I5 | O52: =报表格式!AA52 -> 长期待摊费用
E53: =IF(D53=0,"",VLOOKUP(D53,$N:$O,2,0)) | H53: =IF(G53=0,"",VLOOKUP(G53,$N:$O,2,0)) | N53: =报表格式!Z53 -> 0 | O53: =报表格式!AA53 -> 0
J54: =IF(ABS((SUMIF(E50:E53,"?*",J50:J53)-SUMIF(H50:H53,"?*",J50:J53)))<0.005,"","借贷不等") | N54: =报表格式!Z54 -> 0 | O54: =报表格式!AA54 -> 0
A55: 11 | E55: =IF(D55=0,"",VLOOKUP(D55,$N:$O,2,0)) | H55: =IF(G55=0,"",VLOOKUP(G55,$N:$O,2,0)) | N55: =报表格式!Z55 -> 0 | O55: =报表格式!AA55 -> 股权分置流通权
E56: =IF(D56=0,"",VLOOKUP(D56,$N:$O,2,0)) | H56: =IF(G56=0,"",VLOOKUP(G56,$N:$O,2,0)) | N56: =报表格式!Z56 -> 0 | O56: =报表格式!AA56 -> 其他长期资产
E57: =IF(D57=0,"",VLOOKUP(D57,$N:$O,2,0)) | H57: =IF(G57=0,"",VLOOKUP(G57,$N:$O,2,0)) | N57: =报表格式!Z57 -> 0 | O57: =报表格式!AA57 -> 0
E58: =IF(D58=0,"",VLOOKUP(D58,$N:$O,2,0)) | H58: =IF(G58=0,"",VLOOKUP(G58,$N:$O,2,0)) | N58: =报表格式!Z58 -> 0 | O58: =报表格式!AA58 -> 0
J59: =IF(ABS((SUMIF(E55:E58,"?*",J55:J58)-SUMIF(H55:H58,"?*",J55:J58)))<0.005,"","借贷不等") | N59: =报表格式!Z59 -> 0 | O59: =报表格式!AA59 -> 无形资产及其他资产合计
A60: 12 | E60: =IF(D60=0,"",VLOOKUP(D60,$N:$O,2,0)) | H60: =IF(G60=0,"",VLOOKUP(G60,$N:$O,2,0)) | N60: =报表格式!Z60 -> 0 | O60: =报表格式!AA60 -> 递延税项：
E61: =IF(D61=0,"",VLOOKUP(D61,$N:$O,2,0)) | H61: =IF(G61=0,"",VLOOKUP(G61,$N:$O,2,0)) | N61: =报表格式!Z61 -> I18-1 | O61: =报表格式!AA61 -> 递延税款借项
E62: =IF(D62=0,"",VLOOKUP(D62,$N:$O,2,0)) | H62: =IF(G62=0,"",VLOOKUP(G62,$N:$O,2,0)) | N62: =报表格式!Z62 -> 0 | O62: =报表格式!AA62 -> 0
E63: =IF(D63=0,"",VLOOKUP(D63,$N:$O,2,0)) | H63: =IF(G63=0,"",VLOOKUP(G63,$N:$O,2,0)) | N63: =报表格式!Z63 -> 0 | O63: =报表格式!AA63 -> 资产总计
J64: =IF(ABS((SUMIF(E60:E63,"?*",J60:J63)-SUMIF(H60:H63,"?*",J60:J63)))<0.005,"","借贷不等") | N64: =报表格式!Z64 -> 0 | O64: =报表格式!AA64 -> 0
A65: 13 | E65: =IF(D65=0,"",VLOOKUP(D65,$N:$O,2,0)) | H65: =IF(G65=0,"",VLOOKUP(G65,$N:$O,2,0)) | N65: =报表格式!Z65 -> 0 | O65: =报表格式!AA65 -> 流动负债：
E66: =IF(D66=0,"",VLOOKUP(D66,$N:$O,2,0)) | H66: =IF(G66=0,"",VLOOKUP(G66,$N:$O,2,0)) | N66: =报表格式!Z66 -> F11 | O66: =报表格式!AA66 -> 短期借款
E67: =IF(D67=0,"",VLOOKUP(D67,$N:$O,2,0)) | H67: =IF(G67=0,"",VLOOKUP(G67,$N:$O,2,0)) | N67: =报表格式!Z67 -> E12 | O67: =报表格式!AA67 -> 应付票据
E68: =IF(D68=0,"",VLOOKUP(D68,$N:$O,2,0)) | H68: =IF(G68=0,"",VLOOKUP(G68,$N:$O,2,0)) | N68: =报表格式!Z68 -> E11 | O68: =报表格式!AA68 -> 应付账款
J69: =IF(ABS((SUMIF(E65:E68,"?*",J65:J68)-SUMIF(H65:H68,"?*",J65:J68)))<0.005,"","借贷不等") | N69: =报表格式!Z69 -> D11 | O69: =报表格式!AA69 -> 预收账款
A70: 14 | E70: =IF(D70=0,"",VLOOKUP(D70,$N:$O,2,0)) | H70: =IF(G70=0,"",VLOOKUP(G70,$N:$O,2,0)) | N70: =报表格式!Z70 -> E16 | O70: =报表格式!AA70 -> 应付工资
E71: =IF(D71=0,"",VLOOKUP(D71,$N:$O,2,0)) | H71: =IF(G71=0,"",VLOOKUP(G71,$N:$O,2,0)) | N71: =报表格式!Z71 -> E17 | O71: =报表格式!AA71 -> 应付福利费
E72: =IF(D72=0,"",VLOOKUP(D72,$N:$O,2,0)) | H72: =IF(G72=0,"",VLOOKUP(G72,$N:$O,2,0)) | N72: =报表格式!Z72 -> F15 | O72: =报表格式!AA72 -> 应付股利（利润）
E73: =IF(D73=0,"",VLOOKUP(D73,$N:$O,2,0)) | H73: =IF(G73=0,"",VLOOKUP(G73,$N:$O,2,0)) | N73: =报表格式!Z73 -> F14 | O73: =报表格式!AA73 -> 应付利息
J74: =IF(ABS((SUMIF(E70:E73,"?*",J70:J73)-SUMIF(H70:H73,"?*",J70:J73)))<0.005,"","借贷不等") | N74: =报表格式!Z74 -> I16 | O74: =报表格式!AA74 -> 应交税金
A75: 15 | E75: =IF(D75=0,"",VLOOKUP(D75,$N:$O,2,0)) | H75: =IF(G75=0,"",VLOOKUP(G75,$N:$O,2,0)) | N75: =报表格式!Z75 -> I17 | O75: =报表格式!AA75 -> 其他应交款
E76: =IF(D76=0,"",VLOOKUP(D76,$N:$O,2,0)) | H76: =IF(G76=0,"",VLOOKUP(G76,$N:$O,2,0)) | N76: =报表格式!Z76 -> G11 | O76: =报表格式!AA76 -> 其他应付款
E77: =IF(D77=0,"",VLOOKUP(D77,$N:$O,2,0)) | H77: =IF(G77=0,"",VLOOKUP(G77,$N:$O,2,0)) | N77: =报表格式!Z77 -> I11 | O77: =报表格式!AA77 -> 预提费用
E78: =IF(D78=0,"",VLOOKUP(D78,$N:$O,2,0)) | H78: =IF(G78=0,"",VLOOKUP(G78,$N:$O,2,0)) | N78: =报表格式!Z78 -> I19 | O78: =报表格式!AA78 -> 预计负债
J79: =IF(ABS((SUMIF(E75:E78,"?*",J75:J78)-SUMIF(H75:H78,"?*",J75:J78)))<0.005,"","借贷不等") | N79: =报表格式!Z79 -> D12 | O79: =报表格式!AA79 -> 递延收益
A80: 16 | E80: =IF(D80=0,"",VLOOKUP(D80,$N:$O,2,0)) | H80: =IF(G80=0,"",VLOOKUP(G80,$N:$O,2,0)) | N80: =报表格式!Z80 -> 0 | O80: =报表格式!AA80 -> 一年内到期的长期负债
E81: =IF(D81=0,"",VLOOKUP(D81,$N:$O,2,0)) | H81: =IF(G81=0,"",VLOOKUP(G81,$N:$O,2,0)) | N81: =报表格式!Z81 -> 0 | O81: =报表格式!AA81 -> 应付权证
E82: =IF(D82=0,"",VLOOKUP(D82,$N:$O,2,0)) | H82: =IF(G82=0,"",VLOOKUP(G82,$N:$O,2,0)) | N82: =报表格式!Z82 -> 0 | O82: =报表格式!AA82 -> 其他流动负债
E83: =IF(D83=0,"",VLOOKUP(D83,$N:$O,2,0)) | H83: =IF(G83=0,"",VLOOKUP(G83,$N:$O,2,0)) | N83: =报表格式!Z83 -> 0 | O83: =报表格式!AA83 -> 0
J84: =IF(ABS((SUMIF(E80:E83,"?*",J80:J83)-SUMIF(H80:H83,"?*",J80:J83)))<0.005,"","借贷不等") | N84: =报表格式!Z84 -> 0 | O84: =报表格式!AA84 -> 0
A85: 17 | E85: =IF(D85=0,"",VLOOKUP(D85,$N:$O,2,0)) | H85: =IF(G85=0,"",VLOOKUP(G85,$N:$O,2,0)) | N85: =报表格式!Z85 -> 0 | O85: =报表格式!AA85 -> 流动负债合计
E86: =IF(D86=0,"",VLOOKUP(D86,$N:$O,2,0)) | H86: =IF(G86=0,"",VLOOKUP(G86,$N:$O,2,0)) | N86: =报表格式!Z86 -> 0 | O86: =报表格式!AA86 -> 0
E87: =IF(D87=0,"",VLOOKUP(D87,$N:$O,2,0)) | H87: =IF(G87=0,"",VLOOKUP(G87,$N:$O,2,0)) | N87: =报表格式!Z87 -> 0 | O87: =报表格式!AA87 -> 长期负债：
E88: =IF(D88=0,"",VLOOKUP(D88,$N:$O,2,0)) | H88: =IF(G88=0,"",VLOOKUP(G88,$N:$O,2,0)) | N88: =报表格式!Z88 -> F12 | O88: =报表格式!AA88 -> 长期借款
J89: =IF(ABS((SUMIF(E85:E88,"?*",J85:J88)-SUMIF(H85:H88,"?*",J85:J88)))<0.005,"","借贷不等") | N89: =报表格式!Z89 -> F13 | O89: =报表格式!AA89 -> 应付债券
A90: 18 | E90: =IF(D90=0,"",VLOOKUP(D90,$N:$O,2,0)) | H90: =IF(G90=0,"",VLOOKUP(G90,$N:$O,2,0)) | N90: =报表格式!Z90 -> G12 | O90: =报表格式!AA90 -> 长期应付款
E91: =IF(D91=0,"",VLOOKUP(D91,$N:$O,2,0)) | H91: =IF(G91=0,"",VLOOKUP(G91,$N:$O,2,0)) | N91: =报表格式!Z91 -> G13 | O91: =报表格式!AA91 -> 专项应付款
E92: =IF(D92=0,"",VLOOKUP(D92,$N:$O,2,0)) | H92: =IF(G92=0,"",VLOOKUP(G92,$N:$O,2,0)) | N92: =报表格式!Z92 -> 0 | O92: =报表格式!AA92 -> 其他长期负债
E93: =IF(D93=0,"",VLOOKUP(D93,$N:$O,2,0)) | H93: =IF(G93=0,"",VLOOKUP(G93,$N:$O,2,0)) | N93: =报表格式!Z93 -> 0 | O93: =报表格式!AA93 -> 0
J94: =IF(ABS((SUMIF(E90:E93,"?*",J90:J93)-SUMIF(H90:H93,"?*",J90:J93)))<0.005,"","借贷不等") | N94: =报表格式!Z94 -> 0 | O94: =报表格式!AA94 -> 0
A95: 19 | E95: =IF(D95=0,"",VLOOKUP(D95,$N:$O,2,0)) | H95: =IF(G95=0,"",VLOOKUP(G95,$N:$O,2,0)) | N95: =报表格式!Z95 -> 0 | O95: =报表格式!AA95 -> 0
E96: =IF(D96=0,"",VLOOKUP(D96,$N:$O,2,0)) | H96: =IF(G96=0,"",VLOOKUP(G96,$N:$O,2,0)) | N96: =报表格式!Z96 -> 0 | O96: =报表格式!AA96 -> 长期负债合计
E97: =IF(D97=0,"",VLOOKUP(D97,$N:$O,2,0)) | H97: =IF(G97=0,"",VLOOKUP(G97,$N:$O,2,0)) | N97: =报表格式!Z97 -> 0 | O97: =报表格式!AA97 -> 0
E98: =IF(D98=0,"",VLOOKUP(D98,$N:$O,2,0)) | H98: =IF(G98=0,"",VLOOKUP(G98,$N:$O,2,0)) | N98: =报表格式!Z98 -> 0 | O98: =报表格式!AA98 -> 递延税项：
J99: =IF(ABS((SUMIF(E95:E98,"?*",J95:J98)-SUMIF(H95:H98,"?*",J95:J98)))<0.005,"","借贷不等") | N99: =报表格式!Z99 -> I18-2 | O99: =报表格式!AA99 -> 递延税款贷项
A100: 20 | E100: =IF(D100=0,"",VLOOKUP(D100,$N:$O,2,0)) | H100: =IF(G100=0,"",VLOOKUP(G100,$N:$O,2,0)) | N100: =报表格式!Z100 -> 0 | O100: =报表格式!AA100 -> 0
...

Sheet  
A1: 报表数值 | B1: 逻辑值 | C1: 判断值 | E1: =NOW() -> 45152.7
A3: =SUM(#REF!)+SUM(#REF!)+SUM(#REF!)+SUM(#REF!)+SUM(#REF!)+SUM(#REF!) -> #REF! | B3: =ISERROR(A3) -> TRUE | C3: =IF(B3=TRUE,"您误使用了剪切或拖拽功能，请用撤销键撤销此操作!!",0) -> 您误使用了剪切或拖拽功能，请用撤销键撤销此操作!!
A5: =IF(ABS(' '!E5)>0.0049,"注意！报表项目栏有空格，试算平衡表将不能统计该栏数据！请填写报表项目名称。",IF(ABS(' '!F5)<0.005,IF(ABS(' '!G5-' '!H5)<0.005,IF(#REF!="调整金额合计",IF(ABS(#REF!)<0.005,IF(ABS(#REF!)<0.005,IF(ABS(#REF!)<0.005,IF(#REF!-#REF!=0,""," 审计调整分录使本年净利润净增加："),"客户同意调整的分录不完整,使期初未分配利润与上期报表数不等。请继续调整！差额:"),"调整分录已使本年“年初未分配利润”和上年“末分配利润”不等。请作进一步调整。"),"调整分录错误！上年的报表项目不能与本年的报表项目套在一起出分录，请纠正；或者已输入的会计分录名称在“02报表格式”中已被修改，请手工作相应修改。"),""),"客户同意调整的分录不平，将导致客户报出会计报表不平，请检查!!差额为："),"“以前年度损益调整”应进一步结转入“年初未分配利润”等科目,借贷相抵后差额为：")) -> #REF! | B5: =IF(ABS(' '!E5)>0.0049,"",IF(ABS(' '!F5)<0.005,IF(ABS(' '!G5-' '!H5)<0.005,IF(#REF!="调整金额合计",IF(ABS(#REF!)<0.005,IF(ABS(#REF!)<0.005,IF(ABS(#REF!)<0.005,IF(#REF!-#REF!=0,"",#REF!-#REF!),#REF!),#REF!),#REF!),""),' '!G5-' '!H5),ABS(' '!F5))) -> #REF! | C5: =SUMIF(#REF!,"",#REF!) -> #REF! | D5: =SUMIF(#REF!,"",#REF!) -> #REF! | E5: =ABS(' '!C5)+ABS(' '!D5) -> #REF! | F5: =SUMIF(#REF!,"以前年度损益调整",#REF!)-SUMIF(#REF!,"以前年度损益调整",#REF!) -> #REF! | G5: =SUMIF(#REF!,"Y",#REF!) -> #REF! | H5: =SUMIF(#REF!,"Y",#REF!) -> #REF! | K5: =CONCATENATE("被审计单位：",参数!D3) -> 被审计单位： | L5: =IF(A8=0,CONCATENATE(A5,B5),"请注意，您在第"&(A7-1)&"行之后输入了数据，本系统无法汇总到这些数据。请撤消此操作，然后在第"&(A7-1)&"行之前插入空白行，并在这些空白行中重新输入或粘贴数据。") -> #REF! | Q5: =IF(ABS(#REF!-#REF!)<0.005,"调整金额合计","调整金额借贷不等,请检查!差额为:") -> #REF! | S5: =IF(#REF!=#REF!,"",#REF!-#REF!) -> #REF! | U5: =CONCATENATE("会计期间： ",参数!D10) -> 会计期间： 2007年度
A6: =IF(#REF!=0,IF(#REF!=0,IF(#REF!=0,IF(#REF!=0,"", "客户同意调整的分录不平，导致客户报出报表不平，请检查!!差额为："),"客户同意调整的分录不平，导致客户报出报表不平，请检查!!差额为："),"调整分录使试算平衡表中“现金及现金等价物净增加额”上下不等,差额为："),"调整分录使试算平衡表中“经营活动产生的现金流量”上下不等,差额为：") -> #REF! | I6: =IF(#REF!=0,IF(#REF!=0,IF(#REF!=0,IF(#REF!=0,"",#REF!),#REF!),#REF!),#REF!) -> #REF! | J6: =CONCATENATE(A6,I6) -> #REF! | N6: =CONCATENATE("调整事项使现金净流量增加：",ROUND(#REF!-#REF!,2),"元。其中，","调增",ROUND(#REF!,2),"元，调减",ROUND(#REF!,2),"元。") -> #REF!
A7: =ROW(#REF!) -> #REF!
A8: =SUM(#REF!) -> #REF!

Sheet CF调整
A1: 现金流量表调整
A2: =参数!D10 -> 2007年度
A3: 项 目 | B3: 原报金额 | C3: 调整金额 | D3: 审定金额
A5: 一、经营活动产生的现金流量
A6: 销售商品、提供劳务收到的现金 | B6: =未审CF!C7 -> 0 | D6: =SUM(B6:C6) -> 0
A7: 收到的税费返还 | B7: =未审CF!C8 -> 0 | D7: =SUM(B7:C7) -> 0
A8: 收到的其他与经营活动有关的现金 | B8: =未审CF!C9 -> 0 | D8: =SUM(B8:C8) -> 0
A9: 现金流入小计 | B9: =SUM(B6:B8) -> 0 | C9: =SUM(C6:C8) -> 0 | D9: =SUM(D6:D8) -> 0
A10: 购买商品、接受劳务支付的现金 | B10: =未审CF!C12 -> 0 | D10: =SUM(B10:C10) -> 0
A11: 支付给职工以及为职工支付的现金 | B11: =未审CF!C13 -> 0 | D11: =SUM(B11:C11) -> 0
A12: 支付的各项税费 | B12: =未审CF!C14 -> 0 | D12: =SUM(B12:C12) -> 0
A13: 支付的其他与经营活动有关的现金 | B13: =未审CF!C15 -> 0 | D13: =SUM(B13:C13) -> 0
A14: 现金流出小计 | B14: =B10+B11+B12+B13 -> 0 | C14: =C10+C11+C12+C13 -> 0 | D14: =D10+D11+D12+D13 -> 0
A15: 经营活动产生的现金流量净额 | B15: =B9-B14 -> 0 | C15: =C9-C14 -> 0 | D15: =D9-D14 -> 0
A17: 二、投资活动产生的现金流量：
A18: 收回投资所收到的现金 | B18: =未审CF!C20 -> 0 | D18: =SUM(B18:C18) -> 0
A19: 其中：出售子公司所收到的现金 | B19: =未审CF!C21 -> 0 | D19: =SUM(B19:C19) -> 0
A20: 取得投资收益所收到的现金 | B20: =未审CF!C22 -> 0 | D20: =SUM(B20:C20) -> 0
A21: 处置固定资产、无形资产和其他长期资产所收回的现金净额 | B21: =未审CF!C23 -> 0 | D21: =SUM(B21:C21) -> 0
A22: 收到的其他与投资活动有关的现金 | B22: =未审CF!C24 -> 0 | D22: =SUM(B22:C22) -> 0
A23: 现金流入小计 | B23: =SUM(B18:B22)-B19 -> 0 | C23: =SUM(C18:C22)-C19 -> 0 | D23: =SUM(D18:D22)-D19 -> 0
A24: 购建固定资产、无形资产和其他长期资产所支付的现金 | B24: =未审CF!C27 -> 0 | D24: =SUM(B24:C24) -> 0
A25: 投资所支付的现金 | B25: =未审CF!C28 -> 0 | D25: =SUM(B25:C25) -> 0
A26: 其中：购买子公司所支付的现金 | B26: =未审CF!C29 -> 0 | D26: =SUM(B26:C26) -> 0
A27: 支付的其他与投资活动有关的现金 | B27: =未审CF!C30 -> 0 | D27: =SUM(B27:C27) -> 0
A28: 现金流出小计 | B28: =SUM(B24:B27)-B26 -> 0 | C28: =SUM(C24:C27)-C26 -> 0 | D28: =SUM(D24:D27)-D26 -> 0
A29: 投资活动产生的现金流量净额 | B29: =B23-B28 -> 0 | C29: =C23-C28 -> 0 | D29: =D23-D28 -> 0
A31: 三、筹资活动产生的现金流量：
A32: 吸收投资所收到的现金 | B32: =未审CF!C35 -> 0 | D32: =SUM(B32:C32) -> 0
A33: 借款所收到的现金 | B33: =未审CF!C36 -> 0 | D33: =SUM(B33:C33) -> 0
A34: 收到的其他与筹资活动有关的现金 | B34: =未审CF!C37 -> 0 | D34: =SUM(B34:C34) -> 0
A35: 现金流入小计 | B35: =SUM(B32:B34) -> 0 | C35: =SUM(C32:C34) -> 0 | D35: =SUM(D32:D34) -> 0
A36: 偿还债务所支付的现金 | B36: =未审CF!C40 -> 0 | D36: =SUM(B36:C36) -> 0
A37: 分配股利、利润或偿付利息所支付的现金 | B37: =未审CF!C41 -> 0 | D37: =SUM(B37:C37) -> 0
A38: 支付的其他与筹资活动有关的现金 | B38: =未审CF!C42 -> 0 | D38: =SUM(B38:C38) -> 0
A39: 现金流出小计 | B39: =B36+B37+B38 -> 0 | C39: =C36+C37+C38 -> 0 | D39: =D36+D37+D38 -> 0
A40: 筹资活动产生的现金流量净额 | B40: =B35-B39 -> 0 | C40: =C35-C39 -> 0 | D40: =D35-D39 -> 0
A42: 四、汇率变动对现金的影响 | B42: =未审CF!C46 -> 0 | D42: =SUM(B42:C42) -> 0
A44: 五、现金及现金等价物净增加额 | B44: =B15+B29+B40+B42 -> 0 | C44: =C15+C29+C40+C42 -> 0 | D44: =D15+D29+D40+D42 -> 0
A46: 1、将净利润调节为经营活动现金流量：
A47: 净利润 | B47: =未审CF!F7 -> 0 | C47: =TB损益!I53-TB损益!B53 -> 0 | D47: =SUM(B47:C47) -> 0
A48: 加：少数股东损益 | B48: =未审CF!F8 -> 0 | C48: =TB损益!C51-TB损益!D51+TB损益!E51-TB损益!F51 -> 0 | D48: =SUM(B48:C48) -> 0
A49: 减：*未确认投资损失 | B49: =未审CF!F9 -> 0 | C49: =TB损益!C52-TB损益!D52+TB损益!E52-TB损益!F52 -> 0 | D49: =SUM(B49:C49) -> 0
A50: 加：计提的资产减值准备 | B50: =未审CF!F10 -> 0 | D50: =SUM(B50:C50) -> 0
A51: 固定资产折旧 | B51: =未审CF!F11 -> 0 | C51: =-TB资产!C37+TB资产!D37-TB资产!E37+TB资产!F37 -> 0 | D51: =SUM(B51:C51) -> 0
A52: 无形资产摊销 | B52: =未审CF!F12 -> 0 | D52: =SUM(B52:C52) -> 0
A53: 长期待摊费用摊销 | B53: =未审CF!F13 -> 0 | D53: =SUM(B53:C53) -> 0
A54: 待摊费用减少（减：增加） | B54: =未审CF!F14 -> 0 | C54: =-TB资产!C21+TB资产!D21-TB资产!E21+TB资产!F21 -> 0 | D54: =SUM(B54:C54) -> 0
A55: 预提费用增加（减：减少） | B55: =未审CF!F15 -> 0 | C55: =-TB负债!C18+TB负债!D18-TB负债!E18+TB负债!F18 -> 0 | D55: =SUM(B55:C55) -> 0
A56: 处置固定资产、无形资产和其他长期资产的损失（减：收益） | B56: =未审CF!F16 -> 0 | D56: =SUM(B56:C56) -> 0
A57: 固定资产报废损失 | B57: =未审CF!F17 -> 0 | D57: =SUM(B57:C57) -> 0
A58: 财务费用 | B58: =未审CF!F18 -> 0 | C58: =TB损益!C25-TB损益!D25+TB损益!E25-TB损益!F25 -> 0 | D58: =SUM(B58:C58) -> 0
A59: 投资损失（减：收益） | B59: =未审CF!F19 -> 0 | C59: =-(-TB损益!C31+TB损益!D31-TB损益!E31+TB损益!F31) -> 0 | D59: =SUM(B59:C59) -> 0
A60: 递延税款贷项（减：借项） | B60: =未审CF!F20 -> 0 | C60: =-TB负债!C38+TB负债!D38-TB负债!E38+TB负债!F38+TB资产!C60-TB资产!D60+TB资产!E60-TB资产!F60 -> 0 | D60: =SUM(B60:C60) -> 0
A61: 存货的减少（减：增加） | B61: =未审CF!F21 -> 0 | C61: =-TB资产!C18+TB资产!D18-TB资产!E18+TB资产!F18 -> 0 | D61: =SUM(B61:C61) -> 0
A62: 经营性应收项目的减少（减：增加） | B62: =未审CF!F22 -> 0 | C62: =-TB资产!C9+TB资产!D9-TB资产!E9+TB资产!F9-TB资产!C12+TB资产!D12-TB资产!E12+TB资产!F12-TB资产!C13+TB资产!D13-TB资产!E13+TB资产!F13-TB资产!C24+TB资产!D24-TB资产!E24+TB资产!F24+TB负债!C10-TB负债!D10+TB负债!E10-TB负债!F10 -> 0 | D62: =SUM(B62:C62) -> 0
A63: 经营性应付项目的增加（减：减少） | B63: =未审CF!F23 -> 0 | C63: =-TB负债!C8+TB负债!D8-TB负债!E8+TB负债!F8-TB负债!C9+TB负债!D9-TB负债!E9+TB负债!F9-TB负债!C11+TB负债!D11-TB负债!E11+TB负债!F11-TB负债!C12+TB负债!D12-TB负债!E12+TB负债!F12-TB负债!C13+TB负债!D13-TB负债!E13+TB负债!F13-TB负债!C15+TB负债!D15-TB负债!E15+TB负债!F15-TB负债!C16+TB负债!D16-TB负债!E16+TB负债!F16-TB负债!C17+TB负债!D17-TB负债!E17+TB负债!F17-TB负债!C23+TB负债!D23-TB负债!E23+TB负债!F23+TB资产!C14-TB资产!D14+TB资产!E14-TB资产!F14 -> 0 | D63: =SUM(B63:C63) -> 0
A64: 其他 | B64: =未审CF!F24 -> 0 | D64: =SUM(B64:C64) -> 0
A65: 经营活动产生的现金流量净额 | B65: =SUM(B47:B48,-B49,B50:B64) -> 0 | C65: =SUM(C47:C48,-C49,C50:C64) -> 0 | D65: =SUM(D47:D48,-D49,D50:D64) -> 0
A67: 2、不涉及现金收支的投资和筹资活动：
A68: 债务转为资本 | B68: =未审CF!F30 -> 0 | D68: =SUM(B68:C68) -> 0
A69: 一年内到期的可转换公司债券 | B69: =未审CF!F31 -> 0 | D69: =SUM(B69:C69) -> 0
A70: 融资租入固定资产 | B70: =未审CF!F32 -> 0 | D70: =SUM(B70:C70) -> 0
B71: =未审CF!F33 -> 0 | D71: =SUM(B71:C71) -> 0
A72: 3、现金及现金等价物净增加情况：
A73: 现金的期末余额 | B73: =未审CF!F36 -> 0 | C73: =TB资产!C7-TB资产!D7+TB资产!E7-TB资产!F7 -> 0 | D73: =SUM(B73:C73) -> 0
A74: 减：现金的期初余额 | B74: =未审CF!F37 -> 0 | C74: ='TB资产(期初)'!C7-'TB资产(期初)'!D7+'TB资产(期初)'!E7-'TB资产(期初)'!F7 -> 0 | D74: =SUM(B74:C74) -> 0
A75: 加：现金等价物的期末余额 | B75: =未审CF!F38 -> 0 | D75: =SUM(B75:C75) -> 0
A76: 减：现金等价物的期初余额 | B76: =未审CF!F39 -> 0 | D76: =SUM(B76:C76) -> 0
A77: 现金及现金等价物净增加额 | B77: =B73-B74+B75-B76 -> 0 | C77: =C73-C74+C75-C76 -> 0 | D77: =D73-D74+D75-D76 -> 0

Sheet TB资产
A1: 资产负债表试算平衡
A2: =CONCATENATE("客户名称：",参数!D3) -> 客户名称： | C2: =CONCATENATE("编制：",参数!D17) -> 编制： | E2: =CONCATENATE("复核：",参数!D18) -> 复核： | I2: 索引：
A3: =CONCATENATE("会计时点：",TEXT(参数!D12,"yyyy.mm.dd")) -> 会计时点：2007.12.31 | C3: =CONCATENATE("日期：",TEXT(NOW(),"yyyy.mm.dd")) -> 日期：2023.08.14 | E3: 日期： | I3: 分页：
A4: =IF((ROUND(I62,2))=(ROUND(TB负债!I62,2)),"资 产","报表未调平!") -> 资 产 | B4: 企业原报数 | C4: 账项调整 | E4: 报表调整 | G4: 调后数 | H4: 剥离调整 | I4: 审定数
C5: 借方 | D5: 贷方 | E5: 借方 | F5: 贷方
A6: =报表格式!B5 -> 流动资产：
A7: =报表格式!B6 -> 货币资金 | B7: =未审BS!D7 -> 0 | C7: =SUMIF(账项调整!$E$5:$E$65536,IF(OR(MID(TRIM($A7),2,1)="：",MID(TRIM($A7),2,1)="、"),REPLACEB(TRIM($A7),1,4,""),TRIM($A7)),账项调整!$J$5:$J$65536) -> 0 | D7: =SUMIF(账项调整!$H$5:$H$65536,IF(OR(MID(TRIM($A7),2,1)="：",MID(TRIM($A7),2,1)="、"),REPLACEB(TRIM($A7),1,4,""),TRIM($A7)),账项调整!$J$5:$J$65536) -> 0 | E7: =SUMIF(报表调整!$E$5:$E$65536,IF(OR(MID(TRIM($A7),2,1)="：",MID(TRIM($A7),2,1)="、"),REPLACEB(TRIM($A7),1,4,""),TRIM($A7)),报表调整!$J$5:$J$65536) -> 0 | F7: =SUMIF(报表调整!$H$5:$H$65536,IF(OR(MID(TRIM($A7),2,1)="：",MID(TRIM($A7),2,1)="、"),REPLACEB(TRIM($A7),1,4,""),TRIM($A7)),报表调整!$J$5:$J$65536) -> 0 | G7: =B7+C7+E7-D7-F7 -> 0 | I7: =SUM(G7:H7) -> 0
A8: =报表格式!B7 -> 短期投资 | B8: =未审BS!D8 -> 0 | C8: =SUMIF(账项调整!$E$5:$E$65536,IF(OR(MID(TRIM($A8),2,1)="：",MID(TRIM($A8),2,1)="、"),REPLACEB(TRIM($A8),1,4,""),TRIM($A8)),账项调整!$J$5:$J$65536) -> 0 | D8: =SUMIF(账项调整!$H$5:$H$65536,IF(OR(MID(TRIM($A8),2,1)="：",MID(TRIM($A8),2,1)="、"),REPLACEB(TRIM($A8),1,4,""),TRIM($A8)),账项调整!$J$5:$J$65536) -> 0 | E8: =SUMIF(报表调整!$E$5:$E$65536,IF(OR(MID(TRIM($A8),2,1)="：",MID(TRIM($A8),2,1)="、"),REPLACEB(TRIM($A8),1,4,""),TRIM($A8)),报表调整!$J$5:$J$65536) -> 0 | F8: =SUMIF(报表调整!$H$5:$H$65536,IF(OR(MID(TRIM($A8),2,1)="：",MID(TRIM($A8),2,1)="、"),REPLACEB(TRIM($A8),1,4,""),TRIM($A8)),报表调整!$J$5:$J$65536) -> 0 | G8: =B8+C8+E8-D8-F8 -> 0 | I8: =SUM(G8:H8) -> 0
A9: =报表格式!B8 -> 应收票据 | B9: =未审BS!D9 -> 0 | C9: =SUMIF(账项调整!$E$5:$E$65536,IF(OR(MID(TRIM($A9),2,1)="：",MID(TRIM($A9),2,1)="、"),REPLACEB(TRIM($A9),1,4,""),TRIM($A9)),账项调整!$J$5:$J$65536) -> 0 | D9: =SUMIF(账项调整!$H$5:$H$65536,IF(OR(MID(TRIM($A9),2,1)="：",MID(TRIM($A9),2,1)="、"),REPLACEB(TRIM($A9),1,4,""),TRIM($A9)),账项调整!$J$5:$J$65536) -> 0 | E9: =SUMIF(报表调整!$E$5:$E$65536,IF(OR(MID(TRIM($A9),2,1)="：",MID(TRIM($A9),2,1)="、"),REPLACEB(TRIM($A9),1,4,""),TRIM($A9)),报表调整!$J$5:$J$65536) -> 0 | F9: =SUMIF(报表调整!$H$5:$H$65536,IF(OR(MID(TRIM($A9),2,1)="：",MID(TRIM($A9),2,1)="、"),REPLACEB(TRIM($A9),1,4,""),TRIM($A9)),报表调整!$J$5:$J$65536) -> 0 | G9: =B9+C9+E9-D9-F9 -> 0 | I9: =SUM(G9:H9) -> 0
A10: =报表格式!B9 -> 应收股利 | B10: =未审BS!D10 -> 0 | C10: =SUMIF(账项调整!$E$5:$E$65536,IF(OR(MID(TRIM($A10),2,1)="：",MID(TRIM($A10),2,1)="、"),REPLACEB(TRIM($A10),1,4,""),TRIM($A10)),账项调整!$J$5:$J$65536) -> 0 | D10: =SUMIF(账项调整!$H$5:$H$65536,IF(OR(MID(TRIM($A10),2,1)="：",MID(TRIM($A10),2,1)="、"),REPLACEB(TRIM($A10),1,4,""),TRIM($A10)),账项调整!$J$5:$J$65536) -> 0 | E10: =SUMIF(报表调整!$E$5:$E$65536,IF(OR(MID(TRIM($A10),2,1)="：",MID(TRIM($A10),2,1)="、"),REPLACEB(TRIM($A10),1,4,""),TRIM($A10)),报表调整!$J$5:$J$65536) -> 0 | F10: =SUMIF(报表调整!$H$5:$H$65536,IF(OR(MID(TRIM($A10),2,1)="：",MID(TRIM($A10),2,1)="、"),REPLACEB(TRIM($A10),1,4,""),TRIM($A10)),报表调整!$J$5:$J$65536) -> 0 | G10: =B10+C10+E10-D10-F10 -> 0 | I10: =SUM(G10:H10) -> 0
A11: =报表格式!B10 -> 应收利息 | B11: =未审BS!D11 -> 0 | C11: =SUMIF(账项调整!$E$5:$E$65536,IF(OR(MID(TRIM($A11),2,1)="：",MID(TRIM($A11),2,1)="、"),REPLACEB(TRIM($A11),1,4,""),TRIM($A11)),账项调整!$J$5:$J$65536) -> 0 | D11: =SUMIF(账项调整!$H$5:$H$65536,IF(OR(MID(TRIM($A11),2,1)="：",MID(TRIM($A11),2,1)="、"),REPLACEB(TRIM($A11),1,4,""),TRIM($A11)),账项调整!$J$5:$J$65536) -> 0 | E11: =SUMIF(报表调整!$E$5:$E$65536,IF(OR(MID(TRIM($A11),2,1)="：",MID(TRIM($A11),2,1)="、"),REPLACEB(TRIM($A11),1,4,""),TRIM($A11)),报表调整!$J$5:$J$65536) -> 0 | F11: =SUMIF(报表调整!$H$5:$H$65536,IF(OR(MID(TRIM($A11),2,1)="：",MID(TRIM($A11),2,1)="、"),REPLACEB(TRIM($A11),1,4,""),TRIM($A11)),报表调整!$J$5:$J$65536) -> 0 | G11: =B11+C11+E11-D11-F11 -> 0 | I11: =SUM(G11:H11) -> 0
A12: =报表格式!B11 -> 应收账款 | B12: =未审BS!D12 -> 0 | C12: =SUMIF(账项调整!$E$5:$E$65536,IF(OR(MID(TRIM($A12),2,1)="：",MID(TRIM($A12),2,1)="、"),REPLACEB(TRIM($A12),1,4,""),TRIM($A12)),账项调整!$J$5:$J$65536) -> 0 | D12: =SUMIF(账项调整!$H$5:$H$65536,IF(OR(MID(TRIM($A12),2,1)="：",MID(TRIM($A12),2,1)="、"),REPLACEB(TRIM($A12),1,4,""),TRIM($A12)),账项调整!$J$5:$J$65536) -> 0 | E12: =SUMIF(报表调整!$E$5:$E$65536,IF(OR(MID(TRIM($A12),2,1)="：",MID(TRIM($A12),2,1)="、"),REPLACEB(TRIM($A12),1,4,""),TRIM($A12)),报表调整!$J$5:$J$65536) -> 0 | F12: =SUMIF(报表调整!$H$5:$H$65536,IF(OR(MID(TRIM($A12),2,1)="：",MID(TRIM($A12),2,1)="、"),REPLACEB(TRIM($A12),1,4,""),TRIM($A12)),报表调整!$J$5:$J$65536) -> 0 | G12: =B12+C12+E12-D12-F12 -> 0 | I12: =SUM(G12:H12) -> 0
A13: =报表格式!B12 -> 其他应收款 | B13: =未审BS!D13 -> 0 | C13: =SUMIF(账项调整!$E$5:$E$65536,IF(OR(MID(TRIM($A13),2,1)="：",MID(TRIM($A13),2,1)="、"),REPLACEB(TRIM($A13),1,4,""),TRIM($A13)),账项调整!$J$5:$J$65536) -> 0 | D13: =SUMIF(账项调整!$H$5:$H$65536,IF(OR(MID(TRIM($A13),2,1)="：",MID(TRIM($A13),2,1)="、"),REPLACEB(TRIM($A13),1,4,""),TRIM($A13)),账项调整!$J$5:$J$65536) -> 0 | E13: =SUMIF(报表调整!$E$5:$E$65536,IF(OR(MID(TRIM($A13),2,1)="：",MID(TRIM($A13),2,1)="、"),REPLACEB(TRIM($A13),1,4,""),TRIM($A13)),报表调整!$J$5:$J$65536) -> 0 | F13: =SUMIF(报表调整!$H$5:$H$65536,IF(OR(MID(TRIM($A13),2,1)="：",MID(TRIM($A13),2,1)="、"),REPLACEB(TRIM($A13),1,4,""),TRIM($A13)),报表调整!$J$5:$J$65536) -> 0 | G13: =B13+C13+E13-D13-F13 -> 0 | I13: =SUM(G13:H13) -> 0
A14: =报表格式!B13 -> 预付账款 | B14: =未审BS!D14 -> 0 | C14: =SUMIF(账项调整!$E$5:$E$65536,IF(OR(MID(TRIM($A14),2,1)="：",MID(TRIM($A14),2,1)="、"),REPLACEB(TRIM($A14),1,4,""),TRIM($A14)),账项调整!$J$5:$J$65536) -> 0 | D14: =SUMIF(账项调整!$H$5:$H$65536,IF(OR(MID(TRIM($A14),2,1)="：",MID(TRIM($A14),2,1)="、"),REPLACEB(TRIM($A14),1,4,""),TRIM($A14)),账项调整!$J$5:$J$65536) -> 0 | E14: =SUMIF(报表调整!$E$5:$E$65536,IF(OR(MID(TRIM($A14),2,1)="：",MID(TRIM($A14),2,1)="、"),REPLACEB(TRIM($A14),1,4,""),TRIM($A14)),报表调整!$J$5:$J$65536) -> 0 | F14: =SUMIF(报表调整!$H$5:$H$65536,IF(OR(MID(TRIM($A14),2,1)="：",MID(TRIM($A14),2,1)="、"),REPLACEB(TRIM($A14),1,4,""),TRIM($A14)),报表调整!$J$5:$J$65536) -> 0 | G14: =B14+C14+E14-D14-F14 -> 0 | I14: =SUM(G14:H14) -> 0
A15: =报表格式!B14 -> 期货保证金 | B15: =未审BS!D15 -> 0 | C15: =SUMIF(账项调整!$E$5:$E$65536,IF(OR(MID(TRIM($A15),2,1)="：",MID(TRIM($A15),2,1)="、"),REPLACEB(TRIM($A15),1,4,""),TRIM($A15)),账项调整!$J$5:$J$65536) -> 0 | D15: =SUMIF(账项调整!$H$5:$H$65536,IF(OR(MID(TRIM($A15),2,1)="：",MID(TRIM($A15),2,1)="、"),REPLACEB(TRIM($A15),1,4,""),TRIM($A15)),账项调整!$J$5:$J$65536) -> 0 | E15: =SUMIF(报表调整!$E$5:$E$65536,IF(OR(MID(TRIM($A15),2,1)="：",MID(TRIM($A15),2,1)="、"),REPLACEB(TRIM($A15),1,4,""),TRIM($A15)),报表调整!$J$5:$J$65536) -> 0 | F15: =SUMIF(报表调整!$H$5:$H$65536,IF(OR(MID(TRIM($A15),2,1)="：",MID(TRIM($A15),2,1)="、"),REPLACEB(TRIM($A15),1,4,""),TRIM($A15)),报表调整!$J$5:$J$65536) -> 0 | G15: =B15+C15+E15-D15-F15 -> 0 | I15: =SUM(G15:H15) -> 0
A16: =报表格式!B15 -> 应收补贴款 | B16: =未审BS!D16 -> 0 | C16: =SUMIF(账项调整!$E$5:$E$65536,IF(OR(MID(TRIM($A16),2,1)="：",MID(TRIM($A16),2,1)="、"),REPLACEB(TRIM($A16),1,4,""),TRIM($A16)),账项调整!$J$5:$J$65536) -> 0 | D16: =SUMIF(账项调整!$H$5:$H$65536,IF(OR(MID(TRIM($A16),2,1)="：",MID(TRIM($A16),2,1)="、"),REPLACEB(TRIM($A16),1,4,""),TRIM($A16)),账项调整!$J$5:$J$65536) -> 0 | E16: =SUMIF(报表调整!$E$5:$E$65536,IF(OR(MID(TRIM($A16),2,1)="：",MID(TRIM($A16),2,1)="、"),REPLACEB(TRIM($A16),1,4,""),TRIM($A16)),报表调整!$J$5:$J$65536) -> 0 | F16: =SUMIF(报表调整!$H$5:$H$65536,IF(OR(MID(TRIM($A16),2,1)="：",MID(TRIM($A16),2,1)="、"),REPLACEB(TRIM($A16),1,4,""),TRIM($A16)),报表调整!$J$5:$J$65536) -> 0 | G16: =B16+C16+E16-D16-F16 -> 0 | I16: =SUM(G16:H16) -> 0
A17: =报表格式!B16 -> 应收出口退税 | B17: =未审BS!D17 -> 0 | C17: =SUMIF(账项调整!$E$5:$E$65536,IF(OR(MID(TRIM($A17),2,1)="：",MID(TRIM($A17),2,1)="、"),REPLACEB(TRIM($A17),1,4,""),TRIM($A17)),账项调整!$J$5:$J$65536) -> 0 | D17: =SUMIF(账项调整!$H$5:$H$65536,IF(OR(MID(TRIM($A17),2,1)="：",MID(TRIM($A17),2,1)="、"),REPLACEB(TRIM($A17),1,4,""),TRIM($A17)),账项调整!$J$5:$J$65536) -> 0 | E17: =SUMIF(报表调整!$E$5:$E$65536,IF(OR(MID(TRIM($A17),2,1)="：",MID(TRIM($A17),2,1)="、"),REPLACEB(TRIM($A17),1,4,""),TRIM($A17)),报表调整!$J$5:$J$65536) -> 0 | F17: =SUMIF(报表调整!$H$5:$H$65536,IF(OR(MID(TRIM($A17),2,1)="：",MID(TRIM($A17),2,1)="、"),REPLACEB(TRIM($A17),1,4,""),TRIM($A17)),报表调整!$J$5:$J$65536) -> 0 | G17: =B17+C17+E17-D17-F17 -> 0 | I17: =SUM(G17:H17) -> 0
A18: =报表格式!B17 -> 存货 | B18: =未审BS!D18 -> 0 | C18: =SUMIF(账项调整!$E$5:$E$65536,IF(OR(MID(TRIM($A18),2,1)="：",MID(TRIM($A18),2,1)="、"),REPLACEB(TRIM($A18),1,4,""),TRIM($A18)),账项调整!$J$5:$J$65536) -> 0 | D18: =SUMIF(账项调整!$H$5:$H$65536,IF(OR(MID(TRIM($A18),2,1)="：",MID(TRIM($A18),2,1)="、"),REPLACEB(TRIM($A18),1,4,""),TRIM($A18)),账项调整!$J$5:$J$65536) -> 0 | E18: =SUMIF(报表调整!$E$5:$E$65536,IF(OR(MID(TRIM($A18),2,1)="：",MID(TRIM($A18),2,1)="、"),REPLACEB(TRIM($A18),1,4,""),TRIM($A18)),报表调整!$J$5:$J$65536) -> 0 | F18: =SUMIF(报表调整!$H$5:$H$65536,IF(OR(MID(TRIM($A18),2,1)="：",MID(TRIM($A18),2,1)="、"),REPLACEB(TRIM($A18),1,4,""),TRIM($A18)),报表调整!$J$5:$J$65536) -> 0 | G18: =B18+C18+E18-D18-F18 -> 0 | I18: =SUM(G18:H18) -> 0
A19: =报表格式!B18 -> 其中：原材料 | B19: =未审BS!D19 -> 0 | C19: =SUMIF(账项调整!$F$5:$F$65536,IF(OR(MID(TRIM($A19),2,1)="：",MID(TRIM($A19),2,1)="、"),REPLACEB(TRIM($A19),1,4,""),TRIM($A19)),账项调整!$J$5:$J$65536) -> 0 | D19: =SUMIF(账项调整!$I$5:$I$65536,IF(OR(MID(TRIM($A19),2,1)="：",MID(TRIM($A19),2,1)="、"),REPLACEB(TRIM($A19),1,4,""),TRIM($A19)),账项调整!$J$5:$J$65536) -> 0 | E19: =SUMIF(报表调整!$F$5:$F$65536,IF(OR(MID(TRIM($A19),2,1)="：",MID(TRIM($A19),2,1)="、"),REPLACEB(TRIM($A19),1,4,""),TRIM($A19)),报表调整!$J$5:$J$65536) -> 0 | F19: =SUMIF(报表调整!$I$5:$I$65536,IF(OR(MID(TRIM($A19),2,1)="：",MID(TRIM($A19),2,1)="、"),REPLACEB(TRIM($A19),1,4,""),TRIM($A19)),报表调整!$J$5:$J$65536) -> 0 | G19: =B19+C19+E19-D19-F19 -> 0 | I19: =SUM(G19:H19) -> 0
A20: =报表格式!B19 -> 库存商品（产成品） | B20: =未审BS!D20 -> 0 | C20: =SUMIF(账项调整!$F$5:$F$65536,IF(OR(MID(TRIM($A20),2,1)="：",MID(TRIM($A20),2,1)="、"),REPLACEB(TRIM($A20),1,4,""),TRIM($A20)),账项调整!$J$5:$J$65536) -> 0 | D20: =SUMIF(账项调整!$I$5:$I$65536,IF(OR(MID(TRIM($A20),2,1)="：",MID(TRIM($A20),2,1)="、"),REPLACEB(TRIM($A20),1,4,""),TRIM($A20)),账项调整!$J$5:$J$65536) -> 0 | E20: =SUMIF(报表调整!$F$5:$F$65536,IF(OR(MID(TRIM($A20),2,1)="：",MID(TRIM($A20),2,1)="、"),REPLACEB(TRIM($A20),1,4,""),TRIM($A20)),报表调整!$J$5:$J$65536) -> 0 | F20: =SUMIF(报表调整!$I$5:$I$65536,IF(OR(MID(TRIM($A20),2,1)="：",MID(TRIM($A20),2,1)="、"),REPLACEB(TRIM($A20),1,4,""),TRIM($A20)),报表调整!$J$5:$J$65536) -> 0 | G20: =B20+C20+E20-D20-F20 -> 0 | I20: =SUM(G20:H20) -> 0
A21: =报表格式!B20 -> 待摊费用 | B21: =未审BS!D21 -> 0 | C21: =SUMIF(账项调整!$E$5:$E$65536,IF(OR(MID(TRIM($A21),2,1)="：",MID(TRIM($A21),2,1)="、"),REPLACEB(TRIM($A21),1,4,""),TRIM($A21)),账项调整!$J$5:$J$65536) -> 0 | D21: =SUMIF(账项调整!$H$5:$H$65536,IF(OR(MID(TRIM($A21),2,1)="：",MID(TRIM($A21),2,1)="、"),REPLACEB(TRIM($A21),1,4,""),TRIM($A21)),账项调整!$J$5:$J$65536) -> 0 | E21: =SUMIF(报表调整!$E$5:$E$65536,IF(OR(MID(TRIM($A21),2,1)="：",MID(TRIM($A21),2,1)="、"),REPLACEB(TRIM($A21),1,4,""),TRIM($A21)),报表调整!$J$5:$J$65536) -> 0 | F21: =SUMIF(报表调整!$H$5:$H$65536,IF(OR(MID(TRIM($A21),2,1)="：",MID(TRIM($A21),2,1)="、"),REPLACEB(TRIM($A21),1,4,""),TRIM($A21)),报表调整!$J$5:$J$65536) -> 0 | G21: =B21+C21+E21-D21-F21 -> 0 | I21: =SUM(G21:H21) -> 0
A22: =报表格式!B21 -> 待处理流动资产净损失 | B22: =未审BS!D22 -> 0 | C22: =SUMIF(账项调整!$E$5:$E$65536,IF(OR(MID(TRIM($A22),2,1)="：",MID(TRIM($A22),2,1)="、"),REPLACEB(TRIM($A22),1,4,""),TRIM($A22)),账项调整!$J$5:$J$65536) -> 0 | D22: =SUMIF(账项调整!$H$5:$H$65536,IF(OR(MID(TRIM($A22),2,1)="：",MID(TRIM($A22),2,1)="、"),REPLACEB(TRIM($A22),1,4,""),TRIM($A22)),账项调整!$J$5:$J$65536) -> 0 | E22: =SUMIF(报表调整!$E$5:$E$65536,IF(OR(MID(TRIM($A22),2,1)="：",MID(TRIM($A22),2,1)="、"),REPLACEB(TRIM($A22),1,4,""),TRIM($A22)),报表调整!$J$5:$J$65536) -> 0 | F22: =SUMIF(报表调整!$H$5:$H$65536,IF(OR(MID(TRIM($A22),2,1)="：",MID(TRIM($A22),2,1)="、"),REPLACEB(TRIM($A22),1,4,""),TRIM($A22)),报表调整!$J$5:$J$65536) -> 0 | G22: =B22+C22+E22-D22-F22 -> 0 | I22: =SUM(G22:H22) -> 0
A23: =报表格式!B22 -> 一年内到期的长期债权投资 | B23: =未审BS!D23 -> 0 | C23: =SUMIF(账项调整!$E$5:$E$65536,IF(OR(MID(TRIM($A23),2,1)="：",MID(TRIM($A23),2,1)="、"),REPLACEB(TRIM($A23),1,4,""),TRIM($A23)),账项调整!$J$5:$J$65536) -> 0 | D23: =SUMIF(账项调整!$H$5:$H$65536,IF(OR(MID(TRIM($A23),2,1)="：",MID(TRIM($A23),2,1)="、"),REPLACEB(TRIM($A23),1,4,""),TRIM($A23)),账项调整!$J$5:$J$65536) -> 0 | E23: =SUMIF(报表调整!$E$5:$E$65536,IF(OR(MID(TRIM($A23),2,1)="：",MID(TRIM($A23),2,1)="、"),REPLACEB(TRIM($A23),1,4,""),TRIM($A23)),报表调整!$J$5:$J$65536) -> 0 | F23: =SUMIF(报表调整!$H$5:$H$65536,IF(OR(MID(TRIM($A23),2,1)="：",MID(TRIM($A23),2,1)="、"),REPLACEB(TRIM($A23),1,4,""),TRIM($A23)),报表调整!$J$5:$J$65536) -> 0 | G23: =B23+C23+E23-D23-F23 -> 0 | I23: =SUM(G23:H23) -> 0
A24: =报表格式!B23 -> 其他流动资产 | B24: =未审BS!D24 -> 0 | C24: =SUMIF(账项调整!$E$5:$E$65536,IF(OR(MID(TRIM($A24),2,1)="：",MID(TRIM($A24),2,1)="、"),REPLACEB(TRIM($A24),1,4,""),TRIM($A24)),账项调整!$J$5:$J$65536) -> 0 | D24: =SUMIF(账项调整!$H$5:$H$65536,IF(OR(MID(TRIM($A24),2,1)="：",MID(TRIM($A24),2,1)="、"),REPLACEB(TRIM($A24),1,4,""),TRIM($A24)),账项调整!$J$5:$J$65536) -> 0 | E24: =SUMIF(报表调整!$E$5:$E$65536,IF(OR(MID(TRIM($A24),2,1)="：",MID(TRIM($A24),2,1)="、"),REPLACEB(TRIM($A24),1,4,""),TRIM($A24)),报表调整!$J$5:$J$65536) -> 0 | F24: =SUMIF(报表调整!$H$5:$H$65536,IF(OR(MID(TRIM($A24),2,1)="：",MID(TRIM($A24),2,1)="、"),REPLACEB(TRIM($A24),1,4,""),TRIM($A24)),报表调整!$J$5:$J$65536) -> 0 | G24: =B24+C24+E24-D24-F24 -> 0 | I24: =SUM(G24:H24) -> 0
A25: =报表格式!B24 -> 0 | B25: =未审BS!D25 -> 0 | C25: =SUMIF(账项调整!$E$5:$E$65536,IF(OR(MID(TRIM($A25),2,1)="：",MID(TRIM($A25),2,1)="、"),REPLACEB(TRIM($A25),1,4,""),TRIM($A25)),账项调整!$J$5:$J$65536) -> 0 | D25: =SUMIF(账项调整!$H$5:$H$65536,IF(OR(MID(TRIM($A25),2,1)="：",MID(TRIM($A25),2,1)="、"),REPLACEB(TRIM($A25),1,4,""),TRIM($A25)),账项调整!$J$5:$J$65536) -> 0 | E25: =SUMIF(报表调整!$E$5:$E$65536,IF(OR(MID(TRIM($A25),2,1)="：",MID(TRIM($A25),2,1)="、"),REPLACEB(TRIM($A25),1,4,""),TRIM($A25)),报表调整!$J$5:$J$65536) -> 0 | F25: =SUMIF(报表调整!$H$5:$H$65536,IF(OR(MID(TRIM($A25),2,1)="：",MID(TRIM($A25),2,1)="、"),REPLACEB(TRIM($A25),1,4,""),TRIM($A25)),报表调整!$J$5:$J$65536) -> 0 | G25: =B25+C25+E25-D25-F25 -> 0 | I25: =SUM(G25:H25) -> 0
A26: =报表格式!B25 -> 0 | B26: =未审BS!D26 -> 0 | C26: =SUMIF(账项调整!$E$5:$E$65536,IF(OR(MID(TRIM($A26),2,1)="：",MID(TRIM($A26),2,1)="、"),REPLACEB(TRIM($A26),1,4,""),TRIM($A26)),账项调整!$J$5:$J$65536) -> 0 | D26: =SUMIF(账项调整!$H$5:$H$65536,IF(OR(MID(TRIM($A26),2,1)="：",MID(TRIM($A26),2,1)="、"),REPLACEB(TRIM($A26),1,4,""),TRIM($A26)),账项调整!$J$5:$J$65536) -> 0 | E26: =SUMIF(报表调整!$E$5:$E$65536,IF(OR(MID(TRIM($A26),2,1)="：",MID(TRIM($A26),2,1)="、"),REPLACEB(TRIM($A26),1,4,""),TRIM($A26)),报表调整!$J$5:$J$65536) -> 0 | F26: =SUMIF(报表调整!$H$5:$H$65536,IF(OR(MID(TRIM($A26),2,1)="：",MID(TRIM($A26),2,1)="、"),REPLACEB(TRIM($A26),1,4,""),TRIM($A26)),报表调整!$J$5:$J$65536) -> 0 | G26: =B26+C26+E26-D26-F26 -> 0 | I26: =SUM(G26:H26) -> 0
A27: =报表格式!B26 -> 流动资产合计 | B27: =SUM(B7:B26)-B19-B20 -> 0 | C27: =SUM(C7:C26)-C19-C20 -> 0 | D27: =SUM(D7:D26)-D19-D20 -> 0 | E27: =SUM(E7:E26)-E19-E20 -> 0 | F27: =SUM(F7:F26)-F19-F20 -> 0 | G27: =SUM(G7:G26)-G19-G20 -> 0 | H27: =SUM(H7:H26)-H19-H20 -> 0 | I27: =SUM(G27:H27) -> 0
A28: =报表格式!B27 -> 长期投资 | B28: =SUM(B29:B30) -> 0 | C28: =SUM(C29:C30) -> 0 | D28: =SUM(D29:D30) -> 0 | E28: =SUM(E29:E30) -> 0 | F28: =SUM(F29:F30) -> 0 | G28: =SUM(G29:G30) -> 0 | H28: =SUM(H29:H30) -> 0 | I28: =SUM(G28:H28) -> 0
A29: =报表格式!B28 -> 其中：长期股权投资 | B29: =未审BS!D29 -> 0 | C29: =SUMIF(账项调整!$E$5:$E$65536,IF(OR(MID(TRIM($A29),3,1)="：",MID(TRIM($A29),3,1)="、"),TRIM(REPLACEB(TRIM($A29),1,5,"")),TRIM($A29)),账项调整!$J$5:$J$65536)-C31 -> 0 | D29: =SUMIF(账项调整!$H$5:$H$65536,IF(OR(MID(TRIM($A29),3,1)="：",MID(TRIM($A29),3,1)="、"),TRIM(REPLACEB(TRIM($A29),1,5,"")),TRIM($A29)),账项调整!$J$5:$J$65536)-D31 -> 0 | E29: =SUMIF(报表调整!$E$5:$E$65536,IF(OR(MID(TRIM($A29),3,1)="：",MID(TRIM($A29),3,1)="、"),TRIM(REPLACEB(TRIM($A29),1,5,"")),TRIM($A29)),报表调整!$J$5:$J$65536)-E31 -> 0 | F29: =SUMIF(报表调整!$H$5:$H$65536,IF(OR(MID(TRIM($A29),3,1)="：",MID(TRIM($A29),3,1)="、"),TRIM(REPLACEB(TRIM($A29),1,5,"")),TRIM($A29)),报表调整!$J$5:$J$65536)-F31 -> 0 | G29: =B29+C29+E29-D29-F29 -> 0 | I29: =SUM(G29:H29) -> 0
A30: =报表格式!B29 -> 长期债权投资 | B30: =未审BS!D30 -> 0 | C30: =SUMIF(账项调整!$E$5:$E$65536,IF(OR(MID(TRIM($A30),2,1)="：",MID(TRIM($A30),2,1)="、"),REPLACEB(TRIM($A30),1,4,""),TRIM($A30)),账项调整!$J$5:$J$65536) -> 0 | D30: =SUMIF(账项调整!$H$5:$H$65536,IF(OR(MID(TRIM($A30),2,1)="：",MID(TRIM($A30),2,1)="、"),REPLACEB(TRIM($A30),1,4,""),TRIM($A30)),账项调整!$J$5:$J$65536) -> 0 | E30: =SUMIF(报表调整!$E$5:$E$65536,IF(OR(MID(TRIM($A30),2,1)="：",MID(TRIM($A30),2,1)="、"),REPLACEB(TRIM($A30),1,4,""),TRIM($A30)),报表调整!$J$5:$J$65536) -> 0 | F30: =SUMIF(报表调整!$H$5:$H$65536,IF(OR(MID(TRIM($A30),2,1)="：",MID(TRIM($A30),2,1)="、"),REPLACEB(TRIM($A30),1,4,""),TRIM($A30)),报表调整!$J$5:$J$65536) -> 0 | G30: =B30+C30+E30-D30-F30 -> 0 | I30: =SUM(G30:H30) -> 0
A31: =报表格式!B30 -> *合并价差 | B31: =未审BS!D31 -> 0 | C31: =SUMIF(账项调整!$F$5:$F$65536,REPLACEB(IF(OR(MID(TRIM($A31),2,1)="：",MID(TRIM($A31),2,1)="、"),REPLACEB(TRIM($A31),1,4,""),TRIM($A31)),1,1,""),账项调整!$J$5:$J$65536) -> 0 | D31: =SUMIF(账项调整!$I$5:$I$65536,REPLACEB(IF(OR(MID(TRIM($A31),2,1)="：",MID(TRIM($A31),2,1)="、"),REPLACEB(TRIM($A31),1,4,""),TRIM($A31)),1,1,""),账项调整!$J$5:$J$65536) -> 0 | E31: =SUMIF(报表调整!$F$5:$F$65536,REPLACEB(IF(OR(MID(TRIM($A31),2,1)="：",MID(TRIM($A31),2,1)="、"),REPLACEB(TRIM($A31),1,4,""),TRIM($A31)),1,1,""),报表调整!$J$5:$J$65536) -> 0 | F31: =SUMIF(报表调整!$I$5:$I$65536,REPLACEB(IF(OR(MID(TRIM($A31),2,1)="：",MID(TRIM($A31),2,1)="、"),REPLACEB(TRIM($A31),1,4,""),TRIM($A31)),1,1,""),报表调整!$J$5:$J$65536) -> 0 | G31: =B31+C31+E31-D31-F31 -> 0 | I31: =SUM(G31:H31) -> 0
A32: =报表格式!B31 -> 0 | B32: =未审BS!D32 -> 0 | C32: =SUMIF(账项调整!$E$5:$E$65536,IF(OR(MID(TRIM($A32),2,1)="：",MID(TRIM($A32),2,1)="、"),REPLACEB(TRIM($A32),1,4,""),TRIM($A32)),账项调整!$J$5:$J$65536) -> 0 | D32: =SUMIF(账项调整!$H$5:$H$65536,IF(OR(MID(TRIM($A32),2,1)="：",MID(TRIM($A32),2,1)="、"),REPLACEB(TRIM($A32),1,4,""),TRIM($A32)),账项调整!$J$5:$J$65536) -> 0 | E32: =SUMIF(报表调整!$E$5:$E$65536,IF(OR(MID(TRIM($A32),2,1)="：",MID(TRIM($A32),2,1)="、"),REPLACEB(TRIM($A32),1,4,""),TRIM($A32)),报表调整!$J$5:$J$65536) -> 0 | F32: =SUMIF(报表调整!$H$5:$H$65536,IF(OR(MID(TRIM($A32),2,1)="：",MID(TRIM($A32),2,1)="、"),REPLACEB(TRIM($A32),1,4,""),TRIM($A32)),报表调整!$J$5:$J$65536) -> 0 | G32: =B32+C32+E32-D32-F32 -> 0 | I32: =SUM(G32:H32) -> 0
A33: =报表格式!B32 -> 0 | B33: =未审BS!D33 -> 0 | C33: =SUMIF(账项调整!$E$5:$E$65536,IF(OR(MID(TRIM($A33),2,1)="：",MID(TRIM($A33),2,1)="、"),REPLACEB(TRIM($A33),1,4,""),TRIM($A33)),账项调整!$J$5:$J$65536) -> 0 | D33: =SUMIF(账项调整!$H$5:$H$65536,IF(OR(MID(TRIM($A33),2,1)="：",MID(TRIM($A33),2,1)="、"),REPLACEB(TRIM($A33),1,4,""),TRIM($A33)),账项调整!$J$5:$J$65536) -> 0 | E33: =SUMIF(报表调整!$E$5:$E$65536,IF(OR(MID(TRIM($A33),2,1)="：",MID(TRIM($A33),2,1)="、"),REPLACEB(TRIM($A33),1,4,""),TRIM($A33)),报表调整!$J$5:$J$65536) -> 0 | F33: =SUMIF(报表调整!$H$5:$H$65536,IF(OR(MID(TRIM($A33),2,1)="：",MID(TRIM($A33),2,1)="、"),REPLACEB(TRIM($A33),1,4,""),TRIM($A33)),报表调整!$J$5:$J$65536) -> 0 | G33: =B33+C33+E33-D33-F33 -> 0 | I33: =SUM(G33:H33) -> 0
A34: =报表格式!B33 -> 长期投资合计 | B34: =SUM(B28,B31:B33) -> 0 | C34: =SUM(C28,C31:C33) -> 0 | D34: =SUM(D28,D31:D33) -> 0 | E34: =SUM(E28,E31:E33) -> 0 | F34: =SUM(F28,F31:F33) -> 0 | G34: =SUM(G28,G31:G33) -> 0 | H34: =SUM(H28,H31:H33) -> 0 | I34: =SUM(G34:H34) -> 0
A35: =报表格式!B34 -> 固定资产：
A36: =报表格式!B35 -> 固定资产原价 | B36: =未审BS!D36 -> 0 | C36: =SUMIF(账项调整!$E$5:$E$65536,IF(OR(MID(TRIM($A36),2,1)="：",MID(TRIM($A36),2,1)="、"),REPLACEB(TRIM($A36),1,4,""),TRIM($A36)),账项调整!$J$5:$J$65536) -> 0 | D36: =SUMIF(账项调整!$H$5:$H$65536,IF(OR(MID(TRIM($A36),2,1)="：",MID(TRIM($A36),2,1)="、"),REPLACEB(TRIM($A36),1,4,""),TRIM($A36)),账项调整!$J$5:$J$65536) -> 0 | E36: =SUMIF(报表调整!$E$5:$E$65536,IF(OR(MID(TRIM($A36),2,1)="：",MID(TRIM($A36),2,1)="、"),REPLACEB(TRIM($A36),1,4,""),TRIM($A36)),报表调整!$J$5:$J$65536) -> 0 | F36: =SUMIF(报表调整!$H$5:$H$65536,IF(OR(MID(TRIM($A36),2,1)="：",MID(TRIM($A36),2,1)="、"),REPLACEB(TRIM($A36),1,4,""),TRIM($A36)),报表调整!$J$5:$J$65536) -> 0 | G36: =B36+C36+E36-D36-F36 -> 0 | I36: =SUM(G36:H36) -> 0
A37: =报表格式!B36 -> 减：累计折旧 | B37: =未审BS!D37 -> 0 | C37: =SUMIF(账项调整!$E$5:$E$65536,IF(OR(MID(TRIM($A37),2,1)="：",MID(TRIM($A37),2,1)="、"),REPLACEB(TRIM($A37),1,4,""),TRIM($A37)),账项调整!$J$5:$J$65536) -> 0 | D37: =SUMIF(账项调整!$H$5:$H$65536,IF(OR(MID(TRIM($A37),2,1)="：",MID(TRIM($A37),2,1)="、"),REPLACEB(TRIM($A37),1,4,""),TRIM($A37)),账项调整!$J$5:$J$65536) -> 0 | E37: =SUMIF(报表调整!$E$5:$E$65536,IF(OR(MID(TRIM($A37),2,1)="：",MID(TRIM($A37),2,1)="、"),REPLACEB(TRIM($A37),1,4,""),TRIM($A37)),报表调整!$J$5:$J$65536) -> 0 | F37: =SUMIF(报表调整!$H$5:$H$65536,IF(OR(MID(TRIM($A37),2,1)="：",MID(TRIM($A37),2,1)="、"),REPLACEB(TRIM($A37),1,4,""),TRIM($A37)),报表调整!$J$5:$J$65536) -> 0 | G37: =B37-C37-E37+D37+F37 -> 0 | I37: =SUM(G37:H37) -> 0
A38: =报表格式!B37 -> 固定资产净值 | B38: =未审BS!D38 -> 0 | C38: =C36-C37 -> 0 | D38: =D36-D37 -> 0 | E38: =E36-E37 -> 0 | F38: =F36-F37 -> 0 | G38: =G36-G37 -> 0 | H38: =H36-H37 -> 0 | I38: =SUM(G38:H38) -> 0
A39: =报表格式!B38 -> 减：固定资产减值准备 | B39: =未审BS!D39 -> 0 | C39: =SUMIF(账项调整!$E$5:$E$65536,IF(OR(MID(TRIM($A39),2,1)="：",MID(TRIM($A39),2,1)="、"),REPLACEB(TRIM($A39),1,4,""),TRIM($A39)),账项调整!$J$5:$J$65536) -> 0 | D39: =SUMIF(账项调整!$H$5:$H$65536,IF(OR(MID(TRIM($A39),2,1)="：",MID(TRIM($A39),2,1)="、"),REPLACEB(TRIM($A39),1,4,""),TRIM($A39)),账项调整!$J$5:$J$65536) -> 0 | E39: =SUMIF(报表调整!$E$5:$E$65536,IF(OR(MID(TRIM($A39),2,1)="：",MID(TRIM($A39),2,1)="、"),REPLACEB(TRIM($A39),1,4,""),TRIM($A39)),报表调整!$J$5:$J$65536) -> 0 | F39: =SUMIF(报表调整!$H$5:$H$65536,IF(OR(MID(TRIM($A39),2,1)="：",MID(TRIM($A39),2,1)="、"),REPLACEB(TRIM($A39),1,4,""),TRIM($A39)),报表调整!$J$5:$J$65536) -> 0 | G39: =B39-C39-E39+D39+F39 -> 0 | I39: =SUM(G39:H39) -> 0
A40: =报表格式!B39 -> 固定资产净额 | B40: =未审BS!D40 -> 0 | C40: =C38-C39 -> 0 | D40: =D38-D39 -> 0 | E40: =E38-E39 -> 0 | F40: =F38-F39 -> 0 | G40: =G38-G39 -> 0 | H40: =H38-H39 -> 0 | I40: =SUM(G40:H40) -> 0
A41: =报表格式!B40 -> 工程物资 | B41: =未审BS!D41 -> 0 | C41: =SUMIF(账项调整!$E$5:$E$65536,IF(OR(MID(TRIM($A41),2,1)="：",MID(TRIM($A41),2,1)="、"),REPLACEB(TRIM($A41),1,4,""),TRIM($A41)),账项调整!$J$5:$J$65536) -> 0 | D41: =SUMIF(账项调整!$H$5:$H$65536,IF(OR(MID(TRIM($A41),2,1)="：",MID(TRIM($A41),2,1)="、"),REPLACEB(TRIM($A41),1,4,""),TRIM($A41)),账项调整!$J$5:$J$65536) -> 0 | E41: =SUMIF(报表调整!$E$5:$E$65536,IF(OR(MID(TRIM($A41),2,1)="：",MID(TRIM($A41),2,1)="、"),REPLACEB(TRIM($A41),1,4,""),TRIM($A41)),报表调整!$J$5:$J$65536) -> 0 | F41: =SUMIF(报表调整!$H$5:$H$65536,IF(OR(MID(TRIM($A41),2,1)="：",MID(TRIM($A41),2,1)="、"),REPLACEB(TRIM($A41),1,4,""),TRIM($A41)),报表调整!$J$5:$J$65536) -> 0 | G41: =B41+C41+E41-D41-F41 -> 0 | I41: =SUM(G41:H41) -> 0
A42: =报表格式!B41 -> 在建工程 | B42: =未审BS!D42 -> 0 | C42: =SUMIF(账项调整!$E$5:$E$65536,IF(OR(MID(TRIM($A42),2,1)="：",MID(TRIM($A42),2,1)="、"),REPLACEB(TRIM($A42),1,4,""),TRIM($A42)),账项调整!$J$5:$J$65536) -> 0 | D42: =SUMIF(账项调整!$H$5:$H$65536,IF(OR(MID(TRIM($A42),2,1)="：",MID(TRIM($A42),2,1)="、"),REPLACEB(TRIM($A42),1,4,""),TRIM($A42)),账项调整!$J$5:$J$65536) -> 0 | E42: =SUMIF(报表调整!$E$5:$E$65536,IF(OR(MID(TRIM($A42),2,1)="：",MID(TRIM($A42),2,1)="、"),REPLACEB(TRIM($A42),1,4,""),TRIM($A42)),报表调整!$J$5:$J$65536) -> 0 | F42: =SUMIF(报表调整!$H$5:$H$65536,IF(OR(MID(TRIM($A42),2,1)="：",MID(TRIM($A42),2,1)="、"),REPLACEB(TRIM($A42),1,4,""),TRIM($A42)),报表调整!$J$5:$J$65536) -> 0 | G42: =B42+C42+E42-D42-F42 -> 0 | I42: =SUM(G42:H42) -> 0
A43: =报表格式!B42 -> 固定资产清理 | B43: =未审BS!D43 -> 0 | C43: =SUMIF(账项调整!$E$5:$E$65536,IF(OR(MID(TRIM($A43),2,1)="：",MID(TRIM($A43),2,1)="、"),REPLACEB(TRIM($A43),1,4,""),TRIM($A43)),账项调整!$J$5:$J$65536) -> 0 | D43: =SUMIF(账项调整!$H$5:$H$65536,IF(OR(MID(TRIM($A43),2,1)="：",MID(TRIM($A43),2,1)="、"),REPLACEB(TRIM($A43),1,4,""),TRIM($A43)),账项调整!$J$5:$J$65536) -> 0 | E43: =SUMIF(报表调整!$E$5:$E$65536,IF(OR(MID(TRIM($A43),2,1)="：",MID(TRIM($A43),2,1)="、"),REPLACEB(TRIM($A43),1,4,""),TRIM($A43)),报表调整!$J$5:$J$65536) -> 0 | F43: =SUMIF(报表调整!$H$5:$H$65536,IF(OR(MID(TRIM($A43),2,1)="：",MID(TRIM($A43),2,1)="、"),REPLACEB(TRIM($A43),1,4,""),TRIM($A43)),报表调整!$J$5:$J$65536) -> 0 | G43: =B43+C43+E43-D43-F43 -> 0 | I43: =SUM(G43:H43) -> 0
A44: =报表格式!B43 -> 待处理固定资产净损失 | B44: =未审BS!D44 -> 0 | C44: =SUMIF(账项调整!$E$5:$E$65536,IF(OR(MID(TRIM($A44),2,1)="：",MID(TRIM($A44),2,1)="、"),REPLACEB(TRIM($A44),1,4,""),TRIM($A44)),账项调整!$J$5:$J$65536) -> 0 | D44: =SUMIF(账项调整!$H$5:$H$65536,IF(OR(MID(TRIM($A44),2,1)="：",MID(TRIM($A44),2,1)="、"),REPLACEB(TRIM($A44),1,4,""),TRIM($A44)),账项调整!$J$5:$J$65536) -> 0 | E44: =SUMIF(报表调整!$E$5:$E$65536,IF(OR(MID(TRIM($A44),2,1)="：",MID(TRIM($A44),2,1)="、"),REPLACEB(TRIM($A44),1,4,""),TRIM($A44)),报表调整!$J$5:$J$65536) -> 0 | F44: =SUMIF(报表调整!$H$5:$H$65536,IF(OR(MID(TRIM($A44),2,1)="：",MID(TRIM($A44),2,1)="、"),REPLACEB(TRIM($A44),1,4,""),TRIM($A44)),报表调整!$J$5:$J$65536) -> 0 | G44: =B44+C44+E44-D44-F44 -> 0 | I44: =SUM(G44:H44) -> 0
A45: =报表格式!B44 -> 0 | B45: =未审BS!D45 -> 0 | C45: =SUMIF(账项调整!$E$5:$E$65536,IF(OR(MID(TRIM($A45),2,1)="：",MID(TRIM($A45),2,1)="、"),REPLACEB(TRIM($A45),1,4,""),TRIM($A45)),账项调整!$J$5:$J$65536) -> 0 | D45: =SUMIF(账项调整!$H$5:$H$65536,IF(OR(MID(TRIM($A45),2,1)="：",MID(TRIM($A45),2,1)="、"),REPLACEB(TRIM($A45),1,4,""),TRIM($A45)),账项调整!$J$5:$J$65536) -> 0 | E45: =SUMIF(报表调整!$E$5:$E$65536,IF(OR(MID(TRIM($A45),2,1)="：",MID(TRIM($A45),2,1)="、"),REPLACEB(TRIM($A45),1,4,""),TRIM($A45)),报表调整!$J$5:$J$65536) -> 0 | F45: =SUMIF(报表调整!$H$5:$H$65536,IF(OR(MID(TRIM($A45),2,1)="：",MID(TRIM($A45),2,1)="、"),REPLACEB(TRIM($A45),1,4,""),TRIM($A45)),报表调整!$J$5:$J$65536) -> 0 | G45: =B45+C45+E45-D45-F45 -> 0 | I45: =SUM(G45:H45) -> 0
A46: =报表格式!B45 -> 0 | B46: =未审BS!D46 -> 0 | C46: =SUMIF(账项调整!$E$5:$E$65536,IF(OR(MID(TRIM($A46),2,1)="：",MID(TRIM($A46),2,1)="、"),REPLACEB(TRIM($A46),1,4,""),TRIM($A46)),账项调整!$J$5:$J$65536) -> 0 | D46: =SUMIF(账项调整!$H$5:$H$65536,IF(OR(MID(TRIM($A46),2,1)="：",MID(TRIM($A46),2,1)="、"),REPLACEB(TRIM($A46),1,4,""),TRIM($A46)),账项调整!$J$5:$J$65536) -> 0 | E46: =SUMIF(报表调整!$E$5:$E$65536,IF(OR(MID(TRIM($A46),2,1)="：",MID(TRIM($A46),2,1)="、"),REPLACEB(TRIM($A46),1,4,""),TRIM($A46)),报表调整!$J$5:$J$65536) -> 0 | F46: =SUMIF(报表调整!$H$5:$H$65536,IF(OR(MID(TRIM($A46),2,1)="：",MID(TRIM($A46),2,1)="、"),REPLACEB(TRIM($A46),1,4,""),TRIM($A46)),报表调整!$J$5:$J$65536) -> 0 | G46: =B46+C46+E46-D46-F46 -> 0 | I46: =SUM(G46:H46) -> 0
A47: =报表格式!B46 -> 固定资产合计 | B47: =SUM(B40:B46) -> 0 | C47: =SUM(C40:C46) -> 0 | D47: =SUM(D40:D46) -> 0 | E47: =SUM(E40:E46) -> 0 | F47: =SUM(F40:F46) -> 0 | G47: =SUM(G40:G46) -> 0 | H47: =SUM(H40:H46) -> 0 | I47: =SUM(G47:H47) -> 0
A48: =报表格式!B47 -> 无形资产及其他资产：
A49: =报表格式!B48 -> 无形资产 | B49: =未审BS!D49 -> 0 | C49: =SUMIF(账项调整!$E$5:$E$65536,IF(OR(MID(TRIM($A49),2,1)="：",MID(TRIM($A49),2,1)="、"),REPLACEB(TRIM($A49),1,4,""),TRIM($A49)),账项调整!$J$5:$J$65536) -> 0 | D49: =SUMIF(账项调整!$H$5:$H$65536,IF(OR(MID(TRIM($A49),2,1)="：",MID(TRIM($A49),2,1)="、"),REPLACEB(TRIM($A49),1,4,""),TRIM($A49)),账项调整!$J$5:$J$65536) -> 0 | E49: =SUMIF(报表调整!$E$5:$E$65536,IF(OR(MID(TRIM($A49),2,1)="：",MID(TRIM($A49),2,1)="、"),REPLACEB(TRIM($A49),1,4,""),TRIM($A49)),报表调整!$J$5:$J$65536) -> 0 | F49: =SUMIF(报表调整!$H$5:$H$65536,IF(OR(MID(TRIM($A49),2,1)="：",MID(TRIM($A49),2,1)="、"),REPLACEB(TRIM($A49),1,4,""),TRIM($A49)),报表调整!$J$5:$J$65536) -> 0 | G49: =B49+C49+E49-D49-F49 -> 0 | I49: =SUM(G49:H49) -> 0
A50: =报表格式!B49 -> 其中：土地使用权 | B50: =未审BS!D50 -> 0 | C50: =SUMIF(账项调整!$F$5:$F$65536,IF(OR(MID(TRIM($A50),2,1)="：",MID(TRIM($A50),2,1)="、"),REPLACEB(TRIM($A50),1,4,""),TRIM($A50)),账项调整!$J$5:$J$65536) -> 0 | D50: =SUMIF(账项调整!$I$5:$I$65536,IF(OR(MID(TRIM($A50),2,1)="：",MID(TRIM($A50),2,1)="、"),REPLACEB(TRIM($A50),1,4,""),TRIM($A50)),账项调整!$J$5:$J$65536) -> 0 | E50: =SUMIF(报表调整!$F$5:$F$65536,IF(OR(MID(TRIM($A50),2,1)="：",MID(TRIM($A50),2,1)="、"),REPLACEB(TRIM($A50),1,4,""),TRIM($A50)),报表调整!$J$5:$J$65536) -> 0 | F50: =SUMIF(报表调整!$I$5:$I$65536,IF(OR(MID(TRIM($A50),2,1)="：",MID(TRIM($A50),2,1)="、"),REPLACEB(TRIM($A50),1,4,""),TRIM($A50)),报表调整!$J$5:$J$65536) -> 0 | G50: =B50+C50+E50-D50-F50 -> 0 | I50: =SUM(G50:H50) -> 0
A51: =报表格式!B50 -> 长期待摊费用 | B51: =未审BS!D51 -> 0 | C51: =SUMIF(账项调整!$E$5:$E$65536,IF(OR(MID(TRIM($A51),2,1)="：",MID(TRIM($A51),2,1)="、"),REPLACEB(TRIM($A51),1,4,""),TRIM($A51)),账项调整!$J$5:$J$65536) -> 0 | D51: =SUMIF(账项调整!$H$5:$H$65536,IF(OR(MID(TRIM($A51),2,1)="：",MID(TRIM($A51),2,1)="、"),REPLACEB(TRIM($A51),1,4,""),TRIM($A51)),账项调整!$J$5:$J$65536) -> 0 | E51: =SUMIF(报表调整!$E$5:$E$65536,IF(OR(MID(TRIM($A51),2,1)="：",MID(TRIM($A51),2,1)="、"),REPLACEB(TRIM($A51),1,4,""),TRIM($A51)),报表调整!$J$5:$J$65536) -> 0 | F51: =SUMIF(报表调整!$H$5:$H$65536,IF(OR(MID(TRIM($A51),2,1)="：",MID(TRIM($A51),2,1)="、"),REPLACEB(TRIM($A51),1,4,""),TRIM($A51)),报表调整!$J$5:$J$65536) -> 0 | G51: =B51+C51+E51-D51-F51 -> 0 | I51: =SUM(G51:H51) -> 0
A52: =报表格式!B51 -> 其中：固定资产修理 | B52: =未审BS!D52 -> 0 | C52: =SUMIF(账项调整!$F$5:$F$65536,IF(OR(MID(TRIM($A52),2,1)="：",MID(TRIM($A52),2,1)="、"),REPLACEB(TRIM($A52),1,4,""),TRIM($A52)),账项调整!$J$5:$J$65536) -> 0 | D52: =SUMIF(账项调整!$I$5:$I$65536,IF(OR(MID(TRIM($A52),2,1)="：",MID(TRIM($A52),2,1)="、"),REPLACEB(TRIM($A52),1,4,""),TRIM($A52)),账项调整!$J$5:$J$65536) -> 0 | E52: =SUMIF(报表调整!$F$5:$F$65536,IF(OR(MID(TRIM($A52),2,1)="：",MID(TRIM($A52),2,1)="、"),REPLACEB(TRIM($A52),1,4,""),TRIM($A52)),报表调整!$J$5:$J$65536) -> 0 | F52: =SUMIF(报表调整!$I$5:$I$65536,IF(OR(MID(TRIM($A52),2,1)="：",MID(TRIM($A52),2,1)="、"),REPLACEB(TRIM($A52),1,4,""),TRIM($A52)),报表调整!$J$5:$J$65536) -> 0 | G52: =B52+C52+E52-D52-F52 -> 0 | I52: =SUM(G52:H52) -> 0
A53: =报表格式!B52 -> 固定资产改良支出 | B53: =未审BS!D53 -> 0 | C53: =SUMIF(账项调整!$F$5:$F$65536,IF(OR(MID(TRIM($A53),2,1)="：",MID(TRIM($A53),2,1)="、"),REPLACEB(TRIM($A53),1,4,""),TRIM($A53)),账项调整!$J$5:$J$65536) -> 0 | D53: =SUMIF(账项调整!$I$5:$I$65536,IF(OR(MID(TRIM($A53),2,1)="：",MID(TRIM($A53),2,1)="、"),REPLACEB(TRIM($A53),1,4,""),TRIM($A53)),账项调整!$J$5:$J$65536) -> 0 | E53: =SUMIF(报表调整!$F$5:$F$65536,IF(OR(MID(TRIM($A53),2,1)="：",MID(TRIM($A53),2,1)="、"),REPLACEB(TRIM($A53),1,4,""),TRIM($A53)),报表调整!$J$5:$J$65536) -> 0 | F53: =SUMIF(报表调整!$I$5:$I$65536,IF(OR(MID(TRIM($A53),2,1)="：",MID(TRIM($A53),2,1)="、"),REPLACEB(TRIM($A53),1,4,""),TRIM($A53)),报表调整!$J$5:$J$65536) -> 0 | G53: =B53+C53+E53-D53-F53 -> 0 | I53: =SUM(G53:H53) -> 0
A54: =报表格式!B53 -> 股权分置流通权 | B54: =未审BS!D54 -> 0 | C54: =SUMIF(账项调整!$E$5:$E$65536,IF(OR(MID(TRIM($A54),2,1)="：",MID(TRIM($A54),2,1)="、"),REPLACEB(TRIM($A54),1,4,""),TRIM($A54)),账项调整!$J$5:$J$65536) -> 0 | D54: =SUMIF(账项调整!$H$5:$H$65536,IF(OR(MID(TRIM($A54),2,1)="：",MID(TRIM($A54),2,1)="、"),REPLACEB(TRIM($A54),1,4,""),TRIM($A54)),账项调整!$J$5:$J$65536) -> 0 | E54: =SUMIF(报表调整!$E$5:$E$65536,IF(OR(MID(TRIM($A54),2,1)="：",MID(TRIM($A54),2,1)="、"),REPLACEB(TRIM($A54),1,4,""),TRIM($A54)),报表调整!$J$5:$J$65536) -> 0 | F54: =SUMIF(报表调整!$H$5:$H$65536,IF(OR(MID(TRIM($A54),2,1)="：",MID(TRIM($A54),2,1)="、"),REPLACEB(TRIM($A54),1,4,""),TRIM($A54)),报表调整!$J$5:$J$65536) -> 0 | G54: =B54+C54+E54-D54-F54 -> 0 | I54: =SUM(G54:H54) -> 0
A55: =报表格式!B54 -> 其他长期资产 | B55: =未审BS!D55 -> 0 | C55: =SUMIF(账项调整!$E$5:$E$65536,IF(OR(MID(TRIM($A55),2,1)="：",MID(TRIM($A55),2,1)="、"),REPLACEB(TRIM($A55),1,4,""),TRIM($A55)),账项调整!$J$5:$J$65536) -> 0 | D55: =SUMIF(账项调整!$H$5:$H$65536,IF(OR(MID(TRIM($A55),2,1)="：",MID(TRIM($A55),2,1)="、"),REPLACEB(TRIM($A55),1,4,""),TRIM($A55)),账项调整!$J$5:$J$65536) -> 0 | E55: =SUMIF(报表调整!$E$5:$E$65536,IF(OR(MID(TRIM($A55),2,1)="：",MID(TRIM($A55),2,1)="、"),REPLACEB(TRIM($A55),1,4,""),TRIM($A55)),报表调整!$J$5:$J$65536) -> 0 | F55: =SUMIF(报表调整!$H$5:$H$65536,IF(OR(MID(TRIM($A55),2,1)="：",MID(TRIM($A55),2,1)="、"),REPLACEB(TRIM($A55),1,4,""),TRIM($A55)),报表调整!$J$5:$J$65536) -> 0 | G55: =B55+C55+E55-D55-F55 -> 0 | I55: =SUM(G55:H55) -> 0
A56: =报表格式!B55 -> 其中：特准储备物资 | B56: =未审BS!D56 -> 0 | C56: =SUMIF(账项调整!$F$5:$F$65536,IF(OR(MID(TRIM($A56),2,1)="：",MID(TRIM($A56),2,1)="、"),REPLACEB(TRIM($A56),1,4,""),TRIM($A56)),账项调整!$J$5:$J$65536) -> 0 | D56: =SUMIF(账项调整!$I$5:$I$65536,IF(OR(MID(TRIM($A56),2,1)="：",MID(TRIM($A56),2,1)="、"),REPLACEB(TRIM($A56),1,4,""),TRIM($A56)),账项调整!$J$5:$J$65536) -> 0 | E56: =SUMIF(报表调整!$F$5:$F$65536,IF(OR(MID(TRIM($A56),2,1)="：",MID(TRIM($A56),2,1)="、"),REPLACEB(TRIM($A56),1,4,""),TRIM($A56)),报表调整!$J$5:$J$65536) -> 0 | F56: =SUMIF(报表调整!$I$5:$I$65536,IF(OR(MID(TRIM($A56),2,1)="：",MID(TRIM($A56),2,1)="、"),REPLACEB(TRIM($A56),1,4,""),TRIM($A56)),报表调整!$J$5:$J$65536) -> 0 | G56: =B56+C56+E56-D56-F56 -> 0 | I56: =SUM(G56:H56) -> 0
A57: =报表格式!B56 -> 0 | B57: =未审BS!D57 -> 0 | C57: =SUMIF(账项调整!$E$5:$E$65536,IF(OR(MID(TRIM($A57),2,1)="：",MID(TRIM($A57),2,1)="、"),REPLACEB(TRIM($A57),1,4,""),TRIM($A57)),账项调整!$J$5:$J$65536) -> 0 | D57: =SUMIF(账项调整!$H$5:$H$65536,IF(OR(MID(TRIM($A57),2,1)="：",MID(TRIM($A57),2,1)="、"),REPLACEB(TRIM($A57),1,4,""),TRIM($A57)),账项调整!$J$5:$J$65536) -> 0 | E57: =SUMIF(报表调整!$E$5:$E$65536,IF(OR(MID(TRIM($A57),2,1)="：",MID(TRIM($A57),2,1)="、"),REPLACEB(TRIM($A57),1,4,""),TRIM($A57)),报表调整!$J$5:$J$65536) -> 0 | F57: =SUMIF(报表调整!$H$5:$H$65536,IF(OR(MID(TRIM($A57),2,1)="：",MID(TRIM($A57),2,1)="、"),REPLACEB(TRIM($A57),1,4,""),TRIM($A57)),报表调整!$J$5:$J$65536) -> 0 | G57: =B57+C57+E57-D57-F57 -> 0 | I57: =SUM(G57:H57) -> 0
A58: =报表格式!B57 -> 无形资产及其他资产合计 | B58: =SUM(B49,B51,B54:B55,B57) -> 0 | C58: =SUM(C49,C51,C54:C55,C57) -> 0 | D58: =SUM(D49,D51,D54:D55,D57) -> 0 | E58: =SUM(E49,E51,E54:E55,E57) -> 0 | F58: =SUM(F49,F51,F54:F55,F57) -> 0 | G58: =SUM(G49,G51,G54:G55,G57) -> 0 | H58: =SUM(H49,H51,H54:H55,H57) -> 0 | I58: =SUM(G58:H58) -> 0
A59: =报表格式!B58 -> 递延税项：
A60: =报表格式!B59 -> 递延税款借项 | B60: =未审BS!D60 -> 0 | C60: =SUMIF(账项调整!$E$5:$E$65536,IF(OR(MID(TRIM($A60),2,1)="：",MID(TRIM($A60),2,1)="、"),REPLACEB(TRIM($A60),1,4,""),TRIM($A60)),账项调整!$J$5:$J$65536) -> 0 | D60: =SUMIF(账项调整!$H$5:$H$65536,IF(OR(MID(TRIM($A60),2,1)="：",MID(TRIM($A60),2,1)="、"),REPLACEB(TRIM($A60),1,4,""),TRIM($A60)),账项调整!$J$5:$J$65536) -> 0 | E60: =SUMIF(报表调整!$E$5:$E$65536,IF(OR(MID(TRIM($A60),2,1)="：",MID(TRIM($A60),2,1)="、"),REPLACEB(TRIM($A60),1,4,""),TRIM($A60)),报表调整!$J$5:$J$65536) -> 0 | F60: =SUMIF(报表调整!$H$5:$H$65536,IF(OR(MID(TRIM($A60),2,1)="：",MID(TRIM($A60),2,1)="、"),REPLACEB(TRIM($A60),1,4,""),TRIM($A60)),报表调整!$J$5:$J$65536) -> 0 | G60: =B60+C60+E60-D60-F60 -> 0 | I60: =SUM(G60:H60) -> 0
A61: =报表格式!B60 -> 0 | B61: =期初核对BS!C61 -> 0 | C61: =SUMIF(账项调整!$E$5:$E$65536,IF(OR(MID(TRIM($A61),2,1)="：",MID(TRIM($A61),2,1)="、"),REPLACEB(TRIM($A61),1,4,""),TRIM($A61)),账项调整!$J$5:$J$65536) -> 0 | D61: =SUMIF(账项调整!$H$5:$H$65536,IF(OR(MID(TRIM($A61),2,1)="：",MID(TRIM($A61),2,1)="、"),REPLACEB(TRIM($A61),1,4,""),TRIM($A61)),账项调整!$J$5:$J$65536) -> 0 | E61: =SUMIF(报表调整!$E$5:$E$65536,IF(OR(MID(TRIM($A61),2,1)="：",MID(TRIM($A61),2,1)="、"),REPLACEB(TRIM($A61),1,4,""),TRIM($A61)),报表调整!$J$5:$J$65536) -> 0 | F61: =SUMIF(报表调整!$H$5:$H$65536,IF(OR(MID(TRIM($A61),2,1)="：",MID(TRIM($A61),2,1)="、"),REPLACEB(TRIM($A61),1,4,""),TRIM($A61)),报表调整!$J$5:$J$65536) -> 0 | G61: =B61+C61+E61-D61-F61 -> 0 | I61: =SUM(G61:H61) -> 0
A62: =报表格式!B73 -> 资 产 总 计 | B62: =SUM(B60:B61,B58,B47,B34,B27) -> 0 | C62: =SUM(C60:C61,C58,C47,C34,C27) -> 0 | D62: =SUM(D60:D61,D58,D47,D34,D27) -> 0 | E62: =SUM(E60:E61,E58,E47,E34,E27) -> 0 | F62: =SUM(F60:F61,F58,F47,F34,F27) -> 0 | G62: =SUM(G60:G61,G58,G47,G34,G27) -> 0 | H62: =SUM(H60:H61,H58,H47,H34,H27) -> 0 | I62: =SUM(G62:H62) -> 0
B63: =B62-TB负债!B62 -> 0 | C63: =SUM(C7:C18,C21:C26,C29:C33,C36:C37,C39,C41:C46,C49,C51,C54:C55,C57,C60:C61) -> 0 | D63: =SUM(D7:D18,D21:D26,D29:D33,D36:D37,D39,D41:D46,D49,D51,D54:D55,D57,D60:D61) -> 0 | E63: =SUM(E7:E18,E21:E26,E29:E33,E36:E37,E39,E41:E46,E49,E51,E54:E55,E57,E60:E61) -> 0 | F63: =SUM(F7:F18,F21:F26,F29:F33,F36:F37,F39,F41:F46,F49,F51,F54:F55,F57,F60:F61) -> 0 | G63: =G62-TB负债!G62 -> 0 | H63: =H62-TB负债!H62 -> 0 | I63: =I62-TB负债!I62 -> 0

Sheet TB负债
A1: 资产负债表试算平衡（续）
A2: =CONCATENATE("客户名称：",参数!D3) -> 客户名称： | C2: =CONCATENATE("编制：",参数!D17) -> 编制： | E2: =CONCATENATE("复核：",参数!D18) -> 复核： | I2: =TB资产!I2 -> 索引：
A3: =CONCATENATE("会计时点：",TEXT(参数!D12,"yyyy.mm.dd")) -> 会计时点：2007.12.31 | C3: =CONCATENATE("日期：",TEXT(NOW(),"yyyy.mm.dd")) -> 日期：2023.08.14 | E3: =TB资产!E3 -> 日期： | I3: =TB资产!I3 -> 分页：
A4: =IF((ROUND(G62,2))=(ROUND(TB资产!G62,2)),IF(参数!D$8="股份有限公司"," 负债和股东权益",IF(参数!D$8="一般企业（执行统一会计制度）","负债和所有权益","")),"报表未调平!") -> 负债和所有权益 | B4: 企业原报数 | C4: 账项调整 | E4: 报表调整 | G4: 调后数 | H4: 剥离调整 | I4: 审定数
C5: 借方 | D5: 贷方 | E5: 借方 | F5: 贷方
A6: =报表格式!G5 -> 流动负债：
A7: =报表格式!G6 -> 短期借款 | B7: =未审BS!H7 -> 0 | C7: =SUMIF(账项调整!$E$5:$E$65536,IF(OR(MID(TRIM($A7),2,1)="：",MID(TRIM($A7),2,1)="、"),REPLACEB(TRIM($A7),1,4,""),TRIM($A7)),账项调整!$J$5:$J$65536) -> 0 | D7: =SUMIF(账项调整!$H$5:$H$65536,IF(OR(MID(TRIM($A7),2,1)="：",MID(TRIM($A7),2,1)="、"),REPLACEB(TRIM($A7),1,4,""),TRIM($A7)),账项调整!$J$5:$J$65536) -> 0 | E7: =SUMIF(报表调整!$E$5:$E$65536,IF(OR(MID(TRIM($A7),2,1)="：",MID(TRIM($A7),2,1)="、"),REPLACEB(TRIM($A7),1,4,""),TRIM($A7)),报表调整!$J$5:$J$65536) -> 0 | F7: =SUMIF(报表调整!$H$5:$H$65536,IF(OR(MID(TRIM($A7),2,1)="：",MID(TRIM($A7),2,1)="、"),REPLACEB(TRIM($A7),1,4,""),TRIM($A7)),报表调整!$J$5:$J$65536) -> 0 | G7: =B7-C7-E7+D7+F7 -> 0 | I7: =SUM(G7:H7) -> 0
A8: =报表格式!G7 -> 应付票据 | B8: =未审BS!H8 -> 0 | C8: =SUMIF(账项调整!$E$5:$E$65536,IF(OR(MID(TRIM($A8),2,1)="：",MID(TRIM($A8),2,1)="、"),REPLACEB(TRIM($A8),1,4,""),TRIM($A8)),账项调整!$J$5:$J$65536) -> 0 | D8: =SUMIF(账项调整!$H$5:$H$65536,IF(OR(MID(TRIM($A8),2,1)="：",MID(TRIM($A8),2,1)="、"),REPLACEB(TRIM($A8),1,4,""),TRIM($A8)),账项调整!$J$5:$J$65536) -> 0 | E8: =SUMIF(报表调整!$E$5:$E$65536,IF(OR(MID(TRIM($A8),2,1)="：",MID(TRIM($A8),2,1)="、"),REPLACEB(TRIM($A8),1,4,""),TRIM($A8)),报表调整!$J$5:$J$65536) -> 0 | F8: =SUMIF(报表调整!$H$5:$H$65536,IF(OR(MID(TRIM($A8),2,1)="：",MID(TRIM($A8),2,1)="、"),REPLACEB(TRIM($A8),1,4,""),TRIM($A8)),报表调整!$J$5:$J$65536) -> 0 | G8: =B8-C8-E8+D8+F8 -> 0 | I8: =SUM(G8:H8) -> 0
A9: =报表格式!G8 -> 应付账款 | B9: =未审BS!H9 -> 0 | C9: =SUMIF(账项调整!$E$5:$E$65536,IF(OR(MID(TRIM($A9),2,1)="：",MID(TRIM($A9),2,1)="、"),REPLACEB(TRIM($A9),1,4,""),TRIM($A9)),账项调整!$J$5:$J$65536) -> 0 | D9: =SUMIF(账项调整!$H$5:$H$65536,IF(OR(MID(TRIM($A9),2,1)="：",MID(TRIM($A9),2,1)="、"),REPLACEB(TRIM($A9),1,4,""),TRIM($A9)),账项调整!$J$5:$J$65536) -> 0 | E9: =SUMIF(报表调整!$E$5:$E$65536,IF(OR(MID(TRIM($A9),2,1)="：",MID(TRIM($A9),2,1)="、"),REPLACEB(TRIM($A9),1,4,""),TRIM($A9)),报表调整!$J$5:$J$65536) -> 0 | F9: =SUMIF(报表调整!$H$5:$H$65536,IF(OR(MID(TRIM($A9),2,1)="：",MID(TRIM($A9),2,1)="、"),REPLACEB(TRIM($A9),1,4,""),TRIM($A9)),报表调整!$J$5:$J$65536) -> 0 | G9: =B9-C9-E9+D9+F9 -> 0 | I9: =SUM(G9:H9) -> 0
A10: =报表格式!G9 -> 预收账款 | B10: =未审BS!H10 -> 0 | C10: =SUMIF(账项调整!$E$5:$E$65536,IF(OR(MID(TRIM($A10),2,1)="：",MID(TRIM($A10),2,1)="、"),REPLACEB(TRIM($A10),1,4,""),TRIM($A10)),账项调整!$J$5:$J$65536) -> 0 | D10: =SUMIF(账项调整!$H$5:$H$65536,IF(OR(MID(TRIM($A10),2,1)="：",MID(TRIM($A10),2,1)="、"),REPLACEB(TRIM($A10),1,4,""),TRIM($A10)),账项调整!$J$5:$J$65536) -> 0 | E10: =SUMIF(报表调整!$E$5:$E$65536,IF(OR(MID(TRIM($A10),2,1)="：",MID(TRIM($A10),2,1)="、"),REPLACEB(TRIM($A10),1,4,""),TRIM($A10)),报表调整!$J$5:$J$65536) -> 0 | F10: =SUMIF(报表调整!$H$5:$H$65536,IF(OR(MID(TRIM($A10),2,1)="：",MID(TRIM($A10),2,1)="、"),REPLACEB(TRIM($A10),1,4,""),TRIM($A10)),报表调整!$J$5:$J$65536) -> 0 | G10: =B10-C10-E10+D10+F10 -> 0 | I10: =SUM(G10:H10) -> 0
A11: =报表格式!G10 -> 应付工资 | B11: =未审BS!H11 -> 0 | C11: =SUMIF(账项调整!$E$5:$E$65536,IF(OR(MID(TRIM($A11),2,1)="：",MID(TRIM($A11),2,1)="、"),REPLACEB(TRIM($A11),1,4,""),TRIM($A11)),账项调整!$J$5:$J$65536) -> 0 | D11: =SUMIF(账项调整!$H$5:$H$65536,IF(OR(MID(TRIM($A11),2,1)="：",MID(TRIM($A11),2,1)="、"),REPLACEB(TRIM($A11),1,4,""),TRIM($A11)),账项调整!$J$5:$J$65536) -> 0 | E11: =SUMIF(报表调整!$E$5:$E$65536,IF(OR(MID(TRIM($A11),2,1)="：",MID(TRIM($A11),2,1)="、"),REPLACEB(TRIM($A11),1,4,""),TRIM($A11)),报表调整!$J$5:$J$65536) -> 0 | F11: =SUMIF(报表调整!$H$5:$H$65536,IF(OR(MID(TRIM($A11),2,1)="：",MID(TRIM($A11),2,1)="、"),REPLACEB(TRIM($A11),1,4,""),TRIM($A11)),报表调整!$J$5:$J$65536) -> 0 | G11: =B11-C11-E11+D11+F11 -> 0 | I11: =SUM(G11:H11) -> 0
A12: =报表格式!G11 -> 应付福利费 | B12: =未审BS!H12 -> 0 | C12: =SUMIF(账项调整!$E$5:$E$65536,IF(OR(MID(TRIM($A12),2,1)="：",MID(TRIM($A12),2,1)="、"),REPLACEB(TRIM($A12),1,4,""),TRIM($A12)),账项调整!$J$5:$J$65536) -> 0 | D12: =SUMIF(账项调整!$H$5:$H$65536,IF(OR(MID(TRIM($A12),2,1)="：",MID(TRIM($A12),2,1)="、"),REPLACEB(TRIM($A12),1,4,""),TRIM($A12)),账项调整!$J$5:$J$65536) -> 0 | E12: =SUMIF(报表调整!$E$5:$E$65536,IF(OR(MID(TRIM($A12),2,1)="：",MID(TRIM($A12),2,1)="、"),REPLACEB(TRIM($A12),1,4,""),TRIM($A12)),报表调整!$J$5:$J$65536) -> 0 | F12: =SUMIF(报表调整!$H$5:$H$65536,IF(OR(MID(TRIM($A12),2,1)="：",MID(TRIM($A12),2,1)="、"),REPLACEB(TRIM($A12),1,4,""),TRIM($A12)),报表调整!$J$5:$J$65536) -> 0 | G12: =B12-C12-E12+D12+F12 -> 0 | I12: =SUM(G12:H12) -> 0
A13: =报表格式!G12 -> 应付股利（利润） | B13: =未审BS!H13 -> 0 | C13: =SUMIF(账项调整!$E$5:$E$65536,IF(OR(MID(TRIM($A13),2,1)="：",MID(TRIM($A13),2,1)="、"),REPLACEB(TRIM($A13),1,4,""),TRIM($A13)),账项调整!$J$5:$J$65536) -> 0 | D13: =SUMIF(账项调整!$H$5:$H$65536,IF(OR(MID(TRIM($A13),2,1)="：",MID(TRIM($A13),2,1)="、"),REPLACEB(TRIM($A13),1,4,""),TRIM($A13)),账项调整!$J$5:$J$65536) -> 0 | E13: =SUMIF(报表调整!$E$5:$E$65536,IF(OR(MID(TRIM($A13),2,1)="：",MID(TRIM($A13),2,1)="、"),REPLACEB(TRIM($A13),1,4,""),TRIM($A13)),报表调整!$J$5:$J$65536) -> 0 | F13: =SUMIF(报表调整!$H$5:$H$65536,IF(OR(MID(TRIM($A13),2,1)="：",MID(TRIM($A13),2,1)="、"),REPLACEB(TRIM($A13),1,4,""),TRIM($A13)),报表调整!$J$5:$J$65536) -> 0 | G13: =B13-C13-E13+D13+F13 -> 0 | I13: =SUM(G13:H13) -> 0
A14: =报表格式!G13 -> 应付利息 | B14: =未审BS!H14 -> 0 | C14: =SUMIF(账项调整!$E$5:$E$65536,IF(OR(MID(TRIM($A14),2,1)="：",MID(TRIM($A14),2,1)="、"),REPLACEB(TRIM($A14),1,4,""),TRIM($A14)),账项调整!$J$5:$J$65536) -> 0 | D14: =SUMIF(账项调整!$H$5:$H$65536,IF(OR(MID(TRIM($A14),2,1)="：",MID(TRIM($A14),2,1)="、"),REPLACEB(TRIM($A14),1,4,""),TRIM($A14)),账项调整!$J$5:$J$65536) -> 0 | E14: =SUMIF(报表调整!$E$5:$E$65536,IF(OR(MID(TRIM($A14),2,1)="：",MID(TRIM($A14),2,1)="、"),REPLACEB(TRIM($A14),1,4,""),TRIM($A14)),报表调整!$J$5:$J$65536) -> 0 | F14: =SUMIF(报表调整!$H$5:$H$65536,IF(OR(MID(TRIM($A14),2,1)="：",MID(TRIM($A14),2,1)="、"),REPLACEB(TRIM($A14),1,4,""),TRIM($A14)),报表调整!$J$5:$J$65536) -> 0 | G14: =B14-C14-E14+D14+F14 -> 0 | I14: =SUM(G14:H14) -> 0
A15: =报表格式!G14 -> 应交税金 | B15: =未审BS!H15 -> 0 | C15: =SUMIF(账项调整!$E$5:$E$65536,IF(OR(MID(TRIM($A15),2,1)="：",MID(TRIM($A15),2,1)="、"),REPLACEB(TRIM($A15),1,4,""),TRIM($A15)),账项调整!$J$5:$J$65536) -> 0 | D15: =SUMIF(账项调整!$H$5:$H$65536,IF(OR(MID(TRIM($A15),2,1)="：",MID(TRIM($A15),2,1)="、"),REPLACEB(TRIM($A15),1,4,""),TRIM($A15)),账项调整!$J$5:$J$65536) -> 0 | E15: =SUMIF(报表调整!$E$5:$E$65536,IF(OR(MID(TRIM($A15),2,1)="：",MID(TRIM($A15),2,1)="、"),REPLACEB(TRIM($A15),1,4,""),TRIM($A15)),报表调整!$J$5:$J$65536) -> 0 | F15: =SUMIF(报表调整!$H$5:$H$65536,IF(OR(MID(TRIM($A15),2,1)="：",MID(TRIM($A15),2,1)="、"),REPLACEB(TRIM($A15),1,4,""),TRIM($A15)),报表调整!$J$5:$J$65536) -> 0 | G15: =B15-C15-E15+D15+F15 -> 0 | I15: =SUM(G15:H15) -> 0
A16: =报表格式!G15 -> 其他应交款 | B16: =未审BS!H16 -> 0 | C16: =SUMIF(账项调整!$E$5:$E$65536,IF(OR(MID(TRIM($A16),2,1)="：",MID(TRIM($A16),2,1)="、"),REPLACEB(TRIM($A16),1,4,""),TRIM($A16)),账项调整!$J$5:$J$65536) -> 0 | D16: =SUMIF(账项调整!$H$5:$H$65536,IF(OR(MID(TRIM($A16),2,1)="：",MID(TRIM($A16),2,1)="、"),REPLACEB(TRIM($A16),1,4,""),TRIM($A16)),账项调整!$J$5:$J$65536) -> 0 | E16: =SUMIF(报表调整!$E$5:$E$65536,IF(OR(MID(TRIM($A16),2,1)="：",MID(TRIM($A16),2,1)="、"),REPLACEB(TRIM($A16),1,4,""),TRIM($A16)),报表调整!$J$5:$J$65536) -> 0 | F16: =SUMIF(报表调整!$H$5:$H$65536,IF(OR(MID(TRIM($A16),2,1)="：",MID(TRIM($A16),2,1)="、"),REPLACEB(TRIM($A16),1,4,""),TRIM($A16)),报表调整!$J$5:$J$65536) -> 0 | G16: =B16-C16-E16+D16+F16 -> 0 | I16: =SUM(G16:H16) -> 0
A17: =报表格式!G16 -> 其他应付款 | B17: =未审BS!H17 -> 0 | C17: =SUMIF(账项调整!$E$5:$E$65536,IF(OR(MID(TRIM($A17),2,1)="：",MID(TRIM($A17),2,1)="、"),REPLACEB(TRIM($A17),1,4,""),TRIM($A17)),账项调整!$J$5:$J$65536) -> 0 | D17: =SUMIF(账项调整!$H$5:$H$65536,IF(OR(MID(TRIM($A17),2,1)="：",MID(TRIM($A17),2,1)="、"),REPLACEB(TRIM($A17),1,4,""),TRIM($A17)),账项调整!$J$5:$J$65536) -> 0 | E17: =SUMIF(报表调整!$E$5:$E$65536,IF(OR(MID(TRIM($A17),2,1)="：",MID(TRIM($A17),2,1)="、"),REPLACEB(TRIM($A17),1,4,""),TRIM($A17)),报表调整!$J$5:$J$65536) -> 0 | F17: =SUMIF(报表调整!$H$5:$H$65536,IF(OR(MID(TRIM($A17),2,1)="：",MID(TRIM($A17),2,1)="、"),REPLACEB(TRIM($A17),1,4,""),TRIM($A17)),报表调整!$J$5:$J$65536) -> 0 | G17: =B17-C17-E17+D17+F17 -> 0 | I17: =SUM(G17:H17) -> 0
A18: =报表格式!G17 -> 预提费用 | B18: =未审BS!H18 -> 0 | C18: =SUMIF(账项调整!$E$5:$E$65536,IF(OR(MID(TRIM($A18),2,1)="：",MID(TRIM($A18),2,1)="、"),REPLACEB(TRIM($A18),1,4,""),TRIM($A18)),账项调整!$J$5:$J$65536) -> 0 | D18: =SUMIF(账项调整!$H$5:$H$65536,IF(OR(MID(TRIM($A18),2,1)="：",MID(TRIM($A18),2,1)="、"),REPLACEB(TRIM($A18),1,4,""),TRIM($A18)),账项调整!$J$5:$J$65536) -> 0 | E18: =SUMIF(报表调整!$E$5:$E$65536,IF(OR(MID(TRIM($A18),2,1)="：",MID(TRIM($A18),2,1)="、"),REPLACEB(TRIM($A18),1,4,""),TRIM($A18)),报表调整!$J$5:$J$65536) -> 0 | F18: =SUMIF(报表调整!$H$5:$H$65536,IF(OR(MID(TRIM($A18),2,1)="：",MID(TRIM($A18),2,1)="、"),REPLACEB(TRIM($A18),1,4,""),TRIM($A18)),报表调整!$J$5:$J$65536) -> 0 | G18: =B18-C18-E18+D18+F18 -> 0 | I18: =SUM(G18:H18) -> 0
... A25: =报表格式!G24 -> 0 | B25: =未审BS!H25 -> 0 | C25: =SUMIF(账项调整!$E$5:$E$65536,IF(OR(MID(TRIM($A25),2,1)="：",MID(TRIM($A25),2,1)="、"),REPLACEB(TRIM($A25),1,4,""),TRIM($A25)),账项调整!$J$5:$J$65536) -> 0 | D25: =SUMIF(账项调整!$H$5:$H$65536,IF(OR(MID(TRIM($A25),2,1)="：",MID(TRIM($A25),2,1)="、"),REPLACEB(TRIM($A25),1,4,""),TRIM($A25)),账项调整!$J$5:$J$65536) -> 0 | E25: =SUMIF(报表调整!$E$5:$E$65536,IF(OR(MID(TRIM($A25),2,1)="：",MID(TRIM($A25),2,1)="、"),REPLACEB(TRIM($A25),1,4,""),TRIM($A25)),报表调整!$J$5:$J$65536) -> 0 | F25: =SUMIF(报表调整!$H$5:$H$65536,IF(OR(MID(TRIM($A25),2,1)="：",MID(TRIM($A25),2,1)="、"),REPLACEB(TRIM($A25),1,4,""),TRIM($A25)),报表调整!$J$5:$J$65536) -> 0 | G25: =B25-C25-E25+D25+F25 -> 0 | I25: =SUM(G25:H25) -> 0
A26: =报表格式!G25 -> 流动负债合计 | B26: =SUM(B7:B25) -> 0 | C26: =SUM(C7:C25) -> 0 | D26: =SUM(D7:D25) -> 0 | E26: =SUM(E7:E25) -> 0 | F26: =SUM(F7:F25) -> 0 | G26: =SUM(G7:G25) -> 0 | H26: =SUM(H7:H25) -> 0 | I26: =SUM(G26:H26) -> 0
A27: =报表格式!G26 -> 长期负债：
A28: =报表格式!G27 -> 长期借款 | B28: =未审BS!H28 -> 0 | C28: =SUMIF(账项调整!$E$5:$E$65536,IF(OR(MID(TRIM($A28),2,1)="：",MID(TRIM($A28),2,1)="、"),REPLACEB(TRIM($A28),1,4,""),TRIM($A28)),账项调整!$J$5:$J$65536) -> 0 | D28: =SUMIF(账项调整!$H$5:$H$65536,IF(OR(MID(TRIM($A28),2,1)="：",MID(TRIM($A28),2,1)="、"),REPLACEB(TRIM($A28),1,4,""),TRIM($A28)),账项调整!$J$5:$J$65536) -> 0 | E28: =SUMIF(报表调整!$E$5:$E$65536,IF(OR(MID(TRIM($A28),2,1)="：",MID(TRIM($A28),2,1)="、"),REPLACEB(TRIM($A28),1,4,""),TRIM($A28)),报表调整!$J$5:$J$65536) -> 0 | F28: =SUMIF(报表调整!$H$5:$H$65536,IF(OR(MID(TRIM($A28),2,1)="：",MID(TRIM($A28),2,1)="、"),REPLACEB(TRIM($A28),1,4,""),TRIM($A28)),报表调整!$J$5:$J$65536) -> 0 | G28: =B28-C28-E28+D28+F28 -> 0 | I28: =SUM(G28:H28) -> 0
A29: =报表格式!G28 -> 应付债券 | B29: =未审BS!H29 -> 0 | C29: =SUMIF(账项调整!$E$5:$E$65536,IF(OR(MID(TRIM($A29),2,1)="：",MID(TRIM($A29),2,1)="、"),REPLACEB(TRIM($A29),1,4,""),TRIM($A29)),账项调整!$J$5:$J$65536) -> 0 | D29: =SUMIF(账项调整!$H$5:$H$65536,IF(OR(MID(TRIM($A29),2,1)="：",MID(TRIM($A29),2,1)="、"),REPLACEB(TRIM($A29),1,4,""),TRIM($A29)),账项调整!$J$5:$J$65536) -> 0 | E29: =SUMIF(报表调整!$E$5:$E$65536,IF(OR(MID(TRIM($A29),2,1)="：",MID(TRIM($A29),2,1)="、"),REPLACEB(TRIM($A29),1,4,""),TRIM($A29)),报表调整!$J$5:$J$65536) -> 0 | F29: =SUMIF(报表调整!$H$5:$H$65536,IF(OR(MID(TRIM($A29),2,1)="：",MID(TRIM($A29),2,1)="、"),REPLACEB(TRIM($A29),1,4,""),TRIM($A29)),报表调整!$J$5:$J$65536) -> 0 | G29: =B29-C29-E29+D29+F29 -> 0 | I29: =SUM(G29:H29) -> 0
A30: =报表格式!G29 -> 长期应付款 | B30: =未审BS!H30 -> 0 | C30: =SUMIF(账项调整!$E$5:$E$65536,IF(OR(MID(TRIM($A30),2,1)="：",MID(TRIM($A30),2,1)="、"),REPLACEB(TRIM($A30),1,4,""),TRIM($A30)),账项调整!$J$5:$J$65536) -> 0 | D30: =SUMIF(账项调整!$H$5:$H$65536,IF(OR(MID(TRIM($A30),2,1)="：",MID(TRIM($A30),2,1)="、"),REPLACEB(TRIM($A30),1,4,""),TRIM($A30)),账项调整!$J$5:$J$65536) -> 0 | E30: =SUMIF(报表调整!$E$5:$E$65536,IF(OR(MID(TRIM($A30),2,1)="：",MID(TRIM($A30),2,1)="、"),REPLACEB(TRIM($A30),1,4,""),TRIM($A30)),报表调整!$J$5:$J$65536) -> 0 | F30: =SUMIF(报表调整!$H$5:$H$65536,IF(OR(MID(TRIM($A30),2,1)="：",MID(TRIM($A30),2,1)="、"),REPLACEB(TRIM($A30),1,4,""),TRIM($A30)),报表调整!$J$5:$J$65536) -> 0 | G30: =B30-C30-E30+D30+F30 -> 0 | I30: =SUM(G30:H30) -> 0
A31: =报表格式!G30 -> 专项应付款 | B31: =未审BS!H31 -> 0 | C31: =SUMIF(账项调整!$E$5:$E$65536,IF(OR(MID(TRIM($A31),2,1)="：",MID(TRIM($A31),2,1)="、"),REPLACEB(TRIM($A31),1,4,""),TRIM($A31)),账项调整!$J$5:$J$65536) -> 0 | D31: =SUMIF(账项调整!$H$5:$H$65536,IF(OR(MID(TRIM($A31),2,1)="：",MID(TRIM($A31),2,1)="、"),REPLACEB(TRIM($A31),1,4,""),TRIM($A31)),账项调整!$J$5:$J$65536) -> 0 | E31: =SUMIF(报表调整!$E$5:$E$65536,IF(OR(MID(TRIM($A31),2,1)="：",MID(TRIM($A31),2,1)="、"),REPLACEB(TRIM($A31),1,4,""),TRIM($A31)),报表调整!$J$5:$J$65536) -> 0 | F31: =SUMIF(报表调整!$H$5:$H$65536,IF(OR(MID(TRIM($A31),2,1)="：",MID(TRIM($A31),2,1)="、"),REPLACEB(TRIM($A31),1,4,""),TRIM($A31)),报表调整!$J$5:$J$65536) -> 0 | G31: =B31-C31-E31+D31+F31 -> 0 | I31: =SUM(G31:H31) -> 0
A32: =报表格式!G31 -> 其他长期负债 | B32: =未审BS!H32 -> 0 | C32: =SUMIF(账项调整!$E$5:$E$65536,IF(OR(MID(TRIM($A32),2,1)="：",MID(TRIM($A32),2,1)="、"),REPLACEB(TRIM($A32),1,4,""),TRIM($A32)),账项调整!$J$5:$J$65536) -> 0 | D32: =SUMIF(账项调整!$H$5:$H$65536,IF(OR(MID(TRIM($A32),2,1)="：",MID(TRIM($A32),2,1)="、"),REPLACEB(TRIM($A32),1,4,""),TRIM($A32)),账项调整!$J$5:$J$65536) -> 0 | E32: =SUMIF(报表调整!$E$5:$E$65536,IF(OR(MID(TRIM($A32),2,1)="：",MID(TRIM($A32),2,1)="、"),REPLACEB(TRIM($A32),1,4,""),TRIM($A32)),报表调整!$J$5:$J$65536) -> 0 | F32: =SUMIF(报表调整!$H$5:$H$65536,IF(OR(MID(TRIM($A32),2,1)="：",MID(TRIM($A32),2,1)="、"),REPLACEB(TRIM($A32),1,4,""),TRIM($A32)),报表调整!$J$5:$J$65536) -> 0 | G32: =B32-C32-E32+D32+F32 -> 0 | I32: =SUM(G32:H32) -> 0
A33: =报表格式!G32 -> 其中：特准储备资金 | B33: =未审BS!H33 -> 0 | C33: =SUMIF(账项调整!$F$5:$F$65536,IF(OR(MID(TRIM($A33),2,1)="：",MID(TRIM($A33),2,1)="、"),REPLACEB(TRIM($A33),1,4,""),TRIM($A33)),账项调整!$J$5:$J$65536) -> 0 | D33: =SUMIF(账项调整!$I$5:$I$65536,IF(OR(MID(TRIM($A33),2,1)="：",MID(TRIM($A33),2,1)="、"),REPLACEB(TRIM($A33),1,4,""),TRIM($A33)),账项调整!$J$5:$J$65536) -> 0 | E33: =SUMIF(报表调整!$F$5:$F$65536,IF(OR(MID(TRIM($A33),2,1)="：",MID(TRIM($A33),2,1)="、"),REPLACEB(TRIM($A33),1,4,""),TRIM($A33)),报表调整!$J$5:$J$65536) -> 0 | F33: =SUMIF(报表调整!$I$5:$I$65536,IF(OR(MID(TRIM($A33),2,1)="：",MID(TRIM($A33),2,1)="、"),REPLACEB(TRIM($A33),1,4,""),TRIM($A33)),报表调整!$J$5:$J$65536) -> 0 | G33: =B33-C33-E33+D33+F33 -> 0 | I33: =SUM(G33:H33) -> 0
A34: =报表格式!G33 -> 0 | B34: =未审BS!H34 -> 0 | C34: =SUMIF(账项调整!$E$5:$E$65536,IF(OR(MID(TRIM($A34),2,1)="：",MID(TRIM($A34),2,1)="、"),REPLACEB(TRIM($A34),1,4,""),TRIM($A34)),账项调整!$J$5:$J$65536) -> 0 | D34: =SUMIF(账项调整!$H$5:$H$65536,IF(OR(MID(TRIM($A34),2,1)="：",MID(TRIM($A34),2,1)="、"),REPLACEB(TRIM($A34),1,4,""),TRIM($A34)),账项调整!$J$5:$J$65536) -> 0 | E34: =SUMIF(报表调整!$E$5:$E$65536,IF(OR(MID(TRIM($A34),2,1)="：",MID(TRIM($A34),2,1)="、"),REPLACEB(TRIM($A34),1,4,""),TRIM($A34)),报表调整!$J$5:$J$65536) -> 0 | F34: =SUMIF(报表调整!$H$5:$H$65536,IF(OR(MID(TRIM($A34),2,1)="：",MID(TRIM($A34),2,1)="、"),REPLACEB(TRIM($A34),1,4,""),TRIM($A34)),报表调整!$J$5:$J$65536) -> 0 | G34: =B34-C34-E34+D34+F34 -> 0 | I34: =SUM(G34:H34) -> 0
A35: =报表格式!G34 -> 0 | B35: =未审BS!H35 -> 0 | C35: =SUMIF(账项调整!$E$5:$E$65536,IF(OR(MID(TRIM($A35),2,1)="：",MID(TRIM($A35),2,1)="、"),REPLACEB(TRIM($A35),1,4,""),TRIM($A35)),账项调整!$J$5:$J$65536) -> 0 | D35: =SUMIF(账项调整!$H$5:$H$65536,IF(OR(MID(TRIM($A35),2,1)="：",MID(TRIM($A35),2,1)="、"),REPLACEB(TRIM($A35),1,4,""),TRIM($A35)),账项调整!$J$5:$J$65536) -> 0 | E35: =SUMIF(报表调整!$E$5:$E$65536,IF(OR(MID(TRIM($A35),2,1)="：",MID(TRIM($A35),2,1)="、"),REPLACEB(TRIM($A35),1,4,""),TRIM($A35)),报表调整!$J$5:$J$65536) -> 0 | F35: =SUMIF(报表调整!$H$5:$H$65536,IF(OR(MID(TRIM($A35),2,1)="：",MID(TRIM($A35),2,1)="、"),REPLACEB(TRIM($A35),1,4,""),TRIM($A35)),报表调整!$J$5:$J$65536) -> 0 | G35: =B35-C35-E35+D35+F35 -> 0 | I35: =SUM(G35:H35) -> 0
A36: =报表格式!G35 -> 长期负债合计 | B36: =SUM(B28:B32)+SUM(B34:B35) -> 0 | C36: =SUM(C28:C32)+SUM(C34:C35) -> 0 | D36: =SUM(D28:D32)+SUM(D34:D35) -> 0 | E36: =SUM(E28:E32)+SUM(E34:E35) -> 0 | F36: =SUM(F28:F32)+SUM(F34:F35) -> 0 | G36: =SUM(G28:G32)+SUM(G34:G35) -> 0 | H36: =SUM(H28:H32)+SUM(H34:H35) -> 0 | I36: =SUM(G36:H36) -> 0
A37: =报表格式!G36 -> 递延税项：
A38: =报表格式!G37 -> 递延税款贷项 | B38: =未审BS!H38 -> 0 | C38: =SUMIF(账项调整!$E$5:$E$65536,IF(OR(MID(TRIM($A38),2,1)="：",MID(TRIM($A38),2,1)="、"),REPLACEB(TRIM($A38),1,4,""),TRIM($A38)),账项调整!$J$5:$J$65536) -> 0 | D38: =SUMIF(账项调整!$H$5:$H$65536,IF(OR(MID(TRIM($A38),2,1)="：",MID(TRIM($A38),2,1)="、"),REPLACEB(TRIM($A38),1,4,""),TRIM($A38)),账项调整!$J$5:$J$65536) -> 0 | E38: =SUMIF(报表调整!$E$5:$E$65536,IF(OR(MID(TRIM($A38),2,1)="：",MID(TRIM($A38),2,1)="、"),REPLACEB(TRIM($A38),1,4,""),TRIM($A38)),报表调整!$J$5:$J$65536) -> 0 | F38: =SUMIF(报表调整!$H$5:$H$65536,IF(OR(MID(TRIM($A38),2,1)="：",MID(TRIM($A38),2,1)="、"),REPLACEB(TRIM($A38),1,4,""),TRIM($A38)),报表调整!$J$5:$J$65536) -> 0 | G38: =B38-C38-E38+D38+F38 -> 0 | I38: =SUM(G38:H38) -> 0
A39: =报表格式!G38 -> 负 债 合 计 | B39: =SUM(B38:B38,B36,B26) -> 0 | C39: =SUM(C38:C38,C36,C26) -> 0 | D39: =SUM(D38:D38,D36,D26) -> 0 | E39: =SUM(E38:E38,E36,E26) -> 0 | F39: =SUM(F38:F38,F36,F26) -> 0 | G39: =SUM(G38:G38,G36,G26) -> 0 | H39: =SUM(H38:H38,H36,H26) -> 0 | I39: =SUM(G39:H39) -> 0
A40: =报表格式!G39 -> *少数股东权益 | B40: =未审BS!H40 -> 0 | C40: =SUMIF(账项调整!$E$5:$E$65536,REPLACEB(IF(OR(MID(TRIM($A40),2,1)="：",MID(TRIM($A40),2,1)="、"),REPLACEB(TRIM($A40),1,4,""),TRIM($A40)),1,1,""),账项调整!$J$5:$J$65536) -> 0 | D40: =SUMIF(账项调整!$H$5:$H$65536,REPLACEB(IF(OR(MID(TRIM($A40),2,1)="：",MID(TRIM($A40),2,1)="、"),REPLACEB(TRIM($A40),1,4,""),TRIM($A40)),1,1,""),账项调整!$J$5:$J$65536) -> 0 | E40: =SUMIF(报表调整!$E$5:$E$65536,REPLACEB(IF(OR(MID(TRIM($A40),2,1)="：",MID(TRIM($A40),2,1)="、"),REPLACEB(TRIM($A40),1,4,""),TRIM($A40)),1,1,""),报表调整!$J$5:$J$65536) -> 0 | F40: =SUMIF(报表调整!$H$5:$H$65536,REPLACEB(IF(OR(MID(TRIM($A40),2,1)="：",MID(TRIM($A40),2,1)="、"),REPLACEB(TRIM($A40),1,4,""),TRIM($A40)),1,1,""),报表调整!$J$5:$J$65536) -> 0 | G40: =B40-C40-E40+D40+F40 -> 0 | I40: =SUM(G40:H40) -> 0
A41: =报表格式!G40 -> 0 | B41: =未审BS!H41 -> 0 | C41: =SUMIF(账项调整!$E$5:$E$65536,IF(OR(MID(TRIM($A41),2,1)="：",MID(TRIM($A41),2,1)="、"),REPLACEB(TRIM($A41),1,4,""),TRIM($A41)),账项调整!$J$5:$J$65536) -> 0 | D41: =SUMIF(账项调整!$H$5:$H$65536,IF(OR(MID(TRIM($A41),2,1)="：",MID(TRIM($A41),2,1)="、"),REPLACEB(TRIM($A41),1,4,""),TRIM($A41)),账项调整!$J$5:$J$65536) -> 0 | E41: =SUMIF(报表调整!$E$5:$E$65536,IF(OR(MID(TRIM($A41),2,1)="：",MID(TRIM($A41),2,1)="、"),REPLACEB(TRIM($A41),1,4,""),TRIM($A41)),报表调整!$J$5:$J$65536) -> 0 | F41: =SUMIF(报表调整!$H$5:$H$65536,IF(OR(MID(TRIM($A41),2,1)="：",MID(TRIM($A41),2,1)="、"),REPLACEB(TRIM($A41),1,4,""),TRIM($A41)),报表调整!$J$5:$J$65536) -> 0 | G41: =B41-C41-E41+D41+F41 -> 0 | I41: =SUM(G41:H41) -> 0
A42: =报表格式!G41 -> 所有者权益：
A43: =报表格式!G42 -> 实收资本 | B43: =未审BS!H43 -> 0 | C43: =SUMIF(账项调整!$E$5:$E$65536,IF(OR(MID(TRIM($A43),2,1)="：",MID(TRIM($A43),2,1)="、"),REPLACEB(TRIM($A43),1,4,""),TRIM($A43)),账项调整!$J$5:$J$65536) -> 0 | D43: =SUMIF(账项调整!$H$5:$H$65536,IF(OR(MID(TRIM($A43),2,1)="：",MID(TRIM($A43),2,1)="、"),REPLACEB(TRIM($A43),1,4,""),TRIM($A43)),账项调整!$J$5:$J$65536) -> 0 | E43: =SUMIF(报表调整!$E$5:$E$65536,IF(OR(MID(TRIM($A43),2,1)="：",MID(TRIM($A43),2,1)="、"),REPLACEB(TRIM($A43),1,4,""),TRIM($A43)),报表调整!$J$5:$J$65536) -> 0 | F43: =SUMIF(报表调整!$H$5:$H$65536,IF(OR(MID(TRIM($A43),2,1)="：",MID(TRIM($A43),2,1)="、"),REPLACEB(TRIM($A43),1,4,""),TRIM($A43)),报表调整!$J$5:$J$65536) -> 0 | G43: =B43-C43-E43+D43+F43 -> 0 | I43: =SUM(G43:H43) -> 0
A44: =报表格式!G43 -> 国家资本 | B44: =未审BS!H44 -> 0 | C44: =SUMIF(账项调整!$E$5:$E$65536,IF(OR(MID(TRIM($A44),2,1)="：",MID(TRIM($A44),2,1)="、"),REPLACEB(TRIM($A44),1,4,""),TRIM($A44)),账项调整!$J$5:$J$65536) -> 0 | D44: =SUMIF(账项调整!$H$5:$H$65536,IF(OR(MID(TRIM($A44),2,1)="：",MID(TRIM($A44),2,1)="、"),REPLACEB(TRIM($A44),1,4,""),TRIM($A44)),账项调整!$J$5:$J$65536) -> 0 | E44: =SUMIF(报表调整!$E$5:$E$65536,IF(OR(MID(TRIM($A44),2,1)="：",MID(TRIM($A44),2,1)="、"),REPLACEB(TRIM($A44),1,4,""),TRIM($A44)),报表调整!$J$5:$J$65536) -> 0 | F44: =SUMIF(报表调整!$H$5:$H$65536,IF(OR(MID(TRIM($A44),2,1)="：",MID(TRIM($A44),2,1)="、"),REPLACEB(TRIM($A44),1,4,""),TRIM($A44)),报表调整!$J$5:$J$65536) -> 0 | G44: =B44-C44-E44+D44+F44 -> 0 | I44: =SUM(G44:H44) -> 0
A45: =报表格式!G44 -> 集体资本 | B45: =未审BS!H45 -> 0 | C45: =SUMIF(账项调整!$E$5:$E$65536,IF(OR(MID(TRIM($A45),2,1)="：",MID(TRIM($A45),2,1)="、"),REPLACEB(TRIM($A45),1,4,""),TRIM($A45)),账项调整!$J$5:$J$65536) -> 0 | D45: =SUMIF(账项调整!$H$5:$H$65536,IF(OR(MID(TRIM($A45),2,1)="：",MID(TRIM($A45),2,1)="、"),REPLACEB(TRIM($A45),1,4,""),TRIM($A45)),账项调整!$J$5:$J$65536) -> 0 | E45: =SUMIF(报表调整!$E$5:$E$65536,IF(OR(MID(TRIM($A45),2,1)="：",MID(TRIM($A45),2,1)="、"),REPLACEB(TRIM($A45),1,4,""),TRIM($A45)),报表调整!$J$5:$J$65536) -> 0 | F45: =SUMIF(报表调整!$H$5:$H$65536,IF(OR(MID(TRIM($A45),2,1)="：",MID(TRIM($A45),2,1)="、"),REPLACEB(TRIM($A45),1,4,""),TRIM($A45)),报表调整!$J$5:$J$65536) -> 0 | G45: =B45-C45-E45+D45+F45 -> 0 | I45: =SUM(G45:H45) -> 0
A46: =报表格式!G45 -> 法人资本 | B46: =未审BS!H46 -> 0 | C46: =SUM(C47:C48) -> 0 | D46: =SUM(D47:D48) -> 0 | E46: =SUM(E47:E48) -> 0 | F46: =SUM(F47:F48) -> 0 | G46: =B46-C46-E46+D46+F46 -> 0 | I46: =SUM(G46:H46) -> 0
A47: =报表格式!G46 -> 其中：国有法人资本 | B47: =未审BS!H47 -> 0 | C47: =SUMIF(账项调整!$F$5:$F$65536,IF(OR(MID(TRIM($A47),2,1)="：",MID(TRIM($A47),2,1)="、"),REPLACEB(TRIM($A47),1,4,""),TRIM($A47)),账项调整!$J$5:$J$65536) -> 0 | D47: =SUMIF(账项调整!$I$5:$I$65536,IF(OR(MID(TRIM($A47),2,1)="：",MID(TRIM($A47),2,1)="、"),REPLACEB(TRIM($A47),1,4,""),TRIM($A47)),账项调整!$J$5:$J$65536) -> 0 | E47: =SUMIF(报表调整!$F$5:$F$65536,IF(OR(MID(TRIM($A47),2,1)="：",MID(TRIM($A47),2,1)="、"),REPLACEB(TRIM($A47),1,4,""),TRIM($A47)),报表调整!$J$5:$J$65536) -> 0 | F47: =SUMIF(报表调整!$I$5:$I$65536,IF(OR(MID(TRIM($A47),2,1)="：",MID(TRIM($A47),2,1)="、"),REPLACEB(TRIM($A47),1,4,""),TRIM($A47)),报表调整!$J$5:$J$65536) -> 0 | G47: =B47-C47-E47+D47+F47 -> 0 | I47: =SUM(G47:H47) -> 0
A48: =报表格式!G47 -> 集体法人资本 | B48: =未审BS!H48 -> 0 | C48: =SUMIF(账项调整!$F$5:$F$65536,IF(OR(MID(TRIM($A48),2,1)="：",MID(TRIM($A48),2,1)="、"),REPLACEB(TRIM($A48),1,4,""),TRIM($A48)),账项调整!$J$5:$J$65536) -> 0 | D48: =SUMIF(账项调整!$I$5:$I$65536,IF(OR(MID(TRIM($A48),2,1)="：",MID(TRIM($A48),2,1)="、"),REPLACEB(TRIM($A48),1,4,""),TRIM($A48)),账项调整!$J$5:$J$65536) -> 0 | E48: =SUMIF(报表调整!$F$5:$F$65536,IF(OR(MID(TRIM($A48),2,1)="：",MID(TRIM($A48),2,1)="、"),REPLACEB(TRIM($A48),1,4,""),TRIM($A48)),报表调整!$J$5:$J$65536) -> 0 | F48: =SUMIF(报表调整!$I$5:$I$65536,IF(OR(MID(TRIM($A48),2,1)="：",MID(TRIM($A48),2,1)="、"),REPLACEB(TRIM($A48),1,4,""),TRIM($A48)),报表调整!$J$5:$J$65536) -> 0 | G48: =B48-C48-E48+D48+F48 -> 0 | I48: =SUM(G48:H48) -> 0
A49: =报表格式!G48 -> 个人资本 | B49: =未审BS!H49 -> 0 | C49: =SUMIF(账项调整!$E$5:$E$65536,IF(OR(MID(TRIM($A49),2,1)="：",MID(TRIM($A49),2,1)="、"),REPLACEB(TRIM($A49),1,4,""),TRIM($A49)),账项调整!$J$5:$J$65536) -> 0 | D49: =SUMIF(账项调整!$H$5:$H$65536,IF(OR(MID(TRIM($A49),2,1)="：",MID(TRIM($A49),2,1)="、"),REPLACEB(TRIM($A49),1,4,""),TRIM($A49)),账项调整!$J$5:$J$65536) -> 0 | E49: =SUMIF(报表调整!$E$5:$E$65536,IF(OR(MID(TRIM($A49),2,1)="：",MID(TRIM($A49),2,1)="、"),REPLACEB(TRIM($A49),1,4,""),TRIM($A49)),报表调整!$J$5:$J$65536) -> 0 | F49: =SUMIF(报表调整!$H$5:$H$65536,IF(OR(MID(TRIM($A49),2,1)="：",MID(TRIM($A49),2,1)="、"),REPLACEB(TRIM($A49),1,4,""),TRIM($A49)),报表调整!$J$5:$J$65536) -> 0 | G49: =B49-C49-E49+D49+F49 -> 0 | I49: =SUM(G49:H49) -> 0
A50: =报表格式!G49 -> 外商资本 | B50: =未审BS!H50 -> 0 | C50: =SUMIF(账项调整!$E$5:$E$65536,IF(OR(MID(TRIM($A50),2,1)="：",MID(TRIM($A50),2,1)="、"),REPLACEB(TRIM($A50),1,4,""),TRIM($A50)),账项调整!$J$5:$J$65536) -> 0 | D50: =SUMIF(账项调整!$H$5:$H$65536,IF(OR(MID(TRIM($A50),2,1)="：",MID(TRIM($A50),2,1)="、"),REPLACEB(TRIM($A50),1,4,""),TRIM($A50)),账项调整!$J$5:$J$65536) -> 0 | E50: =SUMIF(报表调整!$E$5:$E$65536,IF(OR(MID(TRIM($A50),2,1)="：",MID(TRIM($A50),2,1)="、"),REPLACEB(TRIM($A50),1,4,""),TRIM($A50)),报表调整!$J$5:$J$65536) -> 0 | F50: =SUMIF(报表调整!$H$5:$H$65536,IF(OR(MID(TRIM($A50),2,1)="：",MID(TRIM($A50),2,1)="、"),REPLACEB(TRIM($A50),1,4,""),TRIM($A50)),报表调整!$J$5:$J$65536) -> 0 | G50: =B50-C50-E50+D50+F50 -> 0 | I50: =SUM(G50:H50) -> 0
A51: =报表格式!G50 -> 资本公积 | B51: =未审BS!H51 -> 0 | C51: =SUMIF(账项调整!$E$5:$E$65536,IF(OR(MID(TRIM($A51),2,1)="：",MID(TRIM($A51),2,1)="、"),REPLACEB(TRIM($A51),1,4,""),TRIM($A51)),账项调整!$J$5:$J$65536) -> 0 | D51: =SUMIF(账项调整!$H$5:$H$65536,IF(OR(MID(TRIM($A51),2,1)="：",MID(TRIM($A51),2,1)="、"),REPLACEB(TRIM($A51),1,4,""),TRIM($A51)),账项调整!$J$5:$J$65536) -> 0 | E51: =SUMIF(报表调整!$E$5:$E$65536,IF(OR(MID(TRIM($A51),2,1)="：",MID(TRIM($A51),2,1)="、"),REPLACEB(TRIM($A51),1,4,""),TRIM($A51)),报表调整!$J$5:$J$65536) -> 0 | F51: =SUMIF(报表调整!$H$5:$H$65536,IF(OR(MID(TRIM($A51),2,1)="：",MID(TRIM($A51),2,1)="、"),REPLACEB(TRIM($A51),1,4,""),TRIM($A51)),报表调整!$J$5:$J$65536) -> 0 | G51: =B51-C51-E51+D51+F51 -> 0 | I51: =SUM(G51:H51) -> 0
A52: =报表格式!G51 -> 盈余公积 | B52: =未审BS!H52 -> 0 | C52: =SUMIF(账项调整!$E$5:$E$65536,IF(OR(MID(TRIM($A52),2,1)="：",MID(TRIM($A52),2,1)="、"),REPLACEB(TRIM($A52),1,4,""),TRIM($A52)),账项调整!$J$5:$J$65536) -> 0 | D52: =SUMIF(账项调整!$H$5:$H$65536,IF(OR(MID(TRIM($A52),2,1)="：",MID(TRIM($A52),2,1)="、"),REPLACEB(TRIM($A52),1,4,""),TRIM($A52)),账项调整!$J$5:$J$65536) -> 0 | E52: =SUMIF(报表调整!$E$5:$E$65536,IF(OR(MID(TRIM($A52),2,1)="：",MID(TRIM($A52),2,1)="、"),REPLACEB(TRIM($A52),1,4,""),TRIM($A52)),报表调整!$J$5:$J$65536) -> 0 | F52: =SUMIF(报表调整!$H$5:$H$65536,IF(OR(MID(TRIM($A52),2,1)="：",MID(TRIM($A52),2,1)="、"),REPLACEB(TRIM($A52),1,4,""),TRIM($A52)),报表调整!$J$5:$J$65536) -> 0 | G52: =B52-C52-E52+D52+F52 -> 0 | I52: =SUM(G52:H52) -> 0
A53: =报表格式!G52 -> 其中：法定公益金 | B53: =未审BS!H53 -> 0 | C53: =SUMIF(账项调整!$F$5:$F$65536,IF(OR(MID(TRIM($A53),2,1)="：",MID(TRIM($A53),2,1)="、"),REPLACEB(TRIM($A53),1,4,""),TRIM($A53)),账项调整!$J$5:$J$65536) -> 0 | D53: =SUMIF(账项调整!$I$5:$I$65536,IF(OR(MID(TRIM($A53),2,1)="：",MID(TRIM($A53),2,1)="、"),REPLACEB(TRIM($A53),1,4,""),TRIM($A53)),账项调整!$J$5:$J$65536) -> 0 | E53: =SUMIF(报表调整!$F$5:$F$65536,IF(OR(MID(TRIM($A53),2,1)="：",MID(TRIM($A53),2,1)="、"),REPLACEB(TRIM($A53),1,4,""),TRIM($A53)),报表调整!$J$5:$J$65536) -> 0 | F53: =SUMIF(报表调整!$I$5:$I$65536,IF(OR(MID(TRIM($A53),2,1)="：",MID(TRIM($A53),2,1)="、"),REPLACEB(TRIM($A53),1,4,""),TRIM($A53)),报表调整!$J$5:$J$65536) -> 0 | G53: =B53-C53-E53+D53+F53 -> 0 | I53: =SUM(G53:H53) -> 0
A54: =报表格式!G53 -> *未确认的投资损失（以“-”号填列） | B54: =未审BS!H54 -> 0 | C54: =SUMIF(账项调整!$E$5:$E$65536,REPLACEB(IF(OR(MID(TRIM($A54),2,1)="：",MID(TRIM($A54),2,1)="、"),REPLACEB(TRIM($A54),1,4,""),TRIM($A54)),1,1,""),账项调整!$J$5:$J$65536) -> 0 | D54: =SUMIF(账项调整!$H$5:$H$65536,REPLACEB(IF(OR(MID(TRIM($A54),2,1)="：",MID(TRIM($A54),2,1)="、"),REPLACEB(TRIM($A54),1,4,""),TRIM($A54)),1,1,""),账项调整!$J$5:$J$65536) -> 0 | E54: =SUMIF(报表调整!$E$5:$E$65536,REPLACEB(IF(OR(MID(TRIM($A54),2,1)="：",MID(TRIM($A54),2,1)="、"),REPLACEB(TRIM($A54),1,4,""),TRIM($A54)),1,1,""),报表调整!$J$5:$J$65536) -> 0 | F54: =SUMIF(报表调整!$H$5:$H$65536,REPLACEB(IF(OR(MID(TRIM($A54),2,1)="：",MID(TRIM($A54),2,1)="、"),REPLACEB(TRIM($A54),1,4,""),TRIM($A54)),1,1,""),报表调整!$J$5:$J$65536) -> 0 | G54: =B54-C54-E54+D54+F54 -> 0 | I54: =SUM(G54:H54) -> 0
A55: =报表格式!G54 -> 未分配利润 | B55: =未审BS!H55 -> 0 | G55: =TB损益!I73 -> 0 | I55: =SUM(G55:H55) -> 0
A56: =报表格式!G55 -> 其中：现金股利 | B56: =未审BS!H56 -> 0 | C56: =SUMIF(账项调整!$F$5:$F$65536,IF(OR(MID(TRIM($A56),2,1)="：",MID(TRIM($A56),2,1)="、"),REPLACEB(TRIM($A56),1,4,""),TRIM($A56)),账项调整!$J$5:$J$65536) -> 0 | D56: =SUMIF(账项调整!$I$5:$I$65536,IF(OR(MID(TRIM($A56),2,1)="：",MID(TRIM($A56),2,1)="、"),REPLACEB(TRIM($A56),1,4,""),TRIM($A56)),账项调整!$J$5:$J$65536) -> 0 | E56: =SUMIF(报表调整!$F$5:$F$65536,IF(OR(MID(TRIM($A56),2,1)="：",MID(TRIM($A56),2,1)="、"),REPLACEB(TRIM($A56),1,4,""),TRIM($A56)),报表调整!$J$5:$J$65536) -> 0 | F56: =SUMIF(报表调整!$I$5:$I$65536,IF(OR(MID(TRIM($A56),2,1)="：",MID(TRIM($A56),2,1)="、"),REPLACEB(TRIM($A56),1,4,""),TRIM($A56)),报表调整!$J$5:$J$65536) -> 0 | G56: =B56-C56-E56+D56+F56 -> 0 | I56: =SUM(G56:H56) -> 0
A57: =报表格式!G56 -> 外币报表折算差额 | B57: =未审BS!H57 -> 0 | C57: =SUMIF(账项调整!$E$5:$E$65536,IF(OR(MID(TRIM($A57),2,1)="：",MID(TRIM($A57),2,1)="、"),REPLACEB(TRIM($A57),1,4,""),TRIM($A57)),账项调整!$J$5:$J$65536) -> 0 | D57: =SUMIF(账项调整!$H$5:$H$65536,IF(OR(MID(TRIM($A57),2,1)="：",MID(TRIM($A57),2,1)="、"),REPLACEB(TRIM($A57),1,4,""),TRIM($A57)),账项调整!$J$5:$J$65536) -> 0 | E57: =SUMIF(报表调整!$E$5:$E$65536,IF(OR(MID(TRIM($A57),2,1)="：",MID(TRIM($A57),2,1)="、"),REPLACEB(TRIM($A57),1,4,""),TRIM($A57)),报表调整!$J$5:$J$65536) -> 0 | F57: =SUMIF(报表调整!$H$5:$H$65536,IF(OR(MID(TRIM($A57),2,1)="：",MID(TRIM($A57),2,1)="、"),REPLACEB(TRIM($A57),1,4,""),TRIM($A57)),报表调整!$J$5:$J$65536) -> 0 | G57: =B57-C57-E57+D57+F57 -> 0 | I57: =SUM(G57:H57) -> 0
A58: =报表格式!G57 -> 0 | B58: =未审BS!H58 -> 0 | C58: =SUMIF(账项调整!$E$5:$E$65536,IF(OR(MID(TRIM($A58),2,1)="：",MID(TRIM($A58),2,1)="、"),REPLACEB(TRIM($A58),1,4,""),TRIM($A58)),账项调整!$J$5:$J$65536) -> 0 | D58: =SUMIF(账项调整!$H$5:$H$65536,IF(OR(MID(TRIM($A58),2,1)="：",MID(TRIM($A58),2,1)="、"),REPLACEB(TRIM($A58),1,4,""),TRIM($A58)),账项调整!$J$5:$J$65536) -> 0 | E58: =SUMIF(报表调整!$E$5:$E$65536,IF(OR(MID(TRIM($A58),2,1)="：",MID(TRIM($A58),2,1)="、"),REPLACEB(TRIM($A58),1,4,""),TRIM($A58)),报表调整!$J$5:$J$65536) -> 0 | F58: =SUMIF(报表调整!$H$5:$H$65536,IF(OR(MID(TRIM($A58),2,1)="：",MID(TRIM($A58),2,1)="、"),REPLACEB(TRIM($A58),1,4,""),TRIM($A58)),报表调整!$J$5:$J$65536) -> 0 | G58: =B58-C58-E58+D58+F58 -> 0 | I58: =SUM(G58:H58) -> 0
A59: =报表格式!G58 -> 所有者权益小计 | B59: =SUM(B43,B51,B52,B54,B55,B57:B58) -> 0 | C59: =SUM(C43,C51,C52,C54,C55,C57:C58) -> 0 | D59: =SUM(D43,D51,D52,D54,D55,D57:D58) -> 0 | E59: =SUM(E43,E51,E52,E54,E55,E57:E58) -> 0 | F59: =SUM(F43,F51,F52,F54,F55,F57:F58) -> 0 | G59: =SUM(G43,G51,G52,G54,G55,G57:G58) -> 0 | H59: =SUM(H43,H51,H52,H54,H55,H57:H58) -> 0 | I59: =SUM(G59:H59) -> 0
A60: =报表格式!G59 -> 减：未处理资产损失 | B60: =未审BS!H60 -> 0 | C60: =SUMIF(账项调整!$E$5:$E$65536,IF(OR(MID(TRIM($A60),2,1)="：",MID(TRIM($A60),2,1)="、"),REPLACEB(TRIM($A60),1,4,""),TRIM($A60)),账项调整!$J$5:$J$65536) -> 0 | D60: =SUMIF(账项调整!$H$5:$H$65536,IF(OR(MID(TRIM($A60),2,1)="：",MID(TRIM($A60),2,1)="、"),REPLACEB(TRIM($A60),1,4,""),TRIM($A60)),账项调整!$J$5:$J$65536) -> 0 | E60: =SUMIF(报表调整!$E$5:$E$65536,IF(OR(MID(TRIM($A60),2,1)="：",MID(TRIM($A60),2,1)="、"),REPLACEB(TRIM($A60),1,4,""),TRIM($A60)),报表调整!$J$5:$J$65536) -> 0 | F60: =SUMIF(报表调整!$H$5:$H$65536,IF(OR(MID(TRIM($A60),2,1)="：",MID(TRIM($A60),2,1)="、"),REPLACEB(TRIM($A60),1,4,""),TRIM($A60)),报表调整!$J$5:$J$65536) -> 0 | G60: =B60+C60+E60-D60-F60 -> 0 | I60: =SUM(G60:H60) -> 0
A61: =报表格式!G60 -> 所有者权益合计(剔除未处理资产损失后的金额) | B61: =B59-B60 -> 0 | C61: =C59-C60 -> 0 | D61: =D59-D60 -> 0 | E61: =E59-E60 -> 0 | F61: =F59-F60 -> 0 | G61: =G59-G60 -> 0 | H61: =H59-H60 -> 0 | I61: =SUM(G61:H61) -> 0
A62: =报表格式!G73 -> 负债及所有者权益合计 | B62: =SUM(B61,B40:B41,B39) -> 0 | C62: =SUM(C61,C40:C41,C39) -> 0 | D62: =SUM(D61,D40:D41,D39) -> 0 | E62: =SUM(E61,E40:E41,E39) -> 0 | F62: =SUM(F61,F40:F41,F39) -> 0 | G62: =SUM(G61,G40:G41,G39) -> 0 | H62: =SUM(H61,H40:H41,H39) -> 0 | I62: =SUM(G62:H62) -> 0
B63: =B62-TB资产!B62 -> 0 | C63: =SUM(C7:C25,C28:C32,C34:C35,C38:C38,C40:C41,C43,C51:C52,C54:C55,C57:C58,C60:C60) -> 0 | D63: =SUM(D7:D25,D28:D32,D38,D40,D43,D51:D52,D54,D57,D60) -> 0 | E63: =SUM(E7:E25,E28:E32,E38,E40,E43,E51:E52,E54,E57,E60) -> 0 | F63: =SUM(F7:F25,F28:F32,F38,F40,F43,F51:F52,F54,F57,F60) -> 0 | I63: =I62-TB资产!I62 -> 0

Sheet TB损益
A1: 利润表及利润分配表试算平衡
A2: =CONCATENATE("客户名称：",参数!D3) -> 客户名称： | C2: =CONCATENATE("编制：",参数!D17) -> 编制： | E2: =CONCATENATE("复核：",参数!D18) -> 复核： | I2: =TB资产!I2 -> 索引：
A3: =CONCATENATE("会计期间：",TEXT(参数!D10,"yyyy.mm.dd")) -> 会计期间：2007年度 | C3: =CONCATENATE("日期：",TEXT(NOW(),"yyyy.mm.dd")) -> 日期：2023.08.14 | E3: =TB资产!E3 -> 日期： | I3: =TB资产!I3 -> 分页：
A4: =IF((ROUND(TB资产!I62,2))=(ROUND(TB负债!I62,2)),"项 目","报表未调平!") -> 项 目 | B4: 企业原报数 | C4: 账项调整 | E4: 报表调整 | G4: 调后数 | H4: 剥离调整 | I4: 审定数
C5: 借方 | D5: 贷方 | E5: 借方 | F5: 贷方
A6: =报表格式!L5 -> 一、主营业务收入 | B6: =未审PL!D6 -> 0 | C6: =SUMIF(账项调整!$E$5:$E$65536,IF(OR(MID(TRIM($A6),2,1)="：",MID(TRIM($A6),2,1)="、"),REPLACEB(TRIM($A6),1,4,""),TRIM($A6)),账项调整!$J$5:$J$65536) -> 0 | D6: =SUMIF(账项调整!$H$5:$H$65536,IF(OR(MID(TRIM($A6),2,1)="：",MID(TRIM($A6),2,1)="、"),REPLACEB(TRIM($A6),1,4,""),TRIM($A6)),账项调整!$J$5:$J$65536) -> 0 | E6: =SUMIF(报表调整!$E$5:$E$65536,IF(OR(MID(TRIM($A6),2,1)="：",MID(TRIM($A6),2,1)="、"),REPLACEB(TRIM($A6),1,4,""),TRIM($A6)),报表调整!$J$5:$J$65536) -> 0 | F6: =SUMIF(报表调整!$H$5:$H$65536,IF(OR(MID(TRIM($A6),2,1)="：",MID(TRIM($A6),2,1)="、"),REPLACEB(TRIM($A6),1,4,""),TRIM($A6)),报表调整!$J$5:$J$65536) -> 0 | G6: =B6-C6-E6+D6+F6 -> 0 | I6: =SUM(G6:H6) -> 0
A7: =报表格式!L6 -> 其中：进口产品（商品）销售收入 | B7: =未审PL!D7 -> 0 | C7: =SUMIF(账项调整!$F$5:$F$65536,IF(OR(MID(TRIM($A7),2,1)="：",MID(TRIM($A7),2,1)="、"),REPLACEB(TRIM($A7),1,4,""),TRIM($A7)),账项调整!$J$5:$J$65536) -> 0 | D7: =SUMIF(账项调整!$I$5:$I$65536,IF(OR(MID(TRIM($A7),2,1)="：",MID(TRIM($A7),2,1)="、"),REPLACEB(TRIM($A7),1,4,""),TRIM($A7)),账项调整!$J$5:$J$65536) -> 0 | E7: =SUMIF(报表调整!$F$5:$F$65536,IF(OR(MID(TRIM($A7),2,1)="：",MID(TRIM($A7),2,1)="、"),REPLACEB(TRIM($A7),1,4,""),TRIM($A7)),报表调整!$J$5:$J$65536) -> 0 | F7: =SUMIF(报表调整!$I$5:$I$65536,IF(OR(MID(TRIM($A7),2,1)="：",MID(TRIM($A7),2,1)="、"),REPLACEB(TRIM($A7),1,4,""),TRIM($A7)),报表调整!$J$5:$J$65536) -> 0 | G7: =B7-C7-E7+D7+F7 -> 0 | I7: =SUM(G7:H7) -> 0
A8: =报表格式!L7 -> 出口产品（商品）销售收入 | B8: =未审PL!D8 -> 0 | C8: =SUMIF(账项调整!$F$5:$F$65536,IF(OR(MID(TRIM($A8),2,1)="：",MID(TRIM($A8),2,1)="、"),REPLACEB(TRIM($A8),1,4,""),TRIM($A8)),账项调整!$J$5:$J$65536) -> 0 | D8: =SUMIF(账项调整!$I$5:$I$65536,IF(OR(MID(TRIM($A8),2,1)="：",MID(TRIM($A8),2,1)="、"),REPLACEB(TRIM($A8),1,4,""),TRIM($A8)),账项调整!$J$5:$J$65536) -> 0 | E8: =SUMIF(报表调整!$F$5:$F$65536,IF(OR(MID(TRIM($A8),2,1)="：",MID(TRIM($A8),2,1)="、"),REPLACEB(TRIM($A8),1,4,""),TRIM($A8)),报表调整!$J$5:$J$65536) -> 0 | F8: =SUMIF(报表调整!$I$5:$I$65536,IF(OR(MID(TRIM($A8),2,1)="：",MID(TRIM($A8),2,1)="、"),REPLACEB(TRIM($A8),1,4,""),TRIM($A8)),报表调整!$J$5:$J$65536) -> 0 | G8: =B8-C8-E8+D8+F8 -> 0 | I8: =SUM(G8:H8) -> 0
A9: =报表格式!L8 -> 减：折扣与折让 | B9: =未审PL!D9 -> 0 | C9: =SUMIF(账项调整!$E$5:$E$65536,IF(OR(MID(TRIM($A9),2,1)="：",MID(TRIM($A9),2,1)="、"),REPLACEB(TRIM($A9),1,4,""),TRIM($A9)),账项调整!$J$5:$J$65536) -> 0 | D9: =SUMIF(账项调整!$H$5:$H$65536,IF(OR(MID(TRIM($A9),2,1)="：",MID(TRIM($A9),2,1)="、"),REPLACEB(TRIM($A9),1,4,""),TRIM($A9)),账项调整!$J$5:$J$65536) -> 0 | E9: =SUMIF(报表调整!$E$5:$E$65536,IF(OR(MID(TRIM($A9),2,1)="：",MID(TRIM($A9),2,1)="、"),REPLACEB(TRIM($A9),1,4,""),TRIM($A9)),报表调整!$J$5:$J$65536) -> 0 | F9: =SUMIF(报表调整!$H$5:$H$65536,IF(OR(MID(TRIM($A9),2,1)="：",MID(TRIM($A9),2,1)="、"),REPLACEB(TRIM($A9),1,4,""),TRIM($A9)),报表调整!$J$5:$J$65536) -> 0 | G9: =B9+C9+E9-D9-F9 -> 0 | I9: =SUM(G9:H9) -> 0
A10: =报表格式!L9 -> 二、主营业务收入净额 | B10: =B6-B9 -> 0 | C10: =C6-C9 -> 0 | D10: =D6-D9 -> 0 | E10: =E6-E9 -> 0 | F10: =F6-F9 -> 0 | G10: =G6-G9 -> 0 | H10: =H6-H9 -> 0 | I10: =SUM(G10:H10) -> 0
A11: =报表格式!L10 -> 减：（一）主营业务成本 | B11: =未审PL!D11 -> 0 | C11: =SUMIF(账项调整!$E$5:$E$65536,REPLACEB(IF(OR(MID(TRIM($A11),2,1)="：",MID(TRIM($A11),2,1)="、"),REPLACEB(TRIM($A11),1,4,""),TRIM($A11)),1,6,""),账项调整!$J$5:$J$65536) -> 0 | D11: =SUMIF(账项调整!$H$5:$H$65536,REPLACEB(IF(OR(MID(TRIM($A11),2,1)="：",MID(TRIM($A11),2,1)="、"),REPLACEB(TRIM($A11),1,4,""),TRIM($A11)),1,6,""),账项调整!$J$5:$J$65536) -> 0 | E11: =SUMIF(报表调整!$E$5:$E$65536,REPLACEB(IF(OR(MID(TRIM($A11),2,1)="：",MID(TRIM($A11),2,1)="、"),REPLACEB(TRIM($A11),1,4,""),TRIM($A11)),1,6,""),报表调整!$J$5:$J$65536) -> 0 | F11: =SUMIF(报表调整!$H$5:$H$65536,REPLACEB(IF(OR(MID(TRIM($A11),2,1)="：",MID(TRIM($A11),2,1)="、"),REPLACEB(TRIM($A11),1,4,""),TRIM($A11)),1,6,""),报表调整!$J$5:$J$65536) -> 0 | G11: =B11+C11+E11-D11-F11 -> 0 | I11: =SUM(G11:H11) -> 0
A12: =报表格式!L11 -> 其中：出口产品（商品）销售成本 | B12: =未审PL!D12 -> 0 | C12: =SUMIF(账项调整!$F$5:$F$65536,IF(OR(MID(TRIM($A12),2,1)="：",MID(TRIM($A12),2,1)="、"),REPLACEB(TRIM($A12),1,4,""),TRIM($A12)),账项调整!$J$5:$J$65536) -> 0 | D12: =SUMIF(账项调整!$I$5:$I$65536,IF(OR(MID(TRIM($A12),2,1)="：",MID(TRIM($A12),2,1)="、"),REPLACEB(TRIM($A12),1,4,""),TRIM($A12)),账项调整!$J$5:$J$65536) -> 0 | E12: =SUMIF(报表调整!$F$5:$F$65536,IF(OR(MID(TRIM($A12),2,1)="：",MID(TRIM($A12),2,1)="、"),REPLACEB(TRIM($A12),1,4,""),TRIM($A12)),报表调整!$J$5:$J$65536) -> 0 | F12: =SUMIF(报表调整!$I$5:$I$65536,IF(OR(MID(TRIM($A12),2,1)="：",MID(TRIM($A12),2,1)="、"),REPLACEB(TRIM($A12),1,4,""),TRIM($A12)),报表调整!$J$5:$J$65536) -> 0 | G12: =B12+C12+E12-D12-F12 -> 0 | I12: =SUM(G12:H12) -> 0
A13: =报表格式!L12 -> （二）主营业务税金及附加 | B13: =未审PL!D13 -> 0 | C13: =SUMIF(账项调整!$E$5:$E$65536,REPLACEB(IF(OR(MID(TRIM($A13),2,1)="：",MID(TRIM($A13),2,1)="、"),REPLACEB(TRIM($A13),1,4,""),TRIM($A13)),1,6,""),账项调整!$J$5:$J$65536) -> 0 | D13: =SUMIF(账项调整!$H$5:$H$65536,REPLACEB(IF(OR(MID(TRIM($A13),2,1)="：",MID(TRIM($A13),2,1)="、"),REPLACEB(TRIM($A13),1,4,""),TRIM($A13)),1,6,""),账项调整!$J$5:$J$65536) -> 0 | E13: =SUMIF(报表调整!$E$5:$E$65536,REPLACEB(IF(OR(MID(TRIM($A13),2,1)="：",MID(TRIM($A13),2,1)="、"),REPLACEB(TRIM($A13),1,4,""),TRIM($A13)),1,6,""),报表调整!$J$5:$J$65536) -> 0 | F13: =SUMIF(报表调整!$H$5:$H$65536,REPLACEB(IF(OR(MID(TRIM($A13),2,1)="：",MID(TRIM($A13),2,1)="、"),REPLACEB(TRIM($A13),1,4,""),TRIM($A13)),1,6,""),报表调整!$J$5:$J$65536) -> 0 | G13: =B13+C13+E13-D13-F13 -> 0 | I13: =SUM(G13:H13) -> 0
A14: =报表格式!L13 -> （三）经营费用 | B14: =未审PL!D14 -> 0 | C14: =SUMIF(账项调整!$E$5:$E$65536,REPLACEB(IF(OR(MID(TRIM($A14),2,1)="：",MID(TRIM($A14),2,1)="、"),REPLACEB(TRIM($A14),1,4,""),TRIM($A14)),1,6,""),账项调整!$J$5:$J$65536) -> 0 | D14: =SUMIF(账项调整!$H$5:$H$65536,REPLACEB(IF(OR(MID(TRIM($A14),2,1)="：",MID(TRIM($A14),2,1)="、"),REPLACEB(TRIM($A14),1,4,""),TRIM($A14)),1,6,""),账项调整!$J$5:$J$65536) -> 0 | E14: =SUMIF(报表调整!$E$5:$E$65536,REPLACEB(IF(OR(MID(TRIM($A14),2,1)="：",MID(TRIM($A14),2,1)="、"),REPLACEB(TRIM($A14),1,4,""),TRIM($A14)),1,6,""),报表调整!$J$5:$J$65536) -> 0 | F14: =SUMIF(报表调整!$H$5:$H$65536,REPLACEB(IF(OR(MID(TRIM($A14),2,1)="：",MID(TRIM($A14),2,1)="、"),REPLACEB(TRIM($A14),1,4,""),TRIM($A14)),1,6,""),报表调整!$J$5:$J$65536) -> 0 | G14: =B14+C14+E14-D14-F14 -> 0 | I14: =SUM(G14:H14) -> 0
A15: =报表格式!L14 -> （四）其他 | B15: =未审PL!D15 -> 0 | C15: =SUMIF(账项调整!$E$5:$E$65536,REPLACEB(IF(OR(MID(TRIM($A15),2,1)="：",MID(TRIM($A15),2,1)="、"),REPLACEB(TRIM($A15),1,4,""),TRIM($A15)),1,6,""),账项调整!$J$5:$J$65536) -> 0 | D15: =SUMIF(账项调整!$H$5:$H$65536,REPLACEB(IF(OR(MID(TRIM($A15),2,1)="：",MID(TRIM($A15),2,1)="、"),REPLACEB(TRIM($A15),1,4,""),TRIM($A15)),1,6,""),账项调整!$J$5:$J$65536) -> 0 | E15: =SUMIF(报表调整!$E$5:$E$65536,REPLACEB(IF(OR(MID(TRIM($A15),2,1)="：",MID(TRIM($A15),2,1)="、"),REPLACEB(TRIM($A15),1,4,""),TRIM($A15)),1,6,""),报表调整!$J$5:$J$65536) -> 0 | F15: =SUMIF(报表调整!$H$5:$H$65536,REPLACEB(IF(OR(MID(TRIM($A15),2,1)="：",MID(TRIM($A15),2,1)="、"),REPLACEB(TRIM($A15),1,4,""),TRIM($A15)),1,6,""),报表调整!$J$5:$J$65536) -> 0 | G15: =B15+C15+E15-D15-F15 -> 0 | I15: =SUM(G15:H15) -> 0
A16: =报表格式!L15 -> 加：（一）递延收益 | B16: =未审PL!D16 -> 0 | C16: =SUMIF(账项调整!$E$5:$E$65536,REPLACEB(IF(OR(MID(TRIM($A16),2,1)="：",MID(TRIM($A16),2,1)="、"),REPLACEB(TRIM($A16),1,4,""),TRIM($A16)),1,6,""),账项调整!$J$5:$J$65536) -> 0 | D16: =SUMIF(账项调整!$H$5:$H$65536,REPLACEB(IF(OR(MID(TRIM($A16),2,1)="：",MID(TRIM($A16),2,1)="、"),REPLACEB(TRIM($A16),1,4,""),TRIM($A16)),1,6,""),账项调整!$J$5:$J$65536) -> 0 | E16: =SUMIF(报表调整!$E$5:$E$65536,REPLACEB(IF(OR(MID(TRIM($A16),2,1)="：",MID(TRIM($A16),2,1)="、"),REPLACEB(TRIM($A16),1,4,""),TRIM($A16)),1,6,""),报表调整!$J$5:$J$65536) -> 0 | F16: =SUMIF(报表调整!$H$5:$H$65536,REPLACEB(IF(OR(MID(TRIM($A16),2,1)="：",MID(TRIM($A16),2,1)="、"),REPLACEB(TRIM($A16),1,4,""),TRIM($A16)),1,6,""),报表调整!$J$5:$J$65536) -> 0 | G16: =B16-C16-E16+D16+F16 -> 0 | I16: =SUM(G16:H16) -> 0
A17: =报表格式!L16 -> （二）代购代销收入 | B17: =未审PL!D17 -> 0 | C17: =SUMIF(账项调整!$E$5:$E$65536,REPLACEB(IF(OR(MID(TRIM($A17),2,1)="：",MID(TRIM($A17),2,1)="、"),REPLACEB(TRIM($A17),1,4,""),TRIM($A17)),1,6,""),账项调整!$J$5:$J$65536) -> 0 | D17: =SUMIF(账项调整!$H$5:$H$65536,REPLACEB(IF(OR(MID(TRIM($A17),2,1)="：",MID(TRIM($A17),2,1)="、"),REPLACEB(TRIM($A17),1,4,""),TRIM($A17)),1,6,""),账项调整!$J$5:$J$65536) -> 0 | E17: =SUMIF(报表调整!$E$5:$E$65536,REPLACEB(IF(OR(MID(TRIM($A17),2,1)="：",MID(TRIM($A17),2,1)="、"),REPLACEB(TRIM($A17),1,4,""),TRIM($A17)),1,6,""),报表调整!$J$5:$J$65536) -> 0 | F17: =SUMIF(报表调整!$H$5:$H$65536,REPLACEB(IF(OR(MID(TRIM($A17),2,1)="：",MID(TRIM($A17),2,1)="、"),REPLACEB(TRIM($A17),1,4,""),TRIM($A17)),1,6,""),报表调整!$J$5:$J$65536) -> 0 | G17: =B17-C17-E17+D17+F17 -> 0 | I17: =SUM(G17:H17) -> 0
A18: =报表格式!L17 -> （三）其他 | B18: =未审PL!D18 -> 0 | C18: =SUMIF(账项调整!$E$5:$E$65536,REPLACEB(IF(OR(MID(TRIM($A18),2,1)="：",MID(TRIM($A18),2,1)="、"),REPLACEB(TRIM($A18),1,4,""),TRIM($A18)),1,6,""),账项调整!$J$5:$J$65536) -> 0 | D18: =SUMIF(账项调整!$H$5:$H$65536,REPLACEB(IF(OR(MID(TRIM($A18),2,1)="：",MID(TRIM($A18),2,1)="、"),REPLACEB(TRIM($A18),1,4,""),TRIM($A18)),1,6,""),账项调整!$J$5:$J$65536) -> 0 | E18: =SUMIF(报表调整!$E$5:$E$65536,REPLACEB(IF(OR(MID(TRIM($A18),2,1)="：",MID(TRIM($A18),2,1)="、"),REPLACEB(TRIM($A18),1,4,""),TRIM($A18)),1,6,""),报表调整!$J$5:$J$65536) -> 0 | F18: =SUMIF(报表调整!$H$5:$H$65536,REPLACEB(IF(OR(MID(TRIM($A18),2,1)="：",MID(TRIM($A18),2,1)="、"),REPLACEB(TRIM($A18),1,4,""),TRIM($A18)),1,6,""),报表调整!$J$5:$J$65536) -> 0 | G18: =B18-C18-E18+D18+F18 -> 0 | I18: =SUM(G18:H18) -> 0
A19: =报表格式!L18 -> 三、主营业务利润 | B19: =B10-B11-B13-B14-B15+B16+B17+B18 -> 0 | C19: =C10-C11-C13-C14-C15+C16+C17+C18 -> 0 | D19: =D10-D11-D13-D14-D15+D16+D17+D18 -> 0 | E19: =E10-E11-E13-E14-E15+E16+E17+E18 -> 0 | F19: =F10-F11-F13-F14-F15+F16+F17+F18 -> 0 | G19: =G10-G11-G13-G14-G15+G16+G17+G18 -> 0 | H19: =H10-H11-H13-H14-H15+H16+H17+H18 -> 0 | I19: =SUM(G19:H19) -> 0
A20: =报表格式!L19 -> 加：其他业务利润 | B20: =未审PL!D20 -> 0 | C20: =SUMIF(账项调整!$E$5:$E$65536,IF(OR(MID(TRIM($A20),2,1)="：",MID(TRIM($A20),2,1)="、"),REPLACEB(TRIM($A20),1,4,""),TRIM($A20)),账项调整!$J$5:$J$65536) -> 0 | D20: =SUMIF(账项调整!$H$5:$H$65536,IF(OR(MID(TRIM($A20),2,1)="：",MID(TRIM($A20),2,1)="、"),REPLACEB(TRIM($A20),1,4,""),TRIM($A20)),账项调整!$J$5:$J$65536) -> 0 | E20: =SUMIF(报表调整!$E$5:$E$65536,IF(OR(MID(TRIM($A20),2,1)="：",MID(TRIM($A20),2,1)="、"),REPLACEB(TRIM($A20),1,4,""),TRIM($A20)),报表调整!$J$5:$J$65536) -> 0 | F20: =SUMIF(报表调整!$H$5:$H$65536,IF(OR(MID(TRIM($A20),2,1)="：",MID(TRIM($A20),2,1)="、"),REPLACEB(TRIM($A20),1,4,""),TRIM($A20)),报表调整!$J$5:$J$65536) -> 0 | G20: =B20-C20-E20+D20+F20 -> 0 | I20: =SUM(G20:H20) -> 0
A21: =报表格式!L20 -> 减：（一）营业费用 | B21: =未审PL!D21 -> 0 | C21: =SUMIF(账项调整!$E$5:$E$65536,REPLACEB(IF(OR(MID(TRIM($A21),2,1)="：",MID(TRIM($A21),2,1)="、"),REPLACEB(TRIM($A21),1,4,""),TRIM($A21)),1,6,""),账项调整!$J$5:$J$65536) -> 0 | D21: =SUMIF(账项调整!$H$5:$H$65536,REPLACEB(IF(OR(MID(TRIM($A21),2,1)="：",MID(TRIM($A21),2,1)="、"),REPLACEB(TRIM($A21),1,4,""),TRIM($A21)),1,6,""),账项调整!$J$5:$J$65536) -> 0 | E21: =SUMIF(报表调整!$E$5:$E$65536,REPLACEB(IF(OR(MID(TRIM($A21),2,1)="：",MID(TRIM($A21),2,1)="、"),REPLACEB(TRIM($A21),1,4,""),TRIM($A21)),1,6,""),报表调整!$J$5:$J$65536) -> 0 | F21: =SUMIF(报表调整!$H$5:$H$65536,REPLACEB(IF(OR(MID(TRIM($A21),2,1)="：",MID(TRIM($A21),2,1)="、"),REPLACEB(TRIM($A21),1,4,""),TRIM($A21)),1,6,""),报表调整!$J$5:$J$65536) -> 0 | G21: =B21+C21+E21-D21-F21 -> 0 | I21: =SUM(G21:H21) -> 0
A22: =报表格式!L21 -> （二）管理费用 | B22: =未审PL!D22 -> 0 | C22: =SUMIF(账项调整!$E$5:$E$65536,REPLACEB(IF(OR(MID(TRIM($A22),2,1)="：",MID(TRIM($A22),2,1)="、"),REPLACEB(TRIM($A22),1,4,""),TRIM($A22)),1,6,""),账项调整!$J$5:$J$65536) -> 0 | D22: =SUMIF(账项调整!$H$5:$H$65536,REPLACEB(IF(OR(MID(TRIM($A22),2,1)="：",MID(TRIM($A22),2,1)="、"),REPLACEB(TRIM($A22),1,4,""),TRIM($A22)),1,6,""),账项调整!$J$5:$J$65536) -> 0 | E22: =SUMIF(报表调整!$E$5:$E$65536,REPLACEB(IF(OR(MID(TRIM($A22),2,1)="：",MID(TRIM($A22),2,1)="、"),REPLACEB(TRIM($A22),1,4,""),TRIM($A22)),1,6,""),报表调整!$J$5:$J$65536) -> 0 | F22: =SUMIF(报表调整!$H$5:$H$65536,REPLACEB(IF(OR(MID(TRIM($A22),2,1)="：",MID(TRIM($A22),2,1)="、"),REPLACEB(TRIM($A22),1,4,""),TRIM($A22)),1,6,""),报表调整!$J$5:$J$65536) -> 0 | G22: =B22+C22+E22-D22-F22 -> 0 | I22: =SUM(G22:H22) -> 0
A23: =报表格式!L22 -> 其中：业务招待费 | B23: =未审PL!D23 -> 0 | C23: =SUMIF(账项调整!$F$5:$F$65536,IF(OR(MID(TRIM($A23),2,1)="：",MID(TRIM($A23),2,1)="、"),REPLACEB(TRIM($A23),1,4,""),TRIM($A23)),账项调整!$J$5:$J$65536) -> 0 | D23: =SUMIF(账项调整!$I$5:$I$65536,IF(OR(MID(TRIM($A23),2,1)="：",MID(TRIM($A23),2,1)="、"),REPLACEB(TRIM($A23),1,4,""),TRIM($A23)),账项调整!$J$5:$J$65536) -> 0 | E23: =SUMIF(报表调整!$F$5:$F$65536,IF(OR(MID(TRIM($A23),2,1)="：",MID(TRIM($A23),2,1)="、"),REPLACEB(TRIM($A23),1,4,""),TRIM($A23)),报表调整!$J$5:$J$65536) -> 0 | F23: =SUMIF(报表调整!$I$5:$I$65536,IF(OR(MID(TRIM($A23),2,1)="：",MID(TRIM($A23),2,1)="、"),REPLACEB(TRIM($A23),1,4,""),TRIM($A23)),报表调整!$J$5:$J$65536) -> 0 | G23: =B23+C23+E23-D23-F23 -> 0 | I23: =SUM(G23:H23) -> 0
A24: =报表格式!L23 -> 研究与开发费 | B24: =未审PL!D24 -> 0 | C24: =SUMIF(账项调整!$F$5:$F$65536,IF(OR(MID(TRIM($A24),2,1)="：",MID(TRIM($A24),2,1)="、"),REPLACEB(TRIM($A24),1,4,""),TRIM($A24)),账项调整!$J$5:$J$65536) -> 0 | D24: =SUMIF(账项调整!$I$5:$I$65536,IF(OR(MID(TRIM($A24),2,1)="：",MID(TRIM($A24),2,1)="、"),REPLACEB(TRIM($A24),1,4,""),TRIM($A24)),账项调整!$J$5:$J$65536) -> 0 | E24: =SUMIF(报表调整!$F$5:$F$65536,IF(OR(MID(TRIM($A24),2,1)="：",MID(TRIM($A24),2,1)="、"),REPLACEB(TRIM($A24),1,4,""),TRIM($A24)),报表调整!$J$5:$J$65536) -> 0 | F24: =SUMIF(报表调整!$I$5:$I$65536,IF(OR(MID(TRIM($A24),2,1)="：",MID(TRIM($A24),2,1)="、"),REPLACEB(TRIM($A24),1,4,""),TRIM($A24)),报表调整!$J$5:$J$65536) -> 0 | G24: =B24+C24+E24-D24-F24 -> 0 | I24: =SUM(G24:H24) -> 0
A25: =报表格式!L24 -> （三）财务费用 | B25: =未审PL!D25 -> 0 | C25: =SUMIF(账项调整!$E$5:$E$65536,REPLACEB(IF(OR(MID(TRIM($A25),2,1)="：",MID(TRIM($A25),2,1)="、"),REPLACEB(TRIM($A25),1,4,""),TRIM($A25)),1,6,""),账项调整!$J$5:$J$65536) -> 0 | D25: =SUMIF(账项调整!$H$5:$H$65536,REPLACEB(IF(OR(MID(TRIM($A25),2,1)="：",MID(TRIM($A25),2,1)="、"),REPLACEB(TRIM($A25),1,4,""),TRIM($A25)),1,6,""),账项调整!$J$5:$J$65536) -> 0 | E25: =SUMIF(报表调整!$E$5:$E$65536,REPLACEB(IF(OR(MID(TRIM($A25),2,1)="：",MID(TRIM($A25),2,1)="、"),REPLACEB(TRIM($A25),1,4,""),TRIM($A25)),1,6,""),报表调整!$J$5:$J$65536) -> 0 | F25: =SUMIF(报表调整!$H$5:$H$65536,REPLACEB(IF(OR(MID(TRIM($A25),2,1)="：",MID(TRIM($A25),2,1)="、"),REPLACEB(TRIM($A25),1,4,""),TRIM($A25)),1,6,""),报表调整!$J$5:$J$65536) -> 0 | G25: =B25+C25+E25-D25-F25 -> 0 | I25: =SUM(G25:H25) -> 0
A26: =报表格式!L25 -> 其中：利息支出 | B26: =未审PL!D26 -> 0 | C26: =SUMIF(账项调整!$F$5:$F$65536,IF(OR(MID(TRIM($A26),2,1)="：",MID(TRIM($A26),2,1)="、"),REPLACEB(TRIM($A26),1,4,""),TRIM($A26)),账项调整!$J$5:$J$65536) -> 0 | D26: =SUMIF(账项调整!$I$5:$I$65536,IF(OR(MID(TRIM($A26),2,1)="：",MID(TRIM($A26),2,1)="、"),REPLACEB(TRIM($A26),1,4,""),TRIM($A26)),账项调整!$J$5:$J$65536) -> 0 | E26: =SUMIF(报表调整!$F$5:$F$65536,IF(OR(MID(TRIM($A26),2,1)="：",MID(TRIM($A26),2,1)="、"),REPLACEB(TRIM($A26),1,4,""),TRIM($A26)),报表调整!$J$5:$J$65536) -> 0 | F26: =SUMIF(报表调整!$I$5:$I$65536,IF(OR(MID(TRIM($A26),2,1)="：",MID(TRIM($A26),2,1)="、"),REPLACEB(TRIM($A26),1,4,""),TRIM($A26)),报表调整!$J$5:$J$65536) -> 0 | G26: =B26+C26+E26-D26-F26 -> 0 | I26: =SUM(G26:H26) -> 0
A27: =报表格式!L26 -> 利息收入 | B27: =未审PL!D27 -> 0 | C27: =SUMIF(账项调整!$F$5:$F$65536,IF(OR(MID(TRIM($A27),2,1)="：",MID(TRIM($A27),2,1)="、"),REPLACEB(TRIM($A27),1,4,""),TRIM($A27)),账项调整!$J$5:$J$65536) -> 0 | D27: =SUMIF(账项调整!$I$5:$I$65536,IF(OR(MID(TRIM($A27),2,1)="：",MID(TRIM($A27),2,1)="、"),REPLACEB(TRIM($A27),1,4,""),TRIM($A27)),账项调整!$J$5:$J$65536) -> 0 | E27: =SUMIF(报表调整!$F$5:$F$65536,IF(OR(MID(TRIM($A27),2,1)="：",MID(TRIM($A27),2,1)="、"),REPLACEB(TRIM($A27),1,4,""),TRIM($A27)),报表调整!$J$5:$J$65536) -> 0 | F27: =SUMIF(报表调整!$I$5:$I$65536,IF(OR(MID(TRIM($A27),2,1)="：",MID(TRIM($A27),2,1)="、"),REPLACEB(TRIM($A27),1,4,""),TRIM($A27)),报表调整!$J$5:$J$65536) -> 0 | G27: =B27+C27+E27-D27-F27 -> 0 | I27: =SUM(G27:H27) -> 0
A28: =报表格式!L27 -> 汇兑净损失 | B28: =未审PL!D28 -> 0 | C28: =SUMIF(账项调整!$F$5:$F$65536,IF(OR(MID(TRIM($A28),2,1)="：",MID(TRIM($A28),2,1)="、"),REPLACEB(TRIM($A28),1,4,""),TRIM($A28)),账项调整!$J$5:$J$65536) -> 0 | D28: =SUMIF(账项调整!$I$5:$I$65536,IF(OR(MID(TRIM($A28),2,1)="：",MID(TRIM($A28),2,1)="、"),REPLACEB(TRIM($A28),1,4,""),TRIM($A28)),账项调整!$J$5:$J$65536) -> 0 | E28: =SUMIF(报表调整!$F$5:$F$65536,IF(OR(MID(TRIM($A28),2,1)="：",MID(TRIM($A28),2,1)="、"),REPLACEB(TRIM($A28),1,4,""),TRIM($A28)),报表调整!$J$5:$J$65536) -> 0 | F28: =SUMIF(报表调整!$I$5:$I$65536,IF(OR(MID(TRIM($A28),2,1)="：",MID(TRIM($A28),2,1)="、"),REPLACEB(TRIM($A28),1,4,""),TRIM($A28)),报表调整!$J$5:$J$65536) -> 0 | G28: =B28+C28+E28-D28-F28 -> 0 | I28: =SUM(G28:H28) -> 0
A29: =报表格式!L28 -> （四）其他 | B29: =未审PL!D29 -> 0 | C29: =SUMIF(账项调整!$E$5:$E$65536,REPLACEB(IF(OR(MID(TRIM($A29),2,1)="：",MID(TRIM($A29),2,1)="、"),REPLACEB(TRIM($A29),1,4,""),TRIM($A29)),1,6,""),账项调整!$J$5:$J$65536) -> 0 | D29: =SUMIF(账项调整!$H$5:$H$65536,REPLACEB(IF(OR(MID(TRIM($A29),2,1)="：",MID(TRIM($A29),2,1)="、"),REPLACEB(TRIM($A29),1,4,""),TRIM($A29)),1,6,""),账项调整!$J$5:$J$65536) -> 0 | E29: =SUMIF(报表调整!$E$5:$E$65536,REPLACEB(IF(OR(MID(TRIM($A29),2,1)="：",MID(TRIM($A29),2,1)="、"),REPLACEB(TRIM($A29),1,4,""),TRIM($A29)),1,6,""),报表调整!$J$5:$J$65536) -> 0 | F29: =SUMIF(报表调整!$H$5:$H$65536,REPLACEB(IF(OR(MID(TRIM($A29),2,1)="：",MID(TRIM($A29),2,1)="、"),REPLACEB(TRIM($A29),1,4,""),TRIM($A29)),1,6,""),报表调整!$J$5:$J$65536) -> 0 | G29: =B29+C29+E29-D29-F29 -> 0 | I29: =SUM(G29:H29) -> 0
A30: =报表格式!L29 -> 四、营业利润 | B30: =B19+B20-B21-B22-B25-B29 -> 0 | C30: =C19+C20-C21-C22-C25-C29 -> 0 | D30: =D19+D20-D21-D22-D25-D29 -> 0 | E30: =E19+E20-E21-E22-E25-E29 -> 0 | F30: =F19+F20-F21-F22-F25-F29 -> 0 | G30: =G19+G20-G21-G22-G25-G29 -> 0 | H30: =H19+H20-H21-H22-H25-H29 -> 0 | I30: =SUM(G30:H30) -> 0
A31: =报表格式!L30 -> 加：（一）投资收益 | B31: =未审PL!D31 -> 0 | C31: =SUMIF(账项调整!$E$5:$E$65536,REPLACEB(IF(OR(MID(TRIM($A31),2,1)="：",MID(TRIM($A31),2,1)="、"),REPLACEB(TRIM($A31),1,4,""),TRIM($A31)),1,6,""),账项调整!$J$5:$J$65536) -> 0 | D31: =SUMIF(账项调整!$H$5:$H$65536,REPLACEB(IF(OR(MID(TRIM($A31),2,1)="：",MID(TRIM($A31),2,1)="、"),REPLACEB(TRIM($A31),1,4,""),TRIM($A31)),1,6,""),账项调整!$J$5:$J$65536) -> 0 | E31: =SUMIF(报表调整!$E$5:$E$65536,REPLACEB(IF(OR(MID(TRIM($A31),2,1)="：",MID(TRIM($A31),2,1)="、"),REPLACEB(TRIM($A31),1,4,""),TRIM($A31)),1,6,""),报表调整!$J$5:$J$65536) -> 0 | F31: =SUMIF(报表调整!$H$5:$H$65536,REPLACEB(IF(OR(MID(TRIM($A31),2,1)="：",MID(TRIM($A31),2,1)="、"),REPLACEB(TRIM($A31),1,4,""),TRIM($A31)),1,6,""),报表调整!$J$5:$J$65536) -> 0 | G31: =B31-C31-E31+D31+F31 -> 0 | I31: =SUM(G31:H31) -> 0
A32: =报表格式!L31 -> （二）期货收益 | B32: =未审PL!D32 -> 0 | C32: =SUMIF(账项调整!$E$5:$E$65536,REPLACEB(IF(OR(MID(TRIM($A32),2,1)="：",MID(TRIM($A32),2,1)="、"),REPLACEB(TRIM($A32),1,4,""),TRIM($A32)),1,6,""),账项调整!$J$5:$J$65536) -> 0 | D32: =SUMIF(账项调整!$H$5:$H$65536,REPLACEB(IF(OR(MID(TRIM($A32),2,1)="：",MID(TRIM($A32),2,1)="、"),REPLACEB(TRIM($A32),1,4,""),TRIM($A32)),1,6,""),账项调整!$J$5:$J$65536) -> 0 | E32: =SUMIF(报表调整!$E$5:$E$65536,REPLACEB(IF(OR(MID(TRIM($A32),2,1)="：",MID(TRIM($A32),2,1)="、"),REPLACEB(TRIM($A32),1,4,""),TRIM($A32)),1,6,""),报表调整!$J$5:$J$65536) -> 0 | F32: =SUMIF(报表调整!$H$5:$H$65536,REPLACEB(IF(OR(MID(TRIM($A32),2,1)="：",MID(TRIM($A32),2,1)="、"),REPLACEB(TRIM($A32),1,4,""),TRIM($A32)),1,6,""),报表调整!$J$5:$J$65536) -> 0 | G32: =B32-C32-E32+D32+F32 -> 0 | I32: =SUM(G32:H32) -> 0
A33: =报表格式!L32 -> （三）补贴收入 | B33: =未审PL!D33 -> 0 | C33: =SUMIF(账项调整!$E$5:$E$65536,REPLACEB(IF(OR(MID(TRIM($A33),2,1)="：",MID(TRIM($A33),2,1)="、"),REPLACEB(TRIM($A33),1,4,""),TRIM($A33)),1,6,""),账项调整!$J$5:$J$65536) -> 0 | D33: =SUMIF(账项调整!$H$5:$H$65536,REPLACEB(IF(OR(MID(TRIM($A33),2,1)="：",MID(TRIM($A33),2,1)="、"),REPLACEB(TRIM($A33),1,4,""),TRIM($A33)),1,6,""),账项调整!$J$5:$J$65536) -> 0 | E33: =SUMIF(报表调整!$E$5:$E$65536,REPLACEB(IF(OR(MID(TRIM($A33),2,1)="：",MID(TRIM($A33),2,1)="、"),REPLACEB(TRIM($A33),1,4,""),TRIM($A33)),1,6,""),报表调整!$J$5:$J$65536) -> 0 | F33: =SUMIF(报表调整!$H$5:$H$65536,REPLACEB(IF(OR(MID(TRIM($A33),2,1)="：",MID(TRIM($A33),2,1)="、"),REPLACEB(TRIM($A33),1,4,""),TRIM($A33)),1,6,""),报表调整!$J$5:$J$65536) -> 0 | G33: =B33-C33-E33+D33+F33 -> 0 | I33: =SUM(G33:H33) -> 0
A34: =报表格式!L33 -> 其中：补贴前亏损的企业补贴收入 | B34: =未审PL!D34 -> 0 | C34: =SUMIF(账项调整!$F$5:$F$65536,IF(OR(MID(TRIM($A34),2,1)="：",MID(TRIM($A34),2,1)="、"),REPLACEB(TRIM($A34),1,4,""),TRIM($A34)),账项调整!$J$5:$J$65536) -> 0 | D34: =SUMIF(账项调整!$I$5:$I$65536,IF(OR(MID(TRIM($A34),2,1)="：",MID(TRIM($A34),2,1)="、"),REPLACEB(TRIM($A34),1,4,""),TRIM($A34)),账项调整!$J$5:$J$65536) -> 0 | E34: =SUMIF(报表调整!$F$5:$F$65536,IF(OR(MID(TRIM($A34),2,1)="：",MID(TRIM($A34),2,1)="、"),REPLACEB(TRIM($A34),1,4,""),TRIM($A34)),报表调整!$J$5:$J$65536) -> 0 | F34: =SUMIF(报表调整!$I$5:$I$65536,IF(OR(MID(TRIM($A34),2,1)="：",MID(TRIM($A34),2,1)="、"),REPLACEB(TRIM($A34),1,4,""),TRIM($A34)),报表调整!$J$5:$J$65536) -> 0 | G34: =B34-C34-E34+D34+F34 -> 0 | I34: =SUM(G34:H34) -> 0
A35: =报表格式!L34 -> （四）营业外收入 | B35: =未审PL!D35 -> 0 | C35: =SUMIF(账项调整!$E$5:$E$65536,REPLACEB(IF(OR(MID(TRIM($A35),2,1)="：",MID(TRIM($A35),2,1)="、"),REPLACEB(TRIM($A35),1,4,""),TRIM($A35)),1,6,""),账项调整!$J$5:$J$65536) -> 0 | D35: =SUMIF(账项调整!$H$5:$H$65536,REPLACEB(IF(OR(MID(TRIM($A35),2,1)="：",MID(TRIM($A35),2,1)="、"),REPLACEB(TRIM($A35),1,4,""),TRIM($A35)),1,6,""),账项调整!$J$5:$J$65536) -> 0 | E35: =SUMIF(报表调整!$E$5:$E$65536,REPLACEB(IF(OR(MID(TRIM($A35),2,1)="：",MID(TRIM($A35),2,1)="、"),REPLACEB(TRIM($A35),1,4,""),TRIM($A35)),1,6,""),报表调整!$J$5:$J$65536) -> 0 | F35: =SUMIF(报表调整!$H$5:$H$65536,REPLACEB(IF(OR(MID(TRIM($A35),2,1)="：",MID(TRIM($A35),2,1)="、"),REPLACEB(TRIM($A35),1,4,""),TRIM($A35)),1,6,""),报表调整!$J$5:$J$65536) -> 0 | G35: =B35-C35-E35+D35+F35 -> 0 | I35: =SUM(G35:H35) -> 0
A36: =报表格式!L35 -> 其中：处置固定资产净收益 | B36: =未审PL!D36 -> 0 | C36: =SUMIF(账项调整!$F$5:$F$65536,IF(OR(MID(TRIM($A36),2,1)="：",MID(TRIM($A36),2,1)="、"),REPLACEB(TRIM($A36),1,4,""),TRIM($A36)),账项调整!$J$5:$J$65536) -> 0 | D36: =SUMIF(账项调整!$I$5:$I$65536,IF(OR(MID(TRIM($A36),2,1)="：",MID(TRIM($A36),2,1)="、"),REPLACEB(TRIM($A36),1,4,""),TRIM($A36)),账项调整!$J$5:$J$65536) -> 0 | E36: =SUMIF(报表调整!$F$5:$F$65536,IF(OR(MID(TRIM($A36),2,1)="：",MID(TRIM($A36),2,1)="、"),REPLACEB(TRIM($A36),1,4,""),TRIM($A36)),报表调整!$J$5:$J$65536) -> 0 | F36: =SUMIF(报表调整!$I$5:$I$65536,IF(OR(MID(TRIM($A36),2,1)="：",MID(TRIM($A36),2,1)="、"),REPLACEB(TRIM($A36),1,4,""),TRIM($A36)),报表调整!$J$5:$J$65536) -> 0 | G36: =B36-C36-E36+D36+F36 -> 0 | I36: =SUM(G36:H36) -> 0
A37: =报表格式!L36 -> 非货币性交易收益 | B37: =未审PL!D37 -> 0 | C37: =SUMIF(账项调整!$F$5:$F$65536,IF(OR(MID(TRIM($A37),2,1)="：",MID(TRIM($A37),2,1)="、"),REPLACEB(TRIM($A37),1,4,""),TRIM($A37)),账项调整!$J$5:$J$65536) -> 0 | D37: =SUMIF(账项调整!$I$5:$I$65536,IF(OR(MID(TRIM($A37),2,1)="：",MID(TRIM($A37),2,1)="、"),REPLACEB(TRIM($A37),1,4,""),TRIM($A37)),账项调整!$J$5:$J$65536) -> 0 | E37: =SUMIF(报表调整!$F$5:$F$65536,IF(OR(MID(TRIM($A37),2,1)="：",MID(TRIM($A37),2,1)="、"),REPLACEB(TRIM($A37),1,4,""),TRIM($A37)),报表调整!$J$5:$J$65536) -> 0 | F37: =SUMIF(报表调整!$I$5:$I$65536,IF(OR(MID(TRIM($A37),2,1)="：",MID(TRIM($A37),2,1)="、"),REPLACEB(TRIM($A37),1,4,""),TRIM($A37)),报表调整!$J$5:$J$65536) -> 0 | G37: =B37-C37-E37+D37+F37 -> 0 | I37: =SUM(G37:H37) -> 0
A38: =报表格式!L37 -> 出售无形资产收益 | B38: =未审PL!D38 -> 0 | C38: =SUMIF(账项调整!$F$5:$F$65536,IF(OR(MID(TRIM($A38),2,1)="：",MID(TRIM($A38),2,1)="、"),REPLACEB(TRIM($A38),1,4,""),TRIM($A38)),账项调整!$J$5:$J$65536) -> 0 | D38: =SUMIF(账项调整!$I$5:$I$65536,IF(OR(MID(TRIM($A38),2,1)="：",MID(TRIM($A38),2,1)="、"),REPLACEB(TRIM($A38),1,4,""),TRIM($A38)),账项调整!$J$5:$J$65536) -> 0 | E38: =SUMIF(报表调整!$F$5:$F$65536,IF(OR(MID(TRIM($A38),2,1)="：",MID(TRIM($A38),2,1)="、"),REPLACEB(TRIM($A38),1,4,""),TRIM($A38)),报表调整!$J$5:$J$65536) -> 0 | F38: =SUMIF(报表调整!$I$5:$I$65536,IF(OR(MID(TRIM($A38),2,1)="：",MID(TRIM($A38),2,1)="、"),REPLACEB(TRIM($A38),1,4,""),TRIM($A38)),报表调整!$J$5:$J$65536) -> 0 | G38: =B38-C38-E38+D38+F38 -> 0 | I38: =SUM(G38:H38) -> 0
A39: =报表格式!L38 -> 罚款净收入 | B39: =未审PL!D39 -> 0 | C39: =SUMIF(账项调整!$F$5:$F$65536,IF(OR(MID(TRIM($A39),2,1)="：",MID(TRIM($A39),2,1)="、"),REPLACEB(TRIM($A39),1,4,""),TRIM($A39)),账项调整!$J$5:$J$65536) -> 0 | D39: =SUMIF(账项调整!$I$5:$I$65536,IF(OR(MID(TRIM($A39),2,1)="：",MID(TRIM($A39),2,1)="、"),REPLACEB(TRIM($A39),1,4,""),TRIM($A39)),账项调整!$J$5:$J$65536) -> 0 | E39: =SUMIF(报表调整!$F$5:$F$65536,IF(OR(MID(TRIM($A39),2,1)="：",MID(TRIM($A39),2,1)="、"),REPLACEB(TRIM($A39),1,4,""),TRIM($A39)),报表调整!$J$5:$J$65536) -> 0 | F39: =SUMIF(报表调整!$I$5:$I$65536,IF(OR(MID(TRIM($A39),2,1)="：",MID(TRIM($A39),2,1)="、"),REPLACEB(TRIM($A39),1,4,""),TRIM($A39)),报表调整!$J$5:$J$65536) -> 0 | G39: =B39-C39-E39+D39+F39 -> 0 | I39: =SUM(G39:H39) -> 0
A40: =报表格式!L39 -> （五）其他 | B40: =未审PL!D40 -> 0 | C40: =SUMIF(账项调整!$E$5:$E$65536,REPLACEB(IF(OR(MID(TRIM($A40),2,1)="：",MID(TRIM($A40),2,1)="、"),REPLACEB(TRIM($A40),1,4,""),TRIM($A40)),1,6,""),账项调整!$J$5:$J$65536) -> 0 | D40: =SUMIF(账项调整!$H$5:$H$65536,REPLACEB(IF(OR(MID(TRIM($A40),2,1)="：",MID(TRIM($A40),2,1)="、"),REPLACEB(TRIM($A40),1,4,""),TRIM($A40)),1,6,""),账项调整!$J$5:$J$65536) -> 0 | E40: =SUMIF(报表调整!$E$5:$E$65536,REPLACEB(IF(OR(MID(TRIM($A40),2,1)="：",MID(TRIM($A40),2,1)="、"),REPLACEB(TRIM($A40),1,4,""),TRIM($A40)),1,6,""),报表调整!$J$5:$J$65536) -> 0 | F40: =SUMIF(报表调整!$H$5:$H$65536,REPLACEB(IF(OR(MID(TRIM($A40),2,1)="：",MID(TRIM($A40),2,1)="、"),REPLACEB(TRIM($A40),1,4,""),TRIM($A40)),1,6,""),报表调整!$J$5:$J$65536) -> 0 | G40: =B40-C40-E40+D40+F40 -> 0 | I40: =SUM(G40:H40) -> 0
A41: =报表格式!L40 -> 其中：用以前年度含量工资结余弥补利润 | B41: =未审PL!D41 -> 0 | C41: =SUMIF(账项调整!$F$5:$F$65536,IF(OR(MID(TRIM($A41),2,1)="：",MID(TRIM($A41),2,1)="、"),REPLACEB(TRIM($A41),1,4,""),TRIM($A41)),账项调整!$J$5:$J$65536) -> 0 | D41: =SUMIF(账项调整!$I$5:$I$65536,IF(OR(MID(TRIM($A41),2,1)="：",MID(TRIM($A41),2,1)="、"),REPLACEB(TRIM($A41),1,4,""),TRIM($A41)),账项调整!$J$5:$J$65536) -> 0 | E41: =SUMIF(报表调整!$F$5:$F$65536,IF(OR(MID(TRIM($A41),2,1)="：",MID(TRIM($A41),2,1)="、"),REPLACEB(TRIM($A41),1,4,""),TRIM($A41)),报表调整!$J$5:$J$65536) -> 0 | F41: =SUMIF(报表调整!$I$5:$I$65536,IF(OR(MID(TRIM($A41),2,1)="：",MID(TRIM($A41),2,1)="、"),REPLACEB(TRIM($A41),1,4,""),TRIM($A41)),报表调整!$J$5:$J$65536) -> 0 | G41: =B41-C41-E41+D41+F41 -> 0 | I41: =SUM(G41:H41) -> 0
A42: =报表格式!L41 -> 减：（一）营业外支出 | B42: =未审PL!D42 -> 0 | C42: =SUMIF(账项调整!$E$5:$E$65536,REPLACEB(IF(OR(MID(TRIM($A42),2,1)="：",MID(TRIM($A42),2,1)="、"),REPLACEB(TRIM($A42),1,4,""),TRIM($A42)),1,6,""),账项调整!$J$5:$J$65536) -> 0 | D42: =SUMIF(账项调整!$H$5:$H$65536,REPLACEB(IF(OR(MID(TRIM($A42),2,1)="：",MID(TRIM($A42),2,1)="、"),REPLACEB(TRIM($A42),1,4,""),TRIM($A42)),1,6,""),账项调整!$J$5:$J$65536) -> 0 | E42: =SUMIF(报表调整!$E$5:$E$65536,REPLACEB(IF(OR(MID(TRIM($A42),2,1)="：",MID(TRIM($A42),2,1)="、"),REPLACEB(TRIM($A42),1,4,""),TRIM($A42)),1,6,""),报表调整!$J$5:$J$65536) -> 0 | F42: =SUMIF(报表调整!$H$5:$H$65536,REPLACEB(IF(OR(MID(TRIM($A42),2,1)="：",MID(TRIM($A42),2,1)="、"),REPLACEB(TRIM($A42),1,4,""),TRIM($A42)),1,6,""),报表调整!$J$5:$J$65536) -> 0 | G42: =B42+C42+E42-D42-F42 -> 0 | I42: =SUM(G42:H42) -> 0
A43: =报表格式!L42 -> 其中：处置固定资产净损失 | B43: =未审PL!D43 -> 0 | C43: =SUMIF(账项调整!$F$5:$F$65536,IF(OR(MID(TRIM($A43),2,1)="：",MID(TRIM($A43),2,1)="、"),REPLACEB(TRIM($A43),1,4,""),TRIM($A43)),账项调整!$J$5:$J$65536) -> 0 | D43: =SUMIF(账项调整!$I$5:$I$65536,IF(OR(MID(TRIM($A43),2,1)="：",MID(TRIM($A43),2,1)="、"),REPLACEB(TRIM($A43),1,4,""),TRIM($A43)),账项调整!$J$5:$J$65536) -> 0 | E43: =SUMIF(报表调整!$F$5:$F$65536,IF(OR(MID(TRIM($A43),2,1)="：",MID(TRIM($A43),2,1)="、"),REPLACEB(TRIM($A43),1,4,""),TRIM($A43)),报表调整!$J$5:$J$65536) -> 0 | F43: =SUMIF(报表调整!$I$5:$I$65536,IF(OR(MID(TRIM($A43),2,1)="：",MID(TRIM($A43),2,1)="、"),REPLACEB(TRIM($A43),1,4,""),TRIM($A43)),报表调整!$J$5:$J$65536) -> 0 | G43: =B43+C43+E43-D43-F43 -> 0 | I43: =SUM(G43:H43) -> 0
A44: =报表格式!L43 -> 出售无形资产损失 | B44: =未审PL!D44 -> 0 | C44: =SUMIF(账项调整!$F$5:$F$65536,IF(OR(MID(TRIM($A44),2,1)="：",MID(TRIM($A44),2,1)="、"),REPLACEB(TRIM($A44),1,4,""),TRIM($A44)),账项调整!$J$5:$J$65536) -> 0 | D44: =SUMIF(账项调整!$I$5:$I$65536,IF(OR(MID(TRIM($A44),2,1)="：",MID(TRIM($A44),2,1)="、"),REPLACEB(TRIM($A44),1,4,""),TRIM($A44)),账项调整!$J$5:$J$65536) -> 0 | E44: =SUMIF(报表调整!$F$5:$F$65536,IF(OR(MID(TRIM($A44),2,1)="：",MID(TRIM($A44),2,1)="、"),REPLACEB(TRIM($A44),1,4,""),TRIM($A44)),报表调整!$J$5:$J$65536) -> 0 | F44: =SUMIF(报表调整!$I$5:$I$65536,IF(OR(MID(TRIM($A44),2,1)="：",MID(TRIM($A44),2,1)="、"),REPLACEB(TRIM($A44),1,4,""),TRIM($A44)),报表调整!$J$5:$J$65536) -> 0 | G44: =B44+C44+E44-D44-F44 -> 0 | I44: =SUM(G44:H44) -> 0
A45: =报表格式!L44 -> 罚款支出 | B45: =未审PL!D45 -> 0 | C45: =SUMIF(账项调整!$F$5:$F$65536,IF(OR(MID(TRIM($A45),2,1)="：",MID(TRIM($A45),2,1)="、"),REPLACEB(TRIM($A45),1,4,""),TRIM($A45)),账项调整!$J$5:$J$65536) -> 0 | D45: =SUMIF(账项调整!$I$5:$I$65536,IF(OR(MID(TRIM($A45),2,1)="：",MID(TRIM($A45),2,1)="、"),REPLACEB(TRIM($A45),1,4,""),TRIM($A45)),账项调整!$J$5:$J$65536) -> 0 | E45: =SUMIF(报表调整!$F$5:$F$65536,IF(OR(MID(TRIM($A45),2,1)="：",MID(TRIM($A45),2,1)="、"),REPLACEB(TRIM($A45),1,4,""),TRIM($A45)),报表调整!$J$5:$J$65536) -> 0 | F45: =SUMIF(报表调整!$I$5:$I$65536,IF(OR(MID(TRIM($A45),2,1)="：",MID(TRIM($A45),2,1)="、"),REPLACEB(TRIM($A45),1,4,""),TRIM($A45)),报表调整!$J$5:$J$65536) -> 0 | G45: =B45+C45+E45-D45-F45 -> 0 | I45: =SUM(G45:H45) -> 0
A46: =报表格式!L45 -> 捐赠支出 | B46: =未审PL!D46 -> 0 | C46: =SUMIF(账项调整!$F$5:$F$65536,IF(OR(MID(TRIM($A46),2,1)="：",MID(TRIM($A46),2,1)="、"),REPLACEB(TRIM($A46),1,4,""),TRIM($A46)),账项调整!$J$5:$J$65536) -> 0 | D46: =SUMIF(账项调整!$I$5:$I$65536,IF(OR(MID(TRIM($A46),2,1)="：",MID(TRIM($A46),2,1)="、"),REPLACEB(TRIM($A46),1,4,""),TRIM($A46)),账项调整!$J$5:$J$65536) -> 0 | E46: =SUMIF(报表调整!$F$5:$F$65536,IF(OR(MID(TRIM($A46),2,1)="：",MID(TRIM($A46),2,1)="、"),REPLACEB(TRIM($A46),1,4,""),TRIM($A46)),报表调整!$J$5:$J$65536) -> 0 | F46: =SUMIF(报表调整!$I$5:$I$65536,IF(OR(MID(TRIM($A46),2,1)="：",MID(TRIM($A46),2,1)="、"),REPLACEB(TRIM($A46),1,4,""),TRIM($A46)),报表调整!$J$5:$J$65536) -> 0 | G46: =B46+C46+E46-D46-F46 -> 0 | I46: =SUM(G46:H46) -> 0
A47: =报表格式!L46 -> （二）其他支出 | B47: =未审PL!D47 -> 0 | C47: =SUMIF(账项调整!$E$5:$E$65536,REPLACEB(IF(OR(MID(TRIM($A47),2,1)="：",MID(TRIM($A47),2,1)="、"),REPLACEB(TRIM($A47),1,4,""),TRIM($A47)),1,6,""),账项调整!$J$5:$J$65536) -> 0 | D47: =SUMIF(账项调整!$H$5:$H$65536,REPLACEB(IF(OR(MID(TRIM($A47),2,1)="：",MID(TRIM($A47),2,1)="、"),REPLACEB(TRIM($A47),1,4,""),TRIM($A47)),1,6,""),账项调整!$J$5:$J$65536) -> 0 | E47: =SUMIF(报表调整!$E$5:$E$65536,REPLACEB(IF(OR(MID(TRIM($A47),2,1)="：",MID(TRIM($A47),2,1)="、"),REPLACEB(TRIM($A47),1,4,""),TRIM($A47)),1,6,""),报表调整!$J$5:$J$65536) -> 0 | F47: =SUMIF(报表调整!$H$5:$H$65536,REPLACEB(IF(OR(MID(TRIM($A47),2,1)="：",MID(TRIM($A47),2,1)="、"),REPLACEB(TRIM($A47),1,4,""),TRIM($A47)),1,6,""),报表调整!$J$5:$J$65536) -> 0 | G47: =B47+C47+E47-D47-F47 -> 0 | I47: =SUM(G47:H47) -> 0
A48: =报表格式!L47 -> 其中：结转的含量工资包干结余 | B48: =未审PL!D48 -> 0 | C48: =SUMIF(账项调整!$F$5:$F$65536,IF(OR(MID(TRIM($A48),2,1)="：",MID(TRIM($A48),2,1)="、"),REPLACEB(TRIM($A48),1,4,""),TRIM($A48)),账项调整!$J$5:$J$65536) -> 0 | D48: =SUMIF(账项调整!$I$5:$I$65536,IF(OR(MID(TRIM($A48),2,1)="：",MID(TRIM($A48),2,1)="、"),REPLACEB(TRIM($A48),1,4,""),TRIM($A48)),账项调整!$J$5:$J$65536) -> 0 | E48: =SUMIF(报表调整!$F$5:$F$65536,IF(OR(MID(TRIM($A48),2,1)="：",MID(TRIM($A48),2,1)="、"),REPLACEB(TRIM($A48),1,4,""),TRIM($A48)),报表调整!$J$5:$J$65536) -> 0 | F48: =SUMIF(报表调整!$I$5:$I$65536,IF(OR(MID(TRIM($A48),2,1)="：",MID(TRIM($A48),2,1)="、"),REPLACEB(TRIM($A48),1,4,""),TRIM($A48)),报表调整!$J$5:$J$65536) -> 0 | G48: =B48+C48+E48-D48-F48 -> 0 | I48: =SUM(G48:H48) -> 0
A49: =报表格式!L48 -> 五、利润总额 | B49: =B30+B31+B32+B33+B35+B40-B42-B47 -> 0 | C49: =C30+C31+C32+C33+C35+C40-C42-C47 -> 0 | D49: =D30+D31+D32+D33+D35+D40-D42-D47 -> 0 | E49: =E30+E31+E32+E33+E35+E40-E42-E47 -> 0 | F49: =F30+F31+F32+F33+F35+F40-F42-F47 -> 0 | G49: =G30+G31+G32+G33+G35+G40-G42-G47 -> 0 | H49: =H30+H31+H32+H33+H35+H40-H42-H47 -> 0 | I49: =SUM(G49:H49) -> 0
A50: =报表格式!L49 -> 减：所得税 | B50: =未审PL!D50 -> 0 | C50: =SUMIF(账项调整!$E$5:$E$65536,IF(OR(MID(TRIM($A50),2,1)="：",MID(TRIM($A50),2,1)="、"),REPLACEB(TRIM($A50),1,4,""),TRIM($A50)),账项调整!$J$5:$J$65536) -> 0 | D50: =SUMIF(账项调整!$H$5:$H$65536,IF(OR(MID(TRIM($A50),2,1)="：",MID(TRIM($A50),2,1)="、"),REPLACEB(TRIM($A50),1,4,""),TRIM($A50)),账项调整!$J$5:$J$65536) -> 0 | E50: =SUMIF(报表调整!$E$5:$E$65536,IF(OR(MID(TRIM($A50),2,1)="：",MID(TRIM($A50),2,1)="、"),REPLACEB(TRIM($A50),1,4,""),TRIM($A50)),报表调整!$J$5:$J$65536) -> 0 | F50: =SUMIF(报表调整!$H$5:$H$65536,IF(OR(MID(TRIM($A50),2,1)="：",MID(TRIM($A50),2,1)="、"),REPLACEB(TRIM($A50),1,4,""),TRIM($A50)),报表调整!$J$5:$J$65536) -> 0 | G50: =B50+C50+E50-D50-F50 -> 0 | I50: =SUM(G50:H50) -> 0
A51: =报表格式!L50 -> *少数股东损益 | B51: =未审PL!D51 -> 0 | C51: =SUMIF(账项调整!$E$5:$E$65536,REPLACEB(IF(OR(MID(TRIM($A51),2,1)="：",MID(TRIM($A51),2,1)="、"),REPLACEB(TRIM($A51),1,4,""),TRIM($A51)),1,1,""),账项调整!$J$5:$J$65536) -> 0 | D51: =SUMIF(账项调整!$H$5:$H$65536,REPLACEB(IF(OR(MID(TRIM($A51),2,1)="：",MID(TRIM($A51),2,1)="、"),REPLACEB(TRIM($A51),1,4,""),TRIM($A51)),1,1,""),账项调整!$J$5:$J$65536) -> 0 | E51: =SUMIF(报表调整!$E$5:$E$65536,REPLACEB(IF(OR(MID(TRIM($A51),2,1)="：",MID(TRIM($A51),2,1)="、"),REPLACEB(TRIM($A51),1,4,""),TRIM($A51)),1,1,""),报表调整!$J$5:$J$65536) -> 0 | F51: =SUMIF(报表调整!$H$5:$H$65536,REPLACEB(IF(OR(MID(TRIM($A51),2,1)="：",MID(TRIM($A51),2,1)="、"),REPLACEB(TRIM($A51),1,4,""),TRIM($A51)),1,1,""),报表调整!$J$5:$J$65536) -> 0 | G51: =B51+C51+E51-D51-F51 -> 0 | I51: =SUM(G51:H51) -> 0
A52: =报表格式!L51 -> 加：*未确认的投资损失 | B52: =未审PL!D52 -> 0 | C52: =SUMIF(账项调整!$E$5:$E$65536,REPLACEB(IF(OR(MID(TRIM($A52),2,1)="：",MID(TRIM($A52),2,1)="、"),REPLACEB(TRIM($A52),1,4,""),TRIM($A52)),1,1,""),账项调整!$J$5:$J$65536) -> 0 | D52: =SUMIF(账项调整!$H$5:$H$65536,REPLACEB(IF(OR(MID(TRIM($A52),2,1)="：",MID(TRIM($A52),2,1)="、"),REPLACEB(TRIM($A52),1,4,""),TRIM($A52)),1,1,""),账项调整!$J$5:$J$65536) -> 0 | E52: =SUMIF(报表调整!$E$5:$E$65536,REPLACEB(IF(OR(MID(TRIM($A52),2,1)="：",MID(TRIM($A52),2,1)="、"),REPLACEB(TRIM($A52),1,4,""),TRIM($A52)),1,1,""),报表调整!$J$5:$J$65536) -> 0 | F52: =SUMIF(报表调整!$H$5:$H$65536,REPLACEB(IF(OR(MID(TRIM($A52),2,1)="：",MID(TRIM($A52),2,1)="、"),REPLACEB(TRIM($A52),1,4,""),TRIM($A52)),1,1,""),报表调整!$J$5:$J$65536) -> 0 | G52: =B52+C52+E52-D52-F52 -> 0 | I52: =SUM(G52:H52) -> 0
A53: =报表格式!L52 -> 六、净利润 | B53: =B49-B50-B51+B52 -> 0 | C53: =C49-C50-C51+C52 -> 0 | D53: =D49-D50-D51+D52 -> 0 | E53: =E49-E50-E51+E52 -> 0 | F53: =F49-F50-F51+F52 -> 0 | G53: =G49-G50-G51+G52 -> 0 | H53: =H49-H50-H51+H52 -> 0 | I53: =SUM(G53:H53) -> 0
A54: =报表格式!L53 -> 加：（一）年初未分配利润 | B54: =未审PL!D54 -> 0 | C54: =SUMIF(账项调整!$E$5:$E$65536,REPLACEB(IF(OR(MID(TRIM($A54),2,1)="：",MID(TRIM($A54),2,1)="、"),REPLACEB(TRIM($A54),1,4,""),TRIM($A54)),1,6,""),账项调整!$J$5:$J$65536) -> 0 | D54: =SUMIF(账项调整!$H$5:$H$65536,REPLACEB(IF(OR(MID(TRIM($A54),2,1)="：",MID(TRIM($A54),2,1)="、"),REPLACEB(TRIM($A54),1,4,""),TRIM($A54)),1,6,""),账项调整!$J$5:$J$65536) -> 0 | E54: =SUMIF(报表调整!$E$5:$E$65536,REPLACEB(IF(OR(MID(TRIM($A54),2,1)="：",MID(TRIM($A54),2,1)="、"),REPLACEB(TRIM($A54),1,4,""),TRIM($A54)),1,6,""),报表调整!$J$5:$J$65536) -> 0 | F54: =SUMIF(报表调整!$H$5:$H$65536,REPLACEB(IF(OR(MID(TRIM($A54),2,1)="：",MID(TRIM($A54),2,1)="、"),REPLACEB(TRIM($A54),1,4,""),TRIM($A54)),1,6,""),报表调整!$J$5:$J$65536) -> 0 | G54: =B54-C54-E54+D54+F54 -> 0 | I54: =SUM(G54:H54) -> 0
A55: =报表格式!L54 -> （二）盈余公积补亏 | B55: =未审PL!D55 -> 0 | C55: =SUMIF(账项调整!$E$5:$E$65536,REPLACEB(IF(OR(MID(TRIM($A55),2,1)="：",MID(TRIM($A55),2,1)="、"),REPLACEB(TRIM($A55),1,4,""),TRIM($A55)),1,6,""),账项调整!$J$5:$J$65536) -> 0 | D55: =SUMIF(账项调整!$H$5:$H$65536,REPLACEB(IF(OR(MID(TRIM($A55),2,1)="：",MID(TRIM($A55),2,1)="、"),REPLACEB(TRIM($A55),1,4,""),TRIM($A55)),1,6,""),账项调整!$J$5:$J$65536) -> 0 | E55: =SUMIF(报表调整!$E$5:$E$65536,REPLACEB(IF(OR(MID(TRIM($A55),2,1)="：",MID(TRIM($A55),2,1)="、"),REPLACEB(TRIM($A55),1,4,""),TRIM($A55)),1,6,""),报表调整!$J$5:$J$65536) -> 0 | F55: =SUMIF(报表调整!$H$5:$H$65536,REPLACEB(IF(OR(MID(TRIM($A55),2,1)="：",MID(TRIM($A55),2,1)="、"),REPLACEB(TRIM($A55),1,4,""),TRIM($A55)),1,6,""),报表调整!$J$5:$J$65536) -> 0 | G55: =B55-C55-E55+D55+F55 -> 0 | I55: =SUM(G55:H55) -> 0
A56: =报表格式!L55 -> （三）其他调整因素 | B56: =未审PL!D56 -> 0 | C56: =SUMIF(账项调整!$E$5:$E$65536,REPLACEB(IF(OR(MID(TRIM($A56),2,1)="：",MID(TRIM($A56),2,1)="、"),REPLACEB(TRIM($A56),1,4,""),TRIM($A56)),1,6,""),账项调整!$J$5:$J$65536) -> 0 | D56: =SUMIF(账项调整!$H$5:$H$65536,REPLACEB(IF(OR(MID(TRIM($A56),2,1)="：",MID(TRIM($A56),2,1)="、"),REPLACEB(TRIM($A56),1,4,""),TRIM($A56)),1,6,""),账项调整!$J$5:$J$65536) -> 0 | E56: =SUMIF(报表调整!$E$5:$E$65536,REPLACEB(IF(OR(MID(TRIM($A56),2,1)="：",MID(TRIM($A56),2,1)="、"),REPLACEB(TRIM($A56),1,4,""),TRIM($A56)),1,6,""),报表调整!$J$5:$J$65536) -> 0 | F56: =SUMIF(报表调整!$H$5:$H$65536,REPLACEB(IF(OR(MID(TRIM($A56),2,1)="：",MID(TRIM($A56),2,1)="、"),REPLACEB(TRIM($A56),1,4,""),TRIM($A56)),1,6,""),报表调整!$J$5:$J$65536) -> 0 | G56: =B56-C56-E56+D56+F56 -> 0 | I56: =SUM(G56:H56) -> 0
A57: =报表格式!L56 -> 七、可供分配的利润 | B57: =B53+B54+B55+B56 -> 0 | C57: =C53+C54+C55+C56 -> 0 | D57: =D53+D54+D55+D56 -> 0 | E57: =E53+E54+E55+E56 -> 0 | F57: =F53+F54+F55+F56 -> 0 | G57: =G53+G54+G55+G56 -> 0 | H57: =H53+H54+H55+H56 -> 0 | I57: =SUM(G57:H57) -> 0
A58: =报表格式!L57 -> 减：（一）提取法定盈余公积 | B58: =未审PL!D58 -> 0 | C58: =SUMIF(账项调整!$E$5:$E$65536,REPLACEB(IF(OR(MID(TRIM($A58),2,1)="：",MID(TRIM($A58),2,1)="、"),REPLACEB(TRIM($A58),1,4,""),TRIM($A58)),1,6,""),账项调整!$J$5:$J$65536) -> 0 | D58: =SUMIF(账项调整!$H$5:$H$65536,REPLACEB(IF(OR(MID(TRIM($A58),2,1)="：",MID(TRIM($A58),2,1)="、"),REPLACEB(TRIM($A58),1,4,""),TRIM($A58)),1,6,""),账项调整!$J$5:$J$65536) -> 0 | E58: =SUMIF(报表调整!$E$5:$E$65536,REPLACEB(IF(OR(MID(TRIM($A58),2,1)="：",MID(TRIM($A58),2,1)="、"),REPLACEB(TRIM($A58),1,4,""),TRIM($A58)),1,6,""),报表调整!$J$5:$J$65536) -> 0 | F58: =SUMIF(报表调整!$H$5:$H$65536,REPLACEB(IF(OR(MID(TRIM($A58),2,1)="：",MID(TRIM($A58),2,1)="、"),REPLACEB(TRIM($A58),1,4,""),TRIM($A58)),1,6,""),报表调整!$J$5:$J$65536) -> 0 | G58: =B58+C58+E58-D58-F58 -> 0 | I58: =SUM(G58:H58) -> 0
