Workbook
Name 调整类别: [1]试算!$C$7:$E$7

Sheet temp_temp__
C26: =SUM(C6)-SUM(C9,C12,C13,C14,C17,C21,C22)+SUM(C23,C24) -> 0

Sheet 说明
B2: 使用说明： | L2: 序号 | M2: 目录
L3: 1 | M3: 说明
B4: 1 | C4: 本工作簿基于2006年《企业会计准则》编制，并考虑了后续的更新。 | L4: 2 | M4: 参数
C5: 为方便阅读与核对，未删除利润分配项目。 | L5: 3 | M5: 报表格式
L6: 4 | M6: 未审报表
B7: 2 | C7: 本工作簿用于单项会计报表审计调整、试算平衡；未审报表及审定报表的横向、纵向、比率分析。 | L7: 5 | M7: 期初核对
L8: 6 | M8: TB
B9: 3 | C9: 本工作簿没有颜色的单元格可以根据需要进行修改， | L9: 7 | M9: TB(期初)
C10: 修改时，请在拟修改的单元格直接输入新的内容，请不要使用剪切或拖拽填充功能。 | L10: 8 | M10: 账项调整
L11: 9 | M11: 报表调整
B12: 4 | C12: 请在 | D12: “参数表” | E12: 中没有颜色的单元格中输入项目基本情况，其他工作表相应区域会随之改变。 | L12: 10 | M12: 审定报表
L13: 11 | M13: 未审BS分析
B14: 5 | C14: 未审报表、试算平衡表（TB）、审定报表、比较分析表的格式由 | G14: “报表格式” | H14: 链接控制； | L14: 12 | M14: 未审PL分析
C15: 如需修改报表科目，请在 | E15: “报表格式” | F15: 中没有颜色的单元格区域修改，其他报表会相应改变。 | L15: 13 | M15: 未审比率分析
L16: 14 | M16: 已审BS分析
B17: 6 | C17: 调整事项汇总表 | D17: 可以根据需要插入行，请勿删除行；调整金额会自动链接到试算平衡表， | L17: 15 | M17: 已审PL分析
C18: 若调整未全部链入试算平衡表，请检查调整分录的借贷方科目是否为报表科目，如不是报表科目，调整事项汇总表N列、O列会进行提示。 | L18: 16 | M18: 已审比率分析
C19: 若需添加或更改报表科目，请在 | D19: “报表格式” | E19: 中没有颜色的单元格区域进行修改，并相应修改 | H19: “报表格式S列”
B21: 7、 | C21: 由于报表项目名称存在重复的情况，主要涉及利润表中的其他及现金流中的其他，所以在
C22: 调整事项汇总表R列 | D22: 对个别报表项目的名称进行
C23: 了修改，已方便对报表项目进行正确调整，并用红色字体进行了标记，具体包括:
C24: 其他（不能重分类）
C25: 其他（可以重分类）
C26: 其他（分配）
C27: 其他（现）

Sheet 参数
B2: 项 目 | D2: 参 数 | E2: 参考格式
B3: 客户情况 | C3: 单位名称： | D3: 二锅头 | E3: 北京二锅头有限责任公司
C4: 法定代表人： | E4: 张一二
C5: 财务负责人： | E5: 陈一二
C6: 会计主管： | E6: 王一二
B8: 会计报表 | C8: 报表类型 | D8: 股份有限公司 | E8: 股份有限公司或一般企业(执行统一会计制度)
C9: 会计年度（上期）： | D9: 2021年度 | E9: 1999年度 或 1997年10月20日～1998年8月10日 | H9: 股份有限公司
C10: 会计年度（本期）： | D10: 2022年度 | E10: 2000年度 或 1998年8月10日～2000年10月20日 | H10: 非股份有限公司
C11: 会计截止（上期）： | D11: 44561 | E11: 1999年12月31日 或 1998年8月10日 | I11: =MONTH(D11) -> 12
C12: 会计截止（本期）： | D12: 44926 | E12: 2000年12月31日 或 2000年10月20日 | I12: =MONTH(D12) -> 12
C13: 金额单位： | D13: 人民币元 | E13: 人民币元
B15: 审计单位 | C15: 审计单位名称： | D15: 致同会计师事务所
C16: 项目负责人：
C17: 底稿编制人： | D17: 张 | E17: 刘一二
C18: 底稿复核人： | D18: 刘 | E18: 周一二
B20: NB | C20: 本表没有颜色的单元格可以根据需要进行修改
B24: 报表勾稽关系审核表
B25: No. | C25: 勾稽审核内容 | D25: 审核结果 | E25: 不符原因
B26: 1 | C26: 期末资产总计＝期末负债和股东权益总计 | D26: =IF(ABS(审定报表!C127-审定报表!C190)<0.01,TRUE,FALSE) -> TRUE | E26: =IF(D26=TRUE,"","期末资产负债表不平")
B27: 2 | C27: 期初资产总计＝期初负债和股东权益总计 | D27: =IF(ABS(审定报表!D127-审定报表!D190)<0.01,TRUE,FALSE) -> TRUE | E27: =IF(D27=TRUE,"","期初资产负债表不平")
B28: 3 | C28: B/S期末未分配利润＝P/L期末未分配利润 | D28: =IF(ABS(审定报表!C186-审定报表!C277)<0.01,TRUE,FALSE) -> TRUE | E28: =IF(D28=TRUE,"","期末利润分配表与资产负债表未分配利润勾稽不对")
B29: 4 | C29: B/S期初未分配利润＝P/L期初未分配利润 | D29: =IF(ABS(审定报表!D277-审定报表!D186)<0.01,TRUE,FALSE) -> TRUE | E29: =IF(D29=TRUE,"","期初利润分配表与资产负债表未分配利润勾稽不对")
B30: 5 | C30: 期末年初未分配利润＝期初未分配利润 | D30: =IF(ABS(审定报表!C266-审定报表!D277)<0.01,TRUE,FALSE) -> TRUE | E30: =IF(D30=TRUE,"","利润及利润分配表年初未分配利润与上期勾稽不对")
B31: 6 | C31: B/S期末货币资金＝Cashflow期末货币资金 | D31: =IF(ABS(审定报表!C8-审定报表!C342)<0.01,TRUE,FALSE) -> FALSE | E31: =IF(D31=TRUE,"","现金流量表与资产负债表期末货币资金勾稽不对") -> 现金流量表与资产负债表期末货币资金勾稽不对
B32: 7 | C32: B/S期初货币资金＝Cashflow期初货币资金 | D32: =IF(ABS(审定报表!D8-审定报表!D342)<0.01,TRUE,FALSE) -> FALSE | E32: =IF(D32=TRUE,"","现金流量表与资产负债表期初货币资金勾稽不对") -> 现金流量表与资产负债表期初货币资金勾稽不对
B33: 8 | C33: 直接法OperatingCF＝间接法OperatingCF | D33: =IF(ABS(审定报表!C307-审定报表!C366)<0.01,TRUE,FALSE) -> FALSE | E33: =IF(D33=TRUE,"","现金流量表主表与附表勾稽不对-经营活动现金净增加额") -> 现金流量表主表与附表勾稽不对-经营活动现金净增加额
B34: 9 | C34: 直接法NetCashflow＝间接法NetCashflow | D34: =IF(ABS(审定报表!C342-审定报表!C382)<0.01,TRUE,FALSE) -> TRUE | E34: =IF(D34=TRUE,"","现金流量表主表与附表勾稽不对-现金净增加额")
B35: 10 | C35: P/L净利润＝Cashflow间接法净利润 | D35: =IF(ABS(审定报表!C233-审定报表!C345)<0.01,TRUE,FALSE) -> TRUE | E35: =IF(D35=TRUE,"","现金流量表与利润表勾稽不对-净利润")
B36: 11 | C36: Cashflow存货的减少＝B/S存货的减少 | D36: =IF(ABS(审定报表!C361-(审定报表!D46-审定报表!C46))<0.01,TRUE,FALSE) -> FALSE | E36: =IF(D36=TRUE,"","现金流量表存货与资产负债表勾稽不对") -> 现金流量表存货与资产负债表勾稽不对
B37: 12 | C37: Cashflow投资收益＝P/L投资收益 | D37: =IF(ABS(审定报表!C358+审定报表!C218)<0.01,TRUE,FALSE) -> FALSE | E37: =IF(D37=TRUE,"","利润分配表与现金流量表投资收益勾稽不对") -> 利润分配表与现金流量表投资收益勾稽不对
B38: 13 | C38: 按净利润的10%提取法定盈余公积 | D38: =IF(ABS(审定报表!C233*0.1-审定报表!C268)<0.01,TRUE,FALSE) -> TRUE | E38: =IF(D38=TRUE,"","按照公司政策，公司提取的法定盈余公积不符")

Sheet 报表格式
A1: 会计报表格式及科目名称 | K1: 会计报表格式及科目名称 | R1: code | S1: 报表项目
B2: 本表没有颜色的单元格可以根据需要进行修改，本系统的其它表格将随之改变。比如，可将“存货”改为“存货1”。正确的修改方法，是在拟修改的单元格直接输入新的内容，请不要使用剪切或拖拽功能。
B3: 资 产 类 | E3: 负债及所有者权益类 | H3: 损 益 类 | K3: 现金流量表类 | N3: 现金流量表类
B4: 项目 | C4: 行 | E4: 项目 | F4: 行 | H4: 项目 | I4: 行 | K4: 项目 | L4: 行 | N4: 补充资料 | O4: 行
B5: 流动资产： | C5: 1 | E5: 流动负债： | F5: =C125+1 -> 122 | H5: 一、营业总收入 | I5: 1 | K5: 一、经营活动产生的现金流量 | L5: 1 | N5: 1、将净利润调节为经营活动现金流量： | O5: =L68+1 -> 65 | S5: 流动资产：
B6: 货币资金 | C6: =C5+1 -> 2 | E6: 短期借款 | F6: =F5+1 -> 123 | H6: 其中：主营业务收入 | I6: =I5+1 -> 2 | K6: 销售商品、提供劳务收到的现金 | L6: =L5+1 -> 2 | N6: 净利润 | O6: =O5+1 -> 66 | R6: D1 | S6: =B6 -> 货币资金
B7: 结算备付金* | C7: =C6+1 -> 3 | E7: 向中央银行借款* | F7: =F6+1 -> 124 | H7: 其他业务收入 | I7: =I6+1 -> 3 | K7: 客户存款和同业存放款项净增加额* | L7: =L6+1 -> 3 | O7: =O6+1 -> 67 | R7: D2 | S7: =B7 -> 结算备付金*
B8: 拆出资金原值* | C8: =C7+1 -> 4 | E8: 拆入资金* | F8: =F7+1 -> 125 | H8: 利息收入* | I8: =I7+1 -> 4 | K8: 向中央银行借款净增加额* | L8: =L7+1 -> 4 | O8: =O7+1 -> 68 | R8: D3 | S8: =B8 -> 拆出资金原值*
B9: 拆出资金减值准备* | C9: =C8+1 -> 5 | E9: 交易性金融负债 | F9: =F8+1 -> 126 | H9: 已赚保费* | I9: =I8+1 -> 5 | K9: 向其他金融机构拆入资金净增加额* | L9: =L8+1 -> 5 | N9: 加：资产减值损失 | O9: =O8+1 -> 69 | R9: D4 | S9: =B9 -> 拆出资金减值准备*
B10: 拆出资金* | C10: =C9+1 -> 6 | E10: 衍生金融负债 | F10: =F9+1 -> 127 | H10: 手续费及佣金收入* | I10: =I9+1 -> 6 | K10: 收到原保险合同保费取得的现金* | L10: =L9+1 -> 6 | N10: 信用减值损失 | O10: =O9+1 -> 70 | S10: =B10 -> 拆出资金*
B11: 交易性金融资产 | C11: =C10+1 -> 7 | E11: 应付票据 | F11: =F10+1 -> 128 | H11: 减：营业总成本 | I11: =I10+1 -> 7 | K11: 收到再保业务现金净额* | L11: =L10+1 -> 7 | N11: 固定资产折旧、投资性房地产折旧、油气资产折耗、生产性生物资产折旧 | O11: =O10+1 -> 71 | R11: D5 | S11: =B11 -> 交易性金融资产
B12: 衍生金融资产 | C12: =C11+1 -> 8 | E12: 应付账款 | F12: =F11+1 -> 129 | H12: 其中：主营业务成本 | I12: =I11+1 -> 8 | K12: 保户储金及投资款净增加额* | L12: =L11+1 -> 8 | N12: 使用权资产折旧 | O12: =O11+1 -> 72 | R12: D6 | S12: =B12 -> 衍生金融资产
B13: 应收票据原值 | C13: =C12+1 -> 9 | E13: 预收款项 | F13: =F12+1 -> 130 | H13: 其他业务成本 | I13: =I12+1 -> 9 | K13: 收取利息、手续费及佣金的现金* | L13: =L12+1 -> 9 | N13: 无形资产摊销 | O13: =O12+1 -> 73 | R13: D7 | S13: =B13 -> 应收票据原值
B14: 应收票据坏账准备 | C14: =C13+1 -> 10 | E14: 合同负债 | F14: =F13+1 -> 131 | H14: 利息支出* | I14: =I13+1 -> 10 | K14: 拆入资金净增加额* | L14: =L13+1 -> 10 | N14: 长期待摊费用摊销 | O14: =O13+1 -> 74 | R14: D8 | S14: =B14 -> 应收票据坏账准备
B15: 应收票据 | C15: =C14+1 -> 11 | E15: 卖出回购金融资产款* | F15: =F14+1 -> 132 | H15: 手续费及佣金支出* | I15: =I14+1 -> 11 | K15: 回购业务资金净增加额* | L15: =L14+1 -> 11 | N15: 处置固定资产、无形资产和其他长期资产的损失（收益以“－”号填列） | O15: =O14+1 -> 75 | S15: =B15 -> 应收票据
B16: 应收账款原值 | C16: =C15+1 -> 12 | E16: 吸收存款及同业存放* | F16: =F15+1 -> 133 | H16: 退保金* | I16: =I15+1 -> 12 | K16: 代理买卖证券收到的现金净额* | L16: =L15+1 -> 12 | N16: 固定资产报废损失（收益以“－”号填列） | O16: =O15+1 -> 76 | R16: D9 | S16: =B16 -> 应收账款原值
B17: 应收账款坏账准备 | C17: =C16+1 -> 13 | E17: 代理买卖证券款* | F17: =F16+1 -> 134 | H17: 赔付支出净额* | I17: =I16+1 -> 13 | K17: 收到的税费返还 | L17: =L16+1 -> 13 | N17: 公允价值变动损失（收益以“－”号填列） | O17: =O16+1 -> 77 | R17: D10 | S17: =B17 -> 应收账款坏账准备
B18: 应收账款 | C18: =C17+1 -> 14 | E18: 代理承销证券款* | F18: =F17+1 -> 135 | H18: 提取保险责任准备金净额* | I18: =I17+1 -> 14 | K18: 收到的其他与经营活动有关的现金 | L18: =L17+1 -> 14 | N18: 财务费用（收益以“－”号填列） | O18: =O17+1 -> 78 | S18: =B18 -> 应收账款
B19: 应收款项融资原值 | C19: =C18+1 -> 15 | E19: 应付职工薪酬 | F19: =F18+1 -> 136 | H19: 保单红利支出* | I19: =I18+1 -> 15 | L19: =L18+1 -> 15 | N19: 投资损失（收益以“－”号填列） | O19: =O18+1 -> 79 | R19: D11 | S19: =B19 -> 应收款项融资原值
B20: 应收款项融资坏账准备 | C20: =C19+1 -> 16 | E20: 其中：应付工资 | F20: =F19+1 -> 137 | H20: 分保费用* | I20: =I19+1 -> 16 | K20: 经营活动现金流入小计 | L20: =L19+1 -> 16 | N20: 递延所得税资产减少（增加以“－”号填列） | O20: =O19+1 -> 80 | R20: D12 | S20: =B20 -> 应收款项融资坏账准备
B21: 应收款项融资 | C21: =C20+1 -> 17 | E21: 应付福利费 | F21: =F20+1 -> 138 | H21: 税金及附加 | I21: =I20+1 -> 17 | K21: 购买商品、接受劳务支付的现金 | L21: =L20+1 -> 17 | N21: 递延所得税负债增加（减少以“－”号填列） | O21: =O20+1 -> 81 | S21: =B21 -> 应收款项融资
B22: 预付款项原值 | C22: =C21+1 -> 18 | E22: #其中：职工奖励及福利基金 | F22: =F21+1 -> 139 | H22: 销售费用 | I22: =I21+1 -> 18 | K22: 客户贷款及垫款净增加额* | L22: =L21+1 -> 18 | N22: 存货的减少（增加以“－”号填列） | O22: =O21+1 -> 82 | R22: D13 | S22: =B22 -> 预付款项原值
B23: 预付款项坏账准备 | C23: =C22+1 -> 19 | E23: 应交税费 | F23: =F22+1 -> 140 | H23: 管理费用 | I23: =I22+1 -> 19 | K23: 存放中央银行和同业款项净增加额* | L23: =L22+1 -> 19 | N23: 经营性应收项目的减少（增加以“－”号填列） | O23: =O22+1 -> 83 | R23: D14 | S23: =B23 -> 预付款项坏账准备
B24: 预付款项 | C24: =C23+1 -> 20 | E24: 其中：应交税金 | F24: =F23+1 -> 141 | H24: 研发费用 | I24: =I23+1 -> 20 | K24: 支付原保险合同赔付款项的现金* | L24: =L23+1 -> 20 | N24: 经营性应付项目的增加（减少以“－”号填列） | O24: =O23+1 -> 84 | S24: =B24 -> 预付款项
B25: 应收保费原值* | C25: =C24+1 -> 21 | E25: 其他应付款 | F25: =F24+1 -> 142 | H25: 财务费用 | I25: =I24+1 -> 21 | K25: 拆出资金净增加额* | L25: =L24+1 -> 21 | N25: 其他 | O25: =O24+1 -> 85 | R25: D15 | S25: =B25 -> 应收保费原值*
B26: 应收保费坏账准备* | C26: =C25+1 -> 22 | E26: 其中：应付利息 | F26: =F25+1 -> 143 | H26: 其中：利息费用 | I26: =I25+1 -> 22 | K26: 支付利息、手续费及佣金的现金* | L26: =L25+1 -> 22 | O26: =O25+1 -> 86 | R26: D16 | S26: =B26 -> 应收保费坏账准备*
B27: 应收保费* | C27: =C26+1 -> 23 | E27: 应付股利 | F27: =F26+1 -> 144 | H27: 利息收入 | I27: =I26+1 -> 23 | K27: 支付保单红利的现金* | L27: =L26+1 -> 23 | N27: 经营活动产生的现金流量净额 | O27: =O26+1 -> 87 | S27: =B27 -> 应收保费*
B28: 应收分保账款原值* | C28: =C27+1 -> 24 | E28: 应付手续费及佣金* | F28: =F27+1 -> 145 | H28: 汇兑净损失（净收益以“－”号填列） | I28: =I27+1 -> 24 | K28: 支付给职工以及为职工支付的现金 | L28: =L27+1 -> 24 | O28: =O27+1 -> 88 | R28: D15 | S28: =B28 -> 应收分保账款原值*
B29: 应收分保账款坏账准备* | C29: =C28+1 -> 25 | E29: 应付分保账款* | F29: =F28+1 -> 146 | H29: 其他 | I29: =I28+1 -> 25 | K29: 支付各项税费 | L29: =L28+1 -> 25 | N29: 2、不涉及现金收支的投资和筹资活动： | O29: =O28+1 -> 89 | R29: D16 | S29: =B29 -> 应收分保账款坏账准备*
B30: 应收分保账款* | C30: =C29+1 -> 26 | E30: 持有待售负债 | F30: =F29+1 -> 147 | H30: 加：其他收益 | I30: =I29+1 -> 26 | K30: 支付的其他与经营活动有关的现金 | L30: =L29+1 -> 26 | N30: 债务转为资本 | O30: =O29+1 -> 90 | S30: =B30 -> 应收分保账款*
B31: 应收分保合同准备金* | C31: =C30+1 -> 27 | E31: 一年内到期的非流动负债 | F31: =F30+1 -> 148 | H31: 投资收益（损失以“－”号填列） | I31: =I30+1 -> 27 | L31: =L30+1 -> 27 | N31: 一年内到期的可转换公司债券 | O31: =O30+1 -> 91 | R31: D17 | S31: =B31 -> 应收分保合同准备金*
B32: 应收利息原值 | C32: =C31+1 -> 28 | E32: 其他流动负债 | F32: =F31+1 -> 149 | H32: 其中：对联营企业和合营企业的投资收益 | I32: =I31+1 -> 28 | K32: 经营活动现金流出小计 | L32: =L31+1 -> 28 | N32: 融资租入固定资产 | O32: =O31+1 -> 92 | R32: D18 | S32: =B32 -> 应收利息原值
B33: 应收利息坏账准备 | C33: =C32+1 -> 29 | E33: 保险合同准备金* | F33: =F32+1 -> 150 | H33: 以摊余成本计量的金融资产终止确认收益（损失以“-”号填列） | I33: =I32+1 -> 29 | K33: 经营活动产生的现金流量净额 | L33: =L32+1 -> 29 | N33: 当期新增的使用权资产 | O33: =O32+1 -> 93 | R33: D19 | S33: =B33 -> 应收利息坏账准备
B34: 应收利息 | C34: =C33+1 -> 30 | E34: 流动负债合计 | F34: =F33+1 -> 151 | H34: 汇兑收益（损失以“-”号填列）* | I34: =I33+1 -> 30 | K34: 二、投资活动产生的现金流量 | L34: =L33+1 -> 30 | O34: =O33+1 -> 94 | S34: =B34 -> 应收利息
B35: 应收股利原值 | C35: =C34+1 -> 31 | E35: 非流动负债: | F35: =F34+1 -> 152 | H35: 净敞口套期收益（损失以“-”号填列） | I35: =I34+1 -> 31 | K35: 收回投资所收到的现金 | L35: =L34+1 -> 31 | O35: =O34+1 -> 95 | R35: D20 | S35: =B35 -> 应收股利原值
B36: 应收股利坏账准备 | C36: =C35+1 -> 32 | E36: 长期借款 | F36: =F35+1 -> 153 | H36: 公允价值变动收益（损失以“－”号填列） | I36: =I35+1 -> 32 | K36: 取得投资收益所收到的现金 | L36: =L35+1 -> 32 | N36: 3、现金及现金等价物净变动情况： | O36: =O35+1 -> 96 | R36: D21 | S36: =B36 -> 应收股利坏账准备
B37: 应收股利 | C37: =C36+1 -> 33 | E37: 应付债券 | F37: =F36+1 -> 154 | H37: 信用减值损失（损失以“-”号填列） | I37: =I36+1 -> 33 | K37: 处置固定资产、无形资产和其他长期资产而收到的现金净额 | L37: =L36+1 -> 33 | N37: 现金的期末余额 | O37: =O36+1 -> 97 | S37: =B37 -> 应收股利
B38: 其他应收款原值 | C38: =C37+1 -> 34 | E38: 其中：优先股 | F38: =F37+1 -> 155 | H38: 资产减值损失（损失以“-”号填列） | I38: =I37+1 -> 34 | K38: 处置子公司及其他营业单位收到的现金净额 | L38: =L37+1 -> 34 | N38: 减：现金的期初余额 | O38: =O37+1 -> 98 | R38: D22 | S38: =B38 -> 其他应收款原值
B39: 其他应收款坏账准备 | C39: =C38+1 -> 35 | E39: 永续债 | F39: =F38+1 -> 156 | H39: 资产处置收益（损失以“-”号填列） | I39: =I38+1 -> 35 | K39: 收到其他与投资活动有关的现金 | L39: =L38+1 -> 35 | N39: 加：现金等价物的期末余额 | O39: =O38+1 -> 99 | R39: D23 | S39: =B39 -> 其他应收款坏账准备
B40: 其他应收款 | C40: =C39+1 -> 36 | E40: 租赁负债 | F40: =F39+1 -> 157 | H40: 二、营业利润（亏损以“－”号填列） | I40: =I39+1 -> 36 | L40: =L39+1 -> 36 | N40: 减：现金等价物的期初余额 | O40: =O39+1 -> 100 | S40: =B40 -> 其他应收款
B41: 买入返售金融资产原值* | C41: =C40+1 -> 37 | E41: 长期应付款 | F41: =F40+1 -> 158 | H41: 加：营业外收入 | I41: =I40+1 -> 37 | K41: 投资活动现金流入小计 | L41: =L40+1 -> 37 | O41: =O40+1 -> 101 | R41: D24 | S41: =B41 -> 买入返售金融资产原值*
B42: 买入返售金融资产减值准备* | C42: =C41+1 -> 38 | E42: 专项应付款 | F42: =F41+1 -> 159 | H42: 其中：政府补助 | I42: =I41+1 -> 38 | K42: 购置固定资产、无形资产和其他长期资产所支付现金 | L42: =L41+1 -> 38 | O42: =O41+1 -> 102 | R42: D25 | S42: =B42 -> 买入返售金融资产减值准备*
B43: 买入返售金融资产* | C43: =C42+1 -> 39 | E43: 长期应付职工薪酬 | F43: =F42+1 -> 160 | H43: 减：营业外支出 | I43: =I42+1 -> 39 | K43: 投资所支付的现金 | L43: =L42+1 -> 39 | N43: 现金及现金等价物净增加额 | O43: =O42+1 -> 103 | S43: =B43 -> 买入返售金融资产*
B44: 存货原值 | C44: =C43+1 -> 40 | E44: 预计负债 | F44: =F43+1 -> 161 | H44: 三、利润总额（亏损总额以“－”号填列） | I44: =I43+1 -> 40 | K44: 质押贷款净增加额* | L44: =L43+1 -> 40 | R44: D26 | S44: =B44 -> 存货原值
B45: 存货跌价准备 | C45: =C44+1 -> 41 | E45: 递延收益 | F45: =F44+1 -> 162 | H45: 减：所得税费用 | I45: =I44+1 -> 41 | K45: 取得子公司及其他营业单位支付的现金净额 | L45: =L44+1 -> 41 | R45: D27 | S45: =B45 -> 存货跌价准备
B46: 存货 | C46: =C45+1 -> 42 | E46: 递延所得税负债 | F46: =F45+1 -> 163 | H46: 四、净利润（净亏损以“－”号填列） | I46: =I45+1 -> 42 | K46: 支付其他与投资活动有关的现金 | L46: =L45+1 -> 42 | S46: =B46 -> 存货
B47: 其中：原材料 | C47: =C46+1 -> 43 | E47: 其他非流动负债 | F47: =F46+1 -> 164 | H47: 同一控制下企业合并的被合并方在合并前实现的净利润 | I47: =I46+1 -> 43 | L47: =L46+1 -> 43 | R47: D27-1 | S47: =B47 -> 其中：原材料
B48: 库存商品（产成品） | C48: =C47+1 -> 44 | E48: 其中：特准储备基金 | F48: =F47+1 -> 165 | H48: （一）按经营持续性分类 | I48: =I47+1 -> 44 | K48: 投资活动现金流出小计 | L48: =L47+1 -> 44 | R48: D27-2 | S48: =B48 -> 库存商品（产成品）
B49: 合同资产原值 | C49: =C48+1 -> 45 | E49: 非流动负债合计 | F49: =F48+1 -> 166 | H49: 其中：持续经营净利润（净亏损以“-”号填列） | I49: =I48+1 -> 45 | K49: 投资活动产生的现金流量净额 | L49: =L48+1 -> 45 | R49: D28 | S49: =B49 -> 合同资产原值
B50: 合同资产减值准备 | C50: =C49+1 -> 46 | E50: 负 债 合 计 | F50: =F49+1 -> 167 | H50: 终止经营净利润（净亏损以“-”号填列） | I50: =I49+1 -> 46 | K50: 三、筹资活动产生的现金流量 | L50: =L49+1 -> 46 | R50: D29 | S50: =B50 -> 合同资产减值准备
B51: 合同资产 | C51: =C50+1 -> 47 | E51: =IF([2]说明!E28="股份有限公司","股东权益：",IF([2]说明!E28="非股份有限公司","所有者权益：","")) -> 股东权益： | F51: =F50+1 -> 168 | H51: （二）按所有权归属分类 | I51: =I50+1 -> 47 | K51: 吸收投资所收到的现金 | L51: =L50+1 -> 47 | S51: =B51 -> 合同资产
B52: 持有待售资产原值 | C52: =C51+1 -> 48 | E52: 实收资本（或股本） | F52: =F51+1 -> 169 | H52: 其中：归属于母公司所有者（或股东）的净利润（净亏损以“-”号填列） | I52: =I51+1 -> 48 | K52: 其中：子公司吸收少数股东投资收到的现金 | L52: =L51+1 -> 48 | R52: D30 | S52: =B52 -> 持有待售资产原值
B53: 持有待售资产减值准备 | C53: =C52+1 -> 49 | E53: 其他权益工具 | F53: =F52+1 -> 170 | H53: 少数股东损益（净亏损以“-”号填列） | I53: =I52+1 -> 49 | K53: 取得借款收到的现金 | L53: =L52+1 -> 49 | R53: D31 | S53: =B53 -> 持有待售资产减值准备
B54: 持有待售资产 | C54: =C53+1 -> 50 | E54: 其中：优先股 | F54: =F53+1 -> 171 | H54: 五、其他综合收益的税后净额 | I54: =I53+1 -> 50 | K54: 发行债券收到的现金 | L54: =L53+1 -> 50 | S54: =B54 -> 持有待售资产
B55: 一年内到期的非流动资产 | C55: =C54+1 -> 51 | E55: 永续债 | F55: =F54+1 -> 172 | H55: 归属于母公司所有者（或股东）的其他综合收益的税后净额 | I55: =I54+1 -> 51 | K55: 收到的其他与筹资活动有关的现金 | L55: =L54+1 -> 51 | R55: D32 | S55: =B55 -> 一年内到期的非流动资产
B56: 其他流动资产 | C56: =C55+1 -> 52 | E56: 资本公积 | F56: =F55+1 -> 173 | H56: （一）不能重分类进损益的其他综合收益 | I56: =I55+1 -> 52 | L56: =L55+1 -> 52 | R56: D33 | S56: =B56 -> 其他流动资产
B57: 流动资产合计 | C57: =C56+1 -> 53 | E57: 减：库存股 | F57: =F56+1 -> 174 | H57: 1.重新计量设定受益计划变动额 | I57: =I56+1 -> 53 | K57: 筹资活动现金流入小计 | L57: =L56+1 -> 53 | S57: =B57 -> 流动资产合计
B58: 非流动资产: | C58: =C57+1 -> 54 | E58: 其他综合收益 | F58: =F57+1 -> 175 | H58: 2.权益法下不能转损益的其他综合收益 | I58: =I57+1 -> 54 | K58: 偿还债务支付的现金 | L58: =L57+1 -> 54 | S58: =B58 -> 非流动资产:
B59: 发放贷款和垫款原值* | C59: =C58+1 -> 55 | E59: 专项储备 | F59: =F58+1 -> 176 | H59: 3.其他权益工具投资公允价值变动 | I59: =I58+1 -> 55 | K59: 分配股利、利润或偿付利息支付的现金 | L59: =L58+1 -> 55 | R59: D34 | S59: =B59 -> 发放贷款和垫款原值*
B60: 发放贷款和垫款减值准备* | C60: =C59+1 -> 56 | E60: 盈余公积 | F60: =F59+1 -> 177 | H60: 4.企业自身信用风险公允价值变动 | I60: =I59+1 -> 56 | K60: 其中：子公司支付给少数股东的股利、利润 | L60: =L59+1 -> 56 | R60: D35 | S60: =B60 -> 发放贷款和垫款减值准备*
B61: 发放贷款和垫款* | C61: =C60+1 -> 57 | E61: 一般风险准备* | F61: =F60+1 -> 178 | H61: 5.其他 | I61: =I60+1 -> 57 | K61: 支付其他与筹资活动有关的现金 | L61: =L60+1 -> 57 | S61: =B61 -> 发放贷款和垫款*
B62: 债权投资原值 | C62: =C61+1 -> 58 | E62: 未分配利润 | F62: =F61+1 -> 179 | H62: （二）将重分类进损益的其他综合收益 | I62: =I61+1 -> 58 | K62: 其中：子公司减资支付给少数股东的现金 | L62: =L61+1 -> 58 | R62: D36 | S62: =B62 -> 债权投资原值
B63: 债权投资减值准备 | C63: =C62+1 -> 59 | E63: 归属于母公司所有者权益（或股东权益）合计 | F63: =F62+1 -> 180 | H63: 1.权益法下可转损益的其他综合收益 | I63: =I62+1 -> 59 | K63: 筹资活动现金流出小计 | L63: =L62+1 -> 59 | R63: D37 | S63: =B63 -> 债权投资减值准备
B64: 债权投资 | C64: =C63+1 -> 60 | E64: 少数股东权益 | F64: =F63+1 -> 181 | H64: 2.其他债权投资公允价值变动 | I64: =I63+1 -> 60 | K64: 筹资活动产生的现金流量净额 | L64: =L63+1 -> 60 | S64: =B64 -> 债权投资
B65: 其他债权投资原值 | C65: =C64+1 -> 61 | E65: 所有者权益（或股东权益）合计 | F65: =F64+1 -> 182 | H65: 3.金融资产重分类计入其他综合收益的金额 | I65: =I64+1 -> 61 | K65: 四、汇率变动对现金及现金等价物的影响 | L65: =L64+1 -> 61 | R65: D38 | S65: =B65 -> 其他债权投资原值
B66: 其他债权投资减值准备 | C66: =C65+1 -> 62 | E66: 负债和所有者权益（或股东权益）总计 | F66: =F65+1 -> 183 | H66: 4.其他债权投资信用减值准备 | I66: =I65+1 -> 62 | K66: 五、现金及现金等价物净增加额 | L66: =L65+1 -> 62 | R66: D39 | S66: =B66 -> 其他债权投资减值准备
B67: 其他债权投资 | C67: =C66+1 -> 63 | H67: 5.现金流量套期储备 | I67: =I66+1 -> 63 | K67: 加：期初现金及现金等价物余额 | L67: =L66+1 -> 63 | S67: =B67 -> 其他债权投资
B68: 长期应收款原值 | C68: =C67+1 -> 64 | H68: 6.外币财务报表折算差额 | I68: =I67+1 -> 64 | K68: 六、期末现金及现金等价物余额 | L68: =L67+1 -> 64 | R68: D40 | S68: =B68 -> 长期应收款原值
B69: 长期应收款坏账准备 | C69: =C68+1 -> 65 | H69: 7.自用房地产或作为存货的房地产转换为以公允价值计量的投资性房地产在转换日公允价值大于账面价值部分 | I69: =I68+1 -> 65 | R69: D41 | S69: =B69 -> 长期应收款坏账准备
B70: 长期应收款 | C70: =C69+1 -> 66 | H70: 8.多次交易分步处置子公司股权构成一揽子交易的，丧失控制权之前各次交易处置价款与对应净资产账面价值份额的差额 | I70: =I69+1 -> 66 | S70: =B70 -> 长期应收款
B71: 设定受益计划净资产 | C71: =C70+1 -> 67 | H71: 9.其他 | I71: =I70+1 -> 67 | R71: D42 | S71: =B71 -> 设定受益计划净资产
B72: 长期股权投资原值 | C72: =C71+1 -> 68 | H72: 归属于少数股东的其他综合收益的税后净额 | I72: =I71+1 -> 68 | R72: D43 | S72: =B72 -> 长期股权投资原值
B73: 长期股权投资减值准备 | C73: =C72+1 -> 69 | H73: 六、综合收益总额 | I73: =I72+1 -> 69 | R73: D44 | S73: =B73 -> 长期股权投资减值准备
B74: 长期股权投资 | C74: =C73+1 -> 70 | H74: 归属于母公司所有者（或股东）的综合收益总额 | I74: =I73+1 -> 70 | S74: =B74 -> 长期股权投资
B75: 其他权益工具投资 | C75: =C74+1 -> 71 | H75: 归属于少数股东的综合收益总额 | I75: =I74+1 -> 71 | R75: D45 | S75: =B75 -> 其他权益工具投资
B76: 其他非流动金融资产 | C76: =C75+1 -> 72 | H76: 七、每股收益 | I76: =I75+1 -> 72 | R76: D46 | S76: =B76 -> 其他非流动金融资产
B77: 投资性房地产原值 | C77: =C76+1 -> 73 | H77: （一）基本每股收益 | I77: =I76+1 -> 73 | R77: D47 | S77: =B77 -> 投资性房地产原值
B78: 投资性房地产累计折旧 | C78: =C77+1 -> 74 | H78: （二）稀释每股收益 | I78: =I77+1 -> 74 | R78: D48 | S78: =B78 -> 投资性房地产累计折旧
B79: 投资性房地产净值 | C79: =C78+1 -> 75 | H79: 加：年初未分配利润 | I79: =I78+1 -> 75 | S79: =B79 -> 投资性房地产净值
B80: 投资性房地产减值准备 | C80: =C79+1 -> 76 | H80: 八、可供分配利润 | I80: =I79+1 -> 76 | R80: D49 | S80: =B80 -> 投资性房地产减值准备
B81: 投资性房地产 | C81: =C80+1 -> 77 | H81: 1、提取法定盈余公积 | I81: =I80+1 -> 77 | S81: =B81 -> 投资性房地产
B82: 固定资产原值 | C82: =C81+1 -> 78 | H82: 2、提取一般风险准备 | I82: =I81+1 -> 78 | R82: D50 | S82: =B82 -> 固定资产原值
B83: 固定资产累计折旧 | C83: =C82+1 -> 79 | H83: 3、提取其他 | I83: =I82+1 -> 79 | R83: D51 | S83: =B83 -> 固定资产累计折旧
B84: 固定资产净值 | C84: =C83+1 -> 80 | H84: 九、可供投资者分配的利润 | I84: =I83+1 -> 80 | S84: =B84 -> 固定资产净值
B85: 固定资产减值准备 | C85: =C84+1 -> 81 | H85: 1、应付优先股股利 | I85: =I84+1 -> 81 | R85: D52 | S85: =B85 -> 固定资产减值准备
B86: 固定资产 | C86: =C85+1 -> 82 | H86: 2、提取任意盈余公积 | I86: =I85+1 -> 82 | S86: =B86 -> 固定资产
B87: 固定资产清理 | C87: =C86+1 -> 83 | H87: 3、应付普通股股利（应付利润） | I87: =I86+1 -> 83 | R87: D53 | S87: =B87 -> 固定资产清理
B88: 在建工程原值 | C88: =C87+1 -> 84 | H88: 4、转作资本（或股本）的普通股股利 | I88: =I87+1 -> 84 | R88: D54 | S88: =B88 -> 在建工程原值
B89: 在建工程减值准备 | C89: =C88+1 -> 85 | H89: 5、其他 | I89: =I88+1 -> 85 | R89: D55 | S89: =B89 -> 在建工程减值准备
B90: 在建工程 | C90: =C89+1 -> 86 | H90: 十、未分配利润 | I90: =I89+1 -> 86 | S90: =B90 -> 在建工程
B91: 工程物资原值 | C91: =C90+1 -> 87 | R91: D56 | S91: =B91 -> 工程物资原值
B92: 工程物资减值准备 | C92: =C91+1 -> 88 | R92: D57 | S92: =B92 -> 工程物资减值准备
B93: 工程物资 | C93: =C92+1 -> 89 | S93: =B93 -> 工程物资
B94: 生产性生物资产原值 | C94: =C93+1 -> 90 | R94: D58 | S94: =B94 -> 生产性生物资产原值
B95: 生产性生物资产累计折旧 | C95: =C94+1 -> 91 | R95: D59 | S95: =B95 -> 生产性生物资产累计折旧
B96: 生产性生物资产净值 | C96: =C95+1 -> 92 | S96: =B96 -> 生产性生物资产净值
B97: 生产性生物资产减值准备 | C97: =C96+1 -> 93 | R97: D60 | S97: =B97 -> 生产性生物资产减值准备
B98: 生产性生物资产 | C98: =C97+1 -> 94 | S98: =B98 -> 生产性生物资产
B99: 油气资产原值 | C99: =C98+1 -> 95 | R99: D61 | S99: =B99 -> 油气资产原值
B100: 油气资产累计折旧 | C100: =C99+1 -> 96 | R100: D62 | S100: =B100 -> 油气资产累计折旧
...

Sheet 试算
A1: 致同会计师事务所
A2: 试算平衡表
A3: 编制单位： | C3: 编制： | D3: 日期： | E3: 索引： | F3: A2-2
A4: 截止/期间： | C4: 复核： | D4: 日期： | E4: 页次：
B5: =IF(ROUND(B121-B167,2)=0,"",ROUND(B121-B167,2)) | C5: =IF(ROUND(C121-C167,2)=0,"",ROUND(C121-C167,2)) | D5: =IF(ROUND(D121-D167,2)=0,"",ROUND(D121-D167,2)) | E5: =IF(ROUND(E121-E167,2)=0,"",ROUND(E121-E167,2)) | F5: =IF(ROUND(F121-F167,2)=0,"",ROUND(F121-F167,2))
A6: =IF(SUM(B6:F6)=0,"","现金流量不平") | B6: =IF(AND(ROUND(B232-B282,2)=0,ROUND(B261-B292,2)<>0),ROUND(B261-B292,2),IF(AND(ROUND(B232-B282,2)<>0,ROUND(B261-B292,2)=0),ROUND(B232-B282,2),IF(AND(ROUND(B232-B282,2)<>0,ROUND(B261-B292,2)),ROUND(B261-B292,2),""))) | C6: =IF(AND(ROUND(C232-C282,2)=0,ROUND(C261-C292,2)<>0),ROUND(C261-C292,2),IF(AND(ROUND(C232-C282,2)<>0,ROUND(C261-C292,2)=0),ROUND(C232-C282,2),IF(AND(ROUND(C232-C282,2)<>0,ROUND(C261-C292,2)),ROUND(C261-C292,2),""))) | D6: =IF(AND(ROUND(D232-D282,2)=0,ROUND(D261-D292,2)<>0),ROUND(D261-D292,2),IF(AND(ROUND(D232-D282,2)<>0,ROUND(D261-D292,2)=0),ROUND(D232-D282,2),IF(AND(ROUND(D232-D282,2)<>0,ROUND(D261-D292,2)),ROUND(D261-D292,2),""))) | E6: =IF(AND(ROUND(E232-E282,2)=0,ROUND(E261-E292,2)<>0),ROUND(E261-E292,2),IF(AND(ROUND(E232-E282,2)<>0,ROUND(E261-E292,2)=0),ROUND(E232-E282,2),IF(AND(ROUND(E232-E282,2)<>0,ROUND(E261-E292,2)),ROUND(E261-E292,2),""))) | F6: =IF(AND(ROUND(F232-F282,2)=0,ROUND(F261-F292,2)<>0),ROUND(F261-F292,2),IF(AND(ROUND(F232-F282,2)<>0,ROUND(F261-F292,2)=0),ROUND(F232-F282,2),IF(AND(ROUND(F232-F282,2)<>0,ROUND(F261-F292,2)),ROUND(F261-F292,2),"")))
A7: 项目 | B7: 未审 | C7: 调账 | D7: 重分类 | E7: 其他 | F7: 审定
A8: 流动资产：
A9: 货币资金 | B9: 1.2884156e+08 | C9: =SUMPRODUCT(([3]分录!$D$7:$D$100=$A9)*INT((([3]分录!$C$7:$C$100="借：")-0.5)*2)*([3]分录!$I$7:$I$100=C$7)*([3]分录!$H$7:$H$100)) -> 0 | D9: =SUMPRODUCT(([3]分录!$D$7:$D$100=$A9)*INT((([3]分录!$C$7:$C$100="借：")-0.5)*2)*([3]分录!$I$7:$I$100=D$7)*([3]分录!$H$7:$H$100)) -> 0 | E9: =SUMPRODUCT(([3]分录!$D$7:$D$100=$A9)*INT((([3]分录!$C$7:$C$100="借：")-0.5)*2)*([3]分录!$I$7:$I$100=E$7)*([3]分录!$H$7:$H$100)) -> 0 | F9: =ROUND(SUM(B9:E9),2) -> 1.2884156e+08
A10: 交易性金融资产 | B10: 1.0338995e+10 | C10: =SUMPRODUCT(([3]分录!$D$7:$D$100=$A10)*INT((([3]分录!$C$7:$C$100="借：")-0.5)*2)*([3]分录!$I$7:$I$100=C$7)*([3]分录!$H$7:$H$100)) -> 0 | D10: =SUMPRODUCT(([3]分录!$D$7:$D$100=$A10)*INT((([3]分录!$C$7:$C$100="借：")-0.5)*2)*([3]分录!$I$7:$I$100=D$7)*([3]分录!$H$7:$H$100)) -> 0 | E10: =SUMPRODUCT(([3]分录!$D$7:$D$100=$A10)*INT((([3]分录!$C$7:$C$100="借：")-0.5)*2)*([3]分录!$I$7:$I$100=E$7)*([3]分录!$H$7:$H$100)) -> 0 | F10: =ROUND(SUM(B10:E10),2) -> 1.0338995e+10
A11: 以公允价值计量且其变动计入当期损益的金融资产 | B11: 0 | C11: =SUMPRODUCT(([3]分录!$D$7:$D$100=$A11)*INT((([3]分录!$C$7:$C$100="借：")-0.5)*2)*([3]分录!$I$7:$I$100=C$7)*([3]分录!$H$7:$H$100)) -> 0 | D11: =SUMPRODUCT(([3]分录!$D$7:$D$100=$A11)*INT((([3]分录!$C$7:$C$100="借：")-0.5)*2)*([3]分录!$I$7:$I$100=D$7)*([3]分录!$H$7:$H$100)) -> 0 | E11: =SUMPRODUCT(([3]分录!$D$7:$D$100=$A11)*INT((([3]分录!$C$7:$C$100="借：")-0.5)*2)*([3]分录!$I$7:$I$100=E$7)*([3]分录!$H$7:$H$100)) -> 0 | F11: =ROUND(SUM(B11:E11),2) -> 0
A12: 衍生金融资产 | B12: 0 | C12: =SUMPRODUCT(([3]分录!$D$7:$D$100=$A12)*INT((([3]分录!$C$7:$C$100="借：")-0.5)*2)*([3]分录!$I$7:$I$100=C$7)*([3]分录!$H$7:$H$100)) -> 0 | D12: =SUMPRODUCT(([3]分录!$D$7:$D$100=$A12)*INT((([3]分录!$C$7:$C$100="借：")-0.5)*2)*([3]分录!$I$7:$I$100=D$7)*([3]分录!$H$7:$H$100)) -> 0 | E12: =SUMPRODUCT(([3]分录!$D$7:$D$100=$A12)*INT((([3]分录!$C$7:$C$100="借：")-0.5)*2)*([3]分录!$I$7:$I$100=E$7)*([3]分录!$H$7:$H$100)) -> 0 | F12: =ROUND(SUM(B12:E12),2) -> 0
A13: 应收票据原值 | B13: 0 | C13: =SUMPRODUCT(([3]分录!$D$7:$D$100=$A13)*INT((([3]分录!$C$7:$C$100="借：")-0.5)*2)*([3]分录!$I$7:$I$100=C$7)*([3]分录!$H$7:$H$100)) -> 0 | D13: =SUMPRODUCT(([3]分录!$D$7:$D$100=$A13)*INT((([3]分录!$C$7:$C$100="借：")-0.5)*2)*([3]分录!$I$7:$I$100=D$7)*([3]分录!$H$7:$H$100)) -> 0 | E13: =SUMPRODUCT(([3]分录!$D$7:$D$100=$A13)*INT((([3]分录!$C$7:$C$100="借：")-0.5)*2)*([3]分录!$I$7:$I$100=E$7)*([3]分录!$H$7:$H$100)) -> 0 | F13: =ROUND(SUM(B13:E13),2) -> 0
A14: 应收票据坏账准备 | B14: 0 | C14: =-SUMPRODUCT(([3]分录!$D$7:$D$100=$A14)*INT((([3]分录!$C$7:$C$100="借：")-0.5)*2)*([3]分录!$I$7:$I$100=C$7)*([3]分录!$H$7:$H$100)) -> 0 | D14: =-SUMPRODUCT(([3]分录!$D$7:$D$100=$A14)*INT((([3]分录!$C$7:$C$100="借：")-0.5)*2)*([3]分录!$I$7:$I$100=D$7)*([3]分录!$H$7:$H$100)) -> 0 | E14: =-SUMPRODUCT(([3]分录!$D$7:$D$100=$A14)*INT((([3]分录!$C$7:$C$100="借：")-0.5)*2)*([3]分录!$I$7:$I$100=E$7)*([3]分录!$H$7:$H$100)) -> 0 | F14: =ROUND(SUM(B14:E14),2) -> 0
A15: 应收票据 | B15: 0 | C15: =C13-C14 -> 0 | D15: =D13-D14 -> 0 | E15: =E13-E14 -> 0 | F15: =ROUND(SUM(B15:E15),2) -> 0
A16: 应收账款原值 | B16: 0 | C16: =SUMPRODUCT(([3]分录!$D$7:$D$100=$A16)*INT((([3]分录!$C$7:$C$100="借：")-0.5)*2)*([3]分录!$I$7:$I$100=C$7)*([3]分录!$H$7:$H$100)) -> 0 | D16: =SUMPRODUCT(([3]分录!$D$7:$D$100=$A16)*INT((([3]分录!$C$7:$C$100="借：")-0.5)*2)*([3]分录!$I$7:$I$100=D$7)*([3]分录!$H$7:$H$100)) -> 0 | E16: =SUMPRODUCT(([3]分录!$D$7:$D$100=$A16)*INT((([3]分录!$C$7:$C$100="借：")-0.5)*2)*([3]分录!$I$7:$I$100=E$7)*([3]分录!$H$7:$H$100)) -> 0 | F16: =ROUND(SUM(B16:E16),2) -> 0
A17: 应收账款坏账准备 | B17: 0 | C17: =-SUMPRODUCT(([3]分录!$D$7:$D$100=$A17)*INT((([3]分录!$C$7:$C$100="借：")-0.5)*2)*([3]分录!$I$7:$I$100=C$7)*([3]分录!$H$7:$H$100)) -> -1807111.9 | D17: =-SUMPRODUCT(([3]分录!$D$7:$D$100=$A17)*INT((([3]分录!$C$7:$C$100="借：")-0.5)*2)*([3]分录!$I$7:$I$100=D$7)*([3]分录!$H$7:$H$100)) -> 0 | E17: =-SUMPRODUCT(([3]分录!$D$7:$D$100=$A17)*INT((([3]分录!$C$7:$C$100="借：")-0.5)*2)*([3]分录!$I$7:$I$100=E$7)*([3]分录!$H$7:$H$100)) -> 0 | F17: =ROUND(SUM(B17:E17),2) -> -1807111.9
A18: 应收账款 | B18: 0 | C18: =C16-C17 -> 1807111.9 | D18: =D16-D17 -> 0 | E18: =E16-E17 -> 0 | F18: =ROUND(SUM(B18:E18),2) -> 1807111.9
A19: 应收款项融资原值 | B19: 0 | C19: =SUMPRODUCT(([3]分录!$D$7:$D$100=$A19)*INT((([3]分录!$C$7:$C$100="借：")-0.5)*2)*([3]分录!$I$7:$I$100=C$7)*([3]分录!$H$7:$H$100)) -> 0 | D19: =SUMPRODUCT(([3]分录!$D$7:$D$100=$A19)*INT((([3]分录!$C$7:$C$100="借：")-0.5)*2)*([3]分录!$I$7:$I$100=D$7)*([3]分录!$H$7:$H$100)) -> 0 | E19: =SUMPRODUCT(([3]分录!$D$7:$D$100=$A19)*INT((([3]分录!$C$7:$C$100="借：")-0.5)*2)*([3]分录!$I$7:$I$100=E$7)*([3]分录!$H$7:$H$100)) -> 0 | F19: =ROUND(SUM(B19:E19),2) -> 0
A20: 应收款项融资坏账准备 | B20: 0 | C20: =-SUMPRODUCT(([3]分录!$D$7:$D$100=$A20)*INT((([3]分录!$C$7:$C$100="借：")-0.5)*2)*([3]分录!$I$7:$I$100=C$7)*([3]分录!$H$7:$H$100)) -> 0 | D20: =-SUMPRODUCT(([3]分录!$D$7:$D$100=$A20)*INT((([3]分录!$C$7:$C$100="借：")-0.5)*2)*([3]分录!$I$7:$I$100=D$7)*([3]分录!$H$7:$H$100)) -> 0 | E20: =-SUMPRODUCT(([3]分录!$D$7:$D$100=$A20)*INT((([3]分录!$C$7:$C$100="借：")-0.5)*2)*([3]分录!$I$7:$I$100=E$7)*([3]分录!$H$7:$H$100)) -> 0 | F20: =ROUND(SUM(B20:E20),2) -> 0
A21: 应收款项融资 | B21: 0 | C21: =C19-C20 -> 0 | D21: =D19-D20 -> 0 | E21: =E19-E20 -> 0 | F21: =ROUND(SUM(B21:E21),2) -> 0
A22: 预付款项原值 | B22: 0 | C22: =SUMPRODUCT(([3]分录!$D$7:$D$100=$A22)*INT((([3]分录!$C$7:$C$100="借：")-0.5)*2)*([3]分录!$I$7:$I$100=C$7)*([3]分录!$H$7:$H$100)) -> 0 | D22: =SUMPRODUCT(([3]分录!$D$7:$D$100=$A22)*INT((([3]分录!$C$7:$C$100="借：")-0.5)*2)*([3]分录!$I$7:$I$100=D$7)*([3]分录!$H$7:$H$100)) -> 0 | E22: =SUMPRODUCT(([3]分录!$D$7:$D$100=$A22)*INT((([3]分录!$C$7:$C$100="借：")-0.5)*2)*([3]分录!$I$7:$I$100=E$7)*([3]分录!$H$7:$H$100)) -> 0 | F22: =ROUND(SUM(B22:E22),2) -> 0
A23: 预付款项坏账准备 | B23: 0 | C23: =-SUMPRODUCT(([3]分录!$D$7:$D$100=$A23)*INT((([3]分录!$C$7:$C$100="借：")-0.5)*2)*([3]分录!$I$7:$I$100=C$7)*([3]分录!$H$7:$H$100)) -> 0 | D23: =-SUMPRODUCT(([3]分录!$D$7:$D$100=$A23)*INT((([3]分录!$C$7:$C$100="借：")-0.5)*2)*([3]分录!$I$7:$I$100=D$7)*([3]分录!$H$7:$H$100)) -> 0 | E23: =-SUMPRODUCT(([3]分录!$D$7:$D$100=$A23)*INT((([3]分录!$C$7:$C$100="借：")-0.5)*2)*([3]分录!$I$7:$I$100=E$7)*([3]分录!$H$7:$H$100)) -> 0 | F23: =ROUND(SUM(B23:E23),2) -> 0
A24: 预付款项 | B24: 0 | C24: =C22-C23 -> 0 | D24: =D22-D23 -> 0 | E24: =E22-E23 -> 0 | F24: =ROUND(SUM(B24:E24),2) -> 0
A25: 应收利息原值 | B25: 0 | C25: =SUMPRODUCT(([3]分录!$D$7:$D$100=$A25)*INT((([3]分录!$C$7:$C$100="借：")-0.5)*2)*([3]分录!$I$7:$I$100=C$7)*([3]分录!$H$7:$H$100)) -> 0 | D25: =SUMPRODUCT(([3]分录!$D$7:$D$100=$A25)*INT((([3]分录!$C$7:$C$100="借：")-0.5)*2)*([3]分录!$I$7:$I$100=D$7)*([3]分录!$H$7:$H$100)) -> 0 | E25: =SUMPRODUCT(([3]分录!$D$7:$D$100=$A25)*INT((([3]分录!$C$7:$C$100="借：")-0.5)*2)*([3]分录!$I$7:$I$100=E$7)*([3]分录!$H$7:$H$100)) -> 0 | F25: =ROUND(SUM(B25:E25),2) -> 0
A26: 应收利息坏账准备 | B26: 0 | C26: =-SUMPRODUCT(([3]分录!$D$7:$D$100=$A26)*INT((([3]分录!$C$7:$C$100="借：")-0.5)*2)*([3]分录!$I$7:$I$100=C$7)*([3]分录!$H$7:$H$100)) -> 0 | D26: =-SUMPRODUCT(([3]分录!$D$7:$D$100=$A26)*INT((([3]分录!$C$7:$C$100="借：")-0.5)*2)*([3]分录!$I$7:$I$100=D$7)*([3]分录!$H$7:$H$100)) -> 0 | E26: =-SUMPRODUCT(([3]分录!$D$7:$D$100=$A26)*INT((([3]分录!$C$7:$C$100="借：")-0.5)*2)*([3]分录!$I$7:$I$100=E$7)*([3]分录!$H$7:$H$100)) -> 0 | F26: =ROUND(SUM(B26:E26),2) -> 0
A27: 应收利息 | B27: 0 | C27: =C25-C26 -> 0 | D27: =D25-D26 -> 0 | E27: =E25-E26 -> 0 | F27: =ROUND(SUM(B27:E27),2) -> 0
A28: 应收股利原值 | B28: 0 | C28: =SUMPRODUCT(([3]分录!$D$7:$D$100=$A28)*INT((([3]分录!$C$7:$C$100="借：")-0.5)*2)*([3]分录!$I$7:$I$100=C$7)*([3]分录!$H$7:$H$100)) -> 0 | D28: =SUMPRODUCT(([3]分录!$D$7:$D$100=$A28)*INT((([3]分录!$C$7:$C$100="借：")-0.5)*2)*([3]分录!$I$7:$I$100=D$7)*([3]分录!$H$7:$H$100)) -> 0 | E28: =SUMPRODUCT(([3]分录!$D$7:$D$100=$A28)*INT((([3]分录!$C$7:$C$100="借：")-0.5)*2)*([3]分录!$I$7:$I$100=E$7)*([3]分录!$H$7:$H$100)) -> 0 | F28: =ROUND(SUM(B28:E28),2) -> 0
A29: 应收股利坏账准备 | B29: 0 | C29: =-SUMPRODUCT(([3]分录!$D$7:$D$100=$A29)*INT((([3]分录!$C$7:$C$100="借：")-0.5)*2)*([3]分录!$I$7:$I$100=C$7)*([3]分录!$H$7:$H$100)) -> 0 | D29: =-SUMPRODUCT(([3]分录!$D$7:$D$100=$A29)*INT((([3]分录!$C$7:$C$100="借：")-0.5)*2)*([3]分录!$I$7:$I$100=D$7)*([3]分录!$H$7:$H$100)) -> 0 | E29: =-SUMPRODUCT(([3]分录!$D$7:$D$100=$A29)*INT((([3]分录!$C$7:$C$100="借：")-0.5)*2)*([3]分录!$I$7:$I$100=E$7)*([3]分录!$H$7:$H$100)) -> 0 | F29: =ROUND(SUM(B29:E29),2) -> 0
A30: 应收股利 | B30: 0 | C30: =C28-C29 -> 0 | D30: =D28-D29 -> 0 | E30: =E28-E29 -> 0 | F30: =ROUND(SUM(B30:E30),2) -> 0
A31: 其他应收款原值 | B31: 0 | C31: =SUMPRODUCT(([3]分录!$D$7:$D$100=$A31)*INT((([3]分录!$C$7:$C$100="借：")-0.5)*2)*([3]分录!$I$7:$I$100=C$7)*([3]分录!$H$7:$H$100)) -> 0 | D31: =SUMPRODUCT(([3]分录!$D$7:$D$100=$A31)*INT((([3]分录!$C$7:$C$100="借：")-0.5)*2)*([3]分录!$I$7:$I$100=D$7)*([3]分录!$H$7:$H$100)) -> 0 | E31: =SUMPRODUCT(([3]分录!$D$7:$D$100=$A31)*INT((([3]分录!$C$7:$C$100="借：")-0.5)*2)*([3]分录!$I$7:$I$100=E$7)*([3]分录!$H$7:$H$100)) -> 0 | F31: =ROUND(SUM(B31:E31),2) -> 0
A32: 其他应收款坏账准备 | B32: 0 | C32: =-SUMPRODUCT(([3]分录!$D$7:$D$100=$A32)*INT((([3]分录!$C$7:$C$100="借：")-0.5)*2)*([3]分录!$I$7:$I$100=C$7)*([3]分录!$H$7:$H$100)) -> 2276.74 | D32: =-SUMPRODUCT(([3]分录!$D$7:$D$100=$A32)*INT((([3]分录!$C$7:$C$100="借：")-0.5)*2)*([3]分录!$I$7:$I$100=D$7)*([3]分录!$H$7:$H$100)) -> 0 | E32: =-SUMPRODUCT(([3]分录!$D$7:$D$100=$A32)*INT((([3]分录!$C$7:$C$100="借：")-0.5)*2)*([3]分录!$I$7:$I$100=E$7)*([3]分录!$H$7:$H$100)) -> 0 | F32: =ROUND(SUM(B32:E32),2) -> 2276.74
A33: 其他应收款 | B33: 0 | C33: =C31-C32 -> -2276.74 | D33: =D31-D32 -> 0 | E33: =E31-E32 -> 0 | F33: =ROUND(SUM(B33:E33),2) -> -2276.74
A34: 存货原值 | B34: 4.0768702e+08 | C34: =SUMPRODUCT(([3]分录!$D$7:$D$100=$A34)*INT((([3]分录!$C$7:$C$100="借：")-0.5)*2)*([3]分录!$I$7:$I$100=C$7)*([3]分录!$H$7:$H$100)) -> 0 | D34: =SUMPRODUCT(([3]分录!$D$7:$D$100=$A34)*INT((([3]分录!$C$7:$C$100="借：")-0.5)*2)*([3]分录!$I$7:$I$100=D$7)*([3]分录!$H$7:$H$100)) -> 0 | E34: =SUMPRODUCT(([3]分录!$D$7:$D$100=$A34)*INT((([3]分录!$C$7:$C$100="借：")-0.5)*2)*([3]分录!$I$7:$I$100=E$7)*([3]分录!$H$7:$H$100)) -> 0 | F34: =ROUND(SUM(B34:E34),2) -> 4.0768702e+08
A35: 存货跌价准备 | B35: 0 | C35: =-SUMPRODUCT(([3]分录!$D$7:$D$100=$A35)*INT((([3]分录!$C$7:$C$100="借：")-0.5)*2)*([3]分录!$I$7:$I$100=C$7)*([3]分录!$H$7:$H$100)) -> 0 | D35: =-SUMPRODUCT(([3]分录!$D$7:$D$100=$A35)*INT((([3]分录!$C$7:$C$100="借：")-0.5)*2)*([3]分录!$I$7:$I$100=D$7)*([3]分录!$H$7:$H$100)) -> 0 | E35: =-SUMPRODUCT(([3]分录!$D$7:$D$100=$A35)*INT((([3]分录!$C$7:$C$100="借：")-0.5)*2)*([3]分录!$I$7:$I$100=E$7)*([3]分录!$H$7:$H$100)) -> 0 | F35: =ROUND(SUM(B35:E35),2) -> 0
A36: 存货 | B36: 0 | C36: =C34-C35 -> 0 | D36: =D34-D35 -> 0 | E36: =E34-E35 -> 0 | F36: =ROUND(SUM(B36:E36),2) -> 0
A37: 合同资产原值 | B37: 0 | C37: =SUMPRODUCT(([3]分录!$D$7:$D$100=$A37)*INT((([3]分录!$C$7:$C$100="借：")-0.5)*2)*([3]分录!$I$7:$I$100=C$7)*([3]分录!$H$7:$H$100)) -> 0 | D37: =SUMPRODUCT(([3]分录!$D$7:$D$100=$A37)*INT((([3]分录!$C$7:$C$100="借：")-0.5)*2)*([3]分录!$I$7:$I$100=D$7)*([3]分录!$H$7:$H$100)) -> 0 | E37: =SUMPRODUCT(([3]分录!$D$7:$D$100=$A37)*INT((([3]分录!$C$7:$C$100="借：")-0.5)*2)*([3]分录!$I$7:$I$100=E$7)*([3]分录!$H$7:$H$100)) -> 0 | F37: =ROUND(SUM(B37:E37),2) -> 0
A38: 合同资产减值准备 | B38: 0 | C38: =-SUMPRODUCT(([3]分录!$D$7:$D$100=$A38)*INT((([3]分录!$C$7:$C$100="借：")-0.5)*2)*([3]分录!$I$7:$I$100=C$7)*([3]分录!$H$7:$H$100)) -> 0 | D38: =-SUMPRODUCT(([3]分录!$D$7:$D$100=$A38)*INT((([3]分录!$C$7:$C$100="借：")-0.5)*2)*([3]分录!$I$7:$I$100=D$7)*([3]分录!$H$7:$H$100)) -> 0 | E38: =-SUMPRODUCT(([3]分录!$D$7:$D$100=$A38)*INT((([3]分录!$C$7:$C$100="借：")-0.5)*2)*([3]分录!$I$7:$I$100=E$7)*([3]分录!$H$7:$H$100)) -> 0 | F38: =ROUND(SUM(B38:E38),2) -> 0
A39: 合同资产 | B39: 0 | C39: =C37-C38 -> 0 | D39: =D37-D38 -> 0 | E39: =E37-E38 -> 0 | F39: =ROUND(SUM(B39:E39),2) -> 0
A40: 持有待售资产原值 | B40: 0 | C40: =SUMPRODUCT(([3]分录!$D$7:$D$100=$A40)*INT((([3]分录!$C$7:$C$100="借：")-0.5)*2)*([3]分录!$I$7:$I$100=C$7)*([3]分录!$H$7:$H$100)) -> 0 | D40: =SUMPRODUCT(([3]分录!$D$7:$D$100=$A40)*INT((([3]分录!$C$7:$C$100="借：")-0.5)*2)*([3]分录!$I$7:$I$100=D$7)*([3]分录!$H$7:$H$100)) -> 0 | E40: =SUMPRODUCT(([3]分录!$D$7:$D$100=$A40)*INT((([3]分录!$C$7:$C$100="借：")-0.5)*2)*([3]分录!$I$7:$I$100=E$7)*([3]分录!$H$7:$H$100)) -> 0 | F40: =ROUND(SUM(B40:E40),2) -> 0
A41: 持有待售资产减值准备 | B41: 0 | C41: =-SUMPRODUCT(([3]分录!$D$7:$D$100=$A41)*INT((([3]分录!$C$7:$C$100="借：")-0.5)*2)*([3]分录!$I$7:$I$100=C$7)*([3]分录!$H$7:$H$100)) -> 0 | D41: =-SUMPRODUCT(([3]分录!$D$7:$D$100=$A41)*INT((([3]分录!$C$7:$C$100="借：")-0.5)*2)*([3]分录!$I$7:$I$100=D$7)*([3]分录!$H$7:$H$100)) -> 0 | E41: =-SUMPRODUCT(([3]分录!$D$7:$D$100=$A41)*INT((([3]分录!$C$7:$C$100="借：")-0.5)*2)*([3]分录!$I$7:$I$100=E$7)*([3]分录!$H$7:$H$100)) -> 0 | F41: =ROUND(SUM(B41:E41),2) -> 0
A42: 持有待售资产 | B42: 0 | C42: =C40-C41 -> 0 | D42: =D40-D41 -> 0 | E42: =E40-E41 -> 0 | F42: =ROUND(SUM(B42:E42),2) -> 0
A43: 一年内到期的非流动资产 | B43: 0 | C43: =SUMPRODUCT(([3]分录!$D$7:$D$100=$A43)*INT((([3]分录!$C$7:$C$100="借：")-0.5)*2)*([3]分录!$I$7:$I$100=C$7)*([3]分录!$H$7:$H$100)) -> 0 | D43: =SUMPRODUCT(([3]分录!$D$7:$D$100=$A43)*INT((([3]分录!$C$7:$C$100="借：")-0.5)*2)*([3]分录!$I$7:$I$100=D$7)*([3]分录!$H$7:$H$100)) -> 0 | E43: =SUMPRODUCT(([3]分录!$D$7:$D$100=$A43)*INT((([3]分录!$C$7:$C$100="借：")-0.5)*2)*([3]分录!$I$7:$I$100=E$7)*([3]分录!$H$7:$H$100)) -> 0 | F43: =ROUND(SUM(B43:E43),2) -> 0
A44: 其他流动资产 | B44: 0 | C44: =SUMPRODUCT(([3]分录!$D$7:$D$100=$A44)*INT((([3]分录!$C$7:$C$100="借：")-0.5)*2)*([3]分录!$I$7:$I$100=C$7)*([3]分录!$H$7:$H$100)) -> 0 | D44: =SUMPRODUCT(([3]分录!$D$7:$D$100=$A44)*INT((([3]分录!$C$7:$C$100="借：")-0.5)*2)*([3]分录!$I$7:$I$100=D$7)*([3]分录!$H$7:$H$100)) -> 0 | E44: =SUMPRODUCT(([3]分录!$D$7:$D$100=$A44)*INT((([3]分录!$C$7:$C$100="借：")-0.5)*2)*([3]分录!$I$7:$I$100=E$7)*([3]分录!$H$7:$H$100)) -> 0 | F44: =ROUND(SUM(B44:E44),2) -> 0
A45: 流动资产合计 | B45: 0 | C45: =SUM(C9:C12,C15,C18,C21,C24,C27,C30,C33,C36,C39,C42,C43,C44) -> 1804835.2 | D45: =SUM(D9:D12,D15,D18,D21,D24,D27,D30,D33,D36,D39,D42,D43,D44) -> 0 | E45: =SUM(E9:E12,E15,E18,E21,E24,E27,E30,E33,E36,E39,E42,E43,E44) -> 0 | F45: =ROUND(SUM(B45:E45),2) -> 1804835.2
A46: 非流动资产： | B46: 0 | F46: =ROUND(SUM(B46:E46),2) -> 0
A47: 债权投资原值 | B47: 0 | C47: =SUMPRODUCT(([3]分录!$D$7:$D$100=$A47)*INT((([3]分录!$C$7:$C$100="借：")-0.5)*2)*([3]分录!$I$7:$I$100=C$7)*([3]分录!$H$7:$H$100)) -> 0 | D47: =SUMPRODUCT(([3]分录!$D$7:$D$100=$A47)*INT((([3]分录!$C$7:$C$100="借：")-0.5)*2)*([3]分录!$I$7:$I$100=D$7)*([3]分录!$H$7:$H$100)) -> 0 | E47: =SUMPRODUCT(([3]分录!$D$7:$D$100=$A47)*INT((([3]分录!$C$7:$C$100="借：")-0.5)*2)*([3]分录!$I$7:$I$100=E$7)*([3]分录!$H$7:$H$100)) -> 0 | F47: =ROUND(SUM(B47:E47),2) -> 0
A48: 债权投资减值准备 | B48: 0 | C48: =-SUMPRODUCT(([3]分录!$D$7:$D$100=$A48)*INT((([3]分录!$C$7:$C$100="借：")-0.5)*2)*([3]分录!$I$7:$I$100=C$7)*([3]分录!$H$7:$H$100)) -> 0 | D48: =-SUMPRODUCT(([3]分录!$D$7:$D$100=$A48)*INT((([3]分录!$C$7:$C$100="借：")-0.5)*2)*([3]分录!$I$7:$I$100=D$7)*([3]分录!$H$7:$H$100)) -> 0 | E48: =-SUMPRODUCT(([3]分录!$D$7:$D$100=$A48)*INT((([3]分录!$C$7:$C$100="借：")-0.5)*2)*([3]分录!$I$7:$I$100=E$7)*([3]分录!$H$7:$H$100)) -> 0 | F48: =ROUND(SUM(B48:E48),2) -> 0
A49: 债权投资 | B49: 0 | C49: =C47-C48 -> 0 | D49: =D47-D48 -> 0 | E49: =E47-E48 -> 0 | F49: =ROUND(SUM(B49:E49),2) -> 0
A50: 可供出售金融资产原值 | B50: 0
A51: 可供出售金融资产减值准备 | B51: 0
A52: 可供出售金融资产 | B52: 0 | C52: =C50-C51 -> 0 | D52: =D50-D51 -> 0 | E52: =E50-E51 -> 0
A53: 其他债权投资原值 | B53: 0 | C53: =SUMPRODUCT(([3]分录!$D$7:$D$100=$A53)*INT((([3]分录!$C$7:$C$100="借：")-0.5)*2)*([3]分录!$I$7:$I$100=C$7)*([3]分录!$H$7:$H$100)) -> 0 | D53: =SUMPRODUCT(([3]分录!$D$7:$D$100=$A53)*INT((([3]分录!$C$7:$C$100="借：")-0.5)*2)*([3]分录!$I$7:$I$100=D$7)*([3]分录!$H$7:$H$100)) -> 0 | E53: =SUMPRODUCT(([3]分录!$D$7:$D$100=$A53)*INT((([3]分录!$C$7:$C$100="借：")-0.5)*2)*([3]分录!$I$7:$I$100=E$7)*([3]分录!$H$7:$H$100)) -> 0 | F53: =ROUND(SUM(B53:E53),2) -> 0
A54: 其他债权投资减值准备 | B54: 0 | C54: =-SUMPRODUCT(([3]分录!$D$7:$D$100=$A54)*INT((([3]分录!$C$7:$C$100="借：")-0.5)*2)*([3]分录!$I$7:$I$100=C$7)*([3]分录!$H$7:$H$100)) -> 0 | D54: =-SUMPRODUCT(([3]分录!$D$7:$D$100=$A54)*INT((([3]分录!$C$7:$C$100="借：")-0.5)*2)*([3]分录!$I$7:$I$100=D$7)*([3]分录!$H$7:$H$100)) -> 0 | E54: =-SUMPRODUCT(([3]分录!$D$7:$D$100=$A54)*INT((([3]分录!$C$7:$C$100="借：")-0.5)*2)*([3]分录!$I$7:$I$100=E$7)*([3]分录!$H$7:$H$100)) -> 0 | F54: =ROUND(SUM(B54:E54),2) -> 0
A55: 其他债权投资 | B55: 0 | C55: =C53-C54 -> 0 | D55: =D53-D54 -> 0 | E55: =E53-E54 -> 0 | F55: =ROUND(SUM(B55:E55),2) -> 0
A56: 持有至到期投资原值 | B56: 0
A57: 持有至到期投资减值准备 | B57: 0
A58: 持有至到期投资 | B58: 0 | C58: =C56-C57 -> 0 | D58: =D56-D57 -> 0 | E58: =E56-E57 -> 0
A59: 长期应收款原值 | B59: 0 | C59: =SUMPRODUCT(([3]分录!$D$7:$D$100=$A59)*INT((([3]分录!$C$7:$C$100="借：")-0.5)*2)*([3]分录!$I$7:$I$100=C$7)*([3]分录!$H$7:$H$100)) -> 0 | D59: =SUMPRODUCT(([3]分录!$D$7:$D$100=$A59)*INT((([3]分录!$C$7:$C$100="借：")-0.5)*2)*([3]分录!$I$7:$I$100=D$7)*([3]分录!$H$7:$H$100)) -> 0 | E59: =SUMPRODUCT(([3]分录!$D$7:$D$100=$A59)*INT((([3]分录!$C$7:$C$100="借：")-0.5)*2)*([3]分录!$I$7:$I$100=E$7)*([3]分录!$H$7:$H$100)) -> 0 | F59: =ROUND(SUM(B59:E59),2) -> 0
A60: 长期应收款坏账准备 | B60: 0 | C60: =-SUMPRODUCT(([3]分录!$D$7:$D$100=$A60)*INT((([3]分录!$C$7:$C$100="借：")-0.5)*2)*([3]分录!$I$7:$I$100=C$7)*([3]分录!$H$7:$H$100)) -> 0 | D60: =-SUMPRODUCT(([3]分录!$D$7:$D$100=$A60)*INT((([3]分录!$C$7:$C$100="借：")-0.5)*2)*([3]分录!$I$7:$I$100=D$7)*([3]分录!$H$7:$H$100)) -> 0 | E60: =-SUMPRODUCT(([3]分录!$D$7:$D$100=$A60)*INT((([3]分录!$C$7:$C$100="借：")-0.5)*2)*([3]分录!$I$7:$I$100=E$7)*([3]分录!$H$7:$H$100)) -> 0 | F60: =ROUND(SUM(B60:E60),2) -> 0
A61: 长期应收款 | B61: 0 | C61: =C59-C60 -> 0 | D61: =D59-D60 -> 0 | E61: =E59-E60 -> 0 | F61: =ROUND(SUM(B61:E61),2) -> 0
A62: 设定受益计划净资产原值 | B62: 0 | C62: =SUMPRODUCT(([3]分录!$D$7:$D$100=$A62)*INT((([3]分录!$C$7:$C$100="借：")-0.5)*2)*([3]分录!$I$7:$I$100=C$7)*([3]分录!$H$7:$H$100)) -> 0 | D62: =SUMPRODUCT(([3]分录!$D$7:$D$100=$A62)*INT((([3]分录!$C$7:$C$100="借：")-0.5)*2)*([3]分录!$I$7:$I$100=D$7)*([3]分录!$H$7:$H$100)) -> 0 | E62: =SUMPRODUCT(([3]分录!$D$7:$D$100=$A62)*INT((([3]分录!$C$7:$C$100="借：")-0.5)*2)*([3]分录!$I$7:$I$100=E$7)*([3]分录!$H$7:$H$100)) -> 0 | F62: =ROUND(SUM(B62:E62),2) -> 0
A63: 设定受益计划净资产减值准备
A64: 设定受益计划净资产
A65: 长期股权投资原值 | B65: 0 | C65: =SUMPRODUCT(([3]分录!$D$7:$D$100=$A65)*INT((([3]分录!$C$7:$C$100="借：")-0.5)*2)*([3]分录!$I$7:$I$100=C$7)*([3]分录!$H$7:$H$100)) -> 0 | D65: =SUMPRODUCT(([3]分录!$D$7:$D$100=$A65)*INT((([3]分录!$C$7:$C$100="借：")-0.5)*2)*([3]分录!$I$7:$I$100=D$7)*([3]分录!$H$7:$H$100)) -> 0 | E65: =SUMPRODUCT(([3]分录!$D$7:$D$100=$A65)*INT((([3]分录!$C$7:$C$100="借：")-0.5)*2)*([3]分录!$I$7:$I$100=E$7)*([3]分录!$H$7:$H$100)) -> 0 | F65: =ROUND(SUM(B65:E65),2) -> 0
A66: 长期股权投资减值准备 | B66: 0 | C66: =-SUMPRODUCT(([3]分录!$D$7:$D$100=$A66)*INT((([3]分录!$C$7:$C$100="借：")-0.5)*2)*([3]分录!$I$7:$I$100=C$7)*([3]分录!$H$7:$H$100)) -> 0 | D66: =-SUMPRODUCT(([3]分录!$D$7:$D$100=$A66)*INT((([3]分录!$C$7:$C$100="借：")-0.5)*2)*([3]分录!$I$7:$I$100=D$7)*([3]分录!$H$7:$H$100)) -> 0 | E66: =-SUMPRODUCT(([3]分录!$D$7:$D$100=$A66)*INT((([3]分录!$C$7:$C$100="借：")-0.5)*2)*([3]分录!$I$7:$I$100=E$7)*([3]分录!$H$7:$H$100)) -> 0 | F66: =ROUND(SUM(B66:E66),2) -> 0
A67: 长期股权投资 | B67: 0 | C67: =C65-C66 -> 0 | D67: =D65-D66 -> 0 | E67: =E65-E66 -> 0 | F67: =ROUND(SUM(B67:E67),2) -> 0
A68: 其他权益工具投资原值 | B68: 32060796 | C68: =SUMPRODUCT(([3]分录!$D$7:$D$100=$A68)*INT((([3]分录!$C$7:$C$100="借：")-0.5)*2)*([3]分录!$I$7:$I$100=C$7)*([3]分录!$H$7:$H$100)) -> 0 | D68: =SUMPRODUCT(([3]分录!$D$7:$D$100=$A68)*INT((([3]分录!$C$7:$C$100="借：")-0.5)*2)*([3]分录!$I$7:$I$100=D$7)*([3]分录!$H$7:$H$100)) -> 0 | E68: =SUMPRODUCT(([3]分录!$D$7:$D$100=$A68)*INT((([3]分录!$C$7:$C$100="借：")-0.5)*2)*([3]分录!$I$7:$I$100=E$7)*([3]分录!$H$7:$H$100)) -> 0 | F68: =ROUND(SUM(B68:E68),2) -> 32060796
A69: 其他权益工具投资减值准备 | B69: 0
A70: 其他权益工具投资 | B70: 0
A71: 其他非流动金融资产原值 | B71: 0 | C71: =SUMPRODUCT(([3]分录!$D$7:$D$100=$A71)*INT((([3]分录!$C$7:$C$100="借：")-0.5)*2)*([3]分录!$I$7:$I$100=C$7)*([3]分录!$H$7:$H$100)) -> 0 | D71: =SUMPRODUCT(([3]分录!$D$7:$D$100=$A71)*INT((([3]分录!$C$7:$C$100="借：")-0.5)*2)*([3]分录!$I$7:$I$100=D$7)*([3]分录!$H$7:$H$100)) -> 0 | E71: =SUMPRODUCT(([3]分录!$D$7:$D$100=$A71)*INT((([3]分录!$C$7:$C$100="借：")-0.5)*2)*([3]分录!$I$7:$I$100=E$7)*([3]分录!$H$7:$H$100)) -> 0 | F71: =ROUND(SUM(B71:E71),2) -> 0
A72: 其他非流动金融资产减值准备 | B72: 0
A73: 其他非流动金融资产 | B73: 0
A74: 投资性房地产原值 | B74: 0 | C74: =SUMPRODUCT(([3]分录!$D$7:$D$100=$A74)*INT((([3]分录!$C$7:$C$100="借：")-0.5)*2)*([3]分录!$I$7:$I$100=C$7)*([3]分录!$H$7:$H$100)) -> 0 | D74: =SUMPRODUCT(([3]分录!$D$7:$D$100=$A74)*INT((([3]分录!$C$7:$C$100="借：")-0.5)*2)*([3]分录!$I$7:$I$100=D$7)*([3]分录!$H$7:$H$100)) -> 0 | E74: =SUMPRODUCT(([3]分录!$D$7:$D$100=$A74)*INT((([3]分录!$C$7:$C$100="借：")-0.5)*2)*([3]分录!$I$7:$I$100=E$7)*([3]分录!$H$7:$H$100)) -> 0 | F74: =ROUND(SUM(B74:E74),2) -> 0
A75: 投资性房地产累计折旧 | B75: 0 | C75: =-SUMPRODUCT(([3]分录!$D$7:$D$100=$A75)*INT((([3]分录!$C$7:$C$100="借：")-0.5)*2)*([3]分录!$I$7:$I$100=C$7)*([3]分录!$H$7:$H$100)) -> 0 | D75: =-SUMPRODUCT(([3]分录!$D$7:$D$100=$A75)*INT((([3]分录!$C$7:$C$100="借：")-0.5)*2)*([3]分录!$I$7:$I$100=D$7)*([3]分录!$H$7:$H$100)) -> 0 | E75: =-SUMPRODUCT(([3]分录!$D$7:$D$100=$A75)*INT((([3]分录!$C$7:$C$100="借：")-0.5)*2)*([3]分录!$I$7:$I$100=E$7)*([3]分录!$H$7:$H$100)) -> 0 | F75: =ROUND(SUM(B75:E75),2) -> 0
A76: 投资性房地产净值 | B76: 0 | C76: =C74-C75 -> 0 | D76: =D74-D75 -> 0 | E76: =E74-E75 -> 0 | F76: =ROUND(SUM(B76:E76),2) -> 0
A77: 投资性房地产减值准备 | B77: 0 | C77: =-SUMPRODUCT(([3]分录!$D$7:$D$100=$A77)*INT((([3]分录!$C$7:$C$100="借：")-0.5)*2)*([3]分录!$I$7:$I$100=C$7)*([3]分录!$H$7:$H$100)) -> 0 | D77: =-SUMPRODUCT(([3]分录!$D$7:$D$100=$A77)*INT((([3]分录!$C$7:$C$100="借：")-0.5)*2)*([3]分录!$I$7:$I$100=D$7)*([3]分录!$H$7:$H$100)) -> 0 | E77: =-SUMPRODUCT(([3]分录!$D$7:$D$100=$A77)*INT((([3]分录!$C$7:$C$100="借：")-0.5)*2)*([3]分录!$I$7:$I$100=E$7)*([3]分录!$H$7:$H$100)) -> 0 | F77: =ROUND(SUM(B77:E77),2) -> 0
A78: 投资性房地产 | B78: 0 | C78: =C76-C77 -> 0 | D78: =D76-D77 -> 0 | E78: =E76-E77 -> 0 | F78: =ROUND(SUM(B78:E78),2) -> 0
A79: 固定资产原值 | B79: 6.4497361e+08 | C79: =SUMPRODUCT(([3]分录!$D$7:$D$100=$A79)*INT((([3]分录!$C$7:$C$100="借：")-0.5)*2)*([3]分录!$I$7:$I$100=C$7)*([3]分录!$H$7:$H$100)) -> 0 | D79: =SUMPRODUCT(([3]分录!$D$7:$D$100=$A79)*INT((([3]分录!$C$7:$C$100="借：")-0.5)*2)*([3]分录!$I$7:$I$100=D$7)*([3]分录!$H$7:$H$100)) -> 0 | E79: =SUMPRODUCT(([3]分录!$D$7:$D$100=$A79)*INT((([3]分录!$C$7:$C$100="借：")-0.5)*2)*([3]分录!$I$7:$I$100=E$7)*([3]分录!$H$7:$H$100)) -> 0 | F79: =ROUND(SUM(B79:E79),2) -> 6.4497361e+08
A80: 固定资产累计折旧 | B80: 2.2373984e+08 | C80: =-SUMPRODUCT(([3]分录!$D$7:$D$100=$A80)*INT((([3]分录!$C$7:$C$100="借：")-0.5)*2)*([3]分录!$I$7:$I$100=C$7)*([3]分录!$H$7:$H$100)) -> 0 | D80: =-SUMPRODUCT(([3]分录!$D$7:$D$100=$A80)*INT((([3]分录!$C$7:$C$100="借：")-0.5)*2)*([3]分录!$I$7:$I$100=D$7)*([3]分录!$H$7:$H$100)) -> 0 | E80: =-SUMPRODUCT(([3]分录!$D$7:$D$100=$A80)*INT((([3]分录!$C$7:$C$100="借：")-0.5)*2)*([3]分录!$I$7:$I$100=E$7)*([3]分录!$H$7:$H$100)) -> 0 | F80: =ROUND(SUM(B80:E80),2) -> 2.2373984e+08
A81: 固定资产净值 | B81: 0 | C81: =C79-C80 -> 0 | D81: =D79-D80 -> 0 | E81: =E79-E80 -> 0 | F81: =ROUND(SUM(B81:E81),2) -> 0
A82: 固定资产减值准备 | B82: 0 | C82: =-SUMPRODUCT(([3]分录!$D$7:$D$100=$A82)*INT((([3]分录!$C$7:$C$100="借：")-0.5)*2)*([3]分录!$I$7:$I$100=C$7)*([3]分录!$H$7:$H$100)) -> 0 | D82: =-SUMPRODUCT(([3]分录!$D$7:$D$100=$A82)*INT((([3]分录!$C$7:$C$100="借：")-0.5)*2)*([3]分录!$I$7:$I$100=D$7)*([3]分录!$H$7:$H$100)) -> 0 | E82: =-SUMPRODUCT(([3]分录!$D$7:$D$100=$A82)*INT((([3]分录!$C$7:$C$100="借：")-0.5)*2)*([3]分录!$I$7:$I$100=E$7)*([3]分录!$H$7:$H$100)) -> 0 | F82: =ROUND(SUM(B82:E82),2) -> 0
A83: 固定资产 | B83: 0 | C83: =C81-C82 -> 0 | D83: =D81-D82 -> 0 | E83: =E81-E82 -> 0 | F83: =ROUND(SUM(B83:E83),2) -> 0
A84: 在建工程原值 | B84: 2.5150497e+08 | C84: =SUMPRODUCT(([3]分录!$D$7:$D$100=$A84)*INT((([3]分录!$C$7:$C$100="借：")-0.5)*2)*([3]分录!$I$7:$I$100=C$7)*([3]分录!$H$7:$H$100)) -> 0 | D84: =SUMPRODUCT(([3]分录!$D$7:$D$100=$A84)*INT((([3]分录!$C$7:$C$100="借：")-0.5)*2)*([3]分录!$I$7:$I$100=D$7)*([3]分录!$H$7:$H$100)) -> 0 | E84: =SUMPRODUCT(([3]分录!$D$7:$D$100=$A84)*INT((([3]分录!$C$7:$C$100="借：")-0.5)*2)*([3]分录!$I$7:$I$100=E$7)*([3]分录!$H$7:$H$100)) -> 0 | F84: =ROUND(SUM(B84:E84),2) -> 2.5150497e+08
A85: 在建工程减值准备 | B85: 0 | C85: =-SUMPRODUCT(([3]分录!$D$7:$D$100=$A85)*INT((([3]分录!$C$7:$C$100="借：")-0.5)*2)*([3]分录!$I$7:$I$100=C$7)*([3]分录!$H$7:$H$100)) -> 0 | D85: =-SUMPRODUCT(([3]分录!$D$7:$D$100=$A85)*INT((([3]分录!$C$7:$C$100="借：")-0.5)*2)*([3]分录!$I$7:$I$100=D$7)*([3]分录!$H$7:$H$100)) -> 0 | E85: =-SUMPRODUCT(([3]分录!$D$7:$D$100=$A85)*INT((([3]分录!$C$7:$C$100="借：")-0.5)*2)*([3]分录!$I$7:$I$100=E$7)*([3]分录!$H$7:$H$100)) -> 0 | F85: =ROUND(SUM(B85:E85),2) -> 0
A86: 在建工程 | B86: 0 | C86: =C84-C85 -> 0 | D86: =D84-D85 -> 0 | E86: =E84-E85 -> 0 | F86: =ROUND(SUM(B86:E86),2) -> 0
A87: 工程物资原值 | B87: 0 | C87: =SUMPRODUCT(([3]分录!$D$7:$D$100=$A87)*INT((([3]分录!$C$7:$C$100="借：")-0.5)*2)*([3]分录!$I$7:$I$100=C$7)*([3]分录!$H$7:$H$100)) -> 0 | D87: =SUMPRODUCT(([3]分录!$D$7:$D$100=$A87)*INT((([3]分录!$C$7:$C$100="借：")-0.5)*2)*([3]分录!$I$7:$I$100=D$7)*([3]分录!$H$7:$H$100)) -> 0 | E87: =SUMPRODUCT(([3]分录!$D$7:$D$100=$A87)*INT((([3]分录!$C$7:$C$100="借：")-0.5)*2)*([3]分录!$I$7:$I$100=E$7)*([3]分录!$H$7:$H$100)) -> 0 | F87: =ROUND(SUM(B87:E87),2) -> 0
A88: 工程物资减值准备 | B88: 0 | C88: =-SUMPRODUCT(([3]分录!$D$7:$D$100=$A88)*INT((([3]分录!$C$7:$C$100="借：")-0.5)*2)*([3]分录!$I$7:$I$100=C$7)*([3]分录!$H$7:$H$100)) -> 0 | D88: =-SUMPRODUCT(([3]分录!$D$7:$D$100=$A88)*INT((([3]分录!$C$7:$C$100="借：")-0.5)*2)*([3]分录!$I$7:$I$100=D$7)*([3]分录!$H$7:$H$100)) -> 0 | E88: =-SUMPRODUCT(([3]分录!$D$7:$D$100=$A88)*INT((([3]分录!$C$7:$C$100="借：")-0.5)*2)*([3]分录!$I$7:$I$100=E$7)*([3]分录!$H$7:$H$100)) -> 0 | F88: =ROUND(SUM(B88:E88),2) -> 0
A89: 工程物资 | B89: 0 | C89: =C87-C88 -> 0 | D89: =D87-D88 -> 0 | E89: =E87-E88 -> 0 | F89: =ROUND(SUM(B89:E89),2) -> 0
A90: 固定资产清理 | B90: 0 | C90: =SUMPRODUCT(([3]分录!$D$7:$D$100=$A90)*INT((([3]分录!$C$7:$C$100="借：")-0.5)*2)*([3]分录!$I$7:$I$100=C$7)*([3]分录!$H$7:$H$100)) -> 0 | D90: =SUMPRODUCT(([3]分录!$D$7:$D$100=$A90)*INT((([3]分录!$C$7:$C$100="借：")-0.5)*2)*([3]分录!$I$7:$I$100=D$7)*([3]分录!$H$7:$H$100)) -> 0 | E90: =SUMPRODUCT(([3]分录!$D$7:$D$100=$A90)*INT((([3]分录!$C$7:$C$100="借：")-0.5)*2)*([3]分录!$I$7:$I$100=E$7)*([3]分录!$H$7:$H$100)) -> 0 | F90: =ROUND(SUM(B90:E90),2) -> 0
A91: 生产性生物资产原值 | B91: 0 | C91: =SUMPRODUCT(([3]分录!$D$7:$D$100=$A91)*INT((([3]分录!$C$7:$C$100="借：")-0.5)*2)*([3]分录!$I$7:$I$100=C$7)*([3]分录!$H$7:$H$100)) -> 0 | D91: =SUMPRODUCT(([3]分录!$D$7:$D$100=$A91)*INT((([3]分录!$C$7:$C$100="借：")-0.5)*2)*([3]分录!$I$7:$I$100=D$7)*([3]分录!$H$7:$H$100)) -> 0 | E91: =SUMPRODUCT(([3]分录!$D$7:$D$100=$A91)*INT((([3]分录!$C$7:$C$100="借：")-0.5)*2)*([3]分录!$I$7:$I$100=E$7)*([3]分录!$H$7:$H$100)) -> 0 | F91: =ROUND(SUM(B91:E91),2) -> 0
A92: 生产性生物资产累计折旧 | B92: 0
A93: 生产性生物资产净值 | B93: 0
A94: 生产性生物资产减值准备 | B94: 0
A95: 生产性生物资产 | B95: 0
A96: 油气资产原值 | B96: 0 | C96: =SUMPRODUCT(([3]分录!$D$7:$D$100=$A96)*INT((([3]分录!$C$7:$C$100="借：")-0.5)*2)*([3]分录!$I$7:$I$100=C$7)*([3]分录!$H$7:$H$100)) -> 0 | D96: =SUMPRODUCT(([3]分录!$D$7:$D$100=$A96)*INT((([3]分录!$C$7:$C$100="借：")-0.5)*2)*([3]分录!$I$7:$I$100=D$7)*([3]分录!$H$7:$H$100)) -> 0 | E96: =SUMPRODUCT(([3]分录!$D$7:$D$100=$A96)*INT((([3]分录!$C$7:$C$100="借：")-0.5)*2)*([3]分录!$I$7:$I$100=E$7)*([3]分录!$H$7:$H$100)) -> 0 | F96: =ROUND(SUM(B96:E96),2) -> 0
A97: 油气资产累计折旧 | B97: 0
A98: 油气资产净值 | B98: 0
A99: 油气资产减值准备 | B99: 0
A100: 油气资产 | B100: 0
...

Sheet Sheet1
A2: 项目 | B2: 行
A3: 流动资产： | B3: 1 | C3: =VLOOKUP(A3,试算!$A$9:$B$121,2,FALSE) -> #N/A | O3: TB调整分录 横向还是纵向
A4: 货币资金 | B4: =B3+1 -> 2 | C4: =VLOOKUP(A4,试算!$A$9:$B$121,2,FALSE) -> 1.2884156e+08
A5: 结算备付金* | B5: =B4+1 -> 3 | C5: =VLOOKUP(A5,试算!$A$9:$B$121,2,FALSE) -> #N/A | F5: 财务费用
A6: 拆出资金* | B6: =B5+1 -> 4 | C6: =VLOOKUP(A6,试算!$A$9:$B$121,2,FALSE) -> #N/A | F6: 其中：利息费用
A7: 交易性金融资产 | B7: =B6+1 -> 5 | C7: =VLOOKUP(A7,试算!$A$9:$B$121,2,FALSE) -> 1.0338995e+10 | F7: 利息收入
A8: 衍生金融资产 | B8: =B7+1 -> 6 | C8: =VLOOKUP(A8,试算!$A$9:$B$121,2,FALSE) -> 0 | F8: 汇兑净损失（净收益以“－”号填列）
A9: 应收票据 | B9: =B8+1 -> 7 | C9: =VLOOKUP(A9,试算!$A$9:$B$121,2,FALSE) -> 0
A10: 应收票据原值 | B10: =B9+1 -> 8 | C10: =VLOOKUP(A10,试算!$A$9:$B$121,2,FALSE) -> 0
A11: 应收票据坏账准备 | B11: =B10+1 -> 9 | C11: =VLOOKUP(A11,试算!$A$9:$B$121,2,FALSE) -> 0
A12: 应收账款原值 | B12: =B11+1 -> 10 | C12: =VLOOKUP(A12,试算!$A$9:$B$121,2,FALSE) -> 0 | H12: 加： 营业外收入
A13: 应收账款坏账准备 | B13: =B12+1 -> 11 | C13: =VLOOKUP(A13,试算!$A$9:$B$121,2,FALSE) -> 0 | H13: 其中：政府补助
A14: 应收账款 | B14: =B13+1 -> 12 | C14: =VLOOKUP(A14,试算!$A$9:$B$121,2,FALSE) -> 0
A15: 应收款项融资 | B15: =B14+1 -> 13 | C15: =VLOOKUP(A15,试算!$A$9:$B$121,2,FALSE) -> 0
A16: 应收款项融资原值 | B16: =B15+1 -> 14 | C16: =VLOOKUP(A16,试算!$A$9:$B$121,2,FALSE) -> 0 | H16: 应付职工薪酬
A17: 应收款项融资坏账准备 | B17: =B16+1 -> 15 | C17: =VLOOKUP(A17,试算!$A$9:$B$121,2,FALSE) -> 0 | H17: 其中：应付工资
A18: 预付款项原值 | B18: =B17+1 -> 16 | C18: =VLOOKUP(A18,试算!$A$9:$B$121,2,FALSE) -> 0 | H18: 应付福利费
A19: 预付款项坏账准备 | B19: =B18+1 -> 17 | C19: =VLOOKUP(A19,试算!$A$9:$B$121,2,FALSE) -> 0 | H19: #其中：职工奖励及福利基金
A20: 预付款项 | B20: =B19+1 -> 18 | C20: =VLOOKUP(A20,试算!$A$9:$B$121,2,FALSE) -> 0
A21: 应收保费* | B21: =B20+1 -> 19 | C21: =VLOOKUP(A21,试算!$A$9:$B$121,2,FALSE) -> #N/A | H21: 应交税费
A22: 应收分保账款* | B22: =B21+1 -> 20 | C22: =VLOOKUP(A22,试算!$A$9:$B$121,2,FALSE) -> #N/A | H22: 其中：应交税金
A23: 应收分保合同准备金* | B23: =B22+1 -> 21 | C23: =VLOOKUP(A23,试算!$A$9:$B$121,2,FALSE) -> #N/A
A24: 应收利息原值 | B24: =B23+1 -> 22 | C24: =VLOOKUP(A24,试算!$A$9:$B$121,2,FALSE) -> 0
A25: 应收利息坏账准备 | B25: =B24+1 -> 23 | C25: =VLOOKUP(A25,试算!$A$9:$B$121,2,FALSE) -> 0 | H25: 存货
A26: 应收利息 | B26: =B25+1 -> 24 | C26: =VLOOKUP(A26,试算!$A$9:$B$121,2,FALSE) -> 0 | H26: 其中：原材料
A27: 应收股利原值 | B27: =B26+1 -> 25 | C27: =VLOOKUP(A27,试算!$A$9:$B$121,2,FALSE) -> 0 | H27: 库存商品（产成品）
A28: 应收股利坏账准备 | B28: =B27+1 -> 26 | C28: =VLOOKUP(A28,试算!$A$9:$B$121,2,FALSE) -> 0
A29: 应收股利 | B29: =B28+1 -> 27 | C29: =VLOOKUP(A29,试算!$A$9:$B$121,2,FALSE) -> 0
A30: 其他应收款原值 | B30: =B29+1 -> 28 | C30: =VLOOKUP(A30,试算!$A$9:$B$121,2,FALSE) -> 0
A31: 其他应收款坏账准备 | B31: =B30+1 -> 29 | C31: =VLOOKUP(A31,试算!$A$9:$B$121,2,FALSE) -> 0
A32: 其他应收款 | B32: =B31+1 -> 30 | C32: =VLOOKUP(A32,试算!$A$9:$B$121,2,FALSE) -> 0
A33: 买入返售金融资产* | B33: =B32+1 -> 31 | C33: =VLOOKUP(A33,试算!$A$9:$B$121,2,FALSE) -> #N/A
A34: 存货原值 | B34: =B33+1 -> 32 | C34: =VLOOKUP(A34,试算!$A$9:$B$121,2,FALSE) -> 4.0768702e+08
A35: 存货跌价准备 | B35: =B34+1 -> 33 | C35: =VLOOKUP(A35,试算!$A$9:$B$121,2,FALSE) -> 0
A36: 存货 | B36: =B35+1 -> 34 | C36: =VLOOKUP(A36,试算!$A$9:$B$121,2,FALSE) -> 0
A37: 其中：原材料 | B37: =B36+1 -> 35 | C37: =VLOOKUP(A37,试算!$A$9:$B$121,2,FALSE) -> #N/A
A38: 库存商品（产成品） | B38: =B37+1 -> 36 | C38: =VLOOKUP(A38,试算!$A$9:$B$121,2,FALSE) -> #N/A
A39: 合同资产原值 | B39: =B38+1 -> 37 | C39: =VLOOKUP(A39,试算!$A$9:$B$121,2,FALSE) -> 0
... A113: 资 产 总 计 | B113: =B112+1 -> 111 | C113: =VLOOKUP(A113,试算!$A$9:$B$121,2,FALSE) -> #N/A

Sheet 未审报表
A1: =IF(ABS(D171-D255)<0.005,"","年初未分配利润勾稽有误！")
A2: 未审报表
D3: 索引号：B15-1-1/B15-1-2/B15-1-3
A4: =IF(ABS(D127-D190)<0.005,0,"年初数不平，差额为：") -> 0
A5: =IF(报表格式!E55=""," 对不起，请到参数表中确定报表类型！",CONCATENATE(" 编制单位：",参数!D3)) -> 编制单位：二锅头 | C5: =参数!$D$12 -> 44926 | D5: =CONCATENATE("金额单位：",参数!$D$13) -> 金额单位：人民币元
A6: 资 产 | B6: 行次 | C6: =参数!D12 -> 44926 | D6: =参数!D11 -> 44561
A7: =报表格式!B5 -> 流动资产： | B7: =报表格式!C5 -> 1
A8: =报表格式!B6 -> 货币资金 | B8: =报表格式!C6 -> 2 | C8: 17053593 | D8: 645471.35
A9: =报表格式!B7 -> 结算备付金* | B9: =报表格式!C7 -> 3
A10: =报表格式!B8 -> 拆出资金原值* | B10: =报表格式!C8 -> 4
A11: =报表格式!B9 -> 拆出资金减值准备* | B11: =报表格式!C9 -> 5
A12: =报表格式!B10 -> 拆出资金* | B12: =报表格式!C10 -> 6 | C12: =C10-C11 -> 0 | D12: =D10-D11 -> 0 | G12: 25580389
A13: =报表格式!B11 -> 交易性金融资产 | B13: =报表格式!C11 -> 7 | G13: 8526796.3
A14: =报表格式!B12 -> 衍生金融资产 | B14: =报表格式!C12 -> 8 | G14: =G12-G13 -> 17053593
A15: =报表格式!B13 -> 应收票据原值 | B15: =报表格式!C13 -> 9
A16: =报表格式!B14 -> 应收票据坏账准备 | B16: =报表格式!C14 -> 10
A17: =报表格式!B15 -> 应收票据 | B17: =报表格式!C15 -> 11 | C17: =C15-C16 -> 0 | D17: =D15-D16 -> 0
A18: =报表格式!B16 -> 应收账款原值 | B18: =报表格式!C16 -> 12 | C18: 15449122 | D18: 16718591
A19: =报表格式!B17 -> 应收账款坏账准备 | B19: =报表格式!C17 -> 13 | C19: 1423224.6
A20: =报表格式!B18 -> 应收账款 | B20: =报表格式!C18 -> 14 | C20: =C18-C19 -> 14025898 | D20: =D18-D19 -> 16718591
A21: =报表格式!B19 -> 应收款项融资原值 | B21: =报表格式!C19 -> 15
A22: =报表格式!B20 -> 应收款项融资坏账准备 | B22: =报表格式!C20 -> 16
A23: =报表格式!B21 -> 应收款项融资 | B23: =报表格式!C21 -> 17 | C23: =C21-C22 -> 0 | D23: =D21-D22 -> 0
A24: =报表格式!B22 -> 预付款项原值 | B24: =报表格式!C22 -> 18 | C24: 574623.4 | D24: 1584.26
A25: =报表格式!B23 -> 预付款项坏账准备 | B25: =报表格式!C23 -> 19
A26: =报表格式!B24 -> 预付款项 | B26: =报表格式!C24 -> 20 | C26: =C24-C25 -> 574623.4 | D26: =D24-D25 -> 1584.26
A27: =报表格式!B25 -> 应收保费原值* | B27: =报表格式!C25 -> 21
A28: =报表格式!B26 -> 应收保费坏账准备* | B28: =报表格式!C26 -> 22
A29: =报表格式!B27 -> 应收保费* | B29: =报表格式!C27 -> 23 | C29: =C27-C28 -> 0 | D29: =D27-D28 -> 0
A30: =报表格式!B28 -> 应收分保账款原值* | B30: =报表格式!C28 -> 24
A31: =报表格式!B29 -> 应收分保账款坏账准备* | B31: =报表格式!C29 -> 25
A32: =报表格式!B30 -> 应收分保账款* | B32: =报表格式!C30 -> 26 | C32: =C30-C31 -> 0 | D32: =D30-D31 -> 0
A33: =报表格式!B31 -> 应收分保合同准备金* | B33: =报表格式!C31 -> 27
A34: =报表格式!B32 -> 应收利息原值 | B34: =报表格式!C32 -> 28
A35: =报表格式!B33 -> 应收利息坏账准备 | B35: =报表格式!C33 -> 29
A36: =报表格式!B34 -> 应收利息 | B36: =报表格式!C34 -> 30 | C36: =C34-C35 -> 0 | D36: =D34-D35 -> 0
A37: =报表格式!B35 -> 应收股利原值 | B37: =报表格式!C35 -> 31 | C37: 32823183 | D37: 10512385
A38: =报表格式!B36 -> 应收股利坏账准备 | B38: =报表格式!C36 -> 32
A39: =报表格式!B37 -> 应收股利 | B39: =报表格式!C37 -> 33 | C39: =C37-C38 -> 32823183 | D39: =D37-D38 -> 10512385
A40: =报表格式!B38 -> 其他应收款原值 | B40: =报表格式!C38 -> 34 | C40: 8096269.4 | D40: 12543397
A41: =报表格式!B39 -> 其他应收款坏账准备 | B41: =报表格式!C39 -> 35 | C41: 13310.74
A42: =报表格式!B40 -> 其他应收款 | B42: =报表格式!C40 -> 36 | C42: =C40-C41 -> 8082958.6 | D42: =D40-D41 -> 12543397
A43: =报表格式!B41 -> 买入返售金融资产原值* | B43: =报表格式!C41 -> 37
A44: =报表格式!B42 -> 买入返售金融资产减值准备* | B44: =报表格式!C42 -> 38
A45: =报表格式!B43 -> 买入返售金融资产* | B45: =报表格式!C43 -> 39 | C45: =C43-C44 -> 0 | D45: =D43-D44 -> 0
A46: =报表格式!B44 -> 存货原值 | B46: =报表格式!C44 -> 40 | C46: 8526796.3
A47: =报表格式!B45 -> 存货跌价准备 | B47: =报表格式!C45 -> 41
A48: =报表格式!B46 -> 存货 | B48: =报表格式!C46 -> 42 | C48: =C46-C47 -> 8526796.3 | D48: =D46-D47 -> 0
A49: =报表格式!B47 -> 其中：原材料 | B49: =报表格式!C47 -> 43 | C49: 698003
A50: =报表格式!B48 -> 库存商品（产成品） | B50: =报表格式!C48 -> 44 | C50: 7000000
A51: =报表格式!B49 -> 合同资产原值 | B51: =报表格式!C49 -> 45
A52: =报表格式!B50 -> 合同资产减值准备 | B52: =报表格式!C50 -> 46
A53: =报表格式!B51 -> 合同资产 | B53: =报表格式!C51 -> 47 | C53: =C51-C52 -> 0 | D53: =D51-D52 -> 0
A54: =报表格式!B52 -> 持有待售资产原值 | B54: =报表格式!C52 -> 48
A55: =报表格式!B53 -> 持有待售资产减值准备 | B55: =报表格式!C53 -> 49
A56: =报表格式!B54 -> 持有待售资产 | B56: =报表格式!C54 -> 50 | C56: =C54-C55 -> 0 | D56: =D54-D55 -> 0
A57: =报表格式!B55 -> 一年内到期的非流动资产 | B57: =报表格式!C55 -> 51
A58: =报表格式!B56 -> 其他流动资产 | B58: =报表格式!C56 -> 52 | D58: 19000000
A59: =报表格式!B57 -> 流动资产合计 | B59: =报表格式!C57 -> 53 | C59: =SUM(C8:C9,C12,C13:C14,C17,C20,C23,C26,C29,C32,C33,C36,C39,C42,C45,C48,C53,C56,C57:C58) -> 81087052 | D59: =SUM(D8:D9,D12,D13:D14,D17,D20,D23,D26,D29,D32,D33,D36,D39,D42,D45,D48,D53,D56,D57:D58) -> 59421429
A60: =报表格式!B58 -> 非流动资产: | B60: =报表格式!C58 -> 54
A61: =报表格式!B59 -> 发放贷款和垫款原值* | B61: =报表格式!C59 -> 55
A62: =报表格式!B60 -> 发放贷款和垫款减值准备* | B62: =报表格式!C60 -> 56
A63: =报表格式!B61 -> 发放贷款和垫款* | B63: =报表格式!C61 -> 57 | C63: =C61-C62 -> 0 | D63: =D61-D62 -> 0
A64: =报表格式!B62 -> 债权投资原值 | B64: =报表格式!C62 -> 58
A65: =报表格式!B63 -> 债权投资减值准备 | B65: =报表格式!C63 -> 59
A66: =报表格式!B64 -> 债权投资 | B66: =报表格式!C64 -> 60 | C66: =C64-C65 -> 0 | D66: =D64-D65 -> 0
A67: =报表格式!B65 -> 其他债权投资原值 | B67: =报表格式!C65 -> 61
A68: =报表格式!B66 -> 其他债权投资减值准备 | B68: =报表格式!C66 -> 62
A69: =报表格式!B67 -> 其他债权投资 | B69: =报表格式!C67 -> 63 | C69: =C67-C68 -> 0 | D69: =D67-D68 -> 0
A70: =报表格式!B68 -> 长期应收款原值 | B70: =报表格式!C68 -> 64
A71: =报表格式!B69 -> 长期应收款坏账准备 | B71: =报表格式!C69 -> 65
A72: =报表格式!B70 -> 长期应收款 | B72: =报表格式!C70 -> 66 | C72: =C70-C71 -> 0 | D72: =D70-D71 -> 0
A73: =报表格式!B71 -> 设定受益计划净资产 | B73: =报表格式!C71 -> 67
A74: =报表格式!B72 -> 长期股权投资原值 | B74: =报表格式!C72 -> 68 | C74: 23870038 | D74: 11290038
A75: =报表格式!B73 -> 长期股权投资减值准备 | B75: =报表格式!C73 -> 69
A76: =报表格式!B74 -> 长期股权投资 | B76: =报表格式!C74 -> 70 | C76: =C74-C75 -> 23870038 | D76: =D74-D75 -> 11290038
A77: =报表格式!B75 -> 其他权益工具投资 | B77: =报表格式!C75 -> 71
A78: =报表格式!B76 -> 其他非流动金融资产 | B78: =报表格式!C76 -> 72
A79: =报表格式!B77 -> 投资性房地产原值 | B79: =报表格式!C77 -> 73
A80: =报表格式!B78 -> 投资性房地产累计折旧 | B80: =报表格式!C78 -> 74
A81: =报表格式!B79 -> 投资性房地产净值 | B81: =报表格式!C79 -> 75 | C81: =C79-C80 -> 0 | D81: =D79-D80 -> 0
A82: =报表格式!B80 -> 投资性房地产减值准备 | B82: =报表格式!C80 -> 76
A83: =报表格式!B81 -> 投资性房地产 | B83: =报表格式!C81 -> 77 | C83: =C81-C82 -> 0 | D83: =D81-D82 -> 0
A84: =报表格式!B82 -> 固定资产原值 | B84: =报表格式!C82 -> 78 | C84: 114529.92
A85: =报表格式!B83 -> 固定资产累计折旧 | B85: =报表格式!C83 -> 79 | C85: 15907.1
A86: =报表格式!B84 -> 固定资产净值 | B86: =报表格式!C84 -> 80 | C86: =C84-C85 -> 98622.82 | D86: =D84-D85 -> 0
A87: =报表格式!B85 -> 固定资产减值准备 | B87: =报表格式!C85 -> 81
A88: =报表格式!B86 -> 固定资产 | B88: =报表格式!C86 -> 82 | C88: =C86-C87 -> 98622.82 | D88: =D86-D87 -> 0
A89: =报表格式!B87 -> 固定资产清理 | B89: =报表格式!C87 -> 83
A90: =报表格式!B88 -> 在建工程原值 | B90: =报表格式!C88 -> 84
A91: =报表格式!B89 -> 在建工程减值准备 | B91: =报表格式!C89 -> 85
A92: =报表格式!B90 -> 在建工程 | B92: =报表格式!C90 -> 86 | C92: =C90-C91 -> 0 | D92: =D90-D91 -> 0
A93: =报表格式!B91 -> 工程物资原值 | B93: =报表格式!C91 -> 87
A94: =报表格式!B92 -> 工程物资减值准备 | B94: =报表格式!C92 -> 88
A95: =报表格式!B93 -> 工程物资 | B95: =报表格式!C93 -> 89 | C95: =C93-C94 -> 0 | D95: =D93-D94 -> 0
A96: =报表格式!B94 -> 生产性生物资产原值 | B96: =报表格式!C94 -> 90
A97: =报表格式!B95 -> 生产性生物资产累计折旧 | B97: =报表格式!C95 -> 91
A98: =报表格式!B96 -> 生产性生物资产净值 | B98: =报表格式!C96 -> 92 | C98: =C96-C97 -> 0 | D98: =D96-D97 -> 0
A99: =报表格式!B97 -> 生产性生物资产减值准备 | B99: =报表格式!C97 -> 93
A100: =报表格式!B98 -> 生产性生物资产 | B100: =报表格式!C98 -> 94 | C100: =C98-C99 -> 0 | D100: =D98-D99 -> 0
...

Sheet 期初核对
A2: 期初报表核对
A5: =IF(报表格式!E55=""," 对不起，请到参数表中确定报表类型！",CONCATENATE(" 客户名称：",参数!D3)) -> 客户名称：二锅头 | C5: =参数!D11 -> 44561 | E5: =CONCATENATE("金额单位：",参数!$D$13) -> 金额单位：人民币元
A6: =IF(E61<=0.005,"资 产","资产明细核对不符！") -> 资 产 | B6: 行次 | C6: 上期审定数 ① | D6: 本年期初数 ② | E6: 辅助列 | F6: 差异 ①-②
A7: =未审报表!A7 -> 流动资产： | B7: =未审报表!B7 -> 1
A8: =未审报表!A8 -> 货币资金 | B8: =未审报表!B8 -> 2 | C8: 645471.35 | D8: =未审报表!D8 -> 645471.35 | E8: =ABS(F8) -> 0 | F8: =C8-D8 -> 0
A9: =未审报表!A9 -> 结算备付金* | B9: =未审报表!B9 -> 3 | D9: =未审报表!D9 -> 0 | E9: =ABS(F9) -> 0 | F9: =C9-D9 -> 0
A10: =未审报表!A10 -> 拆出资金原值* | B10: =未审报表!B10 -> 4 | D10: =未审报表!D10 -> 0 | E10: =ABS(F10) -> 0 | F10: =C10-D10 -> 0
A11: =未审报表!A11 -> 拆出资金减值准备* | B11: =未审报表!B11 -> 5 | D11: =未审报表!D11 -> 0 | E11: =ABS(F11) -> 0 | F11: =C11-D11 -> 0
A12: =未审报表!A12 -> 拆出资金* | B12: =未审报表!B12 -> 6 | C12: =C10-C11 -> 0 | D12: =D10-D11 -> 0 | E12: =ABS(F12) -> 0 | F12: =C12-D12 -> 0
A13: =未审报表!A13 -> 交易性金融资产 | B13: =未审报表!B13 -> 7 | D13: =未审报表!D13 -> 0 | E13: =ABS(F13) -> 0 | F13: =C13-D13 -> 0
A14: =未审报表!A14 -> 衍生金融资产 | B14: =未审报表!B14 -> 8 | D14: =未审报表!D14 -> 0 | E14: =ABS(F14) -> 0 | F14: =C14-D14 -> 0
A15: =未审报表!A15 -> 应收票据原值 | B15: =未审报表!B15 -> 9 | D15: =未审报表!D15 -> 0 | E15: =ABS(F15) -> 0 | F15: =C15-D15 -> 0
A16: =未审报表!A16 -> 应收票据坏账准备 | B16: =未审报表!B16 -> 10 | D16: =未审报表!D16 -> 0 | E16: =ABS(F16) -> 0 | F16: =C16-D16 -> 0
A17: =未审报表!A17 -> 应收票据 | B17: =未审报表!B17 -> 11 | C17: =C15-C16 -> 0 | D17: =D15-D16 -> 0 | E17: =ABS(F17) -> 0 | F17: =C17-D17 -> 0
A18: =未审报表!A18 -> 应收账款原值 | B18: =未审报表!B18 -> 12 | C18: 16718591 | D18: =未审报表!D18 -> 16718591 | E18: =ABS(F18) -> 0 | F18: =C18-D18 -> 0
A19: =未审报表!A19 -> 应收账款坏账准备 | B19: =未审报表!B19 -> 13 | D19: =未审报表!D19 -> 0 | E19: =ABS(F19) -> 0 | F19: =C19-D19 -> 0
A20: =未审报表!A20 -> 应收账款 | B20: =未审报表!B20 -> 14 | C20: =C18-C19 -> 16718591 | D20: =D18-D19 -> 16718591 | E20: =ABS(F20) -> 0 | F20: =C20-D20 -> 0
A21: =未审报表!A21 -> 应收款项融资原值 | B21: =未审报表!B21 -> 15 | D21: =未审报表!D21 -> 0 | E21: =ABS(F21) -> 0 | F21: =C21-D21 -> 0
A22: =未审报表!A22 -> 应收款项融资坏账准备 | B22: =未审报表!B22 -> 16 | D22: =未审报表!D22 -> 0 | E22: =ABS(F22) -> 0 | F22: =C22-D22 -> 0
A23: =未审报表!A23 -> 应收款项融资 | B23: =未审报表!B23 -> 17 | C23: =C21-C22 -> 0 | D23: =D21-D22 -> 0 | E23: =ABS(F23) -> 0 | F23: =C23-D23 -> 0
A24: =未审报表!A24 -> 预付款项原值 | B24: =未审报表!B24 -> 18 | C24: 1584.26 | D24: =未审报表!D24 -> 1584.26 | E24: =ABS(F24) -> 0 | F24: =C24-D24 -> 0
A25: =未审报表!A25 -> 预付款项坏账准备 | B25: =未审报表!B25 -> 19 | D25: =未审报表!D25 -> 0 | E25: =ABS(F25) -> 0 | F25: =C25-D25 -> 0
A26: =未审报表!A26 -> 预付款项 | B26: =未审报表!B26 -> 20 | C26: =C24-C25 -> 1584.26 | D26: =D24-D25 -> 1584.26 | E26: =ABS(F26) -> 0 | F26: =C26-D26 -> 0
A27: =未审报表!A27 -> 应收保费原值* | B27: =未审报表!B27 -> 21 | D27: =未审报表!D27 -> 0 | E27: =ABS(F27) -> 0 | F27: =C27-D27 -> 0
A28: =未审报表!A28 -> 应收保费坏账准备* | B28: =未审报表!B28 -> 22 | D28: =未审报表!D28 -> 0 | E28: =ABS(F28) -> 0 | F28: =C28-D28 -> 0
A29: =未审报表!A29 -> 应收保费* | B29: =未审报表!B29 -> 23 | C29: =C27-C28 -> 0 | D29: =D27-D28 -> 0 | E29: =ABS(F29) -> 0 | F29: =C29-D29 -> 0
A30: =未审报表!A30 -> 应收分保账款原值* | B30: =未审报表!B30 -> 24 | D30: =未审报表!D30 -> 0 | E30: =ABS(F30) -> 0 | F30: =C30-D30 -> 0
A31: =未审报表!A31 -> 应收分保账款坏账准备* | B31: =未审报表!B31 -> 25 | D31: =未审报表!D31 -> 0 | E31: =ABS(F31) -> 0 | F31: =C31-D31 -> 0
A32: =未审报表!A32 -> 应收分保账款* | B32: =未审报表!B32 -> 26 | C32: =C30-C31 -> 0 | D32: =D30-D31 -> 0 | E32: =ABS(F32) -> 0 | F32: =C32-D32 -> 0
A33: =未审报表!A33 -> 应收分保合同准备金* | B33: =未审报表!B33 -> 27 | D33: =未审报表!D33 -> 0 | E33: =ABS(F33) -> 0 | F33: =C33-D33 -> 0
A34: =未审报表!A34 -> 应收利息原值 | B34: =未审报表!B34 -> 28 | D34: =未审报表!D34 -> 0 | E34: =ABS(F34) -> 0 | F34: =C34-D34 -> 0
A35: =未审报表!A35 -> 应收利息坏账准备 | B35: =未审报表!B35 -> 29 | D35: =未审报表!D35 -> 0 | E35: =ABS(F35) -> 0 | F35: =C35-D35 -> 0
A36: =未审报表!A36 -> 应收利息 | B36: =未审报表!B36 -> 30 | C36: =C34-C35 -> 0 | D36: =D34-D35 -> 0 | E36: =ABS(F36) -> 0 | F36: =C36-D36 -> 0
A37: =未审报表!A37 -> 应收股利原值 | B37: =未审报表!B37 -> 31 | C37: 10512385 | D37: =未审报表!D37 -> 10512385 | E37: =ABS(F37) -> 0 | F37: =C37-D37 -> 0
A38: =未审报表!A38 -> 应收股利坏账准备 | B38: =未审报表!B38 -> 32 | D38: =未审报表!D38 -> 0 | E38: =ABS(F38) -> 0 | F38: =C38-D38 -> 0
A39: =未审报表!A39 -> 应收股利 | B39: =未审报表!B39 -> 33 | C39: =C37-C38 -> 10512385 | D39: =D37-D38 -> 10512385 | E39: =ABS(F39) -> 0 | F39: =C39-D39 -> 0
A40: =未审报表!A40 -> 其他应收款原值 | B40: =未审报表!B40 -> 34 | C40: 12543397 | D40: =未审报表!D40 -> 12543397 | E40: =ABS(F40) -> 0 | F40: =C40-D40 -> 0
A41: =未审报表!A41 -> 其他应收款坏账准备 | B41: =未审报表!B41 -> 35 | D41: =未审报表!D41 -> 0 | E41: =ABS(F41) -> 0 | F41: =C41-D41 -> 0
A42: =未审报表!A42 -> 其他应收款 | B42: =未审报表!B42 -> 36 | C42: =C40-C41 -> 12543397 | D42: =D40-D41 -> 12543397 | E42: =ABS(F42) -> 0 | F42: =C42-D42 -> 0
A43: =未审报表!A43 -> 买入返售金融资产原值* | B43: =未审报表!B43 -> 37 | D43: =未审报表!D43 -> 0 | E43: =ABS(F43) -> 0 | F43: =C43-D43 -> 0
A44: =未审报表!A44 -> 买入返售金融资产减值准备* | B44: =未审报表!B44 -> 38 | D44: =未审报表!D44 -> 0 | E44: =ABS(F44) -> 0 | F44: =C44-D44 -> 0
A45: =未审报表!A45 -> 买入返售金融资产* | B45: =未审报表!B45 -> 39 | C45: =C43-C44 -> 0 | D45: =D43-D44 -> 0 | E45: =ABS(F45) -> 0 | F45: =C45-D45 -> 0
A46: =未审报表!A46 -> 存货原值 | B46: =未审报表!B46 -> 40 | D46: =未审报表!D46 -> 0 | E46: =ABS(F46) -> 0 | F46: =C46-D46 -> 0
A47: =未审报表!A47 -> 存货跌价准备 | B47: =未审报表!B47 -> 41 | D47: =未审报表!D47 -> 0 | E47: =ABS(F47) -> 0 | F47: =C47-D47 -> 0
A48: =未审报表!A48 -> 存货 | B48: =未审报表!B48 -> 42 | C48: =C46-C47 -> 0 | D48: =D46-D47 -> 0 | E48: =ABS(F48) -> 0 | F48: =C48-D48 -> 0
A49: =未审报表!A49 -> 其中：原材料 | B49: =未审报表!B49 -> 43 | D49: =未审报表!D49 -> 0 | E49: =ABS(F49) -> 0 | F49: =C49-D49 -> 0
A50: =未审报表!A50 -> 库存商品（产成品） | B50: =未审报表!B50 -> 44 | D50: =未审报表!D50 -> 0 | E50: =ABS(F50) -> 0 | F50: =C50-D50 -> 0
A51: =未审报表!A51 -> 合同资产原值 | B51: =未审报表!B51 -> 45 | D51: =未审报表!D51 -> 0 | E51: =ABS(F51) -> 0 | F51: =C51-D51 -> 0
A52: =未审报表!A52 -> 合同资产减值准备 | B52: =未审报表!B52 -> 46 | D52: =未审报表!D52 -> 0 | E52: =ABS(F52) -> 0 | F52: =C52-D52 -> 0
A53: =未审报表!A53 -> 合同资产 | B53: =未审报表!B53 -> 47 | C53: =C51-C52 -> 0 | D53: =D51-D52 -> 0 | E53: =ABS(F53) -> 0 | F53: =C53-D53 -> 0
A54: =未审报表!A54 -> 持有待售资产原值 | B54: =未审报表!B54 -> 48 | D54: =未审报表!D54 -> 0 | E54: =ABS(F54) -> 0 | F54: =C54-D54 -> 0
A55: =未审报表!A55 -> 持有待售资产减值准备 | B55: =未审报表!B55 -> 49 | D55: =未审报表!D55 -> 0 | E55: =ABS(F55) -> 0 | F55: =C55-D55 -> 0
A56: =未审报表!A56 -> 持有待售资产 | B56: =未审报表!B56 -> 50 | C56: =C54-C55 -> 0 | D56: =D54-D55 -> 0 | E56: =ABS(F56) -> 0 | F56: =C56-D56 -> 0
A57: =未审报表!A57 -> 一年内到期的非流动资产 | B57: =未审报表!B57 -> 51 | D57: =未审报表!D57 -> 0 | E57: =ABS(F57) -> 0 | F57: =C57-D57 -> 0
A58: =未审报表!A58 -> 其他流动资产 | B58: =未审报表!B58 -> 52 | C58: 19000000 | D58: =未审报表!D58 -> 19000000
A59: =未审报表!A59 -> 流动资产合计 | B59: =未审报表!B59 -> 53 | C59: =SUM(C8:C9,C12,C13:C14,C17,C20,C23,C26,C29,C32,C33,C36,C39,C42,C45,C48,C53,C56,C57:C58) -> 59421429 | D59: =SUM(D8:D9,D12,D13:D14,D17,D20,D23,D26,D29,D32,D33,D36,D39,D42,D45,D48,D53,D56,D57:D58) -> 59421429 | E59: =ABS(F59) -> 0 | F59: =C59-D59 -> 0
A60: =未审报表!A60 -> 非流动资产: | B60: =未审报表!B60 -> 54 | D60: =未审报表!D60 -> 0 | E60: =ABS(F60) -> 0 | F60: =C60-D60 -> 0
A61: =未审报表!A61 -> 发放贷款和垫款原值* | B61: =未审报表!B61 -> 55 | D61: =未审报表!D61 -> 0 | E61: =ABS(F61) -> 0 | F61: =C61-D61 -> 0
A62: =未审报表!A62 -> 发放贷款和垫款减值准备* | B62: =未审报表!B62 -> 56
A63: =未审报表!A63 -> 发放贷款和垫款* | B63: =未审报表!B63 -> 57 | C63: =C61-C62 -> 0 | D63: =D61-D62 -> 0
A64: =未审报表!A64 -> 债权投资原值 | B64: =未审报表!B64 -> 58 | D64: =未审报表!D64 -> 0 | E64: =ABS(F64) -> 0 | F64: =C64-D64 -> 0
A65: =未审报表!A65 -> 债权投资减值准备 | B65: =未审报表!B65 -> 59 | D65: =未审报表!D65 -> 0 | E65: =ABS(F65) -> 0 | F65: =C65-D65 -> 0
A66: =未审报表!A66 -> 债权投资 | B66: =未审报表!B66 -> 60 | C66: =C64-C65 -> 0 | D66: =D64-D65 -> 0 | E66: =ABS(F66) -> 0 | F66: =C66-D66 -> 0
A67: =未审报表!A67 -> 其他债权投资原值 | B67: =未审报表!B67 -> 61 | D67: =未审报表!D67 -> 0 | E67: =ABS(F67) -> 0 | F67: =C67-D67 -> 0
A68: =未审报表!A68 -> 其他债权投资减值准备 | B68: =未审报表!B68 -> 62 | D68: =未审报表!D68 -> 0 | E68: =ABS(F68) -> 0 | F68: =C68-D68 -> 0
A69: =未审报表!A69 -> 其他债权投资 | B69: =未审报表!B69 -> 63 | C69: =C67-C68 -> 0 | D69: =D67-D68 -> 0 | E69: =ABS(F69) -> 0 | F69: =C69-D69 -> 0
A70: =未审报表!A70 -> 长期应收款原值 | B70: =未审报表!B70 -> 64 | D70: =未审报表!D70 -> 0 | E70: =ABS(F70) -> 0 | F70: =C70-D70 -> 0
A71: =未审报表!A71 -> 长期应收款坏账准备 | B71: =未审报表!B71 -> 65 | D71: =未审报表!D71 -> 0 | E71: =ABS(F71) -> 0 | F71: =C71-D71 -> 0
A72: =未审报表!A72 -> 长期应收款 | B72: =未审报表!B72 -> 66 | C72: =C70-C71 -> 0 | D72: =D70-D71 -> 0 | E72: =ABS(F72) -> 0 | F72: =C72-D72 -> 0
A73: =未审报表!A73 -> 设定受益计划净资产 | B73: =未审报表!B73 -> 67 | D73: =未审报表!D73 -> 0 | E73: =ABS(F73) -> 0 | F73: =C73-D73 -> 0
A74: =未审报表!A74 -> 长期股权投资原值 | B74: =未审报表!B74 -> 68 | C74: 11290038 | D74: =未审报表!D74 -> 11290038 | E74: =ABS(F74) -> 0 | F74: =C74-D74 -> 0
A75: =未审报表!A75 -> 长期股权投资减值准备 | B75: =未审报表!B75 -> 69 | D75: =未审报表!D75 -> 0 | E75: =ABS(F75) -> 0 | F75: =C75-D75 -> 0
A76: =未审报表!A76 -> 长期股权投资 | B76: =未审报表!B76 -> 70 | C76: =C74-C75 -> 11290038 | D76: =D74-D75 -> 11290038 | E76: =ABS(F76) -> 0 | F76: =C76-D76 -> 0
A77: =未审报表!A77 -> 其他权益工具投资 | B77: =未审报表!B77 -> 71 | D77: =未审报表!D77 -> 0 | E77: =ABS(F77) -> 0 | F77: =C77-D77 -> 0
A78: =未审报表!A78 -> 其他非流动金融资产 | B78: =未审报表!B78 -> 72 | D78: =未审报表!D78 -> 0 | E78: =ABS(F78) -> 0 | F78: =C78-D78 -> 0
A79: =未审报表!A79 -> 投资性房地产原值 | B79: =未审报表!B79 -> 73 | D79: =未审报表!D79 -> 0 | E79: =ABS(F79) -> 0 | F79: =C79-D79 -> 0
A80: =未审报表!A80 -> 投资性房地产累计折旧 | B80: =未审报表!B80 -> 74 | D80: =未审报表!D80 -> 0 | E80: =ABS(F80) -> 0 | F80: =C80-D80 -> 0
A81: =未审报表!A81 -> 投资性房地产净值 | B81: =未审报表!B81 -> 75 | C81: =C79-C80 -> 0 | D81: =D79-D80 -> 0 | E81: =ABS(F81) -> 0 | F81: =C81-D81 -> 0
A82: =未审报表!A82 -> 投资性房地产减值准备 | B82: =未审报表!B82 -> 76 | D82: =未审报表!D82 -> 0 | E82: =ABS(F82) -> 0 | F82: =C82-D82 -> 0
A83: =未审报表!A83 -> 投资性房地产 | B83: =未审报表!B83 -> 77 | C83: =C81-C82 -> 0 | D83: =D81-D82 -> 0 | E83: =ABS(F83) -> 0 | F83: =C83-D83 -> 0
A84: =未审报表!A84 -> 固定资产原值 | B84: =未审报表!B84 -> 78 | D84: =未审报表!D84 -> 0 | E84: =ABS(F84) -> 0 | F84: =C84-D84 -> 0
A85: =未审报表!A85 -> 固定资产累计折旧 | B85: =未审报表!B85 -> 79 | D85: =未审报表!D85 -> 0 | E85: =ABS(F85) -> 0 | F85: =C85-D85 -> 0
A86: =未审报表!A86 -> 固定资产净值 | B86: =未审报表!B86 -> 80 | C86: =C84-C85 -> 0 | D86: =D84-D85 -> 0 | E86: =ABS(F86) -> 0 | F86: =C86-D86 -> 0
A87: =未审报表!A87 -> 固定资产减值准备 | B87: =未审报表!B87 -> 81 | D87: =未审报表!D87 -> 0 | E87: =ABS(F87) -> 0 | F87: =C87-D87 -> 0
A88: =未审报表!A88 -> 固定资产 | B88: =未审报表!B88 -> 82 | C88: =C86-C87 -> 0 | D88: =D86-D87 -> 0 | E88: =ABS(F88) -> 0 | F88: =C88-D88 -> 0
A89: =未审报表!A89 -> 固定资产清理 | B89: =未审报表!B89 -> 83 | D89: =未审报表!D89 -> 0 | E89: =ABS(F89) -> 0 | F89: =C89-D89 -> 0
A90: =未审报表!A90 -> 在建工程原值 | B90: =未审报表!B90 -> 84 | D90: =未审报表!D90 -> 0 | E90: =ABS(F90) -> 0 | F90: =C90-D90 -> 0
A91: =未审报表!A91 -> 在建工程减值准备 | B91: =未审报表!B91 -> 85 | D91: =未审报表!D91 -> 0 | E91: =ABS(F91) -> 0 | F91: =C91-D91 -> 0
A92: =未审报表!A92 -> 在建工程 | B92: =未审报表!B92 -> 86 | C92: =C90-C91 -> 0 | D92: =D90-D91 -> 0 | E92: =ABS(F92) -> 0 | F92: =C92-D92 -> 0
A93: =未审报表!A93 -> 工程物资原值 | B93: =未审报表!B93 -> 87 | D93: =未审报表!D93 -> 0 | E93: =ABS(F93) -> 0 | F93: =C93-D93 -> 0
A94: =未审报表!A94 -> 工程物资减值准备 | B94: =未审报表!B94 -> 88 | D94: =未审报表!D94 -> 0 | E94: =ABS(F94) -> 0 | F94: =C94-D94 -> 0
A95: =未审报表!A95 -> 工程物资 | B95: =未审报表!B95 -> 89 | C95: =C93-C94 -> 0 | D95: =D93-D94 -> 0 | E95: =ABS(F95) -> 0 | F95: =C95-D95 -> 0
A96: =未审报表!A96 -> 生产性生物资产原值 | B96: =未审报表!B96 -> 90 | D96: =未审报表!D96 -> 0 | E96: =ABS(F96) -> 0 | F96: =C96-D96 -> 0
A97: =未审报表!A97 -> 生产性生物资产累计折旧 | B97: =未审报表!B97 -> 91 | D97: =未审报表!D97 -> 0 | E97: =ABS(F97) -> 0 | F97: =C97-D97 -> 0
A98: =未审报表!A98 -> 生产性生物资产净值 | B98: =未审报表!B98 -> 92 | C98: =C96-C97 -> 0 | D98: =D96-D97 -> 0 | E98: =ABS(F98) -> 0 | F98: =C98-D98 -> 0
A99: =未审报表!A99 -> 生产性生物资产减值准备 | B99: =未审报表!B99 -> 93 | D99: =未审报表!D99 -> 0 | E99: =ABS(F99) -> 0 | F99: =C99-D99 -> 0
A100: =未审报表!A100 -> 生产性生物资产 | B100: =未审报表!B100 -> 94 | C100: =C98-C99 -> 0 | D100: =D98-D99 -> 0 | E100: =ABS(F100) -> 0 | F100: =C100-D100 -> 0
A101: =未审报表!A101 -> 油气资产原值 | B101: =未审报表!B101 -> 95 | D101: =未审报表!D101 -> 0 | E101: =ABS(F101) -> 0 | F101: =C101-D101 -> 0
A102: =未审报表!A102 -> 油气资产累计折旧 | B102: =未审报表!B102 -> 96 | D102: =未审报表!D102 -> 0 | E102: =ABS(F102) -> 0 | F102: =C102-D102 -> 0
A103: =未审报表!A103 -> 油气资产净值 | B103: =未审报表!B103 -> 97 | C103: =C101-C102 -> 0 | D103: =D101-D102 -> 0 | E103: =ABS(F103) -> 0 | F103: =C103-D103 -> 0
...

Sheet TB
D1: 期末报表
A2: =CONCATENATE("客户名称：",参数!D3) -> 客户名称：二锅头 | C2: =CONCATENATE("编制：",参数!D17) -> 编制：张 | E2: =CONCATENATE("日期：",TEXT(NOW(),"yyyy.mm.dd")) -> 日期：2025.11.06 | I2: 索引：A2-1
A3: =CONCATENATE("会计时点：",TEXT(参数!D12,"yyyy.mm.dd")) -> 会计时点：2022.12.31 | C3: =CONCATENATE("复核：",参数!D18) -> 复核：刘 | E3: 日期： | I3: 分页：
A4: =CONCATENATE("会计年度：",TEXT(参数!D10,"yyyy.mm.dd")) -> 会计年度：2022年度
A5: =IF((ROUND(I127,2))=(ROUND(I190,2)),"资 产","报表未调平!") -> 资 产 | B5: 企业原报数 | C5: 账项调整 | E5: 报表调整 | G5: 其他调整 | I5: 审定数
C6: 借方 | D6: 贷方 | E6: 借方 | F6: 贷方 | G6: 借方 | H6: 贷方
A7: =未审报表!A7 -> 流动资产： | I7: =B7 -> 0 | J7: =A7=未审报表!A7 -> TRUE | K7: =审定报表!A7=TB!A7 -> TRUE
A8: =未审报表!A8 -> 货币资金 | B8: =未审报表!C8 -> 17053593 | C8: =SUMIFS(调整事项汇总表!$I$7:$I$10020,调整事项汇总表!$D$7:$D$10020,"账项调整",调整事项汇总表!$E$7:$E$10020,IF(OR(MID(TRIM($A8),2,1)="：",MID(TRIM($A8),2,1)="、"),REPLACEB(TRIM($A8),1,4,""),TRIM($A8))) -> 0 | D8: =SUMIFS(调整事项汇总表!$J$7:$J$10020,调整事项汇总表!$D$7:$D$10020,"账项调整",调整事项汇总表!$E$7:$E$10020,IF(OR(MID(TRIM($A8),2,1)="：",MID(TRIM($A8),2,1)="、"),REPLACEB(TRIM($A8),1,4,""),TRIM($A8))) -> 0 | E8: =SUMIFS(调整事项汇总表!$I$7:$I$10020,调整事项汇总表!$D$7:$D$10020,"报表调整",调整事项汇总表!$E$7:$E$10020,IF(OR(MID(TRIM($A8),2,1)="：",MID(TRIM($A8),2,1)="、"),REPLACEB(TRIM($A8),1,4,""),TRIM($A8))) -> 0 | F8: =SUMIFS(调整事项汇总表!$J$7:$J$10020,调整事项汇总表!$D$7:$D$10020,"报表调整",调整事项汇总表!$E$7:$E$10020,IF(OR(MID(TRIM($A8),2,1)="：",MID(TRIM($A8),2,1)="、"),REPLACEB(TRIM($A8),1,4,""),TRIM($A8))) -> 0 | G8: =SUMIFS(调整事项汇总表!$I$7:$I$10020,调整事项汇总表!$D$7:$D$10020,"其他",调整事项汇总表!$E$7:$E$10020,IF(OR(MID(TRIM($A8),2,1)="：",MID(TRIM($A8),2,1)="、"),REPLACEB(TRIM($A8),1,4,""),TRIM($A8))) -> 0 | H8: =SUMIFS(调整事项汇总表!$J$7:$J$10020,调整事项汇总表!$D$7:$D$10020,"其他",调整事项汇总表!$E$7:$E$10020,IF(OR(MID(TRIM($A8),2,1)="：",MID(TRIM($A8),2,1)="、"),REPLACEB(TRIM($A8),1,4,""),TRIM($A8))) -> 0 | I8: =B8+C8+E8+G8-H8-F8-D8 -> 17053593 | J8: =A8=未审报表!A8 -> TRUE | K8: =审定报表!A8=TB!A8 -> TRUE
A9: =未审报表!A9 -> 结算备付金* | B9: =未审报表!C9 -> 0 | C9: =SUMIFS(调整事项汇总表!$I$7:$I$10020,调整事项汇总表!$D$7:$D$10020,"账项调整",调整事项汇总表!$E$7:$E$10020,IF(OR(MID(TRIM($A9),2,1)="：",MID(TRIM($A9),2,1)="、"),REPLACEB(TRIM($A9),1,4,""),TRIM($A9))) -> 0 | D9: =SUMIFS(调整事项汇总表!$J$7:$J$10020,调整事项汇总表!$D$7:$D$10020,"账项调整",调整事项汇总表!$E$7:$E$10020,IF(OR(MID(TRIM($A9),2,1)="：",MID(TRIM($A9),2,1)="、"),REPLACEB(TRIM($A9),1,4,""),TRIM($A9))) -> 0 | E9: =SUMIFS(调整事项汇总表!$I$7:$I$10020,调整事项汇总表!$D$7:$D$10020,"报表调整",调整事项汇总表!$E$7:$E$10020,IF(OR(MID(TRIM($A9),2,1)="：",MID(TRIM($A9),2,1)="、"),REPLACEB(TRIM($A9),1,4,""),TRIM($A9))) -> 0 | F9: =SUMIFS(调整事项汇总表!$J$7:$J$10020,调整事项汇总表!$D$7:$D$10020,"报表调整",调整事项汇总表!$E$7:$E$10020,IF(OR(MID(TRIM($A9),2,1)="：",MID(TRIM($A9),2,1)="、"),REPLACEB(TRIM($A9),1,4,""),TRIM($A9))) -> 0 | G9: =SUMIFS(调整事项汇总表!$I$7:$I$10020,调整事项汇总表!$D$7:$D$10020,"其他",调整事项汇总表!$E$7:$E$10020,IF(OR(MID(TRIM($A9),2,1)="：",MID(TRIM($A9),2,1)="、"),REPLACEB(TRIM($A9),1,4,""),TRIM($A9))) -> 0 | H9: =SUMIFS(调整事项汇总表!$J$7:$J$10020,调整事项汇总表!$D$7:$D$10020,"其他",调整事项汇总表!$E$7:$E$10020,IF(OR(MID(TRIM($A9),2,1)="：",MID(TRIM($A9),2,1)="、"),REPLACEB(TRIM($A9),1,4,""),TRIM($A9))) -> 0 | I9: =B9+C9+E9+G9-H9-F9-D9 -> 0 | J9: =A9=未审报表!A9 -> TRUE | K9: =审定报表!A9=TB!A9 -> TRUE
A10: =未审报表!A10 -> 拆出资金原值* | B10: =未审报表!C10 -> 0 | C10: =SUMIFS(调整事项汇总表!$I$7:$I$10020,调整事项汇总表!$D$7:$D$10020,"账项调整",调整事项汇总表!$E$7:$E$10020,IF(OR(MID(TRIM($A10),2,1)="：",MID(TRIM($A10),2,1)="、"),REPLACEB(TRIM($A10),1,4,""),TRIM($A10))) -> 0 | D10: =SUMIFS(调整事项汇总表!$J$7:$J$10020,调整事项汇总表!$D$7:$D$10020,"账项调整",调整事项汇总表!$E$7:$E$10020,IF(OR(MID(TRIM($A10),2,1)="：",MID(TRIM($A10),2,1)="、"),REPLACEB(TRIM($A10),1,4,""),TRIM($A10))) -> 0 | E10: =SUMIFS(调整事项汇总表!$I$7:$I$10020,调整事项汇总表!$D$7:$D$10020,"报表调整",调整事项汇总表!$E$7:$E$10020,IF(OR(MID(TRIM($A10),2,1)="：",MID(TRIM($A10),2,1)="、"),REPLACEB(TRIM($A10),1,4,""),TRIM($A10))) -> 0 | F10: =SUMIFS(调整事项汇总表!$J$7:$J$10020,调整事项汇总表!$D$7:$D$10020,"报表调整",调整事项汇总表!$E$7:$E$10020,IF(OR(MID(TRIM($A10),2,1)="：",MID(TRIM($A10),2,1)="、"),REPLACEB(TRIM($A10),1,4,""),TRIM($A10))) -> 0 | G10: =SUMIFS(调整事项汇总表!$I$7:$I$10020,调整事项汇总表!$D$7:$D$10020,"其他",调整事项汇总表!$E$7:$E$10020,IF(OR(MID(TRIM($A10),2,1)="：",MID(TRIM($A10),2,1)="、"),REPLACEB(TRIM($A10),1,4,""),TRIM($A10))) -> 0 | H10: =SUMIFS(调整事项汇总表!$J$7:$J$10020,调整事项汇总表!$D$7:$D$10020,"其他",调整事项汇总表!$E$7:$E$10020,IF(OR(MID(TRIM($A10),2,1)="：",MID(TRIM($A10),2,1)="、"),REPLACEB(TRIM($A10),1,4,""),TRIM($A10))) -> 0 | I10: =B10+C10+E10+G10-H10-F10-D10 -> 0 | J10: =A10=未审报表!A10 -> TRUE | K10: =审定报表!A10=TB!A10 -> TRUE
A11: =未审报表!A11 -> 拆出资金减值准备* | B11: =未审报表!C11 -> 0 | C11: =SUMIFS(调整事项汇总表!$I$7:$I$10020,调整事项汇总表!$D$7:$D$10020,"账项调整",调整事项汇总表!$E$7:$E$10020,IF(OR(MID(TRIM($A11),2,1)="：",MID(TRIM($A11),2,1)="、"),REPLACEB(TRIM($A11),1,4,""),TRIM($A11))) -> 0 | D11: =SUMIFS(调整事项汇总表!$J$7:$J$10020,调整事项汇总表!$D$7:$D$10020,"账项调整",调整事项汇总表!$E$7:$E$10020,IF(OR(MID(TRIM($A11),2,1)="：",MID(TRIM($A11),2,1)="、"),REPLACEB(TRIM($A11),1,4,""),TRIM($A11))) -> 0 | E11: =SUMIFS(调整事项汇总表!$I$7:$I$10020,调整事项汇总表!$D$7:$D$10020,"报表调整",调整事项汇总表!$E$7:$E$10020,IF(OR(MID(TRIM($A11),2,1)="：",MID(TRIM($A11),2,1)="、"),REPLACEB(TRIM($A11),1,4,""),TRIM($A11))) -> 0 | F11: =SUMIFS(调整事项汇总表!$J$7:$J$10020,调整事项汇总表!$D$7:$D$10020,"报表调整",调整事项汇总表!$E$7:$E$10020,IF(OR(MID(TRIM($A11),2,1)="：",MID(TRIM($A11),2,1)="、"),REPLACEB(TRIM($A11),1,4,""),TRIM($A11))) -> 0 | G11: =SUMIFS(调整事项汇总表!$I$7:$I$10020,调整事项汇总表!$D$7:$D$10020,"其他",调整事项汇总表!$E$7:$E$10020,IF(OR(MID(TRIM($A11),2,1)="：",MID(TRIM($A11),2,1)="、"),REPLACEB(TRIM($A11),1,4,""),TRIM($A11))) -> 0 | H11: =SUMIFS(调整事项汇总表!$J$7:$J$10020,调整事项汇总表!$D$7:$D$10020,"其他",调整事项汇总表!$E$7:$E$10020,IF(OR(MID(TRIM($A11),2,1)="：",MID(TRIM($A11),2,1)="、"),REPLACEB(TRIM($A11),1,4,""),TRIM($A11))) -> 0 | I11: =B11+D11+F11+H11-G11-E11-C11 -> 0 | J11: =A11=未审报表!A11 -> TRUE | K11: =审定报表!A11=TB!A11 -> TRUE
A12: =未审报表!A12 -> 拆出资金* | B12: =未审报表!C12 -> 0 | C12: =C10+C11 -> 0 | D12: =D10+D11 -> 0 | E12: =E10+E11 -> 0 | F12: =F10+F11 -> 0 | G12: =G10+G11 -> 0 | H12: =H10+H11 -> 0 | I12: =B12+C12+E12+G12-H12-F12-D12 -> 0 | J12: =A12=未审报表!A12 -> TRUE | K12: =审定报表!A12=TB!A12 -> TRUE
A13: =未审报表!A13 -> 交易性金融资产 | B13: =未审报表!C13 -> 0 | C13: =SUMIFS(调整事项汇总表!$I$7:$I$10020,调整事项汇总表!$D$7:$D$10020,"账项调整",调整事项汇总表!$E$7:$E$10020,IF(OR(MID(TRIM($A13),2,1)="：",MID(TRIM($A13),2,1)="、"),REPLACEB(TRIM($A13),1,4,""),TRIM($A13))) -> 0 | D13: =SUMIFS(调整事项汇总表!$J$7:$J$10020,调整事项汇总表!$D$7:$D$10020,"账项调整",调整事项汇总表!$E$7:$E$10020,IF(OR(MID(TRIM($A13),2,1)="：",MID(TRIM($A13),2,1)="、"),REPLACEB(TRIM($A13),1,4,""),TRIM($A13))) -> 0 | E13: =SUMIFS(调整事项汇总表!$I$7:$I$10020,调整事项汇总表!$D$7:$D$10020,"报表调整",调整事项汇总表!$E$7:$E$10020,IF(OR(MID(TRIM($A13),2,1)="：",MID(TRIM($A13),2,1)="、"),REPLACEB(TRIM($A13),1,4,""),TRIM($A13))) -> 0 | F13: =SUMIFS(调整事项汇总表!$J$7:$J$10020,调整事项汇总表!$D$7:$D$10020,"报表调整",调整事项汇总表!$E$7:$E$10020,IF(OR(MID(TRIM($A13),2,1)="：",MID(TRIM($A13),2,1)="、"),REPLACEB(TRIM($A13),1,4,""),TRIM($A13))) -> 0 | G13: =SUMIFS(调整事项汇总表!$I$7:$I$10020,调整事项汇总表!$D$7:$D$10020,"其他",调整事项汇总表!$E$7:$E$10020,IF(OR(MID(TRIM($A13),2,1)="：",MID(TRIM($A13),2,1)="、"),REPLACEB(TRIM($A13),1,4,""),TRIM($A13))) -> 0 | H13: =SUMIFS(调整事项汇总表!$J$7:$J$10020,调整事项汇总表!$D$7:$D$10020,"其他",调整事项汇总表!$E$7:$E$10020,IF(OR(MID(TRIM($A13),2,1)="：",MID(TRIM($A13),2,1)="、"),REPLACEB(TRIM($A13),1,4,""),TRIM($A13))) -> 0 | I13: =B13+C13+E13+G13-H13-F13-D13 -> 0 | J13: =A13=未审报表!A13 -> TRUE | K13: =审定报表!A13=TB!A13 -> TRUE
A14: =未审报表!A14 -> 衍生金融资产 | B14: =未审报表!C14 -> 0 | C14: =SUMIFS(调整事项汇总表!$I$7:$I$10020,调整事项汇总表!$D$7:$D$10020,"账项调整",调整事项汇总表!$E$7:$E$10020,IF(OR(MID(TRIM($A14),2,1)="：",MID(TRIM($A14),2,1)="、"),REPLACEB(TRIM($A14),1,4,""),TRIM($A14))) -> 0 | D14: =SUMIFS(调整事项汇总表!$J$7:$J$10020,调整事项汇总表!$D$7:$D$10020,"账项调整",调整事项汇总表!$E$7:$E$10020,IF(OR(MID(TRIM($A14),2,1)="：",MID(TRIM($A14),2,1)="、"),REPLACEB(TRIM($A14),1,4,""),TRIM($A14))) -> 0 | E14: =SUMIFS(调整事项汇总表!$I$7:$I$10020,调整事项汇总表!$D$7:$D$10020,"报表调整",调整事项汇总表!$E$7:$E$10020,IF(OR(MID(TRIM($A14),2,1)="：",MID(TRIM($A14),2,1)="、"),REPLACEB(TRIM($A14),1,4,""),TRIM($A14))) -> 0 | F14: =SUMIFS(调整事项汇总表!$J$7:$J$10020,调整事项汇总表!$D$7:$D$10020,"报表调整",调整事项汇总表!$E$7:$E$10020,IF(OR(MID(TRIM($A14),2,1)="：",MID(TRIM($A14),2,1)="、"),REPLACEB(TRIM($A14),1,4,""),TRIM($A14))) -> 0 | G14: =SUMIFS(调整事项汇总表!$I$7:$I$10020,调整事项汇总表!$D$7:$D$10020,"其他",调整事项汇总表!$E$7:$E$10020,IF(OR(MID(TRIM($A14),2,1)="：",MID(TRIM($A14),2,1)="、"),REPLACEB(TRIM($A14),1,4,""),TRIM($A14))) -> 0 | H14: =SUMIFS(调整事项汇总表!$J$7:$J$10020,调整事项汇总表!$D$7:$D$10020,"其他",调整事项汇总表!$E$7:$E$10020,IF(OR(MID(TRIM($A14),2,1)="：",MID(TRIM($A14),2,1)="、"),REPLACEB(TRIM($A14),1,4,""),TRIM($A14))) -> 0 | I14: =B14+C14+E14+G14-H14-F14-D14 -> 0 | J14: =A14=未审报表!A14 -> TRUE | K14: =审定报表!A14=TB!A14 -> TRUE
A15: =未审报表!A15 -> 应收票据原值 | B15: =未审报表!C15 -> 0 | C15: =SUMIFS(调整事项汇总表!$I$7:$I$10020,调整事项汇总表!$D$7:$D$10020,"账项调整",调整事项汇总表!$E$7:$E$10020,IF(OR(MID(TRIM($A15),2,1)="：",MID(TRIM($A15),2,1)="、"),REPLACEB(TRIM($A15),1,4,""),TRIM($A15))) -> 0 | D15: =SUMIFS(调整事项汇总表!$J$7:$J$10020,调整事项汇总表!$D$7:$D$10020,"账项调整",调整事项汇总表!$E$7:$E$10020,IF(OR(MID(TRIM($A15),2,1)="：",MID(TRIM($A15),2,1)="、"),REPLACEB(TRIM($A15),1,4,""),TRIM($A15))) -> 0 | E15: =SUMIFS(调整事项汇总表!$I$7:$I$10020,调整事项汇总表!$D$7:$D$10020,"报表调整",调整事项汇总表!$E$7:$E$10020,IF(OR(MID(TRIM($A15),2,1)="：",MID(TRIM($A15),2,1)="、"),REPLACEB(TRIM($A15),1,4,""),TRIM($A15))) -> 0 | F15: =SUMIFS(调整事项汇总表!$J$7:$J$10020,调整事项汇总表!$D$7:$D$10020,"报表调整",调整事项汇总表!$E$7:$E$10020,IF(OR(MID(TRIM($A15),2,1)="：",MID(TRIM($A15),2,1)="、"),REPLACEB(TRIM($A15),1,4,""),TRIM($A15))) -> 0 | G15: =SUMIFS(调整事项汇总表!$I$7:$I$10020,调整事项汇总表!$D$7:$D$10020,"其他",调整事项汇总表!$E$7:$E$10020,IF(OR(MID(TRIM($A15),2,1)="：",MID(TRIM($A15),2,1)="、"),REPLACEB(TRIM($A15),1,4,""),TRIM($A15))) -> 0 | H15: =SUMIFS(调整事项汇总表!$J$7:$J$10020,调整事项汇总表!$D$7:$D$10020,"其他",调整事项汇总表!$E$7:$E$10020,IF(OR(MID(TRIM($A15),2,1)="：",MID(TRIM($A15),2,1)="、"),REPLACEB(TRIM($A15),1,4,""),TRIM($A15))) -> 0 | I15: =B15+C15+E15+G15-H15-F15-D15 -> 0 | J15: =A15=未审报表!A15 -> TRUE | K15: =审定报表!A15=TB!A15 -> TRUE
A16: =未审报表!A16 -> 应收票据坏账准备 | B16: =未审报表!C16 -> 0 | C16: =SUMIFS(调整事项汇总表!$I$7:$I$10020,调整事项汇总表!$D$7:$D$10020,"账项调整",调整事项汇总表!$E$7:$E$10020,IF(OR(MID(TRIM($A16),2,1)="：",MID(TRIM($A16),2,1)="、"),REPLACEB(TRIM($A16),1,4,""),TRIM($A16))) -> 0 | D16: =SUMIFS(调整事项汇总表!$J$7:$J$10020,调整事项汇总表!$D$7:$D$10020,"账项调整",调整事项汇总表!$E$7:$E$10020,IF(OR(MID(TRIM($A16),2,1)="：",MID(TRIM($A16),2,1)="、"),REPLACEB(TRIM($A16),1,4,""),TRIM($A16))) -> 0 | E16: =SUMIFS(调整事项汇总表!$I$7:$I$10020,调整事项汇总表!$D$7:$D$10020,"报表调整",调整事项汇总表!$E$7:$E$10020,IF(OR(MID(TRIM($A16),2,1)="：",MID(TRIM($A16),2,1)="、"),REPLACEB(TRIM($A16),1,4,""),TRIM($A16))) -> 0 | F16: =SUMIFS(调整事项汇总表!$J$7:$J$10020,调整事项汇总表!$D$7:$D$10020,"报表调整",调整事项汇总表!$E$7:$E$10020,IF(OR(MID(TRIM($A16),2,1)="：",MID(TRIM($A16),2,1)="、"),REPLACEB(TRIM($A16),1,4,""),TRIM($A16))) -> 0 | G16: =SUMIFS(调整事项汇总表!$I$7:$I$10020,调整事项汇总表!$D$7:$D$10020,"其他",调整事项汇总表!$E$7:$E$10020,IF(OR(MID(TRIM($A16),2,1)="：",MID(TRIM($A16),2,1)="、"),REPLACEB(TRIM($A16),1,4,""),TRIM($A16))) -> 0 | H16: =SUMIFS(调整事项汇总表!$J$7:$J$10020,调整事项汇总表!$D$7:$D$10020,"其他",调整事项汇总表!$E$7:$E$10020,IF(OR(MID(TRIM($A16),2,1)="：",MID(TRIM($A16),2,1)="、"),REPLACEB(TRIM($A16),1,4,""),TRIM($A16))) -> 0 | I16: =B16+D16+F16+H16-G16-E16-C16 -> 0 | J16: =A16=未审报表!A16 -> TRUE | K16: =审定报表!A16=TB!A16 -> TRUE
A17: =未审报表!A17 -> 应收票据 | B17: =未审报表!C17 -> 0 | C17: =C15+C16 -> 0 | D17: =D15+D16 -> 0 | E17: =E15+E16 -> 0 | F17: =F15+F16 -> 0 | G17: =G15+G16 -> 0 | H17: =H15+H16 -> 0 | I17: =B17+C17+E17+G17-H17-F17-D17 -> 0 | J17: =A17=未审报表!A17 -> TRUE | K17: =审定报表!A17=TB!A17 -> TRUE
A18: =未审报表!A18 -> 应收账款原值 | B18: =未审报表!C18 -> 15449122 | C18: =SUMIFS(调整事项汇总表!$I$7:$I$10020,调整事项汇总表!$D$7:$D$10020,"账项调整",调整事项汇总表!$E$7:$E$10020,IF(OR(MID(TRIM($A18),2,1)="：",MID(TRIM($A18),2,1)="、"),REPLACEB(TRIM($A18),1,4,""),TRIM($A18))) -> 3862755.9 | D18: =SUMIFS(调整事项汇总表!$J$7:$J$10020,调整事项汇总表!$D$7:$D$10020,"账项调整",调整事项汇总表!$E$7:$E$10020,IF(OR(MID(TRIM($A18),2,1)="：",MID(TRIM($A18),2,1)="、"),REPLACEB(TRIM($A18),1,4,""),TRIM($A18))) -> 0 | E18: =SUMIFS(调整事项汇总表!$I$7:$I$10020,调整事项汇总表!$D$7:$D$10020,"报表调整",调整事项汇总表!$E$7:$E$10020,IF(OR(MID(TRIM($A18),2,1)="：",MID(TRIM($A18),2,1)="、"),REPLACEB(TRIM($A18),1,4,""),TRIM($A18))) -> 0 | F18: =SUMIFS(调整事项汇总表!$J$7:$J$10020,调整事项汇总表!$D$7:$D$10020,"报表调整",调整事项汇总表!$E$7:$E$10020,IF(OR(MID(TRIM($A18),2,1)="：",MID(TRIM($A18),2,1)="、"),REPLACEB(TRIM($A18),1,4,""),TRIM($A18))) -> 0 | G18: =SUMIFS(调整事项汇总表!$I$7:$I$10020,调整事项汇总表!$D$7:$D$10020,"其他",调整事项汇总表!$E$7:$E$10020,IF(OR(MID(TRIM($A18),2,1)="：",MID(TRIM($A18),2,1)="、"),REPLACEB(TRIM($A18),1,4,""),TRIM($A18))) -> 0 | H18: =SUMIFS(调整事项汇总表!$J$7:$J$10020,调整事项汇总表!$D$7:$D$10020,"其他",调整事项汇总表!$E$7:$E$10020,IF(OR(MID(TRIM($A18),2,1)="：",MID(TRIM($A18),2,1)="、"),REPLACEB(TRIM($A18),1,4,""),TRIM($A18))) -> 0 | I18: =B18+C18+E18+G18-H18-F18-D18 -> 19311878 | J18: =A18=未审报表!A18 -> TRUE | K18: =审定报表!A18=TB!A18 -> TRUE
A19: =未审报表!A19 -> 应收账款坏账准备 | B19: =未审报表!C19 -> 1423224.6 | C19: =SUMIFS(调整事项汇总表!$I$7:$I$10020,调整事项汇总表!$D$7:$D$10020,"账项调整",调整事项汇总表!$E$7:$E$10020,IF(OR(MID(TRIM($A19),2,1)="：",MID(TRIM($A19),2,1)="、"),REPLACEB(TRIM($A19),1,4,""),TRIM($A19))) -> 0 | D19: =SUMIFS(调整事项汇总表!$J$7:$J$10020,调整事项汇总表!$D$7:$D$10020,"账项调整",调整事项汇总表!$E$7:$E$10020,IF(OR(MID(TRIM($A19),2,1)="：",MID(TRIM($A19),2,1)="、"),REPLACEB(TRIM($A19),1,4,""),TRIM($A19))) -> 207942.74 | E19: =SUMIFS(调整事项汇总表!$I$7:$I$10020,调整事项汇总表!$D$7:$D$10020,"报表调整",调整事项汇总表!$E$7:$E$10020,IF(OR(MID(TRIM($A19),2,1)="：",MID(TRIM($A19),2,1)="、"),REPLACEB(TRIM($A19),1,4,""),TRIM($A19))) -> 0 | F19: =SUMIFS(调整事项汇总表!$J$7:$J$10020,调整事项汇总表!$D$7:$D$10020,"报表调整",调整事项汇总表!$E$7:$E$10020,IF(OR(MID(TRIM($A19),2,1)="：",MID(TRIM($A19),2,1)="、"),REPLACEB(TRIM($A19),1,4,""),TRIM($A19))) -> 0 | G19: =SUMIFS(调整事项汇总表!$I$7:$I$10020,调整事项汇总表!$D$7:$D$10020,"其他",调整事项汇总表!$E$7:$E$10020,IF(OR(MID(TRIM($A19),2,1)="：",MID(TRIM($A19),2,1)="、"),REPLACEB(TRIM($A19),1,4,""),TRIM($A19))) -> 0 | H19: =SUMIFS(调整事项汇总表!$J$7:$J$10020,调整事项汇总表!$D$7:$D$10020,"其他",调整事项汇总表!$E$7:$E$10020,IF(OR(MID(TRIM($A19),2,1)="：",MID(TRIM($A19),2,1)="、"),REPLACEB(TRIM($A19),1,4,""),TRIM($A19))) -> 0 | I19: =B19+D19+F19+H19-G19-E19-C19 -> 1631167.3 | J19: =A19=未审报表!A19 -> TRUE | K19: =审定报表!A19=TB!A19 -> TRUE
A20: =未审报表!A20 -> 应收账款 | B20: =未审报表!C20 -> 14025898 | C20: =C18+C19 -> 3862755.9 | D20: =D18+D19 -> 207942.74 | E20: =E18+E19 -> 0 | F20: =F18+F19 -> 0 | G20: =G18+G19 -> 0 | H20: =H18+H19 -> 0 | I20: =B20+C20+E20+G20-H20-F20-D20 -> 17680711 | J20: =A20=未审报表!A20 -> TRUE | K20: =审定报表!A20=TB!A20 -> TRUE
A21: =未审报表!A21 -> 应收款项融资原值 | B21: =未审报表!C21 -> 0 | C21: =SUMIFS(调整事项汇总表!$I$7:$I$10020,调整事项汇总表!$D$7:$D$10020,"账项调整",调整事项汇总表!$E$7:$E$10020,IF(OR(MID(TRIM($A21),2,1)="：",MID(TRIM($A21),2,1)="、"),REPLACEB(TRIM($A21),1,4,""),TRIM($A21))) -> 0 | D21: =SUMIFS(调整事项汇总表!$J$7:$J$10020,调整事项汇总表!$D$7:$D$10020,"账项调整",调整事项汇总表!$E$7:$E$10020,IF(OR(MID(TRIM($A21),2,1)="：",MID(TRIM($A21),2,1)="、"),REPLACEB(TRIM($A21),1,4,""),TRIM($A21))) -> 0 | E21: =SUMIFS(调整事项汇总表!$I$7:$I$10020,调整事项汇总表!$D$7:$D$10020,"报表调整",调整事项汇总表!$E$7:$E$10020,IF(OR(MID(TRIM($A21),2,1)="：",MID(TRIM($A21),2,1)="、"),REPLACEB(TRIM($A21),1,4,""),TRIM($A21))) -> 0 | F21: =SUMIFS(调整事项汇总表!$J$7:$J$10020,调整事项汇总表!$D$7:$D$10020,"报表调整",调整事项汇总表!$E$7:$E$10020,IF(OR(MID(TRIM($A21),2,1)="：",MID(TRIM($A21),2,1)="、"),REPLACEB(TRIM($A21),1,4,""),TRIM($A21))) -> 0 | G21: =SUMIFS(调整事项汇总表!$I$7:$I$10020,调整事项汇总表!$D$7:$D$10020,"其他",调整事项汇总表!$E$7:$E$10020,IF(OR(MID(TRIM($A21),2,1)="：",MID(TRIM($A21),2,1)="、"),REPLACEB(TRIM($A21),1,4,""),TRIM($A21))) -> 0 | H21: =SUMIFS(调整事项汇总表!$J$7:$J$10020,调整事项汇总表!$D$7:$D$10020,"其他",调整事项汇总表!$E$7:$E$10020,IF(OR(MID(TRIM($A21),2,1)="：",MID(TRIM($A21),2,1)="、"),REPLACEB(TRIM($A21),1,4,""),TRIM($A21))) -> 0 | I21: =B21+C21+E21+G21-H21-F21-D21 -> 0 | J21: =A21=未审报表!A21 -> TRUE | K21: =审定报表!A21=TB!A21 -> TRUE
A22: =未审报表!A22 -> 应收款项融资坏账准备 | B22: =未审报表!C22 -> 0 | C22: =SUMIFS(调整事项汇总表!$I$7:$I$10020,调整事项汇总表!$D$7:$D$10020,"账项调整",调整事项汇总表!$E$7:$E$10020,IF(OR(MID(TRIM($A22),2,1)="：",MID(TRIM($A22),2,1)="、"),REPLACEB(TRIM($A22),1,4,""),TRIM($A22))) -> 0 | D22: =SUMIFS(调整事项汇总表!$J$7:$J$10020,调整事项汇总表!$D$7:$D$10020,"账项调整",调整事项汇总表!$E$7:$E$10020,IF(OR(MID(TRIM($A22),2,1)="：",MID(TRIM($A22),2,1)="、"),REPLACEB(TRIM($A22),1,4,""),TRIM($A22))) -> 0 | E22: =SUMIFS(调整事项汇总表!$I$7:$I$10020,调整事项汇总表!$D$7:$D$10020,"报表调整",调整事项汇总表!$E$7:$E$10020,IF(OR(MID(TRIM($A22),2,1)="：",MID(TRIM($A22),2,1)="、"),REPLACEB(TRIM($A22),1,4,""),TRIM($A22))) -> 0 | F22: =SUMIFS(调整事项汇总表!$J$7:$J$10020,调整事项汇总表!$D$7:$D$10020,"报表调整",调整事项汇总表!$E$7:$E$10020,IF(OR(MID(TRIM($A22),2,1)="：",MID(TRIM($A22),2,1)="、"),REPLACEB(TRIM($A22),1,4,""),TRIM($A22))) -> 0 | G22: =SUMIFS(调整事项汇总表!$I$7:$I$10020,调整事项汇总表!$D$7:$D$10020,"其他",调整事项汇总表!$E$7:$E$10020,IF(OR(MID(TRIM($A22),2,1)="：",MID(TRIM($A22),2,1)="、"),REPLACEB(TRIM($A22),1,4,""),TRIM($A22))) -> 0 | H22: =SUMIFS(调整事项汇总表!$J$7:$J$10020,调整事项汇总表!$D$7:$D$10020,"其他",调整事项汇总表!$E$7:$E$10020,IF(OR(MID(TRIM($A22),2,1)="：",MID(TRIM($A22),2,1)="、"),REPLACEB(TRIM($A22),1,4,""),TRIM($A22))) -> 0 | I22: =B22+D22+F22+H22-G22-E22-C22 -> 0 | J22: =A22=未审报表!A22 -> TRUE | K22: =审定报表!A22=TB!A22 -> TRUE
A23: =未审报表!A23 -> 应收款项融资 | B23: =未审报表!C23 -> 0 | C23: =C21+C22 -> 0 | D23: =D21+D22 -> 0 | E23: =E21+E22 -> 0 | F23: =F21+F22 -> 0 | G23: =G21+G22 -> 0 | H23: =H21+H22 -> 0 | I23: =B23+C23+E23+G23-H23-F23-D23 -> 0 | J23: =A23=未审报表!A23 -> TRUE | K23: =审定报表!A23=TB!A23 -> TRUE
A24: =未审报表!A24 -> 预付款项原值 | B24: =未审报表!C24 -> 574623.4 | C24: =SUMIFS(调整事项汇总表!$I$7:$I$10020,调整事项汇总表!$D$7:$D$10020,"账项调整",调整事项汇总表!$E$7:$E$10020,IF(OR(MID(TRIM($A24),2,1)="：",MID(TRIM($A24),2,1)="、"),REPLACEB(TRIM($A24),1,4,""),TRIM($A24))) -> 0 | D24: =SUMIFS(调整事项汇总表!$J$7:$J$10020,调整事项汇总表!$D$7:$D$10020,"账项调整",调整事项汇总表!$E$7:$E$10020,IF(OR(MID(TRIM($A24),2,1)="：",MID(TRIM($A24),2,1)="、"),REPLACEB(TRIM($A24),1,4,""),TRIM($A24))) -> 0 | E24: =SUMIFS(调整事项汇总表!$I$7:$I$10020,调整事项汇总表!$D$7:$D$10020,"报表调整",调整事项汇总表!$E$7:$E$10020,IF(OR(MID(TRIM($A24),2,1)="：",MID(TRIM($A24),2,1)="、"),REPLACEB(TRIM($A24),1,4,""),TRIM($A24))) -> 0 | F24: =SUMIFS(调整事项汇总表!$J$7:$J$10020,调整事项汇总表!$D$7:$D$10020,"报表调整",调整事项汇总表!$E$7:$E$10020,IF(OR(MID(TRIM($A24),2,1)="：",MID(TRIM($A24),2,1)="、"),REPLACEB(TRIM($A24),1,4,""),TRIM($A24))) -> 0 | G24: =SUMIFS(调整事项汇总表!$I$7:$I$10020,调整事项汇总表!$D$7:$D$10020,"其他",调整事项汇总表!$E$7:$E$10020,IF(OR(MID(TRIM($A24),2,1)="：",MID(TRIM($A24),2,1)="、"),REPLACEB(TRIM($A24),1,4,""),TRIM($A24))) -> 0 | H24: =SUMIFS(调整事项汇总表!$J$7:$J$10020,调整事项汇总表!$D$7:$D$10020,"其他",调整事项汇总表!$E$7:$E$10020,IF(OR(MID(TRIM($A24),2,1)="：",MID(TRIM($A24),2,1)="、"),REPLACEB(TRIM($A24),1,4,""),TRIM($A24))) -> 0 | I24: =B24+C24+E24+G24-H24-F24-D24 -> 574623.4 | J24: =A24=未审报表!A24 -> TRUE | K24: =审定报表!A24=TB!A24 -> TRUE
A25: =未审报表!A25 -> 预付款项坏账准备 | B25: =未审报表!C25 -> 0 | C25: =SUMIFS(调整事项汇总表!$I$7:$I$10020,调整事项汇总表!$D$7:$D$10020,"账项调整",调整事项汇总表!$E$7:$E$10020,IF(OR(MID(TRIM($A25),2,1)="：",MID(TRIM($A25),2,1)="、"),REPLACEB(TRIM($A25),1,4,""),TRIM($A25))) -> 0 | D25: =SUMIFS(调整事项汇总表!$J$7:$J$10020,调整事项汇总表!$D$7:$D$10020,"账项调整",调整事项汇总表!$E$7:$E$10020,IF(OR(MID(TRIM($A25),2,1)="：",MID(TRIM($A25),2,1)="、"),REPLACEB(TRIM($A25),1,4,""),TRIM($A25))) -> 0 | E25: =SUMIFS(调整事项汇总表!$I$7:$I$10020,调整事项汇总表!$D$7:$D$10020,"报表调整",调整事项汇总表!$E$7:$E$10020,IF(OR(MID(TRIM($A25),2,1)="：",MID(TRIM($A25),2,1)="、"),REPLACEB(TRIM($A25),1,4,""),TRIM($A25))) -> 0 | F25: =SUMIFS(调整事项汇总表!$J$7:$J$10020,调整事项汇总表!$D$7:$D$10020,"报表调整",调整事项汇总表!$E$7:$E$10020,IF(OR(MID(TRIM($A25),2,1)="：",MID(TRIM($A25),2,1)="、"),REPLACEB(TRIM($A25),1,4,""),TRIM($A25))) -> 0 | G25: =SUMIFS(调整事项汇总表!$I$7:$I$10020,调整事项汇总表!$D$7:$D$10020,"其他",调整事项汇总表!$E$7:$E$10020,IF(OR(MID(TRIM($A25),2,1)="：",MID(TRIM($A25),2,1)="、"),REPLACEB(TRIM($A25),1,4,""),TRIM($A25))) -> 0 | H25: =SUMIFS(调整事项汇总表!$J$7:$J$10020,调整事项汇总表!$D$7:$D$10020,"其他",调整事项汇总表!$E$7:$E$10020,IF(OR(MID(TRIM($A25),2,1)="：",MID(TRIM($A25),2,1)="、"),REPLACEB(TRIM($A25),1,4,""),TRIM($A25))) -> 0 | I25: =B25+D25+F25+H25-G25-E25-C25 -> 0 | J25: =A25=未审报表!A25 -> TRUE | K25: =审定报表!A25=TB!A25 -> TRUE
A26: =未审报表!A26 -> 预付款项 | B26: =未审报表!C26 -> 574623.4 | C26: =C24+C25 -> 0 | D26: =D24+D25 -> 0 | E26: =E24+E25 -> 0 | F26: =F24+F25 -> 0 | G26: =G24+G25 -> 0 | H26: =H24+H25 -> 0 | I26: =B26+C26+E26+G26-H26-F26-D26 -> 574623.4 | J26: =A26=未审报表!A26 -> TRUE | K26: =审定报表!A26=TB!A26 -> TRUE
A27: =未审报表!A27 -> 应收保费原值* | B27: =未审报表!C27 -> 0 | C27: =SUMIFS(调整事项汇总表!$I$7:$I$10020,调整事项汇总表!$D$7:$D$10020,"账项调整",调整事项汇总表!$E$7:$E$10020,IF(OR(MID(TRIM($A27),2,1)="：",MID(TRIM($A27),2,1)="、"),REPLACEB(TRIM($A27),1,4,""),TRIM($A27))) -> 0 | D27: =SUMIFS(调整事项汇总表!$J$7:$J$10020,调整事项汇总表!$D$7:$D$10020,"账项调整",调整事项汇总表!$E$7:$E$10020,IF(OR(MID(TRIM($A27),2,1)="：",MID(TRIM($A27),2,1)="、"),REPLACEB(TRIM($A27),1,4,""),TRIM($A27))) -> 0 | E27: =SUMIFS(调整事项汇总表!$I$7:$I$10020,调整事项汇总表!$D$7:$D$10020,"报表调整",调整事项汇总表!$E$7:$E$10020,IF(OR(MID(TRIM($A27),2,1)="：",MID(TRIM($A27),2,1)="、"),REPLACEB(TRIM($A27),1,4,""),TRIM($A27))) -> 0 | F27: =SUMIFS(调整事项汇总表!$J$7:$J$10020,调整事项汇总表!$D$7:$D$10020,"报表调整",调整事项汇总表!$E$7:$E$10020,IF(OR(MID(TRIM($A27),2,1)="：",MID(TRIM($A27),2,1)="、"),REPLACEB(TRIM($A27),1,4,""),TRIM($A27))) -> 0 | G27: =SUMIFS(调整事项汇总表!$I$7:$I$10020,调整事项汇总表!$D$7:$D$10020,"其他",调整事项汇总表!$E$7:$E$10020,IF(OR(MID(TRIM($A27),2,1)="：",MID(TRIM($A27),2,1)="、"),REPLACEB(TRIM($A27),1,4,""),TRIM($A27))) -> 0 | H27: =SUMIFS(调整事项汇总表!$J$7:$J$10020,调整事项汇总表!$D$7:$D$10020,"其他",调整事项汇总表!$E$7:$E$10020,IF(OR(MID(TRIM($A27),2,1)="：",MID(TRIM($A27),2,1)="、"),REPLACEB(TRIM($A27),1,4,""),TRIM($A27))) -> 0 | I27: =B27+C27+E27+G27-H27-F27-D27 -> 0 | J27: =A27=未审报表!A27 -> TRUE | K27: =审定报表!A27=TB!A27 -> TRUE
A28: =未审报表!A28 -> 应收保费坏账准备* | B28: =未审报表!C28 -> 0 | C28: =SUMIFS(调整事项汇总表!$I$7:$I$10020,调整事项汇总表!$D$7:$D$10020,"账项调整",调整事项汇总表!$E$7:$E$10020,IF(OR(MID(TRIM($A28),2,1)="：",MID(TRIM($A28),2,1)="、"),REPLACEB(TRIM($A28),1,4,""),TRIM($A28))) -> 0 | D28: =SUMIFS(调整事项汇总表!$J$7:$J$10020,调整事项汇总表!$D$7:$D$10020,"账项调整",调整事项汇总表!$E$7:$E$10020,IF(OR(MID(TRIM($A28),2,1)="：",MID(TRIM($A28),2,1)="、"),REPLACEB(TRIM($A28),1,4,""),TRIM($A28))) -> 0 | E28: =SUMIFS(调整事项汇总表!$I$7:$I$10020,调整事项汇总表!$D$7:$D$10020,"报表调整",调整事项汇总表!$E$7:$E$10020,IF(OR(MID(TRIM($A28),2,1)="：",MID(TRIM($A28),2,1)="、"),REPLACEB(TRIM($A28),1,4,""),TRIM($A28))) -> 0 | F28: =SUMIFS(调整事项汇总表!$J$7:$J$10020,调整事项汇总表!$D$7:$D$10020,"报表调整",调整事项汇总表!$E$7:$E$10020,IF(OR(MID(TRIM($A28),2,1)="：",MID(TRIM($A28),2,1)="、"),REPLACEB(TRIM($A28),1,4,""),TRIM($A28))) -> 0 | G28: =SUMIFS(调整事项汇总表!$I$7:$I$10020,调整事项汇总表!$D$7:$D$10020,"其他",调整事项汇总表!$E$7:$E$10020,IF(OR(MID(TRIM($A28),2,1)="：",MID(TRIM($A28),2,1)="、"),REPLACEB(TRIM($A28),1,4,""),TRIM($A28))) -> 0 | H28: =SUMIFS(调整事项汇总表!$J$7:$J$10020,调整事项汇总表!$D$7:$D$10020,"其他",调整事项汇总表!$E$7:$E$10020,IF(OR(MID(TRIM($A28),2,1)="：",MID(TRIM($A28),2,1)="、"),REPLACEB(TRIM($A28),1,4,""),TRIM($A28))) -> 0 | I28: =B28+D28+F28+H28-G28-E28-C28 -> 0 | J28: =A28=未审报表!A28 -> TRUE | K28: =审定报表!A28=TB!A28 -> TRUE
A29: =未审报表!A29 -> 应收保费* | B29: =未审报表!C29 -> 0 | C29: =C27+C28 -> 0 | D29: =D27+D28 -> 0 | E29: =E27+E28 -> 0 | F29: =F27+F28 -> 0 | G29: =G27+G28 -> 0 | H29: =H27+H28 -> 0 | I29: =B29+C29+E29+G29-H29-F29-D29 -> 0 | J29: =A29=未审报表!A29 -> TRUE | K29: =审定报表!A29=TB!A29 -> TRUE
A30: =未审报表!A30 -> 应收分保账款原值* | B30: =未审报表!C30 -> 0 | C30: =SUMIFS(调整事项汇总表!$I$7:$I$10020,调整事项汇总表!$D$7:$D$10020,"账项调整",调整事项汇总表!$E$7:$E$10020,IF(OR(MID(TRIM($A30),2,1)="：",MID(TRIM($A30),2,1)="、"),REPLACEB(TRIM($A30),1,4,""),TRIM($A30))) -> 0 | D30: =SUMIFS(调整事项汇总表!$J$7:$J$10020,调整事项汇总表!$D$7:$D$10020,"账项调整",调整事项汇总表!$E$7:$E$10020,IF(OR(MID(TRIM($A30),2,1)="：",MID(TRIM($A30),2,1)="、"),REPLACEB(TRIM($A30),1,4,""),TRIM($A30))) -> 0 | E30: =SUMIFS(调整事项汇总表!$I$7:$I$10020,调整事项汇总表!$D$7:$D$10020,"报表调整",调整事项汇总表!$E$7:$E$10020,IF(OR(MID(TRIM($A30),2,1)="：",MID(TRIM($A30),2,1)="、"),REPLACEB(TRIM($A30),1,4,""),TRIM($A30))) -> 0 | F30: =SUMIFS(调整事项汇总表!$J$7:$J$10020,调整事项汇总表!$D$7:$D$10020,"报表调整",调整事项汇总表!$E$7:$E$10020,IF(OR(MID(TRIM($A30),2,1)="：",MID(TRIM($A30),2,1)="、"),REPLACEB(TRIM($A30),1,4,""),TRIM($A30))) -> 0 | G30: =SUMIFS(调整事项汇总表!$I$7:$I$10020,调整事项汇总表!$D$7:$D$10020,"其他",调整事项汇总表!$E$7:$E$10020,IF(OR(MID(TRIM($A30),2,1)="：",MID(TRIM($A30),2,1)="、"),REPLACEB(TRIM($A30),1,4,""),TRIM($A30))) -> 0 | H30: =SUMIFS(调整事项汇总表!$J$7:$J$10020,调整事项汇总表!$D$7:$D$10020,"其他",调整事项汇总表!$E$7:$E$10020,IF(OR(MID(TRIM($A30),2,1)="：",MID(TRIM($A30),2,1)="、"),REPLACEB(TRIM($A30),1,4,""),TRIM($A30))) -> 0 | I30: =B30+C30+E30+G30-H30-F30-D30 -> 0 | J30: =A30=未审报表!A30 -> TRUE | K30: =审定报表!A30=TB!A30 -> TRUE
A31: =未审报表!A31 -> 应收分保账款坏账准备* | B31: =未审报表!C31 -> 0 | C31: =SUMIFS(调整事项汇总表!$I$7:$I$10020,调整事项汇总表!$D$7:$D$10020,"账项调整",调整事项汇总表!$E$7:$E$10020,IF(OR(MID(TRIM($A31),2,1)="：",MID(TRIM($A31),2,1)="、"),REPLACEB(TRIM($A31),1,4,""),TRIM($A31))) -> 0 | D31: =SUMIFS(调整事项汇总表!$J$7:$J$10020,调整事项汇总表!$D$7:$D$10020,"账项调整",调整事项汇总表!$E$7:$E$10020,IF(OR(MID(TRIM($A31),2,1)="：",MID(TRIM($A31),2,1)="、"),REPLACEB(TRIM($A31),1,4,""),TRIM($A31))) -> 0 | E31: =SUMIFS(调整事项汇总表!$I$7:$I$10020,调整事项汇总表!$D$7:$D$10020,"报表调整",调整事项汇总表!$E$7:$E$10020,IF(OR(MID(TRIM($A31),2,1)="：",MID(TRIM($A31),2,1)="、"),REPLACEB(TRIM($A31),1,4,""),TRIM($A31))) -> 0 | F31: =SUMIFS(调整事项汇总表!$J$7:$J$10020,调整事项汇总表!$D$7:$D$10020,"报表调整",调整事项汇总表!$E$7:$E$10020,IF(OR(MID(TRIM($A31),2,1)="：",MID(TRIM($A31),2,1)="、"),REPLACEB(TRIM($A31),1,4,""),TRIM($A31))) -> 0 | G31: =SUMIFS(调整事项汇总表!$I$7:$I$10020,调整事项汇总表!$D$7:$D$10020,"其他",调整事项汇总表!$E$7:$E$10020,IF(OR(MID(TRIM($A31),2,1)="：",MID(TRIM($A31),2,1)="、"),REPLACEB(TRIM($A31),1,4,""),TRIM($A31))) -> 0 | H31: =SUMIFS(调整事项汇总表!$J$7:$J$10020,调整事项汇总表!$D$7:$D$10020,"其他",调整事项汇总表!$E$7:$E$10020,IF(OR(MID(TRIM($A31),2,1)="：",MID(TRIM($A31),2,1)="、"),REPLACEB(TRIM($A31),1,4,""),TRIM($A31))) -> 0 | I31: =B31+D31+F31+H31-G31-E31-C31 -> 0 | J31: =A31=未审报表!A31 -> TRUE | K31: =审定报表!A31=TB!A31 -> TRUE
A32: =未审报表!A32 -> 应收分保账款* | B32: =未审报表!C32 -> 0 | C32: =C30+C31 -> 0 | D32: =D30+D31 -> 0 | E32: =E30+E31 -> 0 | F32: =F30+F31 -> 0 | G32: =G30+G31 -> 0 | H32: =H30+H31 -> 0 | I32: =B32+C32+E32+G32-H32-F32-D32 -> 0 | J32: =A32=未审报表!A32 -> TRUE | K32: =审定报表!A32=TB!A32 -> TRUE
A33: =未审报表!A33 -> 应收分保合同准备金* | B33: =未审报表!C33 -> 0 | C33: =SUMIFS(调整事项汇总表!$I$7:$I$10020,调整事项汇总表!$D$7:$D$10020,"账项调整",调整事项汇总表!$E$7:$E$10020,IF(OR(MID(TRIM($A33),2,1)="：",MID(TRIM($A33),2,1)="、"),REPLACEB(TRIM($A33),1,4,""),TRIM($A33))) -> 0 | D33: =SUMIFS(调整事项汇总表!$J$7:$J$10020,调整事项汇总表!$D$7:$D$10020,"账项调整",调整事项汇总表!$E$7:$E$10020,IF(OR(MID(TRIM($A33),2,1)="：",MID(TRIM($A33),2,1)="、"),REPLACEB(TRIM($A33),1,4,""),TRIM($A33))) -> 0 | E33: =SUMIFS(调整事项汇总表!$I$7:$I$10020,调整事项汇总表!$D$7:$D$10020,"报表调整",调整事项汇总表!$E$7:$E$10020,IF(OR(MID(TRIM($A33),2,1)="：",MID(TRIM($A33),2,1)="、"),REPLACEB(TRIM($A33),1,4,""),TRIM($A33))) -> 0 | F33: =SUMIFS(调整事项汇总表!$J$7:$J$10020,调整事项汇总表!$D$7:$D$10020,"报表调整",调整事项汇总表!$E$7:$E$10020,IF(OR(MID(TRIM($A33),2,1)="：",MID(TRIM($A33),2,1)="、"),REPLACEB(TRIM($A33),1,4,""),TRIM($A33))) -> 0 | G33: =SUMIFS(调整事项汇总表!$I$7:$I$10020,调整事项汇总表!$D$7:$D$10020,"其他",调整事项汇总表!$E$7:$E$10020,IF(OR(MID(TRIM($A33),2,1)="：",MID(TRIM($A33),2,1)="、"),REPLACEB(TRIM($A33),1,4,""),TRIM($A33))) -> 0 | H33: =SUMIFS(调整事项汇总表!$J$7:$J$10020,调整事项汇总表!$D$7:$D$10020,"其他",调整事项汇总表!$E$7:$E$10020,IF(OR(MID(TRIM($A33),2,1)="：",MID(TRIM($A33),2,1)="、"),REPLACEB(TRIM($A33),1,4,""),TRIM($A33))) -> 0 | I33: =B33+C33+E33+G33-H33-F33-D33 -> 0 | J33: =A33=未审报表!A33 -> TRUE | K33: =审定报表!A33=TB!A33 -> TRUE
A34: =未审报表!A34 -> 应收利息原值 | B34: =未审报表!C34 -> 0 | C34: =SUMIFS(调整事项汇总表!$I$7:$I$10020,调整事项汇总表!$D$7:$D$10020,"账项调整",调整事项汇总表!$E$7:$E$10020,IF(OR(MID(TRIM($A34),2,1)="：",MID(TRIM($A34),2,1)="、"),REPLACEB(TRIM($A34),1,4,""),TRIM($A34))) -> 0 | D34: =SUMIFS(调整事项汇总表!$J$7:$J$10020,调整事项汇总表!$D$7:$D$10020,"账项调整",调整事项汇总表!$E$7:$E$10020,IF(OR(MID(TRIM($A34),2,1)="：",MID(TRIM($A34),2,1)="、"),REPLACEB(TRIM($A34),1,4,""),TRIM($A34))) -> 0 | E34: =SUMIFS(调整事项汇总表!$I$7:$I$10020,调整事项汇总表!$D$7:$D$10020,"报表调整",调整事项汇总表!$E$7:$E$10020,IF(OR(MID(TRIM($A34),2,1)="：",MID(TRIM($A34),2,1)="、"),REPLACEB(TRIM($A34),1,4,""),TRIM($A34))) -> 0 | F34: =SUMIFS(调整事项汇总表!$J$7:$J$10020,调整事项汇总表!$D$7:$D$10020,"报表调整",调整事项汇总表!$E$7:$E$10020,IF(OR(MID(TRIM($A34),2,1)="：",MID(TRIM($A34),2,1)="、"),REPLACEB(TRIM($A34),1,4,""),TRIM($A34))) -> 0 | G34: =SUMIFS(调整事项汇总表!$I$7:$I$10020,调整事项汇总表!$D$7:$D$10020,"其他",调整事项汇总表!$E$7:$E$10020,IF(OR(MID(TRIM($A34),2,1)="：",MID(TRIM($A34),2,1)="、"),REPLACEB(TRIM($A34),1,4,""),TRIM($A34))) -> 0 | H34: =SUMIFS(调整事项汇总表!$J$7:$J$10020,调整事项汇总表!$D$7:$D$10020,"其他",调整事项汇总表!$E$7:$E$10020,IF(OR(MID(TRIM($A34),2,1)="：",MID(TRIM($A34),2,1)="、"),REPLACEB(TRIM($A34),1,4,""),TRIM($A34))) -> 0 | I34: =B34+C34+E34+G34-H34-F34-D34 -> 0 | J34: =A34=未审报表!A34 -> TRUE | K34: =审定报表!A34=TB!A34 -> TRUE
A35: =未审报表!A35 -> 应收利息坏账准备 | B35: =未审报表!C35 -> 0 | C35: =SUMIFS(调整事项汇总表!$I$7:$I$10020,调整事项汇总表!$D$7:$D$10020,"账项调整",调整事项汇总表!$E$7:$E$10020,IF(OR(MID(TRIM($A35),2,1)="：",MID(TRIM($A35),2,1)="、"),REPLACEB(TRIM($A35),1,4,""),TRIM($A35))) -> 0 | D35: =SUMIFS(调整事项汇总表!$J$7:$J$10020,调整事项汇总表!$D$7:$D$10020,"账项调整",调整事项汇总表!$E$7:$E$10020,IF(OR(MID(TRIM($A35),2,1)="：",MID(TRIM($A35),2,1)="、"),REPLACEB(TRIM($A35),1,4,""),TRIM($A35))) -> 0 | E35: =SUMIFS(调整事项汇总表!$I$7:$I$10020,调整事项汇总表!$D$7:$D$10020,"报表调整",调整事项汇总表!$E$7:$E$10020,IF(OR(MID(TRIM($A35),2,1)="：",MID(TRIM($A35),2,1)="、"),REPLACEB(TRIM($A35),1,4,""),TRIM($A35))) -> 0 | F35: =SUMIFS(调整事项汇总表!$J$7:$J$10020,调整事项汇总表!$D$7:$D$10020,"报表调整",调整事项汇总表!$E$7:$E$10020,IF(OR(MID(TRIM($A35),2,1)="：",MID(TRIM($A35),2,1)="、"),REPLACEB(TRIM($A35),1,4,""),TRIM($A35))) -> 0 | G35: =SUMIFS(调整事项汇总表!$I$7:$I$10020,调整事项汇总表!$D$7:$D$10020,"其他",调整事项汇总表!$E$7:$E$10020,IF(OR(MID(TRIM($A35),2,1)="：",MID(TRIM($A35),2,1)="、"),REPLACEB(TRIM($A35),1,4,""),TRIM($A35))) -> 0 | H35: =SUMIFS(调整事项汇总表!$J$7:$J$10020,调整事项汇总表!$D$7:$D$10020,"其他",调整事项汇总表!$E$7:$E$10020,IF(OR(MID(TRIM($A35),2,1)="：",MID(TRIM($A35),2,1)="、"),REPLACEB(TRIM($A35),1,4,""),TRIM($A35))) -> 0 | I35: =B35+D35+F35+H35-G35-E35-C35 -> 0 | J35: =A35=未审报表!A35 -> TRUE | K35: =审定报表!A35=TB!A35 -> TRUE
A36: =未审报表!A36 -> 应收利息 | B36: =未审报表!C36 -> 0 | I36: =B36+C36+E36+G36-H36-F36-D36 -> 0 | J36: =A36=未审报表!A36 -> TRUE | K36: =审定报表!A36=TB!A36 -> TRUE
A37: =未审报表!A37 -> 应收股利原值 | B37: =未审报表!C37 -> 32823183 | C37: =SUMIFS(调整事项汇总表!$I$7:$I$10020,调整事项汇总表!$D$7:$D$10020,"账项调整",调整事项汇总表!$E$7:$E$10020,IF(OR(MID(TRIM($A37),2,1)="：",MID(TRIM($A37),2,1)="、"),REPLACEB(TRIM($A37),1,4,""),TRIM($A37))) -> 0 | D37: =SUMIFS(调整事项汇总表!$J$7:$J$10020,调整事项汇总表!$D$7:$D$10020,"账项调整",调整事项汇总表!$E$7:$E$10020,IF(OR(MID(TRIM($A37),2,1)="：",MID(TRIM($A37),2,1)="、"),REPLACEB(TRIM($A37),1,4,""),TRIM($A37))) -> 0 | E37: =SUMIFS(调整事项汇总表!$I$7:$I$10020,调整事项汇总表!$D$7:$D$10020,"报表调整",调整事项汇总表!$E$7:$E$10020,IF(OR(MID(TRIM($A37),2,1)="：",MID(TRIM($A37),2,1)="、"),REPLACEB(TRIM($A37),1,4,""),TRIM($A37))) -> 0 | F37: =SUMIFS(调整事项汇总表!$J$7:$J$10020,调整事项汇总表!$D$7:$D$10020,"报表调整",调整事项汇总表!$E$7:$E$10020,IF(OR(MID(TRIM($A37),2,1)="：",MID(TRIM($A37),2,1)="、"),REPLACEB(TRIM($A37),1,4,""),TRIM($A37))) -> 0 | G37: =SUMIFS(调整事项汇总表!$I$7:$I$10020,调整事项汇总表!$D$7:$D$10020,"其他",调整事项汇总表!$E$7:$E$10020,IF(OR(MID(TRIM($A37),2,1)="：",MID(TRIM($A37),2,1)="、"),REPLACEB(TRIM($A37),1,4,""),TRIM($A37))) -> 0 | H37: =SUMIFS(调整事项汇总表!$J$7:$J$10020,调整事项汇总表!$D$7:$D$10020,"其他",调整事项汇总表!$E$7:$E$10020,IF(OR(MID(TRIM($A37),2,1)="：",MID(TRIM($A37),2,1)="、"),REPLACEB(TRIM($A37),1,4,""),TRIM($A37))) -> 0 | I37: =B37+C37+E37+G37-H37-F37-D37 -> 32823183 | J37: =A37=未审报表!A37 -> TRUE | K37: =审定报表!A37=TB!A37 -> TRUE
A38: =未审报表!A38 -> 应收股利坏账准备 | B38: =未审报表!C38 -> 0 | C38: =SUMIFS(调整事项汇总表!$I$7:$I$10020,调整事项汇总表!$D$7:$D$10020,"账项调整",调整事项汇总表!$E$7:$E$10020,IF(OR(MID(TRIM($A38),2,1)="：",MID(TRIM($A38),2,1)="、"),REPLACEB(TRIM($A38),1,4,""),TRIM($A38))) -> 0 | D38: =SUMIFS(调整事项汇总表!$J$7:$J$10020,调整事项汇总表!$D$7:$D$10020,"账项调整",调整事项汇总表!$E$7:$E$10020,IF(OR(MID(TRIM($A38),2,1)="：",MID(TRIM($A38),2,1)="、"),REPLACEB(TRIM($A38),1,4,""),TRIM($A38))) -> 0 | E38: =SUMIFS(调整事项汇总表!$I$7:$I$10020,调整事项汇总表!$D$7:$D$10020,"报表调整",调整事项汇总表!$E$7:$E$10020,IF(OR(MID(TRIM($A38),2,1)="：",MID(TRIM($A38),2,1)="、"),REPLACEB(TRIM($A38),1,4,""),TRIM($A38))) -> 0 | F38: =SUMIFS(调整事项汇总表!$J$7:$J$10020,调整事项汇总表!$D$7:$D$10020,"报表调整",调整事项汇总表!$E$7:$E$10020,IF(OR(MID(TRIM($A38),2,1)="：",MID(TRIM($A38),2,1)="、"),REPLACEB(TRIM($A38),1,4,""),TRIM($A38))) -> 0 | G38: =SUMIFS(调整事项汇总表!$I$7:$I$10020,调整事项汇总表!$D$7:$D$10020,"其他",调整事项汇总表!$E$7:$E$10020,IF(OR(MID(TRIM($A38),2,1)="：",MID(TRIM($A38),2,1)="、"),REPLACEB(TRIM($A38),1,4,""),TRIM($A38))) -> 0 | H38: =SUMIFS(调整事项汇总表!$J$7:$J$10020,调整事项汇总表!$D$7:$D$10020,"其他",调整事项汇总表!$E$7:$E$10020,IF(OR(MID(TRIM($A38),2,1)="：",MID(TRIM($A38),2,1)="、"),REPLACEB(TRIM($A38),1,4,""),TRIM($A38))) -> 0 | I38: =B38+D38+F38+H38-G38-E38-C38 -> 0 | J38: =A38=未审报表!A38 -> TRUE | K38: =审定报表!A38=TB!A38 -> TRUE
A39: =未审报表!A39 -> 应收股利 | B39: =未审报表!C39 -> 32823183 | C39: =C37+C38 -> 0 | D39: =D37+D38 -> 0 | E39: =E37+E38 -> 0 | F39: =F37+F38 -> 0 | G39: =G37+G38 -> 0 | H39: =H37+H38 -> 0 | I39: =B39+C39+E39+G39-H39-F39-D39 -> 32823183 | J39: =A39=未审报表!A39 -> TRUE | K39: =审定报表!A39=TB!A39 -> TRUE
A40: =未审报表!A40 -> 其他应收款原值 | B40: =未审报表!C40 -> 8096269.4 | C40: =SUMIFS(调整事项汇总表!$I$7:$I$10020,调整事项汇总表!$D$7:$D$10020,"账项调整",调整事项汇总表!$E$7:$E$10020,IF(OR(MID(TRIM($A40),2,1)="：",MID(TRIM($A40),2,1)="、"),REPLACEB(TRIM($A40),1,4,""),TRIM($A40))) -> 9923747.7 | D40: =SUMIFS(调整事项汇总表!$J$7:$J$10020,调整事项汇总表!$D$7:$D$10020,"账项调整",调整事项汇总表!$E$7:$E$10020,IF(OR(MID(TRIM($A40),2,1)="：",MID(TRIM($A40),2,1)="、"),REPLACEB(TRIM($A40),1,4,""),TRIM($A40))) -> 0 | E40: =SUMIFS(调整事项汇总表!$I$7:$I$10020,调整事项汇总表!$D$7:$D$10020,"报表调整",调整事项汇总表!$E$7:$E$10020,IF(OR(MID(TRIM($A40),2,1)="：",MID(TRIM($A40),2,1)="、"),REPLACEB(TRIM($A40),1,4,""),TRIM($A40))) -> 0 | F40: =SUMIFS(调整事项汇总表!$J$7:$J$10020,调整事项汇总表!$D$7:$D$10020,"报表调整",调整事项汇总表!$E$7:$E$10020,IF(OR(MID(TRIM($A40),2,1)="：",MID(TRIM($A40),2,1)="、"),REPLACEB(TRIM($A40),1,4,""),TRIM($A40))) -> 0 | G40: =SUMIFS(调整事项汇总表!$I$7:$I$10020,调整事项汇总表!$D$7:$D$10020,"其他",调整事项汇总表!$E$7:$E$10020,IF(OR(MID(TRIM($A40),2,1)="：",MID(TRIM($A40),2,1)="、"),REPLACEB(TRIM($A40),1,4,""),TRIM($A40))) -> 0 | H40: =SUMIFS(调整事项汇总表!$J$7:$J$10020,调整事项汇总表!$D$7:$D$10020,"其他",调整事项汇总表!$E$7:$E$10020,IF(OR(MID(TRIM($A40),2,1)="：",MID(TRIM($A40),2,1)="、"),REPLACEB(TRIM($A40),1,4,""),TRIM($A40))) -> 0 | I40: =B40+C40+E40+G40-H40-F40-D40 -> 18020017 | J40: =A40=未审报表!A40 -> TRUE | K40: =审定报表!A40=TB!A40 -> TRUE
A41: =未审报表!A41 -> 其他应收款坏账准备 | B41: =未审报表!C41 -> 13310.74 | C41: =SUMIFS(调整事项汇总表!$I$7:$I$10020,调整事项汇总表!$D$7:$D$10020,"账项调整",调整事项汇总表!$E$7:$E$10020,IF(OR(MID(TRIM($A41),2,1)="：",MID(TRIM($A41),2,1)="、"),REPLACEB(TRIM($A41),1,4,""),TRIM($A41))) -> 0 | D41: =SUMIFS(调整事项汇总表!$J$7:$J$10020,调整事项汇总表!$D$7:$D$10020,"账项调整",调整事项汇总表!$E$7:$E$10020,IF(OR(MID(TRIM($A41),2,1)="：",MID(TRIM($A41),2,1)="、"),REPLACEB(TRIM($A41),1,4,""),TRIM($A41))) -> 73148.34 | E41: =SUMIFS(调整事项汇总表!$I$7:$I$10020,调整事项汇总表!$D$7:$D$10020,"报表调整",调整事项汇总表!$E$7:$E$10020,IF(OR(MID(TRIM($A41),2,1)="：",MID(TRIM($A41),2,1)="、"),REPLACEB(TRIM($A41),1,4,""),TRIM($A41))) -> 0 | F41: =SUMIFS(调整事项汇总表!$J$7:$J$10020,调整事项汇总表!$D$7:$D$10020,"报表调整",调整事项汇总表!$E$7:$E$10020,IF(OR(MID(TRIM($A41),2,1)="：",MID(TRIM($A41),2,1)="、"),REPLACEB(TRIM($A41),1,4,""),TRIM($A41))) -> 0 | G41: =SUMIFS(调整事项汇总表!$I$7:$I$10020,调整事项汇总表!$D$7:$D$10020,"其他",调整事项汇总表!$E$7:$E$10020,IF(OR(MID(TRIM($A41),2,1)="：",MID(TRIM($A41),2,1)="、"),REPLACEB(TRIM($A41),1,4,""),TRIM($A41))) -> 0 | H41: =SUMIFS(调整事项汇总表!$J$7:$J$10020,调整事项汇总表!$D$7:$D$10020,"其他",调整事项汇总表!$E$7:$E$10020,IF(OR(MID(TRIM($A41),2,1)="：",MID(TRIM($A41),2,1)="、"),REPLACEB(TRIM($A41),1,4,""),TRIM($A41))) -> 0 | I41: =B41+D41+F41+H41-G41-E41-C41 -> 86459.08 | J41: =A41=未审报表!A41 -> TRUE | K41: =审定报表!A41=TB!A41 -> TRUE
A42: =未审报表!A42 -> 其他应收款 | B42: =未审报表!C42 -> 8082958.6 | C42: =C40+C41 -> 9923747.7 | D42: =D40+D41 -> 73148.34 | E42: =E40+E41 -> 0 | F42: =F40+F41 -> 0 | G42: =G40+G41 -> 0 | H42: =H40+H41 -> 0 | I42: =B42+C42+E42+G42-H42-F42-D42 -> 17933558 | J42: =A42=未审报表!A42 -> TRUE | K42: =审定报表!A42=TB!A42 -> TRUE
A43: =未审报表!A43 -> 买入返售金融资产原值* | B43: =未审报表!C43 -> 0 | C43: =SUMIFS(调整事项汇总表!$I$7:$I$10020,调整事项汇总表!$D$7:$D$10020,"账项调整",调整事项汇总表!$E$7:$E$10020,IF(OR(MID(TRIM($A43),2,1)="：",MID(TRIM($A43),2,1)="、"),REPLACEB(TRIM($A43),1,4,""),TRIM($A43))) -> 0 | D43: =SUMIFS(调整事项汇总表!$J$7:$J$10020,调整事项汇总表!$D$7:$D$10020,"账项调整",调整事项汇总表!$E$7:$E$10020,IF(OR(MID(TRIM($A43),2,1)="：",MID(TRIM($A43),2,1)="、"),REPLACEB(TRIM($A43),1,4,""),TRIM($A43))) -> 0 | E43: =SUMIFS(调整事项汇总表!$I$7:$I$10020,调整事项汇总表!$D$7:$D$10020,"报表调整",调整事项汇总表!$E$7:$E$10020,IF(OR(MID(TRIM($A43),2,1)="：",MID(TRIM($A43),2,1)="、"),REPLACEB(TRIM($A43),1,4,""),TRIM($A43))) -> 0 | F43: =SUMIFS(调整事项汇总表!$J$7:$J$10020,调整事项汇总表!$D$7:$D$10020,"报表调整",调整事项汇总表!$E$7:$E$10020,IF(OR(MID(TRIM($A43),2,1)="：",MID(TRIM($A43),2,1)="、"),REPLACEB(TRIM($A43),1,4,""),TRIM($A43))) -> 0 | G43: =SUMIFS(调整事项汇总表!$I$7:$I$10020,调整事项汇总表!$D$7:$D$10020,"其他",调整事项汇总表!$E$7:$E$10020,IF(OR(MID(TRIM($A43),2,1)="：",MID(TRIM($A43),2,1)="、"),REPLACEB(TRIM($A43),1,4,""),TRIM($A43))) -> 0 | H43: =SUMIFS(调整事项汇总表!$J$7:$J$10020,调整事项汇总表!$D$7:$D$10020,"其他",调整事项汇总表!$E$7:$E$10020,IF(OR(MID(TRIM($A43),2,1)="：",MID(TRIM($A43),2,1)="、"),REPLACEB(TRIM($A43),1,4,""),TRIM($A43))) -> 0 | I43: =B43+C43+E43+G43-H43-F43-D43 -> 0 | J43: =A43=未审报表!A43 -> TRUE | K43: =审定报表!A43=TB!A43 -> TRUE
A44: =未审报表!A44 -> 买入返售金融资产减值准备* | B44: =未审报表!C44 -> 0 | C44: =SUMIFS(调整事项汇总表!$I$7:$I$10020,调整事项汇总表!$D$7:$D$10020,"账项调整",调整事项汇总表!$E$7:$E$10020,IF(OR(MID(TRIM($A44),2,1)="：",MID(TRIM($A44),2,1)="、"),REPLACEB(TRIM($A44),1,4,""),TRIM($A44))) -> 0 | D44: =SUMIFS(调整事项汇总表!$J$7:$J$10020,调整事项汇总表!$D$7:$D$10020,"账项调整",调整事项汇总表!$E$7:$E$10020,IF(OR(MID(TRIM($A44),2,1)="：",MID(TRIM($A44),2,1)="、"),REPLACEB(TRIM($A44),1,4,""),TRIM($A44))) -> 0 | E44: =SUMIFS(调整事项汇总表!$I$7:$I$10020,调整事项汇总表!$D$7:$D$10020,"报表调整",调整事项汇总表!$E$7:$E$10020,IF(OR(MID(TRIM($A44),2,1)="：",MID(TRIM($A44),2,1)="、"),REPLACEB(TRIM($A44),1,4,""),TRIM($A44))) -> 0 | F44: =SUMIFS(调整事项汇总表!$J$7:$J$10020,调整事项汇总表!$D$7:$D$10020,"报表调整",调整事项汇总表!$E$7:$E$10020,IF(OR(MID(TRIM($A44),2,1)="：",MID(TRIM($A44),2,1)="、"),REPLACEB(TRIM($A44),1,4,""),TRIM($A44))) -> 0 | G44: =SUMIFS(调整事项汇总表!$I$7:$I$10020,调整事项汇总表!$D$7:$D$10020,"其他",调整事项汇总表!$E$7:$E$10020,IF(OR(MID(TRIM($A44),2,1)="：",MID(TRIM($A44),2,1)="、"),REPLACEB(TRIM($A44),1,4,""),TRIM($A44))) -> 0 | H44: =SUMIFS(调整事项汇总表!$J$7:$J$10020,调整事项汇总表!$D$7:$D$10020,"其他",调整事项汇总表!$E$7:$E$10020,IF(OR(MID(TRIM($A44),2,1)="：",MID(TRIM($A44),2,1)="、"),REPLACEB(TRIM($A44),1,4,""),TRIM($A44))) -> 0 | I44: =B44+D44+F44+H44-G44-E44-C44 -> 0 | J44: =A44=未审报表!A44 -> TRUE | K44: =审定报表!A44=TB!A44 -> TRUE
A45: =未审报表!A45 -> 买入返售金融资产* | B45: =未审报表!C45 -> 0 | C45: =C43+C44 -> 0 | D45: =D43+D44 -> 0 | E45: =E43+E44 -> 0 | F45: =F43+F44 -> 0 | G45: =G43+G44 -> 0 | H45: =H43+H44 -> 0 | I45: =B45+C45+E45+G45-H45-F45-D45 -> 0 | J45: =A45=未审报表!A45 -> TRUE | K45: =审定报表!A45=TB!A45 -> TRUE
A46: =未审报表!A46 -> 存货原值 | B46: =未审报表!C46 -> 8526796.3 | C46: =SUMIFS(调整事项汇总表!$I$7:$I$10020,调整事项汇总表!$D$7:$D$10020,"账项调整",调整事项汇总表!$E$7:$E$10020,IF(OR(MID(TRIM($A46),2,1)="：",MID(TRIM($A46),2,1)="、"),REPLACEB(TRIM($A46),1,4,""),TRIM($A46))) -> 10000 | D46: =SUMIFS(调整事项汇总表!$J$7:$J$10020,调整事项汇总表!$D$7:$D$10020,"账项调整",调整事项汇总表!$E$7:$E$10020,IF(OR(MID(TRIM($A46),2,1)="：",MID(TRIM($A46),2,1)="、"),REPLACEB(TRIM($A46),1,4,""),TRIM($A46))) -> 10000 | E46: =SUMIFS(调整事项汇总表!$I$7:$I$10020,调整事项汇总表!$D$7:$D$10020,"报表调整",调整事项汇总表!$E$7:$E$10020,IF(OR(MID(TRIM($A46),2,1)="：",MID(TRIM($A46),2,1)="、"),REPLACEB(TRIM($A46),1,4,""),TRIM($A46))) -> 0 | F46: =SUMIFS(调整事项汇总表!$J$7:$J$10020,调整事项汇总表!$D$7:$D$10020,"报表调整",调整事项汇总表!$E$7:$E$10020,IF(OR(MID(TRIM($A46),2,1)="：",MID(TRIM($A46),2,1)="、"),REPLACEB(TRIM($A46),1,4,""),TRIM($A46))) -> 0 | G46: =SUMIFS(调整事项汇总表!$I$7:$I$10020,调整事项汇总表!$D$7:$D$10020,"其他",调整事项汇总表!$E$7:$E$10020,IF(OR(MID(TRIM($A46),2,1)="：",MID(TRIM($A46),2,1)="、"),REPLACEB(TRIM($A46),1,4,""),TRIM($A46))) -> 0 | H46: =SUMIFS(调整事项汇总表!$J$7:$J$10020,调整事项汇总表!$D$7:$D$10020,"其他",调整事项汇总表!$E$7:$E$10020,IF(OR(MID(TRIM($A46),2,1)="：",MID(TRIM($A46),2,1)="、"),REPLACEB(TRIM($A46),1,4,""),TRIM($A46))) -> 0 | I46: =B46+C46+E46+G46-H46-F46-D46 -> 8526796.3 | J46: =A46=未审报表!A46 -> TRUE | K46: =审定报表!A46=TB!A46 -> TRUE
A47: =未审报表!A47 -> 存货跌价准备 | B47: =未审报表!C47 -> 0 | C47: =SUMIFS(调整事项汇总表!$I$7:$I$10020,调整事项汇总表!$D$7:$D$10020,"账项调整",调整事项汇总表!$E$7:$E$10020,IF(OR(MID(TRIM($A47),2,1)="：",MID(TRIM($A47),2,1)="、"),REPLACEB(TRIM($A47),1,4,""),TRIM($A47))) -> 0 | D47: =SUMIFS(调整事项汇总表!$J$7:$J$10020,调整事项汇总表!$D$7:$D$10020,"账项调整",调整事项汇总表!$E$7:$E$10020,IF(OR(MID(TRIM($A47),2,1)="：",MID(TRIM($A47),2,1)="、"),REPLACEB(TRIM($A47),1,4,""),TRIM($A47))) -> 0 | E47: =SUMIFS(调整事项汇总表!$I$7:$I$10020,调整事项汇总表!$D$7:$D$10020,"报表调整",调整事项汇总表!$E$7:$E$10020,IF(OR(MID(TRIM($A47),2,1)="：",MID(TRIM($A47),2,1)="、"),REPLACEB(TRIM($A47),1,4,""),TRIM($A47))) -> 0 | F47: =SUMIFS(调整事项汇总表!$J$7:$J$10020,调整事项汇总表!$D$7:$D$10020,"报表调整",调整事项汇总表!$E$7:$E$10020,IF(OR(MID(TRIM($A47),2,1)="：",MID(TRIM($A47),2,1)="、"),REPLACEB(TRIM($A47),1,4,""),TRIM($A47))) -> 0 | G47: =SUMIFS(调整事项汇总表!$I$7:$I$10020,调整事项汇总表!$D$7:$D$10020,"其他",调整事项汇总表!$E$7:$E$10020,IF(OR(MID(TRIM($A47),2,1)="：",MID(TRIM($A47),2,1)="、"),REPLACEB(TRIM($A47),1,4,""),TRIM($A47))) -> 0 | H47: =SUMIFS(调整事项汇总表!$J$7:$J$10020,调整事项汇总表!$D$7:$D$10020,"其他",调整事项汇总表!$E$7:$E$10020,IF(OR(MID(TRIM($A47),2,1)="：",MID(TRIM($A47),2,1)="、"),REPLACEB(TRIM($A47),1,4,""),TRIM($A47))) -> 0 | I47: =B47+D47+F47+H47-G47-E47-C47 -> 0 | J47: =A47=未审报表!A47 -> TRUE | K47: =审定报表!A47=TB!A47 -> TRUE
A48: =未审报表!A48 -> 存货 | B48: =未审报表!C48 -> 8526796.3 | C48: =C46+C47 -> 10000 | D48: =D46+D47 -> 10000 | E48: =E46+E47 -> 0 | F48: =F46+F47 -> 0 | G48: =G46+G47 -> 0 | H48: =H46+H47 -> 0 | I48: =B48+C48+E48+G48-H48-F48-D48 -> 8526796.3 | J48: =A48=未审报表!A48 -> TRUE | K48: =审定报表!A48=TB!A48 -> TRUE
A49: =未审报表!A49 -> 其中：原材料 | B49: =未审报表!C49 -> 698003 | C49: =SUMIFS(调整事项汇总表!$I$7:$I$10020,调整事项汇总表!$D$7:$D$10020,"账项调整",调整事项汇总表!$E$7:$E$10020,"存货原值",调整事项汇总表!$F$7:$F$10020,IF(OR(MID(TRIM($A49),3,1)="：",MID(TRIM($A49),2,1)="、"),REPLACEB(TRIM($A49),1,6,""),TRIM($A49)))-SUMIFS(调整事项汇总表!$I$7:$I$10020,调整事项汇总表!$D$7:$D$10020,"账项调整",调整事项汇总表!$E$7:$E$10020,"存货跌价准备",调整事项汇总表!$F$7:$F$10020,IF(OR(MID(TRIM($A49),3,1)="：",MID(TRIM($A49),2,1)="、"),REPLACEB(TRIM($A49),1,6,""),TRIM($A49))) -> 10000 | D49: =SUMIFS(调整事项汇总表!$J$7:$J$10020,调整事项汇总表!$D$7:$D$10020,"账项调整",调整事项汇总表!$E$7:$E$10020,"存货原值",调整事项汇总表!$F$7:$F$10020,IF(OR(MID(TRIM($A49),3,1)="：",MID(TRIM($A49),2,1)="、"),REPLACEB(TRIM($A49),1,6,""),TRIM($A49)))-SUMIFS(调整事项汇总表!$J$7:$J$10020,调整事项汇总表!$D$7:$D$10020,"账项调整",调整事项汇总表!$E$7:$E$10020,"存货跌价准备",调整事项汇总表!$F$7:$F$10020,IF(OR(MID(TRIM($A49),3,1)="：",MID(TRIM($A49),2,1)="、"),REPLACEB(TRIM($A49),1,6,""),TRIM($A49))) -> 0 | E49: =SUMIFS(调整事项汇总表!$I$7:$I$10020,调整事项汇总表!$D$7:$D$10020,"报表调整",调整事项汇总表!$E$7:$E$10020,"存货原值",调整事项汇总表!$F$7:$F$10020,IF(OR(MID(TRIM($A49),3,1)="：",MID(TRIM($A49),2,1)="、"),REPLACEB(TRIM($A49),1,6,""),TRIM($A49)))-SUMIFS(调整事项汇总表!$I$7:$I$10020,调整事项汇总表!$D$7:$D$10020,"报表调整",调整事项汇总表!$E$7:$E$10020,"存货跌价准备",调整事项汇总表!$F$7:$F$10020,IF(OR(MID(TRIM($A49),3,1)="：",MID(TRIM($A49),2,1)="、"),REPLACEB(TRIM($A49),1,6,""),TRIM($A49))) -> 0 | F49: =SUMIFS(调整事项汇总表!$J$7:$J$10020,调整事项汇总表!$D$7:$D$10020,"报表调整",调整事项汇总表!$E$7:$E$10020,"存货原值",调整事项汇总表!$F$7:$F$10020,IF(OR(MID(TRIM($A49),3,1)="：",MID(TRIM($A49),2,1)="、"),REPLACEB(TRIM($A49),1,6,""),TRIM($A49)))-SUMIFS(调整事项汇总表!$J$7:$J$10020,调整事项汇总表!$D$7:$D$10020,"报表调整",调整事项汇总表!$E$7:$E$10020,"存货跌价准备",调整事项汇总表!$F$7:$F$10020,IF(OR(MID(TRIM($A49),3,1)="：",MID(TRIM($A49),2,1)="、"),REPLACEB(TRIM($A49),1,6,""),TRIM($A49))) -> 0 | G49: =SUMIFS(调整事项汇总表!$I$7:$I$10020,调整事项汇总表!$D$7:$D$10020,"其他",调整事项汇总表!$E$7:$E$10020,"存货原值",调整事项汇总表!$F$7:$F$10020,IF(OR(MID(TRIM($A49),3,1)="：",MID(TRIM($A49),2,1)="、"),REPLACEB(TRIM($A49),1,6,""),TRIM($A49)))-SUMIFS(调整事项汇总表!$I$7:$I$10020,调整事项汇总表!$D$7:$D$10020,"其他",调整事项汇总表!$E$7:$E$10020,"存货跌价准备",调整事项汇总表!$F$7:$F$10020,IF(OR(MID(TRIM($A49),3,1)="：",MID(TRIM($A49),2,1)="、"),REPLACEB(TRIM($A49),1,6,""),TRIM($A49))) -> 0 | H49: =SUMIFS(调整事项汇总表!$J$7:$J$10020,调整事项汇总表!$D$7:$D$10020,"其他",调整事项汇总表!$E$7:$E$10020,"存货原值",调整事项汇总表!$F$7:$F$10020,IF(OR(MID(TRIM($A49),3,1)="：",MID(TRIM($A49),2,1)="、"),REPLACEB(TRIM($A49),1,6,""),TRIM($A49)))-SUMIFS(调整事项汇总表!$J$7:$J$10020,调整事项汇总表!$D$7:$D$10020,"其他",调整事项汇总表!$E$7:$E$10020,"存货跌价准备",调整事项汇总表!$F$7:$F$10020,IF(OR(MID(TRIM($A49),3,1)="：",MID(TRIM($A49),2,1)="、"),REPLACEB(TRIM($A49),1,6,""),TRIM($A49))) -> 0 | I49: =B49+C49+E49+G49-H49-F49-D49 -> 708003 | J49: =A49=未审报表!A49 -> TRUE | K49: =审定报表!A49=TB!A49 -> TRUE
A50: =未审报表!A50 -> 库存商品（产成品） | B50: =未审报表!C50 -> 7000000 | C50: =SUMIFS(调整事项汇总表!$I$7:$I$10020,调整事项汇总表!$D$7:$D$10020,"账项调整",调整事项汇总表!$E$7:$E$10020,"存货原值",调整事项汇总表!$F$7:$F$10020,IF(OR(MID(TRIM($A50),3,1)="：",MID(TRIM($A50),2,1)="、"),REPLACEB(TRIM($A50),1,6,""),TRIM($A50)))-SUMIFS(调整事项汇总表!$I$7:$I$10020,调整事项汇总表!$D$7:$D$10020,"账项调整",调整事项汇总表!$E$7:$E$10020,"存货跌价准备",调整事项汇总表!$F$7:$F$10020,IF(OR(MID(TRIM($A50),3,1)="：",MID(TRIM($A50),2,1)="、"),REPLACEB(TRIM($A50),1,6,""),TRIM($A50))) -> 0 | D50: =SUMIFS(调整事项汇总表!$J$7:$J$10020,调整事项汇总表!$D$7:$D$10020,"账项调整",调整事项汇总表!$E$7:$E$10020,"存货原值",调整事项汇总表!$F$7:$F$10020,IF(OR(MID(TRIM($A50),3,1)="：",MID(TRIM($A50),2,1)="、"),REPLACEB(TRIM($A50),1,6,""),TRIM($A50)))-SUMIFS(调整事项汇总表!$J$7:$J$10020,调整事项汇总表!$D$7:$D$10020,"账项调整",调整事项汇总表!$E$7:$E$10020,"存货跌价准备",调整事项汇总表!$F$7:$F$10020,IF(OR(MID(TRIM($A50),3,1)="：",MID(TRIM($A50),2,1)="、"),REPLACEB(TRIM($A50),1,6,""),TRIM($A50))) -> 10000 | E50: =SUMIFS(调整事项汇总表!$I$7:$I$10020,调整事项汇总表!$D$7:$D$10020,"报表调整",调整事项汇总表!$E$7:$E$10020,"存货原值",调整事项汇总表!$F$7:$F$10020,IF(OR(MID(TRIM($A50),3,1)="：",MID(TRIM($A50),2,1)="、"),REPLACEB(TRIM($A50),1,6,""),TRIM($A50)))-SUMIFS(调整事项汇总表!$I$7:$I$10020,调整事项汇总表!$D$7:$D$10020,"报表调整",调整事项汇总表!$E$7:$E$10020,"存货跌价准备",调整事项汇总表!$F$7:$F$10020,IF(OR(MID(TRIM($A50),3,1)="：",MID(TRIM($A50),2,1)="、"),REPLACEB(TRIM($A50),1,6,""),TRIM($A50))) -> 0 | F50: =SUMIFS(调整事项汇总表!$J$7:$J$10020,调整事项汇总表!$D$7:$D$10020,"报表调整",调整事项汇总表!$E$7:$E$10020,"存货原值",调整事项汇总表!$F$7:$F$10020,IF(OR(MID(TRIM($A50),3,1)="：",MID(TRIM($A50),2,1)="、"),REPLACEB(TRIM($A50),1,6,""),TRIM($A50)))-SUMIFS(调整事项汇总表!$J$7:$J$10020,调整事项汇总表!$D$7:$D$10020,"报表调整",调整事项汇总表!$E$7:$E$10020,"存货跌价准备",调整事项汇总表!$F$7:$F$10020,IF(OR(MID(TRIM($A50),3,1)="：",MID(TRIM($A50),2,1)="、"),REPLACEB(TRIM($A50),1,6,""),TRIM($A50))) -> 0 | G50: =SUMIFS(调整事项汇总表!$I$7:$I$10020,调整事项汇总表!$D$7:$D$10020,"其他",调整事项汇总表!$E$7:$E$10020,"存货原值",调整事项汇总表!$F$7:$F$10020,IF(OR(MID(TRIM($A50),3,1)="：",MID(TRIM($A50),2,1)="、"),REPLACEB(TRIM($A50),1,6,""),TRIM($A50)))-SUMIFS(调整事项汇总表!$I$7:$I$10020,调整事项汇总表!$D$7:$D$10020,"其他",调整事项汇总表!$E$7:$E$10020,"存货跌价准备",调整事项汇总表!$F$7:$F$10020,IF(OR(MID(TRIM($A50),3,1)="：",MID(TRIM($A50),2,1)="、"),REPLACEB(TRIM($A50),1,6,""),TRIM($A50))) -> 0 | H50: =SUMIFS(调整事项汇总表!$J$7:$J$10020,调整事项汇总表!$D$7:$D$10020,"其他",调整事项汇总表!$E$7:$E$10020,"存货原值",调整事项汇总表!$F$7:$F$10020,IF(OR(MID(TRIM($A50),3,1)="：",MID(TRIM($A50),2,1)="、"),REPLACEB(TRIM($A50),1,6,""),TRIM($A50)))-SUMIFS(调整事项汇总表!$J$7:$J$10020,调整事项汇总表!$D$7:$D$10020,"其他",调整事项汇总表!$E$7:$E$10020,"存货跌价准备",调整事项汇总表!$F$7:$F$10020,IF(OR(MID(TRIM($A50),3,1)="：",MID(TRIM($A50),2,1)="、"),REPLACEB(TRIM($A50),1,6,""),TRIM($A50))) -> 0 | I50: =B50+C50+E50+G50-H50-F50-D50 -> 6990000 | J50: =A50=未审报表!A50 -> TRUE | K50: =审定报表!A50=TB!A50 -> TRUE
A51: =未审报表!A51 -> 合同资产原值 | B51: =未审报表!C51 -> 0 | C51: =SUMIFS(调整事项汇总表!$I$7:$I$10020,调整事项汇总表!$D$7:$D$10020,"账项调整",调整事项汇总表!$E$7:$E$10020,IF(OR(MID(TRIM($A51),2,1)="：",MID(TRIM($A51),2,1)="、"),REPLACEB(TRIM($A51),1,4,""),TRIM($A51))) -> 0 | D51: =SUMIFS(调整事项汇总表!$J$7:$J$10020,调整事项汇总表!$D$7:$D$10020,"账项调整",调整事项汇总表!$E$7:$E$10020,IF(OR(MID(TRIM($A51),2,1)="：",MID(TRIM($A51),2,1)="、"),REPLACEB(TRIM($A51),1,4,""),TRIM($A51))) -> 0 | E51: =SUMIFS(调整事项汇总表!$I$7:$I$10020,调整事项汇总表!$D$7:$D$10020,"报表调整",调整事项汇总表!$E$7:$E$10020,IF(OR(MID(TRIM($A51),2,1)="：",MID(TRIM($A51),2,1)="、"),REPLACEB(TRIM($A51),1,4,""),TRIM($A51))) -> 0 | F51: =SUMIFS(调整事项汇总表!$J$7:$J$10020,调整事项汇总表!$D$7:$D$10020,"报表调整",调整事项汇总表!$E$7:$E$10020,IF(OR(MID(TRIM($A51),2,1)="：",MID(TRIM($A51),2,1)="、"),REPLACEB(TRIM($A51),1,4,""),TRIM($A51))) -> 0 | G51: =SUMIFS(调整事项汇总表!$I$7:$I$10020,调整事项汇总表!$D$7:$D$10020,"其他",调整事项汇总表!$E$7:$E$10020,IF(OR(MID(TRIM($A51),2,1)="：",MID(TRIM($A51),2,1)="、"),REPLACEB(TRIM($A51),1,4,""),TRIM($A51))) -> 0 | H51: =SUMIFS(调整事项汇总表!$J$7:$J$10020,调整事项汇总表!$D$7:$D$10020,"其他",调整事项汇总表!$E$7:$E$10020,IF(OR(MID(TRIM($A51),2,1)="：",MID(TRIM($A51),2,1)="、"),REPLACEB(TRIM($A51),1,4,""),TRIM($A51))) -> 0 | I51: =B51+C51+E51+G51-H51-F51-D51 -> 0 | J51: =A51=未审报表!A51 -> TRUE | K51: =审定报表!A51=TB!A51 -> TRUE
A52: =未审报表!A52 -> 合同资产减值准备 | B52: =未审报表!C52 -> 0 | C52: =SUMIFS(调整事项汇总表!$I$7:$I$10020,调整事项汇总表!$D$7:$D$10020,"账项调整",调整事项汇总表!$E$7:$E$10020,IF(OR(MID(TRIM($A52),2,1)="：",MID(TRIM($A52),2,1)="、"),REPLACEB(TRIM($A52),1,4,""),TRIM($A52))) -> 0 | D52: =SUMIFS(调整事项汇总表!$J$7:$J$10020,调整事项汇总表!$D$7:$D$10020,"账项调整",调整事项汇总表!$E$7:$E$10020,IF(OR(MID(TRIM($A52),2,1)="：",MID(TRIM($A52),2,1)="、"),REPLACEB(TRIM($A52),1,4,""),TRIM($A52))) -> 0 | E52: =SUMIFS(调整事项汇总表!$I$7:$I$10020,调整事项汇总表!$D$7:$D$10020,"报表调整",调整事项汇总表!$E$7:$E$10020,IF(OR(MID(TRIM($A52),2,1)="：",MID(TRIM($A52),2,1)="、"),REPLACEB(TRIM($A52),1,4,""),TRIM($A52))) -> 0 | F52: =SUMIFS(调整事项汇总表!$J$7:$J$10020,调整事项汇总表!$D$7:$D$10020,"报表调整",调整事项汇总表!$E$7:$E$10020,IF(OR(MID(TRIM($A52),2,1)="：",MID(TRIM($A52),2,1)="、"),REPLACEB(TRIM($A52),1,4,""),TRIM($A52))) -> 0 | G52: =SUMIFS(调整事项汇总表!$I$7:$I$10020,调整事项汇总表!$D$7:$D$10020,"其他",调整事项汇总表!$E$7:$E$10020,IF(OR(MID(TRIM($A52),2,1)="：",MID(TRIM($A52),2,1)="、"),REPLACEB(TRIM($A52),1,4,""),TRIM($A52))) -> 0 | H52: =SUMIFS(调整事项汇总表!$J$7:$J$10020,调整事项汇总表!$D$7:$D$10020,"其他",调整事项汇总表!$E$7:$E$10020,IF(OR(MID(TRIM($A52),2,1)="：",MID(TRIM($A52),2,1)="、"),REPLACEB(TRIM($A52),1,4,""),TRIM($A52))) -> 0 | I52: =B52+D52+F52+H52-G52-E52-C52 -> 0 | J52: =A52=未审报表!A52 -> TRUE | K52: =审定报表!A52=TB!A52 -> TRUE
A53: =未审报表!A53 -> 合同资产 | B53: =未审报表!C53 -> 0 | C53: =C51+C52 -> 0 | D53: =D51+D52 -> 0 | E53: =E51+E52 -> 0 | F53: =F51+F52 -> 0 | G53: =G51+G52 -> 0 | H53: =H51+H52 -> 0 | I53: =B53+C53+E53+G53-H53-F53-D53 -> 0 | J53: =A53=未审报表!A53 -> TRUE | K53: =审定报表!A53=TB!A53 -> TRUE
A54: =未审报表!A54 -> 持有待售资产原值 | B54: =未审报表!C54 -> 0 | C54: =SUMIFS(调整事项汇总表!$I$7:$I$10020,调整事项汇总表!$D$7:$D$10020,"账项调整",调整事项汇总表!$E$7:$E$10020,IF(OR(MID(TRIM($A54),2,1)="：",MID(TRIM($A54),2,1)="、"),REPLACEB(TRIM($A54),1,4,""),TRIM($A54))) -> 0 | D54: =SUMIFS(调整事项汇总表!$J$7:$J$10020,调整事项汇总表!$D$7:$D$10020,"账项调整",调整事项汇总表!$E$7:$E$10020,IF(OR(MID(TRIM($A54),2,1)="：",MID(TRIM($A54),2,1)="、"),REPLACEB(TRIM($A54),1,4,""),TRIM($A54))) -> 0 | E54: =SUMIFS(调整事项汇总表!$I$7:$I$10020,调整事项汇总表!$D$7:$D$10020,"报表调整",调整事项汇总表!$E$7:$E$10020,IF(OR(MID(TRIM($A54),2,1)="：",MID(TRIM($A54),2,1)="、"),REPLACEB(TRIM($A54),1,4,""),TRIM($A54))) -> 0 | F54: =SUMIFS(调整事项汇总表!$J$7:$J$10020,调整事项汇总表!$D$7:$D$10020,"报表调整",调整事项汇总表!$E$7:$E$10020,IF(OR(MID(TRIM($A54),2,1)="：",MID(TRIM($A54),2,1)="、"),REPLACEB(TRIM($A54),1,4,""),TRIM($A54))) -> 0 | G54: =SUMIFS(调整事项汇总表!$I$7:$I$10020,调整事项汇总表!$D$7:$D$10020,"其他",调整事项汇总表!$E$7:$E$10020,IF(OR(MID(TRIM($A54),2,1)="：",MID(TRIM($A54),2,1)="、"),REPLACEB(TRIM($A54),1,4,""),TRIM($A54))) -> 0 | H54: =SUMIFS(调整事项汇总表!$J$7:$J$10020,调整事项汇总表!$D$7:$D$10020,"其他",调整事项汇总表!$E$7:$E$10020,IF(OR(MID(TRIM($A54),2,1)="：",MID(TRIM($A54),2,1)="、"),REPLACEB(TRIM($A54),1,4,""),TRIM($A54))) -> 0 | I54: =B54+C54+E54+G54-H54-F54-D54 -> 0 | J54: =A54=未审报表!A54 -> TRUE | K54: =审定报表!A54=TB!A54 -> TRUE
A55: =未审报表!A55 -> 持有待售资产减值准备 | B55: =未审报表!C55 -> 0 | C55: =SUMIFS(调整事项汇总表!$I$7:$I$10020,调整事项汇总表!$D$7:$D$10020,"账项调整",调整事项汇总表!$E$7:$E$10020,IF(OR(MID(TRIM($A55),2,1)="：",MID(TRIM($A55),2,1)="、"),REPLACEB(TRIM($A55),1,4,""),TRIM($A55))) -> 0 | D55: =SUMIFS(调整事项汇总表!$J$7:$J$10020,调整事项汇总表!$D$7:$D$10020,"账项调整",调整事项汇总表!$E$7:$E$10020,IF(OR(MID(TRIM($A55),2,1)="：",MID(TRIM($A55),2,1)="、"),REPLACEB(TRIM($A55),1,4,""),TRIM($A55))) -> 0 | E55: =SUMIFS(调整事项汇总表!$I$7:$I$10020,调整事项汇总表!$D$7:$D$10020,"报表调整",调整事项汇总表!$E$7:$E$10020,IF(OR(MID(TRIM($A55),2,1)="：",MID(TRIM($A55),2,1)="、"),REPLACEB(TRIM($A55),1,4,""),TRIM($A55))) -> 0 | F55: =SUMIFS(调整事项汇总表!$J$7:$J$10020,调整事项汇总表!$D$7:$D$10020,"报表调整",调整事项汇总表!$E$7:$E$10020,IF(OR(MID(TRIM($A55),2,1)="：",MID(TRIM($A55),2,1)="、"),REPLACEB(TRIM($A55),1,4,""),TRIM($A55))) -> 0 | G55: =SUMIFS(调整事项汇总表!$I$7:$I$10020,调整事项汇总表!$D$7:$D$10020,"其他",调整事项汇总表!$E$7:$E$10020,IF(OR(MID(TRIM($A55),2,1)="：",MID(TRIM($A55),2,1)="、"),REPLACEB(TRIM($A55),1,4,""),TRIM($A55))) -> 0 | H55: =SUMIFS(调整事项汇总表!$J$7:$J$10020,调整事项汇总表!$D$7:$D$10020,"其他",调整事项汇总表!$E$7:$E$10020,IF(OR(MID(TRIM($A55),2,1)="：",MID(TRIM($A55),2,1)="、"),REPLACEB(TRIM($A55),1,4,""),TRIM($A55))) -> 0 | I55: =B55+D55+F55+H55-G55-E55-C55 -> 0 | J55: =A55=未审报表!A55 -> TRUE | K55: =审定报表!A55=TB!A55 -> TRUE
A56: =未审报表!A56 -> 持有待售资产 | B56: =未审报表!C56 -> 0 | C56: =C54+C55 -> 0 | D56: =D54+D55 -> 0 | E56: =E54+E55 -> 0 | F56: =F54+F55 -> 0 | G56: =G54+G55 -> 0 | H56: =H54+H55 -> 0 | I56: =B56+C56+E56+G56-H56-F56-D56 -> 0 | J56: =A56=未审报表!A56 -> TRUE | K56: =审定报表!A56=TB!A56 -> TRUE
A57: =未审报表!A57 -> 一年内到期的非流动资产 | B57: =未审报表!C57 -> 0 | C57: =SUMIFS(调整事项汇总表!$I$7:$I$10020,调整事项汇总表!$D$7:$D$10020,"账项调整",调整事项汇总表!$E$7:$E$10020,IF(OR(MID(TRIM($A57),2,1)="：",MID(TRIM($A57),2,1)="、"),REPLACEB(TRIM($A57),1,4,""),TRIM($A57))) -> 0 | D57: =SUMIFS(调整事项汇总表!$J$7:$J$10020,调整事项汇总表!$D$7:$D$10020,"账项调整",调整事项汇总表!$E$7:$E$10020,IF(OR(MID(TRIM($A57),2,1)="：",MID(TRIM($A57),2,1)="、"),REPLACEB(TRIM($A57),1,4,""),TRIM($A57))) -> 0 | E57: =SUMIFS(调整事项汇总表!$I$7:$I$10020,调整事项汇总表!$D$7:$D$10020,"报表调整",调整事项汇总表!$E$7:$E$10020,IF(OR(MID(TRIM($A57),2,1)="：",MID(TRIM($A57),2,1)="、"),REPLACEB(TRIM($A57),1,4,""),TRIM($A57))) -> 0 | F57: =SUMIFS(调整事项汇总表!$J$7:$J$10020,调整事项汇总表!$D$7:$D$10020,"报表调整",调整事项汇总表!$E$7:$E$10020,IF(OR(MID(TRIM($A57),2,1)="：",MID(TRIM($A57),2,1)="、"),REPLACEB(TRIM($A57),1,4,""),TRIM($A57))) -> 0 | G57: =SUMIFS(调整事项汇总表!$I$7:$I$10020,调整事项汇总表!$D$7:$D$10020,"其他",调整事项汇总表!$E$7:$E$10020,IF(OR(MID(TRIM($A57),2,1)="：",MID(TRIM($A57),2,1)="、"),REPLACEB(TRIM($A57),1,4,""),TRIM($A57))) -> 0 | H57: =SUMIFS(调整事项汇总表!$J$7:$J$10020,调整事项汇总表!$D$7:$D$10020,"其他",调整事项汇总表!$E$7:$E$10020,IF(OR(MID(TRIM($A57),2,1)="：",MID(TRIM($A57),2,1)="、"),REPLACEB(TRIM($A57),1,4,""),TRIM($A57))) -> 0 | I57: =B57+C57+E57+G57-H57-F57-D57 -> 0 | J57: =A57=未审报表!A57 -> TRUE | K57: =审定报表!A57=TB!A57 -> TRUE
A58: =未审报表!A58 -> 其他流动资产 | B58: =未审报表!C58 -> 0 | C58: =SUMIFS(调整事项汇总表!$I$7:$I$10020,调整事项汇总表!$D$7:$D$10020,"账项调整",调整事项汇总表!$E$7:$E$10020,IF(OR(MID(TRIM($A58),2,1)="：",MID(TRIM($A58),2,1)="、"),REPLACEB(TRIM($A58),1,4,""),TRIM($A58))) -> 0 | D58: =SUMIFS(调整事项汇总表!$J$7:$J$10020,调整事项汇总表!$D$7:$D$10020,"账项调整",调整事项汇总表!$E$7:$E$10020,IF(OR(MID(TRIM($A58),2,1)="：",MID(TRIM($A58),2,1)="、"),REPLACEB(TRIM($A58),1,4,""),TRIM($A58))) -> 0 | E58: =SUMIFS(调整事项汇总表!$I$7:$I$10020,调整事项汇总表!$D$7:$D$10020,"报表调整",调整事项汇总表!$E$7:$E$10020,IF(OR(MID(TRIM($A58),2,1)="：",MID(TRIM($A58),2,1)="、"),REPLACEB(TRIM($A58),1,4,""),TRIM($A58))) -> 0 | F58: =SUMIFS(调整事项汇总表!$J$7:$J$10020,调整事项汇总表!$D$7:$D$10020,"报表调整",调整事项汇总表!$E$7:$E$10020,IF(OR(MID(TRIM($A58),2,1)="：",MID(TRIM($A58),2,1)="、"),REPLACEB(TRIM($A58),1,4,""),TRIM($A58))) -> 0 | G58: =SUMIFS(调整事项汇总表!$I$7:$I$10020,调整事项汇总表!$D$7:$D$10020,"其他",调整事项汇总表!$E$7:$E$10020,IF(OR(MID(TRIM($A58),2,1)="：",MID(TRIM($A58),2,1)="、"),REPLACEB(TRIM($A58),1,4,""),TRIM($A58))) -> 0 | H58: =SUMIFS(调整事项汇总表!$J$7:$J$10020,调整事项汇总表!$D$7:$D$10020,"其他",调整事项汇总表!$E$7:$E$10020,IF(OR(MID(TRIM($A58),2,1)="：",MID(TRIM($A58),2,1)="、"),REPLACEB(TRIM($A58),1,4,""),TRIM($A58))) -> 0 | I58: =B58+C58+E58+G58-H58-F58-D58 -> 0 | J58: =A58=未审报表!A58 -> TRUE | K58: =审定报表!A58=TB!A58 -> TRUE
A59: =未审报表!A59 -> 流动资产合计 | B59: =未审报表!C59 -> 81087052 | C59: =SUM(C8:C9,C12,C13:C14,C17,C20,C23,C26,C29,C32,C33,C36,C39,C42,C45,C48,C53,C56,C57:C58) -> 13796504 | D59: =SUM(D8:D9,D12,D13:D14,D17,D20,D23,D26,D29,D32,D33,D36,D39,D42,D45,D48,D53,D56,D57:D58) -> 291091.08 | E59: =SUM(E8:E9,E12,E13:E14,E17,E20,E23,E26,E29,E32,E33,E36,E39,E42,E45,E48,E53,E56,E57:E58) -> 0 | F59: =SUM(F8:F9,F12,F13:F14,F17,F20,F23,F26,F29,F32,F33,F36,F39,F42,F45,F48,F53,F56,F57:F58) -> 0 | G59: =SUM(G8:G9,G12,G13:G14,G17,G20,G23,G26,G29,G32,G33,G36,G39,G42,G45,G48,G53,G56,G57:G58) -> 0 | H59: =SUM(H8:H9,H12,H13:H14,H17,H20,H23,H26,H29,H32,H33,H36,H39,H42,H45,H48,H53,H56,H57:H58) -> 0 | I59: =B59+C59+E59+G59-H59-F59-D59 -> 94592464 | J59: =A59=未审报表!A59 -> TRUE | K59: =审定报表!A59=TB!A59 -> TRUE
A60: =未审报表!A60 -> 非流动资产: | J60: =A60=未审报表!A60 -> TRUE | K60: =审定报表!A60=TB!A60 -> TRUE
A61: =未审报表!A61 -> 发放贷款和垫款原值* | B61: =未审报表!C61 -> 0 | C61: =SUMIFS(调整事项汇总表!$I$7:$I$10020,调整事项汇总表!$D$7:$D$10020,"账项调整",调整事项汇总表!$E$7:$E$10020,IF(OR(MID(TRIM($A61),2,1)="：",MID(TRIM($A61),2,1)="、"),REPLACEB(TRIM($A61),1,4,""),TRIM($A61))) -> 0 | D61: =SUMIFS(调整事项汇总表!$J$7:$J$10020,调整事项汇总表!$D$7:$D$10020,"账项调整",调整事项汇总表!$E$7:$E$10020,IF(OR(MID(TRIM($A61),2,1)="：",MID(TRIM($A61),2,1)="、"),REPLACEB(TRIM($A61),1,4,""),TRIM($A61))) -> 0 | E61: =SUMIFS(调整事项汇总表!$I$7:$I$10020,调整事项汇总表!$D$7:$D$10020,"报表调整",调整事项汇总表!$E$7:$E$10020,IF(OR(MID(TRIM($A61),2,1)="：",MID(TRIM($A61),2,1)="、"),REPLACEB(TRIM($A61),1,4,""),TRIM($A61))) -> 0 | F61: =SUMIFS(调整事项汇总表!$J$7:$J$10020,调整事项汇总表!$D$7:$D$10020,"报表调整",调整事项汇总表!$E$7:$E$10020,IF(OR(MID(TRIM($A61),2,1)="：",MID(TRIM($A61),2,1)="、"),REPLACEB(TRIM($A61),1,4,""),TRIM($A61))) -> 0 | G61: =SUMIFS(调整事项汇总表!$I$7:$I$10020,调整事项汇总表!$D$7:$D$10020,"其他",调整事项汇总表!$E$7:$E$10020,IF(OR(MID(TRIM($A61),2,1)="：",MID(TRIM($A61),2,1)="、"),REPLACEB(TRIM($A61),1,4,""),TRIM($A61))) -> 0 | H61: =SUMIFS(调整事项汇总表!$J$7:$J$10020,调整事项汇总表!$D$7:$D$10020,"其他",调整事项汇总表!$E$7:$E$10020,IF(OR(MID(TRIM($A61),2,1)="：",MID(TRIM($A61),2,1)="、"),REPLACEB(TRIM($A61),1,4,""),TRIM($A61))) -> 0 | I61: =B61+C61+E61+G61-H61-F61-D61 -> 0 | J61: =A61=未审报表!A61 -> TRUE | K61: =审定报表!A61=TB!A61 -> TRUE
A62: =未审报表!A62 -> 发放贷款和垫款减值准备* | B62: =未审报表!C62 -> 0 | C62: =SUMIFS(调整事项汇总表!$I$7:$I$10020,调整事项汇总表!$D$7:$D$10020,"账项调整",调整事项汇总表!$E$7:$E$10020,IF(OR(MID(TRIM($A62),2,1)="：",MID(TRIM($A62),2,1)="、"),REPLACEB(TRIM($A62),1,4,""),TRIM($A62))) -> 0 | D62: =SUMIFS(调整事项汇总表!$J$7:$J$10020,调整事项汇总表!$D$7:$D$10020,"账项调整",调整事项汇总表!$E$7:$E$10020,IF(OR(MID(TRIM($A62),2,1)="：",MID(TRIM($A62),2,1)="、"),REPLACEB(TRIM($A62),1,4,""),TRIM($A62))) -> 0 | E62: =SUMIFS(调整事项汇总表!$I$7:$I$10020,调整事项汇总表!$D$7:$D$10020,"报表调整",调整事项汇总表!$E$7:$E$10020,IF(OR(MID(TRIM($A62),2,1)="：",MID(TRIM($A62),2,1)="、"),REPLACEB(TRIM($A62),1,4,""),TRIM($A62))) -> 0 | F62: =SUMIFS(调整事项汇总表!$J$7:$J$10020,调整事项汇总表!$D$7:$D$10020,"报表调整",调整事项汇总表!$E$7:$E$10020,IF(OR(MID(TRIM($A62),2,1)="：",MID(TRIM($A62),2,1)="、"),REPLACEB(TRIM($A62),1,4,""),TRIM($A62))) -> 0 | G62: =SUMIFS(调整事项汇总表!$I$7:$I$10020,调整事项汇总表!$D$7:$D$10020,"其他",调整事项汇总表!$E$7:$E$10020,IF(OR(MID(TRIM($A62),2,1)="：",MID(TRIM($A62),2,1)="、"),REPLACEB(TRIM($A62),1,4,""),TRIM($A62))) -> 0 | H62: =SUMIFS(调整事项汇总表!$J$7:$J$10020,调整事项汇总表!$D$7:$D$10020,"其他",调整事项汇总表!$E$7:$E$10020,IF(OR(MID(TRIM($A62),2,1)="：",MID(TRIM($A62),2,1)="、"),REPLACEB(TRIM($A62),1,4,""),TRIM($A62))) -> 0 | I62: =B62+D62+F62+H62-G62-E62-C62 -> 0 | J62: =A62=未审报表!A62 -> TRUE | K62: =审定报表!A62=TB!A62 -> TRUE
A63: =未审报表!A63 -> 发放贷款和垫款* | B63: =未审报表!C63 -> 0 | C63: =C61+C62 -> 0 | D63: =D61+D62 -> 0 | E63: =E61+E62 -> 0 | F63: =F61+F62 -> 0 | G63: =G61+G62 -> 0 | H63: =H61+H62 -> 0 | I63: =B63+C63+E63+G63-H63-F63-D63 -> 0 | J63: =A63=未审报表!A63 -> TRUE | K63: =审定报表!A63=TB!A63 -> TRUE
A64: =未审报表!A64 -> 债权投资原值 | B64: =未审报表!C64 -> 0 | C64: =SUMIFS(调整事项汇总表!$I$7:$I$10020,调整事项汇总表!$D$7:$D$10020,"账项调整",调整事项汇总表!$E$7:$E$10020,IF(OR(MID(TRIM($A64),2,1)="：",MID(TRIM($A64),2,1)="、"),REPLACEB(TRIM($A64),1,4,""),TRIM($A64))) -> 0 | D64: =SUMIFS(调整事项汇总表!$J$7:$J$10020,调整事项汇总表!$D$7:$D$10020,"账项调整",调整事项汇总表!$E$7:$E$10020,IF(OR(MID(TRIM($A64),2,1)="：",MID(TRIM($A64),2,1)="、"),REPLACEB(TRIM($A64),1,4,""),TRIM($A64))) -> 0 | E64: =SUMIFS(调整事项汇总表!$I$7:$I$10020,调整事项汇总表!$D$7:$D$10020,"报表调整",调整事项汇总表!$E$7:$E$10020,IF(OR(MID(TRIM($A64),2,1)="：",MID(TRIM($A64),2,1)="、"),REPLACEB(TRIM($A64),1,4,""),TRIM($A64))) -> 0 | F64: =SUMIFS(调整事项汇总表!$J$7:$J$10020,调整事项汇总表!$D$7:$D$10020,"报表调整",调整事项汇总表!$E$7:$E$10020,IF(OR(MID(TRIM($A64),2,1)="：",MID(TRIM($A64),2,1)="、"),REPLACEB(TRIM($A64),1,4,""),TRIM($A64))) -> 0 | G64: =SUMIFS(调整事项汇总表!$I$7:$I$10020,调整事项汇总表!$D$7:$D$10020,"其他",调整事项汇总表!$E$7:$E$10020,IF(OR(MID(TRIM($A64),2,1)="：",MID(TRIM($A64),2,1)="、"),REPLACEB(TRIM($A64),1,4,""),TRIM($A64))) -> 0 | H64: =SUMIFS(调整事项汇总表!$J$7:$J$10020,调整事项汇总表!$D$7:$D$10020,"其他",调整事项汇总表!$E$7:$E$10020,IF(OR(MID(TRIM($A64),2,1)="：",MID(TRIM($A64),2,1)="、"),REPLACEB(TRIM($A64),1,4,""),TRIM($A64))) -> 0 | I64: =B64+C64+E64+G64-H64-F64-D64 -> 0 | J64: =A64=未审报表!A64 -> TRUE | K64: =审定报表!A64=TB!A64 -> TRUE
A65: =未审报表!A65 -> 债权投资减值准备 | B65: =未审报表!C65 -> 0 | C65: =SUMIFS(调整事项汇总表!$I$7:$I$10020,调整事项汇总表!$D$7:$D$10020,"账项调整",调整事项汇总表!$E$7:$E$10020,IF(OR(MID(TRIM($A65),2,1)="：",MID(TRIM($A65),2,1)="、"),REPLACEB(TRIM($A65),1,4,""),TRIM($A65))) -> 0 | D65: =SUMIFS(调整事项汇总表!$J$7:$J$10020,调整事项汇总表!$D$7:$D$10020,"账项调整",调整事项汇总表!$E$7:$E$10020,IF(OR(MID(TRIM($A65),2,1)="：",MID(TRIM($A65),2,1)="、"),REPLACEB(TRIM($A65),1,4,""),TRIM($A65))) -> 0 | E65: =SUMIFS(调整事项汇总表!$I$7:$I$10020,调整事项汇总表!$D$7:$D$10020,"报表调整",调整事项汇总表!$E$7:$E$10020,IF(OR(MID(TRIM($A65),2,1)="：",MID(TRIM($A65),2,1)="、"),REPLACEB(TRIM($A65),1,4,""),TRIM($A65))) -> 0 | F65: =SUMIFS(调整事项汇总表!$J$7:$J$10020,调整事项汇总表!$D$7:$D$10020,"报表调整",调整事项汇总表!$E$7:$E$10020,IF(OR(MID(TRIM($A65),2,1)="：",MID(TRIM($A65),2,1)="、"),REPLACEB(TRIM($A65),1,4,""),TRIM($A65))) -> 0 | G65: =SUMIFS(调整事项汇总表!$I$7:$I$10020,调整事项汇总表!$D$7:$D$10020,"其他",调整事项汇总表!$E$7:$E$10020,IF(OR(MID(TRIM($A65),2,1)="：",MID(TRIM($A65),2,1)="、"),REPLACEB(TRIM($A65),1,4,""),TRIM($A65))) -> 0 | H65: =SUMIFS(调整事项汇总表!$J$7:$J$10020,调整事项汇总表!$D$7:$D$10020,"其他",调整事项汇总表!$E$7:$E$10020,IF(OR(MID(TRIM($A65),2,1)="：",MID(TRIM($A65),2,1)="、"),REPLACEB(TRIM($A65),1,4,""),TRIM($A65))) -> 0 | I65: =B65+D65+F65+H65-G65-E65-C65 -> 0 | J65: =A65=未审报表!A65 -> TRUE | K65: =审定报表!A65=TB!A65 -> TRUE
A66: =未审报表!A66 -> 债权投资 | B66: =未审报表!C66 -> 0 | C66: =C64+C65 -> 0 | D66: =D64+D65 -> 0 | E66: =E64+E65 -> 0 | F66: =F64+F65 -> 0 | G66: =G64+G65 -> 0 | H66: =H64+H65 -> 0 | I66: =B66+C66+E66+G66-H66-F66-D66 -> 0 | J66: =A66=未审报表!A66 -> TRUE | K66: =审定报表!A66=TB!A66 -> TRUE
A67: =未审报表!A67 -> 其他债权投资原值 | B67: =未审报表!C67 -> 0 | C67: =SUMIFS(调整事项汇总表!$I$7:$I$10020,调整事项汇总表!$D$7:$D$10020,"账项调整",调整事项汇总表!$E$7:$E$10020,IF(OR(MID(TRIM($A67),2,1)="：",MID(TRIM($A67),2,1)="、"),REPLACEB(TRIM($A67),1,4,""),TRIM($A67))) -> 0 | D67: =SUMIFS(调整事项汇总表!$J$7:$J$10020,调整事项汇总表!$D$7:$D$10020,"账项调整",调整事项汇总表!$E$7:$E$10020,IF(OR(MID(TRIM($A67),2,1)="：",MID(TRIM($A67),2,1)="、"),REPLACEB(TRIM($A67),1,4,""),TRIM($A67))) -> 0 | E67: =SUMIFS(调整事项汇总表!$I$7:$I$10020,调整事项汇总表!$D$7:$D$10020,"报表调整",调整事项汇总表!$E$7:$E$10020,IF(OR(MID(TRIM($A67),2,1)="：",MID(TRIM($A67),2,1)="、"),REPLACEB(TRIM($A67),1,4,""),TRIM($A67))) -> 0 | F67: =SUMIFS(调整事项汇总表!$J$7:$J$10020,调整事项汇总表!$D$7:$D$10020,"报表调整",调整事项汇总表!$E$7:$E$10020,IF(OR(MID(TRIM($A67),2,1)="：",MID(TRIM($A67),2,1)="、"),REPLACEB(TRIM($A67),1,4,""),TRIM($A67))) -> 0 | G67: =SUMIFS(调整事项汇总表!$I$7:$I$10020,调整事项汇总表!$D$7:$D$10020,"其他",调整事项汇总表!$E$7:$E$10020,IF(OR(MID(TRIM($A67),2,1)="：",MID(TRIM($A67),2,1)="、"),REPLACEB(TRIM($A67),1,4,""),TRIM($A67))) -> 0 | H67: =SUMIFS(调整事项汇总表!$J$7:$J$10020,调整事项汇总表!$D$7:$D$10020,"其他",调整事项汇总表!$E$7:$E$10020,IF(OR(MID(TRIM($A67),2,1)="：",MID(TRIM($A67),2,1)="、"),REPLACEB(TRIM($A67),1,4,""),TRIM($A67))) -> 0 | I67: =B67+C67+E67+G67-H67-F67-D67 -> 0 | J67: =A67=未审报表!A67 -> TRUE | K67: =审定报表!A67=TB!A67 -> TRUE
A68: =未审报表!A68 -> 其他债权投资减值准备 | B68: =未审报表!C68 -> 0 | C68: =SUMIFS(调整事项汇总表!$I$7:$I$10020,调整事项汇总表!$D$7:$D$10020,"账项调整",调整事项汇总表!$E$7:$E$10020,IF(OR(MID(TRIM($A68),2,1)="：",MID(TRIM($A68),2,1)="、"),REPLACEB(TRIM($A68),1,4,""),TRIM($A68))) -> 0 | D68: =SUMIFS(调整事项汇总表!$J$7:$J$10020,调整事项汇总表!$D$7:$D$10020,"账项调整",调整事项汇总表!$E$7:$E$10020,IF(OR(MID(TRIM($A68),2,1)="：",MID(TRIM($A68),2,1)="、"),REPLACEB(TRIM($A68),1,4,""),TRIM($A68))) -> 0 | E68: =SUMIFS(调整事项汇总表!$I$7:$I$10020,调整事项汇总表!$D$7:$D$10020,"报表调整",调整事项汇总表!$E$7:$E$10020,IF(OR(MID(TRIM($A68),2,1)="：",MID(TRIM($A68),2,1)="、"),REPLACEB(TRIM($A68),1,4,""),TRIM($A68))) -> 0 | F68: =SUMIFS(调整事项汇总表!$J$7:$J$10020,调整事项汇总表!$D$7:$D$10020,"报表调整",调整事项汇总表!$E$7:$E$10020,IF(OR(MID(TRIM($A68),2,1)="：",MID(TRIM($A68),2,1)="、"),REPLACEB(TRIM($A68),1,4,""),TRIM($A68))) -> 0 | G68: =SUMIFS(调整事项汇总表!$I$7:$I$10020,调整事项汇总表!$D$7:$D$10020,"其他",调整事项汇总表!$E$7:$E$10020,IF(OR(MID(TRIM($A68),2,1)="：",MID(TRIM($A68),2,1)="、"),REPLACEB(TRIM($A68),1,4,""),TRIM($A68))) -> 0 | H68: =SUMIFS(调整事项汇总表!$J$7:$J$10020,调整事项汇总表!$D$7:$D$10020,"其他",调整事项汇总表!$E$7:$E$10020,IF(OR(MID(TRIM($A68),2,1)="：",MID(TRIM($A68),2,1)="、"),REPLACEB(TRIM($A68),1,4,""),TRIM($A68))) -> 0 | I68: =B68+D68+F68+H68-G68-E68-C68 -> 0 | J68: =A68=未审报表!A68 -> TRUE | K68: =审定报表!A68=TB!A68 -> TRUE
A69: =未审报表!A69 -> 其他债权投资 | B69: =未审报表!C69 -> 0 | C69: =C67+C68 -> 0 | D69: =D67+D68 -> 0 | E69: =E67+E68 -> 0 | F69: =F67+F68 -> 0 | G69: =G67+G68 -> 0 | H69: =H67+H68 -> 0 | I69: =B69+C69+E69+G69-H69-F69-D69 -> 0 | J69: =A69=未审报表!A69 -> TRUE | K69: =审定报表!A69=TB!A69 -> TRUE
A70: =未审报表!A70 -> 长期应收款原值 | B70: =未审报表!C70 -> 0 | C70: =SUMIFS(调整事项汇总表!$I$7:$I$10020,调整事项汇总表!$D$7:$D$10020,"账项调整",调整事项汇总表!$E$7:$E$10020,IF(OR(MID(TRIM($A70),2,1)="：",MID(TRIM($A70),2,1)="、"),REPLACEB(TRIM($A70),1,4,""),TRIM($A70))) -> 0 | D70: =SUMIFS(调整事项汇总表!$J$7:$J$10020,调整事项汇总表!$D$7:$D$10020,"账项调整",调整事项汇总表!$E$7:$E$10020,IF(OR(MID(TRIM($A70),2,1)="：",MID(TRIM($A70),2,1)="、"),REPLACEB(TRIM($A70),1,4,""),TRIM($A70))) -> 0 | E70: =SUMIFS(调整事项汇总表!$I$7:$I$10020,调整事项汇总表!$D$7:$D$10020,"报表调整",调整事项汇总表!$E$7:$E$10020,IF(OR(MID(TRIM($A70),2,1)="：",MID(TRIM($A70),2,1)="、"),REPLACEB(TRIM($A70),1,4,""),TRIM($A70))) -> 0 | F70: =SUMIFS(调整事项汇总表!$J$7:$J$10020,调整事项汇总表!$D$7:$D$10020,"报表调整",调整事项汇总表!$E$7:$E$10020,IF(OR(MID(TRIM($A70),2,1)="：",MID(TRIM($A70),2,1)="、"),REPLACEB(TRIM($A70),1,4,""),TRIM($A70))) -> 0 | G70: =SUMIFS(调整事项汇总表!$I$7:$I$10020,调整事项汇总表!$D$7:$D$10020,"其他",调整事项汇总表!$E$7:$E$10020,IF(OR(MID(TRIM($A70),2,1)="：",MID(TRIM($A70),2,1)="、"),REPLACEB(TRIM($A70),1,4,""),TRIM($A70))) -> 0 | H70: =SUMIFS(调整事项汇总表!$J$7:$J$10020,调整事项汇总表!$D$7:$D$10020,"其他",调整事项汇总表!$E$7:$E$10020,IF(OR(MID(TRIM($A70),2,1)="：",MID(TRIM($A70),2,1)="、"),REPLACEB(TRIM($A70),1,4,""),TRIM($A70))) -> 0 | I70: =B70+C70+E70+G70-H70-F70-D70 -> 0 | J70: =A70=未审报表!A70 -> TRUE | K70: =审定报表!A70=TB!A70 -> TRUE
A71: =未审报表!A71 -> 长期应收款坏账准备 | B71: =未审报表!C71 -> 0 | C71: =SUMIFS(调整事项汇总表!$I$7:$I$10020,调整事项汇总表!$D$7:$D$10020,"账项调整",调整事项汇总表!$E$7:$E$10020,IF(OR(MID(TRIM($A71),2,1)="：",MID(TRIM($A71),2,1)="、"),REPLACEB(TRIM($A71),1,4,""),TRIM($A71))) -> 0 | D71: =SUMIFS(调整事项汇总表!$J$7:$J$10020,调整事项汇总表!$D$7:$D$10020,"账项调整",调整事项汇总表!$E$7:$E$10020,IF(OR(MID(TRIM($A71),2,1)="：",MID(TRIM($A71),2,1)="、"),REPLACEB(TRIM($A71),1,4,""),TRIM($A71))) -> 0 | E71: =SUMIFS(调整事项汇总表!$I$7:$I$10020,调整事项汇总表!$D$7:$D$10020,"报表调整",调整事项汇总表!$E$7:$E$10020,IF(OR(MID(TRIM($A71),2,1)="：",MID(TRIM($A71),2,1)="、"),REPLACEB(TRIM($A71),1,4,""),TRIM($A71))) -> 0 | F71: =SUMIFS(调整事项汇总表!$J$7:$J$10020,调整事项汇总表!$D$7:$D$10020,"报表调整",调整事项汇总表!$E$7:$E$10020,IF(OR(MID(TRIM($A71),2,1)="：",MID(TRIM($A71),2,1)="、"),REPLACEB(TRIM($A71),1,4,""),TRIM($A71))) -> 0 | G71: =SUMIFS(调整事项汇总表!$I$7:$I$10020,调整事项汇总表!$D$7:$D$10020,"其他",调整事项汇总表!$E$7:$E$10020,IF(OR(MID(TRIM($A71),2,1)="：",MID(TRIM($A71),2,1)="、"),REPLACEB(TRIM($A71),1,4,""),TRIM($A71))) -> 0 | H71: =SUMIFS(调整事项汇总表!$J$7:$J$10020,调整事项汇总表!$D$7:$D$10020,"其他",调整事项汇总表!$E$7:$E$10020,IF(OR(MID(TRIM($A71),2,1)="：",MID(TRIM($A71),2,1)="、"),REPLACEB(TRIM($A71),1,4,""),TRIM($A71))) -> 0 | I71: =B71+D71+F71+H71-G71-E71-C71 -> 0 | J71: =A71=未审报表!A71 -> TRUE | K71: =审定报表!A71=TB!A71 -> TRUE
A72: =未审报表!A72 -> 长期应收款 | B72: =未审报表!C72 -> 0 | C72: =C70+C71 -> 0 | D72: =D70+D71 -> 0 | E72: =E70+E71 -> 0 | F72: =F70+F71 -> 0 | G72: =G70+G71 -> 0 | H72: =H70+H71 -> 0 | I72: =B72+C72+E72+G72-H72-F72-D72 -> 0 | J72: =A72=未审报表!A72 -> TRUE | K72: =审定报表!A72=TB!A72 -> TRUE
A73: =未审报表!A73 -> 设定受益计划净资产 | B73: =未审报表!C73 -> 0 | C73: =SUMIFS(调整事项汇总表!$I$7:$I$10020,调整事项汇总表!$D$7:$D$10020,"账项调整",调整事项汇总表!$E$7:$E$10020,IF(OR(MID(TRIM($A73),2,1)="：",MID(TRIM($A73),2,1)="、"),REPLACEB(TRIM($A73),1,4,""),TRIM($A73))) -> 0 | D73: =SUMIFS(调整事项汇总表!$J$7:$J$10020,调整事项汇总表!$D$7:$D$10020,"账项调整",调整事项汇总表!$E$7:$E$10020,IF(OR(MID(TRIM($A73),2,1)="：",MID(TRIM($A73),2,1)="、"),REPLACEB(TRIM($A73),1,4,""),TRIM($A73))) -> 0 | E73: =SUMIFS(调整事项汇总表!$I$7:$I$10020,调整事项汇总表!$D$7:$D$10020,"报表调整",调整事项汇总表!$E$7:$E$10020,IF(OR(MID(TRIM($A73),2,1)="：",MID(TRIM($A73),2,1)="、"),REPLACEB(TRIM($A73),1,4,""),TRIM($A73))) -> 0 | F73: =SUMIFS(调整事项汇总表!$J$7:$J$10020,调整事项汇总表!$D$7:$D$10020,"报表调整",调整事项汇总表!$E$7:$E$10020,IF(OR(MID(TRIM($A73),2,1)="：",MID(TRIM($A73),2,1)="、"),REPLACEB(TRIM($A73),1,4,""),TRIM($A73))) -> 0 | G73: =SUMIFS(调整事项汇总表!$I$7:$I$10020,调整事项汇总表!$D$7:$D$10020,"其他",调整事项汇总表!$E$7:$E$10020,IF(OR(MID(TRIM($A73),2,1)="：",MID(TRIM($A73),2,1)="、"),REPLACEB(TRIM($A73),1,4,""),TRIM($A73))) -> 0 | H73: =SUMIFS(调整事项汇总表!$J$7:$J$10020,调整事项汇总表!$D$7:$D$10020,"其他",调整事项汇总表!$E$7:$E$10020,IF(OR(MID(TRIM($A73),2,1)="：",MID(TRIM($A73),2,1)="、"),REPLACEB(TRIM($A73),1,4,""),TRIM($A73))) -> 0 | I73: =B73+C73+E73+G73-H73-F73-D73 -> 0 | J73: =A73=未审报表!A73 -> TRUE | K73: =审定报表!A73=TB!A73 -> TRUE
A74: =未审报表!A74 -> 长期股权投资原值 | B74: =未审报表!C74 -> 23870038 | C74: =SUMIFS(调整事项汇总表!$I$7:$I$10020,调整事项汇总表!$D$7:$D$10020,"账项调整",调整事项汇总表!$E$7:$E$10020,IF(OR(MID(TRIM($A74),2,1)="：",MID(TRIM($A74),2,1)="、"),REPLACEB(TRIM($A74),1,4,""),TRIM($A74))) -> 9120002.2 | D74: =SUMIFS(调整事项汇总表!$J$7:$J$10020,调整事项汇总表!$D$7:$D$10020,"账项调整",调整事项汇总表!$E$7:$E$10020,IF(OR(MID(TRIM($A74),2,1)="：",MID(TRIM($A74),2,1)="、"),REPLACEB(TRIM($A74),1,4,""),TRIM($A74))) -> 0 | E74: =SUMIFS(调整事项汇总表!$I$7:$I$10020,调整事项汇总表!$D$7:$D$10020,"报表调整",调整事项汇总表!$E$7:$E$10020,IF(OR(MID(TRIM($A74),2,1)="：",MID(TRIM($A74),2,1)="、"),REPLACEB(TRIM($A74),1,4,""),TRIM($A74))) -> 0 | F74: =SUMIFS(调整事项汇总表!$J$7:$J$10020,调整事项汇总表!$D$7:$D$10020,"报表调整",调整事项汇总表!$E$7:$E$10020,IF(OR(MID(TRIM($A74),2,1)="：",MID(TRIM($A74),2,1)="、"),REPLACEB(TRIM($A74),1,4,""),TRIM($A74))) -> 0 | G74: =SUMIFS(调整事项汇总表!$I$7:$I$10020,调整事项汇总表!$D$7:$D$10020,"其他",调整事项汇总表!$E$7:$E$10020,IF(OR(MID(TRIM($A74),2,1)="：",MID(TRIM($A74),2,1)="、"),REPLACEB(TRIM($A74),1,4,""),TRIM($A74))) -> 0 | H74: =SUMIFS(调整事项汇总表!$J$7:$J$10020,调整事项汇总表!$D$7:$D$10020,"其他",调整事项汇总表!$E$7:$E$10020,IF(OR(MID(TRIM($A74),2,1)="：",MID(TRIM($A74),2,1)="、"),REPLACEB(TRIM($A74),1,4,""),TRIM($A74))) -> 0 | I74: =B74+C74+E74+G74-H74-F74-D74 -> 32990040 | J74: =A74=未审报表!A74 -> TRUE | K74: =审定报表!A74=TB!A74 -> TRUE
A75: =未审报表!A75 -> 长期股权投资减值准备 | B75: =未审报表!C75 -> 0 | C75: =SUMIFS(调整事项汇总表!$I$7:$I$10020,调整事项汇总表!$D$7:$D$10020,"账项调整",调整事项汇总表!$E$7:$E$10020,IF(OR(MID(TRIM($A75),2,1)="：",MID(TRIM($A75),2,1)="、"),REPLACEB(TRIM($A75),1,4,""),TRIM($A75))) -> 0 | D75: =SUMIFS(调整事项汇总表!$J$7:$J$10020,调整事项汇总表!$D$7:$D$10020,"账项调整",调整事项汇总表!$E$7:$E$10020,IF(OR(MID(TRIM($A75),2,1)="：",MID(TRIM($A75),2,1)="、"),REPLACEB(TRIM($A75),1,4,""),TRIM($A75))) -> 0 | E75: =SUMIFS(调整事项汇总表!$I$7:$I$10020,调整事项汇总表!$D$7:$D$10020,"报表调整",调整事项汇总表!$E$7:$E$10020,IF(OR(MID(TRIM($A75),2,1)="：",MID(TRIM($A75),2,1)="、"),REPLACEB(TRIM($A75),1,4,""),TRIM($A75))) -> 0 | F75: =SUMIFS(调整事项汇总表!$J$7:$J$10020,调整事项汇总表!$D$7:$D$10020,"报表调整",调整事项汇总表!$E$7:$E$10020,IF(OR(MID(TRIM($A75),2,1)="：",MID(TRIM($A75),2,1)="、"),REPLACEB(TRIM($A75),1,4,""),TRIM($A75))) -> 0 | G75: =SUMIFS(调整事项汇总表!$I$7:$I$10020,调整事项汇总表!$D$7:$D$10020,"其他",调整事项汇总表!$E$7:$E$10020,IF(OR(MID(TRIM($A75),2,1)="：",MID(TRIM($A75),2,1)="、"),REPLACEB(TRIM($A75),1,4,""),TRIM($A75))) -> 0 | H75: =SUMIFS(调整事项汇总表!$J$7:$J$10020,调整事项汇总表!$D$7:$D$10020,"其他",调整事项汇总表!$E$7:$E$10020,IF(OR(MID(TRIM($A75),2,1)="：",MID(TRIM($A75),2,1)="、"),REPLACEB(TRIM($A75),1,4,""),TRIM($A75))) -> 0 | I75: =B75+D75+F75+H75-G75-E75-C75 -> 0 | J75: =A75=未审报表!A75 -> TRUE | K75: =审定报表!A75=TB!A75 -> TRUE
A76: =未审报表!A76 -> 长期股权投资 | B76: =未审报表!C76 -> 23870038 | C76: =C74+C75 -> 9120002.2 | D76: =D74+D75 -> 0 | E76: =E74+E75 -> 0 | F76: =F74+F75 -> 0 | G76: =G74+G75 -> 0 | H76: =H74+H75 -> 0 | I76: =B76+C76+E76+G76-H76-F76-D76 -> 32990040 | J76: =A76=未审报表!A76 -> TRUE | K76: =审定报表!A76=TB!A76 -> TRUE
A77: =未审报表!A77 -> 其他权益工具投资 | B77: =未审报表!C77 -> 0 | C77: =SUMIFS(调整事项汇总表!$I$7:$I$10020,调整事项汇总表!$D$7:$D$10020,"账项调整",调整事项汇总表!$E$7:$E$10020,IF(OR(MID(TRIM($A77),2,1)="：",MID(TRIM($A77),2,1)="、"),REPLACEB(TRIM($A77),1,4,""),TRIM($A77))) -> 0 | D77: =SUMIFS(调整事项汇总表!$J$7:$J$10020,调整事项汇总表!$D$7:$D$10020,"账项调整",调整事项汇总表!$E$7:$E$10020,IF(OR(MID(TRIM($A77),2,1)="：",MID(TRIM($A77),2,1)="、"),REPLACEB(TRIM($A77),1,4,""),TRIM($A77))) -> 0 | E77: =SUMIFS(调整事项汇总表!$I$7:$I$10020,调整事项汇总表!$D$7:$D$10020,"报表调整",调整事项汇总表!$E$7:$E$10020,IF(OR(MID(TRIM($A77),2,1)="：",MID(TRIM($A77),2,1)="、"),REPLACEB(TRIM($A77),1,4,""),TRIM($A77))) -> 0 | F77: =SUMIFS(调整事项汇总表!$J$7:$J$10020,调整事项汇总表!$D$7:$D$10020,"报表调整",调整事项汇总表!$E$7:$E$10020,IF(OR(MID(TRIM($A77),2,1)="：",MID(TRIM($A77),2,1)="、"),REPLACEB(TRIM($A77),1,4,""),TRIM($A77))) -> 0 | G77: =SUMIFS(调整事项汇总表!$I$7:$I$10020,调整事项汇总表!$D$7:$D$10020,"其他",调整事项汇总表!$E$7:$E$10020,IF(OR(MID(TRIM($A77),2,1)="：",MID(TRIM($A77),2,1)="、"),REPLACEB(TRIM($A77),1,4,""),TRIM($A77))) -> 0 | H77: =SUMIFS(调整事项汇总表!$J$7:$J$10020,调整事项汇总表!$D$7:$D$10020,"其他",调整事项汇总表!$E$7:$E$10020,IF(OR(MID(TRIM($A77),2,1)="：",MID(TRIM($A77),2,1)="、"),REPLACEB(TRIM($A77),1,4,""),TRIM($A77))) -> 0 | I77: =B77+C77+E77+G77-H77-F77-D77 -> 0 | J77: =A77=未审报表!A77 -> TRUE | K77: =审定报表!A77=TB!A77 -> TRUE
A78: =未审报表!A78 -> 其他非流动金融资产 | B78: =未审报表!C78 -> 0 | C78: =SUMIFS(调整事项汇总表!$I$7:$I$10020,调整事项汇总表!$D$7:$D$10020,"账项调整",调整事项汇总表!$E$7:$E$10020,IF(OR(MID(TRIM($A78),2,1)="：",MID(TRIM($A78),2,1)="、"),REPLACEB(TRIM($A78),1,4,""),TRIM($A78))) -> 0 | D78: =SUMIFS(调整事项汇总表!$J$7:$J$10020,调整事项汇总表!$D$7:$D$10020,"账项调整",调整事项汇总表!$E$7:$E$10020,IF(OR(MID(TRIM($A78),2,1)="：",MID(TRIM($A78),2,1)="、"),REPLACEB(TRIM($A78),1,4,""),TRIM($A78))) -> 0 | E78: =SUMIFS(调整事项汇总表!$I$7:$I$10020,调整事项汇总表!$D$7:$D$10020,"报表调整",调整事项汇总表!$E$7:$E$10020,IF(OR(MID(TRIM($A78),2,1)="：",MID(TRIM($A78),2,1)="、"),REPLACEB(TRIM($A78),1,4,""),TRIM($A78))) -> 0 | F78: =SUMIFS(调整事项汇总表!$J$7:$J$10020,调整事项汇总表!$D$7:$D$10020,"报表调整",调整事项汇总表!$E$7:$E$10020,IF(OR(MID(TRIM($A78),2,1)="：",MID(TRIM($A78),2,1)="、"),REPLACEB(TRIM($A78),1,4,""),TRIM($A78))) -> 0 | G78: =SUMIFS(调整事项汇总表!$I$7:$I$10020,调整事项汇总表!$D$7:$D$10020,"其他",调整事项汇总表!$E$7:$E$10020,IF(OR(MID(TRIM($A78),2,1)="：",MID(TRIM($A78),2,1)="、"),REPLACEB(TRIM($A78),1,4,""),TRIM($A78))) -> 0 | H78: =SUMIFS(调整事项汇总表!$J$7:$J$10020,调整事项汇总表!$D$7:$D$10020,"其他",调整事项汇总表!$E$7:$E$10020,IF(OR(MID(TRIM($A78),2,1)="：",MID(TRIM($A78),2,1)="、"),REPLACEB(TRIM($A78),1,4,""),TRIM($A78))) -> 0 | I78: =B78+C78+E78+G78-H78-F78-D78 -> 0 | J78: =A78=未审报表!A78 -> TRUE | K78: =审定报表!A78=TB!A78 -> TRUE
A79: =未审报表!A79 -> 投资性房地产原值 | B79: =未审报表!C79 -> 0 | C79: =SUMIFS(调整事项汇总表!$I$7:$I$10020,调整事项汇总表!$D$7:$D$10020,"账项调整",调整事项汇总表!$E$7:$E$10020,IF(OR(MID(TRIM($A79),2,1)="：",MID(TRIM($A79),2,1)="、"),REPLACEB(TRIM($A79),1,4,""),TRIM($A79))) -> 0 | D79: =SUMIFS(调整事项汇总表!$J$7:$J$10020,调整事项汇总表!$D$7:$D$10020,"账项调整",调整事项汇总表!$E$7:$E$10020,IF(OR(MID(TRIM($A79),2,1)="：",MID(TRIM($A79),2,1)="、"),REPLACEB(TRIM($A79),1,4,""),TRIM($A79))) -> 0 | E79: =SUMIFS(调整事项汇总表!$I$7:$I$10020,调整事项汇总表!$D$7:$D$10020,"报表调整",调整事项汇总表!$E$7:$E$10020,IF(OR(MID(TRIM($A79),2,1)="：",MID(TRIM($A79),2,1)="、"),REPLACEB(TRIM($A79),1,4,""),TRIM($A79))) -> 0 | F79: =SUMIFS(调整事项汇总表!$J$7:$J$10020,调整事项汇总表!$D$7:$D$10020,"报表调整",调整事项汇总表!$E$7:$E$10020,IF(OR(MID(TRIM($A79),2,1)="：",MID(TRIM($A79),2,1)="、"),REPLACEB(TRIM($A79),1,4,""),TRIM($A79))) -> 0 | G79: =SUMIFS(调整事项汇总表!$I$7:$I$10020,调整事项汇总表!$D$7:$D$10020,"其他",调整事项汇总表!$E$7:$E$10020,IF(OR(MID(TRIM($A79),2,1)="：",MID(TRIM($A79),2,1)="、"),REPLACEB(TRIM($A79),1,4,""),TRIM($A79))) -> 0 | H79: =SUMIFS(调整事项汇总表!$J$7:$J$10020,调整事项汇总表!$D$7:$D$10020,"其他",调整事项汇总表!$E$7:$E$10020,IF(OR(MID(TRIM($A79),2,1)="：",MID(TRIM($A79),2,1)="、"),REPLACEB(TRIM($A79),1,4,""),TRIM($A79))) -> 0 | I79: =B79+C79+E79+G79-H79-F79-D79 -> 0 | J79: =A79=未审报表!A79 -> TRUE | K79: =审定报表!A79=TB!A79 -> TRUE
A80: =未审报表!A80 -> 投资性房地产累计折旧 | B80: =未审报表!C80 -> 0 | C80: =SUMIFS(调整事项汇总表!$I$7:$I$10020,调整事项汇总表!$D$7:$D$10020,"账项调整",调整事项汇总表!$E$7:$E$10020,IF(OR(MID(TRIM($A80),2,1)="：",MID(TRIM($A80),2,1)="、"),REPLACEB(TRIM($A80),1,4,""),TRIM($A80))) -> 0 | D80: =SUMIFS(调整事项汇总表!$J$7:$J$10020,调整事项汇总表!$D$7:$D$10020,"账项调整",调整事项汇总表!$E$7:$E$10020,IF(OR(MID(TRIM($A80),2,1)="：",MID(TRIM($A80),2,1)="、"),REPLACEB(TRIM($A80),1,4,""),TRIM($A80))) -> 0 | E80: =SUMIFS(调整事项汇总表!$I$7:$I$10020,调整事项汇总表!$D$7:$D$10020,"报表调整",调整事项汇总表!$E$7:$E$10020,IF(OR(MID(TRIM($A80),2,1)="：",MID(TRIM($A80),2,1)="、"),REPLACEB(TRIM($A80),1,4,""),TRIM($A80))) -> 0 | F80: =SUMIFS(调整事项汇总表!$J$7:$J$10020,调整事项汇总表!$D$7:$D$10020,"报表调整",调整事项汇总表!$E$7:$E$10020,IF(OR(MID(TRIM($A80),2,1)="：",MID(TRIM($A80),2,1)="、"),REPLACEB(TRIM($A80),1,4,""),TRIM($A80))) -> 0 | G80: =SUMIFS(调整事项汇总表!$I$7:$I$10020,调整事项汇总表!$D$7:$D$10020,"其他",调整事项汇总表!$E$7:$E$10020,IF(OR(MID(TRIM($A80),2,1)="：",MID(TRIM($A80),2,1)="、"),REPLACEB(TRIM($A80),1,4,""),TRIM($A80))) -> 0 | H80: =SUMIFS(调整事项汇总表!$J$7:$J$10020,调整事项汇总表!$D$7:$D$10020,"其他",调整事项汇总表!$E$7:$E$10020,IF(OR(MID(TRIM($A80),2,1)="：",MID(TRIM($A80),2,1)="、"),REPLACEB(TRIM($A80),1,4,""),TRIM($A80))) -> 0 | I80: =B80+D80+F80+H80-G80-E80-C80 -> 0 | J80: =A80=未审报表!A80 -> TRUE | K80: =审定报表!A80=TB!A80 -> TRUE
A81: =未审报表!A81 -> 投资性房地产净值 | B81: =未审报表!C81 -> 0 | C81: =C79+C80 -> 0 | D81: =D79+D80 -> 0 | E81: =E79+E80 -> 0 | F81: =F79+F80 -> 0 | G81: =G79+G80 -> 0 | H81: =H79+H80 -> 0 | I81: =B81+C81+E81+G81-H81-F81-D81 -> 0 | J81: =A81=未审报表!A81 -> TRUE | K81: =审定报表!A81=TB!A81 -> TRUE
A82: =未审报表!A82 -> 投资性房地产减值准备 | B82: =未审报表!C82 -> 0 | C82: =SUMIFS(调整事项汇总表!$I$7:$I$10020,调整事项汇总表!$D$7:$D$10020,"账项调整",调整事项汇总表!$E$7:$E$10020,IF(OR(MID(TRIM($A82),2,1)="：",MID(TRIM($A82),2,1)="、"),REPLACEB(TRIM($A82),1,4,""),TRIM($A82))) -> 0 | D82: =SUMIFS(调整事项汇总表!$J$7:$J$10020,调整事项汇总表!$D$7:$D$10020,"账项调整",调整事项汇总表!$E$7:$E$10020,IF(OR(MID(TRIM($A82),2,1)="：",MID(TRIM($A82),2,1)="、"),REPLACEB(TRIM($A82),1,4,""),TRIM($A82))) -> 0 | E82: =SUMIFS(调整事项汇总表!$I$7:$I$10020,调整事项汇总表!$D$7:$D$10020,"报表调整",调整事项汇总表!$E$7:$E$10020,IF(OR(MID(TRIM($A82),2,1)="：",MID(TRIM($A82),2,1)="、"),REPLACEB(TRIM($A82),1,4,""),TRIM($A82))) -> 0 | F82: =SUMIFS(调整事项汇总表!$J$7:$J$10020,调整事项汇总表!$D$7:$D$10020,"报表调整",调整事项汇总表!$E$7:$E$10020,IF(OR(MID(TRIM($A82),2,1)="：",MID(TRIM($A82),2,1)="、"),REPLACEB(TRIM($A82),1,4,""),TRIM($A82))) -> 0 | G82: =SUMIFS(调整事项汇总表!$I$7:$I$10020,调整事项汇总表!$D$7:$D$10020,"其他",调整事项汇总表!$E$7:$E$10020,IF(OR(MID(TRIM($A82),2,1)="：",MID(TRIM($A82),2,1)="、"),REPLACEB(TRIM($A82),1,4,""),TRIM($A82))) -> 0 | H82: =SUMIFS(调整事项汇总表!$J$7:$J$10020,调整事项汇总表!$D$7:$D$10020,"其他",调整事项汇总表!$E$7:$E$10020,IF(OR(MID(TRIM($A82),2,1)="：",MID(TRIM($A82),2,1)="、"),REPLACEB(TRIM($A82),1,4,""),TRIM($A82))) -> 0 | I82: =B82+D82+F82+H82-G82-E82-C82 -> 0 | J82: =A82=未审报表!A82 -> TRUE | K82: =审定报表!A82=TB!A82 -> TRUE
A83: =未审报表!A83 -> 投资性房地产 | B83: =未审报表!C83 -> 0 | C83: =C81+C82 -> 0 | D83: =D81+D82 -> 0 | E83: =E81+E82 -> 0 | F83: =F81+F82 -> 0 | G83: =G81+G82 -> 0 | H83: =H81+H82 -> 0 | I83: =B83+C83+E83+G83-H83-F83-D83 -> 0 | J83: =A83=未审报表!A83 -> TRUE | K83: =审定报表!A83=TB!A83 -> TRUE
A84: =未审报表!A84 -> 固定资产原值 | B84: =未审报表!C84 -> 114529.92 | C84: =SUMIFS(调整事项汇总表!$I$7:$I$10020,调整事项汇总表!$D$7:$D$10020,"账项调整",调整事项汇总表!$E$7:$E$10020,IF(OR(MID(TRIM($A84),2,1)="：",MID(TRIM($A84),2,1)="、"),REPLACEB(TRIM($A84),1,4,""),TRIM($A84))) -> 0 | D84: =SUMIFS(调整事项汇总表!$J$7:$J$10020,调整事项汇总表!$D$7:$D$10020,"账项调整",调整事项汇总表!$E$7:$E$10020,IF(OR(MID(TRIM($A84),2,1)="：",MID(TRIM($A84),2,1)="、"),REPLACEB(TRIM($A84),1,4,""),TRIM($A84))) -> 0 | E84: =SUMIFS(调整事项汇总表!$I$7:$I$10020,调整事项汇总表!$D$7:$D$10020,"报表调整",调整事项汇总表!$E$7:$E$10020,IF(OR(MID(TRIM($A84),2,1)="：",MID(TRIM($A84),2,1)="、"),REPLACEB(TRIM($A84),1,4,""),TRIM($A84))) -> 0 | F84: =SUMIFS(调整事项汇总表!$J$7:$J$10020,调整事项汇总表!$D$7:$D$10020,"报表调整",调整事项汇总表!$E$7:$E$10020,IF(OR(MID(TRIM($A84),2,1)="：",MID(TRIM($A84),2,1)="、"),REPLACEB(TRIM($A84),1,4,""),TRIM($A84))) -> 0 | G84: =SUMIFS(调整事项汇总表!$I$7:$I$10020,调整事项汇总表!$D$7:$D$10020,"其他",调整事项汇总表!$E$7:$E$10020,IF(OR(MID(TRIM($A84),2,1)="：",MID(TRIM($A84),2,1)="、"),REPLACEB(TRIM($A84),1,4,""),TRIM($A84))) -> 0 | H84: =SUMIFS(调整事项汇总表!$J$7:$J$10020,调整事项汇总表!$D$7:$D$10020,"其他",调整事项汇总表!$E$7:$E$10020,IF(OR(MID(TRIM($A84),2,1)="：",MID(TRIM($A84),2,1)="、"),REPLACEB(TRIM($A84),1,4,""),TRIM($A84))) -> 0 | I84: =B84+C84+E84+G84-H84-F84-D84 -> 114529.92 | J84: =A84=未审报表!A84 -> TRUE | K84: =审定报表!A84=TB!A84 -> TRUE
A85: =未审报表!A85 -> 固定资产累计折旧 | B85: =未审报表!C85 -> 15907.1 | C85: =SUMIFS(调整事项汇总表!$I$7:$I$10020,调整事项汇总表!$D$7:$D$10020,"账项调整",调整事项汇总表!$E$7:$E$10020,IF(OR(MID(TRIM($A85),2,1)="：",MID(TRIM($A85),2,1)="、"),REPLACEB(TRIM($A85),1,4,""),TRIM($A85))) -> 0 | D85: =SUMIFS(调整事项汇总表!$J$7:$J$10020,调整事项汇总表!$D$7:$D$10020,"账项调整",调整事项汇总表!$E$7:$E$10020,IF(OR(MID(TRIM($A85),2,1)="：",MID(TRIM($A85),2,1)="、"),REPLACEB(TRIM($A85),1,4,""),TRIM($A85))) -> 0 | E85: =SUMIFS(调整事项汇总表!$I$7:$I$10020,调整事项汇总表!$D$7:$D$10020,"报表调整",调整事项汇总表!$E$7:$E$10020,IF(OR(MID(TRIM($A85),2,1)="：",MID(TRIM($A85),2,1)="、"),REPLACEB(TRIM($A85),1,4,""),TRIM($A85))) -> 0 | F85: =SUMIFS(调整事项汇总表!$J$7:$J$10020,调整事项汇总表!$D$7:$D$10020,"报表调整",调整事项汇总表!$E$7:$E$10020,IF(OR(MID(TRIM($A85),2,1)="：",MID(TRIM($A85),2,1)="、"),REPLACEB(TRIM($A85),1,4,""),TRIM($A85))) -> 0 | G85: =SUMIFS(调整事项汇总表!$I$7:$I$10020,调整事项汇总表!$D$7:$D$10020,"其他",调整事项汇总表!$E$7:$E$10020,IF(OR(MID(TRIM($A85),2,1)="：",MID(TRIM($A85),2,1)="、"),REPLACEB(TRIM($A85),1,4,""),TRIM($A85))) -> 0 | H85: =SUMIFS(调整事项汇总表!$J$7:$J$10020,调整事项汇总表!$D$7:$D$10020,"其他",调整事项汇总表!$E$7:$E$10020,IF(OR(MID(TRIM($A85),2,1)="：",MID(TRIM($A85),2,1)="、"),REPLACEB(TRIM($A85),1,4,""),TRIM($A85))) -> 0 | I85: =B85+D85+F85+H85-G85-E85-C85 -> 15907.1 | J85: =A85=未审报表!A85 -> TRUE | K85: =审定报表!A85=TB!A85 -> TRUE
A86: =未审报表!A86 -> 固定资产净值 | B86: =未审报表!C86 -> 98622.82 | C86: =C84+C85 -> 0 | D86: =D84+D85 -> 0 | E86: =E84+E85 -> 0 | F86: =F84+F85 -> 0 | G86: =G84+G85 -> 0 | H86: =H84+H85 -> 0 | I86: =B86+C86+E86+G86-H86-F86-D86 -> 98622.82 | J86: =A86=未审报表!A86 -> TRUE | K86: =审定报表!A86=TB!A86 -> TRUE
A87: =未审报表!A87 -> 固定资产减值准备 | B87: =未审报表!C87 -> 0 | C87: =SUMIFS(调整事项汇总表!$I$7:$I$10020,调整事项汇总表!$D$7:$D$10020,"账项调整",调整事项汇总表!$E$7:$E$10020,IF(OR(MID(TRIM($A87),2,1)="：",MID(TRIM($A87),2,1)="、"),REPLACEB(TRIM($A87),1,4,""),TRIM($A87))) -> 0 | D87: =SUMIFS(调整事项汇总表!$J$7:$J$10020,调整事项汇总表!$D$7:$D$10020,"账项调整",调整事项汇总表!$E$7:$E$10020,IF(OR(MID(TRIM($A87),2,1)="：",MID(TRIM($A87),2,1)="、"),REPLACEB(TRIM($A87),1,4,""),TRIM($A87))) -> 0 | E87: =SUMIFS(调整事项汇总表!$I$7:$I$10020,调整事项汇总表!$D$7:$D$10020,"报表调整",调整事项汇总表!$E$7:$E$10020,IF(OR(MID(TRIM($A87),2,1)="：",MID(TRIM($A87),2,1)="、"),REPLACEB(TRIM($A87),1,4,""),TRIM($A87))) -> 0 | F87: =SUMIFS(调整事项汇总表!$J$7:$J$10020,调整事项汇总表!$D$7:$D$10020,"报表调整",调整事项汇总表!$E$7:$E$10020,IF(OR(MID(TRIM($A87),2,1)="：",MID(TRIM($A87),2,1)="、"),REPLACEB(TRIM($A87),1,4,""),TRIM($A87))) -> 0 | G87: =SUMIFS(调整事项汇总表!$I$7:$I$10020,调整事项汇总表!$D$7:$D$10020,"其他",调整事项汇总表!$E$7:$E$10020,IF(OR(MID(TRIM($A87),2,1)="：",MID(TRIM($A87),2,1)="、"),REPLACEB(TRIM($A87),1,4,""),TRIM($A87))) -> 0 | H87: =SUMIFS(调整事项汇总表!$J$7:$J$10020,调整事项汇总表!$D$7:$D$10020,"其他",调整事项汇总表!$E$7:$E$10020,IF(OR(MID(TRIM($A87),2,1)="：",MID(TRIM($A87),2,1)="、"),REPLACEB(TRIM($A87),1,4,""),TRIM($A87))) -> 0 | I87: =B87+D87+F87+H87-G87-E87-C87 -> 0 | J87: =A87=未审报表!A87 -> TRUE | K87: =审定报表!A87=TB!A87 -> TRUE
A88: =未审报表!A88 -> 固定资产 | B88: =未审报表!C88 -> 98622.82 | C88: =C86+C87 -> 0 | D88: =D86+D87 -> 0 | E88: =E86+E87 -> 0 | F88: =F86+F87 -> 0 | G88: =G86+G87 -> 0 | H88: =H86+H87 -> 0 | I88: =B88+C88+E88+G88-H88-F88-D88 -> 98622.82 | J88: =A88=未审报表!A88 -> TRUE | K88: =审定报表!A88=TB!A88 -> TRUE
A89: =未审报表!A89 -> 固定资产清理 | B89: =未审报表!C89 -> 0 | C89: =SUMIFS(调整事项汇总表!$I$7:$I$10020,调整事项汇总表!$D$7:$D$10020,"账项调整",调整事项汇总表!$E$7:$E$10020,IF(OR(MID(TRIM($A89),2,1)="：",MID(TRIM($A89),2,1)="、"),REPLACEB(TRIM($A89),1,4,""),TRIM($A89))) -> 0 | D89: =SUMIFS(调整事项汇总表!$J$7:$J$10020,调整事项汇总表!$D$7:$D$10020,"账项调整",调整事项汇总表!$E$7:$E$10020,IF(OR(MID(TRIM($A89),2,1)="：",MID(TRIM($A89),2,1)="、"),REPLACEB(TRIM($A89),1,4,""),TRIM($A89))) -> 0 | E89: =SUMIFS(调整事项汇总表!$I$7:$I$10020,调整事项汇总表!$D$7:$D$10020,"报表调整",调整事项汇总表!$E$7:$E$10020,IF(OR(MID(TRIM($A89),2,1)="：",MID(TRIM($A89),2,1)="、"),REPLACEB(TRIM($A89),1,4,""),TRIM($A89))) -> 0 | F89: =SUMIFS(调整事项汇总表!$J$7:$J$10020,调整事项汇总表!$D$7:$D$10020,"报表调整",调整事项汇总表!$E$7:$E$10020,IF(OR(MID(TRIM($A89),2,1)="：",MID(TRIM($A89),2,1)="、"),REPLACEB(TRIM($A89),1,4,""),TRIM($A89))) -> 0 | G89: =SUMIFS(调整事项汇总表!$I$7:$I$10020,调整事项汇总表!$D$7:$D$10020,"其他",调整事项汇总表!$E$7:$E$10020,IF(OR(MID(TRIM($A89),2,1)="：",MID(TRIM($A89),2,1)="、"),REPLACEB(TRIM($A89),1,4,""),TRIM($A89))) -> 0 | H89: =SUMIFS(调整事项汇总表!$J$7:$J$10020,调整事项汇总表!$D$7:$D$10020,"其他",调整事项汇总表!$E$7:$E$10020,IF(OR(MID(TRIM($A89),2,1)="：",MID(TRIM($A89),2,1)="、"),REPLACEB(TRIM($A89),1,4,""),TRIM($A89))) -> 0 | I89: =B89+C89+E89+G89-H89-F89-D89 -> 0 | J89: =A89=未审报表!A89 -> TRUE | K89: =审定报表!A89=TB!A89 -> TRUE
A90: =未审报表!A90 -> 在建工程原值 | B90: =未审报表!C90 -> 0 | C90: =SUMIFS(调整事项汇总表!$I$7:$I$10020,调整事项汇总表!$D$7:$D$10020,"账项调整",调整事项汇总表!$E$7:$E$10020,IF(OR(MID(TRIM($A90),2,1)="：",MID(TRIM($A90),2,1)="、"),REPLACEB(TRIM($A90),1,4,""),TRIM($A90))) -> 0 | D90: =SUMIFS(调整事项汇总表!$J$7:$J$10020,调整事项汇总表!$D$7:$D$10020,"账项调整",调整事项汇总表!$E$7:$E$10020,IF(OR(MID(TRIM($A90),2,1)="：",MID(TRIM($A90),2,1)="、"),REPLACEB(TRIM($A90),1,4,""),TRIM($A90))) -> 0 | E90: =SUMIFS(调整事项汇总表!$I$7:$I$10020,调整事项汇总表!$D$7:$D$10020,"报表调整",调整事项汇总表!$E$7:$E$10020,IF(OR(MID(TRIM($A90),2,1)="：",MID(TRIM($A90),2,1)="、"),REPLACEB(TRIM($A90),1,4,""),TRIM($A90))) -> 0 | F90: =SUMIFS(调整事项汇总表!$J$7:$J$10020,调整事项汇总表!$D$7:$D$10020,"报表调整",调整事项汇总表!$E$7:$E$10020,IF(OR(MID(TRIM($A90),2,1)="：",MID(TRIM($A90),2,1)="、"),REPLACEB(TRIM($A90),1,4,""),TRIM($A90))) -> 0 | G90: =SUMIFS(调整事项汇总表!$I$7:$I$10020,调整事项汇总表!$D$7:$D$10020,"其他",调整事项汇总表!$E$7:$E$10020,IF(OR(MID(TRIM($A90),2,1)="：",MID(TRIM($A90),2,1)="、"),REPLACEB(TRIM($A90),1,4,""),TRIM($A90))) -> 0 | H90: =SUMIFS(调整事项汇总表!$J$7:$J$10020,调整事项汇总表!$D$7:$D$10020,"其他",调整事项汇总表!$E$7:$E$10020,IF(OR(MID(TRIM($A90),2,1)="：",MID(TRIM($A90),2,1)="、"),REPLACEB(TRIM($A90),1,4,""),TRIM($A90))) -> 0 | I90: =B90+C90+E90+G90-H90-F90-D90 -> 0 | J90: =A90=未审报表!A90 -> TRUE | K90: =审定报表!A90=TB!A90 -> TRUE
A91: =未审报表!A91 -> 在建工程减值准备 | B91: =未审报表!C91 -> 0 | C91: =SUMIFS(调整事项汇总表!$I$7:$I$10020,调整事项汇总表!$D$7:$D$10020,"账项调整",调整事项汇总表!$E$7:$E$10020,IF(OR(MID(TRIM($A91),2,1)="：",MID(TRIM($A91),2,1)="、"),REPLACEB(TRIM($A91),1,4,""),TRIM($A91))) -> 0 | D91: =SUMIFS(调整事项汇总表!$J$7:$J$10020,调整事项汇总表!$D$7:$D$10020,"账项调整",调整事项汇总表!$E$7:$E$10020,IF(OR(MID(TRIM($A91),2,1)="：",MID(TRIM($A91),2,1)="、"),REPLACEB(TRIM($A91),1,4,""),TRIM($A91))) -> 0 | E91: =SUMIFS(调整事项汇总表!$I$7:$I$10020,调整事项汇总表!$D$7:$D$10020,"报表调整",调整事项汇总表!$E$7:$E$10020,IF(OR(MID(TRIM($A91),2,1)="：",MID(TRIM($A91),2,1)="、"),REPLACEB(TRIM($A91),1,4,""),TRIM($A91))) -> 0 | F91: =SUMIFS(调整事项汇总表!$J$7:$J$10020,调整事项汇总表!$D$7:$D$10020,"报表调整",调整事项汇总表!$E$7:$E$10020,IF(OR(MID(TRIM($A91),2,1)="：",MID(TRIM($A91),2,1)="、"),REPLACEB(TRIM($A91),1,4,""),TRIM($A91))) -> 0 | G91: =SUMIFS(调整事项汇总表!$I$7:$I$10020,调整事项汇总表!$D$7:$D$10020,"其他",调整事项汇总表!$E$7:$E$10020,IF(OR(MID(TRIM($A91),2,1)="：",MID(TRIM($A91),2,1)="、"),REPLACEB(TRIM($A91),1,4,""),TRIM($A91))) -> 0 | H91: =SUMIFS(调整事项汇总表!$J$7:$J$10020,调整事项汇总表!$D$7:$D$10020,"其他",调整事项汇总表!$E$7:$E$10020,IF(OR(MID(TRIM($A91),2,1)="：",MID(TRIM($A91),2,1)="、"),REPLACEB(TRIM($A91),1,4,""),TRIM($A91))) -> 0 | I91: =B91+D91+F91+H91-G91-E91-C91 -> 0 | J91: =A91=未审报表!A91 -> TRUE | K91: =审定报表!A91=TB!A91 -> TRUE
A92: =未审报表!A92 -> 在建工程 | B92: =未审报表!C92 -> 0 | C92: =C90+C91 -> 0 | D92: =D90+D91 -> 0 | E92: =E90+E91 -> 0 | F92: =F90+F91 -> 0 | G92: =G90+G91 -> 0 | H92: =H90+H91 -> 0 | I92: =B92+C92+E92+G92-H92-F92-D92 -> 0 | J92: =A92=未审报表!A92 -> TRUE | K92: =审定报表!A92=TB!A92 -> TRUE
A93: =未审报表!A93 -> 工程物资原值 | B93: =未审报表!C93 -> 0 | C93: =SUMIFS(调整事项汇总表!$I$7:$I$10020,调整事项汇总表!$D$7:$D$10020,"账项调整",调整事项汇总表!$E$7:$E$10020,IF(OR(MID(TRIM($A93),2,1)="：",MID(TRIM($A93),2,1)="、"),REPLACEB(TRIM($A93),1,4,""),TRIM($A93))) -> 0 | D93: =SUMIFS(调整事项汇总表!$J$7:$J$10020,调整事项汇总表!$D$7:$D$10020,"账项调整",调整事项汇总表!$E$7:$E$10020,IF(OR(MID(TRIM($A93),2,1)="：",MID(TRIM($A93),2,1)="、"),REPLACEB(TRIM($A93),1,4,""),TRIM($A93))) -> 0 | E93: =SUMIFS(调整事项汇总表!$I$7:$I$10020,调整事项汇总表!$D$7:$D$10020,"报表调整",调整事项汇总表!$E$7:$E$10020,IF(OR(MID(TRIM($A93),2,1)="：",MID(TRIM($A93),2,1)="、"),REPLACEB(TRIM($A93),1,4,""),TRIM($A93))) -> 0 | F93: =SUMIFS(调整事项汇总表!$J$7:$J$10020,调整事项汇总表!$D$7:$D$10020,"报表调整",调整事项汇总表!$E$7:$E$10020,IF(OR(MID(TRIM($A93),2,1)="：",MID(TRIM($A93),2,1)="、"),REPLACEB(TRIM($A93),1,4,""),TRIM($A93))) -> 0 | G93: =SUMIFS(调整事项汇总表!$I$7:$I$10020,调整事项汇总表!$D$7:$D$10020,"其他",调整事项汇总表!$E$7:$E$10020,IF(OR(MID(TRIM($A93),2,1)="：",MID(TRIM($A93),2,1)="、"),REPLACEB(TRIM($A93),1,4,""),TRIM($A93))) -> 0 | H93: =SUMIFS(调整事项汇总表!$J$7:$J$10020,调整事项汇总表!$D$7:$D$10020,"其他",调整事项汇总表!$E$7:$E$10020,IF(OR(MID(TRIM($A93),2,1)="：",MID(TRIM($A93),2,1)="、"),REPLACEB(TRIM($A93),1,4,""),TRIM($A93))) -> 0 | I93: =B93+C93+E93+G93-H93-F93-D93 -> 0 | J93: =A93=未审报表!A93 -> TRUE | K93: =审定报表!A93=TB!A93 -> TRUE
A94: =未审报表!A94 -> 工程物资减值准备 | B94: =未审报表!C94 -> 0 | C94: =SUMIFS(调整事项汇总表!$I$7:$I$10020,调整事项汇总表!$D$7:$D$10020,"账项调整",调整事项汇总表!$E$7:$E$10020,IF(OR(MID(TRIM($A94),2,1)="：",MID(TRIM($A94),2,1)="、"),REPLACEB(TRIM($A94),1,4,""),TRIM($A94))) -> 0 | D94: =SUMIFS(调整事项汇总表!$J$7:$J$10020,调整事项汇总表!$D$7:$D$10020,"账项调整",调整事项汇总表!$E$7:$E$10020,IF(OR(MID(TRIM($A94),2,1)="：",MID(TRIM($A94),2,1)="、"),REPLACEB(TRIM($A94),1,4,""),TRIM($A94))) -> 0 | E94: =SUMIFS(调整事项汇总表!$I$7:$I$10020,调整事项汇总表!$D$7:$D$10020,"报表调整",调整事项汇总表!$E$7:$E$10020,IF(OR(MID(TRIM($A94),2,1)="：",MID(TRIM($A94),2,1)="、"),REPLACEB(TRIM($A94),1,4,""),TRIM($A94))) -> 0 | F94: =SUMIFS(调整事项汇总表!$J$7:$J$10020,调整事项汇总表!$D$7:$D$10020,"报表调整",调整事项汇总表!$E$7:$E$10020,IF(OR(MID(TRIM($A94),2,1)="：",MID(TRIM($A94),2,1)="、"),REPLACEB(TRIM($A94),1,4,""),TRIM($A94))) -> 0 | G94: =SUMIFS(调整事项汇总表!$I$7:$I$10020,调整事项汇总表!$D$7:$D$10020,"其他",调整事项汇总表!$E$7:$E$10020,IF(OR(MID(TRIM($A94),2,1)="：",MID(TRIM($A94),2,1)="、"),REPLACEB(TRIM($A94),1,4,""),TRIM($A94))) -> 0 | H94: =SUMIFS(调整事项汇总表!$J$7:$J$10020,调整事项汇总表!$D$7:$D$10020,"其他",调整事项汇总表!$E$7:$E$10020,IF(OR(MID(TRIM($A94),2,1)="：",MID(TRIM($A94),2,1)="、"),REPLACEB(TRIM($A94),1,4,""),TRIM($A94))) -> 0 | I94: =B94+D94+F94+H94-G94-E94-C94 -> 0 | J94: =A94=未审报表!A94 -> TRUE | K94: =审定报表!A94=TB!A94 -> TRUE
A95: =未审报表!A95 -> 工程物资 | B95: =未审报表!C95 -> 0 | C95: =C93+C94 -> 0 | D95: =D93+D94 -> 0 | E95: =E93+E94 -> 0 | F95: =F93+F94 -> 0 | G95: =G93+G94 -> 0 | H95: =H93+H94 -> 0 | I95: =B95+C95+E95+G95-H95-F95-D95 -> 0 | J95: =A95=未审报表!A95 -> TRUE | K95: =审定报表!A95=TB!A95 -> TRUE
A96: =未审报表!A96 -> 生产性生物资产原值 | B96: =未审报表!C96 -> 0 | C96: =SUMIFS(调整事项汇总表!$I$7:$I$10020,调整事项汇总表!$D$7:$D$10020,"账项调整",调整事项汇总表!$E$7:$E$10020,IF(OR(MID(TRIM($A96),2,1)="：",MID(TRIM($A96),2,1)="、"),REPLACEB(TRIM($A96),1,4,""),TRIM($A96))) -> 0 | D96: =SUMIFS(调整事项汇总表!$J$7:$J$10020,调整事项汇总表!$D$7:$D$10020,"账项调整",调整事项汇总表!$E$7:$E$10020,IF(OR(MID(TRIM($A96),2,1)="：",MID(TRIM($A96),2,1)="、"),REPLACEB(TRIM($A96),1,4,""),TRIM($A96))) -> 0 | E96: =SUMIFS(调整事项汇总表!$I$7:$I$10020,调整事项汇总表!$D$7:$D$10020,"报表调整",调整事项汇总表!$E$7:$E$10020,IF(OR(MID(TRIM($A96),2,1)="：",MID(TRIM($A96),2,1)="、"),REPLACEB(TRIM($A96),1,4,""),TRIM($A96))) -> 0 | F96: =SUMIFS(调整事项汇总表!$J$7:$J$10020,调整事项汇总表!$D$7:$D$10020,"报表调整",调整事项汇总表!$E$7:$E$10020,IF(OR(MID(TRIM($A96),2,1)="：",MID(TRIM($A96),2,1)="、"),REPLACEB(TRIM($A96),1,4,""),TRIM($A96))) -> 0 | G96: =SUMIFS(调整事项汇总表!$I$7:$I$10020,调整事项汇总表!$D$7:$D$10020,"其他",调整事项汇总表!$E$7:$E$10020,IF(OR(MID(TRIM($A96),2,1)="：",MID(TRIM($A96),2,1)="、"),REPLACEB(TRIM($A96),1,4,""),TRIM($A96))) -> 0 | H96: =SUMIFS(调整事项汇总表!$J$7:$J$10020,调整事项汇总表!$D$7:$D$10020,"其他",调整事项汇总表!$E$7:$E$10020,IF(OR(MID(TRIM($A96),2,1)="：",MID(TRIM($A96),2,1)="、"),REPLACEB(TRIM($A96),1,4,""),TRIM($A96))) -> 0 | I96: =B96+C96+E96+G96-H96-F96-D96 -> 0 | J96: =A96=未审报表!A96 -> TRUE | K96: =审定报表!A96=TB!A96 -> TRUE
A97: =未审报表!A97 -> 生产性生物资产累计折旧 | B97: =未审报表!C97 -> 0 | C97: =SUMIFS(调整事项汇总表!$I$7:$I$10020,调整事项汇总表!$D$7:$D$10020,"账项调整",调整事项汇总表!$E$7:$E$10020,IF(OR(MID(TRIM($A97),2,1)="：",MID(TRIM($A97),2,1)="、"),REPLACEB(TRIM($A97),1,4,""),TRIM($A97))) -> 0 | D97: =SUMIFS(调整事项汇总表!$J$7:$J$10020,调整事项汇总表!$D$7:$D$10020,"账项调整",调整事项汇总表!$E$7:$E$10020,IF(OR(MID(TRIM($A97),2,1)="：",MID(TRIM($A97),2,1)="、"),REPLACEB(TRIM($A97),1,4,""),TRIM($A97))) -> 0 | E97: =SUMIFS(调整事项汇总表!$I$7:$I$10020,调整事项汇总表!$D$7:$D$10020,"报表调整",调整事项汇总表!$E$7:$E$10020,IF(OR(MID(TRIM($A97),2,1)="：",MID(TRIM($A97),2,1)="、"),REPLACEB(TRIM($A97),1,4,""),TRIM($A97))) -> 0 | F97: =SUMIFS(调整事项汇总表!$J$7:$J$10020,调整事项汇总表!$D$7:$D$10020,"报表调整",调整事项汇总表!$E$7:$E$10020,IF(OR(MID(TRIM($A97),2,1)="：",MID(TRIM($A97),2,1)="、"),REPLACEB(TRIM($A97),1,4,""),TRIM($A97))) -> 0 | G97: =SUMIFS(调整事项汇总表!$I$7:$I$10020,调整事项汇总表!$D$7:$D$10020,"其他",调整事项汇总表!$E$7:$E$10020,IF(OR(MID(TRIM($A97),2,1)="：",MID(TRIM($A97),2,1)="、"),REPLACEB(TRIM($A97),1,4,""),TRIM($A97))) -> 0 | H97: =SUMIFS(调整事项汇总表!$J$7:$J$10020,调整事项汇总表!$D$7:$D$10020,"其他",调整事项汇总表!$E$7:$E$10020,IF(OR(MID(TRIM($A97),2,1)="：",MID(TRIM($A97),2,1)="、"),REPLACEB(TRIM($A97),1,4,""),TRIM($A97))) -> 0 | I97: =B97+D97+F97+H97-G97-E97-C97 -> 0 | J97: =A97=未审报表!A97 -> TRUE | K97: =审定报表!A97=TB!A97 -> TRUE
A98: =未审报表!A98 -> 生产性生物资产净值 | B98: =未审报表!C98 -> 0 | C98: =C96+C97 -> 0 | D98: =D96+D97 -> 0 | E98: =E96+E97 -> 0 | F98: =F96+F97 -> 0 | G98: =G96+G97 -> 0 | H98: =H96+H97 -> 0 | I98: =B98+C98+E98+G98-H98-F98-D98 -> 0 | J98: =A98=未审报表!A98 -> TRUE | K98: =审定报表!A98=TB!A98 -> TRUE
A99: =未审报表!A99 -> 生产性生物资产减值准备 | B99: =未审报表!C99 -> 0 | C99: =SUMIFS(调整事项汇总表!$I$7:$I$10020,调整事项汇总表!$D$7:$D$10020,"账项调整",调整事项汇总表!$E$7:$E$10020,IF(OR(MID(TRIM($A99),2,1)="：",MID(TRIM($A99),2,1)="、"),REPLACEB(TRIM($A99),1,4,""),TRIM($A99))) -> 0 | D99: =SUMIFS(调整事项汇总表!$J$7:$J$10020,调整事项汇总表!$D$7:$D$10020,"账项调整",调整事项汇总表!$E$7:$E$10020,IF(OR(MID(TRIM($A99),2,1)="：",MID(TRIM($A99),2,1)="、"),REPLACEB(TRIM($A99),1,4,""),TRIM($A99))) -> 0 | E99: =SUMIFS(调整事项汇总表!$I$7:$I$10020,调整事项汇总表!$D$7:$D$10020,"报表调整",调整事项汇总表!$E$7:$E$10020,IF(OR(MID(TRIM($A99),2,1)="：",MID(TRIM($A99),2,1)="、"),REPLACEB(TRIM($A99),1,4,""),TRIM($A99))) -> 0 | F99: =SUMIFS(调整事项汇总表!$J$7:$J$10020,调整事项汇总表!$D$7:$D$10020,"报表调整",调整事项汇总表!$E$7:$E$10020,IF(OR(MID(TRIM($A99),2,1)="：",MID(TRIM($A99),2,1)="、"),REPLACEB(TRIM($A99),1,4,""),TRIM($A99))) -> 0 | G99: =SUMIFS(调整事项汇总表!$I$7:$I$10020,调整事项汇总表!$D$7:$D$10020,"其他",调整事项汇总表!$E$7:$E$10020,IF(OR(MID(TRIM($A99),2,1)="：",MID(TRIM($A99),2,1)="、"),REPLACEB(TRIM($A99),1,4,""),TRIM($A99))) -> 0 | H99: =SUMIFS(调整事项汇总表!$J$7:$J$10020,调整事项汇总表!$D$7:$D$10020,"其他",调整事项汇总表!$E$7:$E$10020,IF(OR(MID(TRIM($A99),2,1)="：",MID(TRIM($A99),2,1)="、"),REPLACEB(TRIM($A99),1,4,""),TRIM($A99))) -> 0 | I99: =B99+D99+F99+H99-G99-E99-C99 -> 0 | J99: =A99=未审报表!A99 -> TRUE | K99: =审定报表!A99=TB!A99 -> TRUE
A100: =未审报表!A100 -> 生产性生物资产 | B100: =未审报表!C100 -> 0 | C100: =C98+C99 -> 0 | D100: =D98+D99 -> 0 | E100: =E98+E99 -> 0 | F100: =F98+F99 -> 0 | G100: =G98+G99 -> 0 | H100: =H98+H99 -> 0 | I100: =B100+C100+E100+G100-H100-F100-D100 -> 0 | J100: =A100=未审报表!A100 -> TRUE | K100: =审定报表!A100=TB!A100 -> TRUE
...

Sheet TB(期初)
A1: 期初报表
A2: =CONCATENATE("客户名称：",参数!D3) -> 客户名称：二锅头 | C2: =CONCATENATE("编制：",参数!D17) -> 编制：张 | E2: =CONCATENATE("日期：",TEXT(NOW(),"yyyy.mm.dd")) -> 日期：2025.11.06 | I2: 索引：
A3: =CONCATENATE("会计时点：",TEXT(参数!D12,"yyyy.mm.dd")) -> 会计时点：2022.12.31 | C3: =CONCATENATE("复核：",参数!D18) -> 复核：刘 | E3: 日期： | I3: 分页：
A5: =IF((ROUND(I127,2))=(ROUND(I190,2)),"资 产","报表未调平!") -> 资 产 | B5: =CONCATENATE("上期审定期末数",TEXT(参数!D11,"yyyy.mm.dd")) -> 上期审定期末数2021.12.31 | C5: 账项调整 | E5: 报表调整 | G5: 其他调整 | I5: =CONCATENATE("本期审定期初数",TEXT(参数!D11+1,"yyyy.mm.dd")) -> 本期审定期初数2022.01.01
C6: 借方 | D6: 贷方 | E6: 借方 | F6: 贷方 | G6: 借方 | H6: 贷方
A7: =未审报表!A7 -> 流动资产： | J7: =A7=未审报表!A7 -> TRUE | K7: =A7=审定报表!A7 -> TRUE
A8: =未审报表!A8 -> 货币资金 | B8: =期初核对!C8 -> 645471.35 | C8: =SUMIFS(调整事项汇总表!$K$7:$K$10020,调整事项汇总表!$D$7:$D$10020,"账项调整",调整事项汇总表!$E$7:$E$10020,IF(OR(MID(TRIM($A8),2,1)="：",MID(TRIM($A8),2,1)="、"),REPLACEB(TRIM($A8),1,4,""),TRIM($A8))) -> 0 | D8: =SUMIFS(调整事项汇总表!$L$7:$L$10020,调整事项汇总表!$D$7:$D$10020,"账项调整",调整事项汇总表!$E$7:$E$10020,IF(OR(MID(TRIM($A8),2,1)="：",MID(TRIM($A8),2,1)="、"),REPLACEB(TRIM($A8),1,4,""),TRIM($A8))) -> 0 | E8: =SUMIFS(调整事项汇总表!$K$7:$K$10020,调整事项汇总表!$D$7:$D$10020,"报表调整",调整事项汇总表!$E$7:$E$10020,IF(OR(MID(TRIM($A8),2,1)="：",MID(TRIM($A8),2,1)="、"),REPLACEB(TRIM($A8),1,4,""),TRIM($A8))) -> 0 | F8: =SUMIFS(调整事项汇总表!$L$7:$L$10020,调整事项汇总表!$D$7:$D$10020,"报表调整",调整事项汇总表!$E$7:$E$10020,IF(OR(MID(TRIM($A8),2,1)="：",MID(TRIM($A8),2,1)="、"),REPLACEB(TRIM($A8),1,4,""),TRIM($A8))) -> 0 | G8: =SUMIFS(调整事项汇总表!$K$7:$K$10020,调整事项汇总表!$D$7:$D$10020,"其他",调整事项汇总表!$E$7:$E$10020,IF(OR(MID(TRIM($A8),2,1)="：",MID(TRIM($A8),2,1)="、"),REPLACEB(TRIM($A8),1,4,""),TRIM($A8))) -> 0 | H8: =SUMIFS(调整事项汇总表!$L$7:$L$10020,调整事项汇总表!$D$7:$D$10020,"其他",调整事项汇总表!$E$7:$E$10020,IF(OR(MID(TRIM($A8),2,1)="：",MID(TRIM($A8),2,1)="、"),REPLACEB(TRIM($A8),1,4,""),TRIM($A8))) -> 0 | I8: =B8+C8+E8+G8-H8-F8-D8 -> 645471.35 | J8: =A8=未审报表!A8 -> TRUE | K8: =A8=审定报表!A8 -> TRUE
A9: =未审报表!A9 -> 结算备付金* | B9: =期初核对!C9 -> 0 | C9: =SUMIFS(调整事项汇总表!$K$7:$K$10020,调整事项汇总表!$D$7:$D$10020,"账项调整",调整事项汇总表!$E$7:$E$10020,IF(OR(MID(TRIM($A9),2,1)="：",MID(TRIM($A9),2,1)="、"),REPLACEB(TRIM($A9),1,4,""),TRIM($A9))) -> 0 | D9: =SUMIFS(调整事项汇总表!$L$7:$L$10020,调整事项汇总表!$D$7:$D$10020,"账项调整",调整事项汇总表!$E$7:$E$10020,IF(OR(MID(TRIM($A9),2,1)="：",MID(TRIM($A9),2,1)="、"),REPLACEB(TRIM($A9),1,4,""),TRIM($A9))) -> 0 | E9: =SUMIFS(调整事项汇总表!$K$7:$K$10020,调整事项汇总表!$D$7:$D$10020,"报表调整",调整事项汇总表!$E$7:$E$10020,IF(OR(MID(TRIM($A9),2,1)="：",MID(TRIM($A9),2,1)="、"),REPLACEB(TRIM($A9),1,4,""),TRIM($A9))) -> 0 | F9: =SUMIFS(调整事项汇总表!$L$7:$L$10020,调整事项汇总表!$D$7:$D$10020,"报表调整",调整事项汇总表!$E$7:$E$10020,IF(OR(MID(TRIM($A9),2,1)="：",MID(TRIM($A9),2,1)="、"),REPLACEB(TRIM($A9),1,4,""),TRIM($A9))) -> 0 | G9: =SUMIFS(调整事项汇总表!$K$7:$K$10020,调整事项汇总表!$D$7:$D$10020,"其他",调整事项汇总表!$E$7:$E$10020,IF(OR(MID(TRIM($A9),2,1)="：",MID(TRIM($A9),2,1)="、"),REPLACEB(TRIM($A9),1,4,""),TRIM($A9))) -> 0 | H9: =SUMIFS(调整事项汇总表!$L$7:$L$10020,调整事项汇总表!$D$7:$D$10020,"其他",调整事项汇总表!$E$7:$E$10020,IF(OR(MID(TRIM($A9),2,1)="：",MID(TRIM($A9),2,1)="、"),REPLACEB(TRIM($A9),1,4,""),TRIM($A9))) -> 0 | I9: =B9+C9+E9+G9-H9-F9-D9 -> 0 | J9: =A9=未审报表!A9 -> TRUE | K9: =A9=审定报表!A9 -> TRUE
A10: =未审报表!A10 -> 拆出资金原值* | B10: =期初核对!C10 -> 0 | C10: =SUMIFS(调整事项汇总表!$K$7:$K$10020,调整事项汇总表!$D$7:$D$10020,"账项调整",调整事项汇总表!$E$7:$E$10020,IF(OR(MID(TRIM($A10),2,1)="：",MID(TRIM($A10),2,1)="、"),REPLACEB(TRIM($A10),1,4,""),TRIM($A10))) -> 0 | D10: =SUMIFS(调整事项汇总表!$L$7:$L$10020,调整事项汇总表!$D$7:$D$10020,"账项调整",调整事项汇总表!$E$7:$E$10020,IF(OR(MID(TRIM($A10),2,1)="：",MID(TRIM($A10),2,1)="、"),REPLACEB(TRIM($A10),1,4,""),TRIM($A10))) -> 0 | E10: =SUMIFS(调整事项汇总表!$K$7:$K$10020,调整事项汇总表!$D$7:$D$10020,"报表调整",调整事项汇总表!$E$7:$E$10020,IF(OR(MID(TRIM($A10),2,1)="：",MID(TRIM($A10),2,1)="、"),REPLACEB(TRIM($A10),1,4,""),TRIM($A10))) -> 0 | F10: =SUMIFS(调整事项汇总表!$L$7:$L$10020,调整事项汇总表!$D$7:$D$10020,"报表调整",调整事项汇总表!$E$7:$E$10020,IF(OR(MID(TRIM($A10),2,1)="：",MID(TRIM($A10),2,1)="、"),REPLACEB(TRIM($A10),1,4,""),TRIM($A10))) -> 0 | G10: =SUMIFS(调整事项汇总表!$K$7:$K$10020,调整事项汇总表!$D$7:$D$10020,"其他",调整事项汇总表!$E$7:$E$10020,IF(OR(MID(TRIM($A10),2,1)="：",MID(TRIM($A10),2,1)="、"),REPLACEB(TRIM($A10),1,4,""),TRIM($A10))) -> 0 | H10: =SUMIFS(调整事项汇总表!$L$7:$L$10020,调整事项汇总表!$D$7:$D$10020,"其他",调整事项汇总表!$E$7:$E$10020,IF(OR(MID(TRIM($A10),2,1)="：",MID(TRIM($A10),2,1)="、"),REPLACEB(TRIM($A10),1,4,""),TRIM($A10))) -> 0 | I10: =B10+C10+E10+G10-H10-F10-D10 -> 0 | J10: =A10=未审报表!A10 -> TRUE | K10: =A10=审定报表!A10 -> TRUE
A11: =未审报表!A11 -> 拆出资金减值准备* | B11: =期初核对!C11 -> 0 | C11: =SUMIFS(调整事项汇总表!$K$7:$K$10020,调整事项汇总表!$D$7:$D$10020,"账项调整",调整事项汇总表!$E$7:$E$10020,IF(OR(MID(TRIM($A11),2,1)="：",MID(TRIM($A11),2,1)="、"),REPLACEB(TRIM($A11),1,4,""),TRIM($A11))) -> 0 | D11: =SUMIFS(调整事项汇总表!$L$7:$L$10020,调整事项汇总表!$D$7:$D$10020,"账项调整",调整事项汇总表!$E$7:$E$10020,IF(OR(MID(TRIM($A11),2,1)="：",MID(TRIM($A11),2,1)="、"),REPLACEB(TRIM($A11),1,4,""),TRIM($A11))) -> 0 | E11: =SUMIFS(调整事项汇总表!$K$7:$K$10020,调整事项汇总表!$D$7:$D$10020,"报表调整",调整事项汇总表!$E$7:$E$10020,IF(OR(MID(TRIM($A11),2,1)="：",MID(TRIM($A11),2,1)="、"),REPLACEB(TRIM($A11),1,4,""),TRIM($A11))) -> 0 | F11: =SUMIFS(调整事项汇总表!$L$7:$L$10020,调整事项汇总表!$D$7:$D$10020,"报表调整",调整事项汇总表!$E$7:$E$10020,IF(OR(MID(TRIM($A11),2,1)="：",MID(TRIM($A11),2,1)="、"),REPLACEB(TRIM($A11),1,4,""),TRIM($A11))) -> 0 | G11: =SUMIFS(调整事项汇总表!$K$7:$K$10020,调整事项汇总表!$D$7:$D$10020,"其他",调整事项汇总表!$E$7:$E$10020,IF(OR(MID(TRIM($A11),2,1)="：",MID(TRIM($A11),2,1)="、"),REPLACEB(TRIM($A11),1,4,""),TRIM($A11))) -> 0 | H11: =SUMIFS(调整事项汇总表!$L$7:$L$10020,调整事项汇总表!$D$7:$D$10020,"其他",调整事项汇总表!$E$7:$E$10020,IF(OR(MID(TRIM($A11),2,1)="：",MID(TRIM($A11),2,1)="、"),REPLACEB(TRIM($A11),1,4,""),TRIM($A11))) -> 0 | I11: =B11+D11+F11+H11-G11-E11-C11 -> 0 | J11: =A11=未审报表!A11 -> TRUE | K11: =A11=审定报表!A11 -> TRUE
A12: =未审报表!A12 -> 拆出资金* | B12: =期初核对!C12 -> 0 | C12: =C10+C11 -> 0 | D12: =D10+D11 -> 0 | E12: =E10+E11 -> 0 | F12: =F10+F11 -> 0 | G12: =G10+G11 -> 0 | H12: =H10+H11 -> 0 | I12: =B12+C12+E12+G12-H12-F12-D12 -> 0 | J12: =A12=未审报表!A12 -> TRUE | K12: =A12=审定报表!A12 -> TRUE
A13: =未审报表!A13 -> 交易性金融资产 | B13: =期初核对!C13 -> 0 | C13: =SUMIFS(调整事项汇总表!$K$7:$K$10020,调整事项汇总表!$D$7:$D$10020,"账项调整",调整事项汇总表!$E$7:$E$10020,IF(OR(MID(TRIM($A13),2,1)="：",MID(TRIM($A13),2,1)="、"),REPLACEB(TRIM($A13),1,4,""),TRIM($A13))) -> 0 | D13: =SUMIFS(调整事项汇总表!$L$7:$L$10020,调整事项汇总表!$D$7:$D$10020,"账项调整",调整事项汇总表!$E$7:$E$10020,IF(OR(MID(TRIM($A13),2,1)="：",MID(TRIM($A13),2,1)="、"),REPLACEB(TRIM($A13),1,4,""),TRIM($A13))) -> 0 | E13: =SUMIFS(调整事项汇总表!$K$7:$K$10020,调整事项汇总表!$D$7:$D$10020,"报表调整",调整事项汇总表!$E$7:$E$10020,IF(OR(MID(TRIM($A13),2,1)="：",MID(TRIM($A13),2,1)="、"),REPLACEB(TRIM($A13),1,4,""),TRIM($A13))) -> 0 | F13: =SUMIFS(调整事项汇总表!$L$7:$L$10020,调整事项汇总表!$D$7:$D$10020,"报表调整",调整事项汇总表!$E$7:$E$10020,IF(OR(MID(TRIM($A13),2,1)="：",MID(TRIM($A13),2,1)="、"),REPLACEB(TRIM($A13),1,4,""),TRIM($A13))) -> 0 | G13: =SUMIFS(调整事项汇总表!$K$7:$K$10020,调整事项汇总表!$D$7:$D$10020,"其他",调整事项汇总表!$E$7:$E$10020,IF(OR(MID(TRIM($A13),2,1)="：",MID(TRIM($A13),2,1)="、"),REPLACEB(TRIM($A13),1,4,""),TRIM($A13))) -> 0 | H13: =SUMIFS(调整事项汇总表!$L$7:$L$10020,调整事项汇总表!$D$7:$D$10020,"其他",调整事项汇总表!$E$7:$E$10020,IF(OR(MID(TRIM($A13),2,1)="：",MID(TRIM($A13),2,1)="、"),REPLACEB(TRIM($A13),1,4,""),TRIM($A13))) -> 0 | I13: =B13+C13+E13+G13-H13-F13-D13 -> 0 | J13: =A13=未审报表!A13 -> TRUE | K13: =A13=审定报表!A13 -> TRUE
A14: =未审报表!A14 -> 衍生金融资产 | B14: =期初核对!C14 -> 0 | C14: =SUMIFS(调整事项汇总表!$K$7:$K$10020,调整事项汇总表!$D$7:$D$10020,"账项调整",调整事项汇总表!$E$7:$E$10020,IF(OR(MID(TRIM($A14),2,1)="：",MID(TRIM($A14),2,1)="、"),REPLACEB(TRIM($A14),1,4,""),TRIM($A14))) -> 0 | D14: =SUMIFS(调整事项汇总表!$L$7:$L$10020,调整事项汇总表!$D$7:$D$10020,"账项调整",调整事项汇总表!$E$7:$E$10020,IF(OR(MID(TRIM($A14),2,1)="：",MID(TRIM($A14),2,1)="、"),REPLACEB(TRIM($A14),1,4,""),TRIM($A14))) -> 0 | E14: =SUMIFS(调整事项汇总表!$K$7:$K$10020,调整事项汇总表!$D$7:$D$10020,"报表调整",调整事项汇总表!$E$7:$E$10020,IF(OR(MID(TRIM($A14),2,1)="：",MID(TRIM($A14),2,1)="、"),REPLACEB(TRIM($A14),1,4,""),TRIM($A14))) -> 0 | F14: =SUMIFS(调整事项汇总表!$L$7:$L$10020,调整事项汇总表!$D$7:$D$10020,"报表调整",调整事项汇总表!$E$7:$E$10020,IF(OR(MID(TRIM($A14),2,1)="：",MID(TRIM($A14),2,1)="、"),REPLACEB(TRIM($A14),1,4,""),TRIM($A14))) -> 0 | G14: =SUMIFS(调整事项汇总表!$K$7:$K$10020,调整事项汇总表!$D$7:$D$10020,"其他",调整事项汇总表!$E$7:$E$10020,IF(OR(MID(TRIM($A14),2,1)="：",MID(TRIM($A14),2,1)="、"),REPLACEB(TRIM($A14),1,4,""),TRIM($A14))) -> 0 | H14: =SUMIFS(调整事项汇总表!$L$7:$L$10020,调整事项汇总表!$D$7:$D$10020,"其他",调整事项汇总表!$E$7:$E$10020,IF(OR(MID(TRIM($A14),2,1)="：",MID(TRIM($A14),2,1)="、"),REPLACEB(TRIM($A14),1,4,""),TRIM($A14))) -> 0 | I14: =B14+C14+E14+G14-H14-F14-D14 -> 0 | J14: =A14=未审报表!A14 -> TRUE | K14: =A14=审定报表!A14 -> TRUE
A15: =未审报表!A15 -> 应收票据原值 | B15: =期初核对!C15 -> 0 | C15: =SUMIFS(调整事项汇总表!$K$7:$K$10020,调整事项汇总表!$D$7:$D$10020,"账项调整",调整事项汇总表!$E$7:$E$10020,IF(OR(MID(TRIM($A15),2,1)="：",MID(TRIM($A15),2,1)="、"),REPLACEB(TRIM($A15),1,4,""),TRIM($A15))) -> 0 | D15: =SUMIFS(调整事项汇总表!$L$7:$L$10020,调整事项汇总表!$D$7:$D$10020,"账项调整",调整事项汇总表!$E$7:$E$10020,IF(OR(MID(TRIM($A15),2,1)="：",MID(TRIM($A15),2,1)="、"),REPLACEB(TRIM($A15),1,4,""),TRIM($A15))) -> 0 | E15: =SUMIFS(调整事项汇总表!$K$7:$K$10020,调整事项汇总表!$D$7:$D$10020,"报表调整",调整事项汇总表!$E$7:$E$10020,IF(OR(MID(TRIM($A15),2,1)="：",MID(TRIM($A15),2,1)="、"),REPLACEB(TRIM($A15),1,4,""),TRIM($A15))) -> 0 | F15: =SUMIFS(调整事项汇总表!$L$7:$L$10020,调整事项汇总表!$D$7:$D$10020,"报表调整",调整事项汇总表!$E$7:$E$10020,IF(OR(MID(TRIM($A15),2,1)="：",MID(TRIM($A15),2,1)="、"),REPLACEB(TRIM($A15),1,4,""),TRIM($A15))) -> 0 | G15: =SUMIFS(调整事项汇总表!$K$7:$K$10020,调整事项汇总表!$D$7:$D$10020,"其他",调整事项汇总表!$E$7:$E$10020,IF(OR(MID(TRIM($A15),2,1)="：",MID(TRIM($A15),2,1)="、"),REPLACEB(TRIM($A15),1,4,""),TRIM($A15))) -> 0 | H15: =SUMIFS(调整事项汇总表!$L$7:$L$10020,调整事项汇总表!$D$7:$D$10020,"其他",调整事项汇总表!$E$7:$E$10020,IF(OR(MID(TRIM($A15),2,1)="：",MID(TRIM($A15),2,1)="、"),REPLACEB(TRIM($A15),1,4,""),TRIM($A15))) -> 0 | I15: =B15+C15+E15+G15-H15-F15-D15 -> 0 | J15: =A15=未审报表!A15 -> TRUE | K15: =A15=审定报表!A15 -> TRUE
A16: =未审报表!A16 -> 应收票据坏账准备 | B16: =期初核对!C16 -> 0 | C16: =SUMIFS(调整事项汇总表!$K$7:$K$10020,调整事项汇总表!$D$7:$D$10020,"账项调整",调整事项汇总表!$E$7:$E$10020,IF(OR(MID(TRIM($A16),2,1)="：",MID(TRIM($A16),2,1)="、"),REPLACEB(TRIM($A16),1,4,""),TRIM($A16))) -> 0 | D16: =SUMIFS(调整事项汇总表!$L$7:$L$10020,调整事项汇总表!$D$7:$D$10020,"账项调整",调整事项汇总表!$E$7:$E$10020,IF(OR(MID(TRIM($A16),2,1)="：",MID(TRIM($A16),2,1)="、"),REPLACEB(TRIM($A16),1,4,""),TRIM($A16))) -> 0 | E16: =SUMIFS(调整事项汇总表!$K$7:$K$10020,调整事项汇总表!$D$7:$D$10020,"报表调整",调整事项汇总表!$E$7:$E$10020,IF(OR(MID(TRIM($A16),2,1)="：",MID(TRIM($A16),2,1)="、"),REPLACEB(TRIM($A16),1,4,""),TRIM($A16))) -> 0 | F16: =SUMIFS(调整事项汇总表!$L$7:$L$10020,调整事项汇总表!$D$7:$D$10020,"报表调整",调整事项汇总表!$E$7:$E$10020,IF(OR(MID(TRIM($A16),2,1)="：",MID(TRIM($A16),2,1)="、"),REPLACEB(TRIM($A16),1,4,""),TRIM($A16))) -> 0 | G16: =SUMIFS(调整事项汇总表!$K$7:$K$10020,调整事项汇总表!$D$7:$D$10020,"其他",调整事项汇总表!$E$7:$E$10020,IF(OR(MID(TRIM($A16),2,1)="：",MID(TRIM($A16),2,1)="、"),REPLACEB(TRIM($A16),1,4,""),TRIM($A16))) -> 0 | H16: =SUMIFS(调整事项汇总表!$L$7:$L$10020,调整事项汇总表!$D$7:$D$10020,"其他",调整事项汇总表!$E$7:$E$10020,IF(OR(MID(TRIM($A16),2,1)="：",MID(TRIM($A16),2,1)="、"),REPLACEB(TRIM($A16),1,4,""),TRIM($A16))) -> 0 | I16: =B16+D16+F16+H16-G16-E16-C16 -> 0 | J16: =A16=未审报表!A16 -> TRUE | K16: =A16=审定报表!A16 -> TRUE
A17: =未审报表!A17 -> 应收票据 | B17: =期初核对!C17 -> 0 | C17: =C15+C16 -> 0 | D17: =D15+D16 -> 0 | E17: =E15+E16 -> 0 | F17: =F15+F16 -> 0 | G17: =G15+G16 -> 0 | H17: =H15+H16 -> 0 | I17: =B17+C17+E17+G17-H17-F17-D17 -> 0 | J17: =A17=未审报表!A17 -> TRUE | K17: =A17=审定报表!A17 -> TRUE
A18: =未审报表!A18 -> 应收账款原值 | B18: =期初核对!C18 -> 16718591 | C18: =SUMIFS(调整事项汇总表!$K$7:$K$10020,调整事项汇总表!$D$7:$D$10020,"账项调整",调整事项汇总表!$E$7:$E$10020,IF(OR(MID(TRIM($A18),2,1)="：",MID(TRIM($A18),2,1)="、"),REPLACEB(TRIM($A18),1,4,""),TRIM($A18))) -> 0 | D18: =SUMIFS(调整事项汇总表!$L$7:$L$10020,调整事项汇总表!$D$7:$D$10020,"账项调整",调整事项汇总表!$E$7:$E$10020,IF(OR(MID(TRIM($A18),2,1)="：",MID(TRIM($A18),2,1)="、"),REPLACEB(TRIM($A18),1,4,""),TRIM($A18))) -> 0 | E18: =SUMIFS(调整事项汇总表!$K$7:$K$10020,调整事项汇总表!$D$7:$D$10020,"报表调整",调整事项汇总表!$E$7:$E$10020,IF(OR(MID(TRIM($A18),2,1)="：",MID(TRIM($A18),2,1)="、"),REPLACEB(TRIM($A18),1,4,""),TRIM($A18))) -> 0 | F18: =SUMIFS(调整事项汇总表!$L$7:$L$10020,调整事项汇总表!$D$7:$D$10020,"报表调整",调整事项汇总表!$E$7:$E$10020,IF(OR(MID(TRIM($A18),2,1)="：",MID(TRIM($A18),2,1)="、"),REPLACEB(TRIM($A18),1,4,""),TRIM($A18))) -> 0 | G18: =SUMIFS(调整事项汇总表!$K$7:$K$10020,调整事项汇总表!$D$7:$D$10020,"其他",调整事项汇总表!$E$7:$E$10020,IF(OR(MID(TRIM($A18),2,1)="：",MID(TRIM($A18),2,1)="、"),REPLACEB(TRIM($A18),1,4,""),TRIM($A18))) -> 0 | H18: =SUMIFS(调整事项汇总表!$L$7:$L$10020,调整事项汇总表!$D$7:$D$10020,"其他",调整事项汇总表!$E$7:$E$10020,IF(OR(MID(TRIM($A18),2,1)="：",MID(TRIM($A18),2,1)="、"),REPLACEB(TRIM($A18),1,4,""),TRIM($A18))) -> 0 | I18: =B18+C18+E18+G18-H18-F18-D18 -> 16718591 | J18: =A18=未审报表!A18 -> TRUE | K18: =A18=审定报表!A18 -> TRUE
A19: =未审报表!A19 -> 应收账款坏账准备 | B19: =期初核对!C19 -> 0 | C19: =SUMIFS(调整事项汇总表!$K$7:$K$10020,调整事项汇总表!$D$7:$D$10020,"账项调整",调整事项汇总表!$E$7:$E$10020,IF(OR(MID(TRIM($A19),2,1)="：",MID(TRIM($A19),2,1)="、"),REPLACEB(TRIM($A19),1,4,""),TRIM($A19))) -> 0 | D19: =SUMIFS(调整事项汇总表!$L$7:$L$10020,调整事项汇总表!$D$7:$D$10020,"账项调整",调整事项汇总表!$E$7:$E$10020,IF(OR(MID(TRIM($A19),2,1)="：",MID(TRIM($A19),2,1)="、"),REPLACEB(TRIM($A19),1,4,""),TRIM($A19))) -> 0 | E19: =SUMIFS(调整事项汇总表!$K$7:$K$10020,调整事项汇总表!$D$7:$D$10020,"报表调整",调整事项汇总表!$E$7:$E$10020,IF(OR(MID(TRIM($A19),2,1)="：",MID(TRIM($A19),2,1)="、"),REPLACEB(TRIM($A19),1,4,""),TRIM($A19))) -> 0 | F19: =SUMIFS(调整事项汇总表!$L$7:$L$10020,调整事项汇总表!$D$7:$D$10020,"报表调整",调整事项汇总表!$E$7:$E$10020,IF(OR(MID(TRIM($A19),2,1)="：",MID(TRIM($A19),2,1)="、"),REPLACEB(TRIM($A19),1,4,""),TRIM($A19))) -> 0 | G19: =SUMIFS(调整事项汇总表!$K$7:$K$10020,调整事项汇总表!$D$7:$D$10020,"其他",调整事项汇总表!$E$7:$E$10020,IF(OR(MID(TRIM($A19),2,1)="：",MID(TRIM($A19),2,1)="、"),REPLACEB(TRIM($A19),1,4,""),TRIM($A19))) -> 0 | H19: =SUMIFS(调整事项汇总表!$L$7:$L$10020,调整事项汇总表!$D$7:$D$10020,"其他",调整事项汇总表!$E$7:$E$10020,IF(OR(MID(TRIM($A19),2,1)="：",MID(TRIM($A19),2,1)="、"),REPLACEB(TRIM($A19),1,4,""),TRIM($A19))) -> 0 | I19: =B19+D19+F19+H19-G19-E19-C19 -> 0 | J19: =A19=未审报表!A19 -> TRUE | K19: =A19=审定报表!A19 -> TRUE
A20: =未审报表!A20 -> 应收账款 | B20: =期初核对!C20 -> 16718591 | C20: =C18+C19 -> 0 | D20: =D18+D19 -> 0 | E20: =E18+E19 -> 0 | F20: =F18+F19 -> 0 | G20: =G18+G19 -> 0 | H20: =H18+H19 -> 0 | I20: =B20+C20+E20+G20-H20-F20-D20 -> 16718591 | J20: =A20=未审报表!A20 -> TRUE | K20: =A20=审定报表!A20 -> TRUE
A21: =未审报表!A21 -> 应收款项融资原值 | B21: =期初核对!C21 -> 0 | C21: =SUMIFS(调整事项汇总表!$K$7:$K$10020,调整事项汇总表!$D$7:$D$10020,"账项调整",调整事项汇总表!$E$7:$E$10020,IF(OR(MID(TRIM($A21),2,1)="：",MID(TRIM($A21),2,1)="、"),REPLACEB(TRIM($A21),1,4,""),TRIM($A21))) -> 0 | D21: =SUMIFS(调整事项汇总表!$L$7:$L$10020,调整事项汇总表!$D$7:$D$10020,"账项调整",调整事项汇总表!$E$7:$E$10020,IF(OR(MID(TRIM($A21),2,1)="：",MID(TRIM($A21),2,1)="、"),REPLACEB(TRIM($A21),1,4,""),TRIM($A21))) -> 0 | E21: =SUMIFS(调整事项汇总表!$K$7:$K$10020,调整事项汇总表!$D$7:$D$10020,"报表调整",调整事项汇总表!$E$7:$E$10020,IF(OR(MID(TRIM($A21),2,1)="：",MID(TRIM($A21),2,1)="、"),REPLACEB(TRIM($A21),1,4,""),TRIM($A21))) -> 0 | F21: =SUMIFS(调整事项汇总表!$L$7:$L$10020,调整事项汇总表!$D$7:$D$10020,"报表调整",调整事项汇总表!$E$7:$E$10020,IF(OR(MID(TRIM($A21),2,1)="：",MID(TRIM($A21),2,1)="、"),REPLACEB(TRIM($A21),1,4,""),TRIM($A21))) -> 0 | G21: =SUMIFS(调整事项汇总表!$K$7:$K$10020,调整事项汇总表!$D$7:$D$10020,"其他",调整事项汇总表!$E$7:$E$10020,IF(OR(MID(TRIM($A21),2,1)="：",MID(TRIM($A21),2,1)="、"),REPLACEB(TRIM($A21),1,4,""),TRIM($A21))) -> 0 | H21: =SUMIFS(调整事项汇总表!$L$7:$L$10020,调整事项汇总表!$D$7:$D$10020,"其他",调整事项汇总表!$E$7:$E$10020,IF(OR(MID(TRIM($A21),2,1)="：",MID(TRIM($A21),2,1)="、"),REPLACEB(TRIM($A21),1,4,""),TRIM($A21))) -> 0 | I21: =B21+C21+E21+G21-H21-F21-D21 -> 0 | J21: =A21=未审报表!A21 -> TRUE | K21: =A21=审定报表!A21 -> TRUE
A22: =未审报表!A22 -> 应收款项融资坏账准备 | B22: =期初核对!C22 -> 0 | C22: =SUMIFS(调整事项汇总表!$K$7:$K$10020,调整事项汇总表!$D$7:$D$10020,"账项调整",调整事项汇总表!$E$7:$E$10020,IF(OR(MID(TRIM($A22),2,1)="：",MID(TRIM($A22),2,1)="、"),REPLACEB(TRIM($A22),1,4,""),TRIM($A22))) -> 0 | D22: =SUMIFS(调整事项汇总表!$L$7:$L$10020,调整事项汇总表!$D$7:$D$10020,"账项调整",调整事项汇总表!$E$7:$E$10020,IF(OR(MID(TRIM($A22),2,1)="：",MID(TRIM($A22),2,1)="、"),REPLACEB(TRIM($A22),1,4,""),TRIM($A22))) -> 0 | E22: =SUMIFS(调整事项汇总表!$K$7:$K$10020,调整事项汇总表!$D$7:$D$10020,"报表调整",调整事项汇总表!$E$7:$E$10020,IF(OR(MID(TRIM($A22),2,1)="：",MID(TRIM($A22),2,1)="、"),REPLACEB(TRIM($A22),1,4,""),TRIM($A22))) -> 0 | F22: =SUMIFS(调整事项汇总表!$L$7:$L$10020,调整事项汇总表!$D$7:$D$10020,"报表调整",调整事项汇总表!$E$7:$E$10020,IF(OR(MID(TRIM($A22),2,1)="：",MID(TRIM($A22),2,1)="、"),REPLACEB(TRIM($A22),1,4,""),TRIM($A22))) -> 0 | G22: =SUMIFS(调整事项汇总表!$K$7:$K$10020,调整事项汇总表!$D$7:$D$10020,"其他",调整事项汇总表!$E$7:$E$10020,IF(OR(MID(TRIM($A22),2,1)="：",MID(TRIM($A22),2,1)="、"),REPLACEB(TRIM($A22),1,4,""),TRIM($A22))) -> 0 | H22: =SUMIFS(调整事项汇总表!$L$7:$L$10020,调整事项汇总表!$D$7:$D$10020,"其他",调整事项汇总表!$E$7:$E$10020,IF(OR(MID(TRIM($A22),2,1)="：",MID(TRIM($A22),2,1)="、"),REPLACEB(TRIM($A22),1,4,""),TRIM($A22))) -> 0 | I22: =B22+D22+F22+H22-G22-E22-C22 -> 0 | J22: =A22=未审报表!A22 -> TRUE | K22: =A22=审定报表!A22 -> TRUE
A23: =未审报表!A23 -> 应收款项融资 | B23: =期初核对!C23 -> 0 | C23: =C21+C22 -> 0 | D23: =D21+D22 -> 0 | E23: =E21+E22 -> 0 | F23: =F21+F22 -> 0 | G23: =G21+G22 -> 0 | H23: =H21+H22 -> 0 | I23: =B23+C23+E23+G23-H23-F23-D23 -> 0 | J23: =A23=未审报表!A23 -> TRUE | K23: =A23=审定报表!A23 -> TRUE
A24: =未审报表!A24 -> 预付款项原值 | B24: =期初核对!C24 -> 1584.26 | C24: =SUMIFS(调整事项汇总表!$K$7:$K$10020,调整事项汇总表!$D$7:$D$10020,"账项调整",调整事项汇总表!$E$7:$E$10020,IF(OR(MID(TRIM($A24),2,1)="：",MID(TRIM($A24),2,1)="、"),REPLACEB(TRIM($A24),1,4,""),TRIM($A24))) -> 0 | D24: =SUMIFS(调整事项汇总表!$L$7:$L$10020,调整事项汇总表!$D$7:$D$10020,"账项调整",调整事项汇总表!$E$7:$E$10020,IF(OR(MID(TRIM($A24),2,1)="：",MID(TRIM($A24),2,1)="、"),REPLACEB(TRIM($A24),1,4,""),TRIM($A24))) -> 0 | E24: =SUMIFS(调整事项汇总表!$K$7:$K$10020,调整事项汇总表!$D$7:$D$10020,"报表调整",调整事项汇总表!$E$7:$E$10020,IF(OR(MID(TRIM($A24),2,1)="：",MID(TRIM($A24),2,1)="、"),REPLACEB(TRIM($A24),1,4,""),TRIM($A24))) -> 0 | F24: =SUMIFS(调整事项汇总表!$L$7:$L$10020,调整事项汇总表!$D$7:$D$10020,"报表调整",调整事项汇总表!$E$7:$E$10020,IF(OR(MID(TRIM($A24),2,1)="：",MID(TRIM($A24),2,1)="、"),REPLACEB(TRIM($A24),1,4,""),TRIM($A24))) -> 0 | G24: =SUMIFS(调整事项汇总表!$K$7:$K$10020,调整事项汇总表!$D$7:$D$10020,"其他",调整事项汇总表!$E$7:$E$10020,IF(OR(MID(TRIM($A24),2,1)="：",MID(TRIM($A24),2,1)="、"),REPLACEB(TRIM($A24),1,4,""),TRIM($A24))) -> 0 | H24: =SUMIFS(调整事项汇总表!$L$7:$L$10020,调整事项汇总表!$D$7:$D$10020,"其他",调整事项汇总表!$E$7:$E$10020,IF(OR(MID(TRIM($A24),2,1)="：",MID(TRIM($A24),2,1)="、"),REPLACEB(TRIM($A24),1,4,""),TRIM($A24))) -> 0 | I24: =B24+C24+E24+G24-H24-F24-D24 -> 1584.26 | J24: =A24=未审报表!A24 -> TRUE | K24: =A24=审定报表!A24 -> TRUE
A25: =未审报表!A25 -> 预付款项坏账准备 | B25: =期初核对!C25 -> 0 | C25: =SUMIFS(调整事项汇总表!$K$7:$K$10020,调整事项汇总表!$D$7:$D$10020,"账项调整",调整事项汇总表!$E$7:$E$10020,IF(OR(MID(TRIM($A25),2,1)="：",MID(TRIM($A25),2,1)="、"),REPLACEB(TRIM($A25),1,4,""),TRIM($A25))) -> 0 | D25: =SUMIFS(调整事项汇总表!$L$7:$L$10020,调整事项汇总表!$D$7:$D$10020,"账项调整",调整事项汇总表!$E$7:$E$10020,IF(OR(MID(TRIM($A25),2,1)="：",MID(TRIM($A25),2,1)="、"),REPLACEB(TRIM($A25),1,4,""),TRIM($A25))) -> 0 | E25: =SUMIFS(调整事项汇总表!$K$7:$K$10020,调整事项汇总表!$D$7:$D$10020,"报表调整",调整事项汇总表!$E$7:$E$10020,IF(OR(MID(TRIM($A25),2,1)="：",MID(TRIM($A25),2,1)="、"),REPLACEB(TRIM($A25),1,4,""),TRIM($A25))) -> 0 | F25: =SUMIFS(调整事项汇总表!$L$7:$L$10020,调整事项汇总表!$D$7:$D$10020,"报表调整",调整事项汇总表!$E$7:$E$10020,IF(OR(MID(TRIM($A25),2,1)="：",MID(TRIM($A25),2,1)="、"),REPLACEB(TRIM($A25),1,4,""),TRIM($A25))) -> 0 | G25: =SUMIFS(调整事项汇总表!$K$7:$K$10020,调整事项汇总表!$D$7:$D$10020,"其他",调整事项汇总表!$E$7:$E$10020,IF(OR(MID(TRIM($A25),2,1)="：",MID(TRIM($A25),2,1)="、"),REPLACEB(TRIM($A25),1,4,""),TRIM($A25))) -> 0 | H25: =SUMIFS(调整事项汇总表!$L$7:$L$10020,调整事项汇总表!$D$7:$D$10020,"其他",调整事项汇总表!$E$7:$E$10020,IF(OR(MID(TRIM($A25),2,1)="：",MID(TRIM($A25),2,1)="、"),REPLACEB(TRIM($A25),1,4,""),TRIM($A25))) -> 0 | I25: =B25+D25+F25+H25-G25-E25-C25 -> 0 | J25: =A25=未审报表!A25 -> TRUE | K25: =A25=审定报表!A25 -> TRUE
A26: =未审报表!A26 -> 预付款项 | B26: =期初核对!C26 -> 1584.26 | C26: =C24+C25 -> 0 | D26: =D24+D25 -> 0 | E26: =E24+E25 -> 0 | F26: =F24+F25 -> 0 | G26: =G24+G25 -> 0 | H26: =H24+H25 -> 0 | I26: =B26+C26+E26+G26-H26-F26-D26 -> 1584.26 | J26: =A26=未审报表!A26 -> TRUE | K26: =A26=审定报表!A26 -> TRUE
A27: =未审报表!A27 -> 应收保费原值* | B27: =期初核对!C27 -> 0 | C27: =SUMIFS(调整事项汇总表!$K$7:$K$10020,调整事项汇总表!$D$7:$D$10020,"账项调整",调整事项汇总表!$E$7:$E$10020,IF(OR(MID(TRIM($A27),2,1)="：",MID(TRIM($A27),2,1)="、"),REPLACEB(TRIM($A27),1,4,""),TRIM($A27))) -> 0 | D27: =SUMIFS(调整事项汇总表!$L$7:$L$10020,调整事项汇总表!$D$7:$D$10020,"账项调整",调整事项汇总表!$E$7:$E$10020,IF(OR(MID(TRIM($A27),2,1)="：",MID(TRIM($A27),2,1)="、"),REPLACEB(TRIM($A27),1,4,""),TRIM($A27))) -> 0 | E27: =SUMIFS(调整事项汇总表!$K$7:$K$10020,调整事项汇总表!$D$7:$D$10020,"报表调整",调整事项汇总表!$E$7:$E$10020,IF(OR(MID(TRIM($A27),2,1)="：",MID(TRIM($A27),2,1)="、"),REPLACEB(TRIM($A27),1,4,""),TRIM($A27))) -> 0 | F27: =SUMIFS(调整事项汇总表!$L$7:$L$10020,调整事项汇总表!$D$7:$D$10020,"报表调整",调整事项汇总表!$E$7:$E$10020,IF(OR(MID(TRIM($A27),2,1)="：",MID(TRIM($A27),2,1)="、"),REPLACEB(TRIM($A27),1,4,""),TRIM($A27))) -> 0 | G27: =SUMIFS(调整事项汇总表!$K$7:$K$10020,调整事项汇总表!$D$7:$D$10020,"其他",调整事项汇总表!$E$7:$E$10020,IF(OR(MID(TRIM($A27),2,1)="：",MID(TRIM($A27),2,1)="、"),REPLACEB(TRIM($A27),1,4,""),TRIM($A27))) -> 0 | H27: =SUMIFS(调整事项汇总表!$L$7:$L$10020,调整事项汇总表!$D$7:$D$10020,"其他",调整事项汇总表!$E$7:$E$10020,IF(OR(MID(TRIM($A27),2,1)="：",MID(TRIM($A27),2,1)="、"),REPLACEB(TRIM($A27),1,4,""),TRIM($A27))) -> 0 | I27: =B27+C27+E27+G27-H27-F27-D27 -> 0 | J27: =A27=未审报表!A27 -> TRUE | K27: =A27=审定报表!A27 -> TRUE
A28: =未审报表!A28 -> 应收保费坏账准备* | B28: =期初核对!C28 -> 0 | C28: =SUMIFS(调整事项汇总表!$K$7:$K$10020,调整事项汇总表!$D$7:$D$10020,"账项调整",调整事项汇总表!$E$7:$E$10020,IF(OR(MID(TRIM($A28),2,1)="：",MID(TRIM($A28),2,1)="、"),REPLACEB(TRIM($A28),1,4,""),TRIM($A28))) -> 0 | D28: =SUMIFS(调整事项汇总表!$L$7:$L$10020,调整事项汇总表!$D$7:$D$10020,"账项调整",调整事项汇总表!$E$7:$E$10020,IF(OR(MID(TRIM($A28),2,1)="：",MID(TRIM($A28),2,1)="、"),REPLACEB(TRIM($A28),1,4,""),TRIM($A28))) -> 0 | E28: =SUMIFS(调整事项汇总表!$K$7:$K$10020,调整事项汇总表!$D$7:$D$10020,"报表调整",调整事项汇总表!$E$7:$E$10020,IF(OR(MID(TRIM($A28),2,1)="：",MID(TRIM($A28),2,1)="、"),REPLACEB(TRIM($A28),1,4,""),TRIM($A28))) -> 0 | F28: =SUMIFS(调整事项汇总表!$L$7:$L$10020,调整事项汇总表!$D$7:$D$10020,"报表调整",调整事项汇总表!$E$7:$E$10020,IF(OR(MID(TRIM($A28),2,1)="：",MID(TRIM($A28),2,1)="、"),REPLACEB(TRIM($A28),1,4,""),TRIM($A28))) -> 0 | G28: =SUMIFS(调整事项汇总表!$K$7:$K$10020,调整事项汇总表!$D$7:$D$10020,"其他",调整事项汇总表!$E$7:$E$10020,IF(OR(MID(TRIM($A28),2,1)="：",MID(TRIM($A28),2,1)="、"),REPLACEB(TRIM($A28),1,4,""),TRIM($A28))) -> 0 | H28: =SUMIFS(调整事项汇总表!$L$7:$L$10020,调整事项汇总表!$D$7:$D$10020,"其他",调整事项汇总表!$E$7:$E$10020,IF(OR(MID(TRIM($A28),2,1)="：",MID(TRIM($A28),2,1)="、"),REPLACEB(TRIM($A28),1,4,""),TRIM($A28))) -> 0 | I28: =B28+D28+F28+H28-G28-E28-C28 -> 0 | J28: =A28=未审报表!A28 -> TRUE | K28: =A28=审定报表!A28 -> TRUE
A29: =未审报表!A29 -> 应收保费* | B29: =期初核对!C29 -> 0 | C29: =C27+C28 -> 0 | D29: =D27+D28 -> 0 | E29: =E27+E28 -> 0 | F29: =F27+F28 -> 0 | G29: =G27+G28 -> 0 | H29: =H27+H28 -> 0 | I29: =B29+C29+E29+G29-H29-F29-D29 -> 0 | J29: =A29=未审报表!A29 -> TRUE | K29: =A29=审定报表!A29 -> TRUE
A30: =未审报表!A30 -> 应收分保账款原值* | B30: =期初核对!C30 -> 0 | C30: =SUMIFS(调整事项汇总表!$K$7:$K$10020,调整事项汇总表!$D$7:$D$10020,"账项调整",调整事项汇总表!$E$7:$E$10020,IF(OR(MID(TRIM($A30),2,1)="：",MID(TRIM($A30),2,1)="、"),REPLACEB(TRIM($A30),1,4,""),TRIM($A30))) -> 0 | D30: =SUMIFS(调整事项汇总表!$L$7:$L$10020,调整事项汇总表!$D$7:$D$10020,"账项调整",调整事项汇总表!$E$7:$E$10020,IF(OR(MID(TRIM($A30),2,1)="：",MID(TRIM($A30),2,1)="、"),REPLACEB(TRIM($A30),1,4,""),TRIM($A30))) -> 0 | E30: =SUMIFS(调整事项汇总表!$K$7:$K$10020,调整事项汇总表!$D$7:$D$10020,"报表调整",调整事项汇总表!$E$7:$E$10020,IF(OR(MID(TRIM($A30),2,1)="：",MID(TRIM($A30),2,1)="、"),REPLACEB(TRIM($A30),1,4,""),TRIM($A30))) -> 0 | F30: =SUMIFS(调整事项汇总表!$L$7:$L$10020,调整事项汇总表!$D$7:$D$10020,"报表调整",调整事项汇总表!$E$7:$E$10020,IF(OR(MID(TRIM($A30),2,1)="：",MID(TRIM($A30),2,1)="、"),REPLACEB(TRIM($A30),1,4,""),TRIM($A30))) -> 0 | G30: =SUMIFS(调整事项汇总表!$K$7:$K$10020,调整事项汇总表!$D$7:$D$10020,"其他",调整事项汇总表!$E$7:$E$10020,IF(OR(MID(TRIM($A30),2,1)="：",MID(TRIM($A30),2,1)="、"),REPLACEB(TRIM($A30),1,4,""),TRIM($A30))) -> 0 | H30: =SUMIFS(调整事项汇总表!$L$7:$L$10020,调整事项汇总表!$D$7:$D$10020,"其他",调整事项汇总表!$E$7:$E$10020,IF(OR(MID(TRIM($A30),2,1)="：",MID(TRIM($A30),2,1)="、"),REPLACEB(TRIM($A30),1,4,""),TRIM($A30))) -> 0 | I30: =B30+C30+E30+G30-H30-F30-D30 -> 0 | J30: =A30=未审报表!A30 -> TRUE | K30: =A30=审定报表!A30 -> TRUE
A31: =未审报表!A31 -> 应收分保账款坏账准备* | B31: =期初核对!C31 -> 0 | C31: =SUMIFS(调整事项汇总表!$K$7:$K$10020,调整事项汇总表!$D$7:$D$10020,"账项调整",调整事项汇总表!$E$7:$E$10020,IF(OR(MID(TRIM($A31),2,1)="：",MID(TRIM($A31),2,1)="、"),REPLACEB(TRIM($A31),1,4,""),TRIM($A31))) -> 0 | D31: =SUMIFS(调整事项汇总表!$L$7:$L$10020,调整事项汇总表!$D$7:$D$10020,"账项调整",调整事项汇总表!$E$7:$E$10020,IF(OR(MID(TRIM($A31),2,1)="：",MID(TRIM($A31),2,1)="、"),REPLACEB(TRIM($A31),1,4,""),TRIM($A31))) -> 0 | E31: =SUMIFS(调整事项汇总表!$K$7:$K$10020,调整事项汇总表!$D$7:$D$10020,"报表调整",调整事项汇总表!$E$7:$E$10020,IF(OR(MID(TRIM($A31),2,1)="：",MID(TRIM($A31),2,1)="、"),REPLACEB(TRIM($A31),1,4,""),TRIM($A31))) -> 0 | F31: =SUMIFS(调整事项汇总表!$L$7:$L$10020,调整事项汇总表!$D$7:$D$10020,"报表调整",调整事项汇总表!$E$7:$E$10020,IF(OR(MID(TRIM($A31),2,1)="：",MID(TRIM($A31),2,1)="、"),REPLACEB(TRIM($A31),1,4,""),TRIM($A31))) -> 0 | G31: =SUMIFS(调整事项汇总表!$K$7:$K$10020,调整事项汇总表!$D$7:$D$10020,"其他",调整事项汇总表!$E$7:$E$10020,IF(OR(MID(TRIM($A31),2,1)="：",MID(TRIM($A31),2,1)="、"),REPLACEB(TRIM($A31),1,4,""),TRIM($A31))) -> 0 | H31: =SUMIFS(调整事项汇总表!$L$7:$L$10020,调整事项汇总表!$D$7:$D$10020,"其他",调整事项汇总表!$E$7:$E$10020,IF(OR(MID(TRIM($A31),2,1)="：",MID(TRIM($A31),2,1)="、"),REPLACEB(TRIM($A31),1,4,""),TRIM($A31))) -> 0 | I31: =B31+D31+F31+H31-G31-E31-C31 -> 0 | J31: =A31=未审报表!A31 -> TRUE | K31: =A31=审定报表!A31 -> TRUE
A32: =未审报表!A32 -> 应收分保账款* | B32: =期初核对!C32 -> 0 | C32: =C30+C31 -> 0 | D32: =D30+D31 -> 0 | E32: =E30+E31 -> 0 | F32: =F30+F31 -> 0 | G32: =G30+G31 -> 0 | H32: =H30+H31 -> 0 | I32: =B32+C32+E32+G32-H32-F32-D32 -> 0 | J32: =A32=未审报表!A32 -> TRUE | K32: =A32=审定报表!A32 -> TRUE
A33: =未审报表!A33 -> 应收分保合同准备金* | B33: =期初核对!C33 -> 0 | C33: =SUMIFS(调整事项汇总表!$K$7:$K$10020,调整事项汇总表!$D$7:$D$10020,"账项调整",调整事项汇总表!$E$7:$E$10020,IF(OR(MID(TRIM($A33),2,1)="：",MID(TRIM($A33),2,1)="、"),REPLACEB(TRIM($A33),1,4,""),TRIM($A33))) -> 0 | D33: =SUMIFS(调整事项汇总表!$L$7:$L$10020,调整事项汇总表!$D$7:$D$10020,"账项调整",调整事项汇总表!$E$7:$E$10020,IF(OR(MID(TRIM($A33),2,1)="：",MID(TRIM($A33),2,1)="、"),REPLACEB(TRIM($A33),1,4,""),TRIM($A33))) -> 0 | E33: =SUMIFS(调整事项汇总表!$K$7:$K$10020,调整事项汇总表!$D$7:$D$10020,"报表调整",调整事项汇总表!$E$7:$E$10020,IF(OR(MID(TRIM($A33),2,1)="：",MID(TRIM($A33),2,1)="、"),REPLACEB(TRIM($A33),1,4,""),TRIM($A33))) -> 0 | F33: =SUMIFS(调整事项汇总表!$L$7:$L$10020,调整事项汇总表!$D$7:$D$10020,"报表调整",调整事项汇总表!$E$7:$E$10020,IF(OR(MID(TRIM($A33),2,1)="：",MID(TRIM($A33),2,1)="、"),REPLACEB(TRIM($A33),1,4,""),TRIM($A33))) -> 0 | G33: =SUMIFS(调整事项汇总表!$K$7:$K$10020,调整事项汇总表!$D$7:$D$10020,"其他",调整事项汇总表!$E$7:$E$10020,IF(OR(MID(TRIM($A33),2,1)="：",MID(TRIM($A33),2,1)="、"),REPLACEB(TRIM($A33),1,4,""),TRIM($A33))) -> 0 | H33: =SUMIFS(调整事项汇总表!$L$7:$L$10020,调整事项汇总表!$D$7:$D$10020,"其他",调整事项汇总表!$E$7:$E$10020,IF(OR(MID(TRIM($A33),2,1)="：",MID(TRIM($A33),2,1)="、"),REPLACEB(TRIM($A33),1,4,""),TRIM($A33))) -> 0 | I33: =B33+C33+E33+G33-H33-F33-D33 -> 0 | J33: =A33=未审报表!A33 -> TRUE | K33: =A33=审定报表!A33 -> TRUE
A34: =未审报表!A34 -> 应收利息原值 | B34: =期初核对!C34 -> 0 | C34: =SUMIFS(调整事项汇总表!$K$7:$K$10020,调整事项汇总表!$D$7:$D$10020,"账项调整",调整事项汇总表!$E$7:$E$10020,IF(OR(MID(TRIM($A34),2,1)="：",MID(TRIM($A34),2,1)="、"),REPLACEB(TRIM($A34),1,4,""),TRIM($A34))) -> 0 | D34: =SUMIFS(调整事项汇总表!$L$7:$L$10020,调整事项汇总表!$D$7:$D$10020,"账项调整",调整事项汇总表!$E$7:$E$10020,IF(OR(MID(TRIM($A34),2,1)="：",MID(TRIM($A34),2,1)="、"),REPLACEB(TRIM($A34),1,4,""),TRIM($A34))) -> 0 | E34: =SUMIFS(调整事项汇总表!$K$7:$K$10020,调整事项汇总表!$D$7:$D$10020,"报表调整",调整事项汇总表!$E$7:$E$10020,IF(OR(MID(TRIM($A34),2,1)="：",MID(TRIM($A34),2,1)="、"),REPLACEB(TRIM($A34),1,4,""),TRIM($A34))) -> 0 | F34: =SUMIFS(调整事项汇总表!$L$7:$L$10020,调整事项汇总表!$D$7:$D$10020,"报表调整",调整事项汇总表!$E$7:$E$10020,IF(OR(MID(TRIM($A34),2,1)="：",MID(TRIM($A34),2,1)="、"),REPLACEB(TRIM($A34),1,4,""),TRIM($A34))) -> 0 | G34: =SUMIFS(调整事项汇总表!$K$7:$K$10020,调整事项汇总表!$D$7:$D$10020,"其他",调整事项汇总表!$E$7:$E$10020,IF(OR(MID(TRIM($A34),2,1)="：",MID(TRIM($A34),2,1)="、"),REPLACEB(TRIM($A34),1,4,""),TRIM($A34))) -> 0 | H34: =SUMIFS(调整事项汇总表!$L$7:$L$10020,调整事项汇总表!$D$7:$D$10020,"其他",调整事项汇总表!$E$7:$E$10020,IF(OR(MID(TRIM($A34),2,1)="：",MID(TRIM($A34),2,1)="、"),REPLACEB(TRIM($A34),1,4,""),TRIM($A34))) -> 0 | I34: =B34+C34+E34+G34-H34-F34-D34 -> 0 | J34: =A34=未审报表!A34 -> TRUE | K34: =A34=审定报表!A34 -> TRUE
A35: =未审报表!A35 -> 应收利息坏账准备 | B35: =期初核对!C35 -> 0 | C35: =SUMIFS(调整事项汇总表!$K$7:$K$10020,调整事项汇总表!$D$7:$D$10020,"账项调整",调整事项汇总表!$E$7:$E$10020,IF(OR(MID(TRIM($A35),2,1)="：",MID(TRIM($A35),2,1)="、"),REPLACEB(TRIM($A35),1,4,""),TRIM($A35))) -> 0 | D35: =SUMIFS(调整事项汇总表!$L$7:$L$10020,调整事项汇总表!$D$7:$D$10020,"账项调整",调整事项汇总表!$E$7:$E$10020,IF(OR(MID(TRIM($A35),2,1)="：",MID(TRIM($A35),2,1)="、"),REPLACEB(TRIM($A35),1,4,""),TRIM($A35))) -> 0 | E35: =SUMIFS(调整事项汇总表!$K$7:$K$10020,调整事项汇总表!$D$7:$D$10020,"报表调整",调整事项汇总表!$E$7:$E$10020,IF(OR(MID(TRIM($A35),2,1)="：",MID(TRIM($A35),2,1)="、"),REPLACEB(TRIM($A35),1,4,""),TRIM($A35))) -> 0 | F35: =SUMIFS(调整事项汇总表!$L$7:$L$10020,调整事项汇总表!$D$7:$D$10020,"报表调整",调整事项汇总表!$E$7:$E$10020,IF(OR(MID(TRIM($A35),2,1)="：",MID(TRIM($A35),2,1)="、"),REPLACEB(TRIM($A35),1,4,""),TRIM($A35))) -> 0 | G35: =SUMIFS(调整事项汇总表!$K$7:$K$10020,调整事项汇总表!$D$7:$D$10020,"其他",调整事项汇总表!$E$7:$E$10020,IF(OR(MID(TRIM($A35),2,1)="：",MID(TRIM($A35),2,1)="、"),REPLACEB(TRIM($A35),1,4,""),TRIM($A35))) -> 0 | H35: =SUMIFS(调整事项汇总表!$L$7:$L$10020,调整事项汇总表!$D$7:$D$10020,"其他",调整事项汇总表!$E$7:$E$10020,IF(OR(MID(TRIM($A35),2,1)="：",MID(TRIM($A35),2,1)="、"),REPLACEB(TRIM($A35),1,4,""),TRIM($A35))) -> 0 | I35: =B35+D35+F35+H35-G35-E35-C35 -> 0 | J35: =A35=未审报表!A35 -> TRUE | K35: =A35=审定报表!A35 -> TRUE
A36: =未审报表!A36 -> 应收利息 | B36: =期初核对!C36 -> 0 | I36: =B36+C36+E36+G36-H36-F36-D36 -> 0 | J36: =A36=未审报表!A36 -> TRUE | K36: =A36=审定报表!A36 -> TRUE
A37: =未审报表!A37 -> 应收股利原值 | B37: =期初核对!C37 -> 10512385 | C37: =SUMIFS(调整事项汇总表!$K$7:$K$10020,调整事项汇总表!$D$7:$D$10020,"账项调整",调整事项汇总表!$E$7:$E$10020,IF(OR(MID(TRIM($A37),2,1)="：",MID(TRIM($A37),2,1)="、"),REPLACEB(TRIM($A37),1,4,""),TRIM($A37))) -> 0 | D37: =SUMIFS(调整事项汇总表!$L$7:$L$10020,调整事项汇总表!$D$7:$D$10020,"账项调整",调整事项汇总表!$E$7:$E$10020,IF(OR(MID(TRIM($A37),2,1)="：",MID(TRIM($A37),2,1)="、"),REPLACEB(TRIM($A37),1,4,""),TRIM($A37))) -> 0 | E37: =SUMIFS(调整事项汇总表!$K$7:$K$10020,调整事项汇总表!$D$7:$D$10020,"报表调整",调整事项汇总表!$E$7:$E$10020,IF(OR(MID(TRIM($A37),2,1)="：",MID(TRIM($A37),2,1)="、"),REPLACEB(TRIM($A37),1,4,""),TRIM($A37))) -> 0 | F37: =SUMIFS(调整事项汇总表!$L$7:$L$10020,调整事项汇总表!$D$7:$D$10020,"报表调整",调整事项汇总表!$E$7:$E$10020,IF(OR(MID(TRIM($A37),2,1)="：",MID(TRIM($A37),2,1)="、"),REPLACEB(TRIM($A37),1,4,""),TRIM($A37))) -> 0 | G37: =SUMIFS(调整事项汇总表!$K$7:$K$10020,调整事项汇总表!$D$7:$D$10020,"其他",调整事项汇总表!$E$7:$E$10020,IF(OR(MID(TRIM($A37),2,1)="：",MID(TRIM($A37),2,1)="、"),REPLACEB(TRIM($A37),1,4,""),TRIM($A37))) -> 0 | H37: =SUMIFS(调整事项汇总表!$L$7:$L$10020,调整事项汇总表!$D$7:$D$10020,"其他",调整事项汇总表!$E$7:$E$10020,IF(OR(MID(TRIM($A37),2,1)="：",MID(TRIM($A37),2,1)="、"),REPLACEB(TRIM($A37),1,4,""),TRIM($A37))) -> 0 | I37: =B37+C37+E37+G37-H37-F37-D37 -> 10512385 | J37: =A37=未审报表!A37 -> TRUE | K37: =A37=审定报表!A37 -> TRUE
A38: =未审报表!A38 -> 应收股利坏账准备 | B38: =期初核对!C38 -> 0 | C38: =SUMIFS(调整事项汇总表!$K$7:$K$10020,调整事项汇总表!$D$7:$D$10020,"账项调整",调整事项汇总表!$E$7:$E$10020,IF(OR(MID(TRIM($A38),2,1)="：",MID(TRIM($A38),2,1)="、"),REPLACEB(TRIM($A38),1,4,""),TRIM($A38))) -> 0 | D38: =SUMIFS(调整事项汇总表!$L$7:$L$10020,调整事项汇总表!$D$7:$D$10020,"账项调整",调整事项汇总表!$E$7:$E$10020,IF(OR(MID(TRIM($A38),2,1)="：",MID(TRIM($A38),2,1)="、"),REPLACEB(TRIM($A38),1,4,""),TRIM($A38))) -> 0 | E38: =SUMIFS(调整事项汇总表!$K$7:$K$10020,调整事项汇总表!$D$7:$D$10020,"报表调整",调整事项汇总表!$E$7:$E$10020,IF(OR(MID(TRIM($A38),2,1)="：",MID(TRIM($A38),2,1)="、"),REPLACEB(TRIM($A38),1,4,""),TRIM($A38))) -> 0 | F38: =SUMIFS(调整事项汇总表!$L$7:$L$10020,调整事项汇总表!$D$7:$D$10020,"报表调整",调整事项汇总表!$E$7:$E$10020,IF(OR(MID(TRIM($A38),2,1)="：",MID(TRIM($A38),2,1)="、"),REPLACEB(TRIM($A38),1,4,""),TRIM($A38))) -> 0 | G38: =SUMIFS(调整事项汇总表!$K$7:$K$10020,调整事项汇总表!$D$7:$D$10020,"其他",调整事项汇总表!$E$7:$E$10020,IF(OR(MID(TRIM($A38),2,1)="：",MID(TRIM($A38),2,1)="、"),REPLACEB(TRIM($A38),1,4,""),TRIM($A38))) -> 0 | H38: =SUMIFS(调整事项汇总表!$L$7:$L$10020,调整事项汇总表!$D$7:$D$10020,"其他",调整事项汇总表!$E$7:$E$10020,IF(OR(MID(TRIM($A38),2,1)="：",MID(TRIM($A38),2,1)="、"),REPLACEB(TRIM($A38),1,4,""),TRIM($A38))) -> 0 | I38: =B38+D38+F38+H38-G38-E38-C38 -> 0 | J38: =A38=未审报表!A38 -> TRUE | K38: =A38=审定报表!A38 -> TRUE
A39: =未审报表!A39 -> 应收股利 | B39: =期初核对!C39 -> 10512385 | C39: =C37+C38 -> 0 | D39: =D37+D38 -> 0 | E39: =E37+E38 -> 0 | F39: =F37+F38 -> 0 | G39: =G37+G38 -> 0 | H39: =H37+H38 -> 0 | I39: =B39+C39+E39+G39-H39-F39-D39 -> 10512385 | J39: =A39=未审报表!A39 -> TRUE | K39: =A39=审定报表!A39 -> TRUE
A40: =未审报表!A40 -> 其他应收款原值 | B40: =期初核对!C40 -> 12543397 | C40: =SUMIFS(调整事项汇总表!$K$7:$K$10020,调整事项汇总表!$D$7:$D$10020,"账项调整",调整事项汇总表!$E$7:$E$10020,IF(OR(MID(TRIM($A40),2,1)="：",MID(TRIM($A40),2,1)="、"),REPLACEB(TRIM($A40),1,4,""),TRIM($A40))) -> 0 | D40: =SUMIFS(调整事项汇总表!$L$7:$L$10020,调整事项汇总表!$D$7:$D$10020,"账项调整",调整事项汇总表!$E$7:$E$10020,IF(OR(MID(TRIM($A40),2,1)="：",MID(TRIM($A40),2,1)="、"),REPLACEB(TRIM($A40),1,4,""),TRIM($A40))) -> 0 | E40: =SUMIFS(调整事项汇总表!$K$7:$K$10020,调整事项汇总表!$D$7:$D$10020,"报表调整",调整事项汇总表!$E$7:$E$10020,IF(OR(MID(TRIM($A40),2,1)="：",MID(TRIM($A40),2,1)="、"),REPLACEB(TRIM($A40),1,4,""),TRIM($A40))) -> 0 | F40: =SUMIFS(调整事项汇总表!$L$7:$L$10020,调整事项汇总表!$D$7:$D$10020,"报表调整",调整事项汇总表!$E$7:$E$10020,IF(OR(MID(TRIM($A40),2,1)="：",MID(TRIM($A40),2,1)="、"),REPLACEB(TRIM($A40),1,4,""),TRIM($A40))) -> 0 | G40: =SUMIFS(调整事项汇总表!$K$7:$K$10020,调整事项汇总表!$D$7:$D$10020,"其他",调整事项汇总表!$E$7:$E$10020,IF(OR(MID(TRIM($A40),2,1)="：",MID(TRIM($A40),2,1)="、"),REPLACEB(TRIM($A40),1,4,""),TRIM($A40))) -> 0 | H40: =SUMIFS(调整事项汇总表!$L$7:$L$10020,调整事项汇总表!$D$7:$D$10020,"其他",调整事项汇总表!$E$7:$E$10020,IF(OR(MID(TRIM($A40),2,1)="：",MID(TRIM($A40),2,1)="、"),REPLACEB(TRIM($A40),1,4,""),TRIM($A40))) -> 0 | I40: =B40+C40+E40+G40-H40-F40-D40 -> 12543397 | J40: =A40=未审报表!A40 -> TRUE | K40: =A40=审定报表!A40 -> TRUE
A41: =未审报表!A41 -> 其他应收款坏账准备 | B41: =期初核对!C41 -> 0 | C41: =SUMIFS(调整事项汇总表!$K$7:$K$10020,调整事项汇总表!$D$7:$D$10020,"账项调整",调整事项汇总表!$E$7:$E$10020,IF(OR(MID(TRIM($A41),2,1)="：",MID(TRIM($A41),2,1)="、"),REPLACEB(TRIM($A41),1,4,""),TRIM($A41))) -> 0 | D41: =SUMIFS(调整事项汇总表!$L$7:$L$10020,调整事项汇总表!$D$7:$D$10020,"账项调整",调整事项汇总表!$E$7:$E$10020,IF(OR(MID(TRIM($A41),2,1)="：",MID(TRIM($A41),2,1)="、"),REPLACEB(TRIM($A41),1,4,""),TRIM($A41))) -> 0 | E41: =SUMIFS(调整事项汇总表!$K$7:$K$10020,调整事项汇总表!$D$7:$D$10020,"报表调整",调整事项汇总表!$E$7:$E$10020,IF(OR(MID(TRIM($A41),2,1)="：",MID(TRIM($A41),2,1)="、"),REPLACEB(TRIM($A41),1,4,""),TRIM($A41))) -> 0 | F41: =SUMIFS(调整事项汇总表!$L$7:$L$10020,调整事项汇总表!$D$7:$D$10020,"报表调整",调整事项汇总表!$E$7:$E$10020,IF(OR(MID(TRIM($A41),2,1)="：",MID(TRIM($A41),2,1)="、"),REPLACEB(TRIM($A41),1,4,""),TRIM($A41))) -> 0 | G41: =SUMIFS(调整事项汇总表!$K$7:$K$10020,调整事项汇总表!$D$7:$D$10020,"其他",调整事项汇总表!$E$7:$E$10020,IF(OR(MID(TRIM($A41),2,1)="：",MID(TRIM($A41),2,1)="、"),REPLACEB(TRIM($A41),1,4,""),TRIM($A41))) -> 0 | H41: =SUMIFS(调整事项汇总表!$L$7:$L$10020,调整事项汇总表!$D$7:$D$10020,"其他",调整事项汇总表!$E$7:$E$10020,IF(OR(MID(TRIM($A41),2,1)="：",MID(TRIM($A41),2,1)="、"),REPLACEB(TRIM($A41),1,4,""),TRIM($A41))) -> 0 | I41: =B41+D41+F41+H41-G41-E41-C41 -> 0 | J41: =A41=未审报表!A41 -> TRUE | K41: =A41=审定报表!A41 -> TRUE
A42: =未审报表!A42 -> 其他应收款 | B42: =期初核对!C42 -> 12543397 | C42: =C40+C41 -> 0 | D42: =D40+D41 -> 0 | E42: =E40+E41 -> 0 | F42: =F40+F41 -> 0 | G42: =G40+G41 -> 0 | H42: =H40+H41 -> 0 | I42: =B42+C42+E42+G42-H42-F42-D42 -> 12543397 | J42: =A42=未审报表!A42 -> TRUE | K42: =A42=审定报表!A42 -> TRUE
