Workbook
Name _: [1]低值易耗品!$A$1:$I$225
Name _.dbf: '[2]12进销存'!$A$3:$Q$235
Name _0.dbf: [3]累计销售!$A$6:$E$62
Name _11: [4]其他业务利润!$A$5:$G$12
Name _999年12月31日股份应收帐款.dbf: #REF!
Name _999年12月31日股份应收帐款.dbf: #REF!
Name _999年12月31日股份应收帐款.dbf: #REF!
Name _Hlk533511527: 'RP 016'!$A$42
Name _Hlk533597423: 'RP 016'!$A$57
Name a: #REF!
Name a: #REF!
Name a: #REF!
Name AFSDGEGQ: #REF!
Name AFSDGEGQ: #REF!
Name AFSDGEGQ: #REF!
Name ASDFA: #REF!
Name ASDFA: #REF!
Name ASDFA: #REF!
Name ASFDA: #REF!
Name ASFDA: #REF!
Name ASFDA: #REF!
Name clah: #REF!
Name clah: #REF!
Name clah: #REF!
Name clz: #REF!
Name clz: #REF!
Name clz: #REF!
Name fuck: [6]资产负债表!#REF!
Name fuck: [6]资产负债表!#REF!
Name fuck: [6]资产负债表!#REF!
Name OLE_LINK1: 'RP 095'!$A$32
Name OLE_LINK2: 'RP 095'!$A$35
Name OLE_LINK4: 'RP 095'!$A$29
Name OLE_LINK9: 'RP 095'!$A$33
Name Print_Area_MI: #REF!
Name Print_Area_MI: #REF!
Name Print_Area_MI: #REF!
Name Print_Area_MI: #REF!
Name Print_Area_MI: #REF!
Name SD: #REF!
Name SD: #REF!
Name SD: #REF!
Name SDF: #REF!
Name SDF: #REF!
Name SDF: #REF!
Name SDFA: #REF!
Name SDFA: #REF!
Name SDFA: #REF!
Name SDFSD: #REF!
Name SDFSD: #REF!
Name SDFSD: #REF!
Name SF: #REF!
Name SF: #REF!
Name SF: #REF!
Name Sheet1: #REF!
Name Sheet1: #REF!
Name Sheet1: #REF!
Name Sheet10: #REF!
Name Sheet10: #REF!
Name Sheet10: #REF!

Sheet 目录
A2: 20XX年XX月XX日ABC公司报告文件包 | E2: B30-13-1
A4: 序号 | B4: 文件名称 | C4: 目的 | D4: 工作表 | E4: 核对（是否完成）
B5: 基础信息 | C5: 一般信息 | D5: 基础信息 | E5: 完成
A6: =1+A5 -> 1 | B6: 会计政策 | C6: 一般信息 | D6: RP 001 | E6: 完成
A7: 2.1 | B7: 资产负债表 | C7: 财务报表 | D7: RP 002-1 | E7: 完成
A8: 2.2 | B8: 资产负债表 | C8: 财务报表 | D8: RP 002-2 | E8: 完成
A9: 3 | B9: 利润表 | C9: 财务报表 | D9: RP 003 | E9: 完成
A10: =1+A9 -> 4 | B10: 现金流量表 | C10: 财务报表 | D10: RP 004 | E10: 完成
A11: =1+A10 -> 5 | B11: 所有者权益变动表 | C11: 财务报表 | D11: RP 005 | E11: 完成
A12: =1+A11 -> 6 | B12: 准则差异调节表 | C12: 备查信息 | D12: RP 006 | E12: 完成
A13: =1+A12 -> 7 | B13: 集团间交易（销售、采购、费用） | C13: 集团间交易 | D13: RP 007 | E13: 完成
A14: =1+A13 -> 8 | B14: 集团间交易（资产、负债） | C14: 集团间交易 | D14: RP 008 | E14: 完成
A15: =1+A14 -> 9 | B15: 集团间交易（存货） | C15: 未实现内部利润 | D15: RP 009 | E15: 完成
A16: =1+A15 -> 10 | B16: 集团间交易（销售采购固定资产） | C16: 未实现内部利润 | D16: RP 010 | E16: 完成
A17: =1+A16 -> 11 | B17: 集团间交易（现金流量） | C17: 集团间交易 | D17: RP 011 | E17: 完成
A18: =1+A17 -> 12 | B18: 货币资金 | C18: 披露信息 | D18: RP 012 | E18: 完成
A19: 13 | B19: 交易性金融资产 | C19: 披露信息 | D19: RP 013 | E19: 完成
A20: 14 | B20: 以公允价值计量且其变动计入当期损益的金融资产 | C20: 披露信息 | D20: RP 014 | E20: 完成
A21: =1+A20 -> 15 | B21: 衍生金融资产 | C21: 披露信息 | D21: RP 015 | E21: 完成
A22: 16 | B22: 应收票据 | C22: 披露信息 | D22: RP 016 | E22: 完成
A23: 17 | B23: 应收账款 | C23: 披露信息 | D23: RP 017 | E23: 完成
A24: 18 | B24: 应收款项融资 | C24: 披露信息 | D24: RP 018 | E24: 完成
A25: 19 | B25: 预付款项 | C25: 披露信息 | D25: RP 019 | E25: 完成
A26: 20 | B26: 其他应收款（应收利息、应收股利、其他应收款） | C26: 披露信息 | D26: RP 020 | E26: 完成
A27: 20.1 | B27: 其中：应收利息 | C27: 披露信息 | D27: RP 020-1 | E27: 完成
A28: 20.2 | B28: 应收股利 | C28: 披露信息 | D28: RP 020-2 | E28: 完成
A29: 20.3 | B29: 其他应收款 | C29: 披露信息 | D29: RP 020-3 | E29: 完成
A30: 21 | B30: 存货 | C30: 披露信息 | D30: RP 021 | E30: 完成
A31: =A30+1 -> 22 | B31: 合同资产 | C31: 披露信息 | D31: RP 022 | E31: 完成
A32: =A31+1 -> 23 | B32: 持有待售的资产和持有待售的负债 | C32: 披露信息 | D32: RP 023 | E32: 完成
A33: =A32+1 -> 24 | B33: 一年内到期的非流动负债 | C33: 披露信息 | D33: RP 024 | E33: 完成
A34: =A33+1 -> 25 | B34: 其他流动资产 | C34: 披露信息 | D34: RP 025 | E34: 完成
A35: =A34+1 -> 26 | B35: 债权投资 | C35: 披露信息 | D35: RP 026 | E35: 完成
A36: =A35+1 -> 27 | B36: 可供出售金融资产 | C36: 披露信息 | D36: RP 027 | E36: 完成
A37: =A36+1 -> 28 | B37: 其他债权投资 | C37: 披露信息 | D37: RP 028 | E37: 完成
A38: =A37+1 -> 29 | B38: 持有至到期投资 | C38: 披露信息 | D38: RP 029 | E38: 完成
A39: =A38+1 -> 30 | B39: 长期应收款 | C39: 披露信息 | D39: RP 030 | E39: 完成
A40: =A39+1 -> 31 | B40: 设定受益计划净资产 | C40: 披露信息 | D40: RP 031 | E40: 完成
A41: =A40+1 -> 32 | B41: 长期股权投资 | C41: 披露信息 | D41: RP 032 | E41: 完成
A42: =A41+1 -> 33 | B42: 其他权益工具投资 | C42: 披露信息 | D42: RP 033 | E42: 完成
... A45: =A44+1 -> 36 | B45: 固定资产 | C45: 披露信息 | D45: RP 036 | E45: 完成
A46: 36.1 | B46: 其中：固定资产 | C46: 披露信息 | D46: RP 036-1 | E46: 完成
A47: 36.2 | B47: 固定资产清理 | C47: 披露信息 | D47: RP 036-2 | E47: 完成
A48: 37 | B48: 在建工程 | C48: 披露信息 | D48: RP 037 | E48: 完成
A49: =1+A46 -> 37.1 | B49: 其中：在建工程 | C49: 披露信息 | D49: RP 037-1 | E49: 完成
A50: 37.2 | B50: 工程物资 | C50: 披露信息 | D50: RP 037-2 | E50: 完成
A51: 38 | B51: 生产性生物资产 | C51: 披露信息 | D51: RP 038 | E51: 完成
A52: =1+A51 -> 39 | B52: 无形资产 | C52: 披露信息 | D52: RP 039 | E52: 完成
A53: =1+A52 -> 40 | B53: 开发支出 | C53: 披露信息 | D53: RP 040 | E53: 完成
A54: =1+A53 -> 41 | B54: 商誉 | C54: 披露信息 | D54: RP 041 | E54: 完成
A55: =1+A54 -> 42 | B55: 长期待摊费用 | C55: 披露信息 | D55: RP 042 | E55: 完成
A56: =1+A55 -> 43 | B56: 递延所得税资产和递延所得税负债 | C56: 披露信息 | D56: RP 043 | E56: 完成
A57: =1+A56 -> 44 | B57: 其他非流动资产 | C57: 披露信息 | D57: RP 044 | E57: 完成
A58: =1+A57 -> 45 | B58: 资产减值准备 | C58: 披露信息 | D58: RP 045 | E58: 完成
A59: =1+A58 -> 46 | B59: 所有权受到限制的资产 | C59: 披露信息 | D59: RP 046 | E59: 完成
A60: =1+A59 -> 47 | B60: 短期借款 | C60: 披露信息 | D60: RP 047 | E60: 完成
A61: =1+A60 -> 48 | B61: 交易性金融负债 | C61: 披露信息 | D61: RP 048 | E61: 完成
A62: =1+A61 -> 49 | B62: 以公允价值计量且其变动计入当期损益的金融负债 | C62: 披露信息 | D62: RP 049 | E62: 完成
A63: =1+A62 -> 50 | B63: 衍生金融负债 | C63: 披露信息 | D63: RP 050 | E63: 完成
A64: 51 | B64: 应付票据 | C64: 披露信息 | D64: RP 051 | E64: 完成
A65: 52 | B65: 应付账款 | C65: 披露信息 | D65: RP 052 | E65: 完成
A66: 53 | B66: 预收款项 | C66: 披露信息 | D66: RP 053 | E66: 完成
A67: =A66+1 -> 54 | B67: 合同负债 | C67: 披露信息 | D67: RP 054 | E67: 完成
A68: =A67+1 -> 55 | B68: 应付职工薪酬 | C68: 披露信息 | D68: RP 055 | E68: 完成
A69: =A68+1 -> 56 | B69: 应交税费 | C69: 披露信息 | D69: RP 056 | E69: 完成
A70: =A69+1 -> 57 | B70: 其他应付款 | C70: 披露信息 | D70: RP 057 | E70: 完成
A71: 57.1 | B71: 其中：应付利息 | C71: 披露信息 | D71: RP 057-1 | E71: 完成
A72: 57.2 | B72: 应付股利 | C72: 披露信息 | D72: RP 057-2 | E72: 完成
A73: 57.3 | B73: 其他应付款 | C73: 披露信息 | D73: RP 057-3 | E73: 完成
A74: 58 | B74: 一年内到期的非流动负债 | C74: 披露信息 | D74: RP 058 | E74: 完成
A75: =1+A74 -> 59 | B75: 其他流动负债 | C75: 披露信息 | D75: RP 059 | E75: 完成
A76: =1+A75 -> 60 | B76: 长期借款 | C76: 披露信息 | D76: RP 060 | E76: 完成
A77: =1+A76 -> 61 | B77: 应付债券 | C77: 披露信息 | D77: RP 061 | E77: 完成
A78: 62 | B78: 长期应付款 | C78: 披露信息 | D78: RP 062 | E78: 完成
A79: 62.1 | B79: 其中：长期应付款 | C79: 披露信息 | D79: RP 062-1 | E79: 完成
A80: 62.2 | B80: 专项应付款 | C80: 披露信息 | D80: RP 062-2 | E80: 完成
A81: 63 | B81: 长期应付职工薪酬 | C81: 披露信息 | D81: RP 063 | E81: 完成
A82: =A81+1 -> 64 | B82: 预计负债 | C82: 披露信息 | D82: RP 064 | E82: 完成
A83: =1+A82 -> 65 | B83: 递延收益 | C83: 披露信息 | D83: RP 065 | E83: 完成
A84: =1+A83 -> 66 | B84: 其他非流动负债 | C84: 披露信息 | D84: RP 066 | E84: 完成
A85: =1+A84 -> 67 | B85: 营业收入及成本 | C85: 披露信息 | D85: RP 067 | E85: 完成
A86: =1+A85 -> 68 | B86: 税金及附加 | C86: 披露信息 | D86: RP 068 | E86: 完成
A87: =1+A86 -> 69 | B87: 销售费用 | C87: 披露信息 | D87: RP 069 | E87: 完成
A88: =1+A87 -> 70 | B88: 管理费用 | C88: 披露信息 | D88: RP 070 | E88: 完成
A89: =1+A88 -> 71 | B89: 研发费用 | C89: 披露信息 | D89: RP 071 | E89: 完成
A90: =1+A89 -> 72 | B90: 财务费用 | C90: 披露信息 | D90: RP 072 | E90: 完成
A91: =A90+1 -> 73 | B91: 其他收益 | C91: 披露信息 | D91: RP 073 | E91: 完成
A92: =1+A91 -> 74 | B92: 投资收益 | C92: 披露信息 | D92: RP 074 | E92: 完成
A93: =1+A92 -> 75 | B93: 净敞口套期收益 | C93: 披露信息 | D93: RP 075 | E93: 完成
A94: =1+A93 -> 76 | B94: 公允价值变动损益 | C94: 披露信息 | D94: RP 076 | E94: 完成
A95: =1+A94 -> 77 | B95: 信用减值损失 | C95: 披露信息 | D95: RP 077 | E95: 完成
A96: =1+A95 -> 78 | B96: 资产减值损失 | C96: 披露信息 | D96: RP 078 | E96: 完成
A97: =1+A96 -> 79 | B97: 资产处置收益 | C97: 披露信息 | D97: RP 079 | E97: 完成
A98: =1+A97 -> 80 | B98: 营业外收入 | C98: 披露信息 | D98: RP 080 | E98: 完成
A99: =1+A98 -> 81 | B99: 营业外支出 | C99: 披露信息 | D99: RP 081 | E99: 完成
A100: =1+A99 -> 82 | B100: 所得税费用 | C100: 披露信息 | D100: RP 082 | E100: 完成
A101: =1+A100 -> 83 | B101: 收到的其他与经营活动有关的现金 | C101: 披露信息 | D101: RP 083 | E101: 完成
A102: =1+A101 -> 84 | B102: 支付的其他与经营活动有关的现金 | C102: 披露信息 | D102: RP 084 | E102: 完成
A103: =1+A102 -> 85 | B103: 收到的其他与投资活动有关的现金 | C103: 披露信息 | D103: RP 085 | E103: 完成
... A113: =1+A112 -> 95 | B113: 非经常性损益 | C113: 披露信息 | D113: RP 095 | E113: 完成
...

Sheet 基础信息
A1: 基础信息
A2: 一般信息
A4: 公司代码
A5: 公司简称
A6: 公司名称
A7: 报告币种代码
A8: 报告币种
A9: 财务期间
A12: 地址
A13: 董事长
A14: 总经理
A15: 审计师
... A22: 电子邮件
A25: 项目 | B25: 人数
A26: 总经理、董事会秘书、内审
A27: 一般经理
A28: 员工
A29: 合计
A30: 临时工
A31: 外包人员

Sheet RP 001
A1: 公司名称 | B1: =基础信息!C5 -> 0 | E1: BACK
A2: 财务期间 | B2: =基础信息!B9 -> 0
A3: 内容 | B3: 主要会计政策、会计估计（根据具体情况适当增减）
A4: 1 | B4: 会计年度
A6: 2 | B6: 营业周期
A8: 3 | B8: 记账本位币
A10: 4 | B10: 同一控制下和非同一控制下企业合并的会计处理
A12: 5 | B12: 合并财务报表编制方法
A14: 6 | B14: 合营安排的分类及共同经营的会计处理
A16: 7 | B16: 现金等价物
A18: 8 | B18: 外币折算
A20: 9 | B20: 金融工具
A22: 10 | B22: 公允价值计量
A24: 11 | B24: 应收票据及应收账款
A26: 12 | B26: 存货
... A74: 36 | B74: 非金融资产证券化业务的主要会计处理方法

Sheet RP 002-1
A1: 资产负债表
A2: =基础信息!B6 -> 0 | D2: 单位：人民币元
A3: 项目 | B3: 附注 | C3: 20X8.12.31 | D3: 20X7.12.31
A4: 流动资产:
A5: 货币资金 | C5: ='RP 006'!E6 -> 0
A6: 交易性金融资产
A7: 以公允价值计量且其变动计入当期损益的金融资产 | C7: ='RP 006'!E8 -> 0
A8: 衍生金融资产 （不适用的删除）
A9: 应收票据 | C9: ='RP 006'!E10 -> 0
A10: 应收账款
A11: 应收款项融资
A12: 预付款项 | C12: ='RP 006'!E19 -> 0
A13: 其他应收款
A14: 存货 | C14: ='RP 006'!E25 -> 0
A15: 合同资产
A16: 持有待售资产 （不适用的删除）
A17: 一年内到期的非流动资产 | C17: ='RP 006'!E30 -> 0
A18: 其他流动资产 | C18: ='RP 006'!E41 -> 0
A19: 流动资产合计 | C19: =SUM(C5:C18) -> 0 | D19: =SUM(D5:D18) -> 0
A20: 非流动资产:
A21: 债权投资
A22: 可供出售金融资产 | C22: ='RP 006'!E46 -> 0
A23: 其他债权投资
A24: 持有至到期投资 | C24: ='RP 006'!E47 -> 0
A25: 长期应收款 | C25: ='RP 006'!E48 -> 0
A26: 设定受益计划净资产 （不适用的删除）
A27: 长期股权投资 | C27: ='RP 006'!E52 -> 0
A28: 其他权益工具投资
A29: 其他非流动金融资产
A30: 投资性房地产 | C30: ='RP 006'!E57 -> 0
A31: 固定资产 | C31: ='RP 006'!E62 -> 0
A32: 在建工程 | C32: ='RP 006'!E63 -> 0
A33: 生产性生物资产 | C33: ='RP 006'!E64 -> 0
A34: 油气资产 | C34: ='RP 006'!E65 -> 0
A35: 无形资产 | C35: ='RP 006'!E68 -> 0
A36: 开发支出 | C36: ='RP 006'!E69 -> 0
A37: 商誉 | C37: ='RP 006'!E70 -> 0
A38: 长期待摊费用 | C38: ='RP 006'!E71 -> 0
A39: 递延所得税资产 | C39: ='RP 006'!E72 -> 0
A40: 其他非流动资产 | C40: ='RP 006'!E73 -> 0
A41: 非流动资产合计 | C41: =SUM(C22:C40) -> 0 | D41: =SUM(D22:D40) -> 0
A42: 资产总计 | C42: =C19+C41 -> 0 | D42: =D19+D41 -> 0

Sheet RP 002-2
A1: 资产负债表（续）
A3: 项目 | B3: 附注 | C3: 20X7.12.31 | D3: 20X6.12.31
A4: 流动负债:
A5: 短期借款 | C5: ='RP 006'!E81 -> 0
A6: 交易性金融负债
A7: 以公允价值计量且其变动计入当期损益的金融负债 | C7: ='RP 006'!E83 -> 0
A8: 衍生金融负债 （不适用的删除）
A9: 应付票据 | C9: ='RP 006'!E85 -> 0
A10: 应付账款
A11: 预收款项 | C11: ='RP 006'!E87 -> 0
A12: 合同负债
A13: 应付职工薪酬 | C13: ='RP 006'!E89 -> 0
A14: 应交税费 | C14: ='RP 006'!E90 -> 0
A15: 其他应付款 | C15: ='RP 006'!E91 -> 0
A16: 持有待售负债（不适用的删除）
A17: 一年内到期的非流动负债 | C17: ='RP 006'!E93 -> 0
A18: 其他流动负债 | C18: ='RP 006'!E102 -> 0
A19: 流动负债合计 | C19: =SUM(C5:C18) -> 0 | D19: =SUM(D5:D18) -> 0
A20: 非流动负债:
A21: 长期借款 | C21: ='RP 006'!E105 -> 0
A22: 应付债券 | C22: ='RP 006'!E106 -> 0
A23: 其中：优先股（不适用的删除）
A24: 永续债（不适用的删除）
A25: 长期应付款 | C25: ='RP 006'!E107 -> 0
A26: 长期应付职工薪酬（不适用的删除）
A27: 预计负债 | C27: ='RP 006'!E110 -> 0
A28: 递延收益
A29: 递延所得税负债 | C29: ='RP 006'!E112 -> 0
A30: 其他非流动负债 | C30: ='RP 006'!E113 -> 0
A31: 非流动负债合计 | C31: =SUM(C21:C30) -> 0 | D31: =SUM(D21:D30) -> 0
A32: 负债合计 | C32: =C19+C31 -> 0 | D32: =D19+D31 -> 0
A33: 股东权益:
A34: 股本 | C34: ='RP 006'!E117 -> 0
A35: 其他权益工具（不适用的删除）
A36: 其中：优先股
A37: 永续债
A38: 资本公积 | C38: ='RP 006'!E121 -> 0
A39: 减：库存股 | C39: ='RP 006'!E122 -> 0
A40: 其他综合收益
A41: 专项储备
A42: 盈余公积 | C42: ='RP 006'!E124 -> 0
A43: 未分配利润 | C43: ='RP 006'!E125 -> 0
A44: 归属于母公司股东权益合计 | C44: =SUM(C34:C43)-C39-C39 -> 0 | D44: =SUM(D34:D43)-D39-D39 -> 0
A45: 少数股东权益 | C45: ='RP 006'!E127 -> 0
A46: 股东权益合计 | C46: =SUM(C44:C45) -> 0 | D46: =SUM(D44:D45) -> 0
A47: 负债和股东权益总计 | C47: =C32+C46 -> 0 | D47: =D32+D46 -> 0
A48: 公司法定代表人： | B48: 主管会计工作的公司负责人： | D48: 公司会计机构负责人：

Sheet RP 003 
A1: 利润表
A2: =基础信息!B6 -> 0 | F2: 单位：人民币元
A3: 项目 | B3: 附注 | C3: 20X7年度 | E3: 20X6年度
A5: 一、营业收入 | C5: ='RP 006'!E135 -> 0
A6: 减：营业成本 | C6: ='RP 006'!E136 -> 0
A7: 税金及附加 | C7: ='RP 006'!E137 -> 0
A8: 销售费用 | C8: ='RP 006'!E138 -> 0
A9: 管理费用 | C9: ='RP 006'!E139 -> 0
A10: 研发费用
A11: 财务费用 | C11: ='RP 006'!E141 -> 0
A12: 其中：利息费用
A13: 利息收入
A14: 加：其他收益 | C14: ='RP 006'!E144 -> 0
A15: 投资收益(损失以“-”号填列）
A16: 其中：对联营企业和合营企业的投资收益
A17: 净敞口套期收益（损失以“-”号填列） | C17: ='RP 006'!E141 -> 0
A18: 公允价值变动收益(损失以“-”号填列） | C18: ='RP 006'!E144 -> 0
A19: 信用减值损失
A20: 资产减值损失 | C20: ='RP 006'!E147 -> 0
A21: 资产处置收益(损失以“-”号填列）
A22: 二、营业利润(损失以“-”号填列） | C22: =C5-C6-C7-C8-C9-C10-C11-C14+C16+C17+C20+C21 -> 0 | D22: =D5-D6-D7-D8-D9-D10-D11-D14+D16+D17+D20+D21 -> 0 | E22: =E5-E6-E7-E8-E9-E10-E11-E14+E16+E17+E20+E21 -> 0
A23: 加：营业外收入 | C23: ='RP 006'!E155 -> 0
A24: 减：营业外支出 | C24: ='RP 006'!E156 -> 0
A25: 三、利润总额(损失以“-”号填列） | C25: =C22+C23-C24 -> 0 | E25: =E22+E23-E24 -> 0
A26: 减：所得税费用 | C26: ='RP 006'!E158 -> 0
A27: 四、净利润(损失以“-”号填列） | C27: =C25-C26 -> 0 | E27: =E25-E26 -> 0
A28: （一）按经营持续性分类
A29: 1、持续经营净利润（净亏损以“-”号填列） | C29: ='RP 006'!E161 -> 0
A30: 2、终止经营净利润（净亏损以“-”号填列） | C30: ='RP 006'!E162 -> 0
A31: （二）按所有权归属分类
A32: 1、归属于母公司股东的净利润 | C32: ='RP 006'!E164 -> 0
A33: 2、少数股东损益 | C33: ='RP 006'!E165 -> 0
A34: 五、其他综合收益的税后净额
A35: 归属于母公司股东的其他综合收益的税后净额
A36: （一）以后不能重分类进损益的其他综合收益
A37: 1、重新计量设定受益计划变动额（不适用的删除）
A38: 2、权益法下不能转损益的其他综合收益（不适用的删除）
A39: 3、其他权益工具投资公允价值变动
A40: 4、企业自身信用风险公允价值变动
A41: ……
A42: 5、其他（不适用的删除）
A43: （二）以后将重分类进损益的其他综合收益
A44: 1、权益法下可转损益的其他综合收益（不适用的删除）
A45: 2、其他债权投资公允价值变动
... A61: （二）稀释每股收益
A62: 公司法定代表人： 主管会计工作的公司负责人： | C62: 公司会计机构负责人：

Sheet RP 004 
A1: 现金流量表
A2: =基础信息!B6 -> 0 | I2: 单位：人民币元
A3: 项目 | B3: 附注 | C3: 20X7年度 | E3: 20X3年度 | H3: 20X6年度
A5: 一、经营活动产生的现金流量：
A6: 销售商品、提供劳务收到的现金
A7: 收到的税费返还
A8: 收到其他与经营活动有关的现金
A9: 经营活动现金流入小计 | C9: =SUM(C6:C8) -> 0 | E9: =SUM(E6:E8) -> 0 | F9: =SUM(F6:F8) -> 0 | G9: =SUM(G6:G8) -> 0 | H9: =SUM(H6:H8) -> 0
A10: 购买商品、接受劳务支付的现金
A11: 支付给职工以及为职工支付的现金
A12: 支付的各项税费
A13: 支付其他与经营活动有关的现金
A14: 经营活动现金流出小计 | C14: =C10+C11+C12+C13 -> 0 | E14: =E10+E11+E12+E13 -> 0 | F14: =F10+F11+F12+F13 -> 0 | G14: =G10+G11+G12+G13 -> 0 | H14: =H10+H11+H12+H13 -> 0
A15: 经营活动产生的现金流量净额 | C15: =C9-C14 -> 0 | E15: =E9-E14 -> 0 | F15: =F9-F14 -> 0 | G15: =G9-G14 -> 0 | H15: =H9-H14 -> 0
A16: 二、投资活动产生的现金流量：
A17: 收回投资收到的现金
A18: 取得投资收益收到的现金
A19: 处置固定资产、无形资产和其他长期资产收回的 现金净额
A20: 处置子公司及其他营业单位收到的现金净额
A21: 收到其他与投资活动有关的现金
A22: 投资活动现金流入小计 | C22: =SUM(C17:C21) -> 0 | E22: =SUM(E17:E21) -> 0 | F22: =SUM(F17:F21) -> 0 | G22: =SUM(G17:G21) -> 0 | H22: =SUM(H17:H21) -> 0
A23: 购置固定资产、无形资产和其他长期资产支付的现金
A24: 投资支付的现金
A25: 取得子公司及其他营业单位支付的现金净额
A26: 支付其他与投资活动有关的现金
A27: 投资活动现金流出小计 | C27: =SUM(C23:C26) -> 0 | E27: =SUM(E23:E26) -> 0 | F27: =SUM(F23:F26) -> 0 | G27: =SUM(G23:G26) -> 0 | H27: =SUM(H23:H26) -> 0
A28: 投资活动产生的现金流量净额 | C28: =C22-C27 -> 0 | E28: =E22-E27 -> 0 | F28: =F22-F27 -> 0 | G28: =G22-G27 -> 0 | H28: =H22-H27 -> 0
A29: 三、筹资活动产生的现金流量：
A30: 吸收投资收到的现金
A31: 其中：子公司吸收少数股东权益性投资收到的现金
A32: 取得借款收到的现金
A33: 收到其他与筹资活动有关的现金
A34: 筹资活动现金流入小计 | C34: =C30+C32+C33 -> 0 | E34: =E30+E32+E33 -> 0 | F34: =F30+F32+F33 -> 0 | G34: =G30+G32+G33 -> 0 | H34: =H30+H32+H33 -> 0
A35: 偿还债务支付的现金
A36: 分配股利、利润或偿付利息支付的现金
A37: 其中：子公司支付少数股东的现金股利
A38: 支付其他与筹资活动有关的现金
A39: 其中：子公司减资支付给少数股东的现金
A40: 筹资活动现金流出小计 | C40: =C35+C36+C38 -> 0 | E40: =E35+E36+E38 -> 0 | F40: =F35+F36+F38 -> 0 | G40: =G35+G36+G38 -> 0 | H40: =H35+H36+H38 -> 0
A41: 筹资活动产生的现金流量净额 | C41: =C34-C40 -> 0 | E41: =E34-E40 -> 0 | F41: =F34-F40 -> 0 | G41: =G34-G40 -> 0 | H41: =H34-H40 -> 0
A42: 四、汇率变动对现金及现金等价物的影响
A43: 五、现金及现金等价物净增加额 | C43: =C15+C28+C41+C42 -> 0 | E43: =E15+E28+E41+E42 -> 0 | F43: =F15+F28+F41+F42 -> 0 | G43: =G15+G28+G41+G42 -> 0 | H43: =H15+H28+H41+H42 -> 0
A44: 加：期初现金及现金等价物余额
A45: 六、期末现金及现金等价物余额 | C45: =C43+C44 -> 0 | E45: =E43+E44 -> 0 | F45: =F43+F44 -> 0 | G45: =G43+G44 -> 0 | H45: =H43+H44 -> 0
A46: 公司法定代表人： 主管会计工作的公司负责人： | C46: 公司会计机构负责人：
A50: 说明：根据“关于2018年度一般企业财务报表格式有关问题的解读”：企业实际收到的政府补助，无论是与资产相关还是与收益相关，在编制现金流量表时均作为经营活动产生的现金流量列报。

Sheet RP 005
B1: 合并股东（或所有者）权益变动表 | O1: 合并股东（或所有者）权益变动表
A3: =基础信息!B6 -> 0 | N3: 单位：人民币元 | AA3: 单位：人民币元
A4: 项 目 | B4: 20X8年度 | O4: 20X7年度
B5: 归属于母公司股东权益 | M5: 少数股东 权益 | N5: 股东（或所有者）权益 合计 | O5: 归属于母公司股东权益 | Z5: 少数股东 权益 | AA5: 股东（或所有者）权益 合计
B6: 股本 | C6: 其他权益工具（不适用的删除） | F6: 资本公积 | G6: 减：库存股 | H6: 其他综合收益 | I6: 专项储备 | J6: 盈余公积 | K6: 未分配利润 | L6: 其他 | O6: 股本 | P6: 其他权益工具（不适用的删除） | S6: 资本公积 | T6: 减：库存股 | U6: 其他综合收益 | V6: 专项储备 | W6: 盈余公积 | X6: 未分配利润 | Y6: 其他
C7: 优先股 | D7: 永续债 | E7: 其他 | P7: 优先股 | Q7: 永续债 | R7: 其他
A8: 一、上年年末余额 | B8: =O35 -> 0 | C8: =P35 -> 0 | D8: =Q35 -> 0 | E8: =R35 -> 0 | F8: =S35 -> 0 | G8: =T35 -> 0 | H8: =U35 -> 0 | I8: =V35 -> 0 | ... M8: =Z35 -> 0 | N8: =B8+C8+D8+E8+F8-G8+H8+I8+J8+K8+L8+M8 -> 0 | AA8: =O8+P8+Q8+R8+S8-T8+V8+W8+X8+Y8+Z8+U8 -> 0
A9: 加：会计政策变更 | B9: —— | C9: —— | D9: —— | E9: —— | F9: —— | G9: —— | H9: —— | I9: —— | J9: —— | K9: —— | L9: —— | M9: —— | N9: —— | AA9: =O9+P9+Q9+R9+S9-T9+V9+W9+X9+Y9+Z9+U9 -> 0
A10: 前期差错更正 | B10: —— | C10: —— | D10: —— | E10: —— | F10: —— | G10: —— | H10: —— | I10: —— | J10: —— | K10: —— | L10: —— | M10: —— | N10: —— | AA10: =O10+P10+Q10+R10+S10-T10+V10+W10+X10+Y10+Z10+U10 -> 0
A11: 其他 | N11: =B11+C11+D11+E11+F11-G11+H11+I11+J11+K11+L11+M11 -> 0 | AA11: =O11+P11+Q11+R11+S11-T11+V11+W11+X11+Y11+Z11+U11 -> 0
A12: 二、本年年初余额 | B12: =B8+B11 -> 0 | C12: =C8+C11 -> 0 | D12: =D8+D11 -> 0 | E12: =E8+E11 -> 0 | F12: =F8+F11 -> 0 | G12: =G8+G11 -> 0 | H12: =H8+H11 -> 0 | I12: =I8+I11 -> 0 | ... M12: =M8+M11 -> 0 | N12: =B12+C12+D12+E12+F12-G12+H12+I12+J12+K12+L12+M12 -> 0 | O12: =O8+O9+O10+O11 -> 0 | P12: =P8+P9+P10+P11 -> 0 | Q12: =Q8+Q9+Q10+Q11 -> 0 | R12: =R8+R9+R10+R11 -> 0 | S12: =S8+S9+S10+S11 -> 0 | T12: =T8+T9+T10+T11 -> 0 | U12: =U8+U9+U10+U11 -> 0 | V12: =V8+V9+V10+V11 -> 0 | ... Z12: =Z8+Z9+Z10+Z11 -> 0 | AA12: =O12+P12+Q12+R12+S12-T12+V12+W12+X12+Y12+Z12+U12 -> 0
A13: 三、本年增减变动金额（减少以“-”号填列） | B13: =B14+B15+B20+B24+B31 -> 0 | C13: =C14+C15+C20+C24+C31 -> 0 | D13: =D14+D15+D20+D24+D31 -> 0 | E13: =E14+E15+E20+E24+E31 -> 0 | F13: =F14+F15+F20+F24+F31 -> 0 | G13: =G14+G15+G20+G24+G31 -> 0 | H13: =H14+H15+H20+H24+H31 -> 0 | I13: =I14+I15+I20+I24+I31 -> 0 | ... M13: =M14+M15+M20+M24+M31 -> 0 | N13: =B13+C13+D13+E13+F13-G13+H13+I13+J13+K13+L13+M13 -> 0 | O13: =O14+O15+O20+O24+O31 -> 0 | P13: =P14+P15+P20+P24+P31 -> 0 | Q13: =Q14+Q15+Q20+Q24+Q31 -> 0 | R13: =R14+R15+R20+R24+R31 -> 0 | S13: =S14+S15+S20+S24+S31 -> 0 | T13: =T14+T15+T20+T24+T31 -> 0 | U13: =U14+U15+U20+U24+U31 -> 0 | V13: =V14+V15+V20+V24+V31 -> 0 | ... Z13: =Z14+Z15+Z20+Z24+Z31 -> 0 | AA13: =O13+P13+Q13+R13+S13-T13+V13+W13+X13+Y13+Z13+U13 -> 0
A14: （一）综合收益总额 | N14: =B14+C14+D14+E14+F14-G14+H14+I14+J14+K14+L14+M14 -> 0 | AA14: =O14+P14+Q14+R14+S14-T14+V14+W14+X14+Y14+Z14+U14 -> 0
A15: （二）股东（或所有者）投入和减少资本 | B15: =SUM(B16:B19) -> 0 | C15: =SUM(C16:C19) -> 0 | D15: =SUM(D16:D19) -> 0 | E15: =SUM(E16:E19) -> 0 | F15: =SUM(F16:F19) -> 0 | G15: =SUM(G16:G19) -> 0 | H15: =SUM(H16:H19) -> 0 | I15: =SUM(I16:I19) -> 0 | ... M15: =SUM(M16:M19) -> 0 | N15: =B15+C15+D15+E15+F15-G15+H15+I15+J15+K15+L15+M15 -> 0 | O15: =SUM(O16:O19) -> 0 | P15: =SUM(P16:P19) -> 0 | Q15: =SUM(Q16:Q19) -> 0 | R15: =SUM(R16:R19) -> 0 | S15: =SUM(S16:S19) -> 0 | T15: =SUM(T16:T19) -> 0 | U15: =SUM(U16:U19) -> 0 | V15: =SUM(V16:V19) -> 0 | ... Z15: =SUM(Z16:Z19) -> 0 | AA15: =O15+P15+Q15+R15+S15-T15+V15+W15+X15+Y15+Z15+U15 -> 0
A16: 1．股东投入资本 | N16: =B16+C16+D16+E16+F16-G16+H16+I16+J16+K16+L16+M16 -> 0 | AA16: =O16+P16+Q16+R16+S16-T16+V16+W16+X16+Y16+Z16+U16 -> 0
A17: 2. 其他权益工具持有者投入资本（不适用的删除） | N17: =B17+C17+D17+E17+F17-G17+H17+I17+J17+K17+L17+M17 -> 0 | AA17: =O17+P17+Q17+R17+S17-T17+V17+W17+X17+Y17+Z17+U17 -> 0
A18: 3．股份支付计入股东权益的金额 | N18: =B18+C18+D18+E18+F18-G18+H18+I18+J18+K18+L18+M18 -> 0 | AA18: =O18+P18+Q18+R18+S18-T18+V18+W18+X18+Y18+Z18+U18 -> 0
A19: 4．其他 | N19: =B19+C19+D19+E19+F19-G19+H19+I19+J19+K19+L19+M19 -> 0 | AA19: =O19+P19+Q19+R19+S19-T19+V19+W19+X19+Y19+Z19+U19 -> 0
A20: （三）利润分配 | B20: =SUM(B21:B23) -> 0 | C20: =SUM(C21:C23) -> 0 | D20: =SUM(D21:D23) -> 0 | E20: =SUM(E21:E23) -> 0 | F20: =SUM(F21:F23) -> 0 | G20: =SUM(G21:G23) -> 0 | H20: =SUM(H21:H23) -> 0 | I20: =SUM(I21:I23) -> 0 | ... M20: =SUM(M21:M23) -> 0 | N20: =B20+C20+D20+E20+F20-G20+H20+I20+J20+K20+L20+M20 -> 0 | O20: =SUM(O21:O23) -> 0 | P20: =SUM(P21:P23) -> 0 | Q20: =SUM(Q21:Q23) -> 0 | R20: =SUM(R21:R23) -> 0 | S20: =SUM(S21:S23) -> 0 | T20: =SUM(T21:T23) -> 0 | U20: =SUM(U21:U23) -> 0 | V20: =SUM(V21:V23) -> 0 | ... Z20: =SUM(Z21:Z23) -> 0 | AA20: =O20+P20+Q20+R20+S20-T20+V20+W20+X20+Y20+Z20+U20 -> 0
A21: 1．提取盈余公积 | N21: =B21+C21+D21+E21+F21-G21+H21+I21+J21+K21+L21+M21 -> 0 | AA21: =O21+P21+Q21+R21+S21-T21+V21+W21+X21+Y21+Z21+U21 -> 0
A22: 2．对股东（或所有者）的分配 | N22: =B22+C22+D22+E22+F22-G22+H22+I22+J22+K22+L22+M22 -> 0 | AA22: =O22+P22+Q22+R22+S22-T22+V22+W22+X22+Y22+Z22+U22 -> 0
A23: 3．其他 | N23: =B23+C23+D23+E23+F23-G23+H23+I23+J23+K23+L23+M23 -> 0 | AA23: =O23+P23+Q23+R23+S23-T23+V23+W23+X23+Y23+Z23+U23 -> 0
A24: （四）股东权益内部结转 | B24: =SUM(B25:B30) -> 0 | C24: =SUM(C25:C30) -> 0 | D24: =SUM(D25:D30) -> 0 | E24: =SUM(E25:E30) -> 0 | F24: =SUM(F25:F30) -> 0 | G24: =SUM(G25:G30) -> 0 | H24: =SUM(H25:H30) -> 0 | I24: =SUM(I25:I30) -> 0 | ... M24: =SUM(M25:M30) -> 0 | N24: =B24+C24+D24+E24+F24-G24+H24+I24+J24+K24+L24+M24 -> 0 | O24: =SUM(O25:O30) -> 0 | P24: =SUM(P25:P30) -> 0 | Q24: =SUM(Q25:Q30) -> 0 | R24: =SUM(R25:R30) -> 0 | S24: =SUM(S25:S30) -> 0 | T24: =SUM(T25:T30) -> 0 | U24: =SUM(U25:U30) -> 0 | V24: =SUM(V25:V30) -> 0 | ... Z24: =SUM(Z25:Z30) -> 0 | AA24: =O24+P24+Q24+R24+S24-T24+V24+W24+X24+Y24+Z24+U24 -> 0
A25: 1．资本公积转增股本（或资本） | N25: =B25+C25+D25+E25+F25-G25+H25+I25+J25+K25+L25+M25 -> 0 | AA25: =O25+P25+Q25+R25+S25-T25+V25+W25+X25+Y25+Z25+U25 -> 0
A26: 2．盈余公积转增股本（或资本） | N26: =B26+C26+D26+E26+F26-G26+H26+I26+J26+K26+L26+M26 -> 0 | AA26: =O26+P26+Q26+R26+S26-T26+V26+W26+X26+Y26+Z26+U26 -> 0
A27: 3．盈余公积弥补亏损 | N27: =B27+C27+D27+E27+F27-G27+H27+I27+J27+K27+L27+M27 -> 0 | AA27: =O27+P27+Q27+R27+S27-T27+V27+W27+X27+Y27+Z27+U27 -> 0
A28: 4. 设定受益计划变动额结转留存收益（不适用的删除） | N28: =B28+C28+D28+E28+F28-G28+H28+I28+J28+K28+L28+M28 -> 0 | AA28: =O28+P28+Q28+R28+S28-T28+V28+W28+X28+Y28+Z28+U28 -> 0
A29: 5．其他综合收益结转留存收益
A30: 6．其他 | N30: =B30+C30+D30+E30+F30-G30+H30+I30+J30+K30+L30+M30 -> 0 | AA30: =O30+P30+Q30+R30+S30-T30+V30+W30+X30+Y30+Z30+U30 -> 0
A31: （五）专项储备 | B31: =B32+B33 -> 0 | C31: =C32+C33 -> 0 | D31: =D32+D33 -> 0 | E31: =E32+E33 -> 0 | F31: =F32+F33 -> 0 | G31: =G32+G33 -> 0 | H31: =H32+H33 -> 0 | I31: =SUM(I32:I33) -> 0 | J31: =SUM(J32:J33) -> 0 | K31: =SUM(K32:K33) -> 0 | L31: =SUM(L32:L33) -> 0 | M31: =SUM(M32:M33) -> 0 | N31: =B31+C31+D31+E31+F31-G31+H31+I31+J31+K31+L31+M31 -> 0 | O31: =SUM(O32:O33) -> 0 | P31: =SUM(P32:P33) -> 0 | Q31: =SUM(Q32:Q33) -> 0 | R31: =SUM(R32:R33) -> 0 | S31: =SUM(S32:S33) -> 0 | T31: =SUM(T32:T33) -> 0 | U31: =SUM(U32:U33) -> 0 | V31: =SUM(V32:V33) -> 0 | ... Z31: =SUM(Z32:Z33) -> 0 | AA31: =O31+P31+Q31+R31+S31-T31+V31+W31+X31+Y31+Z31+U31 -> 0
A32: 1．本期提取 | N32: =B32+C32+D32+E32+F32-G32+H32+I32+J32+K32+L32+M32 -> 0 | AA32: =O32+P32+Q32+R32+S32-T32+V32+W32+X32+Y32+Z32+U32 -> 0
A33: 2．本期使用（以负号填列） | N33: =B33+C33+D33+E33+F33-G33+H33+I33+J33+K33+L33+M33 -> 0 | AA33: =O33+P33+Q33+R33+S33-T33+V33+W33+X33+Y33+Z33+U33 -> 0
A34: （六）其他 | N34: =B34+C34+D34+E34+F34-G34+H34+I34+J34+K34+L34+M34 -> 0 | Z34: =SUM(O34:Y34) -> 0 | AA34: =SUM(P34:Z34) -> 0 | AB34: 备忘录第3号二、6
A35: 四、本年年末余额 | B35: =B12+B13 -> 0 | C35: =C12+C13 -> 0 | D35: =D12+D13 -> 0 | E35: =E12+E13 -> 0 | F35: =F12+F13 -> 0 | G35: =G12+G13 -> 0 | H35: =H12+H13 -> 0 | I35: =I12+I13 -> 0 | ... O35: =O12+O13 -> 0 | P35: 0 | Q35: 0 | R35: 0 | S35: =S12+S13 -> 0 | T35: =T12+T13 -> 0 | U35: 0 | V35: =V12+V13 -> 0 | W35: =W12+W13 -> 0 | X35: =X12+X13 -> 0 | Y35: =Y12+Y13 -> 0 | Z35: =Z12+Z13 -> 0 | AA35: =AA12+AA13 -> 0
A37: 公司法定代表人： | F37: 主管会计工作的公司负责人： | L37: 公司会计机构负责人： | S37: 主管会计工作的公司负责人： | Y37: 公司会计机构负责人：

Sheet RP 006
A1: 公司名称 | B1: =基础信息!B6 -> 0
A2: 财务期间 | B2: =基础信息!B9 -> 0 | J2: 准则差异调整-政策调整 | R2: 准则差异调整-列报调整
A3: 内容 | B3: 准则差异调节表
A4: 项目 | B4: HKFRS | C4: 准则列报调整 | D4: 准则政策调整调整 | E4: PRC | F4: 序号 | G4: 调整事项 | H4: 一级科目 | I4: 二级科目 | J4: 借方金额 | K4: 贷方金额 | L4: 备注 | M4: 索引号 | N4: 序号 | O4: 调整事项 | P4: 一级科目 | Q4: 二级科目 | R4: 借方金额 | S4: 贷方金额 | T4: 备注 | U4: 索引号
A5: 流动资产:
A6: 货币资金 | C6: =SUMIF($P:$P,A6,R:R)-SUMIF($P:$P,A6,S:S) -> 0 | D6: =SUMIF($H:$H,A6,J:J)-SUMIF($H:$H,A6,K:K) -> 0 | E6: =SUM(B6:D6) -> 0
A7: 交易性金融资产 | C7: =SUMIF($P:$P,A7,R:R)-SUMIF($P:$P,A7,S:S) -> 0 | D7: =SUMIF($H:$H,A7,J:J)-SUMIF($H:$H,A7,K:K) -> 0 | E7: =SUM(B7:D7) -> 0
A8: 以公允价值计量且其变动计入当期损益的金融资产 | C8: =SUMIF($P:$P,A8,R:R)-SUMIF($P:$P,A8,S:S) -> 0 | D8: =SUMIF($H:$H,A8,J:J)-SUMIF($H:$H,A8,K:K) -> 0 | E8: =SUM(B8:D8) -> 0
A9: 衍生金融资产 | C9: =SUMIF($P:$P,A9,R:R)-SUMIF($P:$P,A9,S:S) -> 0 | D9: =SUMIF($H:$H,A9,J:J)-SUMIF($H:$H,A9,K:K) -> 0 | E9: =SUM(B9:D9) -> 0
A10: 应收票据 | C10: =SUMIF($P:$P,A10,R:R)-SUMIF($P:$P,A10,S:S) -> 0 | D10: =SUMIF($H:$H,A10,J:J)-SUMIF($H:$H,A10,K:K) -> 0 | E10: =SUM(B10:D10) -> 0
A11: 应收票据坏帐准备 | C11: =-SUMIF($P:$P,A11,R:R)+SUMIF($P:$P,A11,S:S) -> 0 | D11: =-SUMIF($H:$H,A11,J:J)+SUMIF($H:$H,A11,K:K) -> 0 | E11: =SUM(B11:D11) -> 0
A12: 应收票据净值 | B12: =B10-B11 -> 0 | C12: =C10-C11 -> 0 | D12: =D10-D11 -> 0 | E12: =E10-E11 -> 0
A13: 应收账款 | C13: =SUMIF($P:$P,A13,R:R)-SUMIF($P:$P,A13,S:S) -> 0 | D13: =SUMIF($H:$H,A13,J:J)-SUMIF($H:$H,A13,K:K) -> 0 | E13: =SUM(B13:D13) -> 0
A14: 应收账款坏帐准备 | C14: =-SUMIF($P:$P,A14,R:R)+SUMIF($P:$P,A14,S:S) -> 0 | D14: =-SUMIF($H:$H,A14,J:J)+SUMIF($H:$H,A14,K:K) -> 0 | E14: =SUM(B14:D14) -> 0
A15: 应收账款净值 | B15: =B13-B14 -> 0 | C15: =C13-C14 -> 0 | D15: =D13-D14 -> 0 | E15: =E13-E14 -> 0
A16: 应收款项融资 | C16: =SUMIF($P:$P,A16,R:R)-SUMIF($P:$P,A16,S:S) -> 0 | D16: =SUMIF($H:$H,A16,J:J)-SUMIF($H:$H,A16,K:K) -> 0 | E16: =SUM(B16:D16) -> 0
A17: 应收款项融资坏账准备 | C17: =-SUMIF($P:$P,A17,R:R)+SUMIF($P:$P,A17,S:S) -> 0 | D17: =-SUMIF($H:$H,A17,J:J)+SUMIF($H:$H,A17,K:K) -> 0 | E17: =SUM(B17:D17) -> 0
A18: 应收款项融资净值 | B18: =B16-B17 -> 0 | C18: =C16-C17 -> 0 | D18: =D16-D17 -> 0 | E18: =E16-E17 -> 0
A19: 预付款项 | C19: =SUMIF($P:$P,A19,R:R)-SUMIF($P:$P,A19,S:S) -> 0 | D19: =SUMIF($H:$H,A19,J:J)-SUMIF($H:$H,A19,K:K) -> 0 | E19: =SUM(B19:D19) -> 0
A20: 其他应收款 | C20: =SUMIF($P:$P,A20,R:R)-SUMIF($P:$P,A20,S:S) -> 0 | D20: =SUMIF($H:$H,A20,J:J)-SUMIF($H:$H,A20,K:K) -> 0 | E20: =SUM(B20:D20) -> 0
A21: 其他应收款坏帐准备 | C21: =-SUMIF($P:$P,A21,R:R)+SUMIF($P:$P,A21,S:S) -> 0 | D21: =-SUMIF($H:$H,A21,J:J)+SUMIF($H:$H,A21,K:K) -> 0 | E21: =SUM(B21:D21) -> 0
A22: 其他应收款净值 | B22: =B20-B21 -> 0 | C22: =C20-C21 -> 0 | D22: =D20-D21 -> 0 | E22: =E20-E21 -> 0
A23: 存货 | C23: =SUMIF($P:$P,A23,R:R)-SUMIF($P:$P,A23,S:S) -> 0 | D23: =SUMIF($H:$H,A23,J:J)-SUMIF($H:$H,A23,K:K) -> 0 | E23: =SUM(B23:D23) -> 0
A24: 存货跌价准备 | C24: =-SUMIF($P:$P,A24,R:R)+SUMIF($P:$P,A24,S:S) -> 0 | D24: =-SUMIF($H:$H,A24,J:J)+SUMIF($H:$H,A24,K:K) -> 0 | E24: =SUM(B24:D24) -> 0
A25: 存货净值 | B25: =B23-B24 -> 0 | C25: =C23-C24 -> 0 | D25: =D23-D24 -> 0 | E25: =E23-E24 -> 0
A26: 合同资产 | C26: =C24-C25 -> 0 | D26: =D24-D25 -> 0 | E26: =E24-E25 -> 0
A27: 合同资产减值准备 | C27: =C25-C26 -> 0 | D27: =D25-D26 -> 0 | E27: =E25-E26 -> 0
A28: 合同资产净值 | B28: =B26-B27 -> 0 | C28: =C26-C27 -> 0 | D28: =D26-D27 -> 0 | E28: =E26-E27 -> 0
A29: 持有待售资产 | C29: =C24-C25 -> 0 | D29: =D24-D25 -> 0 | E29: =E24-E25 -> 0
A30: 一年内到期的非流动资产 | C30: =SUMIF($P:$P,A30,R:R)-SUMIF($P:$P,A30,S:S) -> 0 | D30: =SUMIF($H:$H,A30,J:J)-SUMIF($H:$H,A30,K:K) -> 0 | E30: =SUM(B30:D30) -> 0
A31: 待摊费用 | C31: =SUMIF($P:$P,A31,R:R)-SUMIF($P:$P,A31,S:S) -> 0 | D31: =SUMIF($H:$H,A31,J:J)-SUMIF($H:$H,A31,K:K) -> 0 | E31: =SUM(B31:D31) -> 0
A32: 内部应收 | C32: =SUMIF($P:$P,A32,R:R)-SUMIF($P:$P,A32,S:S) -> 0 | D32: =SUMIF($H:$H,A32,J:J)-SUMIF($H:$H,A32,K:K) -> 0 | E32: =SUM(B32:D32) -> 0
A33: 材料采购 | C33: =SUMIF($P:$P,A33,R:R)-SUMIF($P:$P,A33,S:S) -> 0 | D33: =SUMIF($H:$H,A33,J:J)-SUMIF($H:$H,A33,K:K) -> 0 | E33: =SUM(B33:D33) -> 0
A34: 公司间应收 | C34: =SUMIF($P:$P,A34,R:R)-SUMIF($P:$P,A34,S:S) -> 0 | D34: =SUMIF($H:$H,A34,J:J)-SUMIF($H:$H,A34,K:K) -> 0 | E34: =SUM(B34:D34) -> 0
A35: 应收下级单位利润 | C35: =SUMIF($P:$P,A35,R:R)-SUMIF($P:$P,A35,S:S) -> 0 | D35: =SUMIF($H:$H,A35,J:J)-SUMIF($H:$H,A35,K:K) -> 0 | E35: =SUM(B35:D35) -> 0
A36: 应收采购款 | C36: =SUMIF($P:$P,A36,R:R)-SUMIF($P:$P,A36,S:S) -> 0 | D36: =SUMIF($H:$H,A36,J:J)-SUMIF($H:$H,A36,K:K) -> 0 | E36: =SUM(B36:D36) -> 0
A37: 应收采购款坏帐准备 | C37: =-SUMIF($P:$P,A37,R:R)+SUMIF($P:$P,A37,S:S) -> 0 | D37: =-SUMIF($H:$H,A37,J:J)+SUMIF($H:$H,A37,K:K) -> 0 | E37: =SUM(B37:D37) -> 0
A38: 应收采购款净额 | B38: =B36-B37 -> 0 | C38: =C36-C37 -> 0 | D38: =D36-D37 -> 0 | E38: =E36-E37 -> 0
A39: 空行 | C39: =SUMIF($P:$P,A39,R:R)-SUMIF($P:$P,A39,S:S) -> 0 | D39: =SUMIF($H:$H,A39,J:J)-SUMIF($H:$H,A39,K:K) -> 0 | E39: =SUM(B39:D39) -> 0
A40: 空行 | C40: =SUMIF($P:$P,A40,R:R)-SUMIF($P:$P,A40,S:S) -> 0 | D40: =SUMIF($H:$H,A40,J:J)-SUMIF($H:$H,A40,K:K) -> 0 | E40: =SUM(B40:D40) -> 0
A41: 其他流动资产 | C41: =SUMIF($P:$P,A41,R:R)-SUMIF($P:$P,A41,S:S) -> 0 | D41: =SUMIF($H:$H,A41,J:J)-SUMIF($H:$H,A41,K:K) -> 0 | E41: =SUM(B41:D41) -> 0
A42: 流动资产合计 | B42: =SUM(B6:B41)-B10-B11-B20-B21-B23-B24-B36-B37 -> 0 | C42: =SUM(C6:C41)-C10-C11-C20-C21-C23-C24-C36-C37 -> 0 | D42: =SUM(D6:D41)-D10-D11-D20-D21-D23-D24-D36-D37 -> 0 | E42: =SUM(E6:E41)-E10-E11-E20-E21-E23-E24-E36-E37 -> 0
E43: =SUM(B43:D43) -> 0
A44: 非流动资产 | C44: =SUMIF($P:$P,A44,R:R)-SUMIF($P:$P,A44,S:S) -> 0 | D44: =SUMIF($H:$H,A44,J:J)-SUMIF($H:$H,A44,K:K) -> 0 | E44: =SUM(B44:D44) -> 0
A45: 债权投资 | C45: =SUMIF($P:$P,A45,R:R)-SUMIF($P:$P,A45,S:S) -> 0 | D45: =SUMIF($H:$H,A45,J:J)-SUMIF($H:$H,A45,K:K) -> 0 | E45: =SUM(B45:D45) -> 0
A46: 可供出售金融资产 | C46: =SUMIF($P:$P,A46,R:R)-SUMIF($P:$P,A46,S:S) -> 0 | D46: =SUMIF($H:$H,A46,J:J)-SUMIF($H:$H,A46,K:K) -> 0 | E46: =SUM(B46:D46) -> 0
A47: 持有至到期投资 | C47: =SUMIF($P:$P,A47,R:R)-SUMIF($P:$P,A47,S:S) -> 0 | D47: =SUMIF($H:$H,A47,J:J)-SUMIF($H:$H,A47,K:K) -> 0 | E47: =SUM(B47:D47) -> 0
A48: 长期应收款 | C48: =SUMIF($P:$P,A48,R:R)-SUMIF($P:$P,A48,S:S) -> 0 | D48: =SUMIF($H:$H,A48,J:J)-SUMIF($H:$H,A48,K:K) -> 0 | E48: =SUM(B48:D48) -> 0
A49: 设定受益计划净资产 | C49: =SUMIF($P:$P,A49,R:R)-SUMIF($P:$P,A49,S:S) -> 0 | D49: =SUMIF($H:$H,A49,J:J)-SUMIF($H:$H,A49,K:K) -> 0 | E49: =SUM(B49:D49) -> 0
A50: 长期股权投资 | C50: =SUMIF($P:$P,A50,R:R)-SUMIF($P:$P,A50,S:S) -> 0 | D50: =SUMIF($H:$H,A50,J:J)-SUMIF($H:$H,A50,K:K) -> 0 | E50: =SUM(B50:D50) -> 0
A51: 长期投资减值准备 | C51: =-SUMIF($P:$P,A51,R:R)+SUMIF($P:$P,A51,S:S) -> 0 | D51: =-SUMIF($H:$H,A51,J:J)+SUMIF($H:$H,A51,K:K) -> 0 | E51: =SUM(B51:D51) -> 0
A52: 长期股权投资净值 | B52: =B50-B51 -> 0 | C52: =C50-C51 -> 0 | D52: =D50-D51 -> 0 | E52: =E50-E51 -> 0
A53: 其他权益工具投资 | C53: =C51-C52 -> 0 | D53: =D51-D52 -> 0 | E53: =E51-E52 -> 0
A54: 其他非流动金融资产 | C54: =C52-C53 -> 0 | D54: =D52-D53 -> 0 | E54: =E52-E53 -> 0
A55: 投资性房地产 | C55: =SUMIF($P:$P,A55,R:R)-SUMIF($P:$P,A55,S:S) -> 0 | D55: =SUMIF($H:$H,A55,J:J)-SUMIF($H:$H,A55,K:K) -> 0 | E55: =SUM(B55:D55) -> 0
A56: 投资性房地产减值准备 | C56: =-SUMIF($P:$P,A56,R:R)+SUMIF($P:$P,A56,S:S) -> 0 | D56: =-SUMIF($H:$H,A56,J:J)+SUMIF($H:$H,A56,K:K) -> 0 | E56: =SUM(B56:D56) -> 0
A57: 投资行房地产净值 | B57: =B55-B56 -> 0 | C57: =C55-C56 -> 0 | D57: =D55-D56 -> 0 | E57: =E55-E56 -> 0
A58: 固定资产原价 | C58: =SUMIF($P:$P,A58,R:R)-SUMIF($P:$P,A58,S:S) -> 0 | D58: =SUMIF($H:$H,A58,J:J)-SUMIF($H:$H,A58,K:K) -> 0 | E58: =SUM(B58:D58) -> 0
A59: 累计折旧 | C59: =-SUMIF($P:$P,A59,R:R)+SUMIF($P:$P,A59,S:S) -> 0 | D59: =-SUMIF($H:$H,A59,J:J)+SUMIF($H:$H,A59,K:K) -> 0 | E59: =SUM(B59:D59) -> 0
A60: 固定资产净值 | B60: =B58-B59 -> 0 | C60: =C58-C59 -> 0 | D60: =D58-D59 -> 0 | E60: =SUM(B60:D60) -> 0
A61: 固定资产减值准备 | C61: =-SUMIF($P:$P,A61,R:R)+SUMIF($P:$P,A61,S:S) -> 0 | D61: =-SUMIF($H:$H,A61,J:J)+SUMIF($H:$H,A61,K:K) -> 0 | E61: =SUM(B61:D61) -> 0
A62: 固定资产净额 | B62: =B60-B61 -> 0 | C62: =C60-C61 -> 0 | D62: =D60-D61 -> 0 | E62: =E60-E61 -> 0
A63: 在建工程 | C63: =SUMIF($P:$P,A63,R:R)-SUMIF($P:$P,A63,S:S) -> 0 | D63: =SUMIF($H:$H,A63,J:J)-SUMIF($H:$H,A63,K:K) -> 0 | E63: =SUM(B63:D63) -> 0
A64: 生产性生物资产 | C64: =SUMIF($P:$P,A64,R:R)-SUMIF($P:$P,A64,S:S) -> 0 | D64: =SUMIF($H:$H,A64,J:J)-SUMIF($H:$H,A64,K:K) -> 0 | E64: =SUM(B64:D64) -> 0
A65: 油气资产 | C65: =SUMIF($P:$P,A65,R:R)-SUMIF($P:$P,A65,S:S) -> 0 | D65: =SUMIF($H:$H,A65,J:J)-SUMIF($H:$H,A65,K:K) -> 0 | E65: =SUM(B65:D65) -> 0
A66: 无形资产 | C66: =SUMIF($P:$P,A66,R:R)-SUMIF($P:$P,A66,S:S) -> 0 | D66: =SUMIF($H:$H,A66,J:J)-SUMIF($H:$H,A66,K:K) -> 0 | E66: =SUM(B66:D66) -> 0
A67: 无形资产减值准备 | C67: =-SUMIF($P:$P,A67,R:R)+SUMIF($P:$P,A67,S:S) -> 0 | D67: =-SUMIF($H:$H,A67,J:J)+SUMIF($H:$H,A67,K:K) -> 0 | E67: =SUM(B67:D67) -> 0
A68: 无形资产净值 | B68: =B66-B67 -> 0 | C68: =C66-C67 -> 0 | D68: =D66-D67 -> 0 | E68: =E66-E67 -> 0
A69: 开发支出 | C69: =SUMIF($P:$P,A69,R:R)-SUMIF($P:$P,A69,S:S) -> 0 | D69: =SUMIF($H:$H,A69,J:J)-SUMIF($H:$H,A69,K:K) -> 0 | E69: =SUM(B69:D69) -> 0
A70: 商誉 | C70: =SUMIF($P:$P,A70,R:R)-SUMIF($P:$P,A70,S:S) -> 0 | D70: =SUMIF($H:$H,A70,J:J)-SUMIF($H:$H,A70,K:K) -> 0 | E70: =SUM(B70:D70) -> 0
A71: 长期待摊费用 | C71: =SUMIF($P:$P,A71,R:R)-SUMIF($P:$P,A71,S:S) -> 0 | D71: =SUMIF($H:$H,A71,J:J)-SUMIF($H:$H,A71,K:K) -> 0 | E71: =SUM(B71:D71) -> 0
A72: 递延所得税资产 | C72: =SUMIF($P:$P,A72,R:R)-SUMIF($P:$P,A72,S:S) -> 0 | D72: =SUMIF($H:$H,A72,J:J)-SUMIF($H:$H,A72,K:K) -> 0 | E72: =SUM(B72:D72) -> 0
A73: 其他非流动资产 | C73: =SUMIF($P:$P,A73,R:R)-SUMIF($P:$P,A73,S:S) -> 0 | D73: =SUMIF($H:$H,A73,J:J)-SUMIF($H:$H,A73,K:K) -> 0 | E73: =SUM(B73:D73) -> 0
A74: 非流动资产合计 | B74: =B46+B47+B48+B52+B57+B62+B63+B64+B65+B68+B69+B70+B71+B72+B73 -> 0 | C74: =C46+C47+C48+C52+C57+C62+C63+C64+C65+C68+C69+C70+C71+C72+C73 -> 0 | D74: =D46+D47+D48+D52+D57+D62+D63+D64+D65+D68+D69+D70+D71+D72+D73 -> 0 | E74: =E46+E47+E48+E52+E57+E62+E63+E64+E65+E68+E69+E70+E71+E72+E73 -> 0
A75: 资产总计 | B75: =B42+B74 -> 0 | C75: =C42+C74 -> 0 | D75: =D42+D74 -> 0 | E75: =E42+E74 -> 0
A76: 公司名称 | B76: =基础信息!B6 -> 0
A77: 财务期间 | B77: =日期2 -> 0 | J77: 准则差异调整-政策调整 | R77: 准则差异调整-列报调整
A78: 内容 | B78: 准则差异调节表
A79: 项目 | B79: 原报数 | D79: 准则差异调整 | E79: 审定数 | F79: 序号 | G79: 调整事项 | H79: 一级科目 | I79: 二级科目 | J79: 借方金额 | K79: 贷方金额 | L79: 备注 | M79: 索引号 | N79: 序号 | O79: 调整事项 | P79: 一级科目 | Q79: 二级科目 | R79: 借方金额 | S79: 贷方金额 | T79: 备注 | U79: 索引号
A80: 流动负债: | C80: =-SUMIF(A80,$P:$P,R:R)+SUMIF(A80,$P:$P,S:S) -> 0 | D80: =-SUMIF(A80,$H:$H,J:J)+SUMIF(A80,$H:$H,K:K) -> 0 | E80: =SUM(B80:D80) -> 0
A81: 短期借款 | C81: =-SUMIF($P:$P,A81,R:R)+SUMIF($P:$P,A81,S:S) -> 0 | D81: =-SUMIF($H:$H,A81,J:J)+SUMIF($H:$H,A81,K:K) -> 0 | E81: =SUM(B81:D81) -> 0
A82: 交易性金融负债 | C82: =-SUMIF($P:$P,A82,R:R)+SUMIF($P:$P,A82,S:S) -> 0 | D82: =-SUMIF($H:$H,A82,J:J)+SUMIF($H:$H,A82,K:K) -> 0 | E82: =SUM(B82:D82) -> 0
A83: 以公允价值计量且其变动计入当期损益的金融负债 | C83: =-SUMIF($P:$P,A83,R:R)+SUMIF($P:$P,A83,S:S) -> 0 | D83: =-SUMIF($H:$H,A83,J:J)+SUMIF($H:$H,A83,K:K) -> 0 | E83: =SUM(B83:D83) -> 0
A84: 衍生金融负债 | C84: =-SUMIF($P:$P,A84,R:R)+SUMIF($P:$P,A84,S:S) -> 0 | D84: =-SUMIF($H:$H,A84,J:J)+SUMIF($H:$H,A84,K:K) -> 0 | E84: =SUM(B84:D84) -> 0
A85: 应付票据 | C85: =-SUMIF($P:$P,A85,R:R)+SUMIF($P:$P,A85,S:S) -> 0 | D85: =-SUMIF($H:$H,A85,J:J)+SUMIF($H:$H,A85,K:K) -> 0 | E85: =SUM(B85:D85) -> 0
A86: 应付账款 | C86: =-SUMIF($P:$P,A86,R:R)+SUMIF($P:$P,A86,S:S) -> 0 | D86: =-SUMIF($H:$H,A86,J:J)+SUMIF($H:$H,A86,K:K) -> 0 | E86: =SUM(B86:D86) -> 0
A87: 预收款项 | C87: =-SUMIF($P:$P,A87,R:R)+SUMIF($P:$P,A87,S:S) -> 0 | D87: =-SUMIF($H:$H,A87,J:J)+SUMIF($H:$H,A87,K:K) -> 0 | E87: =SUM(B87:D87) -> 0
A88: 合同负债 | C88: =-SUMIF($P:$P,A88,R:R)+SUMIF($P:$P,A88,S:S) -> 0 | D88: =-SUMIF($H:$H,A88,J:J)+SUMIF($H:$H,A88,K:K) -> 0 | E88: =SUM(B88:D88) -> 0
A89: 应付职工薪酬 | C89: =-SUMIF($P:$P,A89,R:R)+SUMIF($P:$P,A89,S:S) -> 0 | D89: =-SUMIF($H:$H,A89,J:J)+SUMIF($H:$H,A89,K:K) -> 0 | E89: =SUM(B89:D89) -> 0
A90: 应交税费 | C90: =-SUMIF($P:$P,A90,R:R)+SUMIF($P:$P,A90,S:S) -> 0 | D90: =-SUMIF($H:$H,A90,J:J)+SUMIF($H:$H,A90,K:K) -> 0 | E90: =SUM(B90:D90) -> 0
A91: 其他应付款 | C91: =-SUMIF($P:$P,A91,R:R)+SUMIF($P:$P,A91,S:S) -> 0 | D91: =-SUMIF($H:$H,A91,J:J)+SUMIF($H:$H,A91,K:K) -> 0 | E91: =SUM(B91:D91) -> 0
A92: 持有待售负债 | C92: =-SUMIF($P:$P,A92,R:R)+SUMIF($P:$P,A92,S:S) -> 0 | D92: =-SUMIF($H:$H,A92,J:J)+SUMIF($H:$H,A92,K:K) -> 0 | E92: =SUM(B92:D92) -> 0
... A102: 其他流动负债 | C102: =-SUMIF($P:$P,A102,R:R)+SUMIF($P:$P,A102,S:S) -> 0 | D102: =-SUMIF($H:$H,A102,J:J)+SUMIF($H:$H,A102,K:K) -> 0 | E102: =SUM(B102:D102) -> 0
A103: 流动负债合计 | B103: =SUM(B81:B102) -> 0 | C103: =SUM(C81:C102) -> 0 | D103: =SUM(D81:D102) -> 0 | E103: =SUM(B103:D103) -> 0
A104: 非流动负债: | C104: =-SUMIF($P:$P,A104,R:R)+SUMIF($P:$P,A104,S:S) -> 0 | D104: =-SUMIF($H:$H,A104,J:J)+SUMIF($H:$H,A104,K:K) -> 0 | E104: =SUM(B104:D104) -> 0
A105: 长期借款 | C105: =-SUMIF($P:$P,A105,R:R)+SUMIF($P:$P,A105,S:S) -> 0 | D105: =-SUMIF($H:$H,A105,J:J)+SUMIF($H:$H,A105,K:K) -> 0 | E105: =SUM(B105:D105) -> 0
A106: 应付债券 | C106: =-SUMIF($P:$P,A106,R:R)+SUMIF($P:$P,A106,S:S) -> 0 | D106: =-SUMIF($H:$H,A106,J:J)+SUMIF($H:$H,A106,K:K) -> 0 | E106: =SUM(B106:D106) -> 0
A107: 长期应付款 | C107: =-SUMIF($P:$P,A107,R:R)+SUMIF($P:$P,A107,S:S) -> 0 | D107: =-SUMIF($H:$H,A107,J:J)+SUMIF($H:$H,A107,K:K) -> 0 | E107: =SUM(B107:D107) -> 0
A108: 长期应付职工薪酬 | C108: =-SUMIF($P:$P,A108,R:R)+SUMIF($P:$P,A108,S:S) -> 0 | D108: =-SUMIF($H:$H,A108,J:J)+SUMIF($H:$H,A108,K:K) -> 0 | E108: =SUM(B108:D108) -> 0
A109: 专项应付款 | C109: =-SUMIF($P:$P,A109,R:R)+SUMIF($P:$P,A109,S:S) -> 0 | D109: =-SUMIF($H:$H,A109,J:J)+SUMIF($H:$H,A109,K:K) -> 0 | E109: =SUM(B109:D109) -> 0
...

Sheet RP 007
A1: 公司名称 | B1: =基础信息!B6 -> 0
A2: 财务期间 | B2: =基础信息!B9 -> 0
A3: 内容 | B3: 集团间交易（销售、采购、费用）
A4: 销售交易对象 | B4: 交易项目
B5: 主营业务收入 | F5: 主营业务成本 | J5: 其他业务收入 | K5: 财务费用 | L5: 营业外收入
B6: 小计 | C6: 硬件 | D6: 服务 | E6: 软件及软件开发 | F6: 小计 | G6: 硬件 | H6: 服务 | I6: 软件及软件开发 | K6: 利息收入
B7: =SUM(C7:E7) -> 0 | F7: =SUM(G7:I7) -> 0
B8: =SUM(C8:E8) -> 0 | F8: =SUM(G8:I8) -> 0
B9: =SUM(C9:E9) -> 0 | F9: =SUM(G9:I9) -> 0
B10: =SUM(C10:E10) -> 0 | F10: =SUM(G10:I10) -> 0
B11: =SUM(C11:E11) -> 0 | F11: =SUM(G11:I11) -> 0
B12: =SUM(C12:E12) -> 0 | F12: =SUM(G12:I12) -> 0
B13: =SUM(C13:E13) -> 0 | F13: =SUM(G13:I13) -> 0
B14: =SUM(C14:E14) -> 0 | F14: =SUM(G14:I14) -> 0
B15: =SUM(C15:E15) -> 0 | F15: =SUM(G15:I15) -> 0
B16: =SUM(C16:E16) -> 0 | F16: =SUM(G16:I16) -> 0
B17: =SUM(C17:E17) -> 0 | F17: =SUM(G17:I17) -> 0
B18: =SUM(C18:E18) -> 0 | F18: =SUM(G18:I18) -> 0
... B20: =SUM(C20:E20) -> 0 | F20: =SUM(G20:I20) -> 0
A21: 合计 | B21: =SUM(B7:B20) -> 0 | C21: =SUM(C7:C20) -> 0 | D21: =SUM(D7:D20) -> 0 | E21: =SUM(E7:E20) -> 0 | F21: =SUM(F7:F20) -> 0 | G21: =SUM(G7:G20) -> 0 | H21: =SUM(H7:H20) -> 0 | I21: =SUM(I7:I20) -> 0 | ... L21: =SUM(L7:L20) -> 0
A23: 采购及费用交易对象 | B23: 交易项目
B24: 采购 | F24: 其他业务成本 | G24: 财务费用 | I24: 营业外支出
B25: 小计 | C25: 硬件 | D25: 服务 | E25: 软件及软件开发 | G25: 利息支出 | H25: 手续费
B26: =SUM(C26:E26) -> 0
B27: =SUM(C27:E27) -> 0
B28: =SUM(C28:E28) -> 0
B29: =SUM(C29:E29) -> 0
B30: =SUM(C30:E30) -> 0
B31: =SUM(C31:E31) -> 0
B32: =SUM(C32:E32) -> 0
B33: =SUM(C33:E33) -> 0
B34: =SUM(C34:E34) -> 0
B35: =SUM(C35:E35) -> 0
B36: =SUM(C36:E36) -> 0
B37: =SUM(C37:E37) -> 0
... B39: =SUM(C39:E39) -> 0
A40: 合计 | B40: =SUM(B26:B39) -> 0 | C40: =SUM(C26:C39) -> 0 | D40: =SUM(D26:D39) -> 0 | E40: =SUM(E26:E39) -> 0 | F40: =SUM(F26:F39) -> 0 | G40: =SUM(G26:G39) -> 0 | I40: =SUM(I26:I39) -> 0

Sheet RP 008
A1: 公司名称 | B1: =基础信息!B6 -> 0
A2: =基础信息!A9 -> 财务期间 | B2: =日期2 -> 0
A3: 内容 | B3: 集团内部往来余额
A4: 债权交易项目 | B4: 应收票据 | G4: 应收账款 | L4: 预付账款 | Q4: 其他应收款
B5: 小计 | C5: 1年以内 | D5: 1-2年 | E5: 2-3年 | F5: 3年以上 | G5: 小计 | H5: 1年以内 | I5: 1-2年 | J5: 2-3年 | K5: 3年以上 | L5: 小计 | M5: 1年以内 | N5: 1-2年 | O5: 2-3年 | P5: 3年以上 | Q5: 小计 | R5: 1年以内 | S5: 1-2年 | T5: 2-3年 | U5: 3年以上
G6: =SUM(H6:K6) -> 0 | Q6: =SUM(R6:U6) -> 0
G7: =SUM(H7:K7) -> 0 | Q7: =SUM(R7:U7) -> 0
G8: =SUM(H8:K8) -> 0 | Q8: =SUM(R8:U8) -> 0
G9: =SUM(H9:K9) -> 0 | Q9: =SUM(R9:U9) -> 0
G10: =SUM(H10:K10) -> 0 | Q10: =SUM(R10:U10) -> 0
G11: =SUM(H11:K11) -> 0 | Q11: =SUM(R11:U11) -> 0
G12: =SUM(H12:K12) -> 0 | Q12: =SUM(R12:U12) -> 0
G13: =SUM(H13:K13) -> 0 | Q13: =SUM(R13:U13) -> 0
G14: =SUM(H14:K14) -> 0 | Q14: =SUM(R14:U14) -> 0
G15: =SUM(H15:K15) -> 0 | Q15: =SUM(R15:U15) -> 0
G16: =SUM(H16:K16) -> 0 | Q16: =SUM(R16:U16) -> 0
G17: =SUM(H17:K17) -> 0 | Q17: =SUM(R17:U17) -> 0
... G19: =SUM(H19:K19) -> 0 | Q19: =SUM(R19:U19) -> 0
A20: 合计 | G20: =SUM(G6:G19) -> 0 | H20: =SUM(H6:H19) -> 0 | I20: =SUM(I6:I19) -> 0 | J20: =SUM(J6:J19) -> 0 | K20: =SUM(K6:K19) -> 0 | Q20: =SUM(Q6:Q19) -> 0 | R20: =SUM(R6:R19) -> 0 | S20: =SUM(S6:S19) -> 0 | T20: =SUM(T6:T19) -> 0 | U20: =SUM(U6:U19) -> 0
A21: 债务交易项目 | B21: 应付票据 | G21: 应付账款 | L21: 预收账款 | Q21: 其他应付款
B22: 小计 | C22: 1年以内 | D22: 1-2年 | E22: 2-3年 | F22: 3年以上 | G22: 小计 | H22: 1年以内 | I22: 1-2年 | J22: 2-3年 | K22: 3年以上 | L22: 小计 | M22: 1年以内 | N22: 1-2年 | O22: 2-3年 | P22: 3年以上 | Q22: 小计 | R22: 1年以内 | S22: 1-2年 | T22: 2-3年 | U22: 3年以上
A23: =A6 -> 0 | G23: =SUM(H23:K23) -> 0 | Q23: =SUM(R23:U23) -> 0
A24: =A7 -> 0 | G24: =SUM(H24:K24) -> 0 | Q24: =SUM(R24:U24) -> 0
A25: =A8 -> 0 | G25: =SUM(H25:K25) -> 0 | Q25: =SUM(R25:U25) -> 0
A26: =A9 -> 0 | G26: =SUM(H26:K26) -> 0 | Q26: =SUM(R26:U26) -> 0
A27: =A10 -> 0 | G27: =SUM(H27:K27) -> 0 | Q27: =SUM(R27:U27) -> 0
A28: =A11 -> 0 | G28: =SUM(H28:K28) -> 0 | Q28: =SUM(R28:U28) -> 0
A29: =A12 -> 0 | G29: =SUM(H29:K29) -> 0 | Q29: =SUM(R29:U29) -> 0
A30: =A13 -> 0 | G30: =SUM(H30:K30) -> 0 | Q30: =SUM(R30:U30) -> 0
A31: =A14 -> 0 | G31: =SUM(H31:K31) -> 0 | Q31: =SUM(R31:U31) -> 0
A32: =A15 -> 0 | G32: =SUM(H32:K32) -> 0 | Q32: =SUM(R32:U32) -> 0
A33: =A16 -> 0 | G33: =SUM(H33:K33) -> 0 | Q33: =SUM(R33:U33) -> 0
A34: =A17 -> 0 | G34: =SUM(H34:K34) -> 0 | Q34: =SUM(R34:U34) -> 0
... A36: =A19 -> 0 | G36: =SUM(H36:K36) -> 0 | Q36: =SUM(R36:U36) -> 0
A37: 合计 | G37: =SUM(G23:G36) -> 0 | H37: =SUM(H23:H36) -> 0 | I37: =SUM(I23:I36) -> 0 | J37: =SUM(J23:J36) -> 0 | K37: =SUM(K23:K36) -> 0 | Q37: =SUM(Q23:Q36) -> 0 | R37: =SUM(R23:R36) -> 0 | S37: =SUM(S23:S36) -> 0 | T37: =SUM(T23:T36) -> 0 | U37: =SUM(U23:U36) -> 0

Sheet RP 009
A1: 公司名称 | B1: =基础信息!B6 -> 0
A2: =基础信息!A9 -> 财务期间 | B2: =基础信息!B9 -> 0
A3: 内容 | B3: 未实现内部利润
A4: 交易对象 | B4: 采购项目 | C4: 存货名称 | D4: 期末库存金额 | E4: 其中：期初结转至期末库存金额 | F4: 期末已计提跌价准备 | G4: 内部毛利率
A22: 合计

Sheet RP 010
A1: 公司名称 | B1: =基础信息!B6 -> 0
A2: =基础信息!A9 -> 财务期间 | B2: =基础信息!B9 -> 0
A3: 内容 | B3: 集团内部固定资产/无形资产交易
A4: 本期销售固定资产/无形资产
A5: 交易对象 | B5: 类别 | C5: 名称 | D5: 原值 | E5: 销售时累计折旧/累计摊销 | F5: 销售时已计提减值准备 | G5: 销售价款 | H5: 处置费用 | I5: 营业外收入（支出“-”） | J5: Check Box | R5: 交易主体 | S5: 类别 | T5: Category | U5: 是/否
J6: =IF(G6-(D6-E6-F6)-H6=I6,"OK","NO") -> OK | R6: TS | S6: 房屋及建筑物 | T6: Buildings | U6: √
J7: =IF(G7-(D7-E7-F7)-H7=I7,"OK","NO") -> OK | R7: JF | S7: 电子设备 | T7: Electronic equipment | U7: ×
J8: =IF(G8-(D8-E8-F8)-H8=I8,"OK","NO") -> OK | R8: US | S8: 办公设备 | T8: Office equipment
J9: =IF(G9-(D9-E9-F9)-H9=I9,"OK","NO") -> OK | R9: HK | S9: 运输设备 | T9: Transportation equipment
J10: =IF(G10-(D10-E10-F10)-H10=I10,"OK","NO") -> OK | R10: ST | S10: 房屋装修 | T10: House decoration
J11: =IF(G11-(D11-E11-F11)-H11=I11,"OK","NO") -> OK | R11: FJ | S11: 其他 | T11: Others
J12: =IF(G12-(D12-E12-F12)-H12=I12,"OK","NO") -> OK | R12: JDSY
J13: =IF(G13-(D13-E13-F13)-H13=I13,"OK","NO") -> OK | R13: SZ | S13: 类别 | T13: Category
J14: =IF(G14-(D14-E14-F14)-H14=I14,"OK","NO") -> OK | R14: NJ | S14: UCWEB软件
J15: =IF(G15-(D15-E15-F15)-H15=I15,"OK","NO") -> OK | R15: CD | S15: 其他软件 | T15: Other software
J16: =IF(G16-(D16-E16-F16)-H16=I16,"OK","NO") -> OK | R16: HWKJ | S16: 专利权及牌照 | T16: Patents and licences
J17: =IF(G17-(D17-E17-F17)-H17=I17,"OK","NO") -> OK | R17: HZWK | S17: 会所会籍 | T17: Club memberships
J18: =IF(G18-(D18-E18-F18)-H18=I18,"OK","NO") -> OK | R18: ITMS
J19: =IF(G19-(D19-E19-F19)-H19=I19,"OK","NO") -> OK | R19: HZKJ
J20: =IF(G20-(D20-E20-F20)-H20=I20,"OK","NO") -> OK | R20: HWST
J21: =IF(G21-(D21-E21-F21)-H21=I21,"OK","NO") -> OK | R21: GCGV
J22: =IF(G22-(D22-E22-F22)-H22=I22,"OK","NO") -> OK | R22: ASL
A23: 合计 | J23: =IF(G23-(D23-E23-F23)-H23=I23,"OK","NO") -> OK
A25: 采购固定资产/无形资产
A26: 交易对象 | B26: 类别 | C26: 名称 | D26: 购买日期 | E26: 采购成本 | F26: 折旧方法 | G26: 预计使用年限 | H26: 预计残值 | I26: 备注（发票）
A44: 合计

Sheet RP 011
A1: 公司名称 | B1: =基础信息!B6 -> 0
A2: =基础信息!A9 -> 财务期间 | B2: =基础信息!B9 -> 0
A3: 内容 | B3: 集团内部现金流
A4: 收到的现金 | B4: 销售商品、提供劳务收到的现金 | C4: 收到其他与经营活动有关的现金 | D4: 收回投资收到的现金 | E4: 取得投资收益收到的现金 | F4: 处置固定资产、无形资产和其他长期资产收回的现金净额 | G4: 处置子公司及其他营业单位收到的现金净额 | H4: 收到其他与投资活动有关的现金 | I4: 吸收投资收到的现金 | J4: 取得借款收到的现金 | K4: 收到其他与筹资活动有关的现金
A21: 合计 | B21: =SUM(B5:B20) -> 0 | C21: =SUM(C5:C20) -> 0
A23: 支付的现金 | B23: 购买商品、接受劳务支付的现金 | C23: 支付其他与经营活动有关的现金 | D23: 购置固定资产、无形资产和其他长期资产支付的现金 | E23: 投资支付的现金 | F23: 取得子公司及其他营业单位支付的现金净额 | G23: 支付其他与投资活动有关的现金 | I23: 偿还债务支付的现金 | J23: 分配股利、利润或偿付利息支付的现金 | K23: 支付其他与筹资活动有关的现金
A24: =A5 -> 0
A25: =A6 -> 0
A26: =A7 -> 0
A27: =A8 -> 0
A28: =A9 -> 0
A29: =A10 -> 0
A30: =A11 -> 0
A31: =A12 -> 0
A32: =A13 -> 0
A33: =A14 -> 0
A34: =A15 -> 0
A35: =A15 -> 0
A36: =A16 -> 0
A37: =A17 -> 0
A38: =A18 -> 0
A39: =A19 -> 0
A40: =A20 -> 0
A41: 合计 | B41: =SUM(B24:B40) -> 0 | C41: =SUM(C24:C40) -> 0

Sheet RP 012
A1: 公司名称 | B1: =基础信息!B5 -> 0
A2: 财务期间 | B2: =基础信息!B9 -> 0
A3: 内容 | B3: 货币资金
A5: 项 目 | B5: 期末
A6: 现金
A7: 银行存款
A8: 银行存款中：财务公司存款
A9: 其他货币资金
A10: 合 计 | B10: =SUM(B6:B9) -> 0
A11: 其中：存放在境外的款项总额
A12: 报表金额 | B12: ='RP 006'!E6 -> 0
B13: =B10-B12 -> 0
B14: =IF(B13=0,"OK","NO") -> OK
A15: 其中，外币如下：(除人民币以外的币种)
A16: 币 种 | B16: 期末
B17: 原 币 | C17: 汇率 | D17: 折合本位币
A18: 美元
A19: 港币
A22: 合 计 | B22: =SUM(B18:B21) -> 0 | D22: =SUM(D18:D21) -> 0
A24: 列示于现金流量表的现金及现金等价物包括： | B24: 金 额
A25: 期末货币资金
A26: 减：使用受到限制的存款
A27: 加：现金等价物
A28: 期末现金及现金等价物余额 | B28: =B25-B26+B27 -> 0
A29: 减：期初现金及现金等价物余额
A30: 现金及现金等价物净增加/（减少）额 | B30: =B28-B29 -> 0
A31: 说明：因抵押或冻结等对使用有限制、存放在境外、有潜在回收风险的款项内容

Sheet RP 013
A1: 公司名称 | B1: =基础信息!B6 -> 0
A2: 财务期间 | B2: =基础信息!B9 -> 0
A3: 内容 | B3: 交易性金融资产
A5: 项 目 | B5: 期末
A6: 债务工具投资
A7: 权益工具投资
A8: 衍生金融资产
A9: 其他
A10: 合 计 | B10: =SUM(B6:B9) -> 0
A11: 报表金额 | B11: ='RP 006'!E7 -> 0
B12: =B10-B11 -> 0
B13: =IF(B12=0,"OK","NO") -> OK
A14: 说明：

Sheet RP 014
A1: 公司名称 | B1: =基础信息!B6 -> 0
A2: 财务期间 | B2: =基础信息!B9 -> 0
A3: 内容 | B3: 以公允价值计量且其变动计入当期损益的金融资产
A5: 项 目 | B5: 期末
A6: 交易性金融资产 | B6: =SUM(B7:B10) -> 0
A7: 其中：债务工具投资
A8: 权益工具投资
A9: 衍生金融资产
A10: 其他
A11: 指定为以公允价值计量且其变动计入当期损益的金融资产 | B11: =SUM(B12:B15) -> 0
A12: 其中：债务工具投资
A13: 权益工具投资
A14: 衍生金融资产
A15: 其他
A16: 合 计 | B16: =B6+B11 -> 0
A17: 报表金额 | B17: ='RP 006'!E8 -> 0
B18: =B16-B17 -> 0
B19: =IF(B18=0,"OK","NO") -> OK
A20: 说明：

Sheet RP 015
A1: 公司名称 | B1: =基础信息!B6 -> 0
A2: 财务期间 | B2: =基础信息!B9 -> 0
A3: 内容 | B3: 衍生金融资产
A5: 项 目 | B5: 期末公允价值
A11: 合 计 | B11: =SUM(B6:B10) -> 0
A12: 报表金额 | B12: ='RP 006'!E9 -> 0
B13: =B11-B12 -> 0
B14: =IF(B13=0,"OK","NO") -> OK
A15: 说明：（衍生金融资产产生的原因以及相关会计处理。）

Sheet RP 016
A1: 公司名称 | B1: =基础信息!B6 -> 0
A2: 财务期间 | B2: =基础信息!B9 -> 0
A3: 内容 | B3: 应收票据
A5: 种 类 | B5: 期末
A6: 银行承兑汇票
A7: 商业承兑汇票
A8: 合 计 | B8: =SUM(B6:B7) -> 0
A9: 报表金额 | B9: ='RP 006'!E12 -> 0
B10: =B8-B9 -> 0
B11: =IF(B10=0,"OK","NO") -> OK
A12: 如发生减值披露格式如下：
A13: 种 类 | B13: 期末数
B14: 期末余额 | C14: 坏账准备 | D14: 期末账面价值
A15: 银行承兑汇票 | C15: 0
A16: 商业承兑汇票
A17: 合 计
A20: 其中，用于质押的票据如下：
A21: 种 类 | B21: 期末已质押金额
A22: 银行承兑汇票
A23: 商业承兑汇票
A25: 合 计 | B25: =SUM(B22:B24) -> 0
A27: 其中，已背书或贴现但尚未到期的应收票据
A28: 种 类 | B28: 期末终止确认金额 | C28: 期末未终止确认金额
A29: 银行承兑票据
A30: 商业承兑票据
A31: 可无限量添加行
A32: 合 计 | B32: =SUM(B29:B31) -> 0 | C32: =SUM(C29:C31) -> 0
A34: 其中，因出票人未履约而其转应收账款
A35: 种 类 | B35: 期末转应收账款金额
A36: 商业承兑票据
A39: 合 计 | B39: =SUM(B36:B38) -> 0
A41: 按坏账计提方法分类
A42: 类别 | B42: 20xx.xx.xx | G42: 20xx.xx.xx
B43: 账面余额 | D43: 坏账准备 | F43: 账面 | G43: 账面余额 | I43: 坏账准备 | K43: 账面
B44: 金额 | C44: 比例(%) | D44: 金额 | E44: 预期信用损失率(%) | F44: 价值 | G44: 金额 | H44: 比例(%) | I44: 金额 | J44: 预期信用损失率(%) | K44: 价值
A45: 按单项计提坏账准备 | B45: =B47+B48 -> 0 | C45: =ROUND(B45/B53*100,2) -> #DIV/0! | D45: =D47+D48 -> 0 | E45: =ROUND(D45/B45*100,2) -> #DIV/0! | F45: =B45-D45 -> 0 | G45: =G47+G48 -> 0 | H45: =ROUND(G45/G53*100,2) -> #DIV/0! | I45: =I47+I48 -> 0 | J45: =ROUND(I45/G45*100,2) -> #DIV/0! | K45: =G45-I45 -> 0
A46: 其中：
C47: =ROUND(B47/$B$53*100,2) -> #DIV/0! | E47: =ROUND(D47/B47*100,2) -> #DIV/0! | F47: =B47-D47 -> 0 | H47: =ROUND(G47/$F$53*100,2) -> #DIV/0! | J47: =ROUND(I47/G47*100,2) -> #DIV/0! | K47: =G47-I47 -> 0
C48: =ROUND(B48/$B$53*100,2) -> #DIV/0! | E48: =ROUND(D48/B48*100,2) -> #DIV/0! | F48: =B48-D48 -> 0 | H48: =ROUND(G48/$F$53*100,2) -> #DIV/0! | J48: =ROUND(I48/G48*100,2) -> #DIV/0! | K48: =G48-I48 -> 0
A49: 按组合计提坏账准备 | B49: =B51+B52 -> 0 | C49: =ROUND(B49/$B$53*100,2) -> #DIV/0! | D49: =D51+D52 -> 0 | E49: =ROUND(D49/B49*100,2) -> #DIV/0! | F49: =B49-D49 -> 0 | G49: =G51+G52 -> 0 | H49: =ROUND(G49/$F$53*100,2) -> #DIV/0! | I49: =I51+I52 -> 0 | J49: =ROUND(I49/G49*100,2) -> #DIV/0! | K49: =G49-I49 -> 0
A50: 其中：
A51: 商业承兑汇票 | C51: =ROUND(B51/$B$53*100,2) -> #DIV/0! | E51: =ROUND(D51/B51*100,2) -> #DIV/0! | F51: =B51-D51 -> 0 | H51: =ROUND(G51/$F$53*100,2) -> #DIV/0! | J51: =ROUND(I51/G51*100,2) -> #DIV/0! | K51: =G51-I51 -> 0
A52: 银行承兑汇票 | C52: =ROUND(B52/$B$53*100,2) -> #DIV/0! | E52: =ROUND(D52/B52*100,2) -> #DIV/0! | F52: =B52-D52 -> 0 | H52: =ROUND(G52/$F$53*100,2) -> #DIV/0! | J52: =ROUND(I52/G52*100,2) -> #DIV/0! | K52: =G52-I52 -> 0
A53: 合 计 | B53: =B45+B49 -> 0 | C53: =ROUND(B53/$B$53*100,2) -> #DIV/0! | D53: =D45+D49 -> 0 | E53: =ROUND(D53/B53*100,2) -> #DIV/0! | F53: =B53-D53 -> 0 | H53: =ROUND(G53/$F$53*100,2) -> #DIV/0! | J53: =ROUND(I53/G53*100,2) -> #DIV/0! | K53: =G53-I53 -> 0
A56: 按单项计提坏账准备：
A57: 名 称 | B57: 2018.12.31
B58: 账面余额 | C58: 坏账准备 | D58: 预期信用损失率(%) | E58: 计提理由
D60: =ROUND(C60/B60*100,2) -> #DIV/0!
D61: =ROUND(C61/B61*100,2) -> #DIV/0!
A62: 合 计 | B62: =SUM(B60:B61) -> 0 | C62: =SUM(C60:C61) -> 0
A64: 按组合计提坏账准备：
A65: 组合计提项目：商业承兑汇票
A66: 名 称 | B66: 2018.12.31
B67: 账面余额 | C67: 坏账准备 | D67: 预期信用损失率(%) | E67: 计提理由
A69: 出票人类型或账龄 | D69: =ROUND(C69/B69*100,2) -> #DIV/0!
D70: =ROUND(C70/B70*100,2) -> #DIV/0!
A71: 合 计 | B71: =SUM(B69:B70) -> 0 | C71: =SUM(C69:C70) -> 0
B74: 坏账准备金额
A75: 2018.12.31
A76: 首次执行新金融工具准则的调整金额
A77: 2019.01.01
A78: 本期收回或转回
A79: 本期核销
A80: [本期转销]
A81: [其他]
A82: 2019.12.31

Sheet RP 017
A1: 公司名称 | B1: =基础信息!B6 -> 0
A2: 财务期间 | B2: =基础信息!B9 -> 0
A3: 内容 | B3: 应收账款
A4: （1）A、按风险分类
A5: 类 别 | B5: 期末
B6: 金 额 | C6: 坏账准备
A7: 单项金额重大的应收账款
A8: 单项金额不重大但按信用风险特征组合后该组合的风险较大的应收账款
A9: 其他不重大应收账款
A10: 合 计 | B10: =SUM(B7:B9) -> 0 | C10: =SUM(C7:C9) -> 0
A11: 报表金额 | B11: ='RP 006'!E13 -> 0 | C11: ='RP 006'!E14 -> 0
B12: =B10-B11 -> 0 | C12: =C10-C11 -> 0
B13: =IF(B12=0,"OK","NO") -> OK | C13: =IF(C12=0,"OK","NO") -> OK
A16: （1）B、期末单项金额重大并单项计提坏账准备的应收账款
A17: 应收账款（按单位） | B17: 账面余额 | C17: 坏账准备 | D17: 计提比例% | E17: 计提理由
A22: 合 计
A23: 核对金额 | B23: =B7 -> 0 | C23: =C7 -> 0
B24: =B22-B23 -> 0 | C24: =C22-C23 -> 0
B25: =IF(B24=0,"OK","NO") -> OK | C25: =IF(C24=0,"OK","NO") -> OK
A27: （1）C、账龄组合（和XX组合），按账龄分析法计提坏账准备的应收账款
A28: 账 龄 | B28: 期末
B29: 金 额 | C29: 坏账准备
A30: 1年以内
A31: 1至2年
A32: 2至3年
A33: 3至4年
A34: 4至5年
A35: 5年以上
A36: 合 计 | B36: =SUM(B30:B33) -> 0 | C36: =SUM(C30:C33) -> 0
A37: 核对金额 | B37: =B8 -> 0 | C37: =C8 -> 0
B38: =B36-B37 -> 0 | C38: =C36-C37 -> 0
B39: =IF(B38=0,"OK","NO") -> OK | C39: =IF(C38=0,"OK","NO") -> OK
A41: （2）本期计提、收回或转回的坏账准备情况
A42: 本期计提坏账准备金额XX元；本期收回或转回坏账准备金额XX元。
A43: 其中，本期坏账准备转回或收回金额重要的：
A44: 单位名称 | B44: 转回原因 | C44: 收回方式 | D44: 原确定坏账准备的依据 | E44: 转回或收回金额
A46: 可无限量添加行
A47: 合 计 | B47: =SUM(B45:B46) -> 0 | E47: =SUM(E45:E46) -> 0
A49: （3）本期实际核销的应收账款情况
A50: 项目 | B50: 核销金额
A51: 实际核销的应收账款
A53: 其中，重要的应收账款核销情况（逐项披露）：
A54: 单位名称 | B54: 应收账款性质 | C54: 核销金额 | D54: 核销原因 | E54: 履行的核销程序 | F54: 是否由关联交易产生
A58: 合 计 | B58: =SUM(B55:B57) -> 0 | C58: =SUM(C55:C57) -> 0
A60: （4）按欠款方归集的应收账款期末余额前五名单位情况
A61: 汇总披露格式：
A62: 本期按欠款方归集的期末余额前五名应收账款汇总金额XXXX元，占应收账款期末余额合计数的比例 %，相应计提的坏账准备期末余额汇总金额 XXXX元。
A63: 分别披露格式：
A64: 单位名称 | B64: 应收账款期末余额 | C64: 占应收账款期末余额合计数的比例% | D64: 坏账准备期末余额
A68: 合 计 | B68: =SUM(B65:B67) -> 0 | C68: =SUM(C65:C67) -> 0 | D68: =SUM(D65:D67) -> 0
A70: （5）因金融资产转移而终止确认的应收账款情况
A71: 项 目 | B71: 转移方式 | C71: 终止确认金额 | D71: 与终止确认相关的利得或损失
A75: 合 计 | C75: =SUM(C72:C74) -> 0 | D75: =SUM(D72:D74) -> 0
A76: 说明：
A77: ①期末，本集团因办理了不附追索权的应收账款保理，保理金额为XXX元，同时终止确认应收账款账面价值为XXX元，账面余额为XXX元，账龄为一年以内，已计提坏账准备XXX元。
A78: ②（不符合终止确认条件的应收账款的转移，应在附注中单独列示其金额。）参考披露格式：
A79: 期末，本集团共有账面价值为XXX元的应收账款，账面余额为XXX元，已计提坏账准备XXX元，质押给银行取得短期借款XXX元。
A81: （6）转移应收账款且继续涉入形成的资产、负债的金额
A82: 项 目 | B82: 期末数
A83: 资产：
A85: 资产小计 | B85: X.XX
A86: 负债：
A88: 负债小计 | B88: X.XX
A89: 说明：（资产转移方式；未全部终止确认的被转移金融资产与相关负债之间的关系，已终止确认的金融资产继续涉入的性质及相关风险的信息。）

Sheet RP 018
A1: 公司名称 | B1: =基础信息!B6 -> 0
A2: 财务期间 | B2: =基础信息!B9 -> 0
A3: 内容 | B3: 应收款项融资
A5: 项 目 | B5: 2019.XX.XX | C5: 2018.12.31
A6: 应收票据
A7: 应收账款
A9: 合 计 | B9: =SUM(B6:B8) -> 0 | C9: =SUM(C6:C8) -> 0
A10: 报表金额 | B10: ='RP 006'!E18 -> 0
B11: =B9-B10 -> 0
B12: =IF(B11=0,"OK","NO") -> OK
A14: 各报告期期末减值准备计提情况
A15: 类别 | B15: 2019.XX.XX | G15: 2019.01.01
B16: 账面余额 | D16: 坏账准备 | F16: 账面 | G16: 账面余额 | I16: 坏账准备 | K16: 账面
B17: 金额 | C17: 比例(%) | D17: 金额 | E17: 预期信用损失率(%) | F17: 价值 | G17: 金额 | H17: 比例(%) | I17: 金额 | J17: 预期信用损失率(%) | K17: 价值
A18: 按单项计提坏账准备 | B18: =B20+B21 -> 0 | C18: =C20+C21 -> #DIV/0! | D18: =D20+D21 -> 0 | E18: =ROUND(D18/B18*100,2) -> #DIV/0! | F18: =F20+F21 -> 0 | G18: =G20+G21 -> 0 | H18: =H20+H21 -> #DIV/0! | I18: =I20+I21 -> 0 | J18: =ROUND(I18/G18*100,2) -> #DIV/0! | K18: =K20+K21 -> 0
A19: 其中：
C20: =ROUND(B20/$B$26*100,2) -> #DIV/0! | E20: =ROUND(D20/B20*100,2) -> #DIV/0! | F20: =B20-D20 -> 0 | H20: =ROUND(G20/$G$26*100,2) -> #DIV/0! | J20: =ROUND(I20/G20*100,2) -> #DIV/0! | K20: =G20-I20 -> 0
C21: =ROUND(B21/$B$26*100,2) -> #DIV/0! | E21: =ROUND(D21/B21*100,2) -> #DIV/0! | F21: =B21-D21 -> 0 | H21: =ROUND(G21/$G$26*100,2) -> #DIV/0! | J21: =ROUND(I21/G21*100,2) -> #DIV/0! | K21: =G21-I21 -> 0
A22: 按组合 计提坏账准备 | B22: =B24+B25 -> 0 | C22: =C24+C25 -> #DIV/0! | D22: =D24+D25 -> 0 | F22: =F24+F25 -> 0 | G22: =G24+G25 -> 0 | H22: =H24+H25 -> #DIV/0! | I22: =I24+I25 -> 0 | J22: =ROUND(I22/G22*100,2) -> #DIV/0! | K22: =K24+K25 -> 0
A23: 其中：
A24: 应收中央企业客户 | C24: =ROUND(B24/$B$26*100,2) -> #DIV/0! | E24: =ROUND(D24/B24*100,2) -> #DIV/0! | F24: =B24-D24 -> 0 | H24: =ROUND(G24/$G$26*100,2) -> #DIV/0! | J24: =ROUND(I24/G24*100,2) -> #DIV/0! | K24: =G24-I24 -> 0
A25: 应收海外企业客户 | C25: =ROUND(B25/$B$26*100,2) -> #DIV/0! | E25: =ROUND(D25/B25*100,2) -> #DIV/0! | F25: =B25-D25 -> 0 | H25: =ROUND(G25/$G$26*100,2) -> #DIV/0! | J25: =ROUND(I25/G25*100,2) -> #DIV/0! | K25: =G25-I25 -> 0
A26: 合 计 | B26: =B22+B18 -> 0 | C26: =C22+C18 -> #DIV/0! | D26: =D22+D18 -> 0 | E26: =ROUND(D26/B26*100,2) -> #DIV/0! | F26: =F22+F18 -> 0 | H26: =H22+H18 -> #DIV/0! | J26: =ROUND(I26/G26*100,2) -> #DIV/0! | K26: =K22+K18 -> 0
A27: 核对金额 | F27: =B9 -> 0
F28: =F26-F27 -> 0
F29: =IF(F28=0,"OK","NO") -> OK
A30: 按单项计提坏账准备：
A31: 名 称 | B31: 2019.12.31
B32: 账面余额 | C32: 坏账准备 | D32: 预期信用损失率(%) | E32: 计提理由
D34: =ROUND(C34/B34*100,2) -> #DIV/0!
D35: =ROUND(C35/B35*100,2) -> #DIV/0!
A36: 合 计 | B36: =SUM(B34:B35) -> 0 | C36: =SUM(C34:C35) -> 0
A37: 核对金额 | B37: =B18 -> 0 | C37: =D18 -> 0
B38: =B36-B37 -> 0 | C38: =C36-C37 -> 0
B39: =IF(B38=0,"OK","NO") -> OK | C39: =IF(C38=0,"OK","NO") -> OK
A40: 按组合计提坏账准备：
A41: 组合计提项目：应收中央企业客户
A42: 名 称 | B42: 2019.12.31
B43: 账面余额 | C43: 坏账准备 | D43: 预期信用损失率(%)
A45: 1年以内 | D45: =ROUND(C45/B45*100,2) -> #DIV/0!
A46: 1-2年
A47: ….. | D47: =ROUND(C47/B47*100,2) -> #DIV/0!
A48: 合 计 | B48: =SUM(B45:B47) -> 0 | C48: =SUM(C45:C47) -> 0
A49: 核对金额 | B49: =B24 -> 0 | C49: =D24 -> 0
B50: =B48-B49 -> 0 | C50: =C48-C49 -> 0
B51: =IF(B50=0,"OK","NO") -> OK | C51: =IF(C50=0,"OK","NO") -> OK
A52: 按组合计提坏账准备：
A53: 组合计提项目：应收海外企业客户
A54: 名 称 | B54: 2019.12.31
B55: 账面余额 | C55: 坏账准备 | D55: 预期信用损失率(%)
A57: 1年以内 | D57: =ROUND(C57/B57*100,2) -> #DIV/0!
A58: 1-2年
A59: ….. | D59: =ROUND(C59/B59*100,2) -> #DIV/0!
A60: 合 计 | B60: =SUM(B57:B59) -> 0 | C60: =SUM(C57:C59) -> 0
A61: 核对金额 | B61: =B36 -> 0 | C61: =D36 -> 0
B62: =B25 -> 0 | C62: =D25 -> 0
B63: =IF(B62=0,"OK","NO") -> OK | C63: =IF(C62=0,"OK","NO") -> OK
A65: 各报告期计提、收回或转回的减值准备情况
B66: 坏账准备金额
A67: 2018.12.31
A68: 首次执行新金融工具准则的调整金额
A69: 2019.01.01
A70: 本期收回或转回
A71: 本期核销
A72: [本期转销]
A73: [其他]
A74: 2019.12.31

Sheet RP 019
A1: 公司名称 | B1: =基础信息!B6 -> 0
A2: 财务期间 | B2: =基础信息!B9 -> 0
A3: 内容 | B3: 预付款项
A4: （1）账龄分析
A5: 账 龄 | B5: 期 末
B6: 金 额 | C6: 比例%
A7: 1年以内
A8: 1至2年
A9: 2至3年
A10: 3年以上
A11: 合 计 | B11: =SUM(B7:B10) -> 0 | C11: =SUM(C7:C10) -> 0
A12: 报表金额 | B12: ='RP 006'!E19 -> 0
B13: =B11-B12 -> 0
B14: =IF(B13=0,"OK","NO") -> OK
A15: 说明：
A16: 账龄在1年以上的预付款项超过XX万元，请说明如下信息
A17: 公司名称 | B17: 预付款项金额 | C17: 账龄超过一年的原因
A19: （2）按预付对象归集的预付款项期末余额前五名单位情况
A20: 汇总披露格式：
A21: 本期按预付对象归集的期末余额前五名预付款项汇总金额XXXX元，占预付款项期末余额合计数的比例 %。
A22: 分别披露格式：
A23: 单位名称 | B23: 预付款项期末余额 | C23: 占预付款项期末余额合计数的比例%
A27: 合 计 | B27: =SUM(B24:B26) -> 0 | C27: =SUM(C24:C26) -> 0

Sheet RP 020
A1: 公司名称 | B1: =基础信息!B6 -> 0
A2: 财务期间 | B2: =基础信息!B9 -> 0
A3: 内容 | B3: 其他应收款
A4: 项 目 | B4: 期末
A5: 应收利息 | B5: ='RP 020-1'!B9 -> 0
A6: 应收股利 | B6: ='RP 020-2'!B8 -> 0
A7: 其他应收款 | B7: ='RP 020-3'!B10-'RP 020-3'!C10 -> 0
A8: 合 计 | B8: =SUM(B5:B7) -> 0
A9: 报表金额 | B9: ='RP 006'!E22 -> 0
B10: =B8-B9 -> 0
B11: =IF(B10=0,"OK","NO") -> OK

Sheet RP 020-1
A1: 公司名称 | B1: =基础信息!B6 -> 0
A2: 财务期间 | B2: =基础信息!B9 -> 0
A3: 内容 | B3: 应收利息
A4: 项 目 | B4: 期末
A5: 定期存款
A6: 委托贷款
A7: 债券投资
A8: 可无限量添加行
A9: 合 计 | B9: =SUM(B5:B8) -> 0
A10: 核对金额 | B10: ='RP 020'!B5 -> 0
B11: =B9-B10 -> 0
B12: =IF(B11=0,"OK","NO") -> OK
A14: 其中，重要的逾期应收利息如下：
A15: 借款单位 | B15: 期末数 | C15: 逾期时间 | D15: 逾期原因 | E15: 是否发生减值及其原因
A19: 合 计 | B19: =SUM(B16:B18) -> 0
A20: （对于重要的逾期应收利息，应按借款单位披露应收利息的期末余额、逾期时间和逾期原因、是否发生减值的判断。）

Sheet RP 020-2
A1: 公司名称 | B1: =基础信息!B6 -> 0
A2: 财务期间 | B2: =基础信息!B9 -> 0
A3: 内容 | B3: 应收股利
A5: 被投资单位名称 | B5: 期末
A8: 合 计 | B8: =SUM(B6:B7) -> 0
A9: 核对金额 | B9: ='RP 020'!B6 -> 0
B10: =B8-B9 -> 0
B11: =IF(B10=0,"OK","NO") -> OK
A14: 其中，重要的账龄超过1年的应收股利如下：
A15: 项目（或被投资单位） | B15: 期末数 | C15: 账龄 | D15: 未收回的原因 | E15: 是否发生减值及其判断依据
A19: 合 计 | B19: =SUM(B16:B18) -> 0
A20: （对于重要的账龄超过1 年的应收股利，应披露未收回的原因和对相关款项是否发生减值的判断。）

Sheet RP 020-3
A1: 公司名称 | B1: =基础信息!B6 -> 0
A2: 财务期间 | B2: =基础信息!B9 -> 0
A3: 内容 | B3: 其他应收款
A4: （1）A、按风险分类
A5: 类 别 | B5: 期末
B6: 金 额 | C6: 坏账准备
A7: 单项金额重大的其他应收款(XX万元以上)
A8: 单项金额不重大但按信用风险特征组合后该组合的风险较大的其他应收款
A9: 其他不重大其他应收款
A10: 合 计 | B10: =SUM(B7:B9) -> 0 | C10: =SUM(C7:C9) -> 0
A11: 核对金额 | C11: ='RP 020'!B7 -> 0
C12: =B10-C10-C11 -> 0
C13: =IF(C12=0,"OK","NO") -> OK
A14: （1）B、期末单项金额重大并单项计提坏账准备的其他应收款
A15: 其他应收款（按单位） | B15: 账面余额 | C15: 坏账准备 | D15: 计提比例% | E15: 计提理由
A16: 可无限量添加行
A17: 合 计 | B17: =SUM(B16) -> 0 | C17: =SUM(C16) -> 0 | D17: =SUM(D16) -> 0
A18: 报表金额 | B18: =B7 -> 0 | C18: =C7 -> 0
B19: =B17-B18 -> 0 | C19: =C17-C18 -> 0
B20: =IF(B19=0,"OK","NO") -> OK | C20: =IF(C19=0,"OK","NO") -> OK
A21: （1）C、账龄组合（和XX组合），按账龄分析法计提坏账准备的其他应收账款
A22: 账 龄 | B22: 期末
B23: 金 额 | C23: 坏账准备
A24: 1年以内
A25: 1至2年
A26: 2至3年
A27: 3年以上
A28: 合 计 | B28: =SUM(B24:B27) -> 0 | C28: =SUM(C24:C27) -> 0
A29: 报表金额 | B29: =B8 -> 0 | C29: =C8 -> 0
B30: =B28-B29 -> 0 | C30: =C28-C29 -> 0
B31: =IF(B30=0,"OK","NO") -> OK | C31: =IF(C30=0,"OK","NO") -> OK
A33: （2）本期计提、收回或转回的坏账准备情况
A34: 本期计提坏账准备金额XX元；本期收回或转回坏账准备金额XX元。
A35: 其中，本期坏账准备转回或收回金额重要的：
A36: 单位名称 | B36: 转回原因 | C36: 收回方式 | D36: 原确定坏账准备的依据 | E36: 转回或收回金额
A38: 可无限量添加行
A39: 合 计 | E39: =SUM(E37:E38) -> 0
A41: （3）本期实际核销的其他应收账款情况
A42: 项目 | B42: 核销金额
A43: 实际核销的其他应收账款
A45: 其中，重要的其他应收账款核销情况（逐项披露）：
A46: 单位名称 | B46: 其他应收账款性质 | C46: 核销金额 | D46: 核销原因 | E46: 履行的核销程序 | F46: 是否由关联交易产生
A50: 合 计 | C50: =SUM(C47:C49) -> 0
A52: （4）其他应收款按款项性质披露
A53: 项 目 | B53: 期末余额
A54: 备用金
A55: 保证金
A56: 可无限量添加行
A58: 合 计
A60: （5）按欠款方归集的其他应收账款期末余额前五名单位情况
A61: 汇总披露格式：
A62: 本期按欠款方归集的期末余额前五名其他应收账款汇总金额XXXX元，占其他应收账款期末余额合计数的比例 %，相应计提的坏账准备期末余额汇总金额 XXXX元。
A63: 分别披露格式：
A64: 单位名称 | B64: 其他应收账款期末余额 | C64: 占其他应收账款期末余额合计数的比例% | D64: 坏账准备期末余额
A68: 合 计 | B68: =SUM(B65:B67) -> 0 | C68: =SUM(C65:C67) -> 0 | D68: =SUM(D65:D67) -> 0
A70: （6）应收政府补助情况（逐项披露）
A71: 单位名称（注：政府补助的发文单位） | B71: 政府补助项目名称 | C71: 期末余额 | D71: 期末账龄 | E71: 预计收取的时间、金额及依据
A75: 合计
A78: （7）因金融资产转移而终止确认的其他应收账款情况
A79: 项 目 | B79: 转移方式 | C79: 终止确认金额 | D79: 与终止确认相关的利得或损失
A83: 合 计 | C83: =SUM(C80:C82) -> 0 | D83: =SUM(D80:D82) -> 0
A84: 说明：
A85: ①期末，本集团因办理了不附追索权的其他应收账款保理，保理金额为XXX元，同时终止确认其他应收账款账面价值为XXX元，账面余额为XXX元，账龄为一年以内，已计提坏账准备XXX元。
A86: ②（不符合终止确认条件的其他应收账款的转移，应在附注中单独列示其金额。）参考披露格式：
A87: 期末，本集团共有账面价值为XXX元的其他应收账款，账面余额为XXX元，已计提坏账准备XXX元，质押给银行取得短期借款XXX元。
A89: （8）转移其他应收账款且继续涉入形成的资产、负债的金额
A90: 项 目 | B90: 期末数
A91: 资产：
A93: 资产小计 | B93: X.XX
A94: 负债：
A96: 负债小计 | B96: X.XX
A97: 说明：（资产转移方式；未全部终止确认的被转移金融资产与相关负债之间的关系，已终止确认的金融资产继续涉入的性质及相关风险的信息。）

Sheet RP 021
A1: 公司名称 | B1: =基础信息!B6 -> 0
A2: 财务期间 | B2: =基础信息!B9 -> 0
A3: 内容 | B3: 存货
A4: （1）存货分项目列示
A5: 项 目 | B5: 期末数
B6: 账面余额 | C6: 跌价准备 | D6: 账面价值
A7: 原材料 | D7: =B7-C7 -> 0
A8: 自制半成品及在产品 | D8: =B8-C8 -> 0
A9: 库存商品（产成品） | D9: =B9-C9 -> 0
A10: 周转材料（包装物、低值易耗品等） | D10: =B10-C10 -> 0
A11: 消耗性生物资产 | D11: =B11-C11 -> 0
A12: 房地产开发成本 | D12: =B12-C12 -> 0
A13: 房地产开发产品 | D13: =B13-C13 -> 0
D14: =B14-C14 -> 0
A15: 其他 | D15: =B15-C15 -> 0
A16: 合 计 | B16: =SUM(B7:B15) -> 0 | C16: =SUM(C7:C15) -> 0 | D16: =SUM(D7:D15) -> 0
A17: 报表金额 | B17: ='RP 006'!E23 -> 0 | C17: ='RP 006'!E24 -> 0 | D17: ='RP 006'!E25 -> 0
B18: =B16-B17 -> 0 | C18: =C16-C17 -> 0 | D18: =D16-D17 -> 0
B19: =IF(B18=0,"OK","NO") -> OK | C19: =IF(C18=0,"OK","NO") -> OK | D19: =IF(D18=0,"OK","NO") -> OK
A20: （注：根据企业具体情况分类，房地产开发企业应增加“开发成本”、“开发产品”等种类）
A21: （2）存货跌价准备
A22: 存货种类 | B22: 期初数 | C22: 本期增加 | E22: 本期减少 | G22: 期末数
C23: 计提 | D23: 其他 | E23: 转回或转销 | F23: 其他
A24: 原材料
A25: 在产品
A26: 库存商品
A27: 周转材料
A28: 消耗性生物资产
A29: 合 计 | B29: =SUM(B24:B28) -> 0 | C29: =SUM(C24:C28) -> 0 | D29: =SUM(D24:D28) -> 0 | E29: =SUM(E24:E28) -> 0 | F29: =SUM(F24:F28) -> 0 | G29: =SUM(G24:G28) -> 0
A30: 报表金额 | G30: =C17 -> 0
G31: =IF(G30=0,"OK","NO") -> OK
A33: 存货跌价准备（续）
A34: 存货种类 | B34: 确定可变现净值的具体依据 | C34: 本期转回或转销存货跌价准备的原因
A35: 原材料
A36: 在产品
A37: 库存商品
A38: 周转材料
A39: 消耗性生物资产 | D39: s
A40: 合 计
A41: 【披露确定可变现净值的具体依据及本期转回或转销存货跌价准备的原因。】
A42: （3）存货期末余额中含有借款费用资本化金额的说明：
A44: （房地产开发企业，应按下列格式披露“开发成本”、“开发产品”等相关信息)

Sheet RP 022
A1: 公司名称 | B1: =基础信息!B6 -> 0
A2: 财务期间 | B2: =基础信息!B9 -> 0
A3: 内容 | B3: 合同资产
A4: （1）合同资产
A5: 项 目 | B5: 期末数
B6: 账面余额 | C6: 跌价准备 | D6: 账面价值
D7: =B7-C7 -> 0
D8: =B8-C8 -> 0
D9: =B9-C9 -> 0
D10: =B10-C10 -> 0
D11: =B11-C11 -> 0
D12: =B12-C12 -> 0
A13: 合 计 | B13: =SUM(B7:B12) -> 0 | C13: =SUM(C7:C12) -> 0 | D13: =SUM(D7:D12) -> 0
A14: 报表金额 | B14: ='RP 006'!E26 -> 0 | C14: ='RP 006'!E27 -> 0 | D14: ='RP 006'!E28 -> 0
B15: =B13-B14 -> 0 | C15: =C13-C14 -> 0 | D15: =D13-D14 -> 0
B16: =IF(B15=0,"OK","NO") -> OK | C16: =IF(C15=0,"OK","NO") -> OK | D16: =IF(D15=0,"OK","NO") -> OK
A18: （2）合同资产减值准备计提情况
A19: 类别 | B19: 2019.XX.XX | G19: 2019.01.01
B20: 账面余额 | D20: 坏账准备 | F20: 账面 | G20: 账面余额 | I20: 坏账准备 | K20: 账面
B21: 金额 | C21: 比例(%) | D21: 金额 | E21: 预期信用损失率(%) | F21: 价值 | G21: 金额 | H21: 比例(%) | I21: 金额 | J21: 预期信用损失率(%) | K21: 价值
A22: 按单项计提坏账准备 | B22: =B24+B25 -> 0 | C22: =C24+C25 -> #DIV/0! | D22: =D24+D25 -> 0 | E22: =ROUND(D22/B22*100,2) -> #DIV/0! | F22: =F24+F25 -> 0 | G22: =G24+G25 -> 0 | H22: =H24+H25 -> #DIV/0! | I22: =I24+I25 -> 0 | J22: =ROUND(I22/G22*100,2) -> #DIV/0! | K22: =K24+K25 -> 0
A23: 其中：
C24: =ROUND(B24/$B$24*100,2) -> #DIV/0! | E24: =ROUND(D24/B24*100,2) -> #DIV/0! | F24: =B24-D24 -> 0 | H24: =ROUND(G24/$G$24*100,2) -> #DIV/0! | J24: =ROUND(I24/G24*100,2) -> #DIV/0! | K24: =G24-I24 -> 0
C25: =ROUND(B25/$B$24*100,2) -> #DIV/0! | E25: =ROUND(D25/B25*100,2) -> #DIV/0! | F25: =B25-D25 -> 0 | H25: =ROUND(G25/$G$24*100,2) -> #DIV/0! | J25: =ROUND(I25/G25*100,2) -> #DIV/0! | K25: =G25-I25 -> 0
A26: 按组合 计提坏账准备 | B26: =B28+B29 -> 0 | C26: =C28+C29 -> #DIV/0! | D26: =D28+D29 -> 0 | F26: =F28+F29 -> 0 | G26: =G28+G29 -> 0 | H26: =H28+H29 -> #DIV/0! | I26: =I28+I29 -> 0 | J26: =ROUND(I26/G26*100,2) -> #DIV/0! | K26: =K28+K29 -> 0
A27: 其中：
C28: =ROUND(B28/$B$24*100,2) -> #DIV/0! | E28: =ROUND(D28/B28*100,2) -> #DIV/0! | F28: =B28-D28 -> 0 | H28: =ROUND(G28/$G$24*100,2) -> #DIV/0! | J28: =ROUND(I28/G28*100,2) -> #DIV/0! | K28: =G28-I28 -> 0
C29: =ROUND(B29/$B$24*100,2) -> #DIV/0! | E29: =ROUND(D29/B29*100,2) -> #DIV/0! | F29: =B29-D29 -> 0 | H29: =ROUND(G29/$G$24*100,2) -> #DIV/0! | J29: =ROUND(I29/G29*100,2) -> #DIV/0! | K29: =G29-I29 -> 0
A30: 合 计 | B30: =B26+B22 -> 0 | C30: =C26+C22 -> #DIV/0! | D30: =D26+D22 -> 0 | E30: =ROUND(D30/B30*100,2) -> #DIV/0! | F30: =F26+F22 -> 0 | H30: =H26+H22 -> #DIV/0! | J30: =ROUND(I30/G30*100,2) -> #DIV/0! | K30: =K26+K22 -> 0
A31: 应与会计政策中披露的组合一致
A32: 核对金额 | F32: =D14 -> 0
F33: =IF(F32-F30=0,"OK","NO") -> OK
A34: （3）本期计提、收回或转回的合同资产减值准备情况
A35: 项目 | B35: 期初数 | C35: 本期增加 | E35: 本期减少 | G35: 期末数
C36: 计提 | D36: 其他 | E36: 转回或转销 | F36: 其他
A43: 合 计 | B43: =SUM(B37:B42) -> 0 | C43: =SUM(C37:C42) -> 0 | D43: =SUM(D37:D42) -> 0 | E43: =SUM(E37:E42) -> 0 | F43: =SUM(F37:F42) -> 0 | G43: =SUM(G37:G42) -> 0
A44: 核对金额 | G44: =C14 -> 0
G45: =IF(G44=0,"OK","NO") -> OK

Sheet RP 023
A1: 公司名称 | B1: =基础信息!B6 -> 0
A2: 财务期间 | B2: =基础信息!B9 -> 0
A3: 内容 | B3: 持有待售资产和持有待售负债
A6: 项 目 | B6: 期末数
A7: 持有待售的资产：
A8: 持有待售的非流动资产
A9: 持有待售的处置组中的资产
A10: 其中：子公司A
A11: 分公司B
A12: 合 计 | B12: =SUM(B7:B11) -> 0
A13: 报表金额 | B13: ='RP 006'!E29 -> 0
B14: =B12-B13 -> 0
B15: =IF(B14=0,"OK","NO") -> OK
A17: 项 目 | B17: 期末数
A18: 持有待售的负债：
A19: 持有待售的处置组中的负债
A20: 其中：子公司A
A21: 分公司B
A22: 合 计 | B22: =SUM(B18:B21) -> 0
A23: 报表金额 | B23: ='RP 006'!E92 -> 0
B24: =B22-B23 -> 0
B25: =IF(B24=0,"OK","NO") -> OK
A27: 说明：（应当说明持有待售的非流动资产及持有待售的处置组中的资产产生的原因、内容及性质）
A28: （1）持有待售的非流动资产
A29: 期末，持有待售的资产的情况：
A30: 项 目 | B30: 账面价值 | C30: 公允价值 | D30: 预计处置费用 | E30: 预计处置时间
A35: 合 计
A37: （2）持有待售的处置组
A38: ①子公司A
A39: 项 目 | B39: 账面价值 | C39: 公允价值 | D39: 预计处置费用 | E39: 预计处置时间
A40: 持有待售的处置组中的资产
A41: 货币资金
A43: 固定资产
A44: ……
A46: 持有待售的处置组中的负债
A47: 应付账款
A48: 长期应付款
A49: ……
A51: ②分公司B
A52: 项 目 | B52: 账面价值 | C52: 公允价值 | D52: 预计处置费用 | E52: 预计处置时间
A53: 持有待售的处置组中的资产
A54: 货币资金
A56: 固定资产
A57: ……
A59: 持有待售的处置组中的负债
A60: 应付账款
A61: 长期应付款
A62: ……
A64: 说明：（如存在专为转售而取得的持有待售的子公司，需披露该子公司出售原因、方式和时间安排；列报该子公司的分部；该子公司确认的减值损失及其转回金额；与该子公司有关的其他综合收益累计金额；归属于母公司股东的持续经营损益和终止经营损益。）
A65: （如果子公司、共同经营、合营企业、联营企业以及部分对合营企业或联营企业的投资不再继续划分为持有待售类别或从持有待售的处置组中移除的，应在当期财务报表中相应调整各个持有待售类别后可比会计期间的比较数据，且需披露改变非流动资产或处置组出售计划的原因及可比会计期间财务报表中受影响的项目名称和影响金额。）

Sheet RP 024
A1: 公司名称 | B1: =基础信息!B6 -> 0
A2: 财务期间 | B2: =基础信息!B9 -> 0
A3: 内容 | B3: 一年内到期的非流动资产
A6: （1）项目分析
A7: 项 目 | B7: 期末数
A8: 1年内到期的长期应收款
A9: 1年内到期的持有至到期投资
A10: 1年内到期的债权投资
A11: 1年内到期的其他债权投资
A12: 其他
A13: 合 计 | B13: =SUM(B8:B11) -> 0
A14: 报表金额 | B14: ='RP 006'!E30 -> 0
B15: =B17-B14 -> 0
B16: =IF(B15=0,"OK","NO") -> OK
A17: 说明：（对于大额的一年内到期的非流动资产说明形成的原因、内容、性质。）
A19: 其他债权投资行项目，反映资产负债表日企业分类为以公允价值计量且其变动计入其他综合收益的长期债权投资的期末账面价值。该项目应根据"其他债权投资"科目的相关明细科目期末余额分析填列。自资产负债表日起一年内到期的长期债权投资的期末账面价值，在"一年内到期的非流动资产"行项目反映。

Sheet RP 025
A1: 公司名称 | B1: =基础信息!B6 -> 0
A2: 财务期间 | B2: =基础信息!B9 -> 0
A3: 内容 | B3: 其他流动资产
A4: 项 目 | B4: 期末
A5: 进项税额
A6: 多交或预缴的增值税额
A7: 待抵扣进项税额
A8: 待认证进项税额
A9: 增值税留抵税额
A10: 预缴所得税
A11: 委托贷款
A12: 预缴其他税费
A13: 短期债权投资
A14: 短期其他债权投资
A15: 合同取得成本
A16: 应收退货成本
A17: 合 计 | B17: =SUM(B5:B16) -> 0
A18: 报表金额 | B18: ='RP 006'!E41 -> 0
B19: =B17-B18 -> 0
B20: =IF(B19=0,"OK","NO") -> OK
A23: 进项税额
A24: 多交或预缴的增值税额
A25: 待抵扣进项税额
A26: 待认证进项税额
A27: 增值税留抵税额
A28: 预缴所得税
A29: 委托贷款
A30: 预缴其他税费
A31: 短期债权投资
A32: 短期其他债权投资
A33: 合同取得成本
A34: 应收退货成本

Sheet RP 026
A1: 公司名称 | B1: =基础信息!B6 -> 0
A2: 财务期间 | B2: =基础信息!B9 -> 0
A3: 内容 | B3: 债权投资
A4: 债券投资情况
A5: 项 目 | B5: 期末数
B6: 账面余额 | C6: 减值准备 | D6: 账面价值
D7: =B7-C7 -> 0
D8: =B8-C8 -> 0
D9: =B9-C9 -> 0
D10: =B10-C10 -> 0
D11: =B11-C11 -> 0
A12: 小 计 | B12: =SUM(B7:B11) -> 0 | C12: =SUM(C7:C11) -> 0 | D12: =SUM(D7:D11) -> 0
A13: 减：1年内到期的债权投资
A14: 合 计 | B14: =B12-B13 -> 0 | C14: =C12-C13 -> 0 | D14: =D12-D13 -> 0
A15: 报表金额 | D15: ='RP 006'!E45 -> 0
D16: =D14-D15 -> 0
D17: =IF(D16=0,"OK","NO") -> OK
A19: （1）重要的债权投资
A20: 债权投资项目 | B20: 面值 | C20: 票面利率 | D20: 实际利率 | E20: 到期日
A22: 合 计 | B22: X.XX | C22: -- | D22: -- | E22: --
A25: （2）减值准备计提情况
A26: 【15号文第十九条（十一），披露用以确定本期减值准备计提金额以及评估金融工具的信用风险自初始确认后是否已显著增加等事项时所采用的输入值、假设等信息。】
A27: 于2019年12月31日，处于第一阶段的债权投资的减值准备分析如下：
A28: 类别 | B28: 账面余额 | C28: 未来12个月内预期信用损失率（%） | D28: 减值准备 | E28: 账面价值 | F28: 理由
A29: 按单项计提坏账准备
A30: 其中：
A33: 按组合计提坏账准备
A34: 其中：
A37: 合 计
A38: 于2018年12月31日，处于第二阶段的债权投资的减值准备分析如下：
A39: 类别 | B39: 账面余额 | C39: 整个存续期预期信用损失率（%） | D39: 减值准备 | E39: 账面价值 | F39: 理由
A40: 按单项计提坏账准备 | B40: =B42+B43 -> 0 | D40: =D42+D43 -> 0 | E40: =B40-C40 -> 0
A41: 其中： | E41: =B41-C41 -> 0
E42: =B42-C42 -> 0
E43: =B43-C43 -> 0
A44: 按组合计提坏账准备 | B44: =B45+B46+B47 -> 0 | D44: =D46+D47 -> 0 | E44: =B44-C44 -> 0
A45: 其中： | E45: =B45-C45 -> 0
E46: =B46-C46 -> 0
E47: =B47-C47 -> 0
A48: 合 计 | B48: =B44+B40 -> 0 | D48: =D44+D40 -> 0 | E48: =E44+E40 -> 0
A49: 于2018年12月31日，处于第三阶段的债权投资的减值准备分析如下：
A50: 类别 | B50: 账面余额 | C50: 整个存续期预期信用损失率（%） | D50: 减值准备 | E50: 账面价值 | F50: 理由
A51: 按单项计提坏账准备 | B51: =B53+B54 -> 0 | D51: =D53+D54 -> 0 | E51: =B51-C51 -> 0
A52: 其中： | E52: =B52-C52 -> 0
E53: =B53-C53 -> 0
E54: =B54-C54 -> 0
A55: 按组合计提坏账准备 | B55: =B56+B57+B58 -> 0 | D55: =D57+D58 -> 0 | E55: =B55-C55 -> 0
A56: 其中： | E56: =B56-C56 -> 0
E57: =B57-C57 -> 0
E58: =B58-C58 -> 0
A59: 合 计 | B59: =B55+B51 -> 0 | D59: =D55+D51 -> 0 | E59: =E55+E51 -> 0
A62: （3）本期计提、收回或转回的减值准备情况
B63: 减值准备金额
A64: 2018.12.31
A66: 首次执行新金融工具准则的调整金额
A68: 2019.01.01
A69: 本期计提
A70: 本期收回或转回
A71: 本期核销
A72: [本期转销]
A73: [其他]
A74: 2019.12.31

Sheet RP 027
A1: 公司名称 | B1: =基础信息!B6 -> 0
A2: 财务期间 | B2: =基础信息!B9 -> 0
A3: 内容 | B3: 可供出售金融资产
A4: （1）可供出售金融资产情况
A5: 项 目 | B5: 期末数
B6: 账面余额 | C6: 减值准备 | D6: 账面价值
A7: 可供出售债务工具 | D7: =B7-C7 -> 0
A8: 可供出售权益工具 | D8: =B8-C8 -> 0
A9: 其中：按公允价值计量 | D9: =B9-C9 -> 0
A10: 按成本计量 | D10: =B10-C10 -> 0
A11: 其他 | D11: =B11-C11 -> 0
A12: 合 计 | B12: =SUM(B7:B11) -> 0 | C12: =SUM(C7:C11) -> 0 | D12: =SUM(D7:D11) -> 0
A13: 报表金额 | D13: ='RP 006'!E46 -> 0
D14: =D12-D13 -> 0
D15: =IF(D14=0,"OK","NO") -> OK

Sheet RP 028
A1: 公司名称 | B1: =基础信息!B6 -> 0
A2: 财务期间 | B2: =基础信息!B9 -> 0
A3: 内容 | B3: 其他债权投资
A4: （1）其他债权投资情况
A5: 项 目 | B5: 期末数
B6: 账面价值
A12: 小计 | B12: =SUM(B7:B11) -> 0
A13: 减：1年内到期的债权投资
A15: 合计 | B15: =B12-B14 -> 0
A16: 报表金额 | B16: ='RP 006'!E53 -> 0
B17: =B15-B16 -> 0
B18: =IF(B17=0,"OK","NO") -> OK
A19: （1）其他债权投资情况
A20: 项目 | B20: 2019.01.01 | C20: 应计利息 | D20: 本期公允价值变动 | E20: 2019.12.31 | F20: 成本 | G20: 累计公允价值变动 | H20: 累计在其他综合收益中确认的损失准备
A23: 合计
A24: 说明：
A25: （2）期末重要的其他债权投资
A26: 项目 | B26: 2019.12.31 | F26: 2018.12.31
B27: 面值 | C27: 票面利率 | D27: 实际利率 | E27: 到期日 | F27: 面值 | G27: 票面利率 | H27: 实际利率 | I27: 到期日
F28: - | G28: - | H28: - | I28: -
F29: - | G29: - | H29: - | I29: -
A30: 合计 | C30: / | D30: / | E30: / | F30: - | G30: / | H30: / | I30: /
A31: （3）减值准备计提情况
A32: 【15号文第十九条（十一），披露用以确定本期减值准备计提金额以及评估金融工具的信用风险自初始确认后是否已显著增加等事项时所采用的输入值、假设等信息。】
A33: 于2019年12月31日，处于第一阶段的其他债权投资的减值准备分析如下：
A34: 类别 | B34: 账面余额 | C34: 未来12个月内预期信用损失率（%） | D34: 减值准备 | E34: 账面价值 | F34: 理由
A35: 按单项计提坏账准备
A36: 其中：
A39: 按组合计提坏账准备
A40: 其中：
A43: 合 计
A45: 于2019年12月31日，处于第二阶段的其他债权投资的减值准备分析如下：
A46: 类别 | B46: 账面余额 | C46: 整个存续期预期信用损失率（%） | D46: 减值准备 | E46: 账面价值 | F46: 理由
A47: 按单项计提坏账准备
A48: 其中：
A51: 按组合计提坏账准备
A52: 其中：
A55: 合 计
A56: 于2019年12月31日，处于第三阶段的其他债权投资的减值准备分析如下：
A57: 类别 | B57: 账面余额 | C57: 整个存续期预期信用损失率（%） | D57: 减值准备 | E57: 账面价值 | F57: 理由
A58: 按单项计提坏账准备
A59: 其中：
A62: 按组合计提坏账准备
A63: 其中：
A66: 合 计
A67: 说明：本期发生损失准备的其他债权投资账面余额显著变动的情况。
A68: 说明：本期坏账准备计提金额以及评估金融工具的信用风险是否显著增加的采用依据
A69: （4）本期计提、收回或转回的减值准备情况
B70: 减值准备金额
A71: 2018.12.31
A73: 首次执行新金融工具准则的调整金额
A75: 2019.01.01
A76: 本期计提
A77: 本期收回或转回
A78: 本期核销
A79: [本期转销]
A80: [其他]
A81: 2019.12.31

Sheet RP 029
A1: 公司名称 | B1: =基础信息!B6 -> 0
A2: 财务期间 | B2: =基础信息!B9 -> 0
A3: 内容 | B3: 持有至到期投资
A4: （1）持有至到期投资情况
A5: 项 目 | B5: 期末数
B6: 账面余额 | C6: 减值准备 | D6: 账面价值
D7: =B7-C7 -> 0
D8: =B8-C8 -> 0
D9: =B9-C9 -> 0
D10: =B10-C10 -> 0
D11: =B11-C11 -> 0
A12: 小 计 | B12: =SUM(B7:B11) -> 0 | C12: =SUM(C7:C11) -> 0 | D12: =SUM(D7:D11) -> 0
A13: 减：1年内到期的持有至到期投资
A14: 合 计 | B14: =B12-B13 -> 0 | C14: =C12-C13 -> 0 | D14: =D12-D13 -> 0
A15: 报表金额 | D15: ='RP 006'!E47 -> 0
D16: =D14-D15 -> 0
D17: =IF(D16=0,"OK","NO") -> OK
A19: （2）重要的持有至到期投资
A20: 债券项目 | B20: 面值 | C20: 票面利率 | D20: 实际利率 | E20: 到期日
A22: 合 计 | B22: X.XX | C22: -- | D22: -- | E22: --
A23: （对于重要的持有至到期投资，应分别列示其面值、票面利率、实际利率、到期日。）
A24: （3）持有至到期投资重分类情况
A25: （本期存在重分类的，应披露重分类的原因和具体情况。）
A26: 由于XX原因，本期将持有至到期投资重分类为可供出售金融资产，重分类的金额XX元，该金额占重分类前持有至到期投资总额的比例XX%。

Sheet RP 030
A1: 公司名称 | B1: =基础信息!B6 -> 0
A2: 财务期间 | B2: =基础信息!B9 -> 0
A3: 内容 | B3: 长期应收款
A4: （1）长期应收款按性质披露
A5: 项 目 | B5: 期末数 | E5: 折现率区间
B6: 账面余额 | C6: 坏账准备 | D6: 账面价值
A7: 融资租赁款 | D7: =B7-C7 -> 0
A8: 其中：未实现融资收益 | D8: =B8-C8 -> 0
A9: 分期收款销售商品 | D9: =B9-C9 -> 0
A10: 其中：未实现融资收益 | D10: =B10-C10 -> 0
A11: 分期收款提供劳务 | D11: =B11-C11 -> 0
A12: 其中：未实现融资收益 | D12: =B12-C12 -> 0
A13: 其他 | D13: =B13-C13 -> 0
A14: 可无限量添加行 | D14: =B14-C14 -> 0
A15: 小 计 | D15: =B15-C15 -> 0
A16: 减：1年内到期的长期应收款 | D16: =B16-C16 -> 0
A17: 合 计 | B17: =B15-B16 -> 0 | C17: =C15-C16 -> 0 | D17: =D15-D16 -> 0
A18: 报表金额 | D18: ='RP 006'!E48 -> 0
D19: =D17-D18 -> 0
D20: =IF(D19=0,"OK","NO") -> OK
A22: （2）坏账准备计提情况
A23: 类别 | B23: 2019.XX.XX | G23: 2019.01.01
B24: 账面余额 | D24: 坏账准备 | F24: 账面 | G24: 账面余额 | I24: 坏账准备 | K24: 账面
B25: 金额 | C25: 比例(%) | D25: 金额 | E25: 预期信用损失率(%) | F25: 价值 | G25: 金额 | H25: 比例(%) | I25: 金额 | J25: 预期信用损失率(%) | K25: 价值
A26: 按单项计提坏账准备 | B26: =B28+B29 -> 0 | C26: =C28+C29 -> #VALUE! | D26: =D28+D29 -> 0 | E26: =ROUND(D26/B26*100,2) -> #DIV/0! | F26: =F28+F29 -> 0 | G26: =G28+G29 -> 0 | H26: =H28+H29 -> #VALUE! | I26: =I28+I29 -> 0 | J26: =ROUND(I26/G26*100,2) -> #DIV/0! | K26: =K28+K29 -> 0
A27: 其中：
C28: =ROUND(B28/$B$24*100,2) -> #VALUE! | E28: =ROUND(D28/B28*100,2) -> #DIV/0! | F28: =B28-D28 -> 0 | H28: =ROUND(G28/$G$24*100,2) -> #VALUE! | J28: =ROUND(I28/G28*100,2) -> #DIV/0! | K28: =G28-I28 -> 0
C29: =ROUND(B29/$B$24*100,2) -> #VALUE! | E29: =ROUND(D29/B29*100,2) -> #DIV/0! | F29: =B29-D29 -> 0 | H29: =ROUND(G29/$G$24*100,2) -> #VALUE! | J29: =ROUND(I29/G29*100,2) -> #DIV/0! | K29: =G29-I29 -> 0
A30: 按组合 计提坏账准备 | B30: =B32+B33 -> 0 | C30: =C32+C33 -> #VALUE! | D30: =D32+D33 -> 0 | F30: =F32+F33 -> 0 | G30: =G32+G33 -> 0 | H30: =H32+H33 -> #VALUE! | I30: =I32+I33 -> 0 | J30: =ROUND(I30/G30*100,2) -> #DIV/0! | K30: =K32+K33 -> 0
A31: 其中：
C32: =ROUND(B32/$B$24*100,2) -> #VALUE! | E32: =ROUND(D32/B32*100,2) -> #DIV/0! | F32: =B32-D32 -> 0 | H32: =ROUND(G32/$G$24*100,2) -> #VALUE! | J32: =ROUND(I32/G32*100,2) -> #DIV/0! | K32: =G32-I32 -> 0
C33: =ROUND(B33/$B$24*100,2) -> #VALUE! | E33: =ROUND(D33/B33*100,2) -> #DIV/0! | F33: =B33-D33 -> 0 | H33: =ROUND(G33/$G$24*100,2) -> #VALUE! | J33: =ROUND(I33/G33*100,2) -> #DIV/0! | K33: =G33-I33 -> 0
A34: 合 计 | B34: =B30+B26 -> 0 | C34: =C30+C26 -> #VALUE! | D34: =D30+D26 -> 0 | E34: =ROUND(D34/B34*100,2) -> #DIV/0! | F34: =F30+F26 -> 0 | H34: =H30+H26 -> #VALUE! | J34: =ROUND(I34/G34*100,2) -> #DIV/0! | K34: =K30+K26 -> 0
A35: 按单项计提坏账准备：
A36: 名 称 | B36: 2019.12.31
B37: 账面余额 | C37: 坏账准备 | D37: 预期信用损失率(%) | E37: 计提理由
D38: =C38/B38*100 -> #DIV/0!
D39: =C39/B39*100 -> #DIV/0!
A40: 合 计 | B40: =SUM(B38:B39) -> 0 | C40: =SUM(C38:C39) -> 0 | D40: =C40/B40*100 -> #DIV/0! | E40: /
A41: 按组合计提坏账准备：
A42: 组合计提项目：XXX
B43: 2018.12.31
B44: 应收账款 | C44: 坏账准备 | D44: 预期信用损失率(%)
A45: 1年以内 | D45: =C45/B45*100 -> #DIV/0!
A46: 1至2年 | D46: =C46/B46*100 -> #DIV/0!
A47: 2至3年 | D47: =C47/B47*100 -> #DIV/0!
A48: …… | D48: =C48/B48*100 -> #DIV/0!
A49: 合 计 | B49: =SUM(B45:B48) -> 0 | C49: =SUM(C45:C48) -> 0 | D49: =C49/B49*100 -> #DIV/0!
A50: 【注：若采用三阶段模型对长期应收款计提坏账准备，请参考其他应收款坏账准备的披露。】
A51: 说明：2018年12月31日，坏账准备的计提情况。
A52: （3）本期计提、收回或转回的坏账准备情况
B53: 坏账准备金额
A54: 2018.12.31 | B54: 100
A55: 首次执行新金融工具准则的调整金额
A57: 2019.01.01 | B57: =B54+B55 -> 100
A58: 本期计提
A59: 本期收回或转回 | B59: 100
A60: 本期核销
A61: [本期转销]
A62: [其他]
A63: 2019.12.31 | B63: =B57+B58-B59+B60 -> 0
A64: （4）长期应收款逾期情况分析
A65: 逾 期 | B65: 2019.12.31 | C65: 2018.12.31
A66: 1年以内
A67: 1至2年
A68: 2至3年
A69: 3年以上
A70: 合 计 | B70: =SUM(B66:B69) -> 0 | C70: =SUM(C66:C69) -> 0
A71: 说明：（逾期客户的名称、逾期年限、逾期原因等）
A72: （5）终止确认的长期应收款情况
A73: （因资产转移而终止确认的长期应收款，列示资产转移的方式、终止确认的长期应收款金额，以及与终止确认相关的利得或损失。）
A74: 项 目 | B74: 转移方式 | C74: 终止确认金额 | D74: 与终止确认相关的利得或损失
A78: 合 计 | C78: =C75+C76+C77 -> 0 | D78: =D75+D76+D77 -> 0
A79: 说明：
A80: （6）转移长期应收款且继续涉入形成的资产、负债的金额
A81: （转移长期应收款且继续涉入的，应披露资产转移方式、分项列示继续涉入形成的资产、负债的金额。）
A82: 项 目 | B82: 期末数
A83: 资产：
A85: 资产小计 | B85: =B84 -> 0
A86: 负债：
A88: 负债小计 | B88: =B87 -> 0
A89: 说明：
A90: （资产转移方式；未全部终止确认的被转移金融资产与相关负债之间的关系，已终止确认的金融资产继续涉入的性质及相关风险的信息。）
A91: X、设定受益计划净资产（不适用删除）
A92: 项 目 | B92: 2018.12.31 | C92: 本期增加 | D92: 本期减少 | E92: 2019.12.31
A93: 设定受益计划净资产
A94: 符合设定受益计划条件的其他长期职工福利的净资产（不适用删除）
A95: 合 计
A96: 【提示：需要按照附注五、45中的披露格式披露设定受益计划相关信息。】

Sheet RP 031
A1: 公司名称 | B1: =基础信息!B6 -> 0
A2: 财务期间 | B2: =基础信息!B9 -> 0
A3: 内容 | B3: 设定受益计划净资产
A4: （1）项目分析
A5: 项 目 | B5: 期初数 | C5: 本期增加 | D5: 本期减少 | E5: 期末数
A6: 设定受益计划净资产 | E6: =B6+C6-D6 -> 0
E7: =B7+C7-D7 -> 0
A8: 符合设定受益计划条件的其他长期职工福利的净资产（不适用删除） | E8: =B8+C8-D8 -> 0
A9: 合 计 | B9: =SUM(B6:B8) -> 0 | C9: =SUM(C6:C8) -> 0 | D9: =SUM(D6:D8) -> 0 | E9: =SUM(E6:E8) -> 0
A10: 报表金额 | E10: ='RP 006'!E49 -> 0
E11: =E9-E10 -> 0
E12: =IF(E11=0,"OK","NO") -> OK
A13: 【提示：需要按照五、46中的披露格式披露设定收益计划相关信息。】

Sheet RP 032
A1: 公司名称 | B1: =基础信息!B6 -> 0
A2: 财务期间 | B2: =基础信息!B9 -> 0
A3: 内容 | B3: 长期股权投资
A4: 被投资单位 | B4: 期初余额 | C4: 本期增减变动 | K4: 期末余额 | L4: 减值准备期末余额
C5: 追加投资 | D5: 减少投资 | E5: 权益法下确认的投资损益 | F5: 其他综合收益调整 | G5: 其他权益变动 | H5: 宣告发放现金股利或利润 | I5: 计提减准备值 | J5: 其他
A6: ①合营企业
A7: …
A9: 小计
A10: ②联营企业
A11: …
A16: 小计
A17: 合 计
A18: 报表金额 | K18: ='RP 006'!E50 -> 0 | L18: ='RP 006'!E51 -> 0
K19: =K17-K18 -> 0 | L19: =L17-L18 -> 0
K20: =IF(K19=0,"OK","NO") -> OK | L20: =IF(L19=0,"OK","NO") -> OK
A22: （1）重要的合营企业或联营企业
A23: 合营企业或联营企业名称 | B23: 主要经营地 | C23: 注册地 | D23: 业务性质 | E23: 持股比例(%) | G23: 对合营企业或联营企业投资的会计处理方法
E24: 直接 | F24: 间接
A25: ①合营企业
A29: ②联营企业
A31: 可无限量添加行
A33: 说明：
A34: （1）持股比例不同于表决权比例的，应说明表决权比例及差异原因。
A35: （2）持有其他主体20%以下表决权但具有重大影响，或者持有其他主体20%或以上表决权但不具有重大影响的，应披露相关判断和依据。
A36: （2）重要合营企业的主要财务信息：（划分为持有待售的除外）
A37: （主要财务信息按照权益法调整后的金额披露；）
A38: （“调整事项”包括投资形成的正商誉、抵消的未实现内部交易损益、减值准备等事项；）
A39: （如果母公司为投资性主体，无需披露下列财务信息。）
A40: 项 目 | B40: （A公司） | D40: （B公司） | F40: （C公司）
B41: 期末数 | C41: 期初数 | D41: 期末数 | E41: 期初数 | F41: 期末数 | G41: 期初数
A42: 流动资产
A43: 其中：现金和现金等价物
A44: 非流动资产
A45: 资产合计
A46: 流动负债
A47: 非流动负债
A48: 负债合计
A49: 净资产
A50: 其中：少数股东权益
A51: 归属于母公司的所有制权益
A52: 按持股比例计算的净资产份额
A53: 调整事项
... A59: 存在公开报价的权益投资的公允价值
A61: 项 目 | B61: （A公司） | D61: （B公司） | F61: （C公司）
B62: 本期发生额 | C62: 上期发生额 | D62: 本期发生额 | E62: 上期发生额 | F62: 本期发生额 | G62: 上期发生额
A63: 营业收入
A64: 财务费用
A65: 所得税费用
A66: 净利润
A67: 终止经营的净利润
A68: 其他综合收益
A69: 综合收益总额
A70: 企业本期收到的来自合营企业的股利
A72: （注：存在终止经营的净利润的，还应当在本表中单列项目披露）
A73: 说明：
A74: （3）重要联营企业的主要财务信息：（持有待售的除外）
A75: （主要财务信息按照权益法调整后的金额披露；）
... A77: （如果母公司为投资性主体，无需披露下列财务信息。）
A78: 项 目 | B78: （A公司） | D78: （B公司） | F78: （C公司）
B79: 期末数 | C79: 期初数 | D79: 期末数 | E79: 期初数 | F79: 期末数 | G79: 期初数
A80: 流动资产
A81: 非流动资产
A82: 资产合计
A83: 流动负债
A84: 非流动负债
A85: 负债合计
A86: 净资产
A87: 其中：少数股东权益
A88: 归属于母公司的所有制权益
A89: 按持股比例计算的净资产份额
A90: 调整事项
A91: 其中：商誉
... A96: 存在公开报价的权益投资的公允价值
A98: 项 目 | B98: （A公司） | D98: （B公司） | F98: （C公司）
B99: 本期发生额 | C99: 上期发生额 | D99: 本期发生额 | E99: 上期发生额 | F99: 本期发生额 | G99: 上期发生额
A100: 营业收入
A101: 净利润
A102: 终止经营的净利润
A103: 其他综合收益
A104: 综合收益总额
A105: 企业本期收到的来自联营企业的股利
A106: （注：存在终止经营的净利润的，还应当在本表中单列项目披露）
A107: 说明：
A108: （4）其他不重要合营企业和联营企业的汇总财务信息
A109: 项 目 | B109: 期末数/ | C109: 本期发生额 | D109: 期初数/ | E109: 上期发生额
A110: 合营企业：
A111: 投资账面价值合计
A112: 下列各项按持股比例计算的合计数
A113: 净利润
A114: 其他综合收益
A115: 综合收益总额
A116: 联营企业：
A117: 投资账面价值合计
A118: 下列各项按持股比例计算的合计数
A119: 净利润
A120: 其他综合收益
A121: 综合收益总额
A123: （8）重要的共同经营
A124: 共同经营名称 | B124: 主要经营地 | C124: 注册地 | D124: 业务性质 | E124: 持股比例/享有的份额(%)
E125: 直接 | F125: 间接
...

Sheet RP 033
A1: 公司名称 | B1: =基础信息!B6 -> 0
A2: 财务期间 | B2: =基础信息!B9 -> 0
A3: 内容 | B3: 其他权益工具投资
A6: 项目 | B6: 2019.12.31 | C6: 2018.12.31
C7: -
C8: -
C9: -
A10: 合 计 | B10: =SUM(B7:B9) -> 0 | C10: =SUM(C7:C9) -> 0
A11: 报表金额 | B11: ='RP 006'!E53 -> 0
B12: =B10-B11 -> 0
B13: =IF(B12=0,"OK","NO") -> OK
A15: [披露企业将上述各项目指定为以公允价值计量且其变动计入其他综合收益的原因。例如：
A16: 由于[项目名称1]是本集团出于战略目的而计划长期持有的投资，因此本集团将其指定为以公允价值计量且其变动计入其他综合收益的金融资产。]
A17: 项 目 | B17: 本期确认的股利收入 | C17: 累计利得 | D17: 累计损失 | E17: 其他综合收益转入留存收益的金额 | F17: 转入原因
A21: [企业本期终止确认了其他权益工具投资的，应披露处置该权益工具投资的原因，该权益工具投资在终止确认时的公允价值及该权益工具投资在终止确认时的累计利得或损失。]

Sheet RP 034
A1: 公司名称 | B1: =基础信息!B6 -> 0
A2: 财务期间 | B2: =基础信息!B9 -> 0
A3: 内容 | B3: 其他非流动金融资产
A6: 种类 | B6: 2018.12.31 | C6: 2017.12.31
A7: 债务工具投资 | C7: -
A8: 权益工具投资 | C8: -
A9: 指定为以公允价值计量且其变动计入当期损益的金融资产 | C9: -
A10: 其他 | C10: -
A11: 合 计 | B11: =SUM(B7:B10) -> 0 | C11: =SUM(C7:C10) -> 0
A12: 报表金额 | B12: ='RP 006'!E54 -> 0
B13: =B11-B12 -> 0
B14: =IF(B13=0,"OK","NO") -> OK

Sheet RP 035
A1: 公司名称 | B1: =基础信息!B6 -> 0
A2: 财务期间 | B2: =基础信息!B9 -> 0
A3: 内容 | B3: 投资性房地产
A4: （1）按成本计量的投资性房地产（如无按公允价值计量的投资性房地产，删除此标题）
A5: 项 目 | B5: 房屋、建筑物 | C5: 土地使用权 | D5: 在建工程 | E5: 合计
A6: 一、账面原值
A7: 1.期初余额 | E7: =SUM(B7:D7) -> 0
A8: 2.本期增加金额 | B8: =SUM(B9:B12) -> 0 | C8: =SUM(C9:C12) -> 0 | D8: =SUM(D9:D12) -> 0 | E8: =SUM(E9:E12) -> 0
A9: （1）外购
A10: （2）存货\固定资产\在建工程转入
A11: （3）企业合并增加
A12: 可无限量添加行
A13: 3.本期减少金额 | B13: =SUM(B14:B16) -> 0 | C13: =SUM(C14:C16) -> 0 | D13: =SUM(D14:D16) -> 0 | E13: =SUM(E14:E16) -> 0
A14: （1）处置
A15: （2）其他转出
A16: 可无限量添加行
A17: 4.期末余额 | B17: =B7+B8-B13 -> 0 | C17: =C7+C8-C13 -> 0 | D17: =D7+D8-D13 -> 0 | E17: =E7+E8-E13 -> 0
A18: 二、累计折旧和累计摊销
A19: 1.期初余额
A20: 2.本期增加金额 | B20: =SUM(B21:B24) -> 0 | C20: =SUM(C21:C24) -> 0 | D20: =SUM(D21:D24) -> 0 | E20: =SUM(E21:E24) -> 0
A21: （1）计提或摊销
A22: （2）企业合并增加
A23: （3）其他增加
A24: 可无限量添加行
A25: 3.本期减少金额 | B25: =SUM(B26:B28) -> 0 | C25: =SUM(C26:C28) -> 0 | D25: =SUM(D26:D28) -> 0 | E25: =SUM(E26:E28) -> 0
A26: （1）处置
A27: （2）其他转出
A28: 可无限量添加行
A29: 4.期末余额 | B29: =B19+B20-B25 -> 0 | C29: =C19+C20-C25 -> 0 | D29: =D19+D20-D25 -> 0 | E29: =E19+E20-E25 -> 0
A30: 三、减值准备
A31: 1.期初余额
A32: 2.本期增加金额 | B32: =SUM(B33:B35) -> 0 | C32: =SUM(C33:C35) -> 0 | D32: =SUM(D33:D35) -> 0 | E32: =SUM(E33:E35) -> 0
A33: （1）计提
A34: （2）其他增加
A35: 可无限量添加行
A36: 3、本期减少金额 | B36: =SUM(B37:B39) -> 0 | C36: =SUM(C37:C39) -> 0 | D36: =SUM(D37:D39) -> 0 | E36: =SUM(E37:E39) -> 0
A37: （1）处置
A38: （2）其他转出
A39: 可无限量添加行
A40: 4.期末余额
A41: 四、账面价值
A42: 1.期末账面价值
A43: 2.期初账面价值
A44: 报表金额 | E44: ='RP 006'!E57 -> 0
E45: =E42-E44 -> 0
E46: =IF(E45=0,"OK","NO") -> OK
A49: （2）按公允价值计量的投资性房地产（不适用的删除）
A50: （采用公允价值计量模式的投资性房地产，分类列示期初余额、期末余额和本期增减变动情况。）
A51: 项 目 | B51: 房屋、建筑物 | C51: 土地使用权 | D51: 在建工程 | E51: 合计
A52: 一、期初余额
A53: 二、本期变动
A54: 加：外购
A55: 存货\固定资产\在建工程转入
A56: 企业合并增加
A57: 减：处置
A58: 其他转出
A59: 公允价值变动
A61: 三、期末余额
A64: （3）未办妥产权证书的情况
A65: （披露未办妥产权证书的投资性房地产账面价值及原因。）
A66: 项 目 | B66: 账面价值 | C66: 未办妥产权证书原因
A67: 可无限量添加行
A71: （4）房地产转换情况及改变计量模式的情况
A72: （说明报告期内房地产转换或改变计量模式的情况、理由，以及对损益或所有者权益的影响。
A73: 房地产开发企业列示出租开发产品时，应披露出租开发产品的成本、租赁合同主要条款等内容。对重要的出租房产应单项披露，非重要或零星的出租房产可采用合并披露。）

Sheet RP 036
A1: 公司名称 | B1: =基础信息!B6 -> 0
A2: 财务期间 | B2: =基础信息!B9 -> 0
A3: 内容 | B3: 固定资产
A4: 项 目 | B4: 期末数 | C4: 转入清理的原因
A5: 固定资产 | B5: ='RP 036-1'!F41 -> 0
A6: 固定资产清理 | B6: ='RP 036-2'!B7 -> 0
A7: 合 计 | B7: =SUM(B5:B6) -> 0
A8: 报表金额 | B8: ='RP 006'!E62 -> 0
B9: =B7-B8 -> 0
B10: =IF(B9=0,"OK","NO") -> OK

Sheet RP 036-1
A1: 公司名称 | B1: =基础信息!B6 -> 0
A2: 财务期间 | B2: =基础信息!B9 -> 0
A3: 内容 | B3: 固定资产及累计折旧
A4: （1）固定资产情况
A5: 项 目 | B5: 房屋及建筑物 | C5: 机器设备 | D5: 运输设备 | E5: …… | F5: 合 计
A6: 一、账面原值： | F6: =SUM(B6:E6) -> 0
A7: 1.期初余额 | F7: =SUM(B7:E7) -> 0
A8: 2.本期增加金额 | B8: =SUM(B9:B12) -> 0 | C8: =SUM(C9:C12) -> 0 | D8: =SUM(D9:D12) -> 0 | E8: =SUM(E9:E12) -> 0 | F8: =SUM(B8:E8) -> 0
A9: （1）购置 | F9: =SUM(B9:E9) -> 0
A10: （2）在建工程转入 | F10: =SUM(B10:E10) -> 0
A11: （3）企业合并增加 | F11: =SUM(B11:E11) -> 0
A12: …… | F12: =SUM(B12:E12) -> 0
A13: 3.本期减少金额 | F13: =SUM(B13:E13) -> 0
A14: （1）处置或报废 | F14: =SUM(B14:E14) -> 0
A15: （2）其他减少 | F15: =SUM(B15:E15) -> 0
A16: …… | F16: =SUM(B16:E16) -> 0
A17: 4.期末余额 | F17: =SUM(B17:E17) -> 0
A18: 二、累计折旧 | F18: =SUM(B18:E18) -> 0
A19: 1.期初余额 | F19: =SUM(B19:E19) -> 0
A20: 2.本期增加金额 | F20: =SUM(B20:E20) -> 0
... A42: 2.期初账面价值 | F42: =SUM(B42:E42) -> 0
A43: 核对金额 | F43: ='RP 036'!B5 -> 0
F44: =F41-F43 -> 0
F45: =IF(F44=0,"OK","NO") -> OK
A46: 说明：
A47: ①（抵押、担保的固定资产情况）
A48: （注：本期发生以明显高于账面价值的价格出售固定资产交易的，应详细说明交易作价的基础和依据，如：估值模型、重要参数的选取依据和估值过程，以及必要的敏感性分析。）
A49: 【提示：在“其他减少”中列示本期收到的政府补助冲减固定资产账面价值的金额。对于冲减无形资产或其他资产账面价值的政府补助，比照披露。】
A50: （提示：对于冲减无形资产或其他资产账面价值的政府补助，在无形资产或其他资产的科目附注中比照上述要求进行披露。）
A51: （2）暂时闲置的固定资产情况
A52: 项 目 | B52: 账面原值 | C52: 累计折旧 | D52: 减值准备 | E52: 账面价值 | F52: 备注
A53: 房屋及建筑物 | E53: =B53-C53-D53 -> 0
A54: 机器设备 | E54: =B54-C54-D54 -> 0
A55: 电子设备 | E55: =B55-C55-D55 -> 0
A56: 运输设备 | E56: =B56-C56-D56 -> 0
A57: 可无限量添加行 | E57: =B57-C57-D57 -> 0
A58: 合 计 | B58: =SUM(B53:B57) -> 0 | C58: =SUM(C53:C57) -> 0 | D58: =SUM(D53:D57) -> 0 | E58: =SUM(E53:E57) -> 0
A61: （3）通过融资租赁租入的固定资产情况
A62: 项 目 | B62: 账面原值 | C62: 累计折旧 | D62: 减值准备 | E62: 账面价值
A63: 房屋及建筑物 | E63: =B63-C63-D63 -> 0
A64: 机器设备 | E64: =B64-C64-D64 -> 0
A65: 电子设备 | E65: =B65-C65-D65 -> 0
A66: 运输设备 | E66: =B66-C66-D66 -> 0
A67: 可无限量添加行 | E67: =B67-C67-D67 -> 0
A68: 合 计 | B68: =SUM(B63:B67) -> 0 | C68: =SUM(C63:C67) -> 0 | D68: =SUM(D63:D67) -> 0 | E68: =SUM(E63:E67) -> 0
A71: （4）通过经营租赁租出的固定资产
A72: 项 目 | B72: 账面价值
A73: 房屋及建筑物
A74: 机器设备
A75: 电子设备
A76: 运输设备
A77: 可无限量添加行
A78: 合 计 | B78: =SUM(B73:B77) -> 0
A81: （5）未办妥产权证书的固定资产情况
A82: （披露期末未办妥产权证书的固定资产账面价值及原因。）
A83: 项 目 | B83: 账面价值 | C83: 未办妥产权证书原因
A87: 说明：

Sheet RP 036-2
A1: 公司名称 | B1: =基础信息!B6 -> 0
A2: 财务期间 | B2: =基础信息!B9 -> 0
A3: 内容 | B3: 固定资产清理
A4: 项 目 | B4: 期末数 | C4: 转入清理的原因
A7: 合 计 | B7: =SUM(B5:B6) -> 0
A8: 核对金额 | B8: ='RP 036'!B6 -> 0
B9: =B7-B8 -> 0
B10: =IF(B9=0,"OK","NO") -> OK
A11: 说明：（转入固定资产清理起始时间已超过1年的固定资产清理进展情况）

Sheet RP 037
A1: 公司名称 | B1: =基础信息!B6 -> 0
A2: 财务期间 | B2: =基础信息!B9 -> 0
A3: 内容 | B3: 在建工程
A4: 项 目 | B4: 期末数
A5: 在建工程 | B5: ='RP 037-1'!D10 -> 0
A6: 工程物资 | B6: ='RP 037-2'!B11 -> 0
A7: 合 计 | B7: =B6+B5 -> 0
A8: 报表金额 | B8: ='RP 006'!E63 -> 0
B9: =B7-B8 -> 0
B10: =IF(B9=0,"OK","NO") -> OK

Sheet RP 037-1
A1: 公司名称 | B1: =基础信息!B6 -> 0
A2: 财务期间 | B2: =基础信息!B9 -> 0
A3: 内容 | B3: 在建工程
A4: （1）在建工程明细
A5: 项 目 | B5: 期末数
B6: 账面余额 | C6: 减值准备 | D6: 账面净值
D7: =B7-C7 -> 0
D8: =B8-C8 -> 0
D9: =B9-C9 -> 0
A10: 合 计 | B10: =SUM(B7:B9) -> 0 | C10: =SUM(C7:C9) -> 0 | D10: =SUM(D7:D9) -> 0
A11: 核对金额 | D11: ='RP 037'!B5 -> 0
D12: =D10-D11 -> 0
D13: =IF(D12=0,"OK","NO") -> OK
A16: （2）重要在建工程项目变动情况
A17: 工程名称 | B17: 期初数 | C17: 本期增加 | D17: 转入固定资产 | E17: 其他减少 | F17: 利息资本化累计金额 | G17: 其中：本期利息资本化金额 | H17: 本期利息资本化率% | I17: 期末数
A20: 合 计 | B20: =SUM(B18:B19) -> 0 | C20: =SUM(C18:C19) -> 0 | D20: =SUM(D18:D19) -> 0 | E20: =SUM(E18:E19) -> 0 | F20: =SUM(F18:F19) -> 0 | G20: =SUM(G18:G19) -> 0 | H20: =SUM(H18:H19) -> 0 | I20: =SUM(I18:I19) -> 0
A21: 重大在建工程项目变动情况（续）：
A22: 工程名称 | B22: 预算数 | C22: 工程累计投入占预算比例% | D22: 工程进度 | E22: 资金来源
A25: 合 计 | B25: =SUM(B23:B24) -> 0 | C25: =SUM(C23:C24) -> 0 | D25: =SUM(D23:D24) -> 0 | E25: =SUM(E23:E24) -> 0
A26: （注：工程进度不一定是投入进度）
A27: 在建工程项目变动情况的说明：
A28: （资金来源应区分募股资金、金融机构贷款和自筹、其他来源等）
A31: （3）在建工程减值准备
A32: 项 目 | B32: 本期计提金额 | C32: 计提原因
A35: 合 计 | B35: =SUM(B33:B34) -> 0
A36: 说明： （分项列示本期计提的在建工程减值准备金额及计提原因。）

Sheet RP 037-2
A1: 公司名称 | B1: =基础信息!B6 -> 0
A2: 财务期间 | B2: =基础信息!B9 -> 0
A3: 内容 | B3: 工程物资
A4: 工程物资
A5: 项 目 | B5: 期末数
A6: 专用材料
A7: 专用设备
A8: 工器具
B9: =SUM(B6:B8) -> 0
A10: 工程物资减值准备
A11: 合 计 | B11: =B9-B10 -> 0
A12: 核对金额 | B12: ='RP 037'!B6 -> 0
B13: =B11-B12 -> 0
B14: =IF(B13=0,"OK","NO") -> OK

Sheet RP 038
A1: 公司名称 | B1: =基础信息!B6 -> 0
A2: 财务期间 | B2: =基础信息!B9 -> 0
A3: 内容 | B3: 生产性生物资产
A4: 项 目 | B4: 种植业 | D4: 畜牧养殖业 | F4: 林业 | H4: 水产业 | J4: 合计
B5: 类别 | C5: …… | D5: 类别 | E5: …… | F5: 类别 | G5: …… | H5: 类别 | I5: ……
A6: 一、账面原值 | J6: =SUM(B6:I6) -> 0
A7: 1.期初余额 | J7: =SUM(B7:I7) -> 0
A8: 2.本期增加金额 | B8: =SUM(B9:B11) -> 0 | C8: =SUM(C9:C11) -> 0 | D8: =SUM(D9:D11) -> 0 | E8: =SUM(E9:E11) -> 0 | F8: =SUM(F9:F11) -> 0 | G8: =SUM(G9:G11) -> 0 | H8: =SUM(H9:H11) -> 0 | I8: =SUM(I9:I11) -> 0 | J8: =SUM(B8:I8) -> 0
A9: （1）外购 | J9: =SUM(B9:I9) -> 0
A10: （2）自行培育 | J10: =SUM(B10:I10) -> 0
A11: （3）其他增加 | J11: =SUM(B11:I11) -> 0
A12: 3.本期减少金额 | J12: =SUM(B12:I12) -> 0
A13: （1）处置 | J13: =SUM(B13:I13) -> 0
A14: （2）其他 | J14: =SUM(B14:I14) -> 0
A15: …… | J15: =SUM(B15:I15) -> 0
A16: 4.期末余额 | J16: =SUM(B16:I16) -> 0
A17: 二、累计折旧 | J17: =SUM(B17:I17) -> 0
A18: 1.期初余额 | J18: =SUM(B18:I18) -> 0
A19: 2.本期增加金额 | J19: =SUM(B19:I19) -> 0
A20: （1）计提 | J20: =SUM(B20:I20) -> 0
... A39: 2.期初账面价值 | J39: =SUM(B39:I39) -> 0
A40: 报表金额 | J40: ='RP 006'!E64 -> 0
J41: =J38-J40 -> 0
J42: =IF(J41=0,"OK","NO") -> OK
A44: （2）以公允价值计量
A45: 项 目 | B45: 种植业 | D45: 畜牧养殖业 | F45: 林业 | H45: 水产业 | J45: 合计
B46: 类别 | C46: …… | D46: 类别 | E46: …… | F46: 类别 | G46: …… | H46: 类别 | I46: ……
A47: 一、期初余额
A48: 二、本期变动
A49: 加：外购
A50: 自行培育
A51: 企业合并增加
A52: 减：处置
A53: 其他转出
A54: 公允价值变动
A55: ……
A56: 三、期末余额
A57: 报表金额 | J57: ='RP 006'!E64 -> 0
J58: =J55-J57 -> 0
J59: =IF(J58=0,"OK","NO") -> OK
A61: 说明：（如有天然起源的生物资产，还应披露该资产的类别、取得方式和数量等。各类生产性生物资产的预计使用寿命、预计净残值、折旧方法、累计折旧和减值准备累计金额。与生物资产相关的风险情况与管理措施。）

Sheet RP 039
A1: 公司名称 | B1: =基础信息!B6 -> 0
A2: 财务期间 | B2: =基础信息!B9 -> 0
A3: 内容 | B3: 无形资产
A4: （1）无形资产情况
A5: 项目 | B5: 土地使用权 | C5: 专利权 | D5: 非专利技术 | E5: …… | F5: 合计
A6: 一、账面原值 | F6: =SUM(B6:E6) -> 0
A7: 1.期初余额 | F7: =SUM(B7:E7) -> 0
A8: 2.本期增加金额 | B8: =SUM(B9:B13) -> 0 | C8: =SUM(C9:C13) -> 0 | D8: =SUM(D9:D13) -> 0 | E8: =SUM(E9:E13) -> 0 | F8: =SUM(B8:E8) -> 0
A9: （1）购置 | F9: =SUM(B9:E9) -> 0
A10: （2）内部研发 | F10: =SUM(B10:E10) -> 0
A11: （3）企业合并增加 | F11: =SUM(B11:E11) -> 0
A12: （4）其他增加 | F12: =SUM(B12:E12) -> 0
A13: …… | F13: =SUM(B13:E13) -> 0
A14: 3.本期减少金额 | B14: =SUM(B15:B17) -> 0 | C14: =SUM(C15:C17) -> 0 | D14: =SUM(D15:D17) -> 0 | E14: =SUM(E15:E17) -> 0 | F14: =SUM(F15:F17) -> 0
A15: （1）处置 | F15: =SUM(B15:E15) -> 0
A16: （2）其他减少 | F16: =SUM(B16:E16) -> 0
A17: …… | F17: =SUM(B17:E17) -> 0
A18: 4.期末余额 | B18: =B7+B8-B14 -> 0 | C18: =C7+C8-C14 -> 0 | D18: =D7+D8-D14 -> 0 | E18: =E7+E8-E14 -> 0 | F18: =SUM(B18:E18) -> 0
A19: 二、累计摊销 | F19: =SUM(B19:E19) -> 0
A20: 1.期初余额 | F20: =SUM(B20:E20) -> 0
A21: 2.本期增加金额 | B21: =SUM(B22:B24) -> 0 | C21: =SUM(C22:C24) -> 0 | D21: =SUM(D22:D24) -> 0 | E21: =SUM(E22:E24) -> 0 | F21: =SUM(B21:E21) -> 0
A22: （1）计提 | F22: =SUM(B22:E22) -> 0
A23: （2）其他增加 | F23: =SUM(B23:E23) -> 0
A24: …… | F24: =SUM(B24:E24) -> 0
A25: 3.本期减少金额 | B25: =SUM(B26:B28) -> 0 | C25: =SUM(C26:C28) -> 0 | D25: =SUM(D26:D28) -> 0 | E25: =SUM(E26:E28) -> 0 | F25: =SUM(B25:E25) -> 0
A26: （1）处置 | F26: =SUM(B26:E26) -> 0
A27: （2）其他减少 | F27: =SUM(B27:E27) -> 0
A28: …… | F28: =SUM(B28:E28) -> 0
A29: 4.期末余额 | B29: =B7+B8-B14 -> 0 | C29: =C7+C8-C14 -> 0 | D29: =D7+D8-D14 -> 0 | E29: =E7+E8-E14 -> 0 | F29: =SUM(B29:E29) -> 0
A30: 三、减值准备 | F30: =SUM(B30:E30) -> 0
A31: 1.期初余额 | F31: =SUM(B31:E31) -> 0
A32: 2.本期增加金额 | B32: =SUM(B33:B35) -> 0 | C32: =SUM(C33:C35) -> 0 | D32: =SUM(D33:D35) -> 0 | E32: =SUM(E33:E35) -> 0 | F32: =SUM(B32:E32) -> 0
A33: （1）计提 | F33: =SUM(B33:E33) -> 0
A34: （2）其他增加 | F34: =SUM(B34:E34) -> 0
A35: …… | F35: =SUM(B35:E35) -> 0
A36: 3.本期减少金额 | B36: =SUM(B37:B39) -> 0 | C36: =SUM(C37:C39) -> 0 | D36: =SUM(D37:D39) -> 0 | E36: =SUM(E37:E39) -> 0 | F36: =SUM(B36:E36) -> 0
A37: （1）处置 | F37: =SUM(B37:E37) -> 0
A38: （2）其他减少 | F38: =SUM(B38:E38) -> 0
A39: …… | F39: =SUM(B39:E39) -> 0
A40: 4.期末余额 | B40: =B31+B32-B36 -> 0 | C40: =C31+C32-C36 -> 0 | D40: =D31+D32-D36 -> 0 | E40: =E31+E32-E36 -> 0 | F40: =F31+F32-F36 -> 0
A41: 四、账面价值 | F41: =SUM(B41:E41) -> 0
A42: 1.期末账面价值 | B42: =B18-B29-B40 -> 0 | C42: =C18-C29-C40 -> 0 | D42: =D18-D29-D40 -> 0 | E42: =E18-E29-E40 -> 0 | F42: =SUM(B42:E42) -> 0
A43: 2.期初账面价值 | B43: =B7-B20-B31 -> 0 | C43: =C7-C20-C31 -> 0 | D43: =D7-D20-D31 -> 0 | E43: =E7-E20-E31 -> 0 | F43: =SUM(B43:E43) -> 0
A44: 报表金额 | F44: ='RP 006'!E68 -> 0
F45: =E42-F44 -> 0
F46: =IF(F45=0,"OK","NO") -> OK
A47: 说明：
A48: ①期末，通过内部研发形成的无形资产占无形资产余额的比例为______。
A49: ②（本集团使用寿命不确定的无形资产的判断依据。）
A50: ③（抵押、担保的土地使用权）
A51: ④（无形资产减值准备计提及减少原因）
A52: ⑤（本期发生以明显高于账面价值的价格出售无形资产交易的，应详细说明交易作价的基础和依据，如：估值模型、重要参数的选取依据和估值过程，以及必要的敏感性分析。）
A55: （2）未办妥产权证书的土地使用权情况
A56: （披露未办妥产权证书的土地使用权账面价值及原因。）
A57: 项 目 | B57: 账面价值 | C57: 未办妥产权证书原因

Sheet RP 040
A1: 公司名称 | B1: =基础信息!B6 -> 0
A2: 财务期间 | B2: =基础信息!B9 -> 0
A3: 内容 | B3: 开发支出
A4: 项 目 | B4: 期初数 | C4: 本期增加 | E4: 本期减少 | G4: 期末数
C5: 内部开发支出 | D5: 其他增加 | E5: 确认为无形资产 | F5: 计入当期损益
A9: 合 计 | B9: =SUM(B6:B8) -> 0 | C9: =SUM(C6:C8) -> 0 | D9: =SUM(D6:D8) -> 0 | E9: =SUM(E6:E8) -> 0 | F9: =SUM(F6:F8) -> 0 | G9: =SUM(G6:G8) -> 0
A10: 报表金额 | G10: ='RP 006'!E69 -> 0
G11: =G9-G10 -> 0
G12: =IF(G11=0,"OK","NO") -> OK
A13: 【增减变动因素可根据实际情况自行添加】
A14: 续：
A15: 项 目 | B15: 资本化开始时点 | C15: 资本化的具体依据 | D15: 截至期末的研发进度
A19: 合 计
A20: 说明：（披露上述项目的资本化开始时点、资本化的具体依据、截至期末的研发进度等。）

Sheet RP 041
A1: 公司名称 | B1: =基础信息!B6 -> 0
A2: 财务期间 | B2: =基础信息!B9 -> 0
A3: 内容 | B3: 商誉
A4: （1）商誉账面原值
A5: 被投资单位名称或形成商誉的事项 | B5: 期初余额 | C5: 本期增加 | E5: 本期减少 | G5: 期末余额
C6: 企业合并形成 | D6: 可无限量添加列 | E6: 处置 | F6: 可无限量添加列
A7: 可无限量添加行 | G7: =B7+C7+D7-E7-F7 -> 0
G8: =B8+C8+D8-E8-F8 -> 0
G9: =B9+C9+D9-E9-F9 -> 0
A10: 合 计 | B10: =SUM(B7:B9) -> 0 | C10: =SUM(C7:C9) -> 0 | D10: =SUM(D7:D9) -> 0 | E10: =SUM(E7:E9) -> 0 | F10: =SUM(F7:F9) -> 0 | G10: =SUM(G7:G9) -> 0
A11: （提示：其他增减变动原因包括境外子公司汇率变化的影响等）
A12: （2）商誉减值准备
A13: 被投资单位名称或形成商誉的事项 | B13: 期初余额 | C13: 本期增加 | E13: 本期减少 | G13: 期末余额
C14: 计提 | D14: 可无限量添加行 | E14: 处置 | F14: 可无限量添加行
A15: 可无限量添加行 | G15: =B15+C15+D15-E15-F15 -> 0
G16: =B16+C16+D16-E16-F16 -> 0
G17: =B17+C17+D17-E17-F17 -> 0
A18: 合 计 | B18: =SUM(B15:B17) -> 0 | C18: =SUM(C15:C17) -> 0 | D18: =SUM(D15:D17) -> 0 | E18: =SUM(E15:E17) -> 0 | F18: =SUM(F15:F17) -> 0 | G18: =SUM(G15:G17) -> 0
A19: 说明：（商誉减值测试过程、参数及商誉减值损失的确认方法）
A20: 本集团采用预计未来现金流现值的方法计算资产组的可收回金额。本集团根据管理层批准的财务预算预计未来5年内现金流量，其后年度采用的现金流量增长率预计为XX%（上期：XX%），不会超过资产组经营业务的长期平均增长率。管理层根据过往表现及其对市场发展的预期编制上述财务预算。计算未来现金流现值所采用的税前折现率为XX%（上期：XX%），已反映了相对于有关分部的风险。根据减值测试的结果，本期期末商誉未发生减值（上期期末：无）。【或：本期期末对商誉计提减值准备XX元（上期期末：XX元）。】
A21: 报表金额 | G21: ='RP 006'!E70 -> 0
G22: =G10-G18-G21 -> 0
G23: =IF(G22=0,"OK","NO") -> OK

Sheet RP 042
A1: 公司名称 | B1: =基础信息!B6 -> 0
A2: 财务期间 | B2: =基础信息!B9 -> 0
A3: 内容 | B3: 长期待摊费用
A4: 项 目 | B4: 期初数 | C4: 本期增加 | D4: 本期减少 | F4: 期末数
D5: 本期摊销 | E5: 其他减少
F6: =B6+C6-D6-E6 -> 0
F7: =B7+C7-D7-E7 -> 0
F8: =B8+C8-D8-E8 -> 0
A9: 合 计 | B9: =SUM(B6:B8) -> 0 | C9: =SUM(C6:C8) -> 0 | D9: =SUM(D6:D8) -> 0 | E9: =SUM(E6:E8) -> 0 | F9: =SUM(F6:F8) -> 0
A10: 报表金额 | F10: ='RP 006'!E71 -> 0
F11: =F9-F10 -> 0
F12: =IF(F11=0,"OK","NO") -> OK
A13: 说明：1年内到期的长期待摊费用X.XX元，详见附注五、11。

Sheet RP 043
A1: 公司名称 | B1: =基础信息!B6 -> 0
A2: 财务期间 | B2: =基础信息!B9 -> 0
A3: 内容 | B3: 递延所得税资产和递延所得税负债
A4: （1）未经抵销的递延所得税资产和递延所得税负债 | F4: s
A5: 项 目 | B5: 期末数 | D5: 期初数
B6: 可抵扣/应纳税暂时性差异 | C6: 递延所得税资产/负债 | D6: 可抵扣/应纳税暂时性差异 | E6: 递延所得税资产/负债
A7: 递延所得税资产：
A8: 资产减值准备
A9: 内部交易未实现利润
A10: 开办费
A11: 可抵扣亏损
A12: 小 计 | B12: =SUM(B8:B11) -> 0 | C12: =SUM(C8:C11) -> 0 | D12: =SUM(D8:D11) -> 0 | E12: =SUM(E8:E11) -> 0
A13: 报表金额 | C13: ='RP 006'!C72 -> 0 | E13: ='RP 002-1'!D39 -> 0
C14: =D12-C13 -> 0 | E14: =F12-E13 -> 0
C15: =IF(C14=0,"OK","NO") -> OK | E15: =IF(E14=0,"OK","NO") -> OK
A16: 项 目 | B16: 期末数 | D16: 期初数
B17: 可抵扣/应纳税暂时性差异 | C17: 递延所得税资产/负债 | D17: 可抵扣/应纳税暂时性差异 | E17: 递延所得税资产/负债
A18: 递延所得税负债：
A19: 非同一控制企业合并资产评估增值
A20: 交易性金融工具、衍生金融工具的估值
A21: 计入其他综合收益的可供出售金融资产公允价值变动
A22: 计入其他综合收益的其他债权投资公允价值变动
A23: 小 计 | B23: =SUM(B19:B22) -> 0 | C23: =SUM(C19:C22) -> 0 | D23: =SUM(D19:D22) -> 0 | E23: =SUM(E19:E22) -> 0
A24: 报表金额 | C24: ='RP 006'!E112 -> 0 | E24: ='RP 002-2'!D29 -> 0
C25: =D23-C24 -> 0 | E25: =F23-E24 -> 0
C26: =IF(C25=0,"OK","NO") -> OK | E26: =IF(E25=0,"OK","NO") -> OK
A28: 说明：其中一年后预期转回的递延所得税资产和递延所得税负债分别为X.XX元、X.XX元。
A29: （2）以抵销后净额列示的递延所得税资产或负债（不适用的删除）
A30: 项 目 | B30: 递延所得税资产和负债期末互抵金额 | C30: 抵销后递延所得税资产或负债期末余额 | D30: 递延所得税资产和负债期初互抵金额 | E30: 抵销后递延所得税资产或负债期初余额
A31: 递延所得税资产
A32: 递延所得税负债
A34: （3）未确认递延所得税资产的可抵扣暂时性差异及可抵扣亏损明细
A35: 项 目 | B35: 期末数 | C35: 期初数
A36: 可抵扣暂时性差异
A37: 可抵扣亏损
A39: 合 计 | B39: X.XX | C39: X.XX
A40: 注：列示由于未来能否获得足够的应纳税所得额具有不确定性，因此没有确认为递延所得税资产的可抵扣暂时性差异和可抵扣亏损。
A41: （4）未确认递延所得税资产的可抵扣亏损将于以下年度到期
A42: 年 份 | B42: 期末数 | C42: 期初数 | D42: 备注
A43: 2019年 | B43: ——
A44: 2020年
A45: 2021年
A46: 2022年
A47: 2023年
A48: 2024年 | C48: ——
A49: 合 计 | B49: X.XX | C49: X.XX
A50: 注：无法在资产负债表日确定全部可抵扣亏损情况的，可只填写能确定部分的金额及其到期年度，并在备注栏予以说明。

Sheet RP 044
A1: 公司名称 | B1: =基础信息!B6 -> 0
A2: 财务期间 | B2: =基础信息!B9 -> 0
A3: 内容 | B3: 其他非流动资产
A4: 项 目 | B4: 期末数
A5: 预付土地出让金
A6: 预付工程款
A7: 预付房屋、设备款
A8: 无形资产预付款
A9: 预付投资款
A10: 委托贷款
A11: 合同取得成本
A12: 合同履约成本
A13: 应收退货成本
A14: 合同资产
A15: 合 计 | B15: =SUM(B5:B14) -> 0
A16: 报表金额 | B16: ='RP 006'!E73 -> 0
B17: =B15-B16 -> 0
B18: =IF(B17=0,"OK","NO") -> OK
A19: 说明：
A21: 1、合同取得成本，初始确认时摊销期限超过一年或一个正常营业周期的项目（考虑合同取得成本减值准备影响）；2、合同履约成本，初始确认时摊销期限超过一年或一个正常营业周期的项目（考虑合同履约成本减值准备影响）；3、附有销售退回条款的销售，确认为资产的应收退货成本，不在一年或一个正常营业周期内出售的项目；4、确认的合同资产，不在一年或一个正常营业周期内收回的项目（考虑合同取得成本减值准备影响）。同一合同下的合同资产和合同负债应当以净额列示，其中净额为借方余额的，应当根据其流动性在“合同资产”或“其他非流动资产”项目中填列。

Sheet RP 045
A1: 公司名称 | B1: =基础信息!B6 -> 0
A2: 财务期间 | B2: =基础信息!B9 -> 0
A3: 内容 | B3: 资产减值准备
A4: 项 目 | B4: 期初 | C4: 本期计提额 | D4: 本期减少额 | F4: 期末
D5: 转回 | E5: 转销
A6: 坏账准备 | F6: =B6+C6-D6-E6 -> 0
A7: 存货跌价准备 | F7: =B7+C7-D7-E7 -> 0
A8: 可供出售金融资产减值准备 | F8: =B8+C8-D8-E8 -> 0
A9: 持有至到期投资减值准备 | F9: =B9+C9-D9-E9 -> 0
A10: 长期股权投资减值准备 | F10: =B10+C10-D10-E10 -> 0
A11: 投资性房地产减值准备 | F11: =B11+C11-D11-E11 -> 0
A12: 固定资产减值准备 | F12: =B12+C12-D12-E12 -> 0
A13: 工程物资减值准备 | F13: =B13+C13-D13-E13 -> 0
A14: 在建工程减值准备 | F14: =B14+C14-D14-E14 -> 0
A15: 无形资产减值准备 | F15: =B15+C15-D15-E15 -> 0
A16: 商誉减值准备 | F16: =B16+C16-D16-E16 -> 0
A17: 其 他 | F17: =B17+C17-D17-E17 -> 0
A18: 合 计 | B18: =SUM(B6:B17) -> 0 | C18: =SUM(C6:C17) -> 0 | D18: =SUM(D6:D17) -> 0 | E18: =SUM(E6:E17) -> 0 | F18: =SUM(F6:F17) -> 0

Sheet RP 046
A1: 公司名称 | B1: =基础信息!B6 -> 0
A2: 财务期间 | B2: =基础信息!B9 -> 0
A3: 内容 | B3: 所有权受到限制的资产
A4: 项 目 | B4: 期末账面价值 | C4: 受限原因
A5: 货币资金
A6: 应收票据
A7: 存货
A8: 固定资产
A9: 无形资产
A10: ……
A11: 合 计 | B11: =SUM(B5:B10) -> 0 | C11: =SUM(C5:C10) -> 0

Sheet RP 047
A1: 公司名称 | B1: =基础信息!B6 -> 0
A2: 财务期间 | B2: =基础信息!B9 -> 0
A3: 内容 | B3: 短期借款
A4: （1）短期借款分类
A5: 项 目 | B5: 期末数
A6: 质押借款
A7: 抵押借款
A8: 保证借款
A9: 信用借款
A10: 合 计 | B10: =SUM(B6:B9) -> 0
A11: 报表金额 | B11: ='RP 006'!E81 -> 0
B12: =B10-B11 -> 0
B13: =IF(B12=0,"OK","NO") -> OK
A15: 说明：（用于抵押、质押的财产）
A16: （2）逾期借款情况（如无，删除）
A17: （汇总披露逾期借款（包括从长期借款转入的）的期末余额。对于重要的逾期借款，还应按借款单位列示借款期末余额、借款利率、逾期时间、逾期利率。）
A18: 本期末已逾期未偿还的短期借款余款合计XXX元，其中由长期借款转入金额为XXX元。
A19: 重要的逾期借款情况如下：
A20: 借款单位 | B20: 期末余额 | C20: 借款利率 | D20: 逾期时间 | E20: 逾期利率
A24: 合 计 | C24: -- | D24: -- | E24: --
A25: 说明：（用于抵押、质押的财产）

Sheet RP 048
A1: 公司名称 | B1: =基础信息!B6 -> 0
A2: 财务期间 | B2: =基础信息!B9 -> 0
A3: 内容 | B3: 交易性金融负债
A5: 项 目 | B5: 期末公允价值
A6: 交易性金融负债
A7: 其中：指定为以公允价值计量且其变动计入当期损益的金融负债
A8: 其他
A14: 合 计
A15: 报表金额 | B15: ='RP 006'!E82 -> 0
B16: =B14-B15 -> 0
B17: =IF(B16=0,"OK","NO") -> OK
A18: [对于指定为以公允价值计量且其变动计入当期损益的金融负债，需区分企业自身信用风险变动引起的该金融负债公允价值变动金额计入其他综合收益和该金融负债 (包括企业自身信用风险变动的影响) 的全部利得或损失计入当期损益两种情况，按照《企业会计准则第37号——金融工具列报》第41-43条的规定进行披露。]
A19: [例如： 对于指定为以公允价值计量且其变动计入当期损益的金融负债，2019年1-X月公允价值的变动情况如下表所示：
A20: 项目 | B20: 2019年1-X月公允价值变动额 | C20: 因自身信用风险变动引起的公允价值本年变动额 | D20: 因自身信用风险变动引起的公允价值累计变动额
A21: 发行的普通债权 | B21: ——
A23: 合 计 | B23: =SUM(B21:B22) -> 0 | C23: =SUM(C21:C22) -> 0
A24: 2019年XX月XX日，指定为以公允价值计量且其变动计入当期损益的金融负债的账面价值与按合同约定到期应支付债权人金额之间的差额为人民币[XX]元。]

Sheet RP 049
A1: 公司名称 | B1: =基础信息!B6 -> 0
A2: 财务期间 | B2: =基础信息!B9 -> 0
A3: 内容 | B3: 以公允价值计量且其变动计入当期损益的金融负债
A4: 以公允价值计量且其变动计入当期损益的金融负债
A5: 项 目 | B5: 期末公允价值
A6: 交易性金融负债
A7: 其中：发行的交易性债券
A8: 衍生金融负债
A9: 其他
A10: 指定为以公允价值计量且其变动计入当期损益的金融负债
A14: 合 计
A15: 报表金额 | B15: ='RP 006'!E83 -> 0
B16: =B14-B15 -> 0
B17: =IF(B16=0,"OK","NO") -> OK
A18: 说明：（交易性金融负债的账面价值以及公允价值及其变动的相关情况，如涉及数量变化以及单位数量公允价值变动情况。）
A19: （存在套期工具的，应对套期工具及相关套期交易作出说明。）

Sheet RP 050
A1: 公司名称 | B1: =基础信息!B6 -> 0
A2: 财务期间 | B2: =基础信息!B9 -> 0
A3: 内容 | B3: 衍生金融负债
A4: 项 目 | B4: 2019.12.31
A10: 合 计 | B10: =SUM(B5:B9) -> 0
A11: 报表金额 | B11: ='RP 006'!E84 -> 0
B12: =B10-B11 -> 0
B13: =IF(B12=0,"OK","NO") -> OK
A14: 说明：（衍生金融负债产生的原因以及相关会计处理。）

Sheet RP 051
A1: 公司名称 | B1: =基础信息!B6 -> 0
A2: 财务期间 | B2: =基础信息!B9 -> 0
A3: 内容 | B3: 应付票据
A4: 种 类 | B4: 期末
A5: 银行承兑汇票
A6: 商业承兑汇票
A7: 合 计
A8: 报表金额 | B8: ='RP 006'!E85 -> 0
B9: =B7-B8 -> 0
B10: =IF(B9=0,"OK","NO") -> OK
A11: 说明：本期末已到期未支付的应付票据总额为XXX元。

Sheet RP 052
A1: 公司名称 | B1: =基础信息!B6 -> 0
A2: 财务期间 | B2: =基础信息!B9 -> 0
A3: 内容 | B3: 应付账款
A4: 项 目 | B4: 期末数
A5: 货款
A6: 工程款
A7: 可无限量添加行
A8: 合 计 | B8: =SUM(B5:B7) -> 0
A9: 报表金额 | B9: ='RP 006'!E86 -> 0
B10: =B8-B9 -> 0
B11: =IF(B10=0,"OK","NO") -> OK
A12: 其中，账龄超过1年的重要应付账款
A13: 项目 | B13: 期末数 | C13: 未偿还或未结转的原因
A16: 合 计

Sheet RP 053
A1: 公司名称 | B1: =基础信息!B6 -> 0
A2: 财务期间 | B2: =基础信息!B9 -> 0
A3: 内容 | B3: 预收款项
A4: 预收款项
B6: 2019.12.31 | C6: 2018.12.31
A7: 货款
A8: 工程款
A9: 建造合同形成的已结算尚未完工款
A10: …..
A11: 合 计 | B11: =SUM(B7:B10) -> 0 | C11: =SUM(C7:C10) -> 0
A12: 报表金额 | B12: ='RP 006'!E87 -> 0
B13: =B11-B12 -> 0
B14: =IF(B13=0,"OK","NO") -> OK
A15: （1）账龄超过1年的重要预收款项
A16: 单位名称 | B16: 预收款项期末余额 | C16: 未偿还或未结转的原因
A19: 合计 | B19: =SUM(B17:B18) -> 0
A20: 说明：（账龄超过1年的金额重要预收账款，应说明未及时结算的原因。）
A21: （2）按预收对象归集的预收款项期末余额前五名单位情况
A22: （按预收对象集中度，汇总或分别披露期末余额前五名的预收款项的期末余额及占预收款项期末余额合计数的比例。）
A23: 汇总披露格式：
A24: 本期按预收对象归集的期末余额前五名预收款项汇总金额XXXX元，占预收款项期末余额合计数的比例 %。
A25: 分别披露格式：
A26: 单位名称 | B26: 预收款项期末余额 | C26: 占预收款项期末余额合计数的比例%
A30: 合 计 | B30: =SUM(B27:B29) -> 0 | C30: =SUM(C27:C29) -> 0

Sheet RP 054
A1: 公司名称 | B1: =基础信息!B6 -> 0
A2: 财务期间 | B2: =基础信息!B9 -> 0
A3: 内容 | B3: 合同负债
A5: 项目 | B5: 期末数
B6: 金 额
A10: 合 计 | B10: =SUM(B6:B9) -> 0
A11: 报表金额 | B11: ='RP 006'!E88 -> 0
B12: =B10-B11 -> 0
B13: =IF(B12=0,"OK","NO") -> OK
A15: （1）本期合同负债账面价值的重大变动
A16: 项 目 | B16: 变动金额 | C16: 变动原因
A21: 合 计 | B21: =SUM(B17:B20) -> 0
A22: 说明：
A23: 1、在本期确认的包括在合同负债期初账面价值中的收入；以及前期已经履行（或部分履行）的履约义务在本期确认的收入（例如，交易价格的变动）。
A24: 2、履行履约义务的时间与通常的付款时间之间的关系，以及此类因素对合同负债（如果对合同资产产生影响在合同负债科目下说明）账面价值的影响的定量或定性信息。
A25: 3、合同负债的账面价值在本期内发生的重大变动的情形包括：
A26: ①企业合并导致的变动；
A27: ②对收入进行累积追加调整导致的相关合同资产和合同负债的变动，此类调整可能源于估计履约进度的变化、估计交易价格的变化（包括对于可变对价是否受到限制的评估发生变化）或者合同变更；
A28: ③履行履约义务（即从合同负债转为收入）的时间安排发生变化。

Sheet RP 055
A1: 公司名称 | B1: =基础信息!B6 -> 0
A2: 财务期间 | B2: =基础信息!B9 -> 0
A3: 内容 | B3: 应付职工薪酬
A4: 项 目 | B4: 期初数 | C4: 本期增加 | D4: 本期减少 | E4: 期末数
A5: 短期薪酬 | E5: =B5+C5-D5 -> 0
A6: 离职后福利-设定提存计划 | E6: =B6+C6-D6 -> 0
A7: 辞退福利 | E7: =B7+C7-D7 -> 0
A8: 一年内到期的其他福利 | E8: =B8+C8-D8 -> 0
E9: =B9+C9-D9 -> 0
A10: 合 计 | B10: =SUM(B5:B9) -> 0 | C10: =SUM(C5:C9) -> 0 | D10: =SUM(D5:D9) -> 0 | E10: =SUM(E5:E9) -> 0
A11: 报表金额 | E11: ='RP 006'!E89 -> 0
E12: =E10-E11 -> 0
E13: =IF(E12=0,"OK","NO") -> OK
A15: 【提示：
A16: 1、辞退福利包括（1）预期在其确认的年度报告期间期末后12个月内完全支付的辞退福利；（2）补偿款超过1年支付的辞退计划将于年度报告期间期末后12个月内支付的款项，例如内退计划将于下一年支付的金额。
A17: 2、一年内到期的其他福利：指一年内到期的设定受益计划及其他长期福利；应根据“长期应付职工薪酬”项目分析填列。
A18: （1）短期薪酬
A19: 项 目 | B19: 期初数 | C19: 本期增加 | D19: 本期减少 | E19: 期末数
A20: 工资、奖金、津贴和补贴 | E20: =B20+C20-D20 -> 0
A21: 职工福利费 | E21: =B21+C21-D21 -> 0
A22: 社会保险费 | B22: =SUM(B23:B29) -> 0 | C22: =SUM(C23:C29) -> 0 | D22: =SUM(D23:D29) -> 0 | E22: =B22+C22-D22 -> 0
A23: 其中：1．医疗保险费 | E23: =B23+C23-D23 -> 0
A24: 2．工伤保险费 | E24: =B24+C24-D24 -> 0
A25: 3．生育保险费 | E25: =B25+C25-D25 -> 0
A26: …… | E26: =B26+C26-D26 -> 0
E27: =B27+C27-D27 -> 0
E28: =B28+C28-D28 -> 0
E29: =B29+C29-D29 -> 0
A30: 住房公积金 | E30: =B30+C30-D30 -> 0
A31: 工会经费和职工教育经费 | E31: =B31+C31-D31 -> 0
A32: 短期带薪缺勤 | E32: =B32+C32-D32 -> 0
A33: 短期利润分享计划 | E33: =B33+C33-D33 -> 0
A34: 非货币性福利 | E34: =B34+C34-D34 -> 0
A35: 其他短期薪酬 | E35: =B35+C35-D35 -> 0
E36: =B36+C36-D36 -> 0
A37: 合 计 | B37: =SUM(B20:B36)-B23-B24-B25-B26-B27-B28-B29 -> 0 | C37: =SUM(C20:C36)-C23-C24-C25-C26-C27-C28-C29 -> 0 | D37: =SUM(D20:D36)-D23-D24-D25-D26-D27-D28-D29 -> 0 | E37: =SUM(E20:E36)-E23-E24-E25-E26-E27-E28-E29 -> 0
A38: 报表金额 | E38: =E5 -> 0
E39: =E37-E38 -> 0
E40: =IF(E39=0,"OK","NO") -> OK
A41: 说明：
A42: 1、（企业本期为职工提供的各项非货币性福利形式、其计算依据。）
A43: 2、（企业依据短期利润分享计划提供的职工薪酬计算依据。）
A44: （2）设定提存计划
A45: 项 目 | B45: 期初数 | C45: 本期增加 | D45: 本期减少 | E45: 期末数
A46: 离职后福利 | B46: =SUM(B47:B50) -> 0 | C46: =SUM(C47:C50) -> 0 | D46: =SUM(D47:D50) -> 0 | E46: =B46+C46-D46 -> 0
A47: 其中：1．基本养老保险费 | E47: =B47+C47-D47 -> 0
A48: 2．失业保险费 | E48: =B48+C48-D48 -> 0
A49: 3．企业年金缴费 | E49: =B49+C49-D49 -> 0
A50: 4．其他 | E50: =B50+C50-D50 -> 0
A51: 其他长期职工福利（不适用的删除） | B51: =SUM(B52:B53) -> 0 | C51: =SUM(C52:C53) -> 0 | D51: =SUM(D52:D53) -> 0 | E51: =B51+C51-D51 -> 0
A52: 其中：1．xxx | E52: =B52+C52-D52 -> 0
A53: 2．其他 | E53: =B53+C53-D53 -> 0
A54: 合 计 | B54: =B46+B51 -> 0 | C54: =C46+C51 -> 0 | D54: =D46+D51 -> 0 | E54: =B54+C54-D54 -> 0
A55: 报表金额 | E55: =E6 -> 0
E56: =E54-E55 -> 0
E57: =IF(E56=0,"OK","NO") -> OK
A58: 说明：（设定提存计划的性质、计算缴费金额的公式或依据）
A59: 【提示：其他长期职工福利指符合设定提存计划条件的其他长期职工福利】
A60: （3）辞退福利
A61: 说明：辞退福利的性质、内容及计算依据。
A62: （注：应付职工薪酬、设定受益计划净负债（净资产）、一年后支付的辞退福利及其他长期职工福利本期减少一般与现金流量中“支付职工”项一致，除非代扣税未交、实物发放等）

Sheet RP 056
A1: 公司名称 | B1: =基础信息!B6 -> 0
A2: 财务期间 | B2: =基础信息!B9 -> 0
A3: 内容 | B3: 应交税费
A4: 项 目 | B4: 年初余额 | C4: 本期应交 | D4: 本期已交 | E4: 期末余额
A5: 增值税 | E5: =B5+C5-D5 -> 0
A6: 消费税 | E6: =B6+C6-D6 -> 0
A7: 营业税 | E7: =B7+C7-D7 -> 0
A8: 资源税 | E8: =B8+C8-D8 -> 0
A9: 企业所得税 | E9: =B9+C9-D9 -> 0
A10: 城市维护建设税 | E10: =B10+C10-D10 -> 0
A11: 房产税 | E11: =B11+C11-D11 -> 0
A12: 土地使用税 | E12: =B12+C12-D12 -> 0
A13: 个人所得税 | E13: =B13+C13-D13 -> 0
A14: 教育费附加 | E14: =B14+C14-D14 -> 0
A15: 其他税费 | E15: =B15+C15-D15 -> 0
A16: 合 计 | B16: =SUM(B5:B15) -> 0 | C16: =SUM(C5:C15) -> 0 | D16: =SUM(D5:D15) -> 0 | E16: =B16+C16-D16 -> 0
A17: 报表金额 | E17: ='RP 006'!E90 -> 0
E18: =E16-E17 -> 0
E19: =IF(E18=0,"OK","NO") -> OK
A20: 说明：
A21: （小税（费）种可合并反映。）
A22: （对于满足条件将当期所得税资产及当期所得税负债以抵销后的净额列示的情况，当企业实际交纳的所得税税款大于按照税法规定计算的应交税时，超过部分在资产负债表中应当列示为“其他流动资产”；当企业实际交纳的所得税税款小于按照税法规定计算的应交税时，差额部分应当作为资产负债表中的“应交税费”项目列示。）

Sheet RP 057
A1: 公司名称 | B1: =基础信息!B6 -> 0
A2: 财务期间 | B2: =基础信息!B9 -> 0
A3: 内容 | B3: 其他应付款
A4: 项 目 | B4: 期末数
A5: 应付利息
A6: 应付股利
A7: 其他应付款
A8: 合 计 | B8: =SUM(B5:B7) -> 0
A9: 报表金额 | B9: ='RP 006'!E91 -> 0
B10: =B8-B9 -> 0
B11: =IF(B10=0,"OK","NO") -> OK

Sheet RP 057-1
A1: 公司名称 | B1: =基础信息!B6 -> 0
A2: 财务期间 | B2: =基础信息!B9 -> 0
A3: 内容 | B3: 应付利息
A4: 项 目 | B4: 期末数
A5: 分期付息到期还本的长期借款利息
A6: 企业债券利息
A7: 短期借款应付利息
A8: 划分为金融负债的优先股\永续债利息
A9: 其中：工具1
A10: 工具2
A12: 合 计 | B12: =SUM(B5:B11) -> 0
A13: 核对金额 | B13: ='RP 057'!B5 -> 0
B14: =B12-B13 -> 0
B15: =IF(B14=0,"OK","NO") -> OK
A17: 重要的逾期未付利息：
A18: 借款单位 | B18: 逾期金额 | C18: 逾期原因
A19: 可无限量添加行
A21: 合计 | C21: --

Sheet RP 057-2
A1: 公司名称 | B1: =基础信息!B6 -> 0
A2: 财务期间 | B2: =基础信息!B9 -> 0
A3: 内容 | B3: 应付股利
A4: 项目（或股东名称） | B4: 期末数
A5: 普通股股利
A6: 划分为权益工具的优先股\永续债股利
A7: 其中：工具1
A8: 工具2
A10: 合 计
A11: 核对金额 | B11: ='RP 057'!B6 -> 0
B12: =B10-B11 -> 0
B13: =IF(B12=0,"OK","NO") -> OK
A15: 重要的超过1年未支付的应付股利：
A16: 股东名称 | B16: 应付股利金额 | C16: 未支付原因
A17: 可无限量添加行
A19: 合计 | C19: --

Sheet RP 057-3
A1: 公司名称 | B1: =基础信息!B6 -> 0
A2: 财务期间 | B2: =基础信息!B9 -> 0
A3: 内容 | B3: 其他应付款
A4: 其他应付款（按款项性质列示）
A5: 项 目 | B5: 期末数
A6: 押金
A7: 质保金
A8: 可无限量添加行
A10: 合 计 | B10: =SUM(B6:B9) -> 0
A11: 核对金额 | B11: ='RP 057'!B7 -> 0
B12: =B10-B11 -> 0
B13: =IF(B12=0,"OK","NO") -> OK
A16: 其中，账龄超过1年的重要其他应付款
A17: 项目 | B17: 金额 | C17: 未偿还或未结转的原因
A20: 合 计 | B20: =SUM(B18:B19) -> 0

Sheet RP 058
A1: 公司名称 | B1: =基础信息!B6 -> 0
A2: 财务期间 | B2: =基础信息!B9 -> 0
A3: 内容 | B3: 一年内到期的非流动负债
A4: 项 目 | B4: 期末数
A5: 一年内到期的长期借款
A6: 一年内到期的应付债券
A7: 一年内到期的长期应付款
A8: 一年内到期的预计负债
A9: 一年内到期的递延收益
A10: 合 计 | B10: =SUM(B5:B9) -> 0
A11: 报表金额 | B11: ='RP 006'!E93 -> 0
B12: =B10-B11 -> 0
B13: =IF(B12=0,"OK","NO") -> OK
A14: （1）一年内到期的长期借款
A15: 项 目 | B15: 期末数
A16: 质押借款
A17: 抵押借款
A18: 保证借款
A19: 信用借款
A20: 合 计 | B20: =SUM(B16:B19) -> 0
A21: 报表金额 | B21: =B5 -> 0
B22: =B20-B21 -> 0
B23: =IF(B22=0,"OK","NO") -> OK
A24: 说明：公司用于抵押、质押的财产；
A26: （2）一年内到期的应付债券
A27: 债券名称 | B27: 面值 | C27: 发行日期 | D27: 债券期限 | E27: 发行金额
A30: 小 计 | B30: =SUM(B28:B29) -> 0 | E30: =SUM(E28:E29) -> 0
A31: 报表金额 | E31: =B6 -> 0
E32: =E30-E31 -> 0
E33: =IF(E32=0,"OK","NO") -> OK
A34: 一年内到期的应付债券（续）
A35: 债券名称 | B35: 期初余额 | C35: 本期发行 | D35: 按面值计提利息 | E35: 溢折价摊销 | F35: 本期偿还 | G35: 期末余额
A38: 合 计 | B38: =SUM(B36:B37) -> 0 | C38: =SUM(C36:C37) -> 0 | D38: =SUM(D36:D37) -> 0 | E38: =SUM(E36:E37) -> 0 | F38: =SUM(F36:F37) -> 0 | G38: =SUM(G36:G37) -> 0
A39: 说明：
A40: （3）一年内到期的长期应付款
A41: 项 目 | B41: 期末数
A42: 应付融资租赁款
A45: 合 计 | B45: =SUM(B42:B44) -> 0
A46: 报表金额 | B46: =B7 -> 0
B47: =B45-B46 -> 0
B48: =IF(B47=0,"OK","NO") -> OK

Sheet RP 059
A1: 公司名称 | B1: =基础信息!B6 -> 0
A2: 财务期间 | B2: =基础信息!B9 -> 0
A3: 内容 | B3: 其他流动负债
A4: 项 目 | B4: 期末数
A5: 短期应付债券
A6: 政府补助
A7: 应付退货款
A8: 合 计 | B8: =SUM(B5:B6) -> 0
A9: 报表金额 | B9: ='RP 006'!E102 -> 0
B10: =B8-B9 -> 0
B11: =IF(B10=0,"OK","NO") -> OK
A13: 说明：
A14: 【公司根据《企业会计准则》规定计入“递延收益”科目的金额，应按如下原则确定所属的报表项目：
A15: （1）取得政府补助时，预计在一年以内（含一年）转入损益的项目，应在“其他流动负债”项目列报；
A16: （2）取得政府补助时，预计转入损益的期限超过一年的项目：
A17: ①自资产负债表日起，下一年度转入损益的金额，应在“一年内到期的其他非流动负债”项目中列报；
A18: ②自资产负债表日起，将于下一年度之后转入损益的金额，在“递延收益”项目中列报。】
A19: 按照《企业会计准则第 14 号--收入》（2017 年修订）的相关规定确认为预计负债的应付退货款，应当根据"预计负债"科目下的"应付退货款"明细科目是否在一年或一个正常营业周期内清偿，在"其他流动负债"或"预计负债"项目中填列。
A20: （1）短期应付债券
A21: 债券名称 | B21: 面值 | C21: 发行日期 | D21: 债券期限 | E21: 发行金额
A24: 小 计 | B24: =SUM(B22:B23) -> 0 | E24: =SUM(E22:E23) -> 0
A25: 短期应付债券（续）
A26: 债券名称 | B26: 期初余额 | C26: 本期发行 | D26: 按面值计提利息 | E26: 溢折价摊销 | F26: 本期偿还 | G26: 期末余额
A29: 合 计 | B29: =SUM(B27:B28) -> 0 | C29: =SUM(C27:C28) -> 0 | D29: =SUM(D27:D28) -> 0 | E29: =SUM(E27:E28) -> 0 | F29: =SUM(F27:F28) -> 0 | G29: =SUM(G27:G28) -> 0
A30: 说明：
A31: （2）递延收益-政府补助情况
A32: 补助项目 | B32: 期初余额 | C32: 本期新增补助金额 | D32: 本期计入营业外收入金额 | E32: 其他 | F32: 期末 | G32: 与资产相关/与收益相关
E33: 变动 | F33: 余额
A37: 合计 | B37: =SUM(B34:B36) -> 0 | C37: =SUM(C34:C36) -> 0 | D37: =SUM(D34:D36) -> 0 | E37: =SUM(E34:E36) -> 0 | F37: =SUM(F34:F36) -> 0
A38: 说明：
A39: （1）XX补助项目，相关文件未明确规定补助对象，由于该项目未来不会形成长期资产，本集团将其作为与收益相关的政府补助。
A40: （信息披露解释性公告第2号规定：公司应当遵循重要性原则，对涉及政府补助的负债项目，在财务报表附注的相关项目下，逐项披露相关期初余额、本期新增补助金额、本期计入营业外收入金额、本期转入资本公积金额以及期末余额。对于相关文件未明确规定补助对象的政府补助项目，公司还应单独说明其划分依据。）

Sheet RP 060
A1: 公司名称 | B1: =基础信息!B6 -> 0
A2: 财务期间 | B2: =基础信息!B9 -> 0
A3: 内容 | B3: 长期借款
A4: 长期借款
A5: 项 目 | B5: 期末数 | C5: 利率区间 | D5: 期初数 | E5: 利率区间
A6: 质押借款
A7: 抵押借款
A8: 保证借款
A9: 信用借款
A10: 小 计 | B10: =SUM(B6:B9) -> 0 | D10: =SUM(D6:D9) -> 0
A11: 减：一年内到期的长期借款
A12: 合 计 | B12: =B10-B11 -> 0 | D12: =D10-D11 -> 0
A13: 报表金额 | B13: ='RP 006'!E105 -> 0
B14: =B12-B13 -> 0
B15: =IF(B14=0,"OK","NO") -> OK
A17: 说明：公司用于抵押、质押的财产。
A19: 一年内到期的长期借款
A20: 项 目 | B20: 期末数
A21: 质押借款
A22: 抵押借款
A23: 保证借款
A24: 信用借款
A25: 合 计 | B25: =SUM(B21:B24) -> 0
A26: 报表金额 | B26: ='RP 058'!B20 -> 0
B27: =B25-B26 -> 0
B28: =IF(B27=0,"OK","NO") -> OK
A29: 说明：公司用于抵押、质押的财产；

Sheet RP 061
A1: 公司名称 | B1: =基础信息!B6 -> 0
A2: 财务期间 | B2: =基础信息!B9 -> 0
A3: 内容 | B3: 应付债券
A4: 应付债券
A5: 项 目 | B5: 期末数
A8: 合 计 | B8: =SUM(B6:B7) -> 0
A9: 报表金额 | B9: ='RP 006'!E106 -> 0
B10: =B8-B9 -> 0
B11: =IF(B10=0,"OK","NO") -> OK
A14: （1）应付债券的增减变动（不包括划分为金融负债的优先股、永续债等其他金融工具）
A15: 债券名称 | B15: 面值 | C15: 发行日期 | D15: 债券期限 | E15: 发行金额
A18: 小 计 | B18: =SUM(B16:B17) -> 0 | E18: =SUM(E16:E17) -> 0
A21: 应付债券（续）
A22: 债券名称 | B22: 期初余额 | C22: 本期发行 | D22: 按面值计提利息 | E22: 溢折价摊销 | F22: 本期偿还 | G22: 期末余额
A25: 小 计 | B25: =SUM(B23:B24) -> 0 | C25: =SUM(C23:C24) -> 0 | D25: =SUM(D23:D24) -> 0 | E25: =SUM(E23:E24) -> 0 | F25: =SUM(F23:F24) -> 0 | G25: =SUM(G23:G24) -> 0
A26: 减：一年内到期的应付债券
A27: 合 计 | B27: =B25-B26 -> 0 | C27: =C25-C26 -> 0 | D27: =D25-D26 -> 0 | E27: =E25-E26 -> 0 | F27: =F25-F26 -> 0 | G27: =G25-G26 -> 0
A30: （2）可转换公司债券
A31: 说明：（可转换公司债券的转股条件、转股时间）
A32: 根据中国证券监督管理委员会证监发行字[200x]XX号核准，本公司于200X年X月X日至200X年X月X日公开发行XX份可转换公司债券，每份面值100元，发行总额XXX元，债券期限为X年。
A33: 本公司发行的可转换公司债券的票面利率为X%，利息按季支付，200X年X月X日为第一次派息日。转股期自发行之日起(200X年X月X日)X个月后的第一个交易日(200X年X月X日)起(含当日)，至可转换公司债券到期日(200X年X月X日)前一个交易日止(含当日)。持有人可在转股期内申请转股。
A34: 可转换公司债券发行时的初始转股价格为每股人民币X元，本公司在200X年X月X日实施200X年度每股派发现金股息人民币X元及用资本公积每十股转增X股的方案后，可转债初始转股价格相应调整为每股人民币X元。]
A35: （3）划分为金融负债的其他金融工具
A36: 【公司发行其他金融工具并划分为金融负债的，应分项披露其基本情况、期初余额、期末余额和本期增减变动情况，以及划分至金融负债的依据。】
A37: 期末发行在外的优先股、永续债等其他金融工具的基本情况：
A38: 【包括：各金融工具的主要条款，利息的设定机制等】
A39: 期末发行在外的优先股、永续债等其他金融工具变动情况表：
A40: 发行在外的金融工具 | B40: 期初数 | D40: 本期增加 | F40: 本期减少 | H40: 期末数
B41: 数量 | C41: 账面价值 | D41: 数量 | E41: 账面价值 | F41: 数量 | G41: 账面价值 | H41: 数量 | I41: 账面价值
A42: 工具1
A44: 合 计 | B44: =SUM(B42:B43) -> 0 | C44: =SUM(C42:C43) -> 0 | D44: =SUM(D42:D43) -> 0 | E44: =SUM(E42:E43) -> 0 | F44: =SUM(F42:F43) -> 0 | G44: =SUM(G42:G43) -> 0 | H44: =SUM(H42:H43) -> 0 | I44: =SUM(I42:I43) -> 0
A45: 说明：划分至金融负债的依据。

Sheet RP 062
A1: 公司名称 | B1: =基础信息!B6 -> 0
A2: 财务期间 | B2: =基础信息!B9 -> 0
A3: 内容 | B3: 长期应付款
A5: 项 目 | B5: 期末数
A6: 长期应付款 | B6: ='RP 062-1'!B11 -> 0
A7: 专项应付款 | B7: ='RP 062-2'!E7 -> 0
A9: 小计 | B9: =SUM(B6:B8) -> 0
A10: 减：一年内到期长期应付款
A11: 合 计 | B11: =B9-B10 -> 0
A12: 报表金额 | B12: ='RP 006'!E107 -> 0
B13: =B11-B12 -> 0
B14: =IF(B13=0,"OK","NO") -> OK
A15: 报表金额 | B15: ='RP 058'!B7 -> 0
B16: =B10-B15 -> 0
B17: =IF(B16=0,"OK","NO") -> OK
A19: 说明：由独立第三方为公司融资租赁提供担保的金额XX元。

Sheet RP 062-1
A1: 公司名称 | B1: =基础信息!B6 -> 0
A2: 财务期间 | B2: =基础信息!B9 -> 0
A3: 内容 | B3: 长期应付款
A4: 长期应付款（按款项性质列示）
A5: 项 目 | B5: 期末数
A6: 应付融资租赁款
A9: 小计 | B9: =SUM(B6:B8) -> 0
A10: 减：一年内到期长期应付款
A11: 合 计 | B11: =B9-B10 -> 0
A12: 核对金额 | B12: ='RP 062'!B6 -> 0
B13: =B10-B12 -> 0
B14: =IF(B13=0,"OK","NO") -> OK
A16: 说明：由独立第三方为公司融资租赁提供担保的金额XX元。

Sheet RP 062-2
A1: 公司名称 | B1: =基础信息!B6 -> 0
A2: 财务期间 | B2: =基础信息!B9 -> 0
A3: 内容 | B3: 专项应付款
A4: 项 目 | B4: 期初 | C4: 本期增加 | D4: 本期减少 | E4: 期末
E5: =B5+C5-D5 -> 0
E6: =B6+C6-D6 -> 0
A7: 合 计 | B7: =SUM(B5:B6) -> 0 | C7: =SUM(C5:C6) -> 0 | D7: =SUM(D5:D6) -> 0 | E7: =SUM(E5:E6) -> 0
A8: 核对金额 | E8: ='RP 062'!B7 -> 0
E9: =E7-E8 -> 0
E10: =IF(E9=0,"OK","NO") -> OK
A12: （注：
A13: （1）应说明专项应付款的来源、指定的专门用途、使用限制等相关内容。如：该专项应付款为财政部按照XX文规定拨付的X项目专用设备购置款。
A14: （2）企业因城镇整体规划、库区建设、棚户区改造、沉陷区治理等公共利益进行搬迁，收到政府从财政预算直接拨付的搬迁补偿款，在专项应付款中核算。）

Sheet RP 063
A1: 公司名称 | B1: =基础信息!B6 -> 0
A2: 财务期间 | B2: =基础信息!B9 -> 0
A3: 内容 | B3: 长期应付职工薪酬
A4: 长期应付职工薪酬（不适用的删除）
A5: 项 目 | B5: 期末数 | C5: 期初数
A6: 设定受益计划净负债
A7: 辞退福利
A8: 符合设定受益计划条件的其他长期职工福利的净负债（不适用删除）
A9: 其他长期福利
A10: 小 计 | B10: =SUM(B6:B9) -> 0 | C10: =SUM(C6:C9) -> 0
A11: 减：一年内到期的长期应付职工薪酬
A12: 合 计 | B12: =B10-B11 -> 0 | C12: =C10-C11 -> 0
A13: 报表金额 | B13: ='RP 006'!E108 -> 0
B14: =B12-B13 -> 0
B15: =IF(B14=0,"OK","NO") -> OK
A16: 说明：1、辞退福利的性质、内容及计算依据详见附注五、35；
A17: 2、其他长期职工福利的性质及计算依据。
A18: （1）设定受益计划变动情况
A19: 设定受益计划义务现值：
A20: 项 目 | B20: 本期金额 | C20: 上期金额
A21: 一、期初余额
A22: 二、计入当期损益的设定受益成本
A23: 1．当期服务成本
A24: 2．过去服务成本
A25: 3．结算利得（损失以“-”表示）
A26: 4．利息净额
A27: 三、计入其他综合收益的设定受益成本
A28: 1．精算利得（损失以“-”表示）
A31: 四、其他变动
A32: 1．结算时消除的负债
A33: 2．已支付的福利
A34: ……
... A37: 计划资产：
A38: 项 目 | B38: 本期金额 | C38: 上期金额
A39: 一、期初余额
A40: 二、计入当期损益的设定受益成本
A41: 1．利息净额
A43: 三、计入其他综合收益的设定受益成本
A44: 1．计划资产的回报（计入利息净额的除外）
A45: 2．资产上限影响的变动（计入利息净额的除外）
A46: 四、其他变动
A49: ……
A50: 五、期末余额
A51: 【提示：设定受益计划存在资产的，企业应当将设定受益计划义务现值减去设定受益计划资产公允价值所形成的赤字或盈余确认为一项设定受益计划净负债或净资产。】
A52: 设定受益计划净负债（净资产）：
A53: 项 目 | B53: 本期金额 | C53: 上期金额
A54: 一、期初余额
A55: 二、计入当期损益的设定受益成本
A56: 三、计入其他综合收益的设定受益成本
A57: 四、其他变动
A58: 五、期末余额
A59: 说明：（1、设定受益计划的内容、形成的原因、特征及与之相关的风险；
A60: 如有对计划的修改或结算的，还应当披露修改或结算计划的有关情况；
A61: 2、设定受益计划对公司未来现金流量的金额、时间和不确定性的影响。披露影响设定受益计划未来缴存金额的有关筹资政策和计划、下一会计年度预期将缴存的金额，设定受益义务有关到期情况的信息，如设定受益义务的加权平均期间、对有关福利支付的到期日分析等）
A62: 未折现的离职后福利预计到期分析：
A63: 项 目 | B63: 金额
A64: 一年以内
A65: 一到两年
A66: 二到五年
A67: 五年以上
A68: 合 计
A69: （2）计划资产
A70: 项 目 | B70: 计划资产的公允价值
B71: 期末数 | C71: 期初数
A72: 现金和现金等价物
A73: 权益工具投资
A74: 1、……
A75: 2、……
A76: ……
A77: 债务工具投资
A78: 1、……
A79: 2、……
A80: ……
A81: 其他
A82: 合 计
A83: 【提示：1、权益工具投资按行业类型或公司规模或地域等分类；
... A85: （3）精算假设
A86: 项 目 | B86: 期末数 | C86: 期初数
A87: 折现率
A88: 死亡率
A89: 预计平均寿命
A90: 职工的离职率
A91: 薪酬的预期增长率
A92: ……
A93: （4）敏感性分析
A94: 项目 | B94: 假设的变动幅度 | C94: 对设定受益义务现值的影响
C95: 计划负债增加 | D95: 计划负债减少
A96: 折现率
A97: 死亡率
A98: 预计平均寿命
A99: 职工的离职率
A100: 薪酬的预期增长率
A101: 说明：
A102: 上述敏感性分析是基于一个假设发生变动而其他假设均保持不变，但实际上各种假设通常是相互关联的。上述敏感性分析在计算设定受益义务现值时也同样采用累积福利单位法。
A103: 进行敏感度分析所采用的重大假设的方法和类型与以前年度比较未发生变动。
A104: （如发生变动，应进一步说明发生的具体变动及原因。）

Sheet RP 064
A1: 公司名称 | B1: =基础信息!B6 -> 0
A2: 财务期间 | B2: =基础信息!B9 -> 0
A3: 内容 | B3: 预计负债
A4: 项 目 | B4: 期末数 | C4: 形成原因
A5: 对外提供担保
A6: 未决诉讼
A7: 产品质量保证
A8: 重组义务
A9: 弃置义务
A10: 待执行的亏损合同
A11: 应付退货款
A12: 其他
A13: 合 计 | B13: =SUM(B5:B12) -> 0
A14: 报表金额 | B14: ='RP 006'!E110 -> 0
B15: =E13-B14 -> 0
B16: =IF(B15=0,"OK","NO") -> OK
A17: 说明：重要的预计负债，应披露相关重要假设、估计。
A19: 按照《企业会计准则第 14 号--收入》（2017 年修订）的相关规定确认为预计负债的应付退货款，应当根据"预计负债"科目下的"应付退货款"明细科目是否在一年或一个正常营业周期内清偿，在"其他流动负债"或"预计负债"项目中填列。

Sheet RP 065
A1: 公司名称 | B1: =基础信息!B6 -> 0
A2: 财务期间 | B2: =基础信息!B9 -> 0
A3: 内容 | B3: 递延收益
A4: 项 目 | B4: 期初数 | C4: 本期增加 | D4: 本期减少 | E4: 期末数 | F4: 形成原因
A5: 政府补助 | E5: =B5+C5-D5 -> 0
E6: =B6+C6-D6 -> 0
A7: 合 计 | B7: =SUM(B5:B6) -> 0 | C7: =SUM(C5:C6) -> 0 | D7: =SUM(D5:D6) -> 0 | E7: =SUM(E5:E6) -> 0 | F7: =SUM(F5:F6) -> 0
A8: 报表金额 | F8: ='RP 006'!E111 -> 0
F9: =E7-F8 -> 0
F10: =IF(F9=0,"OK","NO") -> OK
A12: 说明：
A13: 【公司根据《企业会计准则》规定计入“递延收益”科目的金额，应按如下原则确定所属的报表项目：
A14: （1）受益期预计在一年以内（含一年）的，应在“其他流动负债”项目列报；
A15: （2）自资产负债表日起算的受益期限超过一年的，在“递延收益”目中列报。
A16: 其中：递延收益-政府补助情况
A17: 补助项目 | B17: 期初余额 | C17: 本期新增补助金额 | D17: 本期计入营业外收入金额 | E17: 其他变动 | F17: 期末余额 | G17: 与资产相关/与收益相关
A21: 合 计 | B21: =SUM(B18:B20) -> 0 | C21: =SUM(C18:C20) -> 0 | D21: =SUM(D18:D20) -> 0 | E21: =SUM(E18:E20) -> 0 | F21: =SUM(F18:F20) -> 0 | G21: =SUM(G18:G20) -> 0
A22: 说明：
A23: （1）XX补助项目，相关文件未明确规定补助对象，由于该项目未来不会形成长期资产，本集团将其作为与收益相关的政府补助。
A24: （信息披露解释性公告第2号规定：公司应当遵循重要性原则，对涉及政府补助的负债项目，在财务报表附注的相关项目下，逐项披露相关期初余额、本期新增补助金额、本期计入营业外收入金额、本期转入资本公积金额以及期末余额。对于相关文件未明确规定补助对象的政府补助项目，公司还应单独说明其划分依据。）

Sheet RP 066
A1: 公司名称 | B1: =基础信息!B6 -> 0
A2: 财务期间 | B2: =基础信息!B9 -> 0
A3: 内容 | B3: 其他非流动负债
A4: 项 目 | B4: 期末数
A5: 合同负债
A8: 合 计 | B8: =SUM(B5:B7) -> 0
A9: 报表金额 | B9: ='RP 006'!E113 -> 0
B10: =B8-B9 -> 0
B11: =IF(B10=0,"OK","NO") -> OK

Sheet RP 067
A1: 公司名称 | B1: =基础信息!B6 -> 0
A2: 财务期间 | B2: =基础信息!B9 -> 0
A3: 内容 | B3: 营业收入及成本
A4: A、营业收入列示如下：
A5: 项 目 | B5: 本期
B6: 收入 | C6: 成本
A7: 主营业务收入
A8: 其他业务收入
A9: 合 计 | C9: =SUM(C7:C8) -> 0
A10: 报表金额 | C10: ='RP 006'!E135 -> 0
C11: =C9-C10 -> 0
C12: =IF(C11=0,"OK","NO") -> OK
A14: B、主营业务收入及成本列示如下：
A15: 项 目 | B15: 本期
B16: 收入 | C16: 成本
A17: 系统集成收入 | B17: =B18+B19 -> 0 | C17: =C18+C19 -> 0
A18: 其中：系统产品及系统集成服务
A19: 软件及软件开发
A20: 专业服务收入
A21: 合 计 | B21: =SUM(B17,B20) -> 0 | C21: =SUM(C17,C20) -> 0
B22: =B21-C7 -> 0
B23: =IF(B22=0,"OK","NO") -> OK
A24: 如果企业没有报告分部，应在此处增加披露以下内容：
A25: （1）主营业务（分行业或业务）
A26: 行业（或：业务）名称 | B26: 本期发生额 | D26: 上期发生额
B27: 营业收入 | C27: 营业成本 | D27: 营业收入 | E27: 营业成本
A31: 合 计
A32: （2）主营业务（分产品）
A33: 产品名称 | B33: 本期发生额 | D33: 上期发生额
B34: 营业收入 | C34: 营业成本 | D34: 营业收入 | E34: 营业成本
A38: 合 计
A39: （3）主营业务（分地区）
A40: 地区名称 | B40: 本期发生额 | D40: 上期发生额
B41: 营业收入 | C41: 营业成本 | D41: 营业收入 | E41: 营业成本
A45: 合 计

Sheet RP 068
A1: 公司名称 | B1: =基础信息!B6 -> 0
A2: 财务期间 | B2: =基础信息!B9 -> 0
A3: 内容 | B3: 税金及附加
A4: 项 目 | B4: 计缴标准 | C4: 本期
A5: 消费税
A6: 城市维护建设税
A7: 教育费附加
A8: 资源税
A9: 房产税
A10: 土地使用税
A11: 车船使用税
A12: 印花税
A14: 合 计 | C14: =SUM(C5:C13) -> 0
A15: 报表金额 | C15: ='RP 006'!E137 -> 0
C16: =C14-C15 -> 0
C17: =IF(C16=0,"OK","NO") -> OK

Sheet RP 069
A1: 公司名称 | B1: =基础信息!B6 -> 0
A2: 财务期间 | B2: =基础信息!B9 -> 0
A3: 内容 | B3: 销售费用
A4: 项 目 | B4: 本期发生额
A9: 合 计 | B9: =SUM(B5:B8) -> 0
A10: 报表金额 | B10: ='RP 006'!E138 -> 0
B11: =B9-B10 -> 0
B12: =IF(B11=0,"OK","NO") -> OK

Sheet RP 070
A1: 公司名称 | B1: =基础信息!B6 -> 0
A2: 财务期间 | B2: =基础信息!B9 -> 0
A3: 内容 | B3: 管理费用
A4: 项 目 | B4: 本期发生额
A9: 合 计 | B9: =SUM(B5:B8) -> 0
A10: 报表金额 | B10: ='RP 006'!E139 -> 0
B11: =B9-B10 -> 0
B12: =IF(B11=0,"OK","NO") -> OK

Sheet RP 071
A1: 公司名称 | B1: =基础信息!B6 -> 0
A2: 财务期间 | B2: =基础信息!B9 -> 0
A3: 内容 | B3: 研发费用
A4: 项 目 | B4: 本期发生额
A9: 合 计 | B9: =SUM(B5:B8) -> 0
A10: 报表金额 | B10: ='RP 006'!E140 -> 0
B11: =B9-B10 -> 0
B12: =IF(B11=0,"OK","NO") -> OK

Sheet RP 072
A1: 公司名称 | B1: =基础信息!B6 -> 0
A2: 财务期间 | B2: =基础信息!B9 -> 0
A3: 内容 | B3: 财务费用
A4: 项 目 | B4: 本期发生额
A5: 利息费用
A6: 减：利息资本化
A7: 减：利息收入
A8: 承兑汇票贴息
A9: 汇兑损益
A10: 减：汇兑损益资本化
A11: 手续费及其他
A12: 合 计
A13: 报表金额 | B13: ='RP 006'!E141 -> 0
B14: =B12-B13 -> 0
B15: =IF(B14=0,"OK","NO") -> OK
A16: 说明：
A17: B、利息资本化情况描述：（利息资本化金额已计入的项目，所确定的资本化率）

Sheet RP 073
A1: 公司名称 | B1: =基础信息!B6 -> 0
A2: 财务期间 | B2: =基础信息!B9 -> 0
A3: 内容 | B3: 其他收益
A4: 补助项目（产生其他收益的来源） | B4: 本期发生额 | C4: 上期发生额 | D4: 与资产相关/ 与收益相关
P5: 固定资产处置利得
P6: 无形资产处置利得
P7: 非货币性资产交换利得
P8: 债务重组利得
P9: 政府补助
P10: 捐赠利得
P11: 增值税返还
P12: 赔偿偿收入
P13: 罚款
A15: 合 计 | B15: =SUM(B5:B14) -> 0 | C15: =SUM(C5:C14) -> 0
A16: 报表金额 | B16: ='RP 006'!E146 -> 0
B17: =B15-B16 -> 0
B18: =IF(B17=0,"OK","NO") -> OK
A19: 提示：与日常活动相关的政府补助，采用总额法时计入其他收益。

Sheet RP 074
A1: 公司名称 | B1: =基础信息!B6 -> 0
A2: 财务期间 | B2: =基础信息!B9 -> 0
A3: 内容 | B3: 投资收益
A4: A、按被投资单位
A5: 项 目 | B5: 本期发生额
A6: 权益法核算的长期股权投资收益
A7: 处置长期股权投资产生的投资收益
A8: 以公允价值计量且其变动计入当期损益的金融资产持有期间取得的投资收益
A9: 持有至到期投资持有期间取得的投资收益
A10: 可供出售金融资产持有期间取得的投资收益
A11: 处置以公允价值计量且其变动计入当期损益的金融资产取得的投资收益
A12: 处置持有至到期投资取得的投资收益
A13: 处置可供出售金融资产取得的投资收益
A14: 丧失控制权后，剩余股权按公允价值重新计量产生的利得
A15: 其他
A16: 合 计 | B16: =SUM(B6:B15) -> 0
A17: 报表金额 | B17: ='RP 006'!E147 -> 0
B18: =B16-B17 -> 0
B19: =IF(B18=0,"OK","NO") -> OK
A20: 投资收益汇回存在重大限制的情况
A21: 被投资单位 | B21: 存在限制的原因

Sheet RP 075
A1: 公司名称 | B1: =基础信息!B6 -> 0
A2: 财务期间 | B2: =基础信息!B9 -> 0
A3: 内容 | B3: 净敞口套期收益
B4: 本期发生额
A9: 合 计 | B9: =SUM(B5:B8) -> 0
A10: 报表金额 | B10: ='RP 006'!E149 -> 0
B11: =B9-B10 -> 0
B12: =IF(B11=0,"OK","NO") -> OK

Sheet RP 076
A1: 公司名称 | B1: =基础信息!B6 -> 0
A2: 财务期间 | B2: =基础信息!B9 -> 0
A3: 内容 | B3: 公允价值变动损益
A4: 产生公允价值变动收益的来源 | B4: 本期发生额
A5: 其中：衍生金融工具产生的公允价值变动收益
A6: 以公允价值计量且其变动计入当期损益的金融负债
A7: 按公允价值计量的投资性房地产
A8: 其 他
A9: 合 计 | B9: =SUM(B5:B8) -> 0
A10: 报表金额 | B10: ='RP 006'!E150 -> 0
B11: =B9-B10 -> 0
B12: =IF(B11=0,"OK","NO") -> OK

Sheet RP 077
A1: 公司名称 | B1: =基础信息!B6 -> 0
A2: 财务期间 | B2: =基础信息!B9 -> 0
A3: 内容 | B3: 信用减值损失
A4: 项 目 | B4: 本期
A18: 合 计 | B18: =SUM(B5:B17) -> 0
A19: 报表金额 | B19: ='RP 006'!E151 -> 0
B20: =B18-B19 -> 0
B21: =IF(B20=0,"OK","NO") -> OK

Sheet RP 078
A1: 公司名称 | B1: =基础信息!B6 -> 0
A2: 财务期间 | B2: =基础信息!B9 -> 0
A3: 内容 | B3: 资产减值损失
A4: 项 目 | B4: 本期
A5: 坏账损失
A6: 存货跌价损失
A7: 可供出售金融资产减值损失
A8: 持有至到期投资减值损失
A9: 长期股权投资减值损失
A10: 投资性房地产减值损失
A11: 固定资产减值损失
A12: 工程物资减值损失
A13: 在建工程减值损失
A14: 生产性生物资产减值损失
A15: 无形资产减值损失
A16: 商誉减值损失
A17: 其 他
A18: 合 计 | B18: =SUM(B5:B17) -> 0
A19: 报表金额 | B19: ='RP 006'!E152 -> 0
B20: =B18-B19 -> 0
B21: =IF(B20=0,"OK","NO") -> OK

Sheet RP 079
A1: 公司名称 | B1: =基础信息!B6 -> 0
A2: 财务期间 | B2: =基础信息!B9 -> 0
A3: 内容 | B3: 资产处置收益
A4: 项目 | B4: 本期发生额 | C4: 上期发生额
A5: 持有待售的非流动资产（处置组）处置利得（损失以“-”填列） | O5: 固定资产处置利得
A6: 固定资产处置利得（损失以“-”填列） | O6: 无形资产处置利得
A7: 在建工程处置利得（损失以“-”填列） | O7: 非货币性资产交换利得
A8: 生产性生物资产处置利得（损失以“-”填列） | O8: 债务重组利得
A9: 无形资产处置利得（损失以“-”填列） | O9: 政府补助
A10: 债务重组中因处置非流动资产产生的利得（损失以“-”填列） | O10: 捐赠利得
A11: 非货币性资产交换产生的利得（损失以“-”填列） | O11: 增值税返还
O12: 赔偿偿收入
O13: 罚款
A15: 合 计 | B15: =SUM(B5:B14) -> 0 | C15: =SUM(C5:C14) -> 0
A16: 报表金额 | B16: ='RP 006'!E153 -> 0
B17: =B15-B16 -> 0
B18: =IF(B17=0,"OK","NO") -> OK

Sheet RP 080
A1: 公司名称 | B1: =基础信息!B6 -> 0
A2: 财务期间 | B2: =基础信息!B9 -> 0
A3: 内容 | B3: 营业外收入
A4: 项 目 | B4: 本期 | C4: 计入当期非经常性损益的金额
A5: 债务重组 | O5: 固定资产处置利得
A6: 接受捐赠 | O6: 无形资产处置利得
A7: 政府补助 | O7: 非货币性资产交换利得
A8: 盘盈利得 | O8: 债务重组利得
A9: … | O9: 政府补助
O10: 捐赠利得
O11: 增值税返还
O12: 赔偿偿收入
O13: 罚款
A15: 合 计 | B15: =SUM(B5:B14) -> 0 | C15: =SUM(C5:C14) -> 0
A16: 报表金额 | B16: ='RP 006'!E155 -> 0
B17: =B15-B16 -> 0
B18: =IF(B17=0,"OK","NO") -> OK

Sheet RP 081
A1: 公司名称 | B1: =基础信息!B6 -> 0
A2: 财务期间 | B2: =基础信息!B9 -> 0
A3: 内容 | B3: 营业外支出
A4: 项 目 | B4: 本期 | C4: 计入当期非经常性损益的金额 | N4: 不能修改！！！！
A5: 债务重组损失 | N5: 固定资产处置损失
A6: 对外捐赠 | N6: 无形资产处置损失
A7: 非常损失 | N7: 非流动资产交换利得
A8: 盘亏损失 | N8: 债务重组损失
A9: 非流动资产毁损报废损失 | N9: 公益性捐赠支出
A10: … | N10: 预计负债
N11: 滞纳金
N12: 固定资产报废损失
N13: 罚款
N14: ……
A15: 合 计 | B15: =SUM(B5:B14) -> 0 | C15: =SUM(C5:C14) -> 0
A16: 报表金额 | B16: ='RP 006'!E156 -> 0
B17: =B15-B16 -> 0
B18: =IF(B17=0,"OK","NO") -> OK

Sheet RP 082
A1: 公司名称 | B1: =基础信息!B6 -> 0
A2: 财务期间 | B2: =基础信息!B9 -> 0
A3: 内容 | B3: 所得税费用
A4: （1）所得税费用明细
A5: 项 目 | B5: 本期
A6: 当期所得税
A7: 递延所得税
A8: 合 计 | B8: =SUM(B6:B7) -> 0
A9: 报表金额 | B9: ='RP 006'!E158 -> 0
B10: =B8-B9 -> 0
B11: =IF(B10=0,"OK","NO") -> OK
A13: （2）所得税费用与利润总额的关系列示如下：
A14: 项 目 | B14: 本期
A15: 利润总额
A16: 按法定（或适用）税率计算的所得税费用（利润总额*XX%）
A17: 某些子公司适用不同税率的影响
A18: 对以前期间当期所得税的调整
A19: 归属于合营企业和联营企业的损益
A20: 无须纳税的收入
A21: 不可抵扣的费用
A22: 税率变动的影响对期初递延所得税余额的影响
A23: 利用以前期间的税务亏损
A24: 未确认递延所得税的税务亏损
A25: …
A26: …
A27: …
A28: 所得税费用 | B28: =B16+B17+B18+B19+B20+B21+B22+B23+B24+B27 -> 0
A29: 报表金额-所得税费用 | B29: ='RP 006'!E158 -> 0
A30: 报表金额-利润总额 | B30: ='RP 006'!E157 -> 0
B31: =B28-B29 -> 0
B32: =B30-B15 -> 0
A33: Check Box | B33: =IF(B31=0,"OK","NO") -> OK
A34: Check Box | B34: =IF(B32=0,"OK","NO") -> OK

Sheet RP 083
A1: 公司名称 | B1: =基础信息!B6 -> 0
A2: 财务期间 | B2: =基础信息!B9 -> 0
A3: 内容 | B3: 收到的其他与经营活动有关的现金
A4: 收到的其他与经营活动有关的现金 | B4: ='RP 004 '!C8 -> 0
A5: 项 目 | B5: 本期
A20: 合计 | B20: =SUM(B6:B19) -> 0
B21: =IF(B20=B4,"OK","NO") -> OK

Sheet RP 084
A1: 公司名称 | B1: =基础信息!B6 -> 0
A2: 财务期间 | B2: =基础信息!B9 -> 0
A3: 内容 | B3: 支付的其他与经营活动有关的现金
A4: 支付的其他与经营活动有关的现金 | B4: ='RP 004 '!C13 -> 0
A5: 其中：
A6: 项 目 | B6: 本期
A21: 合计 | B21: =SUM(B7:B20) -> 0
B22: =IF(B21=B4,"OK","NO") -> OK

Sheet RP 085
A1: 公司名称 | B1: =基础信息!B6 -> 0
A2: 财务期间 | B2: =基础信息!B9 -> 0
A3: 内容 | B3: 收到的其他与投资活动有关的现金
A4: 收到的其他与投资活动有关的现金 | B4: ='RP 004 '!C21 -> 0
A5: 项 目 | B5: 本期
A20: 合计 | B20: =SUM(B6:B19) -> 0
B21: =IF(B20=B4,"OK","NO") -> OK

Sheet RP 086
A1: 公司名称 | B1: =基础信息!B6 -> 0
A2: 财务期间 | B2: =基础信息!B9 -> 0
A3: 内容 | B3: 支付的其他与投资活动有关的现金
A4: 支付的其他与投资活动有关的现金 | B4: ='RP 004 '!C26 -> 0
A5: 项 目 | B5: 本期
A20: 合计 | B20: =SUM(B6:B19) -> 0
B21: =IF(B20=B4,"OK","NO") -> OK

Sheet RP 087
A1: 公司名称 | B1: =基础信息!B6 -> 0
A2: 财务期间 | B2: =基础信息!B9 -> 0
A3: 内容 | B3: 收到的其他与筹资活动有关的现金
A4: 收到的其他与筹资活动有关的现金 | B4: ='RP 004 '!C33 -> 0
A5: 项 目 | B5: 本期
A20: 合计 | B20: =SUM(B6:B19) -> 0
B21: =IF(B20=B4,"OK","NO") -> OK

Sheet RP 088
A1: 公司名称 | B1: =基础信息!B6 -> 0
A2: 财务期间 | B2: =基础信息!B9 -> 0
A3: 内容 | B3: 支付的其他与筹资活动有关的现金
A4: 支付的其他与筹资活动有关的现金 | B4: ='RP 004 '!C38 -> 0
A5: 项 目 | B5: 本期
A20: 合计 | B20: =SUM(B6:B19) -> 0
B21: =IF(B20=B4,"OK","NO") -> OK

Sheet RP 089
A1: 公司名称 | B1: =基础信息!B6 -> 0
A2: 财务期间 | B2: =基础信息!B9 -> 0
A3: 内容 | B3: 现金流量表补充资料
A4: 项目 | B4: 审定数
A5: 1、将净利润调节为经营活动现金流量：
A6: 净利润
A7: 加：资产减值准备
A8: 固定资产折旧、油气资产折耗、生产性生物资产折旧
A9: 无形资产摊销
A10: 长期待摊费用摊销 | C10: s
A11: 处置固定资产、无形资产和其他长期资产的损失（收益以“－”号填列）
A12: 固定资产报废损失（收益以“－”号填列）
A13: 公允价值变动损失（收益以“－”号填列）
A14: 财务费用（收益以“－”号填列）
A15: 投资损失（收益以“－”号填列）
A16: 递延所得税资产减少（增加以“－”号填列）
A17: 递延所得税负债增加（减少以“－”号填列）
A18: 存货的减少（增加以“－”号填列）
A19: 经营性应收项目的减少（增加以“－”号填列）
A20: 经营性应付项目的增加（减少以“－”号填列）
A21: 其他
A22: 经营活动产生的现金流量净额 | B22: =SUM(B6:B21) -> 0
A23: 2、不涉及现金收支的重大投资和筹资活动：
A24: 债务转为资本
A25: 一年内到期的可转换公司债券
A26: 融资租入固定资产
A27: 3、现金及现金等价物净变动情况：
A28: 现金的期末余额
A29: 减：现金的期初余额
A30: 加：现金等价物的期末余额
A31: 减：现金等价物的期初余额
A32: 现金及现金等价物净增加额 | B32: =B28-B29+B30-B31 -> 0
A34: （2）本期支付的取得子公司的现金净额
A35: 项 目 | B35: 本期发生额
A36: 本期发生的企业合并于本期支付的现金或现金等价物 | B36: =SUM(B37:B39) -> 0
A37: 其中：XX公司
A38: XX公司
A40: 减：购买日子公司持有的现金及现金等价物 | B40: =SUM(B41:B43) -> 0
A41: 其中：XX公司
A42: XX公司
A44: 加：以前期间发生的企业合并于本期支付的现金或现金等价物 | B44: =SUM(B45:B47) -> 0
A45: 其中：XX公司
A46: XX公司
A48: 取得子公司支付的现金净额 | B48: =B36-B40+B44 -> 0
A50: 说明：
A51: （3）本期收到的处置子公司的现金净额
A52: 项 目 | B52: 本期发生额
A53: 本期处置子公司于本期收到的现金或现金等价物 | B53: =SUM(B54:B57) -> 0
A54: 其中：XX公司
A55: XX公司
A58: 减：丧失控制权日子公司持有的现金及现金等价物 | B58: =SUM(B59:B61) -> 0
A59: 其中：XX公司
A60: XX公司
A62: 加：以前期间处置子公司于本期收到的现金或现金等价物 | B62: =SUM(B63:B66) -> 0
A63: 其中：XX公司
A64: XX公司
A67: 处置子公司收到的现金净额 | B67: =B53-B58+B62 -> 0
A69: 说明：
A70: （4）现金及现金等价物的构成
A71: 项 目 | B71: 期末数
A72: 一、现金
A73: 其中：库存现金
A74: 可随时用于支付的银行存款
A75: 可随时用于支付的其他货币资金
A76: 可用于支付的存放中央银行款项
A77: 存放同业款项
A78: 拆放同业款项
A79: 二、现金等价物
A80: 其中：三个月内到期的债券投资
A81: 三、期末现金及现金等价物余额
A82: （注：现金及现金等价物不含母公司或集团内子公司使用受限制的现金及现金等价物）
A83: 说明：如存在企业持有但不能由母公司或集团内其他子公司使用的大额现金和现金等价物的，披露其金额。

Sheet RP 090
A1: 公司名称 | B1: =基础信息!B6 -> 0
A2: 财务期间 | B2: =基础信息!B9 -> 0
A3: 内容 | B3: 股份支付
A4: 1、计划概述：
A5: 详情如下：
A6: 授与日 | B6: 期初余额 | C6: 本期授出 | D6: 本期行权 | E6: 本期失效 | F6: 本期注销 | G6: 年末余额 | H6: 行权期限 | I6: 每股行权价 | J6: 资本公积-购股权准备余额
B13: =SUM(B7:B12) -> 0 | C13: =SUM(C7:C12) -> 0 | D13: =SUM(D7:D12) -> 0 | E13: =SUM(E7:E12) -> 0 | F13: =SUM(F7:F12) -> 0 | G13: =SUM(G7:G12) -> 0 | J13: =SUM(J7:J12) -> 0
A15: (有多种计划的情况，照此披露)
A18: 2、以权益结算的股份支付的，应披露授予日权益工具公允价值的确定方法；以现金结算的股份支付的，应披露公司承担的、以股份或其他权益工具为基础计算确定的负债的公允价值确定方法。
A23: 3、公司对股份支付进行修改的，应披露修改原因、主要修改条款：

Sheet RP 091
A1: 公司名称 | B1: =基础信息!B6 -> 0
A2: 财务期间 | B2: =基础信息!B9 -> 0
A3: 内容 | B3: 或有事项
A4: 序号 | B4: 或有事项描述 | C4: 预计对财务报表的影响
A5: 1、
A6: 2、
A7: 3、
A11: 或有负债应按未决诉讼或仲裁形成的或有负债、对外提供担保形成的或有负债、其他或有负债（不包括极小可能导致经济利益流出公司的或有负债）等分项披露该事项形成的原因、预计产生的财务影响（如无法预计，应说明理由）、获得补偿的可能性。

Sheet RP 092
A1: 公司名称 | B1: =基础信息!B5 -> 0
A2: 财务期间 | B2: =基础信息!B9 -> 0
A3: 内容 | B3: 承诺事项
A4: 序号 | B4: 或有事项描述 | C4: 预计对财务报表的影响
A5: 1、
A6: 2、
A7: 3、
A9: 对于资产负债表日存在的重大承诺事项，应在财务报表附注中按已签订的尚未履行或尚未完全履行的对外投资合同及有关财务支出、已签订的正在或准备履行的大额发包合同、已签订的正在或准备履行的租赁合同及财务影响、已签订的正在或准备履行的并购协议、已签订的正在或准备履行的重组计划、其他重大财务承诺等分项说明其存在的原因和金额。

Sheet RP 093
A1: 公司名称 | B1: =基础信息!B6 -> 0
A2: 财务期间 | B2: =基础信息!B9 -> 0
A3: 内容 | B3: 资产负债表日后事项
A4: 项目 | B4: 资产负债表日后事项事项描述 | C4: 预计对财务报表的影响 | D4: 无法估计影响数的原因
A5: 股票和债券的发行
A6: 重要的对外投资
A7: 重要的债务重组
A8: 自然灾害
A9: 外汇汇率重要变动
A11: 如果非流动资产或处置组在资产负债表日至财务报告批准报出日之间满足持有待售类别划分条件的，应当作为资产负债表日后非调整事项进行会计处理，并在“附注十三-资产负债表日后事项”中披露持有待售的非流动资产或处置组的出售费用和主要类别，以及每个类别的账面价值和公允价值；持有待售的非流动资产或处置组的出售原因、方式和时间安排；列报持有待售的非流动资产或处置组的分部。

Sheet RP 094
A1: 公司名称 | B1: =基础信息!B6 -> 0
A2: 财务期间 | B2: =基础信息!B9 -> 0
A3: 内容 | B3: 其他重要事项
A4: 序号 | B4: 其他重要事项描述 | C4: 预计对财务报表的影响
A5: 1、
A6: 2、
A7: 3、
A9: 报告期内发生资产置换、转让及出售行为的公司，应专项披露资产置换的详细情况，包括资产账面价值、转让金额、转让原因以及对公司财务状况、经营成果的影响等。 其他对投资者决策有影响的重要事项，应分项说明。
A11: 1、企业合并
A12: （1）同一控制下企业合并
A13: [20XX年[X]月，本公司以现金[X]万元吸收合并了[X公司]，[X公司]系本公司的母公司——[S公司]的子公司，由于合并前后合并双方均受[S公司]控制且该控制并非暂时性，故本合并属同一控制下的企业合并，合并日确定为[X月XX日]。(披露确定合并日的依据。)本公司与[X公司]的吸收合并中取得的资产及负债，均按照合并日在被合并方的账面价值计量。(描述合并的具体情况。)]
A15: [X公司]在合并日、上一会计期间资产负债表日资产及负债的账面价值如下：
A16: 项 目 | C16: 合并日 | D16: XX年X月X日
A17: 流动资产
A18: 长期投资
A19: 固定资产
A20: 无形资产及其他资产
A21: 减：流动负债
A22: 长期负债
A23: ……
A24: 取得净资产
A25: 合并差额（计入权益）
A26: 合并成本
A28: [X公司]自年初至合并日的经营成果和现金流量列示如下：
A29: 项 目 | B29: 20XX年1月1日至X月X日期间
A30: 营业收入
A31: 净利润
A32: 现金流量净额
A34: 取得上述子公司的现金流量净额分析如下：
A35: 项 目 | C35: 金 额
A36: 取得子公司的价格
A37: 取得子公司支付的现金
A38: 减：子公司持有的现金
A39: 取得子公司支付的现金流量净额
A40: [(企业合并发生当期的期末，合并方应当披露与同一控制下企业合并有关的下列信息：(1)以支付现金、转让非现金资产以及承担债务作为合并对价的，所支付对价在合并日的账面价值；以发行权益性证券作为合并对价的，合并中发行权益性证券的数量及定价原则，以及参与合并各方交换有表决权股份的比例。(2)合并合同或协议约定将承担被合并方或有负债的情况。(3)被合并方采用的会计政策与合并方不一致所作调整情况的说明。(4)合并后已处置或准备处置被合并方资产、负债的账面价值、处置价格等。)]
A41: [对同一子公司股权在连续两个会计年度买入再卖出或卖出再买入的，应披露相关的会计处理。)]
A43: （2）非同一控制下企业合并
A44: [本年内，本公司取得了[B公司][90%]股权，合并成本为现金[ ]元及[其他资产][账面价值[ ]元，根据评估确定合并成本的公允价值[ ]元]，购买日确定为8月31日。(披露确定购买日的依据。)(描述合并的具体情况。)]
A46: [B公司]的可辨认资产和负债[及或有负债]于购买日的公允价值、账面价值如下：
A47: 项 目 | C47: 购买日公允价值 | D47: 购买日账面价值
A48: 流动资产
A49: 长期投资
A50: 固定资产
A51: 无形资产及其他资产
A52: 减：流动负债
A53: 长期负债
A54: ……
A55: 购买取得净资产
A56: 购买产生的商誉/[超出合并成本计入当期损益部分]
A57: 合并成本
A59: [B公司]自购买日起至本年末的经营成果和现金流量列示如下：
A60: 项 目 | B60: 20XX年X月X日至12月31日期间
A61: 营业收入
A62: 净利润
A63: 现金流量净额
A64: [(企业合并发生当期的期末，购买方应当披露与非同一控制下企业合并有关的下列信息：(1)合并成本的构成及其账面价值、公允价值及公允价值的确定方法。(2)合同或协议约定将承担被购买方或有负债的情况。(3)合并后已处置或准备处置被购买方资产、负债的账面价值、处置价格等。)]
A65: [对同一子公司股权在连续两个会计年度买入再卖出或卖出再买入的，应披露相关的会计处理。)]
A67: 取得上述子公司的现金流量净额分析如下：
A68: 项 目 | C68: 金 额
A69: 取得子公司的价格
A70: 取得子公司支付的现金
A71: 减：子公司持有的现金
A72: 取得子公司支付的现金流量净额
A74: 2、处置子公司
A75: （1）本年不再纳入合并范围的原子公司
A76: 公司名称 | B76: 注册地 | C76: 业务性质 | D76: 本公司投资额 | E76: 本公司合计的持股比例% | F76: 本公司合计的表决权比例% | G76: 不再成为子公司原因
G77: 〔注X〕
A81: 注1、本公司所属XX有限公司与ZZ有限公司于[20X9年6月30日]签订股权转让协议，以 []元出售其所持有D公司的XX%股权，处置日为20XX年X月1日。故自20XX年X月1日起， 本公司不再将D公司纳入合并范围。
A82: （2）本期出售的子公司出售日、上年末的财务状况列示如下：
A83: 项 目 | B83: （D公司） | D83: （E公司） | F83: （F公司）
B84: 出售日 | C84: 2008.12.31 | D84: 出售日 | E84: 2008.12.31 | F84: 出售日 | G84: 2008.12.31
A85: 流动资产
A86: 长期投资
A87: 固定资产
A88: 无形资产及其他资产
A89: 流动负债
A90: 长期负债
B91: X.XX | D91: X.XX | F91: X.XX
A92: 处置损益 | B92: -- | D92: -- | F92: --
A93: 处置对价 | B93: X.XX | D93: X.XX | F93: X.XX
A95: （3）本期出售的子公司年初至出售日、上年度的经营成果列示如下：
A96: 项 目 | B96: （D公司） | D96: （E公司） | F96: （F公司）
B97: 20X9.01.01-出售日 | C97: 20X8年度 | D97: 20X9.01.01-出售日 | E97: 20X8年度 | F97: 20X9.01.01-出售日 | G97: 20X8年度
A98: 营业收入
A99: 营务利润
A100: 利润总额
A101: 所得税费用
A102: 净利润
A104: （4）处置上述子公司的产生现金流量的净额分析如下：
A105: 项 目 | B105: （D公司） | C105: （E公司） | D105: （F公司）
B106: 20X9.01.01-出售日 | C106: 20X9.01.01-出售日 | D106: 20X9.01.01-出售日
A107: 处置子公司的价格
A108: 处置子公司收到的现金
A109: 减：子公司持有的现金
A110: 处置子公司收到的现金流量净额
A112: 3、终止经营
A113: 项目 | B113: 本期发生额 | C113: 本期发生额 | D113: 上期发生额
A114: 终止经营收入 （A）
A115: 减：终止经营费用（B）
A116: 终止经营利润总额（C） | C116: =C114-C115 -> 0
...

Sheet RP 095
A1: 公司名称 | B1: =基础信息!B6 -> 0
A2: 财务期间 | B2: =基础信息!B9 -> 0
A3: 内容 | B3: 非经常性损益
A4: 项目及其金额如下（损失"-"）
A5: 项 目 | B5: 本期
A6: 非流动性资产处置损益
A7: 越权审批，或无正式批准文件，或偶发性的税收返还、减免
A8: 政府补助
A9: 对非金融企业收取的资金占用费
A10: 取得子公司、联营企业及合营企业的投资成本小于取得投资时应享有被投资单位可辨认净资产公允价值产生的收益
A11: 非货币性资产交换损益
A12: 委托他人投资或管理资产的损益
A13: 因不可抗力因素，如遭受自然灾害而计提的各项资产减值准备
A14: 债务重组损益
A15: 企业重组费用
A16: 交易价格显失公允的交易产生的超过公允价值部分的损益
A17: 同一控制下企业合并产生的子公司期初至合并日的当期净损益
... A27: 其他符合非经常性损益定义的损益项目
A28: 非经常性损益总额 | B28: =SUM(B6:B27) -> 0
A29: 减：非经常性损益的所得税影响数
A30: 非经常性损益净额 | B30: =B28-B29 -> 0
A31: 减：归属于少数股东的非经常性损益净影响数
A32: 归属于公司普通股股东的非经常性损益 | B32: =B30-B31 -> 0
A33: 说明：
A34: （1）（重大非经常性损益项目的说明）
A35: （2）（根据自身正常经营业务的性质和特点将“证监会公告[2008]43号”列举的非经常性损益项目界定为经常性损益的项目的说明)
A36: （3）（其他符合非经常性损益定义的损益项目的说明）

Sheet 0001
A1: 公司名称 | B1: =基础信息!B6 -> 0
A2: 财务期间 | B2: =基础信息!B9 -> 0
A3: 内容

Sheet 0000
A1: 公司名称 | B1: =基础信息!B6 -> 0
A2: 财务期间 | B2: =基础信息!B9 -> 0
A3: 内容

Sheet GT_Custom
A1: C1 | B1: Custom 1
A2: C2 | B2: Custom 2
A3: C3 | B3: Custom 3
A4: C4 | B4: Custom 4
A5: C5 | B5: Custom 5
A6: C6 | B6: Custom 6
A7: C7 | B7: Custom 7
A8: C8 | B8: Custom 8
