Workbook

Sheet 底稿目录
A1: 底稿开列时，可先在以下单元格填写有关内容，以便其他底稿引用有关数据：
A2: 被审计单位： | D2: 序号 | E2: 内容 | F2: 索引号 | G2: 备注
A3: 会计期间：202X年度 | D3: 1 | E3: 资产处置损益实质性程序表 | F3: H10A
A4: 编制人： | D4: =D3+1 | E4: 审定表 | F4: H10-1
A5: 复核人： | D5: =D4+1 | E5: 附注披露信息（上市公司） | G5: 无需打印
A6: 编制日期： | D6: =D5+1 | E6: 附注披露信息（国企） | G6: 无需打印
A7: 复核日期： | D7: =D6+1 | E7: 明细表 | F7: H10-2
D8: =D7+1 | E8: 调整分录汇总 | F8: H10-3
D9: =D8+1 | E9: 检查表 | F9: H10-4
A10: 关于工作底稿与审计程序索引号对应的说明
A11: 1.编制的审计工作底稿应与审计程序对应。审计项目组应根据被审计单位实际情况和风险评估情况在实质性程序表中裁剪、修改或增加审计程序，根据实际执行的审计程序完成相应审计工作底稿，编制的工作底稿中应按自然顺序依次编制索引号，并通过唯一的索引号将与实质性程序表中的程序对应关联（即将工作底稿的索引号填入实质性程序表中的底稿索引号列）。
A15: 2.获取的支持性证据应与审计底稿或程序对应。审计项目组在完成底稿时获取的支持性证据应根据底稿索引号编制下一级按自然顺序排序的索引号（如D1-2-1、D1-2-2、……），并在底稿中说明引用的支持性证据、关联索引号。
A18: 3.工作底稿索引号的编码规则：实质性程序索引号按循环从“D”到“N”,循环内账户以顺序号排列，模板中底稿索引号按账户顺序+自然数顺序（即模板中索引号按二级自然顺序排列，如D1-1、D1-2、D1-3、……D1-N）。

Sheet 资产处置损益实质性程序表H10A
A1: 致同会计师事务所
A2: 资产处置损益实质性程序表
A3: =底稿目录!A2 | C3: =底稿目录!A4 | E3: =底稿目录!A6 | H3: 索引号： | I3: H10A
A4: =底稿目录!A3 | C4: =底稿目录!A5 | E4: =底稿目录!A7 | H4: 页 次：
A5: 一、本账户涉及的科目
A6: 资产处置损益
A7: 二、审计目标与认定的对应关系
A8: 审计目标 | G8: 财务报表的认定
A9: A. 利润表中记录的资产处置损益已发生，且与被审计单位有关，已记录于恰当的账户 | G9: 发生
A10: B. 所有应当记录的资产处置损益均已记录，所有应当包括在财务报表中的相关披露均已包括 | G10: 完整性
A11: C. 与资产处置损益有关的金额及其他数据已恰当记录，相关披露已得到恰当计量和描述 | G11: 准确性
A12: D. 资产处置损益已记录于正确的会计期间 | G12: 截止
A13: E. 资产处置损益已被恰当地汇总或分解且表述清楚，相关披露在按照企业会计准则的编制基础下是相关的、可理解的 | G13: 列报
A14: 三、计划实施的实质性程序
A15: 序号 | B15: 审计程序 | C15: 程序分类 | D15: 审计目标 | I15: 底稿索引号
D16: 发生 | E16: 完整性 | F16: 准确性 | G16: 截止 | H16: 列报 | J16: 根据被审计单位实际情况和风险评估情况裁剪、修改或增加审计程序
A17: 1 | B17: 获取或编制资产处置损益明细表，复核其加计数是否正确，并与报表数、总账数和明细账合计数核对是否相符，并编制审定表。 | C17: 常规★ | D17: √ | E17: √ | F17: √ | G17: √ | I17: H10-1 /H10-2
A18: 2 | B18: 在使用手工编制、自定义信息报告、系统生成的非固定格式报告等由被审计单位生成的信息时，测试有关信息准确性和完整性，并考虑针对编制和维护由被审计单位生成的信息的相关控制实施控制测试，以评价该信息是否能够为实现审计目的提供基础。 | C18: 常规★ | E18: √ | F18: √ | I18: T1 / | J18: 可参见《审计手册》4.2.6，由被审计单位生成的信息可能是由系统生成的、或手工编制的、或二者兼而有之的方式生成的。例如，由被审计单位生成的信息可能包括： • 不涉及自定义的、由系统生成的报告（如，固定格式报告）； • 可能通过人工自定义的、由系统生成的报告，例如，（计算机）查询信息或特别定制的报告； • 手工编制的信息，例如，汇总信息的电子表格或用以支持分配、计算以及调节的电子表格； • 其他系统生成或手工编制的信息，例如，由被审计单位编制的客户发票； • 通过影印、拍摄、扫描或其他方式转换成电子形式的文件记录。
A19: 3 | B19: 对上期发生额的审计：结合本期检查确定资产处置收益的前期期末的截止是否恰当。（适用于首次承接） | C19: 备选 | D19: √ | E19: √ | F19: √ | G19: √ | J19: 由被审计单位生成的信息不包括： • 总分类账或明细分类账、试算平衡表、或经审计的财务报表； • 第三方（除了服务机构）的报表或报告，例如，原始银行对账单，或函证的回函； • 外部数据（例如，第三方发布的数据，如，定价来源）。
A20: 4 | B20: 结合固定资产、无形资产等相关科目审计，检查支持性文件，确定入账金额及会计处理是否正确。 | C20: 常规★ | D20: √ | E20: √ | F20: √ | G20: √ | I20: H10-4
A21: 5 | B21: 确定需在财务报表中单独披露的信息已被记录。 | C21: 常规★ | H21: √ | I21: A 1-1/A1-15 /A1-16

Sheet 审定表H10-1
A1: 致同会计师事务所
A2: 资产处置损益审定表
A3: =底稿目录!A2 | C3: =底稿目录!A4 | H3: =底稿目录!A6 | J3: 索引号： | K3: H10-1
A4: =底稿目录!A3 | C4: =底稿目录!A5 | H4: =底稿目录!A7 | J4: 页 次：
A5: 项目名称 | B5: 本期未审数 | C5: 账项调整 | D5: 重分类调整 | E5: 本期审定数 | F5: 索引号 | G5: 上期未审数 | H5: 账项调整 | I5: 重分类调整 | J5: 上期审定数 | K5: 备注
A6: ='明细表H10-2'!A8 | B6: ='明细表H10-2'!N8 | C6: ='明细表H10-2'!O8 | D6: ='明细表H10-2'!P8 | E6: =B6+C6+D6 | F6: H10-2 | G6: ='明细表H10-2'!U8 | H6: ='明细表H10-2'!V8 | I6: ='明细表H10-2'!W8 | J6: =G6+H6+I6
A7: ='明细表H10-2'!A9 | B7: ='明细表H10-2'!N9 | C7: ='明细表H10-2'!O9 | D7: ='明细表H10-2'!P9 | E7: =B7+C7+D7 | F7: H10-2 | G7: ='明细表H10-2'!U9 | H7: ='明细表H10-2'!V9 | I7: ='明细表H10-2'!W9 | J7: =G7+H7+I7
A8: ='明细表H10-2'!A10 | B8: ='明细表H10-2'!N10 | C8: ='明细表H10-2'!O10 | D8: ='明细表H10-2'!P10 | E8: =B8+C8+D8 | F8: H10-2 | G8: ='明细表H10-2'!U10 | H8: ='明细表H10-2'!V10 | I8: ='明细表H10-2'!W10 | J8: =G8+H8+I8
A9: ='明细表H10-2'!A11 | B9: ='明细表H10-2'!N11 | C9: ='明细表H10-2'!O11 | D9: ='明细表H10-2'!P11 | E9: =B9+C9+D9 | F9: H10-2 | G9: ='明细表H10-2'!U11 | H9: ='明细表H10-2'!V11 | I9: ='明细表H10-2'!W11 | J9: =G9+H9+I9
A10: ='明细表H10-2'!A12 | B10: ='明细表H10-2'!N12 | C10: ='明细表H10-2'!O12 | D10: ='明细表H10-2'!P12 | E10: =B10+C10+D10 | F10: H10-2 | G10: ='明细表H10-2'!U12 | H10: ='明细表H10-2'!V12 | I10: ='明细表H10-2'!W12 | J10: =G10+H10+I10
A11: ='明细表H10-2'!A13 | B11: ='明细表H10-2'!N13 | C11: ='明细表H10-2'!O13 | D11: ='明细表H10-2'!P13 | E11: =B11+C11+D11 | F11: H10-2 | G11: ='明细表H10-2'!U13 | H11: ='明细表H10-2'!V13 | I11: ='明细表H10-2'!W13 | J11: =G11+H11+I11
A12: ='明细表H10-2'!A14 | B12: ='明细表H10-2'!N14 | C12: ='明细表H10-2'!O14 | D12: ='明细表H10-2'!P14 | E12: =B12+C12+D12 | F12: H10-2 | G12: ='明细表H10-2'!U14 | H12: ='明细表H10-2'!V14 | I12: ='明细表H10-2'!W14 | J12: =G12+H12+I12
A13: ='明细表H10-2'!A15 | B13: ='明细表H10-2'!N15 | C13: ='明细表H10-2'!O15 | D13: ='明细表H10-2'!P15 | E13: =B13+C13+D13 | F13: H10-2 | G13: ='明细表H10-2'!U15 | H13: ='明细表H10-2'!V15 | I13: ='明细表H10-2'!W15 | J13: =G13+H13+I13
A14: ='明细表H10-2'!A16 | B14: ='明细表H10-2'!N16 | C14: ='明细表H10-2'!O16 | D14: ='明细表H10-2'!P16 | E14: =B14+C14+D14 | F14: H10-2 | G14: ='明细表H10-2'!U16 | H14: ='明细表H10-2'!V16 | I14: ='明细表H10-2'!W16 | J14: =G14+H14+I14
A15: 合计 | B15: =SUM(B6:B14) | C15: =SUM(C6:C14) | D15: =SUM(D6:D14) | E15: =SUM(E6:E14) | G15: =SUM(G6:G14) | H15: =SUM(H6:H14) | I15: =SUM(I6:I14) | J15: =SUM(J6:J14)
A16: 试算平衡表数（TB 6115净发生额=贷-借）
A17: 差异数 | E17: =E15-E16 | J17: =J15-J16
A18: 提示：
A19: 1.关注非经常性损益列报的正确性。非经常性损益是指公司发生的与生产经营无直接关系，以及虽与生产经营相关，但由于其性质、金额或发生频率，影响了真实、公允地评价公司当期经营成果和获利能力的各项收入、支出，通常企业固定资产或长期资产的处置收益或损失、债务重组损益、资产置换损益等应列报为非经常性损益。
A20: 2.新债务重组准则下，不再区分资产转让损益与债务重组损益。3.使用权资产、油气资产处置损益计入6115；投资性房地产、金融工具、长期股权投资处置不通过本科目。4.本期审定数应与明细表H10-2期末审定合计、检查表抽查总体勾稽；差异数非0须说明或调整。

Sheet 附注披露信息（上市公司）
A1: 致同会计师事务所
A2: 资产处置损益附注披露信息
A3: =底稿目录!A2 | B3: =底稿目录!A4 | C3: =底稿目录!A6 | E3: 索引号： | F3: 返回目录
A4: =底稿目录!A3 | B4: =底稿目录!A5 | C4: =底稿目录!A7 | E4: 页 次：
A5: 附注披露信息（上市公司）：
A7: 74、资产处置收益（损失以“-”填列）（注：以下不存在的项目可以删除）
A8: 项 目 | B8: 本期发生额 | C8: 上期发生额
A9: 持有待售的非流动资产（处置组）处置利得（损失以“-”填列） | B9: ='审定表H10-1'!E6 | C9: ='审定表H10-1'!J6
A10: 固定资产处置利得（损失以“-”填列） | B10: ='审定表H10-1'!E7 | C10: ='审定表H10-1'!J7
A11: 在建工程处置利得（损失以“-”填列） | B11: ='审定表H10-1'!E8 | C11: ='审定表H10-1'!J8
A12: 生产性生物资产处置利得（损失以“-”填列） | B12: ='审定表H10-1'!E9 | C12: ='审定表H10-1'!J9
A13: 无形资产处置利得（损失以“-”填列） | B13: ='审定表H10-1'!E10 | C13: ='审定表H10-1'!J10
A14: 债务重组中因处置非流动资产产生的利得（损失以"-"填列） | B14: ='审定表H10-1'!E11 | C14: ='审定表H10-1'!J11
A15: 非货币性资产交换产生的利得（损失以“-”填列） | B15: ='审定表H10-1'!E12 | C15: ='审定表H10-1'!J12
A16: 使用权资产处置利得（损失以"-"填列） | B16: ='审定表H10-1'!E13 | C16: ='审定表H10-1'!J13
A17: 油气资产处置利得（损失以"-"填列） | B17: ='审定表H10-1'!E14 | C17: ='审定表H10-1'!J14
A18: 试运行销售损益
A19: 合 计 | B19: =SUM(B9:B18) | C19: =SUM(C9:C18)
A21: 【提示：
A22: 1.对于不构成业务的资产组的处置收益，无论直接出售还是先持有待售再出售，均整体计入资产处置收益，与资产组相关的其他综合收益转入资产处置收益。
A23: 2.对于业务（包括子公司和分公司）处置的收益，无论直接出售还是先持有待售再出售，均整体计入投资收益，与业务相关的其他综合收益同时转入投资收益。
A24: 3.单项的投资性房地产的处置，无论是直接出售还是先划分为持有待售资产再出售，处置损益均计入“其他业务收入/成本”，不计入“资产处置收益”。4.使用权资产、油气资产处置损益计入资产处置收益；不适用项目可删除对应行。】
A25: （1）试运行销售损益
A27: 项 目 | B27: 本期发生额 | D27: 上期发生额
B28: 收入 | C28: 成本 | D28: 收入 | E28: 成本
A29: 固定资产试运行销售
A30: 研发样品销售
A31: 合 计
A32: （说明成本的具体核算方法。）

Sheet 附注披露信息（国企）
A1: 致同会计师事务所
A2: 资产处置损益附注披露信息
A3: =底稿目录!A2 | B3: =底稿目录!A4 | C3: =底稿目录!A6 | D3: 索引号： | E3: 返回目录
A4: =底稿目录!A3 | B4: =底稿目录!A5 | C4: =底稿目录!A7 | D4: 页 次：
A5: 附注披露信息（国企）：
A7: 72、资产处置收益（损失以“-”号填列）（不适用的项目，删除）
A8: 项 目 | B8: 本期发生额 | C8: 上期发生额 | D8: 计入当期非经常性损益的金额
A9: 持有待售的非流动资产（处置组）处置利得 | B9: ='审定表H10-1'!E6 | C9: ='审定表H10-1'!J6 | D9: =B9
A10: 固定资产处置利得 | B10: ='审定表H10-1'!E7 | C10: ='审定表H10-1'!J7 | D10: =B10
A11: 在建工程处置利得 | B11: ='审定表H10-1'!E8 | C11: ='审定表H10-1'!J8 | D11: =B11
A12: 生产性生物资产处置利得 | B12: ='审定表H10-1'!E9 | C12: ='审定表H10-1'!J9 | D12: =B12
A13: 无形资产处置利得 | B13: ='审定表H10-1'!E10 | C13: ='审定表H10-1'!J10 | D13: =B13
A14: 债务重组中因处置非流动资产产生的利得 | B14: ='审定表H10-1'!E11 | C14: ='审定表H10-1'!J11 | D14: =B14
A15: 非货币性资产交换产生的利得 | B15: ='审定表H10-1'!E12 | C15: ='审定表H10-1'!J12 | D15: =B15
A16: 使用权资产处置利得 | B16: ='审定表H10-1'!E13 | C16: ='审定表H10-1'!J13 | D16: =B16
A17: 油气资产处置利得 | B17: ='审定表H10-1'!E14 | C17: ='审定表H10-1'!J14 | D17: =B17
A18: 试运行销售损益
A20: 合 计 | B20: =SUM(B9:B18) | C20: =SUM(C9:C18) | D20: =SUM(D9:D18)
A22: 【提示：反映企业出售划分为持有待售的非流动资产（金融工具、长期股权投资和投资性房地产除外）或处置组时确认的处置利得或损失，以及处置未划分为持有待售的固定资产、在建工程、生产性生物资产及无形资产而产生的处置利得或损失。债务重组中因处置非流动资产产生的利得或损失和非货币性资产交换产生的利得或损失也包括在本项目内。该项目应根据在损益类科目新设置的“资产处置损益”科目的发生额分析填列；如为处置损失，以“-”号填列。】
A23: 【提示：1、针对业务（包括子公司和分公司）处置，不论直接出售还是先持有待售再出售，相关处置损益均计入“投资收益”，相关OCI在处置完成时转入“投资收益”。
A24: 2、不构成业务的资产组处置（资产包涵盖42号准则规范及不在42号准则规范的相关资产），除非该资产组仅包括金融工具和长投（其处置损益计入“投资收益”），无论直接出售还是先持有待售再出售，相关处置损益打包确认，均计入“资产处置收益”。与处置组相关的OCI也转入“资产处置收益”。
A25: 3、单项的投资性房地产的处置，无论是直接出售还是先划分为持有待售资产再出售，处置损益均计入 “其他业务收入/成本”】

Sheet 明细表H10-2
A1: 致同会计师事务所
A2: 资产处置损益明细表
A3: =底稿目录!A2 | J3: =底稿目录!A4 | P3: =底稿目录!A6 | Y3: 索引号： | Z3: H10-2
A4: =底稿目录!A3 | J4: =底稿目录!A5 | P4: =底稿目录!A7 | Y4: 页 次：
A5: 一、审计目标：1. 利润表中记录的资产处置损益已发生，且与被审计单位有关，已记录于恰当的账户；2. 所有应当记录的资产处置损益均已记录，所有应当包括在财务报表中的相关披露均已包括； 3. 与资产处置损益有关的金额及其他数据已恰当记录，相关披露已得到恰当计量和描述；4. 资产处置损益已记录于正确的会计期间。
A6: 二、审计过程:
A7: 项目 | B7: 1月 | C7: 2月 | D7: 3月 | E7: 4月 | F7: 5月 | G7: 6月 | H7: 7月 | I7: 8月 | J7: 9月 | K7: 10月 | L7: 11月 | M7: 12月 | N7: 本期合计 | O7: 账项调整 | P7: 重分类调整 | Q7: 期末审定数 | R7: 与相关科目勾稽 | S7: 与相关科目勾稽金额 | T7: 结构比 | U7: 上年同期发生数 | V7: 账项调整 | W7: 重分类调整 | X7: 上年同期审定数 | Y7: 结构比 | Z7: 增长比例
A8: 持有待售的非流动资产（处置组）处置利得（损失以“-”填列） | N8: =SUM(B8:M8) | Q8: =N8+O8+P8 | R8: 与持有待售相关底稿勾稽 | T8: =IF($Q$17=0,0,Q8/$Q$17) | X8: =U8+V8+W8 | Y8: =IF($X$17=0,0,X8/$X$17) | Z8: =IF(AND(X8=0,Q8>0),1,IF(AND(X8=0,Q8=0),0,(Q8-X8)/X8))
A9: 固定资产处置利得（损失以“-”填列） | N9: =SUM(B9:M9) | Q9: =N9+O9+P9 | R9: 与H1固定资产处置/H6清理勾稽 | T9: =IF($Q$17=0,0,Q9/$Q$17) | X9: =U9+V9+W9 | Y9: =IF($X$17=0,0,X9/$X$17) | Z9: =IF(AND(X9=0,Q9>0),1,IF(AND(X9=0,Q9=0),0,(Q9-X9)/X9))
A10: 在建工程处置利得（损失以“-”填列） | N10: =SUM(B10:M10) | Q10: =N10+O10+P10 | R10: 与H2在建工程处置勾稽 | T10: =IF($Q$17=0,0,Q10/$Q$17) | X10: =U10+V10+W10 | Y10: =IF($X$17=0,0,X10/$X$17) | Z10: =IF(AND(X10=0,Q10>0),1,IF(AND(X10=0,Q10=0),0,(Q10-X10)/X10))
A11: 生产性生物资产处置利得（损失以“-”填列） | N11: =SUM(B11:M11) | Q11: =N11+O11+P11 | R11: 与H7生产性生物资产处置勾稽 | T11: =IF($Q$17=0,0,Q11/$Q$17) | X11: =U11+V11+W11 | Y11: =IF($X$17=0,0,X11/$X$17) | Z11: =IF(AND(X11=0,Q11>0),1,IF(AND(X11=0,Q11=0),0,(Q11-X11)/X11))
A12: 无形资产处置利得（损失以“-”填列） | N12: =SUM(B12:M12) | Q12: =N12+O12+P12 | R12: 与H8无形资产处置勾稽 | T12: =IF($Q$17=0,0,Q12/$Q$17) | X12: =U12+V12+W12 | Y12: =IF($X$17=0,0,X12/$X$17) | Z12: =IF(AND(X12=0,Q12>0),1,IF(AND(X12=0,Q12=0),0,(Q12-X12)/X12))
A13: 债务重组中因处置非流动资产产生的利得（损失以“-”填列） | N13: =SUM(B13:M13) | Q13: =N13+O13+P13 | R13: 与债务重组事项底稿勾稽（新准则下可并入对应资产类别） | T13: =IF($Q$17=0,0,Q13/$Q$17) | X13: =U13+V13+W13 | Y13: =IF($X$17=0,0,X13/$X$17) | Z13: =IF(AND(X13=0,Q13>0),1,IF(AND(X13=0,Q13=0),0,(Q13-X13)/X13))
A14: 非货币性资产交换产生的利得（损失以“-”填列） | N14: =SUM(B14:M14) | Q14: =N14+O14+P14 | R14: 与非货币性资产交换底稿勾稽 | T14: =IF($Q$17=0,0,Q14/$Q$17) | X14: =U14+V14+W14 | Y14: =IF($X$17=0,0,X14/$X$17) | Z14: =IF(AND(X14=0,Q14>0),1,IF(AND(X14=0,Q14=0),0,(Q14-X14)/X14))
A15: 使用权资产处置利得（损失以"-"填列） | N15: =SUM(B15:M15) | Q15: =N15+O15+P15 | R15: 与使用权资产/租赁相关底稿勾稽 | T15: =IF($Q$17=0,0,Q15/$Q$17) | X15: =U15+V15+W15 | Y15: =IF($X$17=0,0,X15/$X$17) | Z15: =IF(AND(X15=0,Q15>0),1,IF(AND(X15=0,Q15=0),0,(Q15-X15)/X15))
A16: 油气资产处置利得（损失以"-"填列） | N16: =SUM(B16:M16) | Q16: =N16+O16+P16 | R16: 与H5油气资产处置勾稽 | T16: =IF($Q$17=0,0,Q16/$Q$17) | X16: =U16+V16+W16 | Y16: =IF($X$17=0,0,X16/$X$17) | Z16: =IF(AND(X16=0,Q16>0),1,IF(AND(X16=0,Q16=0),0,(Q16-X16)/X16))
A17: 合计 | B17: =SUM(B8:B16) | C17: =SUM(C8:C16) | D17: =SUM(D8:D16) | E17: =SUM(E8:E16) | F17: =SUM(F8:F16) | G17: =SUM(G8:G16) | H17: =SUM(H8:H16) | I17: =SUM(I8:I16) | ... Q17: =SUM(Q8:Q16) | T17: =IF($Q$17=0,0,Q17/$Q$17) | U17: =SUM(U8:U16) | V17: =SUM(V8:V16) | W17: =SUM(W8:W16) | X17: =U17+V17+W17 | Y17: =IF($X$17=0,0,X17/$X$17) | Z17: =IF(AND(X17=0,Q17>0),1,IF(AND(X17=0,Q17=0),0,(Q17-X17)/X17))
A18: 各月比例 | B18: =IF($N$17=0,0,B17/$N$17) | C18: =IF($N$17=0,0,C17/$N$17) | D18: =IF($N$17=0,0,D17/$N$17) | E18: =IF($N$17=0,0,E17/$N$17) | F18: =IF($N$17=0,0,F17/$N$17) | G18: =IF($N$17=0,0,G17/$N$17) | H18: =IF($N$17=0,0,H17/$N$17) | I18: =IF($N$17=0,0,I17/$N$17) | ... N18: =IF($N$17=0,0,N17/$N$17)
A19: 三、审计说明：
A20: （说明：1）与H1/H2/H5/H7/H8等来源底稿勾稽情况；2）月度波动及结构比异常原因；3）大额/关联方/亏损处置的进一步程序。）
A22: 四、审计结论：
A25: 提示：
A26: 根据《中国注册会计师审计准则问题解答第18号——识别和应对第三方配合实施财务舞弊》：如存在大额资产处置收益，关注是否存在被审计单位在第三方配合下，对资产进行虚假处置或虚增处置价格。另：月度结构比异常集中、与相关科目勾稽不一致时，应扩大检查并考虑调整。

Sheet 调整分录汇总H10-3
A1: 致同会计师事务所
A2: 资产处置损益调整分录汇总表
A3: =底稿目录!A2 | D3: =底稿目录!A4 | G3: =底稿目录!A6 | I3: 索引号： | J3: H10-3
A4: =底稿目录!A3 | D4: =底稿目录!A5 | G4: =底稿目录!A7 | I4: 页 次：
A5: 调整事项说明 | B5: 类别（账项调整AJE/重分类调整RJE/其他） | C5: 报表项目 | D5: 科目名称 | E5: 附注项目 | F5: 对方科目 | G5: 借方调整金额 | H5: 贷方调整金额 | I5: 索引 | J5: 备注
A19: 合计 | G19: =SUM(G6:G18) | H19: =SUM(H6:H18)
A20: 借贷差额（应为0） | G20: =G19-H19 | H20: =IF(G20=0,"平衡","不平衡")
A21: 提示：本底稿适用于调整分录较多、较复杂的项目，且仅列示与本报表项目相关的审计调整。项目组可根据项目实际情况选择是否使用该底稿。调整金额须回写至明细表H10-2「账项调整/重分类调整」列，并与审定表H10-1勾稽；涉及6115的分录借贷须平衡，且与集中调整分录管理保持一致。

Sheet 检查表H10-4
A1: 致同会计师事务所
A2: 资产处置损益检查表
A3: =底稿目录!A2 | E3: =底稿目录!A4 | I3: =底稿目录!A6 | P3: 索引号： | Q3: H10-4
A4: =底稿目录!A3 | E4: =底稿目录!A5 | I4: =底稿目录!A7 | P4: 页 次：
A5: 一、审计目标： 1.利润表中记录的资产处置损益已发生，且与被审计单位有关，已记录于恰当的账户；2.与资产处置损益有关的金额及其他数据已恰当记录，相关披露已得到恰当计量和描述； 3.资产处置损益已记录于正确的会计期间
A6: 二、样本选取： | B6: 测试原因：大额（ ）关联方（ ）大额交易频繁（ ）异常（ ）其他（ ）；样本量确定依据：________________
A7: 三、测试：测试内容说明：1.原始凭证是否齐全；2.记账凭证与原始凭证是否相符；3.账务处理是否正确；4.是否记录于恰当的会计期间；5.处置审批及定价是否公允（含关联方交易）。
A8: 项目 | B8: 记账凭证 | I8: 支持性文件 | J8: 核对内容 | O8: 索引号 | P8: 是否异常 | Q8: 备注说明
B9: 日期 | C9: 凭证编号 | D9: 业务内容 | E9: 对方科目 | F9: 对方明细科目 | G9: 借方金额 | H9: 贷方金额 | J9: 1 | K9: 2 | L9: 3 | M9: 4 | N9: 5
A19: 合计 | G19: =SUM(G10:G18) | H19: =SUM(H10:H18)
A20: 本期发生额 | G20: ='明细表H10-2'!Q17 | H20: ='明细表H10-2'!Q17
A21: 检查比例 | G21: =IF(OR(G20="",G20=0),"—",G19/ABS(G20)) | H21: =IF(OR(H20="",H20=0),"—",H19/ABS(H20))
A22: 四、审计说明：
A23: 1.如果检查比例较低应扩大检查样本量或说明原因
A24: 2.对异常或不合规项目应追查支持性文件，评估错报影响，必要时编制调整分录入H10-3，并与来源底稿（H1/H2/H5/H7/H8等）交叉核对。
A26: 五、审计结论：

Sheet GT_Custom
A1: C1 | B1: Custom 1
A2: C2 | B2: Custom 2
A3: C3 | B3: Custom 3
A4: C4 | B4: Custom 4
A5: C5 | B5: Custom 5
A6: C6 | B6: Custom 6
A7: C7 | B7: Custom 7
A8: C8 | B8: Custom 8
