Workbook

Sheet 底稿目录
A1: 底稿开列时，可先在以下单元格填写有关内容，以便其他底稿引用有关数据：
A2: 被审计单位：
A3: 截止日：202X年12月31日 | D3: 序号 | E3: 内容 | F3: 索引号 | G3: 备注
A4: 编制人： | D4: 1 | E4: 油气资产实质性程序表 | F4: H5A
A5: 复核人： | D5: =D4+1 -> 2 | E5: 审定表 | F5: H5-1
A6: 编制日期： | D6: =D5+1 -> 3 | E6: 附注披露信息（上市公司） | G6: 无需打印
A7: 复核日期： | D7: =D6+1 -> 4 | E7: 附注披露信息（国有企业） | G7: 无需打印
A8: 固定资产类别设置（以下内容请根据实际情况修改）： | D8: =D7+1 -> 5 | E8: 明细表 | F8: H5-2
A9: 探明矿区权益 | D9: =D8+1 -> 6 | E9: 调整分录汇总 | F9: H5-3
A10: 未探明矿区权益 | D10: =D9+1 -> 7 | E10: 闲置检查表 | F10: H5-4
A11: 井及相关设施 | D11: =D10+1 -> 8 | E11: 会计政策会计估计检查表 | F11: H5-5
A12: … | D12: =D11+1 -> 9 | E12: 分析表 | F12: H5-6
A13: … | D13: =D12+1 -> 10 | E13: 增加检查表 | F13: H5-7
D14: =D13+1 -> 11 | E14: 减少检查表 | F14: H5-8
A15: 关于工作底稿与审计程序索引号对应的说明 | D15: =D14+1 -> 12 | E15: 监盘计划 | F15: H5-9
A16: 1.编制的审计工作底稿应与审计程序对应。审计项目组应根据被审计单位实际情况和风险评估情况在实质性程序表中裁剪、修改或增加审计程序，根据实际执行的审计程序完成相应审计工作底稿，编制的工作底稿中应按自然顺序依次编制索引号，并通过唯一的索引号将与实质性程序表中的程序对应关联（即将工作底稿的索引号填入实质性程序表中的底稿索引号列）。 | D16: =D15+1 -> 13 | E16: 盘点检查表 | F16: H5-10
D17: =D16+1 -> 14 | E17: 监盘小结 | F17: H5-11
D18: =D17+1 -> 15 | E18: 折耗测算表（不含减值） | F18: H5-12
D19: =D18+1 -> 16 | E19: 折耗测算表（含减值） | F19: H5-12
A20: 2.获取的支持性证据应与审计底稿或程序对应。审计项目组在完成底稿时获取的支持性证据应根据底稿索引号编制下一级按自然顺序排序的索引号（如D1-2-1、D1-2-2、……），并在底稿中说明引用的支持性证据、关联索引号。 | D20: =D19+1 -> 17 | E20: 折耗分配分析表 | F20: H5-13
D21: =D20+1 -> 18 | E21: 减值测算表 | F21: H5-14
D22: =D21+1 -> 19 | E22: 可收回金额测试表 | F22: H5-15
A23: 3.工作底稿索引号的编码规则：实质性程序索引号按循环从“D”到“N”,循环内账户以顺序号排列，模板中底稿索引号按账户顺序+自然数顺序（即模板中索引号按二级自然顺序排列，如D1-1、D1-2、D1-3、……D1-N）。 | D23: =D22+1 -> 20 | E23: 权属检查表 | F23: H5-16
D24: =D23+1 -> 21 | E24: 关联交易检查表 | F24: H5-17

Sheet 油气资产实质性程序表H5A
A1: 致同会计师事务所
A2: 油气资产及减值准备实质性程序表
A3: =底稿目录!A2 -> 被审计单位： | C3: =底稿目录!A4 -> 编制人： | E3: =底稿目录!A6 -> 编制日期： | H3: 索引号： | I3: H5A
A4: =底稿目录!A3 -> 截止日：202X年12月31日 | C4: =底稿目录!A5 -> 复核人： | E4: =底稿目录!A7 -> 复核日期： | H4: 页 次：
A5: 一、本账户涉及的科目
A6: 油气资产、减值准备
A7: 二、审计目标与认定的对应关系
A8: 审计目标 | G8: 财务报表的认定
A9: A. 资产负债表中记录的油气资产是存在的，且已记录于恰当的账户 | G9: 存在
A10: B. 所有应记录的油气资产均已记录，所有应当包括在财务报表中的相关披露均已包括 | G10: 完整性
A11: C. 记录的油气资产由被审计单位拥有或控制； | G11: 权利和义务
A12: D. 油气资产以恰当的金额包括在财务报表中，与之相关的计价或分摊调整已恰当记录，相关披露已得到恰当计量和描述 | G12: 准确性、计价和分摊
A13: E. 油气资产已被恰当地汇总或分解且表述清楚，相关披露在按照企业会计准则的编制基础下是相关的、可理解的 | G13: 列报
A14: 三、计划实施的实质性程序
A15: 序号 | B15: 审计程序 | C15: 程序分类 | D15: 财务报表的认定 | I15: 底稿索引号
D16: 存在 | E16: 完整性 | F16: 权利和 义务 | G16: 准确性、计价和分摊 | H16: 列报 | J16: 根据被审计单位实际情况和风险评估情况裁剪、修改或增加审计程序
A17: 1 | B17: 获取或编制油气资产的明细表，完成以下工作，并编制审定表 （1）复核加计是否正确，并与总账数和明细账合计数核对是否相符，期初余额与上期审定期末余额是否相符； （2）结合油气资产减值准备科目和报表数核对是否相符 （3）询问闲置资产或未入账资产处置情况（如有）。 | C17: 常规★ | D17: √ | E17: √ | G17: √ | I17: H5-1 /H5-2 /H5-4
A18: 2 | B18: 在使用手工编制、自定义信息报告、系统生成的非固定格式报告等由被审计单位生成的信息时，测试有关信息准确性和完整性，并考虑针对编制和维护由被审计单位生成的信息的相关控制实施控制测试，以评价该信息是否能够为实现审计目的提供基础。 | C18: 常规★ | E18: √ | G18: √ | I18: T1 / | J18: 可参见《审计手册》4.2.6，由被审计单位生成的信息可能是由系统生成的、或手工编制的、或二者兼而有之的方式生成的。例如，由被审计单位生成的信息可能包括： • 不涉及自定义的、由系统生成的报告（如，固定格式报告）； • 可能通过人工自定义的、由系统生成的报告，例如，（计算机）查询信息或特别定制的报告； • 手工编制的信息，例如，汇总信息的电子表格或用以支持分配、计算以及调节的电子表格； • 其他系统生成或手工编制的信息，例如，由被审计单位编制的客户发票； • 通过影印、拍摄、扫描或其他方式转换成电子形式的文件记录。
A19: 3 | B19: 对期初余额的审计，取得上期油气资产明细表的明细表复核加计是否正确，与总账、明细账合计数是否相符； 重新测算期初累计折耗余额准确性；对单项金额重大资产，进行实地查看资产或检查支持性文件，其他必要追加的审计程序。（适用于首次承接） | C19: 备选 | D19: √ | E19: √ | F19: √ | G19: √ | J19: 由被审计单位生成的信息不包括： • 总分类账或明细分类账、试算平衡表、或经审计的财务报表； • 第三方（除了服务机构）的报表或报告，例如，原始银行对账单，或函证的回函； • 外部数据（例如，第三方发布的数据，如，定价来源）。
A20: 4 | B20: 关注会计政策、会计估计合理性、一贯性，关注其是否利用会计政策和会计估计及其变更操纵利润。必要时与同行业其他公司会计政策、会计估计进行对比，主要会计政策和估计包括： （1）油气资产的初始计量； （2）油气资产折耗/减值的政策和方法； （3）油气资产的后续支出（包括支出费用化和资本化）及终止确认。 | C20: 常规★ | D20: √ | E20: √ | G20: √ | I20: H5-5
A21: 5 | B21: 执行分析性程序，考虑识别需要执行额外程序的领域： （1）分析本期和上期油气资产净值占资产总额比例、当期计提折耗额、累计折耗及减值准备余额分别占油气资产原值比例是否异常； （2）分析油气资产原值与本期产品产量的比率（油气资产的规模及其变化是否与产能匹配）、并与以前年度对比； （3）分析租赁资产占相应资产的比例及本期与以前年度租赁收入情况（判断被审计单位对资产租赁收益的依赖程度及盈利能力的稳定性）； （4）分析维修费用与油气资产原值的比例等，并与以前年度对比。 | C21: 常规★ | D21: √ | E21: √ | G21: √ | I21: H5-6
A22: 6 | B22: 检查本期新增的油气资产： （1）对于油气开采活动支出，包括矿区取得支出、油气勘探支出、油气开发支出和油气生产成本，检查购置/租赁合同、发票等文件，抽查测试其计价是否正确，会计处理是否正确；如果超过正常信用条件延期支付购买价款，检查实质上是否具有融资性质，油气资产的成本是否以购买价款的现值为基础确定。 （2）对于在建工程转入的油气资产，结合油气资产盘点程序，检查竣工决算、验收和移交报告是否正确，与在建工程相关的记录是否核对相符，借款费用资本化金额是否恰当；对已经在用或已经达到预定可使用状态但尚未办理竣工决算的油气资产，检查其是否已经暂估入账，并按规定计提折耗；检查资本性支出与收益性支出的划分是否恰当；竣工决算完成后，是否及时调整。 | C22: 常规★ | D22: √ | E22: √ | F22: √ | G22: √ | I22: H5-7
A23: 7 | B23: 检查本期油气资产的处置： 检查处置、报废等相关的合同、发票及其他文件，确认已经办理审批手续，相关收益或损失已正确计算，并进行正确的会计处理。 | C23: 常规★ | D23: √ | E23: √ | G23: √ | I23: H5-8
A24: 8 | B24: 以其他方式增加或减少的油气资产 （1）对于非货币性资产交换、债务重组、企业合并、投资者投入等交易方式取得或减少的有关长期资产，检查相关合同/协议，关注计价是否正确、移交手续是否办理以及会计处理是否正确。 （2）对于因清产核资、资产评估调增或调减有关长期资产价值的，检查有关清产核资报告、资产评估报告、国有资产管理等部门的确认文件、验资报告等，检查会计处理是否正确。 | C24: 备选 | D24: √ | E24: √ | F24: √ | G24: √ | I24: H5-7 /H5-8
A25: 9 | B25: 监盘油气资产： （1）取得公司油气资产清单，盘点范围考虑包括本期新增、容易侵占、重要、数量巨大、已损坏项目、存放在第三方及其他异常等。关注是否存在已报废但仍未核销的油气资产 （2）获取被审计单位对于油气资产的盘点计划，制定和实施监盘计划（如有）及盘点控制文件的复印件（如：盘点清单，标签控制清单）； （3）取得油气资产存放地点清单，初步确定监盘方式、时间、监盘计划； （4）观察被审计单位制定的盘点程序的执行情况 （5）检查油气资产的状态（在用、闲置、毁损或陈旧等）； （6）执行抽盘，注册会计师从油气资产盘点记录追查至油气资产实物，以及从油气资产实物中选取项目追查至油气资产清单，将抽盘结果与账面核对； （7）评价油气资产盘点结果，完成监盘小结。 | C25: 常规★ | D25: √ | F25: √ | G25: √ | I25: H5-9 /H5-10 /H5-11
A26: 10 | B26: 存放其他地方的资产（如有），考虑实地观察或函证由其他人保管或保管在盘点地之外的资产。 | C26: 备选 | D26: √ | F26: √ | G26: √ | I26: H0
A27: 11 | B27: 检查油气资产折耗，考虑执行下列程序： （1）获取或编制折耗分类汇总表，复核加计正确，并与总账数和明细账合计数核对。 （2）重新计算折耗 。 （3）获取暂时闲置、已提足折旧仍继续使用和前期已计提减值准备的油气资产的相关证明文件，并观察其实际状况，检查是否已按规定计提折耗； （4）检查折耗分配到各种费用的情况，将“累计折耗”账户贷方的本期计提折旧额与相应成本费用中的折耗费用明细账户的借方相比较，以查明所计提折耗金额是否已全部摊入本期产品成本或费用；分配是否合理，与上期分配方法是否一致。 | C27: 常规★ | G27: √ | I27: H5-12 /H5-13
A28: 12 | B28: 结合油气资产清单和盘点程序，了解油气资产的状态。针对存在减值迹象的油气资产，考虑执行下列程序： 获取被审计单位在资产负债表日就油气资产是否可能发生减值迹象的判断的说明，判断其合理性。对于已计提减值准备的油气资产，检查减值测试相关参数是否合理，减值准备计提是否正确。对于管理层聘请评估专家出具的评估报告，复核评估报告。 | C28: 常规★ | G28: √ | I28: H5-14 /H5-15
A29: 13 | B29: 检查油气资产的所有权或控制权 （1）检查资产权属证明原件，结合银行借款等项目的检查，了解是否设定对外抵押，并取得复印件作为工作底稿； （2）对于正在办理权属证明的大额资产，了解权属证明办理情况，确认是否存在权属纠纷或实质性障碍。 | C29: 常规★ | F29: √ | I29: H5-16
A30: 14 | B30: 检查关联交易情况，检查关联交易的真实性、合理性及合规性；检查关联交易会计处理是否正确，考虑是否存在未识别的关联方，检查关联交易和余额披露是否正确。 | C30: 常规★ | D30: √ | E30: √ | F30: √ | G30: √ | H30: √ | I30: H5-17
A31: 15 | B31: 针对长期资产租赁（经营租出油气资产），考虑执行下列程序： （1）获取或编制资产租赁明细表，获取租赁合同/协议，核对重要条款，检查租赁分类是否正确。 （2）根据租赁合同/协议等文件，检查初始直接费用、或有租金确认是否合理，会计处理是否正确，重新计算租金收入并与利润表其他业务收入进行核对。 | C31: 备选 | D31: √ | E31: √ | F31: √ | G31: √ | I31: H5-18
A32: 16 | B32: 针对长期资产租赁（融资租出油气资产），考虑执行下列程序： （1）获取或编制资产租赁明细表，获取租赁合同/协议，核对重要条款，检查租赁分类是否正确，与油气资产增减变动明细表核对一致； （2）检查长期应收款、未确认融资收益的计算是否正确，实际利率、初始直接费用及或有租金的确认是否合理； （3）未担保余值发生变动的，分析变动原因，检查会计处理是否正确。 （4）本期租赁期届满的，分析处理方式（收回、优惠续租和出售），检查会计处理是否正确。 | C32: 备选 | D32: √ | E32: √ | F32: √ | G32: √ | I32: H5-19
A33: 17 | B33: 存在弃置义务的油气资产结合预计负债底稿检查会计处理是否正确。 | C33: 备选 | E33: √
A34: 18 | B34: 根据评估的舞弊风险等因素增加的审计程序。 | C34: IPO/上市/新三板/重组/舞弊应对
A35: 19 | B35: 检查油气资产、抵押和担保情况等是否已按企业会计准则或其他适用的规定在财务报表中做出恰当列报和披露 | C35: 常规★ | H35: √ | I35: A 1-1/A1-15 /A1-16

Sheet 审定表H5-1
A1: 致同会计师事务所
A2: 油气资产、累计折耗、减值准备审定表
A3: =底稿目录!A2 -> 被审计单位： | D3: =底稿目录!A4 -> 编制人： | F3: =底稿目录!A6 -> 编制日期： | H3: 索引号： | I3: H5-1
A4: =底稿目录!A3 -> 截止日：202X年12月31日 | D4: =底稿目录!A5 -> 复核人： | F4: =底稿目录!A7 -> 复核日期： | H4: 页 次：
A5: 项目 | B5: 期初数 | E5: 期末数 | H5: 本期审定数与上期 审定数的比较
B6: 未审数 | C6: 账项调整 | D6: 审定数 | E6: 未审数 | F6: 账项调整 | G6: 审定数 | H6: 变动额 | I6: 变动率
A7: 一、油气资产原值
A8: =底稿目录!A9 -> 探明矿区权益 | B8: ='明细表H5-2'!D35 -> 0 | C8: ='明细表H5-2'!J35 -> 0 | D8: =B8+C8 -> 0 | E8: ='明细表H5-2'!I35 -> 0 | F8: ='明细表H5-2'!J35+'明细表H5-2'!K35-'明细表H5-2'!L35 -> 0 | G8: =E8+F8 -> 0 | H8: =G8-D8 -> 0 | I8: =IF(AND(D8=0,H8=0),0,IF(AND(D8=0,H8>0),1,H8/D8)) -> 0
A9: =底稿目录!A10 -> 未探明矿区权益 | B9: ='明细表H5-2'!D36 -> 0 | C9: ='明细表H5-2'!J36 -> 0 | D9: =B9+C9 -> 0 | E9: ='明细表H5-2'!I36 -> 0 | F9: ='明细表H5-2'!J36+'明细表H5-2'!K36-'明细表H5-2'!L36 -> 0 | G9: =E9+F9 -> 0 | H9: =G9-D9 -> 0 | I9: =IF(AND(D9=0,H9=0),0,IF(AND(D9=0,H9>0),1,H9/D9)) -> 0
A10: =底稿目录!A11 -> 井及相关设施 | B10: ='明细表H5-2'!D37 -> 0 | C10: ='明细表H5-2'!J37 -> 0 | D10: =B10+C10 -> 0 | E10: ='明细表H5-2'!I37 -> 0 | F10: ='明细表H5-2'!J37+'明细表H5-2'!K37-'明细表H5-2'!L37 -> 0 | G10: =E10+F10 -> 0 | H10: =G10-D10 -> 0 | I10: =IF(AND(D10=0,H10=0),0,IF(AND(D10=0,H10>0),1,H10/D10)) -> 0
A11: =底稿目录!A12 -> … | B11: ='明细表H5-2'!D38 -> 0 | C11: ='明细表H5-2'!J38 -> 0 | D11: =B11+C11 -> 0 | E11: ='明细表H5-2'!I38 -> 0 | F11: ='明细表H5-2'!J38+'明细表H5-2'!K38-'明细表H5-2'!L38 -> 0 | G11: =E11+F11 -> 0 | H11: =G11-D11 -> 0 | I11: =IF(AND(D11=0,H11=0),0,IF(AND(D11=0,H11>0),1,H11/D11)) -> 0
A12: =底稿目录!A13 -> … | B12: ='明细表H5-2'!D39 -> 0 | C12: ='明细表H5-2'!J39 -> 0 | D12: =B12+C12 -> 0 | E12: ='明细表H5-2'!I39 -> 0 | F12: ='明细表H5-2'!J39+'明细表H5-2'!K39-'明细表H5-2'!L39 -> 0 | G12: =E12+F12 -> 0 | H12: =G12-D12 -> 0 | I12: =IF(AND(D12=0,H12=0),0,IF(AND(D12=0,H12>0),1,H12/D12)) -> 0
A13: 合计 | B13: =SUM(B8:B12) -> 0 | C13: =SUM(C8:C12) -> 0 | D13: =SUM(D8:D12) -> 0 | E13: =SUM(E8:E12) -> 0 | F13: =SUM(F8:F12) -> 0 | G13: =SUM(G8:G12) -> 0 | H13: =G13-D13 -> 0 | I13: =IF(AND(D13=0,H13=0),0,IF(AND(D13=0,H13>0),1,H13/D13)) -> 0
A14: 二、累计折耗
A15: =A8 -> 探明矿区权益 | B15: ='明细表H5-2'!Q35 -> 0 | C15: ='明细表H5-2'!W35 -> 0 | D15: =B15+C15 -> 0 | E15: ='明细表H5-2'!V35 -> 0 | F15: ='明细表H5-2'!W35+'明细表H5-2'!X35-'明细表H5-2'!AA35+'明细表H5-2'!Y35-'明细表H5-2'!Z35 -> 0 | G15: =E15+F15 -> 0 | H15: =G15-D15 -> 0 | I15: =IF(AND(D15=0,H15=0),0,IF(AND(D15=0,H15>0),1,H15/D15)) -> 0
A16: =A9 -> 未探明矿区权益 | B16: ='明细表H5-2'!Q36 -> 0 | C16: ='明细表H5-2'!W36 -> 0 | D16: =B16+C16 -> 0 | E16: ='明细表H5-2'!V36 -> 0 | F16: ='明细表H5-2'!W36+'明细表H5-2'!X36-'明细表H5-2'!AA36+'明细表H5-2'!Y36-'明细表H5-2'!Z36 -> 0 | G16: =E16+F16 -> 0 | H16: =G16-D16 -> 0 | I16: =IF(AND(D16=0,H16=0),0,IF(AND(D16=0,H16>0),1,H16/D16)) -> 0
A17: =A10 -> 井及相关设施 | B17: ='明细表H5-2'!Q37 -> 0 | C17: ='明细表H5-2'!W37 -> 0 | D17: =B17+C17 -> 0 | E17: ='明细表H5-2'!V37 -> 0 | F17: ='明细表H5-2'!W37+'明细表H5-2'!X37-'明细表H5-2'!AA37+'明细表H5-2'!Y37-'明细表H5-2'!Z37 -> 0 | G17: =E17+F17 -> 0 | H17: =G17-D17 -> 0 | I17: =IF(AND(D17=0,H17=0),0,IF(AND(D17=0,H17>0),1,H17/D17)) -> 0
A18: =A11 -> … | B18: ='明细表H5-2'!Q38 -> 0 | C18: ='明细表H5-2'!W38 -> 0 | D18: =B18+C18 -> 0 | E18: ='明细表H5-2'!V38 -> 0 | F18: ='明细表H5-2'!W38+'明细表H5-2'!X38-'明细表H5-2'!AA38+'明细表H5-2'!Y38-'明细表H5-2'!Z38 -> 0 | G18: =E18+F18 -> 0 | H18: =G18-D18 -> 0 | I18: =IF(AND(D18=0,H18=0),0,IF(AND(D18=0,H18>0),1,H18/D18)) -> 0
A19: =A12 -> … | B19: ='明细表H5-2'!Q39 -> 0 | C19: ='明细表H5-2'!W39 -> 0 | D19: =B19+C19 -> 0 | E19: ='明细表H5-2'!V39 -> 0 | F19: ='明细表H5-2'!W39+'明细表H5-2'!X39-'明细表H5-2'!AA39+'明细表H5-2'!Y39-'明细表H5-2'!Z39 -> 0 | G19: =E19+F19 -> 0 | H19: =G19-D19 -> 0 | I19: =IF(AND(D19=0,H19=0),0,IF(AND(D19=0,H19>0),1,H19/D19)) -> 0
A20: 合计 | B20: =SUM(B15:B19) -> 0 | C20: =SUM(C15:C19) -> 0 | D20: =SUM(D15:D19) -> 0 | E20: =SUM(E15:E19) -> 0 | F20: =SUM(F15:F19) -> 0 | G20: =SUM(G15:G19) -> 0 | H20: =G20-D20 -> 0 | I20: =IF(AND(D20=0,H20=0),0,IF(AND(D20=0,H20>0),1,H20/D20)) -> 0
A21: 三、减值准备
A22: =A15 -> 探明矿区权益 | B22: ='明细表H5-2'!AF35 -> 0 | C22: ='明细表H5-2'!AL35 -> 0 | D22: =B22+C22 -> 0 | E22: ='明细表H5-2'!AK35 -> 0 | F22: ='明细表H5-2'!AL35+'明细表H5-2'!AM35-'明细表H5-2'!AP35+'明细表H5-2'!AN35-'明细表H5-2'!AO35 -> 0 | G22: =E22+F22 -> 0 | H22: =G22-D22 -> 0 | I22: =IF(AND(D22=0,H22=0),0,IF(AND(D22=0,H22>0),1,H22/D22)) -> 0
A23: =A16 -> 未探明矿区权益 | B23: ='明细表H5-2'!AF36 -> 0 | C23: ='明细表H5-2'!AL36 -> 0 | D23: =B23+C23 -> 0 | E23: ='明细表H5-2'!AK36 -> 0 | F23: ='明细表H5-2'!AL36+'明细表H5-2'!AM36-'明细表H5-2'!AP36+'明细表H5-2'!AN36-'明细表H5-2'!AO36 -> 0 | G23: =E23+F23 -> 0 | H23: =G23-D23 -> 0 | I23: =IF(AND(D23=0,H23=0),0,IF(AND(D23=0,H23>0),1,H23/D23)) -> 0
A24: =A17 -> 井及相关设施 | B24: ='明细表H5-2'!AF37 -> 0 | C24: ='明细表H5-2'!AL37 -> 0 | D24: =B24+C24 -> 0 | E24: ='明细表H5-2'!AK37 -> 0 | F24: ='明细表H5-2'!AL37+'明细表H5-2'!AM37-'明细表H5-2'!AP37+'明细表H5-2'!AN37-'明细表H5-2'!AO37 -> 0 | G24: =E24+F24 -> 0 | H24: =G24-D24 -> 0 | I24: =IF(AND(D24=0,H24=0),0,IF(AND(D24=0,H24>0),1,H24/D24)) -> 0
A25: =A18 -> … | B25: ='明细表H5-2'!AF38 -> 0 | C25: ='明细表H5-2'!AL38 -> 0 | D25: =B25+C25 -> 0 | E25: ='明细表H5-2'!AK38 -> 0 | F25: ='明细表H5-2'!AL38+'明细表H5-2'!AM38-'明细表H5-2'!AP38+'明细表H5-2'!AN38-'明细表H5-2'!AO38 -> 0 | G25: =E25+F25 -> 0 | H25: =G25-D25 -> 0 | I25: =IF(AND(D25=0,H25=0),0,IF(AND(D25=0,H25>0),1,H25/D25)) -> 0
A26: =A19 -> … | B26: ='明细表H5-2'!AF39 -> 0 | C26: ='明细表H5-2'!AL39 -> 0 | D26: =B26+C26 -> 0 | E26: ='明细表H5-2'!AK39 -> 0 | F26: ='明细表H5-2'!AL39+'明细表H5-2'!AM39-'明细表H5-2'!AP39+'明细表H5-2'!AN39-'明细表H5-2'!AO39 -> 0 | G26: =E26+F26 -> 0 | H26: =G26-D26 -> 0 | I26: =IF(AND(D26=0,H26=0),0,IF(AND(D26=0,H26>0),1,H26/D26)) -> 0
A27: 合计 | B27: =SUM(B22:B26) -> 0 | C27: =SUM(C22:C26) -> 0 | D27: =SUM(D22:D26) -> 0 | E27: =SUM(E22:E26) -> 0 | F27: =SUM(F22:F26) -> 0 | G27: =SUM(G22:G26) -> 0 | H27: =G27-D27 -> 0 | I27: =IF(AND(D27=0,H27=0),0,IF(AND(D27=0,H27>0),1,H27/D27)) -> 0
A28: 四、净值
A29: =A22 -> 探明矿区权益 | B29: =B8-B15-B22 -> 0 | C29: =C8-C15-C22 -> 0 | D29: =D8-D15-D22 -> 0 | E29: =E8-E15-E22 -> 0 | F29: =F8-F15-F22 -> 0 | G29: =G8-G15-G22 -> 0 | H29: =G29-D29 -> 0 | I29: =IF(AND(D29=0,H29=0),0,IF(AND(D29=0,H29>0),1,H29/D29)) -> 0
A30: =A23 -> 未探明矿区权益 | B30: =B9-B16-B23 -> 0 | C30: =C9-C16-C23 -> 0 | D30: =D9-D16-D23 -> 0 | E30: =E9-E16-E23 -> 0 | F30: =F9-F16-F23 -> 0 | G30: =G9-G16-G23 -> 0 | H30: =G30-D30 -> 0 | I30: =IF(AND(D30=0,H30=0),0,IF(AND(D30=0,H30>0),1,H30/D30)) -> 0
A31: =A24 -> 井及相关设施 | B31: =B10-B17-B24 -> 0 | C31: =C10-C17-C24 -> 0 | D31: =D10-D17-D24 -> 0 | E31: =E10-E17-E24 -> 0 | F31: =F10-F17-F24 -> 0 | G31: =G10-G17-G24 -> 0 | H31: =G31-D31 -> 0 | I31: =IF(AND(D31=0,H31=0),0,IF(AND(D31=0,H31>0),1,H31/D31)) -> 0
A32: =A25 -> … | B32: =B11-B18-B25 -> 0 | C32: =C11-C18-C25 -> 0 | D32: =D11-D18-D25 -> 0 | E32: =E11-E18-E25 -> 0 | F32: =F11-F18-F25 -> 0 | G32: =G11-G18-G25 -> 0 | H32: =G32-D32 -> 0 | I32: =IF(AND(D32=0,H32=0),0,IF(AND(D32=0,H32>0),1,H32/D32)) -> 0
A33: =A26 -> … | B33: =B12-B19-B26 -> 0 | C33: =C12-C19-C26 -> 0 | D33: =D12-D19-D26 -> 0 | E33: =E12-E19-E26 -> 0 | F33: =F12-F19-F26 -> 0 | G33: =G12-G19-G26 -> 0 | H33: =G33-D33 -> 0 | I33: =IF(AND(D33=0,H33=0),0,IF(AND(D33=0,H33>0),1,H33/D33)) -> 0
A34: 合计 | B34: =SUM(B29:B33) -> 0 | C34: =SUM(C29:C33) -> 0 | D34: =SUM(D29:D33) -> 0 | E34: =SUM(E29:E33) -> 0 | F34: =SUM(F29:F33) -> 0 | G34: =SUM(G29:G33) -> 0 | H34: =G34-D34 -> 0 | I34: =IF(AND(D34=0,H34=0),0,IF(AND(D34=0,H34>0),1,H34/D34)) -> 0
A35: 1、审计说明：
A36: （1）油气资产期末净值较期初净值增加（负数为减少）：
A37: 主要原因（比例超过30%的）：
A39: （2）本期由在建工程转入：
A41: （3）抵押、担保情况说明：
A43: （4）出售、置换情况说明：
A45: （5）租赁情况说明：（通过融资租赁租入的油气资产应披露每类租入资产的账面原值、累计折耗、账面净值；
A46: 通过经营租赁租出的油气资产应披露每类租出资产的账面价值。）
A48: （6）与试算平衡表的核对：
B49: 期末数 | C49: 期初数
A50: 油气资产净值审定数 | B50: =G34 -> 0 | C50: =D34 -> 0
A51: 试算平衡表
A52: 差异 | B52: =B50-B51 -> 0 | C52: =C50-C51 -> 0
A54: 2、审计结论：
A59: 提示：
A60: 1、如适用，根据1131号等审计准则和指南的要求编制，说明涉及事项内容、应对措施、审计结论或解决方法，
A61: 以及可能对审计报告的影响。
A62: A、风险评估结果和内控了解、测试情况（不适用则说明：不存在重大错报风险。)
A63: (识别和实际评估的重大错报风险、尤其识特别风险，以及对内控了解和控制测试情况〔采用综合方案时〕）；
A64: 提示：a、收入科目应当假定存在舞弊的特别风险，如不存在，应说明理由；
A65: b、涉及特别风险时，应当重点说明有关事项、应当措施、结果〔可索引有关底稿〕。
A66: 特别风险涉及的事项包括但不限于：
A67: （1）舞弊风险（如1141准则的示例）；（2）重大非常规交易（如企业购并、债务重组、非货币性资产交换、
A68: 重大或有事项、持续经营、违反法律法规等）；(3)重大关联交易；(4)重大判断事项（如重大会计估计、
A69: 会计政策及其变更）；(5)重大复杂交易；(6)仅通过实质性程序无法应对的重大错报风险（如日常交易采用
... A75: 2、说明基于获取的审计证据，在有关认定方面，是否发现重大错报或存在重大异常。

Sheet 附注披露信息（上市公司）
A1: 致同会计师事务所
A2: 附注披露信息（上市公司）
A3: =底稿目录!A2 -> 被审计单位： | C3: =底稿目录!A4 -> 编制人： | E3: =底稿目录!A6 -> 编制日期： | G3: 索引号：
A4: =底稿目录!A3 -> 截止日：202X年12月31日 | C4: =底稿目录!A5 -> 复核人： | E4: =底稿目录!A7 -> 复核日期： | G4: 页 次：
A7: 项目 | B7: 探明矿区权益 | C7: 未探明矿区权益 | D7: 井及相关设施 | E7: … | F7: … | G7: 合计 | H7: 返回目录
A8: 一、账面原值
A9: 1.期初余额
A10: 2.本期增加金额
A11: (1)外购
A12: (2)自行建造
A13: (3)其他增加
A14: 3.本期减少金额
A15: (1)处置
A16: (2)其他减少
A17: 4.期末余额
A18: 二、累计折旧
A19: 1.期初余额
... A38: 2.期初账面价值

Sheet 附注披露信息（国有企业）
A1: 致同会计师事务所
A2: 附注披露信息（国有企业）
A3: =底稿目录!A2 -> 被审计单位： | B3: =底稿目录!A4 -> 编制人： | D3: =底稿目录!A6 -> 编制日期： | E3: 索引号：
A4: =底稿目录!A3 -> 截止日：202X年12月31日 | B4: =底稿目录!A5 -> 复核人： | D4: =底稿目录!A7 -> 复核日期： | E4: 页 次：
A6: 25、油气资产
A7: （1）当期在国内和国外发生的取得矿区权益、油气勘探和油气开发各项支出的总额。
A8: （2）油气资产分类 | F8: 返回目录
A9: 项 目 | B9: 期初余额 | C9: 本期增加额 | D9: 本期减少额 | E9: 期末余额
A10: 一、原价合计
A11: 其中：1．探明矿区权益
A12: 2．未探明矿区权益
A13: 3．井及相关设施
A14: 二、累计折耗合计
A15: 其中：1．探明矿区权益
A16: 2．井及相关设施
A17: 三、油气资产减值准备累计金额合计
A18: 其中：1．探明矿区权益
A19: 2．未探明矿区权益
A20: 3．井及相关设施
A21: 四、油气资产账面价值合计 | C21: -- | D21: --
A22: 其中：1．探明矿区权益 | C22: -- | D22: --
A23: 2．未探明矿区权益 | C23: -- | D23: --
A24: 3．井及相关设施 | C24: -- | D24: --

Sheet 明细表H5-2
A1: 致同会计师事务所 | Q1: 致同会计师事务所 | AF1: 致同会计师事务所
A2: 油气资产、累计折耗及减值准备明细表 | Q2: 油气资产、累计折耗及减值准备明细表 | AF2: 油气资产、累计折耗及减值准备明细表
A3: =底稿目录!A2 -> 被审计单位： | F3: =底稿目录!A4 -> 编制人： | K3: =底稿目录!A6 -> 编制日期： | O3: 索引号： | P3: H5-2 | Q3: =底稿目录!A2 -> 被审计单位： | V3: =底稿目录!A4 -> 编制人： | AA3: =底稿目录!A6 -> 编制日期： | AD3: 索引号： | AE3: H5-2 | AF3: =底稿目录!A2 -> 被审计单位： | AL3: =底稿目录!A4 -> 编制人： | AT3: =底稿目录!A6 -> 编制日期： | BA3: 索引号： | BB3: H5-2
A4: =底稿目录!A3 -> 截止日：202X年12月31日 | F4: =底稿目录!A5 -> 复核人： | K4: =底稿目录!A7 -> 复核日期： | O4: 页 次： | Q4: =底稿目录!A3 -> 截止日：202X年12月31日 | V4: =底稿目录!A5 -> 复核人： | AA4: =底稿目录!A7 -> 复核日期： | AD4: 页 次： | AF4: =底稿目录!A3 -> 截止日：202X年12月31日 | AL4: =底稿目录!A5 -> 复核人： | AT4: =底稿目录!A7 -> 复核日期： | BA4: 页 次：
A5: 一、审计目标:
A6: 1.资产负债表中记录的油气资产是存在的，且已记录于恰当的账户；2.所有应记录的油气资产均已记录，所有应当包括在财务报表中的相关披露均已包括；
A7: 3.油气资产以恰当的金额包括在财务报表中，与之相关的计价或分摊调整已恰当记录，相关披露已得到恰当计量和描述
A8: 二、审计过程：
A9: 油气资产类别 | B9: 油气资产编号 | C9: 油气资产名称 | D9: 油气资产原值 | Q9: 累计折耗 | AF9: 减值准备 | AU9: 期初净值 | AW9: 期末净值 | AY9: 是否提足折耗 | AZ9: 是否闲置 | BA9: 是否有权属证明 | BB9: 是否抵押受限
D10: 未审数 | J10: 期初调整 | K10: 账项调整 | M10: 审定数 | Q10: 未审数 | W10: 期初调整 | X10: 账项调整 | AB10: 审定数 | AF10: 未审数 | AL10: 期初调整 | AM10: 账项调整 | AQ10: 审定数
D11: 期初数 | E11: 本期增加 | G11: 本期减少 | I11: 期末数 | K11: 本期增加 | L11: 本期减少 | M11: 期初数 | N11: 本期增加 | O11: 本期减少 | P11: 期末数 | Q11: 期初数 | R11: 本期增加 | T11: 本期减少 | V11: 期末数 | X11: 本期增加 | Z11: 本期减少 | AB11: 期初数 | AC11: 本期增加 | AD11: 本期减少 | AE11: 期末数 | AF11: 期初数 | AG11: 本期增加 | AI11: 本期减少 | AK11: 期末数 | AM11: 本期增加 | AO11: 本期减少 | AQ11: 期初数 | AR11: 本期增加 | AS11: 本期减少 | AT11: 期末数 | AU11: 未审净值 | AV11: 审定净值 | AW11: 未审净值 | AX11: 审定净值
E12: 金额 | F12: 增加方式 | G12: 金额 | H12: 减少方式 | R12: 本期计提 | S12: 其他增加 | T12: 处置 | U12: 其他减少 | X12: 本期计提 | Y12: 其他增加 | Z12: 处置 | AA12: 其他减少 | AG12: 本期计提 | AH12: 其他增加 | AI12: 处置 | AJ12: 其他减少 | AM12: 本期计提 | AN12: 其他增加 | AO12: 处置 | AP12: 其他减少
I13: =SUM(D13:E13)-G13 -> 0 | M13: =D13+J13 -> 0 | N13: =E13+K13 -> 0 | O13: =G13+L13 -> 0 | P13: =M13+N13-O13 -> 0 | V13: =SUM(Q13:S13)-SUM(T13:U13) -> 0 | AB13: =Q13+W13 -> 0 | AC13: =R13+S13+X13+Y13 -> 0 | AD13: =T13+U13+AA13+Z13 -> 0 | AE13: =AB13+AC13-AD13 -> 0 | AK13: =SUM(AF13:AH13)-SUM(AI13:AJ13) -> 0 | AQ13: =AF13+AL13 -> 0 | AR13: =AG13+AH13+AM13+AN13 -> 0 | AS13: =AI13+AJ13+AP13+AO13 -> 0 | AT13: =AQ13+AR13-AS13 -> 0 | AU13: =D13-Q13-AF13 -> 0 | AV13: =M13-AB13-AQ13 -> 0 | AW13: =I13-V13-AK13 -> 0 | AX13: =P13-AE13-AT13 -> 0
I14: =SUM(D14:E14)-G14 -> 0 | M14: =D14+J14 -> 0 | N14: =E14+K14 -> 0 | O14: =G14+L14 -> 0 | P14: =M14+N14-O14 -> 0 | V14: =SUM(Q14:S14)-SUM(T14:U14) -> 0 | AB14: =Q14+W14 -> 0 | AC14: =R14+S14+X14+Y14 -> 0 | AD14: =T14+U14+AA14+Z14 -> 0 | AE14: =AB14+AC14-AD14 -> 0 | AK14: =SUM(AF14:AH14)-SUM(AI14:AJ14) -> 0 | AQ14: =AF14+AL14 -> 0 | AR14: =AG14+AH14+AM14+AN14 -> 0 | AS14: =AI14+AJ14+AP14+AO14 -> 0 | AT14: =AQ14+AR14-AS14 -> 0 | AU14: =D14-Q14-AF14 -> 0 | AV14: =M14-AB14-AQ14 -> 0 | AW14: =I14-V14-AK14 -> 0 | AX14: =P14-AE14-AT14 -> 0
I15: =SUM(D15:E15)-G15 -> 0 | M15: =D15+J15 -> 0 | N15: =E15+K15 -> 0 | O15: =G15+L15 -> 0 | P15: =M15+N15-O15 -> 0 | V15: =SUM(Q15:S15)-SUM(T15:U15) -> 0 | AB15: =Q15+W15 -> 0 | AC15: =R15+S15+X15+Y15 -> 0 | AD15: =T15+U15+AA15+Z15 -> 0 | AE15: =AB15+AC15-AD15 -> 0 | AK15: =SUM(AF15:AH15)-SUM(AI15:AJ15) -> 0 | AQ15: =AF15+AL15 -> 0 | AR15: =AG15+AH15+AM15+AN15 -> 0 | AS15: =AI15+AJ15+AP15+AO15 -> 0 | AT15: =AQ15+AR15-AS15 -> 0 | AU15: =D15-Q15-AF15 -> 0 | AV15: =M15-AB15-AQ15 -> 0 | AW15: =I15-V15-AK15 -> 0 | AX15: =P15-AE15-AT15 -> 0
I16: =SUM(D16:E16)-G16 -> 0 | M16: =D16+J16 -> 0 | N16: =E16+K16 -> 0 | O16: =G16+L16 -> 0 | P16: =M16+N16-O16 -> 0 | V16: =SUM(Q16:S16)-SUM(T16:U16) -> 0 | AB16: =Q16+W16 -> 0 | AC16: =R16+S16+X16+Y16 -> 0 | AD16: =T16+U16+AA16+Z16 -> 0 | AE16: =AB16+AC16-AD16 -> 0 | AK16: =SUM(AF16:AH16)-SUM(AI16:AJ16) -> 0 | AQ16: =AF16+AL16 -> 0 | AR16: =AG16+AH16+AM16+AN16 -> 0 | AS16: =AI16+AJ16+AP16+AO16 -> 0 | AT16: =AQ16+AR16-AS16 -> 0 | AU16: =D16-Q16-AF16 -> 0 | AV16: =M16-AB16-AQ16 -> 0 | AW16: =I16-V16-AK16 -> 0 | AX16: =P16-AE16-AT16 -> 0
I17: =SUM(D17:E17)-G17 -> 0 | M17: =D17+J17 -> 0 | N17: =E17+K17 -> 0 | O17: =G17+L17 -> 0 | P17: =M17+N17-O17 -> 0 | V17: =SUM(Q17:S17)-SUM(T17:U17) -> 0 | AB17: =Q17+W17 -> 0 | AC17: =R17+S17+X17+Y17 -> 0 | AD17: =T17+U17+AA17+Z17 -> 0 | AE17: =AB17+AC17-AD17 -> 0 | AK17: =SUM(AF17:AH17)-SUM(AI17:AJ17) -> 0 | AQ17: =AF17+AL17 -> 0 | AR17: =AG17+AH17+AM17+AN17 -> 0 | AS17: =AI17+AJ17+AP17+AO17 -> 0 | AT17: =AQ17+AR17-AS17 -> 0 | AU17: =D17-Q17-AF17 -> 0 | AV17: =M17-AB17-AQ17 -> 0 | AW17: =I17-V17-AK17 -> 0 | AX17: =P17-AE17-AT17 -> 0
I18: =SUM(D18:E18)-G18 -> 0 | M18: =D18+J18 -> 0 | N18: =E18+K18 -> 0 | O18: =G18+L18 -> 0 | P18: =M18+N18-O18 -> 0 | V18: =SUM(Q18:S18)-SUM(T18:U18) -> 0 | AB18: =Q18+W18 -> 0 | AC18: =R18+S18+X18+Y18 -> 0 | AD18: =T18+U18+AA18+Z18 -> 0 | AE18: =AB18+AC18-AD18 -> 0 | AK18: =SUM(AF18:AH18)-SUM(AI18:AJ18) -> 0 | AQ18: =AF18+AL18 -> 0 | AR18: =AG18+AH18+AM18+AN18 -> 0 | AS18: =AI18+AJ18+AP18+AO18 -> 0 | AT18: =AQ18+AR18-AS18 -> 0 | AU18: =D18-Q18-AF18 -> 0 | AV18: =M18-AB18-AQ18 -> 0 | AW18: =I18-V18-AK18 -> 0 | AX18: =P18-AE18-AT18 -> 0
I19: =SUM(D19:E19)-G19 -> 0 | M19: =D19+J19 -> 0 | N19: =E19+K19 -> 0 | O19: =G19+L19 -> 0 | P19: =M19+N19-O19 -> 0 | V19: =SUM(Q19:S19)-SUM(T19:U19) -> 0 | AB19: =Q19+W19 -> 0 | AC19: =R19+S19+X19+Y19 -> 0 | AD19: =T19+U19+AA19+Z19 -> 0 | AE19: =AB19+AC19-AD19 -> 0 | AK19: =SUM(AF19:AH19)-SUM(AI19:AJ19) -> 0 | AQ19: =AF19+AL19 -> 0 | AR19: =AG19+AH19+AM19+AN19 -> 0 | AS19: =AI19+AJ19+AP19+AO19 -> 0 | AT19: =AQ19+AR19-AS19 -> 0 | AU19: =D19-Q19-AF19 -> 0 | AV19: =M19-AB19-AQ19 -> 0 | AW19: =I19-V19-AK19 -> 0 | AX19: =P19-AE19-AT19 -> 0
I20: =SUM(D20:E20)-G20 -> 0 | M20: =D20+J20 -> 0 | N20: =E20+K20 -> 0 | O20: =G20+L20 -> 0 | P20: =M20+N20-O20 -> 0 | V20: =SUM(Q20:S20)-SUM(T20:U20) -> 0 | AB20: =Q20+W20 -> 0 | AC20: =R20+S20+X20+Y20 -> 0 | AD20: =T20+U20+AA20+Z20 -> 0 | AE20: =AB20+AC20-AD20 -> 0 | AK20: =SUM(AF20:AH20)-SUM(AI20:AJ20) -> 0 | AQ20: =AF20+AL20 -> 0 | AR20: =AG20+AH20+AM20+AN20 -> 0 | AS20: =AI20+AJ20+AP20+AO20 -> 0 | AT20: =AQ20+AR20-AS20 -> 0 | AU20: =D20-Q20-AF20 -> 0 | AV20: =M20-AB20-AQ20 -> 0 | AW20: =I20-V20-AK20 -> 0 | AX20: =P20-AE20-AT20 -> 0
I21: =SUM(D21:E21)-G21 -> 0 | M21: =D21+J21 -> 0 | N21: =E21+K21 -> 0 | O21: =G21+L21 -> 0 | P21: =M21+N21-O21 -> 0 | V21: =SUM(Q21:S21)-SUM(T21:U21) -> 0 | AB21: =Q21+W21 -> 0 | AC21: =R21+S21+X21+Y21 -> 0 | AD21: =T21+U21+AA21+Z21 -> 0 | AE21: =AB21+AC21-AD21 -> 0 | AK21: =SUM(AF21:AH21)-SUM(AI21:AJ21) -> 0 | AQ21: =AF21+AL21 -> 0 | AR21: =AG21+AH21+AM21+AN21 -> 0 | AS21: =AI21+AJ21+AP21+AO21 -> 0 | AT21: =AQ21+AR21-AS21 -> 0 | AU21: =D21-Q21-AF21 -> 0 | AV21: =M21-AB21-AQ21 -> 0 | AW21: =I21-V21-AK21 -> 0 | AX21: =P21-AE21-AT21 -> 0
I22: =SUM(D22:E22)-G22 -> 0 | M22: =D22+J22 -> 0 | N22: =E22+K22 -> 0 | O22: =G22+L22 -> 0 | P22: =M22+N22-O22 -> 0 | V22: =SUM(Q22:S22)-SUM(T22:U22) -> 0 | AB22: =Q22+W22 -> 0 | AC22: =R22+S22+X22+Y22 -> 0 | AD22: =T22+U22+AA22+Z22 -> 0 | AE22: =AB22+AC22-AD22 -> 0 | AK22: =SUM(AF22:AH22)-SUM(AI22:AJ22) -> 0 | AQ22: =AF22+AL22 -> 0 | AR22: =AG22+AH22+AM22+AN22 -> 0 | AS22: =AI22+AJ22+AP22+AO22 -> 0 | AT22: =AQ22+AR22-AS22 -> 0 | AU22: =D22-Q22-AF22 -> 0 | AV22: =M22-AB22-AQ22 -> 0 | AW22: =I22-V22-AK22 -> 0 | AX22: =P22-AE22-AT22 -> 0
I23: =SUM(D23:E23)-G23 -> 0 | M23: =D23+J23 -> 0 | N23: =E23+K23 -> 0 | O23: =G23+L23 -> 0 | P23: =M23+N23-O23 -> 0 | V23: =SUM(Q23:S23)-SUM(T23:U23) -> 0 | AB23: =Q23+W23 -> 0 | AC23: =R23+S23+X23+Y23 -> 0 | AD23: =T23+U23+AA23+Z23 -> 0 | AE23: =AB23+AC23-AD23 -> 0 | AK23: =SUM(AF23:AH23)-SUM(AI23:AJ23) -> 0 | AQ23: =AF23+AL23 -> 0 | AR23: =AG23+AH23+AM23+AN23 -> 0 | AS23: =AI23+AJ23+AP23+AO23 -> 0 | AT23: =AQ23+AR23-AS23 -> 0 | AU23: =D23-Q23-AF23 -> 0 | AV23: =M23-AB23-AQ23 -> 0 | AW23: =I23-V23-AK23 -> 0 | AX23: =P23-AE23-AT23 -> 0
I24: =SUM(D24:E24)-G24 -> 0 | M24: =D24+J24 -> 0 | N24: =E24+K24 -> 0 | O24: =G24+L24 -> 0 | P24: =M24+N24-O24 -> 0 | V24: =SUM(Q24:S24)-SUM(T24:U24) -> 0 | AB24: =Q24+W24 -> 0 | AC24: =R24+S24+X24+Y24 -> 0 | AD24: =T24+U24+AA24+Z24 -> 0 | AE24: =AB24+AC24-AD24 -> 0 | AK24: =SUM(AF24:AH24)-SUM(AI24:AJ24) -> 0 | AQ24: =AF24+AL24 -> 0 | AR24: =AG24+AH24+AM24+AN24 -> 0 | AS24: =AI24+AJ24+AP24+AO24 -> 0 | AT24: =AQ24+AR24-AS24 -> 0 | AU24: =D24-Q24-AF24 -> 0 | AV24: =M24-AB24-AQ24 -> 0 | AW24: =I24-V24-AK24 -> 0 | AX24: =P24-AE24-AT24 -> 0
... I32: =SUM(D32:E32)-G32 -> 0 | M32: =D32+J32 -> 0 | N32: =E32+K32 -> 0 | O32: =G32+L32 -> 0 | P32: =M32+N32-O32 -> 0 | V32: =SUM(Q32:S32)-SUM(T32:U32) -> 0 | AB32: =Q32+W32 -> 0 | AC32: =R32+S32+X32+Y32 -> 0 | AD32: =T32+U32+AA32+Z32 -> 0 | AE32: =AB32+AC32-AD32 -> 0 | AK32: =SUM(AF32:AH32)-SUM(AI32:AJ32) -> 0 | AQ32: =AF32+AL32 -> 0 | AR32: =AG32+AH32+AM32+AN32 -> 0 | AS32: =AI32+AJ32+AP32+AO32 -> 0 | AT32: =AQ32+AR32-AS32 -> 0 | AU32: =D32-Q32-AF32 -> 0 | AV32: =M32-AB32-AQ32 -> 0 | AW32: =I32-V32-AK32 -> 0 | AX32: =P32-AE32-AT32 -> 0
A33: 合计 | D33: =SUM(D13:D32) -> 0 | E33: =SUM(E13:E32) -> 0 | G33: =SUM(G13:G32) -> 0 | I33: =SUM(I13:I32) -> 0 | J33: =SUM(J13:J32) -> 0 | K33: =SUM(K13:K32) -> 0 | L33: =SUM(L13:L32) -> 0 | M33: =SUM(M13:M32) -> 0 | N33: =SUM(N13:N32) -> 0 | O33: =SUM(O13:O32) -> 0 | P33: =SUM(P13:P32) -> 0 | ... AX33: =SUM(AX13:AX32) -> 0
A34: 其中：
A35: 探明矿区权益 | D35: =SUMPRODUCT(($A$13:$A$32=$A35)*(D$13:D$32)) -> 0 | E35: =SUMPRODUCT(($A$13:$A$32=$A35)*(E$13:E$32)) -> 0 | G35: =SUMPRODUCT(($A$13:$A$32=$A35)*(G$13:G$32)) -> 0 | I35: =SUMPRODUCT(($A$13:$A$32=$A35)*(I$13:I$32)) -> 0 | J35: =SUMPRODUCT(($A$13:$A$32=$A35)*(J$13:J$32)) -> 0 | K35: =SUMPRODUCT(($A$13:$A$32=$A35)*(K$13:K$32)) -> 0 | L35: =SUMPRODUCT(($A$13:$A$32=$A35)*(L$13:L$32)) -> 0 | M35: =SUMPRODUCT(($A$13:$A$32=$A35)*(M$13:M$32)) -> 0 | N35: =SUMPRODUCT(($A$13:$A$32=$A35)*(N$13:N$32)) -> 0 | O35: =SUMPRODUCT(($A$13:$A$32=$A35)*(O$13:O$32)) -> 0 | P35: =SUMPRODUCT(($A$13:$A$32=$A35)*(P$13:P$32)) -> 0 | ... AX35: =SUMPRODUCT(($A$13:$A$32=$A35)*(AX$13:AX$32)) -> 0
A36: 未探明矿区权益 | D36: =SUMPRODUCT(($A$13:$A$32=$A36)*(D$13:D$32)) -> 0 | E36: =SUMPRODUCT(($A$13:$A$32=$A36)*(E$13:E$32)) -> 0 | G36: =SUMPRODUCT(($A$13:$A$32=$A36)*(G$13:G$32)) -> 0 | I36: =SUMPRODUCT(($A$13:$A$32=$A36)*(I$13:I$32)) -> 0 | J36: =SUMPRODUCT(($A$13:$A$32=$A36)*(J$13:J$32)) -> 0 | K36: =SUMPRODUCT(($A$13:$A$32=$A36)*(K$13:K$32)) -> 0 | L36: =SUMPRODUCT(($A$13:$A$32=$A36)*(L$13:L$32)) -> 0 | M36: =SUMPRODUCT(($A$13:$A$32=$A36)*(M$13:M$32)) -> 0 | N36: =SUMPRODUCT(($A$13:$A$32=$A36)*(N$13:N$32)) -> 0 | O36: =SUMPRODUCT(($A$13:$A$32=$A36)*(O$13:O$32)) -> 0 | P36: =SUMPRODUCT(($A$13:$A$32=$A36)*(P$13:P$32)) -> 0 | ... AX36: =SUMPRODUCT(($A$13:$A$32=$A36)*(AX$13:AX$32)) -> 0
A37: 井及相关设施 | D37: =SUMPRODUCT(($A$13:$A$32=$A37)*(D$13:D$32)) -> 0 | E37: =SUMPRODUCT(($A$13:$A$32=$A37)*(E$13:E$32)) -> 0 | G37: =SUMPRODUCT(($A$13:$A$32=$A37)*(G$13:G$32)) -> 0 | I37: =SUMPRODUCT(($A$13:$A$32=$A37)*(I$13:I$32)) -> 0 | J37: =SUMPRODUCT(($A$13:$A$32=$A37)*(J$13:J$32)) -> 0 | K37: =SUMPRODUCT(($A$13:$A$32=$A37)*(K$13:K$32)) -> 0 | L37: =SUMPRODUCT(($A$13:$A$32=$A37)*(L$13:L$32)) -> 0 | M37: =SUMPRODUCT(($A$13:$A$32=$A37)*(M$13:M$32)) -> 0 | N37: =SUMPRODUCT(($A$13:$A$32=$A37)*(N$13:N$32)) -> 0 | O37: =SUMPRODUCT(($A$13:$A$32=$A37)*(O$13:O$32)) -> 0 | P37: =SUMPRODUCT(($A$13:$A$32=$A37)*(P$13:P$32)) -> 0 | ... AX37: =SUMPRODUCT(($A$13:$A$32=$A37)*(AX$13:AX$32)) -> 0
A38: … | D38: =SUMPRODUCT(($A$13:$A$32=$A38)*(D$13:D$32)) -> 0 | E38: =SUMPRODUCT(($A$13:$A$32=$A38)*(E$13:E$32)) -> 0 | G38: =SUMPRODUCT(($A$13:$A$32=$A38)*(G$13:G$32)) -> 0 | I38: =SUMPRODUCT(($A$13:$A$32=$A38)*(I$13:I$32)) -> 0 | J38: =SUMPRODUCT(($A$13:$A$32=$A38)*(J$13:J$32)) -> 0 | K38: =SUMPRODUCT(($A$13:$A$32=$A38)*(K$13:K$32)) -> 0 | L38: =SUMPRODUCT(($A$13:$A$32=$A38)*(L$13:L$32)) -> 0 | M38: =SUMPRODUCT(($A$13:$A$32=$A38)*(M$13:M$32)) -> 0 | N38: =SUMPRODUCT(($A$13:$A$32=$A38)*(N$13:N$32)) -> 0 | O38: =SUMPRODUCT(($A$13:$A$32=$A38)*(O$13:O$32)) -> 0 | P38: =SUMPRODUCT(($A$13:$A$32=$A38)*(P$13:P$32)) -> 0 | ... AX38: =SUMPRODUCT(($A$13:$A$32=$A38)*(AX$13:AX$32)) -> 0
A39: … | D39: =SUMPRODUCT(($A$13:$A$32=$A39)*(D$13:D$32)) -> 0 | E39: =SUMPRODUCT(($A$13:$A$32=$A39)*(E$13:E$32)) -> 0 | G39: =SUMPRODUCT(($A$13:$A$32=$A39)*(G$13:G$32)) -> 0 | I39: =SUMPRODUCT(($A$13:$A$32=$A39)*(I$13:I$32)) -> 0 | J39: =SUMPRODUCT(($A$13:$A$32=$A39)*(J$13:J$32)) -> 0 | K39: =SUMPRODUCT(($A$13:$A$32=$A39)*(K$13:K$32)) -> 0 | L39: =SUMPRODUCT(($A$13:$A$32=$A39)*(L$13:L$32)) -> 0 | M39: =SUMPRODUCT(($A$13:$A$32=$A39)*(M$13:M$32)) -> 0 | N39: =SUMPRODUCT(($A$13:$A$32=$A39)*(N$13:N$32)) -> 0 | O39: =SUMPRODUCT(($A$13:$A$32=$A39)*(O$13:O$32)) -> 0 | P39: =SUMPRODUCT(($A$13:$A$32=$A39)*(P$13:P$32)) -> 0 | ... AX39: =SUMPRODUCT(($A$13:$A$32=$A39)*(AX$13:AX$32)) -> 0
A40: 三、审计说明：
A43: 四、审计结论
A46: 提示：
A47: 1.审计说明可以概述:(1)程序的测试情况、结果;(2)拟调整事项及其调整分录、未调整事项及其影响，审计范围受到限制情况及其影响。
A48: 2.审计结论可参考：A、未见异常。 B、除上述重大不符事项应当作为调整事项予以调整外，其余未见异常。 C、由于存在以下重大未调整事项(或审计范围受到限制无法获取充分、适当证据)，不可确认。

Sheet 调整分录汇总H5-3
A1: 致同会计师事务所
A2: 油气资产调整分录汇总表
A3: =底稿目录!A2 -> 被审计单位： | D3: =底稿目录!A4 -> 编制人： | G3: =底稿目录!A6 -> 编制日期： | I3: 索引号： | J3: H5-3
A4: =底稿目录!A3 -> 截止日：202X年12月31日 | D4: =底稿目录!A5 -> 复核人： | G4: =底稿目录!A7 -> 复核日期： | I4: 页 次：
A5: 调整事项说明 | B5: 类别（报表调整/账项调整/其他） | C5: 报表项目 | D5: 科目名称 | E5: 附注项目 | F5: …… | G5: 借方调整金额 | H5: 贷方调整金额 | I5: 索引 | J5: 备注
A23: 提示：本底稿适用于调整分录较多、较复杂的项目，且仅列示与本报表项目相关的审计调整。项目组可根据项目实际情况选择是否使用该底稿。

Sheet 闲置检查表H5-4
A1: 致同会计师事务所
A2: 闲置油气资产检查表
A3: =底稿目录!A2 -> 被审计单位： | D3: =底稿目录!A4 -> 编制人： | F3: =底稿目录!A6 -> 编制日期： | G3: 索引号： | H3: H5-4
A4: =底稿目录!A3 -> 截止日：202X年12月31日 | D4: =底稿目录!A5 -> 复核人： | F4: =底稿目录!A7 -> 复核日期： | G4: 页 次：
A5: 一、审计目标：1.资产负债表中记录的油气资产是存在的，且已记录于恰当的账户；2.油气资产以恰当的金额包括在财务报表中，与之相关的计价或分摊调整已恰当记录，相关披露已得到恰当计量和描述
A6: 二、审计过程：
A7: ①未使用油气资产：
A8: 序号 | B8: 油气资产类别/名称 | C8: 油气资产原值 | D8: 油气资产净值 | E8: 起止时间 | F8: 状况 | G8: 备注
A9: 1
A10: 2
A11: 3
A12: …
A13: 合计 | C13: =SUM(C9:C12) -> 0 | D13: =SUM(D9:D12) -> 0
A14: ②不需用油气资产：
A15: 序号 | B15: 油气资产类别/名称 | C15: 油气资产原值 | D15: 油气资产净值 | E15: 起止时间 | F15: 状况 | G15: 备注
A16: 1
A17: 2
A18: 3
A19: …
A20: 合计 | C20: =SUM(C16:C19) -> 0 | D20: =SUM(D16:D19) -> 0
A21: ③持有待售油气资产：
A22: 序号 | B22: 油气资产类别/名称 | C22: 油气资产原值 | D22: 油气资产净值 | E22: 公允价值 | F22: 预计处置费用 | G22: 预计处置时间 | H22: 备注
A23: 1
A24: 2
A25: 3
A26: …
A27: 合计 | C27: =SUM(C23:C26) -> 0 | D27: =SUM(D23:D26) -> 0 | E27: =SUM(E23:E26) -> 0 | F27: =SUM(F23:F26) -> 0
A28: 三、审计说明：
A30: 四、审计结论：
A34: 提示
A35: 1.获取暂时闲置油气资产的相关证明文件，并观察其实际状况，是否已按规定计提折旧，相关的会计处理是否正确。
A36: 2.获取持有待售油气资产的相关证明文件，并作相应记录，检查对其预计净残值调整是否正确、会计处理是否正确。

Sheet 会计政策会计估计检查表H5-5
A1: 致同会计师事务所
A2: 油气资产相关会计政策/估计检查表
A3: =底稿目录!A2 -> 被审计单位： | D3: =底稿目录!A4 -> 编制人： | H3: =底稿目录!A6 -> 编制日期： | J3: 索引号： | K3: H5-5
A4: =底稿目录!A3 -> 截止日：202X年12月31日 | D4: =底稿目录!A5 -> 复核人： | H4: =底稿目录!A7 -> 复核日期： | J4: 页 次：
A5: 一、审计目标：
A6: 1.所有应记录的油气资产均已记录，所有应当包括在财务报表中的相关披露均已包括； | E6: 2.油气资产以恰当的金额包括在财务报表中，与之相关的计价或分摊调整已恰当记录，相关披露已得到恰当计量和描述 。
A7: 二、审计过程：
B8: 被审计单位的油气资产折耗政策：
A9: 序号 | B9: 类别 | C9: 折耗年限 | D9: 折耗方法 | E9: 残值率 | F9: 是否符合实际经营情况和会计准则的要求 | G9: 是否与相关资产所包含的经济利益预期实现方式相一致 | H9: 与同行业公司相比，会计政策是否合理 | I9: 是否存在会计政策/会计估计变更 | J9: 会计政策/会计估计变更是否合理 | K9: 备注
A10: 1
A11: 2
A12: 3
A13: 4
A14: 5
B15: 同行业其他公司的油气资产折耗政策
A16: 序号 | B16: 类别 | C16: 同行业公司1 | F16: 同行业公司2 | I16: 同行业公司3
C17: 折耗年限 | D17: 折耗方法 | E17: 残值率 | F17: 折耗年限 | G17: 折耗方法 | H17: 残值率 | I17: 折耗年限 | J17: 折耗方法 | K17: 残值率
A18: 1
A19: 2
A20: 3
A21: 4
A22: 5
B23: 如本期存在会计估计变更，原会计估计如下：
A24: 序号 | B24: 类别 | C24: 使用寿命 | D24: 摊销方法 | E24: 残值率
A25: 1
A26: 2
A27: 3
A28: 4
A29: 5
A30: 三、审计说明：
A33: 四、审计结论：

Sheet 分析表H5-6
A1: 致同会计师事务所
A2: 油气资产分析表
A3: =底稿目录!A2 -> 被审计单位： | C3: =底稿目录!A4 -> 编制人： | E3: =底稿目录!A6 -> 编制日期： | G3: 索引号： | H3: H5-6
A4: =底稿目录!A3 -> 截止日：202X年12月31日 | C4: =底稿目录!A5 -> 复核人： | E4: =底稿目录!A7 -> 复核日期： | G4: 页 次：
A5: 一、审计目标：
A6: 1.资产负债表中记录的油气资产是存在的，且已记录于恰当的账户；2.所有应记录的油气资产均已记录，所有应当包括在财务报表中的相关披露均已包括；
A7: 3.油气资产以恰当的金额包括在财务报表中，与之相关的计价或分摊调整已恰当记录，相关披露已得到恰当计量和描述 。
A8: 二、审计过程：
A9: 序号 | B9: 比例 | C9: 2025年 | D9: 2024年 | E9: 变动 | F9: 变动原因及合理性解释
A10: 1 | B10: 油气资产净值÷资产总额 | E10: =(C10-D10)/D10 -> #DIV/0!
A11: 2 | B11: 本期计提折耗额÷油气资产原值 | E11: =(C11-D11)/D11 -> #DIV/0!
A12: 3 | B12: 累计计提折耗额÷油气资产原值 | E12: =(C12-D12)/D12 -> #DIV/0!
A13: 4 | B13: 油气资产减值准备余额÷油气资产原值 | E13: =(C13-D13)/D13 -> #DIV/0!
A14: 5 | B14: 油气资产原值÷本期产品产量 | E14: =(C14-D14)/D14 -> #DIV/0!
A15: 6 | B15: 出租租金收入÷油气资产原值 | E15: =(C15-D15)/D15 -> #DIV/0!
A16: 7 | B16: 维修费用÷油气资产原值 | E16: =(C16-D16)/D16 -> #DIV/0!
A17: 三、审计说明：
A19: 四、审计结论：
A24: 提示：
A25: 1、分析油气资产的构成及其增减变动情况、增减变动原因，与在建工程、现金流量表、生产能力等相关信息交叉复核，检查油气资产相关金额的合理性和准确性；
A26: 2、分析本期末油气资产减值准备数额占期末油气资产原价的比率，并与期初数比较。

Sheet 增加检查表H5-7
A1: 致同会计师事务所
A2: 油气资产增加检查表
A3: =底稿目录!A2 -> 被审计单位： | E3: =底稿目录!A4 -> 编制人： | J3: =底稿目录!A6 -> 编制日期： | V3: 索引号： | W3: H5-7
A4: =底稿目录!A3 -> 截止日：202X年12月31日 | E4: =底稿目录!A5 -> 复核人： | J4: =底稿目录!A7 -> 复核日期： | V4: 页 次：
A5: 一、审计目标：1.资产负债表中记录的油气资产是存在的，且已记录于恰当的账户；2.所有应记录的油气资产均已记录，所有应当包括在财务报表中的相关披露均已包括；3.记录的油气资产由被审计单位拥有或控制；4.油气资产以恰当的金额包括在财务报表中，与之相关的计价或分摊调整已恰当记录，相关披露已得到恰当计量和描述。
A6: 二、样本选取标准与规模：
A7: 测试总体： | B7: 如油气资产借方发生额所有凭证共XX笔金额XX、贷方发生额所有凭证共XX笔金额XX | I7: 特定样本： | J7: XX金额以上（大额）、关联方/关联交易形成的款项、XX异常款项全部测试，共XX笔；
A8: 抽样总体： | B8: 测试总体扣除特定样本以外的样本，共XX笔、金额XX | I8: 确定的抽样样本量： | K8: 抽取XX笔 | L8: （如果使用了样本计算器计算样本量，样本量计算过程见<XX>底稿）
A9: 抽样方法： | B9: 随机选样/系统选样/货币单元抽样/随意选样（非统计抽样适用） | I9: 抽样过程： | J9: 使用IDEA（XX抽样工具）选择XX数量、金额XX的样本进行测试，抽样工具中的样本选择过程和结果见<XX>底稿
A10: 三、测试：
A11: 测试内容说明：1.原始凭证是否齐全； 2.记账凭证与原始凭证是否相符；3.账务处理是否正确；4.是否记录于恰当的会计期间；5.……
A12: 序号 | B12: 油气资产类别 | C12: 油气资产编号 | D12: 油气资产名称 | E12: 增加日期 | F12: 增加方式 | G12: 入账凭证号 | H12: 对方科目 | I12: 增加情况 | M12: 验收单 | O12: 合同/协议/订单 | R12: 采购发票 | U12: …… | V12: 索引号 | W12: 是否异常 | X12: 检查的关键证据和要素根据被审计单位具体情况修改
I13: 原值 | J13: 累计折耗 | K13: 减值准备 | L13: 净值 | M13: 单据编号 | N13: 验收日期 | O13: 日期/编号 | P13: 对手方名称 | Q13: 金额 | R13: 日期/编号 | S13: 对手方名称 | T13: 金额
A14: 1 | L14: =I14-J14-K14 -> 0
A15: 2 | L15: =I15-J15-K15 -> 0
A16: 3 | L16: =I16-J16-K16 -> 0
A17: 4 | L17: =I17-J17-K17 -> 0
A18: 5 | L18: =I18-J18-K18 -> 0
A19: 6 | L19: =I19-J19-K19 -> 0
A20: 7 | L20: =I20-J20-K20 -> 0
A21: 8 | L21: =I21-J21-K21 -> 0
A22: 9 | L22: =I22-J22-K22 -> 0
A23: 10 | L23: =I23-J23-K23 -> 0
A24: 11 | L24: =I24-J24-K24 -> 0
A25: 12 | L25: =I25-J25-K25 -> 0
... A28: 15 | L28: =I28-J28-K28 -> 0
A29: …… | L29: =I29-J29-K29 -> 0
A30: 合计 | I30: =SUM(I14:I29) -> 0 | J30: =SUM(J14:J29) -> 0 | K30: =SUM(K14:K29) -> 0 | L30: =SUM(L14:L29) -> 0
A31: 本期新增油气资产合计 | I31: ='明细表H5-2'!N33 -> 0
A32: 检查比例 | I32: =IF(I30=0,0,I30/$I$31) -> 0
A33: 四、审计说明：
A34: 1.如果检查比例较低应扩大检查样本量或说明原因
A35: 2.……
A36: 五、审计结论：

Sheet 减少检查表H5-8
A1: 致同会计师事务所
A2: 油气资产减少检查表
A3: =底稿目录!A2 -> 被审计单位： | G3: =底稿目录!A4 -> 编制人： | L3: =底稿目录!A6 -> 编制日期： | V3: 索引号： | W3: H5-8
A4: =底稿目录!A3 -> 截止日：202X年12月31日 | G4: =底稿目录!A5 -> 复核人： | L4: =底稿目录!A7 -> 复核日期： | V4: 页 次：
A5: 一、审计目标：1.资产负债表中记录的油气资产是存在的，且已记录于恰当的账户；2.所有应记录的油气资产均已记录，所有应当包括在财务报表中的相关披露均已包括；3.油气资产以恰当的金额包括在财务报表中，与之相关的计价或分摊调整已恰当记录，相关披露已得到恰当计量和描述。
A6: 二、样本选取标准与规模：
A7: 测试总体： | B7: 如油气资产借方发生额所有凭证共XX笔金额XX、贷方发生额所有凭证共XX笔金额XX | I7: 特定样本： | J7: XX金额以上（大额）、关联方/关联交易形成的款项、XX异常款项全部测试，共XX笔；
A8: 抽样总体： | B8: 测试总体扣除特定样本以外的样本，共XX笔、金额XX | I8: 确定的抽样样本量： | K8: 抽取XX笔 | L8: （如果使用了样本计算器计算样本量，样本量计算过程见<XX>底稿）
A9: 抽样方法： | B9: 随机选样/系统选样/货币单元抽样/随意选样（非统计抽样适用） | I9: 抽样过程： | J9: 使用IDEA（XX抽样工具）选择XX数量、金额XX的样本进行测试，抽样工具中的样本选择过程和结果见<XX>底稿
A10: 三、测试：
A11: 测试内容说明：1.原始凭证是否齐全； 2.记账凭证与原始凭证是否相符；3.账务处理是否正确；4.是否记录于恰当的会计期间；5.……
A12: 序号 | B12: 油气资产类别 | C12: 油气资产编号 | D12: 油气资产名称 | E12: 减少方式 | F12: 减少日期 | G12: 凭证号 | H12: 对方科目 | I12: 减少情况 | P12: 审批单 | R12: 合同/协议/订单 | U12: …… | V12: 索引号 | W12: 是否异常
I13: 转入清理的油气资产 | M13: 清理净收入 | O13: 清理净损益 | P13: 日期/编号 | Q13: 是否经过恰当审批 | R13: 日期/编号 | S13: 对手方名称 | T13: 金额
I14: 原值 | J14: 累计折耗 | K14: 减值准备 | L14: 净值 | M14: 清理费用 | N14: 清理收入 | R14: 3 | S14: 4 | T14: 5 | X14: 检查的关键证据和要素根据被审计单位具体情况修改
A15: 1 | L15: =I15-J15-K15 -> 0 | O15: =N15-M15-L15 -> 0
A16: 2 | L16: =I16-J16-K16 -> 0 | O16: =N16-M16-L16 -> 0
A17: 3 | L17: =I17-J17-K17 -> 0 | O17: =N17-M17-L17 -> 0
A18: 4 | L18: =I18-J18-K18 -> 0 | O18: =N18-M18-L18 -> 0
A19: 5 | L19: =I19-J19-K19 -> 0 | O19: =N19-M19-L19 -> 0
A20: 6 | L20: =I20-J20-K20 -> 0 | O20: =N20-M20-L20 -> 0
A21: 7 | L21: =I21-J21-K21 -> 0 | O21: =N21-M21-L21 -> 0
A22: 8 | L22: =I22-J22-K22 -> 0 | O22: =N22-M22-L22 -> 0
A23: 9 | L23: =I23-J23-K23 -> 0 | O23: =N23-M23-L23 -> 0
A24: 10 | L24: =I24-J24-K24 -> 0 | O24: =N24-M24-L24 -> 0
A25: 11 | L25: =I25-J25-K25 -> 0 | O25: =N25-M25-L25 -> 0
A26: 12 | L26: =I26-J26-K26 -> 0 | O26: =N26-M26-L26 -> 0
... A29: 15 | L29: =I29-J29-K29 -> 0 | O29: =N29-M29-L29 -> 0
A30: …… | L30: =I30-J30-K30 -> 0 | O30: =N30-M30-L30 -> 0
A31: 合计 | I31: =SUM(I15:I30) -> 0 | J31: =SUM(J15:J30) -> 0 | K31: =SUM(K15:K30) -> 0 | L31: =SUM(L15:L30) -> 0 | M31: =SUM(M15:M30) -> 0 | N31: =SUM(N15:N30) -> 0 | O31: =SUM(O15:O30) -> 0
A32: 本期减少油气资产合计 | I32: ='明细表H5-2'!O33 -> 0
A33: 检查比例 | I33: =IF(I31=0,0,I31/$I$32) -> 0
A34: 四、审计说明：
A35: 1.如果检查比例较低应扩大检查样本量或说明原因
A36: 2.……
A38: 五、审计结论：

Sheet 监盘计划H5-9
A1: 致同会计师事务所
A2: 油气资产监盘计划
A3: =底稿目录!A2 -> 被审计单位： | D3: =底稿目录!A4 -> 编制人： | F3: =底稿目录!A6 -> 编制日期： | H3: 索引号： | I3: H5-9
A4: =底稿目录!A3 -> 截止日：202X年12月31日 | D4: =底稿目录!A5 -> 复核人： | F4: =底稿目录!A7 -> 复核日期： | H4: 页 次：
A5: 被审计单位名称： | F5: 审计目标：
A6: 一、确定的油气资产存在性认定可能存在重大错报的风险程度：
A8: 二、了解被审计单位油气资产期末状况与管理规定：
A9: （一）油气资产的期末状况：
A10: 1．期末余额： | E10: 提取的减值准备金额：
A11: 2．大类油气资产金额情况：
B12: 类别 | C12: 期末余额 | D12: 减值准备 | E12: 账面净值
A16: 3．期末资产数量：
B17: 类 别 | C17: 计量单位 | D17: 数量 | E17: 说明
A21: 4．资产存放地点：
B22: 类 别 | C22: 仓库（或场所） | D22: 地点 | E22: 说明
A26: （二）企业定期盘点内部控制制度与执行情况：
A27: 1．制度名称：（提示：按企业内部控制制度名称填写） 索引号：（ ）
A28: （1）规定盘点的时间与次数：
A29: （2）负责盘点的部门： | F29: 负责人：
A30: （提示：如制度规定与实际执行不一致的，应按制度规定与实际负责的部门分别填写）
A31: 2．企业实际盘点情况：
A32: （1）盘点计划安排：
A33: （2）盘点会议情况：
A34: （3）预计安排的盘点人员数量： | F34: 负责人：
A35: （4）对企业盘点计划的评价：
A36: （三）查阅以前年度工作底稿记录：
A37: 1．上一年度监盘时间： | F37: 实施监盘的人员：
A38: 2．抽盘的油气资产范围： | F38: 抽盘比例：
A39: 3．实施监盘中发现的问题与存在的不足：
A40: （提示：上年度如是本所实施监盘的，应当查阅上一年度工作底稿；如不是本所实施审计的，应当在与前任会计师实施沟通程序中安排本项沟通内容。）
A41: 三、评估审计人员的专业胜任能力：
A42: 提示：针对特殊类型的存货，应当评估审计人员是否具备专业胜任能力
A43: 四、盘点计划安排：
A44: （一）预计监盘时间：
A45: （二）预计安排监盘人员数量： | F45: 监盘程序负责人：
A46: （三）预计监盘的油气资产范围：
A47: 1．类别范围：
A48: 2．地点范围：
A49: （四）拟实施的盘点方法：
A50: （五）就监盘计划与管理层沟通事项
A51: 1．时间： | E51: 2.管理层人员：
A52: 3．审计小组参与人员：
A53: （六）针对被审计单位具体情况，需要向管理层提出的监盘的特殊要求：
A54: （七）预计监盘中抽取样本的方法与数量
A55: 1．从会计明细账簿中选取样本的方法： | G55: 预计选取数量：
A56: 2．从实际油气资产中选取样本的方法： | G56: 预计选取数量：
A57: （八）实际监盘时点至资产负债表日的推算方法：
A58: 1．推断方法说明：
A59: 2．预计拟要求的盘点复盘比例：

Sheet 盘点检查表H5-10
A1: 致同会计师事务所
A2: 油气资产盘点检查表
A3: =底稿目录!A2 -> 被审计单位： | E3: =底稿目录!A4 -> 编制人： | J3: =底稿目录!A6 -> 编制日期： | L3: 索引号： | M3: H5-10
A4: =底稿目录!A3 -> 截止日：202X年12月31日 | E4: =底稿目录!A5 -> 复核人： | J4: =底稿目录!A7 -> 复核日期： | L4: 页 次：
A5: 一、审计目标：
A6: 1.资产负债表中记录的油气资产是存在的，且已记录于恰当的账户；2.油气资产以恰当的金额包括在财务报表中，与之相关的计价或分摊调整已恰当记录，相关披露已得到恰当计量和描述 。
A7: 二、样本选取标准与规模：
A8: 测试总体： | B8: 如期末油气资产数量XX、金额XX | G8: 特定样本： | H8: XX金额以上（大额）、关联方/关联交易形成的款项、XX异常款项全部测试，共XX笔；
A9: 抽样总体： | B9: 测试总体扣除特定样本以外的样本，数量XX、金额XX | G9: 确定的抽样样本量： | I9: 抽取XX笔 | J9: （如果使用了样本计算器计算样本量，样本量计算过程见<XX>底稿）
A10: 抽样方法： | B10: 随机选样/系统选样/货币单元抽样/随意选样（非统计抽样适用） | G10: 抽样过程： | H10: 使用IDEA（XX抽样工具）选择XX数量、金额XX的样本进行测试，抽样工具中的样本选择过程和结果见<XX>底稿
A11: 三、审计过程：
A12: 抽盘地点：______________ | C12: 盘点人员： | D12: 被审计单位仓库盘点人和财务监盘人签字 | I12: 监盘人员： | J12: （审计人员签字） | L12: 盘点时间：__________________
A13: （一）从油气资产盘点记录中选取项目追查至油气资产实物
A14: 油气资产名称/类别 | B14: 资产编号 | C14: 规格 | D14: 单位 | E14: 单价 | F14: 盘点前财务账面记录 | H14: 企业盘点记录数量 | I14: 抽盘数量 | J14: 抽盘与账面差异（+盈-亏） | K14: 抽盘与企业盘点差异 | L14: 企业盘点与账面差异 | M14: 品质状况（正常/残次/毁损/滞销等）
F15: 数量 | G15: 金额
J16: =I16-F16 -> 0 | K16: =I16-H16 -> 0 | L16: =H16-F16 -> 0
J17: =I17-F17 -> 0 | K17: =I17-H17 -> 0 | L17: =H17-F17 -> 0
J18: =I18-F18 -> 0 | K18: =I18-H18 -> 0 | L18: =H18-F18 -> 0
J19: =I19-F19 -> 0 | K19: =I19-H19 -> 0 | L19: =H19-F19 -> 0
J20: =I20-F20 -> 0 | K20: =I20-H20 -> 0 | L20: =H20-F20 -> 0
J21: =I21-F21 -> 0 | K21: =I21-H21 -> 0 | L21: =H21-F21 -> 0
J22: =I22-F22 -> 0 | K22: =I22-H22 -> 0 | L22: =H22-F22 -> 0
J23: =I23-F23 -> 0 | K23: =I23-H23 -> 0 | L23: =H23-F23 -> 0
J24: =I24-F24 -> 0 | K24: =I24-H24 -> 0 | L24: =H24-F24 -> 0
J25: =I25-F25 -> 0 | K25: =I25-H25 -> 0 | L25: =H25-F25 -> 0
J26: =I26-F26 -> 0 | K26: =I26-H26 -> 0 | L26: =H26-F26 -> 0
A27: 合计 | F27: =SUM(F16:F26) -> 0 | G27: =SUM(G16:G26) -> 0 | H27: =SUM(H16:H26) -> 0 | I27: =SUM(I16:I26) -> 0 | J27: =SUM(J16:J26) -> 0 | K27: =SUM(K16:K26) -> 0 | L27: =SUM(L16:L26) -> 0
A28: 期末油气资产原值合计：
A29: 抽取样本占期末原值合计的比例：（%） | G29: =G27/G28 -> #DIV/0!
A30: （二）从油气资产实物中选取项目追查至油气资产盘点记录
A31: 油气资产名称/类别 | B31: 资产编号 | C31: 规格 | D31: 单位 | E31: 单价 | F31: 盘点前财务账面记录 | H31: 企业盘点记录数量 | I31: 抽盘数量 | J31: 抽盘与账面差异（+盈-亏） | K31: 抽盘与企业盘点差异 | L31: 企业盘点与账面差异 | M31: 品质状况（正常/残次/毁损/滞销等）
F32: 数量 | G32: 金额
J33: =I33-F33 -> 0 | K33: =I33-H33 -> 0 | L33: =H33-F33 -> 0
J34: =I34-F34 -> 0 | K34: =I34-H34 -> 0 | L34: =H34-F34 -> 0
J35: =I35-F35 -> 0 | K35: =I35-H35 -> 0 | L35: =H35-F35 -> 0
J36: =I36-F36 -> 0 | K36: =I36-H36 -> 0 | L36: =H36-F36 -> 0
J37: =I37-F37 -> 0 | K37: =I37-H37 -> 0 | L37: =H37-F37 -> 0
J38: =I38-F38 -> 0 | K38: =I38-H38 -> 0 | L38: =H38-F38 -> 0
J39: =I39-F39 -> 0 | K39: =I39-H39 -> 0 | L39: =H39-F39 -> 0
J40: =I40-F40 -> 0 | K40: =I40-H40 -> 0 | L40: =H40-F40 -> 0
J41: =I41-F41 -> 0 | K41: =I41-H41 -> 0 | L41: =H41-F41 -> 0
J42: =I42-F42 -> 0 | K42: =I42-H42 -> 0 | L42: =H42-F42 -> 0
J43: =I43-F43 -> 0 | K43: =I43-H43 -> 0 | L43: =H43-F43 -> 0
A44: 合计 | F44: =SUM(F33:F43) -> 0 | G44: =SUM(G33:G43) -> 0 | H44: =SUM(H33:H43) -> 0 | I44: =SUM(I33:I43) -> 0 | J44: =SUM(J33:J43) -> 0 | K44: =SUM(K33:K43) -> 0 | L44: =SUM(L33:L43) -> 0 | M44: =SUM(M33:M43) -> 0
A45: 期末油气资产原值合计：
A46: 抽取样本占期末原值合计的比例：（%） | G46: =G44/G45 -> #DIV/0!
A47: 四、审计说明：
A48: （1）备忘录详见“油气资产盘点实地监盘备忘录”。
A50: 五、审计结论：
A54: 提示：
A55: 1、本表可作为油气资产盘点汇总表或盘点明细表或油气资产抽盘表。
A56: 2、财务账面记录与资产管理管理部门账面记录应一致，若存在差异应调整一致。
A57: 3、财务账面记录与实际盘点记录的差异构成盘盈/盘亏，应根据具体原因分析处理。应说明企业的处理结果。
A58: 4、盘点时，应关注易移动的“存量资产”及可能发生减值的“存量资产”；
A59: 5、盘点时应关注资产的品质状况（影响减值准备的计提）。

Sheet 监盘小结H5-11
A1: 致同会计师事务所
A2: 油气资产监盘小结
A3: =底稿目录!A2 -> 被审计单位： | D3: =底稿目录!A4 -> 编制人： | F3: =底稿目录!A6 -> 编制日期： | H3: 索引号： | I3: H5-11
A4: =底稿目录!A3 -> 截止日：202X年12月31日 | D4: =底稿目录!A5 -> 复核人： | F4: =底稿目录!A7 -> 复核日期： | H4: 页 次：
A5: 一、资产负债表日：
A7: 二、主要资产存放情况：
A8: 序号 | B8: 资产类别 | C8: 资产名称 | D8: 存放地点
A9: 1
A10: 2
A11: 3
A12: 三、了解资产管理情况
A13: 序号 | B13: 项目
A14: 1 | B14: 资产管理部门：
A15: 2 | B15: 管理人员：
A16: 3 | B16: 资产是否具有管理标识：
A17: 4 | B17: 资产是否具有定期保养制度：
A18: 5 | B18: 大修理周期时间：
A19: 6 | B19: 资产明细账（卡）是否完整：
A20: 7 | B20: 资产明细账（卡）的各项记录是否完整：
A21: 三、参与盘点人员：
A22: 1． 被审计单位的人员：
A23: 序号 | B23: 盘点人员所属部门 | C23: 人员数量 | D23: 人员名称 | E23: 所负责的部分
A24: 1
A25: 2
A26: 3
A27: 2． 审计人员：
A28: 序号 | B28: 人员名称 | C28: 负责的部分
A29: 1
A30: 2
A31: 3
A32: 四、实际盘点前的检查程序：
A33: 1．资产现场观察说明：
A34: 2．盘点前检查程序：
A35: （1）资产明细账（卡） 是否获取： | G35: 索引：
A36: （2）油气资产管理制度 是否获取： | G36: 索引：
A37: （3）油气资产维修制度是否获取： | G37: 索引：
A38: （4）获取或编制资产位置简图： | G38: 索引：
A39: 五、实际盘点时间：
A40: 实际监盘（盘点）日： | E40: 开始时间： | H40: 结束时间：
A41: 六、企业实际盘点情况说明
A42: （一）企业实际盘点人员
A43: 部门： | E43: 姓名： | H43: 岗位：
A44: 部门： | E44: 姓名： | H44: 岗位：
A45: 部门： | E45: 姓名： | H45: 岗位：
A46: 盘点人员共分 | D46: 组，其中：
A47: 第一组： | D47: 点数并报出型号、规格， | H47: 记录
A48: 第二组： | D48: 点数并报出型号、规格， | H48: 记录
A49: 第三组： | D49: 点数并报出型号、规格， | H49: 记录
A50: （二）特殊情况说明：
A51: 七、审计人员复盘记录：
A52: （一）抽盘样本确定方法
A53: 1．从会计明细账中抽取的方法
A54: 2．从实物资产中抽取样本的方法
A55: （二）盘点方法：
A56: 1．盘点人员共分 | D56: 组，其中：
A57: 2．第一组： | E57: 负责监盘的油气资产类别：
C58: 点数并报出型号、规格， | H58: 记录
A59: 第二组： | E59: 负责监盘的油气资产类别：
C60: 点数并报出型号、规格， | H60: 记录
A61: 第三组： | E61: 负责监盘的油气资产类别：
C62: 点数并报出型号、规格， | H62: 记录
A63: 3．监盘中特殊情况说明：
A64: 上述人员在盘点过程中，除 | F64: 外，自始至终未离开现场 是（ ） 否（ ）。
A65: （三）审计人员实际抽盘情况 | G65: 底稿索引：
A66: 1．探明矿区权益盘点说明：
A68: 2．未探明矿区权益盘点说明：
A70: 3．井及相关设施盘点说明：
A72: 八、盘点中异常情况说明：
A74: 九、复盘记录：（提示：应按照审计准则规定确定复盘的样本）
A75: 1、复盘人员： | F75: 复盘底稿记录索引：
A76: 2、复盘统计：
A77: 设备共有 | C77: 台（套），实施复盘共： | G77: 台（套），占
A78: 油气资产账面余额： | E78: 元，实施复盘： | H78: 元，占
A79: 倒退至资产负债表日是否存在尚未购入且未入账的资产：
A80: 倒退至资产负债表日分析是否存在已报废与处置的资产：
A81: 本次复盘的资产余额合计占资产负债表日的油气资产余额 | G81: %
A82: 3、计算复盘正确率：
A83: 复盘 | C83: 台（套）， 其中复盘正确的共 | G83: 种，占
A84: 复盘金额 | D84: 元， 其中复盘正确的共 | G84: 元，占
A85: 十、盘点结束工作说明：
A86: 盘点结束后的工作记录
A87: 1、对盘点工作的评价：
A88: 设备管理人员对设备保管业务的熟悉程度：
A89: 设备管理人员对盘点工作与复盘工作的负责态度：
A90: 对审计人员索取的资料配合程度：
A91: 2、索取由设备人员编制的〈盘点差异说明〉，并请其加盖公章：
A92: 3、请被审计单位的人员在〈设备复盘抽查情况表〉上签字：
G93: 监盘人员签字：
G94: 复核人员签字：

Sheet 折耗测算表（不含减值）H5-12
A1: 致同会计师事务所
A2: 油气资产折耗测算表
A3: =底稿目录!A2 -> 被审计单位： | F3: =底稿目录!A4 -> 编制人： | N3: =底稿目录!A6 -> 编制日期： | R3: 索引号： | S3: H5-12
A4: =底稿目录!A3 -> 截止日：202X年12月31日 | F4: =底稿目录!A5 -> 复核人： | N4: =底稿目录!A7 -> 复核日期： | R4: 页 次：
A5: 一、审计目标：油气资产以恰当的金额包括在财务报表中，与之相关的计价或分摊调整已恰当记录，相关披露已得到恰当计量和描述。
A6: 二、审计过程：
A7: 折耗期初： | B7: 45658 | C7: 折耗期末： | D7: 46022 | E7: 各列顺序请根据需要进行调整，行数请根据需要增加。非公式列输入数据时请使用“选择性粘贴-数值”。
A8: 油气资产类别 | B8: 油气资产编号 | C8: 油气资产名称 | D8: 管理部门 | E8: 原值 | F8: 累计折耗 | G8: 开始使用日期 | H8: 使用年限 | I8: 残值率 | J8: 账面月折耗额 | K8: 使用月限 | L8: 测算到期日 | M8: 已提折耗月份 | N8: 本期折耗月份 | O8: 测算月折耗 | P8: 当期折耗费用 | Q8: 月折耗额差异 | R8: 累计折耗费用 | S8: 累计折耗额差异
K9: =IF(H9=0,0,IF(RIGHT(H9,1)<>"年",H9*12,IF(LEN(H9)=3,VALUE(LEFT(H9,2))*12,IF(LEN(H9)=2,VALUE(LEFT(H9,1))*12,"??")))) -> 0 | L9: =IF(G9=0,0,DATE(YEAR(G9),MONTH(G9)+K9,DAY(G9)-1)) -> 0 | M9: =IF(G9=0,0,IF(L9>$D$7,DATEDIF(G9,MIN($D$7,L9),"m"),VALUE(DATEDIF(G9,MIN($D$7,L9),"m")+1))) -> 0 | N9: =IF(OR(G9=0,L9<$B$7),0,IF(AND(G9<$B$7,L9>$D$7),VALUE(DATEDIF($B$7,$D$7,"m")+1),IF(AND(G9<$B$7,L9<=$D$7),VALUE(DATEDIF($B$7,L9,"m")+1),IF(AND(G9>=$B$7,L9>$D$7),VALUE(DATEDIF(G9,$D$7,"m")),IF(AND(G9>=$B$7,L9<=$D$7),VALUE(DATEDIF(G9,L9,"m")+1),))))) -> 0 | O9: =IF(K9=0,0,ROUND(((1-I9)/K9)*E9,4)) -> 0 | P9: =ROUND(O9*N9,2) -> 0 | Q9: =ROUND(J9-O9,2) -> 0 | R9: =ROUND(O9*M9,2) -> 0 | S9: =ROUND(F9-R9,2) -> 0
K10: =IF(H10=0,0,IF(RIGHT(H10,1)<>"年",H10*12,IF(LEN(H10)=3,VALUE(LEFT(H10,2))*12,IF(LEN(H10)=2,VALUE(LEFT(H10,1))*12,"??")))) -> 0 | L10: =IF(G10=0,0,DATE(YEAR(G10),MONTH(G10)+K10,DAY(G10)-1)) -> 0 | M10: =IF(G10=0,0,IF(L10>$D$7,DATEDIF(G10,MIN($D$7,L10),"m"),VALUE(DATEDIF(G10,MIN($D$7,L10),"m")+1))) -> 0 | N10: =IF(OR(G10=0,L10<$B$7),0,IF(AND(G10<$B$7,L10>$D$7),VALUE(DATEDIF($B$7,$D$7,"m")+1),IF(AND(G10<$B$7,L10<=$D$7),VALUE(DATEDIF($B$7,L10,"m")+1),IF(AND(G10>=$B$7,L10>$D$7),VALUE(DATEDIF(G10,$D$7,"m")),IF(AND(G10>=$B$7,L10<=$D$7),VALUE(DATEDIF(G10,L10,"m")+1),))))) -> 0 | O10: =IF(K10=0,0,ROUND(((1-I10)/K10)*E10,4)) -> 0 | P10: =ROUND(O10*N10,2) -> 0 | Q10: =ROUND(J10-O10,2) -> 0 | R10: =ROUND(O10*M10,2) -> 0 | S10: =ROUND(F10-R10,2) -> 0
K11: =IF(H11=0,0,IF(RIGHT(H11,1)<>"年",H11*12,IF(LEN(H11)=3,VALUE(LEFT(H11,2))*12,IF(LEN(H11)=2,VALUE(LEFT(H11,1))*12,"??")))) -> 0 | L11: =IF(G11=0,0,DATE(YEAR(G11),MONTH(G11)+K11,DAY(G11)-1)) -> 0 | M11: =IF(G11=0,0,IF(L11>$D$7,DATEDIF(G11,MIN($D$7,L11),"m"),VALUE(DATEDIF(G11,MIN($D$7,L11),"m")+1))) -> 0 | N11: =IF(OR(G11=0,L11<$B$7),0,IF(AND(G11<$B$7,L11>$D$7),VALUE(DATEDIF($B$7,$D$7,"m")+1),IF(AND(G11<$B$7,L11<=$D$7),VALUE(DATEDIF($B$7,L11,"m")+1),IF(AND(G11>=$B$7,L11>$D$7),VALUE(DATEDIF(G11,$D$7,"m")),IF(AND(G11>=$B$7,L11<=$D$7),VALUE(DATEDIF(G11,L11,"m")+1),))))) -> 0 | O11: =IF(K11=0,0,ROUND(((1-I11)/K11)*E11,4)) -> 0 | P11: =ROUND(O11*N11,2) -> 0 | Q11: =ROUND(J11-O11,2) -> 0 | R11: =ROUND(O11*M11,2) -> 0 | S11: =ROUND(F11-R11,2) -> 0
K12: =IF(H12=0,0,IF(RIGHT(H12,1)<>"年",H12*12,IF(LEN(H12)=3,VALUE(LEFT(H12,2))*12,IF(LEN(H12)=2,VALUE(LEFT(H12,1))*12,"??")))) -> 0 | L12: =IF(G12=0,0,DATE(YEAR(G12),MONTH(G12)+K12,DAY(G12)-1)) -> 0 | M12: =IF(G12=0,0,IF(L12>$D$7,DATEDIF(G12,MIN($D$7,L12),"m"),VALUE(DATEDIF(G12,MIN($D$7,L12),"m")+1))) -> 0 | N12: =IF(OR(G12=0,L12<$B$7),0,IF(AND(G12<$B$7,L12>$D$7),VALUE(DATEDIF($B$7,$D$7,"m")+1),IF(AND(G12<$B$7,L12<=$D$7),VALUE(DATEDIF($B$7,L12,"m")+1),IF(AND(G12>=$B$7,L12>$D$7),VALUE(DATEDIF(G12,$D$7,"m")),IF(AND(G12>=$B$7,L12<=$D$7),VALUE(DATEDIF(G12,L12,"m")+1),))))) -> 0 | O12: =IF(K12=0,0,ROUND(((1-I12)/K12)*E12,4)) -> 0 | P12: =ROUND(O12*N12,2) -> 0 | Q12: =ROUND(J12-O12,2) -> 0 | R12: =ROUND(O12*M12,2) -> 0 | S12: =ROUND(F12-R12,2) -> 0
K13: =IF(H13=0,0,IF(RIGHT(H13,1)<>"年",H13*12,IF(LEN(H13)=3,VALUE(LEFT(H13,2))*12,IF(LEN(H13)=2,VALUE(LEFT(H13,1))*12,"??")))) -> 0 | L13: =IF(G13=0,0,DATE(YEAR(G13),MONTH(G13)+K13,DAY(G13)-1)) -> 0 | M13: =IF(G13=0,0,IF(L13>$D$7,DATEDIF(G13,MIN($D$7,L13),"m"),VALUE(DATEDIF(G13,MIN($D$7,L13),"m")+1))) -> 0 | N13: =IF(OR(G13=0,L13<$B$7),0,IF(AND(G13<$B$7,L13>$D$7),VALUE(DATEDIF($B$7,$D$7,"m")+1),IF(AND(G13<$B$7,L13<=$D$7),VALUE(DATEDIF($B$7,L13,"m")+1),IF(AND(G13>=$B$7,L13>$D$7),VALUE(DATEDIF(G13,$D$7,"m")),IF(AND(G13>=$B$7,L13<=$D$7),VALUE(DATEDIF(G13,L13,"m")+1),))))) -> 0 | O13: =IF(K13=0,0,ROUND(((1-I13)/K13)*E13,4)) -> 0 | P13: =ROUND(O13*N13,2) -> 0 | Q13: =ROUND(J13-O13,2) -> 0 | R13: =ROUND(O13*M13,2) -> 0 | S13: =ROUND(F13-R13,2) -> 0
K14: =IF(H14=0,0,IF(RIGHT(H14,1)<>"年",H14*12,IF(LEN(H14)=3,VALUE(LEFT(H14,2))*12,IF(LEN(H14)=2,VALUE(LEFT(H14,1))*12,"??")))) -> 0 | L14: =IF(G14=0,0,DATE(YEAR(G14),MONTH(G14)+K14,DAY(G14)-1)) -> 0 | M14: =IF(G14=0,0,IF(L14>$D$7,DATEDIF(G14,MIN($D$7,L14),"m"),VALUE(DATEDIF(G14,MIN($D$7,L14),"m")+1))) -> 0 | N14: =IF(OR(G14=0,L14<$B$7),0,IF(AND(G14<$B$7,L14>$D$7),VALUE(DATEDIF($B$7,$D$7,"m")+1),IF(AND(G14<$B$7,L14<=$D$7),VALUE(DATEDIF($B$7,L14,"m")+1),IF(AND(G14>=$B$7,L14>$D$7),VALUE(DATEDIF(G14,$D$7,"m")),IF(AND(G14>=$B$7,L14<=$D$7),VALUE(DATEDIF(G14,L14,"m")+1),))))) -> 0 | O14: =IF(K14=0,0,ROUND(((1-I14)/K14)*E14,4)) -> 0 | P14: =ROUND(O14*N14,2) -> 0 | Q14: =ROUND(J14-O14,2) -> 0 | R14: =ROUND(O14*M14,2) -> 0 | S14: =ROUND(F14-R14,2) -> 0
K15: =IF(H15=0,0,IF(RIGHT(H15,1)<>"年",H15*12,IF(LEN(H15)=3,VALUE(LEFT(H15,2))*12,IF(LEN(H15)=2,VALUE(LEFT(H15,1))*12,"??")))) -> 0 | L15: =IF(G15=0,0,DATE(YEAR(G15),MONTH(G15)+K15,DAY(G15)-1)) -> 0 | M15: =IF(G15=0,0,IF(L15>$D$7,DATEDIF(G15,MIN($D$7,L15),"m"),VALUE(DATEDIF(G15,MIN($D$7,L15),"m")+1))) -> 0 | N15: =IF(OR(G15=0,L15<$B$7),0,IF(AND(G15<$B$7,L15>$D$7),VALUE(DATEDIF($B$7,$D$7,"m")+1),IF(AND(G15<$B$7,L15<=$D$7),VALUE(DATEDIF($B$7,L15,"m")+1),IF(AND(G15>=$B$7,L15>$D$7),VALUE(DATEDIF(G15,$D$7,"m")),IF(AND(G15>=$B$7,L15<=$D$7),VALUE(DATEDIF(G15,L15,"m")+1),))))) -> 0 | O15: =IF(K15=0,0,ROUND(((1-I15)/K15)*E15,4)) -> 0 | P15: =ROUND(O15*N15,2) -> 0 | Q15: =ROUND(J15-O15,2) -> 0 | R15: =ROUND(O15*M15,2) -> 0 | S15: =ROUND(F15-R15,2) -> 0
K16: =IF(H16=0,0,IF(RIGHT(H16,1)<>"年",H16*12,IF(LEN(H16)=3,VALUE(LEFT(H16,2))*12,IF(LEN(H16)=2,VALUE(LEFT(H16,1))*12,"??")))) -> 0 | L16: =IF(G16=0,0,DATE(YEAR(G16),MONTH(G16)+K16,DAY(G16)-1)) -> 0 | M16: =IF(G16=0,0,IF(L16>$D$7,DATEDIF(G16,MIN($D$7,L16),"m"),VALUE(DATEDIF(G16,MIN($D$7,L16),"m")+1))) -> 0 | N16: =IF(OR(G16=0,L16<$B$7),0,IF(AND(G16<$B$7,L16>$D$7),VALUE(DATEDIF($B$7,$D$7,"m")+1),IF(AND(G16<$B$7,L16<=$D$7),VALUE(DATEDIF($B$7,L16,"m")+1),IF(AND(G16>=$B$7,L16>$D$7),VALUE(DATEDIF(G16,$D$7,"m")),IF(AND(G16>=$B$7,L16<=$D$7),VALUE(DATEDIF(G16,L16,"m")+1),))))) -> 0 | O16: =IF(K16=0,0,ROUND(((1-I16)/K16)*E16,4)) -> 0 | P16: =ROUND(O16*N16,2) -> 0 | Q16: =ROUND(J16-O16,2) -> 0 | R16: =ROUND(O16*M16,2) -> 0 | S16: =ROUND(F16-R16,2) -> 0
K17: =IF(H17=0,0,IF(RIGHT(H17,1)<>"年",H17*12,IF(LEN(H17)=3,VALUE(LEFT(H17,2))*12,IF(LEN(H17)=2,VALUE(LEFT(H17,1))*12,"??")))) -> 0 | L17: =IF(G17=0,0,DATE(YEAR(G17),MONTH(G17)+K17,DAY(G17)-1)) -> 0 | M17: =IF(G17=0,0,IF(L17>$D$7,DATEDIF(G17,MIN($D$7,L17),"m"),VALUE(DATEDIF(G17,MIN($D$7,L17),"m")+1))) -> 0 | N17: =IF(OR(G17=0,L17<$B$7),0,IF(AND(G17<$B$7,L17>$D$7),VALUE(DATEDIF($B$7,$D$7,"m")+1),IF(AND(G17<$B$7,L17<=$D$7),VALUE(DATEDIF($B$7,L17,"m")+1),IF(AND(G17>=$B$7,L17>$D$7),VALUE(DATEDIF(G17,$D$7,"m")),IF(AND(G17>=$B$7,L17<=$D$7),VALUE(DATEDIF(G17,L17,"m")+1),))))) -> 0 | O17: =IF(K17=0,0,ROUND(((1-I17)/K17)*E17,4)) -> 0 | P17: =ROUND(O17*N17,2) -> 0 | Q17: =ROUND(J17-O17,2) -> 0 | R17: =ROUND(O17*M17,2) -> 0 | S17: =ROUND(F17-R17,2) -> 0
K18: =IF(H18=0,0,IF(RIGHT(H18,1)<>"年",H18*12,IF(LEN(H18)=3,VALUE(LEFT(H18,2))*12,IF(LEN(H18)=2,VALUE(LEFT(H18,1))*12,"??")))) -> 0 | L18: =IF(G18=0,0,DATE(YEAR(G18),MONTH(G18)+K18,DAY(G18)-1)) -> 0 | M18: =IF(G18=0,0,IF(L18>$D$7,DATEDIF(G18,MIN($D$7,L18),"m"),VALUE(DATEDIF(G18,MIN($D$7,L18),"m")+1))) -> 0 | N18: =IF(OR(G18=0,L18<$B$7),0,IF(AND(G18<$B$7,L18>$D$7),VALUE(DATEDIF($B$7,$D$7,"m")+1),IF(AND(G18<$B$7,L18<=$D$7),VALUE(DATEDIF($B$7,L18,"m")+1),IF(AND(G18>=$B$7,L18>$D$7),VALUE(DATEDIF(G18,$D$7,"m")),IF(AND(G18>=$B$7,L18<=$D$7),VALUE(DATEDIF(G18,L18,"m")+1),))))) -> 0 | O18: =IF(K18=0,0,ROUND(((1-I18)/K18)*E18,4)) -> 0 | P18: =ROUND(O18*N18,2) -> 0 | Q18: =ROUND(J18-O18,2) -> 0 | R18: =ROUND(O18*M18,2) -> 0 | S18: =ROUND(F18-R18,2) -> 0
K19: =IF(H19=0,0,IF(RIGHT(H19,1)<>"年",H19*12,IF(LEN(H19)=3,VALUE(LEFT(H19,2))*12,IF(LEN(H19)=2,VALUE(LEFT(H19,1))*12,"??")))) -> 0 | L19: =IF(G19=0,0,DATE(YEAR(G19),MONTH(G19)+K19,DAY(G19)-1)) -> 0 | M19: =IF(G19=0,0,IF(L19>$D$7,DATEDIF(G19,MIN($D$7,L19),"m"),VALUE(DATEDIF(G19,MIN($D$7,L19),"m")+1))) -> 0 | N19: =IF(OR(G19=0,L19<$B$7),0,IF(AND(G19<$B$7,L19>$D$7),VALUE(DATEDIF($B$7,$D$7,"m")+1),IF(AND(G19<$B$7,L19<=$D$7),VALUE(DATEDIF($B$7,L19,"m")+1),IF(AND(G19>=$B$7,L19>$D$7),VALUE(DATEDIF(G19,$D$7,"m")),IF(AND(G19>=$B$7,L19<=$D$7),VALUE(DATEDIF(G19,L19,"m")+1),))))) -> 0 | O19: =IF(K19=0,0,ROUND(((1-I19)/K19)*E19,4)) -> 0 | P19: =ROUND(O19*N19,2) -> 0 | Q19: =ROUND(J19-O19,2) -> 0 | R19: =ROUND(O19*M19,2) -> 0 | S19: =ROUND(F19-R19,2) -> 0
K20: =IF(H20=0,0,IF(RIGHT(H20,1)<>"年",H20*12,IF(LEN(H20)=3,VALUE(LEFT(H20,2))*12,IF(LEN(H20)=2,VALUE(LEFT(H20,1))*12,"??")))) -> 0 | L20: =IF(G20=0,0,DATE(YEAR(G20),MONTH(G20)+K20,DAY(G20)-1)) -> 0 | M20: =IF(G20=0,0,IF(L20>$D$7,DATEDIF(G20,MIN($D$7,L20),"m"),VALUE(DATEDIF(G20,MIN($D$7,L20),"m")+1))) -> 0 | N20: =IF(OR(G20=0,L20<$B$7),0,IF(AND(G20<$B$7,L20>$D$7),VALUE(DATEDIF($B$7,$D$7,"m")+1),IF(AND(G20<$B$7,L20<=$D$7),VALUE(DATEDIF($B$7,L20,"m")+1),IF(AND(G20>=$B$7,L20>$D$7),VALUE(DATEDIF(G20,$D$7,"m")),IF(AND(G20>=$B$7,L20<=$D$7),VALUE(DATEDIF(G20,L20,"m")+1),))))) -> 0 | O20: =IF(K20=0,0,ROUND(((1-I20)/K20)*E20,4)) -> 0 | P20: =ROUND(O20*N20,2) -> 0 | Q20: =ROUND(J20-O20,2) -> 0 | R20: =ROUND(O20*M20,2) -> 0 | S20: =ROUND(F20-R20,2) -> 0
... K33: =IF(H33=0,0,IF(RIGHT(H33,1)<>"年",H33*12,IF(LEN(H33)=3,VALUE(LEFT(H33,2))*12,IF(LEN(H33)=2,VALUE(LEFT(H33,1))*12,"??")))) -> 0 | L33: =IF(G33=0,0,DATE(YEAR(G33),MONTH(G33)+K33,DAY(G33)-1)) -> 0 | M33: =IF(G33=0,0,IF(L33>$D$7,DATEDIF(G33,MIN($D$7,L33),"m"),VALUE(DATEDIF(G33,MIN($D$7,L33),"m")+1))) -> 0 | N33: =IF(OR(G33=0,L33<$B$7),0,IF(AND(G33<$B$7,L33>$D$7),VALUE(DATEDIF($B$7,$D$7,"m")+1),IF(AND(G33<$B$7,L33<=$D$7),VALUE(DATEDIF($B$7,L33,"m")+1),IF(AND(G33>=$B$7,L33>$D$7),VALUE(DATEDIF(G33,$D$7,"m")),IF(AND(G33>=$B$7,L33<=$D$7),VALUE(DATEDIF(G33,L33,"m")+1),))))) -> 0 | O33: =IF(K33=0,0,ROUND(((1-I33)/K33)*E33,4)) -> 0 | P33: =ROUND(O33*N33,2) -> 0 | Q33: =ROUND(J33-O33,2) -> 0 | R33: =ROUND(O33*M33,2) -> 0 | S33: =ROUND(F33-R33,2) -> 0
A34: 合计 | E34: =SUM(E9:E33) -> 0 | F34: =SUM(F9:F33) -> 0 | J34: =SUM(J9:J33) -> 0 | O34: =SUM(O9:O33) -> 0 | P34: =SUM(P9:P33) -> 0 | Q34: =SUM(Q9:Q33) -> 0 | R34: =SUM(R9:R33) -> 0 | S34: =SUM(S9:S33) -> 0
A35: 三、审计说明：
A37: 四、审计结论：

Sheet 折耗测算表（含减值）H5-12
A1: 致同会计师事务所
A2: 油气资产折耗测算表
A3: =底稿目录!A2 -> 被审计单位： | F3: =底稿目录!A4 -> 编制人： | Q3: =底稿目录!A6 -> 编制日期： | X3: 索引号： | Y3: H5-12
A4: =底稿目录!A3 -> 截止日：202X年12月31日 | F4: =底稿目录!A5 -> 复核人： | Q4: =底稿目录!A7 -> 复核日期： | X4: 页 次：
A5: 一、审计目标：油气资产以恰当的金额包括在财务报表中，与之相关的计价或分摊调整已恰当记录，相关披露已得到恰当计量和描述。
A6: 二、审计过程：
A7: 折耗期初： | B7: 45658 | C7: 折耗期末： | D7: 46022 | E7: 计提减值准备日期： | F7: 46022 | G7: 各列顺序请根据需要进行调整，行数请根据需要增加。非公式列输入数据时请使用“选择性粘贴-数值”。
A8: 油气资产类别 | B8: 油气资产编号 | C8: 油气资产名称 | D8: 管理部门 | E8: 原值 | F8: 累计折耗 | G8: 减值准备 | H8: 开始使用日期 | I8: 使用年限 | J8: 残值率 | K8: 账面月折耗额 | L8: 使用月限 | M8: 测算到期日 | N8: 已提折耗月份 | O8: 截止计提减值准备日计提月份 | P8: 本期折耗月份 | Q8: 本期折耗月份（减值前） | R8: 本期折耗月份（减值后） | S8: 计提减值准备前月折耗 | T8: 计提减值准备前累计折耗 | U8: 计提减值准备后月折耗 | V8: 当期折耗费用 | W8: 月折耗额差异 | X8: 累计折耗费用 | Y8: 累计折耗额差异
L9: =IF(I9=0,0,IF(RIGHT(I9,1)<>"年",I9*12,IF(LEN(I9)=3,VALUE(LEFT(I9,2))*12,IF(LEN(I9)=2,VALUE(LEFT(I9,1))*12,"??")))) -> 0 | M9: =IF(H9=0,0,DATE(YEAR(H9),MONTH(H9)+L9,DAY(H9)-1)) -> 0 | N9: =IF(H9=0,0,IF(M9>$D$7,DATEDIF(H9,MIN($D$7,M9),"m"),VALUE(DATEDIF(H9,MIN($D$7,M9),"m")+1))) -> 0 | O9: =IF(H9=0,0,DATEDIF(H9,$F$7,"m")) -> 0 | P9: =IF(OR(H9=0,M9<$B$7),0,IF(AND(H9<$B$7,M9>$D$7),VALUE(DATEDIF($B$7,$D$7,"m")+1),IF(AND(H9<$B$7,M9<=$D$7),VALUE(DATEDIF($B$7,M9,"m")+1),IF(AND(H9>=$B$7,M9>$D$7),VALUE(DATEDIF(H9,$D$7,"m")),IF(AND(H9>=$B$7,M9<=$D$7),VALUE(DATEDIF(H9,M9,"m")+1),))))) -> 0 | Q9: =P9-R9 -> 0 | R9: =IF(H9=0,0,IF($F$7<$B$7,P9,DATEDIF(MAX(H9,$F$7),MIN(M9,$D$7),"m"))) -> 0 | S9: =IF(L9=0,0,ROUND(((1-J9)/L9)*E9,4)) -> 0 | T9: =ROUND(S9*O9,2) -> 0 | U9: =IF((E9*(1-J9)-T9-G9)>0,(E9*(1-J9)-T9-G9)/(L9-O9),0) -> 0 | V9: =ROUND(S9*Q9,2)+ROUND(U9*R9,2) -> 0 | W9: =ROUND(K9-U9,2) -> 0 | X9: =ROUND(S9*O9,2)+ROUND(U9*(N9-O9),2) -> 0 | Y9: =ROUND(F9-X9,2) -> 0
L10: =IF(I10=0,0,IF(RIGHT(I10,1)<>"年",I10*12,IF(LEN(I10)=3,VALUE(LEFT(I10,2))*12,IF(LEN(I10)=2,VALUE(LEFT(I10,1))*12,"??")))) -> 0 | M10: =IF(H10=0,0,DATE(YEAR(H10),MONTH(H10)+L10,DAY(H10)-1)) -> 0 | N10: =IF(H10=0,0,IF(M10>$D$7,DATEDIF(H10,MIN($D$7,M10),"m"),VALUE(DATEDIF(H10,MIN($D$7,M10),"m")+1))) -> 0 | O10: =IF(H10=0,0,DATEDIF(H10,$F$7,"m")) -> 0 | P10: =IF(OR(H10=0,M10<$B$7),0,IF(AND(H10<$B$7,M10>$D$7),VALUE(DATEDIF($B$7,$D$7,"m")+1),IF(AND(H10<$B$7,M10<=$D$7),VALUE(DATEDIF($B$7,M10,"m")+1),IF(AND(H10>=$B$7,M10>$D$7),VALUE(DATEDIF(H10,$D$7,"m")),IF(AND(H10>=$B$7,M10<=$D$7),VALUE(DATEDIF(H10,M10,"m")+1),))))) -> 0 | Q10: =P10-R10 -> 0 | R10: =IF(H10=0,0,IF($F$7<$B$7,P10,DATEDIF(MAX(H10,$F$7),MIN(M10,$D$7),"m"))) -> 0 | S10: =IF(L10=0,0,ROUND(((1-J10)/L10)*E10,4)) -> 0 | T10: =ROUND(S10*O10,2) -> 0 | U10: =IF((E10*(1-J10)-T10-G10)>0,(E10*(1-J10)-T10-G10)/(L10-O10),0) -> 0 | V10: =ROUND(S10*Q10,2)+ROUND(U10*R10,2) -> 0 | W10: =ROUND(K10-U10,2) -> 0 | X10: =ROUND(S10*O10,2)+ROUND(U10*(N10-O10),2) -> 0 | Y10: =ROUND(F10-X10,2) -> 0
L11: =IF(I11=0,0,IF(RIGHT(I11,1)<>"年",I11*12,IF(LEN(I11)=3,VALUE(LEFT(I11,2))*12,IF(LEN(I11)=2,VALUE(LEFT(I11,1))*12,"??")))) -> 0 | M11: =IF(H11=0,0,DATE(YEAR(H11),MONTH(H11)+L11,DAY(H11)-1)) -> 0 | N11: =IF(H11=0,0,IF(M11>$D$7,DATEDIF(H11,MIN($D$7,M11),"m"),VALUE(DATEDIF(H11,MIN($D$7,M11),"m")+1))) -> 0 | O11: =IF(H11=0,0,DATEDIF(H11,$F$7,"m")) -> 0 | P11: =IF(OR(H11=0,M11<$B$7),0,IF(AND(H11<$B$7,M11>$D$7),VALUE(DATEDIF($B$7,$D$7,"m")+1),IF(AND(H11<$B$7,M11<=$D$7),VALUE(DATEDIF($B$7,M11,"m")+1),IF(AND(H11>=$B$7,M11>$D$7),VALUE(DATEDIF(H11,$D$7,"m")),IF(AND(H11>=$B$7,M11<=$D$7),VALUE(DATEDIF(H11,M11,"m")+1),))))) -> 0 | Q11: =P11-R11 -> 0 | R11: =IF(H11=0,0,IF($F$7<$B$7,P11,DATEDIF(MAX(H11,$F$7),MIN(M11,$D$7),"m"))) -> 0 | S11: =IF(L11=0,0,ROUND(((1-J11)/L11)*E11,4)) -> 0 | T11: =ROUND(S11*O11,2) -> 0 | U11: =IF((E11*(1-J11)-T11-G11)>0,(E11*(1-J11)-T11-G11)/(L11-O11),0) -> 0 | V11: =ROUND(S11*Q11,2)+ROUND(U11*R11,2) -> 0 | W11: =ROUND(K11-U11,2) -> 0 | X11: =ROUND(S11*O11,2)+ROUND(U11*(N11-O11),2) -> 0 | Y11: =ROUND(F11-X11,2) -> 0
L12: =IF(I12=0,0,IF(RIGHT(I12,1)<>"年",I12*12,IF(LEN(I12)=3,VALUE(LEFT(I12,2))*12,IF(LEN(I12)=2,VALUE(LEFT(I12,1))*12,"??")))) -> 0 | M12: =IF(H12=0,0,DATE(YEAR(H12),MONTH(H12)+L12,DAY(H12)-1)) -> 0 | N12: =IF(H12=0,0,IF(M12>$D$7,DATEDIF(H12,MIN($D$7,M12),"m"),VALUE(DATEDIF(H12,MIN($D$7,M12),"m")+1))) -> 0 | O12: =IF(H12=0,0,DATEDIF(H12,$F$7,"m")) -> 0 | P12: =IF(OR(H12=0,M12<$B$7),0,IF(AND(H12<$B$7,M12>$D$7),VALUE(DATEDIF($B$7,$D$7,"m")+1),IF(AND(H12<$B$7,M12<=$D$7),VALUE(DATEDIF($B$7,M12,"m")+1),IF(AND(H12>=$B$7,M12>$D$7),VALUE(DATEDIF(H12,$D$7,"m")),IF(AND(H12>=$B$7,M12<=$D$7),VALUE(DATEDIF(H12,M12,"m")+1),))))) -> 0 | Q12: =P12-R12 -> 0 | R12: =IF(H12=0,0,IF($F$7<$B$7,P12,DATEDIF(MAX(H12,$F$7),MIN(M12,$D$7),"m"))) -> 0 | S12: =IF(L12=0,0,ROUND(((1-J12)/L12)*E12,4)) -> 0 | T12: =ROUND(S12*O12,2) -> 0 | U12: =IF((E12*(1-J12)-T12-G12)>0,(E12*(1-J12)-T12-G12)/(L12-O12),0) -> 0 | V12: =ROUND(S12*Q12,2)+ROUND(U12*R12,2) -> 0 | W12: =ROUND(K12-U12,2) -> 0 | X12: =ROUND(S12*O12,2)+ROUND(U12*(N12-O12),2) -> 0 | Y12: =ROUND(F12-X12,2) -> 0
L13: =IF(I13=0,0,IF(RIGHT(I13,1)<>"年",I13*12,IF(LEN(I13)=3,VALUE(LEFT(I13,2))*12,IF(LEN(I13)=2,VALUE(LEFT(I13,1))*12,"??")))) -> 0 | M13: =IF(H13=0,0,DATE(YEAR(H13),MONTH(H13)+L13,DAY(H13)-1)) -> 0 | N13: =IF(H13=0,0,IF(M13>$D$7,DATEDIF(H13,MIN($D$7,M13),"m"),VALUE(DATEDIF(H13,MIN($D$7,M13),"m")+1))) -> 0 | O13: =IF(H13=0,0,DATEDIF(H13,$F$7,"m")) -> 0 | P13: =IF(OR(H13=0,M13<$B$7),0,IF(AND(H13<$B$7,M13>$D$7),VALUE(DATEDIF($B$7,$D$7,"m")+1),IF(AND(H13<$B$7,M13<=$D$7),VALUE(DATEDIF($B$7,M13,"m")+1),IF(AND(H13>=$B$7,M13>$D$7),VALUE(DATEDIF(H13,$D$7,"m")),IF(AND(H13>=$B$7,M13<=$D$7),VALUE(DATEDIF(H13,M13,"m")+1),))))) -> 0 | Q13: =P13-R13 -> 0 | R13: =IF(H13=0,0,IF($F$7<$B$7,P13,DATEDIF(MAX(H13,$F$7),MIN(M13,$D$7),"m"))) -> 0 | S13: =IF(L13=0,0,ROUND(((1-J13)/L13)*E13,4)) -> 0 | T13: =ROUND(S13*O13,2) -> 0 | U13: =IF((E13*(1-J13)-T13-G13)>0,(E13*(1-J13)-T13-G13)/(L13-O13),0) -> 0 | V13: =ROUND(S13*Q13,2)+ROUND(U13*R13,2) -> 0 | W13: =ROUND(K13-U13,2) -> 0 | X13: =ROUND(S13*O13,2)+ROUND(U13*(N13-O13),2) -> 0 | Y13: =ROUND(F13-X13,2) -> 0
L14: =IF(I14=0,0,IF(RIGHT(I14,1)<>"年",I14*12,IF(LEN(I14)=3,VALUE(LEFT(I14,2))*12,IF(LEN(I14)=2,VALUE(LEFT(I14,1))*12,"??")))) -> 0 | M14: =IF(H14=0,0,DATE(YEAR(H14),MONTH(H14)+L14,DAY(H14)-1)) -> 0 | N14: =IF(H14=0,0,IF(M14>$D$7,DATEDIF(H14,MIN($D$7,M14),"m"),VALUE(DATEDIF(H14,MIN($D$7,M14),"m")+1))) -> 0 | O14: =IF(H14=0,0,DATEDIF(H14,$F$7,"m")) -> 0 | P14: =IF(OR(H14=0,M14<$B$7),0,IF(AND(H14<$B$7,M14>$D$7),VALUE(DATEDIF($B$7,$D$7,"m")+1),IF(AND(H14<$B$7,M14<=$D$7),VALUE(DATEDIF($B$7,M14,"m")+1),IF(AND(H14>=$B$7,M14>$D$7),VALUE(DATEDIF(H14,$D$7,"m")),IF(AND(H14>=$B$7,M14<=$D$7),VALUE(DATEDIF(H14,M14,"m")+1),))))) -> 0 | Q14: =P14-R14 -> 0 | R14: =IF(H14=0,0,IF($F$7<$B$7,P14,DATEDIF(MAX(H14,$F$7),MIN(M14,$D$7),"m"))) -> 0 | S14: =IF(L14=0,0,ROUND(((1-J14)/L14)*E14,4)) -> 0 | T14: =ROUND(S14*O14,2) -> 0 | U14: =IF((E14*(1-J14)-T14-G14)>0,(E14*(1-J14)-T14-G14)/(L14-O14),0) -> 0 | V14: =ROUND(S14*Q14,2)+ROUND(U14*R14,2) -> 0 | W14: =ROUND(K14-U14,2) -> 0 | X14: =ROUND(S14*O14,2)+ROUND(U14*(N14-O14),2) -> 0 | Y14: =ROUND(F14-X14,2) -> 0
L15: =IF(I15=0,0,IF(RIGHT(I15,1)<>"年",I15*12,IF(LEN(I15)=3,VALUE(LEFT(I15,2))*12,IF(LEN(I15)=2,VALUE(LEFT(I15,1))*12,"??")))) -> 0 | M15: =IF(H15=0,0,DATE(YEAR(H15),MONTH(H15)+L15,DAY(H15)-1)) -> 0 | N15: =IF(H15=0,0,IF(M15>$D$7,DATEDIF(H15,MIN($D$7,M15),"m"),VALUE(DATEDIF(H15,MIN($D$7,M15),"m")+1))) -> 0 | O15: =IF(H15=0,0,DATEDIF(H15,$F$7,"m")) -> 0 | P15: =IF(OR(H15=0,M15<$B$7),0,IF(AND(H15<$B$7,M15>$D$7),VALUE(DATEDIF($B$7,$D$7,"m")+1),IF(AND(H15<$B$7,M15<=$D$7),VALUE(DATEDIF($B$7,M15,"m")+1),IF(AND(H15>=$B$7,M15>$D$7),VALUE(DATEDIF(H15,$D$7,"m")),IF(AND(H15>=$B$7,M15<=$D$7),VALUE(DATEDIF(H15,M15,"m")+1),))))) -> 0 | Q15: =P15-R15 -> 0 | R15: =IF(H15=0,0,IF($F$7<$B$7,P15,DATEDIF(MAX(H15,$F$7),MIN(M15,$D$7),"m"))) -> 0 | S15: =IF(L15=0,0,ROUND(((1-J15)/L15)*E15,4)) -> 0 | T15: =ROUND(S15*O15,2) -> 0 | U15: =IF((E15*(1-J15)-T15-G15)>0,(E15*(1-J15)-T15-G15)/(L15-O15),0) -> 0 | V15: =ROUND(S15*Q15,2)+ROUND(U15*R15,2) -> 0 | W15: =ROUND(K15-U15,2) -> 0 | X15: =ROUND(S15*O15,2)+ROUND(U15*(N15-O15),2) -> 0 | Y15: =ROUND(F15-X15,2) -> 0
L16: =IF(I16=0,0,IF(RIGHT(I16,1)<>"年",I16*12,IF(LEN(I16)=3,VALUE(LEFT(I16,2))*12,IF(LEN(I16)=2,VALUE(LEFT(I16,1))*12,"??")))) -> 0 | M16: =IF(H16=0,0,DATE(YEAR(H16),MONTH(H16)+L16,DAY(H16)-1)) -> 0 | N16: =IF(H16=0,0,IF(M16>$D$7,DATEDIF(H16,MIN($D$7,M16),"m"),VALUE(DATEDIF(H16,MIN($D$7,M16),"m")+1))) -> 0 | O16: =IF(H16=0,0,DATEDIF(H16,$F$7,"m")) -> 0 | P16: =IF(OR(H16=0,M16<$B$7),0,IF(AND(H16<$B$7,M16>$D$7),VALUE(DATEDIF($B$7,$D$7,"m")+1),IF(AND(H16<$B$7,M16<=$D$7),VALUE(DATEDIF($B$7,M16,"m")+1),IF(AND(H16>=$B$7,M16>$D$7),VALUE(DATEDIF(H16,$D$7,"m")),IF(AND(H16>=$B$7,M16<=$D$7),VALUE(DATEDIF(H16,M16,"m")+1),))))) -> 0 | Q16: =P16-R16 -> 0 | R16: =IF(H16=0,0,IF($F$7<$B$7,P16,DATEDIF(MAX(H16,$F$7),MIN(M16,$D$7),"m"))) -> 0 | S16: =IF(L16=0,0,ROUND(((1-J16)/L16)*E16,4)) -> 0 | T16: =ROUND(S16*O16,2) -> 0 | U16: =IF((E16*(1-J16)-T16-G16)>0,(E16*(1-J16)-T16-G16)/(L16-O16),0) -> 0 | V16: =ROUND(S16*Q16,2)+ROUND(U16*R16,2) -> 0 | W16: =ROUND(K16-U16,2) -> 0 | X16: =ROUND(S16*O16,2)+ROUND(U16*(N16-O16),2) -> 0 | Y16: =ROUND(F16-X16,2) -> 0
L17: =IF(I17=0,0,IF(RIGHT(I17,1)<>"年",I17*12,IF(LEN(I17)=3,VALUE(LEFT(I17,2))*12,IF(LEN(I17)=2,VALUE(LEFT(I17,1))*12,"??")))) -> 0 | M17: =IF(H17=0,0,DATE(YEAR(H17),MONTH(H17)+L17,DAY(H17)-1)) -> 0 | N17: =IF(H17=0,0,IF(M17>$D$7,DATEDIF(H17,MIN($D$7,M17),"m"),VALUE(DATEDIF(H17,MIN($D$7,M17),"m")+1))) -> 0 | O17: =IF(H17=0,0,DATEDIF(H17,$F$7,"m")) -> 0 | P17: =IF(OR(H17=0,M17<$B$7),0,IF(AND(H17<$B$7,M17>$D$7),VALUE(DATEDIF($B$7,$D$7,"m")+1),IF(AND(H17<$B$7,M17<=$D$7),VALUE(DATEDIF($B$7,M17,"m")+1),IF(AND(H17>=$B$7,M17>$D$7),VALUE(DATEDIF(H17,$D$7,"m")),IF(AND(H17>=$B$7,M17<=$D$7),VALUE(DATEDIF(H17,M17,"m")+1),))))) -> 0 | Q17: =P17-R17 -> 0 | R17: =IF(H17=0,0,IF($F$7<$B$7,P17,DATEDIF(MAX(H17,$F$7),MIN(M17,$D$7),"m"))) -> 0 | S17: =IF(L17=0,0,ROUND(((1-J17)/L17)*E17,4)) -> 0 | T17: =ROUND(S17*O17,2) -> 0 | U17: =IF((E17*(1-J17)-T17-G17)>0,(E17*(1-J17)-T17-G17)/(L17-O17),0) -> 0 | V17: =ROUND(S17*Q17,2)+ROUND(U17*R17,2) -> 0 | W17: =ROUND(K17-U17,2) -> 0 | X17: =ROUND(S17*O17,2)+ROUND(U17*(N17-O17),2) -> 0 | Y17: =ROUND(F17-X17,2) -> 0
L18: =IF(I18=0,0,IF(RIGHT(I18,1)<>"年",I18*12,IF(LEN(I18)=3,VALUE(LEFT(I18,2))*12,IF(LEN(I18)=2,VALUE(LEFT(I18,1))*12,"??")))) -> 0 | M18: =IF(H18=0,0,DATE(YEAR(H18),MONTH(H18)+L18,DAY(H18)-1)) -> 0 | N18: =IF(H18=0,0,IF(M18>$D$7,DATEDIF(H18,MIN($D$7,M18),"m"),VALUE(DATEDIF(H18,MIN($D$7,M18),"m")+1))) -> 0 | O18: =IF(H18=0,0,DATEDIF(H18,$F$7,"m")) -> 0 | P18: =IF(OR(H18=0,M18<$B$7),0,IF(AND(H18<$B$7,M18>$D$7),VALUE(DATEDIF($B$7,$D$7,"m")+1),IF(AND(H18<$B$7,M18<=$D$7),VALUE(DATEDIF($B$7,M18,"m")+1),IF(AND(H18>=$B$7,M18>$D$7),VALUE(DATEDIF(H18,$D$7,"m")),IF(AND(H18>=$B$7,M18<=$D$7),VALUE(DATEDIF(H18,M18,"m")+1),))))) -> 0 | Q18: =P18-R18 -> 0 | R18: =IF(H18=0,0,IF($F$7<$B$7,P18,DATEDIF(MAX(H18,$F$7),MIN(M18,$D$7),"m"))) -> 0 | S18: =IF(L18=0,0,ROUND(((1-J18)/L18)*E18,4)) -> 0 | T18: =ROUND(S18*O18,2) -> 0 | U18: =IF((E18*(1-J18)-T18-G18)>0,(E18*(1-J18)-T18-G18)/(L18-O18),0) -> 0 | V18: =ROUND(S18*Q18,2)+ROUND(U18*R18,2) -> 0 | W18: =ROUND(K18-U18,2) -> 0 | X18: =ROUND(S18*O18,2)+ROUND(U18*(N18-O18),2) -> 0 | Y18: =ROUND(F18-X18,2) -> 0
L19: =IF(I19=0,0,IF(RIGHT(I19,1)<>"年",I19*12,IF(LEN(I19)=3,VALUE(LEFT(I19,2))*12,IF(LEN(I19)=2,VALUE(LEFT(I19,1))*12,"??")))) -> 0 | M19: =IF(H19=0,0,DATE(YEAR(H19),MONTH(H19)+L19,DAY(H19)-1)) -> 0 | N19: =IF(H19=0,0,IF(M19>$D$7,DATEDIF(H19,MIN($D$7,M19),"m"),VALUE(DATEDIF(H19,MIN($D$7,M19),"m")+1))) -> 0 | O19: =IF(H19=0,0,DATEDIF(H19,$F$7,"m")) -> 0 | P19: =IF(OR(H19=0,M19<$B$7),0,IF(AND(H19<$B$7,M19>$D$7),VALUE(DATEDIF($B$7,$D$7,"m")+1),IF(AND(H19<$B$7,M19<=$D$7),VALUE(DATEDIF($B$7,M19,"m")+1),IF(AND(H19>=$B$7,M19>$D$7),VALUE(DATEDIF(H19,$D$7,"m")),IF(AND(H19>=$B$7,M19<=$D$7),VALUE(DATEDIF(H19,M19,"m")+1),))))) -> 0 | Q19: =P19-R19 -> 0 | R19: =IF(H19=0,0,IF($F$7<$B$7,P19,DATEDIF(MAX(H19,$F$7),MIN(M19,$D$7),"m"))) -> 0 | S19: =IF(L19=0,0,ROUND(((1-J19)/L19)*E19,4)) -> 0 | T19: =ROUND(S19*O19,2) -> 0 | U19: =IF((E19*(1-J19)-T19-G19)>0,(E19*(1-J19)-T19-G19)/(L19-O19),0) -> 0 | V19: =ROUND(S19*Q19,2)+ROUND(U19*R19,2) -> 0 | W19: =ROUND(K19-U19,2) -> 0 | X19: =ROUND(S19*O19,2)+ROUND(U19*(N19-O19),2) -> 0 | Y19: =ROUND(F19-X19,2) -> 0
L20: =IF(I20=0,0,IF(RIGHT(I20,1)<>"年",I20*12,IF(LEN(I20)=3,VALUE(LEFT(I20,2))*12,IF(LEN(I20)=2,VALUE(LEFT(I20,1))*12,"??")))) -> 0 | M20: =IF(H20=0,0,DATE(YEAR(H20),MONTH(H20)+L20,DAY(H20)-1)) -> 0 | N20: =IF(H20=0,0,IF(M20>$D$7,DATEDIF(H20,MIN($D$7,M20),"m"),VALUE(DATEDIF(H20,MIN($D$7,M20),"m")+1))) -> 0 | O20: =IF(H20=0,0,DATEDIF(H20,$F$7,"m")) -> 0 | P20: =IF(OR(H20=0,M20<$B$7),0,IF(AND(H20<$B$7,M20>$D$7),VALUE(DATEDIF($B$7,$D$7,"m")+1),IF(AND(H20<$B$7,M20<=$D$7),VALUE(DATEDIF($B$7,M20,"m")+1),IF(AND(H20>=$B$7,M20>$D$7),VALUE(DATEDIF(H20,$D$7,"m")),IF(AND(H20>=$B$7,M20<=$D$7),VALUE(DATEDIF(H20,M20,"m")+1),))))) -> 0 | Q20: =P20-R20 -> 0 | R20: =IF(H20=0,0,IF($F$7<$B$7,P20,DATEDIF(MAX(H20,$F$7),MIN(M20,$D$7),"m"))) -> 0 | S20: =IF(L20=0,0,ROUND(((1-J20)/L20)*E20,4)) -> 0 | T20: =ROUND(S20*O20,2) -> 0 | U20: =IF((E20*(1-J20)-T20-G20)>0,(E20*(1-J20)-T20-G20)/(L20-O20),0) -> 0 | V20: =ROUND(S20*Q20,2)+ROUND(U20*R20,2) -> 0 | W20: =ROUND(K20-U20,2) -> 0 | X20: =ROUND(S20*O20,2)+ROUND(U20*(N20-O20),2) -> 0 | Y20: =ROUND(F20-X20,2) -> 0
... L33: =IF(I33=0,0,IF(RIGHT(I33,1)<>"年",I33*12,IF(LEN(I33)=3,VALUE(LEFT(I33,2))*12,IF(LEN(I33)=2,VALUE(LEFT(I33,1))*12,"??")))) -> 0 | M33: =IF(H33=0,0,DATE(YEAR(H33),MONTH(H33)+L33,DAY(H33)-1)) -> 0 | N33: =IF(H33=0,0,IF(M33>$D$7,DATEDIF(H33,MIN($D$7,M33),"m"),VALUE(DATEDIF(H33,MIN($D$7,M33),"m")+1))) -> 0 | O33: =IF(H33=0,0,DATEDIF(H33,$F$7,"m")) -> 0 | P33: =IF(OR(H33=0,M33<$B$7),0,IF(AND(H33<$B$7,M33>$D$7),VALUE(DATEDIF($B$7,$D$7,"m")+1),IF(AND(H33<$B$7,M33<=$D$7),VALUE(DATEDIF($B$7,M33,"m")+1),IF(AND(H33>=$B$7,M33>$D$7),VALUE(DATEDIF(H33,$D$7,"m")),IF(AND(H33>=$B$7,M33<=$D$7),VALUE(DATEDIF(H33,M33,"m")+1),))))) -> 0 | Q33: =P33-R33 -> 0 | R33: =IF(H33=0,0,IF($F$7<$B$7,P33,DATEDIF(MAX(H33,$F$7),MIN(M33,$D$7),"m"))) -> 0 | S33: =IF(L33=0,0,ROUND(((1-J33)/L33)*E33,4)) -> 0 | T33: =ROUND(S33*O33,2) -> 0 | U33: =IF((E33*(1-J33)-T33-G33)>0,(E33*(1-J33)-T33-G33)/(L33-O33),0) -> 0 | V33: =ROUND(S33*Q33,2)+ROUND(U33*R33,2) -> 0 | W33: =ROUND(K33-U33,2) -> 0 | X33: =ROUND(S33*O33,2)+ROUND(U33*(N33-O33),2) -> 0 | Y33: =ROUND(F33-X33,2) -> 0
A34: 合计 | E34: =SUM(E9:E33) -> 0 | F34: =SUM(F9:F33) -> 0 | G34: =SUM(G9:G33) -> 0 | K34: =SUM(K9:K33) -> 0 | P34: =SUM(P9:P33) -> 0 | Q34: =SUM(Q9:Q33) -> 0 | R34: =SUM(R9:R33) -> 0 | S34: =SUM(S9:S33) -> 0 | T34: =SUM(T9:T33) -> 0 | U34: =SUM(U9:U33) -> 0 | V34: =SUM(V9:V33) -> 0 | W34: =SUM(W9:W33) -> 0 | ... Y34: =SUM(Y9:Y33) -> 0
A35: 三、审计说明：
A39: 四、审计结论：

Sheet 折耗分配分析表H5-13
A1: 致同会计师事务所
A2: 油气资产折耗分配分析表
A3: =底稿目录!A2 -> 被审计单位： | D3: =底稿目录!A4 -> 编制人： | G3: =底稿目录!A6 -> 编制日期： | I3: 索引号： | J3: H5-13
A4: =底稿目录!A3 -> 截止日：202X年12月31日 | D4: =底稿目录!A5 -> 复核人： | G4: =底稿目录!A7 -> 复核日期： | I4: 页 次：
A5: 一、审计目标：油气资产以恰当的金额包括在财务报表中，与之相关的计价或分摊调整已恰当记录，相关披露已得到恰当计量和描述。
A6: 二、审计过程：
A7: 序号 | B7: 油气资产类别 | C7: 生产成本 | D7: 制造费用 | E7: 销售费用 | F7: 管理费用 | G7: 研发费用 | H7: … | I7: 合计 | J7: 备注
A8: 1 | B8: 探明矿区权益 | I8: =SUM(C8:H8) -> 0
A9: 2 | B9: 未探明矿区权益 | I9: =SUM(C9:H9) -> 0
A10: 3 | B10: 井及相关设施 | I10: =SUM(C10:H10) -> 0
A11: 4 | B11: … | I11: =SUM(C11:H11) -> 0
A12: 5 | B12: … | I12: =SUM(C12:H12) -> 0
A13: 合计 | C13: =SUM(C8:C12) -> 0 | D13: =SUM(D8:D12) -> 0 | E13: =SUM(E8:E12) -> 0 | F13: =SUM(F8:F12) -> 0 | G13: =SUM(G8:G12) -> 0 | H13: =SUM(H8:H12) -> 0 | I13: =SUM(I8:I12) -> 0
B14: 勾稽关系情况 | C14: 勾稽一致，详见xx-XX | D14: 勾稽一致，详见xx-XX | E14: 勾稽一致，详见xx-XX | F14: 勾稽一致，详见xx-XX | G14: 勾稽一致，详见xx-XX | H14: 勾稽一致，详见xx-XX
A15: 三、审计说明：
A18: 四、审计结论：

Sheet 减值测算表H5-14
A1: 致同会计师事务所
A2: 油气资产减值测算表
A3: =底稿目录!A2 -> 被审计单位： | D3: =底稿目录!A4 -> 编制人： | G3: =底稿目录!A6 -> 编制日期： | K3: 索引号： | L3: H5-14
A4: =底稿目录!A3 -> 截止日：202X年12月31日 | D4: =底稿目录!A5 -> 复核人： | G4: =底稿目录!A7 -> 复核日期： | K4: 页 次：
A5: 一、审计目标：油气资产以恰当的金额包括在财务报表中，与之相关的计价或分摊调整已恰当记录，相关披露已得到恰当计量和描述。
A6: 二、审计过程：
A7: 项目名称 | B7: 是否存在减值迹象 | C7: 减值迹象描述 | D7: 账面价值 | E7: 可收回金额 | H7: 期末应计提的减值金额（当⑤＜②） | I7: 期末账面已计提的减值准备 | J7: 本期应补提 或冲回的减值准备 | K7: 工作底稿索引号 | L7: 备注
E8: 公允价值减处置费用的净额 | F8: 预计未来现金流量现值 | G8: 可收回金额（③、④较高者） | I8: 期末已计提 减值准备
C9: ① | D9: ② | E9: ③ | F9: ④ | G9: ⑤ | H9: ⑥＝⑤－② | I9: ⑦ | J9: ⑧=⑥-⑦
G10: =MAX(E10,F10) -> 0 | H10: =IF(D10>G10,D10-G10,0) -> 0 | J10: =H10-I10 -> 0
G11: =MAX(E11,F11) -> 0 | H11: =IF(D11>G11,D11-G11,0) -> 0 | J11: =H11-I11 -> 0
G12: =MAX(E12,F12) -> 0 | H12: =IF(D12>G12,D12-G12,0) -> 0 | J12: =H12-I12 -> 0
G13: =MAX(E13,F13) -> 0 | H13: =IF(D13>G13,D13-G13,0) -> 0 | J13: =H13-I13 -> 0
G14: =MAX(E14,F14) -> 0 | H14: =IF(D14>G14,D14-G14,0) -> 0 | J14: =H14-I14 -> 0
G15: =MAX(E15,F15) -> 0 | H15: =IF(D15>G15,D15-G15,0) -> 0 | J15: =H15-I15 -> 0
G16: =MAX(E16,F16) -> 0 | H16: =IF(D16>G16,D16-G16,0) -> 0 | J16: =H16-I16 -> 0
G17: =MAX(E17,F17) -> 0 | H17: =IF(D17>G17,D17-G17,0) -> 0 | J17: =H17-I17 -> 0
G18: =MAX(E18,F18) -> 0 | H18: =IF(D18>G18,D18-G18,0) -> 0 | J18: =H18-I18 -> 0
G19: =MAX(E19,F19) -> 0 | H19: =IF(D19>G19,D19-G19,0) -> 0 | J19: =H19-I19 -> 0
A20: 合计 | D20: =SUM(D10:D19) -> 0 | E20: =SUM(E10:E19) -> 0 | F20: =SUM(F10:F19) -> 0 | G20: =SUM(G10:G19) -> 0 | H20: =SUM(H10:H19) -> 0 | I20: =SUM(I10:I19) -> 0 | J20: =SUM(J10:J19) -> 0
A21: 三、审计说明：
A24: 四、审计结论：
A29: 提示：
A30: 1.获取或编制油气资产减值准备明细表，复核加计正确，并与总账数和明细账合计数核对相符；
A31: 2.检查油气资产减值准备计提和转销的批准程序，取得书面报告等证明文件；检查被审计单位计提油气资产减值准备的依据是否充分，会计处理是否正确；
A32: 3.检查油气资产转让时，相应的减值准备是否一并结转，会计处理是否正确；
A33: 4.重新测试被审计单位计提的减值准备是否合理；比较我们预期所估计减值准备和已记录的金额，调查所有重大差异；
A34: 5.上期确认的油气资产减值准备在本期的变动是否适当。

Sheet 可收回金额测试表H5-15
A1: 致同会计师事务所
A2: 油气资产减值准备测试表-可收回金额
A3: =底稿目录!A2 -> 被审计单位： | E3: =底稿目录!A4 -> 编制人： | J3: =底稿目录!A6 -> 编制日期： | N3: 索引号： | O3: H5-15
A4: =底稿目录!A3 -> 截止日：202X年12月31日 | E4: =底稿目录!A5 -> 复核人： | J4: =底稿目录!A7 -> 复核日期： | N4: 页 次：
A5: 一、审计目标：油气资产以恰当的金额包括在财务报表中，与之相关的计价或分摊调整已恰当记录，相关披露已得到恰当计量和描述。
A6: 二、审计过程：
A7: （一）资产的公允价值减去处置费用后的净额
A8: 油气资产类别/名称 | B8: 公允价值 | H8: 处置费用（资产处置的直接归属费用） | N8: 公允价值-处置费用 | O8: 备注
B9: 销售协议价格 | C9: 说明 | D9: 资产活跃市场价格 | E9: 说明 | F9: 估计价格 | G9: 说明 | H9: 法律费用 | I9: 相关税费 | J9: 搬运费 | K9: 直接费用 | L9: 其他费用 | M9: 处置费用合计
M10: =SUM(H10:L10) -> 0 | N10: =IF(B10>0,B10,IF(D10>0,D10,F10))-M10 -> 0
M11: =SUM(H11:L11) -> 0 | N11: =IF(B11>0,B11,IF(D11>0,D11,F11))-M11 -> 0
M12: =SUM(H12:L12) -> 0 | N12: =IF(B12>0,B12,IF(D12>0,D12,F12))-M12 -> 0
A13: 合计 | B13: =SUM(B10:B12) -> 0 | D13: =SUM(D10:D12) -> 0 | F13: =SUM(F10:F12) -> 0 | H13: =SUM(H10:H12) -> 0 | I13: =SUM(I10:I12) -> 0 | J13: =SUM(J10:J12) -> 0 | K13: =SUM(K10:K12) -> 0 | L13: =SUM(L10:L12) -> 0 | M13: =SUM(M10:M12) -> 0 | N13: =SUM(N10:N12) -> 0
A14: 审计说明：
A15: （二）资产预计未来现金流量的现值
A16: 预计未来现金流量 | B16: 预算或者预测期 | G16: 以后年度 | I16: 行业的长期平均增长率 | J16: 市场长期平均增长率 | K16: 所在国家或地区的长期平均增长率 | L16: 增长率确定依据 | N16: 预计未来现金流量的现值 | O16: 备注
B17: 第一年 | C17: 第二年 | D17: 第三年 | E17: 第四年 | F17: 第五年 | G17: 基数 | H17: 增长率
A18: 预计未来现金净流量 | G18: =F18 -> 0
A19: 折现系数 | B19: =1/(1+$K$23)^1 -> #DIV/0! | C19: =1/(1+$K$23)^2 -> #DIV/0! | D19: =1/(1+$K$23)^3 -> #DIV/0! | E19: =1/(1+$K$23)^4 -> #DIV/0! | F19: =1/(1+$K$23)^5 -> #DIV/0! | G19: =(1+H18)/((K23-H18)*(1+K23)^5) -> #DIV/0! | H19: （企业管理层如能证明递增的增长率是合理的，可以以递增的增长率为基础。）
A20: 现值 | B20: =B18*B19 -> #DIV/0! | C20: =C18*C19 -> #DIV/0! | D20: =D18*D19 -> #DIV/0! | E20: =E18*E19 -> #DIV/0! | F20: =F18*F19 -> #DIV/0! | G20: =G18*G19 -> #DIV/0! | H20: （建立在预算或者预测基础上的预计现金流量最多涵盖5年。） | N20: =SUM(B20:G20) -> #DIV/0!
A21: 折现率 | B21: 所得税率 | C21: 债务总额 | D21: 资本总额 | E21: 债务成本Kd | F21: 无风险报酬率Rf | G21: β系数 | H21: 平均风险股票必要报酬率Rm | I21: 资本成本Ke | J21: 折现率(税后) | K21: 折现率(税前) | L21: 税后折税前调整说明 | N21: 可收回金额 | O21: 备注
B22: 适用税率 | L22: 税率调整 | M22: 调整说明
A23: 加权平均资金成本 | I23: =F23+G23*(H23-F23) -> 0 | J23: =((C23*E23*(1-B23)+D23*I23))/(C23+D23) -> #DIV/0! | K23: =J23/(1-(B23+L23)) -> #DIV/0! | N23: =MAX(N13,N20) -> #DIV/0!
A24: 审计说明：
A25: （三）可收回金额
B26: =N23 -> #DIV/0! | C26: 资产的公允价值减去处置费用后的净额与资产预计未来现金流量的现值两者之间较高者
A27: 三、审计说明：
A29: 四、审计结论
A32: 提示：
A33: 1、可收回金额应当根据资产的公允价值减去处置费用后的净额与资产预计未来现金流量的现值两者之间较高者确定。
A35: 2、资产的公允价值减去处置费用后的净额，应当根据公平交易中销售协议价格减去可直接归属于该资产处置费用的金额确定。不存在销售协议但存在资产活跃市场的，
A36: 应当按照该资产的市场价格减去处置费用后的金额确定。资产的市场价格通常应当根据资产的买方出价确定。在不存在销售协议和资产活跃市场的情况下，应当
A37: 以可获取的最佳信息为基础，估计资产的公允价值减去处置费用后的净额，该净额可以参考同行业类似资产的最近交易价格或者结果进行估计。企业按照上述规定
A38: 仍然无法可靠估计资产的公允价值减去处置费用后的净额的，应当以该资产预计未来现金流量的现值作为其可收回金额。
A39: 3、处置费用包括与资产处置有关的法律费用、相关税费、搬运费以及为使资产达到可销售状态所发生的直接费用等。
A41: 4、资产预计未来现金流量的现值，应当按照资产在持续使用过程中和最终处置时所产生的预计未来现金流量，选择恰当的折现率对其进行折现后的金额加以确定。
A42: 5、预计资产的未来现金流量，应当以经企业管理层批准的最近财务预算或者预测数据，以及该预算或者预测期之后年份稳定的或者递减的增长率为基础。
A43: 预计的资产未来现金流量应当包括下列各项：
... A64: 5.上期确认的油气资产减值准备在本期的变动是否适当。

Sheet 权属检查表H5-16
A1: 致同会计师事务所
A2: 油气资产权属检查表
A3: =底稿目录!A2 -> 被审计单位： | G3: =底稿目录!A4 -> 编制人： | L3: =底稿目录!A6 -> 编制日期： | T3: 索引号： | U3: H5-16
A4: =底稿目录!A3 -> 截止日：202X年12月31日 | G4: =底稿目录!A5 -> 复核人： | L4: =底稿目录!A7 -> 复核日期： | T4: 页 次：
A5: 一、审计目标：记录的油气资产由被审计单位拥有或控制。 | G5: （提示：每次审计需要重新取得原件，进行原件和复印件的核对并记录）检查资产的权属证明，验证其属于被审计单位所有。
A6: 二、审计过程：
A7: 资产编号 | B7: 资产名称 | C7: 权属证明记载 | L7: 财务账面记载 | R7: 抵押情况
C8: 探矿权人 | D8: 探矿权人地址 | E8: 勘察项目名称 | F8: 地理位置 | G8: 勘察面积 | H8: 有效期限 | I8: 勘察单位 | J8: 勘察单位地址 | K8: 权证复印件索引 | L8: 勘察面积 | M8: 勘察项目名称 | N8: 原值 | O8: 累计折耗 | P8: 减值准备 | Q8: 净值 | R8: 是否抵押受限 | S8: 抵押面积 | T8: 抵押价值 | U8: 抵押性质
Q9: =N9-O9-P9 -> 0
Q10: =N10-O10-P10 -> 0
Q11: =N11-O11-P11 -> 0
Q12: =N12-O12-P12 -> 0
Q13: =N13-O13-P13 -> 0
Q14: =N14-O14-P14 -> 0
Q15: =N15-O15-P15 -> 0
Q16: =N16-O16-P16 -> 0
A17: 合计 | L17: =SUM(L9:L16) -> 0 | N17: =SUM(N9:N16) -> 0 | O17: =SUM(O9:O16) -> 0 | P17: =SUM(P9:P16) -> 0 | Q17: =N17-O17-P17 -> 0
A18: 三、审计说明：
A19: 1 | B19: 权证是否齐全；是否归属公司所有
A20: 2 | B20: 油气资产抵押情况描述
A21: 四、审计结论：
A25: 提示：
A26: 1.实地查看探矿权等油气资产，并同时查看资产权属证明原件（复印并加盖公司公章（已和原件核对一致）），结合银行借款等项目的检查，了解是否设定对外抵押，并取得复印件作为工作底稿；
A27: 2.对于正在办理权属证明的大额资产，应了解权属证明办理情况，确认是否存在权属纠纷或实质性障碍。
A28: 3.详细记录抵押、担保等事项，并提请被审计单位进行充分披露。<CSRC14-7>

Sheet 关联交易检查表H5-17
A1: 致同会计师事务所
A2: 关联交易检查表
A3: =底稿目录!A2 -> 被审计单位： | F3: =底稿目录!A4 -> 编制人： | I3: =底稿目录!A6 -> 编制日期： | N3: 索引号： | O3: H5-17
A4: =底稿目录!A3 -> 截止日：202X年12月31日 | F4: =底稿目录!A5 -> 复核人： | I4: =底稿目录!A7 -> 复核日期： | N4: 页 次：
A5: 一、审计目标:
A6: 1.资产负债表中记录的固定资产是存在的，且已记录于恰当的账户；2.所有应记录的固定资产均已记录，所有应当包括在财务报表中的相关披露均已包括；3.记录的固定资产由被审计单位拥有或控制。
A7: 4.固定资产以恰当的金额包括在财务报表中，与之相关的计价或分摊调整已恰当记录，相关披露已得到恰当计量和描述；5.固定资产已被恰当地汇总或分解且表述清楚，相关披露在按照企业会计准则的编制基础下是相关的、可理解的。
A8: 二、审计过程：
A9: （1）向合并范围外关联方采购油气资产
A10: 关联单位名称 | B10: 关联方关系 | C10: 资产类别 | D10: 购买油气资产名称 | E10: 购买价款 | F10: 油气资产入账价值 | G10: 占同类交易金额的比例％ | H10: 购入时间 | I10: 折旧年限 | J10: 定价政策 | K10: 关联交易是否存在异常 | L10: 备注 | M10: 索引号
A18: （2）向合并范围外关联方出售固定资产
A19: 关联单位名称 | B19: 关联方关系 | C19: 资产类别 | D19: 出售油气资产名称 | E19: 出售时油气资产原值 | F19: 出售时累计折旧 | G19: 出售时减值准备 | H19: 出售时净值 | I19: 销售价格 （不含税） | J19: 占同类交易金额的比例％ | K19: 出售时间 | L19: 定价政策 | M19: 关联交易是否存在异常 | N19: 备注 | O19: 索引号
H20: =E20-F20-G20 -> 0
H21: =E21-F21-G21 -> 0
H22: =E22-F22-G22 -> 0
H23: =E23-F23-G23 -> 0
H24: =E24-F24-G24 -> 0
H25: =E25-F25-G25 -> 0
A26: 三、审计说明：
A29: 四、审计结论：
A35: 勿删
A36: 关联关系
A37: 实际控制人
A38: 控股股东
A39: 控股股东、实际控制人的附属企业
A40: 持有5%以上股份的法人或其他组织
A41: 联营企业
A42: 合营企业
A43: 董高监等关键管理人员
A44: 其他关联方

Sheet 经营租出油气资产检查表H5-18
A1: 致同会计师事务所
A2: 经营租出油气资产检查表
A3: =底稿目录!A2 -> 被审计单位： | E3: =底稿目录!A4 -> 编制人： | J3: =底稿目录!A6 -> 编制日期： | M3: 索引号： | N3: H5-18
A4: =底稿目录!A3 -> 截止日：202X年12月31日 | E4: =底稿目录!A5 -> 复核人： | J4: =底稿目录!A7 -> 复核日期： | M4: 页 次：
A5: 一、审计目标：
A6: 1.资产负债表中记录的油气资产是存在的，且已记录于恰当的账户；2.记录的油气资产由被审计单位拥有或控制；
A7: 3.油气资产以恰当的金额包括在财务报表中，与之相关的计价或分摊调整已恰当记录，相关披露已得到恰当计量和描述
A8: 二、审计过程：
A9: 序号 | B9: 油气资产名称 | C9: 资产类别 | D9: 承租单位名称 | E9: 油气资产原价 | F9: 租赁开始日 | G9: 租赁到期日 | H9: 本年应计租金月份数 | I9: 月折耗额 | J9: 月租金收入 | K9: 本期应计入其他业务支出的折旧额 | L9: 本期应计租金收入 | M9: 与其他业务收支科目是否勾稽 | N9: 租赁合同 索引号
A10: 1 | K10: =H10*I10 -> 0 | L10: =H10*J10 -> 0
A11: 2 | K11: =H11*I11 -> 0 | L11: =H11*J11 -> 0
A12: 3 | K12: =H12*I12 -> 0 | L12: =H12*J12 -> 0
A13: 4 | K13: =H13*I13 -> 0 | L13: =H13*J13 -> 0
A14: 5 | K14: =H14*I14 -> 0 | L14: =H14*J14 -> 0
A15: 6 | K15: =H15*I15 -> 0 | L15: =H15*J15 -> 0
A16: 7 | K16: =H16*I16 -> 0 | L16: =H16*J16 -> 0
A17: 8 | K17: =H17*I17 -> 0 | L17: =H17*J17 -> 0
A18: 三、审计说明：
A23: 四、审计结论：

Sheet 融资租出油气资产检查表H5-19
A1: 致同会计师事务所
A2: 融资租出油气资产检查表
A3: =底稿目录!A2 -> 被审计单位： | E3: =底稿目录!A4 -> 编制人： | J3: =底稿目录!A6 -> 编制日期： | K3: 索引号： | L3: H5-19
A4: =底稿目录!A3 -> 截止日：202X年12月31日 | E4: =底稿目录!A5 -> 复核人： | J4: =底稿目录!A7 -> 复核日期： | K4: 页 次：
A5: 一、审计目标：1.资产负债表中记录的油气资产是存在的，且已记录于恰当的账户；2.记录的油气资产由被审计单位拥有或控制；3.油气资产以恰当的金额包括在财务报表中，与之相关的计价或分摊调整已恰当记录，相关披露已得到恰当计量和描述
A6: 二、审计过程：
A7: 序号 | B7: 融资租出油气资产编号 | C7: 融资租出油气资产名称 | D7: 承租单位名称 | E7: 租赁开始日 | F7: 租赁合同索引号 | G7: 是否满足融资租赁的定义
G8: 在租赁期届满时，租赁资产的所有权转移给承租人； | H8: 租赁期占租赁资产使用寿命的大部分（>=75%）； | I8: 承租人有购买租赁资产的选择权，在租赁开始日可合理确定承租人将行使该权利 | J8: 承租人租赁开始日的最低租赁付款额的现值，几乎相当于租赁开始日租赁资产公允价值（>=90%） | K8: 出租人租赁开始日的最低租赁收款额的现值，几乎相当于租赁开始日租赁资产公允价值（>=90%） | L8: 租赁资产性质特殊，如不作较大改造，只有承租人才能使用
A9: 1
A10: 2
A11: 3
A12: 4
A13: 5
A14: 6
A15: 7
A16: 8
A17: 1.确定租赁内含利率
A18: 项目 | B18: 各期租金之和 | I18: 行使优惠购买选择权支付的金额
B19: 2014年 | C19: 2015年 | D19: 2016年 | E19: 2017年 | F19: 2018年 | G19: 2019年 | H19: …
A20: 最低租赁收款额
A21: 折现率1
A22: 折现值1 | B22: =B20*B21 -> 0 | C22: =C20*C21 -> 0 | D22: =D20*D21 -> 0 | E22: =E20*E21 -> 0 | F22: =F20*F21 -> 0 | G22: =G20*G21 -> 0 | H22: =H20*H21 -> 0 | I22: =I20*I21 -> 0
A23: 最低租赁收款额现值1 | B23: =SUM(B22:I22) -> 0
A24: 折现率2
A25: 折现值2 | B25: =B20*B24 -> 0 | C25: =C20*C24 -> 0 | D25: =D20*D24 -> 0 | E25: =E20*E24 -> 0 | F25: =F20*F24 -> 0 | G25: =G20*G24 -> 0 | H25: =H20*H24 -> 0 | I25: =I20*I24 -> 0
A26: 最低租赁收款额现值2 | B26: =SUM(B25:I25) -> 0
A27: 租赁开始日，租赁资产的公允价值
A28: 初始直接费用
A29: 两者的合计 | B29: =B27+B28 -> 0
A30: 租赁内含利率
A31: 2.确定应收融资租赁款和未实现融资收益
A32: 序号 | B32: 金额
A33: 最低租赁收款额 | B33: =SUM(B20:I20) -> 0
A34: 初始直接费用 | B34: =B28 -> 0
A35: 应收融资租赁款 | B35: =B33+B34 -> 0
A36: 未实现融资收益 | B36: =B35-B29 -> 0
A37: 3.未确认融资收益分配表（如适用）
A38: 日期 | B38: 租金 | C38: 确认的融资收入 | D38: 租赁投资净额减少额 | E38: 租赁投资净额余额
A39: ① | B39: ② | C39: ③=期初⑤X租赁内含利率 | D39: ④=②-③ | E39: 期末⑤=期初⑤-④
A40: 2014年12月31日 | E40: =B27 -> 0
A41: 2015年12月31日 | B41: =C20 -> 0 | C41: =E40*$C$31 -> 0 | D41: =B41-C41 -> 0 | E41: =E40-D41 -> 0
A42: 2016年12月31日 | B42: =D20 -> 0 | C42: =E41*$C$31 -> 0 | D42: =B42-C42 -> 0 | E42: =E41-D42 -> 0
A43: 2017年12月31日 | B43: =E20 -> 0 | C43: =E42*$C$31 -> 0 | D43: =B43-C43 -> 0 | E43: =E42-D43 -> 0
A44: 2018年12月31日 | B44: =F20 -> 0 | C44: =E43*$C$31 -> 0 | D44: =B44-C44 -> 0 | E44: =E43-D44 -> 0
A45: 2019年12月31日 | B45: =G20 -> 0 | C45: =E44*$C$31 -> 0 | D45: =B45-C45 -> 0 | E45: =E44-D45 -> 0
A46: … | C46: =B46-D46 -> 0 | D46: =E45 -> 0 | E46: =E45-D46 -> 0
A47: 合计 | B47: =SUM(B41:B46) -> 0
A48: 三、审计说明：
A49: 1 | B49: 融资租出油气资产的条件是否满足
A50: 2 | B50: 长期应收款、融资租赁资产、未确认融资收益的入账价值是否正确
A51: 3 | B51: 所采用的租赁内含利率是否正确
A52: 4 | B52: 未确认融资收益的分配是否恰当
A53: 四、审计结论：
A57: 提示：
A58: 1.检查是否将最低租赁收款额挂账长期应收款，是否将租赁租赁收款额、未担保余值之和与其现值的差额作为未确认融资收益。
A59: 2.确定分配未确认融资收益的实际利率是否合理，按实际利率法测算未确认融资收益分配，检查会计处理是否正确。
A60: 3.未担保余值发生变动的，分析变动原因，检查会计处理是否正确。
A61: 4.检查初始直接费用、或有租金确认是否合理，会计处理是否正确。
A62: 5.本期租出油气资产的，与油气资产增减变动明细表核对一致。
A63: 6.本期租赁期届满的，分析处理方式（收回、优惠续租和出售），检查会计处理是否正确。
