Workbook

Sheet 底稿目录
A1: 底稿开列时，可先在以下单元格填写有关内容，以便其他底稿引用有关数据：
A2: 被审计单位：
A3: 截止日：202X年12月31日 | D3: 序号 | E3: 内容 | F3: 索引号 | G3: 备注
A4: 编制人： | D4: 1 | E4: 使用权资产实质性程序表 | F4: H8A
A5: 复核人： | D5: 2 | E5: 审定表 | F5: H8-1
A6: 编制日期： | D6: 3 | E6: 附注披露信息（上市公司） | G6: 无需打印
A7: 复核日期： | D7: 4 | E7: 附注披露信息（国企） | G7: 无需打印
A8: 使用权资产类别设置（以下内容请根据实际情况修改）： | D8: 5 | E8: 明细表 | F8: H8-2
A9: 房屋及建筑物 | D9: 6 | E9: 调整分录汇总 | F9: H8-3
A10: 机器设备 | D10: 7 | E10: 租赁的识别 | F10: H8-4
A11: 运输设备 | D11: 8 | E11: 租赁期的确定 | F11: H8-5
A12: 办公设备 | D12: 9 | E12: 使用权资产 租赁负债初始及后续计量（按年） | F12: H8-6 | G12: 选择使用
A13: 其他设备 | D13: 10 | E13: 使用权资产 租赁负债初始及后续计量（按月） | F13: H8-6 | G13: 选择使用
A14: …… | D14: 11 | E14: 租赁变更 | F14: H8-7
D15: 12 | E15: 折旧测算表（不含减值） | F15: H8-8 | G15: 选择使用
A16: 关于工作底稿与审计程序索引号对应的说明 | D16: 13 | E16: 折旧测算表（含减值） | F16: H8-8 | G16: 选择使用
A17: 1.编制的审计工作底稿应与审计程序对应。审计项目组应根据被审计单位实际情况和风险评估情况在实质性程序表中裁剪、修改或增加审计程序，根据实际执行的审计程序完成相应审计工作底稿，编制的工作底稿中应按自然顺序依次编制索引号，并通过唯一的索引号将与实质性程序表中的程序对应关联（即将工作底稿的索引号填入实质性程序表中的底稿索引号列）。 | D17: 14 | E17: 折旧分配分析表 | F17: H8-9
D18: 15 | E18: 减值测算表 | F18: H8-10
D19: 16 | E19: 可收回金额测试表 | F19: H8-11
D20: 17 | E20: 减少检查表 | F20: H8-12
A21: 2.获取的支持性证据应与审计底稿或程序对应。审计项目组在完成底稿时获取的支持性证据应根据底稿索引号编制下一级按自然顺序排序的索引号（如D1-2-1、D1-2-2、……），并在底稿中说明引用的支持性证据、关联索引号。 | D21: 18 | E21: 简化处理的租赁检查表 | F21: H8-13
D22: 19 | E22: 关联交易检查表 | F22: H8-14
A24: 3.工作底稿索引号的编码规则：实质性程序索引号按循环从“D”到“N”,循环内账户以顺序号排列，模板中底稿索引号按账户顺序+自然数顺序（即模板中索引号按二级自然顺序排列，如D1-1、D1-2、D1-3、……D1-N）。

Sheet 使用权资产实质性程序表H8A
A1: 致同会计师事务所
A2: 使用权资产实质性程序表
A3: =底稿目录!A2 -> 被审计单位： | C3: =底稿目录!A4 -> 编制人： | E3: =底稿目录!A6 -> 编制日期： | H3: 索引号： | I3: H8A
A4: =底稿目录!A3 -> 截止日：202X年12月31日 | C4: =底稿目录!A5 -> 复核人： | E4: =底稿目录!A7 -> 复核日期： | H4: 页 次：
A5: 一、本账户涉及的科目
A6: 使用权资产、累计折旧、减值准备
A7: 二、审计目标与认定的对应关系
A8: 审计目标 | G8: 财务报表的认定
A9: A. 资产负债表中记录的使用权资产是存在的，且已记录于恰当的账户 | G9: 存在
A10: B. 所有应记录的使用权资产均已记录，所有应当包括在财务报表中的相关披露均已包括 | G10: 完整性
A11: C. 记录的使用权资产由被审计单位拥有或控制； | G11: 权利和义务
A12: D. 使用权资产以恰当的金额包括在财务报表中，与之相关的计价或分摊调整已恰当记录，相关披露已得到恰当计量和描述 | G12: 准确性、计价和分摊
A13: E. 使用权资产已被恰当地汇总或分解且表述清楚，相关披露在按照企业会计准则的编制基础下是相关的、可理解的 | G13: 列报
A14: 三、计划实施的实质性程序
A15: 序号 | B15: 审计程序 | C15: 程序分类 | D15: 财务报表的认定 | I15: 底稿索引号
D16: 存在 | E16: 完整性 | F16: 权利和 义务 | G16: 准确性、计价和分摊 | H16: 列报 | J16: 根据被审计单位实际情况和风险评估情况裁剪、修改或增加审计程序
A17: 1 | B17: 获取或编制使用权资产的明细表，完成以下工作，并编制审定表 （1）复核加计是否正确，并与总账数和明细账合计数核对是否相符，期初余额与上期审定期末余额是否相符； （2）分析使用权资产与上期变动情况； （3）询问闲置资产或未入账资产处置情况（如有）。 | C17: 常规★ | D17: √ | E17: √ | G17: √ | I17: H8-1 /H8-2
A18: 2 | B18: 在使用手工编制、自定义信息报告、系统生成的非固定格式报告等由被审计单位生成的信息时，测试有关信息准确性和完整性，并考虑针对编制和维护由被审计单位生成的信息的相关控制实施控制测试，以评价该信息是否能够为实现审计目的提供基础。 | C18: 常规★ | D18: √ | E18: √ | G18: √ | I18: T1 / | J18: 可参见《审计手册》4.2.6，由被审计单位生成的信息可能是由系统生成的、或手工编制的、或二者兼而有之的方式生成的。例如，由被审计单位生成的信息可能包括： • 不涉及自定义的、由系统生成的报告（如，固定格式报告）； • 可能通过人工自定义的、由系统生成的报告，例如，（计算机）查询信息或特别定制的报告； • 手工编制的信息，例如，汇总信息的电子表格或用以支持分配、计算以及调节的电子表格； • 其他系统生成或手工编制的信息，例如，由被审计单位编制的客户发票； • 通过影印、拍摄、扫描或其他方式转换成电子形式的文件记录。
A19: 3 | B19: 对期初余额的审计，取得上期使用权资产明细表复核加计是否正确，与总账、明细账合计数是否相符； 重新测算期初累计折旧余额准确性；对单项金额重大资产，进行实地查看资产或检查支持性文件，其他必要追加的审计程序。（适用于首次承接） | C19: 备选 | D19: √ | E19: √ | F19: √ | G19: √ | J19: 由被审计单位生成的信息不包括： • 总分类账或明细分类账、试算平衡表、或经审计的财务报表； • 第三方（除了服务机构）的报表或报告，例如，原始银行对账单，或函证的回函； • 外部数据（例如，第三方发布的数据，如，定价来源）。
A20: 4 | B20: 关注会计政策、会计估计合理性、一贯性，关注其是否利用会计政策和会计估计及其变更操纵利润。 | C20: 常规★ | D20: √ | E20: √ | G20: √ | I20: H8-1 /H8-2
A21: 5 | B21: 检查相关合同的主要条款，询问被审计单位将该合同识别为租赁或者包含租赁的理由，检查租赁的识别和租赁期的确定是否符合企业会计准则的规定 | C21: 常规★ | D21: √ | F21: √ | I21: H8-4 /H8-5
A22: 6 | B22: 检查使用权资产、租赁负债的初始计量和后续计量： （1）获取相关租赁合同/协议，检查初始直接费用、或有租金确认、折现率是否合理，使用权资产和租赁负债的入账价值是否正确和会计处理是否正确。 （2）当存在续租选择权、购买选择权和终止租赁选择权时，了解被审计单位对是否行使相关权利做出的判断，检查其判断依据是否充分，并评估对使用权资产、租赁负债入账价值的影响； （3）按实际利率法重新计算未确认融资费用摊销、租赁负债余额，计算使用权资产余额，与被审计单位账面记录核对是否一致； （4）重估或租赁变更等原因导致租赁付款额发生变动时，重新计量租赁负债账面价值会计处理是否正确； | C22: 常规★ | D22: √ | E22: √ | F22: √ | G22: √ | I22: H8-6 /H8-7
A23: 7 | B23: 检查累计折旧，考虑执行以下程序： （1）获取或编制使用权资产累计折旧明细表，复核加计是否正确，并与总账数和明细账合计数核对是否相符 （2）检查折旧年限的确定是否恰当；续租选择权、购买选择权和终止租赁选择权对租赁期的影响是否已充分考虑，是否根据租赁的具体情况，已合理选择租赁期或者租赁资产预计剩余使用寿命作为折旧年限 （3）重新计算本期折旧金额是否正确，与相关科目核对是否相符。当存在减值时，是否按照扣除减值损失之后的使用权资产账面价值进行后续折旧 （4）检查折旧分配到成本、费用的情况，关注分配是否合理，与上期分配方法是否一致。 | C23: 常规★ | G23: √ | I23: H8-8 /H8-9
A24: 8 | B24: 监盘使用权资产： （1）取得使用权资产存放地点清单等，初步确定监盘方式、时间、监盘计划； （2）获取被审计单位对于使用权资产的盘点计划，制定和实施监盘计划（如有）； （3）取得使用权资产地点清单，初步确定监盘方式、时间、监盘计划； （4）观察被审计单位制定的盘点程序的执行情况 （5）抽取使用权资产盘点，并检查使用权资产的状态（正常、空置、出租等）； （6）评价使用权资产盘点结果，完成监盘小结。 | C24: 备选 | D24: √ | F24: √ | G24: √ | J24: 具体盘点底稿参考固定资产
A25: 9 | B25: 结合使用权资产清单及资产的实际使用情况，了解使用权资产的状态。针对存在减值迹象的使用权资产，考虑执行下列程序： 获取被审计单位在资产负债表日就使用权资产是否可能发生减值迹象的判断的说明，判断其合理性。对于已计提减值准备的使用权资产，检查减值测试相关参数是否合理，减值准备计提是否正确。如存在管理层聘请评估专家出具的评估报告，复核评估报告。 | C25: 常规★ | G25: √ | I25: H8-10 /H8-11
A26: 10 | B26: 检查本期使用权资产的减少： （1）对于因不再使用租赁资产导致的减少，检查使用权资产减少是否与租赁合同/协议约定的租赁结束日一致，租赁资产移交手续是否齐全，会计处理是否正确； （2）对于因转租使用权资产形成融资租赁导致的减少，获取转租合同，检查转租手续是否齐全，判断其会计处理是否正确。 | C26: 常规★ | D26: √ | E26: √ | G26: √ | I26: H8-12
A27: 11 | B27: 当存在将短期租赁和低价值资产租赁进行简化处理情形时，对本期直接计入当期损益的短期租赁费用和低价值资产租赁费用进行复核； | C27: 常规★ | E27: √ | G27: √ | I27: H8-13
A28: 12 | B28: 检查关联交易情况，检查关联交易的真实性、合理性及合规性；检查关联交易会计处理是否正确，考虑是否存在未识别的关联方，检查关联交易和余额披露是否正确。 | C28: 常规★ | D28: √ | E28: √ | F28: √ | G28: √ | H28: √ | I28: H8-14
A29: 13 | B29: 必要时函证租赁资产、租赁期、应付和已付租金、租赁条款等信息。 | C29: IPO/上市/新三板/重组/舞弊应对 | D29: √ | F29: √ | G29: √ | I29: H0
A30: 14 | B30: 根据评估的舞弊风险等因素增加的审计程序。 | C30: IPO/上市/新三板/重组/舞弊应对
A31: 15 | B31: 检查使用权资产是否已按企业会计准则或其他适用的规定在财务报表中做出恰当列报和披露 | C31: 常规★ | H31: √ | I31: A 1-1/A1-15 /A1-16

Sheet 审定表H8-1
A1: 致同会计师事务所
A2: 使用权资产、累计折旧及减值准备审定表
A3: =底稿目录!A2 -> 被审计单位： | C3: =底稿目录!A4 -> 编制人： | F3: =底稿目录!A6 -> 编制日期： | H3: 索引号： | I3: H8-1
A4: =底稿目录!A3 -> 截止日：202X年12月31日 | C4: =底稿目录!A5 -> 复核人： | F4: =底稿目录!A7 -> 复核日期： | H4: 页 次：
A5: 项目 | B5: 期初数 | E5: 期末数 | H5: 本期审定数与上期 审定数的比较
B6: 未审数 | C6: 账项调整 | D6: 审定数 | E6: 未审数 | F6: 账项调整 | G6: 审定数 | H6: 变动额 | I6: 变动率
A7: 一、使用权资产原值
A8: =底稿目录!A9 -> 房屋及建筑物 | B8: ='明细表H8-2'!D34 -> 0 | C8: ='明细表H8-2'!L34 -> 0 | D8: =B8+C8 -> 0 | E8: ='明细表H8-2'!K34 -> 0 | F8: ='明细表H8-2'!L34+'明细表H8-2'!M34+'明细表H8-2'!N34+'明细表H8-2'!O34-'明细表H8-2'!P34-'明细表H8-2'!Q34-'明细表H8-2'!R34 -> 0 | G8: =E8+F8 -> 0 | H8: =G8-D8 -> 0 | I8: =IF(AND(D8=0,H8=0),0,IF(AND(D8=0,H8>0),1,H8/D8)) -> 0
A9: =底稿目录!A10 -> 机器设备 | B9: ='明细表H8-2'!D35 -> 0 | C9: ='明细表H8-2'!L35 -> 0 | D9: =B9+C9 -> 0 | E9: ='明细表H8-2'!K35 -> 0 | F9: ='明细表H8-2'!L35+'明细表H8-2'!M35+'明细表H8-2'!N35+'明细表H8-2'!O35-'明细表H8-2'!P35-'明细表H8-2'!Q35-'明细表H8-2'!R35 -> 0 | G9: =E9+F9 -> 0 | H9: =G9-D9 -> 0 | I9: =IF(AND(D9=0,H9=0),0,IF(AND(D9=0,H9>0),1,H9/D9)) -> 0
A10: =底稿目录!A11 -> 运输设备 | B10: ='明细表H8-2'!D36 -> 0 | C10: ='明细表H8-2'!L36 -> 0 | D10: =B10+C10 -> 0 | E10: ='明细表H8-2'!K36 -> 0 | F10: ='明细表H8-2'!L36+'明细表H8-2'!M36+'明细表H8-2'!N36+'明细表H8-2'!O36-'明细表H8-2'!P36-'明细表H8-2'!Q36-'明细表H8-2'!R36 -> 0 | G10: =E10+F10 -> 0 | H10: =G10-D10 -> 0 | I10: =IF(AND(D10=0,H10=0),0,IF(AND(D10=0,H10>0),1,H10/D10)) -> 0
A11: =底稿目录!A12 -> 办公设备 | B11: ='明细表H8-2'!D37 -> 0 | C11: ='明细表H8-2'!L37 -> 0 | D11: =B11+C11 -> 0 | E11: ='明细表H8-2'!K37 -> 0 | F11: ='明细表H8-2'!L37+'明细表H8-2'!M37+'明细表H8-2'!N37+'明细表H8-2'!O37-'明细表H8-2'!P37-'明细表H8-2'!Q37-'明细表H8-2'!R37 -> 0 | G11: =E11+F11 -> 0 | H11: =G11-D11 -> 0 | I11: =IF(AND(D11=0,H11=0),0,IF(AND(D11=0,H11>0),1,H11/D11)) -> 0
A12: =底稿目录!A13 -> 其他设备 | B12: ='明细表H8-2'!D38 -> 0 | C12: ='明细表H8-2'!L38 -> 0 | D12: =B12+C12 -> 0 | E12: ='明细表H8-2'!K38 -> 0 | F12: ='明细表H8-2'!L38+'明细表H8-2'!M38+'明细表H8-2'!N38+'明细表H8-2'!O38-'明细表H8-2'!P38-'明细表H8-2'!Q38-'明细表H8-2'!R38 -> 0 | G12: =E12+F12 -> 0 | H12: =G12-D12 -> 0 | I12: =IF(AND(D12=0,H12=0),0,IF(AND(D12=0,H12>0),1,H12/D12)) -> 0
A13: 合计 | B13: =SUM(B8:B12) -> 0 | C13: =SUM(C8:C12) -> 0 | D13: =SUM(D8:D12) -> 0 | E13: =SUM(E8:E12) -> 0 | F13: =SUM(F8:F12) -> 0 | G13: =SUM(G8:G12) -> 0 | H13: =G13-D13 -> 0 | I13: =IF(AND(D13=0,H13=0),0,IF(AND(D13=0,H13>0),1,H13/D13)) -> 0
A14: 二、累计折旧
A15: =A8 -> 房屋及建筑物 | B15: ='明细表H8-2'!W34 -> 0 | C15: ='明细表H8-2'!AD34 -> 0 | D15: =B15+C15 -> 0 | E15: ='明细表H8-2'!AC34 -> 0 | F15: ='明细表H8-2'!AD34+'明细表H8-2'!AE34+'明细表H8-2'!AF34-'明细表H8-2'!AG34-'明细表H8-2'!AH34-'明细表H8-2'!AI34 -> 0 | G15: =E15+F15 -> 0 | H15: =G15-D15 -> 0 | I15: =IF(AND(D15=0,H15=0),0,IF(AND(D15=0,H15>0),1,H15/D15)) -> 0
A16: =A9 -> 机器设备 | B16: ='明细表H8-2'!W35 -> 0 | C16: ='明细表H8-2'!AD35 -> 0 | D16: =B16+C16 -> 0 | E16: ='明细表H8-2'!AC35 -> 0 | F16: ='明细表H8-2'!AD35+'明细表H8-2'!AE35+'明细表H8-2'!AF35-'明细表H8-2'!AG35-'明细表H8-2'!AH35-'明细表H8-2'!AI35 -> 0 | G16: =E16+F16 -> 0 | H16: =G16-D16 -> 0 | I16: =IF(AND(D16=0,H16=0),0,IF(AND(D16=0,H16>0),1,H16/D16)) -> 0
A17: =A10 -> 运输设备 | B17: ='明细表H8-2'!W36 -> 0 | C17: ='明细表H8-2'!AD36 -> 0 | D17: =B17+C17 -> 0 | E17: ='明细表H8-2'!AC36 -> 0 | F17: ='明细表H8-2'!AD36+'明细表H8-2'!AE36+'明细表H8-2'!AF36-'明细表H8-2'!AG36-'明细表H8-2'!AH36-'明细表H8-2'!AI36 -> 0 | G17: =E17+F17 -> 0 | H17: =G17-D17 -> 0 | I17: =IF(AND(D17=0,H17=0),0,IF(AND(D17=0,H17>0),1,H17/D17)) -> 0
A18: =A11 -> 办公设备 | B18: ='明细表H8-2'!W37 -> 0 | C18: ='明细表H8-2'!AD37 -> 0 | D18: =B18+C18 -> 0 | E18: ='明细表H8-2'!AC37 -> 0 | F18: ='明细表H8-2'!AD37+'明细表H8-2'!AE37+'明细表H8-2'!AF37-'明细表H8-2'!AG37-'明细表H8-2'!AH37-'明细表H8-2'!AI37 -> 0 | G18: =E18+F18 -> 0 | H18: =G18-D18 -> 0 | I18: =IF(AND(D18=0,H18=0),0,IF(AND(D18=0,H18>0),1,H18/D18)) -> 0
A19: =A12 -> 其他设备 | B19: ='明细表H8-2'!W38 -> 0 | C19: ='明细表H8-2'!AD38 -> 0 | D19: =B19+C19 -> 0 | E19: ='明细表H8-2'!AC38 -> 0 | F19: ='明细表H8-2'!AD38+'明细表H8-2'!AE38+'明细表H8-2'!AF38-'明细表H8-2'!AG38-'明细表H8-2'!AH38-'明细表H8-2'!AI38 -> 0 | G19: =E19+F19 -> 0 | H19: =G19-D19 -> 0 | I19: =IF(AND(D19=0,H19=0),0,IF(AND(D19=0,H19>0),1,H19/D19)) -> 0
A20: 合计 | B20: =SUM(B15:B19) -> 0 | C20: =SUM(C15:C19) -> 0 | D20: =SUM(D15:D19) -> 0 | E20: =SUM(E15:E19) -> 0 | F20: =SUM(F15:F19) -> 0 | G20: =SUM(G15:G19) -> 0 | H20: =G20-D20 -> 0 | I20: =IF(AND(D20=0,H20=0),0,IF(AND(D20=0,H20>0),1,H20/D20)) -> 0
A21: 三、减值准备
A22: =A15 -> 房屋及建筑物 | B22: ='明细表H8-2'!AN34 -> 0 | C22: ='明细表H8-2'!AU34 -> 0 | D22: =B22+C22 -> 0 | E22: ='明细表H8-2'!AT34 -> 0 | F22: ='明细表H8-2'!AU34+'明细表H8-2'!AV34+'明细表H8-2'!AW34-'明细表H8-2'!AX34-'明细表H8-2'!AY34-'明细表H8-2'!AZ34 -> 0 | G22: =E22+F22 -> 0 | H22: =G22-D22 -> 0 | I22: =IF(AND(D22=0,H22=0),0,IF(AND(D22=0,H22>0),1,H22/D22)) -> 0
A23: =A16 -> 机器设备 | B23: ='明细表H8-2'!AN35 -> 0 | C23: ='明细表H8-2'!AU35 -> 0 | D23: =B23+C23 -> 0 | E23: ='明细表H8-2'!AT35 -> 0 | F23: ='明细表H8-2'!AU35+'明细表H8-2'!AV35+'明细表H8-2'!AW35-'明细表H8-2'!AX35-'明细表H8-2'!AY35-'明细表H8-2'!AZ35 -> 0 | G23: =E23+F23 -> 0 | H23: =G23-D23 -> 0 | I23: =IF(AND(D23=0,H23=0),0,IF(AND(D23=0,H23>0),1,H23/D23)) -> 0
A24: =A17 -> 运输设备 | B24: ='明细表H8-2'!AN36 -> 0 | C24: ='明细表H8-2'!AU36 -> 0 | D24: =B24+C24 -> 0 | E24: ='明细表H8-2'!AT36 -> 0 | F24: ='明细表H8-2'!AU36+'明细表H8-2'!AV36+'明细表H8-2'!AW36-'明细表H8-2'!AX36-'明细表H8-2'!AY36-'明细表H8-2'!AZ36 -> 0 | G24: =E24+F24 -> 0 | H24: =G24-D24 -> 0 | I24: =IF(AND(D24=0,H24=0),0,IF(AND(D24=0,H24>0),1,H24/D24)) -> 0
A25: =A18 -> 办公设备 | B25: ='明细表H8-2'!AN37 -> 0 | C25: ='明细表H8-2'!AU37 -> 0 | D25: =B25+C25 -> 0 | E25: ='明细表H8-2'!AT37 -> 0 | F25: ='明细表H8-2'!AU37+'明细表H8-2'!AV37+'明细表H8-2'!AW37-'明细表H8-2'!AX37-'明细表H8-2'!AY37-'明细表H8-2'!AZ37 -> 0 | G25: =E25+F25 -> 0 | H25: =G25-D25 -> 0 | I25: =IF(AND(D25=0,H25=0),0,IF(AND(D25=0,H25>0),1,H25/D25)) -> 0
A26: =A19 -> 其他设备 | B26: ='明细表H8-2'!AN38 -> 0 | C26: ='明细表H8-2'!AU38 -> 0 | D26: =B26+C26 -> 0 | E26: ='明细表H8-2'!AT38 -> 0 | F26: ='明细表H8-2'!AU38+'明细表H8-2'!AV38+'明细表H8-2'!AW38-'明细表H8-2'!AX38-'明细表H8-2'!AY38-'明细表H8-2'!AZ38 -> 0 | G26: =E26+F26 -> 0 | H26: =G26-D26 -> 0 | I26: =IF(AND(D26=0,H26=0),0,IF(AND(D26=0,H26>0),1,H26/D26)) -> 0
A27: 合计 | B27: =SUM(B22:B26) -> 0 | C27: =SUM(C22:C26) -> 0 | D27: =SUM(D22:D26) -> 0 | E27: =SUM(E22:E26) -> 0 | F27: =SUM(F22:F26) -> 0 | G27: =SUM(G22:G26) -> 0 | H27: =G27-D27 -> 0 | I27: =IF(AND(D27=0,H27=0),0,IF(AND(D27=0,H27>0),1,H27/D27)) -> 0
A28: 四、净值
A29: =A22 -> 房屋及建筑物 | B29: =B8-B15-B22 -> 0 | C29: =C8-C15-C22 -> 0 | D29: =D8-D15-D22 -> 0 | E29: =E8-E15-E22 -> 0 | F29: =F8-F15-F22 -> 0 | G29: =G8-G15-G22 -> 0 | H29: =G29-D29 -> 0 | I29: =IF(AND(D29=0,H29=0),0,IF(AND(D29=0,H29>0),1,H29/D29)) -> 0
A30: =A23 -> 机器设备 | B30: =B9-B16-B23 -> 0 | C30: =C9-C16-C23 -> 0 | D30: =D9-D16-D23 -> 0 | E30: =E9-E16-E23 -> 0 | F30: =F9-F16-F23 -> 0 | G30: =G9-G16-G23 -> 0 | H30: =G30-D30 -> 0 | I30: =IF(AND(D30=0,H30=0),0,IF(AND(D30=0,H30>0),1,H30/D30)) -> 0
A31: =A24 -> 运输设备 | B31: =B10-B17-B24 -> 0 | C31: =C10-C17-C24 -> 0 | D31: =D10-D17-D24 -> 0 | E31: =E10-E17-E24 -> 0 | F31: =F10-F17-F24 -> 0 | G31: =G10-G17-G24 -> 0 | H31: =G31-D31 -> 0 | I31: =IF(AND(D31=0,H31=0),0,IF(AND(D31=0,H31>0),1,H31/D31)) -> 0
A32: =A25 -> 办公设备 | B32: =B11-B18-B25 -> 0 | C32: =C11-C18-C25 -> 0 | D32: =D11-D18-D25 -> 0 | E32: =E11-E18-E25 -> 0 | F32: =F11-F18-F25 -> 0 | G32: =G11-G18-G25 -> 0 | H32: =G32-D32 -> 0 | I32: =IF(AND(D32=0,H32=0),0,IF(AND(D32=0,H32>0),1,H32/D32)) -> 0
A33: =A26 -> 其他设备 | B33: =B12-B19-B26 -> 0 | C33: =C12-C19-C26 -> 0 | D33: =D12-D19-D26 -> 0 | E33: =E12-E19-E26 -> 0 | F33: =F12-F19-F26 -> 0 | G33: =G12-G19-G26 -> 0 | H33: =G33-D33 -> 0 | I33: =IF(AND(D33=0,H33=0),0,IF(AND(D33=0,H33>0),1,H33/D33)) -> 0
A34: 合计 | B34: =SUM(B29:B33) -> 0 | C34: =SUM(C29:C33) -> 0 | D34: =SUM(D29:D33) -> 0 | E34: =SUM(E29:E33) -> 0 | F34: =SUM(F29:F33) -> 0 | G34: =SUM(G29:G33) -> 0 | H34: =G34-D34 -> 0 | I34: =IF(AND(D34=0,H34=0),0,IF(AND(D34=0,H34>0),1,H34/D34)) -> 0
A35: 试算平衡表数
A36: 差异 | D36: =D34-D35 -> 0 | G36: =G34-G35 -> 0
A37: 1、审计说明：
A38: （1）使用权资产期末净值较期初净值增加（负数为减少）：
A39: 主要原因（比例超过30%的）：
A41: （2）采用简化处理方法的情况说明：（短期租赁、低价值资产和未纳入租赁负债计量的可变租赁付款额当期计入费用的情况）
A43: （3）转租情况说明：（转租使用权资产取得的收入）
A45: 2、审计结论：

Sheet 附注披露信息（上市公司）
A1: 致同会计师事务所
A2: 附注披露表（上市公司）
A3: =底稿目录!A2 -> 被审计单位： | C3: =底稿目录!A4 -> 编制人： | E3: =底稿目录!A6 -> 编制日期： | F3: 索引号：
A4: =底稿目录!A3 -> 截止日：202X年12月31日 | C4: =底稿目录!A5 -> 复核人： | E4: =底稿目录!A7 -> 复核日期： | F4: 页 次：
A6: 项 目 | B6: 房屋及建筑物 | C6: 机器设备 | D6: 运输设备 | E6: …… | F6: 合 计 | G6: 返回目录
A7: 一、账面原值：
A8: 1.期初余额
A9: 2.本期增加金额
A10: （1）租入
A11: （2）租赁负债调整
A12: ……
A13: 3.本期减少金额
A14: （1）转租赁为融资租赁
A15: （2）转让或持有待售
A16: （3）其他减少
A17: ……
A18: 4. 期末余额
... A48: 注意：1、本年执行减值测试的，即使未计提减值，也要参照上述要求披露。2、估计可收回金额时通常不应使用重置成本法。】

Sheet 附注披露信息（国企）
A1: 致同会计师事务所
A2: 附注披露信息（国有企业）
A3: =底稿目录!A2 -> 被审计单位： | B3: =底稿目录!A4 -> 编制人： | D3: =底稿目录!A6 -> 编制日期： | E3: 索引号：
A4: =底稿目录!A3 -> 截止日：202X年12月31日 | B4: =底稿目录!A5 -> 复核人： | D4: =底稿目录!A7 -> 复核日期： | E4: 页 次：
A6: 项 目 | B6: 期初余额 | C6: 本期增加 | D6: 本期减少 | E6: 期末余额 | F6: 返回目录
A7: 一、账面原值合计 | B7: XX | C7: XX | D7: XX | E7: XX
A8: 其中：土地
A9: 房屋、建筑物
A10: 机器、运输、办公设备
A11: 其他
A12: 二、累计折旧合计 | B12: XX | C12: XX | D12: XX | E12: XX
A13: 其中：土地
A14: 房屋、建筑物
A15: 机器、运输、办公设备
A16: 其他
A17: 三、使用权资产账面净值合计 | B17: XX | C17: —— | D17: —— | E17: XX
A18: 其中：土地 | C18: —— | D18: ——
A19: 房屋、建筑物 | C19: —— | D19: ——
A20: 机器、运输、办公设备 | C20: —— | D20: ——
A21: 其他 | C21: —— | D21: ——
A22: 四、减值准备合计 | B22: XX | C22: XX | D22: XX | E22: XX
A23: 其中：土地
A24: 房屋、建筑物
A25: 机器、运输、办公设备
A26: 其他 | B26: XX | C26: XX | D26: XX | E26: XX
A27: 五、使用权资产账面价值合计 | B27: XX | C27: —— | D27: —— | E27: XX
A28: 其中：土地 | C28: —— | D28: ——
A29: 房屋、建筑物 | C29: —— | D29: ——
A30: 机器、运输、办公设备 | C30: —— | D30: ——
A31: 其他 | B31: XX | C31: —— | D31: —— | E31: XX

Sheet 明细表H8-2
A1: 致同会计师事务所 | W1: 致同会计师事务所 | AN1: 致同会计师事务所
A2: 使用权资产、累计折旧及减值准备明细表 | W2: 使用权资产、累计折旧及减值准备明细表 | AN2: 使用权资产、累计折旧及减值准备明细表
A3: =底稿目录!A2 -> 被审计单位： | G3: =底稿目录!A4 -> 编制人： | P3: =底稿目录!A6 -> 编制日期： | U3: 索引号： | V3: H8-2 | AC3: =底稿目录!A4 -> 编制人： | AI3: =底稿目录!A6 -> 编制日期： | AL3: 索引号： | AM3: H8-2 | AT3: =底稿目录!A4 -> 编制人： | BA3: =AI3 -> 编制日期： | BE3: 索引号： | BF3: H8-2
A4: =底稿目录!A3 -> 截止日：202X年12月31日 | G4: =底稿目录!A5 -> 复核人： | P4: =底稿目录!A7 -> 复核日期： | U4: 页 次： | AC4: =底稿目录!A5 -> 复核人： | AI4: =底稿目录!A7 -> 复核日期： | AL4: 页 次： | AT4: =底稿目录!A5 -> 复核人： | BA4: =AI4 -> 复核日期： | BE4: 页 次：
A5: 一、审计目标：
A6: 1. 资产负债表中记录的使用权资产是存在的，且已记录于恰当的账户；2. 所有应记录的使用权资产均已记录，所有应当包括在财务报表中的相关披露均已包括；3.使用权资产以恰当的金额包括在财务报表中，与之相关的计价或分摊调整已恰当记录，相关披露已得到恰当计量和描述。
A7: 二、审计过程：
A8: 使用权资产类别 | B8: 使用权资产名称 | C8: 使用权资产编号 | D8: 使用权资产原值 | W8: 累计折旧 | AN8: 减值准备 | BE8: 审定净值
D9: 期初数 | E9: 未审数 | L9: 期初调整 | M9: 账项调整 | S9: 审定数 | W9: 期初数 | X9: 未审数 | AD9: 期初调整 | AE9: 账项调整 | AJ9: 审定数 | AN9: 期初数 | AO9: 未审数 | AU9: 期初调整 | AV9: 账项调整 | BA9: 审定数
E10: 本期增加 | H10: 本期减少 | K10: 期末数 | M10: 本期增加 | P10: 本期减少 | S10: 期初数 | T10: 本期增加 | U10: 本期减少 | V10: 期末数 | X10: 本期增加 | Z10: 本期减少 | AC10: 期末数 | AE10: 本期增加 | AG10: 本期减少 | AJ10: 期初数 | AK10: 本期增加 | AL10: 本期减少 | AM10: 期末数 | AO10: 本期增加 | AQ10: 本期减少 | AT10: 期末数 | AV10: 本期增加 | AX10: 本期减少 | BA10: 期初数 | BB10: 本期增加 | BC10: 本期减少 | BD10: 期末数 | BE10: 期初净值 | BF10: 期末净值
E11: 本期租入 | F11: 租赁负债调整 | G11: 其他增加 | H11: 转租赁为融资租赁 | I11: 转让或持有待售 | J11: 其他减少 | M11: 本期租入 | N11: 租赁负债调整 | O11: 其他增加 | P11: 转租赁为融资租赁 | Q11: 转让或持有待售 | R11: 其他减少 | X11: 本期计提 | Y11: 其他增加 | Z11: 转租赁为融资租赁 | AA11: 转让或持有待售 | AB11: 其他减少 | AE11: 本期计提 | AF11: 其他增加 | AG11: 转租赁为融资租赁 | AH11: 转让或持有待售 | AI11: 其他减少 | AO11: 本期计提 | AP11: 其他增加 | AQ11: 转租赁为融资租赁 | AR11: 转让或持有待售 | AS11: 其他减少 | AV11: 本期计提 | AW11: 其他增加 | AX11: 转租赁为融资租赁 | AY11: 转让或持有待售 | AZ11: 其他减少
K12: =SUM(D12:G12)-SUM(H12:J12) -> 0 | S12: =D12+L12 -> 0 | T12: =(E12+F12+G12)+M12+N12+O12 -> 0 | U12: =(H12+I12+J12)+P12+Q12+R12 -> 0 | V12: =S12+T12-U12 -> 0 | AC12: =SUM(W12:Y12)-SUM(Z12:AB12) -> 0 | AJ12: =W12+AD12 -> 0 | AK12: =X12+AE12+Y12+AF12 -> 0 | AL12: =Z12+AI12+AB12+AA12+AG12+AH12 -> 0 | AM12: =AJ12+AK12-AL12 -> 0 | AT12: =SUM(AN12:AP12)-SUM(AQ12:AS12) -> 0 | BA12: =AN12+AU12 -> 0 | BB12: =AO12+AV12+AP12+AW12 -> 0 | BC12: =AQ12+AZ12+AS12+AR12+AX12+AY12 -> 0 | BD12: =BA12+BB12-BC12 -> 0 | BE12: =S12-AJ12-BA12 -> 0 | BF12: =V12-AM12-BD12 -> 0
K13: =SUM(D13:G13)-SUM(H13:J13) -> 0 | S13: =D13+L13 -> 0 | T13: =(E13+F13+G13)+M13+N13+O13 -> 0 | U13: =(H13+I13+J13)+P13+Q13+R13 -> 0 | V13: =S13+T13-U13 -> 0 | AC13: =SUM(W13:Y13)-SUM(Z13:AB13) -> 0 | AJ13: =W13+AD13 -> 0 | AK13: =X13+AE13+Y13+AF13 -> 0 | AL13: =Z13+AI13+AB13+AA13+AG13+AH13 -> 0 | AM13: =AJ13+AK13-AL13 -> 0 | AT13: =SUM(AN13:AP13)-SUM(AQ13:AS13) -> 0 | BA13: =AN13+AU13 -> 0 | BB13: =AO13+AV13+AP13+AW13 -> 0 | BC13: =AQ13+AZ13+AS13+AR13+AX13+AY13 -> 0 | BD13: =BA13+BB13-BC13 -> 0 | BE13: =S13-AJ13-BA13 -> 0 | BF13: =V13-AM13-BD13 -> 0
K14: =SUM(D14:G14)-SUM(H14:J14) -> 0 | S14: =D14+L14 -> 0 | T14: =(E14+F14+G14)+M14+N14+O14 -> 0 | U14: =(H14+I14+J14)+P14+Q14+R14 -> 0 | V14: =S14+T14-U14 -> 0 | AC14: =SUM(W14:Y14)-SUM(Z14:AB14) -> 0 | AJ14: =W14+AD14 -> 0 | AK14: =X14+AE14+Y14+AF14 -> 0 | AL14: =Z14+AI14+AB14+AA14+AG14+AH14 -> 0 | AM14: =AJ14+AK14-AL14 -> 0 | AT14: =SUM(AN14:AP14)-SUM(AQ14:AS14) -> 0 | BA14: =AN14+AU14 -> 0 | BB14: =AO14+AV14+AP14+AW14 -> 0 | BC14: =AQ14+AZ14+AS14+AR14+AX14+AY14 -> 0 | BD14: =BA14+BB14-BC14 -> 0 | BE14: =S14-AJ14-BA14 -> 0 | BF14: =V14-AM14-BD14 -> 0
K15: =SUM(D15:G15)-SUM(H15:J15) -> 0 | S15: =D15+L15 -> 0 | T15: =(E15+F15+G15)+M15+N15+O15 -> 0 | U15: =(H15+I15+J15)+P15+Q15+R15 -> 0 | V15: =S15+T15-U15 -> 0 | AC15: =SUM(W15:Y15)-SUM(Z15:AB15) -> 0 | AJ15: =W15+AD15 -> 0 | AK15: =X15+AE15+Y15+AF15 -> 0 | AL15: =Z15+AI15+AB15+AA15+AG15+AH15 -> 0 | AM15: =AJ15+AK15-AL15 -> 0 | AT15: =SUM(AN15:AP15)-SUM(AQ15:AS15) -> 0 | BA15: =AN15+AU15 -> 0 | BB15: =AO15+AV15+AP15+AW15 -> 0 | BC15: =AQ15+AZ15+AS15+AR15+AX15+AY15 -> 0 | BD15: =BA15+BB15-BC15 -> 0 | BE15: =S15-AJ15-BA15 -> 0 | BF15: =V15-AM15-BD15 -> 0
K16: =SUM(D16:G16)-SUM(H16:J16) -> 0 | S16: =D16+L16 -> 0 | T16: =(E16+F16+G16)+M16+N16+O16 -> 0 | U16: =(H16+I16+J16)+P16+Q16+R16 -> 0 | V16: =S16+T16-U16 -> 0 | AC16: =SUM(W16:Y16)-SUM(Z16:AB16) -> 0 | AJ16: =W16+AD16 -> 0 | AK16: =X16+AE16+Y16+AF16 -> 0 | AL16: =Z16+AI16+AB16+AA16+AG16+AH16 -> 0 | AM16: =AJ16+AK16-AL16 -> 0 | AT16: =SUM(AN16:AP16)-SUM(AQ16:AS16) -> 0 | BA16: =AN16+AU16 -> 0 | BB16: =AO16+AV16+AP16+AW16 -> 0 | BC16: =AQ16+AZ16+AS16+AR16+AX16+AY16 -> 0 | BD16: =BA16+BB16-BC16 -> 0 | BE16: =S16-AJ16-BA16 -> 0 | BF16: =V16-AM16-BD16 -> 0
K17: =SUM(D17:G17)-SUM(H17:J17) -> 0 | S17: =D17+L17 -> 0 | T17: =(E17+F17+G17)+M17+N17+O17 -> 0 | U17: =(H17+I17+J17)+P17+Q17+R17 -> 0 | V17: =S17+T17-U17 -> 0 | AC17: =SUM(W17:Y17)-SUM(Z17:AB17) -> 0 | AJ17: =W17+AD17 -> 0 | AK17: =X17+AE17+Y17+AF17 -> 0 | AL17: =Z17+AI17+AB17+AA17+AG17+AH17 -> 0 | AM17: =AJ17+AK17-AL17 -> 0 | AT17: =SUM(AN17:AP17)-SUM(AQ17:AS17) -> 0 | BA17: =AN17+AU17 -> 0 | BB17: =AO17+AV17+AP17+AW17 -> 0 | BC17: =AQ17+AZ17+AS17+AR17+AX17+AY17 -> 0 | BD17: =BA17+BB17-BC17 -> 0 | BE17: =S17-AJ17-BA17 -> 0 | BF17: =V17-AM17-BD17 -> 0
K18: =SUM(D18:G18)-SUM(H18:J18) -> 0 | S18: =D18+L18 -> 0 | T18: =(E18+F18+G18)+M18+N18+O18 -> 0 | U18: =(H18+I18+J18)+P18+Q18+R18 -> 0 | V18: =S18+T18-U18 -> 0 | AC18: =SUM(W18:Y18)-SUM(Z18:AB18) -> 0 | AJ18: =W18+AD18 -> 0 | AK18: =X18+AE18+Y18+AF18 -> 0 | AL18: =Z18+AI18+AB18+AA18+AG18+AH18 -> 0 | AM18: =AJ18+AK18-AL18 -> 0 | AT18: =SUM(AN18:AP18)-SUM(AQ18:AS18) -> 0 | BA18: =AN18+AU18 -> 0 | BB18: =AO18+AV18+AP18+AW18 -> 0 | BC18: =AQ18+AZ18+AS18+AR18+AX18+AY18 -> 0 | BD18: =BA18+BB18-BC18 -> 0 | BE18: =S18-AJ18-BA18 -> 0 | BF18: =V18-AM18-BD18 -> 0
K19: =SUM(D19:G19)-SUM(H19:J19) -> 0 | S19: =D19+L19 -> 0 | T19: =(E19+F19+G19)+M19+N19+O19 -> 0 | U19: =(H19+I19+J19)+P19+Q19+R19 -> 0 | V19: =S19+T19-U19 -> 0 | AC19: =SUM(W19:Y19)-SUM(Z19:AB19) -> 0 | AJ19: =W19+AD19 -> 0 | AK19: =X19+AE19+Y19+AF19 -> 0 | AL19: =Z19+AI19+AB19+AA19+AG19+AH19 -> 0 | AM19: =AJ19+AK19-AL19 -> 0 | AT19: =SUM(AN19:AP19)-SUM(AQ19:AS19) -> 0 | BA19: =AN19+AU19 -> 0 | BB19: =AO19+AV19+AP19+AW19 -> 0 | BC19: =AQ19+AZ19+AS19+AR19+AX19+AY19 -> 0 | BD19: =BA19+BB19-BC19 -> 0 | BE19: =S19-AJ19-BA19 -> 0 | BF19: =V19-AM19-BD19 -> 0
K20: =SUM(D20:G20)-SUM(H20:J20) -> 0 | S20: =D20+L20 -> 0 | T20: =(E20+F20+G20)+M20+N20+O20 -> 0 | U20: =(H20+I20+J20)+P20+Q20+R20 -> 0 | V20: =S20+T20-U20 -> 0 | AC20: =SUM(W20:Y20)-SUM(Z20:AB20) -> 0 | AJ20: =W20+AD20 -> 0 | AK20: =X20+AE20+Y20+AF20 -> 0 | AL20: =Z20+AI20+AB20+AA20+AG20+AH20 -> 0 | AM20: =AJ20+AK20-AL20 -> 0 | AT20: =SUM(AN20:AP20)-SUM(AQ20:AS20) -> 0 | BA20: =AN20+AU20 -> 0 | BB20: =AO20+AV20+AP20+AW20 -> 0 | BC20: =AQ20+AZ20+AS20+AR20+AX20+AY20 -> 0 | BD20: =BA20+BB20-BC20 -> 0 | BE20: =S20-AJ20-BA20 -> 0 | BF20: =V20-AM20-BD20 -> 0
K21: =SUM(D21:G21)-SUM(H21:J21) -> 0 | S21: =D21+L21 -> 0 | T21: =(E21+F21+G21)+M21+N21+O21 -> 0 | U21: =(H21+I21+J21)+P21+Q21+R21 -> 0 | V21: =S21+T21-U21 -> 0 | AC21: =SUM(W21:Y21)-SUM(Z21:AB21) -> 0 | AJ21: =W21+AD21 -> 0 | AK21: =X21+AE21+Y21+AF21 -> 0 | AL21: =Z21+AI21+AB21+AA21+AG21+AH21 -> 0 | AM21: =AJ21+AK21-AL21 -> 0 | AT21: =SUM(AN21:AP21)-SUM(AQ21:AS21) -> 0 | BA21: =AN21+AU21 -> 0 | BB21: =AO21+AV21+AP21+AW21 -> 0 | BC21: =AQ21+AZ21+AS21+AR21+AX21+AY21 -> 0 | BD21: =BA21+BB21-BC21 -> 0 | BE21: =S21-AJ21-BA21 -> 0 | BF21: =V21-AM21-BD21 -> 0
K22: =SUM(D22:G22)-SUM(H22:J22) -> 0 | S22: =D22+L22 -> 0 | T22: =(E22+F22+G22)+M22+N22+O22 -> 0 | U22: =(H22+I22+J22)+P22+Q22+R22 -> 0 | V22: =S22+T22-U22 -> 0 | AC22: =SUM(W22:Y22)-SUM(Z22:AB22) -> 0 | AJ22: =W22+AD22 -> 0 | AK22: =X22+AE22+Y22+AF22 -> 0 | AL22: =Z22+AI22+AB22+AA22+AG22+AH22 -> 0 | AM22: =AJ22+AK22-AL22 -> 0 | AT22: =SUM(AN22:AP22)-SUM(AQ22:AS22) -> 0 | BA22: =AN22+AU22 -> 0 | BB22: =AO22+AV22+AP22+AW22 -> 0 | BC22: =AQ22+AZ22+AS22+AR22+AX22+AY22 -> 0 | BD22: =BA22+BB22-BC22 -> 0 | BE22: =S22-AJ22-BA22 -> 0 | BF22: =V22-AM22-BD22 -> 0
K23: =SUM(D23:G23)-SUM(H23:J23) -> 0 | S23: =D23+L23 -> 0 | T23: =(E23+F23+G23)+M23+N23+O23 -> 0 | U23: =(H23+I23+J23)+P23+Q23+R23 -> 0 | V23: =S23+T23-U23 -> 0 | AC23: =SUM(W23:Y23)-SUM(Z23:AB23) -> 0 | AJ23: =W23+AD23 -> 0 | AK23: =X23+AE23+Y23+AF23 -> 0 | AL23: =Z23+AI23+AB23+AA23+AG23+AH23 -> 0 | AM23: =AJ23+AK23-AL23 -> 0 | AT23: =SUM(AN23:AP23)-SUM(AQ23:AS23) -> 0 | BA23: =AN23+AU23 -> 0 | BB23: =AO23+AV23+AP23+AW23 -> 0 | BC23: =AQ23+AZ23+AS23+AR23+AX23+AY23 -> 0 | BD23: =BA23+BB23-BC23 -> 0 | BE23: =S23-AJ23-BA23 -> 0 | BF23: =V23-AM23-BD23 -> 0
... K31: =SUM(D31:G31)-SUM(H31:J31) -> 0 | S31: =D31+L31 -> 0 | T31: =(E31+F31+G31)+M31+N31+O31 -> 0 | U31: =(H31+I31+J31)+P31+Q31+R31 -> 0 | V31: =S31+T31-U31 -> 0 | AC31: =SUM(W31:Y31)-SUM(Z31:AB31) -> 0 | AJ31: =W31+AD31 -> 0 | AK31: =X31+AE31+Y31+AF31 -> 0 | AL31: =Z31+AI31+AB31+AA31+AG31+AH31 -> 0 | AM31: =AJ31+AK31-AL31 -> 0 | AT31: =SUM(AN31:AP31)-SUM(AQ31:AS31) -> 0 | BA31: =AN31+AU31 -> 0 | BB31: =AO31+AV31+AP31+AW31 -> 0 | BC31: =AQ31+AZ31+AS31+AR31+AX31+AY31 -> 0 | BD31: =BA31+BB31-BC31 -> 0 | BE31: =S31-AJ31-BA31 -> 0 | BF31: =V31-AM31-BD31 -> 0
A32: 合计 | D32: =SUM(D12:D31) -> 0 | E32: =SUM(E12:E31) -> 0 | F32: =SUM(F12:F31) -> 0 | G32: =SUM(G12:G31) -> 0 | H32: =SUM(H12:H31) -> 0 | I32: =SUM(I12:I31) -> 0 | J32: =SUM(J12:J31) -> 0 | K32: =SUM(K12:K31) -> 0 | ... BF32: =SUM(BF12:BF31) -> 0
A33: 其中：
A34: =底稿目录!A9 -> 房屋及建筑物 | D34: =SUMPRODUCT(($A$12:$A$31=$A34)*(D$12:D$31)) -> 0 | E34: =SUMPRODUCT(($A$12:$A$31=$A34)*(E$12:E$31)) -> 0 | F34: =SUMPRODUCT(($A$12:$A$31=$A34)*(F$12:F$31)) -> 0 | G34: =SUMPRODUCT(($A$12:$A$31=$A34)*(G$12:G$31)) -> 0 | H34: =SUMPRODUCT(($A$12:$A$31=$A34)*(H$12:H$31)) -> 0 | I34: =SUMPRODUCT(($A$12:$A$31=$A34)*(I$12:I$31)) -> 0 | J34: =SUMPRODUCT(($A$12:$A$31=$A34)*(J$12:J$31)) -> 0 | K34: =SUMPRODUCT(($A$12:$A$31=$A34)*(K$12:K$31)) -> 0 | ... BF34: =SUMPRODUCT(($A$12:$A$31=$A34)*(BF$12:BF$31)) -> 0
A35: =底稿目录!A10 -> 机器设备 | D35: =SUMPRODUCT(($A$12:$A$31=$A35)*(D$12:D$31)) -> 0 | E35: =SUMPRODUCT(($A$12:$A$31=$A35)*(E$12:E$31)) -> 0 | F35: =SUMPRODUCT(($A$12:$A$31=$A35)*(F$12:F$31)) -> 0 | G35: =SUMPRODUCT(($A$12:$A$31=$A35)*(G$12:G$31)) -> 0 | H35: =SUMPRODUCT(($A$12:$A$31=$A35)*(H$12:H$31)) -> 0 | I35: =SUMPRODUCT(($A$12:$A$31=$A35)*(I$12:I$31)) -> 0 | J35: =SUMPRODUCT(($A$12:$A$31=$A35)*(J$12:J$31)) -> 0 | K35: =SUMPRODUCT(($A$12:$A$31=$A35)*(K$12:K$31)) -> 0 | ... P35: =SUMPRODUCT(($A$12:$A$31=$A35)*(P$12:P$31)) -> 0 | Q35: {=SUMPRODUCT(($A$12:$A$31=$A35)*(Q$12:Q$31))} -> 0 | R35: {=SUMPRODUCT(($A$12:$A$31=$A35)*(R$12:R$31))} -> 0 | S35: {=SUMPRODUCT(($A$12:$A$31=$A35)*(S$12:S$31))} -> 0 | T35: {=SUMPRODUCT(($A$12:$A$31=$A35)*(T$12:T$31))} -> 0 | U35: =SUMPRODUCT(($A$12:$A$31=$A35)*(U$12:U$31)) -> 0 | V35: =SUMPRODUCT(($A$12:$A$31=$A35)*(V$12:V$31)) -> 0 | W35: =SUMPRODUCT(($A$12:$A$31=$A35)*(W$12:W$31)) -> 0 | X35: =SUMPRODUCT(($A$12:$A$31=$A35)*(X$12:X$31)) -> 0 | Y35: =SUMPRODUCT(($A$12:$A$31=$A35)*(Y$12:Y$31)) -> 0 | Z35: =SUMPRODUCT(($A$12:$A$31=$A35)*(Z$12:Z$31)) -> 0 | AA35: =SUMPRODUCT(($A$12:$A$31=$A35)*(AA$12:AA$31)) -> 0 | AB35: =SUMPRODUCT(($A$12:$A$31=$A35)*(AB$12:AB$31)) -> 0 | ... BF35: =SUMPRODUCT(($A$12:$A$31=$A35)*(BF$12:BF$31)) -> 0
A36: =底稿目录!A11 -> 运输设备 | D36: =SUMPRODUCT(($A$12:$A$31=$A36)*(D$12:D$31)) -> 0 | E36: =SUMPRODUCT(($A$12:$A$31=$A36)*(E$12:E$31)) -> 0 | F36: =SUMPRODUCT(($A$12:$A$31=$A36)*(F$12:F$31)) -> 0 | G36: =SUMPRODUCT(($A$12:$A$31=$A36)*(G$12:G$31)) -> 0 | H36: =SUMPRODUCT(($A$12:$A$31=$A36)*(H$12:H$31)) -> 0 | I36: =SUMPRODUCT(($A$12:$A$31=$A36)*(I$12:I$31)) -> 0 | J36: =SUMPRODUCT(($A$12:$A$31=$A36)*(J$12:J$31)) -> 0 | K36: =SUMPRODUCT(($A$12:$A$31=$A36)*(K$12:K$31)) -> 0 | ... BF36: =SUMPRODUCT(($A$12:$A$31=$A36)*(BF$12:BF$31)) -> 0
A37: =底稿目录!A12 -> 办公设备 | D37: =SUMPRODUCT(($A$12:$A$31=$A37)*(D$12:D$31)) -> 0 | E37: =SUMPRODUCT(($A$12:$A$31=$A37)*(E$12:E$31)) -> 0 | F37: =SUMPRODUCT(($A$12:$A$31=$A37)*(F$12:F$31)) -> 0 | G37: =SUMPRODUCT(($A$12:$A$31=$A37)*(G$12:G$31)) -> 0 | H37: =SUMPRODUCT(($A$12:$A$31=$A37)*(H$12:H$31)) -> 0 | I37: =SUMPRODUCT(($A$12:$A$31=$A37)*(I$12:I$31)) -> 0 | J37: =SUMPRODUCT(($A$12:$A$31=$A37)*(J$12:J$31)) -> 0 | K37: =SUMPRODUCT(($A$12:$A$31=$A37)*(K$12:K$31)) -> 0 | ... BF37: =SUMPRODUCT(($A$12:$A$31=$A37)*(BF$12:BF$31)) -> 0
A38: =底稿目录!A13 -> 其他设备 | D38: =SUMPRODUCT(($A$12:$A$31=$A38)*(D$12:D$31)) -> 0 | E38: =SUMPRODUCT(($A$12:$A$31=$A38)*(E$12:E$31)) -> 0 | F38: =SUMPRODUCT(($A$12:$A$31=$A38)*(F$12:F$31)) -> 0 | G38: =SUMPRODUCT(($A$12:$A$31=$A38)*(G$12:G$31)) -> 0 | H38: =SUMPRODUCT(($A$12:$A$31=$A38)*(H$12:H$31)) -> 0 | I38: =SUMPRODUCT(($A$12:$A$31=$A38)*(I$12:I$31)) -> 0 | J38: =SUMPRODUCT(($A$12:$A$31=$A38)*(J$12:J$31)) -> 0 | K38: =SUMPRODUCT(($A$12:$A$31=$A38)*(K$12:K$31)) -> 0 | ... BF38: =SUMPRODUCT(($A$12:$A$31=$A38)*(BF$12:BF$31)) -> 0
D39: 三、审计说明： | N39: 四、审计结论：
A45: 提示： | W45: 编制说明： | AN45: 编制说明：
A46: 1.承租人会计处理不再区分经营租赁和融资租赁，而是采用单一的会计处理模型，也就是说，除采用简化处理的短期租赁和低价值资产租赁外， | W46: 承租人通常应当自租赁期开始日起按月计提使用权资产的折旧。 | AN46: 在租赁期开始日后，承租人应当按照《企业会计准则第8号——资产减值》的规定，确定使用权资产是否发生减值，并对已识别的减值损失进行会计处理。
A47: 2.对所有租赁均确认使用权资产和租赁负债，参照固定资产准则对使用权资产计提折旧，采用固定的周期性利率确认每期利息费用。 | W47: 当月计提确有困难的，也可从下月起计提折旧，并在附注中予以披露。 | AN47: 使用权资产减值准备一旦计提，不得转回。
A48: 3.审计说明可以概述:(1)程序的测试情况、结果;(2)拟调整事项及其调整分录、未调整事项及其影响，审计范围受到限制情况及其影响。
A49: 4.审计结论可参考：A、未见异常。 B、除上述重大不符事项应当作为调整事项予以调整外，其余未见异常。 C、由于存在以下重大未调整事项(或审计范围受到限制无法获取充分、适当证据)，不可确认。

Sheet 调整分录汇总H8-3
A1: 致同会计师事务所
A2: 使用权资产调整分录汇总表
A3: =底稿目录!A2 -> 被审计单位： | D3: =底稿目录!A4 -> 编制人： | G3: =底稿目录!A6 -> 编制日期： | I3: 索引号： | J3: H8-3
A4: =底稿目录!A3 -> 截止日：202X年12月31日 | D4: =底稿目录!A5 -> 复核人： | G4: =底稿目录!A7 -> 复核日期： | I4: 页 次：
A5: 调整事项说明 | B5: 类别（报表调整/账项调整/其他） | C5: 报表项目 | D5: 科目名称 | E5: 附注项目 | F5: …… | G5: 借方调整金额 | H5: 贷方调整金额 | I5: 索引 | J5: 备注
A24: 提示：本底稿适用于调整分录较多、较复杂的项目，且仅列示与本报表项目相关的审计调整。项目组可根据项目实际情况选择是否使用该底稿。

Sheet 租赁的识别H8-4
A1: 致同会计师事务所
A2: 租赁的识别
A3: =底稿目录!A2 -> 被审计单位： | D3: =底稿目录!A4 -> 编制人： | E3: =底稿目录!A6 -> 编制日期： | F3: 索引号： | G3: H8-4
A4: =底稿目录!A3 -> 截止日：202X年12月31日 | D4: =底稿目录!A5 -> 复核人： | E4: =底稿目录!A7 -> 复核日期： | F4: 页 次：
A5: 一、审计目标：
A6: 1. 资产负债表中记录的使用权资产是存在的，且已记录于恰当的账户；2. 所有应记录的使用权资产均已记录，所有应当包括在财务报表中的相关披露均已包括；3. 使用权资产以恰当的金额包括在财务报表中，与之相关的计价或分摊调整已恰当记录，相关披露已得到恰当计量和描述。
A7: 二、审计过程：
A9: 1. 租赁的识别
A10: 要素（同时满足） | C10: 公司具体情况 | F10: 是否满足 | G10: 索引
A11: （1）是否存在已识别资产 | F11: =IF(AND(F12="是",F13="否"),"是","否") -> 否 | H11: 通常由合同明确指定，也可以在资产可供客户使用时隐性指定
A12: ①物理可区分 | H12: 如果资产的部分产能在物理上可区分(例如，建筑物的一层)，则该部分产能属于已识别资产
A13: ②供应方实质性替换权 | H13: 如果资产供应方在整个使用期间拥有对该资产的实质性替换权，则该资产不属于已识别资产 | I13: 如果合同仅赋予资产供应方在特定日期或者特定事件发生日或之后拥有替换资产的权利或义务，考虑到资产供应方没有在整个使用期间替换资产的实际能力，资产供应方的替换权不具有实质性。 与资产位于资产供应方所在地相比， 如果资产位于客户所在地或其他位置，替换资产所需要的成本更有可能超过其所能获取的利益。资产供应方在资产运行结果不佳或者进行技术升级的情况下，因修理和维护而替换资产的权利或义务不属于实质性替换权。
A14: 同时符合下列条件时，表明资产供应方拥有资产的实质性替换权：拥有在整个使用期间替换资产的实际能力；通过行使替换资产的权利将获得经济利益。 | H14: 例如，客户无法阻止供应方替换资产，且用于替换的资产对于资产供应方而言易于获得或者可以在合理期间内取得； 替换资产的预期经济利益将超过替换资产所得成本。
A15: （2）是否有权约定使用期间主导已识别资产的使用 | H15: 合同中包含旨在保护资产供应方在已识别资产或其他资产中的权益、保护资产供应方的工作人员或者确保资产供应方不因客户使用租赁资产而违反法律法规的条款和条件，本身不足以否定客户拥有主导资产使用的权利。 | I15: 在合同中，"一定期间" 也可以表述为已识别资产的使用量，例如，某项设备的产出量。如果客户有权在部分合同期内控制已识别资产的使用，则合同包含一项在该部分合同期间的租赁。
A16: ①有权在整个使用期间主导已识别资产的使用目的和使用方式；或 | H16: 如果客户有权在整个使用期间在合同界定的使用权范围内改变资产的使用目的和使用方式，则视为客户有权在该使用期间主导资产的使用目的和使用方式。 | I16: 在判断客户是否有权在整个使用期间主导，已识别资产的使用目的和使用方式时，企业应当考虑在该使用期间与改变资产的使用目的和使用方式最为相关的决策权。相关决策权是指对使用资产所产生的经济利益产生影响的决策权。
A17: ②已识别资产的使用目的和使用方式在使用期间前已预先确定，并且： | H17: 例如，通过设计资产或在合同中对资产的使用做出限制来预先确定相关决策
A18: 有权在整个使用期间自行或主导他人按照其确定的方式运营该资产；或 | H18: 除非资产(或资产的特定方面) 由客户设计，企业应当仅考虑在使用期间对资产使用做出决策的权利。 | I18: 如果客户仅能在使用期间之前指定资产的产出而没有与资产使用相关的任何其他决策权，则该客户享有的权利与任何购买该项商品或服务的其他客户享有的权利并无不同。
A19: 设计了已识别资产(或资产的特定方面)并在设计时已预先确定了该资产在整个使用期间的使用目的和使用方式 | H19: 例如，电厂的使用目的和使用方式，即是否发电、发电时间和发电量；卡车的使用目的和使用方式，即在规定时间内将指定货物从A地运至B地
A20: （3）是否有权获得在使用期间内因使用已识别资产所产生的几乎全部经济利益 | H20: 应当在约定的客户权利范围内考虑其所产生的经济利益； 应当有权获得整个使用期间使用该资产所产生的几乎全部经济利益(例如，在整个使用期间独家使用该资产) | I20: 使用资产所产生的经济利益包括资产的主要产出和副产品(包括来源于这些项目的潜在现金流量)以及通过与第三方之间的商业交易实现的其他经济利益。 如果合同规定客户应向资产供应方或另一方支付因使用资产所产生的部分现金流量作为对价，该现金流量仍应视为客户因使用资产而获得的经济利益的一部分。
A21: 结 论 | C21: =IF(AND(F11="是",F15="是",F20="是"),"合同为租赁或者包含租赁","不包含租赁") -> 不包含租赁
A23: 2.租赁的分拆 | E23: 是否适用
A24: 条件（同时满足） | C24: 公司具体情况 | F24: 是否满足 | G24: 索引
A25: （1）承租人可从单独使用该资产或将其与易于获得的其他资源一起使用中获利； | H25: 易于获得的资源是指出租人或其他供应方单独销售或出租的商品或服务， 或者承租人已从出租人或其他交易中获得的资源
A26: （2）该资产与合同中的其他资产不存在高度依赖或高度关联关系。 | H26: 若承租人租入资产的决定不会对承租人使用合同中的其他资产的权利产生重大影响，则表明该项资产与合同中的其他资产不存在高度依赖或高度关联关系
A27: 结 论 | C27: =IF(AND(F25="是",F26="是"),"构成合同中的一项单独租赁","无须分拆") -> 无须分拆 | I27: 在分拆合同包含的租赁和非租赁部分时，承租人应当按照各项租赁部分单独价格及非租赁部分的单独价格之和的相对比例分担合同对价。
A28: 注1：合同中同时包含多项单独租赁的，承租人和出租人应当将合同予以分拆，并分别各项单独租赁进行会计处理。
A29: 注2：为简化处理，承租人可以按照租赁资产的类别选择是否分拆合同包含的租赁和非租赁部分。
A31: 3.租赁的合并 | E31: 是否适用
A32: 条件（任一） | C32: 公司具体情况 | F32: 是否满足 | G32: 索引
A33: （1）该两份或多份合同基于总体商业目的而订立并构成一揽子交易，若不作为整体考虑则无法理解其总体商业目的； | H33: 在该情况下，对每份合同独立进行会计处理可能无法忠实反映（faithful representation）整个交易
A34: （2）该两份或多份合同中的某份合同的对价金额取决于其他合同的定价或履行情况；
A35: （3）该两份或多份合同让渡的资产使用权合起来构成一项单独租赁。
A36: 结 论 | C36: =IF(OR(F33="是",F34="是",F35="是"),"应当合并为一份合同进行会计处理","单项租赁") -> 单项租赁
A37: 注：两份或多份合同合并为一份合同进行会计处理的，仍然需要区分该一份合同中的租赁部分和非租赁部分。
A39: 4. 短期租赁 | E39: 是否适用 | F39: 是
A40: 条件（同时满足） | C40: 公司具体情况 | F40: 是否满足 | G40: 索引
A41: （1）租赁期不超过12个月 | F41: =IF(AND(F42="是",F43="是"),"是","否") -> 否 | H41: 短期租赁，是指在租赁期开始日，租赁期不超过12个月的租赁
A42: 考虑续租选择权后租赁期不超过12个月 | F42: 是
A43: 续签合同租赁期不超过12个月 | F43: 否
A44: （2）不包含购买选择权 | F44: 是 | H44: 包含购买选择权的租赁不属于短期租赁
A45: 结 论 | C45: =IF(AND(F41="是",F44="是"),"属于短期租赁","不属于短期租赁") -> 不属于短期租赁
A46: 注1：对于短期租赁，承租人应当按照租赁资产的类别作出本准则第三十二条所述的会计处理选择。如房屋建筑物、机器设备、设车辆等类别。
A47: 注2：按照简化会计处理的短期租赁发生租赁变更或者其他原因导致租赁期发生变化的，承租人应当将其视为一项新租赁，重新按照上述原则
A48: 判断项新租赁是否可以选择简化会计处理。
A50: 5.低价值资产租赁 | E50: 是否适用
A51: 条件（同时满足） | C51: 公司具体情况 | G51: 索引
A52: （1）单项租赁资产为全新资产时价值较低（如低于人民币40 000元） | H52: 应基于租赁资产的全新状态下的价值进行评估，不应考虑资产已被使用的年限。 低价值资产租赁的标准应该是一个绝对金额，不受承租人规模、性质等影响、也不考虑该资产对于承租人或相关租赁交易的重要性。
A53: （2）并未转租赁或者并不预期要把相关资产进行转租赁 | H53: 如果承租人已经或者预期要把相关资产进行转租赁，则不能将原租赁按照低价值资产租赁进行简化会计处理。
A54: 结 论 | C54: =IF(AND(F52="是",F53="是"),"属于低价值资产租赁","不属于低价值资产租赁") -> 不属于低价值资产租赁
A55: 注：对于低价值资产租赁，承租人可根据每项租赁的具体情况作出本准则第三十二条所述的会计处理选择。
A56: 三、审计说明：
A59: 四、审计结论：
A62: 提示：
A63: 在合同开始日，企业应当评估合同是否为租赁或者包含租赁。
A86: 除非合同条款或条件发生变化，企业无需重新评估合同是否为租赁或者是否包含租赁。
A88: 第三十二条 对于短期租赁和低价值资产租赁，承租人可以选择不确认使用权资产和租赁负债。
A89: 作出该选择的，承租人应当将短期租赁和低价值资产租赁的租赁付款额，在租赁期内各个期间按照直线法或其他系统合理的方法计入相关资产成本或当期损益。
A90: 其他系统合理的方法能够更好地反映承租人的受益模式的，承租人应当采用该方法。

Sheet 租赁期的确定H8-5
A1: 致同会计师事务所
A2: 租赁期的确定
A3: =底稿目录!A2 -> 被审计单位： | C3: =底稿目录!A4 -> 编制人： | D3: =底稿目录!A6 -> 编制日期： | E3: 索引号： | F3: H8-5
A4: =底稿目录!A3 -> 截止日：202X年12月31日 | C4: =底稿目录!A5 -> 复核人： | D4: =底稿目录!A7 -> 复核日期： | E4: 页 次：
A5: 一、审计目标：
A6: 1. 资产负债表中记录的使用权资产是存在的，且已记录于恰当的账户；2. 所有应记录的使用权资产均已记录，所有应当包括在财务报表中的相关披露均已包括；3. 使用权资产以恰当的金额包括在财务报表中，与之相关的计价或分摊调整已恰当记录，相关披露已得到恰当计量和描述。
A7: 二、审计过程：
A9: 1. 租赁期的确定【承租人有权使用租赁资产且不可撤销的期间】
A10: 项目 | C10: 合同信息 | E10: 是否包含 | F10: 索引
A11: （1）租赁协议约定的起租日或租金起付日 | E11: 不包含 | G11: 租赁协议中对起租日或租金支付时间的约定，并不影响租赁期开始日的判断。
A12: （2）租赁期开始日【出租人提供租赁资产使其可供承租人使用的起始日期】 | E12: 包含 | G12: 租赁期自租赁期开始日起计算，并包括出租人为承租人提供的免租期。 如果承租人在租赁协议约定的起租日或租金起付日之前，已获得对租赁资产使用权的控制，则表明租赁期已经开始。
A13: （3）不可撤销期间 | G13: 在确定租赁期和评估不可撤销租赁期间时，企业应根据租赁条款约定确定可强制执行合同的期间。
A14: ①仅出租人有权终止租赁，则不可撤销的租赁期包括终止租赁选择权所涵盖的期间； | E14: 包含 | G14: 如果只有出租人有权终止租赁，则不可撤销的租赁期包括终止租赁选择权所涵盖的期间。
A15: ②如果只有承租人有权终止租赁，则在确定租赁期时，应将该项权利视为承租人可行使的终止租赁选择权予以考虑； | G15: 应当评估承租人是否合理确定将不行使终止租赁选择权，需考虑的因素详见下（4）。 合理确定将不会行使终止租赁选择权的，租赁期应包括终止租赁选择权涵盖的期间。 | H15: 通常，租赁的不可撤销期间越短，承租人不行使终止租赁选择权的可能性就越大。
A16: ③双方均有权单方面终止，且罚款金额不重大。 | E16: 不包含 | G16: 如果承租人和出租人双方均有权在未经另一方许可的情况下终止租赁，且罚款金额不重大，则该租赁不再可强制执行。 | H16: 应当对罚款作出广义解释以同时涵盖终止租赁付款及其他类型的经济处罚，包括弃置或拆卸不可移除的租赁改良所发生的成本。
A17: （4）续租选择权涵盖的期间 | G17: 应当评估承租人是否合理确定将行使续租选择权。 合理确定将行使续租选择权的，租赁期应包括续租选择权涵盖的期间。 | H17: 同等条件下优先续约不是无条件续约的权利，不属于续约选择权（续约选择权是公司的一项权利，只要公司愿意，都可以无条件续约）
A18: 考虑对承租人行使续租选择权带来经济利益的所有相关事实和情况 | G18: 需考虑的因素：①与市价相比，选择权期间的合同条款和条件；②在合同期内，承租人进行或预期进行重大租赁资产改良；③与终止租赁相关的成本；④租赁资产对承租人运营的重要程度；⑤与行使选择权相关的条件及满足相关条件的可能性。
A19: 与租赁的其他条款相结合判断 | G19: 例如，无论承租人是否行使选择权，均保证向出租人支付基本相等的最低或固定现金，在此情形下，应假设承租人合理确定将行使续租选择权选择权。
A20: （5）购买选择权 | G20: 购买选择权的评估方式应与续租选择权或终止租赁选择权的评估方式相同，购买选择权在经济上与将租赁期延长至租赁资产全部剩余经济寿命的续租选择权类似。
A21: 确定的租赁期（结构化·供H8-6引用）
B22: 起租日 | C22: 44197 | D22: 约满日 | E22: 47848 | F22: 租赁期(月) | G22: =(YEAR($E$22)-YEAR($C$22))*12+MONTH($E$22)-MONTH($C$22)+1 -> 120 | H22: 租赁期(年) | I22: =MAX(1,ROUND($G$22/12,0)) -> 10
A23: 2. 对租赁期和购买选择权的重新评估
A24: 2.1 承租人可控范围内的重大事件或变化的情形 | D24: 是否适用 | E24: 是
A25: 情形 | C25: 合同信息 | E25: 是/否 | F25: 索引
A26: ①重大租赁资产改良 | E26: 是 | G26: 在租赁期开始日未预计到的重大租赁资产改良，在可行使续租选择权、终止租赁选择权或购买选择权时，预期将为承租人带来重大经济利益 | H26: 发生承租人可控范围内的重大事件或变化，且影响承租人是否合理确定将行使相应选择权的，承租人应当对其是否合理确定将行使续租选择权、购买选择权或不行使终止租赁选择权进行重新评估，并根据重新评估结果修改租赁期
A27: ②租赁资产的重大改动或定制化调整 | G27: 在租赁期开始日未预计到的租赁资产的重大改动或定制化调整
A28: ③直接相关的经营决策 | G28: 承租人做出的与行使或不行使选择权直接相关的经营决策。例如，决定续租互补性资产、处置可替代的资产或处置包含相关使用权资产的业务
A29: 结 论 | C29: =IF(OR(E26="是",E27="是",E28="是"),"应当重新评估是否合理确定将行使续租选择权、购买选择权或不行使终止租赁选择权","无需重新评估") -> 应当重新评估是否合理确定将行使续租选择权、购买选择权或不行使终止租赁选择权
A31: 2.2 根据重新评估结果修改租赁期 | D31: 是否适用 | E31: 是
A32: 情形 | C32: 合同信息 | E32: 是/否 | F32: 索引
A33: （1）承租人实际行使了选择权，但该选择权在之前企业确定租赁期时未涵盖； | E33: 是
A34: （2）承租人未实际行使选择权但该选择权在之前企业确定租赁期时已涵盖；
A35: （3）某些事件的发生，导致根据合同规定承租人有义务行使选择权，但该选择权在之前企业确定租赁期时未涵盖；
A36: （4）某些事件的发生，导致根据合同规定禁止承租人行使选择权，但该选择权在之前企业确定租赁期时已涵盖。
A37: 重新确定的租赁期
A39: 三、审计说明：
A42: 四、审计结论：
A45: 提示：
A46: 租赁期是指承租人有权使用租赁资产且不可撤销的期间。
A47: 租赁期自租赁期开始日起计算。

Sheet 使用权资产 租赁负债初始及后续计量（按年）H8-6
A1: 致同会计师事务所
A2: 使用权资产 租赁负债初始及后续计量（按年）
A3: =底稿目录!A2 -> 被审计单位： | D3: =底稿目录!A4 -> 编制人： | F3: =底稿目录!A6 -> 编制日期： | H3: 索引号： | I3: H8-6
A4: =底稿目录!A3 -> 截止日：202X年12月31日 | D4: =底稿目录!A5 -> 复核人： | F4: =底稿目录!A7 -> 复核日期： | H4: 页 次：
A5: 一、审计目标：确认使用权资产与租赁负债按 CAS21 以恰当金额初始确认并后续计量；初始计量：使用权资产=租赁付款额现值(未付部分)+租赁期开始日或之前支付的租赁付款额+初始直接费用+预计复原成本−租赁激励；租赁负债=尚未支付的租赁付款额按增量借款利率/内含利率折现；后续：负债按实际利率法摊余成本，资产按直线法(或其他系统合理方法)折旧，折旧期=min(租赁期,使用寿命)（能合理确定取得所有权时取使用寿命）；相关递延所得税与披露恰当。
A6: 二、审计过程：①核对合同/H8-4识别结论与H8-5租赁期（含续租/终止选择权）；②复核折现率（优先合同内含利率，否则增量借款利率）与付款时点（期初/期末）；③验算表2现值合计=表3负债期初，使用权资产入账=现值+预付+初始直接费用±复原/激励；④抽查后续利息=(期初负债−本期付款)×年折现率、折旧=入账价值/摊销年限，期末勾稽H8-1/H9；⑤复杂长租、非固定年付或需月结时改用「按月」表，并与本表年化结果交叉复核。索引：H8-4 / H8-5 / H8-7 / H8-8 / H9。
A7: 1. 租赁合同的基本信息（H8-5带入 + L9动态期数 + Q9付款时点）
A8: 使用权资产名称 | B8: 租赁期开始日 | C8: 合同约定初始期满日 | D8: 续租期（年） | E8: 租赁期（考虑续租可能后） | F8: 租赁期截止日期 | G8: 增量借款利率 | H8: 折现率 | I8: 使用权资产摊销期限（年） | J8: 适用税率 | K8: 年租金(不含税) | L8: 有效付款期数(年) | M8: 初始直接费用 | N8: 自动自检 | Q8: 付款时点
A9: XX设备 | B9: ='租赁期的确定H8-5'!C22 -> 44197 | C9: 47118 | D9: =2 -> 2 | E9: =(YEAR(C9)-YEAR(B9))+D9+(MONTH(C9)-MONTH(B9)+1)/12 -> 10 | F9: =DATE(YEAR(C9)+D9,MONTH(C9),DAY(C9)) -> 47848 | G9: 0.05 | H9: =G9 -> 0.05 | I9: 10 | J9: 0.25 | K9: 50000 | L9: ='租赁期的确定H8-5'!I22 -> 10 | M9: 15000 | N9: =IF(OR($L$9="",$L$9<1),"待填期数",IF(ABS(INDEX($F$39:$F$50,$L$9))<1,"✓负债期末≈0","×查负债摊销")) -> ✓负债期末≈0 | O9: =IF(OR($L$9="",$L$9<1),"待填期数",IF(ABS(INDEX($I$39:$I$50,MIN($L$9,$I$9)))<1,"✓折旧折尽","×查折旧/寿命")) -> ✓折旧折尽 | P9: =IF(ABS($B$16-$C$16)<0.01,"✓计算区借贷平衡","×计算区不平衡") -> ✓计算区借贷平衡 | Q9: 期初
A10: 【编制入口·必填黄格】先填H8-5的C22起租日/E22约满日 → 本表B9/L9自动带入；再填K9年租金、M9初始直接费用、G9折现率、Q9付款时点(期初/期末)、I9摊销年限。
A11: 计 算 区 域
B12: 借 | C12: 贷 | F12: 借 | G12: 贷
A13: 使用权资产 | B13: =I34 -> 420391.08 | E13: 递延所得税资产 | F13: =J39 -> 93290.159
A14: 租赁负债 | C14: =F34 -> 355391.08 | E14: 递延所得税负债 | G14: =K39 -> 94587.994
A15: 预付租金+初始直接费用 | C15: =H34+G34 -> 65000 | E15: 所得税费用 | F15: =G14-F13 -> 1297.8344
B16: =SUM(B13:B15) -> 420391.08 | C16: =SUM(C13:C15) -> 420391.08
A18: 2. 计算租赁负债余额（L9动态期数 + Q9付款时点，最多30年）
A19: 租金支付日期 | B19: 剩余合同租金（不含税） | C19: 租赁付款额原值 | D19: 租赁负债折现期(年) | E19: 租赁负债折现系数 | F19: 租赁付款额现值 | G19: 租赁预付款 | H19: 初始直接费用 | I19: 使用权资产初始确认金额 | L19: Q9=期初：第0期进预付；Q9=期末：折现期从1起、无租金预付。年租金K9，期数L9（H8-5）。
A20: =IF($L$9>0,$B$9,"") -> 44197 | B20: =IF($L$9>0,$K$9,0) -> 50000 | C20: =IF(OR($L$9<=0,D20="",AND($Q$9<>"期末",D20=0)),0,B20) -> 0 | D20: =IF($L$9>0,IF($Q$9="期末",0+1,0),"") -> 0 | E20: =IF($L$9>0,1/(1+$H$9)^D20,"") -> 1 | F20: =IF($L$9>0,C20*E20,0) -> 0 | G20: =IF(AND($L$9>0,$Q$9<>"期末",D20=0),B20,0) -> 50000 | H20: =$M$9 -> 15000
A21: =IF($L$9>1,DATE(YEAR(A20)+1,MONTH(A20),DAY(A20)),"") -> 44562 | B21: =IF($L$9>1,$K$9,0) -> 50000 | C21: =IF(OR($L$9<=1,D21="",AND($Q$9<>"期末",D21=0)),0,B21) -> 50000 | D21: =IF($L$9>1,IF($Q$9="期末",1+1,1),"") -> 1 | E21: =IF($L$9>1,1/(1+$H$9)^D21,"") -> 0.95238095 | F21: =IF($L$9>1,C21*E21,0) -> 47619.048 | G21: =IF(AND($L$9>1,$Q$9<>"期末",D21=0),B21,0) -> 0 | H21: 0
A22: =IF($L$9>2,DATE(YEAR(A21)+1,MONTH(A21),DAY(A21)),"") -> 44927 | B22: =IF($L$9>2,$K$9,0) -> 50000 | C22: =IF(OR($L$9<=2,D22="",AND($Q$9<>"期末",D22=0)),0,B22) -> 50000 | D22: =IF($L$9>2,IF($Q$9="期末",2+1,2),"") -> 2 | E22: =IF($L$9>2,1/(1+$H$9)^D22,"") -> 0.90702948 | F22: =IF($L$9>2,C22*E22,0) -> 45351.474 | G22: =IF(AND($L$9>2,$Q$9<>"期末",D22=0),B22,0) -> 0 | H22: 0
A23: =IF($L$9>3,DATE(YEAR(A22)+1,MONTH(A22),DAY(A22)),"") -> 45292 | B23: =IF($L$9>3,$K$9,0) -> 50000 | C23: =IF(OR($L$9<=3,D23="",AND($Q$9<>"期末",D23=0)),0,B23) -> 50000 | D23: =IF($L$9>3,IF($Q$9="期末",3+1,3),"") -> 3 | E23: =IF($L$9>3,1/(1+$H$9)^D23,"") -> 0.8638376 | F23: =IF($L$9>3,C23*E23,0) -> 43191.88 | G23: =IF(AND($L$9>3,$Q$9<>"期末",D23=0),B23,0) -> 0 | H23: 0
A24: =IF($L$9>4,DATE(YEAR(A23)+1,MONTH(A23),DAY(A23)),"") -> 45658 | B24: =IF($L$9>4,$K$9,0) -> 50000 | C24: =IF(OR($L$9<=4,D24="",AND($Q$9<>"期末",D24=0)),0,B24) -> 50000 | D24: =IF($L$9>4,IF($Q$9="期末",4+1,4),"") -> 4 | E24: =IF($L$9>4,1/(1+$H$9)^D24,"") -> 0.82270247 | F24: =IF($L$9>4,C24*E24,0) -> 41135.124 | G24: =IF(AND($L$9>4,$Q$9<>"期末",D24=0),B24,0) -> 0 | H24: 0
A25: =IF($L$9>5,DATE(YEAR(A24)+1,MONTH(A24),DAY(A24)),"") -> 46023 | B25: =IF($L$9>5,$K$9,0) -> 50000 | C25: =IF(OR($L$9<=5,D25="",AND($Q$9<>"期末",D25=0)),0,B25) -> 50000 | D25: =IF($L$9>5,IF($Q$9="期末",5+1,5),"") -> 5 | E25: =IF($L$9>5,1/(1+$H$9)^D25,"") -> 0.78352617 | F25: =IF($L$9>5,C25*E25,0) -> 39176.308 | G25: =IF(AND($L$9>5,$Q$9<>"期末",D25=0),B25,0) -> 0 | H25: 0
A26: =IF($L$9>6,DATE(YEAR(A25)+1,MONTH(A25),DAY(A25)),"") -> 46388 | B26: =IF($L$9>6,$K$9,0) -> 50000 | C26: =IF(OR($L$9<=6,D26="",AND($Q$9<>"期末",D26=0)),0,B26) -> 50000 | D26: =IF($L$9>6,IF($Q$9="期末",6+1,6),"") -> 6 | E26: =IF($L$9>6,1/(1+$H$9)^D26,"") -> 0.7462154 | F26: =IF($L$9>6,C26*E26,0) -> 37310.77 | G26: =IF(AND($L$9>6,$Q$9<>"期末",D26=0),B26,0) -> 0 | H26: 0
A27: =IF($L$9>7,DATE(YEAR(A26)+1,MONTH(A26),DAY(A26)),"") -> 46753 | B27: =IF($L$9>7,$K$9,0) -> 50000 | C27: =IF(OR($L$9<=7,D27="",AND($Q$9<>"期末",D27=0)),0,B27) -> 50000 | D27: =IF($L$9>7,IF($Q$9="期末",7+1,7),"") -> 7 | E27: =IF($L$9>7,1/(1+$H$9)^D27,"") -> 0.71068133 | F27: =IF($L$9>7,C27*E27,0) -> 35534.067 | G27: =IF(AND($L$9>7,$Q$9<>"期末",D27=0),B27,0) -> 0 | H27: 0
A28: =IF($L$9>8,DATE(YEAR(A27)+1,MONTH(A27),DAY(A27)),"") -> 47119 | B28: =IF($L$9>8,$K$9,0) -> 50000 | C28: =IF(OR($L$9<=8,D28="",AND($Q$9<>"期末",D28=0)),0,B28) -> 50000 | D28: =IF($L$9>8,IF($Q$9="期末",8+1,8),"") -> 8 | E28: =IF($L$9>8,1/(1+$H$9)^D28,"") -> 0.67683936 | F28: =IF($L$9>8,C28*E28,0) -> 33841.968 | G28: =IF(AND($L$9>8,$Q$9<>"期末",D28=0),B28,0) -> 0 | H28: 0
A29: =IF($L$9>9,DATE(YEAR(A28)+1,MONTH(A28),DAY(A28)),"") -> 47484 | B29: =IF($L$9>9,$K$9,0) -> 50000 | C29: =IF(OR($L$9<=9,D29="",AND($Q$9<>"期末",D29=0)),0,B29) -> 50000 | D29: =IF($L$9>9,IF($Q$9="期末",9+1,9),"") -> 9 | E29: =IF($L$9>9,1/(1+$H$9)^D29,"") -> 0.64460892 | F29: =IF($L$9>9,C29*E29,0) -> 32230.446 | G29: =IF(AND($L$9>9,$Q$9<>"期末",D29=0),B29,0) -> 0 | H29: 0
A30: =IF($L$9>26,DATE(YEAR(#REF!)+1,MONTH(#REF!),DAY(#REF!)),"") | B30: =IF($L$9>26,$K$9,0) -> 0 | C30: =IF(OR($L$9<=26,D30="",AND($Q$9<>"期末",D30=0)),0,B30) -> 0 | D30: =IF($L$9>26,IF($Q$9="期末",26+1,26),"") | E30: =IF($L$9>26,1/(1+$H$9)^D30,"") | F30: =IF($L$9>26,C30*E30,0) -> 0 | G30: =IF(AND($L$9>26,$Q$9<>"期末",D30=0),B30,0) -> 0 | H30: 0
A31: =IF($L$9>27,DATE(YEAR(A30)+1,MONTH(A30),DAY(A30)),"") | B31: =IF($L$9>27,$K$9,0) -> 0 | C31: =IF(OR($L$9<=27,D31="",AND($Q$9<>"期末",D31=0)),0,B31) -> 0 | D31: =IF($L$9>27,IF($Q$9="期末",27+1,27),"") | E31: =IF($L$9>27,1/(1+$H$9)^D31,"") | F31: =IF($L$9>27,C31*E31,0) -> 0 | G31: =IF(AND($L$9>27,$Q$9<>"期末",D31=0),B31,0) -> 0 | H31: 0
A32: =IF($L$9>28,DATE(YEAR(A31)+1,MONTH(A31),DAY(A31)),"") | B32: =IF($L$9>28,$K$9,0) -> 0 | C32: =IF(OR($L$9<=28,D32="",AND($Q$9<>"期末",D32=0)),0,B32) -> 0 | D32: =IF($L$9>28,IF($Q$9="期末",28+1,28),"") | E32: =IF($L$9>28,1/(1+$H$9)^D32,"") | F32: =IF($L$9>28,C32*E32,0) -> 0 | G32: =IF(AND($L$9>28,$Q$9<>"期末",D32=0),B32,0) -> 0 | H32: 0
A33: =IF($L$9>29,DATE(YEAR(A32)+1,MONTH(A32),DAY(A32)),"") | B33: =IF($L$9>29,$K$9,0) -> 0 | C33: =IF(OR($L$9<=29,D33="",AND($Q$9<>"期末",D33=0)),0,B33) -> 0 | D33: =IF($L$9>29,IF($Q$9="期末",29+1,29),"") | E33: =IF($L$9>29,1/(1+$H$9)^D33,"") | F33: =IF($L$9>29,C33*E33,0) -> 0 | G33: =IF(AND($L$9>29,$Q$9<>"期末",D33=0),B33,0) -> 0 | H33: 0
A34: 合计 | B34: =SUM(B20:B33) -> 500000 | C34: =SUM(C20:C33) -> 450000 | F34: =SUM(F20:F33) -> 355391.08 | G34: =SUM(G20:G33) -> 50000 | H34: =SUM(H20:H33) -> 15000 | I34: =F34+G34+H34 -> 420391.08
A36: 3. 租赁负债及使用权资产后续计量（随L9/Q9动态）
A37: 期间 | B37: 租赁负债 | G37: 使用权资产 | J37: 对应递延所得税资产 | K37: 对应递延所得税负债
B38: 期初余额 | C38: 租赁付款额 | D38: 支付月份 | E38: 利息费用 | F38: 期末余额 | G38: 期初余额 | H38: 折旧费用 | I38: 期末余额
A39: =IF($L$9>0,TEXT(YEAR($B$9)+0,"0")&"年度","") -> 2021年度 | B39: =IF($L$9>0,F34,0) -> 355391.08 | C39: =IF($L$9>0,C20,0) -> 0 | D39: =IF($L$9>0,MONTH($B$9),"") -> 1 | E39: =IF($L$9>0,IF($Q$9="期末",B39*$H$9,(B39-C39)*$H$9),0) -> 17769.554 | F39: =IF($L$9>0,IF($Q$9="期末",B39+E39-C39,B39-C39+E39),0) -> 373160.64 | G39: =IF($L$9>0,I34,0) -> 420391.08 | H39: =IF(AND($L$9>0,0<MIN($L$9,$I$9)),$I$34/MIN($L$9,$I$9),0) -> 42039.108 | I39: =IF($L$9>0,G39-H39,0) -> 378351.98 | J39: =IF($L$9>0,F39*$J$9,0) -> 93290.159 | K39: =IF($L$9>0,I39*$J$9,0) -> 94587.994
A40: =IF($L$9>1,TEXT(YEAR($B$9)+1,"0")&"年度","") -> 2022年度 | B40: =IF($L$9>1,B39-C39+E39,0) -> 373160.64 | C40: =IF($L$9>1,C21,0) -> 50000 | D40: =IF($L$9>1,MONTH($B$9),"") -> 1 | E40: =IF($L$9>1,IF($Q$9="期末",B40*$H$9,(B40-C40)*$H$9),0) -> 16158.032 | F40: =IF($L$9>1,IF($Q$9="期末",B40+E40-C40,B40-C40+E40),0) -> 339318.67 | G40: =IF($L$9>1,I39,0) -> 378351.98 | H40: =IF(AND($L$9>1,1<MIN($L$9,$I$9)),$I$34/MIN($L$9,$I$9),0) -> 42039.108 | I40: =IF($L$9>1,G40-H40,0) -> 336312.87 | J40: =IF($L$9>1,F40*$J$9,0) -> 84829.667 | K40: =IF($L$9>1,I40*$J$9,0) -> 84078.217
A41: =IF($L$9>2,TEXT(YEAR($B$9)+2,"0")&"年度","") -> 2023年度 | B41: =IF($L$9>2,B40-C40+E40,0) -> 339318.67 | C41: =IF($L$9>2,C22,0) -> 50000 | D41: =IF($L$9>2,MONTH($B$9),"") -> 1 | E41: =IF($L$9>2,IF($Q$9="期末",B41*$H$9,(B41-C41)*$H$9),0) -> 14465.933 | F41: =IF($L$9>2,IF($Q$9="期末",B41+E41-C41,B41-C41+E41),0) -> 303784.6 | G41: =IF($L$9>2,I40,0) -> 336312.87 | H41: =IF(AND($L$9>2,2<MIN($L$9,$I$9)),$I$34/MIN($L$9,$I$9),0) -> 42039.108 | I41: =IF($L$9>2,G41-H41,0) -> 294273.76 | J41: =IF($L$9>2,F41*$J$9,0) -> 75946.151 | K41: =IF($L$9>2,I41*$J$9,0) -> 73568.44
A42: =IF($L$9>3,TEXT(YEAR($B$9)+3,"0")&"年度","") -> 2024年度 | B42: =IF($L$9>3,B41-C41+E41,0) -> 303784.6 | C42: =IF($L$9>3,C23,0) -> 50000 | D42: =IF($L$9>3,MONTH($B$9),"") -> 1 | E42: =IF($L$9>3,IF($Q$9="期末",B42*$H$9,(B42-C42)*$H$9),0) -> 12689.23 | F42: =IF($L$9>3,IF($Q$9="期末",B42+E42-C42,B42-C42+E42),0) -> 266473.83 | G42: =IF($L$9>3,I41,0) -> 294273.76 | H42: =IF(AND($L$9>3,3<MIN($L$9,$I$9)),$I$34/MIN($L$9,$I$9),0) -> 42039.108 | I42: =IF($L$9>3,G42-H42,0) -> 252234.65 | J42: =IF($L$9>3,F42*$J$9,0) -> 66618.458 | K42: =IF($L$9>3,I42*$J$9,0) -> 63058.663
A43: =IF($L$9>4,TEXT(YEAR($B$9)+4,"0")&"年度","") -> 2025年度 | B43: =IF($L$9>4,B42-C42+E42,0) -> 266473.83 | C43: =IF($L$9>4,C24,0) -> 50000 | D43: =IF($L$9>4,MONTH($B$9),"") -> 1 | E43: =IF($L$9>4,IF($Q$9="期末",B43*$H$9,(B43-C43)*$H$9),0) -> 10823.692 | F43: =IF($L$9>4,IF($Q$9="期末",B43+E43-C43,B43-C43+E43),0) -> 227297.53 | G43: =IF($L$9>4,I42,0) -> 252234.65 | H43: =IF(AND($L$9>4,4<MIN($L$9,$I$9)),$I$34/MIN($L$9,$I$9),0) -> 42039.108 | I43: =IF($L$9>4,G43-H43,0) -> 210195.54 | J43: =IF($L$9>4,F43*$J$9,0) -> 56824.381 | K43: =IF($L$9>4,I43*$J$9,0) -> 52548.885
A44: =IF($L$9>5,TEXT(YEAR($B$9)+5,"0")&"年度","") -> 2026年度 | B44: =IF($L$9>5,B43-C43+E43,0) -> 227297.53 | C44: =IF($L$9>5,C25,0) -> 50000 | D44: =IF($L$9>5,MONTH($B$9),"") -> 1 | E44: =IF($L$9>5,IF($Q$9="期末",B44*$H$9,(B44-C44)*$H$9),0) -> 8864.8763 | F44: =IF($L$9>5,IF($Q$9="期末",B44+E44-C44,B44-C44+E44),0) -> 186162.4 | G44: =IF($L$9>5,I43,0) -> 210195.54 | H44: =IF(AND($L$9>5,5<MIN($L$9,$I$9)),$I$34/MIN($L$9,$I$9),0) -> 42039.108 | I44: =IF($L$9>5,G44-H44,0) -> 168156.43 | J44: =IF($L$9>5,F44*$J$9,0) -> 46540.6 | K44: =IF($L$9>5,I44*$J$9,0) -> 42039.108
A45: =IF($L$9>6,TEXT(YEAR($B$9)+6,"0")&"年度","") -> 2027年度 | B45: =IF($L$9>6,B44-C44+E44,0) -> 186162.4 | C45: =IF($L$9>6,C26,0) -> 50000 | D45: =IF($L$9>6,MONTH($B$9),"") -> 1 | E45: =IF($L$9>6,IF($Q$9="期末",B45*$H$9,(B45-C45)*$H$9),0) -> 6808.1201 | F45: =IF($L$9>6,IF($Q$9="期末",B45+E45-C45,B45-C45+E45),0) -> 142970.52 | G45: =IF($L$9>6,I44,0) -> 168156.43 | H45: =IF(AND($L$9>6,6<MIN($L$9,$I$9)),$I$34/MIN($L$9,$I$9),0) -> 42039.108 | I45: =IF($L$9>6,G45-H45,0) -> 126117.33 | J45: =IF($L$9>6,F45*$J$9,0) -> 35742.63 | K45: =IF($L$9>6,I45*$J$9,0) -> 31529.331
A46: =IF($L$9>7,TEXT(YEAR($B$9)+7,"0")&"年度","") -> 2028年度 | B46: =IF($L$9>7,B45-C45+E45,0) -> 142970.52 | C46: =IF($L$9>7,C27,0) -> 50000 | D46: =IF($L$9>7,MONTH($B$9),"") -> 1 | E46: =IF($L$9>7,IF($Q$9="期末",B46*$H$9,(B46-C46)*$H$9),0) -> 4648.5261 | F46: =IF($L$9>7,IF($Q$9="期末",B46+E46-C46,B46-C46+E46),0) -> 97619.048 | G46: =IF($L$9>7,I45,0) -> 126117.33 | H46: =IF(AND($L$9>7,7<MIN($L$9,$I$9)),$I$34/MIN($L$9,$I$9),0) -> 42039.108 | I46: =IF($L$9>7,G46-H46,0) -> 84078.217 | J46: =IF($L$9>7,F46*$J$9,0) -> 24404.762 | K46: =IF($L$9>7,I46*$J$9,0) -> 21019.554
A47: =IF($L$9>8,TEXT(YEAR($B$9)+8,"0")&"年度","") -> 2029年度 | B47: =IF($L$9>8,B46-C46+E46,0) -> 97619.048 | C47: =IF($L$9>8,C28,0) -> 50000 | D47: =IF($L$9>8,MONTH($B$9),"") -> 1 | E47: =IF($L$9>8,IF($Q$9="期末",B47*$H$9,(B47-C47)*$H$9),0) -> 2380.9524 | F47: =IF($L$9>8,IF($Q$9="期末",B47+E47-C47,B47-C47+E47),0) -> 50000 | G47: =IF($L$9>8,I46,0) -> 84078.217 | H47: =IF(AND($L$9>8,8<MIN($L$9,$I$9)),$I$34/MIN($L$9,$I$9),0) -> 42039.108 | I47: =IF($L$9>8,G47-H47,0) -> 42039.108 | J47: =IF($L$9>8,F47*$J$9,0) -> 12500 | K47: =IF($L$9>8,I47*$J$9,0) -> 10509.777
A48: =IF($L$9>9,TEXT(YEAR($B$9)+9,"0")&"年度","") -> 2030年度 | B48: =IF($L$9>9,B47-C47+E47,0) -> 50000 | C48: =IF($L$9>9,C29,0) -> 50000 | D48: =IF($L$9>9,MONTH($B$9),"") -> 1 | E48: =IF($L$9>9,IF($Q$9="期末",B48*$H$9,(B48-C48)*$H$9),0) -> 0 | F48: =IF($L$9>9,IF($Q$9="期末",B48+E48-C48,B48-C48+E48),0) -> 0 | G48: =IF($L$9>9,I47,0) -> 42039.108 | H48: =IF(AND($L$9>9,9<MIN($L$9,$I$9)),$I$34/MIN($L$9,$I$9),0) -> 42039.108 | I48: =IF($L$9>9,G48-H48,0) -> 0 | J48: =IF($L$9>9,F48*$J$9,0) -> 0 | K48: =IF($L$9>9,I48*$J$9,0) -> 0
A49: =IF($L$9>19,TEXT(YEAR($B$9)+19,"0")&"年度","") | B49: =IF($L$9>19,#REF!-#REF!+#REF!,0) -> 0 | C49: =IF($L$9>19,#REF!,0) -> 0 | D49: =IF($L$9>19,MONTH($B$9),"") | E49: =IF($L$9>19,IF($Q$9="期末",B49*$H$9,(B49-C49)*$H$9),0) -> 0 | F49: =IF($L$9>19,IF($Q$9="期末",B49+E49-C49,B49-C49+E49),0) -> 0 | G49: =IF($L$9>19,#REF!,0) -> 0 | H49: =IF(AND($L$9>19,19<MIN($L$9,$I$9)),$I$34/MIN($L$9,$I$9),0) -> 0 | I49: =IF($L$9>19,G49-H49,0) -> 0 | J49: =IF($L$9>19,F49*$J$9,0) -> 0 | K49: =IF($L$9>19,I49*$J$9,0) -> 0
A50: =IF($L$9>20,TEXT(YEAR($B$9)+20,"0")&"年度","") | B50: =IF($L$9>20,B49-C49+E49,0) -> 0 | C50: =IF($L$9>20,#REF!,0) -> 0 | D50: =IF($L$9>20,MONTH($B$9),"") | E50: =IF($L$9>20,IF($Q$9="期末",B50*$H$9,(B50-C50)*$H$9),0) -> 0 | F50: =IF($L$9>20,IF($Q$9="期末",B50+E50-C50,B50-C50+E50),0) -> 0 | G50: =IF($L$9>20,I49,0) -> 0 | H50: =IF(AND($L$9>20,20<MIN($L$9,$I$9)),$I$34/MIN($L$9,$I$9),0) -> 0 | I50: =IF($L$9>20,G50-H50,0) -> 0 | J50: =IF($L$9>20,F50*$J$9,0) -> 0 | K50: =IF($L$9>20,I50*$J$9,0) -> 0
A51: 合计 | C51: =SUM(C39:C50) -> 450000 | E51: =SUM(E39:E50) -> 94608.916 | H51: =SUM(H39:H50) -> 420391.08
A52: 自检：①L9来自H8-5可覆盖；②Q9期初/期末切换后重算；③第L9年负债期末≈0；④折旧合计≈I50；⑤右侧N9:P9自动自检。
A53: 三、审计说明：H8-5起租/约满/期数；付款时点(Q9)；折现率；初始计量；后续利息/折旧；与H8-1、H9勾稽。
A55: 四、审计结论：□初始及后续计量准确、与账面/H9无重大差异 □除下列差异外未见异常 □存在重大未调整差异不可确认。差异说明：__________。索引：H8-1 / H8-4 / H8-5 / H9。
A58: 提示（编制）：
A59: 1、流程：H8-5填C22/E22 → 本表L9/B9自动带入 → 填K9/M9/G9/Q9 → 表2/表3自动生成。
A60: 2、Q9选「期末」时无租金预付、折现期从1起；选「期初」时首期进预付列。寿命I9与L9取短折旧。
A61: 3、按月表J20默认勾稽本表L9；复杂月付用按月表。变更H8-7；减值折旧H8-8。

Sheet 使用权资产 租赁负债初始及后续计量（按月）H8-6
A1: 致同会计师事务所
A2: 使用权资产 租赁负债初始及后续计量（按月）
A3: =底稿目录!A2 -> 被审计单位： | E3: =底稿目录!A4 -> 编制人： | I3: =底稿目录!A6 -> 编制日期： | L3: 索引号： | M3: H8-6
A4: =底稿目录!A3 -> 截止日：202X年12月31日 | E4: =底稿目录!A5 -> 复核人： | I4: =底稿目录!A7 -> 复核日期： | L4: 页 次：
A5: 【编制入口·必填黄格】C15/C16默认H8-5；J20默认=按年L9；O20付款时点默认=按年Q9；再填C17折现率、C20年租金、E20支付月、G20初始直接费用、L20寿命月数。
A6: 填表说明（按月·动态）：【核心】J20默认=按年L9；也可直接改年数。C16/C18随年数变；填C15/C17/C20/E20/G20/L20后，明细自动生成。右侧N15:P15为自动自检。月利率=年利率/12。
A7: 1、 | B7: 租赁期开始日*(必填） | C7: 必填项，实际起租/交接日，填写格式为YYYY-MM-DD 如：2021-01-01（驱动B列逐月序列）。
A8: 2、 | B8: 约满日期*(必填） | C8: 必填项，考虑续租可能后的租赁期届满日（应与H8-5一致），格式YYYY-MM-DD；摊销期限C18据此计算。
A9: 3、 | B9: 折现率*(必填） | C9: 按合同内含利率或增量借款利率确定年折现率；利息列使用年利率/12。与按年表H9应一致。
A10: 4、 | B10: 摊销期限 | C10: 租期来自H8-5或J20。寿命短于租期时改L20。
A11: 5、 | B11: 月折旧额 | C11: 月折旧按MIN(C18,L20)次月起折尽；O20=期末时首笔租金不早于起租后12个月。
A13: 输 入 区 域 | D13: 计 算 区 域
A14: 使用权资产名称 | C14: XX设备 | E14: 借 | F14: 贷 | I14: 借 | J14: 贷 | N14: 自动自检
A15: 租赁期开始日 | C15: ='租赁期的确定H8-5'!C22 -> 44197 | D15: 使用权资产 | E15: =K22 -> 418559.45 | H15: 递延所得税资产 | I15: =L22 -> 88758.153 | N15: =IF($C$18<=0,"待填租期",IF(ABS(INDEX($G$22:$G$348,$C$18))<1,"✓末月负债≈0","×查利息/付款")) -> ✓末月负债≈0 | O15: =IF($C$18<=0,"待填租期",IF(ABS($I$349-($E$349+$H$349))<1,"✓折旧合计≈入账","×查折旧折尽")) -> ✓折旧合计≈入账 | P15: =IF(ABS($J$20-'使用权资产 租赁负债初始及后续计量（按年）H8-6'!L9)<0.1,"✓与按年L9一致","△与按年L9不一致") -> ✓与按年L9一致
A16: 约满日期(考虑续租可能后） | C16: ='租赁期的确定H8-5'!E22 -> 47848 | D16: 租赁负债 | F16: =E349 -> 353559.45 | H16: 递延所得税负债 | J16: =M22 -> 104639.86
A17: 本合同折现率（例） | C17: 0.05 | D17: 预付租金 | F17: =H349 -> 65000 | H17: 所得税费用 | I17: =J16-I15 -> 15881.709
A18: 摊销期限 | C18: =(YEAR($C$16)-YEAR($C$15))*12+MONTH($C$16)-MONTH($C$15)+1 -> 120 | E18: =SUM(E15:E17) -> 418559.45 | F18: =SUM(F15:F17) -> 418559.45 | I18: =SUM(I15:I17) -> 104639.86 | J18: =SUM(J15:J17) -> 104639.86
A19: 适用税率 | C19: 0.25
A20: 年租金(不含税)* | C20: 50000 | D20: 每年支付月份* | E20: 1 | F20: 初始直接费用 | G20: 15000 | I20: 租赁期(年)* | J20: ='使用权资产 租赁负债初始及后续计量（按年）H8-6'!L9 -> 10 | K20: 使用寿命(月) | L20: =$J$20*12 -> 120 | N20: 付款时点 | O20: ='使用权资产 租赁负债初始及后续计量（按年）H8-6'!Q9 -> 期初
A21: 期数 | B21: 月份 | C21: 合同租金 （不含税） | D21: 复原成本、终止租赁罚金等 | E21: 租赁付款额现值(折现到租赁期开始日) | F21: 利息费用 | G21: 租赁付款额现值余额 | H21: 使用权资产调整 （租赁期开始日前支付的租金、复原成本等） | I21: 月折旧额（次月起计提） | J21: 使用权资产累计折旧 | K21: 使用权资产余值 | L21: 对应递延所得税资产 | M21: 对应递延所得税负债
A22: 1 | B22: =C15 -> 44197 | C22: =IF(AND(A22<=$C$18,MONTH(B22)=$E$20,B22<=$C$16,IF($O$20="期末",B22>=EDATE($C$15,12),B22>$C$15)),$C$20,0) -> 0 | E22: =(D22+C22)/(POWER((1+$C$17/12),A22-1)) -> 0 | F22: =IF($C$18<=0,0,$C$17/12*E349) -> 1473.1644 | G22: =IF($C$18<=0,0,F22+E349) -> 355032.61 | H22: =IF($O$20="期末",$G$20,$C$20+$G$20) -> 65000 | I22: 0 | J22: 0 | K22: =$E$349+$H$349-I22 -> 418559.45 | L22: =IF(G22=0,0,G22*$C$19) -> 88758.153 | M22: =IF(K22=0,0,K22*$C$19) -> 104639.86
A23: =A22+1 -> 2 | B23: =EDATE(B22,1) -> 44228 | C23: =IF(AND(A23<=$C$18,MONTH(B23)=$E$20,B23<=$C$16,IF($O$20="期末",B23>=EDATE($C$15,12),B23>$C$15)),$C$20,0) -> 0 | E23: =(D23+C23)/(POWER((1+$C$17/12),A23-1)) -> 0 | F23: =IF(OR(B23>$C$16,A23>$C$18),0,$C$17/12*(G22-C23)) -> 1479.3026 | G23: =IF(OR(B23>$C$16,A23>$C$18),0,G22-C23+F23) -> 356511.92 | I23: =IF(OR(B23>$C$16,($A23-1)>=MIN($C$18,$L$20),MIN($C$18,$L$20)<=1),0,($E$349+$H$349)/MAX(MIN($C$18,$L$20)-1,1)) -> 3517.3063 | J23: =IF(I23=0,0,J22+I23) -> 3517.3063 | K23: =IF(OR(B23>$C$16,A23>$C$18),0,K22-I23) -> 415042.14 | L23: =IF(G23=0,0,G23*$C$19) -> 89127.979 | M23: =IF(K23=0,0,K23*$C$19) -> 103760.54
A24: =A23+1 -> 3 | B24: =EDATE(B23,1) -> 44256 | C24: =IF(AND(A24<=$C$18,MONTH(B24)=$E$20,B24<=$C$16,IF($O$20="期末",B24>=EDATE($C$15,12),B24>$C$15)),$C$20,0) -> 0 | E24: =(D24+C24)/(POWER((1+$C$17/12),A24-1)) -> 0 | F24: =IF(OR(B24>$C$16,A24>$C$18),0,$C$17/12*(G23-C24)) -> 1485.4663 | G24: =IF(OR(B24>$C$16,A24>$C$18),0,G23-C24+F24) -> 357997.38 | I24: =IF(OR(B24>$C$16,($A24-1)>=MIN($C$18,$L$20),MIN($C$18,$L$20)<=1),0,($E$349+$H$349)/MAX(MIN($C$18,$L$20)-1,1)) -> 3517.3063 | J24: =IF(I24=0,0,J23+I24) -> 7034.6126 | K24: =IF(OR(B24>$C$16,A24>$C$18),0,K23-I24) -> 411524.84 | L24: =IF(G24=0,0,G24*$C$19) -> 89499.346 | M24: =IF(K24=0,0,K24*$C$19) -> 102881.21
A25: =A24+1 -> 4 | B25: =EDATE(B24,1) -> 44287 | C25: =IF(AND(A25<=$C$18,MONTH(B25)=$E$20,B25<=$C$16,IF($O$20="期末",B25>=EDATE($C$15,12),B25>$C$15)),$C$20,0) -> 0 | E25: =(D25+C25)/(POWER((1+$C$17/12),A25-1)) -> 0 | F25: =IF(OR(B25>$C$16,A25>$C$18),0,$C$17/12*(G24-C25)) -> 1491.6558 | G25: =IF(OR(B25>$C$16,A25>$C$18),0,G24-C25+F25) -> 359489.04 | I25: =IF(OR(B25>$C$16,($A25-1)>=MIN($C$18,$L$20),MIN($C$18,$L$20)<=1),0,($E$349+$H$349)/MAX(MIN($C$18,$L$20)-1,1)) -> 3517.3063 | J25: =IF(I25=0,0,J24+I25) -> 10551.919 | K25: =IF(OR(B25>$C$16,A25>$C$18),0,K24-I25) -> 408007.53 | L25: =IF(G25=0,0,G25*$C$19) -> 89872.26 | M25: =IF(K25=0,0,K25*$C$19) -> 102001.88
A26: =A25+1 -> 5 | B26: =EDATE(B25,1) -> 44317 | C26: =IF(AND(A26<=$C$18,MONTH(B26)=$E$20,B26<=$C$16,IF($O$20="期末",B26>=EDATE($C$15,12),B26>$C$15)),$C$20,0) -> 0 | E26: =(D26+C26)/(POWER((1+$C$17/12),A26-1)) -> 0 | F26: =IF(OR(B26>$C$16,A26>$C$18),0,$C$17/12*(G25-C26)) -> 1497.871 | G26: =IF(OR(B26>$C$16,A26>$C$18),0,G25-C26+F26) -> 360986.91 | I26: =IF(OR(B26>$C$16,($A26-1)>=MIN($C$18,$L$20),MIN($C$18,$L$20)<=1),0,($E$349+$H$349)/MAX(MIN($C$18,$L$20)-1,1)) -> 3517.3063 | J26: =IF(I26=0,0,J25+I26) -> 14069.225 | K26: =IF(OR(B26>$C$16,A26>$C$18),0,K25-I26) -> 404490.22 | L26: =IF(G26=0,0,G26*$C$19) -> 90246.727 | M26: =IF(K26=0,0,K26*$C$19) -> 101122.56
A27: =A26+1 -> 6 | B27: =EDATE(B26,1) -> 44348 | C27: =IF(AND(A27<=$C$18,MONTH(B27)=$E$20,B27<=$C$16,IF($O$20="期末",B27>=EDATE($C$15,12),B27>$C$15)),$C$20,0) -> 0 | E27: =(D27+C27)/(POWER((1+$C$17/12),A27-1)) -> 0 | F27: =IF(OR(B27>$C$16,A27>$C$18),0,$C$17/12*(G26-C27)) -> 1504.1121 | G27: =IF(OR(B27>$C$16,A27>$C$18),0,G26-C27+F27) -> 362491.02 | I27: =IF(OR(B27>$C$16,($A27-1)>=MIN($C$18,$L$20),MIN($C$18,$L$20)<=1),0,($E$349+$H$349)/MAX(MIN($C$18,$L$20)-1,1)) -> 3517.3063 | J27: =IF(I27=0,0,J26+I27) -> 17586.531 | K27: =IF(OR(B27>$C$16,A27>$C$18),0,K26-I27) -> 400972.92 | L27: =IF(G27=0,0,G27*$C$19) -> 90622.755 | M27: =IF(K27=0,0,K27*$C$19) -> 100243.23
A28: =A27+1 -> 7 | B28: =EDATE(B27,1) -> 44378 | C28: =IF(AND(A28<=$C$18,MONTH(B28)=$E$20,B28<=$C$16,IF($O$20="期末",B28>=EDATE($C$15,12),B28>$C$15)),$C$20,0) -> 0 | E28: =(D28+C28)/(POWER((1+$C$17/12),A28-1)) -> 0 | F28: =IF(OR(B28>$C$16,A28>$C$18),0,$C$17/12*(G27-C28)) -> 1510.3793 | G28: =IF(OR(B28>$C$16,A28>$C$18),0,G27-C28+F28) -> 364001.4 | I28: =IF(OR(B28>$C$16,($A28-1)>=MIN($C$18,$L$20),MIN($C$18,$L$20)<=1),0,($E$349+$H$349)/MAX(MIN($C$18,$L$20)-1,1)) -> 3517.3063 | J28: =IF(I28=0,0,J27+I28) -> 21103.838 | K28: =IF(OR(B28>$C$16,A28>$C$18),0,K27-I28) -> 397455.61 | L28: =IF(G28=0,0,G28*$C$19) -> 91000.35 | M28: =IF(K28=0,0,K28*$C$19) -> 99363.903
A29: =A28+1 -> 8 | B29: =EDATE(B28,1) -> 44409 | C29: =IF(AND(A29<=$C$18,MONTH(B29)=$E$20,B29<=$C$16,IF($O$20="期末",B29>=EDATE($C$15,12),B29>$C$15)),$C$20,0) -> 0 | E29: =(D29+C29)/(POWER((1+$C$17/12),A29-1)) -> 0 | F29: =IF(OR(B29>$C$16,A29>$C$18),0,$C$17/12*(G28-C29)) -> 1516.6725 | G29: =IF(OR(B29>$C$16,A29>$C$18),0,G28-C29+F29) -> 365518.07 | I29: =IF(OR(B29>$C$16,($A29-1)>=MIN($C$18,$L$20),MIN($C$18,$L$20)<=1),0,($E$349+$H$349)/MAX(MIN($C$18,$L$20)-1,1)) -> 3517.3063 | J29: =IF(I29=0,0,J28+I29) -> 24621.144 | K29: =IF(OR(B29>$C$16,A29>$C$18),0,K28-I29) -> 393938.3 | L29: =IF(G29=0,0,G29*$C$19) -> 91379.518 | M29: =IF(K29=0,0,K29*$C$19) -> 98484.576
A30: =A29+1 -> 9 | B30: =EDATE(B29,1) -> 44440 | C30: =IF(AND(A30<=$C$18,MONTH(B30)=$E$20,B30<=$C$16,IF($O$20="期末",B30>=EDATE($C$15,12),B30>$C$15)),$C$20,0) -> 0 | E30: =(D30+C30)/(POWER((1+$C$17/12),A30-1)) -> 0 | F30: =IF(OR(B30>$C$16,A30>$C$18),0,$C$17/12*(G29-C30)) -> 1522.992 | G30: =IF(OR(B30>$C$16,A30>$C$18),0,G29-C30+F30) -> 367041.06 | I30: =IF(OR(B30>$C$16,($A30-1)>=MIN($C$18,$L$20),MIN($C$18,$L$20)<=1),0,($E$349+$H$349)/MAX(MIN($C$18,$L$20)-1,1)) -> 3517.3063 | J30: =IF(I30=0,0,J29+I30) -> 28138.45 | K30: =IF(OR(B30>$C$16,A30>$C$18),0,K29-I30) -> 390421 | L30: =IF(G30=0,0,G30*$C$19) -> 91760.266 | M30: =IF(K30=0,0,K30*$C$19) -> 97605.25
A31: =A30+1 -> 10 | B31: =EDATE(B30,1) -> 44470 | C31: =IF(AND(A31<=$C$18,MONTH(B31)=$E$20,B31<=$C$16,IF($O$20="期末",B31>=EDATE($C$15,12),B31>$C$15)),$C$20,0) -> 0 | E31: =(D31+C31)/(POWER((1+$C$17/12),A31-1)) -> 0 | F31: =IF(OR(B31>$C$16,A31>$C$18),0,$C$17/12*(G30-C31)) -> 1529.3378 | G31: =IF(OR(B31>$C$16,A31>$C$18),0,G30-C31+F31) -> 368570.4 | I31: =IF(OR(B31>$C$16,($A31-1)>=MIN($C$18,$L$20),MIN($C$18,$L$20)<=1),0,($E$349+$H$349)/MAX(MIN($C$18,$L$20)-1,1)) -> 3517.3063 | J31: =IF(I31=0,0,J30+I31) -> 31655.757 | K31: =IF(OR(B31>$C$16,A31>$C$18),0,K30-I31) -> 386903.69 | L31: =IF(G31=0,0,G31*$C$19) -> 92142.601 | M31: =IF(K31=0,0,K31*$C$19) -> 96725.923
A32: =A31+1 -> 11 | B32: =EDATE(B31,1) -> 44501 | C32: =IF(AND(A32<=$C$18,MONTH(B32)=$E$20,B32<=$C$16,IF($O$20="期末",B32>=EDATE($C$15,12),B32>$C$15)),$C$20,0) -> 0 | E32: =(D32+C32)/(POWER((1+$C$17/12),A32-1)) -> 0 | F32: =IF(OR(B32>$C$16,A32>$C$18),0,$C$17/12*(G31-C32)) -> 1535.71 | G32: =IF(OR(B32>$C$16,A32>$C$18),0,G31-C32+F32) -> 370106.11 | I32: =IF(OR(B32>$C$16,($A32-1)>=MIN($C$18,$L$20),MIN($C$18,$L$20)<=1),0,($E$349+$H$349)/MAX(MIN($C$18,$L$20)-1,1)) -> 3517.3063 | J32: =IF(I32=0,0,J31+I32) -> 35173.063 | K32: =IF(OR(B32>$C$16,A32>$C$18),0,K31-I32) -> 383386.39 | L32: =IF(G32=0,0,G32*$C$19) -> 92526.528 | M32: =IF(K32=0,0,K32*$C$19) -> 95846.597
A33: =A32+1 -> 12 | B33: =EDATE(B32,1) -> 44531 | C33: =IF(AND(A33<=$C$18,MONTH(B33)=$E$20,B33<=$C$16,IF($O$20="期末",B33>=EDATE($C$15,12),B33>$C$15)),$C$20,0) -> 0 | E33: =(D33+C33)/(POWER((1+$C$17/12),A33-1)) -> 0 | F33: =IF(OR(B33>$C$16,A33>$C$18),0,$C$17/12*(G32-C33)) -> 1542.1088 | G33: =IF(OR(B33>$C$16,A33>$C$18),0,G32-C33+F33) -> 371648.22 | I33: =IF(OR(B33>$C$16,($A33-1)>=MIN($C$18,$L$20),MIN($C$18,$L$20)<=1),0,($E$349+$H$349)/MAX(MIN($C$18,$L$20)-1,1)) -> 3517.3063 | J33: =IF(I33=0,0,J32+I33) -> 38690.369 | K33: =IF(OR(B33>$C$16,A33>$C$18),0,K32-I33) -> 379869.08 | L33: =IF(G33=0,0,G33*$C$19) -> 92912.055 | M33: =IF(K33=0,0,K33*$C$19) -> 94967.27
A34: =A33+1 -> 13 | B34: =EDATE(B33,1) -> 44562 | C34: =IF(AND(A34<=$C$18,MONTH(B34)=$E$20,B34<=$C$16,IF($O$20="期末",B34>=EDATE($C$15,12),B34>$C$15)),$C$20,0) -> 50000 | E34: =(D34+C34)/(POWER((1+$C$17/12),A34-1)) -> 47566.412 | F34: =IF(OR(B34>$C$16,A34>$C$18),0,$C$17/12*(G33-C34)) -> 1340.2009 | G34: =IF(OR(B34>$C$16,A34>$C$18),0,G33-C34+F34) -> 322988.42 | I34: =IF(OR(B34>$C$16,($A34-1)>=MIN($C$18,$L$20),MIN($C$18,$L$20)<=1),0,($E$349+$H$349)/MAX(MIN($C$18,$L$20)-1,1)) -> 3517.3063 | J34: =IF(I34=0,0,J33+I34) -> 42207.676 | K34: =IF(OR(B34>$C$16,A34>$C$18),0,K33-I34) -> 376351.77 | L34: =IF(G34=0,0,G34*$C$19) -> 80747.106 | M34: =IF(K34=0,0,K34*$C$19) -> 94087.943
... A348: =A347+1 -> 327 | B348: =EDATE(B347,1) -> 54118 | C348: =IF(AND(A348<=$C$18,MONTH(B348)=$E$20,B348<=$C$16,IF($O$20="期末",B348>=EDATE($C$15,12),B348>$C$15)),$C$20,0) -> 0 | E348: =(D348+C348)/(POWER((1+$C$17/12),A348-1)) -> 0 | F348: =IF(OR(B348>$C$16,A348>$C$18),0,$C$17/12*(G347-C348)) -> 0 | G348: =IF(OR(B348>$C$16,A348>$C$18),0,G347-C348+F348) -> 0 | I348: =IF(OR(B348>$C$16,($A348-1)>=MIN($C$18,$L$20),MIN($C$18,$L$20)<=1),0,($E$349+$H$349)/MAX(MIN($C$18,$L$20)-1,1)) -> 0 | J348: =IF(I348=0,0,J347+I348) -> 0 | K348: =IF(OR(B348>$C$16,A348>$C$18),0,K347-I348) -> 0 | L348: =IF(G348=0,0,G348*$C$19) -> 0 | M348: =IF(K348=0,0,K348*$C$19) -> 0
B349: 合计 | C349: =SUM(C22:C348) -> 450000 | D349: =SUM(D22:D348) -> 0 | E349: =SUM(E22:E348) -> 353559.45 | F349: =SUM(F22:F348) -> 96440.551 | H349: =SUM(H22:H348) -> 65000 | I349: =SUM(I22:I348) -> 418559.45 | J349: —— | K349: ——
A350: 自检：①H8-5日期已带入；②O20与按年Q9一致；③末月负债≈0；④折旧合计≈入账；⑤J20≈按年L9。
A352: 三、审计说明：
A353: 1.租赁条件是否真实、完整（合同/补充协议/续租与终止选择权，索引H8-4/H8-5）
A354: 2.所采用的折现率是否正确（内含利率或增量借款利率；月利率=年利率/12的口径是否披露）
A355: 3.使用权资产入账价值是否正确（现值+预付/初始直接费用/复原成本−激励；与H9负债初始一致）
A356: 4.按月利息/折旧计提时点、付款归属月是否与合同一致；与按年表或H8-1/H9年末余额勾稽结果。
A357: 四、审计结论：□按月计量准确、与账面/H9及按年表无重大差异 □除下列差异外未见异常 □存在重大未调整差异不可确认。差异说明：__________。索引：H8-1 / H8-4 / H8-5 / H8-8 / H9。

Sheet 租赁变更H8-7
A1: 致同会计师事务所
A2: 租赁变更
A3: =底稿目录!A2 -> 被审计单位： | D3: =底稿目录!A4 -> 编制人： | F3: =底稿目录!A6 -> 编制日期： | H3: 索引号： | I3: H8-7
A4: =底稿目录!A3 -> 截止日：202X年12月31日 | D4: =底稿目录!A5 -> 复核人： | F4: =底稿目录!A7 -> 复核日期： | H4: 页 次：
A5: 一、审计目标：1. 资产负债表中记录的使用权资产是存在的，且已记录于恰当的账户；2. 所有应记录的使用权资产均已记录，所有应当包括在财务报表中的相关披露均已包括；3. 记录的使用权资产由被审计单位拥有或控制；4. 使用权资产以恰当的金额包括在财务报表中，与之相关的计价或分摊调整已恰当记录，相关披露已得到恰当计量和描述。
A6: 二、审计过程：
A7: 1. 租赁变更情况
A8: 1. 1 租赁变更是否作为一项单独租赁 | D8: 是否适用 | E8: 是
A9: 条件（同时满足） | C9: 合同信息 | E9: 是否满足 | F9: 分析 | I9: 索引
A10: （1）该租赁变更通过增加一项或多项租赁资产的使用权而扩大了租赁范围； | J10: 租赁变更，是指原合同条款之外的租赁范围、租赁对价、租赁期限的变更，包括增加或终止一项或多项租赁资产的使用权，延长或缩短合同规定的租赁期等。
A11: （2）增加的对价与租赁范围扩大部分的单独价格按该合同情况调整后的金额相当。
A12: 结 论 | C12: =IF(AND(E10="是",E11="是"),"应当将该租赁变更作为一项单独租赁进行会计处理","应当分摊变更后合同的对价，重新确定租赁期，并按照变更后租赁付款额和修订后的折现率计算的现值重新计量租赁负债") -> 应当分摊变更后合同的对价，重新确定租赁期，并按照变更后租赁付款额和修订后的折现率计算的现值重新计量租赁负债
A14: 1.2 租赁变更未作为一项单独租赁处理 | D14: 是否适用 | E14: 是
A15: 情形 | C15: 合同信息 | E15: 是/否 | F15: 分析 | I15: 索引
A16: （1）租赁变更导致租赁范围缩小或租赁期缩短 | F16: 承租人应当调减使用权资产的账面价值，以反映租赁的部分终止或完全终止。承租人应将部分终止或完全终止租赁的相关利得或损失计入当期损益。
A17: （2）其他租赁变更 | C17: 第6年末，情况发生变化，合理确定将行使额外5年续租选择权 | E17: 是 | F17: 承租人应当相应调整使用权资产的账面价值。
A18: 结 论
A20: 2. 原租赁合同
A21: 2.1 原租赁合同的基本信息
A22: 使用权资产名称 | B22: 租赁期开始日 | C22: 合同约定初始期满日 | D22: 续租期（年） | E22: 租赁期（考虑续租可能后） | F22: 租赁期截止日期 | G22: 增量借款利率 | H22: 折现率 | I22: 使用权资产摊销期限（年）
A23: XX设备 | B23: 44197 | C23: 47118 | D23: =2 -> 2 | E23: =(YEAR(C23)-YEAR(B23))+D23+(MONTH(C23)-MONTH(B23)+1)/12 -> 10 | F23: =DATE(YEAR(C23)+D23,MONTH(C23),DAY(C23)) -> 47848 | G23: 0.05 | H23: 0.05 | I23: 10
A26: 2.2 计算租赁负债余额
A27: 租金支付日期 | B27: 剩余合同租金（不含税） | C27: 租赁付款额原值 | D27: 租赁负债折现期(年） | E27: 租赁负债折现系数 | F27: 租赁付款额现值 | G27: 租赁预付款 | H27: 初始直接费用 | I27: 使用权资产初始确认金额
A28: 44197 | B28: 50000 | C28: =IF(E28=1,0,B28) -> 0 | D28: 0 | E28: =1/(1+$H$23)^D28 -> 1 | F28: =C28*E28 -> 0 | G28: =B28 -> 50000 | H28: 15000
A29: 44562 | B29: 50000 | C29: =IF(E29=1,0,B29) -> 50000 | D29: =D28+1 -> 1 | E29: =1/(1+$H$23)^D29 -> 0.95238095 | F29: =C29*E29 -> 47619.048
A30: 44927 | B30: 50000 | C30: =IF(E30=1,0,B30) -> 50000 | D30: =D29+1 -> 2 | E30: =1/(1+$H$23)^D30 -> 0.90702948 | F30: =C30*E30 -> 45351.474
A31: 45292 | B31: 50000 | C31: =IF(E31=1,0,B31) -> 50000 | D31: =D30+1 -> 3 | E31: =1/(1+$H$23)^D31 -> 0.8638376 | F31: =C31*E31 -> 43191.88
A32: 45658 | B32: 50000 | C32: =IF(E32=1,0,B32) -> 50000 | D32: =D31+1 -> 4 | E32: =1/(1+$H$23)^D32 -> 0.82270247 | F32: =C32*E32 -> 41135.124
A33: 46023 | B33: 50000 | C33: =IF(E33=1,0,B33) -> 50000 | D33: =D32+1 -> 5 | E33: =1/(1+$H$23)^D33 -> 0.78352617 | F33: =C33*E33 -> 39176.308
A34: 46388 | B34: 50000 | C34: =IF(E34=1,0,B34) -> 50000 | D34: =D33+1 -> 6 | E34: =1/(1+$H$23)^D34 -> 0.7462154 | F34: =C34*E34 -> 37310.77
A35: 46753 | B35: 50000 | C35: =IF(E35=1,0,B35) -> 50000 | D35: =D34+1 -> 7 | E35: =1/(1+$H$23)^D35 -> 0.71068133 | F35: =C35*E35 -> 35534.067
A36: 47119 | B36: 50000 | C36: =IF(E36=1,0,B36) -> 50000 | D36: =D35+1 -> 8 | E36: =1/(1+$H$23)^D36 -> 0.67683936 | F36: =C36*E36 -> 33841.968
A37: 47484 | B37: 50000 | C37: =IF(E37=1,0,B37) -> 50000 | D37: =D36+1 -> 9 | E37: =1/(1+$H$23)^D37 -> 0.64460892 | F37: =C37*E37 -> 32230.446
A38: 合计 | B38: =SUM(B28:B37) -> 500000 | C38: =SUM(C28:C37) -> 450000 | F38: =SUM(F28:F37) -> 355391.08 | G38: =SUM(G28:G37) -> 50000 | H38: =SUM(H28:H37) -> 15000 | I38: =F38+G38+H38 -> 420391.08
A40: 2.3 租赁负债及使用权资产后续计量
A41: 期间 | B41: 租赁负债 | G41: 使用权资产
B42: 期初余额 | C42: 租赁付款额 | D42: 支付月份 | E42: 利息费用 | F42: 期末余额 | G42: 期初余额 | H42: 折旧费用 | I42: 期末余额
A43: 2021年度 | B43: =F38 -> 355391.08 | C43: =C28 -> 0 | D43: 1 | E43: =(B43-C43)*$H$23 -> 17769.554 | F43: =B43-C43+E43 -> 373160.64 | G43: =I38 -> 420391.08 | H43: =$I$38/$I$23 -> 42039.108 | I43: =G43-H43 -> 378351.98
A44: 2022年度 | B44: =B43-C43+E43 -> 373160.64 | C44: =C29 -> 50000 | D44: 1 | E44: =(B44-C44)*$H$23 -> 16158.032 | F44: =B44-C44+E44 -> 339318.67 | G44: =I43 -> 378351.98 | H44: =H43 -> 42039.108 | I44: =G44-H44 -> 336312.87
A45: 2023年度 | B45: =B44-C44+E44 -> 339318.67 | C45: =C30 -> 50000 | D45: 1 | E45: =(B45-C45)*$H$23 -> 14465.933 | F45: =B45-C45+E45 -> 303784.6 | G45: =I44 -> 336312.87 | H45: =H44 -> 42039.108 | I45: =G45-H45 -> 294273.76
A46: 2024年度 | B46: =B45-C45+E45 -> 303784.6 | C46: =C31 -> 50000 | D46: 1 | E46: =(B46-C46)*$H$23 -> 12689.23 | F46: =B46-C46+E46 -> 266473.83 | G46: =I45 -> 294273.76 | H46: =H45 -> 42039.108 | I46: =G46-H46 -> 252234.65
A47: 2025年度 | B47: =B46-C46+E46 -> 266473.83 | C47: =C32 -> 50000 | D47: 1 | E47: =(B47-C47)*$H$23 -> 10823.692 | F47: =B47-C47+E47 -> 227297.53 | G47: =I46 -> 252234.65 | H47: =H46 -> 42039.108 | I47: =G47-H47 -> 210195.54
A48: 2026年度 | B48: =B47-C47+E47 -> 227297.53 | C48: =C33 -> 50000 | D48: 1 | E48: =(B48-C48)*$H$23 -> 8864.8763 | F48: =B48-C48+E48 -> 186162.4 | G48: =I47 -> 210195.54 | H48: =H47 -> 42039.108 | I48: =G48-H48 -> 168156.43
A49: 2027年度 | B49: =B48-C48+E48 -> 186162.4 | C49: =C34 -> 50000 | D49: 1 | E49: =(B49-C49)*$H$23 -> 6808.1201 | F49: =B49-C49+E49 -> 142970.52 | G49: =I48 -> 168156.43 | H49: =H48 -> 42039.108 | I49: =G49-H49 -> 126117.33
A50: 2028年度 | B50: =B49-C49+E49 -> 142970.52 | C50: =C35 -> 50000 | D50: 1 | E50: =(B50-C50)*$H$23 -> 4648.5261 | F50: =B50-C50+E50 -> 97619.048 | G50: =I49 -> 126117.33 | H50: =H49 -> 42039.108 | I50: =G50-H50 -> 84078.217
A51: 2029年度 | B51: =B50-C50+E50 -> 97619.048 | C51: =C36 -> 50000 | D51: 1 | E51: =(B51-C51)*$H$23 -> 2380.9524 | F51: =B51-C51+E51 -> 50000 | G51: =I50 -> 84078.217 | H51: =H50 -> 42039.108 | I51: =G51-H51 -> 42039.108
A52: 2030年度 | B52: =B51-C51+E51 -> 50000 | C52: =C37 -> 50000 | D52: 1 | E52: =(B52-C52)*$H$23 -> 0 | F52: =B52-C52+E52 -> 0 | G52: =I51 -> 42039.108 | H52: =H51 -> 42039.108 | I52: =G52-H52 -> 0
A53: 合计 | C53: =SUM(C43:C52) -> 450000 | E53: =SUM(E43:E52) -> 94608.916 | H53: =SUM(H43:H52) -> 420391.08
A55: 3. 新租赁合同
A56: 3.1 新租赁合同的基本信息
A57: 使用权资产名称 | B57: 租赁期开始日 | C57: 合同约定初始期满日 | D57: 续租期改变（年） | E57: 租赁期（考虑续租可能后） | F57: 租赁期截止日期 | G57: 增量借款利率 | H57: 折现率 | I57: 使用权资产摊销期限（年）
A58: XX设备 | B58: 44197 | C58: 47118 | D58: 7 | E58: =(YEAR(C58)-YEAR(B58))+D58+(MONTH(C58)-MONTH(B58)+1)/12 -> 15 | F58: =DATE(YEAR(C58)+D58,MONTH(C58),DAY(C58)) -> 49674 | G58: 0.06 | H58: 0.06 | I58: 9
A61: 3.2 计算租赁负债余额
A62: 租金支付日期 | B62: 剩余合同租金（不含税） | C62: 租赁付款额原值 | D62: 租赁负债折现期(年） | E62: 租赁负债折现系数 | F62: 租赁付款额现值 | G62: 租赁预付款 | H62: 初始直接费用 | I62: 使用权资产初始确认金额
A63: 46387 | B63: 50000 | C63: =B63 -> 50000 | D63: 0 | E63: =1/(1+$H$58)^D63 -> 1 | F63: =C63*E63 -> 50000
A64: 46753 | B64: 50000 | C64: =B64 -> 50000 | D64: 1 | E64: =1/(1+$H$58)^D64 -> 0.94339623 | F64: =C64*E64 -> 47169.811
A65: 47119 | B65: 50000 | C65: =B65 -> 50000 | D65: 2 | E65: =1/(1+$H$58)^D65 -> 0.88999644 | F65: =C65*E65 -> 44499.822
A66: 47484 | B66: 50000 | C66: =B66 -> 50000 | D66: 3 | E66: =1/(1+$H$58)^D66 -> 0.83961928 | F66: =C66*E66 -> 41980.964
A67: 47849 | B67: 55000 | C67: =B67 -> 55000 | D67: 4 | E67: =1/(1+$H$58)^D67 -> 0.79209366 | F67: =C67*E67 -> 43565.151
A68: 48214 | B68: 55000 | C68: =B68 -> 55000 | D68: 5 | E68: =1/(1+$H$58)^D68 -> 0.74725817 | F68: =C68*E68 -> 41099.2
A69: 48580 | B69: 55000 | C69: =B69 -> 55000 | D69: 6 | E69: =1/(1+$H$58)^D69 -> 0.70496054 | F69: =C69*E69 -> 38772.83
A70: 48945 | B70: 55000 | C70: =B70 -> 55000 | D70: 7 | E70: =1/(1+$H$58)^D70 -> 0.66505711 | F70: =C70*E70 -> 36578.141
A71: 49310 | B71: 55000 | C71: =B71 -> 55000 | D71: 8 | E71: =1/(1+$H$58)^D71 -> 0.62741237 | F71: =C71*E71 -> 34507.68
A72: 合计 | B72: =SUM(B63:B71) -> 475000 | C72: =SUM(C63:C71) -> 475000 | F72: =SUM(F63:F71) -> 378173.6 | G72: =SUM(G63:G71) -> 0 | H72: =SUM(H63:H71) -> 0 | I72: =F72-F48+I48+G72+H72 -> 360167.63
A74: 3.3 租赁负债及使用权资产后续计量
A75: 期间 | B75: 租赁负债 | G75: 使用权资产
B76: 期初余额 | C76: 租赁付款额 | D76: 支付月份 | E76: 利息费用 | F76: 期末余额 | G76: 期初余额 | H76: 折旧费用 | I76: 期末余额
A77: 2027年度 | B77: =F72 -> 378173.6 | C77: =C63 -> 50000 | D77: 1 | E77: =(B77-C77)*$H$58 -> 19690.416 | F77: =B77-C77+E77 -> 347864.02 | G77: =I72 -> 360167.63 | H77: =$I$72/$I$58 -> 40018.626 | I77: =G77-H77 -> 320149.01
A78: 2028年度 | B78: =B77-C77+E77 -> 347864.02 | C78: =C64 -> 50000 | D78: 1 | E78: =(B78-C78)*$H$58 -> 17871.841 | F78: =B78-C78+E78 -> 315735.86 | G78: =I77 -> 320149.01 | H78: =H77 -> 40018.626 | I78: =G78-H78 -> 280130.38
A79: 2029年度 | B79: =B78-C78+E78 -> 315735.86 | C79: =C65 -> 50000 | D79: 1 | E79: =(B79-C79)*$H$58 -> 15944.151 | F79: =B79-C79+E79 -> 281680.01 | G79: =I78 -> 280130.38 | H79: =H78 -> 40018.626 | I79: =G79-H79 -> 240111.75
A80: 2030年度 | B80: =B79-C79+E79 -> 281680.01 | C80: =C66 -> 50000 | D80: 1 | E80: =(B80-C80)*$H$58 -> 13900.8 | F80: =B80-C80+E80 -> 245580.81 | G80: =I79 -> 240111.75 | H80: =H79 -> 40018.626 | I80: =G80-H80 -> 200093.13
A81: 2031年度 | B81: =B80-C80+E80 -> 245580.81 | C81: =C67 -> 55000 | D81: 1 | E81: =(B81-C81)*$H$58 -> 11434.849 | F81: =B81-C81+E81 -> 202015.66 | G81: =I80 -> 200093.13 | H81: =H80 -> 40018.626 | I81: =G81-H81 -> 160074.5
A82: 2032年度 | B82: =B81-C81+E81 -> 202015.66 | C82: =C68 -> 55000 | D82: 1 | E82: =(B82-C82)*$H$58 -> 8820.9394 | F82: =B82-C82+E82 -> 155836.6 | G82: =I81 -> 160074.5 | H82: =H81 -> 40018.626 | I82: =G82-H82 -> 120055.88
A83: 2033年度 | B83: =B82-C82+E82 -> 155836.6 | C83: =C69 -> 55000 | D83: 1 | E83: =(B83-C83)*$H$58 -> 6050.1958 | F83: =B83-C83+E83 -> 106886.79 | G83: =I82 -> 120055.88 | H83: =H82 -> 40018.626 | I83: =G83-H83 -> 80037.252
A84: 2034年度 | B84: =B83-C83+E83 -> 106886.79 | C84: =C70 -> 55000 | D84: 1 | E84: =(B84-C84)*$H$58 -> 3113.2075 | F84: =B84-C84+E84 -> 55000 | G84: =I83 -> 80037.252 | H84: =H83 -> 40018.626 | I84: =G84-H84 -> 40018.626
A85: 2035年度 | B85: =B84-C84+E84 -> 55000 | C85: =C71 -> 55000 | D85: 1 | E85: =(B85-C85)*$H$58 -> -6.1118044e-12 | F85: =B85-C85+E85 -> -1.0797521e-10 | G85: =I84 -> 40018.626 | H85: =H84 -> 40018.626 | I85: =G85-H85 -> 0
A86: 合计 | C86: =SUM(C77:C85) -> 475000 | E86: =SUM(E77:E85) -> 96826.4 | H86: =SUM(H77:H85) -> 360167.63
A88: 三、审计说明：
A90: 四、审计结论：
A93: 提示：
A94: 租赁变更，是指原合同条款之外的租赁范围、租赁对价、租赁期限的变更，包括增加或终止一项或多项租赁资产的使用权，延长或缩短合同规定的租赁期等。

Sheet 折旧测算表（不含减值）H8-8
A1: 致同会计师事务所
A2: 使用权资产折旧测算表
A3: =[3]底稿目录!A2 -> 被审计单位： | E3: =[3]底稿目录!A4 -> 编制人： | L3: =[3]底稿目录!A6 -> 编制日期： | Q3: 索引号： | R3: H8-8
A4: =[3]底稿目录!A3 -> 截止日：202X年12月31日 | E4: =[3]底稿目录!A5 -> 复核人： | L4: =[3]底稿目录!A7 -> 复核日期： | Q4: 页 次：
A5: 一、审计目标：确认未计提减值的使用权资产折旧以恰当金额计入报表；折旧期=min(租赁期,使用寿命)（能合理确定取得所有权时取使用寿命）；直线法月折旧=原值×(1−残值率)÷使用月限；本期及累计折旧测算与账面无重大差异；相关披露恰当（CAS21第21条）。
A6: 二、审计过程：①自明细表H8-2带入类别/名称/编号/原值/累计折旧/开始使用日期；②核对使用年限与租赁期，确认折旧期取短；残值率无所有权转移预期时通常为0；③按折旧期初/期末测算本期月数、测算月折旧、当期折旧费用及累计差异；④差异>0.01查明原因；⑤本期折旧合计与审定表H8-1累计折旧本期计提、分配表H8-9勾稽。若资产已计提减值，改用「折旧测算表（含减值）H8-8」。
A7: 折旧期初： | B7: 45658 | C7: 折旧期末： | D7: 46022 | F7: 各列顺序可按需调整；非公式列请「选择性粘贴-数值」。公式：使用月限J、测算到期日K、已提月份L、本期月数M、测算月折旧N=原值×(1−残值率)/J、当期折旧O=N×M、月折旧差异P=账面月折旧−N、累计测算Q=N×L、累计差异R=账面累计−Q。
A8: 使用权资产类别 | B8: 使用权资产名称 | C8: 使用权资产编号 | D8: 原值 | E8: 累计折旧 | F8: 开始使用日期 | G8: 使用年限 | H8: 残值率 | I8: 账面月折旧额 | J8: 使用月限 | K8: 测算到期日 | L8: 已提折旧月份 | M8: 本期折旧月份 | N8: 测算月折旧 | O8: 当期折旧费用 | P8: 月折旧额差异 | Q8: 累计折旧费用 | R8: 累计折旧额差异
A9: ='[3]明细表H8-2'!A12 -> 0 | B9: ='[3]明细表H8-2'!B12 -> 0 | C9: ='[3]明细表H8-2'!C12 -> 0 | D9: ='[3]明细表H8-2'!S12 -> 0 | E9: ='[3]明细表H8-2'!AJ12 -> 0 | J9: =IF(G9=0,0,IF(RIGHT(G9,1)<>"年",G9*12,IF(LEN(G9)=3,VALUE(LEFT(G9,2))*12,IF(LEN(G9)=2,VALUE(LEFT(G9,1))*12,"??")))) -> 0 | K9: =DATE((YEAR(F9)+G9),MONTH(F9),DAY(F9)) -> 0 | L9: =MIN((YEAR(K9)-YEAR(F9))*12+(MONTH(K9)-MONTH(F9)),(YEAR($D$7)-YEAR(F9))*12+MONTH($D$7)-MONTH(F9),G9*12) -> 0 | M9: =IF(K9<$B$7,0,IF($D$7>K9,MIN(MONTH($D$7),DATEDIF(DATE(YEAR(F9),MONTH(F9),"1"),$D$7,"M")-DATEDIF(DATE(YEAR(F9),MONTH(F9),"1"),DATEDIF(YEAR(K9),MONTH(K9),"1"),"M")),MIN(DATEDIF(DATE(YEAR(F9),MONTH(F9),"1"),$D$7,"m"),MONTH($D$7)))) -> 0 | N9: =IF(J9=0,0,ROUND(((1-H9)/J9)*D9,4)) -> 0 | O9: =ROUND(N9*M9,2) -> 0 | P9: =ROUND(I9-N9,2) -> 0 | Q9: =ROUND(N9*L9,2) -> 0 | R9: =ROUND(E9-Q9,2) -> 0
A10: ='[3]明细表H8-2'!A13 -> 0 | B10: ='[3]明细表H8-2'!B13 -> 0 | C10: ='[3]明细表H8-2'!C13 -> 0 | D10: ='[3]明细表H8-2'!S13 -> 0 | E10: ='[3]明细表H8-2'!AJ13 -> 0 | J10: =IF(G10=0,0,IF(RIGHT(G10,1)<>"年",G10*12,IF(LEN(G10)=3,VALUE(LEFT(G10,2))*12,IF(LEN(G10)=2,VALUE(LEFT(G10,1))*12,"??")))) -> 0 | K10: =DATE((YEAR(F10)+G10),MONTH(F10),DAY(F10)) -> 0 | L10: =MIN((YEAR(K10)-YEAR(F10))*12+(MONTH(K10)-MONTH(F10)),(YEAR($D$7)-YEAR(F10))*12+MONTH($D$7)-MONTH(F10),G10*12) -> 0 | M10: =IF(K10<$B$7,0,IF($D$7>K10,MIN(MONTH($D$7),DATEDIF(DATE(YEAR(F10),MONTH(F10),"1"),$D$7,"M")-DATEDIF(DATE(YEAR(F10),MONTH(F10),"1"),DATEDIF(YEAR(K10),MONTH(K10),"1"),"M")),MIN(DATEDIF(DATE(YEAR(F10),MONTH(F10),"1"),$D$7,"m"),MONTH($D$7)))) -> 0 | N10: =IF(J10=0,0,ROUND(((1-H10)/J10)*D10,4)) -> 0 | O10: =ROUND(N10*M10,2) -> 0 | P10: =ROUND(I10-N10,2) -> 0 | Q10: =ROUND(N10*L10,2) -> 0 | R10: =ROUND(E10-Q10,2) -> 0
A11: ='[3]明细表H8-2'!A14 -> 0 | B11: ='[3]明细表H8-2'!B14 -> 0 | C11: ='[3]明细表H8-2'!C14 -> 0 | D11: ='[3]明细表H8-2'!S14 -> 0 | E11: ='[3]明细表H8-2'!AJ14 -> 0 | J11: =IF(G11=0,0,IF(RIGHT(G11,1)<>"年",G11*12,IF(LEN(G11)=3,VALUE(LEFT(G11,2))*12,IF(LEN(G11)=2,VALUE(LEFT(G11,1))*12,"??")))) -> 0 | K11: =DATE((YEAR(F11)+G11),MONTH(F11),DAY(F11)) -> 0 | L11: =MIN((YEAR(K11)-YEAR(F11))*12+(MONTH(K11)-MONTH(F11)),(YEAR($D$7)-YEAR(F11))*12+MONTH($D$7)-MONTH(F11),G11*12) -> 0 | M11: =IF(K11<$B$7,0,IF($D$7>K11,MIN(MONTH($D$7),DATEDIF(DATE(YEAR(F11),MONTH(F11),"1"),$D$7,"M")-DATEDIF(DATE(YEAR(F11),MONTH(F11),"1"),DATEDIF(YEAR(K11),MONTH(K11),"1"),"M")),MIN(DATEDIF(DATE(YEAR(F11),MONTH(F11),"1"),$D$7,"m"),MONTH($D$7)))) -> 0 | N11: =IF(J11=0,0,ROUND(((1-H11)/J11)*D11,4)) -> 0 | O11: =ROUND(N11*M11,2) -> 0 | P11: =ROUND(I11-N11,2) -> 0 | Q11: =ROUND(N11*L11,2) -> 0 | R11: =ROUND(E11-Q11,2) -> 0
A12: ='[3]明细表H8-2'!A15 -> 0 | B12: ='[3]明细表H8-2'!B15 -> 0 | C12: ='[3]明细表H8-2'!C15 -> 0 | D12: ='[3]明细表H8-2'!S15 -> 0 | E12: ='[3]明细表H8-2'!AJ15 -> 0 | J12: =IF(G12=0,0,IF(RIGHT(G12,1)<>"年",G12*12,IF(LEN(G12)=3,VALUE(LEFT(G12,2))*12,IF(LEN(G12)=2,VALUE(LEFT(G12,1))*12,"??")))) -> 0 | K12: =DATE((YEAR(F12)+G12),MONTH(F12),DAY(F12)) -> 0 | L12: =MIN((YEAR(K12)-YEAR(F12))*12+(MONTH(K12)-MONTH(F12)),(YEAR($D$7)-YEAR(F12))*12+MONTH($D$7)-MONTH(F12),G12*12) -> 0 | M12: =IF(K12<$B$7,0,IF($D$7>K12,MIN(MONTH($D$7),DATEDIF(DATE(YEAR(F12),MONTH(F12),"1"),$D$7,"M")-DATEDIF(DATE(YEAR(F12),MONTH(F12),"1"),DATEDIF(YEAR(K12),MONTH(K12),"1"),"M")),MIN(DATEDIF(DATE(YEAR(F12),MONTH(F12),"1"),$D$7,"m"),MONTH($D$7)))) -> 0 | N12: =IF(J12=0,0,ROUND(((1-H12)/J12)*D12,4)) -> 0 | O12: =ROUND(N12*M12,2) -> 0 | P12: =ROUND(I12-N12,2) -> 0 | Q12: =ROUND(N12*L12,2) -> 0 | R12: =ROUND(E12-Q12,2) -> 0
A13: ='[3]明细表H8-2'!A16 -> 0 | B13: ='[3]明细表H8-2'!B16 -> 0 | C13: ='[3]明细表H8-2'!C16 -> 0 | D13: ='[3]明细表H8-2'!S16 -> 0 | E13: ='[3]明细表H8-2'!AJ16 -> 0 | J13: =IF(G13=0,0,IF(RIGHT(G13,1)<>"年",G13*12,IF(LEN(G13)=3,VALUE(LEFT(G13,2))*12,IF(LEN(G13)=2,VALUE(LEFT(G13,1))*12,"??")))) -> 0 | K13: =DATE((YEAR(F13)+G13),MONTH(F13),DAY(F13)) -> 0 | L13: =MIN((YEAR(K13)-YEAR(F13))*12+(MONTH(K13)-MONTH(F13)),(YEAR($D$7)-YEAR(F13))*12+MONTH($D$7)-MONTH(F13),G13*12) -> 0 | M13: =IF(K13<$B$7,0,IF($D$7>K13,MIN(MONTH($D$7),DATEDIF(DATE(YEAR(F13),MONTH(F13),"1"),$D$7,"M")-DATEDIF(DATE(YEAR(F13),MONTH(F13),"1"),DATEDIF(YEAR(K13),MONTH(K13),"1"),"M")),MIN(DATEDIF(DATE(YEAR(F13),MONTH(F13),"1"),$D$7,"m"),MONTH($D$7)))) -> 0 | N13: =IF(J13=0,0,ROUND(((1-H13)/J13)*D13,4)) -> 0 | O13: =ROUND(N13*M13,2) -> 0 | P13: =ROUND(I13-N13,2) -> 0 | Q13: =ROUND(N13*L13,2) -> 0 | R13: =ROUND(E13-Q13,2) -> 0
B14: 合计 | D14: =SUM(D9:D13) -> 0 | E14: =SUM(E9:E13) -> 0 | N14: =SUM(N9:N13) -> 0 | O14: =SUM(O9:O13) -> 0 | P14: =SUM(P9:P13) -> 0 | Q14: =SUM(Q9:Q13) -> 0 | R14: =SUM(R9:R13) -> 0
A15: ='[3]明细表H8-2'!A33:C33 -> 其中：
A16: ='[3]明细表H8-2'!A34:C34 -> 房屋及建筑物 | D16: =SUMPRODUCT(($A$9:$A$13=$A16)*(D$9:D$13)) -> 0 | E16: =SUMPRODUCT(($A$9:$A$13=$A16)*(E$9:E$13)) -> 0 | N16: =SUMPRODUCT(($A$9:$A$13=$A16)*(N$9:N$13)) -> 0 | O16: =SUMPRODUCT(($A$9:$A$13=$A16)*(O$9:O$13)) -> 0 | P16: =SUMPRODUCT(($A$9:$A$13=$A16)*(P$9:P$13)) -> 0 | Q16: =SUMPRODUCT(($A$9:$A$13=$A16)*(Q$9:Q$13)) -> 0 | R16: =SUMPRODUCT(($A$9:$A$13=$A16)*(R$9:R$13)) -> 0
A17: ='[3]明细表H8-2'!A35:C35 -> 机器设备 | D17: =SUMPRODUCT(($A$9:$A$13=$A17)*(D$9:D$13)) -> 0 | E17: =SUMPRODUCT(($A$9:$A$13=$A17)*(E$9:E$13)) -> 0 | N17: =SUMPRODUCT(($A$9:$A$13=$A17)*(N$9:N$13)) -> 0 | O17: =SUMPRODUCT(($A$9:$A$13=$A17)*(O$9:O$13)) -> 0 | P17: =SUMPRODUCT(($A$9:$A$13=$A17)*(P$9:P$13)) -> 0 | Q17: =SUMPRODUCT(($A$9:$A$13=$A17)*(Q$9:Q$13)) -> 0 | R17: =SUMPRODUCT(($A$9:$A$13=$A17)*(R$9:R$13)) -> 0
A18: ='[3]明细表H8-2'!A36:C36 -> 运输设备 | D18: =SUMPRODUCT(($A$9:$A$13=$A18)*(D$9:D$13)) -> 0 | E18: =SUMPRODUCT(($A$9:$A$13=$A18)*(E$9:E$13)) -> 0 | N18: =SUMPRODUCT(($A$9:$A$13=$A18)*(N$9:N$13)) -> 0 | O18: =SUMPRODUCT(($A$9:$A$13=$A18)*(O$9:O$13)) -> 0 | P18: =SUMPRODUCT(($A$9:$A$13=$A18)*(P$9:P$13)) -> 0 | Q18: =SUMPRODUCT(($A$9:$A$13=$A18)*(Q$9:Q$13)) -> 0 | R18: =SUMPRODUCT(($A$9:$A$13=$A18)*(R$9:R$13)) -> 0
A19: ='[3]明细表H8-2'!A37:C37 -> 办公设备 | D19: =SUMPRODUCT(($A$9:$A$13=$A19)*(D$9:D$13)) -> 0 | E19: =SUMPRODUCT(($A$9:$A$13=$A19)*(E$9:E$13)) -> 0 | N19: =SUMPRODUCT(($A$9:$A$13=$A19)*(N$9:N$13)) -> 0 | O19: =SUMPRODUCT(($A$9:$A$13=$A19)*(O$9:O$13)) -> 0 | P19: =SUMPRODUCT(($A$9:$A$13=$A19)*(P$9:P$13)) -> 0 | Q19: =SUMPRODUCT(($A$9:$A$13=$A19)*(Q$9:Q$13)) -> 0 | R19: =SUMPRODUCT(($A$9:$A$13=$A19)*(R$9:R$13)) -> 0
A20: ='[3]明细表H8-2'!A38:C38 -> 其他设备 | D20: =SUMPRODUCT(($A$9:$A$13=$A20)*(D$9:D$13)) -> 0 | E20: =SUMPRODUCT(($A$9:$A$13=$A20)*(E$9:E$13)) -> 0 | N20: =SUMPRODUCT(($A$9:$A$13=$A20)*(N$9:N$13)) -> 0 | O20: =SUMPRODUCT(($A$9:$A$13=$A20)*(O$9:O$13)) -> 0 | P20: =SUMPRODUCT(($A$9:$A$13=$A20)*(P$9:P$13)) -> 0 | Q20: =SUMPRODUCT(($A$9:$A$13=$A20)*(Q$9:Q$13)) -> 0 | R20: =SUMPRODUCT(($A$9:$A$13=$A20)*(R$9:R$13)) -> 0
A21: 三、审计说明：参数来源（H8-2）、折旧期判断依据、重大差异原因、与H8-1/H8-9勾稽结果。
A22: 四、审计结论：□折旧测算准确、与账面无重大差异 □除下列差异外未见异常 □存在重大未调整差异不可确认。索引：H8-1 / H8-2 / H8-9。
A24: 提示：
A25: 《企业会计准则第21号——租赁》
A26: 第二十一条 承租人应当参照《企业会计准则第4号——固定资产》有关折旧规定，对使用权资产计提折旧。
A27: 承租人能够合理确定租赁期届满时取得租赁资产所有权的，应当在租赁资产剩余使用寿命内计提折旧。无法合理确定租赁期届满时能够取得租赁资产所有权的，应当在租赁期与租赁资产剩余使用寿命两者孰短的期间内计提折旧。

Sheet 折旧测算表（含减值）H8-8
A1: 致同会计师事务所
A2: 使用权资产折旧测算表
A3: =[3]底稿目录!A2 -> 被审计单位： | E3: =[3]底稿目录!A4 -> 编制人： | Q3: =[3]底稿目录!A6 -> 编制日期： | W3: 索引号： | X3: H8-8
A4: =[3]底稿目录!A3 -> 截止日：202X年12月31日 | E4: =[3]底稿目录!A5 -> 复核人： | Q4: =[3]底稿目录!A7 -> 复核日期： | W4: 页 次：
A5: 一、审计目标：确认已计提减值的使用权资产后续折旧以恰当金额计入报表；减值后月折旧=(原值×(1−残值率)−减值时累计折旧−减值准备)/剩余月数；本期折旧=减值前月数×原月折旧+减值后月数×新月折旧；减值一经确认不得转回（CAS21第21条+CAS8）；披露恰当。
A6: 二、审计过程：①自H8-2带入原值/累计折旧/减值准备；②减值金额、时点与减值测算表H8-10、可收回金额测试表H8-11勾稽（本表F7为模板全局减值日示例，实务宜按资产填写减值日）；③测算减值前/后月数及新旧月折旧；④当期折旧费用与账面、H8-1本期计提、H8-9分配勾稽；⑤无减值资产请改用「不含减值」表。
A7: 折旧期初： | B7: 45658 | C7: 折旧期末： | D7: 46022 | E7: 计提减值准备日期： | F7: 42129 | G7: 含减值关键公式：R=减值前月折旧；S=R×减值时已提月数；T=(原值×(1−残值率)−S−减值)/剩余月数；U=R×本期减值前月数+T×本期减值后月数；W=减值前累计+减值后累计。非公式列请粘贴数值。有⑧补提时须先完成H8-10再回本表重算。
A8: 使用权资产类别 | B8: 使用权资产名称 | C8: 使用权资产编号 | D8: 原值 | E8: 累计折旧 | F8: 减值准备 | G8: 开始使用日期 | H8: 使用年限 | I8: 残值率 | J8: 账面月折旧额 | K8: 使用月限 | L8: 测算到期日 | M8: 已提折旧月份 | N8: 截止计提减值准备日计提月份 | O8: 本期折旧月份 | P8: 本期折旧月份（减值前） | Q8: 本期折旧月份（减值后） | R8: 计提减值准备前月折旧 | S8: 计提减值准备前累计折旧 | T8: 计提减值准备后月折旧 | U8: 当期折旧费用 | V8: 月折旧额差异 | W8: 累计折旧费用 | X8: 累计折旧额差异
A9: ='[3]明细表H8-2'!A12 -> 0 | B9: ='[3]明细表H8-2'!B12 -> 0 | C9: ='[3]明细表H8-2'!C12 -> 0 | D9: ='[3]明细表H8-2'!S12 -> 0 | E9: ='[3]明细表H8-2'!AJ12 -> 0 | F9: ='[3]明细表H8-2'!BA12 -> 0 | K9: =IF(H9=0,0,IF(RIGHT(H9,1)<>"年",H9*12,IF(LEN(H9)=3,VALUE(LEFT(H9,2))*12,IF(LEN(H9)=2,VALUE(LEFT(H9,1))*12,"??")))) -> 0 | L9: =IF(DAY(G9)=1,IF(G9=0,0,DATE(YEAR(G9),MONTH(G9)+K9,DAY(G9))),IF(G9=0,0,DATE(YEAR(G9),MONTH(G9)+K9,DAY(G9)-1))) -> 0 | M9: =MIN(IF(AND(DAY(G9)=31,DAY($D$7)=30),IF(G9=0,0,IF(L9>$D$7,VALUE(DATEDIF(G9,MIN($D$7,L9),"m"))+1,VALUE(DATEDIF(G9,MIN($D$7,L9),"m")+2))),IF(G9=0,0,IF(L9>$D$7,DATEDIF(G9,MIN($D$7,L9),"m"),VALUE(DATEDIF(G9,MIN($D$7,L9),"m")+1)))),K9) -> 0 | N9: =IF(AND(DAY(G9)=31,DAY($F$7)=30),MIN(IF(G9=0,0,IF($F$7>G9,VALUE(DATEDIF(G9,$F$7,"m"))+1,0)),M9+1),MIN(IF(G9=0,0,IF($F$7>G9,DATEDIF(G9,$F$7,"m"),0)),M9)) -> 0 | O9: =IF(OR(G9=0,L9<$B$7),0,IF(AND(G9<$B$7,L9>$D$7),VALUE(DATEDIF($B$7,$D$7,"m")+1),IF(AND(G9<$B$7,L9<=$D$7),VALUE(DATEDIF($B$7,L9,"m")+1),IF(AND(G9>=$B$7,L9>$D$7),VALUE(DATEDIF(G9,$D$7,"m")),IF(AND(G9>=$B$7,L9<=$D$7),VALUE(DATEDIF(G9,L9,"m")+1),))))) -> 0 | P9: =IF(AND(YEAR(G9)=YEAR($D$7),DAY(G9)=31,DAY($D$7)=30),IF(G9>$F$7,0,O9-Q9+1),IF(G9>$F$7,0,O9-Q9)) -> 0 | Q9: =IF(AND(DAY($F$7)=31,DAY($D$7)=30),IF(G9=0,0,IF($F$7<$B$7,O9,VALUE(DATEDIF(MAX(G9,$F$7),MIN(L9,$D$7),"m")))+1),IF(G9=0,0,IF($F$7<$B$7,O9,DATEDIF(MAX(G9,$F$7),MIN(L9,$D$7),"m")))) -> 0 | R9: =IF(K9=0,0,ROUND(((1-I9)/K9)*D9,4)) -> 0 | S9: =ROUND(R9*N9,2) -> 0 | T9: =IF((D9*(1-I9)-S9-F9)>0,(D9*(1-I9)-S9-F9)/(K9-N9),0) -> 0 | U9: =ROUND(R9*P9,2)+ROUND(T9*Q9,2) -> 0 | V9: =ROUND(J9-T9,2) -> 0 | W9: =ROUND(R9*N9,2)+ROUND(T9*(M9-N9),2) -> 0 | X9: =ROUND(E9-W9,2) -> 0
A10: ='[3]明细表H8-2'!A13 -> 0 | B10: ='[3]明细表H8-2'!B13 -> 0 | C10: ='[3]明细表H8-2'!C13 -> 0 | D10: ='[3]明细表H8-2'!S13 -> 0 | E10: ='[3]明细表H8-2'!AJ13 -> 0 | F10: ='[3]明细表H8-2'!BA13 -> 0 | K10: =IF(H10=0,0,IF(RIGHT(H10,1)<>"年",H10*12,IF(LEN(H10)=3,VALUE(LEFT(H10,2))*12,IF(LEN(H10)=2,VALUE(LEFT(H10,1))*12,"??")))) -> 0 | L10: =IF(DAY(G10)=1,IF(G10=0,0,DATE(YEAR(G10),MONTH(G10)+K10,DAY(G10))),IF(G10=0,0,DATE(YEAR(G10),MONTH(G10)+K10,DAY(G10)-1))) -> 0 | M10: =MIN(IF(AND(DAY(G10)=31,DAY($D$7)=30),IF(G10=0,0,IF(L10>$D$7,VALUE(DATEDIF(G10,MIN($D$7,L10),"m"))+1,VALUE(DATEDIF(G10,MIN($D$7,L10),"m")+2))),IF(G10=0,0,IF(L10>$D$7,DATEDIF(G10,MIN($D$7,L10),"m"),VALUE(DATEDIF(G10,MIN($D$7,L10),"m")+1)))),K10) -> 0 | N10: =IF(AND(DAY(G10)=31,DAY($F$7)=30),MIN(IF(G10=0,0,IF($F$7>G10,VALUE(DATEDIF(G10,$F$7,"m"))+1,0)),M10+1),MIN(IF(G10=0,0,IF($F$7>G10,DATEDIF(G10,$F$7,"m"),0)),M10)) -> 0 | O10: =IF(OR(G10=0,L10<$B$7),0,IF(AND(G10<$B$7,L10>$D$7),VALUE(DATEDIF($B$7,$D$7,"m")+1),IF(AND(G10<$B$7,L10<=$D$7),VALUE(DATEDIF($B$7,L10,"m")+1),IF(AND(G10>=$B$7,L10>$D$7),VALUE(DATEDIF(G10,$D$7,"m")),IF(AND(G10>=$B$7,L10<=$D$7),VALUE(DATEDIF(G10,L10,"m")+1),))))) -> 0 | P10: =IF(AND(YEAR(G10)=YEAR($D$7),DAY(G10)=31,DAY($D$7)=30),IF(G10>$F$7,0,O10-Q10+1),IF(G10>$F$7,0,O10-Q10)) -> 0 | Q10: =IF(AND(DAY($F$7)=31,DAY($D$7)=30),IF(G10=0,0,IF($F$7<$B$7,O10,VALUE(DATEDIF(MAX(G10,$F$7),MIN(L10,$D$7),"m")))+1),IF(G10=0,0,IF($F$7<$B$7,O10,DATEDIF(MAX(G10,$F$7),MIN(L10,$D$7),"m")))) -> 0 | R10: =IF(K10=0,0,ROUND(((1-I10)/K10)*D10,4)) -> 0 | S10: =ROUND(R10*N10,2) -> 0 | T10: =IF((D10*(1-I10)-S10-F10)>0,(D10*(1-I10)-S10-F10)/(K10-N10),0) -> 0 | U10: =ROUND(R10*P10,2)+ROUND(T10*Q10,2) -> 0 | V10: =ROUND(J10-T10,2) -> 0 | W10: =ROUND(R10*N10,2)+ROUND(T10*(M10-N10),2) -> 0 | X10: =ROUND(E10-W10,2) -> 0
A11: ='[3]明细表H8-2'!A14 -> 0 | B11: ='[3]明细表H8-2'!B14 -> 0 | C11: ='[3]明细表H8-2'!C14 -> 0 | D11: ='[3]明细表H8-2'!S14 -> 0 | E11: ='[3]明细表H8-2'!AJ14 -> 0 | F11: ='[3]明细表H8-2'!BA14 -> 0 | K11: =IF(H11=0,0,IF(RIGHT(H11,1)<>"年",H11*12,IF(LEN(H11)=3,VALUE(LEFT(H11,2))*12,IF(LEN(H11)=2,VALUE(LEFT(H11,1))*12,"??")))) -> 0 | L11: =IF(DAY(G11)=1,IF(G11=0,0,DATE(YEAR(G11),MONTH(G11)+K11,DAY(G11))),IF(G11=0,0,DATE(YEAR(G11),MONTH(G11)+K11,DAY(G11)-1))) -> 0 | M11: =MIN(IF(AND(DAY(G11)=31,DAY($D$7)=30),IF(G11=0,0,IF(L11>$D$7,VALUE(DATEDIF(G11,MIN($D$7,L11),"m"))+1,VALUE(DATEDIF(G11,MIN($D$7,L11),"m")+2))),IF(G11=0,0,IF(L11>$D$7,DATEDIF(G11,MIN($D$7,L11),"m"),VALUE(DATEDIF(G11,MIN($D$7,L11),"m")+1)))),K11) -> 0 | N11: =IF(AND(DAY(G11)=31,DAY($F$7)=30),MIN(IF(G11=0,0,IF($F$7>G11,VALUE(DATEDIF(G11,$F$7,"m"))+1,0)),M11+1),MIN(IF(G11=0,0,IF($F$7>G11,DATEDIF(G11,$F$7,"m"),0)),M11)) -> 0 | O11: =IF(OR(G11=0,L11<$B$7),0,IF(AND(G11<$B$7,L11>$D$7),VALUE(DATEDIF($B$7,$D$7,"m")+1),IF(AND(G11<$B$7,L11<=$D$7),VALUE(DATEDIF($B$7,L11,"m")+1),IF(AND(G11>=$B$7,L11>$D$7),VALUE(DATEDIF(G11,$D$7,"m")),IF(AND(G11>=$B$7,L11<=$D$7),VALUE(DATEDIF(G11,L11,"m")+1),))))) -> 0 | P11: =IF(AND(YEAR(G11)=YEAR($D$7),DAY(G11)=31,DAY($D$7)=30),IF(G11>$F$7,0,O11-Q11+1),IF(G11>$F$7,0,O11-Q11)) -> 0 | Q11: =IF(AND(DAY($F$7)=31,DAY($D$7)=30),IF(G11=0,0,IF($F$7<$B$7,O11,VALUE(DATEDIF(MAX(G11,$F$7),MIN(L11,$D$7),"m")))+1),IF(G11=0,0,IF($F$7<$B$7,O11,DATEDIF(MAX(G11,$F$7),MIN(L11,$D$7),"m")))) -> 0 | R11: =IF(K11=0,0,ROUND(((1-I11)/K11)*D11,4)) -> 0 | S11: =ROUND(R11*N11,2) -> 0 | T11: =IF((D11*(1-I11)-S11-F11)>0,(D11*(1-I11)-S11-F11)/(K11-N11),0) -> 0 | U11: =ROUND(R11*P11,2)+ROUND(T11*Q11,2) -> 0 | V11: =ROUND(J11-T11,2) -> 0 | W11: =ROUND(R11*N11,2)+ROUND(T11*(M11-N11),2) -> 0 | X11: =ROUND(E11-W11,2) -> 0
A12: ='[3]明细表H8-2'!A15 -> 0 | B12: ='[3]明细表H8-2'!B15 -> 0 | C12: ='[3]明细表H8-2'!C15 -> 0 | D12: ='[3]明细表H8-2'!S15 -> 0 | E12: ='[3]明细表H8-2'!AJ15 -> 0 | F12: ='[3]明细表H8-2'!BA15 -> 0 | K12: =IF(H12=0,0,IF(RIGHT(H12,1)<>"年",H12*12,IF(LEN(H12)=3,VALUE(LEFT(H12,2))*12,IF(LEN(H12)=2,VALUE(LEFT(H12,1))*12,"??")))) -> 0 | L12: =IF(DAY(G12)=1,IF(G12=0,0,DATE(YEAR(G12),MONTH(G12)+K12,DAY(G12))),IF(G12=0,0,DATE(YEAR(G12),MONTH(G12)+K12,DAY(G12)-1))) -> 0 | M12: =MIN(IF(AND(DAY(G12)=31,DAY($D$7)=30),IF(G12=0,0,IF(L12>$D$7,VALUE(DATEDIF(G12,MIN($D$7,L12),"m"))+1,VALUE(DATEDIF(G12,MIN($D$7,L12),"m")+2))),IF(G12=0,0,IF(L12>$D$7,DATEDIF(G12,MIN($D$7,L12),"m"),VALUE(DATEDIF(G12,MIN($D$7,L12),"m")+1)))),K12) -> 0 | N12: =IF(AND(DAY(G12)=31,DAY($F$7)=30),MIN(IF(G12=0,0,IF($F$7>G12,VALUE(DATEDIF(G12,$F$7,"m"))+1,0)),M12+1),MIN(IF(G12=0,0,IF($F$7>G12,DATEDIF(G12,$F$7,"m"),0)),M12)) -> 0 | O12: =IF(OR(G12=0,L12<$B$7),0,IF(AND(G12<$B$7,L12>$D$7),VALUE(DATEDIF($B$7,$D$7,"m")+1),IF(AND(G12<$B$7,L12<=$D$7),VALUE(DATEDIF($B$7,L12,"m")+1),IF(AND(G12>=$B$7,L12>$D$7),VALUE(DATEDIF(G12,$D$7,"m")),IF(AND(G12>=$B$7,L12<=$D$7),VALUE(DATEDIF(G12,L12,"m")+1),))))) -> 0 | P12: =IF(AND(YEAR(G12)=YEAR($D$7),DAY(G12)=31,DAY($D$7)=30),IF(G12>$F$7,0,O12-Q12+1),IF(G12>$F$7,0,O12-Q12)) -> 0 | Q12: =IF(AND(DAY($F$7)=31,DAY($D$7)=30),IF(G12=0,0,IF($F$7<$B$7,O12,VALUE(DATEDIF(MAX(G12,$F$7),MIN(L12,$D$7),"m")))+1),IF(G12=0,0,IF($F$7<$B$7,O12,DATEDIF(MAX(G12,$F$7),MIN(L12,$D$7),"m")))) -> 0 | R12: =IF(K12=0,0,ROUND(((1-I12)/K12)*D12,4)) -> 0 | S12: =ROUND(R12*N12,2) -> 0 | T12: =IF((D12*(1-I12)-S12-F12)>0,(D12*(1-I12)-S12-F12)/(K12-N12),0) -> 0 | U12: =ROUND(R12*P12,2)+ROUND(T12*Q12,2) -> 0 | V12: =ROUND(J12-T12,2) -> 0 | W12: =ROUND(R12*N12,2)+ROUND(T12*(M12-N12),2) -> 0 | X12: =ROUND(E12-W12,2) -> 0
A13: ='[3]明细表H8-2'!A16 -> 0 | B13: ='[3]明细表H8-2'!B16 -> 0 | C13: ='[3]明细表H8-2'!C16 -> 0 | D13: ='[3]明细表H8-2'!S16 -> 0 | E13: ='[3]明细表H8-2'!AJ16 -> 0 | F13: ='[3]明细表H8-2'!BA16 -> 0 | K13: =IF(H13=0,0,IF(RIGHT(H13,1)<>"年",H13*12,IF(LEN(H13)=3,VALUE(LEFT(H13,2))*12,IF(LEN(H13)=2,VALUE(LEFT(H13,1))*12,"??")))) -> 0 | L13: =IF(DAY(G13)=1,IF(G13=0,0,DATE(YEAR(G13),MONTH(G13)+K13,DAY(G13))),IF(G13=0,0,DATE(YEAR(G13),MONTH(G13)+K13,DAY(G13)-1))) -> 0 | M13: =MIN(IF(AND(DAY(G13)=31,DAY($D$7)=30),IF(G13=0,0,IF(L13>$D$7,VALUE(DATEDIF(G13,MIN($D$7,L13),"m"))+1,VALUE(DATEDIF(G13,MIN($D$7,L13),"m")+2))),IF(G13=0,0,IF(L13>$D$7,DATEDIF(G13,MIN($D$7,L13),"m"),VALUE(DATEDIF(G13,MIN($D$7,L13),"m")+1)))),K13) -> 0 | N13: =IF(AND(DAY(G13)=31,DAY($F$7)=30),MIN(IF(G13=0,0,IF($F$7>G13,VALUE(DATEDIF(G13,$F$7,"m"))+1,0)),M13+1),MIN(IF(G13=0,0,IF($F$7>G13,DATEDIF(G13,$F$7,"m"),0)),M13)) -> 0 | O13: =IF(OR(G13=0,L13<$B$7),0,IF(AND(G13<$B$7,L13>$D$7),VALUE(DATEDIF($B$7,$D$7,"m")+1),IF(AND(G13<$B$7,L13<=$D$7),VALUE(DATEDIF($B$7,L13,"m")+1),IF(AND(G13>=$B$7,L13>$D$7),VALUE(DATEDIF(G13,$D$7,"m")),IF(AND(G13>=$B$7,L13<=$D$7),VALUE(DATEDIF(G13,L13,"m")+1),))))) -> 0 | P13: =IF(AND(YEAR(G13)=YEAR($D$7),DAY(G13)=31,DAY($D$7)=30),IF(G13>$F$7,0,O13-Q13+1),IF(G13>$F$7,0,O13-Q13)) -> 0 | Q13: =IF(AND(DAY($F$7)=31,DAY($D$7)=30),IF(G13=0,0,IF($F$7<$B$7,O13,VALUE(DATEDIF(MAX(G13,$F$7),MIN(L13,$D$7),"m")))+1),IF(G13=0,0,IF($F$7<$B$7,O13,DATEDIF(MAX(G13,$F$7),MIN(L13,$D$7),"m")))) -> 0 | R13: =IF(K13=0,0,ROUND(((1-I13)/K13)*D13,4)) -> 0 | S13: =ROUND(R13*N13,2) -> 0 | T13: =IF((D13*(1-I13)-S13-F13)>0,(D13*(1-I13)-S13-F13)/(K13-N13),0) -> 0 | U13: =ROUND(R13*P13,2)+ROUND(T13*Q13,2) -> 0 | V13: =ROUND(J13-T13,2) -> 0 | W13: =ROUND(R13*N13,2)+ROUND(T13*(M13-N13),2) -> 0 | X13: =ROUND(E13-W13,2) -> 0
A14: ='[3]明细表H8-2'!A28 -> 0 | B14: ='[3]明细表H8-2'!B28 -> 0 | C14: ='[3]明细表H8-2'!C28 -> 0 | D14: ='[3]明细表H8-2'!S28 -> 0 | E14: ='[3]明细表H8-2'!AJ28 -> 0 | F14: ='[3]明细表H8-2'!BA28 -> 0 | K14: =IF(H14=0,0,IF(RIGHT(H14,1)<>"年",H14*12,IF(LEN(H14)=3,VALUE(LEFT(H14,2))*12,IF(LEN(H14)=2,VALUE(LEFT(H14,1))*12,"??")))) -> 0 | L14: =IF(DAY(G14)=1,IF(G14=0,0,DATE(YEAR(G14),MONTH(G14)+K14,DAY(G14))),IF(G14=0,0,DATE(YEAR(G14),MONTH(G14)+K14,DAY(G14)-1))) -> 0 | M14: =MIN(IF(AND(DAY(G14)=31,DAY($D$7)=30),IF(G14=0,0,IF(L14>$D$7,VALUE(DATEDIF(G14,MIN($D$7,L14),"m"))+1,VALUE(DATEDIF(G14,MIN($D$7,L14),"m")+2))),IF(G14=0,0,IF(L14>$D$7,DATEDIF(G14,MIN($D$7,L14),"m"),VALUE(DATEDIF(G14,MIN($D$7,L14),"m")+1)))),K14) -> 0 | N14: =IF(AND(DAY(G14)=31,DAY($F$7)=30),MIN(IF(G14=0,0,IF($F$7>G14,VALUE(DATEDIF(G14,$F$7,"m"))+1,0)),M14+1),MIN(IF(G14=0,0,IF($F$7>G14,DATEDIF(G14,$F$7,"m"),0)),M14)) -> 0 | O14: =IF(OR(G14=0,L14<$B$7),0,IF(AND(G14<$B$7,L14>$D$7),VALUE(DATEDIF($B$7,$D$7,"m")+1),IF(AND(G14<$B$7,L14<=$D$7),VALUE(DATEDIF($B$7,L14,"m")+1),IF(AND(G14>=$B$7,L14>$D$7),VALUE(DATEDIF(G14,$D$7,"m")),IF(AND(G14>=$B$7,L14<=$D$7),VALUE(DATEDIF(G14,L14,"m")+1),))))) -> 0 | P14: =IF(AND(YEAR(G14)=YEAR($D$7),DAY(G14)=31,DAY($D$7)=30),IF(G14>$F$7,0,O14-Q14+1),IF(G14>$F$7,0,O14-Q14)) -> 0 | Q14: =IF(AND(DAY($F$7)=31,DAY($D$7)=30),IF(G14=0,0,IF($F$7<$B$7,O14,VALUE(DATEDIF(MAX(G14,$F$7),MIN(L14,$D$7),"m")))+1),IF(G14=0,0,IF($F$7<$B$7,O14,DATEDIF(MAX(G14,$F$7),MIN(L14,$D$7),"m")))) -> 0 | R14: =IF(K14=0,0,ROUND(((1-I14)/K14)*D14,4)) -> 0 | S14: =ROUND(R14*N14,2) -> 0 | T14: =IF((D14*(1-I14)-S14-F14)>0,(D14*(1-I14)-S14-F14)/(K14-N14),0) -> 0 | U14: =ROUND(R14*P14,2)+ROUND(T14*Q14,2) -> 0 | V14: =ROUND(J14-T14,2) -> 0 | W14: =ROUND(R14*N14,2)+ROUND(T14*(M14-N14),2) -> 0 | X14: =ROUND(E14-W14,2) -> 0
A15: ='[3]明细表H8-2'!A29 -> 0 | B15: ='[3]明细表H8-2'!B29 -> 0 | C15: ='[3]明细表H8-2'!C29 -> 0 | D15: ='[3]明细表H8-2'!S29 -> 0 | E15: ='[3]明细表H8-2'!AJ29 -> 0 | F15: ='[3]明细表H8-2'!BA29 -> 0 | K15: =IF(H15=0,0,IF(RIGHT(H15,1)<>"年",H15*12,IF(LEN(H15)=3,VALUE(LEFT(H15,2))*12,IF(LEN(H15)=2,VALUE(LEFT(H15,1))*12,"??")))) -> 0 | L15: =IF(DAY(G15)=1,IF(G15=0,0,DATE(YEAR(G15),MONTH(G15)+K15,DAY(G15))),IF(G15=0,0,DATE(YEAR(G15),MONTH(G15)+K15,DAY(G15)-1))) -> 0 | M15: =MIN(IF(AND(DAY(G15)=31,DAY($D$7)=30),IF(G15=0,0,IF(L15>$D$7,VALUE(DATEDIF(G15,MIN($D$7,L15),"m"))+1,VALUE(DATEDIF(G15,MIN($D$7,L15),"m")+2))),IF(G15=0,0,IF(L15>$D$7,DATEDIF(G15,MIN($D$7,L15),"m"),VALUE(DATEDIF(G15,MIN($D$7,L15),"m")+1)))),K15) -> 0 | N15: =IF(AND(DAY(G15)=31,DAY($F$7)=30),MIN(IF(G15=0,0,IF($F$7>G15,VALUE(DATEDIF(G15,$F$7,"m"))+1,0)),M15+1),MIN(IF(G15=0,0,IF($F$7>G15,DATEDIF(G15,$F$7,"m"),0)),M15)) -> 0 | O15: =IF(OR(G15=0,L15<$B$7),0,IF(AND(G15<$B$7,L15>$D$7),VALUE(DATEDIF($B$7,$D$7,"m")+1),IF(AND(G15<$B$7,L15<=$D$7),VALUE(DATEDIF($B$7,L15,"m")+1),IF(AND(G15>=$B$7,L15>$D$7),VALUE(DATEDIF(G15,$D$7,"m")),IF(AND(G15>=$B$7,L15<=$D$7),VALUE(DATEDIF(G15,L15,"m")+1),))))) -> 0 | P15: =IF(AND(YEAR(G15)=YEAR($D$7),DAY(G15)=31,DAY($D$7)=30),IF(G15>$F$7,0,O15-Q15+1),IF(G15>$F$7,0,O15-Q15)) -> 0 | Q15: =IF(AND(DAY($F$7)=31,DAY($D$7)=30),IF(G15=0,0,IF($F$7<$B$7,O15,VALUE(DATEDIF(MAX(G15,$F$7),MIN(L15,$D$7),"m")))+1),IF(G15=0,0,IF($F$7<$B$7,O15,DATEDIF(MAX(G15,$F$7),MIN(L15,$D$7),"m")))) -> 0 | R15: =IF(K15=0,0,ROUND(((1-I15)/K15)*D15,4)) -> 0 | S15: =ROUND(R15*N15,2) -> 0 | T15: =IF((D15*(1-I15)-S15-F15)>0,(D15*(1-I15)-S15-F15)/(K15-N15),0) -> 0 | U15: =ROUND(R15*P15,2)+ROUND(T15*Q15,2) -> 0 | V15: =ROUND(J15-T15,2) -> 0 | W15: =ROUND(R15*N15,2)+ROUND(T15*(M15-N15),2) -> 0 | X15: =ROUND(E15-W15,2) -> 0
A16: ='[3]明细表H8-2'!A30 -> 0 | B16: ='[3]明细表H8-2'!B30 -> 0 | C16: ='[3]明细表H8-2'!C30 -> 0 | D16: ='[3]明细表H8-2'!S30 -> 0 | E16: ='[3]明细表H8-2'!AJ30 -> 0 | F16: ='[3]明细表H8-2'!BA30 -> 0 | K16: =IF(H16=0,0,IF(RIGHT(H16,1)<>"年",H16*12,IF(LEN(H16)=3,VALUE(LEFT(H16,2))*12,IF(LEN(H16)=2,VALUE(LEFT(H16,1))*12,"??")))) -> 0 | L16: =IF(DAY(G16)=1,IF(G16=0,0,DATE(YEAR(G16),MONTH(G16)+K16,DAY(G16))),IF(G16=0,0,DATE(YEAR(G16),MONTH(G16)+K16,DAY(G16)-1))) -> 0 | M16: =MIN(IF(AND(DAY(G16)=31,DAY($D$7)=30),IF(G16=0,0,IF(L16>$D$7,VALUE(DATEDIF(G16,MIN($D$7,L16),"m"))+1,VALUE(DATEDIF(G16,MIN($D$7,L16),"m")+2))),IF(G16=0,0,IF(L16>$D$7,DATEDIF(G16,MIN($D$7,L16),"m"),VALUE(DATEDIF(G16,MIN($D$7,L16),"m")+1)))),K16) -> 0 | N16: =IF(AND(DAY(G16)=31,DAY($F$7)=30),MIN(IF(G16=0,0,IF($F$7>G16,VALUE(DATEDIF(G16,$F$7,"m"))+1,0)),M16+1),MIN(IF(G16=0,0,IF($F$7>G16,DATEDIF(G16,$F$7,"m"),0)),M16)) -> 0 | O16: =IF(OR(G16=0,L16<$B$7),0,IF(AND(G16<$B$7,L16>$D$7),VALUE(DATEDIF($B$7,$D$7,"m")+1),IF(AND(G16<$B$7,L16<=$D$7),VALUE(DATEDIF($B$7,L16,"m")+1),IF(AND(G16>=$B$7,L16>$D$7),VALUE(DATEDIF(G16,$D$7,"m")),IF(AND(G16>=$B$7,L16<=$D$7),VALUE(DATEDIF(G16,L16,"m")+1),))))) -> 0 | P16: =IF(AND(YEAR(G16)=YEAR($D$7),DAY(G16)=31,DAY($D$7)=30),IF(G16>$F$7,0,O16-Q16+1),IF(G16>$F$7,0,O16-Q16)) -> 0 | Q16: =IF(AND(DAY($F$7)=31,DAY($D$7)=30),IF(G16=0,0,IF($F$7<$B$7,O16,VALUE(DATEDIF(MAX(G16,$F$7),MIN(L16,$D$7),"m")))+1),IF(G16=0,0,IF($F$7<$B$7,O16,DATEDIF(MAX(G16,$F$7),MIN(L16,$D$7),"m")))) -> 0 | R16: =IF(K16=0,0,ROUND(((1-I16)/K16)*D16,4)) -> 0 | S16: =ROUND(R16*N16,2) -> 0 | T16: =IF((D16*(1-I16)-S16-F16)>0,(D16*(1-I16)-S16-F16)/(K16-N16),0) -> 0 | U16: =ROUND(R16*P16,2)+ROUND(T16*Q16,2) -> 0 | V16: =ROUND(J16-T16,2) -> 0 | W16: =ROUND(R16*N16,2)+ROUND(T16*(M16-N16),2) -> 0 | X16: =ROUND(E16-W16,2) -> 0
A17: ='[3]明细表H8-2'!A31 -> 0 | B17: ='[3]明细表H8-2'!B31 -> 0 | C17: ='[3]明细表H8-2'!C31 -> 0 | D17: ='[3]明细表H8-2'!S31 -> 0 | E17: ='[3]明细表H8-2'!AJ31 -> 0 | F17: ='[3]明细表H8-2'!BA31 -> 0 | K17: =IF(H17=0,0,IF(RIGHT(H17,1)<>"年",H17*12,IF(LEN(H17)=3,VALUE(LEFT(H17,2))*12,IF(LEN(H17)=2,VALUE(LEFT(H17,1))*12,"??")))) -> 0 | L17: =IF(DAY(G17)=1,IF(G17=0,0,DATE(YEAR(G17),MONTH(G17)+K17,DAY(G17))),IF(G17=0,0,DATE(YEAR(G17),MONTH(G17)+K17,DAY(G17)-1))) -> 0 | M17: =MIN(IF(AND(DAY(G17)=31,DAY($D$7)=30),IF(G17=0,0,IF(L17>$D$7,VALUE(DATEDIF(G17,MIN($D$7,L17),"m"))+1,VALUE(DATEDIF(G17,MIN($D$7,L17),"m")+2))),IF(G17=0,0,IF(L17>$D$7,DATEDIF(G17,MIN($D$7,L17),"m"),VALUE(DATEDIF(G17,MIN($D$7,L17),"m")+1)))),K17) -> 0 | N17: =IF(AND(DAY(G17)=31,DAY($F$7)=30),MIN(IF(G17=0,0,IF($F$7>G17,VALUE(DATEDIF(G17,$F$7,"m"))+1,0)),M17+1),MIN(IF(G17=0,0,IF($F$7>G17,DATEDIF(G17,$F$7,"m"),0)),M17)) -> 0 | O17: =IF(OR(G17=0,L17<$B$7),0,IF(AND(G17<$B$7,L17>$D$7),VALUE(DATEDIF($B$7,$D$7,"m")+1),IF(AND(G17<$B$7,L17<=$D$7),VALUE(DATEDIF($B$7,L17,"m")+1),IF(AND(G17>=$B$7,L17>$D$7),VALUE(DATEDIF(G17,$D$7,"m")),IF(AND(G17>=$B$7,L17<=$D$7),VALUE(DATEDIF(G17,L17,"m")+1),))))) -> 0 | P17: =IF(AND(YEAR(G17)=YEAR($D$7),DAY(G17)=31,DAY($D$7)=30),IF(G17>$F$7,0,O17-Q17+1),IF(G17>$F$7,0,O17-Q17)) -> 0 | Q17: =IF(AND(DAY($F$7)=31,DAY($D$7)=30),IF(G17=0,0,IF($F$7<$B$7,O17,VALUE(DATEDIF(MAX(G17,$F$7),MIN(L17,$D$7),"m")))+1),IF(G17=0,0,IF($F$7<$B$7,O17,DATEDIF(MAX(G17,$F$7),MIN(L17,$D$7),"m")))) -> 0 | R17: =IF(K17=0,0,ROUND(((1-I17)/K17)*D17,4)) -> 0 | S17: =ROUND(R17*N17,2) -> 0 | T17: =IF((D17*(1-I17)-S17-F17)>0,(D17*(1-I17)-S17-F17)/(K17-N17),0) -> 0 | U17: =ROUND(R17*P17,2)+ROUND(T17*Q17,2) -> 0 | V17: =ROUND(J17-T17,2) -> 0 | W17: =ROUND(R17*N17,2)+ROUND(T17*(M17-N17),2) -> 0 | X17: =ROUND(E17-W17,2) -> 0
A18: 合计 | D18: =SUM(D9:D17) -> 0 | E18: =SUM(E9:E17) -> 0 | F18: =SUM(F9:F17) -> 0 | S18: =SUM(S9:S17) -> 0 | T18: =SUM(T9:T17) -> 0 | U18: =SUM(U9:U17) -> 0 | V18: =SUM(V9:V17) -> 0 | W18: =SUM(W9:W17) -> 0 | X18: =SUM(X9:X17) -> 0
A19: ='[3]明细表H8-2'!A33:C33 -> 其中：
A20: ='[3]明细表H8-2'!A34:C34 -> 房屋及建筑物 | D20: =SUMPRODUCT(($A$9:$A$17=$A20)*(D$9:D$17)) -> 0 | E20: =SUMPRODUCT(($A$9:$A$17=$A20)*(E$9:E$17)) -> 0 | F20: =SUMPRODUCT(($A$9:$A$17=$A20)*(F$9:F$17)) -> 0 | P20: =SUMPRODUCT(($A$9:$A$17=$A20)*(P$9:P$17)) -> 0 | Q20: =SUMPRODUCT(($A$9:$A$17=$A20)*(Q$9:Q$17)) -> 0 | R20: =SUMPRODUCT(($A$9:$A$17=$A20)*(R$9:R$17)) -> 0 | S20: =SUMPRODUCT(($A$9:$A$17=$A20)*(S$9:S$17)) -> 0 | T20: =SUMPRODUCT(($A$9:$A$17=$A20)*(T$9:T$17)) -> 0 | U20: =SUMPRODUCT(($A$9:$A$17=$A20)*(U$9:U$17)) -> 0 | V20: =SUMPRODUCT(($A$9:$A$17=$A20)*(V$9:V$17)) -> 0 | W20: =SUMPRODUCT(($A$9:$A$17=$A20)*(W$9:W$17)) -> 0 | X20: =SUMPRODUCT(($A$9:$A$17=$A20)*(X$9:X$17)) -> 0
A21: ='[3]明细表H8-2'!A35:C35 -> 机器设备 | D21: =SUMPRODUCT(($A$9:$A$17=$A21)*(D$9:D$17)) -> 0 | E21: =SUMPRODUCT(($A$9:$A$17=$A21)*(E$9:E$17)) -> 0 | F21: =SUMPRODUCT(($A$9:$A$17=$A21)*(F$9:F$17)) -> 0 | P21: =SUMPRODUCT(($A$9:$A$17=$A21)*(P$9:P$17)) -> 0 | Q21: =SUMPRODUCT(($A$9:$A$17=$A21)*(Q$9:Q$17)) -> 0 | R21: =SUMPRODUCT(($A$9:$A$17=$A21)*(R$9:R$17)) -> 0 | S21: =SUMPRODUCT(($A$9:$A$17=$A21)*(S$9:S$17)) -> 0 | T21: =SUMPRODUCT(($A$9:$A$17=$A21)*(T$9:T$17)) -> 0 | U21: =SUMPRODUCT(($A$9:$A$17=$A21)*(U$9:U$17)) -> 0 | V21: =SUMPRODUCT(($A$9:$A$17=$A21)*(V$9:V$17)) -> 0 | W21: =SUMPRODUCT(($A$9:$A$17=$A21)*(W$9:W$17)) -> 0 | X21: =SUMPRODUCT(($A$9:$A$17=$A21)*(X$9:X$17)) -> 0
A22: ='[3]明细表H8-2'!A36:C36 -> 运输设备 | D22: =SUMPRODUCT(($A$9:$A$17=$A22)*(D$9:D$17)) -> 0 | E22: =SUMPRODUCT(($A$9:$A$17=$A22)*(E$9:E$17)) -> 0 | F22: =SUMPRODUCT(($A$9:$A$17=$A22)*(F$9:F$17)) -> 0 | P22: =SUMPRODUCT(($A$9:$A$17=$A22)*(P$9:P$17)) -> 0 | Q22: =SUMPRODUCT(($A$9:$A$17=$A22)*(Q$9:Q$17)) -> 0 | R22: =SUMPRODUCT(($A$9:$A$17=$A22)*(R$9:R$17)) -> 0 | S22: =SUMPRODUCT(($A$9:$A$17=$A22)*(S$9:S$17)) -> 0 | T22: =SUMPRODUCT(($A$9:$A$17=$A22)*(T$9:T$17)) -> 0 | U22: =SUMPRODUCT(($A$9:$A$17=$A22)*(U$9:U$17)) -> 0 | V22: =SUMPRODUCT(($A$9:$A$17=$A22)*(V$9:V$17)) -> 0 | W22: =SUMPRODUCT(($A$9:$A$17=$A22)*(W$9:W$17)) -> 0 | X22: =SUMPRODUCT(($A$9:$A$17=$A22)*(X$9:X$17)) -> 0
A23: ='[3]明细表H8-2'!A37:C37 -> 办公设备 | D23: =SUMPRODUCT(($A$9:$A$17=$A23)*(D$9:D$17)) -> 0 | E23: =SUMPRODUCT(($A$9:$A$17=$A23)*(E$9:E$17)) -> 0 | F23: =SUMPRODUCT(($A$9:$A$17=$A23)*(F$9:F$17)) -> 0 | P23: =SUMPRODUCT(($A$9:$A$17=$A23)*(P$9:P$17)) -> 0 | Q23: =SUMPRODUCT(($A$9:$A$17=$A23)*(Q$9:Q$17)) -> 0 | R23: =SUMPRODUCT(($A$9:$A$17=$A23)*(R$9:R$17)) -> 0 | S23: =SUMPRODUCT(($A$9:$A$17=$A23)*(S$9:S$17)) -> 0 | T23: =SUMPRODUCT(($A$9:$A$17=$A23)*(T$9:T$17)) -> 0 | U23: =SUMPRODUCT(($A$9:$A$17=$A23)*(U$9:U$17)) -> 0 | V23: =SUMPRODUCT(($A$9:$A$17=$A23)*(V$9:V$17)) -> 0 | W23: =SUMPRODUCT(($A$9:$A$17=$A23)*(W$9:W$17)) -> 0 | X23: =SUMPRODUCT(($A$9:$A$17=$A23)*(X$9:X$17)) -> 0
A24: ='[3]明细表H8-2'!A38:C38 -> 其他设备 | D24: =SUMPRODUCT(($A$9:$A$17=$A24)*(D$9:D$17)) -> 0 | E24: =SUMPRODUCT(($A$9:$A$17=$A24)*(E$9:E$17)) -> 0 | F24: =SUMPRODUCT(($A$9:$A$17=$A24)*(F$9:F$17)) -> 0 | P24: =SUMPRODUCT(($A$9:$A$17=$A24)*(P$9:P$17)) -> 0 | Q24: =SUMPRODUCT(($A$9:$A$17=$A24)*(Q$9:Q$17)) -> 0 | R24: =SUMPRODUCT(($A$9:$A$17=$A24)*(R$9:R$17)) -> 0 | S24: =SUMPRODUCT(($A$9:$A$17=$A24)*(S$9:S$17)) -> 0 | T24: =SUMPRODUCT(($A$9:$A$17=$A24)*(T$9:T$17)) -> 0 | U24: =SUMPRODUCT(($A$9:$A$17=$A24)*(U$9:U$17)) -> 0 | V24: =SUMPRODUCT(($A$9:$A$17=$A24)*(V$9:V$17)) -> 0 | W24: =SUMPRODUCT(($A$9:$A$17=$A24)*(W$9:W$17)) -> 0 | X24: =SUMPRODUCT(($A$9:$A$17=$A24)*(X$9:X$17)) -> 0
A25: 三、审计说明：减值迹象/可收回金额索引(H8-10/H8-11)、减值日与分段月数、新月折旧计算、与账面差异原因、与H8-9勾稽。
A26: 四、审计结论：□减值后折旧测算准确 □除下列差异外未见异常 □存在重大未调整差异不可确认。索引：H8-1 / H8-2 / H8-9 / H8-10 / H8-11。提示：减值不得转回。

Sheet 折旧分配分析表H8-9
A1: 致同会计师事务所
A2: 使用权资产折旧分配分析表
A3: =底稿目录!A2 -> 被审计单位： | D3: =底稿目录!A4 -> 编制人： | G3: =底稿目录!A6 -> 编制日期： | I3: 索引号： | J3: H8-9
A4: =底稿目录!A3 -> 截止日：202X年12月31日 | D4: =底稿目录!A5 -> 复核人： | G4: =底稿目录!A7 -> 复核日期： | I4: 页 次：
A5: 一、审计目标：使用权资产以恰当的金额包括在财务报表中，与之相关的计价或分摊调整已恰当记录，相关披露已得到恰当计量和描述。
A6: 二、审计过程：
A7: 序号 | B7: 使用权资产类别 | C7: 营业成本 | D7: 制造费用 | E7: 销售费用 | F7: 管理费用 | G7: 研发支出 | H7: … | I7: 合计 | J7: 备注
A8: 1 | B8: 房屋及建筑物 | I8: =SUM(C8:H8) -> 0
A9: 2 | B9: 机器设备 | I9: =SUM(C9:H9) -> 0
A10: 3 | B10: 运输设备 | I10: =SUM(C10:H10) -> 0
A11: 4 | B11: 办公设备 | I11: =SUM(C11:H11) -> 0
A12: 5 | B12: 其他设备 | I12: =SUM(C12:H12) -> 0
A13: 合计 | C13: =SUM(C8:C12) -> 0 | D13: =SUM(D8:D12) -> 0 | E13: =SUM(E8:E12) -> 0 | F13: =SUM(F8:F12) -> 0 | G13: =SUM(G8:G12) -> 0 | H13: =SUM(H8:H12) -> 0 | I13: =SUM(I8:I12) -> 0
B14: 勾稽关系情况 | C14: 勾稽一致，详见xx-XX | D14: 勾稽一致，详见xx-XX | E14: 勾稽一致，详见xx-XX | F14: 勾稽一致，详见xx-XX | G14: 勾稽一致，详见xx-XX | H14: 勾稽一致，详见xx-XX
A15: 三、审计说明：
A17: 四、审计结论：
A22: 提示：
A23: 1.检查折旧分配到各种费用的情况，将“累计折旧”账户贷方的本期计提折旧额与相应成本费用中的折旧费用明细账户的借方相比较，以查明所计提折旧金额是否已全部摊入本期产品成本或费用。
A24: 2.确定分配方法是否合理，本期分配方法与上期是否一致。

Sheet 减值测算表H8-10
A1: 致同会计师事务所
A2: 使用权资产减值测算表
A3: =[2]底稿目录!A2 -> 被审计单位： | E3: =[2]底稿目录!A4 -> 编制人： | H3: =[2]底稿目录!A6 -> 编制日期： | K3: 索引号： | L3: H8-10
A4: =[2]底稿目录!A3 -> 截止日：202X年12月31日 | E4: =[2]底稿目录!A5 -> 复核人： | H4: =[2]底稿目录!A7 -> 复核日期： | K4: 页 次：
A5: 一、审计目标：确认使用权资产减值准备以恰当金额计入财务报表；减值迹象识别充分，可收回金额=max(公允减处置费用,预计未来现金流量现值)测算合理；本期补提/结转会计处理正确；减值一经确认不得转回（CAS8）；相关披露恰当。
A6: 二、审计过程：
A7: 使用权资产名称 | B7: 是否存在减值迹象 | C7: 减值迹象描述 | D7: 账面价值 （原值−累计折旧，不含减值） | E7: 可收回金额 | H7: 期末应计提的减值金额 （当⑤＜②） | I7: 期末账面已计提的减值准备 | J7: 本期应补提的减值准备 （减值一经确认不得转回） | K7: 工作底稿索引号 | L7: 备注 | M7: 多提待查金额 （⑦＞⑥，不得转回）
E8: 公允价值减处置费用的净额 | F8: 预计未来现金流量现值 | G8: 可收回金额（③、④较高者）
C9: ① | D9: ② | E9: ③ | F9: ④ | G9: ⑤=MAX(③,④) | H9: ⑥=MAX(②−⑤,0) | I9: ⑦ | J9: ⑧=MAX(⑥−⑦,0) | M9: ⑨=MAX(⑦−⑥,0)
G10: =IF(OR(B10="",B10="×"),0,MAX(E10,F10)) -> 0 | H10: =IF(OR(B10="",B10="×"),0,MAX(D10-G10,0)) -> 0 | J10: =MAX(H10-I10,0) -> 0 | M10: =MAX(I10-H10,0) -> 0
G11: =IF(OR(B11="",B11="×"),0,MAX(E11,F11)) -> 0 | H11: =IF(OR(B11="",B11="×"),0,MAX(D11-G11,0)) -> 0 | J11: =MAX(H11-I11,0) -> 0 | M11: =MAX(I11-H11,0) -> 0
G12: =IF(OR(B12="",B12="×"),0,MAX(E12,F12)) -> 0 | H12: =IF(OR(B12="",B12="×"),0,MAX(D12-G12,0)) -> 0 | J12: =MAX(H12-I12,0) -> 0 | M12: =MAX(I12-H12,0) -> 0
G13: =IF(OR(B13="",B13="×"),0,MAX(E13,F13)) -> 0 | H13: =IF(OR(B13="",B13="×"),0,MAX(D13-G13,0)) -> 0 | J13: =MAX(H13-I13,0) -> 0 | M13: =MAX(I13-H13,0) -> 0
G14: =IF(OR(B14="",B14="×"),0,MAX(E14,F14)) -> 0 | H14: =IF(OR(B14="",B14="×"),0,MAX(D14-G14,0)) -> 0 | J14: =MAX(H14-I14,0) -> 0 | M14: =MAX(I14-H14,0) -> 0
G15: =IF(OR(B15="",B15="×"),0,MAX(E15,F15)) -> 0 | H15: =IF(OR(B15="",B15="×"),0,MAX(D15-G15,0)) -> 0 | J15: =MAX(H15-I15,0) -> 0 | M15: =MAX(I15-H15,0) -> 0
G16: =IF(OR(B16="",B16="×"),0,MAX(E16,F16)) -> 0 | H16: =IF(OR(B16="",B16="×"),0,MAX(D16-G16,0)) -> 0 | J16: =MAX(H16-I16,0) -> 0 | M16: =MAX(I16-H16,0) -> 0
G17: =IF(OR(B17="",B17="×"),0,MAX(E17,F17)) -> 0 | H17: =IF(OR(B17="",B17="×"),0,MAX(D17-G17,0)) -> 0 | J17: =MAX(H17-I17,0) -> 0 | M17: =MAX(I17-H17,0) -> 0
G18: =IF(OR(B18="",B18="×"),0,MAX(E18,F18)) -> 0 | H18: =IF(OR(B18="",B18="×"),0,MAX(D18-G18,0)) -> 0 | J18: =MAX(H18-I18,0) -> 0 | M18: =MAX(I18-H18,0) -> 0
G19: =IF(OR(B19="",B19="×"),0,MAX(E19,F19)) -> 0 | H19: =IF(OR(B19="",B19="×"),0,MAX(D19-G19,0)) -> 0 | J19: =MAX(H19-I19,0) -> 0 | M19: =MAX(I19-H19,0) -> 0
G20: =IF(OR(B20="",B20="×"),0,MAX(E20,F20)) -> 0 | H20: =IF(OR(B20="",B20="×"),0,MAX(D20-G20,0)) -> 0 | J20: =MAX(H20-I20,0) -> 0 | M20: =MAX(I20-H20,0) -> 0
G21: =IF(OR(B21="",B21="×"),0,MAX(E21,F21)) -> 0 | H21: =IF(OR(B21="",B21="×"),0,MAX(D21-G21,0)) -> 0 | J21: =MAX(H21-I21,0) -> 0 | M21: =MAX(I21-H21,0) -> 0
A22: 合计 | D22: =SUM(D10:D21) -> 0 | E22: =SUM(E10:E21) -> 0 | F22: =SUM(F10:F21) -> 0 | G22: =SUM(G10:G21) -> 0 | H22: =SUM(H10:H21) -> 0 | I22: =SUM(I10:I21) -> 0 | J22: =SUM(J10:J21) -> 0 | M22: =SUM(M10:M21) -> 0
A23: 三、审计说明：
A24: 编制说明：①先评减值迹象（B列）；有迹象者完成H8-11可收回金额测试后回填③④；②账面价值取自H8-2原值−累计折旧（不含减值）；⑦取自账面减值准备科目余额；⑧>0需建议补提并考虑切换「折旧测算表（含减值）H8-8」；⑨>0须查多提原因（处置结转等），禁止转回。
A26: 四、审计结论：
A27: 经审计：（1）减值迹象识别□充分 / □需补充；（2）可收回金额测算□合理 / □需调整；（3）本期应补提合计（⑧）______元，已建议调整□是 / □否 / □不适用；（4）多提待查（⑨）______元，原因及处理____________________；（5）使用权资产减值准备在重大方面□公允反映 / □存在错报风险。
A30: 提示：
A31: 1.获取或编制使用权资产减值准备明细表，复核加计正确，并与总账、明细账及审定表H8-1减值准备余额核对相符；账面价值②与明细表H8-2原值、累计折旧勾稽。
A32: 2.检查减值准备计提的批准程序及书面依据是否充分；会计处理是否正确。注意：CAS8规定减值损失一经确认不得转回；资产处置/转让时相应减值准备应一并结转（终止确认），结转≠转回，勿混淆。
A33: 3.存在减值迹象的项目，须完成可收回金额测试表H8-11（公允净额及/或DCF），将③④回填本表；无减值迹象（B=×）不得仅凭估计计提减值。
A34: 4.重新测试管理层减值估计的合理性，比较预期与已记录金额，调查重大差异；本期补提后应切换至「折旧测算表（含减值）H8-8」重算后续折旧，并与H8-9分配分析勾稽。
A35: 5.检查上期已确认减值准备本期变动是否适当（处置结转、重分类等）；若⑨多提待查>0，查明原因并评估是否需调整，禁止以「转回」冲减资产减值损失。

Sheet 可收回金额测试表H8-11
A1: 致同会计师事务所
A2: 使用权资产减值准备测试表-可收回金额
A3: =底稿目录!A2 -> 被审计单位： | E3: =底稿目录!A4 -> 编制人： | J3: =底稿目录!A6 -> 编制日期： | N3: 索引号： | O3: H8-11
A4: =底稿目录!A3 -> 截止日：202X年12月31日 | E4: =底稿目录!A5 -> 复核人： | J4: =底稿目录!A7 -> 复核日期： | N4: 页 次：
A5: 一、审计目标：使用权资产以恰当的金额包括在财务报表中，与之相关的计价或分摊调整已恰当记录，相关披露已得到恰当计量和描述。
A6: 二、审计过程：
A7: （一）资产的公允价值减去处置费用后的净额
A8: 使用权资产名称 | B8: 公允价值 | H8: 处置费用（资产处置的直接归属费用） | N8: 公允价值-处置费用 | O8: 备注
B9: 销售协议价格 | C9: 说明 | D9: 资产活跃市场价格 | E9: 说明 | F9: 估计价格 | G9: 说明 | H9: 法律费用 | I9: 相关税费 | J9: 搬运费 | K9: 直接费用 | L9: 其他费用 | M9: 处置费用合计
M10: =SUM(H10:L10) -> 0 | N10: =IF(B10>0,B10,IF(D10>0,D10,F10))-M10 -> 0
M11: =SUM(H11:L11) -> 0 | N11: =IF(B11>0,B11,IF(D11>0,D11,F11))-M11 -> 0
M12: =SUM(H12:L12) -> 0 | N12: =IF(B12>0,B12,IF(D12>0,D12,F12))-M12 -> 0
A13: 合 计 | B13: =SUM(B10:B12) -> 0 | D13: =SUM(D10:D12) -> 0 | F13: =SUM(F10:F12) -> 0 | H13: =SUM(H10:H12) -> 0 | I13: =SUM(I10:I12) -> 0 | J13: =SUM(J10:J12) -> 0 | K13: =SUM(K10:K12) -> 0 | L13: =SUM(L10:L12) -> 0 | M13: =SUM(M10:M12) -> 0 | N13: =SUM(N10:N12) -> 0
A14: 审计说明：
A16: （二）资产预计未来现金流量的现值
A17: 预计未来现金流量 | B17: 预算或者预测期 | G17: 以后年度 | I17: 行业的长期平均增长率 | J17: 市场长期平均增长率 | K17: 所在国家或地区的长期平均增长率 | L17: 增长率确定依据 | N17: 预计未来现金流量的现值 | O17: 备注
B18: 第一年 | C18: 第二年 | D18: 第三年 | E18: 第四年 | F18: 第五年 | G18: 基数 | H18: 增长率
A19: 现金净流量（税前） | G19: =F19 -> 0
A20: 折现系数 | B20: =1/(1+$K$24)^1 -> #DIV/0! | C20: =1/(1+$K$24)^2 -> #DIV/0! | D20: =1/(1+$K$24)^3 -> #DIV/0! | E20: =1/(1+$K$24)^4 -> #DIV/0! | F20: =1/(1+$K$24)^5 -> #DIV/0! | G20: =(1+H19)/((J24-H19)*(1+K24)^5) -> #DIV/0! | H20: （企业管理层如能证明递增的增长率是合理的，可以以递增的增长率为基础。）
A21: 现值 | B21: =B19*B20 -> #DIV/0! | C21: =C19*C20 -> #DIV/0! | D21: =D19*D20 -> #DIV/0! | E21: =E19*E20 -> #DIV/0! | F21: =F19*F20 -> #DIV/0! | G21: =G19*G20 -> #DIV/0! | H21: （建立在预算或者预测基础上的预计现金流量最多涵盖5年，更长期间需证明合理性。） | N21: =SUM(B21:G21) -> #DIV/0!
A22: 折现率 | B22: 所得税率 | C22: 债务总额 D | D22: 资本总额 E | E22: 债务成本Kd | F22: 无风险报酬率Rf | G22: β系数 | H22: 市场平均收益率Rm | I22: 资本成本Ke | J22: WACC (税后) | K22: 折现率 (税前) | L22: 税后折税前调整说明 | N22: 可收回金额 | O22: 备注
B23: 适用税率 | L23: 税率调整 | M23: 调整说明
A24: 加权平均资金成本 | I24: =F24+G24*(H24-F24) -> 0 | J24: =((C24*E24*(1-B24)+D24*I24))/(C24+D24) -> #DIV/0! | K24: =J24/(1-(B24+L24)) -> #DIV/0! | N24: =MAX(N13,N21) -> #DIV/0!
A25: 审计说明：
A27: （三）可收回金额
B28: =N24 -> #DIV/0! | C28: 资产的公允价值减去处置费用后的净额与资产预计未来现金流量的现值两者之间较高者
A29: 三、审计说明：
A32: 四、审计结论：
A38: 提示：
A39: 1、可收回金额应当根据资产的公允价值减去处置费用后的净额与资产预计未来现金流量的现值两者之间较高者确定。
A41: 2、资产的公允价值减去处置费用后的净额，应当根据公平交易中销售协议价格减去可直接归属于该资产处置费用的金额确定。不存在销售协议但存在资产活跃市场的，
A42: 应当按照该资产的市场价格减去处置费用后的金额确定。资产的市场价格通常应当根据资产的买方出价确定。在不存在销售协议和资产活跃市场的情况下，应当
A43: 以可获取的最佳信息为基础，估计资产的公允价值减去处置费用后的净额，该净额可以参考同行业类似资产的最近交易价格或者结果进行估计。企业按照上述规定
A44: 仍然无法可靠估计资产的公允价值减去处置费用后的净额的，应当以该资产预计未来现金流量的现值作为其可收回金额。
A45: 3、处置费用包括与资产处置有关的法律费用、相关税费、搬运费以及为使资产达到可销售状态所发生的直接费用等。
A47: 4、资产预计未来现金流量的现值，应当按照资产在持续使用过程中和最终处置时所产生的预计未来现金流量，选择恰当的折现率对其进行折现后的金额加以确定。
A52: 5、预计资产的未来现金流量，应当以经企业管理层批准的最近财务预算或者预测数据，以及该预算或者预测期之后年份稳定的或者递减的增长率为基础。
A53: 预计的资产未来现金流量应当包括下列各项：
... A90: 资产组，是指企业可以认定的最小资产组合，其产生的现金流入应当基本上独立于其他资产或者资产组产生的现金流入。

Sheet 减少检查表H8-12
A1: 致同会计师事务所
A2: 使用权资产/租赁负债减少检查表
A3: =底稿目录!A2 -> 被审计单位： | F3: =底稿目录!A4 -> 编制人： | K3: =底稿目录!A6 -> 编制日期： | U3: 索引号： | V3: H8-13
A4: =底稿目录!A3 -> 截止日：202X年12月31日 | F4: =底稿目录!A5 -> 复核人： | K4: =底稿目录!A7 -> 复核日期： | U4: 页 次：
A5: 一、审计目标：1.资产负债表中记录的使用权是存在的，且已记录于恰当的账户；2.所有应记录的使用权资产均已记录，所有应当包括在财务报表中的相关披露均已包括；3.使用权资产以恰当的金额包括在财务报表中，与之相关的计价或分摊调整已恰当记录，相关披露已得到恰当计量和描述。
A6: 二、样本选取标准与规模：
A7: 测试总体： | B7: 如使用权资产贷方发生额所有凭证共XX笔金额XX | I7: 特定样本： | J7: XX金额以上（大额）、关联方/关联交易形成的款项、XX异常款项全部测试，共XX笔；
A8: 抽样总体： | B8: 测试总体扣除特定样本以外的样本，共XX笔、金额XX | I8: 确定的抽样样本量： | K8: 抽取XX笔 | L8: （如果使用了样本计算器计算样本量，样本量计算过程见<XX>底稿）
A9: 抽样方法： | B9: 随机选样/系统选样/货币单元抽样/随意选样（非统计抽样适用） | I9: 抽样过程： | J9: 使用IDEA（XX抽样工具）选择XX数量、金额XX的样本进行测试，抽样工具中的样本选择过程和结果见<XX>底稿
A10: 三、测试过程：
A11: 测试内容说明：1.原始凭证是否齐全； 2.记账凭证与原始凭证是否相符；3.账务处理是否正确；4.是否记录于恰当的会计期间；5.……
A12: 序号 | B12: 使用权资产类别 | C12: 使用权资产编号 | D12: 使用权资产名称 | E12: 减少方式 | F12: 减少日期 | G12: 凭证号 | H12: 对方科目 | I12: 减少情况 | N12: 支持性文件 | O12: 核对内容 | T12: 索引号 | U12: 是否异常 | V12: 备注说明
I13: 数量 | J13: 原值 | K13: 累计折旧 | L13: 减值准备 | M13: 净值 | O13: 1 | P13: 2 | Q13: 3 | R13: 4 | S13: 5
A14: 1 | M14: =J14-K14-L14 -> 0
A15: 2 | M15: =J15-K15-L15 -> 0
A16: 3 | M16: =J16-K16-L16 -> 0
A17: 4 | M17: =J17-K17-L17 -> 0
A18: 5 | M18: =J18-K18-L18 -> 0
A19: 6 | M19: =J19-K19-L19 -> 0
A20: 7 | M20: =J20-K20-L20 -> 0
A21: 8 | M21: =J21-K21-L21 -> 0
A22: 9 | M22: =J22-K22-L22 -> 0
A23: 10 | M23: =J23-K23-L23 -> 0
A24: 11 | M24: =J24-K24-L24 -> 0
A25: 12 | M25: =J25-K25-L25 -> 0
... A28: 15 | M28: =J28-K28-L28 -> 0
A29: …… | M29: =J29-K29-L29 -> 0
A30: 合计 | I30: =SUM(I14:I29) -> 0 | J30: =SUM(J14:J29) -> 0 | K30: =SUM(K14:K29) -> 0 | L30: =SUM(L14:L29) -> 0 | M30: =SUM(M14:M29) -> 0
A31: 本期减少使用权资产合计 | J31: ='明细表H8-2'!U32 -> 0
A32: 检查比例 | J32: =IF(J30=0,0,J30/$J$31) -> 0
A33: 四、审计说明：
A34: 1.如果检查比例较低应扩大检查样本量或说明原因
A35: 2.……
A36: 五、审计结论：

Sheet 简化处理的租赁检查表H8-13
A1: 致同会计师事务所
A2: 简化处理的租赁检查表
A3: =[1]底稿目录!A2 -> 被审计单位： | E3: =[1]底稿目录!A4 -> 编制人： | K3: =[1]底稿目录!A6 -> 编制日期： | N3: 索引号： | O3: H8-13
A4: =[1]底稿目录!A3 -> 截止日：202X年12月31日 | E4: =[1]底稿目录!A5 -> 复核人： | K4: =[1]底稿目录!A7 -> 复核日期： | N4: 页 次：
A5: 一、审计目标：
A6: 1. 确认被审计单位对短期租赁及低价值资产租赁采用简化处理符合《企业会计准则第21号——租赁》第32条：租赁期不超过12个月（不含购买选择权），或全新状态下价值较低（实务阈值≤40,000元）且未转租；不符合条件的租赁已确认使用权资产与租赁负债。
A7: 2. 确认简化处理项下租赁付款额已按直线法（或其他系统合理方法）计入相关资产成本或当期损益，本期应计租金费用完整、准确，并与相关费用科目勾稽一致；重大差异已追查并考虑调整。
A8: 二、审计过程：
A9: 序号 | B9: 资产类别 | C9: 资产名称 | D9: 合同号 | E9: 租赁期开始日 | F9: 租赁到期日 | G9: 租赁期(月) | H9: 全新资产价值 | I9: 简化类型 | J9: 月租金 | K9: 本期应计月数 | L9: 本期应计租金 | M9: 账面本期租金 | N9: 差异 | O9: 勾稽一致 | P9: 费用科目 | Q9: 核查结论 | R9: 索引号
A10: 1 | G10: =IF(OR(E10="",F10=""),"",MAX(1,(YEAR(F10)-YEAR(E10))*12+MONTH(F10)-MONTH(E10)+1)) | I10: =IF(OR(G10="",H10=""),"",IF(AND(G10<=12,H10<=40000),"短期+低价值",IF(G10<=12,"短期租赁",IF(H10<=40000,"低价值","不符合")))) | K10: =I10*J10 -> #VALUE! | L10: =IF(OR(J10="",K10=""),"",J10*K10) -> #VALUE! | M10: =K10-L10 -> #VALUE! | N10: =IF(OR(L10="",M10=""),"",L10-M10) -> #VALUE!
A11: 2 | G11: =IF(OR(E11="",F11=""),"",MAX(1,(YEAR(F11)-YEAR(E11))*12+MONTH(F11)-MONTH(E11)+1)) | I11: =IF(OR(G11="",H11=""),"",IF(AND(G11<=12,H11<=40000),"短期+低价值",IF(G11<=12,"短期租赁",IF(H11<=40000,"低价值","不符合")))) | K11: =I11*J11 -> #VALUE! | L11: =IF(OR(J11="",K11=""),"",J11*K11) -> #VALUE! | M11: =K11-L11 -> #VALUE! | N11: =IF(OR(L11="",M11=""),"",L11-M11) -> #VALUE!
A12: 3 | G12: =IF(OR(E12="",F12=""),"",MAX(1,(YEAR(F12)-YEAR(E12))*12+MONTH(F12)-MONTH(E12)+1)) | I12: =IF(OR(G12="",H12=""),"",IF(AND(G12<=12,H12<=40000),"短期+低价值",IF(G12<=12,"短期租赁",IF(H12<=40000,"低价值","不符合")))) | K12: =I12*J12 -> #VALUE! | L12: =IF(OR(J12="",K12=""),"",J12*K12) -> #VALUE! | M12: =K12-L12 -> #VALUE! | N12: =IF(OR(L12="",M12=""),"",L12-M12) -> #VALUE!
A13: 4 | G13: =IF(OR(E13="",F13=""),"",MAX(1,(YEAR(F13)-YEAR(E13))*12+MONTH(F13)-MONTH(E13)+1)) | I13: =IF(OR(G13="",H13=""),"",IF(AND(G13<=12,H13<=40000),"短期+低价值",IF(G13<=12,"短期租赁",IF(H13<=40000,"低价值","不符合")))) | K13: =I13*J13 -> #VALUE! | L13: =IF(OR(J13="",K13=""),"",J13*K13) -> #VALUE! | M13: =K13-L13 -> #VALUE! | N13: =IF(OR(L13="",M13=""),"",L13-M13) -> #VALUE!
A14: 5 | G14: =IF(OR(E14="",F14=""),"",MAX(1,(YEAR(F14)-YEAR(E14))*12+MONTH(F14)-MONTH(E14)+1)) | I14: =IF(OR(G14="",H14=""),"",IF(AND(G14<=12,H14<=40000),"短期+低价值",IF(G14<=12,"短期租赁",IF(H14<=40000,"低价值","不符合")))) | K14: =I14*J14 -> #VALUE! | L14: =IF(OR(J14="",K14=""),"",J14*K14) -> #VALUE! | M14: =K14-L14 -> #VALUE! | N14: =IF(OR(L14="",M14=""),"",L14-M14) -> #VALUE!
A15: 6 | G15: =IF(OR(E15="",F15=""),"",MAX(1,(YEAR(F15)-YEAR(E15))*12+MONTH(F15)-MONTH(E15)+1)) | I15: =IF(OR(G15="",H15=""),"",IF(AND(G15<=12,H15<=40000),"短期+低价值",IF(G15<=12,"短期租赁",IF(H15<=40000,"低价值","不符合")))) | K15: =I15*J15 -> #VALUE! | L15: =IF(OR(J15="",K15=""),"",J15*K15) -> #VALUE! | M15: =K15-L15 -> #VALUE! | N15: =IF(OR(L15="",M15=""),"",L15-M15) -> #VALUE!
A16: 7 | G16: =IF(OR(E16="",F16=""),"",MAX(1,(YEAR(F16)-YEAR(E16))*12+MONTH(F16)-MONTH(E16)+1)) | I16: =IF(OR(G16="",H16=""),"",IF(AND(G16<=12,H16<=40000),"短期+低价值",IF(G16<=12,"短期租赁",IF(H16<=40000,"低价值","不符合")))) | K16: =I16*J16 -> #VALUE! | L16: =IF(OR(J16="",K16=""),"",J16*K16) -> #VALUE! | M16: =K16-L16 -> #VALUE! | N16: =IF(OR(L16="",M16=""),"",L16-M16) -> #VALUE!
A17: 8 | G17: =IF(OR(E17="",F17=""),"",MAX(1,(YEAR(F17)-YEAR(E17))*12+MONTH(F17)-MONTH(E17)+1)) | I17: =IF(OR(G17="",H17=""),"",IF(AND(G17<=12,H17<=40000),"短期+低价值",IF(G17<=12,"短期租赁",IF(H17<=40000,"低价值","不符合")))) | K17: =I17*J17 -> #VALUE! | L17: =IF(OR(J17="",K17=""),"",J17*K17) -> #VALUE! | M17: =K17-L17 -> #VALUE! | N17: =IF(OR(L17="",M17=""),"",L17-M17) -> #VALUE!
A18: 9 | G18: =IF(OR(E18="",F18=""),"",MAX(1,(YEAR(F18)-YEAR(E18))*12+MONTH(F18)-MONTH(E18)+1)) | I18: =IF(OR(G18="",H18=""),"",IF(AND(G18<=12,H18<=40000),"短期+低价值",IF(G18<=12,"短期租赁",IF(H18<=40000,"低价值","不符合")))) | K18: =I18*J18 -> #VALUE! | L18: =IF(OR(J18="",K18=""),"",J18*K18) -> #VALUE! | M18: =K18-L18 -> #VALUE! | N18: =IF(OR(L18="",M18=""),"",L18-M18) -> #VALUE!
A19: 10 | G19: =IF(OR(E19="",F19=""),"",MAX(1,(YEAR(F19)-YEAR(E19))*12+MONTH(F19)-MONTH(E19)+1)) | I19: =IF(OR(G19="",H19=""),"",IF(AND(G19<=12,H19<=40000),"短期+低价值",IF(G19<=12,"短期租赁",IF(H19<=40000,"低价值","不符合")))) | K19: =I19*J19 -> #VALUE! | L19: =IF(OR(J19="",K19=""),"",J19*K19) -> #VALUE! | M19: =K19-L19 -> #VALUE! | N19: =IF(OR(L19="",M19=""),"",L19-M19) -> #VALUE!
A20: 合计 | H20: =SUM(H10:H19) -> 0 | J20: =SUM(J10:J19) -> 0 | K20: =SUM(K10:K19) -> #VALUE! | L20: =SUM(L10:L19) -> #VALUE! | M20: =SUM(M10:M19) -> #VALUE! | N20: =SUM(N10:N19) -> #VALUE! | Q20: =COUNTIF(I10:I19,"不符合") -> 0 | R20: 笔不符合
A22: 三、审计说明：
A23: （说明抽查范围、简化处理政策一贯性、免租期/递进租金处理、与费用科目勾稽结果，以及「不符合」笔数的后续处理——是否已转入 H8-2/H9 确认。）
A26: 四、审计结论：
A27: 经检查，本期简化处理的租赁□符合 / □基本符合 / □不符合 CAS21 第32条条件；租金费用计提□准确 / □存在差异已调整 / □待进一步核实。
A29: 提示（编制要点）：
A30: ① 短期租赁：租赁期开始日确定的租赁期不超过12个月；含购买选择权的不属于短期租赁；转租中的转租人不得对原租赁选用短期简化。
A31: ② 低价值资产租赁：按标的资产全新状态绝对金额判断（实务阈值人民币40,000元），与承租人规模、性质无关；预期转租的不适用。
A32: ③ 简化处理会计：不确认使用权资产和租赁负债，将租赁付款额在租赁期内按直线法或其他系统合理方法计入相关资产成本或当期损益。
A33: ④ 费用重算：本期应计租金＝月租金×本期应计月数；存在免租期或租金递增时，应先将合同总对价按系统合理方法分摊后再填列月租金/月数。
A34: ⑤ 「简化类型＝不符合」的租赁应转入 H8-2/H9 按完整租赁模型确认；差异（N列）重大时须追查至凭证与科目余额并考虑调整。
A35: ⑥ 本表索引号为 H8-13，勿与 H8-12（减少/终止检查表）混淆。

Sheet 关联交易检查表H8-14
A1: 致同会计师事务所
A2: 关联交易检查表（使用权资产、租赁负债）
A3: =底稿目录!A2 -> 被审计单位： | F3: =底稿目录!A4 -> 编制人： | J3: =底稿目录!A6 -> 编制日期： | N3: 索引号： | O3: H8-14
A4: =底稿目录!A3 -> 截止日：202X年12月31日 | F4: =底稿目录!A5 -> 复核人： | J4: =底稿目录!A7 -> 复核日期： | N4: 页 次：
A5: 一、审计目标:
A6: 使用权资产的审计目标：1.资产负债表中记录的使用权资产是存在的，且已记录于恰当的账户；2.所有应记录的使用权资产均已记录，所有应当包括在财务报表中的相关披露均已包括；3.记录的使用权资产由被审计单位拥有或控制。4.使用权资产资产以恰当的金额包括在财务报表中，与之相关的计价或分摊调整已恰当记录，相关披露已得到恰当计量和描述；5.使用权资产已被恰当地汇总或分解且表述清楚，相关披露在按照企业会计准则的编制基础下是相关的、可理解的。
A7: 租赁负债的审计目标：1.资产负债表中记录的租赁负债是存在的，且已记录于恰当的账户；2.所有应记录的租赁负债均已记录，所有应当包括在财务报表中的相关披露均已包括；3.记录的租赁负债由被审计单位拥有或控制。；4.租赁负债以恰当的金额包括在财务报表中，与之相关的计价或分摊调整已恰当记录，相关披露已得到恰当计量和描述；5.租赁负债已被恰当地汇总或分解且表述清楚，相关披露在按照企业会计准则的编制基础下是相关的、可理解的。
A8: 二、审计过程：
A9: 1.使用权资产
A10: 关联单位名称 | B10: 关联方关系 | C10: 租赁项目 | D10: 租赁资产种类 | E10: 租赁发生时间及到期日 | F10: 使用权资产原值期末审定数 | G10: 使用权资产累计折旧期末审定数 | H10: 使用权资产减值准备期末审定数 | I10: 使用权资产净值 | J10: 本期新增使用权资产金额（原值） | K10: 使用权资产本期折旧金额 | L10: 定价政策 | M10: 关联交易是否存在异常 | N10: 备注 | O10: 索引号
A18: 2.租赁负债
A19: 关联方名称 | B19: 关联关系 | C19: 租赁项目 | D19: 租赁资产种类 | E19: 租赁发生时间及到期日 | F19: 租赁负债期末审定数 | G19: 本期应支付的租赁款项 | H19: 本期承担的租赁负债利息支出 | I19: 定价政策 | J19: 关联交易是否存在异常 | K19: 备注 | L19: 索引号
A27: 三、审计说明：
A30: 四、审计结论：
A35: 勿删
A36: 关联关系
A37: 实际控制人
A38: 控股股东
A39: 控股股东、实际控制人的附属企业
A40: 持有5%以上股份的法人或其他组织
A41: 联营企业
A42: 合营企业
A43: 董高监等关键管理人员
A44: 其他关联方
