Workbook
Name Conclusion: 'Overall findings'!$C$11
Name Corrected: 'Disclosure misstatements'!$F$11
Name Corrected_Base: 'Corrected misstatements'!#REF!
Name Current: Lists!$A$8:$A$9
Name Disclosure_Base: 'Disclosure misstatements'!#REF!
Name Identified_by: Lists!$A$15:$A$17
Name NA: Lists!$A$11:$A$13
Name Type: Lists!$A$4:$A$6
Name Uncorrected_Base: 'Uncorrected misstatements'!#REF!
Name YesNo: Lists!$A$1:$A$2

Sheet GT_Custom
A1: r | B1: Custom 1
A2: s | B2: Custom 2
A3: t | B3: Custom 3
A4: u | B4: Custom 4
A5: v | B5: Custom 5
A6: w | B6: Custom 6
A7: x | B7: Custom 7
A8: y | B8: Custom 8
A10: a | B10: Traced To Supporting Document
A11: b | B11: Traced To Financial Statement
A12: c | B12: Traced To Subsidiary Ledger
A13: d | B13: Traced To General Ledger
... A28: # | B28: Reviewer Traced To Leads Or Subleads

Sheet Instructions
A1: Summary of identified misstatements at component
A2: June 2021
A4: Delete these instructions and do not include them in the audit file.
A6: Instructional note to group engagement team: This template is used by the component auditor, whether a member firm or non-member firm, only when communicating identified misstatements. A different template or format may be used, provided the necessary information is obtained.
A8: Instructional note to component auditor: This template is used only when communicating identified misstatements, whether identified by the component auditor or by component management. It does not include component management's financial reporting adjustments. A different template or format may be used provided the necessary information is communicated to the group engagement team. Worksheets that are not applicable (such as when there are no disclosure misstatements) may be deleted.
A10: Guidance related to use of this template
A12: The following provides guidance on which worksheet(s) to use.
A14: Overall findings | B14: This worksheet is used to communicate whether any identified misstatements, individually or in aggregate, indicate fraud or that other misstatements may exist.
A15: Corrected misstatements | B15: This worksheet is used to summarize and communicate misstatements identified by the component auditor that were corrected by component management. Multiple lines may be needed for the account number, account name or financial information line item, and the related debits and credits; the other items may be entered once.
A16: Uncorrected misstatements | B16: This worksheet is used to summarize and communicate misstatements identified by the component auditor or component management, and not corrected by component management. Such misstatements may have originated in the current period or be the reversing effect or continuing effect of misstatements identified in the prior period. The worksheet includes an evaluation of the effect of uncorrected misstatements on the component financial information. Multiple lines may be needed for the account number, account name or financial information line item, and the related debits and credits; the other items may be entered once.
A17: Disclosure misstatements | B17: This worksheet is used to summarize and communicate disclosure misstatements identified by the component auditor or component management, whether corrected or uncorrected. It is typically only relevant when the component financial information is prepared in accordance with a general purpose framework (such as accounting principles generally accepted in the United States of America or International Financial Reporting Standards issued by the International Accounting Standards Board) or when the component financial information otherwise includes disclosures.
A19: The following provides specific guidance related to template completion.
A21: Instructions | B21: This template contains cells with conditional formatting and data validation, including drop-down lists. For best results, complete the template top-to-bottom and left-to-right. Rows may be added or deleted, as necessary.
A22: Adding rows | B22: Insert rows as needed for additional misstatements or additional line items in misstatements by copying and pasting existing rows. When adding rows, verify that conditional formatting and data validation has been properly applied to the added rows and that formulas within the row work as intended. Adjust formulas in gray cells accordingly and verify the mathematical accuracy of column totals and summaries.
A23: Deleting rows | B23: To delete rows, select the row(s) that you wish to delete and use Excel's delete function to remove.

Sheet Overall findings
A1: Overall findings at component
B3: Group name
B4: Group period-end date
B5: Component name
B6: Component period-end date
B7: Group trivial amount
B8: Component presentation currency
C11: Conclusion | D11: If yes, describe
B12: In your professional judgment, do any identified misstatements, individually or in the aggregate, indicate that other misstatements may exist?
B13: In your professional judgment, do any identified misstatements, individually or in the aggregate, indicate fraud?

Sheet Corrected misstatements
A1: Corrected misstatements at component
B3: Group name | C3: =IF('Overall findings'!C3:D3="","",'Overall findings'!C3:D3)
B4: Group period-end date | C4: =IF('Overall findings'!C4:D4="","",'Overall findings'!C4:D4)
B5: Component name | C5: =IF('Overall findings'!C5:D5="","",'Overall findings'!C5:D5)
B6: Component period-end date | C6: =IF('Overall findings'!C6:D6="","",'Overall findings'!C6:D6)
B7: Group trivial amount | C7: =IF('Overall findings'!C7:D7="","",'Overall findings'!C7:D7)
B8: Component presentation currency | C8: =IF('Overall findings'!C8:D8="","",'Overall findings'!C8:D8)
B11: Description of misstatement | C11: Type of misstatement | D11: Identified in current or prior period? | E11: Account number (if applicable) | F11: Account name or financial information line item | G11: Amount DR (CR) | H11: Cause of misstatement and, if applicable, related control deficiency
A12: 1
A14: 2
A16: 3
A18: 4
A20: 5
F22: Check | G22: =SUM(G12:G21) -> 0

Sheet Uncorrected misstatements
A1: Uncorrected misstatements at component
B3: Group name | C3: =IF('Overall findings'!C3:D3="","",'Overall findings'!C3:D3)
B4: Group period-end date | C4: =IF('Overall findings'!C4:D4="","",'Overall findings'!C4:D4)
B5: Component name | C5: =IF('Overall findings'!C5:D5="","",'Overall findings'!C5:D5)
B6: Component period-end date | C6: =IF('Overall findings'!C6:D6="","",'Overall findings'!C6:D6)
B7: Group trivial amount | C7: =IF('Overall findings'!C7:D7="","",'Overall findings'!C7:D7)
B8: Component presentation currency | C8: =IF('Overall findings'!C8:D8="","",'Overall findings'!C8:D8)
I10: Increase (decrease)
B11: Description of misstatement | C11: Identified by | D11: Type of misstatement | E11: Identified in current or prior period? | F11: Account number (if applicable) | G11: Account name or financial information line item | H11: Amount DR (CR) | I11: Assets | J11: Liabilities | K11: Equity | L11: Net income | M11: Management's reasons for not correcting | N11: Cause of misstatement and, if applicable, related control deficiency
A12: 1
A14: 2
A16: 3
A18: 4
A20: 5
G22: Check | H22: =SUM(H12:H21) -> 0
I24: Assets | J24: Liabilities | K24: Equity | L24: Net income
F25: Total uncorrected misstatements | I25: =SUM(I12:I22) -> 0 | J25: =SUM(J12:J22) -> 0 | K25: =SUM(K12:K22) -> 0 | L25: =SUM(L12:L22) -> 0
F26: Tax effect
F27: Total uncorrected misstatements, net of tax | I27: =SUM(I25:I26) -> 0 | J27: =SUM(J25:J26) -> 0 | K27: =SUM(K25:K26) -> 0 | L27: =SUM(L25:L26) -> 0
F29: Component financial information total
H30: Total uncorrected misstatements, net of tax, as a percentage of component financial information | I30: =IFERROR(IF(I29="","",IF(I29=0,"N/A",I27/I29)),"") | J30: =IFERROR(IF(J29="","",IF(J29=0,"N/A",J27/J29)),"") | K30: =IFERROR(IF(K29="","",IF(K29=0,"N/A",K27/K29)),"") | L30: =IFERROR(IF(L29="","",IF(L29=0,"N/A",L27/L29)),"")
G32: Conclusion as to whether uncorrected misstatements are material, individually or in aggregate (include quantitative and qualitative factors considered)

Sheet Disclosure misstatements
A1: Disclosure misstatements at component
B3: Group name | C3: =IF('Overall findings'!C3:D3="","",'Overall findings'!C3:D3)
B4: Group period-end date | C4: =IF('Overall findings'!C4:D4="","",'Overall findings'!C4:D4)
B5: Component name | C5: =IF('Overall findings'!C5:D5="","",'Overall findings'!C5:D5)
B6: Component period-end date | C6: =IF('Overall findings'!C6:D6="","",'Overall findings'!C6:D6)
B7: Group trivial amount | C7: =IF('Overall findings'!C7:D7="","",'Overall findings'!C7:D7)
B8: Component presentation currency | C8: =IF('Overall findings'!C8:D8="","",'Overall findings'!C8:D8)
B11: Description of misstatement | C11: Identified by | D11: Identified in current or prior period? | E11: Amount (if applicable) | F11: Corrected? | G11: Management's reasons for not correcting (if uncorrected) | H11: Cause of misstatement and, if applicable, related control deficiency
A12: 1
A13: 2
A14: 3
A15: 4
A16: 5
B18: Conclusion as to whether uncorrected misstatements are material, individually or in aggregate (include quantitative and qualitative factors considered)

Sheet Lists
A1: Yes
A2: No
A4: Factual
A5: Judgmental
A6: Projected
A8: Current
A9: Prior
A11: Yes
A12: No
A13: N/A
A15: Management
A16: Component auditor
A17: Internal audit
