Workbook

Sheet 底稿目录
A1: 底稿开列时，可先在以下单元格填写有关内容，以便其他底稿引用有关数据：
A2: 被审计单位： | D2: 序号 | E2: 内容 | F2: 索引号
A3: 会计期间：202X年度 | D3: 1 | E3: 营业收入审计程序表 | F3: D4A
A4: 编制人： | D4: 2 | E4: 营业收入审定表 | F4: D4-1
A5: 编制日期： | D5: 3 | E5: 附注披露信息（上市公司） | G5: 无需打印
A6: 复核人： | D6: 4 | E6: 附注披露信息（国企） | G6: 无需打印
A7: 复核日期： | D7: 5 | E7: 主营业务收入月度明细表 | F7: D4-2
D8: 6 | E8: 其他业务收入明细表 | F8: D4-3
A9: 关于工作底稿与审计程序索引号对应的说明 | D9: 7 | E9: 调整分录汇总表 | F9: D4-4
A10: 1.编制的审计工作底稿应与审计程序对应。审计项目组应根据被审计单位实际情况和风险评估情况在实质性程序表中裁剪、修改或增加审计程序，根据实际执行的审计程序完成相应审计工作底稿，编制的工作底稿中应按自然顺序依次编制索引号，并通过唯一的索引号将与实质性程序表中的程序对应关联（即将工作底稿的索引号填入实质性程序表中的底稿索引号列）。
A14: 2.获取的支持性证据应与审计底稿或程序对应。审计项目组在完成底稿时获取的支持性证据应根据底稿索引号编制下一级按自然顺序排序的索引号（如D1-2-1、D1-2-2、……），并在底稿中说明引用的支持性证据、关联索引号。
A17: 3.工作底稿索引号的编码规则：实质性程序索引号按循环从“D”到“N”,循环内账户以顺序号排列，模板中底稿索引号按账户顺序+自然数顺序（即模板中索引号按二级自然顺序排列，如D1-1、D1-2、D1-3、……D1-N）。

Sheet 营业收入审计程序表D4A
A1: 致同会计师事务所
A2: 营业收入实质性程序表
A3: =[5]底稿目录!A2 -> 被审计单位： | D3: =[5]底稿目录!A4 -> 编制人： | F3: =[5]底稿目录!A5 -> 编制日期： | I3: 索引号： | J3: D4A
A4: =[5]底稿目录!A3 -> 会计期间：202X年度 | D4: =[5]底稿目录!A6 -> 复核人： | F4: =[5]底稿目录!A7 -> 复核日期： | I4: 页 次：
A5: 一、本账户涉及的科目
A6: 主营业务收入、其他业务收入
A7: 二、审计目标与财务报表认定
A8: 审计目标 | H8: 财务报表的认定
A9: A.利润表中记录的营业收入已发生，且与被审计单位有关，已记录于恰当的账户 | H9: 发生
A10: B.所有应当记录的营业收入均已记录，所有应当包括在财务报表中的相关披露均已包括 | H10: 完整性
A11: C.与营业收入有关的金额及其他数据已恰当记录，相关披露已得到恰当计量和描述 | H11: 准确性
A12: D.与营业收入有关的交易和事项已记录于正确的会计期间 | H12: 截止性
A13: E.营业收入已被恰当地汇总或分解且表述清楚，相关披露在按照企业会计准则的编制基础下是相关的、可理解的 | H13: 列报
A14: 三、计划实施的实质性程序
A15: 序号 | B15: 对应Leap程序 | C15: 审计程序 | D15: 程序分类 | E15: 财务报表认定 | J15: 底稿索引号
E16: 发生 | F16: 完整性 | G16: 准确性 | H16: 截止性 | I16: 列报 | K16: 根据被审计单位实际情况和风险评估情况裁剪、修改或增加审计程序
A17: 1 | B17: 常规程序 | C17: 获取或编制主营业务收入、其他业务收入明细表编制审定表，并完成以下工作： （1）复核加计正确，将总金额与总账、明细账合计数核对相符； （2）检查以非记账本位币结算的营业收入的折算汇率及折算是否正确。 | D17: 常规★ | E17: √ | F17: √ | G17: √ | J17: D4-1 /D4-2 /D4-3
A18: 2 | B18: 常规程序 | C18: 如果被审计单位存在销售业务系统，核对财务账面记录的营业收入数据与销售系统（ERP业务数据）记录是否相符（双向核对）。 | D18: 备选 | E18: √ | F18: √ | G18: √ | J18: D4-13
A19: 3 | B19: IPE程序 | C19: 在使用手工编制、自定义信息报告、系统生成的非固定格式报告等由被审计单位生成的信息时，测试有关信息准确性和完整性，并考虑针对编制和维护由被审计单位生成的信息的相关控制实施控制测试，以评价该信息是否能够为实现审计目的提供基础。 | D19: 常规★ | F19: √ | G19: √ | J19: T1 | K19: 可参见《审计手册》4.2.6，由被审计单位生成的信息可能是由系统生成的、或手工编制的、或二者兼而有之的方式生成的。例如，由被审计单位生成的信息可能包括： • 不涉及自定义的、由系统生成的报告（如，固定格式报告）； • 可能通过人工自定义的、由系统生成的报告，例如，（计算机）查询信息或特别定制的报告； • 手工编制的信息，例如，汇总信息的电子表格或用以支持分配、计算以及调节的电子表格； • 其他系统生成或手工编制的信息，例如，由被审计单位编制的客户发票； • 通过影印、拍摄、扫描或其他方式转换成电子形式的文件记录。
A20: 4 | B20: 期初余额 | C20: 对上期发生额的审计：（适用于首次承接）： （1）向被审计单位人员询问前期期末关于收入截止的相关处理； （2）复核资产负债表日前后一段合理期间里的销售分录，调查任何异常分录。 （3）复核资产负债表日前后一段合理期间里销售退回或销售折扣的记录。 （4）调查接近前期期末发生的大额或异常的销售交易。 （5）必要时执行函证程序。 | D20: 备选 | E20: √ | F20: √ | G20: √ | H20: √ | K20: 由被审计单位生成的信息不包括： • 总分类账或明细分类账、试算平衡表、或经审计的财务报表； • 第三方（除了服务机构）的报表或报告，例如，原始银行对账单，或函证的回函； • 外部数据（例如，第三方发布的数据，如，定价来源）。
A21: 5 | B21: 常规程序/应对措施-会计估计 | C21: 了解被审计单位收入类型，充分了解公司经销售模式，针对不同业务或模式，检查收入确认政策的合理性及与前期的一致性。关注周期性、偶然性的收入是否符合既定的收入确认原则、方法。必要时，与同行业其他公司的会计政策进行对比。 | D21: 常规★ | E21: √ | G21: √ | J21: D4-5 | K21: 营业收入中由被审计单位生成的信息例如：在使用被审计单位提供的发票清单、销售价格表、运输清单等被审计单位提供信息
A22: 6 | B22: 应对措施-实质性/非实质性分析程序 | C22: 实施分析程序： （1）计算本期重要的比率指标：赊销率、应收账款周转率、末月销售情况/当期销售（金额或销量）、重要客户的销售额/销售额等，与可比期间数据、预算数或同行业其他企业数据进行比较； （2）结合收入来源和销售模式，按照产品类别、业务模式、销售区域（如境内、海外）等将本期的主营业务收入与上期的主营业务收入进行比较，分析销售收入结构和价格变动是否异常，是否符合行业和市场同期的变化情况； （3）分月或分季度比较本期主营业务收入波动情况，分析其变动趋势是否正常，是否符合被审计单位季节性、周期性的经营规律，查明异常现象和重大波动的原因； (4）计算本期重要产品的各月毛利率，与上期毛利率进行比较，分析变动原因，关注是否存在显著异常，必要时应与同行业比较； （5）就不同业务模式比较分析主要客户的销售数量、销售金额及占比的变动以及原因，关注是否存在异常。 （6）比较主要客户主要产品销售单价与销售平均价格（或指导价）、同类产品市场价格差异，分析价格合理性，判断有无以低价或高价结算的方法，相互之间有无转移利润的现象。 （7）比较关联方客户销售价格与非关联方销售价格的差异，分析关联方销售价格合理性，判断有无以低价或高价结算的方法，相互之间有无转移利润的现象。 (8)获取产品销售价格目录，与上期末相关文件进行对比分析，选取定价有较大或异常变化的产品进行测试，检查售价变动是否符合定价政策，价格变动是否合理。 | D22: 常规★ | E22: √ | F22: √ | G22: √ | J22: D4-6 /D4-7 /D4-8 /D4-9 /D4-10 /D4-11
A23: 7 | B23: 常规程序(选择“存在重大合同”) | C23: 选取重要合同进行检查： （1）了解与重要合同相关的交易，包括商业理由（或缺乏商业理由）和经济实质； （2）检查重要合同并记录关键条款和条件，判断合同条款的合理性，考虑是否可能存在抽屉协议等； （3）检查重要合同价格，确定是否符合销售及信用管理政策，并测试交易价格的确定是否正确。考虑代第三方收取的款项、预期将退还给客户的款项，以及可变对价（如现金折扣、数量折扣、价格折让等）、合同中存在的重大融资成分、非现金对价、应付客户对价等因素的影响。 （4）判断履约义务识别、交易价格的确定、交易价格分摊、收入控制权转移时点或期间等是否恰当。 （5）判断是否涉及特定交易，例如：附有质量保证条款的销售、附有销售退回条款的销售、主要责任人和代理人、售后回购交易、分期收款销售、寄售商品、以旧换新、授予知识产权，客户未行使的权利等； （6）确定合同是否表明存在以前未识别或未披露的关联方或重大关联方交易、超过被审计单位正常经营过程的交易以及与审计有关的其他问题； （7）确定交易是否按合同条款履行。 | D23: 常规★ | E23: √ | G23: √ | J23: D4-12
A24: 8 | B24: 应对措施-检查 | C24: 采用恰当的抽样方法，选择样本检查时点法收入确认依据（出库单、验收单、物流运输单、发票等）是否充分，记账是否正确；检查时段法的履约进度确认方法是否恰当，前后期是否一致，检查履约进度确认收入依据（监理报告、履约进度审核报告、竣工验收报告、结算资料等）是否充分，记账是否正确。 | D24: 常规★ | E24: √ | G24: √ | H24: √ | J24: D4-14
A25: 9 | B25: 应对措施-检查 | C25: 针对重要出口业务收入： （1）将销售记录与合同、报关单、装箱单、提单、发票、结汇单、物流运输单等出口销售单据进行核对； （2）使用电子口岸卡登陆电子口岸的信息系统，查询交易记录。 （3）必要时，向海关函证出口交易信息。 | D25: 备选 | E25: √ | G25: √ | H25: √ | J25: D4-14 /D4-16
A26: 10 | B26: 应对措施-检查 | C26: 针对电商、游戏等互联网行业等，应充分了解其具体的运营模式、盈利模式、不同参与主体间的责任分担等情况，结合IT审计检查收入数据、结算数据的真实性、完整性、准确性。 | D26: 备选 | E26: √ | G26: √
A27: 11 | B27: 应对措施-检查 | C27: 针对大额现金交易： （1）分析现金收付合理性，是否与行业特征和实际生产经营情况一致。 （2）获取公司报告期内存在现金销售的原因分析，分析被审计单位关于现金交易的相关说明是否合理。与对公司关键人员访谈、生产销售流程观察等程序获取的信息核对。 （3）逐月统计最近三年内现金销售收款金额，核查现金收款异常波动的原因，根据被审计单位情况分层统计分析，并对最近一年现金销售收入进行概要分析； （4）选择大额或异常现金交易，进行测试，核对付款方和付款金额与合同、订单、出库单是否一致，款项是否确实由客户支付。记录主要信息，必要的留存复印件；未见异常的项目，按照随机抽样的原则抽取一定比例，进行测试。必要时，实施函证程序。 | D27: 备选 | E27: √ | G27: √ | H27: √
A28: 12 | B28: 应对措施-检查 | C28: 销售的截止测试： （1）获取资产负债表日前后若干笔会计记录，与发货单证等信息核对，确定收入是否记入了恰当的期间。 （2）获取资产负债表日前后若干张发货单，与会计记录信息核对，确定是否存在收入跨期。 （3）复核资产负债表日前后的销售和发货水平，与正常水平相比是否存在异常，并考虑是否追加截止性测试。 （4）浏览期后一定时间的总账和明细账，以发现是否存在销售收 入冲回或大额销售退回的情况，对期后的大宗或异常的销售退货、冲回进行检查，以确定是否提前确认收入。 （5）结合存货监盘，对于尚未发运的销售（如开出账单但保管商品），查核支持性文件，与客户适当人员讨论，检查是否满足收入确认条件及会计处理的正确性。 | D28: 常规★ | H28: √ | J28: D4-17 /D4-18
A29: 13 | B29: 应对措施-检查 | C29: 销售折扣与折让： (1)获取或编制销售折扣与折让明细表，复核加计正确，并与明细账合计数核对相符； (2)取得被审计单位有关折扣与折让的具体规定和其他文件资料，并抽查较大的折扣发生额的授权批准情况，与实际执行情况进行核对； (3)检查折扣与折让是否及时足额提交对方，有无虚设中介、转移收入、私设账外“小金库”等情况； (4)检查折扣与折让的会计处理是否正确。 | D29: 常规★ | G29: √ | J29: D4-19
A30: 14 | B30: 应对措施-检查 | C30: 存在销货退回的，分析被审计单位对于退货率的估计是否合理，应付退货款、应收退货成本的会计处理是否正确；检查手续是否符合规定，结合原始销售凭证检查其会计处理是否正确；结合存货项目审计关注其真实性。 | D30: 常规★ | E30: √ | G30: √ | H30: √ | J30: D4-20
A31: 15 | B31: 常规程序(选择“存在关联交易”) | C31: 检查关联交易： (1)了解交易的商业理由、交易事项的目的、价格和条件，考虑对关联方销售的合理性、合法性； (2）检查证实交易的支持性文件（例如合同、发票、运输单据等），检查价格公允性，合同条款是否与非关联方一致； （考虑向关联方或其他注册会计师函证重大的关联采购交易和余额（包括担保和其他重要信息）； （4）必要时，向与交易相关的人员和机构（如银行、律师）函证或与其讨论有关信息； （5）考虑是否存在未识别的关联方，关联交易和余额披露是否正确。 | D31: 常规★ | E31: √ | F31: √ | G31: √ | I31: √ | J31: D4-21
A32: 16 | C32: 根据评估的舞弊风险等因素增加的审计程序。 | D32: IPO/上市/新三板/重组/舞弊应对 | J32: D4-22A
A33: 17 | C33: 检查营业收入是否已按企业会计准则或其他适用的规定在财务报表中做出恰当列报和披露。 | D33: 常规★ | I33: √ | J33: A 1-1/A1-15 /A1-16
C34: 针对其他业务收入，考虑执行以下程序：
A35: 18 | B35: 常规程序/应对措施-会计估计 | C35: 了解其他业务收入的业务内容，判断其分类为其他业务收入是否恰当。获取并了解被审计单位其他业务收入确认相关的会计政策，并与上年相比较是否存在重大差异变化。 | D35: 常规★ | E35: √ | J35: D4-3 /D4-5
A36: 19 | B36: 应对措施-实质性/非实质性分析程序 | C36: 计算本期其他业务收入与其他业务成本的比率和毛利率,并与上期该比率比较，检查是否有重大波动，如有，应查明原因。 | D36: 常规★ | E36: √ | F36: √ | G36: √ | J36: D4-33
A37: 20 | B37: 应对措施-检查 | C37: 获取其他业务收入合同，检查合同主要条款，考虑商业实质和合理性；重新计算出租、咨询等服务合同收入金额是否正确。 | D37: 常规★ | E37: √ | F37: √ | G37: √ | H37: √ | J37: D4-34
A38: 21 | B38: 应对措施-检查 | C38: 对于大额其他业务收入，检查支持性文件，分析交易实质，确定是否符合收入确认条件、会计处理是否正确。 | D38: 常规★ | E38: √ | G38: √ | H38: √ | J38: D4-35
A39: 22 | B39: 应对措施-检查 | C39: 抽取资产负债表日前后若干天、一定金额以上的其他业务收入记账凭证与发货单等信息核对，确定其他业务收入是否记入了恰当的期间；抽取资产负债表日前后若干天、一定金额以上的发货单等与记账凭证核对，确定其他业务收入是否记入了恰当的期间； | D39: 常规★ | H39: √ | J39: D4-36

Sheet 营业收入审定表D4-1
A1: 致同会计师事务所
A2: 营业收入审定表
A3: =[5]底稿目录!A2 -> 被审计单位： | C3: =[5]底稿目录!A4 -> 编制人： | F3: =[5]底稿目录!A5 -> 编制日期： | H3: 索引号： | I3: D4-1
A4: =[5]底稿目录!A3 -> 会计期间：202X年度 | C4: =[5]底稿目录!A6 -> 复核人： | F4: =[5]底稿目录!A7 -> 复核日期： | H4: 页次：
A5: 项目 | B5: 本期数 | F5: 上期数
B6: 未审数 | C6: 账项调整 | D6: 重分类调整 | E6: 审定数 | F6: 未审数 | G6: 账项调整 | H6: 重分类调整 | I6: 审定数
A7: 主营业务收入：
E8: =SUM(B8:D8) -> 0 | I8: =SUM(F8:H8) -> 0
E9: =SUM(B9:D9) -> 0 | I9: =SUM(F9:H9) -> 0
E10: =SUM(B10:D10) -> 0 | I10: =SUM(F10:H10) -> 0
E11: =SUM(B11:D11) -> 0 | I11: =SUM(F11:H11) -> 0
A12: 小计 | B12: =SUM(B8:B11) -> 0 | C12: =SUM(C8:C11) -> 0 | D12: =SUM(D8:D11) -> 0 | E12: =B12+C12+D12 -> 0 | F12: =SUM(F8:F11) -> 0 | G12: =SUM(G8:G11) -> 0 | H12: =SUM(H8:H11) -> 0 | I12: =SUM(I8:I11) -> 0
A13: 其他业务收入：
E14: =SUM(B14:D14) -> 0 | I14: =SUM(F14:H14) -> 0
E15: =SUM(B15:D15) -> 0 | I15: =SUM(F15:H15) -> 0
E16: =SUM(B16:D16) -> 0 | I16: =SUM(F16:H16) -> 0
E17: =SUM(B17:D17) -> 0 | I17: =SUM(F17:H17) -> 0
A18: 小计 | B18: =SUM(B14:B17) -> 0 | C18: =SUM(C14:C17) -> 0 | D18: =SUM(D14:D17) -> 0 | E18: =SUM(E14:E17) -> 0 | F18: =SUM(F14:F17) -> 0 | G18: =SUM(G14:G17) -> 0 | H18: =SUM(H14:H17) -> 0 | I18: =SUM(I14:I17) -> 0
A19: 合计 | B19: =B18+B12 -> 0 | C19: =C18+C12 -> 0 | D19: =D18+D12 -> 0 | E19: =E18+E12 -> 0 | F19: =F18+F12 -> 0 | G19: =G18+G12 -> 0 | H19: =H18+H12 -> 0 | I19: =I18+I12 -> 0
A20: 试算平衡表数
A21: 差异数 | E21: =E19-E20 -> 0 | I21: =I19-I20 -> 0
A22: 1.审计说明 | E22: 2.审计结论
A23: （1）营业收入本期较上期增加（负数为减少）：
A24: 主要原因（比例超过30%的）：
A26: （2）公司前五名客户营业收入总额为 元，占公司全部主营业务收入的比例为 %。
A28: （3）实际执行的审计程序和完成的底稿概述
A29: 实施的实质性程序概述 | C29: 执行结果 | E29: 底稿索引号
A36: 注：根据2024年沪深北交易所修订的《上市规则》：公司最近一个会计年度经审计的利润总额、净利润或者扣除非经常性损益后的净利润孰低者为负值的，公司应当在年度报告或者更正公告中披露
A37: 营业收入扣除情况及扣除后的营业收入金额；负责审计的会计师事务所应当就公司营业收入扣除事项是否符合本条规定及扣除后的营业收入金额出具专项核查意见。项目需完成营业收入扣除情况核查底稿<S20>
A39: 提示1：根据2024年沪深北交易所修订的《上市规则》：公司最近一个会计年度经审计的利润总额、净利润或者扣除非经常性损益后的净利润孰低者为负值的，公司应当在年度报告或者更正公告中披露
A40: 营业收入扣除情况及扣除后的营业收入金额；负责审计的会计师事务所应当就公司营业收入扣除事项是否符合本条规定及扣除后的营业收入金额出具专项核查意见。项目需完成营业收入扣除情况核查底稿<S20>
A41: 提示2：针对最近一个会计年度经审计营业收入低于 3亿元（沪深主板）/1亿元（科创板、创业板）但利润总额、净利润及扣除非经常性损益后的净利润均为正值的公司，会计师事务所应当对其非经常
A42: 性损益披露的真实性、准确性、完整性出具专项核查意见。
A74: 出租固定资产
A75: 出租无形资产
A76: 出租包装物和商品
A77: 销售材料
A78: 用材料进行非货币性交换
A79: 用材料进行债务重组
A80: 投资性房地产租金收入

Sheet 附注披露信息（上市公司）
A1: 致同会计师事务所
A2: 附注披露信息（上市公司）
A3: 客户名称： | C3: 编制人： | E3: 编制日期： | I3: 索引号：
A4: 会计期间：201x年度 | C4: 复核人： | E4: 复核日期： | I4: 页 次：1
A6: 营业收入附注汇总
A7: （1）营业收入和营业成本
A8: 项 目 | B8: 本期发生额 | D8: 上期发生额
B9: 收入 | C9: 成本 | D9: 收入 | E9: 成本
A10: 主营业务
A11: 其他业务
A12: 合 计 | B12: =SUM(B10:B11) -> 0 | C12: =SUM(C10:C11) -> 0 | D12: =SUM(D10:D11) -> 0 | E12: =SUM(E10:E11) -> 0
A13: 说明：
A14: [披露本公司前期已经履行 (或部分履行) 的履约义务在本期调整的收入。例如：
A15: 本公司在2023年确认的、源自前期已经履行 (或部分履行) 的履约义务的收入金额为人民币XX元，主要是由于与XX客户签订的XX合同的估计完工进度发生了变化。]
A16: 【提示：
A17: 1.处置投资性房地产（无论采用公允价值模式计量还是成本模式计量）的收入，在“其他业务收入”列示，相应结转成本至“其他业务成本”；
A18: 2.单项的投资性房地产的处置，无论是直接出售还是先划分为持有待售资产再出售，处置损益均计入“其他业务收入/成本”，不计入“资产处置损益”
A19: 3.在停工停产期间继续计提固定资产折旧和无形资产摊销，并根据用途计入相关资产的成本或当期损益。例如，企业因需求不足而停产或因事故而停工检修等，相关生产设备应当继续计提折旧，并计入营业成本。】
A20: （2）营业收入、营业成本按行业（或产品类型）划分
A21: 主要产品类型（或行业） | B21: 本期发生额 | D21: 上期发生额
B22: 收入 | C22: 成本 | D22: 收入 | E22: 成本
A23: 主营业务：
A24: 消费品
A25: 汽车
A26: 能源
A27: ......
A29: 小 计 | B29: =SUM(B24:B28)-B24-B25-B26 -> 0 | C29: =SUM(C24:C28)-C24-C25-C26 -> 0 | D29: =SUM(D24:D28)-D24-D25-D26 -> 0 | E29: =SUM(E24:E28)-E24-E25-E26 -> 0
A30: 其他业务：
A31: 销售材料
A32: 租赁收入
A33: 小 计 | B33: =SUM(B31:B32) -> 0 | C33: =SUM(C31:C32) -> 0 | D33: =SUM(D31:D32) -> 0 | E33: =SUM(E31:E32) -> 0
A34: 合 计 | B34: =B29+B33 -> 0 | C34: =C29+C33 -> 0 | D34: =D29+D33 -> 0 | E34: =E29+E33 -> 0
A35: （3）营业收入、营业成本按地区划分（不适用的，删除）
A36: 主要经营地区 | B36: 本期发生额 | D36: 上期发生额
B37: 主营业务收入 | C37: 主营业务成本 | D37: 主营业务收入 | E37: 主营业务成本
A38: 东北
A39: 华北
A40: 西北
A41: ......
A43: 小 计 | B43: =B40+B39+B38 -> 0 | C43: =C40+C39+C38 -> 0 | D43: =D40+D39+D38 -> 0 | E43: =E40+E39+E38 -> 0
A44: （4）营业收入、营业成本按分解信息
B45: 本期发生额
B46: 消费品 | D46: 汽车 | F46: 能源 | H46: 其他
B47: 收入 | C47: 成本 | D47: 收入 | E47: 成本 | F47: 收入 | G47: 成本 | H47: 收入 | I47: 成本
A48: 主营业务 | B48: =SUM(B49:B51) -> 0 | C48: =SUM(C49:C51) -> 0 | F48: =SUM(F49:F51) -> 0 | I48: =SUM(I49:I51) -> 0
A49: 其中：在某一时点确认
A50: 在某一时段确认
A52: 其他业务 | B52: =SUM(B53:B55) -> 0 | C52: =SUM(C53:C55) -> 0 | F52: =SUM(F53:F55) -> 0 | I52: =SUM(I53:I55) -> 0
A53: 其中：在某一时点确认
A54: 在某一时段确认
A55: 租赁收入
A56: 合 计 | B56: =B52+B48 -> 0 | C56: =C52+C48 -> 0 | F56: =F52+F48 -> 0 | I56: =I52+I48 -> 0
A57: 【提示：在确定对收入进行分解的类别时，企业应当考虑其在下列情况下是如何列报和披露与收入有关的信息：
A58: ①在财务报表之外披露的信息，例如，在企业的业绩公告、年报或向投资者报送的相关资料中披露的收入信息；
A59: ②管理层为评价经营分部的财务业绩所定期复核的信息；以及
A60: ③企业或企业的财务报表使用者在评价企业的财务业绩或作出资源分配决策时，所使用的类似于上述①和②的信息类型的其他信息。
A61: 企业在对收入信息进行分解时，可以采用的类别包括但不限于：商品类型、经营地区、市场或客户类型、合同类型（例如，固定造价合同、成本加成合同等）、商品转让的时间（例如，在某一时点转让或在某一时段内转让）、合同期限（例如，长期合同、短期合同等）、销售渠道（例如，直接销售或通过经销商销售等）等。
A62: ④租赁收入需单独披露。】
A63: （5）履约义务的说明
A64: （披露与履约义务相关的信息，包括履约义务通常的履行时间、重要的支付条款、企业承诺转让的商品的性质（包括说明企业是否作为代理人）、企业承担的预期将退还给客户的款项等类似义务、质量保证的类型及相关义务等。）
A65: （6）与剩余履约义务有关的信息
A66: 【披露与剩余履约义务有关的下列信息：①分摊至本期末尚未履行（或部分未履行）履约义务的交易价格总额；②上述金额确认为收入的预计时间，企业可以按照对于剩余履约义务的期间而言最恰当的时间段为基础提供有关预计时间的定量信息，或者使用定性信息进行说明。】
A67: 分摊至尚未履行的履约义务的交易价格为xxx元，截止xx年xx月xx日，对于上述金额确认为收入的预计时间如下：
A68: 年 度 | B68: 2024年 | C68: 2025年 | D68: 合计
A69: xx合同预计将确认的收入 | D69: =SUM(B69:C69) -> 0
D70: =SUM(B70:C70) -> 0
A71: 【说明：是否存在任何对价金额未纳入交易价格，从而未纳入对于分摊至剩余履约义务的交易价格所需披露的信息之中，例如，由于将可变对价计入交易价格的限制要求而未计入交易价格的可变对价。】
A72: 【如果公司采用了简化操作方法，该方法满足下列条件之一可适用：
A73: 一是该项履约义务是原预计合同期限不超过一年的合同中的一部分。
A74: 二是企业有权对该履约义务下已转让的商品向客户发出账单，且账单金额能够代表企业累计至今已履约部分转移给客户的价值。
A75: 企业应当提供定性信息以说明采用了上述简化操作方法。
A76: 例如：
A77: 本公司与客户签订合同，为客户建造一栋办公楼，合同对价为500万元。本公司在2023年对该合同确认的收入金额为240万元。2023年12月31日，分摊至剩余履约义务的交易价格为260万元，本公司预计该金额将随着工程的完工进度，在未来12-15个月内确认为收入。】
A78: （7）重大合同变更【或重大交易价格调整】
A79: （披露重大合同变更或重大交易价格调整相关的信息、会计处理方法及对收入的影响金额。）
A80: （8）试运行销售收入
A81: 【提示：企业会计准则解释第15号规定，企业应当按照《企业会计准则第1号——存货》、《企业会计准则第14号——收入》、《企业会计准则第30号——财务报表列报》等规定，判断试运行销售是否属于企业的日常活动，并在财务报表中分别日常活动和非日常活动列示试运行销售的相关收入和成本，属于日常活动的，在“营业收入”和“营业成本”项目列示；属于非日常活动的，在“资产处置收益”等项目列示。同时企业应当在附注中单独披露试运行销售的相关收入和成本金额、具体列报项目以及确定试运行销售相关成本时采用的重要会计估计等相关信息。】
A82: 项目 | B82: 本期发生额 | D82: 上期发生额
B83: 收入 | C83: 成本 | D83: 收入 | E83: 成本
A84: 固定资产试运行收入
A85: 研发样品销售收入

Sheet 附注披露信息（国企）
A1: 致同会计师事务所
A2: 附注披露信息（国有企业）
A3: 客户名称： | C3: 编制人： | E3: 编制日期： | I3: 索引号：
A4: 会计期间：201x年度 | C4: 复核人： | E4: 复核日期： | I4: 页 次：1
A5: 营业收入、营业成本附注
A6: （1）营业收入、营业成本
A7: 项 目 | B7: 本期发生额 | D7: 上期发生额
B8: 收入 | C8: 成本 | D8: 收入 | E8: 成本
A9: 主营业务
A10: 其他业务
A11: 合 计 | B11: =SUM(B9:B10) -> 0 | C11: =SUM(C9:C10) -> 0 | D11: =SUM(D9:D10) -> 0 | E11: =SUM(E9:E10) -> 0
A12: 【提示：
A13: 1.处置投资性房地产（无论采用公允价值模式计量还是成本模式计量）的收入，在“其他业务收入”列示，相应结转成本至“其他业务成本”；
A14: 2.单项的投资性房地产的处置，无论是直接出售还是先划分为持有待售资产再出售，处置损益均计入“其他业务收入/成本”，不计入“资产处置损益”
A15: 3.在停工停产期间继续计提固定资产折旧和无形资产摊销，并根据用途计入相关资产的成本或当期损益。例如，企业因需求不足而停产或因事故而停工检修等，相关生产设备应当继续计提折旧，并计入营业成本。
A16: （2）按行业（或产品类型）划分
A17: 主要产品类型（或行业） | B17: 本期发生额 | D17: 上期发生额
B18: 收入 | C18: 成本 | D18: 收入 | E18: 成本
A19: 主营业务：
A20: 消费品
A21: 汽车
A22: 能源
A23: 小 计 | B23: =B20+B21+B22 -> 0 | C23: =C20+C21+C22 -> 0 | D23: =D20+D21+D22 -> 0 | E23: =E20+E21+E22 -> 0
A24: 其他业务：
A25: 销售材料
A26: 租赁收入
A27: 小 计 | B27: =B25+B26 -> 0 | C27: =C25+C26 -> 0 | D27: =D25+D26 -> 0 | E27: =E25+E26 -> 0
A28: 合 计 | B28: =B23+B27 -> 0 | C28: =C23+C27 -> 0 | D28: =D23+D27 -> 0 | E28: =E23+E27 -> 0
A29: （3）营业收入、营业成本按地区划分（不适用的，删除）
A30: 主要经营地区 | B30: 本期发生额 | D30: 上期发生额
B31: 收入 | C31: 成本 | D31: 收入 | E31: 成本
A32: 东北
A33: 华北
A34: 西北
A36: 小 计 | B36: =B32+B33+B34 -> 0 | C36: =C32+C33+C34 -> 0 | D36: =D32+D33+D34 -> 0 | E36: =E32+E33+E34 -> 0
A37: （4）营业收入分解信息
B38: 本期发生额
B39: 消费品 | D39: 汽车 | F39: 能源 | H39: 其他
B40: 收入 | C40: 成本 | D40: 收入 | E40: 成本 | F40: 收入 | G40: 成本 | H40: 收入 | I40: 成本
A41: 主营业务 | B41: =SUM(B42:B44) -> 0 | C41: =SUM(C42:C44) -> 0 | F41: =SUM(F42:F44) -> 0 | I41: =SUM(I42:I44) -> 0
A42: 其中：在某一时点确认
A43: 在某一时段确认
A45: 其他业务 | B45: =SUM(B46:B48) -> 0 | C45: =SUM(C46:C48) -> 0 | F45: =SUM(F46:F48) -> 0 | I45: =SUM(I46:I48) -> 0
A46: 其中：在某一时点确认
A47: 在某一时段确认
A48: 租赁收入
A49: 合 计 | B49: =B45+B41 -> 0 | C49: =C45+C41 -> 0 | F49: =F45+F41 -> 0 | I49: =I45+I41 -> 0
A50: 【提示：在确定对收入、成本进行分解的类别时，企业应当考虑其在下列情况下是如何列报和披露与收入有关的信息：
A51: ①在财务报表之外披露的信息，例如，在企业的业绩公告、年报或向投资者报送的相关资料中披露的收入信息；
A52: ②管理层为评价经营分部的财务业绩所定期复核的信息；以及
A53: ③企业或企业的财务报表使用者在评价企业的财务业绩或作出资源分配决策时，所使用的类似于上述①和②的信息类型的其他信息。
A54: 企业在对收入信息进行分解时，可以采用的类别包括但不限于：商品类型、经营地区、市场或客户类型、合同类型（例如，固定造价合同、成本加成合同等）、商品转让的时间（例如，在某一时点转让或在某一时段内转让）、合同期限（例如，长期合同、短期合同等）、销售渠道（例如，直接销售或通过经销商销售等）等。
A55: ④租赁收入需单独披露。】
A56: （5）履约义务相关信息
A57: 【履约义务相关的信息，包括但不限于：履行履约义务的时间、重要的支付条款、公司承诺转让商品的性质、是否为主要责任人、公司承担的预期将退还给客户的款项等类似义务、公司提供的质量保证类型及相关义务等。】
A58: （6）与剩余履约义务有关的信息
A59: 【与分摊至剩余履约义务的交易价格相关的信息，包括分摊至本期末尚未履行履约义务的交易价格总额及其确认为收入的预计时间、可变对价等。】
A60: 分摊至尚未履行的履约义务的交易价格为xxx元，截止xx年xx月xx日，对于上述金额确认为收入的预计时间如下：
A61: 年 度 | B61: 2024年 | C61: 2025年 | D61: 合计
A62: xx合同预计将确认的收入
A64: 【说明是否存在任何对价金额未纳入交易价格，从而未纳入对于分摊至剩余履约义务的交易价格所需披露的信息之中，例如，由于将可变对价计入交易价格的限制要求而未计入交易价格的可变对价。】
A65: 【如果公司采用了简化操作方法，该方法满足下列条件之一可适用：
A66: 一是该项履约义务是原预计合同期限不超过一年的合同中的一部分。
A67: 二是企业有权对该履约义务下已转让的商品向客户发出账单，且账单金额能够代表企业累计至今已履约部分转移给客户的价值。
A68: 企业应当提供定性信息以说明采用了上述简化操作方法。
A69: 例如：
A70: 本公司与客户签订合同，为客户建造一栋办公楼，合同对价为500万元。本公司在2023年对该合同确认的收入金额为240万元。2023年12月31日，分摊至剩余履约义务的交易价格为260万元，本公司预计该金额将随着工程的完工进度，在未来12-15个月内确认为收入。】
A71: （7）重大合同变更【或重大交易价格调整】
A72: （重大合同变更或重大交易价格调整相关的信息、会计处理方法及对收入的影响金额。）

Sheet 主营业务收入明细表D4-2
A1: 致同会计师事务所
A2: 主营业务收入明细表
A3: =[5]底稿目录!A2 -> 被审计单位： | I3: =[5]底稿目录!A4 -> 编制人： | O3: =[5]底稿目录!A5 -> 编制日期： | U3: 索引号： | V3: D4-2
A4: =[5]底稿目录!A3 -> 会计期间：202X年度 | I4: =[5]底稿目录!A6 -> 复核人： | O4: =[5]底稿目录!A7 -> 复核日期： | U4: 页次：
A5: 一、审计目标
A6: 与主营业务收入有关的金额及其他数据已恰当记录，相关披露已得到恰当计量和描述。
A7: 二、审计过程
A8: 1.……
A11: 项目 | B11: 1月 | C11: 2月 | D11: 3月 | E11: 4月 | F11: 5月 | G11: 6月 | H11: 7月 | I11: 8月 | J11: 9月 | K11: 10月 | L11: 11月 | M11: 12月 | N11: 本期未审数合计 | O11: 本期审计调整 | P11: 本期审定数 | Q11: 上期未审数 | R11: 上期审计调整 | S11: 上期审定数 | T11: 未审变动比例 | U11: 审定变动比例 | V11: 备注
N12: =SUM(B12:M12) -> 0 | P12: =N12+O12 -> 0 | S12: =Q12+R12 -> 0 | T12: =IF(AND(Q12=0,N12=0),0,IF(AND(Q12=0,N12>0),1,(N12-Q12)/Q12)) -> 0 | U12: =IF(AND(S12=0,P12=0),0,IF(AND(S12=0,P12>0),1,(P12-S12)/S12)) -> 0
N13: =SUM(B13:M13) -> 0 | P13: =N13+O13 -> 0 | S13: =Q13+R13 -> 0 | T13: =IF(AND(Q13=0,N13=0),0,IF(AND(Q13=0,N13>0),1,(N13-Q13)/Q13)) -> 0 | U13: =IF(AND(S13=0,P13=0),0,IF(AND(S13=0,P13>0),1,(P13-S13)/S13)) -> 0
N14: =SUM(B14:M14) -> 0 | P14: =N14+O14 -> 0 | S14: =Q14+R14 -> 0 | T14: =IF(AND(Q14=0,N14=0),0,IF(AND(Q14=0,N14>0),1,(N14-Q14)/Q14)) -> 0 | U14: =IF(AND(S14=0,P14=0),0,IF(AND(S14=0,P14>0),1,(P14-S14)/S14)) -> 0
N15: =SUM(B15:M15) -> 0 | P15: =N15+O15 -> 0 | S15: =Q15+R15 -> 0 | T15: =IF(AND(Q15=0,N15=0),0,IF(AND(Q15=0,N15>0),1,(N15-Q15)/Q15)) -> 0 | U15: =IF(AND(S15=0,P15=0),0,IF(AND(S15=0,P15>0),1,(P15-S15)/S15)) -> 0
N16: =SUM(B16:M16) -> 0 | P16: =N16+O16 -> 0 | S16: =Q16+R16 -> 0 | T16: =IF(AND(Q16=0,N16=0),0,IF(AND(Q16=0,N16>0),1,(N16-Q16)/Q16)) -> 0 | U16: =IF(AND(S16=0,P16=0),0,IF(AND(S16=0,P16>0),1,(P16-S16)/S16)) -> 0
N17: =SUM(B17:M17) -> 0 | P17: =N17+O17 -> 0 | S17: =Q17+R17 -> 0 | T17: =IF(AND(Q17=0,N17=0),0,IF(AND(Q17=0,N17>0),1,(N17-Q17)/Q17)) -> 0 | U17: =IF(AND(S17=0,P17=0),0,IF(AND(S17=0,P17>0),1,(P17-S17)/S17)) -> 0
N18: =SUM(B18:M18) -> 0 | P18: =N18+O18 -> 0 | S18: =Q18+R18 -> 0 | T18: =IF(AND(Q18=0,N18=0),0,IF(AND(Q18=0,N18>0),1,(N18-Q18)/Q18)) -> 0 | U18: =IF(AND(S18=0,P18=0),0,IF(AND(S18=0,P18>0),1,(P18-S18)/S18)) -> 0
N19: =SUM(B19:M19) -> 0 | P19: =N19+O19 -> 0 | S19: =Q19+R19 -> 0 | T19: =IF(AND(Q19=0,N19=0),0,IF(AND(Q19=0,N19>0),1,(N19-Q19)/Q19)) -> 0 | U19: =IF(AND(S19=0,P19=0),0,IF(AND(S19=0,P19>0),1,(P19-S19)/S19)) -> 0
N20: =SUM(B20:M20) -> 0 | P20: =N20+O20 -> 0 | S20: =Q20+R20 -> 0 | T20: =IF(AND(Q20=0,N20=0),0,IF(AND(Q20=0,N20>0),1,(N20-Q20)/Q20)) -> 0 | U20: =IF(AND(S20=0,P20=0),0,IF(AND(S20=0,P20>0),1,(P20-S20)/S20)) -> 0
N21: =SUM(B21:M21) -> 0 | P21: =N21+O21 -> 0 | S21: =Q21+R21 -> 0 | T21: =IF(AND(Q21=0,N21=0),0,IF(AND(Q21=0,N21>0),1,(N21-Q21)/Q21)) -> 0 | U21: =IF(AND(S21=0,P21=0),0,IF(AND(S21=0,P21>0),1,(P21-S21)/S21)) -> 0
N22: =SUM(B22:M22) -> 0 | P22: =N22+O22 -> 0 | S22: =Q22+R22 -> 0 | T22: =IF(AND(Q22=0,N22=0),0,IF(AND(Q22=0,N22>0),1,(N22-Q22)/Q22)) -> 0 | U22: =IF(AND(S22=0,P22=0),0,IF(AND(S22=0,P22>0),1,(P22-S22)/S22)) -> 0
N23: =SUM(B23:M23) -> 0 | P23: =N23+O23 -> 0 | S23: =Q23+R23 -> 0 | T23: =IF(AND(Q23=0,N23=0),0,IF(AND(Q23=0,N23>0),1,(N23-Q23)/Q23)) -> 0 | U23: =IF(AND(S23=0,P23=0),0,IF(AND(S23=0,P23>0),1,(P23-S23)/S23)) -> 0
A24: 合计 | B24: =SUM(B12:B23) -> 0 | C24: =SUM(C12:C23) -> 0 | D24: =SUM(D12:D23) -> 0 | E24: =SUM(E12:E23) -> 0 | F24: =SUM(F12:F23) -> 0 | G24: =SUM(G12:G23) -> 0 | H24: =SUM(H12:H23) -> 0 | I24: =SUM(I12:I23) -> 0 | ... S24: =SUM(S12:S23) -> 0 | T24: =IF(AND(Q24=0,N24=0),0,IF(AND(Q24=0,N24>0),1,(N24-Q24)/Q24)) -> 0 | U24: =IF(AND(S24=0,P24=0),0,IF(AND(S24=0,P24>0),1,(P24-S24)/S24)) -> 0
A25: 各月比例 | B25: =IF($N$24=0,0,B24/$N$24) -> 0 | C25: =IF($N$24=0,0,C24/$N$24) -> 0 | D25: =IF($N$24=0,0,D24/$N$24) -> 0 | E25: =IF($N$24=0,0,E24/$N$24) -> 0 | F25: =IF($N$24=0,0,F24/$N$24) -> 0 | G25: =IF($N$24=0,0,G24/$N$24) -> 0 | H25: =IF($N$24=0,0,H24/$N$24) -> 0 | I25: =IF($N$24=0,0,I24/$N$24) -> 0 | ... N25: =IF($N$24=0,0,N24/$N$24) -> 0
A26: 三、审计说明
A27: 1.XX公司收入主要集中在第二季度和第四季度，主要原因是……，经查询同行业数据< >，收入季节变化符合行业周期季节变化，季节性因素对公司各季度收入的影响合理。
A30: 四、审计结论
A32: 提示1：根据项目需要，按照区域、品种等进行分类汇总。

Sheet 其他业务收入明细表D4-3
A1: 致同会计师事务所
A2: 其他业务收入明细表
A3: =[5]底稿目录!A2 -> 被审计单位： | E3: =[5]底稿目录!A4 -> 编制人： | I3: =[5]底稿目录!A5 -> 编制日期： | M3: 索引号： | N3: D4-3
A4: =[5]底稿目录!A3 -> 会计期间：202X年度 | E4: =[5]底稿目录!A6 -> 复核人： | I4: =[5]底稿目录!A7 -> 复核日期： | M4: 页次：
A5: 一、审计目标：
A6: 与其他业务收入有关的金额及其他数据已恰当记录，相关披露已得到恰当计量和描述。
A7: 二、审计过程:
A8: 1.……
A11: 项目 | B11: 本期数 | G11: 上期数 | L11: 本期数比上期增加（减少） | N11: 备注
B12: 本期未审数 | C12: 账项调整 | D12: 重分类调整 | E12: 本期审定数 | F12: 结构比 | G12: 上期未审数 | H12: 账项调整 | I12: 重分类调整 | J12: 上期审定额 | K12: 结构比 | L12: 变动额 | M12: 变动率
A13: 出租固定资产 | E13: =B13+C13+D13 -> 0 | F13: =IF(E13=0,0,E13/$E$20) -> 0 | J13: =G13+H13+I13 -> 0 | K13: =IF(J13=0,0,J13/$J$20) -> 0 | L13: =E13-J13 -> 0 | M13: =IF(AND(J13=0,L13=0),0,IF(AND(J13=0,L13>0),1,L13/J13)) -> 0
A14: 出租无形资产 | E14: =B14+C14+D14 -> 0 | F14: =IF(E14=0,0,E14/$E$20) -> 0 | J14: =G14+H14+I14 -> 0 | K14: =IF(J14=0,0,J14/$J$20) -> 0 | L14: =E14-J14 -> 0 | M14: =IF(AND(J14=0,L14=0),0,IF(AND(J14=0,L14>0),1,L14/J14)) -> 0
A15: 出租包装物和商品 | E15: =B15+C15+D15 -> 0 | F15: =IF(E15=0,0,E15/$E$20) -> 0 | J15: =G15+H15+I15 -> 0 | K15: =IF(J15=0,0,J15/$J$20) -> 0 | L15: =E15-J15 -> 0 | M15: =IF(AND(J15=0,L15=0),0,IF(AND(J15=0,L15>0),1,L15/J15)) -> 0
A16: 销售材料 | E16: =B16+C16+D16 -> 0 | F16: =IF(E16=0,0,E16/$E$20) -> 0 | J16: =G16+H16+I16 -> 0 | K16: =IF(J16=0,0,J16/$J$20) -> 0 | L16: =E16-J16 -> 0 | M16: =IF(AND(J16=0,L16=0),0,IF(AND(J16=0,L16>0),1,L16/J16)) -> 0
A17: 用材料进行非货币性交换 | E17: =B17+C17+D17 -> 0 | F17: =IF(E17=0,0,E17/$E$20) -> 0 | J17: =G17+H17+I17 -> 0 | K17: =IF(J17=0,0,J17/$J$20) -> 0 | L17: =E17-J17 -> 0 | M17: =IF(AND(J17=0,L17=0),0,IF(AND(J17=0,L17>0),1,L17/J17)) -> 0
A18: 投资性房地产租金收入 | E18: =B18+C18+D18 -> 0 | F18: =IF(E18=0,0,E18/$E$20) -> 0 | J18: =G18+H18+I18 -> 0 | K18: =IF(J18=0,0,J18/$J$20) -> 0 | L18: =E18-J18 -> 0 | M18: =IF(AND(J18=0,L18=0),0,IF(AND(J18=0,L18>0),1,L18/J18)) -> 0
A19: …… | E19: =B19+C19+D19 -> 0 | F19: =IF(E19=0,0,E19/$E$20) -> 0 | J19: =G19+H19+I19 -> 0 | K19: =IF(J19=0,0,J19/$J$20) -> 0 | L19: =E19-J19 -> 0 | M19: =IF(AND(J19=0,L19=0),0,IF(AND(J19=0,L19>0),1,L19/J19)) -> 0
A20: 合计 | B20: =SUM(B13:B19) -> 0 | C20: =SUM(C13:C19) -> 0 | D20: =SUM(D13:D19) -> 0 | E20: =SUM(E13:E19) -> 0 | F20: =IF(E20=0,0,E20/$E$20) -> 0 | G20: =SUM(G13:G19) -> 0 | H20: =SUM(H13:H19) -> 0 | I20: =SUM(I13:I19) -> 0 | J20: =SUM(J13:J19) -> 0 | K20: =IF(J20=0,0,J20/$J$20) -> 0 | L20: =E20-J20 -> 0 | M20: =IF(AND(J20=0,L20=0),0,IF(AND(J20=0,L20>0),1,L20/J20)) -> 0
A21: 三、审计说明：
A25: 四、审计结论：
A29: 提示：
A30: 本科目核算企业确认的除主营业务活动以外的其他经营活动实现的收入，包括出租固定资产、出租无形资产、出租包装物和商品、销售材料、用材料进行非货币性交换（非货币性资产交换具有商业实质且公允价值能够可靠计量）或债务重组等实现的收入。
A31: 企业（保险）经营受托管理业务收取的管理费收入，也通过本科目核算。

Sheet 营业收入调整分录汇总D4-4
A1: 致同会计师事务所
A2: 营业收入调整分录汇总表
A3: =[5]底稿目录!A2 -> 被审计单位： | D3: =[5]底稿目录!A4 -> 编制人： | G3: =[5]底稿目录!A5 -> 编制日期： | I3: 索引号： | J3: D4-4
A4: =[5]底稿目录!A3 -> 会计期间：202X年度 | D4: =[5]底稿目录!A6 -> 复核人： | G4: =[5]底稿目录!A7 -> 复核日期： | I4: 页次：
A5: 调整事项说明 | B5: 类别（报表调整/账项调整/其他） | C5: 报表项目 | D5: 科目名称 | E5: 附注项目 | F5: …… | G5: 借方调整金额 | H5: 贷方调整金额 | I5: 索引 | J5: 备注
A21: 提示：本底稿适用于调整分录较多、较复杂的项目，且仅列示与本报表项目相关的审计调整。项目组可根据项目实际情况选择是否使用该底稿。

Sheet 营业收入会计政策检查D4-5
A1: 致同会计师事务所
A2: 营业收入会计政策检查
A3: =[8]底稿目录!$A$2 -> 被审计单位： | B3: =[8]底稿目录!$A$4 -> 编制人： | C3: =[8]底稿目录!$A$5 -> 编制日期： | D3: 索引号： | E3: D4-5
A4: =[8]底稿目录!$A$3 -> 会计期间：202X年度 | B4: =[8]底稿目录!$A$6 -> 复核人： | C4: =[8]底稿目录!$A$7 -> 复核日期： | D4: 页次：
A5: 一、审计目标
A6: 与营业收入有关的金额及其他数据已恰当记录，相关披露已得到恰当计量和描述
A7: 二、审计过程
A8: 1.访谈XX公司管理层XXX，了解XX公司业务类型、销售模式，针对不同业务或模式，检查收入确认政策的合理性及与前期的一致性
A9: 2.……
A10: （一）经营模式
A11: 1.产品应用场景
A12: 2.订单获取方式/渠道，合同签订及履行方式
A13: 3.产销模式
A14: 4.销售模式
A15: 5.定价方式
A16: 6.交货方式
... A59: 提示2：了解和记录经营模式时注意以下方面: (1)产品应用场景，包括产品种类、行业协会（如有）、监管部门网站（如有）、用途、市场空间、行业前景等; (2)订单获取方式/渠道，合同签订及履行方式应来源于销售部门，若有多条业务线，应全面了解；了解该内容，可以整体评估收入的可持续性、销售费用的完整性，并与同行业对比。实质性核查程序，应考虑该因素，如招投标、关联关系等； (3)以销定产（加合理库存）模式，①要分析合理库存的制定方法、合理性、一惯性，存货是否积压，是否有减值迹象；②剔除合理库存后，存货是否有在手订单覆盖，业务是否可持续，存货是否会积压？③是否与产能匹配？以产定销，是否与产品的竞争力匹配，是否与同行业一致？ (4)如果被审计单位采用代理模式、经销商模式，了解其原因及合理性，并通过访谈获取被审计单位选择经销商的原则。部分形式上的直接销售，可能包含转销，要结合产品与客户的业务类型、规模、合同条款，分析识别。若识别不准确，将影响实质性检查程序及风险识别；经销、代销、转销，模式是否符合行业惯例，应穿透至最终客户检查；经销、代销、转销如何规定控制权转移，可能影响收入政策。 (5)了解并记录被审计单位定价方式时应分析主动权，并结合其他描述、同行业分析合理性。是否存在可变对价，可能影响收入政策。 (6)解并记录被审计单位送货还是取货，运输工具，途中耗时等；交货周期（合同签订至交付日），分析大额订单存货、生产周期是否匹配；被审计单位在货物流转前是否取得控制权；验收方式；退换货政策，质保政策。

Sheet 底稿目录 (2)
A1: 1.底稿开列时，可先在以下单元格填写有关内容，以便其他底稿引用有关数据：
A2: 被审计单位名称： | D2: 序号 | E2: 内容 | F2: 索引号
A3: 会计期间：202X年度 | D3: 1 | E3: 重要指标分析 | F3: D4-6
A4: 编制人： | D4: 2 | E4: 毛利率分析表 | F4: D4-7
A5: 编制日期： | D5: 3 | E5: 重要产品毛利分析 | F5: D4-8
A6: 复核人： | D6: 4 | E6: 重要客户结构分析 | F6: D4-9
A7: 复核日期： | D7: 5 | E7: 重要客户销售价格分析 | F7: D4-10
D8: 6 | E8: 产品销售价格分析 | F8: D4-11
A9: 关于工作底稿与审计程序索引号对应的说明
A10: 1.编制的审计工作底稿应与审计程序对应。审计项目组应根据被审计单位实际情况和风险评估情况在实质性程序表中裁剪、修改或增加审计程序，根据实际执行的审计程序完成相应审计工作底稿，编制的工作底稿中应按自然顺序依次编制索引号，并通过唯一的索引号将与实质性程序表中的程序对应关联（即将工作底稿的索引号填入实质性程序表中的底稿索引号列）。
A14: 2.获取的支持性证据应与审计底稿或程序对应。审计项目组在完成底稿时获取的支持性证据应根据底稿索引号编制下一级按自然顺序排序的索引号（如D1-2-1、D1-2-2、……），并在底稿中说明引用的支持性证据、关联索引号。
A17: 3.工作底稿索引号的编码规则：实质性程序索引号按循环从“D”到“N”,循环内账户以顺序号排列，模板中底稿索引号按账户顺序+自然数顺序（即模板中索引号按二级自然顺序排列，如D1-1、D1-2、D1-3、……D1-N）。

Sheet 重要指标分析D4-6
A1: 致同会计师事务所
A2: 重要指标分析表
A3: =[9]底稿目录!A2 -> 被审计单位名称： | B3: =[9]底稿目录!A4 -> 编制人： | E3: =[9]底稿目录!A5 -> 编制日期： | G3: 索引号： | H3: =[9]底稿目录!F3 -> D4-6
A4: =[9]底稿目录!A3 -> 会计期间：202X年度 | B4: =[9]底稿目录!A6 -> 复核人： | E4: =[9]底稿目录!A7 -> 复核日期： | G4: 页次：
A5: 一、审计目标
A6: 1.利润表中记录的营业收入已发生，且与被审计单位有关；2.所有应当记录的营业收入均已记录；
A7: 3.与营业收入有关的金额及其他数据已恰当记录，相关披露已得到恰当计量和描述。
A8: 二、审计过程
A9: 1.……
A11: 指标名称 | B11: 本期 | C11: 上期 | D11: 差异1 | E11: 变化原因及合理性分析1 | F11: 同行业公司平均值 | G11: 差异2 | H11: 变化原因及合理性分析2
B12: ① | C12: ② | D12: ③=(①-②)/② | E12: ④ | F12: ⑤ | G12: ⑥=（①-⑤）/⑤ | H12: ⑦
A13: 应收账款/总资产 | D13: =IF(C13=0,0,(B13-C13)/C13) -> 0 | G13: =IF(F13=0,0,(B13-F13)/F13) -> 0
A14: 应收账款周转天数=应收账款平均余额/(销售收入/365) | D14: =IF(C14=0,0,(B14-C14)/C14) -> 0 | G14: =IF(F14=0,0,(B14-F14)/F14) -> 0
A15: 应收账款周转次数=销售收入/应收账款平均余额 | D15: =IF(C15=0,0,(B15-C15)/C15) -> 0 | G15: =IF(F15=0,0,(B15-F15)/F15) -> 0
A16: (末月/最后一个季度）销售情况/当期销售（金额或销量） | D16: =IF(C16=0,0,(B16-C16)/C16) -> 0 | G16: =IF(F16=0,0,(B16-F16)/F16) -> 0
A17: 销售折扣/销售额 | D17: =IF(C17=0,0,(B17-C17)/C17) -> 0 | G17: =IF(F17=0,0,(B17-F17)/F17) -> 0
A18: 销售折让/销售额 | D18: =IF(C18=0,0,(B18-C18)/C18) -> 0 | G18: =IF(F18=0,0,(B18-F18)/F18) -> 0
A19: 销货退回/销售额 | D19: =IF(C19=0,0,(B19-C19)/C19) -> 0 | G19: =IF(F19=0,0,(B19-F19)/F19) -> 0
A20: 坏账准备余额/应收账款余额 | D20: =IF(C20=0,0,(B20-C20)/C20) -> 0 | G20: =IF(F20=0,0,(B20-F20)/F20) -> 0
A21: 人均创收=销售收入/员工总数 | D21: =IF(C21=0,0,(B21-C21)/C21) -> 0 | G21: =IF(F21=0,0,(B21-F21)/F21) -> 0
A22: 销售净利率=净利润/销售收入 | D22: =IF(C22=0,0,(B22-C22)/C22) -> 0 | G22: =IF(F22=0,0,(B22-F22)/F22) -> 0
A23: 人均创利=净利润/员工总数 | D23: =IF(C23=0,0,(B23-C23)/C23) -> 0 | G23: =IF(F23=0,0,(B23-F23)/F23) -> 0
A24: 当期销售金额/主要原材料采购金额 | D24: =IF(C24=0,0,(B24-C24)/C24) -> 0 | G24: =IF(F24=0,0,(B24-F24)/F24) -> 0
A25: 三、审计说明
A28: 四、审计结论

Sheet 毛利率分析表D4-7
A1: 致同会计师事务所
A2: 主营业务收入毛利率分析表
A3: =[9]底稿目录!A2 -> 被审计单位名称： | I3: =[9]底稿目录!A4 -> 编制人： | Q3: =[9]底稿目录!A5 -> 编制日期： | V3: 索引号： | W3: =[9]底稿目录!F4 -> D4-7
A4: =[9]底稿目录!A3 -> 会计期间：202X年度 | I4: =[9]底稿目录!A6 -> 复核人： | Q4: =[9]底稿目录!A7 -> 复核日期： | V4: 页次：
A5: 一、审计目标：
A6: 利润表中记录的营业收入已发生，且与被审计单位有关。
A7: 二、审计过程
A8: 1.了解公司各月毛利、收入的构成及变化情况是否符合行业和市场同期的变化情况。了解公司的产品或服务价格、销量及变动趋势，了解市场上具有代表性企业的价格信息和趋势、行业协会发布的统计数据，并进行比较，确定是否存在显著异常
A10: （一）月度毛利分析
A11: 月份 | B11: 1月 | C11: 2月 | D11: 3月 | E11: 4月 | F11: 5月 | G11: 6月 | H11: 7月 | I11: 8月 | J11: 9月 | K11: 10月 | L11: 11月 | M11: 12月 | N11: 合计 | O11: 上期 | P11: 变动比例
A12: 主营业务收入 | N12: =SUM(B12:M12) -> 0 | P12: =(N12-O12)/O12 -> #DIV/0!
A13: 主营业务成本 | N13: =SUM(B13:M13) -> 0 | P13: =(N13-O13)/O13 -> #DIV/0!
A14: 毛利 | B14: =B12-B13 -> 0 | C14: =C12-C13 -> 0 | D14: =D12-D13 -> 0 | E14: =E12-E13 -> 0 | F14: =F12-F13 -> 0 | G14: =G12-G13 -> 0 | H14: =H12-H13 -> 0 | I14: =I12-I13 -> 0 | ... O14: =O12-O13 -> 0 | P14: =(N14-O14)/O14 -> #DIV/0!
A15: 毛利率 | B15: =B14/B12 -> #DIV/0! | C15: =C14/C12 -> #DIV/0! | D15: =D14/D12 -> #DIV/0! | E15: =E14/E12 -> #DIV/0! | F15: =F14/F12 -> #DIV/0! | G15: =G14/G12 -> #DIV/0! | H15: =H14/H12 -> #DIV/0! | I15: =I14/I12 -> #DIV/0! | ... O15: =O14/O12 -> #DIV/0!
A17: （二）按产品毛利分析
A18: 产品名称 | B18: 本期 | J18: 上期 | R18: 变动比例 | W18: 备注
B19: 数量 | C19: 平均单价 | D19: 主营业务收入 | E19: 结构比 | F19: 单位成本 | G19: 主营业务成本 | H19: 毛利 | I19: 毛利率 | J19: 数量 | K19: 平均单价 | L19: 主营业务收入 | M19: 结构比 | N19: 单位成本 | O19: 主营业务成本 | P19: 毛利 | Q19: 毛利率 | R19: 平均单价 | S19: 单位成本 | T19: 主营业务收入 | U19: 主营业务成本 | V19: 毛利率
C20: =D20/B20 -> #DIV/0! | E20: =D20/$D$26 -> #DIV/0! | F20: =G20/B20 -> #DIV/0! | H20: =D20-G20 -> 0 | I20: =IF(D20=0,0,H20/D20) -> 0 | K20: =L20/J20 -> #DIV/0! | M20: =L20/$L$26 -> #DIV/0! | N20: =O20/J20 -> #DIV/0! | P20: =L20-O20 -> 0 | Q20: =IF(L20=0,0,P20/L20) -> 0 | R20: =(C20-K20)/K20 -> #DIV/0! | S20: =(F20-N20)/N20 -> #DIV/0! | T20: =(D20-L20)/L20 -> #DIV/0! | U20: =(G20-O20)/O20 -> #DIV/0! | V20: =I20-Q20 -> 0
C21: =D21/B21 -> #DIV/0! | E21: =D21/$D$26 -> #DIV/0! | F21: =G21/B21 -> #DIV/0! | H21: =D21-G21 -> 0 | I21: =IF(D21=0,0,H21/D21) -> 0 | K21: =L21/J21 -> #DIV/0! | M21: =L21/$L$26 -> #DIV/0! | N21: =O21/J21 -> #DIV/0! | P21: =L21-O21 -> 0 | Q21: =IF(L21=0,0,P21/L21) -> 0 | R21: =(C21-K21)/K21 -> #DIV/0! | S21: =(F21-N21)/N21 -> #DIV/0! | T21: =(D21-L21)/L21 -> #DIV/0! | U21: =(G21-O21)/O21 -> #DIV/0! | V21: =I21-Q21 -> 0
C22: =D22/B22 -> #DIV/0! | E22: =D22/$D$26 -> #DIV/0! | F22: =G22/B22 -> #DIV/0! | H22: =D22-G22 -> 0 | I22: =IF(D22=0,0,H22/D22) -> 0 | K22: =L22/J22 -> #DIV/0! | M22: =L22/$L$26 -> #DIV/0! | N22: =O22/J22 -> #DIV/0! | P22: =L22-O22 -> 0 | Q22: =IF(L22=0,0,P22/L22) -> 0 | R22: =(C22-K22)/K22 -> #DIV/0! | S22: =(F22-N22)/N22 -> #DIV/0! | T22: =(D22-L22)/L22 -> #DIV/0! | U22: =(G22-O22)/O22 -> #DIV/0! | V22: =I22-Q22 -> 0
C23: =D23/B23 -> #DIV/0! | E23: =D23/$D$26 -> #DIV/0! | F23: =G23/B23 -> #DIV/0! | H23: =D23-G23 -> 0 | I23: =IF(D23=0,0,H23/D23) -> 0 | K23: =L23/J23 -> #DIV/0! | M23: =L23/$L$26 -> #DIV/0! | N23: =O23/J23 -> #DIV/0! | P23: =L23-O23 -> 0 | Q23: =IF(L23=0,0,P23/L23) -> 0 | R23: =(C23-K23)/K23 -> #DIV/0! | S23: =(F23-N23)/N23 -> #DIV/0! | T23: =(D23-L23)/L23 -> #DIV/0! | U23: =(G23-O23)/O23 -> #DIV/0! | V23: =I23-Q23 -> 0
C24: =D24/B24 -> #DIV/0! | E24: =D24/$D$26 -> #DIV/0! | F24: =G24/B24 -> #DIV/0! | H24: =D24-G24 -> 0 | I24: =IF(D24=0,0,H24/D24) -> 0 | K24: =L24/J24 -> #DIV/0! | M24: =L24/$L$26 -> #DIV/0! | N24: =O24/J24 -> #DIV/0! | P24: =L24-O24 -> 0 | Q24: =IF(L24=0,0,P24/L24) -> 0 | R24: =(C24-K24)/K24 -> #DIV/0! | S24: =(F24-N24)/N24 -> #DIV/0! | T24: =(D24-L24)/L24 -> #DIV/0! | U24: =(G24-O24)/O24 -> #DIV/0! | V24: =I24-Q24 -> 0
C25: =D25/B25 -> #DIV/0! | E25: =D25/$D$26 -> #DIV/0! | F25: =G25/B25 -> #DIV/0! | H25: =D25-G25 -> 0 | I25: =IF(D25=0,0,H25/D25) -> 0 | K25: =L25/J25 -> #DIV/0! | M25: =L25/$L$26 -> #DIV/0! | N25: =O25/J25 -> #DIV/0! | P25: =L25-O25 -> 0 | Q25: =IF(L25=0,0,P25/L25) -> 0 | R25: =(C25-K25)/K25 -> #DIV/0! | S25: =(F25-N25)/N25 -> #DIV/0! | T25: =(D25-L25)/L25 -> #DIV/0! | U25: =(G25-O25)/O25 -> #DIV/0! | V25: =I25-Q25 -> 0
A26: 合计 | B26: =SUM(B20:B25) -> 0 | C26: =D26/B26 -> #DIV/0! | D26: =SUM(D20:D25) -> 0 | E26: =D26/$D$26 -> #DIV/0! | F26: =G26/B26 -> #DIV/0! | G26: =SUM(G20:G25) -> 0 | H26: =SUM(H20:H25) -> 0 | I26: =IF(D26=0,0,H26/D26) -> 0 | J26: =SUM(J20:J25) -> 0 | K26: =L26/J26 -> #DIV/0! | L26: =SUM(L20:L25) -> 0 | M26: =L26/$L$26 -> #DIV/0! | N26: =O26/J26 -> #DIV/0! | O26: =SUM(O20:O25) -> 0 | P26: =SUM(P20:P25) -> 0 | Q26: =IF(L26=0,0,P26/L26) -> 0 | R26: =(C26-K26)/K26 -> #DIV/0! | S26: =(F26-N26)/N26 -> #DIV/0! | T26: =(D26-L26)/L26 -> #DIV/0! | U26: =(G26-O26)/O26 -> #DIV/0! | V26: =I26-Q26 -> 0
A27: 三、审计说明
A28: 1.毛利率变动异常原因：
A29: 2.XX产品单价变动异常，采用审计抽样方法检查该类型产品单价变动的合理性，判断销售给关联方或关系密切的重要客户的产品价格是否合理，有无以低价或高价结算的方法，相互之间有无转移利润的现象，见<产品销售价格分析D4-1>。
A30: 四、审计结论
A32: 提示：除分析主要产品和服务之外，还需要考虑被审计单位是否有联产品和副产品产出；如有，应同时分析联产品和副产品的毛利变化情况，并结合营业成本的审计，判断联产品和副产品的成本分摊是否正确。

Sheet 重要产品毛利分析D4-8
A1: 致同会计师事务所
A2: 重要产品/服务毛利率分析表
A3: =[9]底稿目录!A2 -> 被审计单位名称： | H3: =[9]底稿目录!A4 -> 编制人： | N3: =[9]底稿目录!A5 -> 编制日期： | W3: 索引号： | X3: =[9]底稿目录!F5 -> D4-8
A4: =[9]底稿目录!A3 -> 会计期间：202X年度 | H4: =[9]底稿目录!A6 -> 复核人： | N4: =[9]底稿目录!A7 -> 复核日期： | W4: 页次：
A5: 一、审计目标
A6: 1.利润表中记录的营业收入已发生，且与被审计单位有关；2.所有应当记录的营业收入均已记录；
A7: 3.与营业收入有关的金额及其他数据已恰当记录，相关披露已得到恰当计量和描述。
A8: 二、审计过程
A9: 1.……
A12: 产品A：
A13: 月份 | B13: 本期数 | J13: 上期数 | R13: 本期比上期增减变动分析 | X13: 备注
B14: 营业收入 | E14: 营业成本 | H14: 毛利 | I14: 毛利率 | J14: 营业收入 | M14: 营业成本 | P14: 毛利 | Q14: 毛利率 | R14: 平均单价 | S14: 单位成本 | T14: 主营业务收入 | U14: 主营业务成本 | V14: 毛利 | W14: 毛利率
B15: 销量 | C15: 平均单价 | D15: 金额 | E15: 销量 | F15: 平均单位成本 | G15: 金额 | J15: 销量 | K15: 平均单价 | L15: 金额 | M15: 销量 | N15: 平均单位成本 | O15: 金额
A16: 1 | H16: =D16-G16 -> 0 | I16: =IF(D16=0,0,H16/D16) -> 0 | P16: =L16-O16 -> 0 | Q16: =IF(L16=0,0,P16/L16) -> 0 | R16: =(C16-K16)/K16 -> #DIV/0! | S16: =(F16-N16)/N16 -> #DIV/0! | T16: =(D16-L16)/L16 -> #DIV/0! | U16: =(G16-O16)/O16 -> #DIV/0! | V16: =(H16-P16)/P16 -> #DIV/0! | W16: =I16-Q16 -> 0
A17: 2 | H17: =D17-G17 -> 0 | I17: =IF(D17=0,0,H17/D17) -> 0 | P17: =L17-O17 -> 0 | Q17: =IF(L17=0,0,P17/L17) -> 0 | R17: =(C17-K17)/K17 -> #DIV/0! | S17: =(F17-N17)/N17 -> #DIV/0! | T17: =(D17-L17)/L17 -> #DIV/0! | U17: =(G17-O17)/O17 -> #DIV/0! | V17: =(H17-P17)/P17 -> #DIV/0! | W17: =I17-Q17 -> 0
A18: 3 | H18: =D18-G18 -> 0 | I18: =IF(D18=0,0,H18/D18) -> 0 | P18: =L18-O18 -> 0 | Q18: =IF(L18=0,0,P18/L18) -> 0 | R18: =(C18-K18)/K18 -> #DIV/0! | S18: =(F18-N18)/N18 -> #DIV/0! | T18: =(D18-L18)/L18 -> #DIV/0! | U18: =(G18-O18)/O18 -> #DIV/0! | V18: =(H18-P18)/P18 -> #DIV/0! | W18: =I18-Q18 -> 0
A19: 4 | H19: =D19-G19 -> 0 | I19: =IF(D19=0,0,H19/D19) -> 0 | P19: =L19-O19 -> 0 | Q19: =IF(L19=0,0,P19/L19) -> 0 | R19: =(C19-K19)/K19 -> #DIV/0! | S19: =(F19-N19)/N19 -> #DIV/0! | T19: =(D19-L19)/L19 -> #DIV/0! | U19: =(G19-O19)/O19 -> #DIV/0! | V19: =(H19-P19)/P19 -> #DIV/0! | W19: =I19-Q19 -> 0
A20: 5 | H20: =D20-G20 -> 0 | I20: =IF(D20=0,0,H20/D20) -> 0 | P20: =L20-O20 -> 0 | Q20: =IF(L20=0,0,P20/L20) -> 0 | R20: =(C20-K20)/K20 -> #DIV/0! | S20: =(F20-N20)/N20 -> #DIV/0! | T20: =(D20-L20)/L20 -> #DIV/0! | U20: =(G20-O20)/O20 -> #DIV/0! | V20: =(H20-P20)/P20 -> #DIV/0! | W20: =I20-Q20 -> 0
A21: 6 | H21: =D21-G21 -> 0 | I21: =IF(D21=0,0,H21/D21) -> 0 | P21: =L21-O21 -> 0 | Q21: =IF(L21=0,0,P21/L21) -> 0 | R21: =(C21-K21)/K21 -> #DIV/0! | S21: =(F21-N21)/N21 -> #DIV/0! | T21: =(D21-L21)/L21 -> #DIV/0! | U21: =(G21-O21)/O21 -> #DIV/0! | V21: =(H21-P21)/P21 -> #DIV/0! | W21: =I21-Q21 -> 0
A22: 7 | H22: =D22-G22 -> 0 | I22: =IF(D22=0,0,H22/D22) -> 0 | P22: =L22-O22 -> 0 | Q22: =IF(L22=0,0,P22/L22) -> 0 | R22: =(C22-K22)/K22 -> #DIV/0! | S22: =(F22-N22)/N22 -> #DIV/0! | T22: =(D22-L22)/L22 -> #DIV/0! | U22: =(G22-O22)/O22 -> #DIV/0! | V22: =(H22-P22)/P22 -> #DIV/0! | W22: =I22-Q22 -> 0
A23: 8 | H23: =D23-G23 -> 0 | I23: =IF(D23=0,0,H23/D23) -> 0 | P23: =L23-O23 -> 0 | Q23: =IF(L23=0,0,P23/L23) -> 0 | R23: =(C23-K23)/K23 -> #DIV/0! | S23: =(F23-N23)/N23 -> #DIV/0! | T23: =(D23-L23)/L23 -> #DIV/0! | U23: =(G23-O23)/O23 -> #DIV/0! | V23: =(H23-P23)/P23 -> #DIV/0! | W23: =I23-Q23 -> 0
A24: 9 | H24: =D24-G24 -> 0 | I24: =IF(D24=0,0,H24/D24) -> 0 | P24: =L24-O24 -> 0 | Q24: =IF(L24=0,0,P24/L24) -> 0 | R24: =(C24-K24)/K24 -> #DIV/0! | S24: =(F24-N24)/N24 -> #DIV/0! | T24: =(D24-L24)/L24 -> #DIV/0! | U24: =(G24-O24)/O24 -> #DIV/0! | V24: =(H24-P24)/P24 -> #DIV/0! | W24: =I24-Q24 -> 0
A25: 10 | H25: =D25-G25 -> 0 | I25: =IF(D25=0,0,H25/D25) -> 0 | P25: =L25-O25 -> 0 | Q25: =IF(L25=0,0,P25/L25) -> 0 | R25: =(C25-K25)/K25 -> #DIV/0! | S25: =(F25-N25)/N25 -> #DIV/0! | T25: =(D25-L25)/L25 -> #DIV/0! | U25: =(G25-O25)/O25 -> #DIV/0! | V25: =(H25-P25)/P25 -> #DIV/0! | W25: =I25-Q25 -> 0
A26: 11 | H26: =D26-G26 -> 0 | I26: =IF(D26=0,0,H26/D26) -> 0 | P26: =L26-O26 -> 0 | Q26: =IF(L26=0,0,P26/L26) -> 0 | R26: =(C26-K26)/K26 -> #DIV/0! | S26: =(F26-N26)/N26 -> #DIV/0! | T26: =(D26-L26)/L26 -> #DIV/0! | U26: =(G26-O26)/O26 -> #DIV/0! | V26: =(H26-P26)/P26 -> #DIV/0! | W26: =I26-Q26 -> 0
A27: 12 | H27: =D27-G27 -> 0 | I27: =IF(D27=0,0,H27/D27) -> 0 | P27: =L27-O27 -> 0 | Q27: =IF(L27=0,0,P27/L27) -> 0 | R27: =(C27-K27)/K27 -> #DIV/0! | S27: =(F27-N27)/N27 -> #DIV/0! | T27: =(D27-L27)/L27 -> #DIV/0! | U27: =(G27-O27)/O27 -> #DIV/0! | V27: =(H27-P27)/P27 -> #DIV/0! | W27: =I27-Q27 -> 0
A28: 合计 | B28: =SUM(B16:B27) -> 0 | C28: =IF(B28<>0,D28/B28,0) -> 0 | D28: =SUM(D16:D27) -> 0 | E28: =SUM(E16:E27) -> 0 | F28: =IF(E28<>0,G28/E28,0) -> 0 | G28: =SUM(G16:G27) -> 0 | H28: =SUM(H16:H27) -> 0 | I28: =IF(D28=0,0,H28/D28) -> 0 | J28: =SUM(J16:J27) -> 0 | K28: =IF(J28<>0,L28/J28,0) -> 0 | L28: =SUM(L16:L27) -> 0 | M28: =SUM(M16:M27) -> 0 | N28: =IF(M28<>0,O28/M28,0) -> 0 | O28: =SUM(O16:O27) -> 0 | P28: =SUM(P16:P27) -> 0 | Q28: =IF(L28=0,0,P28/L28) -> 0 | R28: =(C28-K28)/K28 -> #DIV/0! | S28: =(F28-N28)/N28 -> #DIV/0! | T28: =(D28-L28)/L28 -> #DIV/0! | U28: =(G28-O28)/O28 -> #DIV/0! | V28: =(H28-P28)/P28 -> #DIV/0! | W28: =I28-Q28 -> 0
A29: 同行业A企业 | H29: =D29-G29 -> 0 | I29: =IF(D29=0,0,H29/D29) -> 0 | P29: =L29-O29 -> 0 | Q29: =IF(L29=0,0,P29/L29) -> 0 | R29: =(C29-K29)/K29 -> #DIV/0! | S29: =(F29-N29)/N29 -> #DIV/0! | T29: =(D29-L29)/L29 -> #DIV/0! | U29: =(G29-O29)/O29 -> #DIV/0! | V29: =(H29-P29)/P29 -> #DIV/0! | W29: =I29-Q29 -> 0
A30: 同行业B企业 | H30: =D30-G30 -> 0 | I30: =IF(D30=0,0,H30/D30) -> 0 | P30: =L30-O30 -> 0 | Q30: =IF(L30=0,0,P30/L30) -> 0 | R30: =(C30-K30)/K30 -> #DIV/0! | S30: =(F30-N30)/N30 -> #DIV/0! | T30: =(D30-L30)/L30 -> #DIV/0! | U30: =(G30-O30)/O30 -> #DIV/0! | V30: =(H30-P30)/P30 -> #DIV/0! | W30: =I30-Q30 -> 0
A31: 行业平均水平 | H31: =D31-G31 -> 0 | I31: =IF(D31=0,0,H31/D31) -> 0 | P31: =L31-O31 -> 0 | Q31: =IF(L31=0,0,P31/L31) -> 0 | R31: =(C31-K31)/K31 -> #DIV/0! | S31: =(F31-N31)/N31 -> #DIV/0! | T31: =(D31-L31)/L31 -> #DIV/0! | U31: =(G31-O31)/O31 -> #DIV/0! | V31: =(H31-P31)/P31 -> #DIV/0! | W31: =I31-Q31 -> 0
A32: 产品B……（略）：
A35: 三、审计说明
A38: 四、审计结论

Sheet 重要客户结构分析D4-9
A1: 致同会计师事务所
A2: 重要客户结构分析表
A3: =[9]底稿目录!A2 -> 被审计单位名称： | C3: =[9]底稿目录!A4 -> 编制人： | E3: =[9]底稿目录!A5 -> 编制日期： | F3: 索引号： | G3: =[9]底稿目录!F6 -> D4-9
A4: =[9]底稿目录!A3 -> 会计期间：202X年度 | C4: =[9]底稿目录!A6 -> 复核人： | E4: =[9]底稿目录!A7 -> 复核日期： | F4: 页次：
A5: 一、审计目标
A6: 利润表中记录的营业收入已发生，且与被审计单位有关。
A7: 二、审计过程
A8: 1.……
A11: 本期：
A12: 序号 | B12: 客户名称 | C12: 销售金额 | D12: 销售金额占比 | E12: 销售数量 | F12: 销售数量占比 | G12: 上期排名
A13: 1 | D13: =IF(C13=0,0,C13/$C$24) -> 0 | F13: =IF(E13=0,0,E13/$E$24) -> 0
A14: 2 | D14: =IF(C14=0,0,C14/$C$24) -> 0 | F14: =IF(E14=0,0,E14/$E$24) -> 0
A15: 3 | D15: =IF(C15=0,0,C15/$C$24) -> 0 | F15: =IF(E15=0,0,E15/$E$24) -> 0
A16: 4 | D16: =IF(C16=0,0,C16/$C$24) -> 0 | F16: =IF(E16=0,0,E16/$E$24) -> 0
A17: 5 | D17: =IF(C17=0,0,C17/$C$24) -> 0 | F17: =IF(E17=0,0,E17/$E$24) -> 0
A18: 6 | D18: =IF(C18=0,0,C18/$C$24) -> 0 | F18: =IF(E18=0,0,E18/$E$24) -> 0
A19: 7 | D19: =IF(C19=0,0,C19/$C$24) -> 0 | F19: =IF(E19=0,0,E19/$E$24) -> 0
A20: 8 | D20: =IF(C20=0,0,C20/$C$24) -> 0 | F20: =IF(E20=0,0,E20/$E$24) -> 0
A21: 9 | D21: =IF(C21=0,0,C21/$C$24) -> 0 | F21: =IF(E21=0,0,E21/$E$24) -> 0
A22: 10 | D22: =IF(C22=0,0,C22/$C$24) -> 0 | F22: =IF(E22=0,0,E22/$E$24) -> 0
A23: 合计 | C23: =SUM(C13:C22) -> 0 | D23: =IF(C23=0,0,C23/$C$24) -> 0 | E23: =SUM(E13:E22) -> 0 | F23: =IF(E23=0,0,E23/$E$24) -> 0
A24: 本期销售总额 | C24: ='[9]毛利率分析表D4-7'!D26 -> 0 | E24: ='[9]毛利率分析表D4-7'!B26 -> 0
A25: 上期：
A26: 序号 | B26: 客户名称 | C26: 销售金额 | D26: 销售金额占比 | E26: 销售数量 | F26: 销售数量占比 | G26: 上期排名
A27: 1 | D27: =IF(C27=0,0,C27/$C$38) -> 0 | F27: =IF(E27=0,0,E27/$E$38) -> 0
A28: 2 | D28: =IF(C28=0,0,C28/$C$38) -> 0 | F28: =IF(E28=0,0,E28/$E$38) -> 0
A29: 3 | D29: =IF(C29=0,0,C29/$C$38) -> 0 | F29: =IF(E29=0,0,E29/$E$38) -> 0
A30: 4 | D30: =IF(C30=0,0,C30/$C$38) -> 0 | F30: =IF(E30=0,0,E30/$E$38) -> 0
A31: 5 | D31: =IF(C31=0,0,C31/$C$38) -> 0 | F31: =IF(E31=0,0,E31/$E$38) -> 0
A32: 6 | D32: =IF(C32=0,0,C32/$C$38) -> 0 | F32: =IF(E32=0,0,E32/$E$38) -> 0
A33: 7 | D33: =IF(C33=0,0,C33/$C$38) -> 0 | F33: =IF(E33=0,0,E33/$E$38) -> 0
A34: 8 | D34: =IF(C34=0,0,C34/$C$38) -> 0 | F34: =IF(E34=0,0,E34/$E$38) -> 0
A35: 9 | D35: =IF(C35=0,0,C35/$C$38) -> 0 | F35: =IF(E35=0,0,E35/$E$38) -> 0
A36: 10 | D36: =IF(C36=0,0,C36/$C$38) -> 0 | F36: =IF(E36=0,0,E36/$E$38) -> 0
A37: 合计 | C37: =SUM(C27:C36) -> 0 | D37: =IF(C37=0,0,C37/$C$38) -> 0 | E37: =SUM(E27:E36) -> 0 | F37: =IF(E37=0,0,E37/$E$38) -> 0
A38: 本期销售总额 | C38: ='[9]毛利率分析表D4-7'!L26 -> 0 | E38: ='[9]毛利率分析表D4-7'!J26 -> 0
A39: 三、审计说明
A40: 本年前十名客户的销售额较去年增加%，大于本年营业收入比去年营业收入增加的比率%
A41: 主要是因为…………
A42: 本年前十名客户的销售额较去年减少%，小于本年营业收入比去年营业收入减少的比率%
A43: 主要是因为…………
A44: 四、审计结论
A46: 提示：对于IPO、上市公司等审计业务，考虑：
A47: 1. 如果发行人的客户为公众公司，可获取客户的信息披露文件，与客户披露的采购金额核对，同时分析客户的偿债能力；
A48: 2.结合发行人业务特点和主要客户基本经营信息，分析客户购买力、结算周期和销售波动情况，是否存在客户异常采购的情况；
A49: 3.对当期销售占比较大的客户，了解大客户大量采购的原因，以及最终销售情况；对于重要客户为经销商的情况，关注终端客户同经销商地域的匹配性。
A50: 4.关注公司及其实际控制人与大客户是否存在除购销关系外的其他关系。

Sheet 重要客户销售价格分析D4-10
A1: 致同会计师事务所
A2: 重要客户销售价格分析
A3: 被审计单位名称： | F3: 编制人： | I3: 编制日期： | M3: 索引号： | N3: =[9]底稿目录!F7 -> D4-10
A4: 会计期间：2024年度 | F4: 复核人： | I4: 复核日期： | M4: 页次：
A5: 一、审计目标：
A6: 利润表中记录的营业收入已发生，且与被审计单位有关，已记录于恰当的账户。
A7: 二、审计过程
A8: 1.……
A11: 序号 | B11: 客户名称 | C11: 产品种类 | D11: 销售情况 | H11: 销售单价分析
D12: 销售金额 | E12: 占比 | F12: 销售数量 | G12: 占比 | H12: 销售单价 | I12: 年度均价 （或销售指导价格） | J12: 与均价差异 | K12: 差异原因 | L12: 市场价格 | M12: 与均价差异 | N12: 差异原因
A13: 1 | B13: 大额客户一 | C13: 产品1 | E13: =IF(D13=0,0,D13/$D$34) -> 0 | G13: =IF(F13=0,0,F13/$F$34) -> 0 | H13: 0 | J13: =IF(AND(I13=0,H13=0),0,IF(AND(I13=0,H13>0),1,(H13-I13)/I13)) -> 0 | M13: =IF(AND(L13=0,H13=0),0,IF(AND(L13=0,H13>0),1,(H13-L13)/L13)) -> 0
C14: 产品2 | E14: =IF(D14=0,0,D14/$D$34) -> 0 | G14: =IF(F14=0,0,F14/$F$34) -> 0 | H14: 0 | J14: =IF(AND(I14=0,H14=0),0,IF(AND(I14=0,H14>0),1,(H14-I14)/I14)) -> 0 | M14: =IF(AND(L14=0,H14=0),0,IF(AND(L14=0,H14>0),1,(H14-L14)/L14)) -> 0
C15: 产品3 | E15: =IF(D15=0,0,D15/$D$34) -> 0 | G15: =IF(F15=0,0,F15/$F$34) -> 0 | H15: 0 | J15: =IF(AND(I15=0,H15=0),0,IF(AND(I15=0,H15>0),1,(H15-I15)/I15)) -> 0 | M15: =IF(AND(L15=0,H15=0),0,IF(AND(L15=0,H15>0),1,(H15-L15)/L15)) -> 0
A16: 2 | B16: 大额客户二 | C16: 产品1 | E16: =IF(D16=0,0,D16/$D$34) -> 0 | G16: =IF(F16=0,0,F16/$F$34) -> 0 | H16: 0 | J16: =IF(AND(I16=0,H16=0),0,IF(AND(I16=0,H16>0),1,(H16-I16)/I16)) -> 0 | M16: =IF(AND(L16=0,H16=0),0,IF(AND(L16=0,H16>0),1,(H16-L16)/L16)) -> 0
C17: 产品2 | E17: =IF(D17=0,0,D17/$D$34) -> 0 | G17: =IF(F17=0,0,F17/$F$34) -> 0 | H17: 0 | J17: =IF(AND(I17=0,H17=0),0,IF(AND(I17=0,H17>0),1,(H17-I17)/I17)) -> 0 | M17: =IF(AND(L17=0,H17=0),0,IF(AND(L17=0,H17>0),1,(H17-L17)/L17)) -> 0
C18: 产品3 | E18: =IF(D18=0,0,D18/$D$34) -> 0 | G18: =IF(F18=0,0,F18/$F$34) -> 0 | H18: 0 | J18: =IF(AND(I18=0,H18=0),0,IF(AND(I18=0,H18>0),1,(H18-I18)/I18)) -> 0 | M18: =IF(AND(L18=0,H18=0),0,IF(AND(L18=0,H18>0),1,(H18-L18)/L18)) -> 0
A19: 3 | B19: 大额客户三 | C19: 产品1 | E19: =IF(D19=0,0,D19/$D$34) -> 0 | G19: =IF(F19=0,0,F19/$F$34) -> 0 | H19: 0 | J19: =IF(AND(I19=0,H19=0),0,IF(AND(I19=0,H19>0),1,(H19-I19)/I19)) -> 0 | M19: =IF(AND(L19=0,H19=0),0,IF(AND(L19=0,H19>0),1,(H19-L19)/L19)) -> 0
C20: 产品2 | E20: =IF(D20=0,0,D20/$D$34) -> 0 | G20: =IF(F20=0,0,F20/$F$34) -> 0 | H20: 0 | J20: =IF(AND(I20=0,H20=0),0,IF(AND(I20=0,H20>0),1,(H20-I20)/I20)) -> 0 | M20: =IF(AND(L20=0,H20=0),0,IF(AND(L20=0,H20>0),1,(H20-L20)/L20)) -> 0
C21: 产品3 | E21: =IF(D21=0,0,D21/$D$34) -> 0 | G21: =IF(F21=0,0,F21/$F$34) -> 0 | H21: 0 | J21: =IF(AND(I21=0,H21=0),0,IF(AND(I21=0,H21>0),1,(H21-I21)/I21)) -> 0 | M21: =IF(AND(L21=0,H21=0),0,IF(AND(L21=0,H21>0),1,(H21-L21)/L21)) -> 0
A22: 4 | B22: 大额客户四 | C22: 产品1 | E22: =IF(D22=0,0,D22/$D$34) -> 0 | G22: =IF(F22=0,0,F22/$F$34) -> 0 | H22: 0 | J22: =IF(AND(I22=0,H22=0),0,IF(AND(I22=0,H22>0),1,(H22-I22)/I22)) -> 0 | M22: =IF(AND(L22=0,H22=0),0,IF(AND(L22=0,H22>0),1,(H22-L22)/L22)) -> 0
C23: 产品2 | E23: =IF(D23=0,0,D23/$D$34) -> 0 | G23: =IF(F23=0,0,F23/$F$34) -> 0 | H23: 0 | J23: =IF(AND(I23=0,H23=0),0,IF(AND(I23=0,H23>0),1,(H23-I23)/I23)) -> 0 | M23: =IF(AND(L23=0,H23=0),0,IF(AND(L23=0,H23>0),1,(H23-L23)/L23)) -> 0
C24: 产品3 | E24: =IF(D24=0,0,D24/$D$34) -> 0 | G24: =IF(F24=0,0,F24/$F$34) -> 0 | H24: 0 | J24: =IF(AND(I24=0,H24=0),0,IF(AND(I24=0,H24>0),1,(H24-I24)/I24)) -> 0 | M24: =IF(AND(L24=0,H24=0),0,IF(AND(L24=0,H24>0),1,(H24-L24)/L24)) -> 0
A25: 5 | B25: 大额客户五 | C25: 产品1 | E25: =IF(D25=0,0,D25/$D$34) -> 0 | G25: =IF(F25=0,0,F25/$F$34) -> 0 | H25: 0 | J25: =IF(AND(I25=0,H25=0),0,IF(AND(I25=0,H25>0),1,(H25-I25)/I25)) -> 0 | M25: =IF(AND(L25=0,H25=0),0,IF(AND(L25=0,H25>0),1,(H25-L25)/L25)) -> 0
C26: 产品2 | E26: =IF(D26=0,0,D26/$D$34) -> 0 | G26: =IF(F26=0,0,F26/$F$34) -> 0 | H26: 0 | J26: =IF(AND(I26=0,H26=0),0,IF(AND(I26=0,H26>0),1,(H26-I26)/I26)) -> 0 | M26: =IF(AND(L26=0,H26=0),0,IF(AND(L26=0,H26>0),1,(H26-L26)/L26)) -> 0
C27: 产品3 | E27: =IF(D27=0,0,D27/$D$34) -> 0 | G27: =IF(F27=0,0,F27/$F$34) -> 0 | H27: 0 | J27: =IF(AND(I27=0,H27=0),0,IF(AND(I27=0,H27>0),1,(H27-I27)/I27)) -> 0 | M27: =IF(AND(L27=0,H27=0),0,IF(AND(L27=0,H27>0),1,(H27-L27)/L27)) -> 0
A28: 6 | B28: 异常客户X | C28: 产品1 | E28: =IF(D28=0,0,D28/$D$34) -> 0 | G28: =IF(F28=0,0,F28/$F$34) -> 0 | H28: 0 | J28: =IF(AND(I28=0,H28=0),0,IF(AND(I28=0,H28>0),1,(H28-I28)/I28)) -> 0 | M28: =IF(AND(L28=0,H28=0),0,IF(AND(L28=0,H28>0),1,(H28-L28)/L28)) -> 0
C29: 产品2 | E29: =IF(D29=0,0,D29/$D$34) -> 0 | G29: =IF(F29=0,0,F29/$F$34) -> 0 | H29: 0 | J29: =IF(AND(I29=0,H29=0),0,IF(AND(I29=0,H29>0),1,(H29-I29)/I29)) -> 0 | M29: =IF(AND(L29=0,H29=0),0,IF(AND(L29=0,H29>0),1,(H29-L29)/L29)) -> 0
C30: 产品3 | E30: =IF(D30=0,0,D30/$D$34) -> 0 | G30: =IF(F30=0,0,F30/$F$34) -> 0 | H30: 0 | J30: =IF(AND(I30=0,H30=0),0,IF(AND(I30=0,H30>0),1,(H30-I30)/I30)) -> 0 | M30: =IF(AND(L30=0,H30=0),0,IF(AND(L30=0,H30>0),1,(H30-L30)/L30)) -> 0
A31: 7 | B31: 异常客户Y | C31: 产品1 | E31: =IF(D31=0,0,D31/$D$34) -> 0 | G31: =IF(F31=0,0,F31/$F$34) -> 0 | H31: 0 | J31: =IF(AND(I31=0,H31=0),0,IF(AND(I31=0,H31>0),1,(H31-I31)/I31)) -> 0 | M31: =IF(AND(L31=0,H31=0),0,IF(AND(L31=0,H31>0),1,(H31-L31)/L31)) -> 0
C32: 产品2 | E32: =IF(D32=0,0,D32/$D$34) -> 0 | G32: =IF(F32=0,0,F32/$F$34) -> 0 | H32: 0 | J32: =IF(AND(I32=0,H32=0),0,IF(AND(I32=0,H32>0),1,(H32-I32)/I32)) -> 0 | M32: =IF(AND(L32=0,H32=0),0,IF(AND(L32=0,H32>0),1,(H32-L32)/L32)) -> 0
C33: 产品3 | E33: =IF(D33=0,0,D33/$D$34) -> 0 | G33: =IF(F33=0,0,F33/$F$34) -> 0 | H33: 0 | J33: =IF(AND(I33=0,H33=0),0,IF(AND(I33=0,H33>0),1,(H33-I33)/I33)) -> 0 | M33: =IF(AND(L33=0,H33=0),0,IF(AND(L33=0,H33>0),1,(H33-L33)/L33)) -> 0
A34: 本期销售总额 | D34: -- | F34: --
A35: 三、审计说明
A38: 四、审计结论
A40: 提示：根据《中国注册会计师审计准则问题解答第18号——识别和应对第三方配合实施财务舞弊》，项目组在分析主要客户销售产品价格时关注：
A41: 在第三方配合下，进行显失公允的交易。例如，以明显高于其他客户的价格向第三方销售商品。再如，与同一客户或同受一方控制的多个客户在各期发生多次交易，
A42: 在客户配合下，通过调节各次交易的商品销售价格，调节各期销售收入金额。

Sheet 产品销售价格分析D4-11
A1: 致同会计师事务所
A2: 产品销售价格分析
A3: =[9]底稿目录!A2 -> 被审计单位名称： | F3: =[9]底稿目录!A4 -> 编制人： | J3: =[9]底稿目录!A5 -> 编制日期： | N3: 索引号： | O3: =[9]底稿目录!F8 -> D4-11
A4: =[9]底稿目录!A3 -> 会计期间：202X年度 | F4: =[9]底稿目录!A6 -> 复核人： | J4: =[9]底稿目录!A7 -> 复核日期： | N4: 页次：
A5: 一、审计目标
A6: 利润表中记录的营业收入已发生，且与被审计单位有关。
A7: 二、审计过程
A8: 1.……
A11: 序号 | B11: 客户名称 | C11: 品种/规格 | D11: 销售单价 | E11: 销售数量 | F11: 开票日期 | G11: 销售订单 （销售凭证） | H11: 订单日期 | I11: 商品销售价格表所列单价 | J11: 与定价政策差异 | K11: 同期市场价格 | L11: 与市价差异 | M11: 差异原因分析 | N11: 同期市场价格来源（索引号） | O11: 备注
A12: 1 | J12: 0 | L12: 0
A13: 2 | J13: 0 | L13: 0
A14: 3 | J14: 0 | L14: 0
A15: 4 | J15: 0 | L15: 0
A16: 5 | J16: 0 | L16: 0
A17: 6 | J17: 0 | L17: 0
A18: 7 | J18: 0 | L18: 0
A19: 8 | J19: 0 | L19: 0
A20: 9 | J20: 0 | L20: 0
A21: 10 | J21: 0 | L21: 0
A22: 三、审计说明
A25: 四、审计结论

Sheet 合同检查表D4-12
A1: 致同会计师事务所
A2: 合同检查表
A3: =[11]底稿目录!$A$2 -> 被审计单位： | D3: =[11]底稿目录!$A$4 -> 编制人： | G3: =[11]底稿目录!$A$5 -> 编制日期： | J3: 索引号： | K3: D4-12
A4: =[11]底稿目录!$A$3 -> 会计期间：202X年度 | D4: =[11]底稿目录!$A$6 -> 复核人： | G4: =[11]底稿目录!$A$7 -> 复核日期： | J4: 页次：
A5: 一、审计目标
A6: 1.利润表中记录的营业收入已发生，且与被审计单位有关，已记录于恰当的账户；2.与营业收入有关的金额及其他数据已恰当记录，相关披露已得到恰当计量和描述
A7: 二、审计过程
A8: 1.……
A10: 索引号 | B10: D4-12-1 | C10: D4-12-2 | D10: D4-12-3 | E10: D4-12-4 | F10: D4-12-5 | G10: D4-12-6 | H10: D4-12-7 | I10: D4-12-8 | J10: D4-12-9 | K10: D4-12-10
A11: 合同编号
A12: 交易对方名称
A13: 合同签订日期
A14: 服务内容/提供产品名称
A15: 合同金额
A16: 交货时间/服务期间
A17: 交货方式/提供服务方式
A18: 结算方式
A19: 结算时间
A20: 质量保证条款
A21: 销售退回条款
A22: 违约条款
... A57: 提示4：五步法分析、主要责任人和代理人、知识产权等可参考<营业收入五步法、主要责任人代理人、知识产权分析参考示例>。

Sheet 底稿目录 (3)
A1: 底稿开列时，可先在以下单元格填写有关内容，以便其他底稿引用有关数据：
A2: 被审计单位： | D2: 序号 | E2: 内容 | F2: 索引号
A3: 会计期间：202X年度 | D3: 1 | E3: 营业收入账面金额与ERP系统核对记录 | F3: D4-13
A4: 编制人： | D4: 2 | E4: 营业收入发生检查表 | F4: D4-14
A5: 编制日期： | D5: 3 | E5: 营业收入完整性检查表 | F5: D4-15
A6: 复核人： | D6: 4 | E6: 出口收入电子口岸系统核对 | F6: D4-16
A7: 复核日期： | D7: 5 | E7: 营业收入截止测试（账到单据） | F7: D4-17
D8: 6 | E8: 营业收入截止测试（单据到账） | F8: D4-18
A9: 关于工作底稿与审计程序索引号对应的说明 | D9: 7 | E9: 销售折扣与折让检查 | F9: D4-19
A10: 1.编制的审计工作底稿应与审计程序对应。审计项目组应根据被审计单位实际情况和风险评估情况在实质性程序表中裁剪、修改或增加审计程序，根据实际执行的审计程序完成相应审计工作底稿，编制的工作底稿中应按自然顺序依次编制索引号，并通过唯一的索引号将与实质性程序表中的程序对应关联（即将工作底稿的索引号填入实质性程序表中的底稿索引号列）。 | D10: 8 | E10: 销售退货检查 | F10: D4-20
A14: 2.获取的支持性证据应与审计底稿或程序对应。审计项目组在完成底稿时获取的支持性证据应根据底稿索引号编制下一级按自然顺序排序的索引号（如D1-2-1、D1-2-2、……），并在底稿中说明引用的支持性证据、关联索引号。
A17: 3.工作底稿索引号的编码规则：实质性程序索引号按循环从“D”到“N”,循环内账户以顺序号排列，模板中底稿索引号按账户顺序+自然数顺序（即模板中索引号按二级自然顺序排列，如D1-1、D1-2、D1-3、……D1-N）。

Sheet 营业收入账面金额与ERP系统核对记录D4-13
A1: 致同会计师事务所
A2: 营业收入账面金额与ERP系统核对记录
A3: =[13]底稿目录!A2 -> 被审计单位： | B3: =[13]底稿目录!A4 -> 编制人： | C3: =[13]底稿目录!A5 -> 编制日期： | D3: 索引号： | E3: =[13]底稿目录!F3 -> D4-13
A4: =[13]底稿目录!A3 -> 会计期间：202X年度 | B4: =[13]底稿目录!A6 -> 复核人： | C4: =[13]底稿目录!A7 -> 复核日期： | D4: 页次：
A5: 一、核对过程
A15: 二、核对结论
A19: 提示：对于互联网等业务数据量大的被审计单位，应结合IT审计完成核对。

Sheet 营业收入发生检查表D4-14
A1: 致同会计师事务所 | U1: 致同会计师事务所
A2: 营业收入发生检查表 | U2: 营业收入发生检查表
A3: =[13]底稿目录!A2 -> 被审计单位： | H3: =[13]底稿目录!A4 -> 编制人： | M3: =[13]底稿目录!A5 -> 编制日期： | S3: 索引号： | T3: =[13]底稿目录!F4 -> D4-14 | U3: =[13]底稿目录!A2 -> 被审计单位： | Y3: =[13]底稿目录!A4 -> 编制人： | AC3: =[13]底稿目录!A5 -> 编制日期： | AJ3: 索引号： | AK3: =[13]底稿目录!F4 -> D4-14
A4: =[13]底稿目录!A3 -> 会计期间：202X年度 | H4: =[13]底稿目录!A6 -> 复核人： | M4: =[13]底稿目录!A7 -> 复核日期： | S4: 页次： | U4: =[13]底稿目录!A3 -> 会计期间：202X年度 | Y4: =[13]底稿目录!A6 -> 复核人： | AC4: =[13]底稿目录!A7 -> 复核日期： | AJ4: 页次：
A5: 一、审计目标：
A6: 1.利润表中记录的营业收入已发生，且与被审计单位有关；2.与营业收入有关的金额及其他数据已恰当记录，相关披露已得到恰当计量和描述；3.与营业收入有关的交易和事项已记录于正确的会计期间。
A7: 二、样本选取标准与规模：
A8: 测试总体： | C8: 如营业收入所有销售记账凭证共XX笔金额XX、贷方发生额所有凭证共XX笔金额XX | J8: 特定样本： | K8: XX金额以上（大额）、关联方/关联交易形成的款项、XX异常款项全部测试，共XX笔；
A9: 抽样总体： | C9: 测试总体扣除特定样本以外的样本，共XX笔、金额XX | J9: 确定的抽样样本量： | L9: 抽取XX笔 | M9: （如果使用了样本计算器计算样本量，样本量计算过程见<XX>底稿）
A10: 抽样方法： | C10: 随机选样/系统选样/货币单元抽样/随意选样（非统计抽样适用） | J10: 抽样过程： | K10: 使用IDEA（XX抽样工具）选择XX数量、金额XX的样本进行测试，抽样工具中的样本选择过程和结果见<XX>底稿
A11: 三、测试： | C11: 检查内容说明：1.核对合同、出库单、物流单、验收单等品名、规格一致、数量、单价、金额一致；2.核对验收单等控制权转移日期是否与记账相符，是否确认至恰当期间；
C12: 3.核对签收单签收人或盖章信息是否存在异常；4.核对运输地址是否与客户合同记录发货地址一致，是否存在异常；5.……
A13: 序号 | B13: 记账凭证 | H13: 销售合同/销售订单 | J13: 出库单 | N13: 仓库保管员 | O13: 发货审批人 | P13: 运输单 | U13: 签收单 | AB13: 发票 | AG13: …… | AI13: 其他支持性文件或说明 | AJ13: 索引号 | AK13: 是否异常
B14: 客户名称 | C14: 日期 | D14: 编号 | E14: 品名 | F14: 数量 | G14: 金额 | H14: 日期 | I14: 合同号/订单号 | J14: 日期 | K14: 编号 | L14: 品名 | M14: 数量 | P14: 日期 | Q14: 编号 | R14: 运输数量 | S14: 运输公司 | T14: 运输地址 | U14: 日期 | V14: 品名 | W14: 数量 | X14: 金额 | Y14: 签收人 | Z14: 盖章类型 | AA14: 盖章单位 | AB14: 日期 | AC14: 编号 | AD14: 品名 | AE14: 数量 | AF14: 金额 | AG14: …… | AH14: ……
A37: 合计 | G37: =SUM(G15:G36) -> 0 | X37: =SUM(X15:X36) -> 0 | AF37: =SUM(AF15:AF36) -> 0
A38: 本期发生额
A39: 检查比例 | G39: =G37/G38 -> #DIV/0!
A40: 四、审计说明：
A41: 1.如果检查比例较低应扩大检查样本量或说明原因
A44: 五、审计结论：
A48: 提示1：项目组应根据被审计单位业务特点确定应检查的收入确认依据以及检查要点，例如出口收入确认依据一般还包括报关单、提单等，工程施工收入确认依据一般包括进度审核单、竣工验收报告等。必要时，还应记录不同证据时间逻辑一致性检查。
A49: 提示2：根据《中国注册会计师审计准则问题解答第18号——识别和应对第三方配合实施财务舞弊》，项目组在检查收入发生时关注第三方配合虚假销售交易涉及的存货实物、交易单证票据和资金流转；例如，在虚假收入交易中的资金流转过程可能如下：
A50: （1）被审计单位通过虚假交易或虚增交易金额套取自有资金，或者为关联方违规提供担保、由该关联方取得金融机构借款，或者由关联方提供资金（参见《中国注册会计师审计准则问题解答第4号——收入确认》）。
A51: （2）虚假交易对手或关联方将资金支付给被审计单位“客户”；为增加隐蔽性，也可能先将资金支付给“过桥”方，再由“过桥”方支付给“客户”。
A52: （3）“客户”向被审计单位支付货款，形成虚假销售交易的资金闭环。

Sheet 营业收入完整性检查表D4-15
A1: 致同会计师事务所
A2: 营业收入完整性检查表
A3: =[13]底稿目录!A2 -> 被审计单位： | G3: =[13]底稿目录!A4 -> 编制人： | L3: =[13]底稿目录!A5 -> 编制日期： | P3: 索引号： | Q3: =[13]底稿目录!F5 -> D4-15
A4: =[13]底稿目录!A3 -> 会计期间：202X年度 | G4: =[13]底稿目录!A6 -> 复核人： | L4: =[13]底稿目录!A7 -> 复核日期： | P4: 页次：
A5: 一、审计目标：
A6: 所有应当记录的营业收入均已记录，所有应当包括在财务报表中的相关披露均已包括。
A7: 二、审计过程
A8: 1.在报告期内选择一个重要时期，测试收入确认依据的资料文件（如发货单、验收单等）
A9: 2.选择大的或者异常的项目进行测试（如果收入完整性评估为高风险，则应当采用抽样的方式）。
A10: 3.检查每个所选项目的单证，并追查到交易记录（如，销售日记账）。
A11: 序号 | B11: 发货单 | G11: 发票 | L11: 记账凭证 | Q11: 所载信息是否一致√(X)
B12: 日期 | C12: 编号 | D12: 品名 | E12: 数量 | F12: 金额 | G12: 日期 | H12: 编号 | I12: 品名 | J12: 数量 | K12: 金额 | L12: 日期 | M12: 编号 | N12: 品名 | O12: 数量 | P12: 金额
A26: 三、审计说明：
A30: 四、审计结论：

Sheet 出口收入电子口岸系统核对D4-16
A1: 致同会计师事务所
A2: 出口收入电子口岸系统检查
A3: =[13]底稿目录!A2 -> 被审计单位： | E3: =[13]底稿目录!A4 -> 编制人： | H3: =[13]底稿目录!A5 -> 编制日期： | J3: 索引号： | K3: =[13]底稿目录!F6 -> D4-16
A4: =[13]底稿目录!A3 -> 会计期间：202X年度 | E4: =[13]底稿目录!A6 -> 复核人： | H4: =[13]底稿目录!A7 -> 复核日期： | J4: 页 次：
A5: 一、审计目标：
A6: 1.利润表中记录的营业收入已发生，且与被审计单位有关；2.与营业收入有关的金额及其他数据已恰当记录，相关披露已得到恰当计量和描述；
A7: 3.与营业收入有关的交易和事项已记录于正确的会计期间。
A8: 二、审计过程：
A9: 1.……
A11: 账面出口收入金额 | B11: 电子口岸系统 | G11: 免抵退税申报数据
B12: 期间 | C12: 结关金额 | D12: 差异 | E12: 原因 | F12: 索引 | G12: 期间 | H12: 申报外销收入 | I12: 差异 | J12: 原因 | K12: 索引
D13: =C13-A13 -> 0 | I13: =H13-F13 -> 0
A16: 三、审计说明：
A20: 四、审计结论：

Sheet 营业收入截止测试（账到单据）D4-17
A1: 致同会计师事务所
A2: 营业收入截止测试（账到单据）
A3: =[13]底稿目录!A2 -> 被审计单位： | D3: =[13]底稿目录!A4 -> 编制人： | G3: =[13]底稿目录!A5 -> 编制日期： | J3: 索引号： | K3: =[13]底稿目录!F7 -> D4-17
A4: =[13]底稿目录!A3 -> 会计期间：202X年度 | D4: =[13]底稿目录!A6 -> 复核人： | G4: =[13]底稿目录!A7 -> 复核日期： | J4: 页次：
A5: 一、审计目标
A6: 确认与营业收入有关事项已记录于正确的会计期间。
A7: 二、审计过程
A8: 1.获取报表日前（______）天、后（______）天，且金额大于______元收入记账凭证与发货单（或验收单、出库单等）核对确认收入是否记入了恰当的期间；
A9: 2.……
A10: 提示：如果存在跨期舞弊风险或者所检查样本中发现有跨期的，应扩大测试期间和样本，甚至可以考虑将截止测试期间延长至审计报告日。同时考虑是否存在内控缺陷。
A11: 记账凭证 | F11: 发货单 | K11: 是否跨期
A12: 日期 | B12: 编号 | C12: 品名 | D12: 数量 | E12: 金额 | F12: 日期 | G12: 编号 | H12: 品名 | I12: 数量 | J12: 金额 | K12: √（×）
A24: 截止日期：202X年12月31日
A36: 三、审计说明
A40: 四、审计结论
A42: 提示1：本表适用于对“以发货单为确认收入时点”的被审计单位的截止测试，项目组在使用模板时，请根据企业的收入确认政策修改或调整。
A43: 提示2：如果存在跨期舞弊风险或者所检查样本中发现有跨期的，应扩大测试期间和样本，考虑将截止测试期间延长至审计报告日。同时考虑是否存在内控缺陷。

Sheet 营业收入截止测试（单据到账）D4-18
A1: 致同会计师事务所
A2: 营业收入截止测试（单据到账）
A3: =[13]底稿目录!A2 -> 被审计单位： | D3: =[13]底稿目录!A4 -> 编制人： | G3: =[13]底稿目录!A5 -> 编制日期： | J3: 索引号： | K3: =[13]底稿目录!F8 -> D4-18
A4: =[13]底稿目录!A3 -> 会计期间：202X年度 | D4: =[13]底稿目录!A6 -> 复核人： | G4: =[13]底稿目录!A7 -> 复核日期： | J4: 页次：
A5: 一、审计目标
A6: 确认与营业收入有关事项已记录于正确的会计期间。
A7: 二、审计过程
A8: 1.获取报表日前（______）天、后（______）天，且金额大于______元发货单（或验收单、出库单等）与收入记账凭证核对确认收入是否记入了恰当的期间；
A9: 2.……
A10: 提示：如果存在跨期舞弊风险或者所检查样本中发现有跨期的，应扩大测试期间和样本，甚至可以考虑将截止测试期间延长至审计报告日。同时考虑是否存在内控缺陷。
A11: 发货单 | F11: 记账凭证 | K11: 是否跨期
A12: 日期 | B12: 编号 | C12: 品名 | D12: 数量 | E12: 金额 | F12: 日期 | G12: 编号 | H12: 品名 | I12: 数量 | J12: 金额 | K12: √（×）
A24: 截止日期：202X年12月31日
A36: 三、审计说明
A40: 四、审计结论
A42: 提示1：本表适用于对“以发货单为确认收入时点”的被审计单位的截止测试，项目组在使用模板时，请根据企业的收入确认政策修改或调整。
A43: 提示2：如果存在跨期舞弊风险或者所检查样本中发现有跨期的，应扩大测试期间和样本，考虑将截止测试期间延长至审计报告日。同时考虑是否存在内控缺陷。

Sheet 销售折扣与折让检查D4-19
A1: 致同会计师事务所
A2: 销售折扣与折让检查
A3: =[13]底稿目录!A2 -> 被审计单位： | E3: =[13]底稿目录!A4 -> 编制人： | I3: =[13]底稿目录!A5 -> 编制日期： | N3: 索引号： | O3: =[13]底稿目录!F9 -> D4-19
A4: =[13]底稿目录!A3 -> 会计期间：202X年度 | E4: =[13]底稿目录!A6 -> 复核人： | I4: =[13]底稿目录!A7 -> 复核日期： | N4: 页 次：
A5: 一、审计目标
A6: 与营业收入有关的金额及其他数据已恰当记录，相关披露已得到恰当计量和描述。
A7: 二、审计过程
A8: 1.取得被审计单位经授权批准的有关折扣与折让的规定和文件资料，检查发生的折扣或折让是否符合相关规定并经授权批准。
A9: 2.……
A11: 客户名称 | B11: 折扣或折让类型 | C11: 收入金额 | D11: 折扣或折让金额 | E11: 折扣或折让比例 | F11: 折扣或折让 原因 | G11: 记账凭证 | M11: 审批单 | O11: 备注
G12: 日期 | H12: 编号 | I12: 会计科目 | J12: 明细科目 | K12: 借方金额 | L12: 贷方金额 | M12: 日期 | N12: 审批人
P13: 价格折扣
P14: 现金折扣
P15: 实物返利
P16: 销售折让
A24: 三、审计说明
A28: 四、审计结论
A30: 提示：企业应当基于返利的形式和合同条款的约定，考虑相关条款安排是否会导致企业未来需要向客户提供可明确区分的商品或服务，在此基础上判断相关返利属于可变对价还是提供给客户的重大权利。一般而言，对基于客户采购情况等给予的现金返利，企业应当按照可变对价原则进行会计处理；对基于客户一定采购数量的实物返利或仅适用于未来采购的价格折扣，企业应当按照附有额外购买选择权的销售进行会计处理，评估该返利是否构成一项重大权利，以确定是否将其作为单项履约义务并分摊交易对价。《监管规则适用指引—会计类第2号》

Sheet 销售退货检查表 D4-20
A1: 致同会计师事务所
A2: 销售退货检查表
A3: =[13]底稿目录!A2 -> 被审计单位： | F3: =[13]底稿目录!A4 -> 编制人： | J3: =[13]底稿目录!A5 -> 编制日期： | N3: 索引号： | O3: =[13]底稿目录!F10 -> D4-20
A4: =[13]底稿目录!A3 -> 会计期间：202X年度 | F4: =[13]底稿目录!A6 -> 复核人： | J4: =[13]底稿目录!A7 -> 复核日期： | N4: 页次：
A5: 一、审计目标:
A6: 确认与营业收入有关事项已记录于正确的会计期间。
A7: 二、审计过程：
A8: 1.产品退货政策
A11: 2.退货总体情况
A12: 本期退货金额 元，占本期销售收入的 %。按照客户类别/客户性质/产品类别分类统计如下：
A13: 分类 | B13: 本年度 | E13: 上年度
B14: 退货金额 | C14: 收入金额 | D14: 比例 | E14: 退货金额 | F14: 收入金额 | G14: 比例
A15: 贸易商 | D15: =B15/C15 -> #DIV/0! | G15: =E15/F15 -> #DIV/0!
A16: 终端用户 | D16: =B16/C16 -> #DIV/0! | G16: =E16/F16 -> #DIV/0!
A17: 合计 | B17: =B16+B15 -> 0 | C17: =C16+C15 -> 0 | D17: =B17/C17 -> #DIV/0! | E17: =E16+E15 -> 0 | F17: =F16+F15 -> 0 | G17: =E17/F17 -> #DIV/0!
A19: 3.评估产品退货计提比例是否合理
A20: （1)历史退货情况
A22: （2）……
A23: 4.重新测算产品退货金额
A24: 产品名称 | B24: 计提基数 | C24: 计提比例 | D24: 应计提金额 | E24: 账面已计提金额 | F24: 差异金额 | G24: 差异原因
D25: =B25*C25 -> 0
D26: =B26*C26 -> 0
D27: =B27*C27 -> 0
D28: =B28*C28 -> 0
D29: =B29*C29 -> 0
A31: 5.检查本期产品退货情况
A32: 记账凭证 | H32: 退货单 | M32: 是否涉及诉讼 | N32: 是否异常 | O32: 索引号
A33: 日期 | B33: 编号 | C33: 业务内容 | D33: 科目名称 | E33: 二级明细 | F33: 借方金额 | G33: 贷方金额 | H33: 客户名称 | I33: 产品名称 | J33: 退货数量 | K33: 退货金额 | L33: 退货原因
A37: 6.检查期后产品退货情况
A38: 记账凭证 | H38: 退货单 | M38: 是否涉及诉讼 | N38: 是否异常 | O38: 索引号
A39: 日期 | B39: 编号 | C39: 业务内容 | D39: 科目名称 | E39: 二级明细 | F39: 借方金额 | G39: 贷方金额 | H39: 客户名称 | I39: 产品名称 | J39: 退货数量 | K39: 退货金额 | L39: 退货原因
A43: 检查内容说明：
A44: （1）销售退回的原因及合理性判断：
A45: （2）销售退回审批手续是否完备；
A46: （3）相应的主营业务成本是否结转；
A47: （4）退货会计处理是否正确；
A48: （5）是否涉及跨期；
A49: 三、审计说明：
A53: 四、审计结论：

Sheet 关联方销售情况及价格分析D4-21
A1: 致同会计师事务所
A2: 关联方销售收入情况及价格公允性分析
A3: =[11]底稿目录!$A$2 -> 被审计单位： | E3: =[11]底稿目录!$A$4 -> 编制人： | H3: =[11]底稿目录!$A$5 -> 编制日期： | M3: 索引号： | N3: D4-21
A4: =[11]底稿目录!$A$3 -> 会计期间：202X年度 | E4: =[11]底稿目录!$A$6 -> 复核人： | H4: =[11]底稿目录!$A$7 -> 复核日期： | M4: 页 次：
A5: 一、审计目标：
A6: 1.利润表中记录的营业收入已发生，且与被审计单位有关，已记录于恰当的账户。2.所有应当记录的营业收入均已记录，所有应当包括在财务报表中的相关披露均已包括。
A7: 3.与营业收入有关的金额及其他数据已恰当记录，相关披露已得到恰当计量和描述。
A8: 二、审计过程：
A9: 1.调查及标明向关联方销售的情况及，记录其交易品种、价格、数量、金额和比例，并记录占总销售收入的比例。
A10: 2.确定已取得关联方交易披露数据及确定跟关联交易工作底稿相符。
A11: 3.获取关联方交易定价政策，检查定价公允性。
A12: 4.比较关联方交易主要产品价格与同类产品非关联方销售平均单价、可比公允价值的差异，分析合理性。
A13: 5.……
A14: 202X年：
A15: 关联方客户名称 | B15: 关联关系 | C15: 产品名称 | D15: 销售数量 | E15: 销售额 | F15: 销售额占同类产品销售额比例 | G15: 平均单价 | H15: 非关联方销售平均单价 | I15: 差异率 | J15: 可比公允价格 | K15: 差异率 | L15: 上年度销售额占同类产品销售额比例 | M15: 上年度销售平均单价 | N15: 备注
I16: =(G16-H16)/H16 -> #DIV/0! | K16: =(G16-J16)/J16 -> #DIV/0! | O16: 勿删、勿改
I17: =(G17-H17)/H17 -> #DIV/0! | K17: =(G17-J17)/J17 -> #DIV/0! | O17: 实际控制人
I18: =(G18-H18)/H18 -> #DIV/0! | K18: =(G18-J18)/J18 -> #DIV/0! | O18: 控股股东
I19: =(G19-H19)/H19 -> #DIV/0! | K19: =(G19-J19)/J19 -> #DIV/0! | O19: 控股股东、实际控制人的附属企业
I20: =(G20-H20)/H20 -> #DIV/0! | K20: =(G20-J20)/J20 -> #DIV/0! | O20: 持有5%以上股份的法人或其他组织
I21: =(G21-H21)/H21 -> #DIV/0! | K21: =(G21-J21)/J21 -> #DIV/0! | O21: 联营企业
I22: =(G22-H22)/H22 -> #DIV/0! | K22: =(G22-J22)/J22 -> #DIV/0! | O22: 合营企业
I23: =(G23-H23)/H23 -> #DIV/0! | K23: =(G23-J23)/J23 -> #DIV/0! | O23: 董高监等关键管理人员
I24: =(G24-H24)/H24 -> #DIV/0! | K24: =(G24-J24)/J24 -> #DIV/0! | O24: 其他关联方
I25: =(G25-H25)/H25 -> #DIV/0! | K25: =(G25-J25)/J25 -> #DIV/0!
I26: =(G26-H26)/H26 -> #DIV/0! | K26: =(G26-J26)/J26 -> #DIV/0!
I27: =(G27-H27)/H27 -> #DIV/0! | K27: =(G27-J27)/J27 -> #DIV/0!
I28: =(G28-H28)/H28 -> #DIV/0! | K28: =(G28-J28)/J28 -> #DIV/0!
I29: =(G29-H29)/H29 -> #DIV/0! | K29: =(G29-J29)/J29 -> #DIV/0!
I30: =(G30-H30)/H30 -> #DIV/0! | K30: =(G30-J30)/J30 -> #DIV/0!
A31: 三、审计说明：
A34: 四、审计结论：

Sheet 底稿目录 (4)
A1: 底稿开列时，可先在以下单元格填写有关内容，以便其他底稿引用有关数据：
A2: 被审计单位名称： | D2: 序号 | E2: 内容 | F2: 索引号
A3: 会计期间：202X年度 | D3: 1 | E3: 营业收入实质性程序表 | F3: D4-22A
A4: 编制人： | D4: 2 | E4: 重要指标分析 | F4: D4-22
A5: 编制日期： | D5: 3 | E5: 收入与开具发票金额比较分析 | F5: D4-23
A6: 复核人： | D6: 4 | E6: 第三方回款检查 | F6: D4-24
A7: 复核日期： | D7: 5 | E7: 经销商检查 | F7: D4-25
D8: 6 | E8: 境外销售收入检查 | F8: D4-26
D9: 7 | E9: 函证结果汇总表 | F9: D0-1
D10: 8 | E10: 核实被函证单位信息 | F10: D0-2
A11: 关于工作底稿与审计程序索引号对应的说明 | D11: 9 | E11: 跟函函证过程控制 | F11: D0-3
A12: 1.编制的审计工作底稿应与审计程序对应。审计项目组应根据被审计单位实际情况和风险评估情况在实质性程序表中裁剪、修改或增加审计程序，根据实际执行的审计程序完成相应审计工作底稿，编制的工作底稿中应按自然顺序依次编制索引号，并通过唯一的索引号将与实质性程序表中的程序对应关联（即将工作底稿的索引号填入实质性程序表中的底稿索引号列）。 | D12: 10 | E12: 函证差异调节表 | F12: D0-4
D13: 11 | E13: 合同负债及销售替代程序检查表 | F13: D0-5
D14: 12 | E14: 应收及销售替代程序检查表 | F14: D0-6
D15: 13 | E15: 邮件传真回函可靠性验证 | F15: D0-7
A16: 2.获取的支持性证据应与审计底稿或程序对应。审计项目组在完成底稿时获取的支持性证据应根据底稿索引号编制下一级按自然顺序排序的索引号（如D1-2-1、D1-2-2、……），并在底稿中说明引用的支持性证据、关联索引号。 | D16: 14 | E16: 函证程序舞弊风险评价表 | F16: D0-8
D17: 15 | E17: 识别未披露关联方 | F17: D4-27
D18: 16 | E18: 客户信息核查清单 | F18: D4-28
A19: 3.工作底稿索引号的编码规则：实质性程序索引号按循环从“D”到“N”,循环内账户以顺序号排列，模板中底稿索引号按账户顺序+自然数顺序（即模板中索引号按二级自然顺序排列，如D1-1、D1-2、D1-3、……D1-N）。 | D19: 17 | E19: 客户信息检查表 | F19: D4-29
D20: 18 | E20: 客户访谈记录汇总表 | F20: D4-30
D21: 19 | E21: 客户访谈记录 | F21: D4-31
D22: 20 | E22: 客户、供应商等资金流水检查 | F22: D4-32

Sheet 程序表D4-22A
A1: 致同会计师事务所
A2: 营业收入实质性程序表
A3: =[16]底稿目录!A2 -> 被审计单位名称： | D3: =[16]底稿目录!A4 -> 编制人： | G3: =[16]底稿目录!A5 -> 编制日期： | I3: 索引号： | J3: =[16]底稿目录!F3 -> D4-22A
A4: =[16]底稿目录!A3 -> 会计期间：202X年度 | D4: =[16]底稿目录!A6 -> 复核人： | G4: =[16]底稿目录!A7 -> 复核日期： | I4: 页次：
A5: 一、本账户涉及的科目
A6: 主营业务收入、其他业务收入
A7: 二、审计目标和财务报表的认定
A8: 审计目标 | H8: 财务报表的认定
A9: A.利润表中记录的营业收入已发生，且与被审计单位有关，已记录于恰当的账户 | H9: 发生
A10: B.所有应当记录的营业收入均已记录，所有应当包括在财务报表中的相关披露均已包括 | H10: 完整性
A11: C.与营业收入有关的金额及其他数据已恰当记录，相关披露已得到恰当计量和描述 | H11: 准确性
A12: D.与营业收入有关的交易和事项已记录于正确的会计期间 | H12: 截止性
A13: E.营业收入已被恰当地汇总或分解且表述清楚，相关披露在按照企业会计准则的编制基础下是相关的、可理解的 | H13: 列报
A14: 三、计划实施的实质性程序
A15: 序号 | B15: 对应Leap程序 | C15: 审计程序 | D15: 程序分类 | E15: 财务报表认定 | J15: 底稿索引号
E16: 发生 | F16: 完整性 | G16: 准确性 | H16: 截止性 | I16: 列报 | K16: 根据被审计单位实际情况和风险评估情况裁剪、修改或增加审计程序
A17: 1 | C17: 对于通过电子方式自动生成、处理、记录的销售交易,必要时，考虑利用信息系统审计专家的工作。 | D17: IPO/上市/新三板/重组/舞弊应对 | E17: √ | F17: √ | G17: √ | H17: √
A18: 2 | B18: 应对措施-实质性分析 | C18: 分析性程序： （1）结合被审计单位业务特点和其主要客户基本经营信息，分析其客户购买力、结构变化和销售波动情况，是否存在客户异常采购的情况；与其客户信息披露核对（如适用）。 （2）结合存货底稿分析销售收入等财务信息与投入产出率、劳动生产率、产能、水电能耗、运输数量等非财务信息之间的关系。 （3）获取年度预算资料，比较收入金额与年度预算是否存在重大差异，如果发现被审计单位的收入增长幅度明显高于管理层的预期，可以询问管理层的适当人员，并考虑管理层的答复是否与其他审计证据一致。例如，如果管理层表示收入增长是由于销售量增加所致，可以调查与市场需求相关的情况。 （4）将销售收入变动幅度与销售商品及提供劳务收到的现金、应收账款/合同资产、存货、税金等项目的变动幅度进行比较，分析具体原因。 （5）将人均创收金额等指标与同行业及行业领军企业比较是否存在异常，如果被审计单位人均创收超过行业领军企业，应保持警觉，考虑获取的审计证据是否能够支持。 （6）了解期末在手订单情况，分析销售与采购是否配比，以及重要客户大量采购的原因、最终销售情况、终端客户同经销商地域的匹配性。 （7）分析销售收入与销售费用之间的关系，包括销售人员的人均业绩指标、销售人员薪酬、广告费、差旅费，以及销售机构的设置、规模、数量、分布等。 （8）根据增值税发票申报表或普通发票，估算全年收入，与实际收入金额比较。 | D18: IPO/上市/新三板/重组/舞弊应对 | E18: √ | F18: √ | G18: √ | J18: F2-63 /D4-22 /D4-23
A19: 3 | B19: 应对措施-检查 | C19: 对重要客户的货款回收进行检查,关注是否存在第三方回款情况,例如通过第三方账户，包括员工账户和其他个人账户回款，通过保理公司回款的情况。如果存在第三方回款，应获取并检查第三方代付协议，分析第三方回款的必要性和合理性。检查第三方与被审计单位及客户之间是否存在关联关系。必要时，向第三方函证。 | D19: IPO/上市/新三板/重组/舞弊应对 | E19: √ | G19: √ | J19: D4-24
A20: 4 | B20: 应对措施-检查 | C20: 如果被审计单位采用经销商的销售模式，需要关注： （1）检查被审计单位与经销商之间的协议或合同以及实际执行情况，确定与经销商是否为委托代理的关系，对经销商销售收入确认时点是否符合企业会计准则的规定； （2）关注主要的经销商与被审计单位之间是否存在关联方关系，检查出库单、货运单、商品验收单等相关支持性凭证，以确定是否满足收入确认的条件； （3）关注经销商布局的合理性、被审计单位频繁发生经销商加入和退出的情况，以及被审计单位对不稳定经销商的收入确认是否适当、退换货损失的处理是否适当、经销商最终销售情况等； （4）对经销商为委托代理销售的模式，检查被审计单位收入确认是否有代理商的销售清单、货物最终销售证明等支持性凭据。 | D20: IPO/上市/新三板/重组/舞弊应对 | E20: √ | F20: √ | G20: √ | H20: √ | J20: D4-14 /D4-25 /D4-
A21: 5 | B21: 应对措施-检查 | C21: 对境外销售收入，检查向主要国家和地区销售的金额、境外收入占比、结算模式等，不同贸易模式下的收入确认是否符合企业会计准则的规定，关注是否存在第三方回款、是否执行了核查、函证、现场走访等程序。 | D21: IPO/上市/新三板/重组/舞弊应对 | E21: √ | G21: √ | H21: √ | J21: D4-26
A22: 6 | B22: 应对措施-检查 | C22: 如果应收账款、合同资产增长比例高于销售收入的增长比例，考虑扩大函证比例、增加截止测试和期后收款测试的比例、使用与前期不同的抽样方法、实地走访客户等。 | D22: IPO/上市/新三板/重组/舞弊应对 | E22: √ | F22: √ | G22: √
A23: 7 | B23: 应对措施-检查 | C23: 对比历年主要客户清单，找出报告期新增的主要客户、原有主要客户交易额大幅减少或合作关系取消的情况，重点关注变化原因。关注会计期末是否存在突击确认销售以及期后是否存在大量销售退回的情况 | D23: IPO/上市/新三板/重组/舞弊应对 | E23: √ | H23: √
A24: 8 | B24: 应对措施-函证 | C24: 结合应收账款审计，选择主要客户、异常客户收入等执行函证程序。 | D24: IPO/上市/新三板/重组/舞弊应对 | E24: √ | F24: √ | G24: √ | H24: √ | J24: D4-0
A25: 9 | B25: 常规程序(选择“存在重大合同”) | C25: 向被审计单位的客户函证相关的特定合同条款以及是否存在背后协议。相关的会计处理是否适当，往往会受到这些合同条款或协议的影响。例如，商品接受标准、交货与付款条件、不承担期后或持续性的卖方义务、退货权、保证转售金额以及撤销或退款等条款在此种情形下通常是相关的。 | D25: IPO/上市/新三板/重组/舞弊应对 | E25: √ | G25: √
A26: 10 | B26: 应对措施-检查 | C26: 如果被审计单位存在特殊交易模式或创新交易模式，分析其对交易经济实质和收入确认的影响。 | D26: IPO/上市/新三板/重组/舞弊应对 | E26: √
A27: 11 | B27: 常规程序（选择“存在超过被审计单位正常经营范围的交易”） | C27: 考虑大额或异常的交易是否表明存在一个先前没有披露的关联方： （1）查询客户工商、银行、税务信息资料，关注其地址、董事/监事/关键管理人员、联系方式等信息，并与其相关发票信息、网站信息进行核对，识别客户是否存在与被审计单位存在疑似关联关系的信息； （2）选取重要客户，获取关联方关系确认函； （3）取得实际控制人、董高监及其密切家庭人员的对外投资清单，与重要客户的股东和关键经办人员进行比对，关注与发行人实际控制人、董事、监事、高级管理人员关系密切的家庭成员与发行人的客户是否存在关联方关系； （4）取得保荐机构及其关联方、PE投资机构及其关联方、PE投资机构的股东或实际控制人控制或投资的其他企业清单，将这些利益相关方清单和重要客户及其法人、股东和关键经办人员名单进行比对，关注其是否与发行人发生大额交易从而导致发行人在报告期内收入、利润出现较大幅度增长； （5）获取发行人主要股东、董事、监事、关键管理人员及上述利益相关方的确认函，确认除其本人在被审计单位领取薪酬或分得股利外，其本人及其关系密切的家庭成员未与被审计单位有任何形式的交易。 | D27: IPO/上市/新三板/重组/舞弊应对 | E27: √ | G27: √ | H27: √ | I27: √ | J27: D4-27 /D4-29 /D4-
A28: 12 | B28: 应对措施-检查 | C28: 如果存在被审计单位关联方注销及非关联化的情况，需要关注被审计单位将原关联方非关联化行为的动机及后续交易的真实性、公允性。 | D28: IPO/上市/新三板/重组/舞弊应对 | E28: √ | G28: √
A29: 13 | B29: 应对措施-检查 | C29: 结合出库单及销售费用中的运输费等明细，检查货物运输单和提单，必要时向运输单位进行函证或走访，关注货物的流动是否真实发生，从而确定交易的真实性。 | D29: IPO/上市/新三板/重组/舞弊应对 | E29: √
A30: 14 | B30: 应对措施-检查 | C30: 期末在被审计单位的一处或多处发货现场实地观察发货情况或准备发出的商品情况（或待处理的退货），并结合所了解的情况实施适当的销售及存货截止测试。 | D30: IPO/上市/新三板/重组/舞弊应对 | E30: √ | H30: √
A31: 15 | B31: 应对措施-检查 | C31: 关注临近期末的大额销售、退货、调整等情况： （1）向被审计单位负责销售和市场开发的人员询问临近期末的销售或发货情况，向被审计单位内部法律顾问询问临近期末签订的销售合同是否存在异常的合同条款或条件； （2）检查临近期末执行的重要销售合同，以发现是否存在异常的定价、结算、发货、退货、换货或验收条款。对期后实施特定的检查，以发现是否存在改变或撤销合同条款的情况，以及是否存在退款的情况； （3）详细复核被审计单位在临近期末以及期后编制的调整分录，调查性质或金额异常的项目。 | D31: IPO/上市/新三板/重组/舞弊应对 | E31: √ | H31: √
A32: 16 | B32: 应对措施-检查 | C32: 结合存货、固定资产、无形资产循环审计，分析客户、供应商名单以及应收、应付等往来明细，检查是否针对同一对方单位或存在关联关系的对方单位同时存在销售、采购的情况，是否有合理的商业理由，关注是否存在第三方配合舞弊的情形。 | D32: IPO/上市/新三板/重组/舞弊应对 | E32: √ | G32: √ | H32: √
A33: 17 | B33: 应对措施-检查（检查程序中选择是否执行延伸检查） | C33: 如果识别出被审计单位收入真实性存在重大异常情况，且通过常规审计程序无法获取充分、适当的审计证据时，考虑实施“延伸检查”程序，可以实施的“延伸检查”程序包括不限于： （1）利用企业信息查询工具查询公司注册资本、地址、成立时间、经营范围、法定代表人、股东、最终控制人等，了解公司经营范围，判断客户所购产品是否具有合理用途、是否存在关联关系、向客户销售金额是否与客户规模匹配等。 （2）现场走访客户的办公场所、经营场所，访谈客户关键经办人员，或电话访谈关键经办人员。核实被访谈对象对象身份的真实性和适当性，根据实际情况设计访谈计划和访谈提纲，观察对方生产经营情况，判断其与被审计单位之间的交易规模是否和其生产经营规模匹配； （3）了解相关客户向被审计单位进行采购的商业理由、采购被审计单位商品的用途和去向、是否存在销售给被审计单位指定单位的情况、客户与被审计单位是否存在除购销交易以外的资金往来、了解客户从被审计单位采购的商品的生产、库存情况等，必要时进行实地察看。 （4）在采用经销模式的情况下，关注经销商库存量是否存在明显不合理，检查经销商进销存记录、经销商的最终销售实现情况。 （5）当注意到可能存在关联方（例如被审计单位控股股东、实际控制人、关键管理人员）或者第三方客户配合被审计单位虚构收入的迹象时，考虑获取并检查相关关联方或者客户的银行账户资金流水，关注是否存在与被审计单位相关供应商、客户或关联方的异常资金往来；考虑获取其下游客户的订单、对其下游客户进行实地走访等。 | D33: IPO/上市/新三板/重组/舞弊应对 | E33: √ | F33: √ | G33: √ | H33: √ | J33: D4-28 /D4-29 /D4-30 /D4-31 /D4-32
A34: 18 | C34: 根据评估的舞弊风险等因素增加的审计程序。 | D34: IPO/上市/新三板/重组/舞弊应对
A35: 提示：注册会计师在判断是否需要实施“延伸检查”程序及如何实施时，应当根据审计准则的规定，并考虑有经验的专业人士在该场景下通常会作出的合理职业判断。《中国注册会计师审计准则第 1131 号——审计工作底稿》对“有经验的专业人士”进行了定义。此外，实施“延伸检查”程序的可行性和效果受诸多因素影响，注册会计师设计的具体“延伸检查”程序的性质、时间安排和范围，应当针对被审计单位的具体况，与评估的舞弊风险相称，并体现重要性原则。例如，被审计单位所处行业的下游产业链较长，如果对下游产业链的某个或某几个环节实施“延伸检查”程序获取的审计证据，可以应对与收入确认相关的舞弊风险，则“延伸检查”程序无需覆盖所有环节。再者，相对于常规年度财务报表审计而言，在首次公开发行股票并上市审计（IPO 审计）中，由于存在监管要求和相关方的配合，注册会计师实施“延伸检查”程序通常相对可行。

Sheet 重要指标分析表D4-22
A1: 致同会计师事务所
A2: 主营业务收入重要指标分析表
A3: =[16]底稿目录!A2 -> 被审计单位名称： | C3: =[16]底稿目录!$A$4 -> 编制人： | E3: =[16]底稿目录!$A$5 -> 编制日期： | G3: 索引号： | H3: =[16]底稿目录!F4 -> D4-22
A4: =[16]底稿目录!A3 -> 会计期间：202X年度 | C4: =[16]底稿目录!$A$6 -> 复核人： | E4: =[16]底稿目录!$A$7 -> 复核日期： | G4: 页 次：
A5: 一、审计目标
A6: 1.利润表中记录的主营业务收入已发生，且与被审计单位有关；2.所有应当记录的营业收入均已记录；
A7: 3.与主营业务收入有关的金额及其他数据已恰当记录，相关披露已得到恰当计量和描述。
A8: 二、审计过程
A9: 1.向被审计单位询问，并获取年度预算、业绩考核指标等资料。
A11: 指标名称 | B11: 本期 | C11: 上期 | D11: 同行业公司1 | E11: 同行业公司2 | F11: 同行业公司3 | G11: …… | H11: 合理性分析
A12: 年度预算
A13: 主营业务收入
A14: 销售人员数量
A15: 销售人员人均创收
A16: 销售区域分布是否变化（占比和区域数量等）
A17: 销售人员业绩指标
A18: 销售人员薪酬
A19: 期末在手订单
A20: 息税前利润（利润总额＋财务费用）
A21: 薪酬总额（支付给职工以及为职工支付的现金+期末应付职工薪酬-期初应付职工薪酬）
A22: 人力投入回报率(ROP)
A23: 运输费用/营业收入
... A28: 四、审计结论

Sheet 收入与开具发票金额比较分析D4-23
A1: 致同会计师事务所
A2: 收入与开具发票金额比较分析
A3: =[16]底稿目录!A2 -> 被审计单位名称： | D3: =[16]底稿目录!$A$4 -> 编制人： | G3: =[16]底稿目录!$A$5 -> 编制日期： | J3: 索引号： | K3: =[16]底稿目录!F5 -> D4-23
A4: =[16]底稿目录!A3 -> 会计期间：202X年度 | D4: =[16]底稿目录!$A$6 -> 复核人： | G4: =[16]底稿目录!$A$7 -> 复核日期： | J4: 页次：
A5: 一、审计目标：
A7: 二、审计过程：
A8: 1.……
A10: 月份 | B10: 本期账面确认收入 | E10: 本期开具发票的金额
B11: 主营业务收入 | C11: 其他业务收入 | D11: 营业收入合计 | E11: 增值税发票金额 | F11: 防伪税控开具的增值税发票份数 | G11: 普通发票金额 | H11: 开具的普通发票份数 | I11: 申报的开票金额合计 | J11: 差异 | K11: 索引号
A12: 1月 | D12: =B12+C12 -> 0 | I12: =E12+G12 -> 0 | J12: =D12-I12 -> 0
A13: 2月 | D13: =B13+C13 -> 0 | I13: =E13+G13 -> 0 | J13: =D13-I13 -> 0
A14: 3月 | D14: =B14+C14 -> 0 | I14: =E14+G14 -> 0 | J14: =D14-I14 -> 0
A15: 4月 | D15: =B15+C15 -> 0 | I15: =E15+G15 -> 0 | J15: =D15-I15 -> 0
A16: 5月 | D16: =B16+C16 -> 0 | I16: =E16+G16 -> 0 | J16: =D16-I16 -> 0
A17: 6月 | D17: =B17+C17 -> 0 | I17: =E17+G17 -> 0 | J17: =D17-I17 -> 0
A18: 7月 | D18: =B18+C18 -> 0 | I18: =E18+G18 -> 0 | J18: =D18-I18 -> 0
A19: 8月 | D19: =B19+C19 -> 0 | I19: =E19+G19 -> 0 | J19: =D19-I19 -> 0
A20: 9月 | D20: =B20+C20 -> 0 | I20: =E20+G20 -> 0 | J20: =D20-I20 -> 0
A21: 10月 | D21: =B21+C21 -> 0 | I21: =E21+G21 -> 0 | J21: =D21-I21 -> 0
A22: 11月 | D22: =B22+C22 -> 0 | I22: =E22+G22 -> 0 | J22: =D22-I22 -> 0
A23: 12月 | D23: =B23+C23 -> 0 | I23: =E23+G23 -> 0 | J23: =D23-I23 -> 0
A24: 合计 | B24: =SUM(B12:B23) -> 0 | C24: =SUM(C12:C23) -> 0 | D24: =SUM(D12:D23) -> 0 | E24: =SUM(E12:E23) -> 0 | F24: =SUM(F12:F23) -> 0 | G24: =SUM(G12:G23) -> 0 | H24: =SUM(H12:H23) -> 0 | I24: =SUM(I12:I23) -> 0 | J24: =SUM(J12:J23) -> 0
A25: 三、审计说明：
A29: 四、审计结论：

Sheet 第三方回款检查D4-24
A1: 致同会计师事务所
A2: 第三方回款检查
A3: =[16]底稿目录!A2 -> 被审计单位名称： | D3: =[16]底稿目录!$A$4 -> 编制人： | G3: =[16]底稿目录!A5 -> 编制日期： | L3: 索引号： | M3: =[16]底稿目录!F6 -> D4-24
A4: =[16]底稿目录!A3 -> 会计期间：202X年度 | D4: =[16]底稿目录!$A$6 -> 复核人： | G4: =[16]底稿目录!A7 -> 复核日期： | L4: 页次：
A5: 一、审计目标：
A6: 1.利润表中记录的营业收入已发生，且与被审计单位有关，已记录于恰当的账户。2.与营业收入有关的金额及其他数据已恰当记录，相关披露已得到恰当计量和描述。
A7: 二、审计过程：
A8: 1.向被审计单位管理层了解第三方回款原因，获取代付协议，检查第三方回款合理性；
A9: 2.向第三方回款单位函证；
A10: 3.关注被审计单位涉及第三方回款的销售的资金流、实物流与合同约定及商业实质是否一致
A11: 4.核查被审计单位及其实际控制人、董监高或其他关联方与第三方回款的支付方是否存在关联关系或其他利益安排
A12: 5.对于异常的第三方回款，追查期后资金流向；
A13: 6.……
A14: 序号 | B14: 客户名称 | C14: 本年度销售金额 | D14: 期末应收账款余额 | E14: 本年度第三方回款金额 | F14: 第三方回款方名称 | G14: 第三方回款原因 | H14: 第三方回款方与客户关系 | I14: 第三方回款方与被审计单位关系 | J14: 是否有代付协议 | K14: 是否函证 | L14: 合理性分析 | M14: 索引
A23: 三、审计说明：
A24: 1.第三方回函检查明细详见银行流水双向核对表<E1-31>、应收账款检查表<D2-7>
A27: 四、审计结论：

Sheet 经销商检查D4-25
A1: 致同会计师事务所
A2: 经销商检查
A3: =[16]底稿目录!A2 -> 被审计单位名称： | E3: =[16]底稿目录!A4 -> 编制人： | I3: =[16]底稿目录!A5 -> 编制日期： | L3: 索引号： | M3: =[16]底稿目录!F7 -> D4-25
A4: =[16]底稿目录!A3 -> 会计期间：202X年度 | E4: =[16]底稿目录!A6 -> 复核人： | I4: =[16]底稿目录!A7 -> 复核日期： | L4: 页 次：
A5: 一、审计目标：
A6: 利润表中记录的营业收入已发生，且与被审计单位有关，已记录于恰当的账户。
A7: 二、审计过程：
A8: 1.关注客户基本情况是否同销售规模相匹配；
A9: 2.记录经销商情况（是否关联方、是否非法人、销售费用承担方式、补贴或返利情况）；
A10: 3.……
A11: 序号 | B11: 客户名称 | C11: 经销商 | D11: 本期销售数量 | E11: 本期销售金额 | F11: 占同类交易比例 | G11: 期末应收账款余额 | H11: 是否关联方 | I11: 个人/企业 | J11: 销售费用承担方式 | K11: 补贴或返利 | L11: 终端销售金额 | M11: 备注
A12: 1
A13: 2
A14: 3
A15: 4
A16: 5
A17: 6
A18: 7
A19: 8
A20: 9
A21: 10
A23: 三、审计说明：
A27: 四、审计结论：

Sheet 境外销售收入检查D4-26
A1: 致同会计师事务所
A2: 境外销售收入检查
A3: =[16]底稿目录!A2 -> 被审计单位名称： | G3: =[16]底稿目录!A4 -> 编制人： | L3: =[16]底稿目录!A5 -> 编制日期： | R3: 索引号： | S3: =[16]底稿目录!F8 -> D4-26
A4: =[16]底稿目录!A3 -> 会计期间：202X年度 | G4: =[16]底稿目录!A6 -> 复核人： | L4: =[16]底稿目录!A7 -> 复核日期： | R4: 页次：
A5: 一、审计目标：
A6: 确定对境外销售业务的真实性和交易实质
A7: 二、审计过程：
A8: 1.对主要目的国、主要海外客户以及对应的主要贸易条款、付款方式等进行分析和记录；
A9: 2.记录已执行的海关查询、函证等程序。
A11: 客户名称 | B11: 所在国家/地区 | C11: 产品种类 | D11: 业务模式 （直销客户/经销商） | E11: 本期销售金额 | F11: 占同类交易比例 | G11: 贸易模式 （填EXW/FOB/CIF等） | H11: 主要贸易条款 （与商品控制权转移时点相关的约定） | I11: 出口结算模式 （填汇款/托收/信用证/银行保函等） | J11: 是否存在第三方回款 | K11: 第三方回款原因 | L11: 核查程序确认的销售金额 | M11: 差异 | N11: 差异原因分析 | O11: 相关程序索引 （对已执行的程序表中索引号）
O12: 实地走访 | P12: 交易函证 | Q12: 海关函证 | R12: 核对报关单 | S12: 电子口岸数据查询
A30: 三、审计说明：
A31: 【记录发现的差异或者其他异常交易安排的迹象，以及所执行的应对措施。】
A32: 四、审计结论：

Sheet 识别未披露的关联方D4-27
A1: 致同会计师事务所
A2: 识别未披露的关联方
A3: =[16]底稿目录!A2 -> 被审计单位名称： | H3: =[16]底稿目录!A4 -> 编制人： | O3: =[16]底稿目录!A5 -> 编制日期： | Q3: 索引号： | R3: =[16]底稿目录!F17 -> D4-27
A4: =[16]底稿目录!A3 -> 会计期间：202X年度 | H4: =[16]底稿目录!A6 -> 复核人： | O4: =[16]底稿目录!A7 -> 复核日期： | Q4: 页次：
A5: 一、审计目标：
A6: 主要或异常客户是否与被审计单位存在关联方关系。
A7: 二、审计过程：
A8: 1.选择大额、异常的客户或交易。
A9: 2.查询客户工商、银行、税务信息资料，关注其地址、董事/监事/关键管理人员、联系方式等信息，并与其相关发票信息、网站信息进行核对，识别客户是否存在与被审计单位存在疑似关联关系的信息。
A10: 3.选取重要客户，获取关联方关系确认函。
A11: 4.取得发行人实际控制人、董高监及其密切家庭人员的对外投资清单，与重要客户的股东和关键经办人员进行比对，关注与发行人实际控制人、董事、监事、高级管理人员关系密切的家庭成员与发行人的客户是否存在关联方关系。
A12: 5.取得保荐机构及其关联方、PE投资机构及其关联方、PE投资机构的股东或实际控制人控制或投资的其他企业清单，将这些利益相关方清单和重要客户及其法人、股东和关键经办人员名单进行比对，关注其是否与发行人发生大额交易从而导致发行人在报告期内收入、利润出现较大幅度增长。
A13: 6.获取发行人主要股东、董事、监事、关键管理人员及上述利益相关方的确认函，确认除其本人在被审计单位领取薪酬或分得股利外，其本人及其关系密切的家庭成员未与被审计单位有任何形式的交易。
A14: 序号 | B14: 姓名 | C14: 个人客户 | D14: 客户法人 | E14: 合同签订人 | F14: 高管亲属 | G14: 财务部门 | H14: 管理部门 | I14: 技术部门 | J14: 生产部门 | K14: 营销部门 | L14: … | M14: 总计 | N14: 客户与公司员工或高管或/和亲属重名（Y/N） | O14: 公司股东/高管/亲属/员工 | P14: 20XX年度销售额 | Q14: 说明 | R14: 索引号
A15: 1 | B15: 陈XX | D15: 1 | J15: 1 | M15: =SUM(C15:L15) -> 2 | N15: Y | O15: 公司员工 | P15: 942.91 | Q15: 经销商：AAA公司之法人
A16: 2 | B16: 李YY | C16: 1 | G16: 1 | M16: =SUM(C16:L16) -> 2 | N16: Y | O16: 公司股东 | P16: 557.16
A17: 3
A18: 4
A19: 5
A20: 6
A21: 7
A22: 8
A23: 9
A24: 10
A27: 三、审计说明：
A28: 1.公司的主要股东、高管、股东及高管的家属、公司员工名单见< >，主要概况：
A29: XX公司：高管亲属338；之财务部门65；之管理部门323；之技术部门686；之生产部门1344；之营销部门1165；
A30: 2.客户的法人及关键管理人员概况：
A31: 个人经销商70；副经销商1874；客户法人1697；客户合同签订人39。
A32: 3.对比后，有54个姓名存在重复，涉及127人，其中客户60个；涉及2013年销售额约2.1亿元；
A33: 抽取销售额大于500万的个人客户约11个，涉及27人；涉及2013年销售额约为1.43亿，占2013年总销售额的比例约为67.58%。
A34: 4.获取27人的身份证复印件；对身份证信息的身份证号码、家庭地址，做交叉对比。
A35: 核对未发现身份证号码、登记地址有和公司员工重复的现象。
A36: 四、审计结论：
A37: 未识别出重要客户与公司存在关联方关系。

Sheet 客户信息核查清单D4-28
A1: 致同会计师事务所
A2: 客户信息核查清单
A3: =[16]底稿目录!A2 -> 被审计单位名称： | E3: =[16]底稿目录!A4 -> 编制人： | K3: =[16]底稿目录!A5 -> 编制日期： | N3: 索引号： | O3: =[16]底稿目录!F18 -> D4-28
A4: =[16]底稿目录!A3 -> 会计期间：202X年度 | E4: =[16]底稿目录!A6 -> 复核人： | K4: =[16]底稿目录!A7 -> 复核日期： | N4: 页次：
A5: 一、审计目标：
A6: 润表中记录的营业收入已发生，且与被审计单位有关，已记录于恰当的账户。
A7: 二、审计过程：
A8: 1.核查主要客户及交易真实性，包括调查交易对手背景和商业目的等。
A9: 2.对比历年主要客户清单，找出报告期新增的主要客户、原有主要客户交易额大幅减少或合作关系取消的情况，重点关注变化原因。项目组根据客户集中度和风险情况，抽取报告期各期（___）个客户/项目
A10: 考虑实施包括查询工商资料、互联网查询、电话访谈关键经办人员、实地走访客户等程序，并编制执行结果汇总表。
A12: 序号 | B12: 客户名称 | C12: 选取原因 | D12: 销售金额 | E12: 占总交易 比重 | F12: 应收账款 期末余额 | G12: 占期末余额比重 | H12: 合同负债 期末余额 | I12: 占期末余额比重 | J12: 核查方式（√） | O12: 索引号
J13: 工商资料查询 | K13: 互联网信息查询 | L13: 函证 | M13: 视频、电话访谈 | N13: 实地走访
A14: 1 | B14: 客户1 | C14: 新增主要客户
A15: 2 | B15: 客户2 | C15: 第一大客户
A25: 三、审计说明：
A29: 四、审计结论：

Sheet 客户信息检查表D4-29
A1: 致同会计师事务所
A2: 客户信息检查表
A3: =[16]底稿目录!A2 -> 被审计单位名称： | E3: =[16]底稿目录!A4 -> 编制人： | I3: =[16]底稿目录!A5 -> 编制日期： | L3: 索引号： | M3: =[16]底稿目录!F19 -> D4-29
A4: =[16]底稿目录!A3 -> 会计期间：202X年度 | E4: =[16]底稿目录!A6 -> 复核人： | I4: =[16]底稿目录!A7 -> 复核日期： | L4: 页次：
A5: 一、审计目标：
A6: 润表中记录的营业收入已发生，且与被审计单位有关，已记录于恰当的账户。
A7: 二、审计过程
A8: 1.……
A10: 项目 | C10: 客户1XXX | D10: 客户2XXX | E10: 客户3XXX | F10: 客户4XXX | G10: 客户5XXX | H10: 客户6XXX | I10: 客户7XXX | J10: 客户8XXX | K10: 客户9XXX | L10: 客户10XXX | M10: ……
A11: 统一社会信用代码
A12: 注册地址
A13: 办公地址
A14: 网站地址
A15: 网站IP地址
A16: 企业邮箱
A17: 成立时间
A18: 注册资本/实缴资本
A19: 经营范围
A20: 人员规模/社保缴纳人数
A21: 法定代表人
A22: 股东名称及 持股比例 | B22: 股东1及持股比例
B23: 股东2及持股比例
B24: 股东3及持股比例
B25: 股东4及持股比例
B26: 股东5及持股比例
B27: ……
A28: 关键管理人员 | B28: 董事长
B29: 总经理
B30: ……
A31: 关键经办人员
A34: 实际控制人
A35: 是否为关联方
A36: 是否同时为供应商（含同一实际控制人）
A37: 开始合作时间
A38: 是否长期拖欠款项
A39: 经营状态
A40: 是否列入失信人
A41: 信息来源
A42: 三、审计说明：
A46: 四、审计结论：
A48: 提示：
... A76: （8）第三方拒绝确认注册会计师要求其确认的某些事项。例如，注册会计师要求被审计单位客户确认不存在除销售合同之外的“抽屉协议”，该客户拒绝确认。

Sheet 客户访谈记录汇总表D4-30
A1: 致同会计师事务所（特殊普通合伙）
A2: 客户访谈记录汇总表
A3: =[16]底稿目录!A2 -> 被审计单位名称： | C3: =[16]底稿目录!A4 -> 编制人： | E3: =[16]底稿目录!A5 -> 编制日期： | F3: 索引号： | G3: =[16]底稿目录!F20 -> D4-30
A4: =[16]底稿目录!A3 -> 会计期间：202X年度 | C4: =[16]底稿目录!A6 -> 复核人： | E4: =[16]底稿目录!A7 -> 复核日期： | F4: 页次：
A5: 项目 | B5: 客户1 | C5: 客户2 | D5: 客户3 | E5: 客户4 | F5: 客户5 | G5: 客户6
A6: 访谈时间
A7: 访谈原因 | B7: 发行人第X大客户/本期新增客户/采购价格异常客户/……
A8: 访谈方式 | B8: 实地走访/视频访谈/电话访谈/……
A9: 被访谈公司注册地址
A10: 实地走访公司地址
A11: 接受访谈人员及身份 | B11: 身份信息、职务信息、具体负责的工作等
A12: 参与访谈的审计人员
A13: 参与访谈的其他人员
A14: 访谈人员行程信息 | B14: 车票、机票、住宿发票复印件或照片，住宿酒店照片
A15: 是否现场函证
A16: 访谈关注要点
A17: 合同执行核对情况
A18: 交易金额核对是否一致
A19: 往来余额核对是否一致
A20: ……
A21: 访谈结论
A22: 访谈表索引
A23: 提示1：走访的范围：主要客户（如前十名客户）；新增的主要客户；存在疑虑的重要客户
A24: 提示2：访谈需核对和注意事项
A25: 1.走访地址与注册地址是否一致？不一致的原因是否合理？公司基本情况是否与工商信息查询信息一致？走访的公司地址是否与百度地图等查询走访地址一致？
A26: 2.交易内容是否与走访公司实际业务范围一致？
... A34: 10.保留访谈对象身份证复印件、名片/工牌复印件、与访谈对象合影（厂区门口、仓库、车间等地）、走访公司工作现场照片

Sheet 客户访谈记录 D4-31
A1: 致同会计师事务所
A2: 客户访谈记录
A3: =[16]底稿目录!A2 -> 被审计单位名称： | B3: =[16]底稿目录!A4 -> 编制人： | D3: =[16]底稿目录!A5 -> 编制日期： | F3: 索引号： | G3: =[16]底稿目录!F21 -> D4-31
A4: =[16]底稿目录!A3 -> 会计期间：202X年度 | B4: =[16]底稿目录!A6 -> 复核人： | D4: =[16]底稿目录!A7 -> 复核日期： | F4: 页次：
A5: 访谈对象：
A6: 访谈时间及地点：
A7: 接受访谈人员及职务：
A8: 访谈人：
A9: 访谈内容：【根据被审计单位实际情况、关注的客户主要风险情况修改访谈内容】
A10: 一、接受访谈人介绍，包括姓名、任职的公司、职务、具体负责的工作等
A12: 二、客户的基本情况（附有关部门盖章确认的工商登记证明文件、主体纳税证明等）
A13: 公司名称： | D13: 注册资本：
A14: 成立日期： | D14: 经济性质：
A15: 法定代表人： | D15: 股权结构：
A16: 三、与客户业务情况
A17: 1.客户与发行人的业务关系为 | D17: [ ]客户是终端客户 [ ]客户是经销商(客户) [ ]客户是供应商 [ ]客户既是客户又是供应商 [ ]客户是ABC的关联方
A18: 2.客户与发行人的结算方式
A19: （1）客户向发行人的采购 | D19: [ ] 预付款方式 [ ] 货到付款方式 [ ] 赊销方式 [ ] 预付款方式和赊销方式兼有
A20: （2）客户向发行人的销售 | D20: [ ] 预收款方式 [ ] 货到收款方式 [ ] 赊销方式 [ ] 预收款方式和赊销方式兼有
A21: 3.20XX年度至今客户与发行人交易情况
A22: （1）所有的交易行为是否签订合同 | D22: [ ] 是 [ ] 否
A23: （2）客户向发行人采购产品质量情况（适用客户） | D23: [ ] 良好 [ ]一般 [ ] 产品质量不稳定 [ ] 产品质量差
A24: （3）客户与发行人是否定了约定除质量问题以外的退、换货条款 | D24: [ ]是 [ ]否
A25: （4）20XX年度至今客户与发行人约定了除质量问题以外的退、换货条款，而发生的退换货金额 | D25: [ ] 无 [ ]20万元以下 [ ]20-50万元 [ ]50-100万元 [ ] 100万元以上
A26: （5）客户向发行人采购的产品验收入库情况 | D26: [ ]检验合格后计量入库签收确认收到货物 [ ]直接计量入库签收确认收到货物 [ ]其他方式请描述
A27: （6）客户与发行人的交易是否存在返利的约定 | D27: [ ]是 [ ]否
A28: 如存在返利请说明以下情况：
A29: A.通过何种方式支付返利 | D29: [ ]现金 [ ]其他方式
A30: B.20XX年度至今返利金额 | D30: [ ]10万元以下 [ ]10-50万元 [ ]50-100万元 [ ]100万元以上
A31: （7）客户作为发行人的经销商购买的货物是否已经最终销售(适用经销商) | D31: [ ]是 [ ]否
A32: 4.客户除了上述与被审计单位采购以外，是否还存在其他的资金往来？ | D32: [ ]是 [ ]否
A33: 5.其他重要事项
A34: 四、关联关系情况
A35: 发行人的实际控制人、自然人股东、董事、监事或高管人员及主要关联方是否在客户持有股份（关联方情况详见附表) | D35: [ ]是 [ ]否
A36: 是否担任职务 | D36: [ ]是 [ ]否
A37: 是否和客户有交易 | D37: [ ]是 [ ]否
A39: 附：1.供应商盖章确认的工商登记证明文件、……
A40: 2.跟函回函
A41: 3.XX产品销售明细账、XX产品库存商品明细账
A42: 4.XXX账户资金流水
A43: 参与访谈的各方人员签字：
A44: 接受访谈人员： | C44: 审计人员： | E44: 其他人员：
A46: 日期：
A47: 如果识别出客户存在第三方配合实施财务舞弊的风险，则应要求客户就其向注册会计师提供的资料
A48: 、信息以及作出的陈述的真实性和完整性进行承诺，并加盖供应商公章。（所有被访谈的客户
A49: 可参照执行要求提供承诺并在访谈记录加盖公章）
A50: “本公司向XX会计师事务所提供的信息和资料真实、完整，如存在虚假信息 或重大遗漏，
A51: 本公司愿意承担一切法律责任”。
G53: XXX公司（盖章）
A56: 提示：
A57: 根据《中国注册会计师审计准则问题解答第18号——识别和应对第三方配合实施财务舞弊》，如果已经识别出走访对象存在可能配合被审计单位实施财务舞弊的迹象，
A58: 1.注册会计师需要更有针对性地计划实地走访工作以及设计访谈提纲，安排职业敏感性更强的项目组成员实施实地走访，在访谈前需要注意对访谈信息保密，并考虑在进行实地走访时实施以下程序：
A59: （1）选择多名或不同层级的人员访谈相同或类似问题，进行相互印证。
A60: （2）核实被询问人员是否与被审计单位存在特殊关系，如是否为被审计单位的前员工，或被审计单位的关联方。
A61: （3）对于被审计单位的客户，要求对被审计单位生产的产品实施观察、检查等程序。如相关产品为走访对象的存货，观察其生产经营过程中是否使用该存货，关注相关存货的存放、领用是否为走访对象的真实需要；如相关产品为走访对象的设备，观察设备是否正常使用。
A62: （4）对于被审计单位的经销商客户，关注走访对象的库存量是否存在明显不合理，考虑检查经销商进销存记录。
A63: 2.针对识别出的第三方配合实施财务舞弊的风险，可以考虑采用跟函方式进行函证，观察函证处理过程，评估回函可靠性。

Sheet 访谈记录与核对示例
A1: 致同会计师事务所（特殊普通合伙）
A2: 访谈记录与核对
A3: =[16]底稿目录!A2 -> 被审计单位名称： | E3: =[16]底稿目录!A4 -> 编制人： | G3: =[16]底稿目录!A5 -> 编制日期： | I3: 索引：
A4: =[16]底稿目录!A3 -> 会计期间：202X年度 | E4: =[16]底稿目录!A6 -> 复核人： | G4: =[16]底稿目录!A7 -> 复核日期： | I4: 页次：
A5: 走访公司名称：
A6: 一、走访的公司基本信息 | H6: 〔随需填写〕
A7: 【XYZ公司的基本情况，包括：XYZ公司法定代表人、注册地、注册资本、成立时间，股权关系等；公司营业执照复印件或照片、公司章程等】
A8: 工商信息查询结果、天眼查等查询结果：
A10: 百度地图等查询走访地址的结果：
A12: 二、交易基本信息 | H12: 〔随需填写〕
A13: 【XYZ公司与发行人的业务关系，发生业务的起始时间、交易金额、交易量、交易量是否异常，若异常应在访谈结论中明确交易量异常变动的原因，XYZ公司原行业状况、与发行人的交易占XYZ公司的总交易比重（公司基本情况需通过获取XYZ公司工商资料，并与发行人记录情况、增值税发票、XYZ公司网站信息等核对】
A14: 如： | B14: 与发行人合作从2006年至今已超过了5年，XYZ公司主要从发行人采购AAA材料，最近三年一期（2010年、2011年、2012年）的交易量和交易金额，占总交易额比重分别为 ；三年的交易量、交易金额稳步上升，交易比重保持平稳，未见异常变动。发行人的销售员经常到访XYZ公司维护客户关系，两家公司的合作关系良好，均有继续合作发展的意愿。
B15: 检查了XYZ公司的营业执照、组织机构代码证、税务登记证、章程等工商资料（若为特许经营行业，应检查相应证照）并取得复印件，与发行人记录情况、增值税发票、XYZ公司网站的相关信息等核对一致。【若为新增、异常客户/供应商或关联方客户/供应商，考虑获取XYZ公司的工商登记资料、纳税资料、银行账户流水等资料，并了解公司的实际控制人、关键经办人员等相关情况进行核对分析，包括核对XYZ公司的经营业绩、银行账户往来是否与其声称的经营状况和营运能力、现金流量相关等】
B16: XYZ公司不是ABC的关联方
B17: XYZ公司今年对AAA材料的采购目标为3亿（含税），其中约有20%采购自发行人
B18: XYZ公司的业务区域主要集中在山西陕西地区
B19: XYZ公司所在行业具有季节性，春、夏、秋为旺季，冬为淡季；因此原材料采购呈现类似特征。
B20: ……
A21: 三、与发行人的主要合同条款核对 | H21: 〔随需填写〕
A22: 【询问及取得合同样本：核对XYZ公司与发行人的合同条款（交易模式、交易规模、付款方式、付款期限、运输条款、运输保险受益人、销售佣金比例、质保金比例、信用期等）】
A23: 如： | B23: 项目 | C23: 询问所得信息 | G23: 来自发行人合同条款
B24: 交易模式 | C24: 包销 | G24: 与合同条款一致
B25: 交易标的 | C25: AAA材料 | G25: 与合同条款一致
B26: 交易规模 | C26: 500-600吨（含税金额约5000-6000万） | D26: 500-600吨（含税金额约5000-6000万） | G26: 与合同条款一致
B27: 付款方式 | C27: 银行承兑汇票或银行转账 | G27: 与合同条款一致
B28: 预付款项及质保金
B29: 付款期限 | C29: 收货验收后，3个月内（较同行业稍优惠，行业平均约为2.5月，75天） | G29: 与合同条款一致
B30: 订货到发货时间 | C30: 1个月以内，基本在1周之内发货（一般每月发一次订单） | G30: 合同条款为1个月之内
B31: 佣金返利 | C31: 5-6%，每季度按5%结算一次，全年若超过6000万采购量，按全年5.5%结算差额部分，若超过7000万，按全年6%结算差额部分；每年4月份进行全年佣金返利。 | G31: 与合同条款一致
B32: 佣金水平 | C32: 略高于同行业的返利水平，行业平均为4.8-5.5% | G32: 与合同条款一致
B33: 运输方式及费用承担 | C33: 实际承运单位：。物流公司汽运运输，运输时间3-5天，运费由发行人负责；运费中含保险费，保险受益人为发行人 | G33: 与合同条款一致
B34: 交付方式 | C34: XYZ收到材料，验收合格后，在发行人的验收单和物流公司的运单上签字确认后，交付完毕 | G34: 与合同条款一致
B35: 质量保证 | C35: 收货验收后质保1个月 | G35: 与合同条款一致
B36: 验收或检验 | C36: 出具验收报告/验收单 | G36: 与凭证检查情况一致
B37: 退货、换货情况 | C37: 合作5年来，仅在3年前发生过一次质保期内的质量问题，换货解决，价值约为20万 | G37: 与从发行人处获取的信息一致
B38: 是否涉及委托加工
B39: 是否存在实物返利
B40: 现金交易情况
B41: 第三方收款/付款
B42: 代收款、代付款情况
B43: 其他资金往来
B44: 是否涉诉
B45: ……
A46: 四、走访经营场所 | H46: 〔随需填写〕
A47: 【走访XYZ的生产经营场所等（若适用），关注其生产经营现状与访谈内容相互印证】
A48: 如： | B48: XYZ公司位于XXX工业园区，园区面积300亩，主要生产XXXX，主要原材料AAA，年产能XXXX吨。
B49: XYZ公司目前处于生产旺季，现场观察厂房生产正常，开工率约为90%；
B50: 走访XYZ公司的原料库，见到约20吨发行人生产的AAA材料（与年消耗500-600吨，每月订货的应用库存量相符），走访产成品库，见到XXXX产品约30吨，见到XYZ公司向其客户发运XXXX产品。
B51: XYZ公司XXXX产品的销售良好，采用赊销方式，直接销售给最终用户，平均收款周期为2个月；与行业状况基本相符。
B52: ……
A53: 产品使用场景的照片（显示客户公司名称的铭牌，注明日期）：
A55: 五、现场函证 | H55: 〔随需填写〕
A56: 【对XYZ公司进行现场函证（函证内容包括但不限于与发行人的：采购量、采购总额、截止日的债权/债务余额、重要合同条款及其他项目组认为必要的信息；关联方关系确认函）】
A57: 如： | B57: 现场获取经XYZ公司盖章确认的函证，XYZ公司对函证信息确认一致（差异为20吨、200万，系XYZ公司尚未对12月份采购的原材料入账所致，经查12月份发票、出库单、运单核对一致），详见索引号 。
B58: ……
A59: 六、关联方关系 | H59: 〔随需填写〕
A60: 走访公司的控股股东、实际控制人：
A61: 走访公司的董监高、关键经办人员（如采购、销售部门负责人、出纳等）：
A63: 七、其他 | H63: 〔随需填写〕
A66: 走访结论：

Sheet 客户、供应商等资金流水检查D4-32
A1: 致同会计师事务所
A2: 客户、供应商等资金流水检查
A3: =[16]底稿目录!A2 -> 被审计单位名称： | C3: =[16]底稿目录!A4 -> 编制人： | F3: =[16]底稿目录!A5 -> 编制日期： | H3: 索引号： | I3: =[16]底稿目录!F22 -> D4-32
A4: =[16]底稿目录!A3 -> 会计期间：202X年度 | C4: =[16]底稿目录!A6 -> 复核人： | F4: =[16]底稿目录!A7 -> 复核日期： | H4: 页次：
A5: 一、审计目标：
A6: 润表中记录的营业收入已发生，且与被审计单位有关，已记录于恰当的账户。
A7: 二、审计过程：
A8: 1.获取被审计单位主要供应商、客户资金流水，检查是否与被审计单位控股股东、实际控制人以及其他关联方存在大额资金往来，如有，应确定该等资金往来是否与被审计单位收入舞弊有关。
A9: 2.获取被审计单位控股股东、实际控制人、关键管理人员以及其他关联方银行账户资金流水，检查是否存在前述各方提供资金配合被审计单位虚构收入的情况。
A11: 序号 | B11: 单位名称/姓名 | C11: 本期交易金额 | D11: 占同类交易比例 | E11: 开户银行 | F11: 账号 | G11: 资金流水获取途径 | H11: 是否发现异常交易 | I11: 索引号
B12: 主要供应商
A13: 1
A14: 2
A15: 3
A16: 4
A17: 5
A18: ……
B19: 主要客户
A20: 1
A21: 2
A22: 3
A23: 4
A24: 5
A25: ……
B26: 控股股东
A27: 1
A28: 2
A29: ……
B30: 实际控制人
A31: 1
A32: 2
A33: ……
B34: 关键管理人员
A35: 1
A36: 2
A37: 3
A38: 4
A39: 5
A40: ……
B41: 其他关联方
A42: 1
A43: 2
A44: 3
A45: 4
A46: 5
A47: ……
A48: 三、审计说明
A52: 四、审计结论

Sheet 底稿目录 (5)
A1: 底稿开列时，可先在以下单元格填写有关内容，以便其他底稿引用有关数据：
A2: 被审计单位： | D2: 序号 | E2: 内容 | F2: 索引号
A3: 会计期间：202X年度 | D3: 1 | E3: 其他业务毛利率分析表 | F3: D4-33
A4: 编制人： | D4: 2 | E4: 其他业务收入合同测算表 | F4: D4-34
A5: 编制日期： | D5: 3 | E5: 其他业务收入检查表 | F5: D4-35
A6: 复核人： | D6: 4 | E6: 其他业务收入截止性测试 | F6: D4-36
A7: 复核日期：
A9: 关于工作底稿与审计程序索引号对应的说明
A10: 1.编制的审计工作底稿应与审计程序对应。审计项目组应根据被审计单位实际情况和风险评估情况在实质性程序表中裁剪、修改或增加审计程序，根据实际执行的审计程序完成相应审计工作底稿，编制的工作底稿中应按自然顺序依次编制索引号，并通过唯一的索引号将与实质性程序表中的程序对应关联（即将工作底稿的索引号填入实质性程序表中的底稿索引号列）。
A14: 2.获取的支持性证据应与审计底稿或程序对应。审计项目组在完成底稿时获取的支持性证据应根据底稿索引号编制下一级按自然顺序排序的索引号（如D1-2-1、D1-2-2、……），并在底稿中说明引用的支持性证据、关联索引号。
A17: 3.工作底稿索引号的编码规则：实质性程序索引号按循环从“D”到“N”,循环内账户以顺序号排列，模板中底稿索引号按账户顺序+自然数顺序（即模板中索引号按二级自然顺序排列，如D1-1、D1-2、D1-3、……D1-N）。

Sheet 其他业务毛利率分析表D4-33
A1: 致同会计师事务所
A2: 其他业务毛利率分析表
A3: =[17]底稿目录!A2 -> 被审计单位： | F3: =[17]底稿目录!A4 -> 编制人： | I3: =[17]底稿目录!A5 -> 编制日期： | L3: 索引号： | M3: =[17]底稿目录!F3 -> D4-33
A4: =[17]底稿目录!A3 -> 会计期间：202X年度 | F4: =[17]底稿目录!A6 -> 复核人： | I4: =[17]底稿目录!A7 -> 复核日期： | L4: 页次：
A5: 一、审计目标：
A6: 1.利润表中记录的其他业务收入已发生，且与被审计单位有关，已记录于恰当的账户。
A7: 2.所有应当记录的其他业务收入均已记录，所有应当包括在财务报表中的相关披露均已包括。
A8: 3.与其他业务收入有关的金额及其他数据已恰当记录，相关披露已得到恰当计量和描述。
A9: 二、审计过程：
A10: 月份 | B10: 合计 | E10: 出租固定资产 | H10: 出租无形资产 | K10: 销售材料
B11: 收入 | C11: 成本 | D11: 毛利率 | E11: 收入 | F11: 成本 | G11: 毛利率 | H11: 收入 | I11: 成本 | J11: 毛利率 | K11: 收入 | L11: 成本 | M11: 毛利率
A12: 1 | B12: =E12+H12+K12 -> 0 | C12: =F12+I12+L12 -> 0 | D12: =(B12-C12)/B12 -> #DIV/0! | G12: =(E12-F12)/E12 -> #DIV/0! | J12: =(H12-I12)/H12 -> #DIV/0! | M12: =(K12-L12)/K12 -> #DIV/0!
A13: 2 | B13: =E13+H13+K13 -> 0 | C13: =F13+I13+L13 -> 0 | D13: =(B13-C13)/B13 -> #DIV/0! | G13: =(E13-F13)/E13 -> #DIV/0! | J13: =(H13-I13)/H13 -> #DIV/0! | M13: =(K13-L13)/K13 -> #DIV/0!
A14: 3 | B14: =E14+H14+K14 -> 0 | C14: =F14+I14+L14 -> 0 | D14: =(B14-C14)/B14 -> #DIV/0! | G14: =(E14-F14)/E14 -> #DIV/0! | J14: =(H14-I14)/H14 -> #DIV/0! | M14: =(K14-L14)/K14 -> #DIV/0!
A15: 4 | B15: =E15+H15+K15 -> 0 | C15: =F15+I15+L15 -> 0 | D15: =(B15-C15)/B15 -> #DIV/0! | G15: =(E15-F15)/E15 -> #DIV/0! | J15: =(H15-I15)/H15 -> #DIV/0! | M15: =(K15-L15)/K15 -> #DIV/0!
A16: 5 | B16: =E16+H16+K16 -> 0 | C16: =F16+I16+L16 -> 0 | D16: =(B16-C16)/B16 -> #DIV/0! | G16: =(E16-F16)/E16 -> #DIV/0! | J16: =(H16-I16)/H16 -> #DIV/0! | M16: =(K16-L16)/K16 -> #DIV/0!
A17: 6 | B17: =E17+H17+K17 -> 0 | C17: =F17+I17+L17 -> 0 | D17: =(B17-C17)/B17 -> #DIV/0! | G17: =(E17-F17)/E17 -> #DIV/0! | J17: =(H17-I17)/H17 -> #DIV/0! | M17: =(K17-L17)/K17 -> #DIV/0!
A18: 7 | B18: =E18+H18+K18 -> 0 | C18: =F18+I18+L18 -> 0 | D18: =(B18-C18)/B18 -> #DIV/0! | G18: =(E18-F18)/E18 -> #DIV/0! | J18: =(H18-I18)/H18 -> #DIV/0! | M18: =(K18-L18)/K18 -> #DIV/0!
A19: 8 | B19: =E19+H19+K19 -> 0 | C19: =F19+I19+L19 -> 0 | D19: =(B19-C19)/B19 -> #DIV/0! | G19: =(E19-F19)/E19 -> #DIV/0! | J19: =(H19-I19)/H19 -> #DIV/0! | M19: =(K19-L19)/K19 -> #DIV/0!
A20: 9 | B20: =E20+H20+K20 -> 0 | C20: =F20+I20+L20 -> 0 | D20: =(B20-C20)/B20 -> #DIV/0! | G20: =(E20-F20)/E20 -> #DIV/0! | J20: =(H20-I20)/H20 -> #DIV/0! | M20: =(K20-L20)/K20 -> #DIV/0!
A21: 10 | B21: =E21+H21+K21 -> 0 | C21: =F21+I21+L21 -> 0 | D21: =(B21-C21)/B21 -> #DIV/0! | G21: =(E21-F21)/E21 -> #DIV/0! | J21: =(H21-I21)/H21 -> #DIV/0! | M21: =(K21-L21)/K21 -> #DIV/0!
A22: 11 | B22: =E22+H22+K22 -> 0 | C22: =F22+I22+L22 -> 0 | D22: =(B22-C22)/B22 -> #DIV/0! | G22: =(E22-F22)/E22 -> #DIV/0! | J22: =(H22-I22)/H22 -> #DIV/0! | M22: =(K22-L22)/K22 -> #DIV/0!
A23: 12 | B23: =E23+H23+K23 -> 0 | C23: =F23+I23+L23 -> 0 | D23: =(B23-C23)/B23 -> #DIV/0! | G23: =(E23-F23)/E23 -> #DIV/0! | J23: =(H23-I23)/H23 -> #DIV/0! | M23: =(K23-L23)/K23 -> #DIV/0!
A24: 合 计 | B24: =SUM(B12:B23) -> 0 | C24: =SUM(C12:C23) -> 0 | D24: =(B24-C24)/B24 -> #DIV/0! | E24: =SUM(E12:E23) -> 0 | F24: =SUM(F12:F23) -> 0 | G24: =(E24-F24)/E24 -> #DIV/0! | H24: =SUM(H12:H23) -> 0 | I24: =SUM(I12:I23) -> 0 | J24: =(H24-I24)/H24 -> #DIV/0! | K24: =SUM(K12:K23) -> 0 | L24: =SUM(L12:L23) -> 0 | M24: =(K24-L24)/K24 -> #DIV/0!
A25: 上年数 | B25: =E25+H25+K25 -> 0 | C25: =F25+I25+L25 -> 0 | D25: =(B25-C25)/B25 -> #DIV/0! | G25: =(E25-F25)/E25 -> #DIV/0! | J25: =(H25-I25)/H25 -> #DIV/0! | M25: =(K25-L25)/K25 -> #DIV/0!
A26: 变动额 | B26: =B24-B25 -> 0 | C26: =C24-C25 -> 0 | D26: =D24-D25 -> #DIV/0! | E26: =E24-E25 -> 0 | F26: =F24-F25 -> 0 | G26: =G24-G25 -> #DIV/0! | H26: =H24-H25 -> 0 | I26: =I24-I25 -> 0 | ... M26: =M24-M25 -> #DIV/0!
A27: 变动比例 | B27: =IF(AND(B25=0,B24=0),0,IF(B25<=0,"不适用",B26/B25)) -> 0 | C27: =IF(AND(C25=0,C24=0),0,IF(C25<=0,"不适用",C26/C25)) -> 0 | D27: =IF(AND(D25=0,D24=0),0,IF(D25<=0,"不适用",D26/D25)) -> #DIV/0! | E27: =IF(AND(E25=0,E24=0),0,IF(E25<=0,"不适用",E26/E25)) -> 0 | F27: =IF(AND(F25=0,F24=0),0,IF(F25<=0,"不适用",F26/F25)) -> 0 | G27: =IF(AND(G25=0,G24=0),0,IF(G25<=0,"不适用",G26/G25)) -> #DIV/0! | H27: =IF(AND(H25=0,H24=0),0,IF(H25<=0,"不适用",H26/H25)) -> 0 | I27: =IF(AND(I25=0,I24=0),0,IF(I25<=0,"不适用",I26/I25)) -> 0 | ... M27: =IF(AND(M25=0,M24=0),0,IF(M25<=0,"不适用",M26/M25)) -> #DIV/0!
A28: 三、审计说明：
A30: 四、审计结论：

Sheet 其他业务收入合同测算表D4-34
A1: 致同会计师事务所
A2: 其他业务收入合同测算表
A3: =[17]底稿目录!A2 -> 被审计单位： | E3: =[17]底稿目录!A4 -> 编制人： | H3: =[17]底稿目录!A5 -> 编制日期： | J3: 索引号： | K3: =[17]底稿目录!F4 -> D4-34
A4: =[17]底稿目录!A3 -> 会计期间：202X年度 | E4: =[17]底稿目录!A6 -> 复核人： | H4: =[17]底稿目录!A7 -> 复核日期： | J4: 页次：
A5: 一、审计目标：
A6: 1.利润表中记录的其他业务收入已发生，且与被审计单位有关，已记录于恰当的账户。
A7: 2.所有应当记录的其他业务收入均已记录，所有应当包括在财务报表中的相关披露均已包括
A8: 3.与其他业务收入有关的金额及其他数据已恰当记录，相关披露已得到恰当计量和描述
A9: 4.与其他业务收入有关的交易和事项已记录于正确的会计期间。
A10: 二、审计过程：
A11: 1.房屋租赁业务（其他租赁可参照）
A12: 序号 | B12: 承租方 | C12: 租赁期间 | D12: 租赁面积 | E12: 合同单价 | F12: 合同索引 | G12: 本期实际 租赁月数 | H12: 本期应计收入 | I12: 本期实计收入 | J12: 差异 | K12: 索引号
A13: 1 | J13: =H13-I13 -> 0
A14: 2 | J14: =H14-I14 -> 0
A15: 3 | J15: =H15-I15 -> 0
A16: 4 | J16: =H16-I16 -> 0
A17: 5 | J17: =H17-I17 -> 0
A18: 2.咨询业务
A19: 序号 | B19: 委托方 | D19: 咨询项目 | E19: 委托期限 | F19: 合同金额 | G19: 合同索引 | H19: 本期应计收入 | I19: 本期实计收入 | J19: 差异 | K19: 索引号
A20: 1 | J20: =H20-I20 -> 0
A21: 2 | J21: =H21-I21 -> 0
A22: 3 | J22: =H22-I22 -> 0
A23: 4 | J23: =H23-I23 -> 0
A24: 5 | J24: =H24-I24 -> 0
A25: 三、审计说明：
A28: 四、审计结论：

Sheet 其他业务收入检查表D4-35
A1: 致同会计师事务所
A2: 其他业务收入的检查表
A3: =[17]底稿目录!A2 -> 被审计单位： | D3: =[17]底稿目录!A4 -> 编制人： | G3: =[17]底稿目录!A5 -> 编制日期： | P3: 索引号： | Q3: =[17]底稿目录!F5 -> D4-35
A4: =[17]底稿目录!A3 -> 会计期间：202X年度 | D4: =[17]底稿目录!A6 -> 复核人： | G4: =[17]底稿目录!A7 -> 复核日期： | P4: 页次：
A5: 一、审计目标：
A6: 1.利润表中记录的其他业务收入已发生，且与被审计单位有关，已记录于恰当的账户。2.与其他业务收入有关的金额及其他数据已恰当记录，相关披露已得到恰当计量和描述。
A7: 二、样本选取标准与规模：
A8: 测试总体： | B8: 如借方发生额所有凭证共XX笔金额XX、贷方发生额所有凭证共XX笔金额XX | F8: 特定样本： | G8: XX金额以上（大额）、关联方/关联交易形成的款项、XX异常款项全部测试，共XX笔；
A9: 抽样总体： | B9: 测试总体扣除特定样本以外的样本，共XX笔、金额XX | F9: 确定的抽样样本量： | G9: 抽取XX笔（如果使用了样本计算器计算样本量，样本量计算过程见<XX>底稿）
A10: 抽样方法： | B10: 随机选样/系统选样/货币单元抽样/随意选样（非统计抽样适用） | F10: 抽样过程： | G10: 使用IDEA（XX抽样工具）选择XX数量、金额XX的样本进行测试，抽样工具中的样本选择过程和结果见<XX>底稿
A11: 三、测试：
A12: 测试内容说明：1.原始凭证是否齐全；2.记账凭证与原始凭证是否相符；3.账务处理是否正确；4.是否记录于恰当的会计期间；5.……
A13: 日期 | B13: 凭证编号 | C13: 业务内容 | D13: 对方科目 | E13: 明细科目 | F13: 金额 | G13: 支持性文件 | H13: 核对内容 | O13: 索引号 | P13: 是否异常 | Q13: 备注说明
H14: 1 | I14: 2 | J14: 3 | K14: 4 | L14: 5 | M14: 6
A26: 合计 | F26: =SUM(F15:F25) -> 0
A27: 本期发生额 | F27: ='[17]其他业务毛利率分析表D4-33'!B24 -> 0
A28: 检查比例 | F28: =F26/F27 -> #DIV/0!
A29: 四、审计说明：
A33: 五、审计结论：

Sheet 其他业务收入截止性测试D4-36
A1: 致同会计师事务所
A2: 其他业务收入截止性测试
A3: =[17]底稿目录!A2 -> 被审计单位： | E3: =[17]底稿目录!A4 -> 编制人： | H3: =[17]底稿目录!A5 -> 编制日期： | J3: 索引号： | K3: =[17]底稿目录!F6 -> D4-36
A4: =[17]底稿目录!A3 -> 会计期间：202X年度 | E4: =[17]底稿目录!A6 -> 复核人： | H4: =[17]底稿目录!A7 -> 复核日期： | J4: 页次：
A5: 一、审计目标
A6: 确认与其他业务收入有关事项已记录于正确的会计期间。
A7: 二、审计过程
A8: 1.获取报表日前（______）天、后（______）天，且金额大于______元收入记账凭证与发货单（或验收单、出库单等）核对确认
A9: 收入是否记入了恰当的期间；
A10: 2.获取报表日前（______）天、后（______）天，且金额大于______元发货单（或验收单、出库单等）与收入记账凭证核对确认
A11: 收入是否记入了恰当的期间；
A12: 如果存在跨期舞弊风险或者所检查样本中发现有跨期的，应扩大测试期间和样本，甚至可以考虑将截止测试期间延长至审计报告日。同时考虑是否存在内控缺陷。
A13: （一）账到单据
A14: 记账凭证 | F14: 发货单（或验收单、出库单等） | K14: 是否跨期√(×)
A15: 日期 | B15: 编号 | C15: 品名 | D15: 数量 | E15: 金额 | F15: 日期 | G15: 编号 | H15: 品名 | I15: 数量 | J15: 金额
A24: 截止日期：202X年12月31日
A33: （二）单据到账
A34: 发货单（或验收单、出库单等） | F34: 记账凭证 | K34: 是否跨期
A35: 日期 | B35: 编号 | C35: 品名 | D35: 数量 | E35: 金额 | F35: 日期 | G35: 编号 | H35: 品名 | I35: 数量 | J35: 金额 | K35: √（×）
A44: 截止日期：202X年12月31日
A53: 三、审计说明：
A56: 四、审计结论：
A58: 提示1：本表适用于对“以发货单为确认收入时点”的被审计单位的截止测试，项目组在使用模板时，请根据企业的收入确认政策修改或调整。
A59: 提示2：如果存在跨期舞弊风险或者所检查样本中发现有跨期的，应扩大测试期间和样本，甚至可以考虑将截止测试期间延长至审计报告日。同时考虑是否存在内控缺陷。
