Workbook
Name _.dbf: #REF!
Name _00510: #REF!
Name _1、: #REF!
Name _1、受本循环影响的相关交易和账户余额: #REF!
Name _13: #REF!
Name _1w6_: #REF!
Name _1固定资产数据库_筛选打印: #REF!
Name _2、主要业务活动: #REF!
Name _2、注册会计师通常应在本循环中了解与上述业务活动相关的内部控制_如果计划在其他业务循环中对上述: #REF!
Name _2其他资产_开办费除外_明细表: #REF!
Name _3余额表_一级_.dbf: #REF!
Name _YE1: #REF!
Name _YS1: #REF!
Name a: #REF!
Name a1c1: #REF!,#REF!
Name aa: #REF!
Name aaa: #REF!
Name agmmt: #REF!
Name agmt: #REF!
Name agmt1: #REF!
Name al: #REF!
Name b: #REF!
Name BD: #REF!
Name beg_day: #REF!
Name beg_day1: #REF!
Name CarryKnown: #REF!
Name CarryKnownTable: #REF!
Name CarryLikely: #REF!
Name CarryLikelyTable: #REF!
Name Carryover_Effect_of_Prior_Year: #REF!
Name CarryoverTitle: #REF!
Name CC_Instruction: #REF!
Name CE_CarryKnownProtection: #REF!
Name CE_CarryKnownTable: #REF!
Name CE_CarryLikely1Protection: #REF!
Name CE_CarryLikely1Table: #REF!
Name CE_CarryLikely2Protection: #REF!
Name CE_CarryLikely2Table: #REF!
Name CE_CarryTaxable: #REF!
Name CE_Desc: #REF!
Name CE_Income: #REF!
Name CE_KeepFormat: #REF!
Name CE_KnownChange: #REF!
Name CE_KnownFormulaProtection: #REF!
Name CE_KnownImpact: #REF!
Name CE_Likely1Change: #REF!
Name CE_Likely1FormulaProtection: #REF!
Name CE_Likely1Impact: #REF!
Name CE_Likely2Change: #REF!
Name CE_Likely2FormulaProtection: #REF!
Name CE_Likely2Impact: #REF!
Name CE_SheetCorrect: #REF!
Name CE_StatementImpact: #REF!
Name CE_TotalProtection: #REF!
Name CE_WholeSheet: #REF!
Name CE_XF1: #REF!
Name CE_XF1Rng1: #REF!
Name CE_XF1Rng2: #REF!
Name CE_XF2: #REF!
Name CE_XF2Rng1: #REF!

Sheet 底稿目录
A1: 底稿开列时，可先在以下单元格填写有关内容，以便其他底稿引用有关数据：
A2: 被审计单位：
A3: 截止日：202X年12月31日 | D3: 序号 | E3: 内容 | F3: 索引
A4: 编制人： | D4: 1 | E4: 合同资产实质性程序表 | F4: D6A
A5: 编制日期： | D5: 2 | E5: 审定表 | F5: D6-1
A6: 复核人： | D6: 3 | E6: 附注披露信息(上市公司） | G6: 无需打印
A7: 复核日期： | D7: 4 | E7: 附注披露信息（国企） | G7: 无需打印
D8: 5 | E8: 明细表 | F8: D6-2
A9: 关于工作底稿与审计程序索引号对应的说明 | D9: 6 | E9: 合同资产减值准备明细表 | F9: D6-3
A10: 1.编制的审计工作底稿应与审计程序对应。审计项目组应根据被审计单位实际情况和风险评估情况在实质性程序表中裁剪、修改或增加审计程序，根据实际执行的审计程序完成相应审计工作底稿，编制的工作底稿中应按自然顺序依次编制索引号，并通过唯一的索引号将与实质性程序表中的程序对应关联（即将工作底稿的索引号填入实质性程序表中的底稿索引号列）。 | D10: 7 | E10: 调整分录汇总表 | F10: D6-4
D11: 8 | E11: 函证结果汇总表 | F11: D0-1
D12: 9 | E12: 核实被函证单位信息 | F12: D0-2
D13: 10 | E13: 跟函函证过程控制 | F13: D0-3
A14: 2.获取的支持性证据应与审计底稿或程序对应。审计项目组在完成底稿时获取的支持性证据应根据底稿索引号编制下一级按自然顺序排序的索引号（如D1-2-1、D1-2-2、……），并在底稿中说明引用的支持性证据、关联索引号。 | D14: 11 | E14: 函证差异调节表 | F14: D0-4
D15: 12 | E15: 应收及销售替代程序检查表 | F15: D0-6
D16: 13 | E16: 邮件传真回函可靠性验证 | F16: D0-7
A17: 3.工作底稿索引号的编码规则：实质性程序索引号按循环从“D”到“N”,循环内账户以顺序号排列，模板中底稿索引号按账户顺序+自然数顺序（即模板中索引号按二级自然顺序排列，如D1-1、D1-2、D1-3、……D1-N）。 | D17: 14 | E17: 函证程序舞弊风险评价表 | F17: D0-8
D18: 15 | E18: 关联关系及交易检查 | F18: D6-5
D19: 16 | E19: 合同资产检查表 | F19: D6-6
D20: 17 | E20: 合同资产减值准备会计政策检查 | F20: D6-7
D21: 18 | E21: 减值准备测算 | F21: D6-8
D22: 19 | E22: 减值准备转回、核销检查表 | F22: D6-9

Sheet 合同资产实质性程序表 D6A
A1: 致同会计师事务所
A2: 合同资产的实质性程序
A3: =底稿目录!A2 -> 被审计单位： | C3: =底稿目录!A4 -> 编制人： | E3: =底稿目录!A5 -> 编制日期： | H3: 索引号： | I3: =底稿目录!F4 -> D6A
A4: =底稿目录!A3 -> 截止日：202X年12月31日 | C4: =底稿目录!A6 -> 复核人： | E4: =底稿目录!A7 -> 复核日期： | H4: 页次：
A5: 一、本循环涉及的财务报表项目
A6: 合同资产
A7: 二、审计目标与认定的对应关系
A8: 审计目标 | G8: 财务报表的认定
A9: A.资产负债表中记录的合同资产是存在的，且已经记录在恰当的账户中 | G9: 存在
A10: B.所有应记录的合同资产均已记录，所有应当包括在财务报表中的相关披露均已包括 | G10: 完整性
A11: C.记录的合同资产由被审计单位拥有或控制 | G11: 权利和义务
A12: D.合同资产以恰当的金额包括在财务报表中，与之相关的计价或分摊调整已恰当记录，相关披露已得到恰当计量和描述 | G12: 准确性、计价和分摊
A13: E.合同资产已被恰当地汇总或分解且表述清楚，相关披露在按照企业会计准则的编制基础下是相关的、可理解的 | G13: 列报
A14: 三、计划实施的实质性程序
A15: 序号 | B15: 审计程序 | C15: 程序分类 | D15: 财务报表的认定 | I15: 底稿索引号
D16: 存在 | E16: 完整性 | F16: 权利 和义务 | G16: 准确性、计价 和分摊 | H16: 列报 | J16: 根据被审计单位实际情况和风险评估情况裁剪、修改或增加审计程序
A17: 1 | B17: 获取或编制合同资产明细表，完成以下工作，并编制审定表 （1）复核加计是否正确，与总账、明细账合计数核对是否相符，期初余额与上期审定期末余额是否相符； （2）获取管理层编制的合同资产账龄分析表，检查账龄划分是否正确； （3）检查非记账本位币合同资产折算是否正确。 | C17: 常规★ | D17: √ | E17: √ | G17: √ | I17: D6-1 /D6-2 /D6-3
A18: 2 | B18: 在使用手工编制、自定义信息报告、系统生成的非固定格式报告等由被审计单位生成的信息时，测试有关信息准确性和完整性，并考虑针对编制和维护由被审计单位生成的信息的相关控制实施控制测试，以评价该信息是否能够为实现审计目的提供基础。 | C18: 常规★ | E18: √ | G18: √ | I18: T1 / | J18: 可参见《审计手册》4.2.6，由被审计单位生成的信息可能是由系统生成的、或手工编制的、或二者兼而有之的方式生成的。例如，由被审计单位生成的信息可能包括： • 不涉及自定义的、由系统生成的报告（如，固定格式报告）； • 可能通过人工自定义的、由系统生成的报告，例如，（计算机）查询信息或特别定制的报告； • 手工编制的信息，例如，汇总信息的电子表格或用以支持分配、计算以及调节的电子表格； • 其他系统生成或手工编制的信息，例如，由被审计单位编制的客户发票； • 通过影印、拍摄、扫描或其他方式转换成电子形式的文件记录。
A19: 3 | B19: 取得合同资产期初余额明细表复核加计是否正确，与总账、明细账合计数是否相符；检查期初合同资产在本期结算情况，函证期初余额以及其他必要追加的审计程序。（适用于首次承接） | C19: 期初余额 | D19: √ | E19: √ | F19: √ | G19: √ | J19: 由被审计单位生成的信息不包括： • 总分类账或明细分类账、试算平衡表、或经审计的财务报表； • 第三方（除了服务机构）的报表或报告，例如，原始银行对账单，或函证的回函； • 外部数据（例如，第三方发布的数据，如，定价来源）。
A20: 4 | B20: 实施分析性程序： （1）分析借贷方发生额，与对应科目比较是否存在异常； （2）比较主要客户合同资产余额变动情况，分析合理性； （3）与期初余额账龄比较，分析变动合理性。 | C20: 常规★ | D20: √ | G20: √ | I20: D6-1 /D6-2 | J20: 合同资产由被审计单位生成的信息例如：合同资产项目台账等被审计单位提供信息
A21: 5 | B21: 获取合同资产账龄表： (1）确定计算准确性并与总账核对一致； (2）对重要合同资产账龄进行重新计算，与被审计单位提供的账龄表进行比较； (3）对于发现的重大不一致，询问客户内部适当人员，并检查原始凭证，测试账龄划分的准确性。 | C21: 常规★ | G21: √ | I21: D6-2
A22: 6 | B22: 对于长期未结转大额合同资产，应了解原因，并分析合理性。 | C22: 常规★ | D22: √ | G22: √ | I22: D6-2
A23: 7 | B23: 结合营业收入及应收账款函证，实施函证程序。 | C23: 常规★ | D23: √ | E23: √ | F23: √ | G23: √ | I23: D0
A24: 8 | B24: 检查对关联方的合同资产： （1）了解交易的商业理由、交易事项的目的、价格和条件，考虑对关联方合同资产的合理性、合法性； （2）检查证实交易的支持性文件（例如，发票、合同、协议和运输单据等相关文件） （3）考虑向关联方或其他注册会计师函证重大的关联销售交易（包括担保和其他重要信息）； （4）必要时，向与交易相关的人员和机构（如银行、律师）函证或与其讨论有关信息。 （5）考虑是否存在未识别的关联方，关联余额披露是否正确。 | C24: 常规★ | D24: √ | E24: √ | F24: √ | G24: √ | H24: √ | I24: D6-5
A25: 9 | B25: 检查与营业收入有关的的记账凭证和检查相关支持性文件（如销售合同、销售订单、发运凭证等），验证合同资产的确认是否恰当。 | C25: 常规★ | D25: √ | F25: √ | G25: √ | I25: D6-6
A26: 10 | B26: 检查合同资产坏账准备计提是否正确： （1）了解合同资产坏账准备计提会计政策，确定合同资产坏账准备是否以预期信用损失为基础计提，计提政策是否恰当，是否一贯执行。 （2）重新计算坏账准备，与被审计单位已记录的坏账准备进行比较。 （3）关注大额坏账准备转回是否合理。实际发生坏账损失的，检查转销依据是否符合有关规定，会计处理是否正确。已经确认并转销的坏账重新收回的，检查其会计处理是否正确。 | C26: 常规★ | G26: √ | I26: D6-7 /D6-8 /D7-9
A27: 11 | B27: 结合营业收入审计，对重要的客户进行背景调查、电话访谈、实地走访等，核实合同资产真实性。 | C27: IPO/上市公司/新三板/舞弊应对 | D27: √ | E27: √ | F27: √ | G27: √ | I27: D4-24 /D4-25 /D4-26 /D4-27 /D4-28
A28: 12 | B28: 针对评估的舞弊风险等因素增加的审计程序。 | C28: IPO/上市公司/新三板/舞弊应对
A29: 13 | B29: 检查合同资产是否已按企业会计准则或其他适用的规定在财务报表中做出恰当列报和披露。 | C29: 常规★ | H29: √ | I29: A1-1/A1-15 /A1-16

Sheet 合同资产实质性程序表 D7A（原）
A1: 致同会计师事务所
A2: 合同资产的实质性程序
A3: 客户名称： | C3: 编制人： | G3: 编制日期： | I3: 索引号：D7A
A4: 截止日：2024年12月31日 | C4: 复核人： | G4: 复核日期： | I4: 页次：
A5: 一、本循环涉及的财务报表项目
A6: 合同资产
A7: 二、重大错报风险需从实质性程序获取的保证程度
A8: 根据风险评估和内控测试的结果按下列顺序作出判断： | C8: 财务报表的认定 | H8: 信赖/不信赖/不适用 | I8: 索引号
C9: 存在 | D9: 完整性 | E9: 权利 和义务 | F9: 计价 和分摊 | G9: 列报和披露
A10: A资产负债表中记录的合同资产是存在的。 | C10: √ | I10: B22-2,B22-3
A11: B所有应当记录的合同资产均已记录。 | D11: √ | I11: C2
A12: C记录的合同资产由被审计单位拥有或控制。 | E12: √ | I12: ——
A13: D合同资产以恰当的金额包括在财务报表中，与之相关的计价调整已恰当记录。 | F13: √
A14: E合同资产已按照企业会计准则的规定在财务报表中作出恰当列报和披露。 | G14: √
A15: 三、计划实施的实质性程序 | J15: 软件专用
A16: 序号 | B16: 审计程序 | C16: 程序分类 | E16: 审计目标 | H16: 执行情况说明 （含底稿索引） | J16: 风险 | K16: 开机启动项 | L16: 问题
A17: 一 | B17: 编制审定表 | C17: 常规★ | E17: B | H17: D7 | J17: 收入 Revenues-1
A18: 二 | B18: 获取或编制合同资产（包括其他非流动资产中列示的合同资产）明细表。 | C18: 常规★ | E18: C | H18: D7-2 | J18: 收入 Revenues-1
A19: 1 | B19: 复核加计正确 | C19: 常规★ | J19: 收入 Revenues-1
A20: 2 | B20: 将总金额与总账、明细账合计数核对相符 | C20: 常规★ | J20: 收入 Revenues-1
A21: 三 | B21: 在使用被审计单位生成的信息（IPE）时，应当评价该信息对实现审计目的是否足够可靠，包括根据具体情况在必要时实施下列程序： | E21: B | H21: T1
A22: 1 | B22: 获取有关信息准确性和完整性的审计证据。
A23: 2 | B23: 评价信息对实现审计目的是否足够准确和详细。
A24: 四 | B24: 测试上期合同资产（包括其他非流动资产中列示的合同资产）期末余额。（适用于实施新收入准则后的首次承接） | C24: 备选 | E24: D | J24: 收入 Revenues-10 | K24: 首次承接
A25: 1 | B25: 向被审计单位人员询问前期期末关于收入截止的相关处理。 | C25: 备选 | J25: 收入 Revenues-10 | K25: 首次承接
A26: 2 | B26: 复核资产负债表日前后一段合理期间里的销售分录，调查任何异常分录。 | C26: 备选 | J26: 收入 Revenues-10 | K26: 首次承接
A27: 3 | B27: 复核资产负债表日前后一段合理期间里销售退回或销售折扣的记录。 | C27: 备选 | J27: 收入 Revenues-10 | K27: 首次承接
A28: 4 | B28: 调查接近前期期末发生的大额或异常的销售交易。 | C28: 备选 | J28: 收入 Revenues-10 | K28: 首次承接
A29: 五 | B29: 重大会计政策、会计估计合理性检查 | C29: 常规★ | E29: ABCD | H29: D7-13 | J29: 收入 Revenues-12,收入 Revenues-20
A30: 2 | B30: 检查合同资产减值准备计提的会计政策的合理性，并与前期进行对比，分析其是否前后一致。与同行业其他公司的会计政策进行对比，关注其是否利用会计政策和会计估计变更操纵利润。<CSRC14-9> | C30: 常规 | J30: 收入 Revenues-20
A31: 3 | B31: 根据执行程序的结果，包括回顾上期估计值与当期结果，考虑管理层在作出会计估计时的判断和决策时，是否表明存在管理层偏向的迹象。 | C31: 常规 | J31: 收入 Revenues-12,收入 Revenues-20
A32: 六 | B32: 重要合同（包括涉及特定交易的合同）及其履行情况检查： | C32: 常规★ | E32: ABC | H32: D7-18 | J32: 收入 Revenues-15 | L32: 删除
A33: 1 | B33: 分业务类型选取重要合同样本，分析合同是否成立（同时满足合同成立的五项条件）。 | C33: 常规★ | J33: 收入 Revenues-15
A34: 2 | B34: 判断被审计单位对合同所包含的各单项履约义务（客户能够从该商品本身或从该商品与其他易于获得资源一起使用中受益；企业向客户转让该商品的承诺与合同中其他承诺可单独区分）的评估是否恰当。 | C34: 常规★ | J34: 收入 Revenues-15
A35: 3 | B35: 检查重要销售或服务合同的定价和条款，确定是否符合销售及信用管理政策，并测试交易价格的确定是否正确。 考虑代第三方收取的款项、预期将退还给客户的款项，以及可变对价（如现金折扣、数量折扣、价格折让等）、合同中存在的重大融资成分、非现金对价、应付客户对价等因素的影响。 | C35: 常规★ | E35: C | J35: 收入 Revenues-15
A36: 4 | B36: 合同中包含两项或多项履约义务的，测试交易价格的分摊是否正确。考虑单独售价的估计方法、合同折扣的分摊、可变对价后续变动额的分摊是否合理。 | C36: 常规 | J36: 收入 Revenues-15
A37: 5 | B37: 判断收入的确认（在某一时点履行履约义务、在某一时段内履行履约义务）及控制权转移时点或期间的判断是否恰当。 | C37: 常规★ | J37: 收入 Revenues-15
A38: 6 | B38: 确定交易是否按合同条款履行（考虑直接与合同方函证合同条款）。 | C38: 常规 | J38: 收入 Revenues-15
A39: 7 | B39: 对于被审计单位与同一客户（或该客户的关联方）同时订立或在相近时间内先后订立的两份或多份合同，分析会计处理是否正确。 | C39: 备选 | J39: 收入 Revenues-12 | L39: 收入4-1
A40: 8 | B40: 确定对原始合同的修改以及增加均有签字确认，分析合同变更的会计处理是否正确。 | C40: 备选 | J40: 收入 Revenues-12 | L40: 收入4-1
A41: 9 | B41: 判断特定交易的会计处理是否正确。 | C41: 常规★ | J41: 收入 Revenues-12 | L41: 收入4-1
A42: 七 | B42: 确定坏账准备计提的是否充分。 | C42: 常规★ | E42: C | H42: D7-14 | J42: 收入 Revenues-20
A43: 1 | B43: 取得包括账龄或逾期信息的应收票据、应收账款、合同资产明细表，测试账龄或逾期信息的划分是否正确。 | C43: 常规★ | J43: 收入 Revenues-20
A44: 2 | B44: 重新计算应计提的坏账准备，与被审计单位已记录的坏账准备进行比较，调整差异。特别关注大额坏账准备转回是否合理。 | C44: 常规★ | J44: 收入 Revenues-20
A45: 3 | B45: 分析已计提的准备是否以预期信用损失为基础，反映通过评价一系列可能的结果而确定的无偏概率加权平均金额、货币时间价值，及在资产负债表日无须付出不必要的额外成本或努力即可获得的有关过去事项、当前状况以及未来经济状况预测的合理且有依据的信息。 | C45: 常规★ | J45: 收入 Revenues-20
A46: 4 | B46: 实际发生坏账损失的，检查转销依据是否符合有关规定，会计处理是否正确。 | C46: 常规 | J46: 收入 Revenues-20
A47: 5 | B47: 已经确认并转销的坏账重新收回的，检查其会计处理是否正确。 | C47: 常规 | J47: 收入 Revenues-20
A48: 八 | B48: 使用积极式函证方式对合同资产进行函证 | C48: 备选 | D48: 应收账款,主营业务收入,合同负债 | E48: AC | H48: D7-6、D7-7、D7-8 | J48: 收入 Revenues-10,收入 Revenues-11,收入 Revenues-12,收入 Revenues-13
A49: 1 | B49: 样本的选择： 对总体中特定项目（金额重大、性质特殊）全部进行函证，对于剩余项目，如果总体重要，则选用抽样方法，如果总体不重要的，仅执行分析程序。 Select %S items using an appropriate selection method. | C49: 备选 | D49: 应收账款,主营业务收入,合同负债 | J49: 收入 Revenues-10
A50: (1) | B50: 抽样方法：使用IDEA选择%样本，并记录选样标准Use IDEA to select %S items. | C50: 备选 | D50: 应收账款,主营业务收入,合同负债 | J50: 收入 Revenues-10
A51: (2) | B51: 记录函证抽样的依据及比例。
A52: 2 | B52: 设计询证函（可以采用事务所的模板，或根据需要在模板基础上修改），考虑制作询证函防伪标识，并在发函前核实被函证单位信息（函证科目、客户名称、通讯地址、联系人、联系电话、邮政编码、函证人等），对于函证地址与注册地址、办公地址等不一致，不同客户或供应商的函证地址相近、电话号段相邻，函证联系人并非被询证单位员工等情况，需核查并记录原因。 | C52: 备选 | D52: 应收账款,主营业务收入,合同负债 | J52: 收入 Revenues-10
A53: 3 | B53: 对函证过程实施控制：验证被函证对象信息；询证函须由注册会计师直接收发；在底稿中记录控制过程，跟函时观察实地场所以及函证核对过程，确认处理函证的人员身份和权限，防范询证函被拦截、篡改或发生串通舞弊；保存发函回执及收函的相关证据。 | C53: 备选 | D53: 应收账款,主营业务收入,合同负债 | H53: D7-6 | J53: 收入 Revenues-10
A54: （1） | B54: 核实快递物流信息、比对回函印章和签字，确认回函联系人及回函地址的真实性。 | C54: 备选 | D54: 应收账款,主营业务收入,合同负债
A55: （2） | B55: 分析核实未回函、回函不符及回函率较低的原因，必要时实施再次发函、现场走访等程序，获取账面记录与外部证据矛盾的审计证据。 | C55: 备选 | D55: 应收账款,主营业务收入,合同负债
A56: （3） | B56: 回函情况较好时，应结合风险评估情况及各类风险迹象，考虑串通舞弊、伪造交易的可能性等。 | C56: 备选 | D56: 应收账款,主营业务收入,合同负债
A57: 4 | B57: 如果被询证者以传真、电子邮件等方式回函，审计项目组应当直接接收，并要求被询证者在审计报告日之前寄回询证函原件。如果审计项目组在审计报告日之前未收到询证函原件，应当实施以下程序： | C57: 备选 | D57: 应收账款,主营业务收入,合同负债 | J57: 收入 Revenues-10
A58: (1) | B58: 对于以传真方式收到的回函，需致电被询证者并与其确认回函的真实性。并将执行上述确认过程的审计人员姓名及日期、获得被询证者电话的方式、被询证者联络人员姓名及所属部门、沟通的过程及其结果等内容清晰地记录在审计工作底稿中。 | C58: 备选 | D58: 应收账款,主营业务收入,合同负债 | J58: 收入 Revenues-10
A59: (2) | B59: 对于以电子邮件方式收到的回函，审计项目组应当采用与上条中所述相同的方式与被询者确认回函的真实性，并在审计工作底稿中予以记录。采用电子邮件方式收到函证的控制要点详见函证技术提示4号，链接为：https://www.gt-china.com.cn/article_view.php?id=9691。 | C59: 备选 | D59: 应收账款,主营业务收入,合同负债 | J59: 收入 Revenues-10
A60: 5 | B60: 利用第三方电子函证平台收发函证的，项目组应当评估第三方电子函证平台服务的可靠性，了解资质认证或有关控制设计及运行的有效性。第三方电子询证函平台的安全性评估内容相关要点详见函证技术提示3号，链接为：https://www.gt-china.com.cn/article_view.php?id=9682 | C60: 备选 | D60: 应收账款,主营业务收入,合同负债
A61: 6 | B61: 调查那些退回、无法寄到的函证，确定相关账户是否真实。 | C61: 备选 | D61: 应收账款,主营业务收入,合同负债 | J61: 收入 Revenues-10
A62: 7 | B62: 对未回应客户执行二次发函。 | C62: 备选 | D62: 应收账款,主营业务收入,合同负债 | J62: 收入 Revenues-10
A63: 8 | B63: 针对最终未回函的全部账户实施替代审计程序 | C63: 备选 | D63: 应收账款,主营业务收入,合同负债 | H63: D7-10 | J63: 收入 Revenues-10
A64: 9 | B64: 编制“合同资产函证结果汇总表”，对函证结果进行评价。 | C64: 备选 | D64: 应收账款,主营业务收入,合同负债 | H64: D7-4 | J64: 收入 Revenues-10
A65: (1) | B65: 分析不符事项原因，编制“合同资产函证结果调节表”进行调节，并检查支持凭证；如果不符事项构成错报，重新考虑所实施审计程序的性质、时间和范围。 | C65: 备选 | D65: 应收账款,主营业务收入,合同负债 | J65: 收入 Revenues-10
A66: (2) | B66: 用样本评估工具推算总体误差。 在“未更正错报汇总表”中记录推断的误差。 | C66: 备选 | D66: 应收账款,主营业务收入,合同负债 | J66: 收入 Revenues-10
A67: 10 | B67: 对于管理层不允许寄发询证函的，列出客户清单，询问管理层不允许寄发的原因，并就其原因的正当、合理性收集证据。 | C67: 备选 | D67: 应收账款,主营业务收入,合同负债 | H67: D7-10 | J67: 收入 Revenues-10
A68: (1) | B68: 评价管理层不允许寄发询证函对评估的重大错报风险（包括舞弊风险）的影响，考虑对其他审计程序的性质、时间安排和范围的影响。 | C68: 备选 | D68: 应收账款,主营业务收入,合同负债 | J68: 收入 Revenues-10
A69: (2) | B69: 实施替代审计程序，以获取相关、可靠的审计证据。 | C69: 备选 | D69: 应收账款,主营业务收入,合同负债 | J69: 收入 Revenues-10
A70: (3) | B70: 如果认为管理层不允许寄发询证函的原因不合理，或实施替代程序无法获取相关、可靠的审计证据，考虑是否表明存在舞弊或错报，与治理层进行沟通，并确定其对审计工作和审计意见的影响。 | C70: 备选 | D70: 应收账款,主营业务收入,合同负债 | J70: 收入 Revenues-10
A71: 九 | B71: 针对评估的舞弊风险等因素增加的审计程序。 | C71: 备选 | E71: AB | J71: 收入 Revenues-12
A72: 十 | B72: 确定需在财务报表中单独披露的信息已被记录。 | C72: 常规★ | E72: E | H72: D7-1
A73: 1 | B73: 分析合同资产是否正确列示。 | C73: 常规★ | E73: E
A74: 2 | B74: 检查与收入有关的信息是否恰当披露。 | C74: 常规★ | E74: E
A76: 补充-特定行业或业务审计程序N | J76: *不适用请删除 | M76: 删除
A77: 序号 | B77: 审计程序 | C77: 程序分类 | E77: 审计目标 | H77: 执行情况说明 （含底稿索引）
A78: 十 | B78: 对于向客户授予知识产权许可的合同 | C78: 备选 | E78: ABC | L78: 收入 Revenues-19
A79: 1 | B79: 属于客户仅在同时使用相关服务（例如，由被审计单位提供的在线服务，通过授予使用许可使客户能够访问相关内容）时才能获益的使用许可。 | C79: 备选
A80: 2 | B80: 判断被审计单位与知识产权许可相关的收入确认时点是否正确（与提供企业知识产权的使用权的许可相关的收入不得在客户能够使用许可并从中获益的期间开始之前确认）。 | C80: 备选 | D80: 主营业务收入,合同资产、应收账款
A81: 3 | B81: 对于约定按客户实际销售或使用情况收取特许权使用费的合同，收入确认时点是否正确（直至不确定性消除（即，在客户发生后续销售或使用）之前，企业不应就不确定的金额确认任何收入）。 | C81: 备选 | D81: 主营业务收入,合同资产、应收账款
A82: 十一 | B82: 针对网游企业。 | C82: 备选 | E82: ABCD
A83: 1 | B83: 检查线上线下充值活动。 | C83: 备选 | D83: 主营业务收入,合同资产、应收账款
A84: （1） | B84: 了解实物卡销售和充值流程，关注收入确认的时点是否适当。 | C84: 备选 | D84: 主营业务收入,合同资产、应收账款
A85: （2） | B85: 对线上及线下渠道充值情况、实物卡销售情况进行分析性复核。 | C85: 备选 | D85: 主营业务收入,合同资产、应收账款
A86: （3） | B86: 对金额较大的线下和线上渠道商进行背景调查并实地访谈。 | C86: 备选 | D86: 主营业务收入,合同资产、应收账款
A87: 4.2 | B87: 对于玩家的真实进行调查。 | C87: 备选 | D87: 主营业务收入,合同资产、应收账款
A88: （1） | B88: 电话或面对面访谈玩家验证身份真实性、登录情况、充值及消费情况，对充值超过一定金额的玩家进行面对面访谈。 | C88: 备选 | D88: 主营业务收入,合同资产、应收账款
A89: （2） | B89: 具备条件的实施玩家MAC分析。 | C89: 备选 | D89: 主营业务收入,合同资产、应收账款
A90: （3） | B90: 实施网络流量或费用分析，关注流量费用和收入、玩家数量的匹配关系，与行业指标背离的异常情况。 | C90: 备选 | D90: 主营业务收入,合同资产、应收账款
A91: （4） | B91: 分析玩家地域分布的合理性，是否存在玩家分布与收入分布不匹配情况。 | C91: 备选 | D91: 主营业务收入,合同资产、应收账款
A92: （5） | B92: 登录游戏社区了解用户评价。 | C92: 备选 | D92: 主营业务收入,合同资产、应收账款
A93: 4.3 | B93: 其他财务与非财务信息的印证。 | C93: 备选 | D93: 主营业务收入,合同资产、应收账款
A94: （1） | B94: 对平均在线人数、峰值在线人数、付费人数、人均消费金额等指标与收入的匹配关系进行分析性复核，关注异常情况。 | C94: 备选 | D94: 主营业务收入,合同资产、应收账款
... A96: （3） | B96: 分析是否存在异常交易的客户（如交易时间集中、同时进行若干笔交易、交易地点集中、交易时间过长、频繁交易等）。必要时，利用IT专家工作。 | C96: 备选 | D96: 主营业务收入,合同资产、应收账款
B98: 提示：
B99: 根据具体情况，按下述5条所述流程，执行分析程序：
B100: 证实分析性程序中使用的基础性数据是正确的，对已记录的金额作出预期，评价预期值是否足够精确以识别重大错报。 Verify that the underlying data used in the analytics is valid.
B101: 与可比前期（及预期）结果相比较。 Compare results to comparable prior periods (expectations).
B102: 与适当客户人员讨论重大的非预期的差异。 Discuss significant unexpected differences with appropriate client personnel.
B103: 考虑管理层解释的可信度，并在适当情况下进行证实。 Consider plausibility of responses and corroborate as appropriate.
...

Sheet 审定表D6-1
A1: 致同会计师事务所
A2: 合同资产审定表
A3: =底稿目录!A2 -> 被审计单位： | E3: =底稿目录!A4 -> 编制人： | H3: =底稿目录!A5 -> 编制日期： | K3: 索引号： | L3: =底稿目录!F5 -> D6-1
A4: =底稿目录!A3 -> 截止日：202X年12月31日 | E4: =底稿目录!A6 -> 复核人： | H4: =底稿目录!A7 -> 复核日期： | K4: 页次：
A5: 项目 | B5: 期初数 | F5: 期末数 | J5: 本期与上期比较 | L5: 原因分析
B6: 未审数 | C6: 账项调整 | D6: 重分类调整 | E6: 审定数 | F6: 未审数 | G6: 账项调整 | H6: 重分类调整 | I6: 审定数 | J6: 变动额 | K6: 变动率
A7: 一、合同资产原值
E8: =B8+C8+D8 -> 0 | I8: =F8+G8+H8 -> 0 | J8: =I8-E8 -> 0 | K8: =IF(AND(E8=0,I8=0),"",IF(AND(E8=0,I8>0),1,J8/E8))
E9: =B9+C9+D9 -> 0 | I9: =F9+G9+H9 -> 0 | J9: =I9-E9 -> 0 | K9: =IF(AND(E9=0,I9=0),"",IF(AND(E9=0,I9>0),1,J9/E9))
E10: =B10+C10+D10 -> 0 | I10: =F10+G10+H10 -> 0 | J10: =I10-E10 -> 0 | K10: =IF(AND(E10=0,I10=0),"",IF(AND(E10=0,I10>0),1,J10/E10))
E11: =B11+C11+D11 -> 0 | I11: =F11+G11+H11 -> 0 | J11: =I11-E11 -> 0 | K11: =IF(AND(E11=0,I11=0),"",IF(AND(E11=0,I11>0),1,J11/E11))
E12: =B12+C12+D12 -> 0 | I12: =F12+G12+H12 -> 0 | J12: =I12-E12 -> 0 | K12: =IF(AND(E12=0,I12=0),"",IF(AND(E12=0,I12>0),1,J12/E12))
A13: 小计 | B13: =SUM(B8:B12) -> 0 | C13: =SUM(C8:C12) -> 0 | D13: =SUM(D8:D12) -> 0 | E13: =SUM(E8:E12) -> 0 | F13: =SUM(F8:F12) -> 0 | G13: =SUM(G8:G12) -> 0 | H13: =SUM(H8:H12) -> 0 | I13: =SUM(I8:I12) -> 0 | J13: =I13-E13 -> 0 | K13: =IF(AND(E13=0,I13=0),"",IF(AND(E13=0,I13>0),1,J13/E13))
A14: 减：列示于其他非流动资产的合同资产
A15: 合同资产原值小计 | B15: =B13-B14 -> 0 | C15: =C13-C14 -> 0 | D15: =D13-D14 -> 0 | E15: =E13-E14 -> 0 | F15: =F13-F14 -> 0 | G15: =G13-G14 -> 0 | H15: =H13-H14 -> 0 | I15: =I13-I14 -> 0 | J15: =J13-J14 -> 0
A16: 二、合同资产坏账准备
A17: =A8 -> 0 | E17: =B17+C17+D17 -> 0 | I17: =F17+G17+H17 -> 0 | J17: =I17-E17 -> 0 | K17: =IF(AND(E17=0,I17=0),"",IF(AND(E17=0,I17>0),1,J17/E17))
A18: =A9 -> 0 | E18: =B18+C18+D18 -> 0 | I18: =F18+G18+H18 -> 0 | J18: =I18-E18 -> 0 | K18: =IF(AND(E18=0,I18=0),"",IF(AND(E18=0,I18>0),1,J18/E18))
A19: =A10 -> 0 | E19: =B19+C19+D19 -> 0 | I19: =F19+G19+H19 -> 0 | J19: =I19-E19 -> 0 | K19: =IF(AND(E19=0,I19=0),"",IF(AND(E19=0,I19>0),1,J19/E19))
A20: =A11 -> 0 | E20: =B20+C20+D20 -> 0 | I20: =F20+G20+H20 -> 0 | J20: =I20-E20 -> 0 | K20: =IF(AND(E20=0,I20=0),"",IF(AND(E20=0,I20>0),1,J20/E20))
A21: =A12 -> 0 | E21: =B21+C21+D21 -> 0 | I21: =F21+G21+H21 -> 0 | J21: =I21-E21 -> 0 | K21: =IF(AND(E21=0,I21=0),"",IF(AND(E21=0,I21>0),1,J21/E21))
A22: 小计 | B22: =SUM(B17:B21) -> 0 | C22: =SUM(C17:C21) -> 0 | D22: =SUM(D17:D21) -> 0 | E22: =SUM(E17:E21) -> 0 | F22: =SUM(F17:F21) -> 0 | G22: =SUM(G17:G21) -> 0 | H22: =SUM(H17:H21) -> 0 | I22: =SUM(I17:I21) -> 0 | J22: =I22-E22 -> 0 | K22: =IF(AND(E22=0,I22=0),"",IF(AND(E22=0,I22>0),1,J22/E22))
A23: 减：列示于其他非流动资产的合同资产
A24: 合同资产坏账准备小计 | B24: =B22-B23 -> 0 | C24: =C22-C23 -> 0 | D24: =D22-D23 -> 0 | E24: =E22-E23 -> 0 | F24: =F22-F23 -> 0 | G24: =G22-G23 -> 0 | H24: =H22-H23 -> 0 | I24: =I22-I23 -> 0 | J24: =J22-J23 -> 0
A25: 三、合同资产净值
A26: =A8 -> 0 | B26: =B8-B17 -> 0 | C26: =C8-C17 -> 0 | D26: =D8-D17 -> 0 | E26: =E8-E17 -> 0 | F26: =F8-F17 -> 0 | G26: =G8-G17 -> 0 | H26: =H8-H17 -> 0 | I26: =I8-I17 -> 0 | J26: =I26-E26 -> 0 | K26: =IF(AND(E26=0,I26=0),"",IF(AND(E26=0,I26>0),1,J26/E26))
A27: =A9 -> 0 | B27: =SUM(B28:B30) -> 0 | C27: =SUM(C28:C30) -> 0 | D27: =SUM(D28:D30) -> 0 | E27: =SUM(E28:E30) -> 0 | F27: =SUM(F28:F30) -> 0 | G27: =SUM(G28:G30) -> 0 | H27: =SUM(H28:H30) -> 0 | I27: =SUM(I28:I30) -> 0 | J27: =I27-E27 -> 0 | K27: =IF(AND(E27=0,I27=0),"",IF(AND(E27=0,I27>0),1,J27/E27))
A28: =A10 -> 0 | B28: =B10-B19 -> 0 | C28: =C10-C19 -> 0 | D28: =D10-D19 -> 0 | E28: =E10-E19 -> 0 | F28: =F10-F19 -> 0 | G28: =G10-G19 -> 0 | H28: =H10-H19 -> 0 | I28: =I10-I19 -> 0 | J28: =I28-E28 -> 0 | K28: =IF(AND(E28=0,I28=0),"",IF(AND(E28=0,I28>0),1,J28/E28))
A29: =A11 -> 0 | B29: =B11-B20 -> 0 | C29: =C11-C20 -> 0 | D29: =D11-D20 -> 0 | E29: =E11-E20 -> 0 | F29: =F11-F20 -> 0 | G29: =G11-G20 -> 0 | H29: =H11-H20 -> 0 | I29: =I11-I20 -> 0 | J29: =I29-E29 -> 0 | K29: =IF(AND(E29=0,I29=0),"",IF(AND(E29=0,I29>0),1,J29/E29))
A30: =A12 -> 0 | B30: =B12-B21 -> 0 | C30: =C12-C21 -> 0 | D30: =D12-D21 -> 0 | E30: =E12-E21 -> 0 | F30: =F12-F21 -> 0 | G30: =G12-G21 -> 0 | H30: =H12-H21 -> 0 | I30: =I12-I21 -> 0 | J30: =I30-E30 -> 0 | K30: =IF(AND(E30=0,I30=0),"",IF(AND(E30=0,I30>0),1,J30/E30))
A31: 小计 | B31: =SUM(B26:B30) -> 0 | C31: =SUM(C26:C30) -> 0 | D31: =SUM(D26:D30) -> 0 | E31: =SUM(E26:E30) -> 0 | F31: =SUM(F26:F30) -> 0 | G31: =SUM(G26:G30) -> 0 | H31: =SUM(H26:H30) -> 0 | I31: =SUM(I26:I30) -> 0 | J31: =I31-E31 -> 0 | K31: =IF(AND(E31=0,I31=0),"",IF(AND(E31=0,I31>0),1,J31/E31))
A32: 减：列示于其他非流动资产的合同资产 | B32: =B14-B23 -> 0 | C32: =C14-C23 -> 0 | D32: =D14-D23 -> 0 | E32: =SUM(E27,E28) -> 0 | F32: =F14-F23 -> 0 | G32: =G14-G23 -> 0 | H32: =H14-H23 -> 0 | I32: =SUM(I27,I28) -> 0 | J32: =I32-E32 -> 0 | K32: =IF(AND(E32=0,I32=0),"",IF(AND(E32=0,I32>0),1,J32/E32))
A33: 合同资产净值合计 | B33: =B31-B32 -> 0 | C33: =C31-C32 -> 0 | D33: =D31-D32 -> 0 | E33: =E31-E32 -> 0 | F33: =F31-F32 -> 0 | G33: =G31-G32 -> 0 | H33: =H31-H32 -> 0 | I33: =I31-I32 -> 0 | J33: =J31-J32 -> 0
A34: 试算平衡表数
A35: 差异数 | E35: =E33-E34 -> 0 | I35: =I33-I34 -> 0
A36: 1.审计说明
A37: （1）合同资产本期较上期增加（负数为减少）： | E37: =IF(AND(E33=0,I33=0),0,IF(AND(E33=0,I33>0),1,(I33-E33)/E33)) -> 0
A38: 主要原因（比例超过30%的）：
A40: （2）情况说明
A42: 2.审计结论

Sheet 附注披露信息(上市公司）
A1: 致同会计师事务所
A2: 附注披露信息（上市公司）
A3: =底稿目录!A2 -> 被审计单位： | C3: =底稿目录!A4 -> 编制人： | E3: =底稿目录!A5 -> 编制日期： | J3: 索引：D7-1
A4: =底稿目录!A3 -> 截止日：202X年12月31日 | C4: =底稿目录!A6 -> 复核人： | E4: =底稿目录!A7 -> 复核日期： | J4: 页次：
A5: 附注披露信息：
A6: 合同资产（以下不适用的，请删除）
A7: 1、合同资产
A8: 项 目 | B8: 期末余额 | E8: 上年年末余额
B9: 账面余额 | C9: 减值准备 | D9: 账面价值 | E9: 账面余额 | F9: 减值准备 | G9: 账面价值
A10: 单项计提坏账准备 | B10: ='审定表D6-1'!I8 -> 0 | C10: ='审定表D6-1'!I17 -> 0 | D10: =B10-C10 -> 0 | E10: ='审定表D6-1'!E8 -> 0 | F10: ='审定表D6-1'!E17 -> 0 | G10: =E10-F10 -> 0
A11: 按组合计提坏账准备 | B11: ='审定表D6-1'!I9 -> 0 | C11: ='审定表D6-1'!I18 -> 0 | D11: =B11-C11 -> 0 | E11: ='审定表D6-1'!E9 -> 0 | F11: ='审定表D6-1'!E18 -> 0 | G11: =E11-F11 -> 0
A12: 其中：业务类型组合 | B12: ='审定表D6-1'!J10 -> 0 | C12: ='审定表D6-1'!I19 -> 0 | D12: =B12-C12 -> 0 | E12: ='审定表D6-1'!E10 -> 0 | F12: ='审定表D6-1'!E19 -> 0 | G12: =E12-F12 -> 0
A13: 客户类型组合 | B13: ='审定表D6-1'!J11 -> 0 | C13: ='审定表D6-1'!I20 -> 0 | D13: =B13-C13 -> 0 | E13: ='审定表D6-1'!E11 -> 0 | F13: ='审定表D6-1'!E20 -> 0 | G13: =E13-F13 -> 0
A14: ……组合 | B14: ='审定表D6-1'!J12 -> 0 | C14: ='审定表D6-1'!I21 -> 0 | D14: =B14-C14 -> 0 | E14: ='审定表D6-1'!E12 -> 0 | F14: ='审定表D6-1'!E21 -> 0 | G14: =E14-F14 -> 0
A16: 小 计 | B16: =B10+B11 -> 0 | C16: =C10+C11 -> 0 | D16: =B16-C16 -> 0 | E16: =E10+E11 -> 0 | F16: =F10+F11 -> 0 | G16: =E16-F16 -> 0
A17: 减：列示于其他非流动资产的合同资产
A18: 合 计 | B18: =B16-B17 -> 0 | C18: =C16-C17 -> 0 | D18: =D16-D17 -> 0 | E18: =E16-E17 -> 0 | F18: =F16-F17 -> 0 | G18: =G16-G17 -> 0
A19: 【提示：同一合同下的合同资产和合同负债应当以净额在资产负债表列示。净额为借方余额的，应当根据其流动性在“合同资产”或“其他非流动资产”项目中列示，其中预计自资产负债表日起一年内变现的，应当在“合同资产”项目列示，不应在“一年内到期的非流动资产”项目列示；净额为贷方余额的，应当根据其流动性在“合同负债”或“其他非流动负债”项目中列示，其中预计自资产负债表日起一年内到期的，应当在“合同负债”项目列示，不应在“一年内到期的非流动负债”项目列示。】
A20: 【或：披露格式如下】
A21: 项 目 | B21: 期末余额 | C21: 上年年末余额
A22: 合同资产 | B22: ='审定表D6-1'!I15 -> 0 | C22: ='审定表D6-1'!E20 -> 0
A23: 减：合同资产减值准备 | B23: ='审定表D6-1'!I24 -> 0 | C23: ='审定表D6-1'!E29 -> 0
A24: 小 计 | B24: =B22-B23 -> 0 | C24: =C22-C23 -> 0
A25: 减：列示于其他非流动资产的合同资产
A26: 合 计 | B26: =B24-B25 -> 0 | C26: =C24-C25 -> 0
A27: （1）本期合同资产账面价值的重大变动
A28: 项 目 | B28: 变动金额 | C28: 变动原因
A35: 合 计
A36: 说明：
A37: 1、履行履约义务的时间与通常的付款时间之间的关系，以及此类因素对合同资产（如果对合同负债产生影响在合同负债科目下说明）账面价值的影响的定量或定性信息。
A38: 2、合同资产的账面价值在本期内发生的重大变动的情形包括：
A39: ①企业合并导致的变动；
A40: ②对收入进行累积追加调整导致的相关合同资产和合同负债的变动，此类调整可能源于估计履约进度的变化、估计交易价格的变化（包括对于可变对价是否受到限制的评估发生变化）或者合同变更；
A41: ③对合同对价的权利成为无条件权利（即，合同资产重分类为应收款项）的时间安排发生变化。
A42: （2）合同资产减值准备计提情况
A43: 类别 | B43: 期末余额 | G43: 上年年末余额
B44: 账面余额 | D44: 减值准备 | F44: 账面价值 | G44: 账面余额 | I44: 减值准备 | K44: 账面价值
B45: 金额 | C45: 比例(%) | D45: 金额 | E45: 预期信用损失率(%) | G45: 金额 | H45: 比例(%) | I45: 金额 | J45: 预期信用损失率(%)
A46: 按单项计提坏账准备 | B46: =SUM(B47:B49) -> 0 | C46: =IFERROR(B46/$B$49,0) -> 0 | D46: =SUM(D47:D49) -> 0 | E46: =IFERROR(D46/B46,0) -> 0 | F46: =B46-D46 -> 0 | G46: =SUM(G47:G49) -> 0 | H46: =IFERROR(G46/$G$49,0) -> 0 | I46: =SUM(I47:I49) -> 0 | J46: =IFERROR(I46/G46,0) -> 0 | K46: =G46-I46 -> 0
A47: 其中： | C47: =IFERROR(B47/$B$49,0) -> 0 | E47: =IFERROR(D47/B47,0) -> 0 | F47: =B47-D47 -> 0 | H47: =IFERROR(G47/$G$49,0) -> 0 | J47: =IFERROR(I47/G47,0) -> 0 | K47: =G47-I47 -> 0
C48: =IFERROR(B48/$B$49,0) -> 0 | E48: =IFERROR(D48/B48,0) -> 0 | F48: =B48-D48 -> 0 | H48: =IFERROR(G48/$G$49,0) -> 0 | J48: =IFERROR(I48/G48,0) -> 0 | K48: =G48-I48 -> 0
C49: =IFERROR(B49/$B$49,0) -> 0 | E49: =IFERROR(D49/B49,0) -> 0 | F49: =B49-D49 -> 0 | H49: =IFERROR(G49/$G$49,0) -> 0 | J49: =IFERROR(I49/G49,0) -> 0 | K49: =G49-I49 -> 0
A50: 按组合计提坏账准备 | B50: =SUM(B51:B53) -> 0 | C50: =IFERROR(B50/$B$49,0) -> 0 | D50: =SUM(D51:D53) -> 0 | E50: =IFERROR(D50/B50,0) -> 0 | F50: =B50-D50 -> 0 | G50: =SUM(G51:G53) -> 0 | H50: =IFERROR(G50/$G$49,0) -> 0 | I50: =SUM(I51:I53) -> 0 | J50: =IFERROR(I50/G50,0) -> 0 | K50: =G50-I50 -> 0
A51: 其中： | C51: =IFERROR(B51/$B$49,0) -> 0 | E51: =IFERROR(D51/B51,0) -> 0 | F51: =B51-D51 -> 0 | H51: =IFERROR(G51/$G$49,0) -> 0 | J51: =IFERROR(I51/G51,0) -> 0 | K51: =G51-I51 -> 0
C52: =IFERROR(B52/$B$49,0) -> 0 | E52: =IFERROR(D52/B52,0) -> 0 | F52: =B52-D52 -> 0 | H52: =IFERROR(G52/$G$49,0) -> 0 | J52: =IFERROR(I52/G52,0) -> 0 | K52: =G52-I52 -> 0
C53: =IFERROR(B53/$B$49,0) -> 0 | E53: =IFERROR(D53/B53,0) -> 0 | F53: =B53-D53 -> 0 | H53: =IFERROR(G53/$G$49,0) -> 0 | J53: =IFERROR(I53/G53,0) -> 0 | K53: =G53-I53 -> 0
A54: 合 计 | B54: =B46+B50 -> 0 | C54: =IFERROR(B54/$B$49,0) -> 0 | D54: =D46+D50 -> 0 | E54: =IFERROR(D54/B54,0) -> 0 | F54: =F46+F50 -> 0 | G54: =G46+G50 -> 0 | H54: =IFERROR(G54/$G$49,0) -> 0 | I54: =I46+I50 -> 0 | J54: =IFERROR(I54/G54,0) -> 0 | K54: =K46+K50 -> 0
A55: 按单项计提坏账准备：
A56: 名 称 | B56: 期末余额
B57: 账面余额 | C57: 坏账准备 | D57: 预期信用损失率(%) | E57: 计提理由
D58: =IFERROR(C58/B58,0) -> 0
D59: =IFERROR(C59/B59,0) -> 0
A60: 合 计 | B60: =SUM(B58:B59) -> 0 | C60: =SUM(C58:C59) -> 0 | D60: =IFERROR(C60/B60,0) -> 0 | E60: /
A61: 续：
A62: 名 称 | B62: 上年年末余额
B63: 账面余额 | C63: 坏账准备 | D63: 预期信用损失率(%) | E63: 计提理由
D64: =IFERROR(C64/B64,0) -> 0
D65: =IFERROR(C65/B65,0) -> 0
A66: 合 计 | B66: =SUM(B64:B65) -> 0 | C66: =SUM(C64:C65) -> 0 | D66: =IFERROR(C66/B66,0) -> 0
A67: 按组合计提坏账准备：
A68: 组合计提项目：工程施工
B69: 期末余额 | E69: 上年年末余额
B70: 合同资产 | C70: 坏账准备 | D70: 预期信用损失率(%) | E70: 合同资产 | F70: 坏账准备 | G70: 预期信用损失率(%)
A71: 1年以内 | D71: =IFERROR(C71/B71,0) -> 0 | G71: =IFERROR(F71/E71,0) -> 0
A72: 1至2年 | D72: =IFERROR(C72/B72,0) -> 0 | G72: =IFERROR(F72/E72,0) -> 0
A73: 2至3年 | D73: =IFERROR(C73/B73,0) -> 0 | G73: =IFERROR(F73/E73,0) -> 0
A74: …… | D74: =IFERROR(C74/B74,0) -> 0 | G74: =IFERROR(F74/E74,0) -> 0
A75: 合 计 | B75: =SUM(B71:B74) -> 0 | C75: =SUM(C71:C74) -> 0 | D75: =IFERROR(C75/B75,0) -> 0 | E75: =SUM(E71:E74) -> 0 | F75: =SUM(F71:F74) -> 0 | G75: =IFERROR(F75/E75,0) -> 0
A76: 组合计提项目：质量保证金
B77: 期末余额 | E77: 上年年末余额
B78: 合同资产 | C78: 坏账准备 | D78: 预期信用损失率(%) | E78: 合同资产 | F78: 坏账准备 | G78: 预期信用损失率(%)
A79: 1年以内 | D79: =IFERROR(C79/B79,0) -> 0 | G79: =IFERROR(F79/E79,0) -> 0
A80: 1至2年 | D80: =IFERROR(C80/B80,0) -> 0 | G80: =IFERROR(F80/E80,0) -> 0
A81: 2至3年 | D81: =IFERROR(C81/B81,0) -> 0 | G81: =IFERROR(F81/E81,0) -> 0
A82: …… | D82: =IFERROR(C82/B82,0) -> 0 | G82: =IFERROR(F82/E82,0) -> 0
A83: 合 计 | B83: =SUM(B79:B82) -> 0 | C83: =SUM(C79:C82) -> 0 | D83: =IFERROR(C83/B83,0) -> 0 | E83: =SUM(E79:E82) -> 0 | F83: =SUM(F79:F82) -> 0 | G83: =IFERROR(F83/E83,0) -> 0
A84: （3）本期计提、收回或转回的合同资产减值准备情况
A85: 项 目 | B85: 本期计提 | C85: 本期转回 | D85: 本期转销/核销 | E85: 原因
A89: 合 计 | B89: =SUM(B86:B88) -> 0 | C89: =SUM(C86:C88) -> 0 | D89: =SUM(D86:D88) -> 0

Sheet 附注披露信息（国企）
A1: 致同会计师事务所
A2: 附注披露信息（国企）
A3: =底稿目录!A2 -> 被审计单位： | C3: =底稿目录!A4 -> 编制人： | E3: =底稿目录!A5 -> 编制日期： | G3: 索引：D7-1
A4: =底稿目录!A3 -> 截止日：202X年12月31日 | C4: =底稿目录!A6 -> 复核人： | E4: =底稿目录!A7 -> 复核日期： | G4: 页次：1
A5: 附注披露信息：
A6: 合同资产
A7: （1）合同资产情况
A8: 项 目 | B8: 期末数 | E8: 期初数
B9: 账面余额 | C9: 减值准备 | D9: 账面价值 | E9: 账面余额 | F9: 减值准备 | G9: 账面价值
A10: 单项计提坏账准备 | B10: ='审定表D6-1'!I8 -> 0 | C10: ='审定表D6-1'!I17 -> 0 | D10: =B10-C10 -> 0 | E10: ='审定表D6-1'!E8 -> 0 | F10: ='审定表D6-1'!E17 -> 0 | G10: =E10-F10 -> 0
A11: 按组合计提坏账准备 | B11: ='审定表D6-1'!I9 -> 0 | C11: ='审定表D6-1'!I18 -> 0 | D11: =B11-C11 -> 0 | E11: ='审定表D6-1'!E9 -> 0 | F11: ='审定表D6-1'!E18 -> 0
A12: 其中：业务类型组合 | B12: ='审定表D6-1'!I10 -> 0 | C12: ='审定表D6-1'!I19 -> 0 | D12: =B12-C12 -> 0 | E12: ='审定表D6-1'!E10 -> 0 | F12: ='审定表D6-1'!E19 -> 0 | G12: =E12-F12 -> 0
A13: 客户类型组合 | B13: ='审定表D6-1'!I11 -> 0 | C13: ='审定表D6-1'!I20 -> 0 | D13: =B13-C13 -> 0 | E13: ='审定表D6-1'!E11 -> 0 | F13: ='审定表D6-1'!E20 -> 0 | G13: =E13-F13 -> 0
A14: ……组合 | B14: ='审定表D6-1'!I12 -> 0 | C14: ='审定表D6-1'!I21 -> 0 | D14: =B14-C14 -> 0 | E14: ='审定表D6-1'!E12 -> 0 | F14: ='审定表D6-1'!E21 -> 0 | G14: =E14-F14 -> 0
A16: 合 计 | B16: =B10+B11 -> 0 | C16: =C10+C11 -> 0 | D16: =D10+D11 -> 0 | E16: =E10+E11 -> 0 | F16: =F10+F11 -> 0 | G16: =G10+G11 -> 0
A18: （2）合同资产减值准备
A19: 项 目 | B19: 期初数 | C19: 本期变动金额 | F19: 期末数
C20: 计提 | D20: 转回 | E20: 转销/核销 | G20: 原因
F21: =B21+C21-D21-E21 -> 0
F22: =B22+C22-D22-E22 -> 0
F23: =B23+C23-D23-E23 -> 0
A24: 合 计 | B24: =SUM(B21:B23) -> 0 | C24: =SUM(C21:C23) -> 0 | D24: =SUM(D21:D23) -> 0 | E24: =SUM(E21:E23) -> 0 | F24: =SUM(F21:F23) -> 0
A25: （3）本期合同资产账面价值的重大变动【国资委格式未要求披露】
A26: 项 目 | B26: 变动金额 | C26: 变动原因
A31: 合 计 | B31: =SUM(B27:B30) -> 0
A32: 1、说明履行履约义务的时间与通常的付款时间之间的关系，以及此类因素对合同资产（如果对合同负债产生影响在合同负债科目下说明）账面价值的影响的定量或定性信息。
A33: 2、说明合同资产的账面价值在本期内发生的重大变动的情形包括：
A34: ①企业合并导致的变动；
A35: ②对收入进行累积追加调整导致的相关合同资产和合同负债的变动，此类调整可能源于估计履约进度的变化、估计交易价格的变化（包括对于可变对价是否受到限制的评估发生变化）或者合同变更；
A36: ③对合同对价的权利成为无条件权利（即，合同资产重分类为应收款项）的时间安排发生变化。

Sheet 明细表D6-2
A1: 致同会计师事务所
A2: 合同资产明细表
A3: =底稿目录!A2 -> 被审计单位： | J3: =底稿目录!A4 -> 编制人： | T3: =底稿目录!A5 -> 编制日期： | AC3: 索引号： | AD3: =底稿目录!F8 -> D6-2
A4: =底稿目录!A3 -> 截止日：202X年12月31日 | J4: =底稿目录!A6 -> 复核人： | T4: =底稿目录!A7 -> 复核日期： | AC4: 页次：
A5: 一、审计目标:
A6: 合同资产以恰当的金额包括在财务报表中，与之相关的计价或分摊调整已恰当记录，相关披露已得到恰当计量和描述
A7: 二、审计过程：
A8: 1.核对企业提供的明细表，关注合同资产贷方非收款减少和借方其他调整的情况。
A9: 2.与客户讨论并记录各主要明细项目的性质，并对波动较大的内容进行分析。根据相关审计情况，确定调整事项。
A10: 3.对合同资产进行账龄分析，结合账龄的分析关注长期不结转应收账款的原因。
A11: 4.结合工程施工收入底稿<D4- >核对合同资产是否按照会计准则规定正确列报。
A12: 序号 | B12: 合同名称/项目名称 | C12: 类型 | D12: 客户名称 | E12: 公司代码 | F12: 关联关系 | G12: 期初未审数 | H12: 期初账项调整 | I12: 期初重分类调整 | J12: 期初审定余额 | K12: 期初审定账龄 | O12: 借方发生 | P12: 贷方发生 | Q12: 期末未审余额 | R12: 账项调整 | S12: 重分类调整 | T12: 期末审定余额 | U12: 期末审定账龄 | Y12: 1年以内收款权 | Z12: 1年以上收款权 | AA12: 是否在建设期或质保期内 | AB12: 信用风险组合方式 | AC12: 是否函证 | AD12: 期后结转金额
K13: 1年以下 | L13: 1～2年 | M13: ２～3年 | N13: 3年以上 | U13: 1年以下 | V13: 1～2年 | W13: ２～3年 | X13: 3年以上
A14: 1 | J14: =G14+H14+I14 -> 0 | Q14: =G14+O14-P14 -> 0 | T14: =Q14+R14+S14 -> 0 | AE14: 合并范围内关联方
A15: 2 | J15: =G15+H15+I15 -> 0 | Q15: =G15+O15-P15 -> 0 | T15: =Q15+R15+S15 -> 0 | AE15: 合并范围外关联方
A16: 3 | J16: =G16+H16+I16 -> 0 | Q16: =G16+O16-P16 -> 0 | T16: =Q16+R16+S16 -> 0 | AE16: 非关联方
A17: 4 | J17: =G17+H17+I17 -> 0 | Q17: =G17+O17-P17 -> 0 | T17: =Q17+R17+S17 -> 0
A18: 5 | J18: =G18+H18+I18 -> 0 | Q18: =G18+O18-P18 -> 0 | T18: =Q18+R18+S18 -> 0 | AE18: 单项计提坏账准备
A19: 6 | J19: =G19+H19+I19 -> 0 | Q19: =G19+O19-P19 -> 0 | T19: =Q19+R19+S19 -> 0 | AE19: 业务类型组合
A20: 7 | J20: =G20+H20+I20 -> 0 | Q20: =G20+O20-P20 -> 0 | T20: =Q20+R20+S20 -> 0 | AE20: 客户类型组合
A21: 8 | J21: =G21+H21+I21 -> 0 | Q21: =G21+O21-P21 -> 0 | T21: =Q21+R21+S21 -> 0
A22: 9 | J22: =G22+H22+I22 -> 0 | Q22: =G22+O22-P22 -> 0 | T22: =Q22+R22+S22 -> 0
A23: 10 | J23: =G23+H23+I23 -> 0 | Q23: =G23+O23-P23 -> 0 | T23: =Q23+R23+S23 -> 0
A24: 11 | J24: =G24+H24+I24 -> 0 | Q24: =G24+O24-P24 -> 0 | T24: =Q24+R24+S24 -> 0
A25: 12 | J25: =G25+H25+I25 -> 0 | Q25: =G25+O25-P25 -> 0 | T25: =Q25+R25+S25 -> 0
A26: 合 计 | G26: =SUM(G14:G25) -> 0 | H26: =SUM(H14:H25) -> 0 | I26: =SUM(I14:I25) -> 0 | J26: =SUM(J14:J25) -> 0 | K26: =SUM(K14:K25) -> 0 | L26: =SUM(L14:L25) -> 0 | M26: =SUM(M14:M25) -> 0 | N26: =SUM(N14:N25) -> 0 | ... Z26: =SUM(Z14:Z25) -> 0 | AD26: =SUM(AD14:AD25) -> 0
A27: 账龄占比 | J27: =IF((J26-SUM(K26:N26)=0),"OK","账龄与审定不匹配") -> OK | T27: =IF((T26-SUM(U26:X26)=0),"OK","账龄与审定不匹配") -> OK | V27: =IF(V26<=K26,TRUE,FALSE) -> TRUE | W27: =IF(W26<=L26,TRUE,FALSE) -> TRUE | X27: =IF(X26<=(M26+N26),TRUE,FALSE) -> TRUE
A28: 三、审计说明：
A32: 四、审计结论：
A34: 提示：
A35: 本科目核算企业已向客户转让商品而有权收取对价的权利。仅取决于时间流逝因素的权利不在本科目核算。
A36: 企业在客户实际支付合同对价或在该对价到期应付之前，已经向客户转让了商品的，应当按因已转让商品而有权收取的对价金额，借记本科目或“应收账款”科目，贷记“主营业务收入”“其他业务收入”等科目；
A37: 企业取得无条件收款权时，借记“应收账款”等科目，贷记本科目。
A38: 合同资产和合同负债应当在资产负债表中单独列示。同一合同下的合同资产和合同负债应当以净额列示，不同合同下的合同资产和合同负债不能互相抵销。

Sheet 合同资产减值准备明细表D6-3
A1: 致同会计师事务所
A2: 合同资产减值准备明细表
A3: 被审计单位名称： | F3: 编制人： | J3: 编制日期： | M3: 索引号： | N3: =底稿目录!F9 -> D6-3
A4: 截止日：2024年12月31日 | F4: 复核人： | J4: 复核日期： | M4: 页次：
A5: 一、审计目标：
A6: 合同资产以恰当的金额包括在财务报表中，与之相关的计价或分摊调整已恰当记录，相关披露已得到恰当计量和描述
A7: 二、审计过程
A8: 1.……
A10: 项目 | B10: 期初数 | F10: 本期增加 | H10: 本期减少 | K10: 期末数
B11: 未审余额 | C11: 账项调整 | D11: 重分类调整 | E11: 审定余额 | F11: 计提 | G11: 其他增加 | H11: 转回 | I11: 核销 | J11: 其他减少 | K11: 未审余额 | L11: 账项调整 | M11: 重分类调整 | N11: 审定余额
A12: 按单项评估计提 | B12: =SUM(B13:B16) -> 0 | C12: =SUM(C13:C16) -> 0 | D12: =SUM(D13:D16) -> 0 | E12: =SUM(E13:E16) -> 0 | F12: =SUM(F13:F16) -> 0 | G12: =SUM(G13:G16) -> 0 | H12: =SUM(H13:H16) -> 0 | I12: =SUM(I13:I16) -> 0 | J12: =SUM(J13:J16) -> 0 | K12: =B12+SUM(F12:G12)-SUM(H12:J12) -> 0 | L12: =SUM(L13:L16) -> 0 | M12: =SUM(M13:M16) -> 0 | N12: =K12+L12+M12 -> 0
A13: 其中： | E13: =B13+C13+D13 -> 0 | K13: =B13+SUM(F13:G13)-SUM(H13:J13) -> 0 | N13: =K13+L13+M13 -> 0
E14: =B14+C14+D14 -> 0 | K14: =B14+SUM(F14:G14)-SUM(H14:J14) -> 0 | N14: =K14+L14+M14 -> 0
E15: =B15+C15+D15 -> 0 | K15: =B15+SUM(F15:G15)-SUM(H15:J15) -> 0 | N15: =K15+L15+M15 -> 0
E16: =B16+C16+D16 -> 0 | K16: =B16+SUM(F16:G16)-SUM(H16:J16) -> 0 | N16: =K16+L16+M16 -> 0
A17: 信用风险组合计提 | B17: =SUM(B18:B21) -> 0 | C17: =SUM(C18:C21) -> 0 | D17: =SUM(D18:D21) -> 0 | E17: =SUM(E18:E21) -> 0 | F17: =SUM(F18:F21) -> 0 | G17: =SUM(G18:G21) -> 0 | H17: =SUM(H18:H21) -> 0 | I17: =SUM(I18:I21) -> 0 | J17: =SUM(J18:J21) -> 0 | K17: =B17+SUM(F17:G17)-SUM(H17:J17) -> 0 | L17: =SUM(L18:L21) -> 0 | M17: =SUM(M18:M21) -> 0 | N17: =K17+L17+M17 -> 0
A18: 其中： | E18: =B18+C18+D18 -> 0 | K18: =B18+SUM(F18:G18)-SUM(H18:J18) -> 0 | N18: =K18+L18+M18 -> 0
E19: =B19+C19+D19 -> 0 | K19: =B19+SUM(F19:G19)-SUM(H19:J19) -> 0 | N19: =K19+L19+M19 -> 0
E20: =B20+C20+D20 -> 0 | K20: =B20+SUM(F20:G20)-SUM(H20:J20) -> 0 | N20: =K20+L20+M20 -> 0
E21: =B21+C21+D21 -> 0 | K21: =B21+SUM(F21:G21)-SUM(H21:J21) -> 0 | N21: =K21+L21+M21 -> 0
A22: 合计 | B22: =B12+B17 -> 0 | C22: =C12+C17 -> 0 | E22: =E12+E17 -> 0 | F22: =F12+F17 -> 0 | G22: =G12+G17 -> 0 | H22: =H12+H17 -> 0 | I22: =I12+I17 -> 0 | J22: =J12+J17 -> 0 | K22: =K12+K17 -> 0 | L22: =L12+L17 -> 0 | ... N22: =N12+N17 -> 0
A23: 三、审计说明
A27: 四、审计结论

Sheet 调整分录汇总表D6-4
A1: 致同会计师事务所
A2: 合同资产调整分录汇总表
A3: =底稿目录!A2 -> 被审计单位： | D3: =底稿目录!A4 -> 编制人： | G3: =底稿目录!A5 -> 编制日期： | I3: 索引： | J3: =底稿目录!F10 -> D6-4
A4: =底稿目录!A3 -> 截止日：202X年12月31日 | D4: =底稿目录!A6 -> 复核人： | G4: =底稿目录!A7 -> 复核日期： | I4: 页次：
A5: 调整事项说明 | B5: 类别（报表调整/账项调整/其他） | C5: 报表项目 | D5: 科目名称 | E5: 附注项目 | F5: …… | G5: 借方调整金额 | H5: 贷方调整金额 | I5: 索引 | J5: 备注
A21: 提示：本底稿适用于调整分录较多、较复杂的项目，且仅列示与本报表项目相关的审计调整。项目组可根据项目实际情况选择是否使用该底稿。

Sheet 关联关系及交易检查D6-5
A1: 致同会计师事务所
A2: 合同资产关联关系及交易检查表
A3: =底稿目录!A2 -> 被审计单位： | E3: =底稿目录!A4 -> 编制人： | H3: =底稿目录!A5 -> 编制日期： | K3: 索引号： | L3: =底稿目录!F18 -> D6-5
A4: =底稿目录!A3 -> 截止日：202X年12月31日 | E4: =底稿目录!A6 -> 复核人： | H4: =底稿目录!A7 -> 复核日期： | K4: 页次：
A5: 一、审计目标
A6: 1.资产负债表中记录的合同资产是存在的； 2.所有应当记录的合同资产均已记录；3.记录的合同资产由被审计单位拥有或控制。
A7: 4.合同资产以恰当的金额包括在财务报表中，与之相关的计价调整已恰当记录。
A8: 二、审计过程
A9: 关联方名称 | B9: 关联关系 | C9: 期初余额 | D9: 借方发生 | E9: 贷方发生 | F9: 期末余额 | G9: 减：坏账准备 | H9: 账面价值 | I9: 发生时间及账龄 | J9: 发生原因（款项性质） | K9: 索引号 | L9: 备注
F10: =C10+D10-E10 -> 0 | H10: =F10-G10 -> 0
F11: =C11+D11-E11 -> 0 | H11: =F11-G11 -> 0
F12: =C12+D12-E12 -> 0 | H12: =F12-G12 -> 0
A13: 合计 | C13: =SUM(C10:C12) -> 0 | D13: =SUM(D10:D12) -> 0 | E13: =SUM(E10:E12) -> 0 | F13: =SUM(F10:F12) -> 0 | G13: =SUM(G10:G12) -> 0 | H13: =SUM(H10:H12) -> 0
A14: 三、审计说明：
A18: 四、审计结论：
B22: 勿改、勿删
B23: 实际控制人
B24: 控股股东
B25: 控股股东、实际控制人的附属企业
B26: 持有5%以上股份的法人或其他组织
B27: 联营企业
B28: 合营企业
B29: 董高监等关键管理人员
B30: 其他关联方

Sheet 合同资产检查表D6-6
A1: 致同会计师事务所
A2: 合同资产检查表
A3: =底稿目录!A2 -> 被审计单位： | E3: =底稿目录!A4 -> 编制人： | H3: =底稿目录!A5 -> 编制日期： | P3: 索引号： | Q3: =底稿目录!F19 -> D6-6
A4: =底稿目录!A3 -> 截止日：202X年12月31日 | E4: =底稿目录!A6 -> 复核人： | H4: =底稿目录!A7 -> 复核日期： | P4: 页次：
A5: 一、审计目标：
A6: 1.资产负债表中记录的合同资产是存在的，且已经记录在恰当的账户中；2.记录的合同资产由被审计单位拥有或控制；
A7: 3.合同资产以恰当的金额包括在财务报表中，与之相关的计价或分摊调整已恰当记录，相关披露已得到恰当计量和描述
A8: 二、审计过程：
A9: 1.样本选取标准与规模：
A10: 测试总体： | B10: 如应收账款借方发生额所有凭证共XX笔金额XX、贷方发生额所有凭证共XX笔金额XX | H10: 特定样本： | I10: XX金额以上（大额）、关联方/关联交易形成的款项、XX异常款项全部测试，共XX笔；
A11: 抽样总体： | B11: 测试总体扣除特定样本以外的样本，共XX笔、金额XX | H11: 确定的抽样样本量： | I11: 抽取XX笔（如果使用了样本计算器计算样本量，样本量计算过程见<XX>底稿）
A12: 抽样方法： | B12: 随机选样/系统选样/货币单元抽样/随意选样（非统计抽样适用） | H12: 抽样过程： | I12: 使用IDEA（XX抽样工具）选择XX数量、金额XX的样本进行测试，抽样工具中的样本选择过程和结果见<XX>底稿
A13: 2.测试：
A14: 测试内容说明：1.原始凭证是否齐全； 2.记账凭证与原始凭证是否相符；3.账务处理是否正确；4.是否记录于恰当的会计期间；5.……
A15: （1）本期增减变动检查（本期借方发生额可结合主营业务收入检查底稿完成）
A16: 客户名称 | B16: 记账凭证 | I16: 支持性文件 | J16: 核对内容 | O16: 索引号 | P16: 是否异常 | Q16: 备注说明
B17: 日期 | C17: 凭证编号 | D17: 业务内容 | E17: 对方科目 | F17: 对方明细科目 | G17: 借方金额 | H17: 贷方金额 | J17: 1 | K17: 2 | L17: 3 | M17: 4 | N17: 5
A31: 合计 | G31: =SUM(G18:G30) -> 0 | H31: =SUM(H18:H30) -> 0
A32: （2）期后贴现\背书\调整等检查
A33: 客户名称 | B33: 记账凭证 | H33: 支持性文件 | J33: 核对内容 | O33: 索引号 | P33: 是否异常 | Q33: 备注说明
B34: 日期 | C34: 凭证编号 | D34: 业务内容 | E34: 对方科目 | F34: 对方明细科目 | G34: 贷方金额 | J34: 1 | K34: 2 | L34: 3 | M34: 4 | N34: 5
A40: 合计 | G40: =SUM(G35:G39) -> 0
A41: 三、审计说明
A42: 1.本期发生额、期末余额检查比例： | D42: 方向 | E42: 账面金额 | F42: 检查金额 | G42: 检查比例 | H42: 如果检查比例较低应扩大检查样本量或说明原因
D43: 本期借方 | E43: ='明细表D6-2'!O26 -> 0 | F43: =G31 -> 0 | G43: =ROUND(F43/E43,4) -> #DIV/0!
D44: 本期贷方 | E44: ='明细表D6-2'!P26 -> 0 | F44: =H31 -> 0 | G44: =ROUND(F44/E44,2) -> #DIV/0!
D45: 期末余额 | E45: ='明细表D6-2'!T26 -> 0 | F45: =G40 -> 0 | G45: =ROUND(F45/E45,2) -> #DIV/0!
A46: 2.……
A48: 四、审计结论：

Sheet 合同资产减值准备会计政策检查D6-7
A1: 致同会计师事务所
A2: 合同资产减值准备会计政策检查
A3: =底稿目录!A2 -> 被审计单位： | C3: =底稿目录!A4 -> 编制人： | E3: =底稿目录!A5 -> 编制日期： | H3: 索引号： | I3: =底稿目录!F20 -> D6-7
A4: =底稿目录!A3 -> 截止日：202X年12月31日 | C4: =底稿目录!A6 -> 复核人： | E4: =底稿目录!A7 -> 复核日期： | H4: 页次：
A5: 一、审计目标：
A6: 1.资产负债表中记录的合同资产是存在的；
A7: 2.合同资产以恰当的金额包括在财务报表中，与之相关的计价调整已恰当记录。
A8: 二、审计过程：
A9: 1.……
A12: （一）合同资产减值准备计提会计政策
A16: 【应说明被审计单位应收账款坏账准备信用风险组合划分依据、预期信用损失计量方法等】
A17: （二）被审计单位历史坏账损失情况
A21: 【应说明被审计单位应收账款历史损失率的数据来源，以及项目组核实该等数据所执行的程序。需考虑货币的时间价值】
A22: （三）前瞻性信息的来源及其影响
A26: 【应说明被审计单位确定预期损失率的前瞻性信息来源（包括内部模型、第三方服务机构或利用外部专家工作等，以及项目组对前瞻性信息可靠性所执行的程序】
A27: （四）同行业公司的会计政策
... A50: 上市公司合同资产减值准备会计政策披露示例：
A51: 中国中铁 | B51: 对于应收票据及应收账款和合同资产，无论是否存在重大融资成分，本集团均按照整个存续期的预期信用损失计量损失准备。 当单项应收票据及应收账款和合同资产无法以合理成本评估预期信用损失的信息时，本集团依据信用风险特征将应收票据及应收账款和合同资产划分为若干组合，在组合基础上计算预期信用损失，确定组合的依据如下： 合同资产组合1 基础设施建设项目 合同资产组合2 土地一级开发项目 合同资产组合3 处于建设期的金融资产模式的PPP 项目 合同资产组合4 未到期的质保金 对于划分为组合的应收票据和合同资产，本集团参考历史信用损失经验，结合当前状况以及对未来经济状况的预测，通过违约风险敞口和整个存续期预期信用损失率，计算预期信用损失。
A52: 中国中冶 | B52: 在预期信用损失法下，本集团对由新收入准则规范的交易而形成的未包含重大融资成分或不考虑不超过一年的合同中的融资成分的合同资产与应收账款按照相当于整个存续期内预期信用损失的金额计量信用损失准备。信用损失准备的确认需要运用判断和估计。如重新估计结果与现有估计存在差异，该差异将会影响估计改变期间的利润、合同资产和应收账款账面价值。 确定组合的依据如下： 工程承包服务相关的合同资产 工程质保金相关的合同资产
A53: 中煤能源 | B53: 本集团对租赁应收款在单项资产的基础上确定其信用损失，对应收账款、合同资产、债权投资除对发生重大财务困难的债务人在单项资产的基础上确定其信用损失外，对其余款项在组合基础上采用减值矩阵确定相关金融工具的信用损失。 10.2.4 本集团依据信用风险特征将应收票据及应收账款和合同资产划分为若干组合 ，在组合基础上计算预期信用损失，确定组合的依据如下： • 应收账款\合同资产组合A 信用优良。在未来的信用风险很低，自身抗风险能力很强，不确定性因素对其经营与发展的影响很小。 • 应收账款\合同资产组合B ，信用较好。在未来的信用风险较低，自身有一定抗风险能力，但是可能存在一些影响其未来经营与发展的不确定性因素。 • 应收账款\合同资产组合C ，信用一般。在未来存在一定的信用风险，经营状况、盈利水平及未来发展易受不确定因素的影响。 • 应收账款\合同资产组合D ，信用较差。在未来的信用风险较高，未来前景不明朗或不安全，可能出现逾期非常严重的应收账款、合同资产。 对于划分为组合的应收账款，本集团参考历史信用损失经验，结合当前状况以及对未来经济状况的预测，编制应收账款账龄与整个存续期预期信用损失率对照表，计算预期信用损失。 对于划分为组合的合同资产，本集团参考历史信用损失经验，结合当前状况以及对未来经济状况的预测，通过违约风险敞口和整个存续期预期信用损失率，计算预期信用损失。
A54: 长飞光纤 | B54: 对于应收账款，本集团始终按照相当于整个存续期内预期信用损失的金额计量其损失准备。本集团基于历史信用损失经验、使用准备矩阵计算上述金融资产的预期信用损失，相关历史经验根据资产负债表日借款人的特定因素、以及对当前状况和未来经济状况预测的评估进行调整。 本公司根据历史经验，不同细分客户群体发生损失的情况存在差异，将本公司客户细分为以下群体： 群体1：集团外关联方；群体2：中国电信网络运营商及其他信用记录良好的企业；群体3：除群体1、2以外的其他客户。 本集团始终按照相当于整个存续期内预期信用损失的金额计量应收账款的减值准备，并以逾期天数与违约损失率对照表为基础计算其预期信用损失。根据本集团的历史经验，不同细分客户群体发生损失的情况存在差异，因此本集团根据历史经验区分不同的客户群体根据逾期信息计算减值准备。 违约损失率基于过去5年的实际信用损失经验计算，并根据历史数据收集期间的经济状况、当前的经济状况与本集团所认为的预计存续期内的经济状况三者之间的差异进行调整。
A55: 中国中车 | B55: 本集团对由收入准则规范的交易形成的合同资产与应收账款、租赁应收款按照相当于整个存续期内预期信用损失的金额计量损失准备。 本集团除对单项金额重大或已发生信用减值的金融资产、合同资产、租赁应收款、贷款承诺和财务担保合同在单项资产/合同基础上确定其信用损失外，在组合基础上采用减值矩阵确定相关金融工具的信用损失。本集团以共同信用风险特征为依据，将金融工具分为不同组别。本集团采用的共同信用风险特征包括：金融工具类型、信用风险评级、担保物类型、剩余合同期限、债务人所处行业、债务人所处地理位置、担保品相对于金融资产的价值等。 确定组合的依据如下： 销售商品 工程承包
A56: 美凯龙 | B56: 对于不含重大融资成分的应收款项以及合同资产，本集团运用简化计量方法，按照相当于整个存续期内的预期信用损失金额计量损失准备。 本集团基于单项和组合评估金融工具的预期信用损失。本集团考虑了不同客户的信用风险特征，以账龄组合为基础评估应收账款、其他应收款、合同资产和长期应收款等金融工具的预期信用损失。 确定组合的依据如下： 建筑施工及设计 项目前期品牌咨询委托管理费服务

Sheet 减值准备测算D6-8
A1: 致同会计师事务所
A2: 合同资产减值准备测算表
A3: =底稿目录!A2 -> 被审计单位： | C3: =底稿目录!A4 -> 编制人： | E3: =底稿目录!A5 -> 编制日期： | G3: 索引号： | H3: =底稿目录!F21 -> D6-8
A4: =底稿目录!A3 -> 截止日：202X年12月31日 | C4: =底稿目录!A6 -> 复核人： | E4: =底稿目录!A7 -> 复核日期： | G4: 页次：
A5: 一、审计目标
A6: 合同资产以恰当的金额包括在财务报表中，与之相关的计价调整已恰当记录。
A7: 二、审计过程
A8: 1.……
A10: （一）单项计提坏账准备
A11: 债务人名称 | B11: 审定账面余额 | C11: 预期信用损失率 | D11: 期末应计提坏账准备 | E11: 期末坏账准备账面余额 | F11: 差异 | G11: 计提依据及文件 | H11: 索引号
B12: ① | C12: ② | D12: ③=①×② | E12: ④ | F12: ⑤=③-④
D13: =B13*C13 -> 0 | F13: =B13-E13 -> 0
D14: =B14*C14 -> 0 | F14: =B14-E14 -> 0
D15: =B15*C15 -> 0 | F15: =B15-E15 -> 0
D16: =B16*C16 -> 0 | F16: =B16-E16 -> 0
D17: =B17*C17 -> 0 | F17: =B17-E17 -> 0
A18: 小计 | B18: =SUM(B13:B17) -> 0 | C18: =SUM(C13:C17) -> 0 | D18: =IF(B18=0,"",C18/B18) | E18: =SUM(E13:E17) -> 0 | F18: =SUM(F13:F17) -> 0
A19: （二）账龄组合计提坏账准备
A20: 账龄 | B20: 审定账面余额 | C20: 预期信用损失率 | D20: 期末应计提坏账准备 | E20: 期末坏账准备账面余额 | F20: 差异
B21: ① | C21: ② | D21: ③=①×② | E21: ④ | F21: ⑤=③-④
A22: 组合1：
A23: 1年以内 | D23: =B23*C23 -> 0 | F23: =D23-E23 -> 0
A24: 1年-2年 | D24: =B24*C24 -> 0 | F24: =D24-E24 -> 0
A25: 2年-3年 | D25: =B25*C25 -> 0 | F25: =D25-E25 -> 0
A26: 3年-4年 | D26: =B26*C26 -> 0 | F26: =D26-E26 -> 0
A27: 4年-5年 | D27: =B27*C27 -> 0 | F27: =D27-E27 -> 0
A28: 5年以上 | D28: =B28*C28 -> 0 | F28: =D28-E28 -> 0
A29: 小计 | B29: =SUM(B23:B28) -> 0 | D29: =SUM(D23:D28) -> 0 | E29: =SUM(E23:E28) -> 0 | F29: =SUM(F23:F28) -> 0
A30: 组合2：
A31: 1年以内 | D31: =B31*C31 -> 0 | F31: =D31-E31 -> 0
A32: 1年-2年 | D32: =B32*C32 -> 0 | F32: =D32-E32 -> 0
A33: 2年-3年 | D33: =B33*C33 -> 0 | F33: =D33-E33 -> 0
A34: 3年-4年 | D34: =B34*C34 -> 0 | F34: =D34-E34 -> 0
A35: 4年-5年 | D35: =B35*C35 -> 0 | F35: =D35-E35 -> 0
A36: 5年以上 | D36: =B36*C36 -> 0 | F36: =D36-E36 -> 0
A37: 小计 | B37: =SUM(B31:B36) -> 0 | D37: =SUM(D31:D36) -> 0 | E37: =SUM(E31:E36) -> 0 | F37: =SUM(F31:F36) -> 0
A38: 合计 | B38: =B37+B29 -> 0 | D38: =D37+D29 -> 0 | E38: =E37+E29 -> 0 | F38: =F37+F29 -> 0
A39: 三、审计说明
A43: 四、审计结论
A45: 提示：预期信用损失以客户的违约风险为基础，同一客户的违约风险相同，上市公司对于同一客户的合同资产与应收账款，采用不同计提比例计量
A46: 预期信用损失时，应充分析两者存在不同违约风险损失的原因及合理性。由于现金流缺口要基于预期能收到的现金流量进行计算，因此在计量合同
A47: 资产的预期信用损失时考虑的期限应截止于预期收取现金流量之日，即需要考虑合同资产转为应收款项后可能发生的信用违约事件造成的损失。
A48: 提示2：预期信用损失计量测试可参考应收账款预期信用损失计量示例。

Sheet 减值准备转回、核销检查表D6-9
A1: 致同会计师事务所
A2: 合同资产大额减值准备转回、核销检查表
A3: =底稿目录!A2 -> 被审计单位： | C3: =底稿目录!A4 -> 编制人： | E3: =底稿目录!A5 -> 编制日期： | G3: 索引号： | H3: =底稿目录!F22 -> D6-9
A4: =底稿目录!A3 -> 截止日：202X年12月31日 | C4: =底稿目录!A6 -> 复核人： | E4: =底稿目录!A7 -> 复核日期： | G4: 页次：
A5: 一、审计目标
A6: 合同资产以恰当的金额包括在财务报表中，与之相关的计价或分摊调整已恰当记录，相关披露已得到恰当计量和描述
A7: 二、审计过程
A8: 1.取得被审计单位大额合同资产减值准备及合同资产核销清单；
A9: 2.了解大额减值准备转回（收回）、核销的原因、方式，判断其合理性。
A10: 3.对于实际发生减值损失的，检查转销依据是否符合有关规定，会计处理是否正确。
A11: 4.已经确认并核销的减值重新收回的，检查其会计处理是否正确。
A12: （一）本期重要的减值准备转回检查
A13: 客户名称 | B13: 转回原因 | C13: 收回方式 | D13: 原确定减值准备的依据 | E13: 转回金额 | F13: 转销前累计已计提坏账准备金额 | G13: 合理性分析 | H13: 索引号
A17: 合 计 | E17: =SUM(E14:E16) -> 0 | F17: =SUM(F14:F16) -> 0
A18: （二）核销的合同资产检查
A19: 客户名称 | B19: 核销金额 | C19: 核销原因 | D19: 履行的核销程序 | E19: 是否由关联交易产生 | F19: 合理性分析 | G19: 索引号
A23: 合 计 | B23: =SUM(B20:B22) -> 0
A24: 三、审计说明
A28: 四、审计结论

Sheet GT_Custom
A1: C1 | B1: Custom 1
A2: C2 | B2: Custom 2
A3: C3 | B3: Custom 3
A4: C4 | B4: Custom 4
A5: C5 | B5: Custom 5
A6: C6 | B6: Custom 6
A7: C7 | B7: Custom 7
A8: C8 | B8: Custom 8
