Workbook
Name _13102: #REF!
Name _13302: #REF!
Name _13398: #REF!
Name _18102: #REF!
Name _18198: #REF!
Name _2003附注: [1]附注汇总!$C$5:$AY$646
Name _2其他资产_开办费除外_明细表: #REF!
Name _scn11: #REF!
Name _scn15: #REF!
Name _scn16: #REF!
Name _scn17: #REF!
Name _scn19: #REF!
Name _scn2: #REF!
Name _scn20: #REF!
Name _scn3: #REF!
Name _scn4: #REF!
Name _scn5: #REF!
Name _scn6: #REF!
Name _scn7: #REF!
Name _scn8: #REF!
Name _scn9: #REF!
Name _scq1: #REF!
Name _scq11: #REF!
Name _scq15: #REF!
Name _scq16: #REF!
Name _scq17: #REF!
Name _scq19: #REF!
Name _scq2: #REF!
Name _scq20: #REF!
Name _scq3: #REF!
Name _scq4: #REF!
Name _scq5: #REF!
Name _scq6: #REF!
Name _scq7: #REF!
Name _scq8: #REF!
Name _scq9: #REF!
Name a: #REF!
Name Approach: [2]选择键!$G$2:$G$6
Name as: #REF!
Name AS2WebLink1: #REF!
Name AS2WebLink10: #REF!
Name AS2WebLink11: #REF!
Name AS2WebLink12: #REF!
Name AS2WebLink13: #REF!
Name AS2WebLink14: #REF!
Name AS2WebLink15: #REF!
Name AS2WebLink16: #REF!
Name AS2WebLink17: #REF!
Name AS2WebLink18: #REF!
Name AS2WebLink19: #REF!
Name AS2WebLink2: #REF!
Name AS2WebLink21: #REF!
Name AS2WebLink22: #REF!
Name AS2WebLink23: #REF!
Name AS2WebLink24: #REF!
Name AS2WebLink3: #REF!
Name AS2WebLink4: #REF!
Name AS2WebLink5: #REF!
Name AS2WebLink6: #REF!
Name AS2WebLink7: #REF!

Sheet TB资产负债
A1: 资产负债表试算平衡
A2: =CONCATENATE("客户名称：",[28]说明!E23) -> 客户名称： | D2: =CONCATENATE("复核：",[28]说明!E37) -> 复核： | G2: 索引：
A3: =CONCATENATE("会计时点：",TEXT([28]说明!E32,"yyyy.mm.dd")) -> 会计时点：2019.12.31 | D3: 日期： | G3: 分页：
A4: 项目 | B4: 未审数 | C4: 账项调整 | E4: 报表调整 | G4: 审定数
C5: 借方 | D5: 贷方 | E5: 借方 | F5: 贷方
A6: =[28]报表格式!B5 -> 流动资产：
A7: =[28]报表格式!B6 -> 货币资金
A8: =[28]报表格式!B7 -> 交易性金融资产
A9: =[28]报表格式!B8 -> 以公允价值计量且其变动计入当期损益的金融资产
A10: =[28]报表格式!B9 -> 衍生金融资产
A11: =[28]报表格式!B10 -> 应收票据
A12: =[28]报表格式!B11 -> 应收账款
A13: =[28]报表格式!B12 -> 应收款项融资
A14: =[28]报表格式!B13 -> 预付款项
A15: =[28]报表格式!B14 -> 其他应收款
A16: =[28]报表格式!B15 -> 其中：应收利息
A17: =[28]报表格式!B16 -> 应收股利
... A52: =[28]报表格式!B51 -> 资 产 总 计
A53: 流动负债：
A54: 短期借款
A55: 交易性金融负债
A56: 以公允价值计量且其变动计入当期损益的金融负债
A57: 衍生金融负债
A58: 应付票据
A59: 应付账款
A60: 预收款项
A61: 合同负债
A62: 应付职工薪酬
A63: 应交税费
A64: 其他应付款
... A99: 负债和股东权益合计

Sheet TB损益
A1: 母公司利润及利润分配表试算平衡
A2: =CONCATENATE("客户名称：",[28]说明!E23) -> 客户名称： | D2: =CONCATENATE("编制：",[28]说明!E36) -> 编制： | G2: =CONCATENATE("复核：",[28]说明!E37) -> 复核： | K2: =[28]母公司TB资产!K2 -> 索引：
A3: =CONCATENATE("会计期间：",TEXT([28]说明!E30,"yyyy.mm.dd")) -> 会计期间：2019年度 | D3: =CONCATENATE("日期：",TEXT(NOW(),"yyyy.mm.dd")) -> 日期：2026.05.03 | G3: =[28]母公司TB资产!F3 -> 日期： | K3: =[28]母公司TB资产!K3 -> 分页：
A4: =IF((ROUND([28]母公司TB资产!K52,2))=(ROUND(#REF!,2)),"项 目","报表未调平!") -> #REF! | B4: 母公司汇总 | C4: 汇总抵销 | E4: 账项调整 | G4: 报表调整 | I4: 调后数 | J4: 剥离调整 | K4: 母公司审定数
C5: 借方 | D5: 贷方 | E5: 借方 | F5: 贷方 | G5: 借方 | H5: 贷方
A6: =[28]报表格式!L5 -> 一、营业收入 | B6: =[28]母公司PL汇总!B6 -> 0 | C6: =SUMIF([28]母公司汇总抵销!$E$5:$E$65538,IF(OR(MID(TRIM($A6),2,1)="：",MID(TRIM($A6),2,1)="、"),REPLACEB(TRIM($A6),1,4,""),TRIM($A6)),[28]母公司汇总抵销!$J$5:$J$65538) -> 0 | D6: =SUMIF([28]母公司汇总抵销!$H$5:$H$65538,IF(OR(MID(TRIM($A6),2,1)="：",MID(TRIM($A6),2,1)="、"),REPLACEB(TRIM($A6),1,4,""),TRIM($A6)),[28]母公司汇总抵销!$J$5:$J$65538) -> 0 | E6: =SUMIF([28]母公司账项调整!$E$5:$E$65536,IF(OR(MID(TRIM($A6),2,1)="：",MID(TRIM($A6),2,1)="、"),REPLACEB(TRIM($A6),1,4,""),TRIM($A6)),[28]母公司账项调整!$J$5:$J$65536) -> 0 | F6: =SUMIF([28]母公司账项调整!$H$5:$H$65536,IF(OR(MID(TRIM($A6),2,1)="：",MID(TRIM($A6),2,1)="、"),REPLACEB(TRIM($A6),1,4,""),TRIM($A6)),[28]母公司账项调整!$J$5:$J$65536) -> 0 | G6: =SUMIF([28]母公司报表调整!$E$5:$E$65536,IF(OR(MID(TRIM($A6),2,1)="：",MID(TRIM($A6),2,1)="、"),REPLACEB(TRIM($A6),1,4,""),TRIM($A6)),[28]母公司报表调整!$J$5:$J$65536) -> 0 | H6: =SUMIF([28]母公司报表调整!$H$5:$H$65536,IF(OR(MID(TRIM($A6),2,1)="：",MID(TRIM($A6),2,1)="、"),REPLACEB(TRIM($A6),1,4,""),TRIM($A6)),[28]母公司报表调整!$J$5:$J$65536) -> 0 | I6: =B6-E6-G6+F6+H6-C6+D6 -> 0 | K6: =SUM(I6:J6) -> 0
A7: =[28]报表格式!L6 -> 其中：主营业务收入 | B7: =[28]母公司PL汇总!B7 -> 0 | C7: =SUMIF([28]母公司汇总抵销!$F$5:$F$65538,IF(OR(MID(TRIM($A7),3,1)="：",MID(TRIM($A7),2,1)="、"),REPLACEB(TRIM($A7),1,6,""),TRIM($A7)),[28]母公司汇总抵销!$J$5:$J$65538) -> 0 | D7: =SUMIF([28]母公司汇总抵销!$I$5:$I$65538,IF(OR(MID(TRIM($A7),3,1)="：",MID(TRIM($A7),2,1)="、"),REPLACEB(TRIM($A7),1,6,""),TRIM($A7)),[28]母公司汇总抵销!$J$5:$J$65538) -> 0 | E7: =SUMIF([28]母公司账项调整!$F$5:$F$65536,IF(OR(MID(TRIM($A7),3,1)="：",MID(TRIM($A7),2,1)="、"),REPLACEB(TRIM($A7),1,6,""),TRIM($A7)),[28]母公司账项调整!$J$5:$J$65536) -> 0 | F7: =SUMIF([28]母公司账项调整!$I$5:$I$65536,IF(OR(MID(TRIM($A7),3,1)="：",MID(TRIM($A7),2,1)="、"),REPLACEB(TRIM($A7),1,6,""),TRIM($A7)),[28]母公司账项调整!$J$5:$J$65536) -> 0 | G7: =SUMIF([28]母公司报表调整!$F$5:$F$65536,IF(OR(MID(TRIM($A7),3,1)="：",MID(TRIM($A7),2,1)="、"),REPLACEB(TRIM($A7),1,6,""),TRIM($A7)),[28]母公司报表调整!$J$5:$J$65536) -> 0 | H7: =SUMIF([28]母公司报表调整!$I$5:$I$65536,IF(OR(MID(TRIM($A7),3,1)="：",MID(TRIM($A7),2,1)="、"),REPLACEB(TRIM($A7),1,6,""),TRIM($A7)),[28]母公司报表调整!$J$5:$J$65536) -> 0 | I7: =B7-E7-G7+F7+H7-C7+D7 -> 0 | K7: =SUM(I7:J7) -> 0
A8: =[28]报表格式!L7 -> 其他业务收入 | B8: =[28]母公司PL汇总!B8 -> 0 | C8: =SUMIF([28]母公司汇总抵销!$F$5:$F$65538,IF(OR(MID(TRIM($A8),3,1)="：",MID(TRIM($A8),2,1)="、"),REPLACEB(TRIM($A8),1,6,""),TRIM($A8)),[28]母公司汇总抵销!$J$5:$J$65538) -> 0 | D8: =SUMIF([28]母公司汇总抵销!$I$5:$I$65538,IF(OR(MID(TRIM($A8),3,1)="：",MID(TRIM($A8),2,1)="、"),REPLACEB(TRIM($A8),1,6,""),TRIM($A8)),[28]母公司汇总抵销!$J$5:$J$65538) -> 0 | E8: =SUMIF([28]母公司账项调整!$F$5:$F$65536,IF(OR(MID(TRIM($A8),3,1)="：",MID(TRIM($A8),2,1)="、"),REPLACEB(TRIM($A8),1,6,""),TRIM($A8)),[28]母公司账项调整!$J$5:$J$65536) -> 0 | F8: =SUMIF([28]母公司账项调整!$I$5:$I$65536,IF(OR(MID(TRIM($A8),3,1)="：",MID(TRIM($A8),2,1)="、"),REPLACEB(TRIM($A8),1,6,""),TRIM($A8)),[28]母公司账项调整!$J$5:$J$65536) -> 0 | G8: =SUMIF([28]母公司报表调整!$F$5:$F$65536,IF(OR(MID(TRIM($A8),3,1)="：",MID(TRIM($A8),2,1)="、"),REPLACEB(TRIM($A8),1,6,""),TRIM($A8)),[28]母公司报表调整!$J$5:$J$65536) -> 0 | H8: =SUMIF([28]母公司报表调整!$I$5:$I$65536,IF(OR(MID(TRIM($A8),3,1)="：",MID(TRIM($A8),2,1)="、"),REPLACEB(TRIM($A8),1,6,""),TRIM($A8)),[28]母公司报表调整!$J$5:$J$65536) -> 0 | I8: =B8-E8-G8+F8+H8-C8+D8 -> 0 | K8: =SUM(I8:J8) -> 0
A9: =[28]报表格式!L8 -> 减：营业成本 | B9: =[28]母公司PL汇总!B9 -> 0 | C9: =SUMIF([28]母公司汇总抵销!$E$5:$E$65538,IF(OR(MID(TRIM($A9),2,1)="：",MID(TRIM($A9),2,1)="、"),REPLACEB(TRIM($A9),1,4,""),TRIM($A9)),[28]母公司汇总抵销!$J$5:$J$65538) -> 0 | D9: =SUMIF([28]母公司汇总抵销!$H$5:$H$65538,IF(OR(MID(TRIM($A9),2,1)="：",MID(TRIM($A9),2,1)="、"),REPLACEB(TRIM($A9),1,4,""),TRIM($A9)),[28]母公司汇总抵销!$J$5:$J$65538) -> 0 | E9: =SUMIF([28]母公司账项调整!$E$5:$E$65536,IF(OR(MID(TRIM($A9),2,1)="：",MID(TRIM($A9),2,1)="、"),REPLACEB(TRIM($A9),1,4,""),TRIM($A9)),[28]母公司账项调整!$J$5:$J$65536) -> 0 | F9: =SUMIF([28]母公司账项调整!$H$5:$H$65536,IF(OR(MID(TRIM($A9),2,1)="：",MID(TRIM($A9),2,1)="、"),REPLACEB(TRIM($A9),1,4,""),TRIM($A9)),[28]母公司账项调整!$J$5:$J$65536) -> 0 | G9: =SUMIF([28]母公司报表调整!$E$5:$E$65536,IF(OR(MID(TRIM($A9),2,1)="：",MID(TRIM($A9),2,1)="、"),REPLACEB(TRIM($A9),1,4,""),TRIM($A9)),[28]母公司报表调整!$J$5:$J$65536) -> 0 | H9: =SUMIF([28]母公司报表调整!$H$5:$H$65536,IF(OR(MID(TRIM($A9),2,1)="：",MID(TRIM($A9),2,1)="、"),REPLACEB(TRIM($A9),1,4,""),TRIM($A9)),[28]母公司报表调整!$J$5:$J$65536) -> 0 | I9: =B9+E9+G9-F9-H9+C9-D9 -> 0 | K9: =SUM(I9:J9) -> 0
A10: =[28]报表格式!L9 -> 其中：主营业务成本 | B10: =[28]母公司PL汇总!B10 -> 0 | C10: =SUMIF([28]母公司汇总抵销!$F$5:$F$65538,IF(OR(MID(TRIM($A10),3,1)="：",MID(TRIM($A10),2,1)="、"),REPLACEB(TRIM($A10),1,6,""),TRIM($A10)),[28]母公司汇总抵销!$J$5:$J$65538) -> 0 | D10: =SUMIF([28]母公司汇总抵销!$I$5:$I$65538,IF(OR(MID(TRIM($A10),3,1)="：",MID(TRIM($A10),2,1)="、"),REPLACEB(TRIM($A10),1,6,""),TRIM($A10)),[28]母公司汇总抵销!$J$5:$J$65538) -> 0 | E10: =SUMIF([28]母公司账项调整!$F$5:$F$65536,IF(OR(MID(TRIM($A10),3,1)="：",MID(TRIM($A10),2,1)="、"),REPLACEB(TRIM($A10),1,6,""),TRIM($A10)),[28]母公司账项调整!$J$5:$J$65536) -> 0 | F10: =SUMIF([28]母公司账项调整!$I$5:$I$65536,IF(OR(MID(TRIM($A10),3,1)="：",MID(TRIM($A10),2,1)="、"),REPLACEB(TRIM($A10),1,6,""),TRIM($A10)),[28]母公司账项调整!$J$5:$J$65536) -> 0 | G10: =SUMIF([28]母公司报表调整!$F$5:$F$65536,IF(OR(MID(TRIM($A10),3,1)="：",MID(TRIM($A10),2,1)="、"),REPLACEB(TRIM($A10),1,6,""),TRIM($A10)),[28]母公司报表调整!$J$5:$J$65536) -> 0 | H10: =SUMIF([28]母公司报表调整!$I$5:$I$65536,IF(OR(MID(TRIM($A10),3,1)="：",MID(TRIM($A10),2,1)="、"),REPLACEB(TRIM($A10),1,6,""),TRIM($A10)),[28]母公司报表调整!$J$5:$J$65536) -> 0 | I10: =B10+E10+G10-F10-H10+C10-D10 -> 0 | K10: =SUM(I10:J10) -> 0
A11: =[28]报表格式!L10 -> 其他业务成本 | B11: =[28]母公司PL汇总!B11 -> 0 | C11: =SUMIF([28]母公司汇总抵销!$F$5:$F$65538,IF(OR(MID(TRIM($A11),3,1)="：",MID(TRIM($A11),2,1)="、"),REPLACEB(TRIM($A11),1,6,""),TRIM($A11)),[28]母公司汇总抵销!$J$5:$J$65538) -> 0 | D11: =SUMIF([28]母公司汇总抵销!$I$5:$I$65538,IF(OR(MID(TRIM($A11),3,1)="：",MID(TRIM($A11),2,1)="、"),REPLACEB(TRIM($A11),1,6,""),TRIM($A11)),[28]母公司汇总抵销!$J$5:$J$65538) -> 0 | E11: =SUMIF([28]母公司账项调整!$F$5:$F$65536,IF(OR(MID(TRIM($A11),3,1)="：",MID(TRIM($A11),2,1)="、"),REPLACEB(TRIM($A11),1,6,""),TRIM($A11)),[28]母公司账项调整!$J$5:$J$65536) -> 0 | F11: =SUMIF([28]母公司账项调整!$I$5:$I$65536,IF(OR(MID(TRIM($A11),3,1)="：",MID(TRIM($A11),2,1)="、"),REPLACEB(TRIM($A11),1,6,""),TRIM($A11)),[28]母公司账项调整!$J$5:$J$65536) -> 0 | G11: =SUMIF([28]母公司报表调整!$F$5:$F$65536,IF(OR(MID(TRIM($A11),3,1)="：",MID(TRIM($A11),2,1)="、"),REPLACEB(TRIM($A11),1,6,""),TRIM($A11)),[28]母公司报表调整!$J$5:$J$65536) -> 0 | H11: =SUMIF([28]母公司报表调整!$I$5:$I$65536,IF(OR(MID(TRIM($A11),3,1)="：",MID(TRIM($A11),2,1)="、"),REPLACEB(TRIM($A11),1,6,""),TRIM($A11)),[28]母公司报表调整!$J$5:$J$65536) -> 0 | I11: =B11+E11+G11-F11-H11+C11-D11 -> 0 | K11: =SUM(I11:J11) -> 0
A12: =[28]报表格式!L11 -> 税金及附加 | B12: =[28]母公司PL汇总!B12 -> 0 | C12: =SUMIF([28]母公司汇总抵销!$E$5:$E$65538,IF(OR(MID(TRIM($A12),2,1)="：",MID(TRIM($A12),2,1)="、"),REPLACEB(TRIM($A12),1,4,""),TRIM($A12)),[28]母公司汇总抵销!$J$5:$J$65538) -> 0 | D12: =SUMIF([28]母公司汇总抵销!$H$5:$H$65538,IF(OR(MID(TRIM($A12),2,1)="：",MID(TRIM($A12),2,1)="、"),REPLACEB(TRIM($A12),1,4,""),TRIM($A12)),[28]母公司汇总抵销!$J$5:$J$65538) -> 0 | E12: =SUMIF([28]母公司账项调整!$E$5:$E$65536,IF(OR(MID(TRIM($A12),2,1)="：",MID(TRIM($A12),2,1)="、"),REPLACEB(TRIM($A12),1,4,""),TRIM($A12)),[28]母公司账项调整!$J$5:$J$65536) -> 0 | F12: =SUMIF([28]母公司账项调整!$H$5:$H$65536,IF(OR(MID(TRIM($A12),2,1)="：",MID(TRIM($A12),2,1)="、"),REPLACEB(TRIM($A12),1,4,""),TRIM($A12)),[28]母公司账项调整!$J$5:$J$65536) -> 0 | G12: =SUMIF([28]母公司报表调整!$E$5:$E$65536,IF(OR(MID(TRIM($A12),2,1)="：",MID(TRIM($A12),2,1)="、"),REPLACEB(TRIM($A12),1,4,""),TRIM($A12)),[28]母公司报表调整!$J$5:$J$65536) -> 0 | H12: =SUMIF([28]母公司报表调整!$H$5:$H$65536,IF(OR(MID(TRIM($A12),2,1)="：",MID(TRIM($A12),2,1)="、"),REPLACEB(TRIM($A12),1,4,""),TRIM($A12)),[28]母公司报表调整!$J$5:$J$65536) -> 0 | I12: =B12+E12+G12-F12-H12+C12-D12 -> 0 | K12: =SUM(I12:J12) -> 0
A13: =[28]报表格式!L12 -> 销售费用 | B13: =[28]母公司PL汇总!B13 -> 0 | C13: =SUMIF([28]母公司汇总抵销!$E$5:$E$65538,IF(OR(MID(TRIM($A13),2,1)="：",MID(TRIM($A13),2,1)="、"),REPLACEB(TRIM($A13),1,4,""),TRIM($A13)),[28]母公司汇总抵销!$J$5:$J$65538) -> 0 | D13: =SUMIF([28]母公司汇总抵销!$H$5:$H$65538,IF(OR(MID(TRIM($A13),2,1)="：",MID(TRIM($A13),2,1)="、"),REPLACEB(TRIM($A13),1,4,""),TRIM($A13)),[28]母公司汇总抵销!$J$5:$J$65538) -> 0 | E13: =SUMIF([28]母公司账项调整!$E$5:$E$65536,IF(OR(MID(TRIM($A13),2,1)="：",MID(TRIM($A13),2,1)="、"),REPLACEB(TRIM($A13),1,4,""),TRIM($A13)),[28]母公司账项调整!$J$5:$J$65536) -> 0 | F13: =SUMIF([28]母公司账项调整!$H$5:$H$65536,IF(OR(MID(TRIM($A13),2,1)="：",MID(TRIM($A13),2,1)="、"),REPLACEB(TRIM($A13),1,4,""),TRIM($A13)),[28]母公司账项调整!$J$5:$J$65536) -> 0 | G13: =SUMIF([28]母公司报表调整!$E$5:$E$65536,IF(OR(MID(TRIM($A13),2,1)="：",MID(TRIM($A13),2,1)="、"),REPLACEB(TRIM($A13),1,4,""),TRIM($A13)),[28]母公司报表调整!$J$5:$J$65536) -> 0 | H13: =SUMIF([28]母公司报表调整!$H$5:$H$65536,IF(OR(MID(TRIM($A13),2,1)="：",MID(TRIM($A13),2,1)="、"),REPLACEB(TRIM($A13),1,4,""),TRIM($A13)),[28]母公司报表调整!$J$5:$J$65536) -> 0 | I13: =B13+E13+G13-F13-H13+C13-D13 -> 0 | K13: =SUM(I13:J13) -> 0
A14: =[28]报表格式!L13 -> 管理费用 | B14: =[28]母公司PL汇总!B14 -> 0 | C14: =SUMIF([28]母公司汇总抵销!$E$5:$E$65538,IF(OR(MID(TRIM($A14),2,1)="：",MID(TRIM($A14),2,1)="、"),REPLACEB(TRIM($A14),1,4,""),TRIM($A14)),[28]母公司汇总抵销!$J$5:$J$65538) -> 0 | D14: =SUMIF([28]母公司汇总抵销!$H$5:$H$65538,IF(OR(MID(TRIM($A14),2,1)="：",MID(TRIM($A14),2,1)="、"),REPLACEB(TRIM($A14),1,4,""),TRIM($A14)),[28]母公司汇总抵销!$J$5:$J$65538) -> 0 | E14: =SUMIF([28]母公司账项调整!$E$5:$E$65536,IF(OR(MID(TRIM($A14),2,1)="：",MID(TRIM($A14),2,1)="、"),REPLACEB(TRIM($A14),1,4,""),TRIM($A14)),[28]母公司账项调整!$J$5:$J$65536) -> 0 | F14: =SUMIF([28]母公司账项调整!$H$5:$H$65536,IF(OR(MID(TRIM($A14),2,1)="：",MID(TRIM($A14),2,1)="、"),REPLACEB(TRIM($A14),1,4,""),TRIM($A14)),[28]母公司账项调整!$J$5:$J$65536) -> 0 | G14: =SUMIF([28]母公司报表调整!$E$5:$E$65536,IF(OR(MID(TRIM($A14),2,1)="：",MID(TRIM($A14),2,1)="、"),REPLACEB(TRIM($A14),1,4,""),TRIM($A14)),[28]母公司报表调整!$J$5:$J$65536) -> 0 | H14: =SUMIF([28]母公司报表调整!$H$5:$H$65536,IF(OR(MID(TRIM($A14),2,1)="：",MID(TRIM($A14),2,1)="、"),REPLACEB(TRIM($A14),1,4,""),TRIM($A14)),[28]母公司报表调整!$J$5:$J$65536) -> 0 | I14: =B14+E14+G14-F14-H14+C14-D14 -> 0 | K14: =SUM(I14:J14) -> 0
A15: =[28]报表格式!L14 -> 研发费用 | B15: =[28]母公司PL汇总!B15 -> 0 | C15: =SUMIF([28]母公司汇总抵销!$E$5:$E$65538,IF(OR(MID(TRIM($A15),2,1)="：",MID(TRIM($A15),2,1)="、"),REPLACEB(TRIM($A15),1,4,""),TRIM($A15)),[28]母公司汇总抵销!$J$5:$J$65538) -> 0 | D15: =SUMIF([28]母公司汇总抵销!$H$5:$H$65538,IF(OR(MID(TRIM($A15),2,1)="：",MID(TRIM($A15),2,1)="、"),REPLACEB(TRIM($A15),1,4,""),TRIM($A15)),[28]母公司汇总抵销!$J$5:$J$65538) -> 0 | E15: =SUMIF([28]母公司账项调整!$E$5:$E$65536,IF(OR(MID(TRIM($A15),2,1)="：",MID(TRIM($A15),2,1)="、"),REPLACEB(TRIM($A15),1,4,""),TRIM($A15)),[28]母公司账项调整!$J$5:$J$65536) -> 0 | F15: =SUMIF([28]母公司账项调整!$H$5:$H$65536,IF(OR(MID(TRIM($A15),2,1)="：",MID(TRIM($A15),2,1)="、"),REPLACEB(TRIM($A15),1,4,""),TRIM($A15)),[28]母公司账项调整!$J$5:$J$65536) -> 0 | G15: =SUMIF([28]母公司报表调整!$E$5:$E$65536,IF(OR(MID(TRIM($A15),2,1)="：",MID(TRIM($A15),2,1)="、"),REPLACEB(TRIM($A15),1,4,""),TRIM($A15)),[28]母公司报表调整!$J$5:$J$65536) -> 0 | H15: =SUMIF([28]母公司报表调整!$H$5:$H$65536,IF(OR(MID(TRIM($A15),2,1)="：",MID(TRIM($A15),2,1)="、"),REPLACEB(TRIM($A15),1,4,""),TRIM($A15)),[28]母公司报表调整!$J$5:$J$65536) -> 0 | I15: =B15+E15+G15-F15-H15+C15-D15 -> 0 | K15: =SUM(I15:J15) -> 0
A16: =[28]报表格式!L15 -> 财务费用 | B16: =[28]母公司PL汇总!B16 -> 0 | C16: =SUMIF([28]母公司汇总抵销!$E$5:$E$65538,IF(OR(MID(TRIM($A16),2,1)="：",MID(TRIM($A16),2,1)="、"),REPLACEB(TRIM($A16),1,4,""),TRIM($A16)),[28]母公司汇总抵销!$J$5:$J$65538) -> 0 | D16: =SUMIF([28]母公司汇总抵销!$H$5:$H$65538,IF(OR(MID(TRIM($A16),2,1)="：",MID(TRIM($A16),2,1)="、"),REPLACEB(TRIM($A16),1,4,""),TRIM($A16)),[28]母公司汇总抵销!$J$5:$J$65538) -> 0 | E16: =SUMIF([28]母公司账项调整!$E$5:$E$65536,IF(OR(MID(TRIM($A16),2,1)="：",MID(TRIM($A16),2,1)="、"),REPLACEB(TRIM($A16),1,4,""),TRIM($A16)),[28]母公司账项调整!$J$5:$J$65536) -> 0 | F16: =SUMIF([28]母公司账项调整!$H$5:$H$65536,IF(OR(MID(TRIM($A16),2,1)="：",MID(TRIM($A16),2,1)="、"),REPLACEB(TRIM($A16),1,4,""),TRIM($A16)),[28]母公司账项调整!$J$5:$J$65536) -> 0 | G16: =SUMIF([28]母公司报表调整!$E$5:$E$65536,IF(OR(MID(TRIM($A16),2,1)="：",MID(TRIM($A16),2,1)="、"),REPLACEB(TRIM($A16),1,4,""),TRIM($A16)),[28]母公司报表调整!$J$5:$J$65536) -> 0 | H16: =SUMIF([28]母公司报表调整!$H$5:$H$65536,IF(OR(MID(TRIM($A16),2,1)="：",MID(TRIM($A16),2,1)="、"),REPLACEB(TRIM($A16),1,4,""),TRIM($A16)),[28]母公司报表调整!$J$5:$J$65536) -> 0 | I16: =B16+E16+G16-F16-H16+C16-D16 -> 0 | K16: =SUM(I16:J16) -> 0
A17: =[28]报表格式!L16 -> 其中：利息费用 | B17: =[28]母公司PL汇总!B17 -> 0 | C17: =SUMIF([28]母公司汇总抵销!$F$5:$F$65538,IF(OR(MID(TRIM($A17),3,1)="：",MID(TRIM($A17),2,1)="、"),REPLACEB(TRIM($A17),1,6,""),TRIM($A17)),[28]母公司汇总抵销!$J$5:$J$65538) -> 0 | D17: =SUMIF([28]母公司汇总抵销!$I$5:$I$65538,IF(OR(MID(TRIM($A17),3,1)="：",MID(TRIM($A17),2,1)="、"),REPLACEB(TRIM($A17),1,6,""),TRIM($A17)),[28]母公司汇总抵销!$J$5:$J$65538) -> 0 | E17: =SUMIF([28]母公司账项调整!$F$5:$F$65536,IF(OR(MID(TRIM($A17),3,1)="：",MID(TRIM($A17),2,1)="、"),REPLACEB(TRIM($A17),1,6,""),TRIM($A17)),[28]母公司账项调整!$J$5:$J$65536) -> 0 | F17: =SUMIF([28]母公司账项调整!$I$5:$I$65536,IF(OR(MID(TRIM($A17),3,1)="：",MID(TRIM($A17),2,1)="、"),REPLACEB(TRIM($A17),1,6,""),TRIM($A17)),[28]母公司账项调整!$J$5:$J$65536) -> 0 | G17: =SUMIF([28]母公司报表调整!$F$5:$F$65536,IF(OR(MID(TRIM($A17),3,1)="：",MID(TRIM($A17),2,1)="、"),REPLACEB(TRIM($A17),1,6,""),TRIM($A17)),[28]母公司报表调整!$J$5:$J$65536) -> 0 | H17: =SUMIF([28]母公司报表调整!$I$5:$I$65536,IF(OR(MID(TRIM($A17),3,1)="：",MID(TRIM($A17),2,1)="、"),REPLACEB(TRIM($A17),1,6,""),TRIM($A17)),[28]母公司报表调整!$J$5:$J$65536) -> 0 | I17: =B17+E17+G17-F17-H17+C17-D17 -> 0 | K17: =SUM(I17:J17) -> 0
A18: =[28]报表格式!L17 -> 利息收入 | B18: =[28]母公司PL汇总!B18 -> 0 | C18: =SUMIF([28]母公司汇总抵销!$F$5:$F$65538,IF(OR(MID(TRIM($A18),3,1)="：",MID(TRIM($A18),2,1)="、"),REPLACEB(TRIM($A18),1,6,""),TRIM($A18)),[28]母公司汇总抵销!$J$5:$J$65538) -> 0 | D18: =SUMIF([28]母公司汇总抵销!$I$5:$I$65538,IF(OR(MID(TRIM($A18),3,1)="：",MID(TRIM($A18),2,1)="、"),REPLACEB(TRIM($A18),1,6,""),TRIM($A18)),[28]母公司汇总抵销!$J$5:$J$65538) -> 0 | E18: =SUMIF([28]母公司账项调整!$F$5:$F$65536,IF(OR(MID(TRIM($A18),3,1)="：",MID(TRIM($A18),2,1)="、"),REPLACEB(TRIM($A18),1,6,""),TRIM($A18)),[28]母公司账项调整!$J$5:$J$65536) -> 0 | F18: =SUMIF([28]母公司账项调整!$I$5:$I$65536,IF(OR(MID(TRIM($A18),3,1)="：",MID(TRIM($A18),2,1)="、"),REPLACEB(TRIM($A18),1,6,""),TRIM($A18)),[28]母公司账项调整!$J$5:$J$65536) -> 0 | G18: =SUMIF([28]母公司报表调整!$F$5:$F$65536,IF(OR(MID(TRIM($A18),3,1)="：",MID(TRIM($A18),2,1)="、"),REPLACEB(TRIM($A18),1,6,""),TRIM($A18)),[28]母公司报表调整!$J$5:$J$65536) -> 0 | H18: =SUMIF([28]母公司报表调整!$I$5:$I$65536,IF(OR(MID(TRIM($A18),3,1)="：",MID(TRIM($A18),2,1)="、"),REPLACEB(TRIM($A18),1,6,""),TRIM($A18)),[28]母公司报表调整!$J$5:$J$65536) -> 0 | I18: =B18+E18+G18-F18-H18+C18-D18 -> 0 | K18: =SUM(I18:J18) -> 0
A19: =[28]报表格式!L18 -> 加：其他收益 | B19: =[28]母公司PL汇总!B19 -> 0 | C19: =SUMIF([28]母公司汇总抵销!$E$5:$E$65538,IF(OR(MID(TRIM($A19),2,1)="：",MID(TRIM($A19),2,1)="、"),REPLACEB(TRIM($A19),1,4,""),TRIM($A19)),[28]母公司汇总抵销!$J$5:$J$65538) -> 0 | D19: =SUMIF([28]母公司汇总抵销!$H$5:$H$65538,IF(OR(MID(TRIM($A19),2,1)="：",MID(TRIM($A19),2,1)="、"),REPLACEB(TRIM($A19),1,4,""),TRIM($A19)),[28]母公司汇总抵销!$J$5:$J$65538) -> 0 | E19: =SUMIF([28]母公司账项调整!$E$5:$E$65536,IF(OR(MID(TRIM($A19),2,1)="：",MID(TRIM($A19),2,1)="、"),REPLACEB(TRIM($A19),1,4,""),TRIM($A19)),[28]母公司账项调整!$J$5:$J$65536) -> 0 | F19: =SUMIF([28]母公司账项调整!$H$5:$H$65536,IF(OR(MID(TRIM($A19),2,1)="：",MID(TRIM($A19),2,1)="、"),REPLACEB(TRIM($A19),1,4,""),TRIM($A19)),[28]母公司账项调整!$J$5:$J$65536) -> 0 | G19: =SUMIF([28]母公司报表调整!$E$5:$E$65536,IF(OR(MID(TRIM($A19),2,1)="：",MID(TRIM($A19),2,1)="、"),REPLACEB(TRIM($A19),1,4,""),TRIM($A19)),[28]母公司报表调整!$J$5:$J$65536) -> 0 | H19: =SUMIF([28]母公司报表调整!$H$5:$H$65536,IF(OR(MID(TRIM($A19),2,1)="：",MID(TRIM($A19),2,1)="、"),REPLACEB(TRIM($A19),1,4,""),TRIM($A19)),[28]母公司报表调整!$J$5:$J$65536) -> 0 | I19: =B19-E19-G19+F19+H19-C19+D19 -> 0 | K19: =SUM(I19:J19) -> 0
A20: =[28]报表格式!L19 -> 投资收益（损失以“－”号填列） | B20: =[28]母公司PL汇总!B20 -> 0 | C20: =SUMIF([28]母公司汇总抵销!$E$5:$E$65538,LEFT(IF(OR(MID(TRIM($A20),2,1)="：",MID(TRIM($A20),2,1)="、"),REPLACEB(TRIM($A20),1,4,""),TRIM($A20)),4),[28]母公司汇总抵销!$J$5:$J$65538) -> 0 | D20: =SUMIF([28]母公司汇总抵销!$H$5:$H$65538,LEFT(IF(OR(MID(TRIM($A20),2,1)="：",MID(TRIM($A20),2,1)="、"),REPLACEB(TRIM($A20),1,4,""),TRIM($A20)),4),[28]母公司汇总抵销!$J$5:$J$65538) -> 0 | E20: =SUMIF([28]母公司账项调整!$E$5:$E$65536,LEFT(IF(OR(MID(TRIM($A20),2,1)="：",MID(TRIM($A20),2,1)="、"),REPLACEB(TRIM($A20),1,4,""),TRIM($A20)),4),[28]母公司账项调整!$J$5:$J$65536) -> 0 | F20: =SUMIF([28]母公司账项调整!$H$5:$H$65536,LEFT(IF(OR(MID(TRIM($A20),2,1)="：",MID(TRIM($A20),2,1)="、"),REPLACEB(TRIM($A20),1,4,""),TRIM($A20)),4),[28]母公司账项调整!$J$5:$J$65536) -> 0 | G20: =SUMIF([28]母公司报表调整!$E$5:$E$65536,LEFT(IF(OR(MID(TRIM($A20),2,1)="：",MID(TRIM($A20),2,1)="、"),REPLACEB(TRIM($A20),1,4,""),TRIM($A20)),4),[28]母公司报表调整!$J$5:$J$65536) -> 0 | H20: =SUMIF([28]母公司报表调整!$H$5:$H$65536,LEFT(IF(OR(MID(TRIM($A20),2,1)="：",MID(TRIM($A20),2,1)="、"),REPLACEB(TRIM($A20),1,4,""),TRIM($A20)),4),[28]母公司报表调整!$J$5:$J$65536) -> 0 | I20: =B20-E20-G20+F20+H20-C20+D20 -> 0 | K20: =SUM(I20:J20) -> 0
A21: =[28]报表格式!L20 -> 其中：对联营企业和合营企业的投资收益 | B21: =[28]母公司PL汇总!B21 -> 0 | C21: =SUMIF([28]母公司汇总抵销!$F$5:$F$65538,IF(OR(MID(TRIM($A21),3,1)="：",MID(TRIM($A21),2,1)="、"),REPLACEB(TRIM($A21),1,6,""),TRIM($A21)),[28]母公司汇总抵销!$J$5:$J$65538) -> 0 | D21: =SUMIF([28]母公司汇总抵销!$I$5:$I$65538,IF(OR(MID(TRIM($A21),3,1)="：",MID(TRIM($A21),2,1)="、"),REPLACEB(TRIM($A21),1,6,""),TRIM($A21)),[28]母公司汇总抵销!$J$5:$J$65538) -> 0 | E21: =SUMIF([28]母公司账项调整!$F$5:$F$65536,IF(OR(MID(TRIM($A21),3,1)="：",MID(TRIM($A21),2,1)="、"),REPLACEB(TRIM($A21),1,6,""),TRIM($A21)),[28]母公司账项调整!$J$5:$J$65536) -> 0 | F21: =SUMIF([28]母公司账项调整!$I$5:$I$65536,IF(OR(MID(TRIM($A21),3,1)="：",MID(TRIM($A21),2,1)="、"),REPLACEB(TRIM($A21),1,6,""),TRIM($A21)),[28]母公司账项调整!$J$5:$J$65536) -> 0 | G21: =SUMIF([28]母公司报表调整!$F$5:$F$65536,IF(OR(MID(TRIM($A21),3,1)="：",MID(TRIM($A21),2,1)="、"),REPLACEB(TRIM($A21),1,6,""),TRIM($A21)),[28]母公司报表调整!$J$5:$J$65536) -> 0 | H21: =SUMIF([28]母公司报表调整!$I$5:$I$65536,IF(OR(MID(TRIM($A21),3,1)="：",MID(TRIM($A21),2,1)="、"),REPLACEB(TRIM($A21),1,6,""),TRIM($A21)),[28]母公司报表调整!$J$5:$J$65536) -> 0 | I21: =B21-E21-G21+F21+H21-C21+D21 -> 0 | K21: =SUM(I21:J21) -> 0
A22: =[28]报表格式!L21 -> 以摊余成本计量的金融资产终止确认收益（损失以“-”号填列） | B22: =[28]母公司PL汇总!B22 -> 0 | C22: =SUMIF([28]母公司汇总抵销!$F$5:$F$65538,LEFT(IF(OR(MID(TRIM($A22),3,1)="：",MID(TRIM($A22),2,1)="、"),REPLACEB(TRIM($A22),1,6,""),TRIM($A22)),18),[28]母公司汇总抵销!$J$5:$J$65538) -> 0 | D22: =SUMIF([28]母公司汇总抵销!$I$5:$I$65538,LEFT(IF(OR(MID(TRIM($A22),3,1)="：",MID(TRIM($A22),2,1)="、"),REPLACEB(TRIM($A22),1,6,""),TRIM($A22)),18),[28]母公司汇总抵销!$J$5:$J$65538) -> 0 | E22: =SUMIF([28]母公司账项调整!$F$5:$F$65536,LEFT(IF(OR(MID(TRIM($A22),3,1)="：",MID(TRIM($A22),2,1)="、"),REPLACEB(TRIM($A22),1,6,""),TRIM($A22)),18),[28]母公司账项调整!$J$5:$J$65536) -> 0 | F22: =SUMIF([28]母公司账项调整!$I$5:$I$65536,LEFT(IF(OR(MID(TRIM($A22),3,1)="：",MID(TRIM($A22),2,1)="、"),REPLACEB(TRIM($A22),1,6,""),TRIM($A22)),18),[28]母公司账项调整!$J$5:$J$65536) -> 0 | G22: =SUMIF([28]母公司报表调整!$F$5:$F$65536,LEFT(IF(OR(MID(TRIM($A22),3,1)="：",MID(TRIM($A22),2,1)="、"),REPLACEB(TRIM($A22),1,6,""),TRIM($A22)),18),[28]母公司报表调整!$J$5:$J$65536) -> 0 | H22: =SUMIF([28]母公司报表调整!$I$5:$I$65536,LEFT(IF(OR(MID(TRIM($A22),3,1)="：",MID(TRIM($A22),2,1)="、"),REPLACEB(TRIM($A22),1,6,""),TRIM($A22)),18),[28]母公司报表调整!$J$5:$J$65536) -> 0 | I22: =B22-E22-G22+F22+H22-C22+D22 -> 0 | K22: =SUM(I22:J22) -> 0
A23: =[28]报表格式!L22 -> 净敞口套期收益（损失以“-”号填列） | B23: =[28]母公司PL汇总!B23 -> 0 | C23: =SUMIF([28]母公司汇总抵销!$E$5:$E$65538,LEFT(IF(OR(MID(TRIM($A23),2,1)="：",MID(TRIM($A23),2,1)="、"),REPLACEB(TRIM($A23),1,4,""),TRIM($A23)),7),[28]母公司汇总抵销!$J$5:$J$65538) -> 0 | D23: =SUMIF([28]母公司汇总抵销!$H$5:$H$65538,LEFT(IF(OR(MID(TRIM($A23),2,1)="：",MID(TRIM($A23),2,1)="、"),REPLACEB(TRIM($A23),1,4,""),TRIM($A23)),7),[28]母公司汇总抵销!$J$5:$J$65538) -> 0 | E23: =SUMIF([28]母公司账项调整!$E$5:$E$65536,LEFT(IF(OR(MID(TRIM($A23),2,1)="：",MID(TRIM($A23),2,1)="、"),REPLACEB(TRIM($A23),1,4,""),TRIM($A23)),7),[28]母公司账项调整!$J$5:$J$65536) -> 0 | F23: =SUMIF([28]母公司账项调整!$H$5:$H$65536,LEFT(IF(OR(MID(TRIM($A23),2,1)="：",MID(TRIM($A23),2,1)="、"),REPLACEB(TRIM($A23),1,4,""),TRIM($A23)),7),[28]母公司账项调整!$J$5:$J$65536) -> 0 | G23: =SUMIF([28]母公司报表调整!$E$5:$E$65536,LEFT(IF(OR(MID(TRIM($A23),2,1)="：",MID(TRIM($A23),2,1)="、"),REPLACEB(TRIM($A23),1,4,""),TRIM($A23)),7),[28]母公司报表调整!$J$5:$J$65536) -> 0 | H23: =SUMIF([28]母公司报表调整!$H$5:$H$65536,LEFT(IF(OR(MID(TRIM($A23),2,1)="：",MID(TRIM($A23),2,1)="、"),REPLACEB(TRIM($A23),1,4,""),TRIM($A23)),7),[28]母公司报表调整!$J$5:$J$65536) -> 0 | I23: =B23-E23-G23+F23+H23-C23+D23 -> 0 | K23: =SUM(I23:J23) -> 0
A24: =[28]报表格式!L23 -> 公允价值变动收益（损失以“－”号填列） | B24: =[28]母公司PL汇总!B24 -> 0 | C24: =SUMIF([28]母公司汇总抵销!$E$5:$E$65538,LEFT(IF(OR(MID(TRIM($A24),2,1)="：",MID(TRIM($A24),2,1)="、"),REPLACEB(TRIM($A24),1,4,""),TRIM($A24)),8),[28]母公司汇总抵销!$J$5:$J$65538) -> 0 | D24: =SUMIF([28]母公司汇总抵销!$H$5:$H$65538,LEFT(IF(OR(MID(TRIM($A24),2,1)="：",MID(TRIM($A24),2,1)="、"),REPLACEB(TRIM($A24),1,4,""),TRIM($A24)),8),[28]母公司汇总抵销!$J$5:$J$65538) -> 0 | E24: =SUMIF([28]母公司账项调整!$E$5:$E$65536,LEFT(IF(OR(MID(TRIM($A24),2,1)="：",MID(TRIM($A24),2,1)="、"),REPLACEB(TRIM($A24),1,4,""),TRIM($A24)),8),[28]母公司账项调整!$J$5:$J$65536) -> 0 | F24: =SUMIF([28]母公司账项调整!$H$5:$H$65536,LEFT(IF(OR(MID(TRIM($A24),2,1)="：",MID(TRIM($A24),2,1)="、"),REPLACEB(TRIM($A24),1,4,""),TRIM($A24)),8),[28]母公司账项调整!$J$5:$J$65536) -> 0 | G24: =SUMIF([28]母公司报表调整!$E$5:$E$65536,LEFT(IF(OR(MID(TRIM($A24),2,1)="：",MID(TRIM($A24),2,1)="、"),REPLACEB(TRIM($A24),1,4,""),TRIM($A24)),8),[28]母公司报表调整!$J$5:$J$65536) -> 0 | H24: =SUMIF([28]母公司报表调整!$H$5:$H$65536,LEFT(IF(OR(MID(TRIM($A24),2,1)="：",MID(TRIM($A24),2,1)="、"),REPLACEB(TRIM($A24),1,4,""),TRIM($A24)),8),[28]母公司报表调整!$J$5:$J$65536) -> 0 | I24: =B24-E24-G24+F24+H24-C24+D24 -> 0 | K24: =SUM(I24:J24) -> 0
A25: =[28]报表格式!L24 -> 信用减值损失(损失以“-”号填列） | B25: =[28]母公司PL汇总!B25 -> 0 | C25: =SUMIF([28]母公司汇总抵销!$E$5:$E$65538,LEFT(IF(OR(MID(TRIM($A25),2,1)="：",MID(TRIM($A25),2,1)="、"),REPLACEB(TRIM($A25),1,4,""),TRIM($A25)),6),[28]母公司汇总抵销!$J$5:$J$65538) -> 0 | D25: =SUMIF([28]母公司汇总抵销!$H$5:$H$65538,LEFT(IF(OR(MID(TRIM($A25),2,1)="：",MID(TRIM($A25),2,1)="、"),REPLACEB(TRIM($A25),1,4,""),TRIM($A25)),6),[28]母公司汇总抵销!$J$5:$J$65538) -> 0 | E25: =SUMIF([28]母公司账项调整!$E$5:$E$65536,LEFT(IF(OR(MID(TRIM($A25),2,1)="：",MID(TRIM($A25),2,1)="、"),REPLACEB(TRIM($A25),1,4,""),TRIM($A25)),6),[28]母公司账项调整!$J$5:$J$65536) -> 0 | F25: =SUMIF([28]母公司账项调整!$H$5:$H$65536,LEFT(IF(OR(MID(TRIM($A25),2,1)="：",MID(TRIM($A25),2,1)="、"),REPLACEB(TRIM($A25),1,4,""),TRIM($A25)),6),[28]母公司账项调整!$J$5:$J$65536) -> 0 | G25: =SUMIF([28]母公司报表调整!$E$5:$E$65536,LEFT(IF(OR(MID(TRIM($A25),2,1)="：",MID(TRIM($A25),2,1)="、"),REPLACEB(TRIM($A25),1,4,""),TRIM($A25)),6),[28]母公司报表调整!$J$5:$J$65536) -> 0 | H25: =SUMIF([28]母公司报表调整!$H$5:$H$65536,LEFT(IF(OR(MID(TRIM($A25),2,1)="：",MID(TRIM($A25),2,1)="、"),REPLACEB(TRIM($A25),1,4,""),TRIM($A25)),6),[28]母公司报表调整!$J$5:$J$65536) -> 0 | I25: =B25-E25-G25+F25+H25-C25+D25 -> 0 | K25: =SUM(I25:J25) -> 0
A26: =[28]报表格式!L25 -> 资产减值损失(损失以“-”号填列） | B26: =[28]母公司PL汇总!B26 -> 0 | C26: =SUMIF([28]母公司汇总抵销!$E$5:$E$65538,LEFT(IF(OR(MID(TRIM($A26),2,1)="：",MID(TRIM($A26),2,1)="、"),REPLACEB(TRIM($A26),1,4,""),TRIM($A26)),6),[28]母公司汇总抵销!$J$5:$J$65538) -> 0 | D26: =SUMIF([28]母公司汇总抵销!$H$5:$H$65538,LEFT(IF(OR(MID(TRIM($A26),2,1)="：",MID(TRIM($A26),2,1)="、"),REPLACEB(TRIM($A26),1,4,""),TRIM($A26)),6),[28]母公司汇总抵销!$J$5:$J$65538) -> 0 | E26: =SUMIF([28]母公司账项调整!$E$5:$E$65536,LEFT(IF(OR(MID(TRIM($A26),2,1)="：",MID(TRIM($A26),2,1)="、"),REPLACEB(TRIM($A26),1,4,""),TRIM($A26)),6),[28]母公司账项调整!$J$5:$J$65536) -> 0 | F26: =SUMIF([28]母公司账项调整!$H$5:$H$65536,LEFT(IF(OR(MID(TRIM($A26),2,1)="：",MID(TRIM($A26),2,1)="、"),REPLACEB(TRIM($A26),1,4,""),TRIM($A26)),6),[28]母公司账项调整!$J$5:$J$65536) -> 0 | G26: =SUMIF([28]母公司报表调整!$E$5:$E$65536,LEFT(IF(OR(MID(TRIM($A26),2,1)="：",MID(TRIM($A26),2,1)="、"),REPLACEB(TRIM($A26),1,4,""),TRIM($A26)),6),[28]母公司报表调整!$J$5:$J$65536) -> 0 | H26: =SUMIF([28]母公司报表调整!$H$5:$H$65536,LEFT(IF(OR(MID(TRIM($A26),2,1)="：",MID(TRIM($A26),2,1)="、"),REPLACEB(TRIM($A26),1,4,""),TRIM($A26)),6),[28]母公司报表调整!$J$5:$J$65536) -> 0 | I26: =B26-E26-G26+F26+H26-C26+D26 -> 0 | K26: =SUM(I26:J26) -> 0
A27: =[28]报表格式!L26 -> 资产处置收益(损失以“-”号填列） | B27: =[28]母公司PL汇总!B27 -> 0 | C27: =SUMIF([28]母公司汇总抵销!$E$5:$E$65538,LEFT(IF(OR(MID(TRIM($A27),2,1)="：",MID(TRIM($A27),2,1)="、"),REPLACEB(TRIM($A27),1,4,""),TRIM($A27)),6),[28]母公司汇总抵销!$J$5:$J$65538) -> 0 | D27: =SUMIF([28]母公司汇总抵销!$H$5:$H$65538,LEFT(IF(OR(MID(TRIM($A27),2,1)="：",MID(TRIM($A27),2,1)="、"),REPLACEB(TRIM($A27),1,4,""),TRIM($A27)),6),[28]母公司汇总抵销!$J$5:$J$65538) -> 0 | E27: =SUMIF([28]母公司账项调整!$E$5:$E$65536,LEFT(IF(OR(MID(TRIM($A27),2,1)="：",MID(TRIM($A27),2,1)="、"),REPLACEB(TRIM($A27),1,4,""),TRIM($A27)),6),[28]母公司账项调整!$J$5:$J$65536) -> 0 | F27: =SUMIF([28]母公司账项调整!$H$5:$H$65536,LEFT(IF(OR(MID(TRIM($A27),2,1)="：",MID(TRIM($A27),2,1)="、"),REPLACEB(TRIM($A27),1,4,""),TRIM($A27)),6),[28]母公司账项调整!$J$5:$J$65536) -> 0 | G27: =SUMIF([28]母公司报表调整!$E$5:$E$65536,LEFT(IF(OR(MID(TRIM($A27),2,1)="：",MID(TRIM($A27),2,1)="、"),REPLACEB(TRIM($A27),1,4,""),TRIM($A27)),6),[28]母公司报表调整!$J$5:$J$65536) -> 0 | H27: =SUMIF([28]母公司报表调整!$H$5:$H$65536,LEFT(IF(OR(MID(TRIM($A27),2,1)="：",MID(TRIM($A27),2,1)="、"),REPLACEB(TRIM($A27),1,4,""),TRIM($A27)),6),[28]母公司报表调整!$J$5:$J$65536) -> 0 | I27: =B27-E27-G27+F27+H27-C27+D27 -> 0 | K27: =SUM(I27:J27) -> 0
A28: =[28]报表格式!L27 -> 二、营业利润（亏损以“－”号填列） | B28: =SUM(B6)-SUM(B9,B12:B16)+SUM(B19:B20)+SUM(B23:B27) -> 0 | C28: =SUM(C6)-SUM(C9,C12:C16)+SUM(C19:C20)+SUM(C23:C27) -> 0 | D28: =SUM(D6)-SUM(D9,D12:D16)+SUM(D19:D20)+SUM(D23:D27) -> 0 | E28: =SUM(E6)-SUM(E9,E12:E16)+SUM(E19:E20)+SUM(E23:E27) -> 0 | F28: =SUM(F6)-SUM(F9,F12:F16)+SUM(F19:F20)+SUM(F23:F27) -> 0 | G28: =SUM(G6)-SUM(G9,G12:G16)+SUM(G19:G20)+SUM(G23:G27) -> 0 | H28: =SUM(H6)-SUM(H9,H12:H16)+SUM(H19:H20)+SUM(H23:H27) -> 0 | I28: =SUM(I6)-SUM(I9,I12:I16)+SUM(I19:I20)+SUM(I23:I27) -> 0 | ... K28: =SUM(K6)-SUM(K9,K12:K16)+SUM(K19:K20)+SUM(K23:K27) -> 0
A29: =[28]报表格式!L28 -> 加：营业外收入 | B29: =[28]母公司PL汇总!B29 -> 0 | C29: =SUMIF([28]母公司汇总抵销!$E$5:$E$65538,IF(OR(MID(TRIM($A29),2,1)="：",MID(TRIM($A29),2,1)="、"),REPLACEB(TRIM($A29),1,4,""),TRIM($A29)),[28]母公司汇总抵销!$J$5:$J$65538) -> 0 | D29: =SUMIF([28]母公司汇总抵销!$H$5:$H$65538,IF(OR(MID(TRIM($A29),2,1)="：",MID(TRIM($A29),2,1)="、"),REPLACEB(TRIM($A29),1,4,""),TRIM($A29)),[28]母公司汇总抵销!$J$5:$J$65538) -> 0 | E29: =SUMIF([28]母公司账项调整!$E$5:$E$65536,IF(OR(MID(TRIM($A29),2,1)="：",MID(TRIM($A29),2,1)="、"),REPLACEB(TRIM($A29),1,4,""),TRIM($A29)),[28]母公司账项调整!$J$5:$J$65536) -> 0 | F29: =SUMIF([28]母公司账项调整!$H$5:$H$65536,IF(OR(MID(TRIM($A29),2,1)="：",MID(TRIM($A29),2,1)="、"),REPLACEB(TRIM($A29),1,4,""),TRIM($A29)),[28]母公司账项调整!$J$5:$J$65536) -> 0 | G29: =SUMIF([28]母公司报表调整!$E$5:$E$65536,IF(OR(MID(TRIM($A29),2,1)="：",MID(TRIM($A29),2,1)="、"),REPLACEB(TRIM($A29),1,4,""),TRIM($A29)),[28]母公司报表调整!$J$5:$J$65536) -> 0 | H29: =SUMIF([28]母公司报表调整!$H$5:$H$65536,IF(OR(MID(TRIM($A29),2,1)="：",MID(TRIM($A29),2,1)="、"),REPLACEB(TRIM($A29),1,4,""),TRIM($A29)),[28]母公司报表调整!$J$5:$J$65536) -> 0 | I29: =B29-E29-G29+F29+H29-C29+D29 -> 0 | K29: =SUM(I29:J29) -> 0
A30: =[28]报表格式!L29 -> 减：营业外支出 | B30: =[28]母公司PL汇总!B30 -> 0 | C30: =SUMIF([28]母公司汇总抵销!$E$5:$E$65538,IF(OR(MID(TRIM($A30),2,1)="：",MID(TRIM($A30),2,1)="、"),REPLACEB(TRIM($A30),1,4,""),TRIM($A30)),[28]母公司汇总抵销!$J$5:$J$65538) -> 0 | D30: =SUMIF([28]母公司汇总抵销!$H$5:$H$65538,IF(OR(MID(TRIM($A30),2,1)="：",MID(TRIM($A30),2,1)="、"),REPLACEB(TRIM($A30),1,4,""),TRIM($A30)),[28]母公司汇总抵销!$J$5:$J$65538) -> 0 | E30: =SUMIF([28]母公司账项调整!$E$5:$E$65536,IF(OR(MID(TRIM($A30),2,1)="：",MID(TRIM($A30),2,1)="、"),REPLACEB(TRIM($A30),1,4,""),TRIM($A30)),[28]母公司账项调整!$J$5:$J$65536) -> 0 | F30: =SUMIF([28]母公司账项调整!$H$5:$H$65536,IF(OR(MID(TRIM($A30),2,1)="：",MID(TRIM($A30),2,1)="、"),REPLACEB(TRIM($A30),1,4,""),TRIM($A30)),[28]母公司账项调整!$J$5:$J$65536) -> 0 | G30: =SUMIF([28]母公司报表调整!$E$5:$E$65536,IF(OR(MID(TRIM($A30),2,1)="：",MID(TRIM($A30),2,1)="、"),REPLACEB(TRIM($A30),1,4,""),TRIM($A30)),[28]母公司报表调整!$J$5:$J$65536) -> 0 | H30: =SUMIF([28]母公司报表调整!$H$5:$H$65536,IF(OR(MID(TRIM($A30),2,1)="：",MID(TRIM($A30),2,1)="、"),REPLACEB(TRIM($A30),1,4,""),TRIM($A30)),[28]母公司报表调整!$J$5:$J$65536) -> 0 | I30: =B30+E30+G30-F30-H30+C30-D30 -> 0 | K30: =SUM(I30:J30) -> 0
A31: =[28]报表格式!L30 -> 三、利润总额（亏损总额以“－”号填列） | B31: =SUM(B28)+SUM(B29)-SUM(B30) -> 0 | C31: =SUM(C28)+SUM(C29)-SUM(C30) -> 0 | D31: =SUM(D28)+SUM(D29)-SUM(D30) -> 0 | E31: =SUM(E28)+SUM(E29)-SUM(E30) -> 0 | F31: =SUM(F28)+SUM(F29)-SUM(F30) -> 0 | G31: =SUM(G28)+SUM(G29)-SUM(G30) -> 0 | H31: =SUM(H28)+SUM(H29)-SUM(H30) -> 0 | I31: =SUM(I28)+SUM(I29)-SUM(I30) -> 0 | J31: =SUM(J28)+SUM(J29)-SUM(J30) -> 0 | K31: =SUM(I31:J31) -> 0
A32: =[28]报表格式!L31 -> 减：所得税费用 | B32: =[28]母公司PL汇总!B32 -> 0 | C32: =SUMIF([28]母公司汇总抵销!$E$5:$E$65538,IF(OR(MID(TRIM($A32),2,1)="：",MID(TRIM($A32),2,1)="、"),REPLACEB(TRIM($A32),1,4,""),TRIM($A32)),[28]母公司汇总抵销!$J$5:$J$65538) -> 0 | D32: =SUMIF([28]母公司汇总抵销!$H$5:$H$65538,IF(OR(MID(TRIM($A32),2,1)="：",MID(TRIM($A32),2,1)="、"),REPLACEB(TRIM($A32),1,4,""),TRIM($A32)),[28]母公司汇总抵销!$J$5:$J$65538) -> 0 | E32: =SUMIF([28]母公司账项调整!$E$5:$E$65536,IF(OR(MID(TRIM($A32),2,1)="：",MID(TRIM($A32),2,1)="、"),REPLACEB(TRIM($A32),1,4,""),TRIM($A32)),[28]母公司账项调整!$J$5:$J$65536) -> 0 | F32: =SUMIF([28]母公司账项调整!$H$5:$H$65536,IF(OR(MID(TRIM($A32),2,1)="：",MID(TRIM($A32),2,1)="、"),REPLACEB(TRIM($A32),1,4,""),TRIM($A32)),[28]母公司账项调整!$J$5:$J$65536) -> 0 | G32: =SUMIF([28]母公司报表调整!$E$5:$E$65536,IF(OR(MID(TRIM($A32),2,1)="：",MID(TRIM($A32),2,1)="、"),REPLACEB(TRIM($A32),1,4,""),TRIM($A32)),[28]母公司报表调整!$J$5:$J$65536) -> 0 | H32: =SUMIF([28]母公司报表调整!$H$5:$H$65536,IF(OR(MID(TRIM($A32),2,1)="：",MID(TRIM($A32),2,1)="、"),REPLACEB(TRIM($A32),1,4,""),TRIM($A32)),[28]母公司报表调整!$J$5:$J$65536) -> 0 | I32: =B32+E32+G32-F32-H32+C32-D32 -> 0 | K32: =SUM(I32:J32) -> 0
A33: =[28]报表格式!L32 -> 0 | B33: =[28]母公司PL汇总!B33 -> 0 | C33: =SUMIF([28]母公司汇总抵销!$E$5:$E$65538,IF(OR(MID(TRIM($A33),2,1)="：",MID(TRIM($A33),2,1)="、"),REPLACEB(TRIM($A33),1,4,""),TRIM($A33)),[28]母公司汇总抵销!$J$5:$J$65538) -> 0 | D33: =SUMIF([28]母公司汇总抵销!$H$5:$H$65538,IF(OR(MID(TRIM($A33),2,1)="：",MID(TRIM($A33),2,1)="、"),REPLACEB(TRIM($A33),1,4,""),TRIM($A33)),[28]母公司汇总抵销!$J$5:$J$65538) -> 0 | E33: =SUMIF([28]母公司账项调整!$E$5:$E$65536,IF(OR(MID(TRIM($A33),2,1)="：",MID(TRIM($A33),2,1)="、"),REPLACEB(TRIM($A33),1,4,""),TRIM($A33)),[28]母公司账项调整!$J$5:$J$65536) -> 0 | F33: =SUMIF([28]母公司账项调整!$H$5:$H$65536,IF(OR(MID(TRIM($A33),2,1)="：",MID(TRIM($A33),2,1)="、"),REPLACEB(TRIM($A33),1,4,""),TRIM($A33)),[28]母公司账项调整!$J$5:$J$65536) -> 0 | G33: =SUMIF([28]母公司报表调整!$E$5:$E$65536,IF(OR(MID(TRIM($A33),2,1)="：",MID(TRIM($A33),2,1)="、"),REPLACEB(TRIM($A33),1,4,""),TRIM($A33)),[28]母公司报表调整!$J$5:$J$65536) -> 0 | H33: =SUMIF([28]母公司报表调整!$H$5:$H$65536,IF(OR(MID(TRIM($A33),2,1)="：",MID(TRIM($A33),2,1)="、"),REPLACEB(TRIM($A33),1,4,""),TRIM($A33)),[28]母公司报表调整!$J$5:$J$65536) -> 0 | I33: =B33+E33+G33-F33-H33+C33-D33 -> 0 | K33: =SUM(I33:J33) -> 0
A34: =[28]报表格式!L33 -> 四、净利润（净亏损以“－”号填列） | B34: =B31-B32-B33 -> 0 | C34: =C31-C32-C33 -> 0 | D34: =D31-D32-D33 -> 0 | E34: =E31-E32-E33 -> 0 | F34: =F31-F32-F33 -> 0 | G34: =G31-G32-G33 -> 0 | H34: =H31-H32-H33 -> 0 | I34: =I31-I32-I33 -> 0 | J34: =J31-J32-J33 -> 0 | K34: =SUM(I34:J34) -> 0
A35: =[28]报表格式!L34 -> （一）按经营持续性分类
A36: =[28]报表格式!L35 -> 其中：持续经营净利润（净亏损以“-”号填列） | B36: =[28]母公司PL汇总!B36 -> 0 | I36: =B36-E36-G36+F36+H36-C36+D36 -> 0 | J36: =J33-J34-J35 -> 0 | K36: =SUM(I36:J36) -> 0
A37: =[28]报表格式!L36 -> 终止经营净利润（净亏损以“-”号填列） | B37: =[28]母公司PL汇总!B37 -> 0 | I37: =B37-E37-G37+F37+H37-C37+D37 -> 0 | J37: =J34-J35-J36 -> 0 | K37: =SUM(I37:J37) -> 0
A38: =[28]报表格式!L37 -> （二）按所有权归属分类
A39: =[28]报表格式!L38 -> 其中：归属于母公司股东的净利润（净亏损以“-”号填列） | B39: =[28]母公司PL汇总!B39 -> 0 | C39: =C34-C40 -> 0 | D39: =D34-D40 -> 0 | E39: =E34-E40 -> 0 | F39: =F34-F40 -> 0 | G39: =G34-G40 -> 0 | H39: =H34-H40 -> 0 | I39: =I34-I40 -> 0 | J39: =J34-J40 -> 0 | K39: =SUM(I39:J39) -> 0
A40: =[28]报表格式!L39 -> 少数股东损益（净亏损以“-”号填列） | B40: =[28]母公司PL汇总!B40 -> 0 | C40: =SUMIF([28]母公司汇总抵销!$E$5:$E$65538,LEFT(IF(OR(MID(TRIM($A40),2,1)="：",MID(TRIM($A40),2,1)="、"),REPLACEB(TRIM($A40),1,4,""),TRIM($A40)),6),[28]母公司汇总抵销!$J$5:$J$65538) -> 0 | D40: =SUMIF([28]母公司汇总抵销!$H$5:$H$65538,LEFT(IF(OR(MID(TRIM($A40),2,1)="：",MID(TRIM($A40),2,1)="、"),REPLACEB(TRIM($A40),1,4,""),TRIM($A40)),6),[28]母公司汇总抵销!$J$5:$J$65538) -> 0 | E40: =SUMIF([28]母公司账项调整!$E$5:$E$65536,LEFT(IF(OR(MID(TRIM($A40),2,1)="：",MID(TRIM($A40),2,1)="、"),REPLACEB(TRIM($A40),1,4,""),TRIM($A40)),6),[28]母公司账项调整!$J$5:$J$65536) -> 0 | F40: =SUMIF([28]母公司账项调整!$H$5:$H$65536,LEFT(IF(OR(MID(TRIM($A40),2,1)="：",MID(TRIM($A40),2,1)="、"),REPLACEB(TRIM($A40),1,4,""),TRIM($A40)),6),[28]母公司账项调整!$J$5:$J$65536) -> 0 | G40: =SUMIF([28]母公司报表调整!$E$5:$E$65536,LEFT(IF(OR(MID(TRIM($A40),2,1)="：",MID(TRIM($A40),2,1)="、"),REPLACEB(TRIM($A40),1,4,""),TRIM($A40)),6),[28]母公司报表调整!$J$5:$J$65536) -> 0 | H40: =SUMIF([28]母公司报表调整!$H$5:$H$65536,LEFT(IF(OR(MID(TRIM($A40),2,1)="：",MID(TRIM($A40),2,1)="、"),REPLACEB(TRIM($A40),1,4,""),TRIM($A40)),6),[28]母公司报表调整!$J$5:$J$65536) -> 0 | I40: =B40-E40-G40+F40+H40-C40+D40 -> 0 | K40: =SUM(I40:J40) -> 0
A41: =[28]报表格式!L40 -> 五、其他综合收益的税后净额 | B41: =[28]母公司PL汇总!B41 -> 0 | C41: =C42+C61 -> 0 | D41: =D42+D61 -> 0 | E41: =E42+E61 -> 0 | F41: =F42+F61 -> 0 | G41: =G42+G61 -> 0 | H41: =H42+H61 -> 0 | I41: =B41-E41-G41+F41+H41-C41+D41 -> 0 | K41: =SUM(I41:J41) -> 0
A42: =[28]报表格式!L41 -> 归属于母公司股东的其他综合收益的税后净额 | B42: =[28]母公司PL汇总!B42 -> 0 | C42: =C43+C49 -> 0 | D42: =D43+D49 -> 0 | E42: =E43+E49 -> 0 | F42: =F43+F49 -> 0 | G42: =G43+G49 -> 0 | H42: =H43+H49 -> 0 | I42: =B42-E42-G42+F42+H42-C42+D42 -> 0 | K42: =SUM(I42:J42) -> 0
A43: =[28]报表格式!L42 -> （一）不能重分类进损益的其他综合收益 | B43: =[28]母公司PL汇总!B43 -> 0 | C43: =SUM(C44:C48) -> 0 | D43: =SUM(D44:D48) -> 0 | E43: =SUM(E44:E48) -> 0 | F43: =SUM(F44:F48) -> 0 | G43: =SUM(G44:G48) -> 0 | H43: =SUM(H44:H48) -> 0 | I43: =B43-E43-G43+F43+H43-C43+D43 -> 0 | K43: =SUM(I43:J43) -> 0
A44: =[28]报表格式!L43 -> 1.重新计量设定受益计划变动额 | B44: =[28]母公司PL汇总!B44 -> 0 | C44: =SUMIF([28]母公司汇总抵销!$E$5:$E$65538,IF(OR(MID(TRIM($A44),2,1)="：",MID(TRIM($A44),2,1)="、"),REPLACEB(TRIM($A44),1,4,""),TRIM($A44)),[28]母公司汇总抵销!$J$5:$J$65538) -> 0 | D44: =SUMIF([28]母公司汇总抵销!$H$5:$H$65538,IF(OR(MID(TRIM($A44),2,1)="：",MID(TRIM($A44),2,1)="、"),REPLACEB(TRIM($A44),1,4,""),TRIM($A44)),[28]母公司汇总抵销!$J$5:$J$65538) -> 0 | E44: =SUMIF([28]母公司账项调整!$E$5:$E$65536,IF(OR(MID(TRIM($A44),2,1)="：",MID(TRIM($A44),2,1)="、"),REPLACEB(TRIM($A44),1,4,""),TRIM($A44)),[28]母公司账项调整!$J$5:$J$65536) -> 0 | F44: =SUMIF([28]母公司账项调整!$H$5:$H$65536,IF(OR(MID(TRIM($A44),2,1)="：",MID(TRIM($A44),2,1)="、"),REPLACEB(TRIM($A44),1,4,""),TRIM($A44)),[28]母公司账项调整!$J$5:$J$65536) -> 0 | G44: =SUMIF([28]母公司报表调整!$E$5:$E$65536,IF(OR(MID(TRIM($A44),2,1)="：",MID(TRIM($A44),2,1)="、"),REPLACEB(TRIM($A44),1,4,""),TRIM($A44)),[28]母公司报表调整!$J$5:$J$65536) -> 0 | H44: =SUMIF([28]母公司报表调整!$H$5:$H$65536,IF(OR(MID(TRIM($A44),2,1)="：",MID(TRIM($A44),2,1)="、"),REPLACEB(TRIM($A44),1,4,""),TRIM($A44)),[28]母公司报表调整!$J$5:$J$65536) -> 0 | I44: =B44-E44-G44+F44+H44-C44+D44 -> 0 | K44: =SUM(I44:J44) -> 0
A45: =[28]报表格式!L44 -> 2.权益法下不能转损益的其他综合收益 | B45: =[28]母公司PL汇总!B45 -> 0 | C45: =SUMIF([28]母公司汇总抵销!$E$5:$E$65538,IF(OR(MID(TRIM($A45),2,1)="：",MID(TRIM($A45),2,1)="、"),REPLACEB(TRIM($A45),1,4,""),TRIM($A45)),[28]母公司汇总抵销!$J$5:$J$65538) -> 0 | D45: =SUMIF([28]母公司汇总抵销!$H$5:$H$65538,IF(OR(MID(TRIM($A45),2,1)="：",MID(TRIM($A45),2,1)="、"),REPLACEB(TRIM($A45),1,4,""),TRIM($A45)),[28]母公司汇总抵销!$J$5:$J$65538) -> 0 | E45: =SUMIF([28]母公司账项调整!$E$5:$E$65536,IF(OR(MID(TRIM($A45),2,1)="：",MID(TRIM($A45),2,1)="、"),REPLACEB(TRIM($A45),1,4,""),TRIM($A45)),[28]母公司账项调整!$J$5:$J$65536) -> 0 | F45: =SUMIF([28]母公司账项调整!$H$5:$H$65536,IF(OR(MID(TRIM($A45),2,1)="：",MID(TRIM($A45),2,1)="、"),REPLACEB(TRIM($A45),1,4,""),TRIM($A45)),[28]母公司账项调整!$J$5:$J$65536) -> 0 | G45: =SUMIF([28]母公司报表调整!$E$5:$E$65536,IF(OR(MID(TRIM($A45),2,1)="：",MID(TRIM($A45),2,1)="、"),REPLACEB(TRIM($A45),1,4,""),TRIM($A45)),[28]母公司报表调整!$J$5:$J$65536) -> 0 | H45: =SUMIF([28]母公司报表调整!$H$5:$H$65536,IF(OR(MID(TRIM($A45),2,1)="：",MID(TRIM($A45),2,1)="、"),REPLACEB(TRIM($A45),1,4,""),TRIM($A45)),[28]母公司报表调整!$J$5:$J$65536) -> 0 | I45: =B45-E45-G45+F45+H45-C45+D45 -> 0 | K45: =SUM(I45:J45) -> 0
A46: =[28]报表格式!L45 -> 3.其他权益工具投资公允价值变动 | B46: =[28]母公司PL汇总!B46 -> 0 | C46: =SUMIF([28]母公司汇总抵销!$E$5:$E$65538,IF(OR(MID(TRIM($A46),2,1)="：",MID(TRIM($A46),2,1)="、"),REPLACEB(TRIM($A46),1,4,""),TRIM($A46)),[28]母公司汇总抵销!$J$5:$J$65538) -> 0 | D46: =SUMIF([28]母公司汇总抵销!$H$5:$H$65538,IF(OR(MID(TRIM($A46),2,1)="：",MID(TRIM($A46),2,1)="、"),REPLACEB(TRIM($A46),1,4,""),TRIM($A46)),[28]母公司汇总抵销!$J$5:$J$65538) -> 0 | E46: =SUMIF([28]母公司账项调整!$E$5:$E$65536,IF(OR(MID(TRIM($A46),2,1)="：",MID(TRIM($A46),2,1)="、"),REPLACEB(TRIM($A46),1,4,""),TRIM($A46)),[28]母公司账项调整!$J$5:$J$65536) -> 0 | F46: =SUMIF([28]母公司账项调整!$H$5:$H$65536,IF(OR(MID(TRIM($A46),2,1)="：",MID(TRIM($A46),2,1)="、"),REPLACEB(TRIM($A46),1,4,""),TRIM($A46)),[28]母公司账项调整!$J$5:$J$65536) -> 0 | G46: =SUMIF([28]母公司报表调整!$E$5:$E$65536,IF(OR(MID(TRIM($A46),2,1)="：",MID(TRIM($A46),2,1)="、"),REPLACEB(TRIM($A46),1,4,""),TRIM($A46)),[28]母公司报表调整!$J$5:$J$65536) -> 0 | H46: =SUMIF([28]母公司报表调整!$H$5:$H$65536,IF(OR(MID(TRIM($A46),2,1)="：",MID(TRIM($A46),2,1)="、"),REPLACEB(TRIM($A46),1,4,""),TRIM($A46)),[28]母公司报表调整!$J$5:$J$65536) -> 0 | I46: =B46-E46-G46+F46+H46-C46+D46 -> 0 | K46: =SUM(I46:J46) -> 0
A47: =[28]报表格式!L46 -> 4.企业自身信用风险公允价值变动 | B47: =[28]母公司PL汇总!B47 -> 0 | C47: =SUMIF([28]母公司汇总抵销!$E$5:$E$65538,IF(OR(MID(TRIM($A47),2,1)="：",MID(TRIM($A47),2,1)="、"),REPLACEB(TRIM($A47),1,4,""),TRIM($A47)),[28]母公司汇总抵销!$J$5:$J$65538) -> 0 | D47: =SUMIF([28]母公司汇总抵销!$H$5:$H$65538,IF(OR(MID(TRIM($A47),2,1)="：",MID(TRIM($A47),2,1)="、"),REPLACEB(TRIM($A47),1,4,""),TRIM($A47)),[28]母公司汇总抵销!$J$5:$J$65538) -> 0 | E47: =SUMIF([28]母公司账项调整!$E$5:$E$65536,IF(OR(MID(TRIM($A47),2,1)="：",MID(TRIM($A47),2,1)="、"),REPLACEB(TRIM($A47),1,4,""),TRIM($A47)),[28]母公司账项调整!$J$5:$J$65536) -> 0 | F47: =SUMIF([28]母公司账项调整!$H$5:$H$65536,IF(OR(MID(TRIM($A47),2,1)="：",MID(TRIM($A47),2,1)="、"),REPLACEB(TRIM($A47),1,4,""),TRIM($A47)),[28]母公司账项调整!$J$5:$J$65536) -> 0 | G47: =SUMIF([28]母公司报表调整!$E$5:$E$65536,IF(OR(MID(TRIM($A47),2,1)="：",MID(TRIM($A47),2,1)="、"),REPLACEB(TRIM($A47),1,4,""),TRIM($A47)),[28]母公司报表调整!$J$5:$J$65536) -> 0 | H47: =SUMIF([28]母公司报表调整!$H$5:$H$65536,IF(OR(MID(TRIM($A47),2,1)="：",MID(TRIM($A47),2,1)="、"),REPLACEB(TRIM($A47),1,4,""),TRIM($A47)),[28]母公司报表调整!$J$5:$J$65536) -> 0 | I47: =B47-E47-G47+F47+H47-C47+D47 -> 0 | K47: =SUM(I47:J47) -> 0
A48: =[28]报表格式!L47 -> 5.其他 | B48: =[28]母公司PL汇总!B48 -> 0 | C48: =SUMIF([28]母公司汇总抵销!$E$5:$E$65538,IF(OR(MID(TRIM($A48),2,1)="：",MID(TRIM($A48),2,1)="、"),REPLACEB(TRIM($A48),1,4,""),TRIM($A48)),[28]母公司汇总抵销!$J$5:$J$65538) -> 0 | D48: =SUMIF([28]母公司汇总抵销!$H$5:$H$65538,IF(OR(MID(TRIM($A48),2,1)="：",MID(TRIM($A48),2,1)="、"),REPLACEB(TRIM($A48),1,4,""),TRIM($A48)),[28]母公司汇总抵销!$J$5:$J$65538) -> 0 | E48: =SUMIF([28]母公司账项调整!$E$5:$E$65536,IF(OR(MID(TRIM($A48),2,1)="：",MID(TRIM($A48),2,1)="、"),REPLACEB(TRIM($A48),1,4,""),TRIM($A48)),[28]母公司账项调整!$J$5:$J$65536) -> 0 | F48: =SUMIF([28]母公司账项调整!$H$5:$H$65536,IF(OR(MID(TRIM($A48),2,1)="：",MID(TRIM($A48),2,1)="、"),REPLACEB(TRIM($A48),1,4,""),TRIM($A48)),[28]母公司账项调整!$J$5:$J$65536) -> 0 | G48: =SUMIF([28]母公司报表调整!$E$5:$E$65536,IF(OR(MID(TRIM($A48),2,1)="：",MID(TRIM($A48),2,1)="、"),REPLACEB(TRIM($A48),1,4,""),TRIM($A48)),[28]母公司报表调整!$J$5:$J$65536) -> 0 | H48: =SUMIF([28]母公司报表调整!$H$5:$H$65536,IF(OR(MID(TRIM($A48),2,1)="：",MID(TRIM($A48),2,1)="、"),REPLACEB(TRIM($A48),1,4,""),TRIM($A48)),[28]母公司报表调整!$J$5:$J$65536) -> 0 | I48: =B48-E48-G48+F48+H48-C48+D48 -> 0 | K48: =SUM(I48:J48) -> 0
A49: =[28]报表格式!L48 -> （二）将重分类进损益的其他综合收益 | B49: =[28]母公司PL汇总!B49 -> 0 | C49: =SUM(C50:C60) -> 0 | D49: =SUM(D50:D60) -> 0 | E49: =SUM(E50:E60) -> 0 | F49: =SUM(F50:F60) -> 0 | G49: =SUM(G50:G60) -> 0 | H49: =SUM(H50:H60) -> 0 | I49: =B49-E49-G49+F49+H49-C49+D49 -> 0 | K49: =SUM(I49:J49) -> 0
A50: =[28]报表格式!L49 -> 1.权益法下可转损益的其他综合收益 | B50: =[28]母公司PL汇总!B50 -> 0 | C50: =SUMIF([28]母公司汇总抵销!$E$5:$E$65538,IF(OR(MID(TRIM($A50),2,1)="：",MID(TRIM($A50),2,1)="、"),REPLACEB(TRIM($A50),1,4,""),TRIM($A50)),[28]母公司汇总抵销!$J$5:$J$65538) -> 0 | D50: =SUMIF([28]母公司汇总抵销!$H$5:$H$65538,IF(OR(MID(TRIM($A50),2,1)="：",MID(TRIM($A50),2,1)="、"),REPLACEB(TRIM($A50),1,4,""),TRIM($A50)),[28]母公司汇总抵销!$J$5:$J$65538) -> 0 | E50: =SUMIF([28]母公司账项调整!$E$5:$E$65536,IF(OR(MID(TRIM($A50),2,1)="：",MID(TRIM($A50),2,1)="、"),REPLACEB(TRIM($A50),1,4,""),TRIM($A50)),[28]母公司账项调整!$J$5:$J$65536) -> 0 | F50: =SUMIF([28]母公司账项调整!$H$5:$H$65536,IF(OR(MID(TRIM($A50),2,1)="：",MID(TRIM($A50),2,1)="、"),REPLACEB(TRIM($A50),1,4,""),TRIM($A50)),[28]母公司账项调整!$J$5:$J$65536) -> 0 | G50: =SUMIF([28]母公司报表调整!$E$5:$E$65536,IF(OR(MID(TRIM($A50),2,1)="：",MID(TRIM($A50),2,1)="、"),REPLACEB(TRIM($A50),1,4,""),TRIM($A50)),[28]母公司报表调整!$J$5:$J$65536) -> 0 | H50: =SUMIF([28]母公司报表调整!$H$5:$H$65536,IF(OR(MID(TRIM($A50),2,1)="：",MID(TRIM($A50),2,1)="、"),REPLACEB(TRIM($A50),1,4,""),TRIM($A50)),[28]母公司报表调整!$J$5:$J$65536) -> 0 | I50: =B50-E50-G50+F50+H50-C50+D50 -> 0 | K50: =SUM(I50:J50) -> 0
A51: =[28]报表格式!L50 -> 2.其他债权投资公允价值变动 | B51: =[28]母公司PL汇总!B51 -> 0 | C51: =SUMIF([28]母公司汇总抵销!$E$5:$E$65538,IF(OR(MID(TRIM($A51),2,1)="：",MID(TRIM($A51),2,1)="、"),REPLACEB(TRIM($A51),1,4,""),TRIM($A51)),[28]母公司汇总抵销!$J$5:$J$65538) -> 0 | D51: =SUMIF([28]母公司汇总抵销!$H$5:$H$65538,IF(OR(MID(TRIM($A51),2,1)="：",MID(TRIM($A51),2,1)="、"),REPLACEB(TRIM($A51),1,4,""),TRIM($A51)),[28]母公司汇总抵销!$J$5:$J$65538) -> 0 | E51: =SUMIF([28]母公司账项调整!$E$5:$E$65536,IF(OR(MID(TRIM($A51),2,1)="：",MID(TRIM($A51),2,1)="、"),REPLACEB(TRIM($A51),1,4,""),TRIM($A51)),[28]母公司账项调整!$J$5:$J$65536) -> 0 | F51: =SUMIF([28]母公司账项调整!$H$5:$H$65536,IF(OR(MID(TRIM($A51),2,1)="：",MID(TRIM($A51),2,1)="、"),REPLACEB(TRIM($A51),1,4,""),TRIM($A51)),[28]母公司账项调整!$J$5:$J$65536) -> 0 | G51: =SUMIF([28]母公司报表调整!$E$5:$E$65536,IF(OR(MID(TRIM($A51),2,1)="：",MID(TRIM($A51),2,1)="、"),REPLACEB(TRIM($A51),1,4,""),TRIM($A51)),[28]母公司报表调整!$J$5:$J$65536) -> 0 | H51: =SUMIF([28]母公司报表调整!$H$5:$H$65536,IF(OR(MID(TRIM($A51),2,1)="：",MID(TRIM($A51),2,1)="、"),REPLACEB(TRIM($A51),1,4,""),TRIM($A51)),[28]母公司报表调整!$J$5:$J$65536) -> 0 | I51: =B51-E51-G51+F51+H51-C51+D51 -> 0 | K51: =SUM(I51:J51) -> 0
A52: =[28]报表格式!L51 -> 3.可供出售金融资产公允价值变动损益 | B52: =[28]母公司PL汇总!B52 -> 0 | C52: =SUMIF([28]母公司汇总抵销!$E$5:$E$65538,IF(OR(MID(TRIM($A52),2,1)="：",MID(TRIM($A52),2,1)="、"),REPLACEB(TRIM($A52),1,4,""),TRIM($A52)),[28]母公司汇总抵销!$J$5:$J$65538) -> 0 | D52: =SUMIF([28]母公司汇总抵销!$H$5:$H$65538,IF(OR(MID(TRIM($A52),2,1)="：",MID(TRIM($A52),2,1)="、"),REPLACEB(TRIM($A52),1,4,""),TRIM($A52)),[28]母公司汇总抵销!$J$5:$J$65538) -> 0 | E52: =SUMIF([28]母公司账项调整!$E$5:$E$65536,IF(OR(MID(TRIM($A52),2,1)="：",MID(TRIM($A52),2,1)="、"),REPLACEB(TRIM($A52),1,4,""),TRIM($A52)),[28]母公司账项调整!$J$5:$J$65536) -> 0 | F52: =SUMIF([28]母公司账项调整!$H$5:$H$65536,IF(OR(MID(TRIM($A52),2,1)="：",MID(TRIM($A52),2,1)="、"),REPLACEB(TRIM($A52),1,4,""),TRIM($A52)),[28]母公司账项调整!$J$5:$J$65536) -> 0 | G52: =SUMIF([28]母公司报表调整!$E$5:$E$65536,IF(OR(MID(TRIM($A52),2,1)="：",MID(TRIM($A52),2,1)="、"),REPLACEB(TRIM($A52),1,4,""),TRIM($A52)),[28]母公司报表调整!$J$5:$J$65536) -> 0 | H52: =SUMIF([28]母公司报表调整!$H$5:$H$65536,IF(OR(MID(TRIM($A52),2,1)="：",MID(TRIM($A52),2,1)="、"),REPLACEB(TRIM($A52),1,4,""),TRIM($A52)),[28]母公司报表调整!$J$5:$J$65536) -> 0 | I52: =B52-E52-G52+F52+H52-C52+D52 -> 0 | K52: =SUM(I52:J52) -> 0
A53: =[28]报表格式!L52 -> 4.金融资产重分类计入其他综合收益的金额 | B53: =[28]母公司PL汇总!B53 -> 0 | C53: =SUMIF([28]母公司汇总抵销!$E$5:$E$65538,IF(OR(MID(TRIM($A53),2,1)="：",MID(TRIM($A53),2,1)="、"),REPLACEB(TRIM($A53),1,4,""),TRIM($A53)),[28]母公司汇总抵销!$J$5:$J$65538) -> 0 | D53: =SUMIF([28]母公司汇总抵销!$H$5:$H$65538,IF(OR(MID(TRIM($A53),2,1)="：",MID(TRIM($A53),2,1)="、"),REPLACEB(TRIM($A53),1,4,""),TRIM($A53)),[28]母公司汇总抵销!$J$5:$J$65538) -> 0 | E53: =SUMIF([28]母公司账项调整!$E$5:$E$65536,IF(OR(MID(TRIM($A53),2,1)="：",MID(TRIM($A53),2,1)="、"),REPLACEB(TRIM($A53),1,4,""),TRIM($A53)),[28]母公司账项调整!$J$5:$J$65536) -> 0 | F53: =SUMIF([28]母公司账项调整!$H$5:$H$65536,IF(OR(MID(TRIM($A53),2,1)="：",MID(TRIM($A53),2,1)="、"),REPLACEB(TRIM($A53),1,4,""),TRIM($A53)),[28]母公司账项调整!$J$5:$J$65536) -> 0 | G53: =SUMIF([28]母公司报表调整!$E$5:$E$65536,IF(OR(MID(TRIM($A53),2,1)="：",MID(TRIM($A53),2,1)="、"),REPLACEB(TRIM($A53),1,4,""),TRIM($A53)),[28]母公司报表调整!$J$5:$J$65536) -> 0 | H53: =SUMIF([28]母公司报表调整!$H$5:$H$65536,IF(OR(MID(TRIM($A53),2,1)="：",MID(TRIM($A53),2,1)="、"),REPLACEB(TRIM($A53),1,4,""),TRIM($A53)),[28]母公司报表调整!$J$5:$J$65536) -> 0 | I53: =B53-E53-G53+F53+H53-C53+D53 -> 0 | K53: =SUM(I53:J53) -> 0
A54: =[28]报表格式!L53 -> 5.持有至到期投资重分类为可供出售金融资产损益 | B54: =[28]母公司PL汇总!B54 -> 0 | C54: =SUMIF([28]母公司汇总抵销!$E$5:$E$65538,IF(OR(MID(TRIM($A54),2,1)="：",MID(TRIM($A54),2,1)="、"),REPLACEB(TRIM($A54),1,4,""),TRIM($A54)),[28]母公司汇总抵销!$J$5:$J$65538) -> 0 | D54: =SUMIF([28]母公司汇总抵销!$H$5:$H$65538,IF(OR(MID(TRIM($A54),2,1)="：",MID(TRIM($A54),2,1)="、"),REPLACEB(TRIM($A54),1,4,""),TRIM($A54)),[28]母公司汇总抵销!$J$5:$J$65538) -> 0 | E54: =SUMIF([28]母公司账项调整!$E$5:$E$65536,IF(OR(MID(TRIM($A54),2,1)="：",MID(TRIM($A54),2,1)="、"),REPLACEB(TRIM($A54),1,4,""),TRIM($A54)),[28]母公司账项调整!$J$5:$J$65536) -> 0 | F54: =SUMIF([28]母公司账项调整!$H$5:$H$65536,IF(OR(MID(TRIM($A54),2,1)="：",MID(TRIM($A54),2,1)="、"),REPLACEB(TRIM($A54),1,4,""),TRIM($A54)),[28]母公司账项调整!$J$5:$J$65536) -> 0 | G54: =SUMIF([28]母公司报表调整!$E$5:$E$65536,IF(OR(MID(TRIM($A54),2,1)="：",MID(TRIM($A54),2,1)="、"),REPLACEB(TRIM($A54),1,4,""),TRIM($A54)),[28]母公司报表调整!$J$5:$J$65536) -> 0 | H54: =SUMIF([28]母公司报表调整!$H$5:$H$65536,IF(OR(MID(TRIM($A54),2,1)="：",MID(TRIM($A54),2,1)="、"),REPLACEB(TRIM($A54),1,4,""),TRIM($A54)),[28]母公司报表调整!$J$5:$J$65536) -> 0 | I54: =B54-E54-G54+F54+H54-C54+D54 -> 0 | K54: =SUM(I54:J54) -> 0
A55: =[28]报表格式!L54 -> 6.其他债权投资信用减值准备 | B55: =[28]母公司PL汇总!B55 -> 0 | C55: =SUMIF([28]母公司汇总抵销!$E$5:$E$65538,IF(OR(MID(TRIM($A55),2,1)="：",MID(TRIM($A55),2,1)="、"),REPLACEB(TRIM($A55),1,4,""),TRIM($A55)),[28]母公司汇总抵销!$J$5:$J$65538) -> 0 | D55: =SUMIF([28]母公司汇总抵销!$H$5:$H$65538,IF(OR(MID(TRIM($A55),2,1)="：",MID(TRIM($A55),2,1)="、"),REPLACEB(TRIM($A55),1,4,""),TRIM($A55)),[28]母公司汇总抵销!$J$5:$J$65538) -> 0 | E55: =SUMIF([28]母公司账项调整!$E$5:$E$65536,IF(OR(MID(TRIM($A55),2,1)="：",MID(TRIM($A55),2,1)="、"),REPLACEB(TRIM($A55),1,4,""),TRIM($A55)),[28]母公司账项调整!$J$5:$J$65536) -> 0 | F55: =SUMIF([28]母公司账项调整!$H$5:$H$65536,IF(OR(MID(TRIM($A55),2,1)="：",MID(TRIM($A55),2,1)="、"),REPLACEB(TRIM($A55),1,4,""),TRIM($A55)),[28]母公司账项调整!$J$5:$J$65536) -> 0 | G55: =SUMIF([28]母公司报表调整!$E$5:$E$65536,IF(OR(MID(TRIM($A55),2,1)="：",MID(TRIM($A55),2,1)="、"),REPLACEB(TRIM($A55),1,4,""),TRIM($A55)),[28]母公司报表调整!$J$5:$J$65536) -> 0 | H55: =SUMIF([28]母公司报表调整!$H$5:$H$65536,IF(OR(MID(TRIM($A55),2,1)="：",MID(TRIM($A55),2,1)="、"),REPLACEB(TRIM($A55),1,4,""),TRIM($A55)),[28]母公司报表调整!$J$5:$J$65536) -> 0 | I55: =B55-E55-G55+F55+H55-C55+D55 -> 0 | K55: =SUM(I55:J55) -> 0
A56: =[28]报表格式!L55 -> 7.现金流量套期储备 | B56: =[28]母公司PL汇总!B56 -> 0 | C56: =SUMIF([28]母公司汇总抵销!$E$5:$E$65538,IF(OR(MID(TRIM($A56),2,1)="：",MID(TRIM($A56),2,1)="、"),REPLACEB(TRIM($A56),1,4,""),TRIM($A56)),[28]母公司汇总抵销!$J$5:$J$65538) -> 0 | D56: =SUMIF([28]母公司汇总抵销!$H$5:$H$65538,IF(OR(MID(TRIM($A56),2,1)="：",MID(TRIM($A56),2,1)="、"),REPLACEB(TRIM($A56),1,4,""),TRIM($A56)),[28]母公司汇总抵销!$J$5:$J$65538) -> 0 | E56: =SUMIF([28]母公司账项调整!$E$5:$E$65536,IF(OR(MID(TRIM($A56),2,1)="：",MID(TRIM($A56),2,1)="、"),REPLACEB(TRIM($A56),1,4,""),TRIM($A56)),[28]母公司账项调整!$J$5:$J$65536) -> 0 | F56: =SUMIF([28]母公司账项调整!$H$5:$H$65536,IF(OR(MID(TRIM($A56),2,1)="：",MID(TRIM($A56),2,1)="、"),REPLACEB(TRIM($A56),1,4,""),TRIM($A56)),[28]母公司账项调整!$J$5:$J$65536) -> 0 | G56: =SUMIF([28]母公司报表调整!$E$5:$E$65536,IF(OR(MID(TRIM($A56),2,1)="：",MID(TRIM($A56),2,1)="、"),REPLACEB(TRIM($A56),1,4,""),TRIM($A56)),[28]母公司报表调整!$J$5:$J$65536) -> 0 | H56: =SUMIF([28]母公司报表调整!$H$5:$H$65536,IF(OR(MID(TRIM($A56),2,1)="：",MID(TRIM($A56),2,1)="、"),REPLACEB(TRIM($A56),1,4,""),TRIM($A56)),[28]母公司报表调整!$J$5:$J$65536) -> 0 | I56: =B56-E56-G56+F56+H56-C56+D56 -> 0 | K56: =SUM(I56:J56) -> 0
A57: =[28]报表格式!L56 -> 8.外币财务报表折算差额 | B57: =[28]母公司PL汇总!B57 -> 0 | C57: =SUMIF([28]母公司汇总抵销!$E$5:$E$65538,IF(OR(MID(TRIM($A57),2,1)="：",MID(TRIM($A57),2,1)="、"),REPLACEB(TRIM($A57),1,4,""),TRIM($A57)),[28]母公司汇总抵销!$J$5:$J$65538) -> 0 | D57: =SUMIF([28]母公司汇总抵销!$H$5:$H$65538,IF(OR(MID(TRIM($A57),2,1)="：",MID(TRIM($A57),2,1)="、"),REPLACEB(TRIM($A57),1,4,""),TRIM($A57)),[28]母公司汇总抵销!$J$5:$J$65538) -> 0 | E57: =SUMIF([28]母公司账项调整!$E$5:$E$65536,IF(OR(MID(TRIM($A57),2,1)="：",MID(TRIM($A57),2,1)="、"),REPLACEB(TRIM($A57),1,4,""),TRIM($A57)),[28]母公司账项调整!$J$5:$J$65536) -> 0 | F57: =SUMIF([28]母公司账项调整!$H$5:$H$65536,IF(OR(MID(TRIM($A57),2,1)="：",MID(TRIM($A57),2,1)="、"),REPLACEB(TRIM($A57),1,4,""),TRIM($A57)),[28]母公司账项调整!$J$5:$J$65536) -> 0 | G57: =SUMIF([28]母公司报表调整!$E$5:$E$65536,IF(OR(MID(TRIM($A57),2,1)="：",MID(TRIM($A57),2,1)="、"),REPLACEB(TRIM($A57),1,4,""),TRIM($A57)),[28]母公司报表调整!$J$5:$J$65536) -> 0 | H57: =SUMIF([28]母公司报表调整!$H$5:$H$65536,IF(OR(MID(TRIM($A57),2,1)="：",MID(TRIM($A57),2,1)="、"),REPLACEB(TRIM($A57),1,4,""),TRIM($A57)),[28]母公司报表调整!$J$5:$J$65536) -> 0 | I57: =B57-E57-G57+F57+H57-C57+D57 -> 0 | K57: =SUM(I57:J57) -> 0
A58: =[28]报表格式!L57 -> 9.自用房地产或作为存货的房地产转换为以公允价值计量的投资性房地产在转换日公允价值大于账面价值部分 | B58: =[28]母公司PL汇总!B58 -> 0 | C58: =SUMIF([28]母公司汇总抵销!$E$5:$E$65538,IF(OR(MID(TRIM($A58),2,1)="：",MID(TRIM($A58),2,1)="、"),REPLACEB(TRIM($A58),1,4,""),TRIM($A58)),[28]母公司汇总抵销!$J$5:$J$65538) -> 0 | D58: =SUMIF([28]母公司汇总抵销!$H$5:$H$65538,IF(OR(MID(TRIM($A58),2,1)="：",MID(TRIM($A58),2,1)="、"),REPLACEB(TRIM($A58),1,4,""),TRIM($A58)),[28]母公司汇总抵销!$J$5:$J$65538) -> 0 | E58: =SUMIF([28]母公司账项调整!$E$5:$E$65536,IF(OR(MID(TRIM($A58),2,1)="：",MID(TRIM($A58),2,1)="、"),REPLACEB(TRIM($A58),1,4,""),TRIM($A58)),[28]母公司账项调整!$J$5:$J$65536) -> 0 | F58: =SUMIF([28]母公司账项调整!$H$5:$H$65536,IF(OR(MID(TRIM($A58),2,1)="：",MID(TRIM($A58),2,1)="、"),REPLACEB(TRIM($A58),1,4,""),TRIM($A58)),[28]母公司账项调整!$J$5:$J$65536) -> 0 | G58: =SUMIF([28]母公司报表调整!$E$5:$E$65536,IF(OR(MID(TRIM($A58),2,1)="：",MID(TRIM($A58),2,1)="、"),REPLACEB(TRIM($A58),1,4,""),TRIM($A58)),[28]母公司报表调整!$J$5:$J$65536) -> 0 | H58: =SUMIF([28]母公司报表调整!$H$5:$H$65536,IF(OR(MID(TRIM($A58),2,1)="：",MID(TRIM($A58),2,1)="、"),REPLACEB(TRIM($A58),1,4,""),TRIM($A58)),[28]母公司报表调整!$J$5:$J$65536) -> 0 | I58: =B58-E58-G58+F58+H58-C58+D58 -> 0 | K58: =SUM(I58:J58) -> 0
A59: =[28]报表格式!L58 -> 10.多次交易分步处置子公司股权构成一揽子交易的，丧失控制权之前各次交易处置价款与对应净资产账面价值份额的差额 | B59: =[28]母公司PL汇总!B59 -> 0 | C59: =SUMIF([28]母公司汇总抵销!$E$5:$E$65538,IF(OR(MID(TRIM($A59),2,1)="：",MID(TRIM($A59),2,1)="、"),REPLACEB(TRIM($A59),1,4,""),TRIM($A59)),[28]母公司汇总抵销!$J$5:$J$65538) -> 0 | D59: =SUMIF([28]母公司汇总抵销!$H$5:$H$65538,IF(OR(MID(TRIM($A59),2,1)="：",MID(TRIM($A59),2,1)="、"),REPLACEB(TRIM($A59),1,4,""),TRIM($A59)),[28]母公司汇总抵销!$J$5:$J$65538) -> 0 | E59: =SUMIF([28]母公司账项调整!$E$5:$E$65536,IF(OR(MID(TRIM($A59),2,1)="：",MID(TRIM($A59),2,1)="、"),REPLACEB(TRIM($A59),1,4,""),TRIM($A59)),[28]母公司账项调整!$J$5:$J$65536) -> 0 | F59: =SUMIF([28]母公司账项调整!$H$5:$H$65536,IF(OR(MID(TRIM($A59),2,1)="：",MID(TRIM($A59),2,1)="、"),REPLACEB(TRIM($A59),1,4,""),TRIM($A59)),[28]母公司账项调整!$J$5:$J$65536) -> 0 | G59: =SUMIF([28]母公司报表调整!$E$5:$E$65536,IF(OR(MID(TRIM($A59),2,1)="：",MID(TRIM($A59),2,1)="、"),REPLACEB(TRIM($A59),1,4,""),TRIM($A59)),[28]母公司报表调整!$J$5:$J$65536) -> 0 | H59: =SUMIF([28]母公司报表调整!$H$5:$H$65536,IF(OR(MID(TRIM($A59),2,1)="：",MID(TRIM($A59),2,1)="、"),REPLACEB(TRIM($A59),1,4,""),TRIM($A59)),[28]母公司报表调整!$J$5:$J$65536) -> 0 | I59: =B59-E59-G59+F59+H59-C59+D59 -> 0 | K59: =SUM(I59:J59) -> 0
A60: =[28]报表格式!L59 -> 11.其他 | B60: =[28]母公司PL汇总!B60 -> 0 | C60: =SUMIF([28]母公司汇总抵销!$E$5:$E$65538,IF(OR(MID(TRIM($A60),2,1)="：",MID(TRIM($A60),2,1)="、"),REPLACEB(TRIM($A60),1,4,""),TRIM($A60)),[28]母公司汇总抵销!$J$5:$J$65538) -> 0 | D60: =SUMIF([28]母公司汇总抵销!$H$5:$H$65538,IF(OR(MID(TRIM($A60),2,1)="：",MID(TRIM($A60),2,1)="、"),REPLACEB(TRIM($A60),1,4,""),TRIM($A60)),[28]母公司汇总抵销!$J$5:$J$65538) -> 0 | E60: =SUMIF([28]母公司账项调整!$E$5:$E$65536,IF(OR(MID(TRIM($A60),2,1)="：",MID(TRIM($A60),2,1)="、"),REPLACEB(TRIM($A60),1,4,""),TRIM($A60)),[28]母公司账项调整!$J$5:$J$65536) -> 0 | F60: =SUMIF([28]母公司账项调整!$H$5:$H$65536,IF(OR(MID(TRIM($A60),2,1)="：",MID(TRIM($A60),2,1)="、"),REPLACEB(TRIM($A60),1,4,""),TRIM($A60)),[28]母公司账项调整!$J$5:$J$65536) -> 0 | G60: =SUMIF([28]母公司报表调整!$E$5:$E$65536,IF(OR(MID(TRIM($A60),2,1)="：",MID(TRIM($A60),2,1)="、"),REPLACEB(TRIM($A60),1,4,""),TRIM($A60)),[28]母公司报表调整!$J$5:$J$65536) -> 0 | H60: =SUMIF([28]母公司报表调整!$H$5:$H$65536,IF(OR(MID(TRIM($A60),2,1)="：",MID(TRIM($A60),2,1)="、"),REPLACEB(TRIM($A60),1,4,""),TRIM($A60)),[28]母公司报表调整!$J$5:$J$65536) -> 0 | I60: =B60-E60-G60+F60+H60-C60+D60 -> 0 | K60: =SUM(I60:J60) -> 0
A61: =[28]报表格式!L60 -> 归属于少数股东的其他综合收益的税后净额 | B61: =[28]母公司PL汇总!B61 -> 0 | C61: =SUMIF([28]母公司汇总抵销!$E$5:$E$65538,IF(OR(MID(TRIM($A61),2,1)="：",MID(TRIM($A61),2,1)="、"),REPLACEB(TRIM($A61),1,4,""),TRIM($A61)),[28]母公司汇总抵销!$J$5:$J$65538) -> 0 | D61: =SUMIF([28]母公司汇总抵销!$H$5:$H$65538,IF(OR(MID(TRIM($A61),2,1)="：",MID(TRIM($A61),2,1)="、"),REPLACEB(TRIM($A61),1,4,""),TRIM($A61)),[28]母公司汇总抵销!$J$5:$J$65538) -> 0 | E61: =SUMIF([28]母公司账项调整!$E$5:$E$65536,IF(OR(MID(TRIM($A61),2,1)="：",MID(TRIM($A61),2,1)="、"),REPLACEB(TRIM($A61),1,4,""),TRIM($A61)),[28]母公司账项调整!$J$5:$J$65536) -> 0 | F61: =SUMIF([28]母公司账项调整!$H$5:$H$65536,IF(OR(MID(TRIM($A61),2,1)="：",MID(TRIM($A61),2,1)="、"),REPLACEB(TRIM($A61),1,4,""),TRIM($A61)),[28]母公司账项调整!$J$5:$J$65536) -> 0 | G61: =SUMIF([28]母公司报表调整!$E$5:$E$65536,IF(OR(MID(TRIM($A61),2,1)="：",MID(TRIM($A61),2,1)="、"),REPLACEB(TRIM($A61),1,4,""),TRIM($A61)),[28]母公司报表调整!$J$5:$J$65536) -> 0 | H61: =SUMIF([28]母公司报表调整!$H$5:$H$65536,IF(OR(MID(TRIM($A61),2,1)="：",MID(TRIM($A61),2,1)="、"),REPLACEB(TRIM($A61),1,4,""),TRIM($A61)),[28]母公司报表调整!$J$5:$J$65536) -> 0 | I61: =B61-E61-G61+F61+H61-C61+D61 -> 0 | K61: =SUM(I61:J61) -> 0
A62: =[28]报表格式!L61 -> 六、综合收益总额 | B62: =[28]母公司PL汇总!B62 -> 0 | C62: =C34+C41 -> 0 | D62: =D34+D41 -> 0 | E62: =E34+E41 -> 0 | F62: =F34+F41 -> 0 | G62: =G34+G41 -> 0 | H62: =H34+H41 -> 0 | I62: =I34+I41 -> 0 | J62: =J34+J41 -> 0 | K62: =SUM(I62:J62) -> 0
A63: =[28]报表格式!L62 -> 归属于母公司股东的综合收益总额 | B63: =[28]母公司PL汇总!B63 -> 0 | C63: =C39+C42 -> 0 | D63: =D39+D42 -> 0 | E63: =E39+E42 -> 0 | F63: =F39+F42 -> 0 | G63: =G39+G42 -> 0 | H63: =H39+H42 -> 0 | I63: =I39+I42 -> 0 | J63: =J39+J42 -> 0 | K63: =SUM(I63:J63) -> 0
A64: =[28]报表格式!L63 -> 归属于少数股东的综合收益总额 | B64: =[28]母公司PL汇总!B64 -> 0 | C64: =C40+C61 -> 0 | D64: =D40+D61 -> 0 | E64: =E40+E61 -> 0 | F64: =F40+F61 -> 0 | G64: =G40+G61 -> 0 | H64: =H40+H61 -> 0 | I64: =B64-E64-G64+F64+H64-C64+D64 -> 0 | K64: =SUM(I64:J64) -> 0
A65: =[28]报表格式!L64 -> 七、每股收益
A66: =[28]报表格式!L65 -> （一）基本每股收益 | B66: =[28]母公司PL汇总!B66 -> 0 | C66: =SUMIF([28]母公司汇总抵销!$E$5:$E$65538,IF(OR(MID(TRIM($A66),2,1)="：",MID(TRIM($A66),2,1)="、"),REPLACEB(TRIM($A66),1,4,""),TRIM($A66)),[28]母公司汇总抵销!$J$5:$J$65538) -> 0 | D66: =SUMIF([28]母公司汇总抵销!$H$5:$H$65538,IF(OR(MID(TRIM($A66),2,1)="：",MID(TRIM($A66),2,1)="、"),REPLACEB(TRIM($A66),1,4,""),TRIM($A66)),[28]母公司汇总抵销!$J$5:$J$65538) -> 0 | E66: =SUMIF([28]母公司账项调整!$E$5:$E$65536,IF(OR(MID(TRIM($A66),2,1)="：",MID(TRIM($A66),2,1)="、"),REPLACEB(TRIM($A66),1,4,""),TRIM($A66)),[28]母公司账项调整!$J$5:$J$65536) -> 0 | F66: =SUMIF([28]母公司账项调整!$H$5:$H$65536,IF(OR(MID(TRIM($A66),2,1)="：",MID(TRIM($A66),2,1)="、"),REPLACEB(TRIM($A66),1,4,""),TRIM($A66)),[28]母公司账项调整!$J$5:$J$65536) -> 0 | G66: =SUMIF([28]母公司报表调整!$E$5:$E$65536,IF(OR(MID(TRIM($A66),2,1)="：",MID(TRIM($A66),2,1)="、"),REPLACEB(TRIM($A66),1,4,""),TRIM($A66)),[28]母公司报表调整!$J$5:$J$65536) -> 0 | H66: =SUMIF([28]母公司报表调整!$H$5:$H$65536,IF(OR(MID(TRIM($A66),2,1)="：",MID(TRIM($A66),2,1)="、"),REPLACEB(TRIM($A66),1,4,""),TRIM($A66)),[28]母公司报表调整!$J$5:$J$65536) -> 0 | I66: =B66-E66-G66+F66+H66-C66+D66 -> 0 | K66: =SUM(I66:J66) -> 0
A67: =[28]报表格式!L66 -> （二）稀释每股收益 | B67: =[28]母公司PL汇总!B67 -> 0 | C67: =SUMIF([28]母公司汇总抵销!$E$5:$E$65538,IF(OR(MID(TRIM($A67),2,1)="：",MID(TRIM($A67),2,1)="、"),REPLACEB(TRIM($A67),1,4,""),TRIM($A67)),[28]母公司汇总抵销!$J$5:$J$65538) -> 0 | D67: =SUMIF([28]母公司汇总抵销!$H$5:$H$65538,IF(OR(MID(TRIM($A67),2,1)="：",MID(TRIM($A67),2,1)="、"),REPLACEB(TRIM($A67),1,4,""),TRIM($A67)),[28]母公司汇总抵销!$J$5:$J$65538) -> 0 | E67: =SUMIF([28]母公司账项调整!$E$5:$E$65536,IF(OR(MID(TRIM($A67),2,1)="：",MID(TRIM($A67),2,1)="、"),REPLACEB(TRIM($A67),1,4,""),TRIM($A67)),[28]母公司账项调整!$J$5:$J$65536) -> 0 | F67: =SUMIF([28]母公司账项调整!$H$5:$H$65536,IF(OR(MID(TRIM($A67),2,1)="：",MID(TRIM($A67),2,1)="、"),REPLACEB(TRIM($A67),1,4,""),TRIM($A67)),[28]母公司账项调整!$J$5:$J$65536) -> 0 | G67: =SUMIF([28]母公司报表调整!$E$5:$E$65536,IF(OR(MID(TRIM($A67),2,1)="：",MID(TRIM($A67),2,1)="、"),REPLACEB(TRIM($A67),1,4,""),TRIM($A67)),[28]母公司报表调整!$J$5:$J$65536) -> 0 | H67: =SUMIF([28]母公司报表调整!$H$5:$H$65536,IF(OR(MID(TRIM($A67),2,1)="：",MID(TRIM($A67),2,1)="、"),REPLACEB(TRIM($A67),1,4,""),TRIM($A67)),[28]母公司报表调整!$J$5:$J$65536) -> 0 | I67: =B67-E67-G67+F67+H67-C67+D67 -> 0 | K67: =SUM(I67:J67) -> 0
A68: =[28]报表格式!L67 -> 八、利润分配
A69: =[28]报表格式!L68 -> （一）年初未分配利润 | B69: =[28]母公司PL汇总!B69 -> 0 | C69: =SUMIF([28]母公司汇总抵销!$E$5:$E$65538,IF(OR(MID(TRIM($A69),1,1)="（",MID(TRIM($A69),2,1)="、"),REPLACEB(TRIM($A69),1,6,""),TRIM($A69)),[28]母公司汇总抵销!$J$5:$J$65538) -> 0 | D69: =SUMIF([28]母公司汇总抵销!$H$5:$H$65538,IF(OR(MID(TRIM($A69),1,1)="（",MID(TRIM($A69),2,1)="、"),REPLACEB(TRIM($A69),1,6,""),TRIM($A69)),[28]母公司汇总抵销!$J$5:$J$65538) -> 0 | E69: =SUMIF([28]母公司账项调整!$E$5:$E$65536,IF(OR(MID(TRIM($A69),1,1)="（",MID(TRIM($A69),2,1)="、"),REPLACEB(TRIM($A69),1,6,""),TRIM($A69)),[28]母公司账项调整!$J$5:$J$65536) -> 0 | F69: =SUMIF([28]母公司账项调整!$H$5:$H$65536,IF(OR(MID(TRIM($A69),1,1)="（",MID(TRIM($A69),2,1)="、"),REPLACEB(TRIM($A69),1,6,""),TRIM($A69)),[28]母公司账项调整!$J$5:$J$65536) -> 0 | G69: =SUMIF([28]母公司报表调整!$E$5:$E$65536,IF(OR(MID(TRIM($A69),1,1)="（",MID(TRIM($A69),2,1)="、"),REPLACEB(TRIM($A69),1,6,""),TRIM($A69)),[28]母公司报表调整!$J$5:$J$65536) -> 0 | H69: =SUMIF([28]母公司报表调整!$H$5:$H$65536,IF(OR(MID(TRIM($A69),1,1)="（",MID(TRIM($A69),2,1)="、"),REPLACEB(TRIM($A69),1,6,""),TRIM($A69)),[28]母公司报表调整!$J$5:$J$65536) -> 0 | I69: =B69-E69-G69+F69+H69-C69+D69 -> 0 | K69: =SUM(I69:J69) -> 0
A70: =[28]报表格式!L69 -> （二）可供分配的利润 | B70: =[28]母公司PL汇总!B70 -> 0 | C70: =C39+C69 -> 0 | D70: =D39+D69 -> 0 | E70: =E39+E69 -> 0 | F70: =F39+F69 -> 0 | G70: =G39+G69 -> 0 | H70: =H39+H69 -> 0 | I70: =I39+I69 -> 0 | J70: =J39+J69 -> 0 | K70: =SUM(I70:J70) -> 0
A71: =[28]报表格式!L70 -> 1、提取法定盈余公积 | B71: =[28]母公司PL汇总!B71 -> 0 | C71: =SUMIF([28]母公司汇总抵销!$E$5:$E$65538,IF(OR(MID(TRIM($A71),2,1)="：",MID(TRIM($A71),2,1)="."),REPLACEB(TRIM($A71),1,4,""),TRIM($A71)),[28]母公司汇总抵销!$J$5:$J$65538) -> 0 | D71: =SUMIF([28]母公司汇总抵销!$H$5:$H$65538,IF(OR(MID(TRIM($A71),2,1)="：",MID(TRIM($A71),2,1)="."),REPLACEB(TRIM($A71),1,4,""),TRIM($A71)),[28]母公司汇总抵销!$J$5:$J$65538) -> 0 | E71: =SUMIF([28]母公司账项调整!$E$5:$E$65536,IF(OR(MID(TRIM($A71),2,1)="：",MID(TRIM($A71),2,1)="."),REPLACEB(TRIM($A71),1,4,""),TRIM($A71)),[28]母公司账项调整!$J$5:$J$65536) -> 0 | F71: =SUMIF([28]母公司账项调整!$H$5:$H$65536,IF(OR(MID(TRIM($A71),2,1)="：",MID(TRIM($A71),2,1)="."),REPLACEB(TRIM($A71),1,4,""),TRIM($A71)),[28]母公司账项调整!$J$5:$J$65536) -> 0 | G71: =SUMIF([28]母公司报表调整!$E$5:$E$65536,IF(OR(MID(TRIM($A71),2,1)="：",MID(TRIM($A71),2,1)="."),REPLACEB(TRIM($A71),1,4,""),TRIM($A71)),[28]母公司报表调整!$J$5:$J$65536) -> 0 | H71: =SUMIF([28]母公司报表调整!$H$5:$H$65536,IF(OR(MID(TRIM($A71),2,1)="：",MID(TRIM($A71),2,1)="."),REPLACEB(TRIM($A71),1,4,""),TRIM($A71)),[28]母公司报表调整!$J$5:$J$65536) -> 0 | I71: =B71-E71-G71+F71+H71-C71+D71 -> 0 | K71: =SUM(I71:J71) -> 0
A72: =[28]报表格式!L71 -> 2、其他 | B72: =[28]母公司PL汇总!B72 -> 0 | C72: =SUMIF([28]母公司汇总抵销!$E$5:$E$65538,IF(OR(MID(TRIM($A72),2,1)="：",MID(TRIM($A72),2,1)="."),REPLACEB(TRIM($A72),1,4,""),TRIM($A72)),[28]母公司汇总抵销!$J$5:$J$65538) -> 0 | D72: =SUMIF([28]母公司汇总抵销!$H$5:$H$65538,IF(OR(MID(TRIM($A72),2,1)="：",MID(TRIM($A72),2,1)="."),REPLACEB(TRIM($A72),1,4,""),TRIM($A72)),[28]母公司汇总抵销!$J$5:$J$65538) -> 0 | E72: =SUMIF([28]母公司账项调整!$E$5:$E$65536,IF(OR(MID(TRIM($A72),2,1)="：",MID(TRIM($A72),2,1)="."),REPLACEB(TRIM($A72),1,4,""),TRIM($A72)),[28]母公司账项调整!$J$5:$J$65536) -> 0 | F72: =SUMIF([28]母公司账项调整!$H$5:$H$65536,IF(OR(MID(TRIM($A72),2,1)="：",MID(TRIM($A72),2,1)="."),REPLACEB(TRIM($A72),1,4,""),TRIM($A72)),[28]母公司账项调整!$J$5:$J$65536) -> 0 | G72: =SUMIF([28]母公司报表调整!$E$5:$E$65536,IF(OR(MID(TRIM($A72),2,1)="：",MID(TRIM($A72),2,1)="."),REPLACEB(TRIM($A72),1,4,""),TRIM($A72)),[28]母公司报表调整!$J$5:$J$65536) -> 0 | H72: =SUMIF([28]母公司报表调整!$H$5:$H$65536,IF(OR(MID(TRIM($A72),2,1)="：",MID(TRIM($A72),2,1)="."),REPLACEB(TRIM($A72),1,4,""),TRIM($A72)),[28]母公司报表调整!$J$5:$J$65536) -> 0 | I72: =B72-E72-G72+F72+H72-C72+D72 -> 0 | K72: =SUM(I72:J72) -> 0
A73: =[28]报表格式!L72 -> （三）可供投资者分配的利润 | B73: =[28]母公司PL汇总!B73 -> 0 | C73: =C70-C71-C72 -> 0 | D73: =D70-D71-D72 -> 0 | E73: =E70-E71-E72 -> 0 | F73: =F70-F71-F72 -> 0 | G73: =G70-G71-G72 -> 0 | H73: =H70-H71-H72 -> 0 | I73: =I70-I71-I72 -> 0 | J73: =J70-J71-J72 -> 0 | K73: =SUM(I73:J73) -> 0
A74: =[28]报表格式!L73 -> 1、应付优先股股利 | B74: =[28]母公司PL汇总!B74 -> 0 | C74: =SUMIF([28]母公司汇总抵销!$E$5:$E$65538,IF(OR(MID(TRIM($A74),2,1)="：",MID(TRIM($A74),2,1)="."),REPLACEB(TRIM($A74),1,4,""),TRIM($A74)),[28]母公司汇总抵销!$J$5:$J$65538) -> 0 | D74: =SUMIF([28]母公司汇总抵销!$H$5:$H$65538,IF(OR(MID(TRIM($A74),2,1)="：",MID(TRIM($A74),2,1)="."),REPLACEB(TRIM($A74),1,4,""),TRIM($A74)),[28]母公司汇总抵销!$J$5:$J$65538) -> 0 | E74: =SUMIF([28]母公司账项调整!$E$5:$E$65536,IF(OR(MID(TRIM($A74),2,1)="：",MID(TRIM($A74),2,1)="."),REPLACEB(TRIM($A74),1,4,""),TRIM($A74)),[28]母公司账项调整!$J$5:$J$65536) -> 0 | F74: =SUMIF([28]母公司账项调整!$H$5:$H$65536,IF(OR(MID(TRIM($A74),2,1)="：",MID(TRIM($A74),2,1)="."),REPLACEB(TRIM($A74),1,4,""),TRIM($A74)),[28]母公司账项调整!$J$5:$J$65536) -> 0 | G74: =SUMIF([28]母公司报表调整!$E$5:$E$65536,IF(OR(MID(TRIM($A74),2,1)="：",MID(TRIM($A74),2,1)="."),REPLACEB(TRIM($A74),1,4,""),TRIM($A74)),[28]母公司报表调整!$J$5:$J$65536) -> 0 | H74: =SUMIF([28]母公司报表调整!$H$5:$H$65536,IF(OR(MID(TRIM($A74),2,1)="：",MID(TRIM($A74),2,1)="."),REPLACEB(TRIM($A74),1,4,""),TRIM($A74)),[28]母公司报表调整!$J$5:$J$65536) -> 0 | I74: =B74-E74-G74+F74+H74-C74+D74 -> 0 | K74: =SUM(I74:J74) -> 0
A75: =[28]报表格式!L74 -> 2、提取任意盈余公积 | B75: =[28]母公司PL汇总!B75 -> 0 | C75: =SUMIF([28]母公司汇总抵销!$E$5:$E$65538,IF(OR(MID(TRIM($A75),2,1)="：",MID(TRIM($A75),2,1)="."),REPLACEB(TRIM($A75),1,4,""),TRIM($A75)),[28]母公司汇总抵销!$J$5:$J$65538) -> 0 | D75: =SUMIF([28]母公司汇总抵销!$H$5:$H$65538,IF(OR(MID(TRIM($A75),2,1)="：",MID(TRIM($A75),2,1)="."),REPLACEB(TRIM($A75),1,4,""),TRIM($A75)),[28]母公司汇总抵销!$J$5:$J$65538) -> 0 | E75: =SUMIF([28]母公司账项调整!$E$5:$E$65536,IF(OR(MID(TRIM($A75),2,1)="：",MID(TRIM($A75),2,1)="."),REPLACEB(TRIM($A75),1,4,""),TRIM($A75)),[28]母公司账项调整!$J$5:$J$65536) -> 0 | F75: =SUMIF([28]母公司账项调整!$H$5:$H$65536,IF(OR(MID(TRIM($A75),2,1)="：",MID(TRIM($A75),2,1)="."),REPLACEB(TRIM($A75),1,4,""),TRIM($A75)),[28]母公司账项调整!$J$5:$J$65536) -> 0 | G75: =SUMIF([28]母公司报表调整!$E$5:$E$65536,IF(OR(MID(TRIM($A75),2,1)="：",MID(TRIM($A75),2,1)="."),REPLACEB(TRIM($A75),1,4,""),TRIM($A75)),[28]母公司报表调整!$J$5:$J$65536) -> 0 | H75: =SUMIF([28]母公司报表调整!$H$5:$H$65536,IF(OR(MID(TRIM($A75),2,1)="：",MID(TRIM($A75),2,1)="."),REPLACEB(TRIM($A75),1,4,""),TRIM($A75)),[28]母公司报表调整!$J$5:$J$65536) -> 0 | I75: =B75-E75-G75+F75+H75-C75+D75 -> 0 | K75: =SUM(I75:J75) -> 0
A76: =[28]报表格式!L75 -> 3、应付普通股股利（应付利润） | B76: =[28]母公司PL汇总!B76 -> 0 | C76: =SUMIF([28]母公司汇总抵销!$E$5:$E$65538,IF(OR(MID(TRIM($A76),2,1)="：",MID(TRIM($A76),2,1)="."),REPLACEB(TRIM($A76),1,4,""),TRIM($A76)),[28]母公司汇总抵销!$J$5:$J$65538) -> 0 | D76: =SUMIF([28]母公司汇总抵销!$H$5:$H$65538,IF(OR(MID(TRIM($A76),2,1)="：",MID(TRIM($A76),2,1)="."),REPLACEB(TRIM($A76),1,4,""),TRIM($A76)),[28]母公司汇总抵销!$J$5:$J$65538) -> 0 | E76: =SUMIF([28]母公司账项调整!$E$5:$E$65536,IF(OR(MID(TRIM($A76),2,1)="：",MID(TRIM($A76),2,1)="."),REPLACEB(TRIM($A76),1,4,""),TRIM($A76)),[28]母公司账项调整!$J$5:$J$65536) -> 0 | F76: =SUMIF([28]母公司账项调整!$H$5:$H$65536,IF(OR(MID(TRIM($A76),2,1)="：",MID(TRIM($A76),2,1)="."),REPLACEB(TRIM($A76),1,4,""),TRIM($A76)),[28]母公司账项调整!$J$5:$J$65536) -> 0 | G76: =SUMIF([28]母公司报表调整!$E$5:$E$65536,IF(OR(MID(TRIM($A76),2,1)="：",MID(TRIM($A76),2,1)="."),REPLACEB(TRIM($A76),1,4,""),TRIM($A76)),[28]母公司报表调整!$J$5:$J$65536) -> 0 | H76: =SUMIF([28]母公司报表调整!$H$5:$H$65536,IF(OR(MID(TRIM($A76),2,1)="：",MID(TRIM($A76),2,1)="."),REPLACEB(TRIM($A76),1,4,""),TRIM($A76)),[28]母公司报表调整!$J$5:$J$65536) -> 0 | I76: =B76-E76-G76+F76+H76-C76+D76 -> 0 | K76: =SUM(I76:J76) -> 0
A77: =[28]报表格式!L76 -> 4、转作资本（或股本）的普通股股利 | B77: =[28]母公司PL汇总!B77 -> 0 | C77: =SUMIF([28]母公司汇总抵销!$E$5:$E$65538,IF(OR(MID(TRIM($A77),2,1)="：",MID(TRIM($A77),2,1)="."),REPLACEB(TRIM($A77),1,4,""),TRIM($A77)),[28]母公司汇总抵销!$J$5:$J$65538) -> 0 | D77: =SUMIF([28]母公司汇总抵销!$H$5:$H$65538,IF(OR(MID(TRIM($A77),2,1)="：",MID(TRIM($A77),2,1)="."),REPLACEB(TRIM($A77),1,4,""),TRIM($A77)),[28]母公司汇总抵销!$J$5:$J$65538) -> 0 | E77: =SUMIF([28]母公司账项调整!$E$5:$E$65536,IF(OR(MID(TRIM($A77),2,1)="：",MID(TRIM($A77),2,1)="."),REPLACEB(TRIM($A77),1,4,""),TRIM($A77)),[28]母公司账项调整!$J$5:$J$65536) -> 0 | F77: =SUMIF([28]母公司账项调整!$H$5:$H$65536,IF(OR(MID(TRIM($A77),2,1)="：",MID(TRIM($A77),2,1)="."),REPLACEB(TRIM($A77),1,4,""),TRIM($A77)),[28]母公司账项调整!$J$5:$J$65536) -> 0 | G77: =SUMIF([28]母公司报表调整!$E$5:$E$65536,IF(OR(MID(TRIM($A77),2,1)="：",MID(TRIM($A77),2,1)="."),REPLACEB(TRIM($A77),1,4,""),TRIM($A77)),[28]母公司报表调整!$J$5:$J$65536) -> 0 | H77: =SUMIF([28]母公司报表调整!$H$5:$H$65536,IF(OR(MID(TRIM($A77),2,1)="：",MID(TRIM($A77),2,1)="."),REPLACEB(TRIM($A77),1,4,""),TRIM($A77)),[28]母公司报表调整!$J$5:$J$65536) -> 0 | I77: =B77-E77-G77+F77+H77-C77+D77 -> 0 | K77: =SUM(I77:J77) -> 0
A78: =[28]报表格式!L77 -> 5、其他 | B78: =[28]母公司PL汇总!B78 -> 0 | C78: =SUMIF([28]母公司汇总抵销!$E$5:$E$65538,IF(OR(MID(TRIM($A78),2,1)="：",MID(TRIM($A78),2,1)="."),REPLACEB(TRIM($A78),1,4,""),TRIM($A78)),[28]母公司汇总抵销!$J$5:$J$65538) -> 0 | D78: =SUMIF([28]母公司汇总抵销!$H$5:$H$65538,IF(OR(MID(TRIM($A78),2,1)="：",MID(TRIM($A78),2,1)="."),REPLACEB(TRIM($A78),1,4,""),TRIM($A78)),[28]母公司汇总抵销!$J$5:$J$65538) -> 0 | E78: =SUMIF([28]母公司账项调整!$E$5:$E$65536,IF(OR(MID(TRIM($A78),2,1)="：",MID(TRIM($A78),2,1)="."),REPLACEB(TRIM($A78),1,4,""),TRIM($A78)),[28]母公司账项调整!$J$5:$J$65536) -> 0 | F78: =SUMIF([28]母公司账项调整!$H$5:$H$65536,IF(OR(MID(TRIM($A78),2,1)="：",MID(TRIM($A78),2,1)="."),REPLACEB(TRIM($A78),1,4,""),TRIM($A78)),[28]母公司账项调整!$J$5:$J$65536) -> 0 | G78: =SUMIF([28]母公司报表调整!$E$5:$E$65536,IF(OR(MID(TRIM($A78),2,1)="：",MID(TRIM($A78),2,1)="."),REPLACEB(TRIM($A78),1,4,""),TRIM($A78)),[28]母公司报表调整!$J$5:$J$65536) -> 0 | H78: =SUMIF([28]母公司报表调整!$H$5:$H$65536,IF(OR(MID(TRIM($A78),2,1)="：",MID(TRIM($A78),2,1)="."),REPLACEB(TRIM($A78),1,4,""),TRIM($A78)),[28]母公司报表调整!$J$5:$J$65536) -> 0 | I78: =B78-E78-G78+F78+H78-C78+D78 -> 0 | K78: =SUM(I78:J78) -> 0
A79: =[28]报表格式!L78 -> 九、未分配利润 | B79: =[28]母公司PL汇总!B79 -> 0 | C79: =C73-SUM(C74:C78) -> 0 | D79: =D73-SUM(D74:D78) -> 0 | E79: =E73-SUM(E74:E78) -> 0 | F79: =F73-SUM(F74:F78) -> 0 | G79: =G73-SUM(G74:G78) -> 0 | H79: =H73-SUM(H74:H78) -> 0 | I79: =I73-SUM(I74:I78) -> 0 | J79: =J73-SUM(J74:J78) -> 0 | K79: =SUM(I79:J79) -> 0
B80: =#REF! -> #REF! | C80: =SUM(C6,C9,C12:C16,C19:C20,C23:C27,C29:C30,C32:C33,C40,C44:C48,C50:C61,C66:C67,C69,C71:C72,C74:C78) -> 0 | D80: =SUM(D6,D9,D12:D16,D19:D20,D23:D27,D29:D30,D32:D33,D40,D44:D48,D50:D61,D66:D67,D69,D71:D72,D74:D78) -> 0 | E80: =SUM(E6,E9,E12:E16,E19:E20,E23:E27,E29:E30,E32:E33,E40,E44:E48,E50:E61,E66:E67,E69,E71:E72,E74:E78) -> 0 | F80: =SUM(F6,F9,F12:F16,F19:F20,F23:F27,F29:F30,F32:F33,F40,F44:F48,F50:F61,F66:F67,F69,F71:F72,F74:F78) -> 0 | G80: =SUM(G6,G9,G12:G16,G19:G20,G23:G27,G29:G30,G32:G33,G40,G44:G48,G50:G61,G66:G67,G69,G71:G72,G74:G78) -> 0 | H80: =SUM(H6,H9,H12:H16,H19:H20,H23:H27,H29:H30,H32:H33,H40,H44:H48,H50:H61,H66:H67,H69,H71:H72,H74:H78) -> 0 | J80: =SUM(J6,J9,J12:J14,J16,J20,J21,J22:J23,J29,J30,J32:J33,J40,J44:J48,J50:J60,J61,J69,J71:J72,J74:J78) -> 0 | K80: =#REF! -> #REF!
B81: =B80-B79 -> #REF! | K81: =K80-K79 -> #REF!

Sheet TB现金流
A1: 母公司汇总现金流量表试算平衡
A2: =CONCATENATE("客户名称：",[28]说明!E23) -> 客户名称： | B2: =CONCATENATE("编制：",[28]说明!E36) -> 编制： | D2: =CONCATENATE("复核：",[28]说明!E37) -> 复核： | E2: 索引：
A3: =CONCATENATE("会计时点：",TEXT([28]说明!E32,"yyyy.mm.dd")) -> 会计时点：2019.12.31 | B3: =CONCATENATE("日期：",TEXT(NOW(),"yyyy.mm.dd")) -> 日期：2026.05.03 | D3: 日期： | E3: 分页：
A4: 项目 | B4: 未审数 | C4: 汇总抵销 | D4: 报表调整 | E4: 审定数
A6: =[28]报表格式!Q5 -> 一、经营活动产生的现金流量
A7: =[28]报表格式!Q6 -> 销售商品、提供劳务收到的现金
A8: =[28]报表格式!Q7 -> 收到的税费返还
A9: =[28]报表格式!Q8 -> 收到的其他与经营活动有关的现金
A10: =[28]报表格式!Q10 -> 经营活动现金流入小计
A11: =[28]报表格式!Q11 -> 购买商品、接受劳务支付的现金
A12: =[28]报表格式!Q12 -> 支付给职工以及为职工支付的现金
A13: =[28]报表格式!Q13 -> 支付各项税费
A14: =[28]报表格式!Q14 -> 支付的其他与经营活动有关的现金
A15: =[28]报表格式!Q16 -> 经营活动现金流出小计
A16: =[28]报表格式!Q17 -> 经营活动产生的现金流量净额
A17: =[28]报表格式!Q18 -> 二、投资活动产生的现金流量
A18: =[28]报表格式!Q19 -> 收回投资所收到的现金
A19: =[28]报表格式!Q20 -> 取得投资收益所收到的现金
A20: =[28]报表格式!Q21 -> 处置固定资产、无形资产和其他长期资产而收到的现金净额
A21: =[28]报表格式!Q22 -> 处置子公司及其他营业单位收到的现金净额
A22: =[28]报表格式!Q23 -> 收到其他与投资活动有关的现金
A23: =[28]报表格式!Q25 -> 投资活动现金流入小计
A24: =[28]报表格式!Q26 -> 购置固定资产、无形资产和其他长期资产所支付现金
A25: =[28]报表格式!Q27 -> 投资所支付的现金
A26: =[28]报表格式!Q28 -> 取得子公司及其他营业单位支付的现金净额
A27: =[28]报表格式!Q29 -> 支付其他与投资活动有关的现金
A28: =[28]报表格式!Q31 -> 投资活动现金流出小计
A29: =[28]报表格式!Q32 -> 投资活动产生的现金流量净额
A30: =[28]报表格式!Q33 -> 三、筹资活动产生的现金流量
A31: =[28]报表格式!Q34 -> 吸收投资所收到的现金
A32: =[28]报表格式!Q35 -> 其中:子公司吸收少数股东权益性投资收到的现金
A33: =[28]报表格式!Q36 -> 取得借款收到的现金
A34: =[28]报表格式!Q37 -> 收到的其他与筹资活动有关的现金
A35: =[28]报表格式!Q38 -> 0
A36: =[28]报表格式!Q39 -> 筹资活动现金流入小计
A37: =[28]报表格式!Q40 -> 偿还债务支付的现金
A38: =[28]报表格式!Q41 -> 分配股利、利润或偿付利息支付的现金
A39: =[28]报表格式!Q42 -> 其中:子公司支付少数股东的现金股利
... A43: =[28]报表格式!Q46 -> 筹资活动产生的现金流量净额
A45: =[28]报表格式!Q47 -> 四、汇率变动对现金及现金等价物的影响
A46: =[28]报表格式!Q48 -> 五、现金及现金等价物净增加额
A47: =[28]报表格式!Q49 -> 加：期初现金及现金等价物余额
A48: =[28]报表格式!Q50 -> 六、期末现金及现金等价物余额
A51: =[28]报表格式!U4 -> 补充资料
A52: =[28]报表格式!U5 -> 1、将净利润调节为经营活动现金流量：
A53: =[28]报表格式!U6 -> 净利润
A54: =[28]报表格式!U9 -> 加：资产减值损失
A55: =[28]报表格式!U10 -> 信用减值损失
A56: =[28]报表格式!U11 -> 固定资产折旧、油气资产折耗、生产性生物资产折旧
A57: =[28]报表格式!U12 -> 无形资产摊销
A58: =[28]报表格式!U13 -> 长期待摊费用摊销
A59: =[28]报表格式!U14 -> 处置固定资产、无形资产和其他长期资产的损失（收益以“－”号填列）
A60: =[28]报表格式!U15 -> 固定资产报废损失（收益以“－”号填列）
A61: =[28]报表格式!U16 -> 公允价值变动损失（收益以“－”号填列）
A62: =[28]报表格式!U17 -> 财务费用（收益以“－”号填列）
A63: =[28]报表格式!U18 -> 投资损失（收益以“－”号填列）
A64: =[28]报表格式!U19 -> 递延所得税资产减少（增加以“－”号填列）
A65: =[28]报表格式!U20 -> 递延所得税负债增加（减少以“－”号填列）
... A68: =[28]报表格式!U23 -> 经营性应付项目的增加（减少以“－”号填列）
A69: =[28]报表格式!U26 -> 经营活动产生的现金流量净额
A70: =[28]报表格式!U27 -> 0
A71: =[28]报表格式!U28 -> 2、不涉及现金收支的投资和筹资活动：
A72: =[28]报表格式!U29 -> 债务转为资本
A73: =[28]报表格式!U30 -> 一年内到期的可转换公司债券
A74: =[28]报表格式!U31 -> 融资租入固定资产
A75: =[28]报表格式!U32 -> 其他
A76: =[28]报表格式!U34 -> 0
A77: =[28]报表格式!U35 -> 3、现金及现金等价物净变动情况：
A78: =[28]报表格式!U36 -> 现金的期末余额
A79: =[28]报表格式!U37 -> 减：现金的期初余额
A80: =[28]报表格式!U38 -> 加：现金等价物的期末余额
A81: =[28]报表格式!U39 -> 减：现金等价物的期初余额
A82: =[28]报表格式!U50 -> 现金及现金等价物净增加额
