Workbook
Name _13102: #REF!
Name _13302: #REF!
Name _13398: #REF!
Name _18102: #REF!
Name _18198: #REF!
Name _2003附注: [1]附注汇总!$C$5:$AY$646
Name _2其他资产_开办费除外_明细表: #REF!
Name _scn11: #REF!
Name _scn15: #REF!
Name _scn16: #REF!
Name _scn17: #REF!
Name _scn19: #REF!
Name _scn2: #REF!
Name _scn20: #REF!
Name _scn3: #REF!
Name _scn4: #REF!
Name _scn5: #REF!
Name _scn6: #REF!
Name _scn7: #REF!
Name _scn8: #REF!
Name _scn9: #REF!
Name _scq1: #REF!
Name _scq11: #REF!
Name _scq15: #REF!
Name _scq16: #REF!
Name _scq17: #REF!
Name _scq19: #REF!
Name _scq2: #REF!
Name _scq20: #REF!
Name _scq3: #REF!
Name _scq4: #REF!
Name _scq5: #REF!
Name _scq6: #REF!
Name _scq7: #REF!
Name _scq8: #REF!
Name _scq9: #REF!
Name a: #REF!
Name Approach: [2]选择键!$G$2:$G$6
Name as: #REF!
Name AS2WebLink1: #REF!
Name AS2WebLink10: #REF!
Name AS2WebLink11: #REF!
Name AS2WebLink12: #REF!
Name AS2WebLink13: #REF!
Name AS2WebLink14: #REF!
Name AS2WebLink15: #REF!
Name AS2WebLink16: #REF!
Name AS2WebLink17: #REF!
Name AS2WebLink18: #REF!
Name AS2WebLink19: #REF!
Name AS2WebLink2: #REF!
Name AS2WebLink21: #REF!
Name AS2WebLink22: #REF!
Name AS2WebLink23: #REF!
Name AS2WebLink24: #REF!
Name AS2WebLink3: #REF!
Name AS2WebLink4: #REF!
Name AS2WebLink5: #REF!
Name AS2WebLink6: #REF!
Name AS2WebLink7: #REF!

Sheet 合并TB资产负债
A1: 合并资产负债表试算平衡
A2: 客户名称： | D2: 编制： | F2: 复核： | I2: 索引：
A3: 会计时点：2019.12.31 | D3: =CONCATENATE("日期：",TEXT(NOW(),"yyyy.mm.dd")) -> 日期：2026.05.03 | F3: 日期： | I3: 分页：
A4: 项目 | B4: 审定汇总 | C4: 合并权益抵销 | E4: 合并往来交易抵销 | G4: 合并报表调整 | I4: 合并审定数
C5: 借方 | D5: 贷方 | E5: 借方 | F5: 贷方 | G5: 借方 | H5: 贷方
A6: 流动资产：
A7: 货币资金 | B7: 0 | C7: 0 | D7: 0 | E7: 0 | F7: 0 | G7: 0 | H7: 0 | I7: =B7+E7+G7-F7-H7+C7-D7 -> 0
A8: 交易性金融资产 | B8: 0 | C8: 0 | D8: 0 | E8: 0 | F8: 0 | G8: 0 | H8: 0 | I8: =B8+E8+G8-F8-H8+C8-D8 -> 0
A9: 以公允价值计量且其变动计入当期损益的金融资产 | B9: 0 | C9: 0 | D9: 0 | E9: 0 | F9: 0 | G9: 0 | H9: 0 | I9: =B9+E9+G9-F9-H9+C9-D9 -> 0
A10: 衍生金融资产 | B10: 0 | C10: 0 | D10: 0 | E10: 0 | F10: 0 | G10: 0 | H10: 0 | I10: =B10+E10+G10-F10-H10+C10-D10 -> 0
A11: 应收票据 | B11: 0 | C11: 0 | D11: 0 | E11: 0 | F11: 0 | G11: 0 | H11: 0 | I11: =B11+E11+G11-F11-H11+C11-D11 -> 0
A12: 应收账款 | B12: 0 | C12: 0 | D12: 0 | E12: 0 | F12: 0 | G12: 0 | H12: 0 | I12: =B12+E12+G12-F12-H12+C12-D12 -> 0
A13: 应收款项融资 | B13: 0 | C13: 0 | D13: 0 | E13: 0 | F13: 0 | G13: 0 | H13: 0 | I13: =B13+E13+G13-F13-H13+C13-D13 -> 0
A14: 预付款项 | B14: 0 | C14: 0 | D14: 0 | E14: 0 | F14: 0 | G14: 0 | H14: 0 | I14: =B14+E14+G14-F14-H14+C14-D14 -> 0
A15: 其他应收款 | B15: 0 | C15: 0 | D15: 0 | E15: 0 | F15: 0 | G15: 0 | H15: 0 | I15: =B15+E15+G15-F15-H15+C15-D15 -> 0
A16: 其中：应收利息 | B16: 0 | C16: 0 | D16: 0 | E16: 0 | F16: 0 | G16: 0 | H16: 0 | I16: =B16+E16+G16-F16-H16+C16-D16 -> 0
A17: 应收股利 | B17: 0 | C17: 0 | D17: 0 | E17: 0 | F17: 0 | G17: 0 | H17: 0 | I17: =B17+E17+G17-F17-H17+C17-D17 -> 0
A18: 存货 | B18: 0 | C18: 0 | D18: 0 | E18: 0 | F18: 0 | G18: 0 | H18: 0 | I18: =B18+E18+G18-F18-H18+C18-D18 -> 0
... A22: 其他流动资产 | B22: 0 | C22: 0 | D22: 0 | E22: 0 | F22: 0 | G22: 0 | H22: 0 | I22: =B22+E22+G22-F22-H22+C22-D22 -> 0
A23: 0 | B23: 0 | C23: 0 | D23: 0 | E23: 0 | F23: 0 | G23: 0 | H23: 0 | I23: =B23+E23+G23-F23-H23+C23-D23 -> 0
A24: 0 | B24: 0 | C24: 0 | D24: 0 | E24: 0 | F24: 0 | G24: 0 | H24: 0 | I24: =B24+E24+G24-F24-H24+C24-D24 -> 0
A25: 流动资产合计 | B25: =SUM(B7:B24)-B16-B17 -> 0 | C25: =SUM(C7:C24)-C16-C17 -> 0 | D25: =SUM(D7:D24)-D16-D17 -> 0 | E25: =SUM(E7:E24)-E16-E17 -> 0 | F25: =SUM(F7:F24)-F16-F17 -> 0 | G25: =SUM(G7:G24)-G16-G17 -> 0 | H25: =SUM(H7:H24)-H16-H17 -> 0 | I25: =SUM(I7:I24)-I16-I17 -> 0
A26: 非流动资产:
A27: 债权投资 | B27: 0 | C27: 0 | D27: 0 | E27: 0 | F27: 0 | G27: 0 | H27: 0 | I27: =B27+E27+G27-F27-H27+C27-D27 -> 0
A28: 可供出售金融资产 | B28: 0 | C28: 0 | D28: 0 | E28: 0 | F28: 0 | G28: 0 | H28: 0 | I28: =B28+E28+G28-F28-H28+C28-D28 -> 0
A29: 其他债权投资 | B29: 0 | C29: 0 | D29: 0 | E29: 0 | F29: 0 | G29: 0 | H29: 0 | I29: =B29+E29+G29-F29-H29+C29-D29 -> 0
A30: 持有至到期投资 | B30: 0 | C30: 0 | D30: 0 | E30: 0 | F30: 0 | G30: 0 | H30: 0 | I30: =B30+E30+G30-F30-H30+C30-D30 -> 0
A31: 长期应收款 | B31: 0 | C31: 0 | D31: 0 | E31: 0 | F31: 0 | G31: 0 | H31: 0 | I31: =B31+E31+G31-F31-H31+C31-D31 -> 0
A32: 设定受益计划净资产 | B32: 0 | C32: 0 | D32: 0 | E32: 0 | F32: 0 | G32: 0 | H32: 0 | I32: =B32+E32+G32-F32-H32+C32-D32 -> 0
A33: 长期股权投资 | B33: 0 | C33: 0 | D33: 0 | E33: 0 | F33: 0 | G33: 0 | H33: 0 | I33: =B33+E33+G33-F33-H33+C33-D33 -> 0
A34: 其他权益工具投资 | B34: 0 | C34: 0 | D34: 0 | E34: 0 | F34: 0 | G34: 0 | H34: 0 | I34: =B34+E34+G34-F34-H34+C34-D34 -> 0
A35: 其他非流动金融资产 | B35: 0 | C35: 0 | D35: 0 | E35: 0 | F35: 0 | G35: 0 | H35: 0 | I35: =B35+E35+G35-F35-H35+C35-D35 -> 0
A36: 投资性房地产 | B36: 0 | C36: 0 | D36: 0 | E36: 0 | F36: 0 | G36: 0 | H36: 0 | I36: =B36+E36+G36-F36-H36+C36-D36 -> 0
A37: 固定资产 | B37: 0 | C37: 0 | D37: 0 | E37: 0 | F37: 0 | G37: 0 | H37: 0 | I37: =B37+E37+G37-F37-H37+C37-D37 -> 0
A38: 在建工程 | B38: 0 | C38: 0 | D38: 0 | E38: 0 | F38: 0 | G38: 0 | H38: 0 | I38: =B38+E38+G38-F38-H38+C38-D38 -> 0
... A47: 其他非流动资产 | B47: 0 | C47: 0 | D47: 0 | E47: 0 | F47: 0 | G47: 0 | H47: 0 | I47: =B47+E47+G47-F47-H47+C47-D47 -> 0
A48: 0 | B48: 0 | C48: 0 | D48: 0 | E48: 0 | F48: 0 | G48: 0 | H48: 0 | I48: =B48+E48+G48-F48-H48+C48-D48 -> 0
A49: 0 | B49: 0 | C49: 0 | D49: 0 | E49: 0 | F49: 0 | G49: 0 | H49: 0 | I49: =B49+E49+G49-F49-H49+C49-D49 -> 0
A50: 0 | B50: 0 | C50: 0 | D50: 0 | E50: 0 | F50: 0 | G50: 0 | H50: 0 | I50: =B50+E50+G50-F50-H50+C50-D50 -> 0
A51: 非流动资产合计 | B51: =SUM(B27:B50) -> 0 | C51: =SUM(C27:C50) -> 0 | D51: =SUM(D27:D50) -> 0 | E51: =SUM(E27:E50) -> 0 | F51: =SUM(F27:F50) -> 0 | G51: =SUM(G27:G50) -> 0 | H51: =SUM(H27:H50) -> 0 | I51: =SUM(I27:I50) -> 0
A52: 资 产 总 计 | B52: =SUM(B25,B51) -> 0 | C52: =SUM(C25,C51) -> 0 | D52: =SUM(D25,D51) -> 0 | E52: =SUM(E25,E51) -> 0 | F52: =SUM(F25,F51) -> 0 | G52: =SUM(G25,G51) -> 0 | H52: =SUM(H25,H51) -> 0 | I52: =SUM(I25,I51) -> 0
A53: 流动负债：
A54: 短期借款 | B54: 0 | C54: 0 | D54: 0 | E54: 0 | F54: 0 | G54: 0 | H54: 0 | I54: =B54-E54-G54+F54+H54-C54+D54 -> 0
A55: 交易性金融负债 | B55: 0 | C55: 0 | D55: 0 | E55: 0 | F55: 0 | G55: 0 | H55: 0 | I55: =B55-E55-G55+F55+H55-C55+D55 -> 0
A56: 以公允价值计量且其变动计入当期损益的金融负债 | B56: 0 | C56: 0 | D56: 0 | E56: 0 | F56: 0 | G56: 0 | H56: 0 | I56: =B56-E56-G56+F56+H56-C56+D56 -> 0
A57: 衍生金融负债 | B57: 0 | C57: 0 | D57: 0 | E57: 0 | F57: 0 | G57: 0 | H57: 0 | I57: =B57-E57-G57+F57+H57-C57+D57 -> 0
A58: 应付票据 | B58: 0 | C58: 0 | D58: 0 | E58: 0 | F58: 0 | G58: 0 | H58: 0 | I58: =B58-E58-G58+F58+H58-C58+D58 -> 0
A59: 应付账款 | B59: 0 | C59: 0 | D59: 0 | E59: 0 | F59: 0 | G59: 0 | H59: 0 | I59: =B59-E59-G59+F59+H59-C59+D59 -> 0
A60: 预收款项 | B60: 0 | C60: 0 | D60: 0 | E60: 0 | F60: 0 | G60: 0 | H60: 0 | I60: =B60-E60-G60+F60+H60-C60+D60 -> 0
A61: 合同负债 | B61: 0 | C61: 0 | D61: 0 | E61: 0 | F61: 0 | G61: 0 | H61: 0 | I61: =B61-E61-G61+F61+H61-C61+D61 -> 0
A62: 应付职工薪酬 | B62: 0 | C62: 0 | D62: 0 | E62: 0 | F62: 0 | G62: 0 | H62: 0 | I62: =B62-E62-G62+F62+H62-C62+D62 -> 0
A63: 应交税费 | B63: 0 | C63: 0 | D63: 0 | E63: 0 | F63: 0 | G63: 0 | H63: 0 | I63: =B63-E63-G63+F63+H63-C63+D63 -> 0
A64: 其他应付款 | B64: 0 | C64: 0 | D64: 0 | E64: 0 | F64: 0 | G64: 0 | H64: 0 | I64: =B64-E64-G64+F64+H64-C64+D64 -> 0
A65: 其中：应付利息 | B65: 0 | C65: 0 | D65: 0 | E65: 0 | F65: 0 | G65: 0 | H65: 0 | I65: =B65-E65-G65+F65+H65-C65+D65 -> 0
... A69: 其他流动负债 | B69: 0 | C69: 0 | D69: 0 | E69: 0 | F69: 0 | G69: 0 | H69: 0 | I69: =B69-E69-G69+F69+H69-C69+D69 -> 0
A70: 流动负债合计 | B70: =SUM(B54:B69)-B65-B66 -> 0 | C70: =SUM(C54:C69)-C65-C66 -> 0 | D70: =SUM(D54:D69)-D65-D66 -> 0 | E70: =SUM(E54:E69)-E65-E66 -> 0 | F70: =SUM(F54:F69)-F65-F66 -> 0 | G70: =SUM(G54:G69)-G65-G66 -> 0 | H70: =SUM(H54:H69)-H65-H66 -> 0 | I70: =SUM(I54:I69)-I65-I66 -> 0
A71: 非流动负债:
A72: 长期借款 | B72: 0 | C72: 0 | D72: 0 | E72: 0 | F72: 0 | G72: 0 | H72: 0 | I72: =B72-E72-G72+F72+H72-C72+D72 -> 0
A73: 应付债券 | B73: 0 | C73: 0 | D73: 0 | E73: 0 | F73: 0 | G73: 0 | H73: 0 | I73: =B73-E73-G73+F73+H73-C73+D73 -> 0
A74: 其中：优先股 | B74: 0 | C74: 0 | D74: 0 | E74: 0 | F74: 0 | G74: 0 | H74: 0 | I74: =B74-E74-G74+F74+H74-C74+D74 -> 0
A75: 永续债 | B75: 0 | C75: 0 | D75: 0 | E75: 0 | F75: 0 | G75: 0 | H75: 0 | I75: =B75-E75-G75+F75+H75-C75+D75 -> 0
A76: 租赁负债 | B76: 0 | C76: 0 | D76: 0 | E76: 0 | F76: 0 | G76: 0 | H76: 0 | I76: =B76-E76-G76+F76+H76-C76+D76 -> 0
A77: 长期应付款 | B77: 0 | C77: 0 | D77: 0 | E77: 0 | F77: 0 | G77: 0 | H77: 0 | I77: =B77-E77-G77+F77+H77-C77+D77 -> 0
A78: 长期应付职工薪酬 | B78: 0 | C78: 0 | D78: 0 | E78: 0 | F78: 0 | G78: 0 | H78: 0 | I78: =B78-E78-G78+F78+H78-C78+D78 -> 0
A79: 预计负债 | B79: 0 | C79: 0 | D79: 0 | E79: 0 | F79: 0 | G79: 0 | H79: 0 | I79: =B79-E79-G79+F79+H79-C79+D79 -> 0
A80: 递延收益 | B80: 0 | C80: 0 | D80: 0 | E80: 0 | F80: 0 | G80: 0 | H80: 0 | I80: =B80-E80-G80+F80+H80-C80+D80 -> 0
A81: 递延所得税负债 | B81: 0 | C81: 0 | D81: 0 | E81: 0 | F81: 0 | G81: 0 | H81: 0 | I81: =B81-E81-G81+F81+H81-C81+D81 -> 0
A82: 其他非流动负债 | B82: 0 | C82: 0 | D82: 0 | E82: 0 | F82: 0 | G82: 0 | H82: 0 | I82: =B82-E82-G82+F82+H82-C82+D82 -> 0
A83: 非流动负债合计 | B83: =SUM(B72:B82)-B74-B75 -> 0 | C83: =SUM(C72:C82)-C74-C75 -> 0 | D83: =SUM(D72:D82)-D74-D75 -> 0 | E83: =SUM(E72:E82)-E74-E75 -> 0 | F83: =SUM(F72:F82)-F74-F75 -> 0 | G83: =SUM(G72:G82)-G74-G75 -> 0 | H83: =SUM(H72:H82)-H74-H75 -> 0 | I83: =SUM(I72:I82)-I74-I75 -> 0
A84: 负 债 合 计 | B84: =SUM(B70,B83) -> 0 | C84: =SUM(C70,C83) -> 0 | D84: =SUM(D70,D83) -> 0 | E84: =SUM(E70,E83) -> 0 | F84: =SUM(F70,F83) -> 0 | G84: =SUM(G70,G83) -> 0 | H84: =SUM(H70,H83) -> 0 | I84: =SUM(I70,I83) -> 0
A85: 股东权益：
A86: 股本 | B86: 0 | C86: 0 | D86: 0 | E86: 0 | F86: 0 | G86: 0 | H86: 0 | I86: =B86-E86-G86+F86+H86-C86+D86 -> 0
A87: 其他权益工具 | B87: 0 | C87: 0 | D87: 0 | E87: 0 | F87: 0 | G87: 0 | H87: 0 | I87: =B87-E87-G87+F87+H87-C87+D87 -> 0
A88: 其中：优先股 | B88: 0 | C88: 0 | D88: 0 | E88: 0 | F88: 0 | G88: 0 | H88: 0 | I88: =B88-E88-G88+F88+H88-C88+D88 -> 0
A89: 永续债 | B89: 0 | C89: 0 | D89: 0 | E89: 0 | F89: 0 | G89: 0 | H89: 0 | I89: =B89-E89-G89+F89+H89-C89+D89 -> 0
A90: 资本公积 | B90: 0 | C90: 0 | D90: 0 | E90: 0 | F90: 0 | G90: 0 | H90: 0 | I90: =B90-E90-G90+F90+H90-C90+D90 -> 0
A91: 减：库存股 | B91: 0 | C91: 0 | D91: 0 | E91: 0 | F91: 0 | G91: 0 | H91: 0 | I91: =B91-E91-G91+F91+H91-C91+D91 -> 0
A92: 其他综合收益 | B92: 0 | C92: 0 | D92: 0 | E92: 0 | F92: 0 | G92: 0 | H92: 0 | I92: =B92-E92-G92+F92+H92-C92+D92 -> 0
A93: 专项储备 | B93: 0 | C93: 0 | D93: 0 | E93: 0 | F93: 0 | G93: 0 | H93: 0 | I93: =B93-E93-G93+F93+H93-C93+D93 -> 0
A94: 盈余公积 | B94: 0 | C94: 0 | D94: 0 | E94: 0 | F94: 0 | G94: 0 | H94: 0 | I94: =B94-E94-G94+F94+H94-C94+D94 -> 0
A95: 未分配利润 | B95: 0 | C95: =合并TB损益!C126 -> 0 | D95: =合并TB损益!D126 -> 0 | E95: =合并TB损益!E126 -> 0 | F95: =合并TB损益!F126 -> 0 | G95: =合并TB损益!G126 -> 0 | H95: =合并TB损益!H126 -> 0 | I95: =合并TB损益!I126 -> 0
A96: 归属于母公司股东权益合计 | B96: =SUM(B86:B87,B90,-B91,B92:B95) -> 0 | C96: =SUM(C86:C87,C90,-C91,C92:C95) -> 0 | D96: =SUM(D86:D87,D90,-D91,D92:D95) -> 0 | E96: =SUM(E86:E87,E90,-E91,E92:E95) -> 0 | F96: =SUM(F86:F87,F90,-F91,F92:F95) -> 0 | G96: =SUM(G86:G87,G90,-G91,G92:G95) -> 0 | H96: =SUM(H86:H87,H90,-H91,H92:H95) -> 0 | I96: =SUM(I86:I87,I90,-I91,I92:I95) -> 0
A97: 少数股东权益 | B97: 0 | C97: 0 | D97: 0 | E97: 0 | F97: 0 | G97: 0 | H97: 0 | I97: =B97-E97-G97+F97+H97-C97+D97 -> 0
A98: 股东权益合计 | B98: =SUM(B96:B97) -> 0 | C98: =SUM(C96:C97) -> 0 | D98: =SUM(D96:D97) -> 0 | E98: =SUM(E96:E97) -> 0 | F98: =SUM(F96:F97) -> 0 | G98: =SUM(G96:G97) -> 0 | H98: =SUM(H96:H97) -> 0 | I98: =SUM(I96:I97) -> 0
A99: 负债和股东权益合计 | B99: =SUM(B84,B98) -> 0 | C99: =SUM(C84,C98) -> 0 | D99: =SUM(D84,D98) -> 0 | E99: =SUM(E84,E98) -> 0 | F99: =SUM(F84,F98) -> 0 | G99: =SUM(G84,G98) -> 0 | H99: =SUM(H84,H98) -> 0 | I99: =SUM(I84,I98) -> 0

Sheet 合并TB损益
A1: 合并利润及利润分配表试算平衡
A2: 客户名称： | D2: 编制： | G2: 复核：
A3: 会计期间：2019年度 | D3: =CONCATENATE("日期：",TEXT(NOW(),"yyyy.mm.dd")) -> 日期：2026.05.03 | G3: =合并TB资产负债!F3 -> 日期：
A4: 项目 | B4: 审定汇总 | C4: 合并权益抵销 | E4: 合并往来交易抵销 | G4: 合并报表调整 | I4: 合并审定数
C5: 借方 | D5: 贷方 | E5: 借方 | F5: 贷方 | G5: 借方 | H5: 贷方
A6: 一、营业收入 | B6: 0 | C6: 0 | D6: 0 | E6: 0 | F6: 0 | G6: 0 | H6: 0 | I6: =B6-E6-G6+F6+H6-C6+D6 -> 0
A7: 其中：主营业务收入 | B7: 0 | C7: 0 | D7: 0 | E7: 0 | F7: 0 | G7: 0 | H7: 0 | I7: =B7-E7-G7+F7+H7-C7+D7 -> 0
A8: 其他业务收入 | B8: 0 | C8: 0 | D8: 0 | E8: 0 | F8: 0 | G8: 0 | H8: 0 | I8: =B8-E8-G8+F8+H8-C8+D8 -> 0
A9: 减：营业成本 | B9: 0 | C9: 0 | D9: 0 | E9: 0 | F9: 0 | G9: 0 | H9: 0 | I9: =B9+E9+G9-F9-H9+C9-D9 -> 0
A10: 其中：主营业务成本 | B10: 0 | C10: 0 | D10: 0 | E10: 0 | F10: 0 | G10: 0 | H10: 0 | I10: =B10+E10+G10-F10-H10+C10-D10 -> 0
A11: 其他业务成本 | B11: 0 | C11: 0 | D11: 0 | E11: 0 | F11: 0 | G11: 0 | H11: 0 | I11: =B11+E11+G11-F11-H11+C11-D11 -> 0
A12: 税金及附加 | B12: 0 | C12: 0 | D12: 0 | E12: 0 | F12: 0 | G12: 0 | H12: 0 | I12: =B12+E12+G12-F12-H12+C12-D12 -> 0
A13: 销售费用 | B13: 0 | C13: 0 | D13: 0 | E13: 0 | F13: 0 | G13: 0 | H13: 0 | I13: =B13+E13+G13-F13-H13+C13-D13 -> 0
A14: 管理费用 | B14: 0 | C14: 0 | D14: 0 | E14: 0 | F14: 0 | G14: 0 | H14: 0 | I14: =B14+E14+G14-F14-H14+C14-D14 -> 0
A15: 研发费用 | B15: 0 | C15: 0 | D15: 0 | E15: 0 | F15: 0 | G15: 0 | H15: 0 | I15: =B15+E15+G15-F15-H15+C15-D15 -> 0
A16: 财务费用 | B16: 0 | C16: 0 | D16: 0 | E16: 0 | F16: 0 | G16: 0 | H16: 0 | I16: =B16+E16+G16-F16-H16+C16-D16 -> 0
A17: 其中：利息费用 | B17: 0 | C17: 0 | D17: 0 | E17: 0 | F17: 0 | G17: 0 | H17: 0 | I17: =B17+E17+G17-F17-H17+C17-D17 -> 0
A18: 利息收入 | B18: 0 | C18: 0 | D18: 0 | E18: 0 | F18: 0 | G18: 0 | H18: 0 | I18: =B18+E18+G18-F18-H18+C18-D18 -> 0
A19: 加：其他收益 | B19: 0 | C19: 0 | D19: 0 | E19: 0 | F19: 0 | G19: 0 | H19: 0 | I19: =B19-E19-G19+F19+H19-C19+D19 -> 0
A20: 投资收益（损失以“－”号填列） | B20: 0 | C20: 0 | D20: 0 | E20: 0 | F20: 0 | G20: 0 | H20: 0 | I20: =B20-E20-G20+F20+H20-C20+D20 -> 0
A21: 其中：对联营企业和合营企业的投资收益 | B21: 0 | C21: 0 | D21: 0 | E21: 0 | F21: 0 | G21: 0 | H21: 0 | I21: =B21-E21-G21+F21+H21-C21+D21 -> 0
A22: 以摊余成本计量的金融资产终止确认收益（损失以“-”号填列） | B22: 0 | C22: 0 | D22: 0 | E22: 0 | F22: 0 | G22: 0 | H22: 0 | I22: =B22-E22-G22+F22+H22-C22+D22 -> 0
A23: 净敞口套期收益（损失以“-”号填列） | B23: 0 | C23: 0 | D23: 0 | E23: 0 | F23: 0 | G23: 0 | H23: 0 | I23: =B23-E23-G23+F23+H23-C23+D23 -> 0
A24: 公允价值变动收益（损失以“－”号填列） | B24: 0 | C24: 0 | D24: 0 | E24: 0 | F24: 0 | G24: 0 | H24: 0 | I24: =B24-E24-G24+F24+H24-C24+D24 -> 0
A25: 信用减值损失(损失以“-”号填列） | B25: 0 | C25: 0 | D25: 0 | E25: 0 | F25: 0 | G25: 0 | H25: 0 | I25: =B25-E25-G25+F25+H25-C25+D25 -> 0
A26: 资产减值损失(损失以“-”号填列） | B26: 0 | C26: 0 | D26: 0 | E26: 0 | F26: 0 | G26: 0 | H26: 0 | I26: =B26-E26-G26+F26+H26-C26+D26 -> 0
A27: 资产处置收益(损失以“-”号填列） | B27: 0 | C27: 0 | D27: 0 | E27: 0 | F27: 0 | G27: 0 | H27: 0 | I27: =B27-E27-G27+F27+H27-C27+D27 -> 0
A28: 二、营业利润（亏损以“－”号填列） | B28: =SUM(B6)-SUM(B9,B12:B16)+SUM(B19:B20)+SUM(B23:B27) -> 0 | C28: =SUM(C6)-SUM(C9,C12:C16)+SUM(C19:C20)+SUM(C23:C27) -> 0 | D28: =SUM(D6)-SUM(D9,D12:D16)+SUM(D19:D20)+SUM(D23:D27) -> 0 | E28: =SUM(E6)-SUM(E9,E12:E16)+SUM(E19:E20)+SUM(E23:E27) -> 0 | F28: =SUM(F6)-SUM(F9,F12:F16)+SUM(F19:F20)+SUM(F23:F27) -> 0 | G28: =SUM(G6)-SUM(G9,G12:G16)+SUM(G19:G20)+SUM(G23:G27) -> 0 | H28: =SUM(H6)-SUM(H9,H12:H16)+SUM(H19:H20)+SUM(H23:H27) -> 0 | I28: =SUM(I6)-SUM(I9,I12:I16)+SUM(I19:I20)+SUM(I23:I27) -> 0
A29: 加：营业外收入 | B29: 0 | C29: 0 | D29: 0 | E29: 0 | F29: 0 | G29: 0 | H29: 0 | I29: =B29-E29-G29+F29+H29-C29+D29 -> 0
A30: 减：营业外支出 | B30: 0 | C30: 0 | D30: 0 | E30: 0 | F30: 0 | G30: 0 | H30: 0 | I30: =B30+E30+G30-F30-H30+C30-D30 -> 0
A31: 三、利润总额（亏损总额以“－”号填列） | B31: =SUM(B28)+SUM(B29)-SUM(B30) -> 0 | C31: =SUM(C28)+SUM(C29)-SUM(C30) -> 0 | D31: =SUM(D28)+SUM(D29)-SUM(D30) -> 0 | E31: =SUM(E28)+SUM(E29)-SUM(E30) -> 0 | F31: =SUM(F28)+SUM(F29)-SUM(F30) -> 0 | G31: =SUM(G28)+SUM(G29)-SUM(G30) -> 0 | H31: =SUM(H28)+SUM(H29)-SUM(H30) -> 0 | I31: =SUM(I28)+SUM(I29)-SUM(I30) -> 0
A32: 减：所得税费用 | B32: 0 | C32: 0 | D32: 0 | E32: 0 | F32: 0 | G32: 0 | H32: 0 | I32: =B32+E32+G32-F32-H32+C32-D32 -> 0
A33: 0 | B33: 0 | C33: 0 | D33: 0 | E33: 0 | F33: 0 | G33: 0 | H33: 0 | I33: =B33+E33+G33-F33-H33+C33-D33 -> 0
A34: 四、净利润（净亏损以“－”号填列） | B34: =B31-B32-B33 -> 0 | C34: =C31-C32-C33 -> 0 | D34: =D31-D32-D33 -> 0 | E34: =E31-E32-E33 -> 0 | F34: =F31-F32-F33 -> 0 | G34: =G31-G32-G33 -> 0 | H34: =H31-H32-H33 -> 0 | I34: =I31-I32-I33 -> 0
A35: （一）按经营持续性分类
A36: 其中：持续经营净利润（净亏损以“-”号填列） | B36: 0 | I36: =B36-E36-G36+F36+H36-C36+D36 -> 0
A37: 终止经营净利润（净亏损以“-”号填列） | B37: 0 | I37: =B37-E37-G37+F37+H37-C37+D37 -> 0
A38: （二）按所有权归属分类
A39: 其中：归属于母公司股东的净利润（净亏损以“-”号填列） | B39: 0 | C39: =C34-C40 -> 0 | D39: =D34-D40 -> 0 | E39: =E34-E40 -> 0 | F39: =F34-F40 -> 0 | G39: =G34-G40 -> 0 | H39: =H34-H40 -> 0 | I39: =I34-I40 -> 0
A40: 少数股东损益（净亏损以“-”号填列） | B40: 0 | C40: 0 | D40: 0 | E40: 0 | F40: 0 | G40: 0 | H40: 0 | I40: =B40+E40+G40-F40-H40+C40-D40 -> 0
A41: 五、其他综合收益的税后净额 | B41: 0 | C41: =C42+C61 -> 0 | D41: =D42+D61 -> 0 | E41: =E42+E61 -> 0 | F41: =F42+F61 -> 0 | G41: =G42+G61 -> 0 | H41: =H42+H61 -> 0 | I41: =B41-E41-G41+F41+H41-C41+D41 -> 0
A42: 归属于母公司股东的其他综合收益的税后净额 | B42: =B35+B41 -> 0 | C42: =C43+C49 -> 0 | D42: =D43+D49 -> 0 | E42: =E43+E49 -> 0 | F42: =F43+F49 -> 0 | G42: =G43+G49 -> 0 | H42: =H43+H49 -> 0 | I42: =B42-E42-G42+F42+H42-C42+D42 -> 0
A43: （一）不能重分类进损益的其他综合收益 | B43: 0 | C43: =SUM(C44:C48) -> 0 | D43: =SUM(D44:D48) -> 0 | E43: =SUM(E44:E48) -> 0 | F43: =SUM(F44:F48) -> 0 | G43: =SUM(G44:G48) -> 0 | H43: =SUM(H44:H48) -> 0 | I43: =B43-E43-G43+F43+H43-C43+D43 -> 0
A44: 1.重新计量设定受益计划变动额 | B44: 0 | C44: 0 | D44: 0 | E44: 0 | F44: 0 | G44: 0 | H44: 0 | I44: =B44-E44-G44+F44+H44-C44+D44 -> 0
A45: 2.权益法下不能转损益的其他综合收益 | B45: 0 | C45: 0 | D45: 0 | E45: 0 | F45: 0 | G45: 0 | H45: 0 | I45: =B45-E45-G45+F45+H45-C45+D45 -> 0
A46: 3.其他权益工具投资公允价值变动 | B46: 0 | C46: 0 | D46: 0 | E46: 0 | F46: 0 | G46: 0 | H46: 0 | I46: =B46-E46-G46+F46+H46-C46+D46 -> 0
A47: 4.企业自身信用风险公允价值变动 | B47: 0 | C47: 0 | D47: 0 | E47: 0 | F47: 0 | G47: 0 | H47: 0 | I47: =B47-E47-G47+F47+H47-C47+D47 -> 0
A48: 5.其他 | B48: 0 | C48: 0 | D48: 0 | E48: 0 | F48: 0 | G48: 0 | H48: 0 | I48: =B48-E48-G48+F48+H48-C48+D48 -> 0
A49: （二）将重分类进损益的其他综合收益 | B49: 0 | C49: =SUM(C50:C60) -> 0 | D49: =SUM(D50:D60) -> 0 | E49: =SUM(E50:E60) -> 0 | F49: =SUM(F50:F60) -> 0 | G49: =SUM(G50:G60) -> 0 | H49: =SUM(H50:H60) -> 0 | I49: =B49-E49-G49+F49+H49-C49+D49 -> 0
A50: 1.权益法下可转损益的其他综合收益 | B50: 0 | C50: 0 | D50: 0 | E50: 0 | F50: 0 | G50: 0 | H50: 0 | I50: =B50-E50-G50+F50+H50-C50+D50 -> 0
A51: 2.其他债权投资公允价值变动 | B51: 0 | C51: 0 | D51: 0 | E51: 0 | F51: 0 | G51: 0 | H51: 0 | I51: =B51-E51-G51+F51+H51-C51+D51 -> 0
A52: 3.可供出售金融资产公允价值变动损益 | B52: 0 | C52: 0 | D52: 0 | E52: 0 | F52: 0 | G52: 0 | H52: 0 | I52: =B52-E52-G52+F52+H52-C52+D52 -> 0
A53: 4.金融资产重分类计入其他综合收益的金额 | B53: 0 | C53: 0 | D53: 0 | E53: 0 | F53: 0 | G53: 0 | H53: 0 | I53: =B53-E53-G53+F53+H53-C53+D53 -> 0
A54: 5.持有至到期投资重分类为可供出售金融资产损益 | B54: 0 | C54: 0 | D54: 0 | E54: 0 | F54: 0 | G54: 0 | H54: 0 | I54: =B54-E54-G54+F54+H54-C54+D54 -> 0
A55: 6.其他债权投资信用减值准备 | B55: 0 | C55: 0 | D55: 0 | E55: 0 | F55: 0 | G55: 0 | H55: 0 | I55: =B55-E55-G55+F55+H55-C55+D55 -> 0
A56: 7.现金流量套期储备 | B56: 0 | C56: 0 | D56: 0 | E56: 0 | F56: 0 | G56: 0 | H56: 0 | I56: =B56-E56-G56+F56+H56-C56+D56 -> 0
A57: 8.外币财务报表折算差额 | B57: 0 | C57: 0 | D57: 0 | E57: 0 | F57: 0 | G57: 0 | H57: 0 | I57: =B57-E57-G57+F57+H57-C57+D57 -> 0
A58: 9.自用房地产或作为存货的房地产转换为以公允价值计量的投资性房地产在转换日公允价值大于账面价值部分 | B58: 0 | C58: 0 | D58: 0 | E58: 0 | F58: 0 | G58: 0 | H58: 0 | I58: =B58-E58-G58+F58+H58-C58+D58 -> 0
A59: 10.多次交易分步处置子公司股权构成一揽子交易的，丧失控制权之前各次交易处置价款与对应净资产账面价值份额的差额 | B59: 0 | C59: 0 | D59: 0 | E59: 0 | F59: 0 | G59: 0 | H59: 0 | I59: =B59-E59-G59+F59+H59-C59+D59 -> 0
A60: 11.其他 | B60: 0 | C60: 0 | D60: 0 | E60: 0 | F60: 0 | G60: 0 | H60: 0 | I60: =B60-E60-G60+F60+H60-C60+D60 -> 0
A61: 归属于少数股东的其他综合收益的税后净额 | B61: 0 | C61: 0 | D61: 0 | E61: 0 | F61: 0 | G61: 0 | H61: 0 | I61: =B61-E61-G61+F61+H61-C61+D61 -> 0
A62: 六、综合收益总额 | B62: 0 | C62: =C34+C41 -> 0 | D62: =D34+D41 -> 0 | E62: =E34+E41 -> 0 | F62: =F34+F41 -> 0 | G62: =G34+G41 -> 0 | H62: =H34+H41 -> 0 | I62: =B62-E62-G62+F62+H62-C62+D62 -> 0
A63: 归属于母公司股东的综合收益总额 | B63: 0 | C63: =C39+C42 -> 0 | D63: =D39+D42 -> 0 | E63: =E39+E42 -> 0 | F63: =F39+F42 -> 0 | G63: =G39+G42 -> 0 | H63: =H39+H42 -> 0 | I63: =B63-E63-G63+F63+H63-C63+D63 -> 0
A64: 归属于少数股东的综合收益总额 | B64: 0 | C64: =C40+C61 -> 0 | D64: =D40+D61 -> 0 | E64: =E40+E61 -> 0 | F64: =F40+F61 -> 0 | G64: =G40+G61 -> 0 | H64: =H40+H61 -> 0 | I64: =B64-E64-G64+F64+H64-C64+D64 -> 0
A65: 七、每股收益
A66: （一）基本每股收益 | B66: 0 | C66: 0 | D66: 0 | E66: 0 | F66: 0 | G66: 0 | H66: 0 | I66: =B66-E66-G66+F66+H66-C66+D66 -> 0
A67: （二）稀释每股收益 | B67: 0 | C67: 0 | D67: 0 | E67: 0 | F67: 0 | G67: 0 | H67: 0 | I67: =B67-E67-G67+F67+H67-C67+D67 -> 0
A68: 八、利润分配 | B68: 0
A69: （一）年初未分配利润 | B69: 0 | C69: 0 | D69: 0 | E69: 0 | F69: 0 | G69: 0 | H69: 0 | I69: =B69-E69-G69+F69+H69-C69+D69 -> 0
A70: （二）可供分配的利润 | B70: 0 | C70: 0 | D70: 0 | E70: 0 | F70: 0 | G70: 0 | H70: 0 | I70: =I39+I69 -> 0
A71: 1、提取法定盈余公积 | B71: 0 | C71: 0 | D71: 0 | E71: 0 | F71: 0 | G71: 0 | H71: 0 | I71: =B71-E71-G71+F71+H71-C71+D71 -> 0
A72: 2、其他 | B72: 0 | C72: 0 | D72: 0 | E72: 0 | F72: 0 | G72: 0 | H72: 0 | I72: =B72-E72-G72+F72+H72-C72+D72 -> 0
A73: （三）可供投资者分配的利润 | B73: 0 | C73: =C70-C71-C72 -> 0 | D73: =D70-D71-D72 -> 0 | E73: =E70-E71-E72 -> 0 | F73: =F70-F71-F72 -> 0 | G73: =G70-G71-G72 -> 0 | H73: =H70-H71-H72 -> 0 | I73: =I70-I71-I72 -> 0
A74: 1、应付优先股股利 | B74: 0 | C74: 0 | D74: 0 | E74: 0 | F74: 0 | G74: 0 | H74: 0 | I74: =B74-E74-G74+F74+H74-C74+D74 -> 0
A75: 2、提取任意盈余公积 | B75: 0 | C75: 0 | D75: 0 | E75: 0 | F75: 0 | G75: 0 | H75: 0 | I75: =B75-E75-G75+F75+H75-C75+D75 -> 0
A76: 3、应付普通股股利（应付利润） | B76: 0 | C76: 0 | D76: 0 | E76: 0 | F76: 0 | G76: 0 | H76: 0 | I76: =B76-E76-G76+F76+H76-C76+D76 -> 0
A77: 4、转作资本（或股本）的普通股股利 | B77: 0 | C77: 0 | D77: 0 | E77: 0 | F77: 0 | G77: 0 | H77: 0 | I77: =B77-E77-G77+F77+H77-C77+D77 -> 0
A78: 5、其他 | B78: 0 | C78: 0 | D78: 0 | E78: 0 | F78: 0 | G78: 0 | H78: 0 | I78: =B78-E78-G78+F78+H78-C78+D78 -> 0
A79: 九、未分配利润 | B79: 0 | C79: =C73-SUM(C74:C78) -> 0 | D79: =D73-SUM(D74:D78) -> 0 | E79: =E73-SUM(E74:E78) -> 0 | F79: =F73-SUM(F74:F78) -> 0 | G79: =G73-SUM(G74:G78) -> 0 | H79: =H73-SUM(H74:H78) -> 0 | I79: =I73-SUM(I74:I78) -> 0
B80: =#REF! -> #REF! | C80: =SUM(C6,C9,C12:C16,C19:C20,C23:C27,C29:C30,C32:C33,C40,C44:C48,C50:C61,C66:C67,C69,C71:C72,C74:C78) -> 0 | D80: =SUM(D6,D9,D12:D16,D19:D20,D23:D27,D29:D30,D32:D33,D40,D44:D48,D50:D61,D66:D67,D69,D71:D72,D74:D78) -> 0 | E80: =SUM(E6,E9,E12:E16,E19:E20,E23:E27,E29:E30,E32:E33,E40,E44:E48,E50:E61,E66:E67,E69,E71:E72,E74:E78) -> 0 | F80: =SUM(F6,F9,F12:F16,F19:F20,F23:F27,F29:F30,F32:F33,F40,F44:F48,F50:F61,F66:F67,F69,F71:F72,F74:F78) -> 0 | G80: =SUM(G6,G9,G12:G16,G19:G20,G23:G27,G29:G30,G32:G33,G40,G44:G48,G50:G61,G66:G67,G69,G71:G72,G74:G78) -> 0 | H80: =SUM(H6,H9,H12:H16,H19:H20,H23:H27,H29:H30,H32:H33,H40,H44:H48,H50:H61,H66:H67,H69,H71:H72,H74:H78) -> 0 | I80: =SUM(I6,I9,I12:I16,I19:I20,I23:I27,I29:I30,I32:I33,I40,I44:I48,I50:I61,I66:I67,I69,I71:I72,I74:I78) -> 0
B81: =B80-B79 -> #REF!

Sheet TB合并CF
A1: 合并现金流量表试算平衡
A2: 客户名称： | B2: 编制： | D2: 复核： | E2: 索引：
A3: 会计时点：2019.12.31 | B3: =CONCATENATE("日期：",TEXT(NOW(),"yyyy.mm.dd")) -> 日期：2026.05.03 | D3: 日期： | E3: 分页：
A4: 项目 | B4: 审定汇总 | C4: 汇总抵销 | D4: 报表调整 | E4: 合并审定数
A6: 一、经营活动产生的现金流量
A7: 销售商品、提供劳务收到的现金
A8: 收到的税费返还
A9: 收到的其他与经营活动有关的现金
A10: 经营活动现金流入小计
A11: 购买商品、接受劳务支付的现金
A12: 支付给职工以及为职工支付的现金
A13: 支付各项税费
A14: 支付的其他与经营活动有关的现金
A15: 经营活动现金流出小计
A16: 经营活动产生的现金流量净额
A17: 二、投资活动产生的现金流量
... A34: 收到的其他与筹资活动有关的现金
A35: 0
A36: 筹资活动现金流入小计
A37: 偿还债务支付的现金
A38: 分配股利、利润或偿付利息支付的现金
A39: 其中:子公司支付少数股东的现金股利
A40: 支付其他与筹资活动有关的现金
A41: 其中:子公司减资支付给少数股东的现金
A42: 筹资活动现金流出小计
A43: 筹资活动产生的现金流量净额
A45: 四、汇率变动对现金及现金等价物的影响
A46: 五、现金及现金等价物净增加额
A47: 加：期初现金及现金等价物余额
A48: 六、期末现金及现金等价物余额
... A52: 1、将净利润调节为经营活动现金流量：
A53: 净利润 | B53: 0 | E53: =SUM(B53:D53) -> 0
A54: 加：资产减值损失 | B54: 0 | E54: =SUM(B54:D54) -> 0
A55: 信用减值损失 | B55: 0 | E55: =SUM(B55:D55) -> 0
A56: 固定资产折旧、油气资产折耗、生产性生物资产折旧 | B56: 0 | E56: =SUM(B56:D56) -> 0
A57: 无形资产摊销 | B57: 0 | E57: =SUM(B57:D57) -> 0
A58: 长期待摊费用摊销 | B58: 0 | E58: =SUM(B58:D58) -> 0
A59: 处置固定资产、无形资产和其他长期资产的损失（收益以“－”号填列） | B59: 0 | E59: =SUM(B59:D59) -> 0
A60: 固定资产报废损失（收益以“－”号填列） | B60: 0 | E60: =SUM(B60:D60) -> 0
A61: 公允价值变动损失（收益以“－”号填列） | B61: 0 | E61: =SUM(B61:D61) -> 0
A62: 财务费用（收益以“－”号填列） | B62: 0 | E62: =SUM(B62:D62) -> 0
A63: 投资损失（收益以“－”号填列） | B63: 0 | E63: =SUM(B63:D63) -> 0
A64: 递延所得税资产减少（增加以“－”号填列） | B64: 0 | E64: =SUM(B64:D64) -> 0
... A68: 经营性应付项目的增加（减少以“－”号填列） | B68: 0 | E68: =SUM(B68:D68) -> 0
A69: 经营活动产生的现金流量净额 | B69: =SUM(B53:B68) -> 0 | C69: =SUM(C53:C68) -> 0 | D69: =SUM(D53:D68) -> 0 | E69: =SUM(E53:E68) -> 0
A71: 2、不涉及现金收支的投资和筹资活动：
A72: 债务转为资本 | B72: 0 | E72: =SUM(B72:D72) -> 0
A73: 一年内到期的可转换公司债券 | B73: 0 | E73: =SUM(B73:D73) -> 0
A74: 融资租入固定资产 | B74: 0 | E74: =SUM(B74:D74) -> 0
A75: 其他 | B75: 0 | E75: =SUM(B75:D75) -> 0
A76: 0 | B76: 0 | E76: =SUM(B76:D76) -> 0
A77: 3、现金及现金等价物净变动情况：
A78: 现金的期末余额 | B78: 0 | E78: =SUM(B78:D78) -> 0
A79: 减：现金的期初余额 | B79: 0 | E79: =SUM(B79:D79) -> 0
A80: 加：现金等价物的期末余额 | B80: 0 | E80: =SUM(B80:D80) -> 0
A81: 减：现金等价物的期初余额 | B81: 0 | E81: =SUM(B81:D81) -> 0
A82: 现金及现金等价物净增加额 | B82: =B78-B79+B80-B81 -> 0 | C82: =C78-C79+C80-C81 -> 0 | D82: =D78-D79+D80-D81 -> 0 | E82: =E78-E79+E80-E81 -> 0
