Workbook

Sheet 底稿目录
A1: 底稿开列时，可先在以下单元格填写有关内容，以便其他底稿引用有关数据：
A2: 被审计单位：
A3: 截止日：202X年12月31日 | D3: 序号 | E3: 内容 | F3: 索引号
A4: 编制人： | E4: 长期股权投资实质性程序表 | F4: G7A
A5: 编制日期： | D5: 1 | E5: 长期股权投资审定表 | F5: G7-1
A6: 复核人： | D6: 2 | E6: 附注披露信息（上市公司） | G6: 无需打印
A7: 复核日期： | D7: 3 | E7: 附注披露信息（国企） | G7: 无需打印
D8: 4 | E8: 明细表 | F8: G7-2
A9: 关于工作底稿与审计程序索引号对应的说明 | D9: 5 | E9: 调整分录汇总 | F9: G7-3
A10: 1.编制的审计工作底稿应与审计程序对应。审计项目组应根据被审计单位实际情况和风险评估情况在实质性程序表中裁剪、修改或增加审计程序，根据实际执行的审计程序完成相应审计工作底稿，编制的工作底稿中应按自然顺序依次编制索引号，并通过唯一的索引号将与实质性程序表中的程序对应关联（即将工作底稿的索引号填入实质性程序表中的底稿索引号列）。 | D10: 6 | E10: 被投资单位基本信息 | F10: G7-4
D11: 7 | E11: 被投资单位财务信息（合营、联营） | F11: G7-5
D12: 8 | E12: 被投资公司会计政策 | F12: G7-6
D13: 9 | E13: 长期股权投资初始判断 | F13: G7-7
A14: 2.获取的支持性证据应与审计底稿或程序对应。审计项目组在完成底稿时获取的支持性证据应根据底稿索引号编制下一级按自然顺序排序的索引号（如D1-2-1、D1-2-2、……），并在底稿中说明引用的支持性证据、关联索引号。 | D14: 10 | E14: 子公司初始计量测试（同控） | F14: G7-8
D15: 11 | E15: 子公司初始计量测试（非同控） | F15: G7-9
D16: 12 | E16: 子公司后续计量测试表 | F16: G7-10
A17: 3.工作底稿索引号的编码规则：实质性程序索引号按循环从“D”到“N”,循环内账户以顺序号排列，模板中底稿索引号按账户顺序+自然数顺序（即模板中索引号按二级自然顺序排列，如D1-1、D1-2、D1-3、……D1-N）。 | D17: 13 | E17: 处置子公司测试表（不包含一揽子交易） | F17: G7-11
D18: 14 | E18: 处置子公司测试表（一揽子交易） | F18: G7-12
D19: 15 | E19: 合营、联营企业投资成本测试表 | F19: G7-13
D20: 16 | E20: 权益法测算表 | F20: G7-14
D21: 17 | E21: 权益法未实现内部交易抵销测算表 | F21: G7-15
D22: 18 | E22: 未确认投资损失测试表 | F22: G7-16
D23: 19 | E23: 减值测试表 | F23: G7-17
D24: 20 | E24: 凭证检查表 | F24: G7-18

Sheet 长期股权投资实质性程序表G7A
A1: 致同会计师事务所
A2: 长期股权投资实质性程序表
A3: =底稿目录!A2 | C3: =底稿目录!A4 | F3: =底稿目录!A5 | H3: 索引号： | I3: =底稿目录!F4
A4: =底稿目录!A3 | C4: =底稿目录!A6 | F4: =底稿目录!A7 | H4: 页 次：
A5: 一、本账户涉及的科目
A6: 长期股权投资、长期股权投资减值准备
A7: 二、审计目标与认定的对应关系
A8: 审计目标 | G8: 财务报表的认定
A9: A. 资产负债表中记录的长期股权投资是存在的，且已记录于恰当的账户 | G9: 存在
A10: B. 所有应记录的长期股权投资均已记录，所有应当包括在财务报表中的相关披露均已包括 | G10: 完整性
A11: C. 记录的长期股权投资由被审计单位拥有或控制 | G11: 权利和义务
A12: D. 长期股权投资以恰当的金额包括在财务报表中，与之相关的计价或分摊调整已恰当记录，相关披露已得到恰当计量和描述 | G12: 准确性、计价和分摊
A13: E. 长期股权投资已被恰当地汇总或分解且表述清楚，相关披露在按照企业会计准则的编制基础下是相关的、可理解的 | G13: 列报
A14: 三、计划实施的实质性程序
A15: 序号 | B15: 审计程序 | C15: 程序分类 | D15: 财务报表的认定 | I15: 底稿索引号
D16: 存在 | E16: 完整性 | F16: 权利和 义务 | G16: 准确性、计价和分摊 | H16: 列报 | J16: 根据被审计单位实际情况和风险评估情况裁剪、修改或增加审计程序
A17: 1 | B17: 获取或编制长期股权投资的明细表，完成以下工作，并编制审定表 （1）复核加计是否正确，与总账、明细账合计数核对是否相符； （2）将期初余额与上期期末余额核对； （3）与上年明细项目进行比较，确定与上年分类相同； （4）检查非记账本位币计量的长期股权投资的折算汇率及折算是否正确。 | C17: 常规★ | D17: √ | E17: √ | G17: √ | I17: G7-1 /G7-2
A18: 2 | B18: 在使用手工编制、自定义信息报告、系统生成的非固定格式报告等由被审计单位生成的信息时，测试有关信息准确性和完整性，并考虑针对编制和维护由被审计单位生成的信息的相关控制实施控制测试，以评价该信息是否能够为实现审计目的提供基础。 | C18: 常规★ | E18: √ | G18: √ | I18: T1 /G0-2 /
A19: 3 | B19: 对期初余额的审计，获取前期期末对被投资单位股权投资的明细，以及相关支持文件并分析，判断公司对投资的分类及其影响程度的认定是否正确，关注计算的准确性，会计处理是否恰当；确定是否需要补充必要的程序。（适用于首次承接） | C19: 备选 | D19: √ | E19: √ | F19: √ | G19: √
A20: 4 | B20: 确认长期股权投资会计政策、会计处理是否合理并与前期一致；核对相关资产减值准备本期与以前年度计提方法是否一致，如有差异，查明政策调整的原因，并确定政策改变对本期损益的影响，提请被审计单位做适当披露。 | C20: 常规★ | D20: √ | E20: √ | G20: √ | I20: G7-6
A21: 5 | B21: 取得被投资单位的章程、营业执照、组织机构代码证等资料，根据有关合同和文件，确认长期股权投资的股权比例、表决权等，检查长期股权投资的分类和核算方法是否正确。 | C21: 常规★ | D21: √ | E21: √ | F21: √ | G21: √ | I21: G7-7 /G7-8 /G7-9 /G7-13 /G7-18
A22: 6 | B22: 对本期发生的长期股权投资的增减变动，检查至支持性文件，综合判断长期股权投资的购买日（或交易日）的认定是否正确，确定其会计处理是否正确，是否被记录在恰当的期间内。 | C22: 常规★ | D22: √ | F22: √ | G22: √ | I22: G7-10 /G7-14 /G7-15 /G7-16 /G7-18
A23: 7 | B23: 必要时对被投资单位进行函证确认主要条款（或查询工商存档文件），核实投资是否存在。 | C23: 备选 | D23: √ | E23: √ | F23: √ | G23: √ | I23: G0
A24: 8 | B24: 确定本期处置的重大股权投资，并执行下列程序： （1）检查与股权投资处置相关的合同、发票及其他文件； （2）重新计算相关的利得或损失； （3）确定会计处理是否恰当。 对于成本法和权益法相互转换的，检查会计处理是否正确。 | C24: 常规★ | D24: √ | E24: √ | F24: √ | G24: √ | I24: G7-11 /G7-12 /G7-18
A25: 9 | B25: 确定本期按权益法核算的长期股权投资进行正确的核算，考虑以下因素：（1）被投资单位的经营成果、财务状况和资本交易； （2）被投资单位为符合投资单位的会计政策而作出的任何必要的会计政策调整； （3）针对被投资单位账面价值、股利分配、收益影响、其他综合收益及其他权益变动的持续调整。 | C25: 常规★ | G25: √ | I25: G7-14 /G7-15 /G7-16
A26: 10 | B26: 对于按成本法核算的长期股权投资，检查股利分配的原始凭证及分配决议等资料，确定会计处理是否正确。 | C26: 常规★ | G26: √ | I26: G7-10
A27: 11 | B27: 针对存在减值迹象的长期股权投资，考虑执行下列程序： （1）获取长期股权投资的减值明细表，考虑对该投资可能造成减值的事件或环境变化； （2）获取被审计单位管理层在资产负债表日就长期股权投资是否存在可能发生减值迹象的判断说明及减值测试过程，关注计提减值准备的依据是否充分，减值测试过程是否合理，会计处理是否正确。 （3）考虑是否需要利用估值专家的工作，如需要完成利用专家工作底稿。 | C27: 常规★ | G27: √ | I27: G7-17
A28: 12 | B28: 了解长期股权投资是否存在所有权限制，承诺或留置。 | C28: 常规★ | F28: √ | I28: G7-2
A29: 13 | B29: 与被审计单位人员讨论确定是否存在被投资单位由于所在国家和地区及其他方面的影响，其向被审计单位转移资金的能力受到限制的情况，如存在，应详细记录受限情况，并提请被审计单位充分披露。 | C29: 常规★ | H29: √ | I29: G7-2
A30: 14 | B30: 检查关联方交易： （1）了解关联交易的商业理由、交易事项的目的、价格和条件，考虑对关联方交易性金融资产的合理性、合法性； （2）检查对关联方交易性金融资产的真实性相关的支持性文件、检查会计处理是否正确； （3）考虑向关联方或其他注册会计师函证重大的关联交易和余额（包括担保和其他重要信息）； （4）必要时，向与交易相关的人员和机构函证或与其讨论有关信息； （5）考虑是否存在未识别的关联方，关联交易和余额披露是否正确。 | C30: 常规★ | D30: √ | E30: √ | F30: √ | G30: √ | H30: √
A31: 15 | B31: 根据评估的舞弊风险等因素增加的审计程序。 | C31: IPO/上市/新三板/重组/舞弊应对
A32: 16 | B32: 检查长期股权投资是否已按照企业会计准则的规定在财务报表中作出恰当列报和披露。 | C32: 常规★ | H32: √ | I32: A1-1/A1-15 /A1-16

Sheet 长期股权投资审定表G7-1
A1: 致同会计师事务所
A2: 长期股权投资审定表
A3: =底稿目录!A2 | D3: =底稿目录!A4 | E3: =底稿目录!A5 | F3: 索引号： | G3: =底稿目录!F5
A4: =底稿目录!A3 | D4: =底稿目录!A6 | E4: =底稿目录!A7 | F4: 页 次：
A5: 项目 | C5: 期初数 | D5: 本期增加 | E5: 本期减少 | F5: 期末数 | G5: 索引
A6: 一、原值
A7: 未审数 | C7: =SUM(C8:C11) | D7: =SUM(D8:D11) | E7: =SUM(E8:E11) | F7: =SUM(F8:F11)
A8: 一、对子公司投资 | C8: ='明细表G7-2'!M26 | D8: ='明细表G7-2'!O26 | E8: ='明细表G7-2'!R26 | F8: =C8+D8-E8
A9: 二、对合营企业投资 | C9: ='明细表G7-2'!H38 | D9: ='明细表G7-2'!J38+'明细表G7-2'!N38 | E9: ='明细表G7-2'!Q38+'明细表G7-2'!R38 | F9: =C9+D9-E9
A10: 三、对联营企业投资 | C10: ='明细表G7-2'!H45 | D10: ='明细表G7-2'!J45+'明细表G7-2'!N45 | E10: ='明细表G7-2'!Q45+'明细表G7-2'!R45 | F10: =C10+D10-E10
F11: =C11+D11-E11
A12: 账项调整 | C12: =SUM(C13:C16) | D12: =SUM(D13:D16) | E12: =SUM(E13:E16) | F12: =SUM(F13:F16)
A13: =A8 | C13: ='明细表G7-2'!V26 | D13: ='明细表G7-2'!X26 | E13: ='明细表G7-2'!Y26 | F13: =C13+D13-E13
A14: =A9 | C14: ='明细表G7-2'!V38 | D14: ='明细表G7-2'!X38+'明细表G7-2'!Y38+'明细表G7-2'!Z38+'明细表G7-2'!AA38 | E14: ='明细表G7-2'!AC38+'明细表G7-2'!AD38 | F14: =C14+D14-E14
A15: =A10 | C15: ='明细表G7-2'!V45 | D15: ='明细表G7-2'!X45+'明细表G7-2'!Y45+'明细表G7-2'!Z45+'明细表G7-2'!AA45 | E15: ='明细表G7-2'!AC45+'明细表G7-2'!AD45 | F15: =C15+D15-E15
A16: =A11 | F16: =C16+D16-E16
A17: 重分类调整 | C17: =SUM(C18:C21) | D17: =SUM(D18:D21) | E17: =SUM(E18:E21) | F17: =SUM(F18:F21)
A18: =A13 | C18: ='明细表G7-2'!W26 | D18: ='明细表G7-2'!Z26 | E18: ='明细表G7-2'!AA26 | F18: =C18+D18-E18
A19: =A14 | C19: ='明细表G7-2'!W38 | D19: ='明细表G7-2'!AF38+'明细表G7-2'!AG38+'明细表G7-2'!AH38+'明细表G7-2'!AI38 | E19: ='明细表G7-2'!AK38+'明细表G7-2'!AL38 | F19: =C19+D19-E19
A20: =A15 | C20: ='明细表G7-2'!W45 | D20: ='明细表G7-2'!AF45+'明细表G7-2'!AG45+'明细表G7-2'!AH45+'明细表G7-2'!AI45 | E20: ='明细表G7-2'!AK45+'明细表G7-2'!AL45 | F20: =C20+D20-E20
A21: =A16 | F21: =C21+D21-E21
A22: 审定数1 | C22: =SUM(C23:C26) | D22: =SUM(D23:D26) | E22: =SUM(E23:E26) | F22: =SUM(F23:F26)
A23: =A18 | C23: =C8+C13+C18 | D23: =D8+D13+D18 | E23: =E8+E13+E18 | F23: =C23+D23-E23
A24: =A19 | C24: =C9+C14+C19 | D24: =D9+D14+D19 | E24: =E9+E14+E19 | F24: =C24+D24-E24
A25: =A20 | C25: =C10+C15+C20 | D25: =D10+D15+D20 | E25: =E10+E15+E20 | F25: =C25+D25-E25
A26: =A21 | C26: =C11+C16+C21 | D26: =D11+D16+D21 | E26: =E11+E16+E21 | F26: =C26+D26-E26
A27: 二、减值准备
A28: 未审数 | C28: =SUM(C29:C32) | D28: =SUM(D29:D32) | E28: =SUM(E29:E32) | F28: =SUM(F29:F32)
A29: =A8 | C29: ='明细表G7-2'!G63 | D29: ='明细表G7-2'!H63 | E29: ='明细表G7-2'!I63 | F29: =C29+D29-E29
A30: =A9 | C30: ='明细表G7-2'!G71 | D30: ='明细表G7-2'!H71 | E30: ='明细表G7-2'!I71 | F30: =C30+D30-E30
A31: =A10 | C31: ='明细表G7-2'!G78 | D31: ='明细表G7-2'!H78 | E31: ='明细表G7-2'!I78 | F31: =C31+D31-E31
A32: =A11 | F32: =C32+D32-E32
A33: 账项调整 | C33: =SUM(C34:C37) | D33: =SUM(D34:D37) | E33: =SUM(E34:E37) | F33: =SUM(F34:F37)
A34: =A13 | C34: ='明细表G7-2'!L63 | D34: ='明细表G7-2'!N63 | E34: ='明细表G7-2'!O63 | F34: =C34+D34-E34
A35: =A14 | C35: ='明细表G7-2'!L71 | D35: ='明细表G7-2'!N71 | E35: ='明细表G7-2'!O71 | F35: =C35+D35-E35
A36: =A15 | C36: ='明细表G7-2'!L78 | D36: ='明细表G7-2'!N78 | E36: ='明细表G7-2'!O78 | F36: =C36+D36-E36
A37: =A16 | F37: =C37+D37-E37
A38: 重分类调整 | C38: =SUM(C39:C42) | D38: =SUM(D39:D42) | E38: =SUM(E39:E42) | F38: =SUM(F39:F42)
A39: =A18 | C39: ='明细表G7-2'!M63 | D39: ='明细表G7-2'!P63 | E39: ='明细表G7-2'!Q63 | F39: =C39+D39-E39
A40: =A19 | C40: ='明细表G7-2'!M71 | D40: ='明细表G7-2'!P71 | E40: ='明细表G7-2'!Q71 | F40: =C40+D40-E40
A41: =A20 | C41: ='明细表G7-2'!M78 | D41: ='明细表G7-2'!P78 | E41: ='明细表G7-2'!Q78 | F41: =C41+D41-E41
A42: =A21 | F42: =C42+D42-E42
A43: 审定数2 | C43: =SUM(C44:C47) | D43: =SUM(D44:D47) | E43: =SUM(E44:E47) | F43: =SUM(F44:F47)
A44: =A23 | C44: =C29+C34+C39 | D44: =D29+D34+D39 | E44: =E29+E34+E39 | F44: =C44+D44-E44
A45: =A24 | C45: =C30+C35+C40 | D45: =D30+D35+D40 | E45: =E30+E35+E40 | F45: =C45+D45-E45
A46: =A25 | C46: =C31+C36+C41 | D46: =D31+D36+D41 | E46: =E31+E36+E41 | F46: =C46+D46-E46
A47: =A26 | C47: =C32+C37+C42 | D47: =D32+D37+D42 | E47: =E32+E37+E42 | F47: =C47+D47-E47
A48: 三、净值
A49: 审定数3 | C49: =SUM(C50:C53) | D49: =SUM(D50:D53) | E49: =SUM(E50:E53) | F49: =SUM(F50:F53)
A50: =A8 | C50: =C23-C44 | D50: =D23-D44 | E50: =E23-E44 | F50: =C50+D50-E50
A51: =A9 | C51: =C24-C45 | D51: =D24-D45 | E51: =E24-E45 | F51: =C51+D51-E51
A52: =A10 | C52: =C25-C46 | D52: =D25-D46 | E52: =E25-E46 | F52: =C52+D52-E52
A53: =A11 | C53: =C26-C47 | D53: =D26-D47 | E53: =E26-E47 | F53: =C53+D53-E53
A54: 试算平衡表数
A55: 差异数 | C55: =C49-C54 | F55: =F49-F54
A56: 1、审计说明：
A57: （1）期末净值较期初净值增加（负数为减少）： | E57: =IF(AND(C49=0,F49>0),1,(F49-C49)/C49)
A58: 主要原因（比例超过30%的）：
A63: （2）情况说明：
A68: 2、审计结论：
A75: 编制说明：
A76: 1、原持有的对被投资单位不具有控制、共同控制或重大影响，并且在活跃市场中没有报价、公允价值不能可靠计量的
A77: 权益性投资（“三无投资”）按照《企业会计准则第22号——金融工具确认和计量》（CAS 22）进行处理。
A78: 2、如适用，根据1131号等审计准则和指南的要求编制，说明涉及事项内容、应对措施、审计结论或解决方法，
A79: 以及可能对审计报告的影响。
A80: A、风险评估结果和内控了解、测试情况（不适用则说明：不存在重大错报风险。)
A81: (识别和实际评估的重大错报风险、尤其识特别风险，以及对内控了解和控制测试情况〔采用综合方案时〕）；
A82: 提示：a、收入科目应当假定存在舞弊的特别风险，如不存在，应说明理由；
A83: b、涉及特别风险时，应当重点说明有关事项、应当措施、结果〔可索引有关底稿〕。
... A94: 参考结论：
A95: A、 | B95: 未见异常，可以确认。
A96: B、 | B96: 经审计调整后可确认。
A97: C、 | B97: 由于存在上述重大未调整事项（或审计范围受到限制无法获取充分、适当证据），不可确认。

Sheet 附注披露信息（上市公司）
A1: 致同会计师事务所
A2: 附注披露信息（上市公司）
A3: =底稿目录!A2 | C3: =底稿目录!A4 | F3: =底稿目录!A5 | K3: 索引号： | L3: =底稿目录!F6
A4: =底稿目录!A3 | C4: =底稿目录!A6 | F4: =底稿目录!A7 | K4: 页次：
A5: 附注披露信息
A6: 长期股权投资
A8: 被投资单位 | B8: 期初余额（账面价值） | D8: 本期增减变动 | L8: 期末余额（账面价值） | M8: 减值准备期末余额
C9: 减值准备期初余额 | D9: 追加/新增投资 | E9: 减少投资 | F9: 权益法下 | G9: 其他综合 | H9: 其他权益变动 | I9: 宣告发放现金股利或利润 | J9: 计提减值准备 | K9: 其他
F10: 确认的 | G10: 收益调整
F11: 投资损益
A12: ①合营企业
A13: …
A15: 小 计
A16: ②联营企业
A17: …
A22: 小 计
A23: 合 计
A24: （长期资产本期进行减值测试的，应披露可收回金额的具体确定方法。可收回金额按公允价值减去处置费用后的净额确定的，应披露公允价值和处置费用的确定方式、关键参数及其确定依据。可收回金额按预计未来现金流量的现值确定的，应披露预测期的年限、预测期及稳定期的关键参数及其确定依据。前述信息与以前年度减值测试采用的信息或外部信息明显不一致的，或公司以前年度减值测试采用信息与当年实际情况明显不一致的，应披露差异原因。（15号文第十九条（十九）））
A26: 1、在子公司中的权益
A27: （1）企业集团的构成
A28: 子公司名称 | B28: 主要经营地 | C28: 注册地 | D28: 业务性质 | E28: 持股比例% | G28: 取得方式
E29: 直接 | F29: 间接
A30: ='被投资单位基本信息G7-4'!B12 | B30: ='被投资单位基本信息G7-4'!F12 | C30: ='被投资单位基本信息G7-4'!G12 | D30: ='被投资单位基本信息G7-4'!H12 | E30: ='被投资单位基本信息G7-4'!M12 | F30: ='被投资单位基本信息G7-4'!N12 | G30: ='被投资单位基本信息G7-4'!S12
A31: ='被投资单位基本信息G7-4'!B13 | B31: ='被投资单位基本信息G7-4'!F13 | C31: ='被投资单位基本信息G7-4'!G13 | D31: ='被投资单位基本信息G7-4'!H13 | E31: ='被投资单位基本信息G7-4'!M13 | F31: ='被投资单位基本信息G7-4'!N13 | G31: ='被投资单位基本信息G7-4'!S13
A32: ='被投资单位基本信息G7-4'!B14 | B32: ='被投资单位基本信息G7-4'!F14 | C32: ='被投资单位基本信息G7-4'!G14 | D32: ='被投资单位基本信息G7-4'!H14 | E32: ='被投资单位基本信息G7-4'!M14 | F32: ='被投资单位基本信息G7-4'!N14 | G32: ='被投资单位基本信息G7-4'!S14
A33: ='被投资单位基本信息G7-4'!B15 | B33: ='被投资单位基本信息G7-4'!F15 | C33: ='被投资单位基本信息G7-4'!G15 | D33: ='被投资单位基本信息G7-4'!H15 | E33: ='被投资单位基本信息G7-4'!M15 | F33: ='被投资单位基本信息G7-4'!N15 | G33: ='被投资单位基本信息G7-4'!S15
A34: ='被投资单位基本信息G7-4'!B16 | B34: ='被投资单位基本信息G7-4'!F16 | C34: ='被投资单位基本信息G7-4'!G16 | D34: ='被投资单位基本信息G7-4'!H16 | E34: ='被投资单位基本信息G7-4'!M16 | F34: ='被投资单位基本信息G7-4'!N16 | G34: ='被投资单位基本信息G7-4'!S16
A35: ='被投资单位基本信息G7-4'!B17 | B35: ='被投资单位基本信息G7-4'!F17 | C35: ='被投资单位基本信息G7-4'!G17 | D35: ='被投资单位基本信息G7-4'!H17 | E35: ='被投资单位基本信息G7-4'!M17 | F35: ='被投资单位基本信息G7-4'!N17 | G35: ='被投资单位基本信息G7-4'!S17
A36: ='被投资单位基本信息G7-4'!B18 | B36: ='被投资单位基本信息G7-4'!F18 | C36: ='被投资单位基本信息G7-4'!G18 | D36: ='被投资单位基本信息G7-4'!H18 | E36: ='被投资单位基本信息G7-4'!M18 | F36: ='被投资单位基本信息G7-4'!N18 | G36: ='被投资单位基本信息G7-4'!S18
A37: ='被投资单位基本信息G7-4'!B19 | B37: ='被投资单位基本信息G7-4'!F19 | C37: ='被投资单位基本信息G7-4'!G19 | D37: ='被投资单位基本信息G7-4'!H19 | E37: ='被投资单位基本信息G7-4'!M19 | F37: ='被投资单位基本信息G7-4'!N19 | G37: ='被投资单位基本信息G7-4'!S19
A38: ='被投资单位基本信息G7-4'!B20 | B38: ='被投资单位基本信息G7-4'!F20 | C38: ='被投资单位基本信息G7-4'!G20 | D38: ='被投资单位基本信息G7-4'!H20 | E38: ='被投资单位基本信息G7-4'!M20 | F38: ='被投资单位基本信息G7-4'!N20 | G38: ='被投资单位基本信息G7-4'!S20
A39: ='被投资单位基本信息G7-4'!B21 | B39: ='被投资单位基本信息G7-4'!F21 | C39: ='被投资单位基本信息G7-4'!G21 | D39: ='被投资单位基本信息G7-4'!H21 | E39: ='被投资单位基本信息G7-4'!M21 | F39: ='被投资单位基本信息G7-4'!N21 | G39: ='被投资单位基本信息G7-4'!S21
A40: 说明：
A41: （1）子公司的持股比例不同于表决权比例的，应说明表决权比例及差异原因。
A42: （2）持有其他主体半数或以下表决权但仍控制该主体、以及公司持有其他主体半数以上表决权但不控制该主体的，公司应披露相关判断和依据。
A43: （3）披露确定公司是代理人还是委托人的判断和依据。
A44: （4）对于纳入合并范围的重要的结构化主体，应披露控制的相关判断和依据。
A45: 【例如资产证券化，公司应根据《信贷资产证券化试点管理办法》和《企业会计准则第23号-金融资产转移》，披露金融资产证券化业务的主要交易安排及其会计处理。涉及非金融资产的资产证券化业务，参照《信贷资产证券化试点管理办法》和《企业会计准则第23号-金融资产转移》的有关规定，披露资产证券化业务的主要交易安排及其会计处理。同时，应详细说明资产证券化业务的破产隔离条款。
A46: （本集团于本年度内将一笔金额为人民币[X]元（200Y年：人民币[X]元）的应收账款证券化转让给由XX银行设立的XX信托计划。作为转让的一部分，本集团就该笔应收账款的预期损失向信托计划提供信用担保。因此，本集团继续全额确认应收账款的账面金额并将因转让而收取的现金确认为抵押借款。在200X年12月31日，被转让的应收账款账面金额为人民币[X]元（200Y年：人民币[X]元），而相关负债的账面金额为人民币[X]元。）】
A47: （2）重要的非全资子公司
A48: 【提示：如果单个非全资子公司的少数股东权益对企业集团而言并不重要，则不需要披露下述信息。】
A49: 子公司名称 | B49: 少数股东持股比例% | C49: 本期归属于少数股东的损益 | D49: 本期向少数股东宣告分派的股利 | E49: 期末少数股东权益余额
A55: 说明：持股比例不同于表决权比例的，应说明表决权比例及差异原因
A56: （3）重要非全资子公司的主要财务信息：（划分为持有待售的除外）
A57: 【提示：如果单个非全资子公司的少数股东权益对企业集团而言并不重要，则不需要披露下述信息。】
A58: 子公司名称 | B58: 期末数
B59: 流动资产 | C59: 非流动资产 | D59: 资产合计 | E59: 流动负债 | F59: 非流动负债 | G59: 负债合计
A65: 续（1）：
A66: 子公司名称 | B66: 期初数
B67: 流动资产 | C67: 非流动资产 | D67: 资产合计 | E67: 流动负债 | F67: 非流动负债 | G67: 负债合计
A73: 续（2）：
A74: 子公司名称 | B74: 本期发生额 | F74: 上期发生额
B75: 营业收入 | C75: 净利润 | D75: 综合收益总额 | E75: 经营活动现金流量 | F75: 营业收入 | G75: 净利润 | H75: 综合收益总额 | I75: 经营活动现金流量
A81: 【提示：上述财务数据以合并日子公司可辨认资产和负债的公允价值为基础进行调整；被划分为持有待售资产的，不需要披露该子公司的上述财务信息。】
A82: （4）使用资产和清偿负债存在的重大限制（不适用的删除）
A83: 说明：（1）限制内容，包括对母公司或子公司与集团内其他主体相互转移现金或其他资产的限制，以及对集团内主体之间发放股利或进行利润分配、发放或收回贷款或垫款等的限制；
A84: （2）子公司少数股东享有保护性权利，并且该保护性权利对使用集团资产或清偿集团负债的能力存在重大限制的，披露限制的性质和程度；
A85: （3）限制涉及的资产和负债在合并财务报表中的金额。
A86: （5）向纳入合并财务报表范围的结构化主体提供的财务支持或其他支持
A87: 说明：应披露与结构化主体相关的风险信息，向结构化主体提供财务支持或其他支持，包括帮助结构化主体取得财务支持：
A88: （1）有合同约定的，披露财务支持的合同条款包括可能导致企业承担损失的事项或情况；
A89: （2）在没有合同约定的情况下，披露所提供支持的类型、金额及原因，包括帮助该结构化主体获得财务支持的情况。其中，本期对以前未纳入合并财务报表范围的结构化主体提供了财务支持或其他支持并且该支持导致控制了该结构化主体的，披露决定提供支持的相关因素；
A90: （3）存在提供支持意图的，披露该意图，包括帮助该结构化主体获得财务支持的意图。
A91: （6）在子公司的所有者权益份额发生变化且仍控制子公司的交易
A92: （15号文第三十五条，公司在子公司的所有者权益份额发生变化且该变化未影响公司对子公司的控制权的，应披露在子公司所有者权益份额的变化情况、对归属于母公司所有者权益和少数股东权益的影响金额，以及上述金额的计算依据。）
... A95: ②交易对于少数股东权益及归属于母公司所有者权益的影响：
A96: 项 目 | B96: 公司1 | C96: 公司2 | D96: 公司3 | E96: 公司4 | F96: 公司5 | G96: 公司6
A97: 购买成本/处置对价：
A98: 现金
A99: 非现金资产的公允价值
A100: 发行或承担的债务的账面价值
A101: 发行的权益性证券的面值
A102: 或有对价
A103: 购买成本/处置对价合计
A104: 减：按取得/处置的股权比例计算的子公司净资产份额
A105: 差额
A106: 其中：调整资本公积
A107: 调整盈余公积
A108: 调整未分配利润 | B108: ='子公司后续计量测试表G7-10'!G21 | C108: ='子公司后续计量测试表G7-10'!H21 | D108: ='子公司后续计量测试表G7-10'!I21 | E108: ='子公司后续计量测试表G7-10'!G34 | F108: ='子公司后续计量测试表G7-10'!H34 | G108: ='子公司后续计量测试表G7-10'!I34
A109: 2、在合营安排或联营企业中的权益
A110: （1）重要的合营企业或联营企业
A111: 合营企业或联营企业名称 | B111: 主要经营地 | C111: 注册地 | D111: 业务性质 | E111: 持股比例(%) | G111: 对合营企业或联营企业投资的会计处理方法
E112: 直接 | F112: 间接
A113: ①合营企业
A114: ='被投资单位基本信息G7-4'!B23 | B114: ='被投资单位基本信息G7-4'!F23 | C114: ='被投资单位基本信息G7-4'!G23 | D114: ='被投资单位基本信息G7-4'!H23 | E114: ='被投资单位基本信息G7-4'!M23 | F114: ='被投资单位基本信息G7-4'!N23 | G114: ='被投资单位基本信息G7-4'!T23
A115: ='被投资单位基本信息G7-4'!B24 | B115: ='被投资单位基本信息G7-4'!F24 | C115: ='被投资单位基本信息G7-4'!G24 | D115: ='被投资单位基本信息G7-4'!H24 | E115: ='被投资单位基本信息G7-4'!M24 | F115: ='被投资单位基本信息G7-4'!N24 | G115: ='被投资单位基本信息G7-4'!T24
A116: ='被投资单位基本信息G7-4'!B25 | B116: ='被投资单位基本信息G7-4'!F25 | C116: ='被投资单位基本信息G7-4'!G25 | D116: ='被投资单位基本信息G7-4'!H25 | E116: ='被投资单位基本信息G7-4'!M25 | F116: ='被投资单位基本信息G7-4'!N25 | G116: ='被投资单位基本信息G7-4'!T25
A117: ='被投资单位基本信息G7-4'!B26 | B117: ='被投资单位基本信息G7-4'!F26 | C117: ='被投资单位基本信息G7-4'!G26 | D117: ='被投资单位基本信息G7-4'!H26 | E117: ='被投资单位基本信息G7-4'!M26 | F117: ='被投资单位基本信息G7-4'!N26 | G117: ='被投资单位基本信息G7-4'!T26
A118: ='被投资单位基本信息G7-4'!B27 | B118: ='被投资单位基本信息G7-4'!F27 | C118: ='被投资单位基本信息G7-4'!G27 | D118: ='被投资单位基本信息G7-4'!H27 | E118: ='被投资单位基本信息G7-4'!M27 | F118: ='被投资单位基本信息G7-4'!N27 | G118: ='被投资单位基本信息G7-4'!T27
A119: ②联营企业
A120: ='被投资单位基本信息G7-4'!B29 | B120: ='被投资单位基本信息G7-4'!F29 | C120: ='被投资单位基本信息G7-4'!G29 | D120: ='被投资单位基本信息G7-4'!H29 | E120: ='被投资单位基本信息G7-4'!M29 | F120: ='被投资单位基本信息G7-4'!N29 | G120: ='被投资单位基本信息G7-4'!T29
A121: ='被投资单位基本信息G7-4'!B30 | B121: ='被投资单位基本信息G7-4'!F30 | C121: ='被投资单位基本信息G7-4'!G30 | D121: ='被投资单位基本信息G7-4'!H30 | E121: ='被投资单位基本信息G7-4'!M30 | F121: ='被投资单位基本信息G7-4'!N30 | G121: ='被投资单位基本信息G7-4'!T30
A122: ='被投资单位基本信息G7-4'!B31 | B122: ='被投资单位基本信息G7-4'!F31 | C122: ='被投资单位基本信息G7-4'!G31 | D122: ='被投资单位基本信息G7-4'!H31 | E122: ='被投资单位基本信息G7-4'!M31 | F122: ='被投资单位基本信息G7-4'!N31 | G122: ='被投资单位基本信息G7-4'!T31
A123: ='被投资单位基本信息G7-4'!B32 | B123: ='被投资单位基本信息G7-4'!F32 | C123: ='被投资单位基本信息G7-4'!G32 | D123: ='被投资单位基本信息G7-4'!H32 | E123: ='被投资单位基本信息G7-4'!M32 | F123: ='被投资单位基本信息G7-4'!N32 | G123: ='被投资单位基本信息G7-4'!T32
A124: ='被投资单位基本信息G7-4'!B33 | B124: ='被投资单位基本信息G7-4'!F33 | C124: ='被投资单位基本信息G7-4'!G33 | D124: ='被投资单位基本信息G7-4'!H33 | E124: ='被投资单位基本信息G7-4'!M33 | F124: ='被投资单位基本信息G7-4'!N33 | G124: ='被投资单位基本信息G7-4'!T33
A125: 说明：
A126: （1）持股比例不同于表决权比例的，应说明表决权比例及差异原因。
A127: （2）持有其他主体20%以下表决权但具有重大影响，或者持有其他主体20%或以上表决权但不具有重大影响的，应披露相关判断和依据。
A128: （2）重要合营企业的主要财务信息：（划分为持有待售的除外）
A129: （主要财务信息按照权益法调整后的金额披露；）
...

Sheet 附注披露信息（国企）
A1: 致同会计师事务所
A2: 附注披露信息（国企）
A3: =底稿目录!A2 | D3: =底稿目录!A4 | H3: =底稿目录!A5 | K3: 索引号： | L3: =底稿目录!F7
A4: =底稿目录!A3 | D4: =底稿目录!A6 | H4: =底稿目录!A7 | K4: 页次：
A5: 附注披露信息
A6: 七、企业合并及合并财务报表
A7: （一）本期纳入合并报表范围的子公司基本情况
A8: （企业应当按下列格式披露纳入报表合并范围的全部子公司主要情况；大型企业集团合并报表范围可以披露到二级子公司，集团所属重要子公司不分级次全部披露）
A9: 序号 | B9: 企业名称 | C9: 级次 | D9: 企业类型 | E9: 注册地 | F9: 主要经营地 | G9: 业务性质 | H9: 实收资本 | I9: 认缴持股比例 （%） | J9: 实缴持股比例（%） | K9: 享有的表决权（%） | L9: 投资额 | M9: 取得方式
A10: 1 | B10: ='被投资单位基本信息G7-4'!B12 | C10: ='被投资单位基本信息G7-4'!C12 | D10: ='被投资单位基本信息G7-4'!D12 | E10: ='被投资单位基本信息G7-4'!G12 | F10: ='被投资单位基本信息G7-4'!F12 | G10: ='被投资单位基本信息G7-4'!H12 | H10: ='被投资单位基本信息G7-4'!I12 | J10: ='被投资单位基本信息G7-4'!M12+'被投资单位基本信息G7-4'!N12 | K10: ='被投资单位基本信息G7-4'!O12 | L10: ='明细表G7-2'!AI16 | M10: ='被投资单位基本信息G7-4'!S12
A11: 2 | B11: ='被投资单位基本信息G7-4'!B13 | C11: ='被投资单位基本信息G7-4'!C13 | D11: ='被投资单位基本信息G7-4'!D13 | E11: ='被投资单位基本信息G7-4'!G13 | F11: ='被投资单位基本信息G7-4'!F13 | G11: ='被投资单位基本信息G7-4'!H13 | H11: ='被投资单位基本信息G7-4'!I13 | J11: ='被投资单位基本信息G7-4'!M13+'被投资单位基本信息G7-4'!N13 | K11: ='被投资单位基本信息G7-4'!O13 | L11: ='明细表G7-2'!AI17 | M11: ='被投资单位基本信息G7-4'!S13
A12: 3 | B12: ='被投资单位基本信息G7-4'!B14 | C12: ='被投资单位基本信息G7-4'!C14 | D12: ='被投资单位基本信息G7-4'!D14 | E12: ='被投资单位基本信息G7-4'!G14 | F12: ='被投资单位基本信息G7-4'!F14 | G12: ='被投资单位基本信息G7-4'!H14 | H12: ='被投资单位基本信息G7-4'!I14 | J12: ='被投资单位基本信息G7-4'!M14+'被投资单位基本信息G7-4'!N14 | K12: ='被投资单位基本信息G7-4'!O14 | L12: ='明细表G7-2'!AI18 | M12: ='被投资单位基本信息G7-4'!S14
A13: 4 | B13: ='被投资单位基本信息G7-4'!B15 | C13: ='被投资单位基本信息G7-4'!C15 | D13: ='被投资单位基本信息G7-4'!D15 | E13: ='被投资单位基本信息G7-4'!G15 | F13: ='被投资单位基本信息G7-4'!F15 | G13: ='被投资单位基本信息G7-4'!H15 | H13: ='被投资单位基本信息G7-4'!I15 | J13: ='被投资单位基本信息G7-4'!M15+'被投资单位基本信息G7-4'!N15 | K13: ='被投资单位基本信息G7-4'!O15 | L13: ='明细表G7-2'!AI19 | M13: ='被投资单位基本信息G7-4'!S15
A14: 5 | B14: ='被投资单位基本信息G7-4'!B16 | C14: ='被投资单位基本信息G7-4'!C16 | D14: ='被投资单位基本信息G7-4'!D16 | E14: ='被投资单位基本信息G7-4'!G16 | F14: ='被投资单位基本信息G7-4'!F16 | G14: ='被投资单位基本信息G7-4'!H16 | H14: ='被投资单位基本信息G7-4'!I16 | J14: ='被投资单位基本信息G7-4'!M16+'被投资单位基本信息G7-4'!N16 | K14: ='被投资单位基本信息G7-4'!O16 | L14: ='明细表G7-2'!AI20 | M14: ='被投资单位基本信息G7-4'!S16
A15: 6 | B15: ='被投资单位基本信息G7-4'!B17 | C15: ='被投资单位基本信息G7-4'!C17 | D15: ='被投资单位基本信息G7-4'!D17 | E15: ='被投资单位基本信息G7-4'!G17 | F15: ='被投资单位基本信息G7-4'!F17 | G15: ='被投资单位基本信息G7-4'!H17 | H15: ='被投资单位基本信息G7-4'!I17 | J15: ='被投资单位基本信息G7-4'!M17+'被投资单位基本信息G7-4'!N17 | K15: ='被投资单位基本信息G7-4'!O17 | L15: ='明细表G7-2'!AI21 | M15: ='被投资单位基本信息G7-4'!S17
A16: 7 | B16: ='被投资单位基本信息G7-4'!B18 | C16: ='被投资单位基本信息G7-4'!C18 | D16: ='被投资单位基本信息G7-4'!D18 | E16: ='被投资单位基本信息G7-4'!G18 | F16: ='被投资单位基本信息G7-4'!F18 | G16: ='被投资单位基本信息G7-4'!H18 | H16: ='被投资单位基本信息G7-4'!I18 | J16: ='被投资单位基本信息G7-4'!M18+'被投资单位基本信息G7-4'!N18 | K16: ='被投资单位基本信息G7-4'!O18 | L16: ='明细表G7-2'!AI22 | M16: ='被投资单位基本信息G7-4'!S18
A17: 8 | B17: ='被投资单位基本信息G7-4'!B19 | C17: ='被投资单位基本信息G7-4'!C19 | D17: ='被投资单位基本信息G7-4'!D19 | E17: ='被投资单位基本信息G7-4'!G19 | F17: ='被投资单位基本信息G7-4'!F19 | G17: ='被投资单位基本信息G7-4'!H19 | H17: ='被投资单位基本信息G7-4'!I19 | J17: ='被投资单位基本信息G7-4'!M19+'被投资单位基本信息G7-4'!N19 | K17: ='被投资单位基本信息G7-4'!O19 | L17: ='明细表G7-2'!AI23 | M17: ='被投资单位基本信息G7-4'!S19
A18: 9 | B18: ='被投资单位基本信息G7-4'!B20 | C18: ='被投资单位基本信息G7-4'!C20 | D18: ='被投资单位基本信息G7-4'!D20 | E18: ='被投资单位基本信息G7-4'!G20 | F18: ='被投资单位基本信息G7-4'!F20 | G18: ='被投资单位基本信息G7-4'!H20 | H18: ='被投资单位基本信息G7-4'!I20 | J18: ='被投资单位基本信息G7-4'!M20+'被投资单位基本信息G7-4'!N20 | K18: ='被投资单位基本信息G7-4'!O20 | L18: ='明细表G7-2'!AI24 | M18: ='被投资单位基本信息G7-4'!S20
A19: 10 | B19: ='被投资单位基本信息G7-4'!B21 | C19: ='被投资单位基本信息G7-4'!C21 | D19: ='被投资单位基本信息G7-4'!D21 | E19: ='被投资单位基本信息G7-4'!G21 | F19: ='被投资单位基本信息G7-4'!F21 | G19: ='被投资单位基本信息G7-4'!H21 | H19: ='被投资单位基本信息G7-4'!I21 | J19: ='被投资单位基本信息G7-4'!M21+'被投资单位基本信息G7-4'!N21 | K19: ='被投资单位基本信息G7-4'!O21 | L19: ='明细表G7-2'!AI25 | M19: ='被投资单位基本信息G7-4'!S21
A20: （注：企业类型：1.境内非金融子企业，2.境内金融子企业，3.境外子企业，4.事业单位，5.基建单位；
A21: 取得方式：1.投资设立，2.同一控制下的企业合并，3.非同一控制下的企业合并，4.其他）
A22: （注：子公司的持股比例不同于表决权比例的，应说明表决权比例及差异原因。）
A23: （注：级次为在整个中央企业集团内的法人级次）
A24: （二）母公司拥有被投资单位表决权不足半数但能对被投资单位形成控制的原因
A25: 序号 | B25: 企业名称 | C25: 认缴持股 比例（%） | D25: 享有的表决权 | E25: 注册资本 | F25: 投资额 | G25: 级次 | H25: 纳入合并范围原因
B26: =IF('被投资单位基本信息G7-4'!O12<=0.5,'被投资单位基本信息G7-4'!B12,0) | C26: =IF('被投资单位基本信息G7-4'!O12<=0.5,'被投资单位基本信息G7-4'!M12+'被投资单位基本信息G7-4'!N12,0) | D26: =IF('被投资单位基本信息G7-4'!O12<=0.5,'被投资单位基本信息G7-4'!O12,0) | E26: =IF('被投资单位基本信息G7-4'!O12<=0.5,'被投资单位基本信息G7-4'!I12,0) | F26: =IF('被投资单位基本信息G7-4'!O12<=0.5,'被投资单位基本信息G7-4'!J12,0) | G26: =IF('被投资单位基本信息G7-4'!O12<=0.5,'被投资单位基本信息G7-4'!C12,0) | H26: =IF('被投资单位基本信息G7-4'!O12<=0.5,'被投资单位基本信息G7-4'!Q12,0)
B27: =IF('被投资单位基本信息G7-4'!O13<=0.5,'被投资单位基本信息G7-4'!B13,0) | C27: =IF('被投资单位基本信息G7-4'!O13<=0.5,'被投资单位基本信息G7-4'!M13+'被投资单位基本信息G7-4'!N13,0) | D27: =IF('被投资单位基本信息G7-4'!O13<=0.5,'被投资单位基本信息G7-4'!O13,0) | E27: =IF('被投资单位基本信息G7-4'!O13<=0.5,'被投资单位基本信息G7-4'!I13,0) | F27: =IF('被投资单位基本信息G7-4'!O13<=0.5,'被投资单位基本信息G7-4'!J13,0) | G27: =IF('被投资单位基本信息G7-4'!O13<=0.5,'被投资单位基本信息G7-4'!C13,0) | H27: =IF('被投资单位基本信息G7-4'!O13<=0.5,'被投资单位基本信息G7-4'!Q13,0)
B28: =IF('被投资单位基本信息G7-4'!O14<=0.5,'被投资单位基本信息G7-4'!B14,0) | C28: =IF('被投资单位基本信息G7-4'!O14<=0.5,'被投资单位基本信息G7-4'!M14+'被投资单位基本信息G7-4'!N14,0) | D28: =IF('被投资单位基本信息G7-4'!O14<=0.5,'被投资单位基本信息G7-4'!O14,0) | E28: =IF('被投资单位基本信息G7-4'!O14<=0.5,'被投资单位基本信息G7-4'!I14,0) | F28: =IF('被投资单位基本信息G7-4'!O14<=0.5,'被投资单位基本信息G7-4'!J14,0) | G28: =IF('被投资单位基本信息G7-4'!O14<=0.5,'被投资单位基本信息G7-4'!C14,0) | H28: =IF('被投资单位基本信息G7-4'!O14<=0.5,'被投资单位基本信息G7-4'!Q14,0)
B29: =IF('被投资单位基本信息G7-4'!O15<=0.5,'被投资单位基本信息G7-4'!B15,0) | C29: =IF('被投资单位基本信息G7-4'!O15<=0.5,'被投资单位基本信息G7-4'!M15+'被投资单位基本信息G7-4'!N15,0) | D29: =IF('被投资单位基本信息G7-4'!O15<=0.5,'被投资单位基本信息G7-4'!O15,0) | E29: =IF('被投资单位基本信息G7-4'!O15<=0.5,'被投资单位基本信息G7-4'!I15,0) | F29: =IF('被投资单位基本信息G7-4'!O15<=0.5,'被投资单位基本信息G7-4'!J15,0) | G29: =IF('被投资单位基本信息G7-4'!O15<=0.5,'被投资单位基本信息G7-4'!C15,0) | H29: =IF('被投资单位基本信息G7-4'!O15<=0.5,'被投资单位基本信息G7-4'!Q15,0)
B30: =IF('被投资单位基本信息G7-4'!O16<=0.5,'被投资单位基本信息G7-4'!B16,0) | C30: =IF('被投资单位基本信息G7-4'!O16<=0.5,'被投资单位基本信息G7-4'!M16+'被投资单位基本信息G7-4'!N16,0) | D30: =IF('被投资单位基本信息G7-4'!O16<=0.5,'被投资单位基本信息G7-4'!O16,0) | E30: =IF('被投资单位基本信息G7-4'!O16<=0.5,'被投资单位基本信息G7-4'!I16,0) | F30: =IF('被投资单位基本信息G7-4'!O16<=0.5,'被投资单位基本信息G7-4'!J16,0) | G30: =IF('被投资单位基本信息G7-4'!O16<=0.5,'被投资单位基本信息G7-4'!C16,0) | H30: =IF('被投资单位基本信息G7-4'!O16<=0.5,'被投资单位基本信息G7-4'!Q16,0)
B31: =IF('被投资单位基本信息G7-4'!O17<=0.5,'被投资单位基本信息G7-4'!B17,0) | C31: =IF('被投资单位基本信息G7-4'!O17<=0.5,'被投资单位基本信息G7-4'!M17+'被投资单位基本信息G7-4'!N17,0) | D31: =IF('被投资单位基本信息G7-4'!O17<=0.5,'被投资单位基本信息G7-4'!O17,0) | E31: =IF('被投资单位基本信息G7-4'!O17<=0.5,'被投资单位基本信息G7-4'!I17,0) | F31: =IF('被投资单位基本信息G7-4'!O17<=0.5,'被投资单位基本信息G7-4'!J17,0) | G31: =IF('被投资单位基本信息G7-4'!O17<=0.5,'被投资单位基本信息G7-4'!C17,0) | H31: =IF('被投资单位基本信息G7-4'!O17<=0.5,'被投资单位基本信息G7-4'!Q17,0)
B32: =IF('被投资单位基本信息G7-4'!O18<=0.5,'被投资单位基本信息G7-4'!B18,0) | C32: =IF('被投资单位基本信息G7-4'!O18<=0.5,'被投资单位基本信息G7-4'!M18+'被投资单位基本信息G7-4'!N18,0) | D32: =IF('被投资单位基本信息G7-4'!O18<=0.5,'被投资单位基本信息G7-4'!O18,0) | E32: =IF('被投资单位基本信息G7-4'!O18<=0.5,'被投资单位基本信息G7-4'!I18,0) | F32: =IF('被投资单位基本信息G7-4'!O18<=0.5,'被投资单位基本信息G7-4'!J18,0) | G32: =IF('被投资单位基本信息G7-4'!O18<=0.5,'被投资单位基本信息G7-4'!C18,0) | H32: =IF('被投资单位基本信息G7-4'!O18<=0.5,'被投资单位基本信息G7-4'!Q18,0)
B33: =IF('被投资单位基本信息G7-4'!O19<=0.5,'被投资单位基本信息G7-4'!B19,0) | C33: =IF('被投资单位基本信息G7-4'!O19<=0.5,'被投资单位基本信息G7-4'!M19+'被投资单位基本信息G7-4'!N19,0) | D33: =IF('被投资单位基本信息G7-4'!O19<=0.5,'被投资单位基本信息G7-4'!O19,0) | E33: =IF('被投资单位基本信息G7-4'!O19<=0.5,'被投资单位基本信息G7-4'!I19,0) | F33: =IF('被投资单位基本信息G7-4'!O19<=0.5,'被投资单位基本信息G7-4'!J19,0) | G33: =IF('被投资单位基本信息G7-4'!O19<=0.5,'被投资单位基本信息G7-4'!C19,0) | H33: =IF('被投资单位基本信息G7-4'!O19<=0.5,'被投资单位基本信息G7-4'!Q19,0)
B34: =IF('被投资单位基本信息G7-4'!O20<=0.5,'被投资单位基本信息G7-4'!B20,0) | C34: =IF('被投资单位基本信息G7-4'!O20<=0.5,'被投资单位基本信息G7-4'!M20+'被投资单位基本信息G7-4'!N20,0) | D34: =IF('被投资单位基本信息G7-4'!O20<=0.5,'被投资单位基本信息G7-4'!O20,0) | E34: =IF('被投资单位基本信息G7-4'!O20<=0.5,'被投资单位基本信息G7-4'!I20,0) | F34: =IF('被投资单位基本信息G7-4'!O20<=0.5,'被投资单位基本信息G7-4'!J20,0) | G34: =IF('被投资单位基本信息G7-4'!O20<=0.5,'被投资单位基本信息G7-4'!C20,0) | H34: =IF('被投资单位基本信息G7-4'!O20<=0.5,'被投资单位基本信息G7-4'!Q20,0)
B35: =IF('被投资单位基本信息G7-4'!O21<=0.5,'被投资单位基本信息G7-4'!B21,0) | C35: =IF('被投资单位基本信息G7-4'!O21<=0.5,'被投资单位基本信息G7-4'!M21+'被投资单位基本信息G7-4'!N21,0) | D35: =IF('被投资单位基本信息G7-4'!O21<=0.5,'被投资单位基本信息G7-4'!O21,0) | E35: =IF('被投资单位基本信息G7-4'!O21<=0.5,'被投资单位基本信息G7-4'!I21,0) | F35: =IF('被投资单位基本信息G7-4'!O21<=0.5,'被投资单位基本信息G7-4'!J21,0) | G35: =IF('被投资单位基本信息G7-4'!O21<=0.5,'被投资单位基本信息G7-4'!C21,0) | H35: =IF('被投资单位基本信息G7-4'!O21<=0.5,'被投资单位基本信息G7-4'!Q21,0)
A36: （三）母公司直接或通过其他子公司间接拥有被投资单位半数以上的表决权但未能对其形成控制的原因
A37: 序号 | B37: 企业名称 | C37: 认缴持股 比例（%） | D37: 享有的表决权 | E37: 注册资本 | F37: 投资额 | G37: 级次 | H37: 未纳入合并范围原因
B38: 合营企业
B39: =IF('被投资单位基本信息G7-4'!M23+'被投资单位基本信息G7-4'!N23>0.5,'被投资单位基本信息G7-4'!B23,0) | C39: =IF('被投资单位基本信息G7-4'!M23+'被投资单位基本信息G7-4'!N23>0.5,'被投资单位基本信息G7-4'!M23+'被投资单位基本信息G7-4'!N23,0) | D39: =IF('被投资单位基本信息G7-4'!M23+'被投资单位基本信息G7-4'!N23>0.5,'被投资单位基本信息G7-4'!O23,0) | E39: =IF('被投资单位基本信息G7-4'!M23+'被投资单位基本信息G7-4'!N23>0.5,'被投资单位基本信息G7-4'!I23,0) | F39: =IF('被投资单位基本信息G7-4'!M23+'被投资单位基本信息G7-4'!N23>0.5,'被投资单位基本信息G7-4'!J23,0) | G39: =IF('被投资单位基本信息G7-4'!M23+'被投资单位基本信息G7-4'!N23>0.5,'被投资单位基本信息G7-4'!C23,0) | H39: =IF('被投资单位基本信息G7-4'!M23+'被投资单位基本信息G7-4'!N23>0.5,'被投资单位基本信息G7-4'!R23,0)
B40: =IF('被投资单位基本信息G7-4'!M24+'被投资单位基本信息G7-4'!N24>0.5,'被投资单位基本信息G7-4'!B24,0) | C40: =IF('被投资单位基本信息G7-4'!M24+'被投资单位基本信息G7-4'!N24>0.5,'被投资单位基本信息G7-4'!M24+'被投资单位基本信息G7-4'!N24,0) | D40: =IF('被投资单位基本信息G7-4'!M24+'被投资单位基本信息G7-4'!N24>0.5,'被投资单位基本信息G7-4'!O24,0) | E40: =IF('被投资单位基本信息G7-4'!M24+'被投资单位基本信息G7-4'!N24>0.5,'被投资单位基本信息G7-4'!I24,0) | F40: =IF('被投资单位基本信息G7-4'!M24+'被投资单位基本信息G7-4'!N24>0.5,'被投资单位基本信息G7-4'!J24,0) | G40: =IF('被投资单位基本信息G7-4'!M24+'被投资单位基本信息G7-4'!N24>0.5,'被投资单位基本信息G7-4'!C24,0) | H40: =IF('被投资单位基本信息G7-4'!M24+'被投资单位基本信息G7-4'!N24>0.5,'被投资单位基本信息G7-4'!R24,0)
B41: =IF('被投资单位基本信息G7-4'!M25+'被投资单位基本信息G7-4'!N25>0.5,'被投资单位基本信息G7-4'!B25,0) | C41: =IF('被投资单位基本信息G7-4'!M25+'被投资单位基本信息G7-4'!N25>0.5,'被投资单位基本信息G7-4'!M25+'被投资单位基本信息G7-4'!N25,0) | D41: =IF('被投资单位基本信息G7-4'!M25+'被投资单位基本信息G7-4'!N25>0.5,'被投资单位基本信息G7-4'!O25,0) | E41: =IF('被投资单位基本信息G7-4'!M25+'被投资单位基本信息G7-4'!N25>0.5,'被投资单位基本信息G7-4'!I25,0) | F41: =IF('被投资单位基本信息G7-4'!M25+'被投资单位基本信息G7-4'!N25>0.5,'被投资单位基本信息G7-4'!J25,0) | G41: =IF('被投资单位基本信息G7-4'!M25+'被投资单位基本信息G7-4'!N25>0.5,'被投资单位基本信息G7-4'!C25,0) | H41: =IF('被投资单位基本信息G7-4'!M25+'被投资单位基本信息G7-4'!N25>0.5,'被投资单位基本信息G7-4'!R25,0)
B42: =IF('被投资单位基本信息G7-4'!M26+'被投资单位基本信息G7-4'!N26>0.5,'被投资单位基本信息G7-4'!B26,0) | C42: =IF('被投资单位基本信息G7-4'!M26+'被投资单位基本信息G7-4'!N26>0.5,'被投资单位基本信息G7-4'!M26+'被投资单位基本信息G7-4'!N26,0) | D42: =IF('被投资单位基本信息G7-4'!M26+'被投资单位基本信息G7-4'!N26>0.5,'被投资单位基本信息G7-4'!O26,0) | E42: =IF('被投资单位基本信息G7-4'!M26+'被投资单位基本信息G7-4'!N26>0.5,'被投资单位基本信息G7-4'!I26,0) | F42: =IF('被投资单位基本信息G7-4'!M26+'被投资单位基本信息G7-4'!N26>0.5,'被投资单位基本信息G7-4'!J26,0) | G42: =IF('被投资单位基本信息G7-4'!M26+'被投资单位基本信息G7-4'!N26>0.5,'被投资单位基本信息G7-4'!C26,0) | H42: =IF('被投资单位基本信息G7-4'!M26+'被投资单位基本信息G7-4'!N26>0.5,'被投资单位基本信息G7-4'!R26,0)
B43: =IF('被投资单位基本信息G7-4'!M27+'被投资单位基本信息G7-4'!N27>0.5,'被投资单位基本信息G7-4'!B27,0) | C43: =IF('被投资单位基本信息G7-4'!M27+'被投资单位基本信息G7-4'!N27>0.5,'被投资单位基本信息G7-4'!M27+'被投资单位基本信息G7-4'!N27,0) | D43: =IF('被投资单位基本信息G7-4'!M27+'被投资单位基本信息G7-4'!N27>0.5,'被投资单位基本信息G7-4'!O27,0) | E43: =IF('被投资单位基本信息G7-4'!M27+'被投资单位基本信息G7-4'!N27>0.5,'被投资单位基本信息G7-4'!I27,0) | F43: =IF('被投资单位基本信息G7-4'!M27+'被投资单位基本信息G7-4'!N27>0.5,'被投资单位基本信息G7-4'!J27,0) | G43: =IF('被投资单位基本信息G7-4'!M27+'被投资单位基本信息G7-4'!N27>0.5,'被投资单位基本信息G7-4'!C27,0) | H43: =IF('被投资单位基本信息G7-4'!M27+'被投资单位基本信息G7-4'!N27>0.5,'被投资单位基本信息G7-4'!R27,0)
B44: 联营企业
B45: =IF('被投资单位基本信息G7-4'!M29+'被投资单位基本信息G7-4'!N29>0.5,'被投资单位基本信息G7-4'!B29,0) | C45: =IF('被投资单位基本信息G7-4'!M29+'被投资单位基本信息G7-4'!N29>0.5,'被投资单位基本信息G7-4'!M29+'被投资单位基本信息G7-4'!N29,0) | D45: =IF('被投资单位基本信息G7-4'!M29+'被投资单位基本信息G7-4'!N29>0.5,'被投资单位基本信息G7-4'!O29+'被投资单位基本信息G7-4'!N29,0) | E45: =IF('被投资单位基本信息G7-4'!M29+'被投资单位基本信息G7-4'!N29>0.5,'被投资单位基本信息G7-4'!I29,0) | F45: =IF('被投资单位基本信息G7-4'!M29+'被投资单位基本信息G7-4'!N29>0.5,'被投资单位基本信息G7-4'!J29,0) | G45: =IF('被投资单位基本信息G7-4'!M29+'被投资单位基本信息G7-4'!N29>0.5,'被投资单位基本信息G7-4'!C29,0) | H45: =IF('被投资单位基本信息G7-4'!M29+'被投资单位基本信息G7-4'!N29>0.5,'被投资单位基本信息G7-4'!R29,0)
B46: =IF('被投资单位基本信息G7-4'!M30+'被投资单位基本信息G7-4'!N30>0.5,'被投资单位基本信息G7-4'!B30,0) | C46: =IF('被投资单位基本信息G7-4'!M30+'被投资单位基本信息G7-4'!N30>0.5,'被投资单位基本信息G7-4'!M30+'被投资单位基本信息G7-4'!N30,0) | D46: =IF('被投资单位基本信息G7-4'!M30+'被投资单位基本信息G7-4'!N30>0.5,'被投资单位基本信息G7-4'!O30+'被投资单位基本信息G7-4'!N30,0) | E46: =IF('被投资单位基本信息G7-4'!M30+'被投资单位基本信息G7-4'!N30>0.5,'被投资单位基本信息G7-4'!I30,0) | F46: =IF('被投资单位基本信息G7-4'!M30+'被投资单位基本信息G7-4'!N30>0.5,'被投资单位基本信息G7-4'!J30,0) | G46: =IF('被投资单位基本信息G7-4'!M30+'被投资单位基本信息G7-4'!N30>0.5,'被投资单位基本信息G7-4'!C30,0) | H46: =IF('被投资单位基本信息G7-4'!M30+'被投资单位基本信息G7-4'!N30>0.5,'被投资单位基本信息G7-4'!R30,0)
B47: =IF('被投资单位基本信息G7-4'!M31+'被投资单位基本信息G7-4'!N31>0.5,'被投资单位基本信息G7-4'!B31,0) | C47: =IF('被投资单位基本信息G7-4'!M31+'被投资单位基本信息G7-4'!N31>0.5,'被投资单位基本信息G7-4'!M31+'被投资单位基本信息G7-4'!N31,0) | D47: =IF('被投资单位基本信息G7-4'!M31+'被投资单位基本信息G7-4'!N31>0.5,'被投资单位基本信息G7-4'!O31+'被投资单位基本信息G7-4'!N31,0) | E47: =IF('被投资单位基本信息G7-4'!M31+'被投资单位基本信息G7-4'!N31>0.5,'被投资单位基本信息G7-4'!I31,0) | F47: =IF('被投资单位基本信息G7-4'!M31+'被投资单位基本信息G7-4'!N31>0.5,'被投资单位基本信息G7-4'!J31,0) | G47: =IF('被投资单位基本信息G7-4'!M31+'被投资单位基本信息G7-4'!N31>0.5,'被投资单位基本信息G7-4'!C31,0) | H47: =IF('被投资单位基本信息G7-4'!M31+'被投资单位基本信息G7-4'!N31>0.5,'被投资单位基本信息G7-4'!R31,0)
B48: =IF('被投资单位基本信息G7-4'!M32+'被投资单位基本信息G7-4'!N32>0.5,'被投资单位基本信息G7-4'!B32,0) | C48: =IF('被投资单位基本信息G7-4'!M32+'被投资单位基本信息G7-4'!N32>0.5,'被投资单位基本信息G7-4'!M32+'被投资单位基本信息G7-4'!N32,0) | D48: =IF('被投资单位基本信息G7-4'!M32+'被投资单位基本信息G7-4'!N32>0.5,'被投资单位基本信息G7-4'!O32+'被投资单位基本信息G7-4'!N32,0) | E48: =IF('被投资单位基本信息G7-4'!M32+'被投资单位基本信息G7-4'!N32>0.5,'被投资单位基本信息G7-4'!I32,0) | F48: =IF('被投资单位基本信息G7-4'!M32+'被投资单位基本信息G7-4'!N32>0.5,'被投资单位基本信息G7-4'!J32,0) | G48: =IF('被投资单位基本信息G7-4'!M32+'被投资单位基本信息G7-4'!N32>0.5,'被投资单位基本信息G7-4'!C32,0) | H48: =IF('被投资单位基本信息G7-4'!M32+'被投资单位基本信息G7-4'!N32>0.5,'被投资单位基本信息G7-4'!R32,0)
B49: =IF('被投资单位基本信息G7-4'!M33+'被投资单位基本信息G7-4'!N33>0.5,'被投资单位基本信息G7-4'!B33,0) | C49: =IF('被投资单位基本信息G7-4'!M33+'被投资单位基本信息G7-4'!N33>0.5,'被投资单位基本信息G7-4'!M33+'被投资单位基本信息G7-4'!N33,0) | D49: =IF('被投资单位基本信息G7-4'!M33+'被投资单位基本信息G7-4'!N33>0.5,'被投资单位基本信息G7-4'!O33+'被投资单位基本信息G7-4'!N33,0) | E49: =IF('被投资单位基本信息G7-4'!M33+'被投资单位基本信息G7-4'!N33>0.5,'被投资单位基本信息G7-4'!I33,0) | F49: =IF('被投资单位基本信息G7-4'!M33+'被投资单位基本信息G7-4'!N33>0.5,'被投资单位基本信息G7-4'!J33,0) | G49: =IF('被投资单位基本信息G7-4'!M33+'被投资单位基本信息G7-4'!N33>0.5,'被投资单位基本信息G7-4'!C33,0) | H49: =IF('被投资单位基本信息G7-4'!M33+'被投资单位基本信息G7-4'!N33>0.5,'被投资单位基本信息G7-4'!R33,0)
B50: 其他（含共同经营等）
B51: =IF('被投资单位基本信息G7-4'!M35+'被投资单位基本信息G7-4'!N35>0.5,'被投资单位基本信息G7-4'!B35,0) | C51: =IF('被投资单位基本信息G7-4'!M35+'被投资单位基本信息G7-4'!N35>0.5,'被投资单位基本信息G7-4'!M35+'被投资单位基本信息G7-4'!N35,0) | D51: =IF('被投资单位基本信息G7-4'!M35+'被投资单位基本信息G7-4'!N35>0.5,'被投资单位基本信息G7-4'!O35,0) | E51: =IF('被投资单位基本信息G7-4'!M35+'被投资单位基本信息G7-4'!N35>0.5,'被投资单位基本信息G7-4'!I35,0) | F51: =IF('被投资单位基本信息G7-4'!M35+'被投资单位基本信息G7-4'!N35>0.5,'被投资单位基本信息G7-4'!J35,0) | G51: =IF('被投资单位基本信息G7-4'!M35+'被投资单位基本信息G7-4'!N35>0.5,'被投资单位基本信息G7-4'!C35,0) | H51: =IF('被投资单位基本信息G7-4'!M35+'被投资单位基本信息G7-4'!N35>0.5,'被投资单位基本信息G7-4'!R35,0)
B52: =IF('被投资单位基本信息G7-4'!M36+'被投资单位基本信息G7-4'!N36>0.5,'被投资单位基本信息G7-4'!B36,0) | C52: =IF('被投资单位基本信息G7-4'!M36+'被投资单位基本信息G7-4'!N36>0.5,'被投资单位基本信息G7-4'!M36+'被投资单位基本信息G7-4'!N36,0) | D52: =IF('被投资单位基本信息G7-4'!M36+'被投资单位基本信息G7-4'!N36>0.5,'被投资单位基本信息G7-4'!O36,0) | E52: =IF('被投资单位基本信息G7-4'!M36+'被投资单位基本信息G7-4'!N36>0.5,'被投资单位基本信息G7-4'!I36,0) | F52: =IF('被投资单位基本信息G7-4'!M36+'被投资单位基本信息G7-4'!N36>0.5,'被投资单位基本信息G7-4'!J36,0) | G52: =IF('被投资单位基本信息G7-4'!M36+'被投资单位基本信息G7-4'!N36>0.5,'被投资单位基本信息G7-4'!C36,0) | H52: =IF('被投资单位基本信息G7-4'!M36+'被投资单位基本信息G7-4'!N36>0.5,'被投资单位基本信息G7-4'!R36,0)
A53: （四）重要非全资子公司情况
A54: 1、少数股东
A55: 序号 | B55: 企业名称 | C55: 少数股东持股比例 | D55: 当期归属于少数股东的损益 | E55: 当期向少数股东支付的股利 | F55: 期末累计少数股东权益
A61: 2、主要财务信息：
A62: 项 目
C63: 期末数/本期发生额 | D63: 期初数/上期发生额 | E63: 期末数/本期发生额 | F63: 期初数/上期发生额 | G63: 期末数/本期发生额 | H63: 期初数/上期发生额 | I63: 期末数/本期发生额 | J63: 期初数/上期发生额 | K63: 期末数/本期发生额 | L63: 期初数/上期发生额
A64: 流动资产
A65: 非流动资产
A66: 资产合计
A67: 流动负债
A68: 非流动负债
A69: 负债合计
A70: 营业收入
A71: 净利润
A72: 综合收益总额
A73: 经营活动现金流量
A74: 【提示：上述财务数据以合并日子公司可辨认资产和负债的公允价值为基础进行调整；被划分为持有待售资产的，不需要披露该子公司的上述财务信息。】
A75: （五）子公司与母公司会计期间不一致的，母公司编制合并财务报表的处理方法
... A77: （1）原子公司的基本情况
A78: 序号 | B78: 企业名称 | C78: 注册地 | D78: 业务性质 | E78: 持股比例（%） | F78: 表决权比例（%） | G78: 本期不再成为子公司的原因
A79: 1 | B79: ='处置子公司测试表（不包含一揽子交易）G7-11'!B9 | C79: ='处置子公司测试表（不包含一揽子交易）G7-11'!C9 | D79: ='处置子公司测试表（不包含一揽子交易）G7-11'!D9 | E79: ='处置子公司测试表（不包含一揽子交易）G7-11'!E9 | F79: ='处置子公司测试表（不包含一揽子交易）G7-11'!F9 | G79: ='处置子公司测试表（不包含一揽子交易）G7-11'!G9
A80: 2 | B80: ='处置子公司测试表（不包含一揽子交易）G7-11'!B10 | C80: ='处置子公司测试表（不包含一揽子交易）G7-11'!C10 | D80: ='处置子公司测试表（不包含一揽子交易）G7-11'!D10 | E80: ='处置子公司测试表（不包含一揽子交易）G7-11'!E10 | F80: ='处置子公司测试表（不包含一揽子交易）G7-11'!F10 | G80: ='处置子公司测试表（不包含一揽子交易）G7-11'!G10
A81: 3 | B81: ='处置子公司测试表（不包含一揽子交易）G7-11'!B11 | C81: ='处置子公司测试表（不包含一揽子交易）G7-11'!C11 | D81: ='处置子公司测试表（不包含一揽子交易）G7-11'!D11 | E81: ='处置子公司测试表（不包含一揽子交易）G7-11'!E11 | F81: ='处置子公司测试表（不包含一揽子交易）G7-11'!F11 | G81: ='处置子公司测试表（不包含一揽子交易）G7-11'!G11
A82: 4 | B82: ='处置子公司测试表（不包含一揽子交易）G7-11'!B12 | C82: ='处置子公司测试表（不包含一揽子交易）G7-11'!C12 | D82: ='处置子公司测试表（不包含一揽子交易）G7-11'!D12 | E82: ='处置子公司测试表（不包含一揽子交易）G7-11'!E12 | F82: ='处置子公司测试表（不包含一揽子交易）G7-11'!F12 | G82: ='处置子公司测试表（不包含一揽子交易）G7-11'!G12
A83: 5 | B83: ='处置子公司测试表（不包含一揽子交易）G7-11'!B13 | C83: ='处置子公司测试表（不包含一揽子交易）G7-11'!C13 | D83: ='处置子公司测试表（不包含一揽子交易）G7-11'!D13 | E83: ='处置子公司测试表（不包含一揽子交易）G7-11'!E13 | F83: ='处置子公司测试表（不包含一揽子交易）G7-11'!F13 | G83: ='处置子公司测试表（不包含一揽子交易）G7-11'!G13
A85: （2）本期出售的子公司出售日的财务状况
A86: （说明出售日的确定方法）
A87: 公司名称 | C87: 公司1 | E87: 公司2
A88: 截止日期 | C88: 出售日 | D88: 期初余额 | E88: 出售日 | F88: 期初余额
A89: 流动资产
A90: 长期股权投资
A91: 固定资产
A92: 无形资产
A93: 其他非流动资产
A94: 流动负债
A95: 非流动负债
A96: 所有者权益
A97: （3）本期出售的子公司出售日的经营成果
A98: 公司名称 | C98: A公司 | E98: B公司 | G98: C公司 | I98: D公司 | K98: E公司
A99: 期间 | C99: 本年年初-出售日 | D99: 上年发生额 | E99: 本年年初-出售日 | F99: 上年发生额 | G99: 本年年初-出售日 | H99: 上年发生额 | I99: 本年年初-出售日 | J99: 上年发生额 | K99: 本年年初-出售日 | L99: 上年发生额
A100: 营业收入
A101: 营业成本
A102: 期间费用
A103: 营业利润
A104: 利润总额
A105: 所得税费用
A106: 净利润
A107: 【提示：本期因处置部分股权投资或其他原因丧失了对原有子公司控制权的，对于处置后的剩余股权，还应按照《企业会计准则解释第4号》的规定，在附注中披露处置后的剩余股权在丧失控制权日的公允价值、按照公允价值重新计量产生的相关利得或损失的金额，具体披露格式请参考本所“股份公司年审报告模板”】
...

Sheet 明细表G7-2
A1: 致同会计师事务所 | V1: 致同会计师事务所 | AN1: 致同会计师事务所
A2: 长期股权投资明细表 | V2: 长期股权投资明细表 | AN2: 长期股权投资明细表
A3: =底稿目录!A2 | C3: =底稿目录!A4 | E3: =底稿目录!A5 | I3: 索引号： | J3: =底稿目录!F8 | L3: =A3 | P3: =C3 | R3: =E3 | T3: =I3 | U3: =J3 | V3: =底稿目录!A2 | AA3: =底稿目录!A4 | AE3: =底稿目录!A5 | AL3: 索引号： | AM3: =底稿目录!F8 | AN3: =底稿目录!A2 | AS3: =底稿目录!A4 | AX3: =底稿目录!A5 | BA3: 索引号： | BB3: =底稿目录!F8
A4: =底稿目录!A3 | C4: =底稿目录!A6 | E4: =底稿目录!A7 | I4: 页 次： | L4: =A4 | P4: =C4 | R4: =E4 | T4: =I4 | U4: =J4 | V4: =底稿目录!A3 | AA4: =底稿目录!A6 | AE4: =底稿目录!A7 | AL4: 页次： | AN4: =底稿目录!A3 | AS4: =底稿目录!A6 | AX4: =底稿目录!A7 | BA4: 页次：
A5: 一、审计目标： | L5: =A5 | V5: =L5 | AN5: =V5
A6: 1.资产负债表中记录的长期股权投资是存在的，且已经记录在恰当的账户中； | L6: 1.资产负债表中记录的长期股权投资是存在的，且已经记录在恰当的账户中； | V6: =L6 | AN6: =V6
A7: 2.所有应记录的长期股权投资均已记录，所有应当包括在财务报表中的相关披露均已包括； | L7: 2.所有应记录的长期股权投资均已记录，所有应当包括在财务报表中的相关披露均已包括； | V7: =L7 | AN7: =V7
A8: 3.长期股权投资以恰当的金额包括在财务报表中，与之相关的计价或分摊调整已恰当记录，相关披露已得到恰当计量和描述； | L8: 3.长期股权投资以恰当的金额包括在财务报表中，与之相关的计价或分摊调整已恰当记录，相关披露已得到恰当计量和描述； | V8: =L8 | AN8: =V8
A9: 4.记录的长期股权投资由被审计单位拥有或控制 | L9: 4.记录的长期股权投资由被审计单位拥有或控制 | V9: =L9 | AN9: =V9
A10: 二、审计过程 | L10: =A10 | V10: =L10 | AN10: =V10
A11: 提示：与被审计单位人员讨论确定是否存在被投资单位由于所在国家和地区及其他方面的影响，其向被审计单位转移资金的能力受到限制的情况，如存在，应详细记录受限情况，并提请被审计单位充分披露 | L11: =A11 | V11: =L11 | AN11: =V11
A12: （一）按成本法核算的长期股权投资 | L12: （一）按成本法核算的长期股权投资 | V12: （一）按成本法核算的长期股权投资
A13: 序号 | B13: 被投资单位名称 | F13: 初始投资成本 | H13: 投资比例 | I13: 投资时间 | J13: 投资方式 | K13: 本期现金红利 | L13: 未审数 | V13: 期初调整 | X13: 账项调整 | Z13: 重分类调整 | AB13: 审定数
L14: 期初余额 | N14: 本期增加 | Q14: 本期减少 | T14: 期末余额 | V14: 账项调整 | W14: 重分类调整 | X14: 本期增加 | Y14: 本期减少 | Z14: 本期增加 | AA14: 本期减少 | AB14: 期初余额 | AD14: 本期增加 | AF14: 本期减少 | AH14: 期末余额
L15: 投资比例 | M15: 金额 | N15: 投资比例 | O15: 金额 | P15: 索引号 | Q15: 投资比例 | R15: 金额 | S15: 索引号 | T15: 投资比例 | U15: 金额 | AB15: 投资比例 | AC15: 金额 | AD15: 投资比例 | AE15: 金额 | AF15: 投资比例 | AG15: 金额 | AH15: 投资比例 | AI15: 金额
A16: 1 | T16: =L16+N16-Q16 | U16: =M16+O16-R16 | AB16: =L16 | AC16: =M16+V16+W16 | AD16: =N16 | AE16: =O16+X16+Z16 | AF16: =Q16 | AG16: =R16+Y16+AA16 | AH16: =AB16+AD16-AF16 | AI16: =AC16+AE16-AG16
A17: 2 | T17: =L17+N17-Q17 | U17: =M17+O17-R17 | AB17: =L17 | AC17: =M17+V17+W17 | AD17: =N17 | AE17: =O17+X17+Z17 | AF17: =Q17 | AG17: =R17+Y17+AA17 | AH17: =AB17+AD17-AF17 | AI17: =AC17+AE17-AG17
A18: 3 | T18: =L18+N18-Q18 | U18: =M18+O18-R18 | AB18: =L18 | AC18: =M18+V18+W18 | AD18: =N18 | AE18: =O18+X18+Z18 | AF18: =Q18 | AG18: =R18+Y18+AA18 | AH18: =AB18+AD18-AF18 | AI18: =AC18+AE18-AG18
A19: 4 | T19: =L19+N19-Q19 | U19: =M19+O19-R19 | AB19: =L19 | AC19: =M19+V19+W19 | AD19: =N19 | AE19: =O19+X19+Z19 | AF19: =Q19 | AG19: =R19+Y19+AA19 | AH19: =AB19+AD19-AF19 | AI19: =AC19+AE19-AG19
A20: 5 | T20: =L20+N20-Q20 | U20: =M20+O20-R20 | AB20: =L20 | AC20: =M20+V20+W20 | AD20: =N20 | AE20: =O20+X20+Z20 | AF20: =Q20 | AG20: =R20+Y20+AA20 | AH20: =AB20+AD20-AF20 | AI20: =AC20+AE20-AG20
A21: 6 | T21: =L21+N21-Q21 | U21: =M21+O21-R21 | AB21: =L21 | AC21: =M21+V21+W21 | AD21: =N21 | AE21: =O21+X21+Z21 | AF21: =Q21 | AG21: =R21+Y21+AA21 | AH21: =AB21+AD21-AF21 | AI21: =AC21+AE21-AG21
A22: 7 | T22: =L22+N22-Q22 | U22: =M22+O22-R22 | AB22: =L22 | AC22: =M22+V22+W22 | AD22: =N22 | AE22: =O22+X22+Z22 | AF22: =Q22 | AG22: =R22+Y22+AA22 | AH22: =AB22+AD22-AF22 | AI22: =AC22+AE22-AG22
A23: 8 | T23: =L23+N23-Q23 | U23: =M23+O23-R23 | AB23: =L23 | AC23: =M23+V23+W23 | AD23: =N23 | AE23: =O23+X23+Z23 | AF23: =Q23 | AG23: =R23+Y23+AA23 | AH23: =AB23+AD23-AF23 | AI23: =AC23+AE23-AG23
A24: 9 | T24: =L24+N24-Q24 | U24: =M24+O24-R24 | AB24: =L24 | AC24: =M24+V24+W24 | AD24: =N24 | AE24: =O24+X24+Z24 | AF24: =Q24 | AG24: =R24+Y24+AA24 | AH24: =AB24+AD24-AF24 | AI24: =AC24+AE24-AG24
A25: 10 | B25: …… | T25: =L25+N25-Q25 | U25: =M25+O25-R25 | AB25: =L25 | AC25: =M25+V25+W25 | AD25: =N25 | AE25: =O25+X25+Z25 | AF25: =Q25 | AG25: =R25+Y25+AA25 | AH25: =AB25+AD25-AF25 | AI25: =AC25+AE25-AG25
A26: 成本法小计 | G26: =SUM(G16:G25) | H26: -- | I26: -- | J26: -- | K26: =SUM(K16:K25) | L26: -- | M26: =SUM(M16:M25) | N26: -- | O26: =SUM(O16:O25) | P26: -- | Q26: -- | R26: =SUM(R16:R25) | S26: -- | T26: -- | U26: =SUM(U16:U25) | V26: =SUM(V16:V25) | W26: =SUM(W16:W25) | X26: =SUM(X16:X25) | Y26: =SUM(Y16:Y25) | Z26: =SUM(Z16:Z25) | AA26: =SUM(AA16:AA25) | AB26: -- | AC26: =SUM(AC16:AC25) | AD26: -- | AE26: =SUM(AE16:AE25) | AF26: -- | AG26: =SUM(AG16:AG25) | AH26: -- | AI26: =SUM(AI16:AI25)
A27: （二）按权益法核算的长期股权投资 | V27: （二）按权益法核算的长期股权投资 | AN27: （二）按权益法核算的长期股权投资
A28: 序号 | B28: 被投资单位名称 | C28: 初始投资成本 | D28: 投资比例 | E28: 投资时间 | F28: 投资方式 | G28: 未审数 | V28: 期初调整 | X28: 账项调整 | AF28: 重分类调整 | AN28: 审定数
G29: 期初余额 | I29: 本期增加 | P29: 本期减少 | T29: 期末余额 | V29: 账项调整 | W29: 重分类调整 | X29: 本期增加 | AC29: 本期减少 | AF29: 本期增加 | AK29: 本期减少 | AN29: 期初余额 | AP29: 本期增加 | AW29: 本期减少 | BA29: 期末余额
G30: 投资比例 | H30: 金额 | I30: 投资比例 | J30: 投资成本增加 | K30: 权益增加 | O30: 其他 | P30: 投资比例 | Q30: 投资成本减少 | R30: 本期分回利润 | S30: 其他 | T30: 投资比例 | U30: 金额 | X30: 投资成本增加 | Y30: 权益增加 | AB30: 其他 | AC30: 投资成本减少 | AD30: 本期分回利润 | AE30: 其他 | AF30: 投资成本增加 | AG30: 权益增加 | AJ30: 其他 | AK30: 投资成本减少 | AL30: 本期分回利润 | AM30: 其他 | AN30: 投资比例 | AO30: 金额 | AP30: 投资比例 | AQ30: 投资成本增加 | AR30: 权益增加 | AV30: 其他 | AW30: 投资比例 | AX30: 投资成本减少 | AY30: 本期分回利润 | AZ30: 其他 | BA30: 投资比例 | BB30: 金额
K31: 损益调整 | L31: 其他综合收益 | M31: 其他权益变动 | N31: 权益增加小计 | Y31: 损益调整 | Z31: 其他综合收益 | AA31: 其他权益变动 | AG31: 损益调整 | AH31: 其他综合收益 | AI31: 其他权益变动 | AR31: 损益调整 | AS31: 其他综合收益 | AT31: 其他权益变动 | AU31: 权益增加小计
A32: 合营企业：
A33: 1 | N33: =SUM(K33:M33) | T33: =G33+I33-P33 | U33: =H33+J33+N33-Q33-R33+O33-S33 | AN33: =G33 | AO33: =H33+V33+W33 | AP33: =I33 | AQ33: =J33+X33+AF33 | AR33: =K33+Y33+AG33 | AS33: =L33+Z33+AH33 | AT33: =M33+AA33+AI33 | AU33: =SUM(AR33:AT33) | AV33: =O33+AB33+AJ33 | AW33: =P33 | AX33: =Q33+AC33+AK33 | AY33: =R33+AD33+AL33 | AZ33: =S33+AE33+AM33 | BA33: =AN33+AP33-AW33 | BB33: =AO33+AQ33+AU33-AX33-AY33
A34: 2 | N34: =SUM(K34:M34) | T34: =G34+I34-P34 | U34: =H34+J34+N34-Q34-R34+O34-S34 | AN34: =G34 | AO34: =H34+V34+W34 | AP34: =I34 | AQ34: =J34+X34+AF34 | AR34: =K34+Y34+AG34 | AS34: =L34+Z34+AH34 | AT34: =M34+AA34+AI34 | AU34: =SUM(AR34:AT34) | AV34: =O34+AB34+AJ34 | AW34: =P34 | AX34: =Q34+AC34+AK34 | AY34: =R34+AD34+AL34 | AZ34: =S34+AE34+AM34 | BA34: =AN34+AP34-AW34 | BB34: =AO34+AQ34+AU34-AX34-AY34
A35: 3 | N35: =SUM(K35:M35) | T35: =G35+I35-P35 | U35: =H35+J35+N35-Q35-R35+O35-S35 | AN35: =G35 | AO35: =H35+V35+W35 | AP35: =I35 | AQ35: =J35+X35+AF35 | AR35: =K35+Y35+AG35 | AS35: =L35+Z35+AH35 | AT35: =M35+AA35+AI35 | AU35: =SUM(AR35:AT35) | AV35: =O35+AB35+AJ35 | AW35: =P35 | AX35: =Q35+AC35+AK35 | AY35: =R35+AD35+AL35 | AZ35: =S35+AE35+AM35 | BA35: =AN35+AP35-AW35 | BB35: =AO35+AQ35+AU35-AX35-AY35
A36: 4 | N36: =SUM(K36:M36) | T36: =G36+I36-P36 | U36: =H36+J36+N36-Q36-R36+O36-S36 | AN36: =G36 | AO36: =H36+V36+W36 | AP36: =I36 | AQ36: =J36+X36+AF36 | AR36: =K36+Y36+AG36 | AS36: =L36+Z36+AH36 | AT36: =M36+AA36+AI36 | AU36: =SUM(AR36:AT36) | AV36: =O36+AB36+AJ36 | AW36: =P36 | AX36: =Q36+AC36+AK36 | AY36: =R36+AD36+AL36 | AZ36: =S36+AE36+AM36 | BA36: =AN36+AP36-AW36 | BB36: =AO36+AQ36+AU36-AX36-AY36
A37: 5 | B37: …… | N37: =SUM(K37:M37) | T37: =G37+I37-P37 | U37: =H37+J37+N37-Q37-R37+O37-S37 | AN37: =G37 | AO37: =H37+V37+W37 | AP37: =I37 | AQ37: =J37+X37+AF37 | AR37: =K37+Y37+AG37 | AS37: =L37+Z37+AH37 | AT37: =M37+AA37+AI37 | AU37: =SUM(AR37:AT37) | AV37: =O37+AB37+AJ37 | AW37: =P37 | AX37: =Q37+AC37+AK37 | AY37: =R37+AD37+AL37 | AZ37: =S37+AE37+AM37 | BA37: =AN37+AP37-AW37 | BB37: =AO37+AQ37+AU37-AX37-AY37
A38: 小计 | G38: -- | H38: =SUM(H33:H37) | I38: -- | J38: =SUM(J33:J37) | K38: =SUM(K33:K37) | L38: =SUM(L33:L37) | M38: =SUM(M33:M37) | N38: =SUM(K38:M38) | O38: =SUM(O33:O37) | P38: =SUM(P33:P37) | Q38: =SUM(Q33:Q37) | R38: =SUM(R33:R37) | T38: -- | U38: =SUM(U33:U37) | V38: =SUM(V33:V37) | W38: =SUM(W33:W37) | X38: =SUM(X33:X37) | Y38: =SUM(Y33:Y37) | Z38: =SUM(Z33:Z37) | AA38: =SUM(AA33:AA37) | AB38: =SUM(AB33:AB37) | ... AM38: =SUM(AM33:AM37) | AN38: -- | AO38: =SUM(AO33:AO37) | AP38: -- | AQ38: =SUM(AQ33:AQ37) | AR38: =SUM(AR33:AR37) | AS38: =SUM(AS33:AS37) | AT38: =SUM(AT33:AT37) | AU38: =SUM(AU33:AU37) | AV38: =SUM(AV33:AV37) | AW38: -- | AX38: =SUM(AX33:AX37) | AY38: =SUM(AY33:AY37) | AZ38: =SUM(AZ33:AZ37) | BA38: -- | BB38: =SUM(BB33:BB37)
A39: 联营企业：
A40: 1 | N40: =SUM(K40:M40) | T40: =G40+I40-P40 | U40: =H40+J40+N40-Q40-R40+O40-S40 | AN40: =G40 | AO40: =H40+V40+W40 | AP40: =I40 | AQ40: =J40+X40+AF40 | AR40: =K40+Y40+AG40 | AS40: =L40+Z40+AH40 | AT40: =M40+AA40+AI40 | AU40: =SUM(AR40:AT40) | AV40: =O40+AB40+AJ40 | AW40: =P40 | AX40: =Q40+AC40+AK40 | AY40: =R40+AD40+AL40 | AZ40: =S40+AE40+AM40 | BA40: =AN40+AP40-AW40 | BB40: =AO40+AQ40+AU40-AX40-AY40
A41: 2 | N41: =SUM(K41:M41) | T41: =G41+I41-P41 | U41: =H41+J41+N41-Q41-R41 | AN41: =G41 | AO41: =H41+V41+W41 | AP41: =I41 | AQ41: =J41+X41+AF41 | AR41: =K41+Y41+AG41 | AS41: =L41+Z41+AH41 | AT41: =M41+AA41+AI41 | AU41: =SUM(AR41:AT41) | AV41: =O41+AB41+AJ41 | AW41: =P41 | AX41: =Q41+AC41+AK41 | AY41: =R41+AD41+AL41 | AZ41: =S41+AE41+AM41 | BA41: =AN41+AP41-AW41 | BB41: =AO41+AQ41+AU41-AX41-AY41
A42: 3 | N42: =SUM(K42:M42) | T42: =G42+I42-P42 | U42: =H42+J42+N42-Q42-R42 | AN42: =G42 | AO42: =H42+V42+W42 | AP42: =I42 | AQ42: =J42+X42+AF42 | AR42: =K42+Y42+AG42 | AS42: =L42+Z42+AH42 | AT42: =M42+AA42+AI42 | AU42: =SUM(AR42:AT42) | AV42: =O42+AB42+AJ42 | AW42: =P42 | AX42: =Q42+AC42+AK42 | AY42: =R42+AD42+AL42 | AZ42: =S42+AE42+AM42 | BA42: =AN42+AP42-AW42 | BB42: =AO42+AQ42+AU42-AX42-AY42
A43: 4 | N43: =SUM(K43:M43) | T43: =G43+I43-P43 | U43: =H43+J43+N43-Q43-R43 | AN43: =G43 | AO43: =H43+V43+W43 | AP43: =I43 | AQ43: =J43+X43+AF43 | AR43: =K43+Y43+AG43 | AS43: =L43+Z43+AH43 | AT43: =M43+AA43+AI43 | AU43: =SUM(AR43:AT43) | AV43: =O43+AB43+AJ43 | AW43: =P43 | AX43: =Q43+AC43+AK43 | AY43: =R43+AD43+AL43 | AZ43: =S43+AE43+AM43 | BA43: =AN43+AP43-AW43 | BB43: =AO43+AQ43+AU43-AX43-AY43
A44: 5 | B44: …… | N44: =SUM(K44:M44) | T44: =G44+I44-P44 | U44: =H44+J44+N44-Q44-R44 | AN44: =G44 | AO44: =H44+V44+W44 | AP44: =I44 | AQ44: =J44+X44+AF44 | AR44: =K44+Y44+AG44 | AS44: =L44+Z44+AH44 | AT44: =M44+AA44+AI44 | AU44: =SUM(AR44:AT44) | AV44: =O44+AB44+AJ44 | AW44: =P44 | AX44: =Q44+AC44+AK44 | AY44: =R44+AD44+AL44 | AZ44: =S44+AE44+AM44 | BA44: =AN44+AP44-AW44 | BB44: =AO44+AQ44+AU44-AX44-AY44
A45: 小计 | G45: -- | H45: =SUM(H40:H44) | I45: -- | J45: =SUM(J40:J44) | K45: =SUM(K40:K44) | L45: =SUM(L40:L44) | M45: =SUM(M40:M44) | N45: =SUM(K45:M45) | O45: =SUM(O40:O44) | P45: =SUM(P40:P44) | Q45: =SUM(Q40:Q44) | R45: =SUM(R40:R44) | S45: =SUM(S40:S44) | T45: -- | U45: =H45+J45+N45-Q45-R45+O45-S45 | V45: =SUM(V40:V44) | W45: =SUM(W40:W44) | X45: =SUM(X40:X44) | Y45: =SUM(Y40:Y44) | Z45: =SUM(Z40:Z44) | AA45: =SUM(AA40:AA44) | AB45: =SUM(AB40:AB44) | AC45: =SUM(AC40:AC44) | ... AM45: =SUM(AM40:AM44) | AN45: -- | AO45: =SUM(AO40:AO44) | AP45: -- | AQ45: =SUM(AQ40:AQ44) | AR45: =SUM(AR40:AR44) | AS45: =SUM(AS40:AS44) | AT45: =SUM(AT40:AT44) | AU45: =SUM(AU40:AU44) | AV45: =SUM(AV40:AV44) | AW45: -- | AX45: =SUM(AX40:AX44) | AY45: =SUM(AY40:AY44) | AZ45: =S45+AE45+AM45 | BA45: -- | BB45: =SUM(BB40:BB44)
A46: 权益法小计 | C46: =SUM(C33:C44) | D46: -- | E46: -- | F46: -- | G46: -- | H46: =H45+H38 | I46: -- | J46: =J38+J45 | K46: =K38+K45 | L46: =L38+L45 | M46: =M38+M45 | N46: =N38+N45 | O46: =O38+O45 | P46: -- | Q46: =Q38+Q45 | R46: =R38+R45 | S46: =S38+S45 | T46: -- | U46: =U38+U45 | V46: =SUM(V33:V44) | W46: =SUM(W33:W44) | X46: =SUM(X33:X44) | Y46: =SUM(Y33:Y44) | AA46: =SUM(AA33:AA44) | AB46: =SUM(AB33:AB44) | AC46: =SUM(AC33:AC44) | AD46: =SUM(AD33:AD44) | AE46: =SUM(AE33:AE44) | AF46: =SUM(AF33:AF44) | AG46: =SUM(AG33:AG44) | AH46: =SUM(AH33:AH44) | ... AM46: =SUM(AM33:AM44) | AN46: -- | AO46: =SUM(AO33:AO44) | AP46: =SUM(AP33:AP44) | AQ46: =SUM(AQ33:AQ44) | AR46: =SUM(AR33:AR44) | AS46: =SUM(AS33:AS44) | AT46: =SUM(AT33:AT44) | AU46: =SUM(AU33:AU44) | AV46: =SUM(AV33:AV44) | AW46: -- | AX46: =SUM(AX33:AX44) | AY46: =SUM(AY33:AY44) | AZ46: =SUM(AZ33:AZ44) | BB46: =SUM(BB33:BB44)
A47: 长期股权投资合计 | C47: -- | D47: -- | E47: -- | F47: -- | G47: -- | H47: =M26+H46 | I47: -- | J47: =J46+O26 | K47: =K46 | L47: =L46 | M47: =M46 | N47: =N46 | O47: =O46 | P47: -- | U47: =SUM(U26,U46) | V47: =V26+V46 | W47: =W26+W46 | X47: =X26+X46 | Y47: =Y46 | Z47: =Z46 | AA47: =AA46 | AC47: =AC46+Y26 | AD47: =AD46 | AE47: =AE46 | AF47: =Z26+AF46 | AG47: =AG46 | AH47: =AH46 | AI47: =AI46 | AJ47: =AJ46 | AK47: =AK46+AA26 | AL47: =AL46 | AM47: =AM46 | AN47: -- | AO47: =AO46+AC26 | AP47: -- | AQ47: =AQ46+AE26 | AR47: =AR46 | AS47: =AS46 | AT47: =AT46 | AU47: =AU46 | AV47: =AV46 | AW47: -- | AX47: =AX46+AG26 | AY47: =AY46 | AZ47: =AZ46 | BA47: -- | BB47: =BB46+AI26
A48: （三）长期股权投资减值准备 | T48: （三）长期股权投资减值准备
A49: 序号 | B49: 被投资单位名称 | C49: 初始投资成本 | D49: 投资比例 | E49: 投资时间 | F49: 投资方式 | G49: 未审数 | L49: 期初调整 | N49: 账项调整 | P49: 重分类调整 | R49: 审定数
G50: 期初余额 | H50: 本期增加 | I50: 本期减少 | J50: 期末余额 | K50: 备注 | L50: 账项调整 | M50: 重分类调整 | N50: 本期增加 | O50: 本期减少 | P50: 本期增加 | Q50: 本期减少 | R50: 期初余额 | S50: 本期增加 | T50: 本期减少 | U50: 期末余额
A52: 按成本法核算的长期股权投资
A53: 1 | B53: =B16 | J53: =G53+H53-I53 | R53: =G53+L53+M53 | S53: =H53+N53+P53 | T53: =I53+O53+Q53 | U53: =R53+S53-T53
A54: 2 | B54: =B17 | J54: =G54+H54-I54 | R54: =G54+L54+M54 | S54: =H54+N54+P54 | T54: =I54+O54+Q54 | U54: =R54+S54-T54
A55: 3 | B55: =B18 | J55: =G55+H55-I55 | R55: =G55+L55+M55 | S55: =H55+N55+P55 | T55: =I55+O55+Q55 | U55: =R55+S55-T55
A56: 4 | B56: =B19 | J56: =G56+H56-I56 | R56: =G56+L56+M56 | S56: =H56+N56+P56 | T56: =I56+O56+Q56 | U56: =R56+S56-T56
A57: 5 | B57: =B20 | J57: =G57+H57-I57 | R57: =G57+L57+M57 | S57: =H57+N57+P57 | T57: =I57+O57+Q57 | U57: =R57+S57-T57
A58: 6 | B58: =B21 | J58: =G58+H58-I58 | R58: =G58+L58+M58 | S58: =H58+N58+P58 | T58: =I58+O58+Q58 | U58: =R58+S58-T58
A59: 7 | B59: =B22 | J59: =G59+H59-I59 | R59: =G59+L59+M59 | S59: =H59+N59+P59 | T59: =I59+O59+Q59 | U59: =R59+S59-T59
A60: 8 | B60: =B23 | J60: =G60+H60-I60 | R60: =G60+L60+M60 | S60: =H60+N60+P60 | T60: =I60+O60+Q60 | U60: =R60+S60-T60
A61: 9 | B61: =B24 | J61: =G61+H61-I61 | R61: =G61+L61+M61 | S61: =H61+N61+P61 | T61: =I61+O61+Q61 | U61: =R61+S61-T61
A62: 10 | B62: =B25 | J62: =G62+H62-I62 | R62: =G62+L62+M62 | S62: =H62+N62+P62 | T62: =I62+O62+Q62 | U62: =R62+S62-T62
A63: 按成本法核算的长期股权投资小计 | C63: -- | D63: -- | E63: -- | F63: -- | G63: =SUM(G53:G62) | H63: =SUM(H53:H62) | I63: =SUM(I53:I62) | J63: =SUM(J53:J62) | K63: -- | L63: =SUM(L53:L62) | M63: =SUM(M53:M62) | N63: =SUM(N53:N62) | O63: =SUM(O53:O62) | P63: =SUM(P53:P62) | Q63: =SUM(Q53:Q62) | R63: =SUM(R53:R62) | S63: =SUM(S53:S62) | ... U63: =SUM(U53:U62)
A64: 按权益法核算的长期股权投资 | J64: -- | R64: =G64+L64+M64 | S64: =H64+N64+P64 | T64: =I64+O64+Q64 | U64: =R64+S64-T64
A65: ——合营企业： | J65: --
A66: 1 | B66: =B33 | J66: =G66+H66-I66 | R66: =G66+L66+M66 | S66: =H66+N66+P66 | T66: =I66+O66+Q66 | U66: =R66+S66-T66
A67: 2 | B67: =B34 | J67: =G67+H67-I67 | R67: =G67+L67+M67 | S67: =H67+N67+P67 | T67: =I67+O67+Q67 | U67: =R67+S67-T67
A68: 3 | B68: =B35 | J68: =G68+H68-I68 | R68: =G68+L68+M68 | S68: =H68+N68+P68 | T68: =I68+O68+Q68 | U68: =R68+S68-T68
A69: 4 | B69: =B36 | J69: =G69+H69-I69 | R69: =G69+L69+M69 | S69: =H69+N69+P69 | T69: =I69+O69+Q69 | U69: =R69+S69-T69
A70: 5 | B70: =B37 | J70: =G70+H70-I70 | R70: =G70+L70+M70 | S70: =H70+N70+P70 | T70: =I70+O70+Q70 | U70: =R70+S70-T70
A71: 合营企业小计 | C71: -- | D71: -- | E71: -- | F71: -- | G71: =SUM(G66:G70) | H71: =SUM(H66:H70) | I71: =SUM(I66:I70) | J71: =SUM(J66:J70) | K71: -- | L71: =SUM(L66:L70) | M71: =SUM(M66:M70) | N71: =SUM(N66:N70) | O71: =SUM(O66:O70) | P71: =SUM(P66:P70) | Q71: =SUM(Q66:Q70) | R71: =SUM(R66:R70) | S71: =SUM(S66:S70) | ... U71: =SUM(U66:U70)
A72: ——联营企业 | J72: --
A73: 1 | B73: =B40 | J73: =G73+H73-I73 | R73: =G73+L73+M73 | S73: =H73+N73+P73 | T73: =I73+O73+Q73 | U73: =R73+S73-T73
A74: 2 | B74: =B41 | J74: =G74+H74-I74 | R74: =G74+L74+M74 | S74: =H74+N74+P74 | T74: =I74+O74+Q74 | U74: =R74+S74-T74
A75: 3 | B75: =B42 | J75: =G75+H75-I75 | R75: =G75+L75+M75 | S75: =H75+N75+P75 | T75: =I75+O75+Q75 | U75: =R75+S75-T75
A76: 4 | B76: =B43 | J76: =G76+H76-I76 | R76: =G76+L76+M76 | S76: =H76+N76+P76 | T76: =I76+O76+Q76 | U76: =R76+S76-T76
A77: 5 | B77: =B44 | J77: =G77+H77-I77 | R77: =G77+L77+M77 | S77: =H77+N77+P77 | T77: =I77+O77+Q77 | U77: =R77+S77-T77
A78: 联营企业小计 | C78: -- | D78: -- | E78: -- | F78: -- | G78: =SUM(G73:G77) | H78: =SUM(H73:H77) | I78: =SUM(I73:I77) | J78: =SUM(J73:J77) | K78: -- | L78: =SUM(L73:L77) | M78: =SUM(M73:M77) | N78: =SUM(N73:N77) | O78: =SUM(O73:O77) | P78: =SUM(P73:P77) | Q78: =SUM(Q73:Q77) | R78: =SUM(R73:R77) | S78: =SUM(S73:S77) | ... U78: =SUM(U73:U77)
A79: 按权益法核算的长期股权投资小计 | C79: -- | D79: -- | E79: -- | F79: -- | G79: =G71+G78 | H79: =H71+H78 | I79: =I71+I78 | J79: =J71+J78 | K79: -- | L79: =L71+L78 | M79: =M71+M78 | N79: =N71+N78 | O79: =O71+O78 | P79: =P71+P78 | Q79: =Q71+Q78 | R79: =G79+L79+M79 | S79: =H79+N79+P79 | T79: =I79+O79+Q79 | U79: =R79+S79-T79
A80: 减值准备合计 | C80: -- | D80: -- | E80: -- | F80: -- | G80: =G63+G79 | H80: =H63+H79 | I80: =I63+I79 | J80: =SUM(J53:J79) | K80: -- | L80: =L63+L79 | M80: =M63+M79 | N80: =N63+N79 | O80: =O63+O79 | P80: =P63+P79 | Q80: =Q63+Q79 | R80: =G80+L80+M80 | S80: =H80+N80+P80 | T80: =I80+O80+Q80 | U80: =R80+S80-T80
A81: 长期股权投资净值合计 | C81: -- | D81: -- | E81: -- | F81: -- | G81: =H47-G80 | H81: -- | I81: -- | J81: =U47-J80 | K81: -- | L81: -- | M81: -- | N81: -- | O81: -- | P81: -- | Q81: -- | R81: =AO47-R80 | S81: -- | T81: -- | U81: =BB47-U80
A82: 三、审计说明：
A83: 1、 | B83: 长期股权投资存在所有权限制、承诺或留置的情况如下：
A86: 四、审计结论：
A91: 编制说明：
B92: 1、投资方式指现金出资、发行权益性证券、投资者投入、非货币性资产交换、债务重组、企业合并等。
B93: 2、投资文件指产权登记表、投资协议、出资证明、验资报告等。
B94: 3、备注可填写本年新增加、处置投资是否有授权批准、投资文件索引号或其他说明事项。
B95: 4、根据《中国注册会计师审计准则问题解答第18号——识别和应对第三方配合实施财务舞弊》：当期存在大额对外投资时，需考虑是否存在通过被审计单位将资金投入被投资单位，
B96: 再从被投资单位套取资金（如投资私募基金后，在私募基金配合下将投资款从私募基金转出），如果还识别出被审计单位存在可能导致关联方资金占用以及其他套取资金行为的舞弊风险因素，则很可能表面存在第三方配合舞弊，应采取恰当的措施应对。
B97: 5、审计说明可以概述:(1)程序的测试情况、结果;(2)拟调整事项及其调整分录、未调整事项及其影响，审计范围受到限制情况及其影响。
B98: 6、审计结论可参考:A、未见异常。 B、除上述重大不符事项应当作为调整事项予以调整外，其余未见异常。由于存在以下重大未调整事项(或审计范围受到限制无法获取充分、适当证据)，不可确认。

Sheet 调整分录汇总G7-3
A1: 致同会计师事务所
A2: 长期股权投资调整分录汇总表
A3: =底稿目录!A2 | D3: =底稿目录!A4 | G3: =底稿目录!A5 | I3: 索引号： | J3: =底稿目录!F9
A4: =底稿目录!A3 | D4: =底稿目录!A6 | G4: =底稿目录!A7 | I4: 页 次：
A5: 调整事项说明 | B5: 类别（报表调整/账项调整/其他） | C5: 报表项目 | D5: 科目名称 | E5: 附注项目 | F5: …… | G5: 借方调整金额 | H5: 贷方调整金额 | I5: 索引 | J5: 备注

Sheet 被投资单位基本信息G7-4
A1: 致同会计师事务所
A2: 被投资单位基本信息
A3: =底稿目录!A2 | F3: =底稿目录!A4 | M3: =底稿目录!A5 | S3: 索引号： | T3: =底稿目录!F10
A4: =底稿目录!A3 | F4: =底稿目录!A6 | M4: =底稿目录!A7 | S4: 页 次：
A5: 一、审计目标： | C5: 了解被审计单位投资公司的基本情况
A6: 二、审计过程 | C6: 1、取得被审计单位投资单位备查明细簿，了解投资单位的基本情况；
C7: 2、结合以前年度审计情况，了解被审计单位对各投资单位的核算方法。
C8: 3、结合“子公司初始计量测试”底稿，了解表决权比例不足半数但能对被投资单位形成控制的原因及直接或通过其他子公司间接拥有被投资单位半数以上的表决权但未能对其形成控制的原因
A9: 公司名称 | C9: 级次（国企适用） | D9: 企业类型（国企适用） | E9: 是否为本期新纳入合并范围的子公司（国企适用） | F9: 主要经营地 | G9: 注册地 | H9: 业务性质 | I9: 注册资本 | J9: 投资额 | K9: 期末净资产 | L9: 本期净利润 | M9: 持股比例/享有的份额% | O9: 表决权比例 | P9: 持股比例与表决权比例不一致的原因 | Q9: 表决权比例不足半数但能对被投资单位形成控制的原因 | R9: 直接或通过其他子公司间接拥有被投资单位半数以上的表决权但未能对其形成控制的原因 | S9: 取得方式 | T9: 会计处理方法
M10: 直接 | N10: 间接
A11: （一）子公司
B12: ='明细表G7-2'!B16 | T12: 成本法
B13: ='明细表G7-2'!B17
B14: ='明细表G7-2'!B18
B15: ='明细表G7-2'!B19
B16: ='明细表G7-2'!B20
B17: ='明细表G7-2'!B21
B18: ='明细表G7-2'!B22
B19: ='明细表G7-2'!B23
B20: ='明细表G7-2'!B24
B21: ='明细表G7-2'!B25
A22: （二）合营企业（共同控制）
B23: ='明细表G7-2'!B33 | C23: -- | D23: -- | Q23: -- | T23: 权益法
B24: ='明细表G7-2'!B34 | C24: -- | D24: -- | Q24: --
B25: ='明细表G7-2'!B35 | C25: -- | D25: -- | Q25: --
B26: ='明细表G7-2'!B36 | C26: -- | D26: -- | Q26: --
B27: ='明细表G7-2'!B37 | C27: -- | D27: -- | Q27: --
A28: （三）联营企业（重大影响）
B29: ='明细表G7-2'!B40 | C29: -- | D29: -- | Q29: -- | T29: 权益法
B30: ='明细表G7-2'!B41 | C30: -- | D30: -- | Q30: --
B31: ='明细表G7-2'!B42 | C31: -- | D31: -- | Q31: --
B32: ='明细表G7-2'!B43 | C32: -- | D32: -- | Q32: --
B33: ='明细表G7-2'!B44 | C33: -- | D33: -- | Q33: --
A34: （四）共同经营（共同控制）
C35: -- | D35: -- | O35: -- | P35: -- | T35: 各项单独确认
C36: -- | D36: -- | O36: -- | P36: --
C37: -- | D37: -- | O37: -- | P37: --
C38: -- | D38: -- | O38: -- | P38: --
A39: （注：企业类型：1.境内非金融子企业，2.境内金融子企业，3.境外子企业，4.事业单位，5.基建单位；
A40: 三、审计说明：
A42: 四、审计结论：

Sheet 被投资单位财务信息（合营、联营）G7-5
B1: 致同会计师事务所
B2: 被投资单位主要财务信息（合营、联营）
A3: =底稿目录!A2 | D3: =底稿目录!A4 | F3: =底稿目录!A5 | I3: 索引号： | J3: =底稿目录!F11
A4: =底稿目录!A3 | D4: =底稿目录!A6 | F4: =底稿目录!A7 | I4: 页 次：
A5: 一、审计目标： | C5: 了解被审计单位合营、联营企业主要财务信息
A6: 二、审计过程 | C6: 取得被审计单位联营、合营企业已审计/审阅的财务报表；确定被投资单位联营、合营企业的主要财务信息
A7: 1.1重要合营、联营企业
B8: 项目 | C8: 合营企业1 | E8: 合营企业2 | G8: 联营企业1 | I8: 联营企业2
C9: 本期数 | D9: 上期数 | E9: 本期数 | F9: 上期数 | G9: 本期数 | H9: 上期数 | I9: 本期数 | J9: 上期数
B10: 流动资产
B11: 其中：现金和现金等价物
B12: 非流动资产
B13: 资产合计 | C13: =C10+C12 | D13: =D10+D12 | E13: =E10+E12 | F13: =F10+F12 | G13: =G10+G12 | H13: =H10+H12 | I13: =I10+I12 | J13: =J10+J12
B14: 流动负债
B15: 非流动负债
B16: 负债合计 | C16: =C14+C15 | D16: =D14+D15 | E16: =E14+E15 | F16: =F14+F15 | G16: =G14+G15 | H16: =H14+H15 | I16: =I14+I15 | J16: =J14+J15
B17: 净资产
B18: 其中：少数股东权益
B19: 归属于母公司的所有者权益
B20: 持股比例%
B21: 按持股比例计算的净资产份额 | C21: =C17*C20 | D21: =D17*D20 | E21: =E17*E20 | F21: =F17*F20 | G21: =G17*G20 | H21: =H17*H20 | I21: =I17*I20 | J21: =J17*J20
B22: 调整事项 | C22: =SUM(C23:C26) | D22: =SUM(D23:D26) | E22: =SUM(E23:E26) | F22: =SUM(F23:F26) | G22: =SUM(G23:G26) | H22: =SUM(H23:H26) | I22: =SUM(I23:I26) | J22: =SUM(J23:J26)
B23: 其中：商誉
B24: 未实现内部交易损益
B25: 减值准备
B26: 其他
B27: 对合营/联营企业权益投资的账面价值 | C27: =C21-C22 | D27: =D21-D22 | E27: =E21-E22 | F27: =F21-F22 | G27: =G21-G22 | H27: =H21-H22 | I27: =I21-I22 | J27: =J21-J22
B28: 存在公开报价的权益投资的公允价值
B29: 营业收入
B30: 财务费用
B31: 所得税费用
B32: 净利润
B33: 终止经营的净利润
B34: 其他综合收益
B35: 综合收益总额 | C35: =C32+C34 | D35: =D32+D34 | E35: =E32+E34 | F35: =F32+F34 | G35: =G32+G34 | H35: =H32+H34 | I35: =I32+I34 | J35: =J32+J34
B36: 企业本期收到的来自合营/联营企业的股利
B37: 前期累积未确认的损失份额
B38: 本期未确认的损失份额（或本期实现净利润的分享额）
B39: 本期末累积未确认的损失份额 | C39: =C37+C38 | D39: =D37+D38 | E39: =E37+E38 | F39: =F37+F38 | G39: =G37+G38 | H39: =H37+H38 | I39: =I37+I38 | J39: =J37+J38
A40: 1.2其他合营企业
B41: 项 目 | C41: 公司1 | D41: 公司2 | E41: 公司3 | F41: 公司4 | G41: 期末数/本期发生数 | H41: 上期数/上期发生数
B42: 投资账面价值合计 | G42: =SUM(C42:F42)
B43: 下列各项按持股比例计算的合计数 | G43: =SUM(C43:F43)
B44: 净利润 | G44: =SUM(C44:F44)
B45: 其他综合收益 | G45: =SUM(C45:F45)
B46: 综合收益总额 | G46: =SUM(C46:F46)
A47: 1.3其他联营企业
B48: 项 目 | C48: 公司1 | D48: 公司2 | E48: 公司3 | F48: 公司4 | G48: 期末数/本期发生数 | H48: 上期数/上期发生数
B49: 投资账面价值合计 | G49: =SUM(C49:F49)
B50: 下列各项按持股比例计算的合计数 | G50: =SUM(C50:F50)
B51: 净利润 | G51: =SUM(C51:F51)
B52: 其他综合收益 | G52: =SUM(C52:F52)
B53: 综合收益总额 | G53: =SUM(C53:F53)
A54: 三、审计说明：
A56: 四、审计结论：

Sheet 被投资公司会计政策G7-6
A1: 致同会计师事务所
A2: 被投资单位会计政策
A3: =底稿目录!A2 | C3: =底稿目录!A4 | D3: =底稿目录!A5 | E3: 索引号： | F3: =底稿目录!F12
A4: =底稿目录!A3 | C4: =底稿目录!A6 | D4: =底稿目录!A7 | E4: 页 次：
A5: 一、审计目标： | C5: 被投资公司会计政策与母公司主要会计政策比较，对主要会计政策差异在合并时进行调整
A6: 二、审计过程 | C6: 1、取得被投资单位会计政策，与被审计单位会计政策进行比对；
C7: 2、确定被投资单位是否需要为符合投资单位的会计政策而作出的任何必要的会计政策调整。
B8: 政策项目 | C8: AAA公司 | F8: 与本公司政策是否一致
B9: 会计年度 | C9: 1月1日-12月31日 | F9: 是
B10: 计量属性 | C10: 除公允价值套期工具外，按照历史价格计价 | F10: 是
B11: 记账本位币 | C11: 人民币 | F11: 是
B12: 外币折算 | C12: 交易发生日即期汇率折算 | F12: 是
B13: 现金及现金等价物 | C13: 随时可用于支付的流动性强、价值变动很小的投资
B14: 存货 | C14: 取得时实际成本入账、月末一次加权平均和移动加权平均法、成本与可变现净值孰低，永续盘存。 | F14: 是
B15: 长期股权投资 | F15: 是
B16: 固定资产 | C16: 使用周期超过一个会计年度的有形资产。 | F16: 是
B17: 累计折旧 | C17: 平均年限法 | F17: 是
B18: 在建工程 | C18: 达到预定可使用状态时转入固定资产，在建工程不计提折旧 | F18: 是
B19: 无形资产 | C19: 以成本减累计折旧于报表列示，直线法在预计可使用期限内摊销，土地使用权摊销按照土地证上年限摊销，无使用期限不固定的无形资产。 | F19: 是
B20: 职工薪酬 | C20: 除辞退福利外，其他计入当期负债及成本费用 | F20: 是
B21: 收入 | C21: 权责发生制 | F21: 是
B22: ……
A23: 三、审计说明
A24: 1 | B24: 主要会计政策基本相同。
B25: AAA公司为07年11月成立，其成立时被审计单位即持股30%。其主要资产为自行购建，且主要为自用，公允价值与其账面价值一致。
A29: 四、审计结论
B30: 经审计，未发现重大异常。

Sheet 长期股权投资初始判断G7-7
A1: 致同会计师事务所
A2: 长期股权投资初始判断
A3: =底稿目录!A2 | D3: =底稿目录!A4 | E3: =底稿目录!A5 | G3: 索引号： | H3: =底稿目录!F13
A4: =底稿目录!A3 | D4: =底稿目录!A6 | E4: =底稿目录!A7 | G4: 页 次：
A5: 一、审计目标： | C5: 确定被审计单位对子公司长期股权投资初始计量是否恰当
A6: 二、审计过程：
A7: 1、是否控制的判断及结论
A8: 判断的事项 | D8: 公司1 | F8: 公司2
D9: 对应情形 | E9: 结论 | F9: 对应情形 | G9: 结论
A10: 被投资者的目标及设计
A11: 是否控制
A12: （1）权力
A13: （2）面临可变回报的风险
A14: （3）使用权力影响可变回报的能力
A15: 结 论
A16: 2、联营企业与合营企业的判断
A17: 合营判断（共同控制）： | D17: 说明 | E17: 联营判断（重大影响）： | H17: 说明 | I17: 审计证据
A18: （l）任何一个合营方均不能单独控制合营企业的相关活动 | E18: （1）在被投资单位的董事会或类似权力机构中派有代表
A19: （2）涉及合营企业的相关活动的决策需要各合营方一致同意 | E19: （2）参与被投资单位的政策制定过程,包括股利分配政策等的制定
A20: （3）各合营方可能通过合同或协议的形式任命其中的一个合营方对合营企业的日常活动进行管理,但其必须在各合营方已经一致同意的相关活动范围内行使管理权。 | E20: （3）与被投资单位之间发生重要交易
E21: （4）向被投资单位派出管理人员
A22: （4）其他 | E22: （5）向被投资单位提供关键技术资料
E23: （6）其他
A24: 3、确认合并（购买）日：
A25: 确认依据： | D25: 公司1 | E25: 公司2 | F25: 公司3
A26: （1）企业合并合同或协议已获股东大会等内部权力机构通过。
A27: （2）合并事项需要经过国家有关主管部门审批的，已获得相关部门的批准
A28: （3）参与合并各方已办理了必要的财产权交接手续。
A29: （4）购买方已支付了购买价款的大部分（一般应超过50％），并且有能力、有计划支付剩余款项。
A30: （5）购买方实际上已经控制了被购买方的财务和经营政策，享有相应的收益并承担相应的风险。
A31: 最终确定的合并（购买）日 | D31: 年 月 日 | E31: 年 月 日 | F31: 年 月 日
A32: 审计证据索引号
A33: 三、审计说明
A37: 四、审计结论
A40: 提示：
A41: 3、合并方式取得的长期股权投资初始投资成本：
A42: A、上述计算前提是合并前合并方与被合并方采用的会计政策应当一致。如企业合并前合并方与被合并方采用的会计政策不同的，应基于重要性原则，统一合并方与被合并方的会计政策。在按照合并方的会计政策对被合并方资产、负债的账面价值进行调整的基础上，计算确定形成长期股权投资的初始投资成本。
A43: B、在编制合并资产负债表时，对于被合并方在企业合并前实现的留存收益（盈余公积和未分配利润之和）中归属于合并方的部分，应按以下原则，自合并方的资本公积转入留存收益和未分配利润：
A44: ①确认企业合并形成的长期股权投资后，合并方账面资本公积（资本溢价或股本溢价）贷方余额大于被合并方在合并前实现的留存收益中归属于合并方的部分，在合并资产负债表中，应将被合并方在合并前实现的留存收益中归属于合并方的部分自“资本公积”转入“盈余公积”和“未分配利润”。在合并工作底稿中，借记“资本公积”项目，贷记“盈余公积”和“未分配利润”项目。 ②确认企业合并形成的长期股权投资后，合并方面资本公积（资本溢价或股本溢价）贷方余额小于被合并方在合并前实现的留存收益中归属于合并方的部分的，在合并资产负债表中，应以合并方资本公积(资本溢价或股本溢价)的贷方余额为限，将被合并方在企业合并前实现的留存收益中归属于合并方的部分自“资本公积”转入“盈余公积”和“未分配利润”。在合并工作底稿中，借记“资本公积”项目，贷记“盈余公积”和“未分配利润”项目。 因合并方的资本公积（资本溢价或股本溢价）余额不足，被合并方在合并前实现的留存收益中归属于合并方的部分在合并资产负债表中未予全额恢复的，合并方应当在会计报表附注中对这一情况进行说明。
A45: C、如果分步取得对子公司股权投资直至取得控制权的各项交易属于“一揽子交易”，应当将各项交易作为一项取得子公司控制权的交易。
A46: 4、通过多次交易分步实现的同一控制下企业合并（不构成一揽子交易）：
A47: 通过多次交易分步实现同一控制下的企业合并，在个别财务报表中，以合并日持股比例计算的合并日应享有被合并方净资产在最终控制方合并财务报表中的账面价值的份额作为该项投资的初始投资成本；初始投资成本与原持有投资的账面价值加上合并日新增投资成本之和的差额，调整资本公积（股本溢价/资本溢价），资本公积不足冲减的，调整留存收益。

Sheet 子公司初始计量测试（同控）G7-8
A1: 致同会计师事务所
A2: 子公司初始计量测试表
A3: =底稿目录!A2 | D3: =底稿目录!A4 | F3: =底稿目录!A5 | H3: 索引号： | I3: =底稿目录!F14
A4: =底稿目录!A3 | D4: =底稿目录!A6 | F4: =底稿目录!A7 | H4: 页 次：
A5: 一、审计目标： | C5: 确定被审计单位对子公司长期股权投资初始计量是否恰当
A6: 二、审计过程：
A7: 1、合并方式取得的长期股权投资初始投资成本：
A8: 审核项目 | D8: 公司1 | E8: 索引 | F8: 公司2 | G8: 索引 | H8: 公司3 | I8: 索引
A9: 最终控制方
A10: 被合并方所有者权益账面价值（如果被合并方存在合并财务报表，则取合并报表数据）① | D10: 100
A11: 合并方合并后占被投资单位的出资比例② | D11: 0.32
A12: 长期股权投资初始投资成本：③=①*② | D12: =D10*D11 | F12: =F10*F11 | H12: =H10*H11
A13: 购买方付出的资产，发生或承担的负债、发行的权益性证券的账面价值之和④ | D13: =SUM(D14:D18) | F13: =SUM(F14:F18) | H13: =SUM(H14:H18)
A14: 其中：现金 | D14: 2
A15: 非现金资产的账面价值 | D15: 2
A16: 发行或承担的债务的账面价值 | D16: 3
A17: 发行的权益性证券的面值
A18: 或有对价 | D18: 3
A19: 母公司报表中调整资本公积、留存收益⑤=③-④ | D19: =D12-D13 | F19: =F12-F13 | H19: =H12-H13
A21: 2、通过多次交易分步实现的同一控制下企业合并（不构成一揽子交易）：
A22: 项目 | D22: P公司 | G22: Q公司
A23: 次别 | D23: 1 | E23: 2 | F23: 小计 | G23: 4 | H23: 5 | I23: 小计
A24: 交易日期 | D24: 1 | E24: 1 | F24: -- | I24: --
A25: 购买比例① | D25: 0.01 | E25: 0.02 | F25: =SUM(D25:E25) | I25: =SUM(G25:H25)
A26: 支付对价② | D26: 1 | E26: 3 | F26: =SUM(D26:E26) | I26: =SUM(G26:H26)
A27: 每笔交易发生时被投资方可辨认净资产的账面价值 | D27: 22 | E27: 44 | F27: -- | I27: --
A28: 因权益法核算确认的长期股权投资其他综合收益、损益调整和其他变动或其他投资确认的计入其他综合收益的公允价值调整③ | D28: 22 | E28: 4 | F28: =SUM(D28:E28) | I28: =SUM(G28:H28)
A29: 公司名称 | C29: 合并日被投资方可辨认净资产的账面价值④ | D29: 合并日长期股权投资投资成本：⑤=④*① | E29: 母公司报表中调整资本公积、留存收益⑥=②+③-⑤ | F29: 索引/备注
A30: P公司 | C30: =E27 | D30: =C30*F25 | E30: =F26+F28-D30
A31: Q公司 | C31: =H27 | D31: =C31*I25 | E31: =I26+I28-D31
A33: 3、反向购买
A34: 交易内容 | C34: 会计上的购买方 | D34: 会计上的购买方的股东 | E34: 会计上的被购买方（上市公司） | F34: 会计上的被购买方的原股东（上市公司原股东） | G34: 判断构成反向购买的依据 | H34: 是否构成业务及其判断依据 | I34: 索引号
A38: 三、审计说明
A42: 四、审计结论
A45: 提示：
A46: 3、合并方式取得的长期股权投资初始投资成本：
A47: A、上述计算前提是合并前合并方与被合并方采用的会计政策应当一致。如企业合并前合并方与被合并方采用的会计政策不同的，应基于重要性原则，统一合并方与被合并方的会计政策。在按照合并方的会计政策对被合并方资产、负债的账面价值进行调整的基础上，计算确定形成长期股权投资的初始投资成本。
A48: B、在编制合并资产负债表时，对于被合并方在企业合并前实现的留存收益（盈余公积和未分配利润之和）中归属于合并方的部分，应按以下原则，自合并方的资本公积转入留存收益和未分配利润：
A49: ①确认企业合并形成的长期股权投资后，合并方账面资本公积（资本溢价或股本溢价）贷方余额大于被合并方在合并前实现的留存收益中归属于合并方的部分，在合并资产负债表中，应将被合并方在合并前实现的留存收益中归属于合并方的部分自“资本公积”转入“盈余公积”和“未分配利润”。在合并工作底稿中，借记“资本公积”项目，贷记“盈余公积”和“未分配利润”项目。 ②确认企业合并形成的长期股权投资后，合并方面资本公积（资本溢价或股本溢价）贷方余额小于被合并方在合并前实现的留存收益中归属于合并方的部分的，在合并资产负债表中，应以合并方资本公积(资本溢价或股本溢价)的贷方余额为限，将被合并方在企业合并前实现的留存收益中归属于合并方的部分自“资本公积”转入“盈余公积”和“未分配利润”。在合并工作底稿中，借记“资本公积”项目，贷记“盈余公积”和“未分配利润”项目。 因合并方的资本公积（资本溢价或股本溢价）余额不足，被合并方在合并前实现的留存收益中归属于合并方的部分在合并资产负债表中未予全额恢复的，合并方应当在会计报表附注中对这一情况进行说明。
A50: C、如果分步取得对子公司股权投资直至取得控制权的各项交易属于“一揽子交易”，应当将各项交易作为一项取得子公司控制权的交易。
A51: 4、通过多次交易分步实现的同一控制下企业合并（不构成一揽子交易）：
A52: 通过多次交易分步实现同一控制下的企业合并，在个别财务报表中，以合并日持股比例计算的合并日应享有被合并方净资产在最终控制方合并财务报表中的账面价值的份额作为该项投资的初始投资成本；初始投资成本与原持有投资的账面价值加上合并日新增投资成本之和的差额，调整资本公积（股本溢价/资本溢价），资本公积不足冲减的，调整留存收益。

Sheet 子公司初始计量测试（非同控）G7-9
A1: 致同会计师事务所
A2: 子公司初始计量测试表
A3: =底稿目录!A2 | D3: =底稿目录!A4 | F3: =底稿目录!A5 | H3: 索引号： | I3: =底稿目录!F15
A4: =底稿目录!A3 | D4: =底稿目录!A6 | F4: =底稿目录!A7 | H4: 页 次：
A5: 一、审计目标： | C5: 确定被审计单位对子公司长期股权投资初始计量是否恰当
A6: 二、审计过程：
A7: 1、合并方式取得的长期股权投资初始投资成本：
A8: 审核项目 | D8: A公司 | E8: 索引 | F8: B公司 | G8: 索引 | H8: C公司 | I8: 索引
A9: 被合并方所有者权益账面价值
A10: 被购买方可辨认净资产的公允价值①
A11: 合并后占被投资单位的出资比例②
A12: 购买方付出的资产，发生或承担的负债、发行的权益性证券的公允价值之和③ | D12: =SUM(D13:D17) | F12: =SUM(F13:F17) | H12: =SUM(H13:H17)
A13: 其中：现金
A14: 非现金资产的公允价值
A15: 发行或承担的债务的公允价值
A16: 发行的权益性证券的公允价值
A17: 或有对价的公允价值
A18: 购买日之前持有的股权于购买日的公允价值④
A19: 购买方付出的资产，发生或承担的负债、发行的权益性证券的账面价值之和⑤
A20: 投资方初始投资成本：⑥=③+④ | D20: =D12+D18 | F20: =F12+F18 | H20: =H12+H18
A21: 记入当期损益（营业外收入）⑦=③-⑤ | D21: =D12-D19 | F21: =F12-F19 | H21: =H12-H19
A22: 合并报表中的商誉或损益（或吸收合并时计入母公司报表中的商誉或损益）⑧=⑥-①*② | D22: =D20-D10*D11 | F22: =F20-F10*F11 | H22: =H20-H10*H11
A24: 2、通过多次交易分步实现的非同一控制下企业合并（不构成一揽子交易）
A25: 项目 | D25: M公司 | G25: N公司
A26: 次别 | D26: 1 | E26: 2 | F26: 小计 | G26: 1 | H26: 2 | I26: 小计
A27: 交易日期 | F27: -- | I27: --
A28: 购买比例① | F28: =SUM(D28:E28) | I28: =SUM(G28:H28)
A29: 支付对价② | F29: =SUM(D29:E29) | I29: =SUM(G29:H29)
A30: 每笔交易发生时被投资方可辨认净资产的公允价值③ | F30: -- | I30: --
A31: 每单交易应享有的被投资方可辨认净资产的公允价值的份额 ④=①*③ | D31: =D28*D30 | E31: =E28*E30 | F31: =SUM(D31:E31) | G31: =G28*G30 | H31: =H28*H30 | I31: =SUM(G31:H31)
A32: 每单交易应确认的商誉或损益⑤=②-④ | D32: =D29-D31 | E32: =E29-E31 | F32: =SUM(D32:E32) | G32: =G29-G31 | H32: =H29-H31 | I32: =SUM(G32:H32)
A33: 因权益法核算确认的长期股权投资其他综合收益、损益调整和其他变动或其他投资确认的计入其他综合收益的公允价值调整⑥ | F33: =SUM(D33:E33) | I33: =SUM(G33:H33)
A34: 合并日母公司长期股权投资的确认金额⑦=②+⑥ | D34: -- | E34: -- | F34: =F29+F33 | G34: -- | H34: -- | I34: =I29+I33
A36: 3、反向购买
A37: 交易内容 | C37: 会计上的购买方 | D37: 会计上的购买方的股东 | E37: 会计上的被购买方（上市公司） | F37: 会计上的被购买方的原股东（上市公司原股东） | G37: 判断构成反向购买的依据 | H37: 是否构成业务及其判断依据 | I37: 索引号
A41: 三、审计说明
A44: 四、审计结论
A47: 提示：
A48: 3、合并方式取得的长期股权投资初始投资成本：
A49: A、购买方为企业合并发生的审计、法律服务、评估咨询等中介费用以及其他相关管理费用，应当于发生时计入当期损益；购买方作为合并对价发行的权益性证券或债务性证券的交易费用，应当计入权益性证券或债务性证券的初始确认金额。
A50: B、取得投资时点一般会与评估基准日有时间差异，请注意公允价值的调整。
A51: C、如果分步取得对子公司股权投资直至取得控制权的各项交易属于“一揽子交易”，应当将各项交易作为一项取得子公司控制权的交易。
A52: 4、通过多次交易分步实现的非同一控制下企业合并（不构成一揽子交易）
A53: A、通过多次交换交易分步实现非同一控制下企业合并的，在个别财务报表中，以购买日之前所持被购买方的股权投资的账面价值与购买日新增投资成本之和，作为该项投资的初始投资成本。购买日之前持有的股权投资因采用权益法核算而确认的其他综合收益，应当在处置该项投资时采用与被投资单位直接处置相关资产或负债相同的基础进行会计处理；因被投资方除净损益、其他综合收益和利润分配以外的其他所有者权益变动而确认的所有者权益，应当在处置该项投资时转入处置期间的当期损益。购买日之前持有的股权投资按照《企业会计准则第22号——金融工具确认和计量》的有关规定进行会计处理的，原计入其他综合收益的累计公允价值变动应当在改按成本法核算时转入当期损益。

Sheet 子公司后续计量测试表G7-10
A1: 致同会计师事务所
A2: 子公司后续计量测试表
A3: =底稿目录!A2 | D3: =底稿目录!A4 | F3: =底稿目录!A5 | H3: 索引号： | I3: =底稿目录!F16
A4: =底稿目录!A3 | D4: =底稿目录!A6 | F4: =底稿目录!A7 | H4: 页 次：
A5: 一、审计目标： | C5: 确定子公司长期股权投资及其相关账户后续计量是否正确。
A6: 二、审计过程：
A7: 1、被投资单位分配股利测算
A8: 公司名称 | B8: 分配方案、股东/董事会决议 | C8: 持股比例 | D8: 宣告分派股利日 | E8: 主要股利分配政策 | F8: 宣告分派的股利金额 | G8: 被审计单位应分配股利 | H8: 实际入账股利 | I8: 差异
G9: =C9*F9 | I9: =G9-H9
G10: =C10*F10 | I10: =G10-H10
G11: =C11*F11 | I11: =G11-H11
G12: =C12*F12 | I12: =G12-H12
G13: =C13*F13 | I13: =G13-H13
A14: 2、购买少数股东股权的处理
A15: 项 目 | C15: 公司1 | D15: 公司2 | E15: 项 目 | G15: 公司1 | H15: 公司2
A16: 新增日长期股权投资账面价值 | E16: 子公司自购买日(或合并日)开始持续计算的可辨认净资产的公允价值③
A17: 原持股比例 | E17: 按新增持股比例计算应享有子公司自购买日(或合并日)开始持续计算的可辨认净资产的公允价值的份额 ④=③*① | G17: =G16*C18 | H17: =H16*D18
A18: 新增的持股比例① | E18: 调整合并报表中的资本公积/留存收益⑤=④-② | G18: =G17-C19 | H18: =H17-D19
A19: 购买成本② | C19: =SUM(C20:C24) | D19: =SUM(D20:D24) | E19: 其中：调整资本公积
A20: 其中：现金 | E20: 调整盈余公积
A21: 非现金资产的公允价值 | E21: 调整未分配利润
A22: 发行或承担的债务的账面价值 | E22: 索引号
A23: 发行的权益性证券的面值
A24: 或有对价
A25: 购买少数股权后长期股权投资账面价值 | C25: =C16+C19 | D25: =D16+D19
A27: 3、处置子公司权益但不丧失控制权
A28: 项 目 | C28: 公司1 | D28: 公司2 | E28: 项 目 | G28: 公司1 | H28: 公司2
A29: 处置日长期股权投资账面价值① | E29: 子公司自购买日(或合并日)开始持续计算的可辨认净资产的公允价值⑥
A30: 原持股比例② | E30: 按减少的持股比例计算应享有子公司自购买日(或合并日)开始持续计算的可辨认净资产的公允价值的份额⑦=⑥*③ | G30: =H29*C31 | H30: =I29*D31
A31: 减少的持股比例③ | E31: 调整合并报表中的资本公积/留存收益 ⑧=⑦-④ | G31: =G30-C32 | H31: =H30-D32
A32: 处置对价④ | C32: =SUM(C33:C37) | D32: =SUM(D33:D37) | E32: 其中：调整资本公积
A33: 其中：现金 | E33: 调整盈余公积
A34: 非现金资产的公允价值 | E34: 调整未分配利润
A35: 发行或承担的债务的账面价值 | E35: 索引号
A36: 发行的权益性证券的面值
A37: 或有对价
A38: 计入个别报表的投资收益 ⑤=④-③/②*① | C38: =IF(C30=0,0,C32-C31/C30*C29) | D38: =IF(D30=0,0,D32-D31/D30*D29)
A39: 三、审计说明
A42: 四、审计结论
A45: 提示：
A46: 2、购买少数股东股权的处理
A47: A、母公司个别财务报表中对于自子公司少数股东处新取得的长期股权投资，应当按照《企业会计准则第2 号——长期股权投资》第四条的规定，确定长期股权投资的入账价值。
A48: B、在合并财务报表中，子公司的资产、负债应以购买日（或合并日）开始持续计算的金额反映。母公司新取得的长期股权投资成本与按照新增持股股比例计算应享有子公司自购买日（或合并日）开始持续计算的可辨认净资产份额之间的差额，应当调整合并财务报表中的资本公积（资本溢价或股本溢价），资本公积（资本溢价或股本溢价）的余额不足冲减的，调整留存收益。

Sheet 处置子公司测试表（不包含一揽子交易）G7-11
A1: 致同会计师事务所
A2: 处置子公司测试表（不包含一揽子交易）
A3: =底稿目录!A2 | E3: =底稿目录!A4 | I3: =底稿目录!A5 | K3: 索引号： | L3: =底稿目录!F17
A4: =底稿目录!A3 | E4: =底稿目录!A6 | I4: =底稿目录!A7 | K4: 页 次：
A5: 一、审计目标： | C5: 确定处置子公司的会计处理是否恰当。
A6: 二、审计过程： | C6: 程序链：①核对协议/决议/收款确认丧失控制权时点 → ②确认非一揽子（一揽子见G7-12）→ ③按剩余股权分类测算单体损益 → ④合并层净资产/商誉/OCI/外币折算 → ⑤剩余为联营合营则追溯权益法 → ⑥与G7-2及账面投资收益勾稽 → ⑦结论与轨迹
A7: 1.本期处置的子公司基本情况
B8: 企业名称 | C8: 注册地 | D8: 业务性质 | E8: 持股比例(小数) | F8: 表决权比例(小数) | G8: 本期不再成为子公司的原因 | H8: G7-4匹配状态
C9: =IF($B9="","",IFERROR(INDEX('被投资单位基本信息G7-4'!$G$12:$G$38,MATCH($B9,'被投资单位基本信息G7-4'!$B$12:$B$38,0)),"")) | D9: =IF($B9="","",IFERROR(INDEX('被投资单位基本信息G7-4'!$H$12:$H$38,MATCH($B9,'被投资单位基本信息G7-4'!$B$12:$B$38,0)),"")) | E9: =IF($B9="","",IFERROR(INDEX('被投资单位基本信息G7-4'!$M$12:$M$38,MATCH($B9,'被投资单位基本信息G7-4'!$B$12:$B$38,0))+N(INDEX('被投资单位基本信息G7-4'!$N$12:$N$38,MATCH($B9,'被投资单位基本信息G7-4'!$B$12:$B$38,0))),"")) | F9: =IF($B9="","",IFERROR(INDEX('被投资单位基本信息G7-4'!$O$12:$O$38,MATCH($B9,'被投资单位基本信息G7-4'!$B$12:$B$38,0)),"")) | H9: =IF($B9="","",IF(ISNUMBER(MATCH($B9,'被投资单位基本信息G7-4'!$B$12:$B$38,0)),"已匹配G7-4","未匹配-请手工补全C至F"))
C10: =IF($B10="","",IFERROR(INDEX('被投资单位基本信息G7-4'!$G$12:$G$38,MATCH($B10,'被投资单位基本信息G7-4'!$B$12:$B$38,0)),"")) | D10: =IF($B10="","",IFERROR(INDEX('被投资单位基本信息G7-4'!$H$12:$H$38,MATCH($B10,'被投资单位基本信息G7-4'!$B$12:$B$38,0)),"")) | E10: =IF($B10="","",IFERROR(INDEX('被投资单位基本信息G7-4'!$M$12:$M$38,MATCH($B10,'被投资单位基本信息G7-4'!$B$12:$B$38,0))+N(INDEX('被投资单位基本信息G7-4'!$N$12:$N$38,MATCH($B10,'被投资单位基本信息G7-4'!$B$12:$B$38,0))),"")) | F10: =IF($B10="","",IFERROR(INDEX('被投资单位基本信息G7-4'!$O$12:$O$38,MATCH($B10,'被投资单位基本信息G7-4'!$B$12:$B$38,0)),"")) | H10: =IF($B10="","",IF(ISNUMBER(MATCH($B10,'被投资单位基本信息G7-4'!$B$12:$B$38,0)),"已匹配G7-4","未匹配-请手工补全C至F"))
C11: =IF($B11="","",IFERROR(INDEX('被投资单位基本信息G7-4'!$G$12:$G$38,MATCH($B11,'被投资单位基本信息G7-4'!$B$12:$B$38,0)),"")) | D11: =IF($B11="","",IFERROR(INDEX('被投资单位基本信息G7-4'!$H$12:$H$38,MATCH($B11,'被投资单位基本信息G7-4'!$B$12:$B$38,0)),"")) | E11: =IF($B11="","",IFERROR(INDEX('被投资单位基本信息G7-4'!$M$12:$M$38,MATCH($B11,'被投资单位基本信息G7-4'!$B$12:$B$38,0))+N(INDEX('被投资单位基本信息G7-4'!$N$12:$N$38,MATCH($B11,'被投资单位基本信息G7-4'!$B$12:$B$38,0))),"")) | F11: =IF($B11="","",IFERROR(INDEX('被投资单位基本信息G7-4'!$O$12:$O$38,MATCH($B11,'被投资单位基本信息G7-4'!$B$12:$B$38,0)),"")) | H11: =IF($B11="","",IF(ISNUMBER(MATCH($B11,'被投资单位基本信息G7-4'!$B$12:$B$38,0)),"已匹配G7-4","未匹配-请手工补全C至F"))
C12: =IF($B12="","",IFERROR(INDEX('被投资单位基本信息G7-4'!$G$12:$G$38,MATCH($B12,'被投资单位基本信息G7-4'!$B$12:$B$38,0)),"")) | D12: =IF($B12="","",IFERROR(INDEX('被投资单位基本信息G7-4'!$H$12:$H$38,MATCH($B12,'被投资单位基本信息G7-4'!$B$12:$B$38,0)),"")) | E12: =IF($B12="","",IFERROR(INDEX('被投资单位基本信息G7-4'!$M$12:$M$38,MATCH($B12,'被投资单位基本信息G7-4'!$B$12:$B$38,0))+N(INDEX('被投资单位基本信息G7-4'!$N$12:$N$38,MATCH($B12,'被投资单位基本信息G7-4'!$B$12:$B$38,0))),"")) | F12: =IF($B12="","",IFERROR(INDEX('被投资单位基本信息G7-4'!$O$12:$O$38,MATCH($B12,'被投资单位基本信息G7-4'!$B$12:$B$38,0)),"")) | H12: =IF($B12="","",IF(ISNUMBER(MATCH($B12,'被投资单位基本信息G7-4'!$B$12:$B$38,0)),"已匹配G7-4","未匹配-请手工补全C至F"))
C13: =IF($B13="","",IFERROR(INDEX('被投资单位基本信息G7-4'!$G$12:$G$38,MATCH($B13,'被投资单位基本信息G7-4'!$B$12:$B$38,0)),"")) | D13: =IF($B13="","",IFERROR(INDEX('被投资单位基本信息G7-4'!$H$12:$H$38,MATCH($B13,'被投资单位基本信息G7-4'!$B$12:$B$38,0)),"")) | E13: =IF($B13="","",IFERROR(INDEX('被投资单位基本信息G7-4'!$M$12:$M$38,MATCH($B13,'被投资单位基本信息G7-4'!$B$12:$B$38,0))+N(INDEX('被投资单位基本信息G7-4'!$N$12:$N$38,MATCH($B13,'被投资单位基本信息G7-4'!$B$12:$B$38,0))),"")) | F13: =IF($B13="","",IFERROR(INDEX('被投资单位基本信息G7-4'!$O$12:$O$38,MATCH($B13,'被投资单位基本信息G7-4'!$B$12:$B$38,0)),"")) | H13: =IF($B13="","",IF(ISNUMBER(MATCH($B13,'被投资单位基本信息G7-4'!$B$12:$B$38,0)),"已匹配G7-4","未匹配-请手工补全C至F"))
A14: 1.1 处置交易要素
B15: 子公司名称 | C15: 股权处置价款 | D15: 原股权比例(小数) | E15: 处置比例(小数) | F15: 剩余比例(小数) | G15: 剩余股权构成 | H15: 股权处置方式 | I15: 丧失控制权的时点 | J15: 丧失控制权时点的确定依据 | K15: 取得的查验资料 | L15: 索引号 | N15: 类型必填/自动复核
B16: =B9 | D16: =IF(B16="","",IF(E9="",0,E9)) | F16: =IF(B16="","",D16-E16) | K16: 股权转让协议、产权交割单、银行收款回单、董事会/股东会决议、评估报告… | N16: =IF(B16="","",IF(OR(D16<0,D16>1,E16<0,E16>D16),"比例异常",IF(OR(C16="",I16="",J16="",L16=""),"交易要素不完整",IF(AND(F16>0,OR(G16="",G16="无")),"剩余股权分类缺失",IF(AND(F16=0,AND(G16<>"",G16<>"无")),"无剩余股权但分类不一致",IF(AND(OR(G16="联营",G16="合营"),I16=""),"联营/合营须明确丧失控制权时点",IF(AND(G16="金融资产",F16<=0),"金融资产须有剩余股权","通过")))))))
B17: =B10 | D17: =IF(B17="","",IF(E10="",0,E10)) | F17: =IF(B17="","",D17-E17) | K17: 股权转让协议、产权交割单、银行收款回单、董事会/股东会决议、评估报告… | N17: =IF(B17="","",IF(OR(D17<0,D17>1,E17<0,E17>D17),"比例异常",IF(OR(C17="",I17="",J17="",L17=""),"交易要素不完整",IF(AND(F17>0,OR(G17="",G17="无")),"剩余股权分类缺失",IF(AND(F17=0,AND(G17<>"",G17<>"无")),"无剩余股权但分类不一致",IF(AND(OR(G17="联营",G17="合营"),I17=""),"联营/合营须明确丧失控制权时点",IF(AND(G17="金融资产",F17<=0),"金融资产须有剩余股权","通过")))))))
B18: =B11 | D18: =IF(B18="","",IF(E11="",0,E11)) | F18: =IF(B18="","",D18-E18) | K18: 股权转让协议、产权交割单、银行收款回单、董事会/股东会决议、评估报告… | N18: =IF(B18="","",IF(OR(D18<0,D18>1,E18<0,E18>D18),"比例异常",IF(OR(C18="",I18="",J18="",L18=""),"交易要素不完整",IF(AND(F18>0,OR(G18="",G18="无")),"剩余股权分类缺失",IF(AND(F18=0,AND(G18<>"",G18<>"无")),"无剩余股权但分类不一致",IF(AND(OR(G18="联营",G18="合营"),I18=""),"联营/合营须明确丧失控制权时点",IF(AND(G18="金融资产",F18<=0),"金融资产须有剩余股权","通过")))))))
B19: =B12 | D19: =IF(B19="","",IF(E12="",0,E12)) | F19: =IF(B19="","",D19-E19) | K19: 股权转让协议、产权交割单、银行收款回单、董事会/股东会决议、评估报告… | N19: =IF(B19="","",IF(OR(D19<0,D19>1,E19<0,E19>D19),"比例异常",IF(OR(C19="",I19="",J19="",L19=""),"交易要素不完整",IF(AND(F19>0,OR(G19="",G19="无")),"剩余股权分类缺失",IF(AND(F19=0,AND(G19<>"",G19<>"无")),"无剩余股权但分类不一致",IF(AND(OR(G19="联营",G19="合营"),I19=""),"联营/合营须明确丧失控制权时点",IF(AND(G19="金融资产",F19<=0),"金融资产须有剩余股权","通过")))))))
B20: =B13 | D20: =IF(B20="","",IF(E13="",0,E13)) | F20: =IF(B20="","",D20-E20) | K20: 股权转让协议、产权交割单、银行收款回单、董事会/股东会决议、评估报告… | N20: =IF(B20="","",IF(OR(D20<0,D20>1,E20<0,E20>D20),"比例异常",IF(OR(C20="",I20="",J20="",L20=""),"交易要素不完整",IF(AND(F20>0,OR(G20="",G20="无")),"剩余股权分类缺失",IF(AND(F20=0,AND(G20<>"",G20<>"无")),"无剩余股权但分类不一致",IF(AND(OR(G20="联营",G20="合营"),I20=""),"联营/合营须明确丧失控制权时点",IF(AND(G20="金融资产",F20<=0),"金融资产须有剩余股权","通过")))))))
A22: 2.1 单体报表
B23: 子公司名称 | C23: 处置日长期股权投资账面价值 | D23: 应转出的长投 | E23: 丧失控制权之日剩余股权的账面价值 | F23: 丧失控制权之日剩余股权的公允价值 | G23: 按公允价值重新计量产生的利得/损失 | H23: 原联营/合营可重分类OCI及其他净资产变动 | I23: 原金融资产OCI | J23: 原联营/合营不可重分类OCI | K23: 处置子公司应确认的投资收益 | L23: 应转入权益 | N23: 类型必填/自动复核
B24: =B16 | D24: =IF(OR(B24="",D16=0),0,C24*E16/D16) | E24: =IF(B24="","",C24-D24) | G24: =IF(B24="","",IF(OR(F16<=0,G16="无",G16=""),0,F24-E24)) | K24: =IF(OR(B24="",D16=0),0,IF(OR(G16="联营",G16="合营"),G24+N(H24)*E16/D16,IF(G16="金融资产",G24+N(I24),IF(OR(G16="无",G16="",F16<=0),C16-D24+N(H24)+N(I24),G24+N(I24))))) | L24: =IF(OR(B24="",D16=0),0,IF(OR(G16="联营",G16="合营"),N(J24)*E16/D16,IF(OR(G16="无",G16="",F16<=0),0,N(J24)))) | N24: =IF(B24="","",IF(C24="","单体长投账面价值未填",IF(AND(F16>0,F24=""),"剩余股权公允价值未填",IF(AND(OR(G16="联营",G16="合营"),H24="",J24=""),"联营/合营OCI区建议复核",IF(AND(G16="金融资产",I24=""),"金融资产OCI未填",IF(AND(OR(G16="无",F16<=0),F24<>"",F24<>0),"无剩余股权但填了公允价值","通过"))))))
B25: =B17 | D25: =IF(OR(B25="",D17=0),0,C25*E17/D17) | E25: =IF(B25="","",C25-D25) | G25: =IF(B25="","",IF(OR(F17<=0,G17="无",G17=""),0,F25-E25)) | K25: =IF(OR(B25="",D17=0),0,IF(OR(G17="联营",G17="合营"),G25+N(H25)*E17/D17,IF(G17="金融资产",G25+N(I25),IF(OR(G17="无",G17="",F17<=0),C17-D25+N(H25)+N(I25),G25+N(I25))))) | L25: =IF(OR(B25="",D17=0),0,IF(OR(G17="联营",G17="合营"),N(J25)*E17/D17,IF(OR(G17="无",G17="",F17<=0),0,N(J25)))) | N25: =IF(B25="","",IF(C25="","单体长投账面价值未填",IF(AND(F17>0,F25=""),"剩余股权公允价值未填",IF(AND(OR(G17="联营",G17="合营"),H25="",J25=""),"联营/合营OCI区建议复核",IF(AND(G17="金融资产",I25=""),"金融资产OCI未填",IF(AND(OR(G17="无",F17<=0),F25<>"",F25<>0),"无剩余股权但填了公允价值","通过"))))))
B26: =B18 | D26: =IF(OR(B26="",D18=0),0,C26*E18/D18) | E26: =IF(B26="","",C26-D26) | G26: =IF(B26="","",IF(OR(F18<=0,G18="无",G18=""),0,F26-E26)) | K26: =IF(OR(B26="",D18=0),0,IF(OR(G18="联营",G18="合营"),G26+N(H26)*E18/D18,IF(G18="金融资产",G26+N(I26),IF(OR(G18="无",G18="",F18<=0),C18-D26+N(H26)+N(I26),G26+N(I26))))) | L26: =IF(OR(B26="",D18=0),0,IF(OR(G18="联营",G18="合营"),N(J26)*E18/D18,IF(OR(G18="无",G18="",F18<=0),0,N(J26)))) | N26: =IF(B26="","",IF(C26="","单体长投账面价值未填",IF(AND(F18>0,F26=""),"剩余股权公允价值未填",IF(AND(OR(G18="联营",G18="合营"),H26="",J26=""),"联营/合营OCI区建议复核",IF(AND(G18="金融资产",I26=""),"金融资产OCI未填",IF(AND(OR(G18="无",F18<=0),F26<>"",F26<>0),"无剩余股权但填了公允价值","通过"))))))
B27: =B19 | D27: =IF(OR(B27="",D19=0),0,C27*E19/D19) | E27: =IF(B27="","",C27-D27) | G27: =IF(B27="","",IF(OR(F19<=0,G19="无",G19=""),0,F27-E27)) | K27: =IF(OR(B27="",D19=0),0,IF(OR(G19="联营",G19="合营"),G27+N(H27)*E19/D19,IF(G19="金融资产",G27+N(I27),IF(OR(G19="无",G19="",F19<=0),C19-D27+N(H27)+N(I27),G27+N(I27))))) | L27: =IF(OR(B27="",D19=0),0,IF(OR(G19="联营",G19="合营"),N(J27)*E19/D19,IF(OR(G19="无",G19="",F19<=0),0,N(J27)))) | N27: =IF(B27="","",IF(C27="","单体长投账面价值未填",IF(AND(F19>0,F27=""),"剩余股权公允价值未填",IF(AND(OR(G19="联营",G19="合营"),H27="",J27=""),"联营/合营OCI区建议复核",IF(AND(G19="金融资产",I27=""),"金融资产OCI未填",IF(AND(OR(G19="无",F19<=0),F27<>"",F27<>0),"无剩余股权但填了公允价值","通过"))))))
B28: =B20 | D28: =IF(OR(B28="",D20=0),0,C28*E20/D20) | E28: =IF(B28="","",C28-D28) | G28: =IF(B28="","",IF(OR(F20<=0,G20="无",G20=""),0,F28-E28)) | K28: =IF(OR(B28="",D20=0),0,IF(OR(G20="联营",G20="合营"),G28+N(H28)*E20/D20,IF(G20="金融资产",G28+N(I28),IF(OR(G20="无",G20="",F20<=0),C20-D28+N(H28)+N(I28),G28+N(I28))))) | L28: =IF(OR(B28="",D20=0),0,IF(OR(G20="联营",G20="合营"),N(J28)*E20/D20,IF(OR(G20="无",G20="",F20<=0),0,N(J28)))) | N28: =IF(B28="","",IF(C28="","单体长投账面价值未填",IF(AND(F20>0,F28=""),"剩余股权公允价值未填",IF(AND(OR(G20="联营",G20="合营"),H28="",J28=""),"联营/合营OCI区建议复核",IF(AND(G20="金融资产",I28=""),"金融资产OCI未填",IF(AND(OR(G20="无",F20<=0),F28<>"",F28<>0),"无剩余股权但填了公允价值","通过"))))))
A30: 2.2 合并报表
B31: 子公司名称 | C31: 处置日合并层面子公司净资产（100%） | D31: 原持股对应净资产份额 | E31: 处置价款与处置部分净资产份额差额 | F31: 合并报表相关商誉 | G31: 剩余股权合并层面账面价值 | H31: 剩余股权公允价值 | I31: 按公允价值重新计量利得/损失 | J31: 公允价值确定方法及主要假设 | K31: OCI重分类至投资损益 | L31: 外币报表折算差额转入损益 | M31: 少数股东权益终止确认 | N31: 类型必填/自动复核 | O31: 所得税影响（减少收益填正数） | P31: 合并层面处置投资收益
B32: =B16 | D32: =IF(OR(B32="",D16=""),0,C32*D16) | E32: =IF(B32="","",C16-C32*E16) | G32: =IF(B32="","",IF(F16<=0,0,C32*F16)) | H32: =F24 | I32: =IF(B32="","",IF(F16<=0,0,H32-G32)) | N32: =IF(B32="","",IF(OR(C32="",F32=""),"合并净资产/商誉未填",IF(AND(F16>0,OR(H32="",J32="")),"剩余股权FV或假设未填",IF(AND(F16<=0,E16<D16,M32=""),"存在少数股权建议填终止确认额","通过")))) | P32: =IF(B32="","",C16+N(H32)-D32-N(F32)+N(K32)+N(L32)-N(O32))
B33: =B17 | D33: =IF(OR(B33="",D17=""),0,C33*D17) | E33: =IF(B33="","",C17-C33*E17) | G33: =IF(B33="","",IF(F17<=0,0,C33*F17)) | H33: =F25 | I33: =IF(B33="","",IF(F17<=0,0,H33-G33)) | N33: =IF(B33="","",IF(OR(C33="",F33=""),"合并净资产/商誉未填",IF(AND(F17>0,OR(H33="",J33="")),"剩余股权FV或假设未填",IF(AND(F17<=0,E17<D17,M33=""),"存在少数股权建议填终止确认额","通过")))) | P33: =IF(B33="","",C17+N(H33)-D33-N(F33)+N(K33)+N(L33)-N(O33))
B34: =B18 | D34: =IF(OR(B34="",D18=""),0,C34*D18) | E34: =IF(B34="","",C18-C34*E18) | G34: =IF(B34="","",IF(F18<=0,0,C34*F18)) | H34: =F26 | I34: =IF(B34="","",IF(F18<=0,0,H34-G34)) | N34: =IF(B34="","",IF(OR(C34="",F34=""),"合并净资产/商誉未填",IF(AND(F18>0,OR(H34="",J34="")),"剩余股权FV或假设未填",IF(AND(F18<=0,E18<D18,M34=""),"存在少数股权建议填终止确认额","通过")))) | P34: =IF(B34="","",C18+N(H34)-D34-N(F34)+N(K34)+N(L34)-N(O34))
B35: =B19 | D35: =IF(OR(B35="",D19=""),0,C35*D19) | E35: =IF(B35="","",C19-C35*E19) | G35: =IF(B35="","",IF(F19<=0,0,C35*F19)) | H35: =F27 | I35: =IF(B35="","",IF(F19<=0,0,H35-G35)) | N35: =IF(B35="","",IF(OR(C35="",F35=""),"合并净资产/商誉未填",IF(AND(F19>0,OR(H35="",J35="")),"剩余股权FV或假设未填",IF(AND(F19<=0,E19<D19,M35=""),"存在少数股权建议填终止确认额","通过")))) | P35: =IF(B35="","",C19+N(H35)-D35-N(F35)+N(K35)+N(L35)-N(O35))
B36: =B20 | D36: =IF(OR(B36="",D20=""),0,C36*D20) | E36: =IF(B36="","",C20-C36*E20) | G36: =IF(B36="","",IF(F20<=0,0,C36*F20)) | H36: =F28 | I36: =IF(B36="","",IF(F20<=0,0,H36-G36)) | N36: =IF(B36="","",IF(OR(C36="",F36=""),"合并净资产/商誉未填",IF(AND(F20>0,OR(H36="",J36="")),"剩余股权FV或假设未填",IF(AND(F20<=0,E20<D20,M36=""),"存在少数股权建议填终止确认额","通过")))) | P36: =IF(B36="","",C20+N(H36)-D36-N(F36)+N(K36)+N(L36)-N(O36))
A38: 3.单次处置剩余股权为联营、合营时追溯调整为权益法
B39: 被投资单位名称 | C39: 持股比例 | D39: 被投资单位 | H39: 归属于母公司 | M39: 测算参数
D40: 原取得投资日至本期期初累计净利润 | E40: 本期净利润 | F40: 其他综合收益 | G40: 其他所有者权益变动 | H40: 期初未分配利润 | I40: 盈余公积 | J40: 投资收益 | K40: 长期投资-其他综合收益 | L40: 长期投资-其他变动 | M40: 盈余公积计提比例
C41: ① | D41: ② | E41: ③ | F41: ④ | G41: ⑤ | H41: ⑥=①×②×(1-⑪) | I41: ⑦=①×②×⑪ | J41: ⑧=①×③ | K41: ⑨=①×④ | L41: ⑩=①×⑤ | M41: ⑪
B42: =IF(OR(G16="联营",G16="合营"),B16,"") | C42: =IF(OR(G16="联营",G16="合营"),F16,"") | H42: =IF(OR(B42="",M42=""),"",C42*D42*(1-M42)) | I42: =IF(OR(B42="",M42=""),"",C42*D42*M42) | J42: =IF(B42="","",C42*E42) | K42: =IF(B42="","",C42*F42) | L42: =IF(B42="","",G42*C42) | N42: =IF(B42="","",IF(OR(D42="",E42="",M42=""),"权益法追溯输入不完整","通过"))
B43: =IF(OR(G17="联营",G17="合营"),B17,"") | C43: =IF(OR(G17="联营",G17="合营"),F17,"") | H43: =IF(OR(B43="",M43=""),"",C43*D43*(1-M43)) | I43: =IF(OR(B43="",M43=""),"",C43*D43*M43) | J43: =IF(B43="","",C43*E43) | K43: =IF(B43="","",C43*F43) | L43: =IF(B43="","",G43*C43) | N43: =IF(B43="","",IF(OR(D43="",E43="",M43=""),"权益法追溯输入不完整","通过"))
B44: =IF(OR(G18="联营",G18="合营"),B18,"") | C44: =IF(OR(G18="联营",G18="合营"),F18,"") | H44: =IF(OR(B44="",M44=""),"",C44*D44*(1-M44)) | I44: =IF(OR(B44="",M44=""),"",C44*D44*M44) | J44: =IF(B44="","",C44*E44) | K44: =IF(B44="","",C44*F44) | L44: =IF(B44="","",G44*C44) | N44: =IF(B44="","",IF(OR(D44="",E44="",M44=""),"权益法追溯输入不完整","通过"))
B45: =IF(OR(G19="联营",G19="合营"),B19,"") | C45: =IF(OR(G19="联营",G19="合营"),F19,"") | H45: =IF(OR(B45="",M45=""),"",C45*D45*(1-M45)) | I45: =IF(OR(B45="",M45=""),"",C45*D45*M45) | J45: =IF(B45="","",C45*E45) | K45: =IF(B45="","",C45*F45) | L45: =IF(B45="","",G45*C45) | N45: =IF(B45="","",IF(OR(D45="",E45="",M45=""),"权益法追溯输入不完整","通过"))
B46: =IF(OR(G20="联营",G20="合营"),B20,"") | C46: =IF(OR(G20="联营",G20="合营"),F20,"") | H46: =IF(OR(B46="",M46=""),"",C46*D46*(1-M46)) | I46: =IF(OR(B46="",M46=""),"",C46*D46*M46) | J46: =IF(B46="","",C46*E46) | K46: =IF(B46="","",C46*F46) | L46: =IF(B46="","",G46*C46) | N46: =IF(B46="","",IF(OR(D46="",E46="",M46=""),"权益法追溯输入不完整","通过"))
A48: 4.账务勾稽与差异提示 | Q48: 重要性水平（金额）
B49: 子公司名称 | C49: ①处置价款(底稿) | D49: ②实际收款/协议对价 | E49: ③=①−②价款差异 | F49: ④长投账面(底稿) | G49: ⑤G7-2可匹配账面 | H49: ⑥=④−⑤长投差异 | I49: ⑦单体测算投资收益 | J49: ⑧账面/调整投资收益 | K49: ⑨=⑦−⑧收益差异 | L49: ⑩是否超重要性 | N49: ⑪勾稽结论 | O49: 合并层测算收益(参)
B50: =B16 | C50: =C16 | E50: =IF(B50="","",N(C50)-N(D50)) | F50: =C24 | G50: =IF(B50="","",IFERROR(INDEX('明细表G7-2'!$R$16:$R$25,MATCH(B50,'明细表G7-2'!$B$16:$B$25,0)),IFERROR(INDEX('明细表G7-2'!$M$16:$M$25,MATCH(B50,'明细表G7-2'!$B$16:$B$25,0)),IFERROR(INDEX('明细表G7-2'!$U$16:$U$25,MATCH(B50,'明细表G7-2'!$B$16:$B$25,0)),IFERROR(INDEX('明细表G7-2'!$H$33:$H$37,MATCH(B50,'明细表G7-2'!$B$33:$B$37,0)),IFERROR(INDEX('明细表G7-2'!$H$40:$H$44,MATCH(B50,'明细表G7-2'!$B$40:$B$44,0)),"未匹配")))))) | H50: =IF(OR(B50="",G50="未匹配",G50=""),"",N(F50)-N(G50)) | I50: =K24 | K50: =IF(B50="","",N(I50)-N(J50)) | L50: =IF(B50="","",IF($R$48="","请填重要性水平",IF(MAX(ABS(N(E50)),IF(H50="",0,ABS(N(H50))),ABS(N(K50)))>$R$48,"超过","未超过"))) | N50: =IF(B50="","",IF(OR(D50="",J50=""),"勾稽输入不完整",IF(L50="超过","存在超重要性差异-需说明",IF(L50="请填重要性水平","待填重要性水平","通过")))) | O50: =P32
B51: =B17 | C51: =C17 | E51: =IF(B51="","",N(C51)-N(D51)) | F51: =C25 | G51: =IF(B51="","",IFERROR(INDEX('明细表G7-2'!$R$16:$R$25,MATCH(B51,'明细表G7-2'!$B$16:$B$25,0)),IFERROR(INDEX('明细表G7-2'!$M$16:$M$25,MATCH(B51,'明细表G7-2'!$B$16:$B$25,0)),IFERROR(INDEX('明细表G7-2'!$U$16:$U$25,MATCH(B51,'明细表G7-2'!$B$16:$B$25,0)),IFERROR(INDEX('明细表G7-2'!$H$33:$H$37,MATCH(B51,'明细表G7-2'!$B$33:$B$37,0)),IFERROR(INDEX('明细表G7-2'!$H$40:$H$44,MATCH(B51,'明细表G7-2'!$B$40:$B$44,0)),"未匹配")))))) | H51: =IF(OR(B51="",G51="未匹配",G51=""),"",N(F51)-N(G51)) | I51: =K25 | K51: =IF(B51="","",N(I51)-N(J51)) | L51: =IF(B51="","",IF($R$48="","请填重要性水平",IF(MAX(ABS(N(E51)),IF(H51="",0,ABS(N(H51))),ABS(N(K51)))>$R$48,"超过","未超过"))) | N51: =IF(B51="","",IF(OR(D51="",J51=""),"勾稽输入不完整",IF(L51="超过","存在超重要性差异-需说明",IF(L51="请填重要性水平","待填重要性水平","通过")))) | O51: =P33
B52: =B18 | C52: =C18 | E52: =IF(B52="","",N(C52)-N(D52)) | F52: =C26 | G52: =IF(B52="","",IFERROR(INDEX('明细表G7-2'!$R$16:$R$25,MATCH(B52,'明细表G7-2'!$B$16:$B$25,0)),IFERROR(INDEX('明细表G7-2'!$M$16:$M$25,MATCH(B52,'明细表G7-2'!$B$16:$B$25,0)),IFERROR(INDEX('明细表G7-2'!$U$16:$U$25,MATCH(B52,'明细表G7-2'!$B$16:$B$25,0)),IFERROR(INDEX('明细表G7-2'!$H$33:$H$37,MATCH(B52,'明细表G7-2'!$B$33:$B$37,0)),IFERROR(INDEX('明细表G7-2'!$H$40:$H$44,MATCH(B52,'明细表G7-2'!$B$40:$B$44,0)),"未匹配")))))) | H52: =IF(OR(B52="",G52="未匹配",G52=""),"",N(F52)-N(G52)) | I52: =K26 | K52: =IF(B52="","",N(I52)-N(J52)) | L52: =IF(B52="","",IF($R$48="","请填重要性水平",IF(MAX(ABS(N(E52)),IF(H52="",0,ABS(N(H52))),ABS(N(K52)))>$R$48,"超过","未超过"))) | N52: =IF(B52="","",IF(OR(D52="",J52=""),"勾稽输入不完整",IF(L52="超过","存在超重要性差异-需说明",IF(L52="请填重要性水平","待填重要性水平","通过")))) | O52: =P34
B53: =B19 | C53: =C19 | E53: =IF(B53="","",N(C53)-N(D53)) | F53: =C27 | G53: =IF(B53="","",IFERROR(INDEX('明细表G7-2'!$R$16:$R$25,MATCH(B53,'明细表G7-2'!$B$16:$B$25,0)),IFERROR(INDEX('明细表G7-2'!$M$16:$M$25,MATCH(B53,'明细表G7-2'!$B$16:$B$25,0)),IFERROR(INDEX('明细表G7-2'!$U$16:$U$25,MATCH(B53,'明细表G7-2'!$B$16:$B$25,0)),IFERROR(INDEX('明细表G7-2'!$H$33:$H$37,MATCH(B53,'明细表G7-2'!$B$33:$B$37,0)),IFERROR(INDEX('明细表G7-2'!$H$40:$H$44,MATCH(B53,'明细表G7-2'!$B$40:$B$44,0)),"未匹配")))))) | H53: =IF(OR(B53="",G53="未匹配",G53=""),"",N(F53)-N(G53)) | I53: =K27 | K53: =IF(B53="","",N(I53)-N(J53)) | L53: =IF(B53="","",IF($R$48="","请填重要性水平",IF(MAX(ABS(N(E53)),IF(H53="",0,ABS(N(H53))),ABS(N(K53)))>$R$48,"超过","未超过"))) | N53: =IF(B53="","",IF(OR(D53="",J53=""),"勾稽输入不完整",IF(L53="超过","存在超重要性差异-需说明",IF(L53="请填重要性水平","待填重要性水平","通过")))) | O53: =P35
B54: =B20 | C54: =C20 | E54: =IF(B54="","",N(C54)-N(D54)) | F54: =C28 | G54: =IF(B54="","",IFERROR(INDEX('明细表G7-2'!$R$16:$R$25,MATCH(B54,'明细表G7-2'!$B$16:$B$25,0)),IFERROR(INDEX('明细表G7-2'!$M$16:$M$25,MATCH(B54,'明细表G7-2'!$B$16:$B$25,0)),IFERROR(INDEX('明细表G7-2'!$U$16:$U$25,MATCH(B54,'明细表G7-2'!$B$16:$B$25,0)),IFERROR(INDEX('明细表G7-2'!$H$33:$H$37,MATCH(B54,'明细表G7-2'!$B$33:$B$37,0)),IFERROR(INDEX('明细表G7-2'!$H$40:$H$44,MATCH(B54,'明细表G7-2'!$B$40:$B$44,0)),"未匹配")))))) | H54: =IF(OR(B54="",G54="未匹配",G54=""),"",N(F54)-N(G54)) | I54: =K28 | K54: =IF(B54="","",N(I54)-N(J54)) | L54: =IF(B54="","",IF($R$48="","请填重要性水平",IF(MAX(ABS(N(E54)),IF(H54="",0,ABS(N(H54))),ABS(N(K54)))>$R$48,"超过","未超过"))) | N54: =IF(B54="","",IF(OR(D54="",J54=""),"勾稽输入不完整",IF(L54="超过","存在超重要性差异-需说明",IF(L54="请填重要性水平","待填重要性水平","通过")))) | O54: =P36
A56: 三、审计说明
A57: （自动汇总异常/待跟进；无数据时显示引导语。可在下方继续手工补充。）
A58: =IF(COUNTA(B9:B13)=0,"（尚未录入处置子公司。请先在第1节填写企业名称，系统将自动匹配G7-4并汇总各节复核异常。）",IF(TEXTJOIN("；",TRUE,IF(AND(N16<>"",N16<>"通过"),IF(B16="","",B16&"：")&N16,""),IF(AND(N17<>"",N17<>"通过"),IF(B17="","",B17&"：")&N17,""),IF(AND(N18<>"",N18<>"通过"),IF(B18="","",B18&"：")&N18,""),IF(AND(N19<>"",N19<>"通过"),IF(B19="","",B19&"：")&N19,""),IF(AND(N20<>"",N20<>"通过"),IF(B20="","",B20&"：")&N20,""),IF(AND(N24<>"",N24<>"通过"),IF(B24="","",B24&"：")&N24,""),IF(AND(N25<>"",N25<>"通过"),IF(B25="","",B25&"：")&N25,""),IF(AND(N26<>"",N26<>"通过"),IF(B26="","",B26&"：")&N26,""),IF(AND(N27<>"",N27<>"通过"),IF(B27="","",B27&"：")&N27,""),IF(AND(N28<>"",N28<>"通过"),IF(B28="","",B28&"：")&N28,""),IF(AND(N32<>"",N32<>"通过"),IF(B32="","",B32&"：")&N32,""),IF(AND(N33<>"",N33<>"通过"),IF(B33="","",B33&"：")&N33,""),IF(AND(N34<>"",N34<>"通过"),IF(B34="","",B34&"：")&N34,""),IF(AND(N35<>"",N35<>"通过"),IF(B35="","",B35&"：")&N35,""),IF(AND(N36<>"",N36<>"通过"),IF(B36="","",B36&"：")&N36,""),IF(AND(N42<>"",N42<>"通过"),IF(B42="","",B42&"：")&N42,""),IF(AND(N43<>"",N43<>"通过"),IF(B43="","",B43&"：")&N43,""),IF(AND(N44<>"",N44<>"通过"),IF(B44="","",B44&"：")&N44,""),IF(AND(N45<>"",N45<>"通过"),IF(B45="","",B45&"：")&N45,""),IF(AND(N46<>"",N46<>"通过"),IF(B46="","",B46&"：")&N46,""),IF(AND(N50<>"",N50<>"通过"),IF(B50="","",B50&"：")&N50,""),IF(AND(N51<>"",N51<>"通过"),IF(B51="","",B51&"：")&N51,""),IF(AND(N52<>"",N52<>"通过"),IF(B52="","",B52&"：")&N52,""),IF(AND(N53<>"",N53<>"通过"),IF(B53="","",B53&"：")&N53,""),IF(AND(N54<>"",N54<>"通过"),IF(B54="","",B54&"：")&N54,""))="","各节自动复核未发现未通过项，请结合查验资料完成结论勾选与复核签字。",TEXTJOIN("；",TRUE,IF(AND(N16<>"",N16<>"通过"),IF(B16="","",B16&"：")&N16,""),IF(AND(N17<>"",N17<>"通过"),IF(B17="","",B17&"：")&N17,""),IF(AND(N18<>"",N18<>"通过"),IF(B18="","",B18&"：")&N18,""),IF(AND(N19<>"",N19<>"通过"),IF(B19="","",B19&"：")&N19,""),IF(AND(N20<>"",N20<>"通过"),IF(B20="","",B20&"：")&N20,""),IF(AND(N24<>"",N24<>"通过"),IF(B24="","",B24&"：")&N24,""),IF(AND(N25<>"",N25<>"通过"),IF(B25="","",B25&"：")&N25,""),IF(AND(N26<>"",N26<>"通过"),IF(B26="","",B26&"：")&N26,""),IF(AND(N27<>"",N27<>"通过"),IF(B27="","",B27&"：")&N27,""),IF(AND(N28<>"",N28<>"通过"),IF(B28="","",B28&"：")&N28,""),IF(AND(N32<>"",N32<>"通过"),IF(B32="","",B32&"：")&N32,""),IF(AND(N33<>"",N33<>"通过"),IF(B33="","",B33&"：")&N33,""),IF(AND(N34<>"",N34<>"通过"),IF(B34="","",B34&"：")&N34,""),IF(AND(N35<>"",N35<>"通过"),IF(B35="","",B35&"：")&N35,""),IF(AND(N36<>"",N36<>"通过"),IF(B36="","",B36&"：")&N36,""),IF(AND(N42<>"",N42<>"通过"),IF(B42="","",B42&"：")&N42,""),IF(AND(N43<>"",N43<>"通过"),IF(B43="","",B43&"：")&N43,""),IF(AND(N44<>"",N44<>"通过"),IF(B44="","",B44&"：")&N44,""),IF(AND(N45<>"",N45<>"通过"),IF(B45="","",B45&"：")&N45,""),IF(AND(N46<>"",N46<>"通过"),IF(B46="","",B46&"：")&N46,""),IF(AND(N50<>"",N50<>"通过"),IF(B50="","",B50&"：")&N50,""),IF(AND(N51<>"",N51<>"通过"),IF(B51="","",B51&"：")&N51,""),IF(AND(N52<>"",N52<>"通过"),IF(B52="","",B52&"：")&N52,""),IF(AND(N53<>"",N53<>"通过"),IF(B53="","",B53&"：")&N53,""),IF(AND(N54<>"",N54<>"通过"),IF(B54="","",B54&"：")&N54,""))))
A62: 四、审计结论
A63: 经审计，本期处置子公司（不包含一揽子交易）的会计处理 □恰当 □不恰当（说明：__________）。已区分G7-12一揽子交易范围。复核人确认异常事项已关闭或已在说明中充分披露。
A67: 五、审计轨迹
B68: 编制人 | D68: 编制日期 | F68: 复核人 | H68: 复核日期
B69: 关键证据索引（协议/评估/收款/决议）
B70: 附件/底稿超链接说明

Sheet 处置子公司测试表（一揽子交易）G7-12
A1: 致同会计师事务所
A2: 处置子公司测试表（一揽子交易）
A3: =底稿目录!A2 | E3: =底稿目录!A4 | I3: =底稿目录!A5 | K3: 索引号： | L3: =底稿目录!F18
A4: =底稿目录!A3 | E4: =底稿目录!A6 | I4: =底稿目录!A7 | K4: 页 次：
A5: 一、审计目标： | C5: 确定多次交易是否构成一揽子交易、丧失控制权时点是否恰当，以及个别和合并财务报表会计处理是否符合企业会计准则。
A6: 二、审计过程：
A7: 1.本期处置的子公司基本情况
B8: 企业名称 | C8: 注册地 | D8: 业务性质 | E8: 持股比例% | F8: 表决权比例% | G8: 本期不再成为子公司的原因
A14: 2.多次交易分步处置股权至丧失控制权而减少的子公司
B15: 一揽子交易的判断事项 | E15: 公司1 | G15: 公司2 | I15: 公司3 | K15: 公司4
E16: 对应情形 | F16: 结论 | G16: 对应情形 | H16: 结论 | I16: 对应情形 | J16: 结论 | K16: 对应情形 | L16: 结论
B17: 这些交易是同时或者在考虑了彼此影响的情况下订立的
B18: 这些交易整体才能达成一项完整的商业结果
B19: 一项交易的发生取决于其他至少一项交易的发生
B20: 一项交易单独看是不经济的，但是和其他交易一并考虑时是经济的
B21: 结论
B22: 子公司名称 | C22: 股权处置价款 | D22: 原股权比例% | E22: 股权处置比例% | F22: 剩余股权比例% | G22: 剩余股权构成 | H22: 股权处置方式 | I22: 丧失控制权的时点 | J22: 丧失控制权时点的确定依据 | K22: 取得的查验资料 | L22: 索引号
F23: =D23-E23 | K23: 股权转让协议、产权交割单、…
F24: =D24-E24
F25: =D25-E25
F26: =D26-E26
A27: 2.1单体报表
B28: 子公司名称 | C28: 处置日长期股权投资账面价值 | D28: 应转出的长投 | E28: 丧失控制权之日剩余股权的账面价值 | F28: 丧失控制权之日剩余股权的公允价值 | G28: 按公允价值重新计量产生的利得/损失 | H28: 原子公司投资系联营/合营投资追加投资形成，与原联营/合营投资有关的可重分类至损益的OCI和其他净资产变动 | I28: 原子公司投资系金融资产投资追加投资形成，与原金融资产相关的按照公允价值计量的OCI | J28: 原子公司投资系联营/合营投资追加投资形成，与原联营/合营投资有关不可重分类至损益的OCI | K28: 处置子公司应确认的投资收益 | L28: 应转入权益
B29: =B23 | D29: =IF(D23=0,0,C29*E23/D23) | E29: =C29-D29 | G29: =F29-E29 | K29: =IF(D23=0,0,IF(G23="联营",G29+H29*E23/D23,IF(G23="合营",F29-E29+H29*E23/D23,G29+I29))) | L29: =IF(D23=0,0,IF(G23="联营",J29*E23/D23,IF(G23="合营",J29*E23/D23,J29)))
B30: =B24 | D30: =IF(D24=0,0,C30*E24/D24) | E30: =C30-D30 | G30: =F30-E30 | K30: =IF(D24=0,0,IF(G24="联营",G30+H30*E24/D24,IF(G24="合营",F30-E30+H30*E24/D24,G30+I30))) | L30: =IF(D24=0,0,IF(G24="联营",J30*E24/D24,IF(G24="合营",J30*E24/D24,J30)))
B31: =B25 | D31: =IF(D25=0,0,C31*E25/D25) | E31: =C31-D31 | G31: =F31-E31 | K31: =IF(D25=0,0,IF(G25="联营",G31+H31*E25/D25,IF(G25="合营",F31-E31+H31*E25/D25,G31+I31))) | L31: =IF(D25=0,0,IF(G25="联营",J31*E25/D25,IF(G25="合营",J31*E25/D25,J31)))
B32: =B26 | D32: =IF(D26=0,0,C32*E26/D26) | E32: =C32-D32 | G32: =F32-E32 | K32: =IF(D26=0,0,IF(G26="联营",G32+H32*E26/D26,IF(G26="合营",F32-E32+H32*E26/D26,G32+I32))) | L32: =IF(D26=0,0,IF(G26="联营",J32*E26/D26,IF(G26="合营",J32*E26/D26,J32)))
A33: 2.2合并报表
B34: 子公司名称 | C34: 处置日合并财务报表层面子公司的净资产 | D34: 处置日合并财务报表层面享有该子公司净资产份额 | E34: 处置价款与处置投资对应的合并财务报表层面享有该子公司净资产份额的差额 | F34: 合并财务报表中与该子公司相关的商誉 | G34: 丧失控制权之日剩余股权的账面价值 | H34: 丧失控制权之日剩余股权的公允价值 | I34: 按公允价值重新计量产生的利得/损失 | J34: 丧失控制权之日剩余股权的公允价值的确定方法及主要假设 | K34: 与原子公司股权投资相关的其他综合收益转入投资损益的金额 | L34: 丧失控制权之前的各步交易处置价款与处置投资对应的合并财务报表层面享有该子公司净资产份额的差额 | M34: 合并处置损益
B35: =B23 | D35: =IF(D23=0,0,C35*E23/D23) | E35: =C23-D35 | G35: =E29 | H35: =F29 | I35: =H35-G35 | K35: =C23+H35-C35-F35 | M35: =C23+H35-C35-F35+K35+L35
B36: =B24 | D36: =IF(D24=0,0,C36*E24/D24) | E36: =C24-D36 | G36: =E30 | H36: =F30 | I36: =H36-G36 | K36: =C24+H36-C36-F36 | M36: =C24+H36-C36-F36+K36+L36
B37: =B25 | D37: =IF(D25=0,0,C37*E25/D25) | E37: =C25-D37 | G37: =E31 | H37: =F31 | I37: =H37-G37 | K37: =C25+H37-C37-F37 | M37: =C25+H37-C37-F37+K37+L37
B38: =B26 | D38: =IF(D26=0,0,C38*E26/D26) | E38: =C26-D38 | G38: =E32 | H38: =F32 | I38: =H38-G38 | K38: =C26+H38-C38-F38 | M38: =C26+H38-C38-F38+K38+L38
A39: 2.3剩余股权为联营、合营时追溯调整为权益法
B40: 被投资单位名称 | C40: 持股比例 | D40: 被投资单位 | H40: 归属于母公司
D41: 原取得投资日至处置日净利润 | E41: 本期净利润 | F41: 其他综合收益 | G41: 其他所有者权益变动 | H41: 期初未分配利润 | I41: 盈余公积 | J41: 投资收益 | K41: 长期投资-其他综合收益 | L41: 长期投资-其他变动
C42: ① | D42: ② | E42: ③ | F42: ④ | G42: ⑤ | H42: ⑥=①*②*90% | I42: ⑦=①*②*10% | J42: ⑧=③×① | K42: ⑨=④×① | L42: ⑩=⑤×①
H43: =C43*D43*90% | I43: =D43*C43*10% | J43: =C43*E43 | K43: =C43*F43 | L43: =G43*C43
H44: =C44*D44*90% | I44: =D44*C44*10% | J44: =C44*E44 | K44: =C44*F44 | L44: =G44*C44
H45: =C45*D45*90% | I45: =D45*C45*10% | J45: =C45*E45 | K45: =C45*F45 | L45: =G45*C45
H46: =C46*D46*90% | I46: =D46*C46*10% | J46: =C46*E46 | K46: =C46*F46 | L46: =G46*C46
A47: 三、审计说明
A51: 四、审计结论

Sheet 合营、联营企业投资成本测试表G7-13
A1: 致同会计师事务所
A2: 合营、联营企业投资成本测试表
A3: =底稿目录!A2 | F3: =底稿目录!A4 | I3: =底稿目录!A5 | L3: 索引号： | M3: =底稿目录!F19
A4: =底稿目录!A3 | F4: =底稿目录!A6 | I4: =底稿目录!A7 | L4: 页 次：
A5: 一、审计目标： | C5: 确定合营、联营企业长期股权投资的初始投资成本确认是否恰当，差额（内含商誉/营业外收入）及公允价值基础后续调整是否符合CAS2。
A6: 二、审计过程 | C6: 1、检查与长期股权投资相关的原始文件或其他支持文件（股权投资协议及框架协议（如有）、交易双方对于交易事项的审批文件、相关政府机关的批准文件、权利交接手续（特别是董事会改选）、款项的收付凭据）。
C7: 2、综合判断长期股权投资是否满足共同控制/重大影响。
C8: 3、取得被审计单位管理层对被投资单位可辨认净资产公允价值的认定及依据的中介机构报告。检查被投资单位可辨认净资产公允价值的确认依据是否充分；
C9: 4、识别期后发生的长期股权投资的增加，检查至支持性文件，确定是否是被记录在恰当的期间内。
C10: 5、对于不纳入合并范围的被投资单位的预付投资款项或预收处置款项，确认重大条款和金额。 ｜ 程序链：识别形成路径（一次投入/金融资产转权益法/主动增资）→核实共同控制或重大影响→测算初始成本与净资产份额差额→建立购买日公允价值差异台账→勾稽G7-2/G7-4/G7-14→结论。 ｜ 边界：取得子公司控制权见G7-8/G7-9；权益法后续计量见G7-14；丧失重大影响见G7-11/G7-12。
A11: （一）被投资单位基本情况
A12: 被投资单位名称：
B13: 出资单位名称 | D13: 注册资本 | H13: 实收资本 | L13: 复核
D14: 期初注册资本 | E14: 本期增加 | F14: 本期减少 | G14: 期末注册资本 | H14: 期初实收资本 （股本） | I14: 本期增加 | J14: 本期减少 | K14: 期末实收资本 （股本） | L14: 自动
B15: 1、本公司 | G15: =IF(COUNTA(D15:F15)=0,"",D15+E15-F15) | K15: =IF(COUNTA(H15:J15)=0,"",H15+I15-J15) | L15: =IF(AND(G15="",K15=""),"",IF(OR(G15<0,K15<0),"资本金额异常",IF(AND(ISNUMBER(G15),ISNUMBER(K15),K15>G15),"实收>注册需说明","通过")))
B16: 2、 …股东 | G16: =IF(COUNTA(D16:F16)=0,"",D16+E16-F16) | K16: =IF(COUNTA(H16:J16)=0,"",H16+I16-J16) | L16: =IF(AND(G16="",K16=""),"",IF(OR(G16<0,K16<0),"资本金额异常",IF(AND(ISNUMBER(G16),ISNUMBER(K16),K16>G16),"实收>注册需说明","通过")))
B17: 3、 …股东 | G17: =IF(COUNTA(D17:F17)=0,"",D17+E17-F17) | K17: =IF(COUNTA(H17:J17)=0,"",H17+I17-J17) | L17: =IF(AND(G17="",K17=""),"",IF(OR(G17<0,K17<0),"资本金额异常",IF(AND(ISNUMBER(G17),ISNUMBER(K17),K17>G17),"实收>注册需说明","通过")))
B18: 合计 | D18: =SUM(D15:D17) | E18: =SUM(E15:E17) | F18: =SUM(F15:F17) | G18: =SUM(G15:G17) | H18: =SUM(H15:H17) | I18: =SUM(I15:I17) | J18: =SUM(J15:J17) | K18: =SUM(K15:K17) | L18: =IF(COUNTA(B15:B17)=0,"",IF(SUMPRODUCT((L15:L17<>"")*(L15:L17<>"通过"))>0,"存在异常","通过"))
A19: （二）公司对其历次投资情况检查
B20: 1、一次投入投资成本确认：
B21: 被投资单位名称 | C21: 投资时间 | D21: 初始投资成本(支付对价)(A) | E21: 投资发生时被投资单位可辨认净资产公允价值 | G21: 差额(D)=A−B×C | H21: 确认本次投资成本(E) | I21: 计入营业外收入(F) | J21: 类型复核
E22: 金额(B) | F22: 投资比例(C)
G23: =IF(OR(B23="",D23="",E23="",F23=""),"",D23-E23*F23) | H23: =IF(G23="","",IF(G23>0,D23,D23-G23)) | I23: =IF(G23="","",IF(G23<0,-G23,0)) | J23: =IF(B23="","",IF(OR(D23="",E23="",F23=""),"一次投入要素不完整",IF(OR(F23<0,F23>1),"投资比例异常",IF(OR(D23<=0,E23<=0),"对价/净资产异常","通过"))))
G24: =IF(OR(B24="",D24="",E24="",F24=""),"",D24-E24*F24) | H24: =IF(G24="","",IF(G24>0,D24,D24-G24)) | I24: =IF(G24="","",IF(G24<0,-G24,0)) | J24: =IF(B24="","",IF(OR(D24="",E24="",F24=""),"一次投入要素不完整",IF(OR(F24<0,F24>1),"投资比例异常",IF(OR(D24<=0,E24<=0),"对价/净资产异常","通过"))))
G25: =IF(OR(B25="",D25="",E25="",F25=""),"",D25-E25*F25) | H25: =IF(G25="","",IF(G25>0,D25,D25-G25)) | I25: =IF(G25="","",IF(G25<0,-G25,0)) | J25: =IF(B25="","",IF(OR(D25="",E25="",F25=""),"一次投入要素不完整",IF(OR(F25<0,F25>1),"投资比例异常",IF(OR(D25<=0,E25<=0),"对价/净资产异常","通过"))))
G26: =IF(OR(B26="",D26="",E26="",F26=""),"",D26-E26*F26) | H26: =IF(G26="","",IF(G26>0,D26,D26-G26)) | I26: =IF(G26="","",IF(G26<0,-G26,0)) | J26: =IF(B26="","",IF(OR(D26="",E26="",F26=""),"一次投入要素不完整",IF(OR(F26<0,F26>1),"投资比例异常",IF(OR(D26<=0,E26<=0),"对价/净资产异常","通过"))))
B27: 合计 | D27: =SUM(D23:D26) | E27: =SUM(E23:E26) | F27: -- | G27: =SUM(G23:G26) | H27: =SUM(H23:H26) | I27: =SUM(I23:I26) | J27: =IF(COUNTA(B23:B26)=0,"",IF(SUMPRODUCT((J23:J26<>"")*(J23:J26<>"通过"))>0,"存在异常","通过"))
B28: 2、原持有的对被投资单位不具有控制、共同控制或重大影响的金融资产，因追加投资导致持股比例上升，能够对被投资单位施加重大影响或实施共同控制的，长期股权投资初始投资成本测算：
B29: 被投资单位名称 | C29: 原投资在追加投资日的公允价值(A) | D29: 原投资比例(B) | E29: 新增投资确认的投资成本（C） | F29: 追加的投资比例(D) | G29: 追加投资时被投资单位可辨认净资产公允价值(E) | H29: 新增投资与应享有的被投资单位可辨认净资产公允价值份额的差额（F）=(A)+(C)-(B+D)*E | I29: 确认本次投资的投资成本（G） | J29: 计入营业外收入金额（H） | K29: 原取得投资后至追加投资的交易日之间被投资单位公允价值的变动 | N29: 类型复核
K30: 原取得投资至追加投资当期期初已计入其他综合收益的累计公允价值变动（I） | L30: 追加投资当期期初至追加投资交易日之间的公允价值变动（J） | M30: 转入投资收益：公允价值变动合计（K=I+J） | N30: 自动
H31: =IF(OR(B31="",C31="",E31="",G31=""),"",C31+E31-(D31+F31)*G31) | I31: =IF(H31="","",IF(H31>0,C31+E31,C31+E31-H31)) | J31: =IF(H31="","",IF(H31<0,-H31,0)) | M31: =IF(OR(B31="",AND(K31="",L31="")),"",N(K31)+N(L31)) | N31: =IF(B31="","",IF(OR(C31="",E31="",G31="",D31="",F31=""),"追加投资要素不完整",IF(OR(D31<0,F31<0,D31+F31>1),"持股比例异常",IF(AND(K31="",L31=""),"OCI结转区建议复核-区分可否转损益","通过"))))
H32: =IF(OR(B32="",C32="",E32="",G32=""),"",C32+E32-(D32+F32)*G32) | I32: =IF(H32="","",IF(H32>0,C32+E32,C32+E32-H32)) | J32: =IF(H32="","",IF(H32<0,-H32,0)) | M32: =IF(OR(B32="",AND(K32="",L32="")),"",N(K32)+N(L32)) | N32: =IF(B32="","",IF(OR(C32="",E32="",G32="",D32="",F32=""),"追加投资要素不完整",IF(OR(D32<0,F32<0,D32+F32>1),"持股比例异常",IF(AND(K32="",L32=""),"OCI结转区建议复核-区分可否转损益","通过"))))
H33: =IF(OR(B33="",C33="",E33="",G33=""),"",C33+E33-(D33+F33)*G33) | I33: =IF(H33="","",IF(H33>0,C33+E33,C33+E33-H33)) | J33: =IF(H33="","",IF(H33<0,-H33,0)) | M33: =IF(OR(B33="",AND(K33="",L33="")),"",N(K33)+N(L33)) | N33: =IF(B33="","",IF(OR(C33="",E33="",G33="",D33="",F33=""),"追加投资要素不完整",IF(OR(D33<0,F33<0,D33+F33>1),"持股比例异常",IF(AND(K33="",L33=""),"OCI结转区建议复核-区分可否转损益","通过"))))
B34: 合计 | C34: =SUM(C31:C33) | D34: -- | E34: =SUM(E31:E33) | F34: -- | G34: -- | H34: =SUM(H31:H33) | I34: =SUM(I31:I33) | J34: =SUM(J31:J33) | K34: -- | L34: -- | M34: =SUM(M31:M33) | N34: =IF(COUNTA(B31:B33)=0,"",IF(SUMPRODUCT((N31:N33<>"")*(N31:N33<>"通过"))>0,"存在异常","通过"))
B36: 3、主动增资：投资单位对联营企业/合营企业的持股比例增加，但被投资单位仍然是投资单位的联营企业或合营企业时，长期股权投资成本测算：
B37: 被投资单位名称 | C37: 新增投资时原账面价值(A) | D37: 其中:原投资内含商誉(B) | E37: 原投资比例(C) | F37: 新增投资确认的投资成本(D) | G37: 新增投资比例(E) | H37: 新增投资时可辨认净资产公允价值(F) | I37: 新增差额(G)=D−E×F | J37: 确认本次新增投资成本(H) | K37: 计入营业外收入(I) | L37: 类型复核
I38: =IF(OR(B38="",F38="",G38="",H38=""),"",F38-G38*H38) | J38: =IF(I38="","",IF(N(D38)+I38>=0,F38,F38-(N(D38)+I38))) | K38: =IF(I38="","",MAX(-(N(D38)+I38),0)) | L38: =IF(B38="","",IF(OR(C38="",F38="",G38="",H38=""),"主动增资要素不完整",IF(OR(E38<0,G38<0,E38+G38>1),"持股比例异常",IF(AND(D38<>"",D38<0),"原内含商誉为负需复核","通过"))))
I39: =IF(OR(B39="",F39="",G39="",H39=""),"",F39-G39*H39) | J39: =IF(I39="","",IF(N(D39)+I39>=0,F39,F39-(N(D39)+I39))) | K39: =IF(I39="","",MAX(-(N(D39)+I39),0)) | L39: =IF(B39="","",IF(OR(C39="",F39="",G39="",H39=""),"主动增资要素不完整",IF(OR(E39<0,G39<0,E39+G39>1),"持股比例异常",IF(AND(D39<>"",D39<0),"原内含商誉为负需复核","通过"))))
I40: =IF(OR(B40="",F40="",G40="",H40=""),"",F40-G40*H40) | J40: =IF(I40="","",IF(N(D40)+I40>=0,F40,F40-(N(D40)+I40))) | K40: =IF(I40="","",MAX(-(N(D40)+I40),0)) | L40: =IF(B40="","",IF(OR(C40="",F40="",G40="",H40=""),"主动增资要素不完整",IF(OR(E40<0,G40<0,E40+G40>1),"持股比例异常",IF(AND(D40<>"",D40<0),"原内含商誉为负需复核","通过"))))
I41: =IF(OR(B41="",F41="",G41="",H41=""),"",F41-G41*H41) | J41: =IF(I41="","",IF(N(D41)+I41>=0,F41,F41-(N(D41)+I41))) | K41: =IF(I41="","",MAX(-(N(D41)+I41),0)) | L41: =IF(B41="","",IF(OR(C41="",F41="",G41="",H41=""),"主动增资要素不完整",IF(OR(E41<0,G41<0,E41+G41>1),"持股比例异常",IF(AND(D41<>"",D41<0),"原内含商誉为负需复核","通过"))))
B42: 合计 | C42: -- | D42: -- | E42: -- | F42: -- | G42: -- | H42: -- | I42: =SUM(I38:I41) | J42: =SUM(J38:J41) | K42: =SUM(K38:K41) | L42: =IF(COUNTA(B38:B41)=0,"",IF(SUMPRODUCT((L38:L41<>"")*(L38:L41<>"通过"))>0,"存在异常","通过"))
A44: （三）取得投资时被投资单位可辨认净资产账面价值与公允价值差异及以后年度对账面净利润的调整
B45: 项目 | C45: 取得投资时 | F45: 差异在取得投资以后期间的调整数（调增净利润填正，调减填负）
C46: 账面价值 | D46: 公允价值 | E46: 差异△=公允−账面 | F46: ××年 | G46: ××年 | H46: ××年 | I46: ××年 | J46: ××年 | K46: ××年 | L46: 以后年度小计 | M46: 累计调整(含取得年度) | N46: 复核
B47: 存货 | E47: =IF(OR(C47="",D47=""),"",D47-C47) | L47: =IF(COUNTA(F47:K47)=0,"",SUM(F47:K47)) | M47: =IF(L47="","",L47) | N47: =IF(E47="","",IF(AND(L47<>"",ABS(N(L47))>ABS(N(E47))+0.01),"转回合计超差异需说明","通过"))
B48: 固定资产 | E48: =IF(OR(C48="",D48=""),"",D48-C48) | L48: =IF(COUNTA(F48:K48)=0,"",SUM(F48:K48)) | M48: =IF(L48="","",L48) | N48: =IF(E48="","",IF(AND(L48<>"",ABS(N(L48))>ABS(N(E48))+0.01),"转回合计超差异需说明","通过"))
B49: 无形资产 | E49: =IF(OR(C49="",D49=""),"",D49-C49) | L49: =IF(COUNTA(F49:K49)=0,"",SUM(F49:K49)) | M49: =IF(L49="","",L49) | N49: =IF(E49="","",IF(AND(L49<>"",ABS(N(L49))>ABS(N(E49))+0.01),"转回合计超差异需说明","通过"))
B50: 资产类合计 | C50: =SUM(C47:C49) | D50: =SUM(D47:D49) | E50: =IF(COUNTA(E47:E49)=0,"",SUM(E47:E49)) | F50: =IF(COUNTA(F47:F49)=0,"",SUM(F47:F49)) | G50: =IF(COUNTA(G47:G49)=0,"",SUM(G47:G49)) | H50: =IF(COUNTA(H47:H49)=0,"",SUM(H47:H49)) | I50: =IF(COUNTA(I47:I49)=0,"",SUM(I47:I49)) | J50: =IF(COUNTA(J47:J49)=0,"",SUM(J47:J49)) | K50: =IF(COUNTA(K47:K49)=0,"",SUM(K47:K49)) | L50: =IF(COUNTA(L47:L49)=0,"",SUM(L47:L49)) | M50: =IF(COUNTA(M47:M49)=0,"",SUM(M47:M49)) | N50: =IF(COUNTA(B47:B49)=0,"",IF(SUMPRODUCT((N47:N49<>"")*(N47:N49<>"通过"))>0,"存在异常","通过"))
B51: 应付账款等负债 | E51: =IF(OR(C51="",D51=""),"",D51-C51) | L51: =IF(COUNTA(F51:K51)=0,"",SUM(F51:K51)) | M51: =IF(L51="","",L51) | N51: =IF(E51="","",IF(AND(L51<>"",ABS(N(L51))>ABS(N(E51))+0.01),"转回合计超差异需说明","通过"))
B52: 负债类合计 | C52: =C51 | D52: =D51 | E52: =IF(E51="","",E51) | F52: =IF(COUNTA(F51)=0,"",F51) | G52: =IF(COUNTA(G51)=0,"",G51) | H52: =IF(COUNTA(H51)=0,"",H51) | I52: =IF(COUNTA(I51)=0,"",I51) | J52: =IF(COUNTA(J51)=0,"",J51) | K52: =IF(COUNTA(K51)=0,"",K51) | L52: =IF(COUNTA(L51)=0,"",L51) | M52: =IF(COUNTA(M51)=0,"",M51) | N52: =IF(E51="","",N51)
B53: 可辨认净资产 | C53: =IF(AND(C50="",C52=""),"",N(C50)-N(C52)) | D53: =IF(AND(D50="",D52=""),"",N(D50)-N(D52)) | E53: =IF(OR(E50="",E52=""),IF(E50="","",E50),E50-N(E52)) | F53: =IF(AND(F50="",F52=""),"",N(F50)-N(F52)) | G53: =IF(AND(G50="",G52=""),"",N(G50)-N(G52)) | H53: =IF(AND(H50="",H52=""),"",N(H50)-N(H52)) | I53: =IF(AND(I50="",I52=""),"",N(I50)-N(I52)) | J53: =IF(AND(J50="",J52=""),"",N(J50)-N(J52)) | K53: =IF(AND(K50="",K52=""),"",N(K50)-N(K52)) | L53: =IF(AND(L50="",L52=""),"",N(L50)-N(L52)) | M53: =IF(AND(M50="",M52=""),"",N(M50)-N(M52)) | N53: =IF(E53="","",IF(ABS(N(E53)-(N(E50)-N(E52)))>0.01,"净资产差异勾稽异常","通过"))
B54: 当期/累计净利润调整数（差异转回合计，供G7-14权益法测算引用） | F54: =IF(AND(F50="",F52=""),"",N(F50)-N(F52)) | G54: =IF(AND(G50="",G52=""),"",N(G50)-N(G52)) | H54: =IF(AND(H50="",H52=""),"",N(H50)-N(H52)) | I54: =IF(AND(I50="",I52=""),"",N(I50)-N(I52)) | J54: =IF(AND(J50="",J52=""),"",N(J50)-N(J52)) | K54: =IF(AND(K50="",K52=""),"",N(K50)-N(K52)) | L54: =IF(AND(L50="",L52=""),"",N(L50)-N(L52)) | M54: =IF(AND(M50="",M52=""),"",N(M50)-N(M52)) | N54: =IF(M54="","",IF(ABS(N(M54)-N(M53))>0.01,"与净资产累计调整不一致","通过"))
B55: 审计说明（公允价值基础）：
B56: 1.取得投资时公允价值依据是【评估报告/管理层认定】：________________ 索引：____
B57: 2.账面价值与公允价值差异在以后期间的调整依据：【存货结转/剩余折旧年限/摊销年限】：________________
B58: 3.评估基准日与投资时点存在时间差的，已/未（ ）将基准日至投资日账面变动调整至取得时点公允价值。
A60: （四）投资成本与账面勾稽（可选）
B61: 被投资单位 | C61: 本表确认投资成本 | D61: G7-2可匹配账面(参考) | E61: 差异 | F61: 重要性水平 | G61: 勾稽结论
A62: 四、审计结论 | B62: =IF(B23<>"",B23,IF(B31<>"",B31,IF(B38<>"",B38,""))) | C62: =IF(B62="","",IF(B23<>"",H23,IF(B31<>"",I31,IF(B38<>"",J38,"")))) | D62: =IF(B62="","",IFERROR(INDEX('明细表G7-2'!$H$33:$H$37,MATCH(B62,'明细表G7-2'!$B$33:$B$37,0)),IFERROR(INDEX('明细表G7-2'!$H$40:$H$44,MATCH(B62,'明细表G7-2'!$B$40:$B$44,0)),IFERROR(INDEX('明细表G7-2'!$M$16:$M$25,MATCH(B62,'明细表G7-2'!$B$16:$B$25,0)),"未匹配")))) | E62: =IF(OR(B62="",D62="未匹配",D62=""),"",N(C62)-N(D62)) | G62: =IF(B62="","",IF(OR(D62="未匹配",D62=""),"未匹配G7-2",IF(F62="","请填重要性水平",IF(ABS(N(E62))>N(F62),"超过重要性-需说明","通过"))))
A64: 三、审计说明
A65: （自动汇总各区复核未通过事项；可继续手工补充）
A66: =IF(AND(COUNTA(B23:B26)=0,COUNTA(B31:B33)=0,COUNTA(B38:B41)=0),"（尚未录入投资成本测试数据。请按形成路径填写第（二）节对应区段。）",IF(TEXTJOIN("；",TRUE,IF(AND(L15<>"",L15<>"通过"),L15,""),IF(AND(L16<>"",L16<>"通过"),L16,""),IF(AND(L17<>"",L17<>"通过"),L17,""),IF(AND(L18<>"",L18<>"通过"),L18,""),IF(AND(J23<>"",J23<>"通过"),J23,""),IF(AND(J24<>"",J24<>"通过"),J24,""),IF(AND(J25<>"",J25<>"通过"),J25,""),IF(AND(J26<>"",J26<>"通过"),J26,""),IF(AND(J27<>"",J27<>"通过"),J27,""),IF(AND(N31<>"",N31<>"通过"),N31,""),IF(AND(N32<>"",N32<>"通过"),N32,""),IF(AND(N33<>"",N33<>"通过"),N33,""),IF(AND(N34<>"",N34<>"通过"),N34,""),IF(AND(L38<>"",L38<>"通过"),L38,""),IF(AND(L39<>"",L39<>"通过"),L39,""),IF(AND(L40<>"",L40<>"通过"),L40,""),IF(AND(L41<>"",L41<>"通过"),L41,""),IF(AND(L42<>"",L42<>"通过"),L42,""),IF(AND(N47<>"",N47<>"通过"),N47,""),IF(AND(N48<>"",N48<>"通过"),N48,""),IF(AND(N49<>"",N49<>"通过"),N49,""),IF(AND(N50<>"",N50<>"通过"),N50,""),IF(AND(N51<>"",N51<>"通过"),N51,""),IF(AND(N52<>"",N52<>"通过"),N52,""),IF(AND(N53<>"",N53<>"通过"),N53,""),IF(AND(N54<>"",N54<>"通过"),N54,""),IF(AND(G62<>"",G62<>"通过"),G62,""))="","各节自动复核未发现未通过项，请结合协议/评估/付款证据完成结论勾选。",TEXTJOIN("；",TRUE,IF(AND(L15<>"",L15<>"通过"),L15,""),IF(AND(L16<>"",L16<>"通过"),L16,""),IF(AND(L17<>"",L17<>"通过"),L17,""),IF(AND(L18<>"",L18<>"通过"),L18,""),IF(AND(J23<>"",J23<>"通过"),J23,""),IF(AND(J24<>"",J24<>"通过"),J24,""),IF(AND(J25<>"",J25<>"通过"),J25,""),IF(AND(J26<>"",J26<>"通过"),J26,""),IF(AND(J27<>"",J27<>"通过"),J27,""),IF(AND(N31<>"",N31<>"通过"),N31,""),IF(AND(N32<>"",N32<>"通过"),N32,""),IF(AND(N33<>"",N33<>"通过"),N33,""),IF(AND(N34<>"",N34<>"通过"),N34,""),IF(AND(L38<>"",L38<>"通过"),L38,""),IF(AND(L39<>"",L39<>"通过"),L39,""),IF(AND(L40<>"",L40<>"通过"),L40,""),IF(AND(L41<>"",L41<>"通过"),L41,""),IF(AND(L42<>"",L42<>"通过"),L42,""),IF(AND(N47<>"",N47<>"通过"),N47,""),IF(AND(N48<>"",N48<>"通过"),N48,""),IF(AND(N49<>"",N49<>"通过"),N49,""),IF(AND(N50<>"",N50<>"通过"),N50,""),IF(AND(N51<>"",N51<>"通过"),N51,""),IF(AND(N52<>"",N52<>"通过"),N52,""),IF(AND(N53<>"",N53<>"通过"),N53,""),IF(AND(N54<>"",N54<>"通过"),N54,""),IF(AND(G62<>"",G62<>"通过"),G62,""))))
A70: 四、审计结论
A71: 经审计，本期合营、联营企业投资成本的会计处理 □恰当 □不恰当（说明：__________）。已按形成路径分别测试；公允价值差异后续调整已与G7-14衔接安排。复核人确认异常事项已关闭或已在说明中充分披露。
A74: 五、审计轨迹
B75: 编制人 | D75: 编制日期 | F75: 复核人 | H75: 复核日期
B77: 关键证据索引（投资协议/审批/评估报告/付款凭证/董事会改选文件）
A79: 提示（准则摘要）：
A80: 1) 一次投入：初始成本与应享有可辨认净资产公允价值份额比较，前者大不调整（内含商誉），前者小调增长投并计入营业外收入。
A81: 2) 金融资产转权益法：初始成本=原股权追加日FV+新增对价；原计入OCI的累计公允价值变动，按原分类判断转入当期损益或留存收益。
A82: 3) 主动增资但仍为联营/合营：按新增比例比较新增成本与新增份额，并综合考虑原投资相关商誉或已计入损益金额后确认是否调整及营业外收入。

Sheet 权益法测算表G7-14
A1: 致同会计师事务所 | J1: 致同会计师事务所
A2: 权益法测算表 | J2: 权益法测算表
A3: =底稿目录!A2 | D3: =底稿目录!A4 | F3: =底稿目录!A5 | H3: 索引号： | I3: =底稿目录!F20 | J3: =A3 | L3: =D3 | N3: =F3 | S3: =H3 | T3: =I3
A4: =底稿目录!A3 | D4: =底稿目录!A6 | F4: =底稿目录!A7 | H4: 页 次： | J4: =A4 | L4: =D4 | N4: =F4 | S4: =H4 | T4: =I4
A5: 一、审计目标： | C5: 确定权益法核算的会计处理是否恰当，包括本期投资收益/OCI/其他权益变动测算、期末长投余额与应享净资产核对，以及差异原因分析。 | J5: =A5 | K5: =B5 | L5: =C5
A6: 二、审计过程 | J6: =A6 | K6: =B6 | L6: =C6
A7: 1、被投资单位权益法调整测算 | J7: =A7 | K7: =B7 | L7: =C7
B8: 被投资单位名称 | C8: 持股比例 | D8: 被投资单位 | G8: 测算 | J8: 已宣告发放的归属于被审计单位单位的股利 | K8: 账面确认投资收益 | L8: 投资收益差异 | M8: 账面确认的其他综合收益 | N8: 差异 | O8: 账面确认的其他权益变动 | P8: 差异 | Q8: 备注/差异解释
D9: 本期净利润 | E9: 其他综合收益 | F9: 其他权益变动 | G9: 投资收益 | H9: 长期投资-其他综合收益 | I9: 其他权益变动
C10: ① | D10: ② | E10: ③ | F10: ④ | G10: ⑤=①×② | H10: ⑥=①×③ | I10: ⑦=①×④ | J10: ⑧ | K10: ⑨ | L10: ⑩=⑨-⑤+⑧ | M10: ⑪ | N10: ⑫=⑪-⑥ | O10: ⑬ | P10: ⑭=⑬-⑦
B11: =IF(OR('明细表G7-2'!B33="",'明细表G7-2'!B33="……"),"",'明细表G7-2'!B33) | C11: =IF(B11="","",'明细表G7-2'!D33) | G11: =IF(B11="","",C11*D11) | H11: =IF(B11="","",C11*E11) | I11: =IF(B11="","",C11*F11) | L11: =IF(B11="","",K11-G11+J11) | N11: =IF(B11="","",M11-H11)
B12: =IF(OR('明细表G7-2'!B34="",'明细表G7-2'!B34="……"),"",'明细表G7-2'!B34) | C12: =IF(B12="","",'明细表G7-2'!D34) | G12: =IF(B12="","",C12*D12) | H12: =IF(B12="","",C12*E12) | I12: =IF(B12="","",C12*F12) | L12: =IF(B12="","",K12-G12+J12) | N12: =IF(B12="","",M12-H12)
B13: =IF(OR('明细表G7-2'!B35="",'明细表G7-2'!B35="……"),"",'明细表G7-2'!B35) | C13: =IF(B13="","",'明细表G7-2'!D35) | G13: =IF(B13="","",C13*D13) | H13: =IF(B13="","",C13*E13) | I13: =IF(B13="","",C13*F13) | L13: =IF(B13="","",K13-G13+J13) | N13: =IF(B13="","",M13-H13)
B14: =IF(OR('明细表G7-2'!B36="",'明细表G7-2'!B36="……"),"",'明细表G7-2'!B36) | C14: =IF(B14="","",'明细表G7-2'!D36) | G14: =IF(B14="","",C14*D14) | H14: =IF(B14="","",C14*E14) | I14: =IF(B14="","",C14*F14) | L14: =IF(B14="","",K14-G14+J14) | N14: =IF(B14="","",M14-H14)
B15: =IF(OR('明细表G7-2'!B37="",'明细表G7-2'!B37="……"),"",'明细表G7-2'!B37) | C15: =IF(B15="","",'明细表G7-2'!D37) | G15: =IF(B15="","",C15*D15) | H15: =IF(B15="","",C15*E15) | I15: =IF(B15="","",C15*F15) | L15: =IF(B15="","",K15-G15+J15) | N15: =IF(B15="","",M15-H15)
B16: =IF(OR('明细表G7-2'!B40="",'明细表G7-2'!B40="……"),"",'明细表G7-2'!B40) | C16: =IF(B16="","",'明细表G7-2'!D40) | G16: =IF(B16="","",C16*D16) | H16: =IF(B16="","",C16*E16) | I16: =IF(B16="","",C16*F16) | L16: =IF(B16="","",K16-G16+J16) | N16: =IF(B16="","",M16-H16)
B17: =IF(OR('明细表G7-2'!B41="",'明细表G7-2'!B41="……"),"",'明细表G7-2'!B41) | C17: =IF(B17="","",'明细表G7-2'!D41) | G17: =IF(B17="","",C17*D17) | H17: =IF(B17="","",C17*E17) | I17: =IF(B17="","",C17*F17) | L17: =IF(B17="","",K17-G17+J17) | N17: =IF(B17="","",M17-H17) | U17: 商誉/初始差额 | V17: 累计公允价值调整 | W17: 减值准备 | X17: 未解释差额
B18: =IF(OR('明细表G7-2'!B42="",'明细表G7-2'!B42="……"),"",'明细表G7-2'!B42) | C18: =IF(B18="","",'明细表G7-2'!D42) | G18: =IF(B18="","",C18*D18) | H18: =IF(B18="","",C18*E18) | I18: =IF(B18="","",C18*F18) | L18: =IF(B18="","",K18-G18+J18) | N18: =IF(B18="","",M18-H18) | U18: （填列） | V18: （填列） | W18: （填列） | X18: ⑮=S-U-V+W
B19: =IF(OR('明细表G7-2'!B43="",'明细表G7-2'!B43="……"),"",'明细表G7-2'!B43) | C19: =IF(B19="","",'明细表G7-2'!D43) | G19: =IF(B19="","",C19*D19) | H19: =IF(B19="","",C19*E19) | I19: =IF(B19="","",C19*F19) | L19: =IF(B19="","",K19-G19+J19) | N19: =IF(B19="","",M19-H19) | X19: =S19-U19-V19+W19
B20: =IF(OR('明细表G7-2'!B44="",'明细表G7-2'!B44="……"),"",'明细表G7-2'!B44) | C20: =IF(B20="","",'明细表G7-2'!D44) | G20: =IF(B20="","",C20*D20) | H20: =IF(B20="","",C20*E20) | I20: =IF(B20="","",C20*F20) | L20: =IF(B20="","",K20-G20+J20) | N20: =IF(B20="","",M20-H20) | X20: =S20-U20-V20+W20
B21: 合计 | D21: =SUM(D11:D20) | E21: =SUM(E11:E20) | F21: =SUM(F11:F20) | G21: =SUM(G11:G20) | H21: =SUM(H11:H20) | I21: =SUM(I11:I20) | J21: =SUM(J11:J20) | K21: =SUM(K11:K20) | ... O21: =SUM(O11:O20) | X21: =S21-U21-V21+W21
A22: 2、长期股权投资期末余额审核 | X22: =S22-U22-V22+W22
B23: 被投资单位 | C23: 持股比例 | D23: 投资成本 | G23: 损益调整 | J23: 其他综合收益 | M23: 其他权益变动 | P23: 期初勾稽 差异 | Q23: 期末账面 合计 | R23: G7-2 期末总额 | S23: 期末勾稽 差异 | U23: =SUM(U19:U22) | V23: =SUM(V19:V22) | W23: =SUM(W19:W22) | X23: =SUM(X19:X22)
D24: 期初余额 | E24: 本期增减（+/-）金额 | F24: 期末余额 | G24: 期初余额 | H24: 本期增减（+/-）金额 | I24: 期末余额 | J24: 期初余额 | K24: 本期增减（+/-）金额 | L24: 期末余额 | M24: 期初余额 | N24: 本期增减（+/-）金额 | O24: 期末余额
B25: =B11 | C25: =C11 | D25: =IF(B25="","",'明细表G7-2'!AO33) | E25: =IF(B25="","",N('明细表G7-2'!AQ33)-N('明细表G7-2'!AX33)) | F25: =IF(B25="","",D25+E25) | H25: =IF(B25="","",N('明细表G7-2'!AR33)-N('明细表G7-2'!AY33)) | I25: =IF(B25="","",N(G25)+N(H25)) | K25: =IF(B25="","",'明细表G7-2'!AS33) | L25: =IF(B25="","",N(J25)+N(K25)) | N25: =IF(B25="","",'明细表G7-2'!AT33) | O25: =IF(B25="","",N(M25)+N(N25)) | P25: =IF(B25="","",N(D25)+N(G25)+N(J25)+N(M25)-N('明细表G7-2'!AO33)) | Q25: =IF(B25="","",N(F25)+N(I25)+N(L25)+N(O25)) | R25: =IF(B25="","",'明细表G7-2'!BB33) | S25: =IF(B25="","",N(Q25)-N(R25))
B26: =B12 | C26: =C12 | D26: =IF(B26="","",'明细表G7-2'!AO34) | E26: =IF(B26="","",N('明细表G7-2'!AQ34)-N('明细表G7-2'!AX34)) | F26: =IF(B26="","",D26+E26) | H26: =IF(B26="","",N('明细表G7-2'!AR34)-N('明细表G7-2'!AY34)) | I26: =IF(B26="","",N(G26)+N(H26)) | K26: =IF(B26="","",'明细表G7-2'!AS34) | L26: =IF(B26="","",N(J26)+N(K26)) | N26: =IF(B26="","",'明细表G7-2'!AT34) | O26: =IF(B26="","",N(M26)+N(N26)) | P26: =IF(B26="","",N(D26)+N(G26)+N(J26)+N(M26)-N('明细表G7-2'!AO34)) | Q26: =IF(B26="","",N(F26)+N(I26)+N(L26)+N(O26)) | R26: =IF(B26="","",'明细表G7-2'!BB34) | S26: =IF(B26="","",N(Q26)-N(R26))
B27: =B13 | C27: =C13 | D27: =IF(B27="","",'明细表G7-2'!AO35) | E27: =IF(B27="","",N('明细表G7-2'!AQ35)-N('明细表G7-2'!AX35)) | F27: =IF(B27="","",D27+E27) | H27: =IF(B27="","",N('明细表G7-2'!AR35)-N('明细表G7-2'!AY35)) | I27: =IF(B27="","",N(G27)+N(H27)) | K27: =IF(B27="","",'明细表G7-2'!AS35) | L27: =IF(B27="","",N(J27)+N(K27)) | N27: =IF(B27="","",'明细表G7-2'!AT35) | O27: =IF(B27="","",N(M27)+N(N27)) | P27: =IF(B27="","",N(D27)+N(G27)+N(J27)+N(M27)-N('明细表G7-2'!AO35)) | Q27: =IF(B27="","",N(F27)+N(I27)+N(L27)+N(O27)) | R27: =IF(B27="","",'明细表G7-2'!BB35) | S27: =IF(B27="","",N(Q27)-N(R27))
B28: =B14 | C28: =C14 | D28: =IF(B28="","",'明细表G7-2'!AO36) | E28: =IF(B28="","",N('明细表G7-2'!AQ36)-N('明细表G7-2'!AX36)) | F28: =IF(B28="","",D28+E28) | H28: =IF(B28="","",N('明细表G7-2'!AR36)-N('明细表G7-2'!AY36)) | I28: =IF(B28="","",N(G28)+N(H28)) | K28: =IF(B28="","",'明细表G7-2'!AS36) | L28: =IF(B28="","",N(J28)+N(K28)) | N28: =IF(B28="","",'明细表G7-2'!AT36) | O28: =IF(B28="","",N(M28)+N(N28)) | P28: =IF(B28="","",N(D28)+N(G28)+N(J28)+N(M28)-N('明细表G7-2'!AO36)) | Q28: =IF(B28="","",N(F28)+N(I28)+N(L28)+N(O28)) | R28: =IF(B28="","",'明细表G7-2'!BB36) | S28: =IF(B28="","",N(Q28)-N(R28))
B29: =B15 | C29: =C15 | D29: =IF(B29="","",'明细表G7-2'!AO37) | E29: =IF(B29="","",N('明细表G7-2'!AQ37)-N('明细表G7-2'!AX37)) | F29: =IF(B29="","",D29+E29) | H29: =IF(B29="","",N('明细表G7-2'!AR37)-N('明细表G7-2'!AY37)) | I29: =IF(B29="","",N(G29)+N(H29)) | K29: =IF(B29="","",'明细表G7-2'!AS37) | L29: =IF(B29="","",N(J29)+N(K29)) | N29: =IF(B29="","",'明细表G7-2'!AT37) | O29: =IF(B29="","",N(M29)+N(N29)) | P29: =IF(B29="","",N(D29)+N(G29)+N(J29)+N(M29)-N('明细表G7-2'!AO37)) | Q29: =IF(B29="","",N(F29)+N(I29)+N(L29)+N(O29)) | R29: =IF(B29="","",'明细表G7-2'!BB37) | S29: =IF(B29="","",N(Q29)-N(R29))
B30: =B16 | C30: =C16 | D30: =IF(B30="","",'明细表G7-2'!AO40) | E30: =IF(B30="","",N('明细表G7-2'!AQ40)-N('明细表G7-2'!AX40)) | F30: =IF(B30="","",D30+E30) | H30: =IF(B30="","",N('明细表G7-2'!AR40)-N('明细表G7-2'!AY40)) | I30: =IF(B30="","",N(G30)+N(H30)) | K30: =IF(B30="","",'明细表G7-2'!AS40) | L30: =IF(B30="","",N(J30)+N(K30)) | N30: =IF(B30="","",'明细表G7-2'!AT40) | O30: =IF(B30="","",N(M30)+N(N30)) | P30: =IF(B30="","",N(D30)+N(G30)+N(J30)+N(M30)-N('明细表G7-2'!AO40)) | Q30: =IF(B30="","",N(F30)+N(I30)+N(L30)+N(O30)) | R30: =IF(B30="","",'明细表G7-2'!BB40) | S30: =IF(B30="","",N(Q30)-N(R30))
B31: =B17 | C31: =C17 | D31: =IF(B31="","",'明细表G7-2'!AO41) | E31: =IF(B31="","",N('明细表G7-2'!AQ41)-N('明细表G7-2'!AX41)) | F31: =IF(B31="","",D31+E31) | H31: =IF(B31="","",N('明细表G7-2'!AR41)-N('明细表G7-2'!AY41)) | I31: =IF(B31="","",N(G31)+N(H31)) | K31: =IF(B31="","",'明细表G7-2'!AS41) | L31: =IF(B31="","",N(J31)+N(K31)) | N31: =IF(B31="","",'明细表G7-2'!AT41) | O31: =IF(B31="","",N(M31)+N(N31)) | P31: =IF(B31="","",N(D31)+N(G31)+N(J31)+N(M31)-N('明细表G7-2'!AO41)) | Q31: =IF(B31="","",N(F31)+N(I31)+N(L31)+N(O31)) | R31: =IF(B31="","",'明细表G7-2'!BB41) | S31: =IF(B31="","",N(Q31)-N(R31))
B32: =B18 | C32: =C18 | D32: =IF(B32="","",'明细表G7-2'!AO42) | E32: =IF(B32="","",N('明细表G7-2'!AQ42)-N('明细表G7-2'!AX42)) | F32: =IF(B32="","",D32+E32) | H32: =IF(B32="","",N('明细表G7-2'!AR42)-N('明细表G7-2'!AY42)) | I32: =IF(B32="","",N(G32)+N(H32)) | K32: =IF(B32="","",'明细表G7-2'!AS42) | L32: =IF(B32="","",N(J32)+N(K32)) | N32: =IF(B32="","",'明细表G7-2'!AT42) | O32: =IF(B32="","",N(M32)+N(N32)) | P32: =IF(B32="","",N(D32)+N(G32)+N(J32)+N(M32)-N('明细表G7-2'!AO42)) | Q32: =IF(B32="","",N(F32)+N(I32)+N(L32)+N(O32)) | R32: =IF(B32="","",'明细表G7-2'!BB42) | S32: =IF(B32="","",N(Q32)-N(R32))
B33: =B19 | C33: =C19 | D33: =IF(B33="","",'明细表G7-2'!AO43) | E33: =IF(B33="","",N('明细表G7-2'!AQ43)-N('明细表G7-2'!AX43)) | F33: =IF(B33="","",D33+E33) | H33: =IF(B33="","",N('明细表G7-2'!AR43)-N('明细表G7-2'!AY43)) | I33: =IF(B33="","",N(G33)+N(H33)) | K33: =IF(B33="","",'明细表G7-2'!AS43) | L33: =IF(B33="","",N(J33)+N(K33)) | N33: =IF(B33="","",'明细表G7-2'!AT43) | O33: =IF(B33="","",N(M33)+N(N33)) | P33: =IF(B33="","",N(D33)+N(G33)+N(J33)+N(M33)-N('明细表G7-2'!AO43)) | Q33: =IF(B33="","",N(F33)+N(I33)+N(L33)+N(O33)) | R33: =IF(B33="","",'明细表G7-2'!BB43) | S33: =IF(B33="","",N(Q33)-N(R33))
B34: =B20 | C34: =C20 | D34: =IF(B34="","",'明细表G7-2'!AO44) | E34: =IF(B34="","",N('明细表G7-2'!AQ44)-N('明细表G7-2'!AX44)) | F34: =IF(B34="","",D34+E34) | H34: =IF(B34="","",N('明细表G7-2'!AR44)-N('明细表G7-2'!AY44)) | I34: =IF(B34="","",N(G34)+N(H34)) | K34: =IF(B34="","",'明细表G7-2'!AS44) | L34: =IF(B34="","",N(J34)+N(K34)) | N34: =IF(B34="","",'明细表G7-2'!AT44) | O34: =IF(B34="","",N(M34)+N(N34)) | P34: =IF(B34="","",N(D34)+N(G34)+N(J34)+N(M34)-N('明细表G7-2'!AO44)) | Q34: =IF(B34="","",N(F34)+N(I34)+N(L34)+N(O34)) | R34: =IF(B34="","",'明细表G7-2'!BB44) | S34: =IF(B34="","",N(Q34)-N(R34))
B35: 合计 | D35: =SUM(D25:D34) | E35: =SUM(E25:E34) | F35: =SUM(F25:F34) | G35: =SUM(G25:G34) | H35: =SUM(H25:H34) | I35: =SUM(I25:I34) | J35: =SUM(J25:J34) | K35: =SUM(K25:K34) | ... S35: =SUM(S25:S34)
A36: 3、被投资单位所有者权益账面价值变动及调整情况
B37: 项目 | D37: 年初净资产 | E37: 本期增加 | F37: 本期减少 | G37: 期末净资产
B38: 账面数： | G38: =D37+E37-F37
B39: 实收资本（或股本） | G39: =D38+E38-F38
B40: 资本公积 | G40: =D39+E39-F39
B41: 减：库存股 | G41: =D40+E40-F40
B42: 其他综合收益 | G42: =D41+E41-F41
B43: 盈余公积 | G43: =D42+E42-F42
B44: 专项储备 | G44: =D43+E43-F43
B45: 未分配利润 | G45: =D44+E44-F44
B46: 归属于母公司所有者权益合计 | D46: =SUM(D38:D39,-D40,D41:D44) | E46: =SUM(E38:E39,-E40,E41:E44) | F46: =SUM(F38:F39,-F40,F41:F44) | G46: =SUM(G38:G39,-G40,G41:G44)
B47: 少数股东权益 | G47: =D46+E46-F46
B48: 所有者权益合计 | D48: =D46+D45 | E48: =E46+E45 | F48: =F46+F45 | G48: =G46+G45
B49: 加： | G49: =D48+E48-F48
B50: 取得投资时公允价值与账面价值差异调整数（表四） | G50: =D49+E49-F49
B51: 本期净利润的其他调整数 | G51: =D50+E50-F50
B52: 期初公允价值差异累计调整数 | G52: =D51+E51-F51
B53: 减： | G53: =D52+E52-F52
B54: 未实现内部交易损益抵消（见内部交易抵销测算表 ） | E54: =IFERROR(ABS(N('权益法未实现内部交易抵销测算表G7-15'!G32)),"") | G54: =IFERROR(N('权益法未实现内部交易抵销测算表G7-15'!C32)*N('权益法未实现内部交易抵销测算表G7-15'!F8),N(D54)+N(E54)-N(F54))
B55: 调整后所有者权益合计 | D55: =D47+D49+D50+D51-D54 | E55: =E47+E49+E50+E51-E54 | F55: =F47+F49+F50+F51-F54 | G55: =G47+G49+G50+G51-G54
B56: （备用调整项，无则留空） | G56: =D56+E56-F56
B57: 本公司持股比例 | G57: =D56+E56-F56
B58: 本公司应享有的所有者权益 | D58: =D55*D57 | E58: =E55*E57 | F58: =F55*F57 | G58: =G55*G57
B59: 注：1、上表中被投资单位与投资单位的会计政策应当一致，如不一致应按调整后的账面价值数据填入上表。
B60: 2、请关注本公司持股比例与表决权比例不一致时需要对上表数据调整，如不一致，必须作出说明。
B61: 3、第2部分“与享有净资产差额”应通过商誉/累计公允价值调整/减值准备解释；“未解释差额”接近0。
B62: 4、投资收益差异⑩=⑨-⑤+⑧：⑨建议取损益调整本期净增加；若取投资收益科目发生额，则正确时⑨≈⑤，股利冲减长投另行核对。
B63: 5、第1部分与第2部分被投资单位行次应一一对应；第3部分按公司分别编制或附多公司附表。
A64: 三、审计说明
B65: 4、投资收益差异⑩=⑨-⑤+⑧：⑨建议取损益调整本期净增加；若取投资收益科目发生额，则正确时⑨≈⑤，股利冲减长投另行核对。
B66: 5、第1部分与第2部分被投资单位行次应一一对应；第3部分按公司分别编制或附多公司附表。
A67: 四、审计结论

Sheet 权益法未实现内部交易抵销测算表G7-15
A1: 致同会计师事务所
A2: 权益法未实现内部交易抵销测算表
A3: =底稿目录!A2 | E3: =底稿目录!A4 | H3: =底稿目录!A5 | K3: 索引号： | L3: =底稿目录!F21
A4: =底稿目录!A3 | E4: =底稿目录!A6 | H4: =底稿目录!A7 | K4: 页 次：
A5: 一、审计目标： | D5: 确定投资方与联营、合营企业之间未实现内部交易损益的抵销金额是否正确，并正确计算对权益法投资收益的调整（×持股比例）。
A6: 二、审计过程 | D6: 程序链：①识别与联营/合营内部交易并区分顺流/逆流 → ②确认标的资产期末是否仍持有及已实现部分（折旧/对外出售）→ ③测算期末未实现④及本期变动⑤ → ④属资产减值的未实现损失不抵销（L列选是）→ ⑤按持股比例计算投资收益调整⑦ → ⑥汇总索引G7-14（名称/比例自动勾稽）→ ⑦结论
D7: 边界：子公司之间内部交易抵销见合并底稿，不在本表。橙色=输入，绿色=公式。被投资单位从G7-14下拉选择，比例自动带出。
B8: 被投资单位： | E8: 持股比例： | F8: =IF(C8="","",IFERROR(INDEX('权益法测算表G7-14'!$C$11:$C$20,MATCH(C8,'权益法测算表G7-14'!$B$11:$B$20,0)),"")) | G8: 与G7-14匹配 | H8: =IF(C8="","",IFERROR(IF(ABS(N(F8)-N(INDEX('权益法测算表G7-14'!$C$11:$C$20,MATCH(C8,'权益法测算表G7-14'!$B$11:$B$20,0))))<=0.000001,"名称/比例均匹配G7-14","名称匹配但比例不一致"),IF(ISNUMBER(MATCH(C8,'明细表G7-2'!$B$33:$B$44,0)),"已匹配G7-2-请核对G7-14","未匹配-请核对名称"))) | I8: 重要性水平(可选)
A9: 1、未实现的内部顺流交易（投资方出售给联营/合营；含①期初未实现余额项目与②本期发生且期末仍未实现项目）
A10: 出售项目 | C10: 出售方(投资企业)损益科目 | D10: 购买方(联营/合营)资产负债科目 | E10: 出售期间 | F10: 出售金额① | G10: 出售成本② | H10: 期末已实现③ | I10: 期末未实现④=①−②−③ | J10: 未实现变动与投资收益调整 | L10: 减值损失不抵销 | M10: 投资收益调整额⑦=−⑤×持股比例（调增+ / 调减−） | N10: 复核
J11: 本期变动⑤=④−⑥ | K11: 以前年度累计⑥
A12: 出售库存商品 | C12: 主营业务收入 | D12: 库存商品（固定资产） | I12: =IF(AND(F12="",G12=""),"",N(F12)-N(G12)-N(H12)) | J12: =IF(I12="","",IF(OR(L12="是",L12="Y",L12="y"),0,N(I12)-N(K12))) | M12: =IF(OR(J12="",$F$8=""),"",-N(J12)*N($F$8)) | N12: =IF(AND(F12="",G12=""),"",IF($F$8="","请填持股比例",IF(OR($F$8<0,$F$8>1),"持股比例异常",IF(AND(N(F12)<N(G12),L12<>"是",L12<>"Y",L12<>"y"),"毛利为负-若属减值请选是",IF(AND(K12<>"",ABS(N(K12))>ABS(N(F12)-N(G12))+0.01),"以前年度累计异常","通过"))))))
A13: 出售固定资产 | C13: 营业外收入 | D13: 固定资产（库存商品） | I13: =IF(AND(F13="",G13=""),"",N(F13)-N(G13)-N(H13)) | J13: =IF(I13="","",IF(OR(L13="是",L13="Y",L13="y"),0,N(I13)-N(K13))) | M13: =IF(OR(J13="",$F$8=""),"",-N(J13)*N($F$8)) | N13: =IF(AND(F13="",G13=""),"",IF($F$8="","请填持股比例",IF(OR($F$8<0,$F$8>1),"持股比例异常",IF(AND(N(F13)<N(G13),L13<>"是",L13<>"Y",L13<>"y"),"毛利为负-若属减值请选是",IF(AND(K13<>"",ABS(N(K13))>ABS(N(F13)-N(G13))+0.01),"以前年度累计异常","通过"))))))
I14: =IF(AND(F14="",G14=""),"",N(F14)-N(G14)-N(H14)) | J14: =IF(I14="","",IF(OR(L14="是",L14="Y",L14="y"),0,N(I14)-N(K14))) | M14: =IF(OR(J14="",$F$8=""),"",-N(J14)*N($F$8)) | N14: =IF(AND(F14="",G14=""),"",IF($F$8="","请填持股比例",IF(OR($F$8<0,$F$8>1),"持股比例异常",IF(AND(N(F14)<N(G14),L14<>"是",L14<>"Y",L14<>"y"),"毛利为负-若属减值请选是",IF(AND(K14<>"",ABS(N(K14))>ABS(N(F14)-N(G14))+0.01),"以前年度累计异常","通过"))))))
I15: =IF(AND(F15="",G15=""),"",N(F15)-N(G15)-N(H15)) | J15: =IF(I15="","",IF(OR(L15="是",L15="Y",L15="y"),0,N(I15)-N(K15))) | M15: =IF(OR(J15="",$F$8=""),"",-N(J15)*N($F$8)) | N15: =IF(AND(F15="",G15=""),"",IF($F$8="","请填持股比例",IF(OR($F$8<0,$F$8>1),"持股比例异常",IF(AND(N(F15)<N(G15),L15<>"是",L15<>"Y",L15<>"y"),"毛利为负-若属减值请选是",IF(AND(K15<>"",ABS(N(K15))>ABS(N(F15)-N(G15))+0.01),"以前年度累计异常","通过"))))))
I16: =IF(AND(F16="",G16=""),"",N(F16)-N(G16)-N(H16)) | J16: =IF(I16="","",IF(OR(L16="是",L16="Y",L16="y"),0,N(I16)-N(K16))) | M16: =IF(OR(J16="",$F$8=""),"",-N(J16)*N($F$8)) | N16: =IF(AND(F16="",G16=""),"",IF($F$8="","请填持股比例",IF(OR($F$8<0,$F$8>1),"持股比例异常",IF(AND(N(F16)<N(G16),L16<>"是",L16<>"Y",L16<>"y"),"毛利为负-若属减值请选是",IF(AND(K16<>"",ABS(N(K16))>ABS(N(F16)-N(G16))+0.01),"以前年度累计异常","通过"))))))
A17: 顺流合计 | F17: =SUM(F12:F16) | G17: =SUM(G12:G16) | H17: =SUM(H12:H16) | I17: =SUM(I12:I16) | J17: =SUM(J12:J16) | K17: =SUM(K12:K16) | M17: =SUM(M12:M16) | N17: =IF(COUNTA(F12:G16)=0,"",IF(SUMPRODUCT((N12:N16<>"")*(N12:N16<>"通过"))>0,"存在异常","通过"))
A18: 2、未实现的内部逆流交易（联营/合营出售给投资方；含①期初未实现余额项目与②本期发生且期末仍未实现项目）
A19: 出售项目 | C19: 出售方(联营/合营)损益科目 | D19: 购买方(投资企业)资产负债科目 | E19: 出售期间 | F19: 出售金额① | G19: 出售成本② | H19: 期末已实现③ | I19: 期末未实现④=①−②−③ | J19: 未实现变动与投资收益调整 | L19: 减值损失不抵销 | M19: 投资收益调整额⑦=−⑤×持股比例（调增+ / 调减−） | N19: 复核
J20: 本期变动⑤=④−⑥ | K20: 以前年度累计⑥
A21: 出售库存商品 | C21: 主营业务收入 | D21: 库存商品（固定资产） | I21: =IF(AND(F21="",G21=""),"",N(F21)-N(G21)-N(H21)) | J21: =IF(I21="","",IF(OR(L21="是",L21="Y",L21="y"),0,N(I21)-N(K21))) | M21: =IF(OR(J21="",$F$8=""),"",-N(J21)*N($F$8)) | N21: =IF(AND(F21="",G21=""),"",IF($F$8="","请填持股比例",IF(OR($F$8<0,$F$8>1),"持股比例异常",IF(AND(N(F21)<N(G21),L21<>"是",L21<>"Y",L21<>"y"),"毛利为负-若属减值请选是",IF(AND(K21<>"",ABS(N(K21))>ABS(N(F21)-N(G21))+0.01),"以前年度累计异常","通过"))))))
A22: 出售固定资产 | C22: 营业外收入 | D22: 固定资产（库存商品） | I22: =IF(AND(F22="",G22=""),"",N(F22)-N(G22)-N(H22)) | J22: =IF(I22="","",IF(OR(L22="是",L22="Y",L22="y"),0,N(I22)-N(K22))) | M22: =IF(OR(J22="",$F$8=""),"",-N(J22)*N($F$8)) | N22: =IF(AND(F22="",G22=""),"",IF($F$8="","请填持股比例",IF(OR($F$8<0,$F$8>1),"持股比例异常",IF(AND(N(F22)<N(G22),L22<>"是",L22<>"Y",L22<>"y"),"毛利为负-若属减值请选是",IF(AND(K22<>"",ABS(N(K22))>ABS(N(F22)-N(G22))+0.01),"以前年度累计异常","通过"))))))
I23: =IF(AND(F23="",G23=""),"",N(F23)-N(G23)-N(H23)) | J23: =IF(I23="","",IF(OR(L23="是",L23="Y",L23="y"),0,N(I23)-N(K23))) | M23: =IF(OR(J23="",$F$8=""),"",-N(J23)*N($F$8)) | N23: =IF(AND(F23="",G23=""),"",IF($F$8="","请填持股比例",IF(OR($F$8<0,$F$8>1),"持股比例异常",IF(AND(N(F23)<N(G23),L23<>"是",L23<>"Y",L23<>"y"),"毛利为负-若属减值请选是",IF(AND(K23<>"",ABS(N(K23))>ABS(N(F23)-N(G23))+0.01),"以前年度累计异常","通过"))))))
I24: =IF(AND(F24="",G24=""),"",N(F24)-N(G24)-N(H24)) | J24: =IF(I24="","",IF(OR(L24="是",L24="Y",L24="y"),0,N(I24)-N(K24))) | M24: =IF(OR(J24="",$F$8=""),"",-N(J24)*N($F$8)) | N24: =IF(AND(F24="",G24=""),"",IF($F$8="","请填持股比例",IF(OR($F$8<0,$F$8>1),"持股比例异常",IF(AND(N(F24)<N(G24),L24<>"是",L24<>"Y",L24<>"y"),"毛利为负-若属减值请选是",IF(AND(K24<>"",ABS(N(K24))>ABS(N(F24)-N(G24))+0.01),"以前年度累计异常","通过"))))))
I25: =IF(AND(F25="",G25=""),"",N(F25)-N(G25)-N(H25)) | J25: =IF(I25="","",IF(OR(L25="是",L25="Y",L25="y"),0,N(I25)-N(K25))) | M25: =IF(OR(J25="",$F$8=""),"",-N(J25)*N($F$8)) | N25: =IF(AND(F25="",G25=""),"",IF($F$8="","请填持股比例",IF(OR($F$8<0,$F$8>1),"持股比例异常",IF(AND(N(F25)<N(G25),L25<>"是",L25<>"Y",L25<>"y"),"毛利为负-若属减值请选是",IF(AND(K25<>"",ABS(N(K25))>ABS(N(F25)-N(G25))+0.01),"以前年度累计异常","通过"))))))
A26: 逆流合计 | F26: =SUM(F21:F25) | G26: =SUM(G21:G25) | H26: =SUM(H21:H25) | I26: =SUM(I21:I25) | J26: =SUM(J21:J25) | K26: =SUM(K21:K25) | M26: =SUM(M21:M25) | N26: =IF(COUNTA(F21:G25)=0,"",IF(SUMPRODUCT((N21:N25<>"")*(N21:N25<>"通过"))>0,"存在异常","通过"))
A27: 提示：
A28: 3、抵销结果汇总（G32可索引至G7-14投资收益调整；期末未实现份额同步G7-14第3部分）
A29: 项目 | C29: 期末未实现④合计 | E29: 本期变动⑤合计 | G29: 投资收益调整额⑦（调增+ / 调减−） | I29: 方向说明 | K29: 与重要性比较
A30: 顺流 | C30: =I17 | E30: =J17 | G30: =M17 | I30: 顺流新增未实现利润调减投资收益；以前年度转回调增 | K30: =IF(OR($J$8="",G30=""),"",IF(ABS(N(G30))>N($J$8),"超过重要性","未超过"))
A31: 逆流 | C31: =I26 | E31: =J26 | G31: =M26 | I31: 逆流按持股比例调整；正负方向同顺流 | K31: =IF(OR($J$8="",G31=""),"",IF(ABS(N(G31))>N($J$8),"超过重要性","未超过"))
A32: 合计 | C32: =C30+C31 | E32: =E30+E31 | G32: =G30+G31 | I32: 本列合计可直接作为G7-14投资收益调整金额 | K32: =IF(OR($J$8="",G32=""),"",IF(ABS(N(G32))>N($J$8),"超过重要性","未超过"))
C33: 借：主营业务收入（营业外收入等） | F33: →按（本期出售金额（1）*投资比例）确认
A34: 提示（编制要点）： | C34: 贷：主营业务成本（……） | G34: →按（本期出售成本（2）*投资比例）确认
A35: 1、重要性：不具重要性的内部交易项目可不予调整，但应在审计说明中说明判断。
A36: 2、本表与G7-14交叉索引：名称取G7-14的B11:B20（合营5+联营5），比例自动勾稽；投资收益调整见G32；期末未实现份额同步至G7-14「未实现内部交易损益抵消」行。
A37: 3、减值：顺流/逆流产生的未实现内部交易损失，若属于所转让资产减值损失，不应抵销（L列选「是」）。
A38: 4、顺流—投资方个别报表：按⑤×持股比例调整投资收益；若需编制合并报表，合并层面还须按份额抵销收入/成本（收入①×比例、成本②×比例、差额进投资收益）。
A39: 5、逆流—合并报表示意：未实现损益体现在投资方持有资产中，按④份额抵销存货/固定资产等，并调整长期股权投资—损益调整；已实现部分③相应调整累计折旧等。
A40: 6、投资收益调整额⑦=−本期未实现变动⑤×持股比例：⑦负数调减G7-14投资收益，⑦正数调增G7-14投资收益；⑤=期末未实现④−以前年度累计⑥，转回时⑤可为负。
C41: 贷：库存商品（或固定资产等） | G41: →按未实现内部损益项目的（出售金额（1）-出售成本（2））确认
A42: 三、审计说明
A43: （自动汇总复核未通过项；可手工补充）
A44: =IF(AND(COUNTA(F12:G16)=0,COUNTA(F21:G25)=0),"（尚未录入内部交易。请先填写被投资单位与持股比例，再分顺流/逆流填列未实现项目。）",IF(TEXTJOIN("；",TRUE,IF(AND(H8<>"",H8<>"名称/比例均匹配G7-14"),H8,""),IF(AND(N17<>"",N17<>"通过"),"顺流:"&N17,""),IF(AND(N26<>"",N26<>"通过"),"逆流:"&N26,""),IF(AND(N12<>"",N12<>"通过"),IF(A12="","行12",A12)&"："&N12,""),IF(AND(N13<>"",N13<>"通过"),IF(A13="","行13",A13)&"："&N13,""),IF(AND(N14<>"",N14<>"通过"),IF(A14="","行14",A14)&"："&N14,""),IF(AND(N15<>"",N15<>"通过"),IF(A15="","行15",A15)&"："&N15,""),IF(AND(N16<>"",N16<>"通过"),IF(A16="","行16",A16)&"："&N16,""),IF(AND(N21<>"",N21<>"通过"),IF(A21="","行21",A21)&"："&N21,""),IF(AND(N22<>"",N22<>"通过"),IF(A22="","行22",A22)&"："&N22,""),IF(AND(N23<>"",N23<>"通过"),IF(A23="","行23",A23)&"："&N23,""),IF(AND(N24<>"",N24<>"通过"),IF(A24="","行24",A24)&"："&N24,""),IF(AND(N25<>"",N25<>"通过"),IF(A25="","行25",A25)&"："&N25,""),IF(AND(K30<>"",K30="超过重要性"),A30&"调整额超过重要性",""),IF(AND(K31<>"",K31="超过重要性"),A31&"调整额超过重要性",""),IF(AND(K32<>"",K32="超过重要性"),A32&"调整额超过重要性",""))="","各节自动复核未发现未通过项。本期带方向投资收益调整额见G32（调增+、调减−），请索引至G7-14。",TEXTJOIN("；",TRUE,IF(AND(H8<>"",H8<>"名称/比例均匹配G7-14"),H8,""),IF(AND(N17<>"",N17<>"通过"),"顺流:"&N17,""),IF(AND(N26<>"",N26<>"通过"),"逆流:"&N26,""),IF(AND(N12<>"",N12<>"通过"),IF(A12="","行12",A12)&"："&N12,""),IF(AND(N13<>"",N13<>"通过"),IF(A13="","行13",A13)&"："&N13,""),IF(AND(N14<>"",N14<>"通过"),IF(A14="","行14",A14)&"："&N14,""),IF(AND(N15<>"",N15<>"通过"),IF(A15="","行15",A15)&"："&N15,""),IF(AND(N16<>"",N16<>"通过"),IF(A16="","行16",A16)&"："&N16,""),IF(AND(N21<>"",N21<>"通过"),IF(A21="","行21",A21)&"："&N21,""),IF(AND(N22<>"",N22<>"通过"),IF(A22="","行22",A22)&"："&N22,""),IF(AND(N23<>"",N23<>"通过"),IF(A23="","行23",A23)&"："&N23,""),IF(AND(N24<>"",N24<>"通过"),IF(A24="","行24",A24)&"："&N24,""),IF(AND(N25<>"",N25<>"通过"),IF(A25="","行25",A25)&"："&N25,""),IF(AND(K30<>"",K30="超过重要性"),A30&"调整额超过重要性",""),IF(AND(K31<>"",K31="超过重要性"),A31&"调整额超过重要性",""),IF(AND(K32<>"",K32="超过重要性"),A32&"调整额超过重要性",""))))
A48: 四、审计结论
A49: 经审计，本期与联营、合营企业未实现内部交易损益的抵销调整 □恰当 □不恰当（说明：__________）。已区分顺流/逆流，减值损失未予抵销（如适用），调整额已与G7-14交叉索引。复核人确认异常事项已关闭或已在说明中充分披露。
A52: 五、审计轨迹
B53: 编制人 | D53: 编制日期 | F53: 复核人 | H53: 复核日期
B55: 关键证据索引（内部交易合同/出入库/固定资产卡片/联营报表/上期底稿）

Sheet 未确认投资损失测试表G7-16
A1: 致同会计师事务所
A2: 未确认投资损失测试表
A3: =底稿目录!A2 | E3: =底稿目录!A4 | G3: =底稿目录!A5 | J3: 索引号： | K3: =底稿目录!F22
A4: =底稿目录!A3 | E4: =底稿目录!A6 | G4: =底稿目录!A7 | J4: 页 次：
A5: 一、审计目标： | C5: 依据《企业会计准则第2号——长期股权投资》第12条/应用指南及超额亏损相关规定，验证对合营、联营企业超额亏损的确认、冲减顺序及未确认投资损失（备查）是否恰当。
A6: 二、审计过程： | C6: 程序链：①取得被投资单位报表/净资产变动说明（期中比例变动则按时段拆行）→ ②核对持股比例与G7-4/G7-5 → ③从G7-14取账面长期股权投资（本表⑯自动勾稽）及损益调整轨迹 → ④识别其他实质上构成净投资的长期权益（长应收等）→ ⑤按CAS2顺序测算可确认损失 vs 未确认损失 → ⑥查合同是否负有额外损失义务（预计负债）→ ⑦与未确认投资损失备查簿勾稽 → ⑧结论与轨迹
C7: 执行要点：取得备查簿及上年审定数；区分合营/联营；关注持股比例变动、处置、减值（G7-17）及内部交易（G7-15）对净资产/损益的影响；橙色为输入，绿色为公式。
A8: 被投资单位名称 | C8: 持股比例 (小数) | D8: 账面期末余额 | F8: 被投资单位净资产 | H8: 未确认投资损失 | K8: 备注 | L8: 应享有净资产 变动 | M8: 额外损失 义务 | N8: 应确认 预计负债 | O8: 备查簿 期末数 | P8: 与备查簿 差异 | Q8: 勾稽复核 | R8: G7-14长投 期末(取数) | S8: 与G7-14 差异 | T8: 关注提示
D9: 长期投资 | E9: 长期权益 | F9: 期初数 | G9: 期末数 | H9: 期初数 | I9: 本期数 | J9: 期末数
A10: ① | C10: ② | D10: ③ | E10: ④ | F10: ⑤ | G10: ⑥ | H10: ⑦ | I10: ⑧分支公式 | J10: ⑨=⑦+⑧ | L10: ⑩=(⑥-⑤)×② | M10: ⑪ | N10: ⑫ | O10: ⑬ | P10: ⑭=⑨-⑬ | Q10: ⑮ | R10: ⑯ | S10: ⑰=③-⑯ | T10: ⑱
A11: 合营企业
A12: =IF('权益法测算表G7-14'!B11="","",'权益法测算表G7-14'!B11) | C12: =IF(A12="","",'权益法测算表G7-14'!C11) | I12: =IF(OR(A12="",C12=""),"",IF((G12-F12)*C12>=0,-MIN(N(H12),(G12-F12)*C12),MAX(0,-(G12-F12)*C12-N(D12)-N(E12)-N(N12)))) | J12: =IF(A12="","",N(H12)+N(I12)) | L12: =IF(OR(A12="",C12=""),"",(G12-F12)*C12) | P12: =IF(OR(A12="",O12=""),"",N(J12)-N(O12)) | Q12: =IF(A12="","",IF(OR(C12<0,C12>1),"持股比例异常",IF(AND(N(I12)>0,N(D12)+N(E12)>0.005),"仍有账面余额却新增未确认，请复核冲减顺序",IF(AND(M12="是",N(N12)<=0),"有额外义务但未填预计负债",IF(AND(M12="否",N(N12)<>0),"无额外义务但填了预计负债",IF(AND(O12<>"",ABS(N(P12))>0.005),"与备查簿不一致",IF(N(J12)<-0.005,"期末未确认不能为负",IF(AND(R12<>"",ABS(N(S12))>0.005,N(J12)<=0.005,N(I12)<=0.005),"与G7-14长投期末不一致",IF(AND(R12<>"",ABS(N(S12))>0.005,OR(N(J12)>0.005,N(I12)>0.005)),"通过(超额亏损致长投差异，已关注)","通过"))))))))) | R12: =IF(A12="","",IFERROR(N('权益法测算表G7-14'!F25)+N('权益法测算表G7-14'!I25)+N('权益法测算表G7-14'!L25)+N('权益法测算表G7-14'!O25),"")) | S12: =IF(OR(A12="",R12=""),"",N(D12)-N(R12)) | T12: =IF(A12="","",IF(N(I12)>0.005,"▲本期新增未确认",IF(N(J12)>0.005,"●期末仍有未确认",IF(AND(O12<>"",ABS(N(P12))>0.005),"备查差异",IF(AND(R12<>"",ABS(N(S12))>0.005,OR(N(I12)>0.005,N(J12)>0.005)),"超额亏损·长投已冲减","—"))))
A13: =IF('权益法测算表G7-14'!B12="","",'权益法测算表G7-14'!B12) | C13: =IF(A13="","",'权益法测算表G7-14'!C12) | I13: =IF(OR(A13="",C13=""),"",IF((G13-F13)*C13>=0,-MIN(N(H13),(G13-F13)*C13),MAX(0,-(G13-F13)*C13-N(D13)-N(E13)-N(N13)))) | J13: =IF(A13="","",N(H13)+N(I13)) | L13: =IF(OR(A13="",C13=""),"",(G13-F13)*C13) | P13: =IF(OR(A13="",O13=""),"",N(J13)-N(O13)) | Q13: =IF(A13="","",IF(OR(C13<0,C13>1),"持股比例异常",IF(AND(N(I13)>0,N(D13)+N(E13)>0.005),"仍有账面余额却新增未确认，请复核冲减顺序",IF(AND(M13="是",N(N13)<=0),"有额外义务但未填预计负债",IF(AND(M13="否",N(N13)<>0),"无额外义务但填了预计负债",IF(AND(O13<>"",ABS(N(P13))>0.005),"与备查簿不一致",IF(N(J13)<-0.005,"期末未确认不能为负",IF(AND(R13<>"",ABS(N(S13))>0.005,N(J13)<=0.005,N(I13)<=0.005),"与G7-14长投期末不一致",IF(AND(R13<>"",ABS(N(S13))>0.005,OR(N(J13)>0.005,N(I13)>0.005)),"通过(超额亏损致长投差异，已关注)","通过"))))))))) | R13: =IF(A13="","",IFERROR(N('权益法测算表G7-14'!F26)+N('权益法测算表G7-14'!I26)+N('权益法测算表G7-14'!L26)+N('权益法测算表G7-14'!O26),"")) | S13: =IF(OR(A13="",R13=""),"",N(D13)-N(R13)) | T13: =IF(A13="","",IF(N(I13)>0.005,"▲本期新增未确认",IF(N(J13)>0.005,"●期末仍有未确认",IF(AND(O13<>"",ABS(N(P13))>0.005),"备查差异",IF(AND(R13<>"",ABS(N(S13))>0.005,OR(N(I13)>0.005,N(J13)>0.005)),"超额亏损·长投已冲减","—"))))
A14: =IF('权益法测算表G7-14'!B13="","",'权益法测算表G7-14'!B13) | C14: =IF(A14="","",'权益法测算表G7-14'!C13) | I14: =IF(OR(A14="",C14=""),"",IF((G14-F14)*C14>=0,-MIN(N(H14),(G14-F14)*C14),MAX(0,-(G14-F14)*C14-N(D14)-N(E14)-N(N14)))) | J14: =IF(A14="","",N(H14)+N(I14)) | L14: =IF(OR(A14="",C14=""),"",(G14-F14)*C14) | P14: =IF(OR(A14="",O14=""),"",N(J14)-N(O14)) | Q14: =IF(A14="","",IF(OR(C14<0,C14>1),"持股比例异常",IF(AND(N(I14)>0,N(D14)+N(E14)>0.005),"仍有账面余额却新增未确认，请复核冲减顺序",IF(AND(M14="是",N(N14)<=0),"有额外义务但未填预计负债",IF(AND(M14="否",N(N14)<>0),"无额外义务但填了预计负债",IF(AND(O14<>"",ABS(N(P14))>0.005),"与备查簿不一致",IF(N(J14)<-0.005,"期末未确认不能为负",IF(AND(R14<>"",ABS(N(S14))>0.005,N(J14)<=0.005,N(I14)<=0.005),"与G7-14长投期末不一致",IF(AND(R14<>"",ABS(N(S14))>0.005,OR(N(J14)>0.005,N(I14)>0.005)),"通过(超额亏损致长投差异，已关注)","通过"))))))))) | R14: =IF(A14="","",IFERROR(N('权益法测算表G7-14'!F27)+N('权益法测算表G7-14'!I27)+N('权益法测算表G7-14'!L27)+N('权益法测算表G7-14'!O27),"")) | S14: =IF(OR(A14="",R14=""),"",N(D14)-N(R14)) | T14: =IF(A14="","",IF(N(I14)>0.005,"▲本期新增未确认",IF(N(J14)>0.005,"●期末仍有未确认",IF(AND(O14<>"",ABS(N(P14))>0.005),"备查差异",IF(AND(R14<>"",ABS(N(S14))>0.005,OR(N(I14)>0.005,N(J14)>0.005)),"超额亏损·长投已冲减","—"))))
A15: =IF('权益法测算表G7-14'!B14="","",'权益法测算表G7-14'!B14) | C15: =IF(A15="","",'权益法测算表G7-14'!C14) | I15: =IF(OR(A15="",C15=""),"",IF((G15-F15)*C15>=0,-MIN(N(H15),(G15-F15)*C15),MAX(0,-(G15-F15)*C15-N(D15)-N(E15)-N(N15)))) | J15: =IF(A15="","",N(H15)+N(I15)) | L15: =IF(OR(A15="",C15=""),"",(G15-F15)*C15) | P15: =IF(OR(A15="",O15=""),"",N(J15)-N(O15)) | Q15: =IF(A15="","",IF(OR(C15<0,C15>1),"持股比例异常",IF(AND(N(I15)>0,N(D15)+N(E15)>0.005),"仍有账面余额却新增未确认，请复核冲减顺序",IF(AND(M15="是",N(N15)<=0),"有额外义务但未填预计负债",IF(AND(M15="否",N(N15)<>0),"无额外义务但填了预计负债",IF(AND(O15<>"",ABS(N(P15))>0.005),"与备查簿不一致",IF(N(J15)<-0.005,"期末未确认不能为负",IF(AND(R15<>"",ABS(N(S15))>0.005,N(J15)<=0.005,N(I15)<=0.005),"与G7-14长投期末不一致",IF(AND(R15<>"",ABS(N(S15))>0.005,OR(N(J15)>0.005,N(I15)>0.005)),"通过(超额亏损致长投差异，已关注)","通过"))))))))) | R15: =IF(A15="","",IFERROR(N('权益法测算表G7-14'!F28)+N('权益法测算表G7-14'!I28)+N('权益法测算表G7-14'!L28)+N('权益法测算表G7-14'!O28),"")) | S15: =IF(OR(A15="",R15=""),"",N(D15)-N(R15)) | T15: =IF(A15="","",IF(N(I15)>0.005,"▲本期新增未确认",IF(N(J15)>0.005,"●期末仍有未确认",IF(AND(O15<>"",ABS(N(P15))>0.005),"备查差异",IF(AND(R15<>"",ABS(N(S15))>0.005,OR(N(I15)>0.005,N(J15)>0.005)),"超额亏损·长投已冲减","—"))))
A16: =IF('权益法测算表G7-14'!B15="","",'权益法测算表G7-14'!B15) | C16: =IF(A16="","",'权益法测算表G7-14'!C15) | I16: =IF(OR(A16="",C16=""),"",IF((G16-F16)*C16>=0,-MIN(N(H16),(G16-F16)*C16),MAX(0,-(G16-F16)*C16-N(D16)-N(E16)-N(N16)))) | J16: =IF(A16="","",N(H16)+N(I16)) | L16: =IF(OR(A16="",C16=""),"",(G16-F16)*C16) | P16: =IF(OR(A16="",O16=""),"",N(J16)-N(O16)) | Q16: =IF(A16="","",IF(OR(C16<0,C16>1),"持股比例异常",IF(AND(N(I16)>0,N(D16)+N(E16)>0.005),"仍有账面余额却新增未确认，请复核冲减顺序",IF(AND(M16="是",N(N16)<=0),"有额外义务但未填预计负债",IF(AND(M16="否",N(N16)<>0),"无额外义务但填了预计负债",IF(AND(O16<>"",ABS(N(P16))>0.005),"与备查簿不一致",IF(N(J16)<-0.005,"期末未确认不能为负",IF(AND(R16<>"",ABS(N(S16))>0.005,N(J16)<=0.005,N(I16)<=0.005),"与G7-14长投期末不一致",IF(AND(R16<>"",ABS(N(S16))>0.005,OR(N(J16)>0.005,N(I16)>0.005)),"通过(超额亏损致长投差异，已关注)","通过"))))))))) | R16: =IF(A16="","",IFERROR(N('权益法测算表G7-14'!F29)+N('权益法测算表G7-14'!I29)+N('权益法测算表G7-14'!L29)+N('权益法测算表G7-14'!O29),"")) | S16: =IF(OR(A16="",R16=""),"",N(D16)-N(R16)) | T16: =IF(A16="","",IF(N(I16)>0.005,"▲本期新增未确认",IF(N(J16)>0.005,"●期末仍有未确认",IF(AND(O16<>"",ABS(N(P16))>0.005),"备查差异",IF(AND(R16<>"",ABS(N(S16))>0.005,OR(N(I16)>0.005,N(J16)>0.005)),"超额亏损·长投已冲减","—"))))
A17: 小 计 | C17: — | D17: =SUM(D12:D16) | E17: =SUM(E12:E16) | F17: — | G17: — | H17: =SUM(H12:H16) | I17: =SUM(I12:I16) | J17: =SUM(J12:J16) | L17: =SUM(L12:L16) | N17: =SUM(N12:N16) | O17: =SUM(O12:O16) | P17: =SUM(P12:P16) | Q17: =IF(COUNTA(A12:A16)=0,"","—") | R17: =SUM(R12:R16) | S17: =SUM(S12:S16) | T17: =IF(COUNTA(A12:16)=0,"","未确认"&COUNTIF(J12:16,">0")&"家")
A18: 联营企业
A19: =IF('权益法测算表G7-14'!B16="","",'权益法测算表G7-14'!B16) | C19: =IF(A19="","",'权益法测算表G7-14'!C16) | I19: =IF(OR(A19="",C19=""),"",IF((G19-F19)*C19>=0,-MIN(N(H19),(G19-F19)*C19),MAX(0,-(G19-F19)*C19-N(D19)-N(E19)-N(N19)))) | J19: =IF(A19="","",N(H19)+N(I19)) | L19: =IF(OR(A19="",C19=""),"",(G19-F19)*C19) | P19: =IF(OR(A19="",O19=""),"",N(J19)-N(O19)) | Q19: =IF(A19="","",IF(OR(C19<0,C19>1),"持股比例异常",IF(AND(N(I19)>0,N(D19)+N(E19)>0.005),"仍有账面余额却新增未确认，请复核冲减顺序",IF(AND(M19="是",N(N19)<=0),"有额外义务但未填预计负债",IF(AND(M19="否",N(N19)<>0),"无额外义务但填了预计负债",IF(AND(O19<>"",ABS(N(P19))>0.005),"与备查簿不一致",IF(N(J19)<-0.005,"期末未确认不能为负",IF(AND(R19<>"",ABS(N(S19))>0.005,N(J19)<=0.005,N(I19)<=0.005),"与G7-14长投期末不一致",IF(AND(R19<>"",ABS(N(S19))>0.005,OR(N(J19)>0.005,N(I19)>0.005)),"通过(超额亏损致长投差异，已关注)","通过"))))))))) | R19: =IF(A19="","",IFERROR(N('权益法测算表G7-14'!F30)+N('权益法测算表G7-14'!I30)+N('权益法测算表G7-14'!L30)+N('权益法测算表G7-14'!O30),"")) | S19: =IF(OR(A19="",R19=""),"",N(D19)-N(R19)) | T19: =IF(A19="","",IF(N(I19)>0.005,"▲本期新增未确认",IF(N(J19)>0.005,"●期末仍有未确认",IF(AND(O19<>"",ABS(N(P19))>0.005),"备查差异",IF(AND(R19<>"",ABS(N(S19))>0.005,OR(N(I19)>0.005,N(J19)>0.005)),"超额亏损·长投已冲减","—"))))
A20: =IF('权益法测算表G7-14'!B17="","",'权益法测算表G7-14'!B17) | C20: =IF(A20="","",'权益法测算表G7-14'!C17) | I20: =IF(OR(A20="",C20=""),"",IF((G20-F20)*C20>=0,-MIN(N(H20),(G20-F20)*C20),MAX(0,-(G20-F20)*C20-N(D20)-N(E20)-N(N20)))) | J20: =IF(A20="","",N(H20)+N(I20)) | L20: =IF(OR(A20="",C20=""),"",(G20-F20)*C20) | P20: =IF(OR(A20="",O20=""),"",N(J20)-N(O20)) | Q20: =IF(A20="","",IF(OR(C20<0,C20>1),"持股比例异常",IF(AND(N(I20)>0,N(D20)+N(E20)>0.005),"仍有账面余额却新增未确认，请复核冲减顺序",IF(AND(M20="是",N(N20)<=0),"有额外义务但未填预计负债",IF(AND(M20="否",N(N20)<>0),"无额外义务但填了预计负债",IF(AND(O20<>"",ABS(N(P20))>0.005),"与备查簿不一致",IF(N(J20)<-0.005,"期末未确认不能为负",IF(AND(R20<>"",ABS(N(S20))>0.005,N(J20)<=0.005,N(I20)<=0.005),"与G7-14长投期末不一致",IF(AND(R20<>"",ABS(N(S20))>0.005,OR(N(J20)>0.005,N(I20)>0.005)),"通过(超额亏损致长投差异，已关注)","通过"))))))))) | R20: =IF(A20="","",IFERROR(N('权益法测算表G7-14'!F31)+N('权益法测算表G7-14'!I31)+N('权益法测算表G7-14'!L31)+N('权益法测算表G7-14'!O31),"")) | S20: =IF(OR(A20="",R20=""),"",N(D20)-N(R20)) | T20: =IF(A20="","",IF(N(I20)>0.005,"▲本期新增未确认",IF(N(J20)>0.005,"●期末仍有未确认",IF(AND(O20<>"",ABS(N(P20))>0.005),"备查差异",IF(AND(R20<>"",ABS(N(S20))>0.005,OR(N(I20)>0.005,N(J20)>0.005)),"超额亏损·长投已冲减","—"))))
A21: =IF('权益法测算表G7-14'!B18="","",'权益法测算表G7-14'!B18) | C21: =IF(A21="","",'权益法测算表G7-14'!C18) | I21: =IF(OR(A21="",C21=""),"",IF((G21-F21)*C21>=0,-MIN(N(H21),(G21-F21)*C21),MAX(0,-(G21-F21)*C21-N(D21)-N(E21)-N(N21)))) | J21: =IF(A21="","",N(H21)+N(I21)) | L21: =IF(OR(A21="",C21=""),"",(G21-F21)*C21) | P21: =IF(OR(A21="",O21=""),"",N(J21)-N(O21)) | Q21: =IF(A21="","",IF(OR(C21<0,C21>1),"持股比例异常",IF(AND(N(I21)>0,N(D21)+N(E21)>0.005),"仍有账面余额却新增未确认，请复核冲减顺序",IF(AND(M21="是",N(N21)<=0),"有额外义务但未填预计负债",IF(AND(M21="否",N(N21)<>0),"无额外义务但填了预计负债",IF(AND(O21<>"",ABS(N(P21))>0.005),"与备查簿不一致",IF(N(J21)<-0.005,"期末未确认不能为负",IF(AND(R21<>"",ABS(N(S21))>0.005,N(J21)<=0.005,N(I21)<=0.005),"与G7-14长投期末不一致",IF(AND(R21<>"",ABS(N(S21))>0.005,OR(N(J21)>0.005,N(I21)>0.005)),"通过(超额亏损致长投差异，已关注)","通过"))))))))) | R21: =IF(A21="","",IFERROR(N('权益法测算表G7-14'!F32)+N('权益法测算表G7-14'!I32)+N('权益法测算表G7-14'!L32)+N('权益法测算表G7-14'!O32),"")) | S21: =IF(OR(A21="",R21=""),"",N(D21)-N(R21)) | T21: =IF(A21="","",IF(N(I21)>0.005,"▲本期新增未确认",IF(N(J21)>0.005,"●期末仍有未确认",IF(AND(O21<>"",ABS(N(P21))>0.005),"备查差异",IF(AND(R21<>"",ABS(N(S21))>0.005,OR(N(I21)>0.005,N(J21)>0.005)),"超额亏损·长投已冲减","—"))))
A22: =IF('权益法测算表G7-14'!B19="","",'权益法测算表G7-14'!B19) | C22: =IF(A22="","",'权益法测算表G7-14'!C19) | I22: =IF(OR(A22="",C22=""),"",IF((G22-F22)*C22>=0,-MIN(N(H22),(G22-F22)*C22),MAX(0,-(G22-F22)*C22-N(D22)-N(E22)-N(N22)))) | J22: =IF(A22="","",N(H22)+N(I22)) | L22: =IF(OR(A22="",C22=""),"",(G22-F22)*C22) | P22: =IF(OR(A22="",O22=""),"",N(J22)-N(O22)) | Q22: =IF(A22="","",IF(OR(C22<0,C22>1),"持股比例异常",IF(AND(N(I22)>0,N(D22)+N(E22)>0.005),"仍有账面余额却新增未确认，请复核冲减顺序",IF(AND(M22="是",N(N22)<=0),"有额外义务但未填预计负债",IF(AND(M22="否",N(N22)<>0),"无额外义务但填了预计负债",IF(AND(O22<>"",ABS(N(P22))>0.005),"与备查簿不一致",IF(N(J22)<-0.005,"期末未确认不能为负",IF(AND(R22<>"",ABS(N(S22))>0.005,N(J22)<=0.005,N(I22)<=0.005),"与G7-14长投期末不一致",IF(AND(R22<>"",ABS(N(S22))>0.005,OR(N(J22)>0.005,N(I22)>0.005)),"通过(超额亏损致长投差异，已关注)","通过"))))))))) | R22: =IF(A22="","",IFERROR(N('权益法测算表G7-14'!F33)+N('权益法测算表G7-14'!I33)+N('权益法测算表G7-14'!L33)+N('权益法测算表G7-14'!O33),"")) | S22: =IF(OR(A22="",R22=""),"",N(D22)-N(R22)) | T22: =IF(A22="","",IF(N(I22)>0.005,"▲本期新增未确认",IF(N(J22)>0.005,"●期末仍有未确认",IF(AND(O22<>"",ABS(N(P22))>0.005),"备查差异",IF(AND(R22<>"",ABS(N(S22))>0.005,OR(N(I22)>0.005,N(J22)>0.005)),"超额亏损·长投已冲减","—"))))
A23: =IF('权益法测算表G7-14'!B20="","",'权益法测算表G7-14'!B20) | C23: =IF(A23="","",'权益法测算表G7-14'!C20) | I23: =IF(OR(A23="",C23=""),"",IF((G23-F23)*C23>=0,-MIN(N(H23),(G23-F23)*C23),MAX(0,-(G23-F23)*C23-N(D23)-N(E23)-N(N23)))) | J23: =IF(A23="","",N(H23)+N(I23)) | L23: =IF(OR(A23="",C23=""),"",(G23-F23)*C23) | P23: =IF(OR(A23="",O23=""),"",N(J23)-N(O23)) | Q23: =IF(A23="","",IF(OR(C23<0,C23>1),"持股比例异常",IF(AND(N(I23)>0,N(D23)+N(E23)>0.005),"仍有账面余额却新增未确认，请复核冲减顺序",IF(AND(M23="是",N(N23)<=0),"有额外义务但未填预计负债",IF(AND(M23="否",N(N23)<>0),"无额外义务但填了预计负债",IF(AND(O23<>"",ABS(N(P23))>0.005),"与备查簿不一致",IF(N(J23)<-0.005,"期末未确认不能为负",IF(AND(R23<>"",ABS(N(S23))>0.005,N(J23)<=0.005,N(I23)<=0.005),"与G7-14长投期末不一致",IF(AND(R23<>"",ABS(N(S23))>0.005,OR(N(J23)>0.005,N(I23)>0.005)),"通过(超额亏损致长投差异，已关注)","通过"))))))))) | R23: =IF(A23="","",IFERROR(N('权益法测算表G7-14'!F34)+N('权益法测算表G7-14'!I34)+N('权益法测算表G7-14'!L34)+N('权益法测算表G7-14'!O34),"")) | S23: =IF(OR(A23="",R23=""),"",N(D23)-N(R23)) | T23: =IF(A23="","",IF(N(I23)>0.005,"▲本期新增未确认",IF(N(J23)>0.005,"●期末仍有未确认",IF(AND(O23<>"",ABS(N(P23))>0.005),"备查差异",IF(AND(R23<>"",ABS(N(S23))>0.005,OR(N(I23)>0.005,N(J23)>0.005)),"超额亏损·长投已冲减","—"))))
A24: 小 计 | C24: — | D24: =SUM(D19:D23) | E24: =SUM(E19:E23) | F24: — | G24: — | H24: =SUM(H19:H23) | I24: =SUM(I19:I23) | J24: =SUM(J19:J23) | L24: =SUM(L19:L23) | N24: =SUM(N19:N23) | O24: =SUM(O19:O23) | P24: =SUM(P19:P23) | Q24: =IF(COUNTA(A19:A23)=0,"","—") | R24: =SUM(R19:R23) | S24: =SUM(S19:S23) | T24: =IF(COUNTA(A19:23)=0,"","未确认"&COUNTIF(J19:23,">0")&"家")
A25: 合 计 | C25: — | D25: =D17+D24 | E25: =E17+E24 | F25: — | G25: — | H25: =H17+H24 | I25: =I17+I24 | J25: =J17+J24 | L25: =L17+L24 | N25: =N17+N24 | O25: =O17+O24 | P25: =P17+P24 | Q25: =IF(J25="","",IF(ABS(N(P25))>0.005,"合计与备查簿存在差异，见审计说明",IF(AND(ABS(N(S25))>0.005,N(J25)<=0.005),"合计与G7-14长投存在差异，见审计说明",IF(AND(ABS(N(S25))>0.005,N(J25)>0.005),"通过(含超额亏损长投差异)",IF(N(N25)>0,"存在应确认预计负债，请与负债科目勾稽","通过"))))) | R25: =R17+R24 | S25: =S17+S24 | T25: =IF(J25="","","合计未确认"&(COUNTIF(J12:J16,">0")+COUNTIF(J19:J23,">0"))&"家；"&IF(ABS(N(P25))>0.005,"备查有差；","")&IF(ABS(N(S25))>0.005,"与G7-14有差","勾稽正常"))
A26: 【填写提示】①名称/比例由G7-14自动带出；②期中比例变动请拆行；③⑯取G7-14长投期末，超额亏损冲减后③<⑯为常见可解释差异（关注列会提示）；④⑱关注列筛选需重点说明的被投资单位；⑤备查簿⑬与⑨必须勾稽。
A27: 三、审计说明：
A28: 【引导】无超额亏损：本期合营/联营企业未发生需登记备查的未确认投资损失，与备查簿及G7-14一致。 有数据时按被投资单位说明：①净资产变动及比例是否拆行；②冲减顺序；③额外义务/预计负债；④与备查簿差异；⑤与G7-14长投差异原因及是否提调整。
A30: 四、审计结论： | C30: 结论选用： | D30: A
A33: 编制说明：
A34: 1、③长期投资、④长期权益：取权益法核算后仍可抵减超额亏损的账面余额；④通常为长期应收款等实质净投资。跨主体的⑤⑥净资产不得合计。合营/联营各预留5行；不够可在同区段下方自行插入并同步公式。
A35: 2、⑧公式：S=(⑥-⑤)×②；S≥0时⑧=-MIN(⑦,S)；S<0时⑧=MAX(0,-S-③-④-⑫)。旧版“③+④-S”已废止。
A36: 3、期中比例变动必须拆行：每一行对应一个稳定持股区间的S测算；禁止用变动后比例乘全年净资产变动。变动依据索引至G7-4/工商/协议。
A37: 4、⑯从G7-14第2部分按名称汇总长投四明细期末；⑰=③-⑯。若④长期权益已单独列示，③应仅含长期股权投资科目，避免与G7-14重复。⑪选“是”时⑫填预计负债并与负债勾稽。
A38: 5、⑬备查簿与⑨勾稽；⑮自动提示比例/冲减顺序/义务/备查/G7-14异常。交叉索引：G7-14权益法、G7-15内部交易、G7-17减值。
A39: 参考结论：
A40: A、未见异常。
A41: B、除以下重大不符事项应当作为调整事项予以调整外，其余未见异常。
A42: C、由于存在以下重大未调整事项（或审计范围受到限制无法获取充分、适当证据），不可确认。

Sheet 减值测试表G7-17
A1: 致同会计师事务所
A2: 长期股权投资减值测试表
A3: =底稿目录!A2 | E3: =底稿目录!A4 | G3: =底稿目录!A5 | I3: 底稿目录!F23 | M3: 索引号： | N3: =底稿目录!F23
A4: =底稿目录!A3 | E4: =底稿目录!A6 | G4: =底稿目录!A7 | M4: 页 次：
A5: 一、审计目标： | C5: 确认长期股权投资是否存在减值迹象；可收回金额测算是否恰当；减值准备计提是否充分、准确，且减值损失未不当转回。
A6: 二、审计过程： | C6: 程序链：①从G7-14带出测试对象 → ②识别减值迹象（关注持续亏损与G7-16未确认损失）→ ③确定账面净额（勾稽G7-14/G7-2）→ ④双路径测算可收回金额 → ⑤应补提与账面计提比较 → ⑥检查不得转回 → ⑦与G7-16超额亏损衔接 → ⑧结论。 ｜ 边界：金融资产/商誉减值见相应底稿；账面已因超额亏损冲至零时，重点关注其他长期权益与预计负债。
A7: 【联动】名称取数见M9；第3节比例/账面/类型自动取G7-14；X/Y列勾稽G7-16未确认损失。橙色输入、绿色公式。
A8: 1. 减值迹象识别（按被投资单位填列；存在任一“是”则通常进入金额测试）
A9: 考虑事项（长期股权投资） | F9: 公司1 | G9: 公司2 | H9: 公司3 | I9: 公司4 | J9: 公司5 | K9: 证据/索引 | L9: 名称取数 | M9: 合营前5
A10: 被投资单位名称 | F10: =IF($M$9="联营前5",IF('权益法测算表G7-14'!B16="","",'权益法测算表G7-14'!B16),IF('权益法测算表G7-14'!B11="","",'权益法测算表G7-14'!B11)) | G10: =IF($M$9="联营前5",IF('权益法测算表G7-14'!B17="","",'权益法测算表G7-14'!B17),IF('权益法测算表G7-14'!B12="","",'权益法测算表G7-14'!B12)) | H10: =IF($M$9="联营前5",IF('权益法测算表G7-14'!B18="","",'权益法测算表G7-14'!B18),IF('权益法测算表G7-14'!B13="","",'权益法测算表G7-14'!B13)) | I10: =IF($M$9="联营前5",IF('权益法测算表G7-14'!B19="","",'权益法测算表G7-14'!B19),IF('权益法测算表G7-14'!B14="","",'权益法测算表G7-14'!B14)) | J10: =IF($M$9="联营前5",IF('权益法测算表G7-14'!B20="","",'权益法测算表G7-14'!B20),IF('权益法测算表G7-14'!B15="","",'权益法测算表G7-14'!B15))
A11: 市价/估值显著低于账面价值，且非暂时性
A12: 被投资单位持续亏损或净资产大幅下降
A13: 经营现金流恶化、债务违约或资金链紧张
A14: 行业/政策/许可等外部环境发生重大不利变化
A15: 实际业绩显著低于投资决策时的盈利预测
A16: 关键客户流失、核心业务停滞或计划提前处置/退出
A17: 市场利率或必要报酬率上升，导致现值大幅降低
A18: 其他减值迹象（请在说明中描述）
A19: 是否存在减值迹象（自动） | F19: =IF(F10="","",IF(COUNTIF(F11:F18,"是")>0,"是",IF(COUNTIF(F11:F18,"否")=8,"否","请完整填列迹象"))) | G19: =IF(G10="","",IF(COUNTIF(G11:G18,"是")>0,"是",IF(COUNTIF(G11:G18,"否")=8,"否","请完整填列迹象"))) | H19: =IF(H10="","",IF(COUNTIF(H11:H18,"是")>0,"是",IF(COUNTIF(H11:H18,"否")=8,"否","请完整填列迹象"))) | I19: =IF(I10="","",IF(COUNTIF(I11:I18,"是")>0,"是",IF(COUNTIF(I11:I18,"否")=8,"否","请完整填列迹象"))) | J19: =IF(J10="","",IF(COUNTIF(J11:J18,"是")>0,"是",IF(COUNTIF(J11:J18,"否")=8,"否","请完整填列迹象")))
A20: 进入金额测试？ | F20: =IF(F19="","",IF(F19="是","是-进入第3节",IF(F19="否","否-记录证据即可","待补全"))) | G20: =IF(G19="","",IF(G19="是","是-进入第3节",IF(G19="否","否-记录证据即可","待补全"))) | H20: =IF(H19="","",IF(H19="是","是-进入第3节",IF(H19="否","否-记录证据即可","待补全"))) | I20: =IF(I19="","",IF(I19="是","是-进入第3节",IF(I19="否","否-记录证据即可","待补全"))) | J20: =IF(J19="","",IF(J19="是","是-进入第3节",IF(J19="否","否-记录证据即可","待补全")))
A22: 2. 利用专家工作（依赖评估/现金流折现模型时填列）
A23: 序号 | B23: 复核事项 | E23: 公司1 | F23: 公司2 | G23: 公司3 | H23: 公司4 | I23: 公司5 | J23: 结论/说明 | L23: 索引号
A24: 1 | B24: 专家胜任能力、资质与客观性
A25: 2 | B25: 工作范围、估值目的与报告日是否适当
A26: 3 | B26: 估值方法是否符合CAS8/相关指南
A27: 4 | B27: 关键假设：折现率、增长率、预测期、终值
A28: 5 | B28: 基础数据来源及与实际业绩/预算的勾稽
A29: 6 | B29: 审计人员复核结论：可否依赖
A31: 3. 减值金额测试（可收回金额=MAX(公允价值减处置费用, 预计未来现金流量现值)）
A32: 被投资单位 | B32: 长投账面原值 | C32: 测试前累计减值准备 | D32: 测试前账面净额①=B−C | E32: 持股比例 | F32: 路径一：公允价值减处置费用 | I32: 路径二：预计未来现金流量现值 | K32: 可收回金额②=MAX(H,J) | L32: 本期应补提减值③=MAX(①−②,0) | M32: 本期账面实际计提④ | N32: 少提/(多提)⑤=③−④ | O32: 是否超重要性 | P32: 复核 | Q32: 投资类型 | R32: 权益法内含商誉 | S32: 合并层单独商誉? | T32: 未采用另一路径原因 | U32: 安全边际=②−① | V32: 安全边际率 | W32: 应计提≤净额? | X32: G7-16期末 未确认损失 | Y32: 超额亏损/ 减值衔接提示
F33: 公允价值 | G33: 处置费用 | H33: FV−费用 | I33: 现值依据/索引 | J33: 预计现金流量现值
A34: 辅助参考（可选）：被投资单位净资产公允价值×持股比例 | F34: 净资产FV | G34: ×比例份额 | H34: 与可收回金额差异 | I34: 说明：仅作参考，不得直接替代可收回金额 | O34: 重要性水平
A35: =F10 | B35: =IF(A35="","",IFERROR(INDEX('权益法测算表G7-14'!$Q$25:$Q$34,MATCH(A35,'权益法测算表G7-14'!$B$25:$B$34,0)),"")) | D35: =IF(A35="","",N(B35)-N(C35)) | E35: =IF(A35="","",IFERROR(INDEX('权益法测算表G7-14'!$C$11:$C$20,MATCH(A35,'权益法测算表G7-14'!$B$11:$B$20,0)),"")) | H35: =IF(OR(A35="",F35=""),"",N(F35)-N(G35)) | K35: =IF(A35="","",IF(AND(H35="",J35=""),"",MAX(IF(H35="",0,N(H35)),IF(J35="",0,N(J35)),0))) | L35: =IF(OR(A35="",K35=""),"",MAX(N(D35)-N(K35),0)) | N35: =IF(OR(A35="",L35=""),"",N(L35)-N(M35)) | O35: =IF(A35="","",IF($P$34="","请填重要性水平",IF(ABS(N(N35))>N($P$34),"超过","未超过"))) | P35: =IF(A35="","",IF(B35="","账面原值未填",IF(AND(H35="",J35=""),"可收回金额两路径均未填",IF(AND(OR(AND(H35<>"",J35=""),AND(H35="",J35<>"")),T35=""),"单路径须说明未采用另一路径原因",IF(Q35="","投资类型未填",IF(AND(H35<>"",H35<0),"公允价值减费用为负已按0计入可收回-请复核",IF(M35="","本期实际计提未填",IF(W35<>"通过",W35,IF(O35="超过","存在超重要性差异-需说明",IF(O35="请填重要性水平","待填重要性水平",IF(AND(U35<>"",U35>=0,U35<N(D35)*0.1),"安全边际偏低-建议敏感性分析","通过"))))))))))) | Q35: =IF(A35="","",IF(ISNUMBER(MATCH(A35,'权益法测算表G7-14'!$B$11:$B$15,0)),"合营企业",IF(ISNUMBER(MATCH(A35,'权益法测算表G7-14'!$B$16:$B$20,0)),"联营企业","请核对"))) | U35: =IF(OR(A35="",K35=""),"",N(K35)-N(D35)) | V35: =IF(OR(A35="",D35="",N(D35)=0),"",N(U35)/N(D35)) | W35: =IF(OR(A35="",L35=""),"",IF(N(L35)-N(D35)>0.01,"异常-应计提超过账面净额","通过")) | X35: =IF(A35="","",IFERROR(SUMIF('未确认投资损失测试表G7-16'!$A$12:$A$16,A35,'未确认投资损失测试表G7-16'!$J$12:$J$16),0)+IFERROR(SUMIF('未确认投资损失测试表G7-16'!$A$19:$A$23,A35,'未确认投资损失测试表G7-16'!$J$19:$J$23),0)) | Y35: =IF(A35="","",IF(AND(N(X35)>0.005,N(D35)<=0.005),"▲账面≈0且有未确认损失：长投减值空间有限，转查G7-16长权益/预计负债",IF(AND(N(X35)>0.005,N(D35)>0.005),"●有未确认损失但仍有账面-核对冲减顺序与减值是否重复",IF(N(X35)>0.005,"见G7-16未确认损失","—"))))
A36: =G10 | B36: =IF(A36="","",IFERROR(INDEX('权益法测算表G7-14'!$Q$25:$Q$34,MATCH(A36,'权益法测算表G7-14'!$B$25:$B$34,0)),"")) | D36: =IF(A36="","",N(B36)-N(C36)) | E36: =IF(A36="","",IFERROR(INDEX('权益法测算表G7-14'!$C$11:$C$20,MATCH(A36,'权益法测算表G7-14'!$B$11:$B$20,0)),"")) | H36: =IF(OR(A36="",F36=""),"",N(F36)-N(G36)) | K36: =IF(A36="","",IF(AND(H36="",J36=""),"",MAX(IF(H36="",0,N(H36)),IF(J36="",0,N(J36)),0))) | L36: =IF(OR(A36="",K36=""),"",MAX(N(D36)-N(K36),0)) | N36: =IF(OR(A36="",L36=""),"",N(L36)-N(M36)) | O36: =IF(A36="","",IF($P$34="","请填重要性水平",IF(ABS(N(N36))>N($P$34),"超过","未超过"))) | P36: =IF(A36="","",IF(B36="","账面原值未填",IF(AND(H36="",J36=""),"可收回金额两路径均未填",IF(AND(OR(AND(H36<>"",J36=""),AND(H36="",J36<>"")),T36=""),"单路径须说明未采用另一路径原因",IF(Q36="","投资类型未填",IF(AND(H36<>"",H36<0),"公允价值减费用为负已按0计入可收回-请复核",IF(M36="","本期实际计提未填",IF(W36<>"通过",W36,IF(O36="超过","存在超重要性差异-需说明",IF(O36="请填重要性水平","待填重要性水平",IF(AND(U36<>"",U36>=0,U36<N(D36)*0.1),"安全边际偏低-建议敏感性分析","通过"))))))))))) | Q36: =IF(A36="","",IF(ISNUMBER(MATCH(A36,'权益法测算表G7-14'!$B$11:$B$15,0)),"合营企业",IF(ISNUMBER(MATCH(A36,'权益法测算表G7-14'!$B$16:$B$20,0)),"联营企业","请核对"))) | U36: =IF(OR(A36="",K36=""),"",N(K36)-N(D36)) | V36: =IF(OR(A36="",D36="",N(D36)=0),"",N(U36)/N(D36)) | W36: =IF(OR(A36="",L36=""),"",IF(N(L36)-N(D36)>0.01,"异常-应计提超过账面净额","通过")) | X36: =IF(A36="","",IFERROR(SUMIF('未确认投资损失测试表G7-16'!$A$12:$A$16,A36,'未确认投资损失测试表G7-16'!$J$12:$J$16),0)+IFERROR(SUMIF('未确认投资损失测试表G7-16'!$A$19:$A$23,A36,'未确认投资损失测试表G7-16'!$J$19:$J$23),0)) | Y36: =IF(A36="","",IF(AND(N(X36)>0.005,N(D36)<=0.005),"▲账面≈0且有未确认损失：长投减值空间有限，转查G7-16长权益/预计负债",IF(AND(N(X36)>0.005,N(D36)>0.005),"●有未确认损失但仍有账面-核对冲减顺序与减值是否重复",IF(N(X36)>0.005,"见G7-16未确认损失","—"))))
A37: =H10 | B37: =IF(A37="","",IFERROR(INDEX('权益法测算表G7-14'!$Q$25:$Q$34,MATCH(A37,'权益法测算表G7-14'!$B$25:$B$34,0)),"")) | D37: =IF(A37="","",N(B37)-N(C37)) | E37: =IF(A37="","",IFERROR(INDEX('权益法测算表G7-14'!$C$11:$C$20,MATCH(A37,'权益法测算表G7-14'!$B$11:$B$20,0)),"")) | H37: =IF(OR(A37="",F37=""),"",N(F37)-N(G37)) | K37: =IF(A37="","",IF(AND(H37="",J37=""),"",MAX(IF(H37="",0,N(H37)),IF(J37="",0,N(J37)),0))) | L37: =IF(OR(A37="",K37=""),"",MAX(N(D37)-N(K37),0)) | N37: =IF(OR(A37="",L37=""),"",N(L37)-N(M37)) | O37: =IF(A37="","",IF($P$34="","请填重要性水平",IF(ABS(N(N37))>N($P$34),"超过","未超过"))) | P37: =IF(A37="","",IF(B37="","账面原值未填",IF(AND(H37="",J37=""),"可收回金额两路径均未填",IF(AND(OR(AND(H37<>"",J37=""),AND(H37="",J37<>"")),T37=""),"单路径须说明未采用另一路径原因",IF(Q37="","投资类型未填",IF(AND(H37<>"",H37<0),"公允价值减费用为负已按0计入可收回-请复核",IF(M37="","本期实际计提未填",IF(W37<>"通过",W37,IF(O37="超过","存在超重要性差异-需说明",IF(O37="请填重要性水平","待填重要性水平",IF(AND(U37<>"",U37>=0,U37<N(D37)*0.1),"安全边际偏低-建议敏感性分析","通过"))))))))))) | Q37: =IF(A37="","",IF(ISNUMBER(MATCH(A37,'权益法测算表G7-14'!$B$11:$B$15,0)),"合营企业",IF(ISNUMBER(MATCH(A37,'权益法测算表G7-14'!$B$16:$B$20,0)),"联营企业","请核对"))) | U37: =IF(OR(A37="",K37=""),"",N(K37)-N(D37)) | V37: =IF(OR(A37="",D37="",N(D37)=0),"",N(U37)/N(D37)) | W37: =IF(OR(A37="",L37=""),"",IF(N(L37)-N(D37)>0.01,"异常-应计提超过账面净额","通过")) | X37: =IF(A37="","",IFERROR(SUMIF('未确认投资损失测试表G7-16'!$A$12:$A$16,A37,'未确认投资损失测试表G7-16'!$J$12:$J$16),0)+IFERROR(SUMIF('未确认投资损失测试表G7-16'!$A$19:$A$23,A37,'未确认投资损失测试表G7-16'!$J$19:$J$23),0)) | Y37: =IF(A37="","",IF(AND(N(X37)>0.005,N(D37)<=0.005),"▲账面≈0且有未确认损失：长投减值空间有限，转查G7-16长权益/预计负债",IF(AND(N(X37)>0.005,N(D37)>0.005),"●有未确认损失但仍有账面-核对冲减顺序与减值是否重复",IF(N(X37)>0.005,"见G7-16未确认损失","—"))))
A38: =I10 | B38: =IF(A38="","",IFERROR(INDEX('权益法测算表G7-14'!$Q$25:$Q$34,MATCH(A38,'权益法测算表G7-14'!$B$25:$B$34,0)),"")) | D38: =IF(A38="","",N(B38)-N(C38)) | E38: =IF(A38="","",IFERROR(INDEX('权益法测算表G7-14'!$C$11:$C$20,MATCH(A38,'权益法测算表G7-14'!$B$11:$B$20,0)),"")) | H38: =IF(OR(A38="",F38=""),"",N(F38)-N(G38)) | K38: =IF(A38="","",IF(AND(H38="",J38=""),"",MAX(IF(H38="",0,N(H38)),IF(J38="",0,N(J38)),0))) | L38: =IF(OR(A38="",K38=""),"",MAX(N(D38)-N(K38),0)) | N38: =IF(OR(A38="",L38=""),"",N(L38)-N(M38)) | O38: =IF(A38="","",IF($P$34="","请填重要性水平",IF(ABS(N(N38))>N($P$34),"超过","未超过"))) | P38: =IF(A38="","",IF(B38="","账面原值未填",IF(AND(H38="",J38=""),"可收回金额两路径均未填",IF(AND(OR(AND(H38<>"",J38=""),AND(H38="",J38<>"")),T38=""),"单路径须说明未采用另一路径原因",IF(Q38="","投资类型未填",IF(AND(H38<>"",H38<0),"公允价值减费用为负已按0计入可收回-请复核",IF(M38="","本期实际计提未填",IF(W38<>"通过",W38,IF(O38="超过","存在超重要性差异-需说明",IF(O38="请填重要性水平","待填重要性水平",IF(AND(U38<>"",U38>=0,U38<N(D38)*0.1),"安全边际偏低-建议敏感性分析","通过"))))))))))) | Q38: =IF(A38="","",IF(ISNUMBER(MATCH(A38,'权益法测算表G7-14'!$B$11:$B$15,0)),"合营企业",IF(ISNUMBER(MATCH(A38,'权益法测算表G7-14'!$B$16:$B$20,0)),"联营企业","请核对"))) | U38: =IF(OR(A38="",K38=""),"",N(K38)-N(D38)) | V38: =IF(OR(A38="",D38="",N(D38)=0),"",N(U38)/N(D38)) | W38: =IF(OR(A38="",L38=""),"",IF(N(L38)-N(D38)>0.01,"异常-应计提超过账面净额","通过")) | X38: =IF(A38="","",IFERROR(SUMIF('未确认投资损失测试表G7-16'!$A$12:$A$16,A38,'未确认投资损失测试表G7-16'!$J$12:$J$16),0)+IFERROR(SUMIF('未确认投资损失测试表G7-16'!$A$19:$A$23,A38,'未确认投资损失测试表G7-16'!$J$19:$J$23),0)) | Y38: =IF(A38="","",IF(AND(N(X38)>0.005,N(D38)<=0.005),"▲账面≈0且有未确认损失：长投减值空间有限，转查G7-16长权益/预计负债",IF(AND(N(X38)>0.005,N(D38)>0.005),"●有未确认损失但仍有账面-核对冲减顺序与减值是否重复",IF(N(X38)>0.005,"见G7-16未确认损失","—"))))
A39: =J10 | B39: =IF(A39="","",IFERROR(INDEX('权益法测算表G7-14'!$Q$25:$Q$34,MATCH(A39,'权益法测算表G7-14'!$B$25:$B$34,0)),"")) | D39: =IF(A39="","",N(B39)-N(C39)) | E39: =IF(A39="","",IFERROR(INDEX('权益法测算表G7-14'!$C$11:$C$20,MATCH(A39,'权益法测算表G7-14'!$B$11:$B$20,0)),"")) | H39: =IF(OR(A39="",F39=""),"",N(F39)-N(G39)) | K39: =IF(A39="","",IF(AND(H39="",J39=""),"",MAX(IF(H39="",0,N(H39)),IF(J39="",0,N(J39)),0))) | L39: =IF(OR(A39="",K39=""),"",MAX(N(D39)-N(K39),0)) | N39: =IF(OR(A39="",L39=""),"",N(L39)-N(M39)) | O39: =IF(A39="","",IF($P$34="","请填重要性水平",IF(ABS(N(N39))>N($P$34),"超过","未超过"))) | P39: =IF(A39="","",IF(B39="","账面原值未填",IF(AND(H39="",J39=""),"可收回金额两路径均未填",IF(AND(OR(AND(H39<>"",J39=""),AND(H39="",J39<>"")),T39=""),"单路径须说明未采用另一路径原因",IF(Q39="","投资类型未填",IF(AND(H39<>"",H39<0),"公允价值减费用为负已按0计入可收回-请复核",IF(M39="","本期实际计提未填",IF(W39<>"通过",W39,IF(O39="超过","存在超重要性差异-需说明",IF(O39="请填重要性水平","待填重要性水平",IF(AND(U39<>"",U39>=0,U39<N(D39)*0.1),"安全边际偏低-建议敏感性分析","通过"))))))))))) | Q39: =IF(A39="","",IF(ISNUMBER(MATCH(A39,'权益法测算表G7-14'!$B$11:$B$15,0)),"合营企业",IF(ISNUMBER(MATCH(A39,'权益法测算表G7-14'!$B$16:$B$20,0)),"联营企业","请核对"))) | U39: =IF(OR(A39="",K39=""),"",N(K39)-N(D39)) | V39: =IF(OR(A39="",D39="",N(D39)=0),"",N(U39)/N(D39)) | W39: =IF(OR(A39="",L39=""),"",IF(N(L39)-N(D39)>0.01,"异常-应计提超过账面净额","通过")) | X39: =IF(A39="","",IFERROR(SUMIF('未确认投资损失测试表G7-16'!$A$12:$A$16,A39,'未确认投资损失测试表G7-16'!$J$12:$J$16),0)+IFERROR(SUMIF('未确认投资损失测试表G7-16'!$A$19:$A$23,A39,'未确认投资损失测试表G7-16'!$J$19:$J$23),0)) | Y39: =IF(A39="","",IF(AND(N(X39)>0.005,N(D39)<=0.005),"▲账面≈0且有未确认损失：长投减值空间有限，转查G7-16长权益/预计负债",IF(AND(N(X39)>0.005,N(D39)>0.005),"●有未确认损失但仍有账面-核对冲减顺序与减值是否重复",IF(N(X39)>0.005,"见G7-16未确认损失","—"))))
A40: 辅助参考明细（可选填）：净资产公允价值份额 vs 可收回金额
A41: 被投资单位 | B41: 净资产公允价值 | C41: 持股比例 | D41: 份额=B×C | E41: 可收回金额(引自上表) | F41: 份额−可收回 | G41: 说明
A42: =A35 | C42: =E35 | D42: =IF(OR(A42="",B42=""),"",N(B42)*N(C42)) | E42: =K35 | F42: =IF(OR(D42="",E42=""),"",N(D42)-N(E42))
A43: =A36 | C43: =E36 | D43: =IF(OR(A43="",B43=""),"",N(B43)*N(C43)) | E43: =K36 | F43: =IF(OR(D43="",E43=""),"",N(D43)-N(E43))
A44: =A37 | C44: =E37 | D44: =IF(OR(A44="",B44=""),"",N(B44)*N(C44)) | E44: =K37 | F44: =IF(OR(D44="",E44=""),"",N(D44)-N(E44))
A45: =A38 | C45: =E38 | D45: =IF(OR(A45="",B45=""),"",N(B45)*N(C45)) | E45: =K38 | F45: =IF(OR(D45="",E45=""),"",N(D45)-N(E45))
A46: =A39 | C46: =E39 | D46: =IF(OR(A46="",B46=""),"",N(B46)*N(C46)) | E46: =K39 | F46: =IF(OR(D46="",E46=""),"",N(D46)-N(E46))
A49: 4. 测试结果汇总
A50: 项目 | C50: 金额 | E50: 说明
A51: 本期应补提减值合计③ | C51: =SUM(L35:L39) | E51: 各被投资单位应计提减值之和
A52: 本期账面实际计提合计④ | C52: =SUM(M35:M39) | E52: 与G7-2减值准备勾稽
A53: 各项目少提合计（仅正差异，禁止净额） | C53: =SUMIF(N35:N39,">0") | E53: 不同被投资单位不得正负抵销
A54: 建议补提金额（=少提合计） | C54: =C53 | E54: 可据以编制补提调整分录
A55: 可能计提偏高合计（仅负差异绝对值） | C55: =ABS(SUMIF(N35:N39,"<0")) | E55: 不得据此转回；仅作调查/说明事项
A56: 5. 减值转回检查（长期股权投资减值损失原则上不得转回）
A57: 被投资单位 | B57: 本期是否转回以前年度减值 | C57: 转回金额 | D57: 转回理由（账面） | E57: 审计结论 | F57: 索引
A58: =A35 | E58: =IF(A58="","",IF(OR(B58="否",B58=""),"通过",IF(OR(B58="是",N(C58)>0),"异常-减值原则上不得转回-需追查","请填是/否")))
A59: =A36 | E59: =IF(A59="","",IF(OR(B59="否",B59=""),"通过",IF(OR(B59="是",N(C59)>0),"异常-减值原则上不得转回-需追查","请填是/否")))
A60: =A37 | E60: =IF(A60="","",IF(OR(B60="否",B60=""),"通过",IF(OR(B60="是",N(C60)>0),"异常-减值原则上不得转回-需追查","请填是/否")))
A61: =A38 | E61: =IF(A61="","",IF(OR(B61="否",B61=""),"通过",IF(OR(B61="是",N(C61)>0),"异常-减值原则上不得转回-需追查","请填是/否")))
A62: =A39 | E62: =IF(A62="","",IF(OR(B62="否",B62=""),"通过",IF(OR(B62="是",N(C62)>0),"异常-减值原则上不得转回-需追查","请填是/否")))
A65: 6. 与明细表G7-2审定期末账面勾稽
A66: 被投资单位 | B66: 本表测试前净额 | C66: G7-2审定期末金额 | D66: 差异 | E66: 勾稽结论
A67: =A35 | B67: =D35 | C67: =IF(A67="","",IFERROR(INDEX('明细表G7-2'!$AI$16:$AI$25,MATCH(A67,'明细表G7-2'!$B$16:$B$25,0)),IFERROR(INDEX('明细表G7-2'!$BB$33:$BB$37,MATCH(A67,'明细表G7-2'!$B$33:$B$37,0)),IFERROR(INDEX('明细表G7-2'!$BB$40:$BB$44,MATCH(A67,'明细表G7-2'!$B$40:$B$44,0)),"未匹配")))) | D67: =IF(OR(A67="",C67="未匹配",C67=""),"",N(B67)-N(C67)) | E67: =IF(A67="","",IF(OR(C67="未匹配",C67=""),"未匹配G7-2",IF($P$34="","请填重要性水平",IF(ABS(N(D67))>N($P$34),"超过重要性-需说明","通过"))))
A68: =A36 | B68: =D36 | C68: =IF(A68="","",IFERROR(INDEX('明细表G7-2'!$AI$16:$AI$25,MATCH(A68,'明细表G7-2'!$B$16:$B$25,0)),IFERROR(INDEX('明细表G7-2'!$BB$33:$BB$37,MATCH(A68,'明细表G7-2'!$B$33:$B$37,0)),IFERROR(INDEX('明细表G7-2'!$BB$40:$BB$44,MATCH(A68,'明细表G7-2'!$B$40:$B$44,0)),"未匹配")))) | D68: =IF(OR(A68="",C68="未匹配",C68=""),"",N(B68)-N(C68)) | E68: =IF(A68="","",IF(OR(C68="未匹配",C68=""),"未匹配G7-2",IF($P$34="","请填重要性水平",IF(ABS(N(D68))>N($P$34),"超过重要性-需说明","通过"))))
A69: =A37 | B69: =D37 | C69: =IF(A69="","",IFERROR(INDEX('明细表G7-2'!$AI$16:$AI$25,MATCH(A69,'明细表G7-2'!$B$16:$B$25,0)),IFERROR(INDEX('明细表G7-2'!$BB$33:$BB$37,MATCH(A69,'明细表G7-2'!$B$33:$B$37,0)),IFERROR(INDEX('明细表G7-2'!$BB$40:$BB$44,MATCH(A69,'明细表G7-2'!$B$40:$B$44,0)),"未匹配")))) | D69: =IF(OR(A69="",C69="未匹配",C69=""),"",N(B69)-N(C69)) | E69: =IF(A69="","",IF(OR(C69="未匹配",C69=""),"未匹配G7-2",IF($P$34="","请填重要性水平",IF(ABS(N(D69))>N($P$34),"超过重要性-需说明","通过"))))
A70: =A38 | B70: =D38 | C70: =IF(A70="","",IFERROR(INDEX('明细表G7-2'!$AI$16:$AI$25,MATCH(A70,'明细表G7-2'!$B$16:$B$25,0)),IFERROR(INDEX('明细表G7-2'!$BB$33:$BB$37,MATCH(A70,'明细表G7-2'!$B$33:$B$37,0)),IFERROR(INDEX('明细表G7-2'!$BB$40:$BB$44,MATCH(A70,'明细表G7-2'!$B$40:$B$44,0)),"未匹配")))) | D70: =IF(OR(A70="",C70="未匹配",C70=""),"",N(B70)-N(C70)) | E70: =IF(A70="","",IF(OR(C70="未匹配",C70=""),"未匹配G7-2",IF($P$34="","请填重要性水平",IF(ABS(N(D70))>N($P$34),"超过重要性-需说明","通过"))))
A71: =A39 | B71: =D39 | C71: =IF(A71="","",IFERROR(INDEX('明细表G7-2'!$AI$16:$AI$25,MATCH(A71,'明细表G7-2'!$B$16:$B$25,0)),IFERROR(INDEX('明细表G7-2'!$BB$33:$BB$37,MATCH(A71,'明细表G7-2'!$B$33:$B$37,0)),IFERROR(INDEX('明细表G7-2'!$BB$40:$BB$44,MATCH(A71,'明细表G7-2'!$B$40:$B$44,0)),"未匹配")))) | D71: =IF(OR(A71="",C71="未匹配",C71=""),"",N(B71)-N(C71)) | E71: =IF(A71="","",IF(OR(C71="未匹配",C71=""),"未匹配G7-2",IF($P$34="","请填重要性水平",IF(ABS(N(D71))>N($P$34),"超过重要性-需说明","通过"))))
A74: 三、审计说明
A75: （自动汇总异常/待跟进；可继续手工补充）
A76: =IF(COUNTA(F10:J10)=0,"（尚未录入被投资单位。请先在第1节填写公司名称并判断减值迹象。）",IF(TEXTJOIN("；",TRUE,IF(AND(F19<>"",F19<>"是",F19<>"否"),F10&"迹象:"&F19,""),IF(AND(G19<>"",G19<>"是",G19<>"否"),G10&"迹象:"&G19,""),IF(AND(H19<>"",H19<>"是",H19<>"否"),H10&"迹象:"&H19,""),IF(AND(I19<>"",I19<>"是",I19<>"否"),I10&"迹象:"&I19,""),IF(AND(J19<>"",J19<>"是",J19<>"否"),J10&"迹象:"&J19,""),IF(AND(P35<>"",P35<>"通过"),IF(A35="","行35",A35)&"："&P35,""),IF(AND(W35<>"",W35<>"通过"),IF(A35="","",A35&"：")&W35,""),IF(AND(P36<>"",P36<>"通过"),IF(A36="","行36",A36)&"："&P36,""),IF(AND(W36<>"",W36<>"通过"),IF(A36="","",A36&"：")&W36,""),IF(AND(P37<>"",P37<>"通过"),IF(A37="","行37",A37)&"："&P37,""),IF(AND(W37<>"",W37<>"通过"),IF(A37="","",A37&"：")&W37,""),IF(AND(P38<>"",P38<>"通过"),IF(A38="","行38",A38)&"："&P38,""),IF(AND(W38<>"",W38<>"通过"),IF(A38="","",A38&"：")&W38,""),IF(AND(P39<>"",P39<>"通过"),IF(A39="","行39",A39)&"："&P39,""),IF(AND(W39<>"",W39<>"通过"),IF(A39="","",A39&"：")&W39,""),IF(AND(E58<>"",E58<>"通过"),IF(A58="","",A58&"：")&E58,""),IF(AND(E59<>"",E59<>"通过"),IF(A59="","",A59&"：")&E59,""),IF(AND(E60<>"",E60<>"通过"),IF(A60="","",A60&"：")&E60,""),IF(AND(E61<>"",E61<>"通过"),IF(A61="","",A61&"：")&E61,""),IF(AND(E62<>"",E62<>"通过"),IF(A62="","",A62&"：")&E62,""),IF(AND(E67<>"",E67<>"通过"),IF(A67="","",A67&"勾稽：")&E67,""),IF(AND(E68<>"",E68<>"通过"),IF(A68="","",A68&"勾稽：")&E68,""),IF(AND(E69<>"",E69<>"通过"),IF(A69="","",A69&"勾稽：")&E69,""),IF(AND(E70<>"",E70<>"通过"),IF(A70="","",A70&"勾稽：")&E70,""),IF(AND(E71<>"",E71<>"通过"),IF(A71="","",A71&"勾稽：")&E71,""),IF(AND(I98<>"",I98<>"通过"),IF(A98="","",A98&"敏感性：")&I98,""),IF(AND(I99<>"",I99<>"通过"),IF(A99="","",A99&"敏感性：")&I99,""),IF(AND(I100<>"",I100<>"通过"),IF(A100="","",A100&"敏感性：")&I100,""),IF(AND(I101<>"",I101<>"通过"),IF(A101="","",A101&"敏感性：")&I101,""),IF(AND(I102<>"",I102<>"通过"),IF(A102="","",A102&"敏感性：")&I102,""))="","各节自动复核未发现未通过项。少提合计见C53，建议补提见C54；可能偏高见C55（不得转回）。",TEXTJOIN("；",TRUE,IF(AND(F19<>"",F19<>"是",F19<>"否"),F10&"迹象:"&F19,""),IF(AND(G19<>"",G19<>"是",G19<>"否"),G10&"迹象:"&G19,""),IF(AND(H19<>"",H19<>"是",H19<>"否"),H10&"迹象:"&H19,""),IF(AND(I19<>"",I19<>"是",I19<>"否"),I10&"迹象:"&I19,""),IF(AND(J19<>"",J19<>"是",J19<>"否"),J10&"迹象:"&J19,""),IF(AND(P35<>"",P35<>"通过"),IF(A35="","行35",A35)&"："&P35,""),IF(AND(W35<>"",W35<>"通过"),IF(A35="","",A35&"：")&W35,""),IF(AND(P36<>"",P36<>"通过"),IF(A36="","行36",A36)&"："&P36,""),IF(AND(W36<>"",W36<>"通过"),IF(A36="","",A36&"：")&W36,""),IF(AND(P37<>"",P37<>"通过"),IF(A37="","行37",A37)&"："&P37,""),IF(AND(W37<>"",W37<>"通过"),IF(A37="","",A37&"：")&W37,""),IF(AND(P38<>"",P38<>"通过"),IF(A38="","行38",A38)&"："&P38,""),IF(AND(W38<>"",W38<>"通过"),IF(A38="","",A38&"：")&W38,""),IF(AND(P39<>"",P39<>"通过"),IF(A39="","行39",A39)&"："&P39,""),IF(AND(W39<>"",W39<>"通过"),IF(A39="","",A39&"：")&W39,""),IF(AND(E58<>"",E58<>"通过"),IF(A58="","",A58&"：")&E58,""),IF(AND(E59<>"",E59<>"通过"),IF(A59="","",A59&"：")&E59,""),IF(AND(E60<>"",E60<>"通过"),IF(A60="","",A60&"：")&E60,""),IF(AND(E61<>"",E61<>"通过"),IF(A61="","",A61&"：")&E61,""),IF(AND(E62<>"",E62<>"通过"),IF(A62="","",A62&"：")&E62,""),IF(AND(E67<>"",E67<>"通过"),IF(A67="","",A67&"勾稽：")&E67,""),IF(AND(E68<>"",E68<>"通过"),IF(A68="","",A68&"勾稽：")&E68,""),IF(AND(E69<>"",E69<>"通过"),IF(A69="","",A69&"勾稽：")&E69,""),IF(AND(E70<>"",E70<>"通过"),IF(A70="","",A70&"勾稽：")&E70,""),IF(AND(E71<>"",E71<>"通过"),IF(A71="","",A71&"勾稽：")&E71,""),IF(AND(I98<>"",I98<>"通过"),IF(A98="","",A98&"敏感性：")&I98,""),IF(AND(I99<>"",I99<>"通过"),IF(A99="","",A99&"敏感性：")&I99,""),IF(AND(I100<>"",I100<>"通过"),IF(A100="","",A100&"敏感性：")&I100,""),IF(AND(I101<>"",I101<>"通过"),IF(A101="","",A101&"敏感性：")&I101,""),IF(AND(I102<>"",I102<>"通过"),IF(A102="","",A102&"敏感性：")&I102,""))))
A80: 四、审计结论
A81: 经审计，本期长期股权投资减值准备计提 □充分准确 □不充分/不准确（说明：__________）。已按CAS8采用可收回金额双路径测试；未发现不当转回减值（或已在说明中披露）。复核人确认异常事项已关闭或已在说明中充分披露。
A84: 五、审计轨迹
B85: 编制人 | D85: 编制日期 | F85: 复核人 | H85: 复核日期
B87: 关键证据索引（评估报告/现金流预测/折现率底稿/市价资料/董事会决议/G7-2）
A89: 提示（准则摘要）：
A90: 1) 可收回金额=MAX(公允价值减处置费用, 预计未来现金流量现值, 0)；不得为负。
A91: 2) 净资产公允价值×持股比例仅为辅助参考，不能直接替代可收回金额。
A92: 3) 本期应补提=MAX(测试前账面净额−可收回金额,0)；少提合计按项目正差异SUMIF，禁止跨项目净额抵销。
A93: 4) 长期股权投资减值损失一经确认不得转回；“可能计提偏高”仅作调查，不得直接冲回。
A94: 5) 本表与G7-2勾稽优先使用审定期末金额（成本法AI列/权益法BB列）。
A95: 6) 仅用单路径估值须说明未采用另一路径原因；安全边际偏低时应做敏感性分析。与G7-16衔接：超额亏损冲减后账面为零的，长投减值测试可记录“无余额”，并索引未确认损失备查；存在其他长期权益的，评估是否对其减值/坏账。
A96: 7. 敏感性分析（安全边际偏低或依赖现金流现值时填列）
A97: 被投资单位 | B97: 基准现值 | C97: 折现率+1%后现值 | D97: 永续增长率-0.5%后现值 | E97: 收入/现金流-10%后现值 | F97: 最不利情景可收回 | G97: 最不利下应补提 | H97: 临界说明 | I97: 复核
A98: =A35 | B98: =IF(J35="","",J35) | F98: =IF(A98="","",IF(COUNTA(C98:E98)=0,"",MAX(0,MIN(IF(C98="",9E99,N(C98)),IF(D98="",9E99,N(D98)),IF(E98="",9E99,N(E98)))))) | G98: =IF(OR(A98="",F98=""),"",MAX(N(D35)-MAX(N(H35),N(F98)),0)) | I98: =IF(A98="","",IF(AND(P35="安全边际偏低-建议敏感性分析",COUNTA(C98:E98)=0),"建议补做敏感性",IF(AND(G98<>"",G98>N(L35)),"不利情景下需追加减值-需说明","通过")))
A99: =A36 | B99: =IF(J36="","",J36) | F99: =IF(A99="","",IF(COUNTA(C99:E99)=0,"",MAX(0,MIN(IF(C99="",9E99,N(C99)),IF(D99="",9E99,N(D99)),IF(E99="",9E99,N(E99)))))) | G99: =IF(OR(A99="",F99=""),"",MAX(N(D36)-MAX(N(H36),N(F99)),0)) | I99: =IF(A99="","",IF(AND(P36="安全边际偏低-建议敏感性分析",COUNTA(C99:E99)=0),"建议补做敏感性",IF(AND(G99<>"",G99>N(L36)),"不利情景下需追加减值-需说明","通过")))
A100: =A37 | B100: =IF(J37="","",J37) | F100: =IF(A100="","",IF(COUNTA(C100:E100)=0,"",MAX(0,MIN(IF(C100="",9E99,N(C100)),IF(D100="",9E99,N(D100)),IF(E100="",9E99,N(E100)))))) | G100: =IF(OR(A100="",F100=""),"",MAX(N(D37)-MAX(N(H37),N(F100)),0)) | I100: =IF(A100="","",IF(AND(P37="安全边际偏低-建议敏感性分析",COUNTA(C100:E100)=0),"建议补做敏感性",IF(AND(G100<>"",G100>N(L37)),"不利情景下需追加减值-需说明","通过")))
A101: =A38 | B101: =IF(J38="","",J38) | F101: =IF(A101="","",IF(COUNTA(C101:E101)=0,"",MAX(0,MIN(IF(C101="",9E99,N(C101)),IF(D101="",9E99,N(D101)),IF(E101="",9E99,N(E101)))))) | G101: =IF(OR(A101="",F101=""),"",MAX(N(D38)-MAX(N(H38),N(F101)),0)) | I101: =IF(A101="","",IF(AND(P38="安全边际偏低-建议敏感性分析",COUNTA(C101:E101)=0),"建议补做敏感性",IF(AND(G101<>"",G101>N(L38)),"不利情景下需追加减值-需说明","通过")))
A102: =A39 | B102: =IF(J39="","",J39) | F102: =IF(A102="","",IF(COUNTA(C102:E102)=0,"",MAX(0,MIN(IF(C102="",9E99,N(C102)),IF(D102="",9E99,N(D102)),IF(E102="",9E99,N(E102)))))) | G102: =IF(OR(A102="",F102=""),"",MAX(N(D39)-MAX(N(H39),N(F102)),0)) | I102: =IF(A102="","",IF(AND(P39="安全边际偏低-建议敏感性分析",COUNTA(C102:E102)=0),"建议补做敏感性",IF(AND(G102<>"",G102>N(L39)),"不利情景下需追加减值-需说明","通过")))

Sheet 凭证检查表G7-18
A1: 致同会计师事务所
A2: 长期股权投资凭证检查表
A3: =底稿目录!A2 | E3: =底稿目录!A4 | H3: =底稿目录!A5 | Q3: 底稿目录!F18 | U3: 索引号： | V3: =底稿目录!F24
A4: =底稿目录!A3 | E4: =底稿目录!A6 | H4: =底稿目录!A7 | U4: 页 次：
A5: 一、审计目标
A6: 确认长期股权投资相关交易的存在性、完整性、权利和义务、准确性、截止、分类及披露；通过凭证细节测试获取充分、适当的审计证据。
A7: 程序链：①与G7-1勾稽发生额总体 → ②设重要性/可容忍错报并算参考样本量 → ③特定项目全查+剩余抽样 → ④按交易类型抽凭并索引G7-8~17专项底稿 → ⑤六要素打√/X → ⑥金额差异与评价 → ⑦期后截止 → ⑧结论与待关闭事项。 ｜ 橙色输入、绿色公式；S列自动提示关联底稿。
A8: 二、样本选取标准与规模（数字化勾稽）
A9: 项目 | B9: 借方笔数 | C9: 借方金额 | D9: 贷方笔数 | E9: 贷方金额 | F9: 说明/索引 | H9: 抽样参数 | I9: 数值 | J9: 说明 | L9: 特定项目标准
A10: G7-1本期发生额 | C10: ='长期股权投资审定表G7-1'!D22 | E10: ='长期股权投资审定表G7-1'!E22 | H10: 重要性水平 | J10: 可填账户/报表整体重要性 | L10: 大额阈值：
A11: 凭证总体（测试范围） | H11: 可容忍错报 | J11: 通常为重要性的一定比例 | L11: 关联方交易：
A12: 与G7-1差异 | C12: =IF(OR(C10="",C11=""),"",N(C11)-N(C10)) | E12: =IF(OR(E10="",E11=""),"",N(E11)-N(E10)) | F12: =IF(OR(C12="",E12=""),"",IF(AND(ABS(N(C12))<0.01,ABS(N(E12))<0.01),"勾稽一致","与G7-1不一致-需说明")) | H12: 预计错报 | J12: 基于以前经验/风险 | L12: 异常/特别风险：
A13: 特定项目（全部测试） | H13: 误受风险% | J13: 如5表示5% | L13: 抽样工具：
A14: 剩余抽样总体 | B14: =IF(OR(B11="",B13=""),"",N(B11)-N(B13)) | C14: =IF(OR(C11="",C13=""),"",N(C11)-N(C13)) | D14: =IF(OR(D11="",D13=""),"",N(D11)-N(D13)) | E14: =IF(OR(E11="",E13=""),"",N(E11)-N(E13)) | F14: =IF(OR(B14="",C14=""),"",IF(OR(B14<0,C14<0,D14<0,E14<0),"特定项目超出总体-异常","通过")) | H14: 风险系数 | J14: 可参考：误受5%时风险系数约1.6（MUS）
H15: 扩展系数 | I15: =IF(I13="","",IFERROR(INDEX($C$85:$C$87,MATCH(N(I13),$B$85:$B$87,0)),IFERROR(INDEX($C$85:$C$87,MATCH(N(I13),$B$85:$B$87,1)),""))) | J15: 预计错报>0时使用
H16: 参考计算样本量 | I16: =IF(OR(I11="",I14=""),"",IF(AND(C14="",E14=""),"",IF(N(I11)-N(I12)*IF(I15="",1,N(I15))<=0,"参数异常-分母≤0",ROUNDUP(MAX(N(C14),N(E14))*N(I14)/(N(I11)-N(I12)*IF(I15="",1,N(I15))),0))))
H17: 实际抽取样本量(笔)
H18: 抽样方法
H19: 随机种子/工具索引
H20: 样本量复核 | I20: =IF(OR(I16="",I17=""),"",IF(I16="参数异常-分母≤0",I16,IF(N(I17)<N(I16),"实际样本<参考值-需说明","通过")))
A22: 三、本期发生额凭证检查（核对：1完整 2授权 3真实权利 4账务 5成本/权益法 6截止分类关联方）
A23: 结果填√/X/N/A。任一X→异常；存在空且无X→待完成；全部√或N/A→通过。交易类型用于提示关联G7-8/9/10/11/12/13/14/15/16/17；权益法链：核算→G7-14，内部交易→G7-15，超额亏损→G7-16，减值→G7-17。
A24: 日期 | B24: 凭证编号 | C24: 业务内容 | D24: 交易类型 | E24: 对方科目 | F24: 借方金额 | G24: 贷方金额 | H24: 支持性文件 | I24: 1完整 | J24: 2授权 | K24: 3真实 | L24: 4账务 | M24: 5计价 | N24: 6截止等 | O24: 支持金额 | P24: 错报金额 | Q24: 自动异常 | R24: 处理结果 | S24: 关联底稿提示 | T24: 样本来源 | U24: 索引号 | V24: 备注
H25: 付款审批/投资协议/评估/银行回单/决议… | P25: =IF(OR(AND(F25="",G25=""),O25=""),"",ABS(N(O25)-IF(AND(F25<>"",G25<>""),N(F25)+N(G25),IF(N(F25)>=N(G25),N(F25),N(G25))))) | Q25: =IF(AND(B25="",C25=""),"",IF(OR(I25="X",J25="X",K25="X",L25="X",M25="X",N25="X"),IF(OR(R25="",R25="无需处理"),"异常-待关闭","异常-已处理"),IF(OR(I25="",J25="",K25="",L25="",M25="",N25=""),"待完成",IF(AND(P25<>"",N(P25)>0),"金额差异待解释","通过")))) | S25: =IF(D25="","",IF(OR(D25="取得子公司-同控",D25="取得子公司-非同控"),"查G7-8/G7-9",IF(D25="后续计量/划转","查G7-10",IF(OR(D25="处置-非一揽子",D25="处置-一揽子"),"查G7-11/G7-12",IF(D25="合营联营初始","查G7-13",IF(D25="权益法核算","查G7-14",IF(D25="内部交易抵销","查G7-15→G7-14",IF(D25="超额亏损/未确认损失","查G7-16",IF(D25="减值","查G7-17",IF(D25="预计负债(额外义务)","查G7-16预计负债+负债科目","查G7-2/G7-4"))))))))))
P26: =IF(OR(AND(F26="",G26=""),O26=""),"",ABS(N(O26)-IF(AND(F26<>"",G26<>""),N(F26)+N(G26),IF(N(F26)>=N(G26),N(F26),N(G26))))) | Q26: =IF(AND(B26="",C26=""),"",IF(OR(I26="X",J26="X",K26="X",L26="X",M26="X",N26="X"),IF(OR(R26="",R26="无需处理"),"异常-待关闭","异常-已处理"),IF(OR(I26="",J26="",K26="",L26="",M26="",N26=""),"待完成",IF(AND(P26<>"",N(P26)>0),"金额差异待解释","通过")))) | S26: =IF(D26="","",IF(OR(D26="取得子公司-同控",D26="取得子公司-非同控"),"查G7-8/G7-9",IF(D26="后续计量/划转","查G7-10",IF(OR(D26="处置-非一揽子",D26="处置-一揽子"),"查G7-11/G7-12",IF(D26="合营联营初始","查G7-13",IF(D26="权益法核算","查G7-14",IF(D26="内部交易抵销","查G7-15→G7-14",IF(D26="超额亏损/未确认损失","查G7-16",IF(D26="减值","查G7-17",IF(D26="预计负债(额外义务)","查G7-16预计负债+负债科目","查G7-2/G7-4"))))))))))
P27: =IF(OR(AND(F27="",G27=""),O27=""),"",ABS(N(O27)-IF(AND(F27<>"",G27<>""),N(F27)+N(G27),IF(N(F27)>=N(G27),N(F27),N(G27))))) | Q27: =IF(AND(B27="",C27=""),"",IF(OR(I27="X",J27="X",K27="X",L27="X",M27="X",N27="X"),IF(OR(R27="",R27="无需处理"),"异常-待关闭","异常-已处理"),IF(OR(I27="",J27="",K27="",L27="",M27="",N27=""),"待完成",IF(AND(P27<>"",N(P27)>0),"金额差异待解释","通过")))) | S27: =IF(D27="","",IF(OR(D27="取得子公司-同控",D27="取得子公司-非同控"),"查G7-8/G7-9",IF(D27="后续计量/划转","查G7-10",IF(OR(D27="处置-非一揽子",D27="处置-一揽子"),"查G7-11/G7-12",IF(D27="合营联营初始","查G7-13",IF(D27="权益法核算","查G7-14",IF(D27="内部交易抵销","查G7-15→G7-14",IF(D27="超额亏损/未确认损失","查G7-16",IF(D27="减值","查G7-17",IF(D27="预计负债(额外义务)","查G7-16预计负债+负债科目","查G7-2/G7-4"))))))))))
P28: =IF(OR(AND(F28="",G28=""),O28=""),"",ABS(N(O28)-IF(AND(F28<>"",G28<>""),N(F28)+N(G28),IF(N(F28)>=N(G28),N(F28),N(G28))))) | Q28: =IF(AND(B28="",C28=""),"",IF(OR(I28="X",J28="X",K28="X",L28="X",M28="X",N28="X"),IF(OR(R28="",R28="无需处理"),"异常-待关闭","异常-已处理"),IF(OR(I28="",J28="",K28="",L28="",M28="",N28=""),"待完成",IF(AND(P28<>"",N(P28)>0),"金额差异待解释","通过")))) | S28: =IF(D28="","",IF(OR(D28="取得子公司-同控",D28="取得子公司-非同控"),"查G7-8/G7-9",IF(D28="后续计量/划转","查G7-10",IF(OR(D28="处置-非一揽子",D28="处置-一揽子"),"查G7-11/G7-12",IF(D28="合营联营初始","查G7-13",IF(D28="权益法核算","查G7-14",IF(D28="内部交易抵销","查G7-15→G7-14",IF(D28="超额亏损/未确认损失","查G7-16",IF(D28="减值","查G7-17",IF(D28="预计负债(额外义务)","查G7-16预计负债+负债科目","查G7-2/G7-4"))))))))))
P29: =IF(OR(AND(F29="",G29=""),O29=""),"",ABS(N(O29)-IF(AND(F29<>"",G29<>""),N(F29)+N(G29),IF(N(F29)>=N(G29),N(F29),N(G29))))) | Q29: =IF(AND(B29="",C29=""),"",IF(OR(I29="X",J29="X",K29="X",L29="X",M29="X",N29="X"),IF(OR(R29="",R29="无需处理"),"异常-待关闭","异常-已处理"),IF(OR(I29="",J29="",K29="",L29="",M29="",N29=""),"待完成",IF(AND(P29<>"",N(P29)>0),"金额差异待解释","通过")))) | S29: =IF(D29="","",IF(OR(D29="取得子公司-同控",D29="取得子公司-非同控"),"查G7-8/G7-9",IF(D29="后续计量/划转","查G7-10",IF(OR(D29="处置-非一揽子",D29="处置-一揽子"),"查G7-11/G7-12",IF(D29="合营联营初始","查G7-13",IF(D29="权益法核算","查G7-14",IF(D29="内部交易抵销","查G7-15→G7-14",IF(D29="超额亏损/未确认损失","查G7-16",IF(D29="减值","查G7-17",IF(D29="预计负债(额外义务)","查G7-16预计负债+负债科目","查G7-2/G7-4"))))))))))
P30: =IF(OR(AND(F30="",G30=""),O30=""),"",ABS(N(O30)-IF(AND(F30<>"",G30<>""),N(F30)+N(G30),IF(N(F30)>=N(G30),N(F30),N(G30))))) | Q30: =IF(AND(B30="",C30=""),"",IF(OR(I30="X",J30="X",K30="X",L30="X",M30="X",N30="X"),IF(OR(R30="",R30="无需处理"),"异常-待关闭","异常-已处理"),IF(OR(I30="",J30="",K30="",L30="",M30="",N30=""),"待完成",IF(AND(P30<>"",N(P30)>0),"金额差异待解释","通过")))) | S30: =IF(D30="","",IF(OR(D30="取得子公司-同控",D30="取得子公司-非同控"),"查G7-8/G7-9",IF(D30="后续计量/划转","查G7-10",IF(OR(D30="处置-非一揽子",D30="处置-一揽子"),"查G7-11/G7-12",IF(D30="合营联营初始","查G7-13",IF(D30="权益法核算","查G7-14",IF(D30="内部交易抵销","查G7-15→G7-14",IF(D30="超额亏损/未确认损失","查G7-16",IF(D30="减值","查G7-17",IF(D30="预计负债(额外义务)","查G7-16预计负债+负债科目","查G7-2/G7-4"))))))))))
P31: =IF(OR(AND(F31="",G31=""),O31=""),"",ABS(N(O31)-IF(AND(F31<>"",G31<>""),N(F31)+N(G31),IF(N(F31)>=N(G31),N(F31),N(G31))))) | Q31: =IF(AND(B31="",C31=""),"",IF(OR(I31="X",J31="X",K31="X",L31="X",M31="X",N31="X"),IF(OR(R31="",R31="无需处理"),"异常-待关闭","异常-已处理"),IF(OR(I31="",J31="",K31="",L31="",M31="",N31=""),"待完成",IF(AND(P31<>"",N(P31)>0),"金额差异待解释","通过")))) | S31: =IF(D31="","",IF(OR(D31="取得子公司-同控",D31="取得子公司-非同控"),"查G7-8/G7-9",IF(D31="后续计量/划转","查G7-10",IF(OR(D31="处置-非一揽子",D31="处置-一揽子"),"查G7-11/G7-12",IF(D31="合营联营初始","查G7-13",IF(D31="权益法核算","查G7-14",IF(D31="内部交易抵销","查G7-15→G7-14",IF(D31="超额亏损/未确认损失","查G7-16",IF(D31="减值","查G7-17",IF(D31="预计负债(额外义务)","查G7-16预计负债+负债科目","查G7-2/G7-4"))))))))))
P32: =IF(OR(AND(F32="",G32=""),O32=""),"",ABS(N(O32)-IF(AND(F32<>"",G32<>""),N(F32)+N(G32),IF(N(F32)>=N(G32),N(F32),N(G32))))) | Q32: =IF(AND(B32="",C32=""),"",IF(OR(I32="X",J32="X",K32="X",L32="X",M32="X",N32="X"),IF(OR(R32="",R32="无需处理"),"异常-待关闭","异常-已处理"),IF(OR(I32="",J32="",K32="",L32="",M32="",N32=""),"待完成",IF(AND(P32<>"",N(P32)>0),"金额差异待解释","通过")))) | S32: =IF(D32="","",IF(OR(D32="取得子公司-同控",D32="取得子公司-非同控"),"查G7-8/G7-9",IF(D32="后续计量/划转","查G7-10",IF(OR(D32="处置-非一揽子",D32="处置-一揽子"),"查G7-11/G7-12",IF(D32="合营联营初始","查G7-13",IF(D32="权益法核算","查G7-14",IF(D32="内部交易抵销","查G7-15→G7-14",IF(D32="超额亏损/未确认损失","查G7-16",IF(D32="减值","查G7-17",IF(D32="预计负债(额外义务)","查G7-16预计负债+负债科目","查G7-2/G7-4"))))))))))
P33: =IF(OR(AND(F33="",G33=""),O33=""),"",ABS(N(O33)-IF(AND(F33<>"",G33<>""),N(F33)+N(G33),IF(N(F33)>=N(G33),N(F33),N(G33))))) | Q33: =IF(AND(B33="",C33=""),"",IF(OR(I33="X",J33="X",K33="X",L33="X",M33="X",N33="X"),IF(OR(R33="",R33="无需处理"),"异常-待关闭","异常-已处理"),IF(OR(I33="",J33="",K33="",L33="",M33="",N33=""),"待完成",IF(AND(P33<>"",N(P33)>0),"金额差异待解释","通过")))) | S33: =IF(D33="","",IF(OR(D33="取得子公司-同控",D33="取得子公司-非同控"),"查G7-8/G7-9",IF(D33="后续计量/划转","查G7-10",IF(OR(D33="处置-非一揽子",D33="处置-一揽子"),"查G7-11/G7-12",IF(D33="合营联营初始","查G7-13",IF(D33="权益法核算","查G7-14",IF(D33="内部交易抵销","查G7-15→G7-14",IF(D33="超额亏损/未确认损失","查G7-16",IF(D33="减值","查G7-17",IF(D33="预计负债(额外义务)","查G7-16预计负债+负债科目","查G7-2/G7-4"))))))))))
P34: =IF(OR(AND(F34="",G34=""),O34=""),"",ABS(N(O34)-IF(AND(F34<>"",G34<>""),N(F34)+N(G34),IF(N(F34)>=N(G34),N(F34),N(G34))))) | Q34: =IF(AND(B34="",C34=""),"",IF(OR(I34="X",J34="X",K34="X",L34="X",M34="X",N34="X"),IF(OR(R34="",R34="无需处理"),"异常-待关闭","异常-已处理"),IF(OR(I34="",J34="",K34="",L34="",M34="",N34=""),"待完成",IF(AND(P34<>"",N(P34)>0),"金额差异待解释","通过")))) | S34: =IF(D34="","",IF(OR(D34="取得子公司-同控",D34="取得子公司-非同控"),"查G7-8/G7-9",IF(D34="后续计量/划转","查G7-10",IF(OR(D34="处置-非一揽子",D34="处置-一揽子"),"查G7-11/G7-12",IF(D34="合营联营初始","查G7-13",IF(D34="权益法核算","查G7-14",IF(D34="内部交易抵销","查G7-15→G7-14",IF(D34="超额亏损/未确认损失","查G7-16",IF(D34="减值","查G7-17",IF(D34="预计负债(额外义务)","查G7-16预计负债+负债科目","查G7-2/G7-4"))))))))))
A35: 样本合计 | F35: =SUM(F25:F34) | G35: =SUM(G25:G34) | O35: =SUM(O25:O34) | P35: =SUM(P25:P34)
A36: 已填样本笔数 | B36: =COUNTA(B25:B34) | C36: 异常笔数 | D36: =COUNTIF(Q25:Q34,"异常*") | E36: 待完成笔数 | F36: =COUNTIF(Q25:Q34,"待完成") | I36: 待关闭异常 | J36: =COUNTIF(Q25:Q34,"异常-待关闭")+COUNTIF(Q42:Q46,"异常-待关闭")+COUNTIF(Q25:Q34,"金额差异待解释")+COUNTIF(Q42:Q46,"调整事项待处理") | L36: 特定项目样本笔数 | M36: =COUNTIF(T25:T34,"特定项目") | N36: 抽样样本笔数 | O36: =COUNTIF(T25:T34,"随机/系统抽样")+COUNTIF(T25:T34,"MUS")+COUNTIF(T25:T34,"补充样本")
A37: 借方金额覆盖率 | B37: =IF(OR(C11="",C11=0),"",F35/C11) | C37: 贷方金额覆盖率 | D37: =IF(OR(E11="",E11=0),"",G35/E11) | E37: 笔数覆盖率 | F37: =IF(OR(B11="",B11=0),"",B36/B11) | G37: 异常率 | H37: =IF(B36=0,"",D36/B36) | L37: 特定项目借方金额 | M37: =SUMIF(T25:T34,"特定项目",F25:F34) | N37: 抽样借方金额 | O37: =SUM(F35)-M37
L38: 特定覆盖率(借) | M38: =IF(OR(C13="",C13=0),"",M37/C13) | N38: 抽样占剩余(借) | O38: =IF(OR(C14="",C14=0),"",O37/C14)
A39: 四、期后新增/处置及截止检查（资产负债表日至检查日）
A40: 资产负债表日 | C40: 检查截止日 | E40: 期后总体笔数 | G40: 期后总体金额 | I40: 检查说明
A41: 日期 | B41: 凭证编号 | C41: 业务内容 | D41: 交易类型 | E41: 是否属期前交易 | F41: 借方金额 | G41: 贷方金额 | H41: 支持性文件 | I41: 1完整 | J41: 2授权 | K41: 3真实 | L41: 4账务 | M41: 5计价 | N41: 6截止等 | O41: 事项性质 | P41: 错报/影响金额 | Q41: 自动异常 | R41: 处理结果 | S41: 关联底稿提示 | T41: 是否调整事项 | U41: 索引号 | V41: 备注
Q42: =IF(AND(B42="",C42=""),"",IF(OR(I42="X",J42="X",K42="X",L42="X",M42="X",N42="X"),IF(OR(R42="",R42="无需处理"),"异常-待关闭","异常-已处理"),IF(OR(I42="",J42="",K42="",L42="",M42="",N42=""),"待完成",IF(AND(OR(E42="是",T42="是"),OR(R42="",R42="无需处理")),"调整事项待处理","通过")))) | S42: =IF(D42="","",IF(OR(D42="取得子公司-同控",D42="取得子公司-非同控"),"查G7-8/G7-9",IF(D42="后续计量/划转","查G7-10",IF(OR(D42="处置-非一揽子",D42="处置-一揽子"),"查G7-11/G7-12",IF(D42="合营联营初始","查G7-13",IF(D42="权益法核算","查G7-14",IF(D42="内部交易抵销","查G7-15→G7-14",IF(D42="超额亏损/未确认损失","查G7-16",IF(D42="减值","查G7-17",IF(D42="预计负债(额外义务)","查G7-16预计负债+负债科目","查G7-2/G7-4"))))))))))
Q43: =IF(AND(B43="",C43=""),"",IF(OR(I43="X",J43="X",K43="X",L43="X",M43="X",N43="X"),IF(OR(R43="",R43="无需处理"),"异常-待关闭","异常-已处理"),IF(OR(I43="",J43="",K43="",L43="",M43="",N43=""),"待完成",IF(AND(OR(E43="是",T43="是"),OR(R43="",R43="无需处理")),"调整事项待处理","通过")))) | S43: =IF(D43="","",IF(OR(D43="取得子公司-同控",D43="取得子公司-非同控"),"查G7-8/G7-9",IF(D43="后续计量/划转","查G7-10",IF(OR(D43="处置-非一揽子",D43="处置-一揽子"),"查G7-11/G7-12",IF(D43="合营联营初始","查G7-13",IF(D43="权益法核算","查G7-14",IF(D43="内部交易抵销","查G7-15→G7-14",IF(D43="超额亏损/未确认损失","查G7-16",IF(D43="减值","查G7-17",IF(D43="预计负债(额外义务)","查G7-16预计负债+负债科目","查G7-2/G7-4"))))))))))
Q44: =IF(AND(B44="",C44=""),"",IF(OR(I44="X",J44="X",K44="X",L44="X",M44="X",N44="X"),IF(OR(R44="",R44="无需处理"),"异常-待关闭","异常-已处理"),IF(OR(I44="",J44="",K44="",L44="",M44="",N44=""),"待完成",IF(AND(OR(E44="是",T44="是"),OR(R44="",R44="无需处理")),"调整事项待处理","通过")))) | S44: =IF(D44="","",IF(OR(D44="取得子公司-同控",D44="取得子公司-非同控"),"查G7-8/G7-9",IF(D44="后续计量/划转","查G7-10",IF(OR(D44="处置-非一揽子",D44="处置-一揽子"),"查G7-11/G7-12",IF(D44="合营联营初始","查G7-13",IF(D44="权益法核算","查G7-14",IF(D44="内部交易抵销","查G7-15→G7-14",IF(D44="超额亏损/未确认损失","查G7-16",IF(D44="减值","查G7-17",IF(D44="预计负债(额外义务)","查G7-16预计负债+负债科目","查G7-2/G7-4"))))))))))
Q45: =IF(AND(B45="",C45=""),"",IF(OR(I45="X",J45="X",K45="X",L45="X",M45="X",N45="X"),IF(OR(R45="",R45="无需处理"),"异常-待关闭","异常-已处理"),IF(OR(I45="",J45="",K45="",L45="",M45="",N45=""),"待完成",IF(AND(OR(E45="是",T45="是"),OR(R45="",R45="无需处理")),"调整事项待处理","通过")))) | S45: =IF(D45="","",IF(OR(D45="取得子公司-同控",D45="取得子公司-非同控"),"查G7-8/G7-9",IF(D45="后续计量/划转","查G7-10",IF(OR(D45="处置-非一揽子",D45="处置-一揽子"),"查G7-11/G7-12",IF(D45="合营联营初始","查G7-13",IF(D45="权益法核算","查G7-14",IF(D45="内部交易抵销","查G7-15→G7-14",IF(D45="超额亏损/未确认损失","查G7-16",IF(D45="减值","查G7-17",IF(D45="预计负债(额外义务)","查G7-16预计负债+负债科目","查G7-2/G7-4"))))))))))
Q46: =IF(AND(B46="",C46=""),"",IF(OR(I46="X",J46="X",K46="X",L46="X",M46="X",N46="X"),IF(OR(R46="",R46="无需处理"),"异常-待关闭","异常-已处理"),IF(OR(I46="",J46="",K46="",L46="",M46="",N46=""),"待完成",IF(AND(OR(E46="是",T46="是"),OR(R46="",R46="无需处理")),"调整事项待处理","通过")))) | S46: =IF(D46="","",IF(OR(D46="取得子公司-同控",D46="取得子公司-非同控"),"查G7-8/G7-9",IF(D46="后续计量/划转","查G7-10",IF(OR(D46="处置-非一揽子",D46="处置-一揽子"),"查G7-11/G7-12",IF(D46="合营联营初始","查G7-13",IF(D46="权益法核算","查G7-14",IF(D46="内部交易抵销","查G7-15→G7-14",IF(D46="超额亏损/未确认损失","查G7-16",IF(D46="减值","查G7-17",IF(D46="预计负债(额外义务)","查G7-16预计负债+负债科目","查G7-2/G7-4"))))))))))
A47: 期后样本合计 | F47: =SUM(F42:F46) | G47: =SUM(G42:G46) | P47: =SUM(P42:P46)
A48: 期后异常笔数 | B48: =COUNTIF(Q42:Q46,"异常*") | C48: 期后待完成 | D48: =COUNTIF(Q42:Q46,"待完成")
A50: 五、样本结果评价
A51: 评价项目 | C51: 金额/结果 | E51: 说明
A52: 本期已识别错报(含特定项目) | C52: =P35 | E52: 样本中支持金额与账面差异合计
A53: 期后影响金额合计 | C53: =P47 | E53: 期后检查识别的影响
A54: 已识别错报合计 | C54: =N(C52)+N(C53) | E54: 未含推断
A55: 推断总体错报(建议) | C55: =IF(OR(O37="",O37=0,C14=""),"",IF(SUMIF(T25:T34,"随机/系统抽样",P25:P34)+SUMIF(T25:T34,"MUS",P25:P34)+SUMIF(T25:T34,"补充样本",P25:P34)=0,0,ROUND((SUMIF(T25:T34,"随机/系统抽样",P25:P34)+SUMIF(T25:T34,"MUS",P25:P34)+SUMIF(T25:T34,"补充样本",P25:P34))/O37*N(C14),2))) | E55: ≈抽样样本错报合计÷抽样借方金额×剩余借方总体；可手工覆盖
A56: 与可容忍错报比较 | C56: =IF(OR(I11="",C54=""),"",IF(N(C54)+N(C55)>N(I11),"超过可容忍错报","未超过可容忍错报")) | E56: 自动
A57: 是否需要扩大样本 | C57: =IF(C56="","",IF(OR(C56="超过可容忍错报",H37>0.05,D36>=2,J36>0,N(C55)>N(I11)*0.5),"建议扩大样本/改全查","可维持现有样本-需判断")) | E57: 自动
A58: 系统性错误迹象 | E58: 是/否，手工
A59: 五(附)、权益法专项底稿交叉索引（选样前对照；金额取自各表公式）
A60: 六、审计说明
A61: （自动汇总异常/待完成；可继续手工补充）
A62: =IF(AND(COUNTA(B25:B34)=0,COUNTA(B42:B46)=0),"（尚未录入凭证样本。请先完成第二节抽样参数，再抽凭填列第三节/第四节。）",IF(TEXTJOIN("；",TRUE,IF(AND(F12<>"",F12<>"勾稽一致"),"总体:"&F12,""),IF(AND(F14<>"",F14<>"通过"),"剩余总体:"&F14,""),IF(AND(I20<>"",I20<>"通过"),"样本量:"&I20,""),IF(D36>0,"本期异常"&D36&"笔",""),IF(F36>0,"本期待完成"&F36&"笔",""),IF(B48>0,"期后异常"&B48&"笔",""),IF(D48>0,"期后待完成"&D48&"笔",""),IF(J36>0,"待关闭/待解释事项"&J36&"项",""),IF(AND(M38<>"",M38<0.95),"特定项目借方覆盖不足",""),IF(AND(C56<>"",C56<>"未超过可容忍错报"),C56,""),IF(AND(C57<>"",LEFT(C57,2)="建议"),C57,""),IF(AND(Q25<>"",Q25<>"通过"),IF(B25="","行25",B25)&"："&Q25,""),IF(AND(Q26<>"",Q26<>"通过"),IF(B26="","行26",B26)&"："&Q26,""),IF(AND(Q27<>"",Q27<>"通过"),IF(B27="","行27",B27)&"："&Q27,""),IF(AND(Q28<>"",Q28<>"通过"),IF(B28="","行28",B28)&"："&Q28,""),IF(AND(Q29<>"",Q29<>"通过"),IF(B29="","行29",B29)&"："&Q29,""),IF(AND(Q30<>"",Q30<>"通过"),IF(B30="","行30",B30)&"："&Q30,""),IF(AND(Q31<>"",Q31<>"通过"),IF(B31="","行31",B31)&"："&Q31,""),IF(AND(Q32<>"",Q32<>"通过"),IF(B32="","行32",B32)&"："&Q32,""),IF(AND(Q33<>"",Q33<>"通过"),IF(B33="","行33",B33)&"："&Q33,""),IF(AND(Q34<>"",Q34<>"通过"),IF(B34="","行34",B34)&"："&Q34,""),IF(AND(Q42<>"",Q42<>"通过"),IF(B42="","行42",B42)&"："&Q42,""),IF(AND(Q43<>"",Q43<>"通过"),IF(B43="","行43",B43)&"："&Q43,""),IF(AND(Q44<>"",Q44<>"通过"),IF(B44="","行44",B44)&"："&Q44,""),IF(AND(Q45<>"",Q45<>"通过"),IF(B45="","行45",B45)&"："&Q45,""),IF(AND(Q46<>"",Q46<>"通过"),IF(B46="","行46",B46)&"："&Q46,""))="","自动复核未见未通过项。请结合覆盖率与样本评价完成结论勾选。",TEXTJOIN("；",TRUE,IF(AND(F12<>"",F12<>"勾稽一致"),"总体:"&F12,""),IF(AND(F14<>"",F14<>"通过"),"剩余总体:"&F14,""),IF(AND(I20<>"",I20<>"通过"),"样本量:"&I20,""),IF(D36>0,"本期异常"&D36&"笔",""),IF(F36>0,"本期待完成"&F36&"笔",""),IF(B48>0,"期后异常"&B48&"笔",""),IF(D48>0,"期后待完成"&D48&"笔",""),IF(J36>0,"待关闭/待解释事项"&J36&"项",""),IF(AND(M38<>"",M38<0.95),"特定项目借方覆盖不足",""),IF(AND(C56<>"",C56<>"未超过可容忍错报"),C56,""),IF(AND(C57<>"",LEFT(C57,2)="建议"),C57,""),IF(AND(Q25<>"",Q25<>"通过"),IF(B25="","行25",B25)&"："&Q25,""),IF(AND(Q26<>"",Q26<>"通过"),IF(B26="","行26",B26)&"："&Q26,""),IF(AND(Q27<>"",Q27<>"通过"),IF(B27="","行27",B27)&"："&Q27,""),IF(AND(Q28<>"",Q28<>"通过"),IF(B28="","行28",B28)&"："&Q28,""),IF(AND(Q29<>"",Q29<>"通过"),IF(B29="","行29",B29)&"："&Q29,""),IF(AND(Q30<>"",Q30<>"通过"),IF(B30="","行30",B30)&"："&Q30,""),IF(AND(Q31<>"",Q31<>"通过"),IF(B31="","行31",B31)&"："&Q31,""),IF(AND(Q32<>"",Q32<>"通过"),IF(B32="","行32",B32)&"："&Q32,""),IF(AND(Q33<>"",Q33<>"通过"),IF(B33="","行33",B33)&"："&Q33,""),IF(AND(Q34<>"",Q34<>"通过"),IF(B34="","行34",B34)&"："&Q34,""),IF(AND(Q42<>"",Q42<>"通过"),IF(B42="","行42",B42)&"："&Q42,""),IF(AND(Q43<>"",Q43<>"通过"),IF(B43="","行43",B43)&"："&Q43,""),IF(AND(Q44<>"",Q44<>"通过"),IF(B44="","行44",B44)&"："&Q44,""),IF(AND(Q45<>"",Q45<>"通过"),IF(B45="","行45",B45)&"："&Q45,""),IF(AND(Q46<>"",Q46<>"通过"),IF(B46="","行46",B46)&"："&Q46,""))))
A66: 七、审计结论
A67: 经凭证检查，长期股权投资相关交易 □未见异常 □除下列重大不符事项应调整外其余未见异常 □因重大未调整事项或范围受限不可确认（说明：__________）。样本覆盖与评价见第五部分；异常及金额差异事项已关闭或已在说明中充分披露；待关闭事项见J36。
A70: 八、审计轨迹
B71: 编制人 | D71: 编制日期 | F71: 复核人 | H71: 复核日期
B73: 关键证据索引（总账导出/IDEA抽样文件/凭证复印件/协议/G7-1/G7-14权益法/G7-15内部交易/G7-16未确认损失/G7-17减值）
A75: 附录：抽样参考（非本项目执行记录）
A76: 1) 特定项目（大额/关联方/特别风险）应全部测试，不构成审计抽样。
A77: 2) 统计抽样需随机选样并用概率论评价；否则为非统计抽样，依赖职业判断。
A78: 3) 参考样本量≈剩余总体金额×风险系数/(可容忍错报−预计错报×扩展系数)。
A79: 4) 误受风险1%/5%/10%时，预计错报扩展系数常见参考为1.9/1.6/1.5。
A80: 5) 发现错报应评价是否系统性错误，并决定扩大样本、调整或修改风险应对。
A81: 6) 期后检查重点：截止错误、期后处置/新增、减值迹象恶化、调整 vs 非调整事项。
A83: 预计错报扩展系数参考
B84: 误受风险% | C84: 扩展系数
B85: 1 | C85: 1.9
B86: 5 | C86: 1.6
B87: 10 | C87: 1.5
A88: 附录B：权益法专项底稿交叉索引（选样/核对用）
A89: 底稿 | B89: 关键指标 | C89: 金额/结果 | D89: 抽凭关注点 | E89: 索引
A90: G7-14 | B90: 权益法投资收益测算差异等 | C90: =IFERROR('权益法测算表G7-14'!L21,"") | D90: 抽「权益法核算」类凭证；核对损益调整分录 | E90: G7-14
A91: G7-15 | B91: 内部交易投资收益调整⑦合计 | C91: =IFERROR('权益法未实现内部交易抵销测算表G7-15'!G32,"") | D91: 抽「内部交易抵销」类；核对抵销分录与比例 | E91: G7-15
A92: G7-16 | B92: 未确认投资损失期末合计 | C92: =IFERROR('未确认投资损失测试表G7-16'!J25,"") | D92: 抽「超额亏损/未确认损失」「预计负债」；备查与冲减顺序 | E92: G7-16
A93: G7-17 | B93: 建议补提减值（少提合计） | C93: =IFERROR('减值测试表G7-17'!C54,"") | D93: 抽「减值」类凭证；禁止转回检查 | E93: G7-17
A94: 说明：上表便于对照专项测算是否需抽对应凭证；C列为空表示源表未出数。G7-14的L21为第1部分投资收益差异合计。
